Workbook

Sheet Company1153 Assumptions
B2: COMPANY1153 (Company0080) - OPERATING MODEL ASSUMPTIONS
B3: 3-Year Historical (2021-2023) | 5-Year Projections (2024-2028)
B5: SCENARIO SELECTION
B6: Selected Scenario: | D6: Base
B8: Historical | G8: Projections
D9: 2021 | E9: 2022 | F9: 2023 | G9: 2024 | H9: 2025 | I9: 2026 | J9: 2027 | K9: 2028
B11: 1. REVENUE ASSUMPTIONS
B13: Revenue Growth Rates (%)
C14: Scenario | D14: 2021 | E14: 2022 | F14: 2023 | G14: 2024 | H14: 2025 | I14: 2026 | J14: 2027 | K14: 2028
B15: Company1153 Search | C15: Base | G15: 0.085 | H15: 0.075 | I15: 0.065 | J15: 0.055 | K15: 0.05
C16: Bull | G16: 0.105 | H16: 0.095 | I16: 0.085 | J16: 0.075 | K16: 0.07
C17: Bear | G17: 0.06 | H17: 0.05 | I17: 0.04 | J17: 0.035 | K17: 0.03
B19: Product0476 Ads | C19: Base | G19: 0.15 | H19: 0.13 | I19: 0.11 | J19: 0.1 | K19: 0.09
C20: Bull | G20: 0.18 | H20: 0.16 | I20: 0.14 | J20: 0.12 | K20: 0.11
C21: Bear | G21: 0.12 | H21: 0.1 | I21: 0.08 | J21: 0.07 | K21: 0.06
B23: Company1153 Cloud | C23: Base | G23: 0.28 | H23: 0.25 | I23: 0.22 | J23: 0.2 | K23: 0.18
C24: Bull | G24: 0.32 | H24: 0.3 | I24: 0.27 | J24: 0.24 | K24: 0.22
C25: Bear | G25: 0.24 | H25: 0.2 | I25: 0.17 | J25: 0.15 | K25: 0.14
B27: Other Revenues | C27: Base | G27: 0.05 | H27: 0.045 | I27: 0.04 | J27: 0.035 | K27: 0.03
C28: Bull | G28: 0.07 | H28: 0.06 | I28: 0.055 | J28: 0.05 | K28: 0.045
C29: Bear | G29: 0.03 | H29: 0.025 | I29: 0.02 | J29: 0.015 | K29: 0.01
B31: 2. OPERATING EXPENSE ASSUMPTIONS
B33: Operating Expenses (% of Revenue)
B35: Research & Development | C35: Base | D35: 0.151 | E35: 0.148 | F35: 0.145 | G35: 0.143 | H35: 0.14 | I35: 0.138 | J35: 0.135 | K35: 0.133
C36: Bull | D36: 0.151 | E36: 0.148 | F36: 0.145 | G36: 0.138 | H36: 0.135 | I36: 0.132 | J36: 0.13 | K36: 0.128
C37: Bear | D37: 0.151 | E37: 0.148 | F37: 0.145 | G37: 0.148 | H37: 0.145 | I37: 0.143 | J37: 0.14 | K37: 0.138
B39: Sales & Marketing | C39: Base | D39: 0.115 | E39: 0.112 | F39: 0.108 | G39: 0.105 | H39: 0.103 | I39: 0.1 | J39: 0.098 | K39: 0.095
C40: Bull | D40: 0.115 | E40: 0.112 | F40: 0.108 | G40: 0.102 | H40: 0.1 | I40: 0.097 | J40: 0.095 | K40: 0.092
C41: Bear | D41: 0.115 | E41: 0.112 | F41: 0.108 | G41: 0.108 | H41: 0.106 | I41: 0.103 | J41: 0.101 | K41: 0.098
B43: General & Administrative | C43: Base | D43: 0.068 | E43: 0.065 | F43: 0.063 | G43: 0.062 | H43: 0.06 | I43: 0.058 | J43: 0.057 | K43: 0.055
C44: Bull | D44: 0.068 | E44: 0.065 | F44: 0.063 | G44: 0.06 | H44: 0.058 | I44: 0.056 | J44: 0.055 | K44: 0.053
C45: Bear | D45: 0.068 | E45: 0.065 | F45: 0.063 | G45: 0.064 | H45: 0.062 | I45: 0.06 | J45: 0.059 | K45: 0.057
B47: Stock-Based Compensation | C47: Base | D47: 0.092 | E47: 0.095 | F47: 0.098 | G47: 0.095 | H47: 0.093 | I47: 0.09 | J47: 0.088 | K47: 0.085
C48: Bull | D48: 0.092 | E48: 0.095 | F48: 0.098 | G48: 0.092 | H48: 0.09 | I48: 0.087 | J48: 0.085 | K48: 0.082
C49: Bear | D49: 0.092 | E49: 0.095 | F49: 0.098 | G49: 0.098 | H49: 0.096 | I49: 0.093 | J49: 0.091 | K49: 0.088
B51: 3. BALANCE SHEET & CASH FLOW ASSUMPTIONS
B53: Working Capital Metrics
B55: Days Sales Outstanding (DSO) | C55: Base | D55: 48 | E55: 47 | F55: 46 | G55: 46 | H55: 45 | I55: 45 | J55: 44 | K55: 44
C56: Bull | D56: 48 | E56: 47 | F56: 46 | G56: 45 | H56: 44 | I56: 43 | J56: 42 | K56: 42
C57: Bear | D57: 48 | E57: 47 | F57: 46 | G57: 47 | H57: 47 | I57: 46 | J57: 46 | K57: 45
B59: Days Payable Outstanding (DPO) | C59: Base | D59: 32 | E59: 33 | F59: 34 | G59: 34 | H59: 35 | I59: 35 | J59: 36 | K59: 36
C60: Bull | D60: 32 | E60: 33 | F60: 34 | G60: 35 | H60: 36 | I60: 37 | J60: 38 | K60: 38
C61: Bear | D61: 32 | E61: 33 | F61: 34 | G61: 33 | H61: 33 | I61: 34 | J61: 34 | K61: 34
B63: ='Company1153 3-Statement'!$B$53 | C63: % Increase | E63: 0.058823529 | F63: 0.055555556 | G63: 0.05 | H63: 0.05 | I63: 0.05 | J63: 0.05 | K63: 0.05
B64: ='Company1153 3-Statement'!$B$61 | C64: % Increase | E64: 0.085714286 | F64: 0.10526316 | G64: 0.08 | H64: 0.08 | I64: 0.08 | J64: 0.08 | K64: 0.08
B65: ='Company1153 3-Statement'!$B$70 | C65: % Increase | E65: 0.083333333 | F65: 0.076923077 | G65: 0.06 | H65: 0.06 | I65: 0.06 | J65: 0.06 | K65: 0.06
B67: Capital Expenditure
B69: CapEx (% of Revenue) | C69: Base | D69: 0.125 | E69: 0.132 | F69: 0.14 | G69: 0.135 | H69: 0.13 | I69: 0.125 | J69: 0.12 | K69: 0.115
C70: Bull | D70: 0.125 | E70: 0.132 | F70: 0.14 | G70: 0.13 | H70: 0.125 | I70: 0.12 | J70: 0.115 | K70: 0.11
C71: Bear | D71: 0.125 | E71: 0.132 | F71: 0.14 | G71: 0.14 | H71: 0.135 | I71: 0.13 | J71: 0.125 | K71: 0.12
B73: D&A (% of Prior Year CapEx) | C73: Base | D73: 0.7 | E73: 0.7 | F73: 0.7 | G73: 0.7 | H73: 0.7 | I73: 0.7 | J73: 0.7 | K73: 0.7
C74: Bull | D74: 0.7 | E74: 0.7 | F74: 0.7 | G74: 0.68 | H74: 0.68 | I74: 0.68 | J74: 0.68 | K74: 0.68
C75: Bear | D75: 0.7 | E75: 0.7 | F75: 0.7 | G75: 0.72 | H75: 0.72 | I75: 0.72 | J75: 0.72 | K75: 0.72
B77: 4. OTHER FINANCIAL ASSUMPTIONS
B79: Tax Rate
B81: Effective Tax Rate | C81: Base | D81: 0.162 | E81: 0.16 | F81: 0.158 | G81: 0.165 | H81: 0.17 | I81: 0.175 | J81: 0.18 | K81: 0.185
C82: Bull | D82: 0.162 | E82: 0.16 | F82: 0.158 | G82: 0.16 | H82: 0.165 | I82: 0.17 | J82: 0.175 | K82: 0.18
C83: Bear | D83: 0.162 | E83: 0.16 | F83: 0.158 | G83: 0.17 | H83: 0.175 | I83: 0.18 | J83: 0.185 | K83: 0.19
B86: Interest Rates
B88: Interest Income Rate (on cash) | C88: Base | D88: 0.005 | E88: 0.015 | F88: 0.025 | G88: 0.035 | H88: 0.03 | I88: 0.025 | J88: 0.025 | K88: 0.02
C89: Bull | D89: 0.01 | E89: 0.02 | F89: 0.03 | G89: 0.04 | H89: 0.045 | I89: 0.04 | J89: 0.035 | K89: 0.035
C90: Bear | D90: 0.0025 | E90: 0.0125 | F90: 0.0225 | G90: 0.0325 | H90: 0.0375 | I90: 0.0325 | J90: 0.0275 | K90: 0.0275
B92: Interest Expense Rate (on LT debt) | C92: Base | D92: 0.03 | E92: 0.035 | F92: 0.04 | G92: 0.045 | H92: 0.04 | I92: 0.035 | J92: 0.03 | K92: 0.03
C93: Bull | D93: 0.025 | E93: 0.03 | F93: 0.035 | G93: 0.04 | H93: 0.035 | I93: 0.03 | J93: 0.025 | K93: 0.025
C94: Bear | D94: 0.04 | E94: 0.045 | F94: 0.05 | G94: 0.055 | H94: 0.05 | I94: 0.045 | J94: 0.04 | K94: 0.04
B96: Share Buyback
B98: Buyback (% of FCF) | C98: Base | D98: 0.75 | E98: 0.75 | F98: 0.75 | G98: 0.7 | H98: 0.7 | I98: 0.65 | J98: 0.65 | K98: 0.6
C99: Bull | D99: 0.75 | E99: 0.75 | F99: 0.75 | G99: 0.75 | H99: 0.75 | I99: 0.7 | J99: 0.7 | K99: 0.65
C100: Bear | D100: 0.75 | E100: 0.75 | F100: 0.75 | G100: 0.65 | H100: 0.65 | I100: 0.6 | J100: 0.6 | K100: 0.55

Sheet Company1808 Assumptions
B2: COMPANY1809 - OPERATING MODEL ASSUMPTIONS
B3: 3-Year Historical (2021-2023) | 5-Year Projections (2024-2028)
B5: SCENARIO SELECTION
B6: Selected Scenario: | D6: Base
B8: Historical | G8: Projections
D9: 2021 | E9: 2022 | F9: 2023 | G9: 2024 | H9: 2025 | I9: 2026 | J9: 2027 | K9: 2028
B11: 1. REVENUE ASSUMPTIONS
B13: Revenue Growth Rates (%)
C14: Scenario | D14: 2021 | E14: 2022 | F14: 2023 | G14: 2024 | H14: 2025 | I14: 2026 | J14: 2027 | K14: 2028
B15: Family of Apps (FoA) | C15: Base | G15: 0.12 | H15: 0.1 | I15: 0.085 | J15: 0.075 | K15: 0.07
C16: Bull | G16: 0.14 | H16: 0.12 | I16: 0.105 | J16: 0.095 | K16: 0.09
C17: Bear | G17: 0.1 | H17: 0.08 | I17: 0.065 | J17: 0.055 | K17: 0.05
B19: Product0338 | C19: Base | G19: 0.25 | H19: 0.35 | I19: 0.45 | J19: 0.4 | K19: 0.35
C20: Bull | G20: 0.3 | H20: 0.45 | I20: 0.55 | J20: 0.5 | K20: 0.45
C21: Bear | G21: 0.2 | H21: 0.25 | I21: 0.35 | J21: 0.3 | K21: 0.25
B24: User Growth Metrics
B26: DAU Growth (%) | C26: Base | G26: 0.03 | H26: 0.025 | I26: 0.02 | J26: 0.015 | K26: 0.01
C27: Bull | G27: 0.04 | H27: 0.035 | I27: 0.03 | J27: 0.025 | K27: 0.02
C28: Bear | G28: 0.02 | H28: 0.015 | I28: 0.01 | J28: 0.005 | K28: 0
B30: ARPU Growth (%) | C30: Base | G30: 0.085 | H30: 0.07 | I30: 0.06 | J30: 0.055 | K30: 0.05
C31: Bull | G31: 0.1 | H31: 0.085 | I31: 0.075 | J31: 0.07 | K31: 0.065
C32: Bear | G32: 0.07 | H32: 0.055 | I32: 0.045 | J32: 0.04 | K32: 0.035
B34: 2. OPERATING EXPENSE ASSUMPTIONS
B36: Operating Expenses (% of Revenue)
B38: Research & Development | C38: Base | D38: 0.255 | E38: 0.27 | F38: 0.29 | G38: 0.285 | H38: 0.28 | I38: 0.275 | J38: 0.27 | K38: 0.265
C39: Bull | D39: 0.255 | E39: 0.27 | F39: 0.29 | G39: 0.28 | H39: 0.275 | I39: 0.27 | J39: 0.265 | K39: 0.26
C40: Bear | D40: 0.255 | E40: 0.27 | F40: 0.29 | G40: 0.29 | H40: 0.285 | I40: 0.28 | J40: 0.275 | K40: 0.27
B42: Sales & Marketing | C42: Base | D42: 0.118 | E42: 0.125 | F42: 0.13 | G42: 0.125 | H42: 0.12 | I42: 0.115 | J42: 0.11 | K42: 0.105
C43: Bull | D43: 0.118 | E43: 0.125 | F43: 0.13 | G43: 0.12 | H43: 0.115 | I43: 0.11 | J43: 0.105 | K43: 0.1
C44: Bear | D44: 0.118 | E44: 0.125 | F44: 0.13 | G44: 0.13 | H44: 0.125 | I44: 0.12 | J44: 0.115 | K44: 0.11
B46: General & Administrative | C46: Base | D46: 0.102 | E46: 0.108 | F46: 0.115 | G46: 0.11 | H46: 0.105 | I46: 0.1 | J46: 0.095 | K46: 0.09
C47: Bull | D47: 0.102 | E47: 0.108 | F47: 0.115 | G47: 0.105 | H47: 0.1 | I47: 0.095 | J47: 0.09 | K47: 0.085
C48: Bear | D48: 0.102 | E48: 0.108 | F48: 0.115 | G48: 0.115 | H48: 0.11 | I48: 0.105 | J48: 0.1 | K48: 0.095
B50: Stock-Based Compensation | C50: Base | D50: 0.085 | E50: 0.102 | F50: 0.118 | G50: 0.11 | H50: 0.105 | I50: 0.1 | J50: 0.095 | K50: 0.09
C51: Bull | D51: 0.085 | E51: 0.102 | F51: 0.118 | G51: 0.105 | H51: 0.1 | I51: 0.095 | J51: 0.09 | K51: 0.085
C52: Bear | D52: 0.085 | E52: 0.102 | F52: 0.118 | G52: 0.115 | H52: 0.11 | I52: 0.105 | J52: 0.1 | K52: 0.095
B54: Product0338 Operating Margin
B56: Operating Margin (%) | C56: Base | D56: -3.5 | E56: -3 | F56: -2.5 | G56: -2 | H56: -1.5 | I56: -1 | J56: -0.75 | K56: -0.5
C57: Bull | D57: -3.5 | E57: -3 | F57: -2.5 | G57: -1.75 | H57: -1.25 | I57: -0.75 | J57: -0.5 | K57: -0.25
C58: Bear | D58: -3.5 | E58: -3 | F58: -2.5 | G58: -2.25 | H58: -1.75 | I58: -1.25 | J58: -1 | K58: -0.75
B60: 3. BALANCE SHEET & CASH FLOW ASSUMPTIONS
B62: Working Capital Metrics
B64: Days Sales Outstanding (DSO) | C64: Base | D64: 55 | E64: 53 | F64: 51 | G64: 50 | H64: 49 | I64: 48 | J64: 47 | K64: 46
C65: Bull | D65: 55 | E65: 53 | F65: 51 | G65: 49 | H65: 47 | I65: 46 | J65: 45 | K65: 44
C66: Bear | D66: 55 | E66: 53 | F66: 51 | G66: 52 | H66: 51 | I66: 50 | J66: 49 | K66: 48
B68: Days Payable Outstanding (DPO) | C68: Base | D68: 28 | E68: 30 | F68: 32 | G68: 33 | H68: 34 | I68: 35 | J68: 36 | K68: 37
C69: Bull | D69: 28 | E69: 30 | F69: 32 | G69: 34 | H69: 36 | I69: 37 | J69: 38 | K69: 39
C70: Bear | D70: 28 | E70: 30 | F70: 32 | G70: 32 | H70: 32 | I70: 33 | J70: 34 | K70: 35
B72: ='Company1808 3-Statement'!$B$51 | C72: % Increase | E72: 0.04 | F72: 0.038461538 | G72: 0.04 | H72: 0.04 | I72: 0.04 | J72: 0.04 | K72: 0.04
B73: ='Company1808 3-Statement'!$B$59 | C73: % Increase | E73: 0.12 | F73: 0.14285714 | G73: 0.1 | H73: 0.1 | I73: 0.1 | J73: 0.1 | K73: 0.1
B74: ='Company1808 3-Statement'!$B$68 | C74: % Increase | E74: 0.0625 | F74: 0.058823529 | G74: 0.05 | H74: 0.05 | I74: 0.05 | J74: 0.05 | K74: 0.05
B76: Capital Expenditure
B78: CapEx (% of Revenue) | C78: Base | D78: 0.185 | E78: 0.22 | F78: 0.245 | G78: 0.23 | H78: 0.215 | I78: 0.2 | J78: 0.19 | K78: 0.18
C79: Bull | D79: 0.185 | E79: 0.22 | F79: 0.245 | G79: 0.22 | H79: 0.205 | I79: 0.19 | J79: 0.18 | K79: 0.17
C80: Bear | D80: 0.185 | E80: 0.22 | F80: 0.245 | G80: 0.24 | H80: 0.225 | I80: 0.21 | J80: 0.2 | K80: 0.19
B82: D&A (% of Prior Year CapEx) | C82: Base | D82: 0.65 | E82: 0.65 | F82: 0.65 | G82: 0.65 | H82: 0.65 | I82: 0.65 | J82: 0.65 | K82: 0.65
C83: Bull | D83: 0.65 | E83: 0.65 | F83: 0.65 | G83: 0.63 | H83: 0.63 | I83: 0.63 | J83: 0.63 | K83: 0.63
C84: Bear | D84: 0.65 | E84: 0.65 | F84: 0.65 | G84: 0.67 | H84: 0.67 | I84: 0.67 | J84: 0.67 | K84: 0.67
B88: 4. OTHER FINANCIAL ASSUMPTIONS
B90: Tax Rate
B92: Effective Tax Rate | C92: Base | D92: 0.175 | E92: 0.19 | F92: 0.185 | G92: 0.19 | H92: 0.195 | I92: 0.2 | J92: 0.205 | K92: 0.21
C93: Bull | D93: 0.175 | E93: 0.19 | F93: 0.185 | G93: 0.185 | H93: 0.19 | I93: 0.195 | J93: 0.2 | K93: 0.205
C94: Bear | D94: 0.175 | E94: 0.19 | F94: 0.185 | G94: 0.195 | H94: 0.2 | I94: 0.205 | J94: 0.21 | K94: 0.215
B97: Interest Rates
B99: Interest Income Rate (on cash) | C99: Base | D99: 0.005 | E99: 0.015 | F99: 0.025 | G99: 0.035 | H99: 0.03 | I99: 0.025 | J99: 0.025 | K99: 0.02
C100: Bull | D100: 0.01 | E100: 0.02 | F100: 0.03 | G100: 0.04 | H100: 0.045 | I100: 0.04 | J100: 0.035 | K100: 0.035
C101: Bear | D101: 0.0025 | E101: 0.0125 | F101: 0.0225 | G101: 0.0325 | H101: 0.0375 | I101: 0.0325 | J101: 0.0275 | K101: 0.0275
B103: Interest Expense Rate (on LT debt) | C103: Base | D103: 0.03 | E103: 0.035 | F103: 0.04 | G103: 0.045 | H103: 0.04 | I103: 0.035 | J103: 0.03 | K103: 0.03
C104: Bull | D104: 0.025 | E104: 0.03 | F104: 0.035 | G104: 0.04 | H104: 0.035 | I104: 0.03 | J104: 0.025 | K104: 0.025
C105: Bear | D105: 0.04 | E105: 0.045 | F105: 0.05 | G105: 0.055 | H105: 0.05 | I105: 0.045 | J105: 0.04 | K105: 0.04
B107: Share Buyback & Dividends
B109: Buyback (% of FCF) | C109: Base | D109: 0.6 | E109: 0.65 | F109: 0.7 | G109: 0.65 | H109: 0.65 | I109: 0.6 | J109: 0.6 | K109: 0.55
C110: Bull | D110: 0.6 | E110: 0.65 | F110: 0.7 | G110: 0.7 | H110: 0.7 | I110: 0.65 | J110: 0.65 | K110: 0.6
C111: Bear | D111: 0.6 | E111: 0.65 | F111: 0.7 | G111: 0.6 | H111: 0.6 | I111: 0.55 | J111: 0.55 | K111: 0.5
B113: Dividend Payout Ratio | C113: Base | D113: 0 | E113: 0 | F113: 0.02 | G113: 0.03 | H113: 0.04 | I113: 0.05 | J113: 0.06 | K113: 0.07
C114: Bull | D114: 0 | E114: 0 | F114: 0.02 | G114: 0.04 | H114: 0.05 | I114: 0.06 | J114: 0.07 | K114: 0.08
C115: Bear | D115: 0 | E115: 0 | F115: 0.02 | G115: 0.02 | H115: 0.03 | I115: 0.04 | J115: 0.05 | K115: 0.06

Sheet Company1153 3-Statement
B2: COMPANY1153 (Company0080) - INCOME STATEMENT
B3: $ in millions
B5: Selected Scenario: | D5: ='Company1153 Assumptions'!D6
B7: Historical | F7: Projections
C8: 2021 | D8: 2022 | E8: 2023 | F8: 2024 | G8: 2025 | H8: 2026 | I8: 2027 | J8: 2028
B10: INCOME STATEMENT
B12: Company1153 Search | C12: 148951 | D12: 162450 | E12: 175033 | F12: =E12*(1+INDEX('Company1153 Assumptions'!G$15:G$17,MATCH($D$5,'Company1153 Assumptions'!$C$15:$C$17,0))) | G12: =F12*(1+INDEX('Company1153 Assumptions'!H$15:H$17,MATCH($D$5,'Company1153 Assumptions'!$C$15:$C$17,0))) | H12: =G12*(1+INDEX('Company1153 Assumptions'!I$15:I$17,MATCH($D$5,'Company1153 Assumptions'!$C$15:$C$17,0))) | I12: =H12*(1+INDEX('Company1153 Assumptions'!J$15:J$17,MATCH($D$5,'Company1153 Assumptions'!$C$15:$C$17,0))) | J12: =I12*(1+INDEX('Company1153 Assumptions'!K$15:K$17,MATCH($D$5,'Company1153 Assumptions'!$C$15:$C$17,0)))
B13: Product0476 Ads | C13: 28845 | D13: 29243 | E13: 31865 | F13: =E13*(1+INDEX('Company1153 Assumptions'!G$19:G$21,MATCH($D$5,'Company1153 Assumptions'!$C$19:$C$21,0))) | G13: =F13*(1+INDEX('Company1153 Assumptions'!H$19:H$21,MATCH($D$5,'Company1153 Assumptions'!$C$19:$C$21,0))) | H13: =G13*(1+INDEX('Company1153 Assumptions'!I$19:I$21,MATCH($D$5,'Company1153 Assumptions'!$C$19:$C$21,0))) | I13: =H13*(1+INDEX('Company1153 Assumptions'!J$19:J$21,MATCH($D$5,'Company1153 Assumptions'!$C$19:$C$21,0))) | J13: =I13*(1+INDEX('Company1153 Assumptions'!K$19:K$21,MATCH($D$5,'Company1153 Assumptions'!$C$19:$C$21,0)))
B14: Company1153 Cloud | C14: 13059 | D14: 19206 | E14: 26280 | F14: =E14*(1+INDEX('Company1153 Assumptions'!G$23:G$25,MATCH($D$5,'Company1153 Assumptions'!$C$23:$C$25,0))) | G14: =F14*(1+INDEX('Company1153 Assumptions'!H$23:H$25,MATCH($D$5,'Company1153 Assumptions'!$C$23:$C$25,0))) | H14: =G14*(1+INDEX('Company1153 Assumptions'!I$23:I$25,MATCH($D$5,'Company1153 Assumptions'!$C$23:$C$25,0))) | I14: =H14*(1+INDEX('Company1153 Assumptions'!J$23:J$25,MATCH($D$5,'Company1153 Assumptions'!$C$23:$C$25,0))) | J14: =I14*(1+INDEX('Company1153 Assumptions'!K$23:K$25,MATCH($D$5,'Company1153 Assumptions'!$C$23:$C$25,0)))
B15: Other Revenues | C15: 28032 | D15: 29071 | E15: 30300 | F15: =E15*(1+INDEX('Company1153 Assumptions'!G$27:G$29,MATCH($D$5,'Company1153 Assumptions'!$C$27:$C$29,0))) | G15: =F15*(1+INDEX('Company1153 Assumptions'!H$27:H$29,MATCH($D$5,'Company1153 Assumptions'!$C$27:$C$29,0))) | H15: =G15*(1+INDEX('Company1153 Assumptions'!I$27:I$29,MATCH($D$5,'Company1153 Assumptions'!$C$27:$C$29,0))) | I15: =H15*(1+INDEX('Company1153 Assumptions'!J$27:J$29,MATCH($D$5,'Company1153 Assumptions'!$C$27:$C$29,0))) | J15: =I15*(1+INDEX('Company1153 Assumptions'!K$27:K$29,MATCH($D$5,'Company1153 Assumptions'!$C$27:$C$29,0)))
B16: Total Revenue | C16: =SUM(C12:C15) | D16: =SUM(D12:D15) | E16: =SUM(E12:E15) | F16: =SUM(F12:F15) | G16: =SUM(G12:G15) | H16: =SUM(H12:H15) | I16: =SUM(I12:I15) | J16: =SUM(J12:J15)
B17: YoY Growth % | D17: =D16/C16-1 | E17: =E16/D16-1 | F17: =F16/E16-1 | G17: =G16/F16-1 | H17: =H16/G16-1 | I17: =I16/H16-1 | J17: =J16/I16-1
B19: Cost of Revenue | C19: =C16*(1-C21) | D19: =D16*(1-D21) | E19: =E16*(1-E21) | F19: =F16*(1-F21) | G19: =G16*(1-G21) | H19: =H16*(1-H21) | I19: =I16*(1-I21) | J19: =J16*(1-J21)
B20: Gross Profit | C20: =C16-C19 | D20: =D16-D19 | E20: =E16-E19 | F20: =F16-F19 | G20: =G16-G19 | H20: =H16-H19 | I20: =I16-I19 | J20: =J16-J19
B21: Gross Margin % | C21: 0.545 | D21: 0.548 | E21: 0.55 | F21: 0.552 | G21: 0.554 | H21: 0.556 | I21: 0.558 | J21: 0.56
B23: Research & Development | C23: =C16*INDEX('Company1153 Assumptions'!D$35:D$37,MATCH($D$5,'Company1153 Assumptions'!$C$35:$C$37,0)) | D23: =D16*INDEX('Company1153 Assumptions'!E$35:E$37,MATCH($D$5,'Company1153 Assumptions'!$C$35:$C$37,0)) | E23: =E16*INDEX('Company1153 Assumptions'!F$35:F$37,MATCH($D$5,'Company1153 Assumptions'!$C$35:$C$37,0)) | F23: =F16*INDEX('Company1153 Assumptions'!G$35:G$37,MATCH($D$5,'Company1153 Assumptions'!$C$35:$C$37,0)) | G23: =G16*INDEX('Company1153 Assumptions'!H$35:H$37,MATCH($D$5,'Company1153 Assumptions'!$C$35:$C$37,0)) | H23: =H16*INDEX('Company1153 Assumptions'!I$35:I$37,MATCH($D$5,'Company1153 Assumptions'!$C$35:$C$37,0)) | I23: =I16*INDEX('Company1153 Assumptions'!J$35:J$37,MATCH($D$5,'Company1153 Assumptions'!$C$35:$C$37,0)) | J23: =J16*INDEX('Company1153 Assumptions'!K$35:K$37,MATCH($D$5,'Company1153 Assumptions'!$C$35:$C$37,0))
B24: Sales & Marketing | C24: =C16*INDEX('Company1153 Assumptions'!D$39:D$41,MATCH($D$5,'Company1153 Assumptions'!$C$39:$C$41,0)) | D24: =D16*INDEX('Company1153 Assumptions'!E$39:E$41,MATCH($D$5,'Company1153 Assumptions'!$C$39:$C$41,0)) | E24: =E16*INDEX('Company1153 Assumptions'!F$39:F$41,MATCH($D$5,'Company1153 Assumptions'!$C$39:$C$41,0)) | F24: =F16*INDEX('Company1153 Assumptions'!G$39:G$41,MATCH($D$5,'Company1153 Assumptions'!$C$39:$C$41,0)) | G24: =G16*INDEX('Company1153 Assumptions'!H$39:H$41,MATCH($D$5,'Company1153 Assumptions'!$C$39:$C$41,0)) | H24: =H16*INDEX('Company1153 Assumptions'!I$39:I$41,MATCH($D$5,'Company1153 Assumptions'!$C$39:$C$41,0)) | I24: =I16*INDEX('Company1153 Assumptions'!J$39:J$41,MATCH($D$5,'Company1153 Assumptions'!$C$39:$C$41,0)) | J24: =J16*INDEX('Company1153 Assumptions'!K$39:K$41,MATCH($D$5,'Company1153 Assumptions'!$C$39:$C$41,0))
B25: General & Administrative | C25: =C16*INDEX('Company1153 Assumptions'!D$43:D$45,MATCH($D$5,'Company1153 Assumptions'!$C$43:$C$45,0)) | D25: =D16*INDEX('Company1153 Assumptions'!E$43:E$45,MATCH($D$5,'Company1153 Assumptions'!$C$43:$C$45,0)) | E25: =E16*INDEX('Company1153 Assumptions'!F$43:F$45,MATCH($D$5,'Company1153 Assumptions'!$C$43:$C$45,0)) | F25: =F16*INDEX('Company1153 Assumptions'!G$43:G$45,MATCH($D$5,'Company1153 Assumptions'!$C$43:$C$45,0)) | G25: =G16*INDEX('Company1153 Assumptions'!H$43:H$45,MATCH($D$5,'Company1153 Assumptions'!$C$43:$C$45,0)) | H25: =H16*INDEX('Company1153 Assumptions'!I$43:I$45,MATCH($D$5,'Company1153 Assumptions'!$C$43:$C$45,0)) | I25: =I16*INDEX('Company1153 Assumptions'!J$43:J$45,MATCH($D$5,'Company1153 Assumptions'!$C$43:$C$45,0)) | J25: =J16*INDEX('Company1153 Assumptions'!K$43:K$45,MATCH($D$5,'Company1153 Assumptions'!$C$43:$C$45,0))
B26: Stock-Based Compensation | C26: =C16*INDEX('Company1153 Assumptions'!D$47:D$49,MATCH($D$5,'Company1153 Assumptions'!$C$47:$C$49,0)) | D26: =D16*INDEX('Company1153 Assumptions'!E$47:E$49,MATCH($D$5,'Company1153 Assumptions'!$C$47:$C$49,0)) | E26: =E16*INDEX('Company1153 Assumptions'!F$47:F$49,MATCH($D$5,'Company1153 Assumptions'!$C$47:$C$49,0)) | F26: =F16*INDEX('Company1153 Assumptions'!G$47:G$49,MATCH($D$5,'Company1153 Assumptions'!$C$47:$C$49,0)) | G26: =G16*INDEX('Company1153 Assumptions'!H$47:H$49,MATCH($D$5,'Company1153 Assumptions'!$C$47:$C$49,0)) | H26: =H16*INDEX('Company1153 Assumptions'!I$47:I$49,MATCH($D$5,'Company1153 Assumptions'!$C$47:$C$49,0)) | I26: =I16*INDEX('Company1153 Assumptions'!J$47:J$49,MATCH($D$5,'Company1153 Assumptions'!$C$47:$C$49,0)) | J26: =J16*INDEX('Company1153 Assumptions'!K$47:K$49,MATCH($D$5,'Company1153 Assumptions'!$C$47:$C$49,0))
B27: Total Operating Expenses | C27: =SUM(C23:C26) | D27: =SUM(D23:D26) | E27: =SUM(E23:E26) | F27: =SUM(F23:F26) | G27: =SUM(G23:G26) | H27: =SUM(H23:H26) | I27: =SUM(I23:I26) | J27: =SUM(J23:J26)
B29: Operating Income (EBIT) | C29: =C20-C27 | D29: =D20-D27 | E29: =E20-E27 | F29: =F20-F27 | G29: =G20-G27 | H29: =H20-H27 | I29: =I20-I27 | J29: =J20-J27
B30: Operating Margin % | C30: =C29/C16 | D30: =D29/D16 | E30: =E29/E16 | F30: =F29/F16 | G30: =G29/G16 | H30: =H29/H16 | I30: =I29/I16 | J30: =J29/J16
B32: Interest (Expense) / Income | C32: =(C$51*INDEX('Company1153 Assumptions'!$D$88:$D$90,MATCH($D$5,'Company1153 Assumptions'!$C$88:$C$90,0)))-(C73*INDEX('Company1153 Assumptions'!$D$92:$D$94,MATCH($D$5,'Company1153 Assumptions'!$C$92:$C$94,0))) | D32: =(D$51*INDEX('Company1153 Assumptions'!$D$88:$D$90,MATCH($D$5,'Company1153 Assumptions'!$C$88:$C$90,0)))-(D73*INDEX('Company1153 Assumptions'!$D$92:$D$94,MATCH($D$5,'Company1153 Assumptions'!$C$92:$C$94,0))) | E32: =(E$51*INDEX('Company1153 Assumptions'!$D$88:$D$90,MATCH($D$5,'Company1153 Assumptions'!$C$88:$C$90,0)))-(E73*INDEX('Company1153 Assumptions'!$D$92:$D$94,MATCH($D$5,'Company1153 Assumptions'!$C$92:$C$94,0))) | F32: =(F$51*INDEX('Company1153 Assumptions'!$D$88:$D$90,MATCH($D$5,'Company1153 Assumptions'!$C$88:$C$90,0)))-(F73*INDEX('Company1153 Assumptions'!$D$92:$D$94,MATCH($D$5,'Company1153 Assumptions'!$C$92:$C$94,0))) | G32: =(G$51*INDEX('Company1153 Assumptions'!$D$88:$D$90,MATCH($D$5,'Company1153 Assumptions'!$C$88:$C$90,0)))-(G73*INDEX('Company1153 Assumptions'!$D$92:$D$94,MATCH($D$5,'Company1153 Assumptions'!$C$92:$C$94,0))) | H32: =(H$51*INDEX('Company1153 Assumptions'!$D$88:$D$90,MATCH($D$5,'Company1153 Assumptions'!$C$88:$C$90,0)))-(H73*INDEX('Company1153 Assumptions'!$D$92:$D$94,MATCH($D$5,'Company1153 Assumptions'!$C$92:$C$94,0))) | I32: =(I$51*INDEX('Company1153 Assumptions'!$D$88:$D$90,MATCH($D$5,'Company1153 Assumptions'!$C$88:$C$90,0)))-(I73*INDEX('Company1153 Assumptions'!$D$92:$D$94,MATCH($D$5,'Company1153 Assumptions'!$C$92:$C$94,0))) | J32: =(J$51*INDEX('Company1153 Assumptions'!$D$88:$D$90,MATCH($D$5,'Company1153 Assumptions'!$C$88:$C$90,0)))-(J73*INDEX('Company1153 Assumptions'!$D$92:$D$94,MATCH($D$5,'Company1153 Assumptions'!$C$92:$C$94,0)))
B34: Income Before Tax | C34: =C29+C32 | D34: =D29+D32 | E34: =E29+E32 | F34: =F29+F32 | G34: =G29+G32 | H34: =H29+H32 | I34: =I29+I32 | J34: =J29+J32
B35: Tax Provision | C35: =C34*INDEX('Company1153 Assumptions'!D$81:D$83,MATCH($D$5,'Company1153 Assumptions'!$C$81:$C$83,0)) | D35: =D34*INDEX('Company1153 Assumptions'!E$81:E$83,MATCH($D$5,'Company1153 Assumptions'!$C$81:$C$83,0)) | E35: =E34*INDEX('Company1153 Assumptions'!F$81:F$83,MATCH($D$5,'Company1153 Assumptions'!$C$81:$C$83,0)) | F35: =F34*INDEX('Company1153 Assumptions'!G$81:G$83,MATCH($D$5,'Company1153 Assumptions'!$C$81:$C$83,0)) | G35: =G34*INDEX('Company1153 Assumptions'!H$81:H$83,MATCH($D$5,'Company1153 Assumptions'!$C$81:$C$83,0)) | H35: =H34*INDEX('Company1153 Assumptions'!I$81:I$83,MATCH($D$5,'Company1153 Assumptions'!$C$81:$C$83,0)) | I35: =I34*INDEX('Company1153 Assumptions'!J$81:J$83,MATCH($D$5,'Company1153 Assumptions'!$C$81:$C$83,0)) | J35: =J34*INDEX('Company1153 Assumptions'!K$81:K$83,MATCH($D$5,'Company1153 Assumptions'!$C$81:$C$83,0))
B37: NET INCOME | C37: =C34-C35 | D37: =D34-D35 | E37: =E34-E35 | F37: =F34-F35 | G37: =G34-G35 | H37: =H34-H35 | I37: =I34-I35 | J37: =J34-J35
B38: Net Margin % | C38: =C37/C16 | D38: =D37/D16 | E38: =E37/E16 | F38: =F37/F16 | G38: =G37/G16 | H38: =H37/H16 | I38: =I37/I16 | J38: =J37/J16
B40: EARNINGS PER SHARE
B42: Basic Shares Outstanding | C42: 13000 | D42: 12800 | E42: 12600 | F42: 12400 | G42: 12200 | H42: 12000 | I42: 11800 | J42: 11600
B43: Basic EPS | C43: =C37/C42 | D43: =D37/D42 | E43: =E37/E42 | F43: =F37/F42 | G43: =G37/G42 | H43: =H37/H42 | I43: =I37/I42 | J43: =J37/J42
B46: BALANCE SHEET
B48: ASSETS
B50: Current Assets
B51: Cash & Cash Equivalents | C51: 90000 | D51: =D$108 | E51: =E$108 | F51: =F$108 | G51: =G$108 | H51: =H$108 | I51: =I$108 | J51: =J$108
B52: Accounts Receivable | C52: =C$16*INDEX('Company1153 Assumptions'!D$55:D$57,MATCH($D$5,'Company1153 Assumptions'!$C$55:$C$57,0))/365 | D52: =D$16*INDEX('Company1153 Assumptions'!E$55:E$57,MATCH($D$5,'Company1153 Assumptions'!$C$55:$C$57,0))/365 | E52: =E$16*INDEX('Company1153 Assumptions'!F$55:F$57,MATCH($D$5,'Company1153 Assumptions'!$C$55:$C$57,0))/365 | F52: =F$16*INDEX('Company1153 Assumptions'!G$55:G$57,MATCH($D$5,'Company1153 Assumptions'!$C$55:$C$57,0))/365 | G52: =G$16*INDEX('Company1153 Assumptions'!H$55:H$57,MATCH($D$5,'Company1153 Assumptions'!$C$55:$C$57,0))/365 | H52: =H$16*INDEX('Company1153 Assumptions'!I$55:I$57,MATCH($D$5,'Company1153 Assumptions'!$C$55:$C$57,0))/365 | I52: =I$16*INDEX('Company1153 Assumptions'!J$55:J$57,MATCH($D$5,'Company1153 Assumptions'!$C$55:$C$57,0))/365 | J52: =J$16*INDEX('Company1153 Assumptions'!K$55:K$57,MATCH($D$5,'Company1153 Assumptions'!$C$55:$C$57,0))/365
B53: Other Current Assets | C53: 8500 | D53: =C53*(1+'Company1153 Assumptions'!E$63) | E53: =D53*(1+'Company1153 Assumptions'!F$63) | F53: =E53*(1+'Company1153 Assumptions'!G$63) | G53: =F53*(1+'Company1153 Assumptions'!H$63) | H53: =G53*(1+'Company1153 Assumptions'!I$63) | I53: =H53*(1+'Company1153 Assumptions'!J$63) | J53: =I53*(1+'Company1153 Assumptions'!K$63)
B54: Total Current Assets | C54: =SUM(C51:C53) | D54: =SUM(D51:D53) | E54: =SUM(E51:E53) | F54: =SUM(F51:F53) | G54: =SUM(G51:G53) | H54: =SUM(H51:H53) | I54: =SUM(I51:I53) | J54: =SUM(J51:J53)
B56: Non-Current Assets
B57: Property, Plant & Equipment (Gross) | C57: 80000 | D57: =C57+D97 | E57: =D57+E97 | F57: =E57+F97 | G57: =F57+G97 | H57: =G57+H97 | I57: =H57+I97 | J57: =I57+J97
B58: Less: Accumulated Depreciation | C58: 25000 | D58: =C58+D89 | E58: =D58+E89 | F58: =E58+F89 | G58: =F58+G89 | H58: =G58+H89 | I58: =H58+I89 | J58: =I58+J89
B59: Net PP&E | C59: =C57-C58 | D59: =D57-D58 | E59: =E57-E58 | F59: =F57-F58 | G59: =G57-G58 | H59: =H57-H58 | I59: =I57-I58 | J59: =J57-J58
B61: Other Long-term Assets | C61: 35000 | D61: =C61*(1+'Company1153 Assumptions'!E$64) | E61: =D61*(1+'Company1153 Assumptions'!F$64) | F61: =E61*(1+'Company1153 Assumptions'!G$64) | G61: =F61*(1+'Company1153 Assumptions'!H$64) | H61: =G61*(1+'Company1153 Assumptions'!I$64) | I61: =H61*(1+'Company1153 Assumptions'!J$64) | J61: =I61*(1+'Company1153 Assumptions'!K$64)
B62: Total Non-Current Assets | C62: =C59+C61 | D62: =D59+D61 | E62: =E59+E61 | F62: =F59+F61 | G62: =G59+G61 | H62: =H59+H61 | I62: =I59+I61 | J62: =J59+J61
B64: TOTAL ASSETS | C64: =C54+C62 | D64: =D54+D62 | E64: =E54+E62 | F64: =F54+F62 | G64: =G54+G62 | H64: =H54+H62 | I64: =I54+I62 | J64: =J54+J62
B66: LIABILITIES & EQUITY
B68: Current Liabilities
B69: Accounts Payable | C69: =(C19+C23+C24+C25)*INDEX('Company1153 Assumptions'!D$59:D$61,MATCH($D$5,'Company1153 Assumptions'!$C$59:$C$61,0))/365 | D69: =(D19+D23+D24+D25)*INDEX('Company1153 Assumptions'!E$59:E$61,MATCH($D$5,'Company1153 Assumptions'!$C$59:$C$61,0))/365 | E69: =(E19+E23+E24+E25)*INDEX('Company1153 Assumptions'!F$59:F$61,MATCH($D$5,'Company1153 Assumptions'!$C$59:$C$61,0))/365 | F69: =(F19+F23+F24+F25)*INDEX('Company1153 Assumptions'!G$59:G$61,MATCH($D$5,'Company1153 Assumptions'!$C$59:$C$61,0))/365 | G69: =(G19+G23+G24+G25)*INDEX('Company1153 Assumptions'!H$59:H$61,MATCH($D$5,'Company1153 Assumptions'!$C$59:$C$61,0))/365 | H69: =(H19+H23+H24+H25)*INDEX('Company1153 Assumptions'!I$59:I$61,MATCH($D$5,'Company1153 Assumptions'!$C$59:$C$61,0))/365 | I69: =(I19+I23+I24+I25)*INDEX('Company1153 Assumptions'!J$59:J$61,MATCH($D$5,'Company1153 Assumptions'!$C$59:$C$61,0))/365 | J69: =(J19+J23+J24+J25)*INDEX('Company1153 Assumptions'!K$59:K$61,MATCH($D$5,'Company1153 Assumptions'!$C$59:$C$61,0))/365
B70: Accrued Expenses | C70: 12000 | D70: =C70*(1+'Company1153 Assumptions'!E$65) | E70: =D70*(1+'Company1153 Assumptions'!F$65) | F70: =E70*(1+'Company1153 Assumptions'!G$65) | G70: =F70*(1+'Company1153 Assumptions'!H$65) | H70: =G70*(1+'Company1153 Assumptions'!I$65) | I70: =H70*(1+'Company1153 Assumptions'!J$65) | J70: =I70*(1+'Company1153 Assumptions'!K$65)
B71: Total Current Liabilities | C71: =SUM(C69:C70) | D71: =SUM(D69:D70) | E71: =SUM(E69:E70) | F71: =SUM(F69:F70) | G71: =SUM(G69:G70) | H71: =SUM(H69:H70) | I71: =SUM(I69:I70) | J71: =SUM(J69:J70)
B73: Long-term Debt | C73: 15000 | D73: 14000 | E73: 13000 | F73: 12500 | G73: 12000 | H73: 11500 | I73: 11000 | J73: 10500
B74: Total Liabilities | C74: =C71+C73 | D74: =D71+D73 | E74: =E71+E73 | F74: =F71+F73 | G74: =G71+G73 | H74: =H71+H73 | I74: =I71+I73 | J74: =J71+J73
B76: Shareholders' Equity
B77: Common Stock & APIC | C77: 50000 | D77: =C77+D90 | E77: =D77+E90 | F77: =E77+F90 | G77: =F77+G90 | H77: =G77+H90 | I77: =H77+I90 | J77: =I77+J90
B78: Treasury Stock | C78: 24855.844 | D78: =C78+D102 | E78: =D78+E102 | F78: =E78+F102 | G78: =F78+G102 | H78: =G78+H102 | I78: =H78+I102 | J78: =I78+J102
B79: Retained Earnings | C79: 150000 | D79: =C79+D88 | E79: =D79+E88 | F79: =E79+F88 | G79: =F79+G88 | H79: =G79+H88 | I79: =H79+I88 | J79: =I79+J88
B80: Total Shareholders' Equity | C80: =C77-C78+C79 | D80: =D77-D78+D79 | E80: =E77-E78+E79 | F80: =F77-F78+F79 | G80: =G77-G78+G79 | H80: =H77-H78+H79 | I80: =I77-I78+I79 | J80: =J77-J78+J79
B82: TOTAL LIABILITIES & EQUITY | C82: =C74+C80 | D82: =D74+D80 | E82: =E74+E80 | F82: =F74+F80 | G82: =G74+G80 | H82: =H74+H80 | I82: =I74+I80 | J82: =J74+J80
B84: Balance Check (Assets - L&E) | C84: =C64-C82 | D84: =D64-D82 | E84: =E64-E82 | F84: =F64-F82 | G84: =G64-G82 | H84: =H64-H82 | I84: =I64-I82 | J84: =J64-J82
B86: CASH FLOW STATEMENT
B87: Cash Flow from Operating Activities
B88: Net Income | D88: {=D37} | E88: {=E37} | F88: {=F37} | G88: {=G37} | H88: {=H37} | I88: {=I37} | J88: {=J37}
B89: Add: Depreciation & Amortization | D89: =C$97*INDEX('Company1153 Assumptions'!E$73:E$75,MATCH($D$5,'Company1153 Assumptions'!$C$73:$C$75,0)) | E89: =D$97*INDEX('Company1153 Assumptions'!F$73:F$75,MATCH($D$5,'Company1153 Assumptions'!$C$73:$C$75,0)) | F89: =E$97*INDEX('Company1153 Assumptions'!G$73:G$75,MATCH($D$5,'Company1153 Assumptions'!$C$73:$C$75,0)) | G89: =F$97*INDEX('Company1153 Assumptions'!H$73:H$75,MATCH($D$5,'Company1153 Assumptions'!$C$73:$C$75,0)) | H89: =G$97*INDEX('Company1153 Assumptions'!I$73:I$75,MATCH($D$5,'Company1153 Assumptions'!$C$73:$C$75,0)) | I89: =H$97*INDEX('Company1153 Assumptions'!J$73:J$75,MATCH($D$5,'Company1153 Assumptions'!$C$73:$C$75,0)) | J89: =I$97*INDEX('Company1153 Assumptions'!K$73:K$75,MATCH($D$5,'Company1153 Assumptions'!$C$73:$C$75,0))
B90: Add: Stock-Based Compensation | D90: {=D26} | E90: {=E26} | F90: {=F26} | G90: {=G26} | H90: {=H26} | I90: {=I26} | J90: {=J26}
B91: Changes in Working Capital:
B92: (Increase)/Decrease in Current Assets | D92: =-(SUM(D52:D53)-SUM(C52:C53)) | E92: =-(SUM(E52:E53)-SUM(D52:D53)) | F92: =-(SUM(F52:F53)-SUM(E52:E53)) | G92: =-(SUM(G52:G53)-SUM(F52:F53)) | H92: =-(SUM(H52:H53)-SUM(G52:G53)) | I92: =-(SUM(I52:I53)-SUM(H52:H53)) | J92: =-(SUM(J52:J53)-SUM(I52:I53))
B93: Increase/(Decrease) in Current Liabilities | D93: =SUM(D69:D70)-SUM(C69:C70) | E93: =SUM(E69:E70)-SUM(D69:D70) | F93: =SUM(F69:F70)-SUM(E69:E70) | G93: =SUM(G69:G70)-SUM(F69:F70) | H93: =SUM(H69:H70)-SUM(G69:G70) | I93: =SUM(I69:I70)-SUM(H69:H70) | J93: =SUM(J69:J70)-SUM(I69:I70)
B94: Net Cash from Operating Activities | D94: =SUM(D88:D93) | E94: =SUM(E88:E93) | F94: =SUM(F88:F93) | G94: =SUM(G88:G93) | H94: =SUM(H88:H93) | I94: =SUM(I88:I93) | J94: =SUM(J88:J93)
B96: Cash Flow from Investing Activities
B97: Capital Expenditures | C97: =C$16*INDEX('Company1153 Assumptions'!D$69:D$71,MATCH($D$5,'Company1153 Assumptions'!$C$69:$C$71,0)) | D97: =D$16*INDEX('Company1153 Assumptions'!E$69:E$71,MATCH($D$5,'Company1153 Assumptions'!$C$69:$C$71,0)) | E97: =E$16*INDEX('Company1153 Assumptions'!F$69:F$71,MATCH($D$5,'Company1153 Assumptions'!$C$69:$C$71,0)) | F97: =F$16*INDEX('Company1153 Assumptions'!G$69:G$71,MATCH($D$5,'Company1153 Assumptions'!$C$69:$C$71,0)) | G97: =G$16*INDEX('Company1153 Assumptions'!H$69:H$71,MATCH($D$5,'Company1153 Assumptions'!$C$69:$C$71,0)) | H97: =H$16*INDEX('Company1153 Assumptions'!I$69:I$71,MATCH($D$5,'Company1153 Assumptions'!$C$69:$C$71,0)) | I97: =I$16*INDEX('Company1153 Assumptions'!J$69:J$71,MATCH($D$5,'Company1153 Assumptions'!$C$69:$C$71,0)) | J97: =J$16*INDEX('Company1153 Assumptions'!K$69:K$71,MATCH($D$5,'Company1153 Assumptions'!$C$69:$C$71,0))
B98: Long-term investments | D98: =D61-C61 | E98: =E61-D61 | F98: =F61-E61 | G98: =G61-F61 | H98: =H61-G61 | I98: =I61-H61 | J98: =J61-I61
B99: Net Cash from Investing Activities | D99: =-D97-D98 | E99: =-E97-E98 | F99: =-F97-F98 | G99: =-G97-G98 | H99: =-H97-H98 | I99: =-I97-I98 | J99: =-J97-J98
B101: Cash Flow from Financing Activities
B102: Share Repurchases | D102: =MAX(D94+D99,0)*INDEX('Company1153 Assumptions'!E$98:E$100,MATCH($D$5,'Company1153 Assumptions'!$C$98:$C$100,0)) | E102: =MAX(E94+E99,0)*INDEX('Company1153 Assumptions'!F$98:F$100,MATCH($D$5,'Company1153 Assumptions'!$C$98:$C$100,0)) | F102: =MAX(F94+F99,0)*INDEX('Company1153 Assumptions'!G$98:G$100,MATCH($D$5,'Company1153 Assumptions'!$C$98:$C$100,0)) | G102: =MAX(G94+G99,0)*INDEX('Company1153 Assumptions'!H$98:H$100,MATCH($D$5,'Company1153 Assumptions'!$C$98:$C$100,0)) | H102: =MAX(H94+H99,0)*INDEX('Company1153 Assumptions'!I$98:I$100,MATCH($D$5,'Company1153 Assumptions'!$C$98:$C$100,0)) | I102: =MAX(I94+I99,0)*INDEX('Company1153 Assumptions'!J$98:J$100,MATCH($D$5,'Company1153 Assumptions'!$C$98:$C$100,0)) | J102: =MAX(J94+J99,0)*INDEX('Company1153 Assumptions'!K$98:K$100,MATCH($D$5,'Company1153 Assumptions'!$C$98:$C$100,0))
B103: Debt Repayments | D103: =-D$73+C$73 | E103: =-E$73+D$73 | F103: =-F$73+E$73 | G103: =-G$73+F$73 | H103: =-H$73+G$73 | I103: =-I$73+H$73 | J103: =-J$73+I$73
B104: Net Cash from Financing Activities | D104: =-D102-D103 | E104: =-E102-E103 | F104: =-F102-F103 | G104: =-G102-G103 | H104: =-H102-H103 | I104: =-I102-I103 | J104: =-J102-J103
B106: Net Change in Cash | D106: =D94+D99+D104 | E106: =E94+E99+E104 | F106: =F94+F99+F104 | G106: =G94+G99+G104 | H106: =H94+H99+H104 | I106: =I94+I99+I104 | J106: =J94+J99+J104
B107: Beginning Cash | D107: =C$108 | E107: =D$108 | F107: =E$108 | G107: =F$108 | H107: =G$108 | I107: =H$108 | J107: =I$108
B108: Ending Cash | C108: =C51 | D108: =D106+D107 | E108: =E106+E107 | F108: =F106+F107 | G108: =G106+G107 | H108: =H106+H107 | I108: =I106+I107 | J108: =J106+J107
B110: Cash Balance Check | C110: =C108-C51 | D110: =D108-D51 | E110: =E108-E51 | F110: =F108-F51 | G110: =G108-G51 | H110: =H108-H51 | I110: =I108-I51 | J110: =J108-J51

Sheet Company1808 3-Statement
B2: COMPANY1809 - INCOME STATEMENT
B3: $ in millions
B5: Selected Scenario: | D5: ='Company1808 Assumptions'!D6
B7: Historical | F7: Projections
C8: 2021 | D8: 2022 | E8: 2023 | F8: 2024 | G8: 2025 | H8: 2026 | I8: 2027 | J8: 2028
B10: INCOME STATEMENT
B12: Family of Apps | C12: 115655 | D12: 114450 | E12: 133008 | F12: =E12*(1+INDEX('Company1808 Assumptions'!G$15:G$17,MATCH($D$5,'Company1808 Assumptions'!$C$15:$C$17,0))) | G12: =F12*(1+INDEX('Company1808 Assumptions'!H$15:H$17,MATCH($D$5,'Company1808 Assumptions'!$C$15:$C$17,0))) | H12: =G12*(1+INDEX('Company1808 Assumptions'!I$15:I$17,MATCH($D$5,'Company1808 Assumptions'!$C$15:$C$17,0))) | I12: =H12*(1+INDEX('Company1808 Assumptions'!J$15:J$17,MATCH($D$5,'Company1808 Assumptions'!$C$15:$C$17,0))) | J12: =I12*(1+INDEX('Company1808 Assumptions'!K$15:K$17,MATCH($D$5,'Company1808 Assumptions'!$C$15:$C$17,0)))
B13: Product0338 | C13: 2274 | D13: 2159 | E13: 1896 | F13: =E13*(1+INDEX('Company1808 Assumptions'!G$19:G$21,MATCH($D$5,'Company1808 Assumptions'!$C$19:$C$21,0))) | G13: =F13*(1+INDEX('Company1808 Assumptions'!H$19:H$21,MATCH($D$5,'Company1808 Assumptions'!$C$19:$C$21,0))) | H13: =G13*(1+INDEX('Company1808 Assumptions'!I$19:I$21,MATCH($D$5,'Company1808 Assumptions'!$C$19:$C$21,0))) | I13: =H13*(1+INDEX('Company1808 Assumptions'!J$19:J$21,MATCH($D$5,'Company1808 Assumptions'!$C$19:$C$21,0))) | J13: =I13*(1+INDEX('Company1808 Assumptions'!K$19:K$21,MATCH($D$5,'Company1808 Assumptions'!$C$19:$C$21,0)))
B14: Total Revenue | C14: =SUM(C12:C13) | D14: =SUM(D12:D13) | E14: =SUM(E12:E13) | F14: =SUM(F12:F13) | G14: =SUM(G12:G13) | H14: =SUM(H12:H13) | I14: =SUM(I12:I13) | J14: =SUM(J12:J13)
B15: YoY Growth % | D15: =D14/C14-1 | E15: =E14/D14-1 | F15: =F14/E14-1 | G15: =G14/F14-1 | H15: =H14/G14-1 | I15: =I14/H14-1 | J15: =J14/I14-1
B17: Cost of Revenue | C17: =C14*(1-C19) | D17: =D14*(1-D19) | E17: =E14*(1-E19) | F17: =F14*(1-F19) | G17: =G14*(1-G19) | H17: =H14*(1-H19) | I17: =I14*(1-I19) | J17: =J14*(1-J19)
B18: Gross Profit | C18: =C14-C17 | D18: =D14-D17 | E18: =E14-E17 | F18: =F14-F17 | G18: =G14-G17 | H18: =H14-H17 | I18: =I14-I17 | J18: =J14-J17
B19: Gross Margin % | C19: 0.802 | D19: 0.798 | E19: 0.795 | F19: 0.797 | G19: 0.799 | H19: 0.801 | I19: 0.803 | J19: 0.805
B21: Research & Development | C21: =C14*INDEX('Company1808 Assumptions'!D$38:D$40,MATCH($D$5,'Company1808 Assumptions'!$C$38:$C$40,0)) | D21: =D14*INDEX('Company1808 Assumptions'!E$38:E$40,MATCH($D$5,'Company1808 Assumptions'!$C$38:$C$40,0)) | E21: =E14*INDEX('Company1808 Assumptions'!F$38:F$40,MATCH($D$5,'Company1808 Assumptions'!$C$38:$C$40,0)) | F21: =F14*INDEX('Company1808 Assumptions'!G$38:G$40,MATCH($D$5,'Company1808 Assumptions'!$C$38:$C$40,0)) | G21: =G14*INDEX('Company1808 Assumptions'!H$38:H$40,MATCH($D$5,'Company1808 Assumptions'!$C$38:$C$40,0)) | H21: =H14*INDEX('Company1808 Assumptions'!I$38:I$40,MATCH($D$5,'Company1808 Assumptions'!$C$38:$C$40,0)) | I21: =I14*INDEX('Company1808 Assumptions'!J$38:J$40,MATCH($D$5,'Company1808 Assumptions'!$C$38:$C$40,0)) | J21: =J14*INDEX('Company1808 Assumptions'!K$38:K$40,MATCH($D$5,'Company1808 Assumptions'!$C$38:$C$40,0))
B22: Sales & Marketing | C22: =C14*INDEX('Company1808 Assumptions'!D$42:D$44,MATCH($D$5,'Company1808 Assumptions'!$C$42:$C$44,0)) | D22: =D14*INDEX('Company1808 Assumptions'!E$42:E$44,MATCH($D$5,'Company1808 Assumptions'!$C$42:$C$44,0)) | E22: =E14*INDEX('Company1808 Assumptions'!F$42:F$44,MATCH($D$5,'Company1808 Assumptions'!$C$42:$C$44,0)) | F22: =F14*INDEX('Company1808 Assumptions'!G$42:G$44,MATCH($D$5,'Company1808 Assumptions'!$C$42:$C$44,0)) | G22: =G14*INDEX('Company1808 Assumptions'!H$42:H$44,MATCH($D$5,'Company1808 Assumptions'!$C$42:$C$44,0)) | H22: =H14*INDEX('Company1808 Assumptions'!I$42:I$44,MATCH($D$5,'Company1808 Assumptions'!$C$42:$C$44,0)) | I22: =I14*INDEX('Company1808 Assumptions'!J$42:J$44,MATCH($D$5,'Company1808 Assumptions'!$C$42:$C$44,0)) | J22: =J14*INDEX('Company1808 Assumptions'!K$42:K$44,MATCH($D$5,'Company1808 Assumptions'!$C$42:$C$44,0))
B23: General & Administrative | C23: =C14*INDEX('Company1808 Assumptions'!D$46:D$48,MATCH($D$5,'Company1808 Assumptions'!$C$46:$C$48,0)) | D23: =D14*INDEX('Company1808 Assumptions'!E$46:E$48,MATCH($D$5,'Company1808 Assumptions'!$C$46:$C$48,0)) | E23: =E14*INDEX('Company1808 Assumptions'!F$46:F$48,MATCH($D$5,'Company1808 Assumptions'!$C$46:$C$48,0)) | F23: =F14*INDEX('Company1808 Assumptions'!G$46:G$48,MATCH($D$5,'Company1808 Assumptions'!$C$46:$C$48,0)) | G23: =G14*INDEX('Company1808 Assumptions'!H$46:H$48,MATCH($D$5,'Company1808 Assumptions'!$C$46:$C$48,0)) | H23: =H14*INDEX('Company1808 Assumptions'!I$46:I$48,MATCH($D$5,'Company1808 Assumptions'!$C$46:$C$48,0)) | I23: =I14*INDEX('Company1808 Assumptions'!J$46:J$48,MATCH($D$5,'Company1808 Assumptions'!$C$46:$C$48,0)) | J23: =J14*INDEX('Company1808 Assumptions'!K$46:K$48,MATCH($D$5,'Company1808 Assumptions'!$C$46:$C$48,0))
B24: Stock-Based Compensation | C24: =C14*INDEX('Company1808 Assumptions'!D$50:D$52,MATCH($D$5,'Company1808 Assumptions'!$C$50:$C$52,0)) | D24: =D14*INDEX('Company1808 Assumptions'!E$50:E$52,MATCH($D$5,'Company1808 Assumptions'!$C$50:$C$52,0)) | E24: =E14*INDEX('Company1808 Assumptions'!F$50:F$52,MATCH($D$5,'Company1808 Assumptions'!$C$50:$C$52,0)) | F24: =F14*INDEX('Company1808 Assumptions'!G$50:G$52,MATCH($D$5,'Company1808 Assumptions'!$C$50:$C$52,0)) | G24: =G14*INDEX('Company1808 Assumptions'!H$50:H$52,MATCH($D$5,'Company1808 Assumptions'!$C$50:$C$52,0)) | H24: =H14*INDEX('Company1808 Assumptions'!I$50:I$52,MATCH($D$5,'Company1808 Assumptions'!$C$50:$C$52,0)) | I24: =I14*INDEX('Company1808 Assumptions'!J$50:J$52,MATCH($D$5,'Company1808 Assumptions'!$C$50:$C$52,0)) | J24: =J14*INDEX('Company1808 Assumptions'!K$50:K$52,MATCH($D$5,'Company1808 Assumptions'!$C$50:$C$52,0))
B25: Total Operating Expenses | C25: =SUM(C21:C24) | D25: =SUM(D21:D24) | E25: =SUM(E21:E24) | F25: =SUM(F21:F24) | G25: =SUM(G21:G24) | H25: =SUM(H21:H24) | I25: =SUM(I21:I24) | J25: =SUM(J21:J24)
B27: Operating Income (EBIT) | C27: =C18-C25 | D27: =D18-D25 | E27: =E18-E25 | F27: =F18-F25 | G27: =G18-G25 | H27: =H18-H25 | I27: =I18-I25 | J27: =J18-J25
B28: Operating Margin % | C28: =C27/C14 | D28: =D27/D14 | E28: =E27/E14 | F28: =F27/F14 | G28: =G27/G14 | H28: =H27/H14 | I28: =I27/I14 | J28: =J27/J14
B30: Interest (Expense) / Income | C30: =(C$49*INDEX('Company1808 Assumptions'!$D$99:$D$101,MATCH($D$5,'Company1808 Assumptions'!$C$99:$C$101,0)))-(C71*INDEX('Company1808 Assumptions'!$D$103:$D$105,MATCH($D$5,'Company1808 Assumptions'!$C$103:$C$105,0))) | D30: =(D$49*INDEX('Company1808 Assumptions'!$D$99:$D$101,MATCH($D$5,'Company1808 Assumptions'!$C$99:$C$101,0)))-(D71*INDEX('Company1808 Assumptions'!$D$103:$D$105,MATCH($D$5,'Company1808 Assumptions'!$C$103:$C$105,0))) | E30: =(E$49*INDEX('Company1808 Assumptions'!$D$99:$D$101,MATCH($D$5,'Company1808 Assumptions'!$C$99:$C$101,0)))-(E71*INDEX('Company1808 Assumptions'!$D$103:$D$105,MATCH($D$5,'Company1808 Assumptions'!$C$103:$C$105,0))) | F30: =(F$49*INDEX('Company1808 Assumptions'!$D$99:$D$101,MATCH($D$5,'Company1808 Assumptions'!$C$99:$C$101,0)))-(F71*INDEX('Company1808 Assumptions'!$D$103:$D$105,MATCH($D$5,'Company1808 Assumptions'!$C$103:$C$105,0))) | G30: =(G$49*INDEX('Company1808 Assumptions'!$D$99:$D$101,MATCH($D$5,'Company1808 Assumptions'!$C$99:$C$101,0)))-(G71*INDEX('Company1808 Assumptions'!$D$103:$D$105,MATCH($D$5,'Company1808 Assumptions'!$C$103:$C$105,0))) | H30: =(H$49*INDEX('Company1808 Assumptions'!$D$99:$D$101,MATCH($D$5,'Company1808 Assumptions'!$C$99:$C$101,0)))-(H71*INDEX('Company1808 Assumptions'!$D$103:$D$105,MATCH($D$5,'Company1808 Assumptions'!$C$103:$C$105,0))) | I30: =(I$49*INDEX('Company1808 Assumptions'!$D$99:$D$101,MATCH($D$5,'Company1808 Assumptions'!$C$99:$C$101,0)))-(I71*INDEX('Company1808 Assumptions'!$D$103:$D$105,MATCH($D$5,'Company1808 Assumptions'!$C$103:$C$105,0))) | J30: =(J$49*INDEX('Company1808 Assumptions'!$D$99:$D$101,MATCH($D$5,'Company1808 Assumptions'!$C$99:$C$101,0)))-(J71*INDEX('Company1808 Assumptions'!$D$103:$D$105,MATCH($D$5,'Company1808 Assumptions'!$C$103:$C$105,0)))
B32: Income Before Tax | C32: =C27+C30 | D32: =D27+D30 | E32: =E27+E30 | F32: =F27+F30 | G32: =G27+G30 | H32: =H27+H30 | I32: =I27+I30 | J32: =J27+J30
B33: Tax Provision | C33: =C32*INDEX('Company1808 Assumptions'!D$92:D$94,MATCH($D$5,'Company1808 Assumptions'!$C$92:$C$94,0)) | D33: =D32*INDEX('Company1808 Assumptions'!E$92:E$94,MATCH($D$5,'Company1808 Assumptions'!$C$92:$C$94,0)) | E33: =E32*INDEX('Company1808 Assumptions'!F$92:F$94,MATCH($D$5,'Company1808 Assumptions'!$C$92:$C$94,0)) | F33: =F32*INDEX('Company1808 Assumptions'!G$92:G$94,MATCH($D$5,'Company1808 Assumptions'!$C$92:$C$94,0)) | G33: =G32*INDEX('Company1808 Assumptions'!H$92:H$94,MATCH($D$5,'Company1808 Assumptions'!$C$92:$C$94,0)) | H33: =H32*INDEX('Company1808 Assumptions'!I$92:I$94,MATCH($D$5,'Company1808 Assumptions'!$C$92:$C$94,0)) | I33: =I32*INDEX('Company1808 Assumptions'!J$92:J$94,MATCH($D$5,'Company1808 Assumptions'!$C$92:$C$94,0)) | J33: =J32*INDEX('Company1808 Assumptions'!K$92:K$94,MATCH($D$5,'Company1808 Assumptions'!$C$92:$C$94,0))
B35: NET INCOME | C35: =C32-C33 | D35: =D32-D33 | E35: =E32-E33 | F35: =F32-F33 | G35: =G32-G33 | H35: =H32-H33 | I35: =I32-I33 | J35: =J32-J33
B36: Net Margin % | C36: =C35/C14 | D36: =D35/D14 | E36: =E35/E14 | F36: =F35/F14 | G36: =G35/G14 | H36: =H35/H14 | I36: =I35/I14 | J36: =J35/J14
B38: EARNINGS PER SHARE
B40: Basic Shares Outstanding | C40: 2800 | D40: 2750 | E40: 2700 | F40: 2650 | G40: 2600 | H40: 2550 | I40: 2500 | J40: 2450
B41: Basic EPS | C41: =C35/C40 | D41: =D35/D40 | E41: =E35/E40 | F41: =F35/F40 | G41: =G35/G40 | H41: =H35/H40 | I41: =I35/I40 | J41: =J35/J40
B44: BALANCE SHEET
B46: ASSETS
B48: Current Assets
B49: Cash & Cash Equivalents | C49: 35000 | D49: =D$106 | E49: =E$106 | F49: =F$106 | G49: =G$106 | H49: =H$106 | I49: =I$106 | J49: =J$106
B50: Accounts Receivable | C50: =C$14*INDEX('Company1808 Assumptions'!D$64:D$66,MATCH($D$5,'Company1808 Assumptions'!$C$64:$C$66,0))/365 | D50: =D$14*INDEX('Company1808 Assumptions'!E$64:E$66,MATCH($D$5,'Company1808 Assumptions'!$C$64:$C$66,0))/365 | E50: =E$14*INDEX('Company1808 Assumptions'!F$64:F$66,MATCH($D$5,'Company1808 Assumptions'!$C$64:$C$66,0))/365 | F50: =F$14*INDEX('Company1808 Assumptions'!G$64:G$66,MATCH($D$5,'Company1808 Assumptions'!$C$64:$C$66,0))/365 | G50: =G$14*INDEX('Company1808 Assumptions'!H$64:H$66,MATCH($D$5,'Company1808 Assumptions'!$C$64:$C$66,0))/365 | H50: =H$14*INDEX('Company1808 Assumptions'!I$64:I$66,MATCH($D$5,'Company1808 Assumptions'!$C$64:$C$66,0))/365 | I50: =I$14*INDEX('Company1808 Assumptions'!J$64:J$66,MATCH($D$5,'Company1808 Assumptions'!$C$64:$C$66,0))/365 | J50: =J$14*INDEX('Company1808 Assumptions'!K$64:K$66,MATCH($D$5,'Company1808 Assumptions'!$C$64:$C$66,0))/365
B51: Other Current Assets | C51: 5000 | D51: =C51*(1+'Company1808 Assumptions'!E$72) | E51: =D51*(1+'Company1808 Assumptions'!F$72) | F51: =E51*(1+'Company1808 Assumptions'!G$72) | G51: =F51*(1+'Company1808 Assumptions'!H$72) | H51: =G51*(1+'Company1808 Assumptions'!I$72) | I51: =H51*(1+'Company1808 Assumptions'!J$72) | J51: =I51*(1+'Company1808 Assumptions'!K$72)
B52: Total Current Assets | C52: =SUM(C49:C51) | D52: =SUM(D49:D51) | E52: =SUM(E49:E51) | F52: =SUM(F49:F51) | G52: =SUM(G49:G51) | H52: =SUM(H49:H51) | I52: =SUM(I49:I51) | J52: =SUM(J49:J51)
B54: Non-Current Assets
B55: Property, Plant & Equipment (Gross) | C55: 60000 | D55: =C55+D95 | E55: =D55+E95 | F55: =E55+F95 | G55: =F55+G95 | H55: =G55+H95 | I55: =H55+I95 | J55: =I55+J95
B56: Less: Accumulated Depreciation | C56: 15000 | D56: =C56+D87 | E56: =D56+E87 | F56: =E56+F87 | G56: =F56+G87 | H56: =G56+H87 | I56: =H56+I87 | J56: =I56+J87
B57: Net PP&E | C57: =C55-C56 | D57: =D55-D56 | E57: =E55-E56 | F57: =F55-F56 | G57: =G55-G56 | H57: =H55-H56 | I57: =I55-I56 | J57: =J55-J56
B59: Other Long-term Assets | C59: 25000 | D59: =C59*(1+'Company1808 Assumptions'!E$73) | E59: =D59*(1+'Company1808 Assumptions'!F$73) | F59: =E59*(1+'Company1808 Assumptions'!G$73) | G59: =F59*(1+'Company1808 Assumptions'!H$73) | H59: =G59*(1+'Company1808 Assumptions'!I$73) | I59: =H59*(1+'Company1808 Assumptions'!J$73) | J59: =I59*(1+'Company1808 Assumptions'!K$73)
B60: Total Non-Current Assets | C60: =C57+C59 | D60: =D57+D59 | E60: =E57+E59 | F60: =F57+F59 | G60: =G57+G59 | H60: =H57+H59 | I60: =I57+I59 | J60: =J57+J59
B62: TOTAL ASSETS | C62: =C52+C60 | D62: =D52+D60 | E62: =E52+E60 | F62: =F52+F60 | G62: =G52+G60 | H62: =H52+H60 | I62: =I52+I60 | J62: =J52+J60
B64: LIABILITIES & EQUITY
B66: Current Liabilities
B67: Accounts Payable | C67: =(C17+C21+C22+C23)*INDEX('Company1808 Assumptions'!D$68:D$70,MATCH($D$5,'Company1808 Assumptions'!$C$68:$C$70,0))/365 | D67: =(D17+D21+D22+D23)*INDEX('Company1808 Assumptions'!E$68:E$70,MATCH($D$5,'Company1808 Assumptions'!$C$68:$C$70,0))/365 | E67: =(E17+E21+E22+E23)*INDEX('Company1808 Assumptions'!F$68:F$70,MATCH($D$5,'Company1808 Assumptions'!$C$68:$C$70,0))/365 | F67: =(F17+F21+F22+F23)*INDEX('Company1808 Assumptions'!G$68:G$70,MATCH($D$5,'Company1808 Assumptions'!$C$68:$C$70,0))/365 | G67: =(G17+G21+G22+G23)*INDEX('Company1808 Assumptions'!H$68:H$70,MATCH($D$5,'Company1808 Assumptions'!$C$68:$C$70,0))/365 | H67: =(H17+H21+H22+H23)*INDEX('Company1808 Assumptions'!I$68:I$70,MATCH($D$5,'Company1808 Assumptions'!$C$68:$C$70,0))/365 | I67: =(I17+I21+I22+I23)*INDEX('Company1808 Assumptions'!J$68:J$70,MATCH($D$5,'Company1808 Assumptions'!$C$68:$C$70,0))/365 | J67: =(J17+J21+J22+J23)*INDEX('Company1808 Assumptions'!K$68:K$70,MATCH($D$5,'Company1808 Assumptions'!$C$68:$C$70,0))/365
B68: Accrued Expenses | C68: 8000 | D68: =C68*(1+'Company1808 Assumptions'!E$74) | E68: =D68*(1+'Company1808 Assumptions'!F$74) | F68: =E68*(1+'Company1808 Assumptions'!G$74) | G68: =F68*(1+'Company1808 Assumptions'!H$74) | H68: =G68*(1+'Company1808 Assumptions'!I$74) | I68: =H68*(1+'Company1808 Assumptions'!J$74) | J68: =I68*(1+'Company1808 Assumptions'!K$74)
B69: Total Current Liabilities | C69: =SUM(C67:C68) | D69: =SUM(D67:D68) | E69: =SUM(E67:E68) | F69: =SUM(F67:F68) | G69: =SUM(G67:G68) | H69: =SUM(H67:H68) | I69: =SUM(I67:I68) | J69: =SUM(J67:J68)
B71: Long-term Debt | C71: 10000 | D71: 9500 | E71: 9000 | F71: 8500 | G71: 8000 | H71: 7500 | I71: 7000 | J71: 6500
B72: Total Liabilities | C72: =C69+C71 | D72: =D69+D71 | E72: =E69+E71 | F72: =F69+F71 | G72: =G69+G71 | H72: =H69+H71 | I72: =I69+I71 | J72: =J69+J71
B74: Shareholders' Equity
B75: Common Stock & APIC | C75: 40000 | D75: =C75+D88 | E75: =D75+E88 | F75: =E75+F88 | G75: =F75+G88 | H75: =G75+H88 | I75: =H75+I88 | J75: =I75+J88
B76: Treasury Stock | C76: 36318.244 | D76: =C76-D100 | E76: =D76-E100 | F76: =E76-F100 | G76: =F76-G100 | H76: =G76-H100 | I76: =H76-I100 | J76: =I76-J100
B77: Retained Earnings | C77: 100000 | D77: =C77+D86 | E77: =D77+E86 | F77: =E77+F86 | G77: =F77+G86 | H77: =G77+H86 | I77: =H77+I86 | J77: =I77+J86
B78: Total Shareholders' Equity | C78: =C75-C76+C77 | D78: =D75-D76+D77 | E78: =E75-E76+E77 | F78: =F75-F76+F77 | G78: =G75-G76+G77 | H78: =H75-H76+H77 | I78: =I75-I76+I77 | J78: =J75-J76+J77
B80: TOTAL LIABILITIES & EQUITY | C80: =C72+C78 | D80: =D72+D78 | E80: =E72+E78 | F80: =F72+F78 | G80: =G72+G78 | H80: =H72+H78 | I80: =I72+I78 | J80: =J72+J78
B82: Balance Check (Assets - L&E) | C82: =C62-C80 | D82: =D62-D80 | E82: =E62-E80 | F82: =F62-F80 | G82: =G62-G80 | H82: =H62-H80 | I82: =I62-I80 | J82: =J62-J80
B84: CASH FLOW STATEMENT
B85: Cash Flow from Operating Activities
B86: Net Income | D86: {=D35} | E86: {=E35} | F86: {=F35} | G86: {=G35} | H86: {=H35} | I86: {=I35} | J86: {=J35}
B87: Add: Depreciation & Amortization | D87: =C$95*INDEX('Company1808 Assumptions'!E$82:E$84,MATCH($D$5,'Company1808 Assumptions'!$C$82:$C$84,0)) | E87: =D$95*INDEX('Company1808 Assumptions'!F$82:F$84,MATCH($D$5,'Company1808 Assumptions'!$C$82:$C$84,0)) | F87: =E$95*INDEX('Company1808 Assumptions'!G$82:G$84,MATCH($D$5,'Company1808 Assumptions'!$C$82:$C$84,0)) | G87: =F$95*INDEX('Company1808 Assumptions'!H$82:H$84,MATCH($D$5,'Company1808 Assumptions'!$C$82:$C$84,0)) | H87: =G$95*INDEX('Company1808 Assumptions'!I$82:I$84,MATCH($D$5,'Company1808 Assumptions'!$C$82:$C$84,0)) | I87: =H$95*INDEX('Company1808 Assumptions'!J$82:J$84,MATCH($D$5,'Company1808 Assumptions'!$C$82:$C$84,0)) | J87: =I$95*INDEX('Company1808 Assumptions'!K$82:K$84,MATCH($D$5,'Company1808 Assumptions'!$C$82:$C$84,0))
B88: Add: Stock-Based Compensation | D88: {=D24} | E88: {=E24} | F88: {=F24} | G88: {=G24} | H88: {=H24} | I88: {=I24} | J88: {=J24}
B89: Changes in Working Capital:
B90: (Increase)/Decrease in Current Assets | D90: =-(SUM(D50:D51)-SUM(C50:C51)) | E90: =-(SUM(E50:E51)-SUM(D50:D51)) | F90: =-(SUM(F50:F51)-SUM(E50:E51)) | G90: =-(SUM(G50:G51)-SUM(F50:F51)) | H90: =-(SUM(H50:H51)-SUM(G50:G51)) | I90: =-(SUM(I50:I51)-SUM(H50:H51)) | J90: =-(SUM(J50:J51)-SUM(I50:I51))
B91: Increase/(Decrease) in Current Liabilities | D91: =SUM(D67:D68)-SUM(C67:C68) | E91: =SUM(E67:E68)-SUM(D67:D68) | F91: =SUM(F67:F68)-SUM(E67:E68) | G91: =SUM(G67:G68)-SUM(F67:F68) | H91: =SUM(H67:H68)-SUM(G67:G68) | I91: =SUM(I67:I68)-SUM(H67:H68) | J91: =SUM(J67:J68)-SUM(I67:I68)
B92: Net Cash from Operating Activities | D92: =SUM(D86:D91) | E92: =SUM(E86:E91) | F92: =SUM(F86:F91) | G92: =SUM(G86:G91) | H92: =SUM(H86:H91) | I92: =SUM(I86:I91) | J92: =SUM(J86:J91)
B94: Cash Flow from Investing Activities
B95: Capital Expenditures | C95: =C$14*INDEX('Company1808 Assumptions'!D$78:D$80,MATCH($D$5,'Company1808 Assumptions'!$C$78:$C$80,0)) | D95: =D$14*INDEX('Company1808 Assumptions'!E$78:E$80,MATCH($D$5,'Company1808 Assumptions'!$C$78:$C$80,0)) | E95: =E$14*INDEX('Company1808 Assumptions'!F$78:F$80,MATCH($D$5,'Company1808 Assumptions'!$C$78:$C$80,0)) | F95: =F$14*INDEX('Company1808 Assumptions'!G$78:G$80,MATCH($D$5,'Company1808 Assumptions'!$C$78:$C$80,0)) | G95: =G$14*INDEX('Company1808 Assumptions'!H$78:H$80,MATCH($D$5,'Company1808 Assumptions'!$C$78:$C$80,0)) | H95: =H$14*INDEX('Company1808 Assumptions'!I$78:I$80,MATCH($D$5,'Company1808 Assumptions'!$C$78:$C$80,0)) | I95: =I$14*INDEX('Company1808 Assumptions'!J$78:J$80,MATCH($D$5,'Company1808 Assumptions'!$C$78:$C$80,0)) | J95: =J$14*INDEX('Company1808 Assumptions'!K$78:K$80,MATCH($D$5,'Company1808 Assumptions'!$C$78:$C$80,0))
B96: Long-term investments | D96: =D59-C59 | E96: =E59-D59 | F96: =F59-E59 | G96: =G59-F59 | H96: =H59-G59 | I96: =I59-H59 | J96: =J59-I59
B97: Net Cash from Investing Activities | D97: =-SUM(D95:D96) | E97: =-SUM(E95:E96) | F97: =-SUM(F95:F96) | G97: =-SUM(G95:G96) | H97: =-SUM(H95:H96) | I97: =-SUM(I95:I96) | J97: =-SUM(J95:J96)
B99: Cash Flow from Financing Activities
B100: Share Repurchases | D100: =-MAX(D92+D97,0)*INDEX('Company1808 Assumptions'!$G$109:$G$111,MATCH($D$5,'Company1808 Assumptions'!$C$109:$C$111,0)) | E100: =-MAX(E92+E97,0)*INDEX('Company1808 Assumptions'!$G$109:$G$111,MATCH($D$5,'Company1808 Assumptions'!$C$109:$C$111,0)) | F100: =-MAX(F92+F97,0)*INDEX('Company1808 Assumptions'!$G$109:$G$111,MATCH($D$5,'Company1808 Assumptions'!$C$109:$C$111,0)) | G100: =-MAX(G92+G97,0)*INDEX('Company1808 Assumptions'!$G$109:$G$111,MATCH($D$5,'Company1808 Assumptions'!$C$109:$C$111,0)) | H100: =-MAX(H92+H97,0)*INDEX('Company1808 Assumptions'!$G$109:$G$111,MATCH($D$5,'Company1808 Assumptions'!$C$109:$C$111,0)) | I100: =-MAX(I92+I97,0)*INDEX('Company1808 Assumptions'!$G$109:$G$111,MATCH($D$5,'Company1808 Assumptions'!$C$109:$C$111,0)) | J100: =-MAX(J92+J97,0)*INDEX('Company1808 Assumptions'!$G$109:$G$111,MATCH($D$5,'Company1808 Assumptions'!$C$109:$C$111,0))
B101: Debt Repayments | D101: =D$71-C$71 | E101: =E$71-D$71 | F101: =F$71-E$71 | G101: =G$71-F$71 | H101: =H$71-G$71 | I101: =I$71-H$71 | J101: =J$71-I$71
B102: Net Cash from Financing Activities | D102: =SUM(D99:D101) | E102: =SUM(E99:E101) | F102: =SUM(F99:F101) | G102: =SUM(G99:G101) | H102: =SUM(H99:H101) | I102: =SUM(I99:I101) | J102: =SUM(J99:J101)
B104: Net Change in Cash | D104: =D92+D97+D102 | E104: =E92+E97+E102 | F104: =F92+F97+F102 | G104: =G92+G97+G102 | H104: =H92+H97+H102 | I104: =I92+I97+I102 | J104: =J92+J97+J102
B105: Beginning Cash | D105: =C$106 | E105: =D$106 | F105: =E$106 | G105: =F$106 | H105: =G$106 | I105: =H$106 | J105: =I$106
B106: Ending Cash | C106: =C$49 | D106: =D104+D105 | E106: =E104+E105 | F106: =F104+F105 | G106: =G104+G105 | H106: =H104+H105 | I106: =I104+I105 | J106: =J104+J105
B108: Cash Balance Check | C108: =C106-C49 | D108: =D106-D49 | E108: =E106-E49 | F108: =F106-F49 | G108: =G106-G49 | H108: =H106-H49 | I108: =I106-I49 | J108: =J106-J49

Sheet Combination Assumptions
B2: M&A TRANSACTION ASSUMPTIONS - COMPANY1153 / COMPANY1808 COMBINATION
B3: Pro Forma Merger Model Assumptions
B5: 1. TRANSACTION OVERVIEW
B7: Transaction Structure
B8: Acquirer | D8: Company1153 (Company0215)
B9: Target | D9: Company1809
B10: Transaction Type | D10: Stock & Cash Combination
B11: Announcement Date | D11: Q4 2023
B12: Expected Close | D12: Q1 2024
B14: 2. PURCHASE PRICE CALCULATION
B16: Stock Prices & Premium
B17: Company1808 Current Stock Price | D17: 520
B18: Premium Offered | D18: 0.3
B19: Offer Price per Share | D19: =D17*(1+D18)
B20: Company1808 Shares Outstanding (mm) | D20: 2700
B21: Total Purchase Price ($mm) | D21: =D19*D20
B23: Consideration Mix
B24: % Cash Consideration | D24: 0.5
B25: % Stock Consideration | D25: 0.5
B26: Cash Required ($mm) | D26: =$D$21*D24
B27: Stock Value Required ($mm) | D27: =$D$21*D25
B28: Company1153 Stock Price | D28: 175
B29: New Company1153 Shares Issued (mm) | D29: =D27/D28
B31: 3. SOURCES & USES OF FUNDS
B33: Sources of Funds ($mm) | F33: Uses of Funds ($mm)
B34: Stock Issued | D34: =$D$27 | F34: Purchase Price | H34: {=D21}
B35: New Term Loan | D35: 400000 | F35: Transaction Fees | H35: =$D$21*$I$35 | I35: 0.02
B36: Bridge Loan | D36: 100000 | F36: Financing Fees | H36: =(D35+D36)*$I$36 | I36: 0.025
B37: Cash on Hand | D37: =H38-D34-D35-D36 | F37: Integration Costs | H37: 5000
B38: Total Sources | D38: =SUM(D34:D37) | F38: Total Uses | H38: =SUM(H34:H37)
B40: 4. SYNERGY ASSUMPTIONS
B42: Revenue Synergies ($mm)
D43: Year 1 | E43: Year 2 | F43: Year 3 | G43: Year 4 | H43: Year 5
B44: Cross-Platform Advertising | D44: 2000 | E44: 4000 | F44: 6000 | G44: 7000 | H44: 8000
B45: Data & AI Integration | D45: 1000 | E45: 2500 | F45: 4000 | G45: 5000 | H45: 6000
B46: Market Expansion | D46: 500 | E46: 1500 | F46: 2500 | G46: 3000 | H46: 3500
B47: Total Revenue Synergies | D47: =SUM(D44:D46) | E47: =SUM(E44:E46) | F47: =SUM(F44:F46) | G47: =SUM(G44:G46) | H47: =SUM(H44:H46)
B49: Cost Synergies ($mm)
B50: Infrastructure & Cloud | D50: 3000 | E50: 5000 | F50: 7000 | G50: 8000 | H50: 8500
B51: R&D Efficiency | D51: 2000 | E51: 3500 | F51: 4500 | G51: 5000 | H51: 5500
B52: G&A Consolidation | D52: 1500 | E52: 2500 | F52: 3000 | G52: 3200 | H52: 3400
B53: Sales & Marketing | D53: 1000 | E53: 2000 | F53: 2500 | G53: 2800 | H53: 3000
B54: Total Cost Synergies | D54: =SUM(D50:D53) | E54: =SUM(E50:E53) | F54: =SUM(F50:F53) | G54: =SUM(G50:G53) | H54: =SUM(H50:H53)
B56: Dis-Synergies & Implementation
B57: Customer Attrition | D57: -1000 | E57: -800 | F57: -500 | G57: -300 | H57: -200
B58: Integration Costs | D58: -3000 | E58: -2000 | F58: -1000 | G58: -500 | H58: 0
B59: Retention Bonuses | D59: -2000 | E59: -1500 | F59: -1000 | G59: -500 | H59: 0
B60: Total Dis-Synergies | D60: =SUM(D57:D59) | E60: =SUM(E57:E59) | F60: =SUM(F57:F59) | G60: =SUM(G57:G59) | H60: =SUM(H57:H59)
B62: NET SYNERGIES | D62: =D47+D54+D60 | E62: =E47+E54+E60 | F62: =F47+F54+F60 | G62: =G47+G54+G60 | H62: =H47+H54+H60
B64: 5. PURCHASE ACCOUNTING
B66: Purchase Price Allocation ($mm)
B67: Purchase Price | D67: {=D21}
B68: Less: Book Value of Equity | D68: -141740
B69: Premium Over Book | D69: =D67+D68
B71: Allocation:
B72: Identifiable Intangible Assets ($mm) | D72: 25000
B73: PP&E Fair Value Adjustment | D73: 0
B74: Deferred Tax Liability | D74: =-(D72+D73)*$D$95
B75: Goodwill | D75: =D69-D72-D73-D74
B77: 6. FINANCING ASSUMPTIONS
B79: Debt Financing
B80: New Term Loan Amount ($mm) | D80: {=D35}
B81: New Term Loan Interest Rate | D81: 0.055
B82: Bridge Loan Amount ($mm) | D82: {=D36}
B83: Bridge Loan Interest Rate | D83: 0.065
B84: Mandatory Amortization % p.a. | D84: 0.05
B86: 7. PRO FORMA ADJUSTMENTS
B88: Amortization of Intangibles
B89: Identifiable Intangible Assets ($mm) | D89: =D72
B90: Amortization Period (years) | D90: 10
B91: Annual Amortization ($mm) | D91: =D89/D90
B93: Other Adjustments
B94: Stock-Based Comp Adjustment % | D94: 0
B95: Combined Tax Rate | D95: 0.21

Sheet PF Combination
B2: PRO FORMA COMBINED ENTITY - COMPANY1153 / COMPANY1808
B3: $ in millions
B5: TRANSACTION SUMMARY
B7: Purchase Price ($mm): | D7: ='Combination Assumptions'!$D$21
B8: Cash Consideration: | D8: ='Combination Assumptions'!$D$26
B9: Stock Consideration: | D9: ='Combination Assumptions'!$D$27
B10: Total Debt Raised: | D10: ='Combination Assumptions'!$D$35+'Combination Assumptions'!$D$36
B11: Goodwill Created: | D11: ='Combination Assumptions'!$D$75
B13: PRO FORMA INCOME STATEMENT
B15: For the Year Ending | D15: 2024 | E15: 2025 | F15: 2026 | G15: 2027 | H15: 2028
B17: COMBINED REVENUE
B18: Company1153 Revenue | D18: ='Company1153 3-Statement'!F$16 | E18: ='Company1153 3-Statement'!G$16 | F18: ='Company1153 3-Statement'!H$16 | G18: ='Company1153 3-Statement'!I$16 | H18: ='Company1153 3-Statement'!J$16
B19: Company1808 Revenue | D19: ='Company1808 3-Statement'!F$14 | E19: ='Company1808 3-Statement'!G$14 | F19: ='Company1808 3-Statement'!H$14 | G19: ='Company1808 3-Statement'!I$14 | H19: ='Company1808 3-Statement'!J$14
B20: Revenue Synergies | D20: ='Combination Assumptions'!D$47 | E20: ='Combination Assumptions'!E$47 | F20: ='Combination Assumptions'!F$47 | G20: ='Combination Assumptions'!G$47 | H20: ='Combination Assumptions'!H$47
B21: Total Combined Revenue | D21: =SUM(D18:D20) | E21: =SUM(E18:E20) | F21: =SUM(F18:F20) | G21: =SUM(G18:G20) | H21: =SUM(H18:H20)
B23: OPERATING EXPENSES
B24: Cost of Revenue (Combined) | D24: ='Company1153 3-Statement'!F$19+'Company1808 3-Statement'!F$17 | E24: ='Company1153 3-Statement'!G$19+'Company1808 3-Statement'!G$17 | F24: ='Company1153 3-Statement'!H$19+'Company1808 3-Statement'!H$17 | G24: ='Company1153 3-Statement'!I$19+'Company1808 3-Statement'!I$17 | H24: ='Company1153 3-Statement'!J$19+'Company1808 3-Statement'!J$17
B25: Infrastructure Synergy | D25: =-'Combination Assumptions'!D$50 | E25: =-'Combination Assumptions'!E$50 | F25: =-'Combination Assumptions'!F$50 | G25: =-'Combination Assumptions'!G$50 | H25: =-'Combination Assumptions'!H$50
B26: Gross Profit | D26: =D21-D24-D25 | E26: =E21-E24-E25 | F26: =F21-F24-F25 | G26: =G21-G24-G25 | H26: =H21-H24-H25
B28: R&D (Combined) | D28: ='Company1153 3-Statement'!F$23+'Company1808 3-Statement'!F$21 | E28: ='Company1153 3-Statement'!G$23+'Company1808 3-Statement'!G$21 | F28: ='Company1153 3-Statement'!H$23+'Company1808 3-Statement'!H$21 | G28: ='Company1153 3-Statement'!I$23+'Company1808 3-Statement'!I$21 | H28: ='Company1153 3-Statement'!J$23+'Company1808 3-Statement'!J$21
B29: R&D Synergy | D29: =-'Combination Assumptions'!D$51 | E29: =-'Combination Assumptions'!E$51 | F29: =-'Combination Assumptions'!F$51 | G29: =-'Combination Assumptions'!G$51 | H29: =-'Combination Assumptions'!H$51
B30: S&M (Combined) | D30: ='Company1153 3-Statement'!F$24+'Company1808 3-Statement'!F$22 | E30: ='Company1153 3-Statement'!G$24+'Company1808 3-Statement'!G$22 | F30: ='Company1153 3-Statement'!H$24+'Company1808 3-Statement'!H$22 | G30: ='Company1153 3-Statement'!I$24+'Company1808 3-Statement'!I$22 | H30: ='Company1153 3-Statement'!J$24+'Company1808 3-Statement'!J$22
B31: S&M Synergy | D31: =-'Combination Assumptions'!D$53 | E31: =-'Combination Assumptions'!E$53 | F31: =-'Combination Assumptions'!F$53 | G31: =-'Combination Assumptions'!G$53 | H31: =-'Combination Assumptions'!H$53
B32: G&A (Combined) | D32: ='Company1153 3-Statement'!F$25+'Company1808 3-Statement'!F$23 | E32: ='Company1153 3-Statement'!G$25+'Company1808 3-Statement'!G$23 | F32: ='Company1153 3-Statement'!H$25+'Company1808 3-Statement'!H$23 | G32: ='Company1153 3-Statement'!I$25+'Company1808 3-Statement'!I$23 | H32: ='Company1153 3-Statement'!J$25+'Company1808 3-Statement'!J$23
B33: G&A Synergy | D33: =-'Combination Assumptions'!D$52 | E33: =-'Combination Assumptions'!E$52 | F33: =-'Combination Assumptions'!F$52 | G33: =-'Combination Assumptions'!G$52 | H33: =-'Combination Assumptions'!H$52
B34: Stock-Based Compensation (Combined) | D34: ='Company1153 3-Statement'!F$26+'Company1808 3-Statement'!F$24 | E34: ='Company1153 3-Statement'!G$26+'Company1808 3-Statement'!G$24 | F34: ='Company1153 3-Statement'!H$26+'Company1808 3-Statement'!H$24 | G34: ='Company1153 3-Statement'!I$26+'Company1808 3-Statement'!I$24 | H34: ='Company1153 3-Statement'!J$26+'Company1808 3-Statement'!J$24
B35: Dis-synergies & Integration | D35: =-'Combination Assumptions'!D$60 | E35: =-'Combination Assumptions'!E$60 | F35: =-'Combination Assumptions'!F$60 | G35: =-'Combination Assumptions'!G$60 | H35: =-'Combination Assumptions'!H$60
B36: Amortization of new intangibles | D36: ='Combination Assumptions'!$D$91 | E36: ='Combination Assumptions'!$D$91 | F36: ='Combination Assumptions'!$D$91 | G36: ='Combination Assumptions'!$D$91 | H36: ='Combination Assumptions'!$D$91
B37: EBIT | D37: =D26-D28-D29-D30-D31-D32-D33-D34-D35-D36 | E37: =E26-E28-E29-E30-E31-E32-E33-E34-E35-E36 | F37: =F26-F28-F29-F30-F31-F32-F33-F34-F35-F36 | G37: =G26-G28-G29-G30-G31-G32-G33-G34-G35-G36 | H37: =H26-H28-H29-H30-H31-H32-H33-H34-H35-H36
B39: Existing interest expense / (income) | D39: =-('Company1153 3-Statement'!F$32+'Company1808 3-Statement'!F$30) | E39: =-('Company1153 3-Statement'!G$32+'Company1808 3-Statement'!G$30) | F39: =-('Company1153 3-Statement'!H$32+'Company1808 3-Statement'!H$30) | G39: =-('Company1153 3-Statement'!I$32+'Company1808 3-Statement'!I$30) | H39: =-('Company1153 3-Statement'!J$32+'Company1808 3-Statement'!J$30)
B40: New interest expense | D40: =(('Combination Assumptions'!$D$80*((1-'Combination Assumptions'!$D$84)^(D$15-$D$15)))*'Combination Assumptions'!$D$81)+(('Combination Assumptions'!$D$82*((1-'Combination Assumptions'!$D$84)^(D$15-$D$15)))*'Combination Assumptions'!$D$83) | E40: =(('Combination Assumptions'!$D$80*((1-'Combination Assumptions'!$D$84)^(E$15-$D$15)))*'Combination Assumptions'!$D$81)+(('Combination Assumptions'!$D$82*((1-'Combination Assumptions'!$D$84)^(E$15-$D$15)))*'Combination Assumptions'!$D$83) | F40: =(('Combination Assumptions'!$D$80*((1-'Combination Assumptions'!$D$84)^(F$15-$D$15)))*'Combination Assumptions'!$D$81)+(('Combination Assumptions'!$D$82*((1-'Combination Assumptions'!$D$84)^(F$15-$D$15)))*'Combination Assumptions'!$D$83) | G40: =(('Combination Assumptions'!$D$80*((1-'Combination Assumptions'!$D$84)^(G$15-$D$15)))*'Combination Assumptions'!$D$81)+(('Combination Assumptions'!$D$82*((1-'Combination Assumptions'!$D$84)^(G$15-$D$15)))*'Combination Assumptions'!$D$83) | H40: =(('Combination Assumptions'!$D$80*((1-'Combination Assumptions'!$D$84)^(H$15-$D$15)))*'Combination Assumptions'!$D$81)+(('Combination Assumptions'!$D$82*((1-'Combination Assumptions'!$D$84)^(H$15-$D$15)))*'Combination Assumptions'!$D$83)
B41: EBT | D41: =D37-D39-D40 | E41: =E37-E39-E40 | F41: =F37-F39-F40 | G41: =G37-G39-G40 | H41: =H37-H39-H40
B42: Taxes | D42: =D41*'Combination Assumptions'!$D$95 | E42: =E41*'Combination Assumptions'!$D$95 | F42: =F41*'Combination Assumptions'!$D$95 | G42: =G41*'Combination Assumptions'!$D$95 | H42: =H41*'Combination Assumptions'!$D$95
B44: NET INCOME | D44: =D41-D42 | E44: =E41-E42 | F44: =F41-F42 | G44: =G41-G42 | H44: =H41-H42
B46: ACCRETION / DILUTION ANALYSIS
B48: Pro Forma Shares (mm) | D48: ='Company1153 3-Statement'!F$42+'Combination Assumptions'!$D$29 | E48: ='Company1153 3-Statement'!G$42+'Combination Assumptions'!$D$29 | F48: ='Company1153 3-Statement'!H$42+'Combination Assumptions'!$D$29 | G48: ='Company1153 3-Statement'!I$42+'Combination Assumptions'!$D$29 | H48: ='Company1153 3-Statement'!J$42+'Combination Assumptions'!$D$29
B49: Pro Forma EPS | D49: =D44/D48 | E49: =E44/E48 | F49: =F44/F48 | G49: =G44/G48 | H49: =H44/H48
B50: % Accretion (Dilution) | D50: =D49/'Company1153 3-Statement'!F$43-1 | E50: =E49/'Company1153 3-Statement'!G$43-1 | F50: =F49/'Company1153 3-Statement'!H$43-1 | G50: =G49/'Company1153 3-Statement'!I$43-1 | H50: =H49/'Company1153 3-Statement'!J$43-1
