Workbook
Name A_ALL_KEYWORDS_TYPE_ScalarContributed_EQTY_200001320: Ticker0024_Annotation_Sheet!$268:$276,Ticker0024_Annotation_Sheet!$318:$318,Ticker0024_Annotation_Sheet!$322:$324,Ticker0024_Annotation_Sheet!$329:$331
Name A_ALL_KEYWORDS_TYPE_ScalarReference_EQTY_200001320: Ticker0024_Annotation_Sheet!$261:$266
Name A_ALL_KEYWORDS_TYPE_ScalarReference_ISSR_208000430: Ticker0024_Annotation_Sheet!$6:$7
Name A_ALL_Ticker0024: Ticker0024_Annotation_Sheet!$A$1:$FT$331
Name A_ALL_PERIODS_Ticker0024: Ticker0024_Annotation_Sheet!$F$1:$FT$1
Name A_ALL_SECTION_KEYWORDS_EQTY_200001320_1314: Ticker0024_Annotation_Sheet!$C$320
Name A_ALL_SECTION_KEYWORDS_EQTY_200001320_1319: Ticker0024_Annotation_Sheet!$C$322:$C$325
Name A_ALL_SECTION_KEYWORDS_EQTY_200001320_131E: Ticker0024_Annotation_Sheet!$C$327
Name A_ALL_SECTION_KEYWORDS_EQTY_200001320_131O: Ticker0024_Annotation_Sheet!$C$329:$C$331
Name A_ALL_SECTION_KEYWORDS_EQTY_200001320_13A: Ticker0024_Annotation_Sheet!$C$268:$C$276
Name A_ALL_SECTION_KEYWORDS_EQTY_200001320_13K: Ticker0024_Annotation_Sheet!$C$278:$C$293
Name A_ALL_SECTION_KEYWORDS_EQTY_200001320_13U: Ticker0024_Annotation_Sheet!$C$295:$C$310
Name A_ALL_SECTION_KEYWORDS_EQTY_200001320_13V: Ticker0024_Annotation_Sheet!$C$312
Name A_ALL_SECTION_KEYWORDS_EQTY_200001320_13W: Ticker0024_Annotation_Sheet!$C$314:$C$318
Name A_ALL_SECTION_KEYWORDS_EQTY_200001320_Reference_Data: Ticker0024_Annotation_Sheet!$C$261:$C$266
Name A_ALL_SECTION_KEYWORDS_ISSR_208000430_1314: Ticker0024_Annotation_Sheet!$C$54:$C$84
Name A_ALL_SECTION_KEYWORDS_ISSR_208000430_13168: Ticker0024_Annotation_Sheet!$C$167:$C$228
Name A_ALL_SECTION_KEYWORDS_ISSR_208000430_1316T: Ticker0024_Annotation_Sheet!$C$230:$C$231
Name A_ALL_SECTION_KEYWORDS_ISSR_208000430_1316U: Ticker0024_Annotation_Sheet!$C$233:$C$247
Name A_ALL_SECTION_KEYWORDS_ISSR_208000430_1319: Ticker0024_Annotation_Sheet!$C$86:$C$104
Name A_ALL_SECTION_KEYWORDS_ISSR_208000430_131E: Ticker0024_Annotation_Sheet!$C$106:$C$122
Name A_ALL_SECTION_KEYWORDS_ISSR_208000430_131J: Ticker0024_Annotation_Sheet!$C$124:$C$137
Name A_ALL_SECTION_KEYWORDS_ISSR_208000430_131O: Ticker0024_Annotation_Sheet!$C$139:$C$165
Name A_ALL_SECTION_KEYWORDS_ISSR_208000430_136E: Ticker0024_Annotation_Sheet!$C$249:$C$258
Name A_ALL_SECTION_KEYWORDS_ISSR_208000430_13A: Ticker0024_Annotation_Sheet!$C$9
Name A_ALL_SECTION_KEYWORDS_ISSR_208000430_13U: Ticker0024_Annotation_Sheet!$C$11:$C$30
Name A_ALL_SECTION_KEYWORDS_ISSR_208000430_13V: Ticker0024_Annotation_Sheet!$C$32:$C$52
Name A_ALL_SECTION_KEYWORDS_ISSR_208000430_Reference_Data: Ticker0024_Annotation_Sheet!$C$6:$C$7
Name A_CURRENCY_EQTY_200001320_PRI: Ticker0024_Annotation_Sheet!$E$265
Name A_CURRENCY_EQTY_200001320_PUB: Ticker0024_Annotation_Sheet!$E$264
Name A_CURRENCY_EQTY_200001320_REP: Ticker0024_Annotation_Sheet!$E$266
Name A_CURRENCY_ISSR_208000430_REP: Ticker0024_Annotation_Sheet!$E$7
Name A_ENTITY_DATA_EQTY_200001320: Ticker0024_Annotation_Sheet!$E$260:$FT$331
Name A_ENTITY_DATA_ISSR_208000430: Ticker0024_Annotation_Sheet!$E$5:$FT$258
Name A_KEYWORD_EQTY_200001320_AMER_LIST: Ticker0024_Annotation_Sheet!$268:$268
Name A_KEYWORD_EQTY_200001320_BETA_ANALYST: Ticker0024_Annotation_Sheet!$329:$329
Name A_KEYWORD_EQTY_200001320_BVPS: Ticker0024_Annotation_Sheet!$320:$320
Name A_KEYWORD_EQTY_200001320_BVPS_PUB: Ticker0024_Annotation_Sheet!$278:$278
Name A_KEYWORD_EQTY_200001320_CEEE_EPS: Ticker0024_Annotation_Sheet!$283:$283
Name A_KEYWORD_EQTY_200001320_CEEE_NDEBT: Ticker0024_Annotation_Sheet!$288:$288
Name A_KEYWORD_EQTY_200001320_CF_NI_PRE_PREF: Ticker0024_Annotation_Sheet!$327:$327
Name A_KEYWORD_EQTY_200001320_COMMON_DIV_PAID: Ticker0024_Annotation_Sheet!$306:$306
Name A_KEYWORD_EQTY_200001320_CURRENCY_ISO: Ticker0024_Annotation_Sheet!$266:$266
Name A_KEYWORD_EQTY_200001320_DILUTE_SHARES: Ticker0024_Annotation_Sheet!$309:$309
Name A_KEYWORD_EQTY_200001320_DPS: Ticker0024_Annotation_Sheet!$307:$307
Name A_KEYWORD_EQTY_200001320_DPS_PUB: Ticker0024_Annotation_Sheet!$279:$279
Name A_KEYWORD_EQTY_200001320_DPS_SPECIAL_PUB: Ticker0024_Annotation_Sheet!$280:$280
Name A_KEYWORD_EQTY_200001320_EBIT_PUB: Ticker0024_Annotation_Sheet!$290:$290
Name A_KEYWORD_EQTY_200001320_EBITDA_PUB: Ticker0024_Annotation_Sheet!$281:$281
Name A_KEYWORD_EQTY_200001320_EPS: Ticker0024_Annotation_Sheet!$302:$302
Name A_KEYWORD_EQTY_200001320_EPS_EX_ESO_B: Ticker0024_Annotation_Sheet!$316:$316
Name A_KEYWORD_EQTY_200001320_EPS_EX_ESO_D: Ticker0024_Annotation_Sheet!$317:$317
Name A_KEYWORD_EQTY_200001320_EPS_FUL_DIL: Ticker0024_Annotation_Sheet!$303:$303
Name A_KEYWORD_EQTY_200001320_EPS_POST_BASIC: Ticker0024_Annotation_Sheet!$304:$304
Name A_KEYWORD_EQTY_200001320_EPS_PUB: Ticker0024_Annotation_Sheet!$282:$282
Name A_KEYWORD_EQTY_200001320_EPS_PUB_EX_ESO: Ticker0024_Annotation_Sheet!$284:$284
Name A_KEYWORD_EQTY_200001320_EQ_PUB: Ticker0024_Annotation_Sheet!$293:$293
Name A_KEYWORD_EQTY_200001320_ESO_POST_TAX: Ticker0024_Annotation_Sheet!$315:$315
Name A_KEYWORD_EQTY_200001320_ESO_YEAR: Ticker0024_Annotation_Sheet!$318:$318
Name A_KEYWORD_EQTY_200001320_EV_ADJ_PUB: Ticker0024_Annotation_Sheet!$285:$285

Sheet __FDSCACHE__
B1: This sheet contains FactSet XML data for use with this workbook's =FDS codes. Modifying the worksheet's contents may damage the workbook's =FDS functionality.

Sheet Cover
C2: Microsoft Analyst Model
C3: Ticker: | D3: Ticker0024
C4: Date: | D4: =TODAY()
B6: Person0591
B7: (415) 249-7318
B8: person@example.com
B10: Person0462
B11: (212) 357-6378
B12: person@example.com
B14: Person0749 Person0744
B15: (212) 902-0695
B16: person@example.com
B18: Person0818
B19: (332) 245-7726
B20: person@example.com
... B24: person@example.com

Sheet Rev. Summary
B2: Microsoft, Inc.
B3: Fiscal Year Ends Jun. 30
B4: ($ millions, except per share amounts) | ER4: Resegmented | EV4: x
C6: =Dates!C3 | H6: =Dates!H3 | M6: =Dates!M3 | R6: =Dates!R3 | W6: =Dates!W3 | AB6: =Dates!AB3 | AG6: =Dates!AG3 | AL6: =Dates!AL3 | AQ6: =Dates!AQ3 | AV6: =Dates!AV3 | BA6: =Dates!BA3 | BF6: =Dates!BF3 | BK6: =Dates!BK3 | BP6: =Dates!BP3 | BU6: =Dates!BU3 | BZ6: =Dates!BZ3 | CE6: =Dates!CE3 | CJ6: =Dates!CJ3 | CO6: =Dates!CO3 | CT6: =Dates!CT3 | CY6: =Dates!CY3 | DD6: =Dates!DD3 | DI6: =Dates!DI3 | DN6: =Dates!DN3 | DS6: =Dates!DS3 | DX6: =Dates!DX3 | EC6: =Dates!EC3 | EH6: =Dates!EH3 | EM6: =Dates!EM3 | ER6: =Dates!ER3 | EW6: =Dates!EW3 | FB6: =Dates!FB3 | FG6: =Dates!FG3 | FL6: =Dates!FL3 | FQ6: =Dates!FQ3 | FV6: =Dates!FV3 | GA6: =Dates!GA3 | GF6: =Dates!GF3
C7: =Dates!C4 | D7: =Dates!D4 | E7: =Dates!E4 | F7: =Dates!F4 | G7: =Dates!G4 | H7: =Dates!H4 | I7: =Dates!I4 | J7: =Dates!J4 | ... GJ7: =Dates!GJ4
C8: =Dates!C5 | D8: =Dates!D5 | E8: =Dates!E5 | F8: =Dates!F5 | G8: =Dates!G5 | H8: =Dates!H5 | I8: =Dates!I5 | J8: =Dates!J5 | ... GJ8: =Dates!GJ5
A10: TREV | B10: Total Revenue | CY10: =CY19+CY44+CY64 | CZ10: =CZ19+CZ44+CZ64 | DA10: =DA19+DA44+DA64 | DB10: =DB19+DB44+DB64 | DC10: =DC19+DC44+DC64 | DD10: =DD19+DD44+DD64 | DE10: =DE19+DE44+DE64 | DF10: =DF19+DF44+DF64 | ... GJ10: =GJ19+GJ44+GJ64
B11: % yoy | DD11: =IFERROR(DD10/CY10-1,"") | DE11: =IFERROR(DE10/CZ10-1,"") | DF11: =IFERROR(DF10/DA10-1,"") | DG11: =IFERROR(DG10/DB10-1,"") | DH11: =IFERROR(DH10/DC10-1,"") | DI11: =IFERROR(DI10/DD10-1,"") | DJ11: =IFERROR(DJ10/DE10-1,"") | DK11: =IFERROR(DK10/DF10-1,"") | ... GJ11: =IFERROR(GJ10/GE10-1,"")
B12: % qoq | CZ12: =IFERROR(CZ10/CY10-1,"") | DA12: =IFERROR(DA10/CZ10-1,"") | DB12: =IFERROR(DB10/DA10-1,"") | DD12: =IFERROR(DD10/DB10-1,"") | DE12: =IFERROR(DE10/DD10-1,"") | DF12: =IFERROR(DF10/DE10-1,"") | DG12: =IFERROR(DG10/DF10-1,"") | DI12: =IFERROR(DI10/DG10-1,"") | DJ12: =IFERROR(DJ10/DI10-1,"") | DK12: =IFERROR(DK10/DJ10-1,"") | DL12: =IFERROR(DL10/DK10-1,"") | DN12: =IFERROR(DN10/DL10-1,"") | DO12: =IFERROR(DO10/DN10-1,"") | DP12: =IFERROR(DP10/DO10-1,"") | DQ12: =IFERROR(DQ10/DP10-1,"") | DS12: =IFERROR(DS10/DQ10-1,"") | DT12: =IFERROR(DT10/DS10-1,"") | DU12: =IFERROR(DU10/DT10-1,"") | DV12: =IFERROR(DV10/DU10-1,"") | DX12: =IFERROR(DX10/DV10-1,"") | DY12: =IFERROR(DY10/DX10-1,"") | DZ12: =IFERROR(DZ10/DY10-1,"") | EA12: =IFERROR(EA10/DZ10-1,"") | EC12: =IFERROR(EC10/EA10-1,"") | ED12: =IFERROR(ED10/EC10-1,"") | EE12: =IFERROR(EE10/ED10-1,"") | EF12: =IFERROR(EF10/EE10-1,"") | EH12: =IFERROR(EH10/EF10-1,"") | EI12: =IFERROR(EI10/EH10-1,"") | EJ12: =IFERROR(EJ10/EI10-1,"") | EK12: =IFERROR(EK10/EJ10-1,"") | EM12: =IFERROR(EM10/EK10-1,"") | EN12: =IFERROR(EN10/EM10-1,"") | EO12: =IFERROR(EO10/EN10-1,"") | EP12: =IFERROR(EP10/EO10-1,"") | ER12: =IFERROR(ER10/EP10-1,"") | ES12: =IFERROR(ES10/ER10-1,"") | ET12: =IFERROR(ET10/ES10-1,"") | EU12: =IFERROR(EU10/ET10-1,"") | EW12: =IFERROR(EW10/EU10-1,"") | EX12: =IFERROR(EX10/EW10-1,"") | EY12: =IFERROR(EY10/EX10-1,"") | EZ12: =IFERROR(EZ10/EY10-1,"") | FB12: =IFERROR(FB10/EZ10-1,"") | FC12: =IFERROR(FC10/FB10-1,"") | FD12: =IFERROR(FD10/FC10-1,"") | FE12: =IFERROR(FE10/FD10-1,"") | FG12: =IFERROR(FG10/FE10-1,"") | FH12: =IFERROR(FH10/FG10-1,"") | FI12: =IFERROR(FI10/FH10-1,"") | FJ12: =IFERROR(FJ10/FI10-1,"") | FL12: =IFERROR(FL10/FJ10-1,"") | FM12: =IFERROR(FM10/FL10-1,"") | FN12: =IFERROR(FN10/FM10-1,"") | FO12: =IFERROR(FO10/FN10-1,"") | FQ12: =IFERROR(FQ10/FO10-1,"") | FR12: =IFERROR(FR10/FQ10-1,"") | FS12: =IFERROR(FS10/FR10-1,"") | FT12: =IFERROR(FT10/FS10-1,"") | FV12: =IFERROR(FV10/FT10-1,"") | FW12: =IFERROR(FW10/FV10-1,"") | FX12: =IFERROR(FX10/FW10-1,"") | FY12: =IFERROR(FY10/FX10-1,"") | GA12: =IFERROR(GA10/FY10-1,"") | GB12: =IFERROR(GB10/GA10-1,"") | GC12: =IFERROR(GC10/GB10-1,"") | GD12: =IFERROR(GD10/GC10-1,"") | GF12: =IFERROR(GF10/GD10-1,"") | GG12: =IFERROR(GG10/GF10-1,"") | GH12: =IFERROR(GH10/GG10-1,"") | GI12: =IFERROR(GI10/GH10-1,"")
B14: Microsoft Cloud Revenue | DG14: ='Ticker0024 Cloud'!DG10 | DH14: ='Ticker0024 Cloud'!DH10 | DI14: ='Ticker0024 Cloud'!DI10 | DJ14: ='Ticker0024 Cloud'!DJ10 | DK14: ='Ticker0024 Cloud'!DK10 | DL14: ='Ticker0024 Cloud'!DL10 | DM14: ='Ticker0024 Cloud'!DM10 | DN14: ='Ticker0024 Cloud'!DN10 | ... GJ14: ='Ticker0024 Cloud'!GJ10
B15: % yoy | DD15: =IFERROR(DD14/CY14-1,"") | DE15: =IFERROR(DE14/CZ14-1,"") | DF15: =IFERROR(DF14/DA14-1,"") | DG15: =IFERROR(DG14/DB14-1,"") | DH15: =IFERROR(DH14/DC14-1,"") | DI15: =IFERROR(DI14/DD14-1,"") | DJ15: =IFERROR(DJ14/DE14-1,"") | DK15: =IFERROR(DK14/DF14-1,"") | ... GJ15: =IFERROR(GJ14/GE14-1,"")
B16: % qoq | CZ16: =IFERROR(CZ14/CY14-1,"") | DA16: =IFERROR(DA14/CZ14-1,"") | DB16: =IFERROR(DB14/DA14-1,"") | DD16: =IFERROR(DD14/DB14-1,"") | DE16: =IFERROR(DE14/DD14-1,"") | DF16: =IFERROR(DF14/DE14-1,"") | DG16: =IFERROR(DG14/DF14-1,"") | DI16: =IFERROR(DI14/DG14-1,"") | DJ16: =IFERROR(DJ14/DI14-1,"") | DK16: =IFERROR(DK14/DJ14-1,"") | DL16: =IFERROR(DL14/DK14-1,"") | DN16: =IFERROR(DN14/DL14-1,"") | DO16: =IFERROR(DO14/DN14-1,"") | DP16: =IFERROR(DP14/DO14-1,"") | DQ16: =IFERROR(DQ14/DP14-1,"") | DS16: =IFERROR(DS14/DQ14-1,"") | DT16: =IFERROR(DT14/DS14-1,"") | DU16: =IFERROR(DU14/DT14-1,"") | DV16: =IFERROR(DV14/DU14-1,"") | DX16: =IFERROR(DX14/DV14-1,"") | DY16: =IFERROR(DY14/DX14-1,"") | DZ16: =IFERROR(DZ14/DY14-1,"") | EA16: =IFERROR(EA14/DZ14-1,"") | EC16: =IFERROR(EC14/EA14-1,"") | ED16: =IFERROR(ED14/EC14-1,"") | EE16: =IFERROR(EE14/ED14-1,"") | EF16: =IFERROR(EF14/EE14-1,"") | EH16: =IFERROR(EH14/EF14-1,"") | EI16: =IFERROR(EI14/EH14-1,"") | EJ16: =IFERROR(EJ14/EI14-1,"") | EK16: =IFERROR(EK14/EJ14-1,"") | EM16: =IFERROR(EM14/EK14-1,"") | EN16: =IFERROR(EN14/EM14-1,"") | EO16: =IFERROR(EO14/EN14-1,"") | EP16: =IFERROR(EP14/EO14-1,"") | ER16: =IFERROR(ER14/EP14-1,"") | ES16: =IFERROR(ES14/ER14-1,"") | ET16: =IFERROR(ET14/ES14-1,"") | EU16: =IFERROR(EU14/ET14-1,"") | EW16: =IFERROR(EW14/EU14-1,"") | EX16: =IFERROR(EX14/EW14-1,"") | EY16: =IFERROR(EY14/EX14-1,"") | EZ16: =IFERROR(EZ14/EY14-1,"") | FB16: =IFERROR(FB14/EZ14-1,"") | FC16: =IFERROR(FC14/FB14-1,"") | FD16: =IFERROR(FD14/FC14-1,"") | FE16: =IFERROR(FE14/FD14-1,"") | FG16: =IFERROR(FG14/FE14-1,"") | FH16: =IFERROR(FH14/FG14-1,"") | FI16: =IFERROR(FI14/FH14-1,"") | FJ16: =IFERROR(FJ14/FI14-1,"") | FL16: =IFERROR(FL14/FJ14-1,"") | FM16: =IFERROR(FM14/FL14-1,"") | FN16: =IFERROR(FN14/FM14-1,"") | FO16: =IFERROR(FO14/FN14-1,"") | FQ16: =IFERROR(FQ14/FO14-1,"") | FR16: =IFERROR(FR14/FQ14-1,"") | FS16: =IFERROR(FS14/FR14-1,"") | FT16: =IFERROR(FT14/FS14-1,"") | FV16: =IFERROR(FV14/FT14-1,"") | FW16: =IFERROR(FW14/FV14-1,"") | FX16: =IFERROR(FX14/FW14-1,"") | FY16: =IFERROR(FY14/FX14-1,"") | GA16: =IFERROR(GA14/FY14-1,"") | GB16: =IFERROR(GB14/GA14-1,"") | GC16: =IFERROR(GC14/GB14-1,"") | GD16: =IFERROR(GD14/GC14-1,"") | GF16: =IFERROR(GF14/GD14-1,"") | GG16: =IFERROR(GG14/GF14-1,"") | GH16: =IFERROR(GH14/GG14-1,"") | GI16: =IFERROR(GI14/GH14-1,"")
B17: % Total Revenue | CY17: =CY14/CY$10 | CZ17: =CZ14/CZ$10 | DA17: =DA14/DA$10 | DB17: =DB14/DB$10 | DC17: =DC14/DC$10 | DD17: =DD14/DD$10 | DE17: =DE14/DE$10 | DF17: =DF14/DF$10 | ... GJ17: =GJ14/GJ$10
EV18: =EV14-EQ14
B19: PBP Revenue | CY19: =IFERROR(PBP!CY50,"") | CZ19: =IFERROR(PBP!CZ50,"") | DA19: =IFERROR(PBP!DA50,"") | DB19: =IFERROR(PBP!DB50,"") | DC19: =IFERROR(PBP!DC50,"") | DD19: =IFERROR(PBP!DD50,"") | DE19: =IFERROR(PBP!DE50,"") | DF19: =IFERROR(PBP!DF50,"") | ... EQ19: =IFERROR(PBP!EQ50,"") | ER19: =PBP!ER10 | ES19: =PBP!ES10 | ET19: =PBP!ET10 | EU19: =PBP!EU10 | EV19: =PBP!EV10 | EW19: =PBP!EW10 | EX19: =PBP!EX10 | EY19: =PBP!EY10 | ... GJ19: =PBP!GJ10
B20: % yoy | DD20: =IFERROR(DD19/CY19-1,"") | DE20: =IFERROR(DE19/CZ19-1,"") | DF20: =IFERROR(DF19/DA19-1,"") | DG20: =IFERROR(DG19/DB19-1,"") | DH20: =IFERROR(DH19/DC19-1,"") | DI20: =IFERROR(DI19/DD19-1,"") | DJ20: =IFERROR(DJ19/DE19-1,"") | DK20: =IFERROR(DK19/DF19-1,"") | ... GJ20: =IFERROR(GJ19/GE19-1,"")
B21: % qoq | CZ21: =IFERROR(CZ19/CY19-1,"") | DA21: =IFERROR(DA19/CZ19-1,"") | DB21: =IFERROR(DB19/DA19-1,"") | DD21: =IFERROR(DD19/DB19-1,"") | DE21: =IFERROR(DE19/DD19-1,"") | DF21: =IFERROR(DF19/DE19-1,"") | DG21: =IFERROR(DG19/DF19-1,"") | DI21: =IFERROR(DI19/DG19-1,"") | DJ21: =IFERROR(DJ19/DI19-1,"") | DK21: =IFERROR(DK19/DJ19-1,"") | DL21: =IFERROR(DL19/DK19-1,"") | DN21: =IFERROR(DN19/DL19-1,"") | DO21: =IFERROR(DO19/DN19-1,"") | DP21: =IFERROR(DP19/DO19-1,"") | DQ21: =IFERROR(DQ19/DP19-1,"") | DS21: =IFERROR(DS19/DQ19-1,"") | DT21: =IFERROR(DT19/DS19-1,"") | DU21: =IFERROR(DU19/DT19-1,"") | DV21: =IFERROR(DV19/DU19-1,"") | DX21: =IFERROR(DX19/DV19-1,"") | DY21: =IFERROR(DY19/DX19-1,"") | DZ21: =IFERROR(DZ19/DY19-1,"") | EA21: =IFERROR(EA19/DZ19-1,"") | EC21: =IFERROR(EC19/EA19-1,"") | ED21: =IFERROR(ED19/EC19-1,"") | EE21: =IFERROR(EE19/ED19-1,"") | EF21: =IFERROR(EF19/EE19-1,"") | EH21: =IFERROR(EH19/EF19-1,"") | EI21: =IFERROR(EI19/EH19-1,"") | EJ21: =IFERROR(EJ19/EI19-1,"") | EK21: =IFERROR(EK19/EJ19-1,"") | EM21: =IFERROR(EM19/EK19-1,"") | EN21: =IFERROR(EN19/EM19-1,"") | EO21: =IFERROR(EO19/EN19-1,"") | EP21: =IFERROR(EP19/EO19-1,"") | ER21: =IFERROR(ER19/EP19-1,"") | ES21: =IFERROR(ES19/ER19-1,"") | ET21: =IFERROR(ET19/ES19-1,"") | EU21: =IFERROR(EU19/ET19-1,"") | EW21: =IFERROR(EW19/EU19-1,"") | EX21: =IFERROR(EX19/EW19-1,"") | EY21: =IFERROR(EY19/EX19-1,"") | EZ21: =IFERROR(EZ19/EY19-1,"") | FB21: =IFERROR(FB19/EZ19-1,"") | FC21: =IFERROR(FC19/FB19-1,"") | FD21: =IFERROR(FD19/FC19-1,"") | FE21: =IFERROR(FE19/FD19-1,"") | FG21: =IFERROR(FG19/FE19-1,"") | FH21: =IFERROR(FH19/FG19-1,"") | FI21: =IFERROR(FI19/FH19-1,"") | FJ21: =IFERROR(FJ19/FI19-1,"") | FL21: =IFERROR(FL19/FJ19-1,"") | FM21: =IFERROR(FM19/FL19-1,"") | FN21: =IFERROR(FN19/FM19-1,"") | FO21: =IFERROR(FO19/FN19-1,"") | FQ21: =IFERROR(FQ19/FO19-1,"") | FR21: =IFERROR(FR19/FQ19-1,"") | FS21: =IFERROR(FS19/FR19-1,"") | FT21: =IFERROR(FT19/FS19-1,"") | FV21: =IFERROR(FV19/FT19-1,"") | FW21: =IFERROR(FW19/FV19-1,"") | FX21: =IFERROR(FX19/FW19-1,"") | FY21: =IFERROR(FY19/FX19-1,"") | GA21: =IFERROR(GA19/FY19-1,"") | GB21: =IFERROR(GB19/GA19-1,"") | GC21: =IFERROR(GC19/GB19-1,"") | GD21: =IFERROR(GD19/GC19-1,"") | GF21: =IFERROR(GF19/GD19-1,"") | GG21: =IFERROR(GG19/GF19-1,"") | GH21: =IFERROR(GH19/GG19-1,"") | GI21: =IFERROR(GI19/GH19-1,"")
B22: % Total Revenue | CY22: =CY19/CY$10 | CZ22: =CZ19/CZ$10 | DA22: =DA19/DA$10 | DB22: =DB19/DB$10 | DC22: =DC19/DC$10 | DD22: =DD19/DD$10 | DE22: =DE19/DE$10 | DF22: =DF19/DF$10 | ... GJ22: =GJ19/GJ$10
B24: Microsoft 365 Commercial Cloud | ER24: =PBP!ER195 | ES24: =PBP!ES195 | ET24: =PBP!ET195 | EU24: =PBP!EU195 | EV24: =PBP!EV195 | EW24: =PBP!EW195 | EX24: =PBP!EX195 | EY24: =PBP!EY195 | ... GJ24: =PBP!GJ195
B25: % yoy | DD25: =IFERROR(DD24/CY24-1,"") | DE25: =IFERROR(DE24/CZ24-1,"") | DF25: =IFERROR(DF24/DA24-1,"") | DG25: =IFERROR(DG24/DB24-1,"") | DH25: =IFERROR(DH24/DC24-1,"") | ER25: =IFERROR(ER24/EM24-1,"") | ES25: =IFERROR(ES24/EN24-1,"") | ET25: =IFERROR(ET24/EO24-1,"") | EU25: =IFERROR(EU24/EP24-1,"") | EV25: =IFERROR(EV24/EQ24-1,"") | EW25: =IFERROR(EW24/ER24-1,"") | EX25: =IFERROR(EX24/ES24-1,"") | EY25: =IFERROR(EY24/ET24-1,"") | ... GJ25: =IFERROR(GJ24/GE24-1,"")
B26: % qoq | CZ26: =IFERROR(CZ24/CY24-1,"") | DA26: =IFERROR(DA24/CZ24-1,"") | DB26: =IFERROR(DB24/DA24-1,"") | DD26: =IFERROR(DD24/DB24-1,"") | DE26: =IFERROR(DE24/DD24-1,"") | DF26: =IFERROR(DF24/DE24-1,"") | DG26: =IFERROR(DG24/DF24-1,"") | ER26: =IFERROR(ER24/EP24-1,"") | ES26: =IFERROR(ES24/ER24-1,"") | ET26: =IFERROR(ET24/ES24-1,"") | EU26: =IFERROR(EU24/ET24-1,"") | EW26: =IFERROR(EW24/EU24-1,"") | EX26: =IFERROR(EX24/EW24-1,"") | EY26: =IFERROR(EY24/EX24-1,"") | EZ26: =IFERROR(EZ24/EY24-1,"") | FB26: =IFERROR(FB24/EZ24-1,"") | FC26: =IFERROR(FC24/FB24-1,"") | FD26: =IFERROR(FD24/FC24-1,"") | FE26: =IFERROR(FE24/FD24-1,"") | FG26: =IFERROR(FG24/FE24-1,"") | FH26: =IFERROR(FH24/FG24-1,"") | FI26: =IFERROR(FI24/FH24-1,"") | FJ26: =IFERROR(FJ24/FI24-1,"") | FL26: =IFERROR(FL24/FJ24-1,"") | FM26: =IFERROR(FM24/FL24-1,"") | FN26: =IFERROR(FN24/FM24-1,"") | FO26: =IFERROR(FO24/FN24-1,"") | FQ26: =IFERROR(FQ24/FO24-1,"") | FR26: =IFERROR(FR24/FQ24-1,"") | FS26: =IFERROR(FS24/FR24-1,"") | FT26: =IFERROR(FT24/FS24-1,"") | FV26: =IFERROR(FV24/FT24-1,"") | FW26: =IFERROR(FW24/FV24-1,"") | FX26: =IFERROR(FX24/FW24-1,"") | FY26: =IFERROR(FY24/FX24-1,"") | GA26: =IFERROR(GA24/FY24-1,"") | GB26: =IFERROR(GB24/GA24-1,"") | GC26: =IFERROR(GC24/GB24-1,"") | GD26: =IFERROR(GD24/GC24-1,"") | GF26: =IFERROR(GF24/GD24-1,"") | GG26: =IFERROR(GG24/GF24-1,"") | GH26: =IFERROR(GH24/GG24-1,"") | GI26: =IFERROR(GI24/GH24-1,"")
B27: % of PBP | ER27: =ER24/ER$19 | ES27: =ES24/ES$19 | ET27: =ET24/ET$19 | EU27: =EU24/EU$19 | EV27: =EV24/EV$19 | EW27: =EW24/EW$19 | EX27: =EX24/EX$19 | EY27: =EY24/EY$19 | ... GJ27: =GJ24/GJ$19
B29: Total Microsoft 365 | ER29: =PBP!ER131 | ES29: =PBP!ES131 | ET29: =PBP!ET131 | EU29: =PBP!EU131 | EV29: =PBP!EV131 | EW29: =PBP!EW131 | EX29: =PBP!EX131 | EY29: =PBP!EY131 | ... GJ29: =PBP!GJ131
B30: % yoy | ER30: =IFERROR(ER29/EM29-1,"") | ES30: =IFERROR(ES29/EN29-1,"") | ET30: =IFERROR(ET29/EO29-1,"") | EU30: =IFERROR(EU29/EP29-1,"") | EV30: =IFERROR(EV29/EQ29-1,"") | EW30: =IFERROR(EW29/ER29-1,"") | EX30: =IFERROR(EX29/ES29-1,"") | EY30: =IFERROR(EY29/ET29-1,"") | ... GJ30: =IFERROR(GJ29/GE29-1,"")
B31: % qoq | ER31: =IFERROR(ER29/EP29-1,"") | ES31: =IFERROR(ES29/ER29-1,"") | ET31: =IFERROR(ET29/ES29-1,"") | EU31: =IFERROR(EU29/ET29-1,"") | EW31: =IFERROR(EW29/EU29-1,"") | EX31: =IFERROR(EX29/EW29-1,"") | EY31: =IFERROR(EY29/EX29-1,"") | EZ31: =IFERROR(EZ29/EY29-1,"") | FB31: =IFERROR(FB29/EZ29-1,"") | FC31: =IFERROR(FC29/FB29-1,"") | FD31: =IFERROR(FD29/FC29-1,"") | FE31: =IFERROR(FE29/FD29-1,"") | FG31: =IFERROR(FG29/FE29-1,"") | FH31: =IFERROR(FH29/FG29-1,"") | FI31: =IFERROR(FI29/FH29-1,"") | FJ31: =IFERROR(FJ29/FI29-1,"") | FL31: =IFERROR(FL29/FJ29-1,"") | FM31: =IFERROR(FM29/FL29-1,"") | FN31: =IFERROR(FN29/FM29-1,"") | FO31: =IFERROR(FO29/FN29-1,"") | FQ31: =IFERROR(FQ29/FO29-1,"") | FR31: =IFERROR(FR29/FQ29-1,"") | FS31: =IFERROR(FS29/FR29-1,"") | FT31: =IFERROR(FT29/FS29-1,"") | FV31: =IFERROR(FV29/FT29-1,"") | FW31: =IFERROR(FW29/FV29-1,"") | FX31: =IFERROR(FX29/FW29-1,"") | FY31: =IFERROR(FY29/FX29-1,"") | GA31: =IFERROR(GA29/FY29-1,"") | GB31: =IFERROR(GB29/GA29-1,"") | GC31: =IFERROR(GC29/GB29-1,"") | GD31: =IFERROR(GD29/GC29-1,"") | GF31: =IFERROR(GF29/GD29-1,"") | GG31: =IFERROR(GG29/GF29-1,"") | GH31: =IFERROR(GH29/GG29-1,"") | GI31: =IFERROR(GI29/GH29-1,"")
B32: % of PBP | ER32: =ER29/ER$19 | ES32: =ES29/ES$19 | ET32: =ET29/ET$19 | EU32: =EU29/EU$19 | EV32: =EV29/EV$19 | EW32: =EW29/EW$19 | EX32: =EX29/EX$19 | EY32: =EY29/EY$19 | ... GJ32: =GJ29/GJ$19
B34: Product0219 | DJ34: =PBP!DJ312 | DK34: =PBP!DK312 | DL34: =PBP!DL312 | DM34: =PBP!DM312 | DN34: =PBP!DN312 | DO34: =PBP!DO312 | DP34: =PBP!DP312 | DQ34: =PBP!DQ312 | ... GJ34: =PBP!GJ312
B35: % yoy | CT35: =IFERROR(CT34/CO34-1,"") | CU35: =IFERROR(CU34/CP34-1,"") | CV35: =IFERROR(CV34/CQ34-1,"") | CW35: =IFERROR(CW34/CR34-1,"") | CX35: =IFERROR(CX34/CS34-1,"") | CY35: =IFERROR(CY34/CT34-1,"") | CZ35: =IFERROR(CZ34/CU34-1,"") | DA35: =IFERROR(DA34/CV34-1,"") | ... GJ35: =IFERROR(GJ34/GE34-1,"")
B36: % qoq | CT36: =IFERROR(CT34/CR34-1,"") | CU36: =IFERROR(CU34/CT34-1,"") | CV36: =IFERROR(CV34/CU34-1,"") | CW36: =IFERROR(CW34/CV34-1,"") | CY36: =IFERROR(CY34/CW34-1,"") | CZ36: =IFERROR(CZ34/CY34-1,"") | DA36: =IFERROR(DA34/CZ34-1,"") | DB36: =IFERROR(DB34/DA34-1,"") | DD36: =IFERROR(DD34/DB34-1,"") | DE36: =IFERROR(DE34/DD34-1,"") | DF36: =IFERROR(DF34/DE34-1,"") | DG36: =IFERROR(DG34/DF34-1,"") | DI36: =IFERROR(DI34/DG34-1,"") | DJ36: =IFERROR(DJ34/DI34-1,"") | DK36: =IFERROR(DK34/DJ34-1,"") | DL36: =IFERROR(DL34/DK34-1,"") | DN36: =IFERROR(DN34/DL34-1,"") | DO36: =IFERROR(DO34/DN34-1,"") | DP36: =IFERROR(DP34/DO34-1,"") | DQ36: =IFERROR(DQ34/DP34-1,"") | DS36: =IFERROR(DS34/DQ34-1,"") | DT36: =IFERROR(DT34/DS34-1,"") | DU36: =IFERROR(DU34/DT34-1,"") | DV36: =IFERROR(DV34/DU34-1,"") | DX36: =IFERROR(DX34/DV34-1,"") | DY36: =IFERROR(DY34/DX34-1,"") | DZ36: =IFERROR(DZ34/DY34-1,"") | EA36: =IFERROR(EA34/DZ34-1,"") | EC36: =IFERROR(EC34/EA34-1,"") | ED36: =IFERROR(ED34/EC34-1,"") | EE36: =IFERROR(EE34/ED34-1,"") | EF36: =IFERROR(EF34/EE34-1,"") | EH36: =IFERROR(EH34/EF34-1,"") | EI36: =IFERROR(EI34/EH34-1,"") | EJ36: =IFERROR(EJ34/EI34-1,"") | EK36: =IFERROR(EK34/EJ34-1,"") | EM36: =IFERROR(EM34/EK34-1,"") | EN36: =IFERROR(EN34/EM34-1,"") | EO36: =IFERROR(EO34/EN34-1,"") | EP36: =IFERROR(EP34/EO34-1,"") | ER36: =IFERROR(ER34/EP34-1,"") | ES36: =IFERROR(ES34/ER34-1,"") | ET36: =IFERROR(ET34/ES34-1,"") | EU36: =IFERROR(EU34/ET34-1,"") | EW36: =IFERROR(EW34/EU34-1,"") | EX36: =IFERROR(EX34/EW34-1,"") | EY36: =IFERROR(EY34/EX34-1,"") | EZ36: =IFERROR(EZ34/EY34-1,"") | FB36: =IFERROR(FB34/EZ34-1,"") | FC36: =IFERROR(FC34/FB34-1,"") | FD36: =IFERROR(FD34/FC34-1,"") | FE36: =IFERROR(FE34/FD34-1,"") | FG36: =IFERROR(FG34/FE34-1,"") | FH36: =IFERROR(FH34/FG34-1,"") | FI36: =IFERROR(FI34/FH34-1,"") | FJ36: =IFERROR(FJ34/FI34-1,"") | FL36: =IFERROR(FL34/FJ34-1,"") | FM36: =IFERROR(FM34/FL34-1,"") | FN36: =IFERROR(FN34/FM34-1,"") | FO36: =IFERROR(FO34/FN34-1,"") | FQ36: =IFERROR(FQ34/FO34-1,"") | FR36: =IFERROR(FR34/FQ34-1,"") | FS36: =IFERROR(FS34/FR34-1,"") | FT36: =IFERROR(FT34/FS34-1,"") | FV36: =IFERROR(FV34/FT34-1,"") | FW36: =IFERROR(FW34/FV34-1,"") | FX36: =IFERROR(FX34/FW34-1,"") | FY36: =IFERROR(FY34/FX34-1,"") | GA36: =IFERROR(GA34/FY34-1,"") | GB36: =IFERROR(GB34/GA34-1,"") | GC36: =IFERROR(GC34/GB34-1,"") | GD36: =IFERROR(GD34/GC34-1,"") | GF36: =IFERROR(GF34/GD34-1,"") | GG36: =IFERROR(GG34/GF34-1,"") | GH36: =IFERROR(GH34/GG34-1,"") | GI36: =IFERROR(GI34/GH34-1,"")
B37: % of PBP | DJ37: =DJ34/DJ$19 | DK37: =DK34/DK$19 | DL37: =DL34/DL$19 | DM37: =DM34/DM$19 | DN37: =DN34/DN$19 | DO37: =DO34/DO$19 | DP37: =DP34/DP$19 | DQ37: =DQ34/DQ$19 | ... GJ37: =GJ34/GJ$19
B39: Dynamics | CT39: =PBP!CT347 | CU39: =PBP!CU347 | CV39: =PBP!CV347 | CW39: =PBP!CW347 | CX39: =PBP!CX347 | CY39: =PBP!CY347 | CZ39: =PBP!CZ347 | DA39: =PBP!DA347 | ... GJ39: =PBP!GJ347
B40: % yoy | CT40: =IFERROR(CT39/CO39-1,"") | CU40: =IFERROR(CU39/CP39-1,"") | CV40: =IFERROR(CV39/CQ39-1,"") | CW40: =IFERROR(CW39/CR39-1,"") | CX40: =IFERROR(CX39/CS39-1,"") | CY40: =IFERROR(CY39/CT39-1,"") | CZ40: =IFERROR(CZ39/CU39-1,"") | DA40: =IFERROR(DA39/CV39-1,"") | ... GJ40: =IFERROR(GJ39/GE39-1,"")
B41: % qoq | CT41: =IFERROR(CT39/CR39-1,"") | CU41: =IFERROR(CU39/CT39-1,"") | CV41: =IFERROR(CV39/CU39-1,"") | CW41: =IFERROR(CW39/CV39-1,"") | CY41: =IFERROR(CY39/CW39-1,"") | CZ41: =IFERROR(CZ39/CY39-1,"") | DA41: =IFERROR(DA39/CZ39-1,"") | DB41: =IFERROR(DB39/DA39-1,"") | DD41: =IFERROR(DD39/DB39-1,"") | DE41: =IFERROR(DE39/DD39-1,"") | DF41: =IFERROR(DF39/DE39-1,"") | DG41: =IFERROR(DG39/DF39-1,"") | DI41: =IFERROR(DI39/DG39-1,"") | DJ41: =IFERROR(DJ39/DI39-1,"") | DK41: =IFERROR(DK39/DJ39-1,"") | DL41: =IFERROR(DL39/DK39-1,"") | DN41: =IFERROR(DN39/DL39-1,"") | DO41: =IFERROR(DO39/DN39-1,"") | DP41: =IFERROR(DP39/DO39-1,"") | DQ41: =IFERROR(DQ39/DP39-1,"") | DS41: =IFERROR(DS39/DQ39-1,"") | DT41: =IFERROR(DT39/DS39-1,"") | DU41: =IFERROR(DU39/DT39-1,"") | DV41: =IFERROR(DV39/DU39-1,"") | DX41: =IFERROR(DX39/DV39-1,"") | DY41: =IFERROR(DY39/DX39-1,"") | DZ41: =IFERROR(DZ39/DY39-1,"") | EA41: =IFERROR(EA39/DZ39-1,"") | EC41: =IFERROR(EC39/EA39-1,"") | ED41: =IFERROR(ED39/EC39-1,"") | EE41: =IFERROR(EE39/ED39-1,"") | EF41: =IFERROR(EF39/EE39-1,"") | EH41: =IFERROR(EH39/EF39-1,"") | EI41: =IFERROR(EI39/EH39-1,"") | EJ41: =IFERROR(EJ39/EI39-1,"") | EK41: =IFERROR(EK39/EJ39-1,"") | EM41: =IFERROR(EM39/EK39-1,"") | EN41: =IFERROR(EN39/EM39-1,"") | EO41: =IFERROR(EO39/EN39-1,"") | EP41: =IFERROR(EP39/EO39-1,"") | ER41: =IFERROR(ER39/EP39-1,"") | ES41: =IFERROR(ES39/ER39-1,"") | ET41: =IFERROR(ET39/ES39-1,"") | EU41: =IFERROR(EU39/ET39-1,"") | EW41: =IFERROR(EW39/EU39-1,"") | EX41: =IFERROR(EX39/EW39-1,"") | EY41: =IFERROR(EY39/EX39-1,"") | EZ41: =IFERROR(EZ39/EY39-1,"") | FB41: =IFERROR(FB39/EZ39-1,"") | FC41: =IFERROR(FC39/FB39-1,"") | FD41: =IFERROR(FD39/FC39-1,"") | FE41: =IFERROR(FE39/FD39-1,"") | FG41: =IFERROR(FG39/FE39-1,"") | FH41: =IFERROR(FH39/FG39-1,"") | FI41: =IFERROR(FI39/FH39-1,"") | FJ41: =IFERROR(FJ39/FI39-1,"") | FL41: =IFERROR(FL39/FJ39-1,"") | FM41: =IFERROR(FM39/FL39-1,"") | FN41: =IFERROR(FN39/FM39-1,"") | FO41: =IFERROR(FO39/FN39-1,"") | FQ41: =IFERROR(FQ39/FO39-1,"") | FR41: =IFERROR(FR39/FQ39-1,"") | FS41: =IFERROR(FS39/FR39-1,"") | FT41: =IFERROR(FT39/FS39-1,"") | FV41: =IFERROR(FV39/FT39-1,"") | FW41: =IFERROR(FW39/FV39-1,"") | FX41: =IFERROR(FX39/FW39-1,"") | FY41: =IFERROR(FY39/FX39-1,"") | GA41: =IFERROR(GA39/FY39-1,"") | GB41: =IFERROR(GB39/GA39-1,"") | GC41: =IFERROR(GC39/GB39-1,"") | GD41: =IFERROR(GD39/GC39-1,"") | GF41: =IFERROR(GF39/GD39-1,"") | GG41: =IFERROR(GG39/GF39-1,"") | GH41: =IFERROR(GH39/GG39-1,"") | GI41: =IFERROR(GI39/GH39-1,"")
B42: % of PBP | DJ42: =DJ39/DJ$19 | DK42: =DK39/DK$19 | DL42: =DL39/DL$19 | DM42: =DM39/DM$19 | DN42: =DN39/DN$19 | DO42: =DO39/DO$19 | DP42: =DP39/DP$19 | DQ42: =DQ39/DQ$19 | ... GJ42: =GJ39/GJ$19
B44: IC Revenue | CY44: =IFERROR(IC!CY50,"") | CZ44: =IFERROR(IC!CZ50,"") | DA44: =IFERROR(IC!DA50,"") | DB44: =IFERROR(IC!DB50,"") | DC44: =IFERROR(IC!DC50,"") | DD44: =IFERROR(IC!DD50,"") | DE44: =IFERROR(IC!DE50,"") | DF44: =IFERROR(IC!DF50,"") | ... EQ44: =IFERROR(IC!EQ50,"") | ER44: =IC!ER10 | ES44: =IC!ES10 | ET44: =IC!ET10 | EU44: =IC!EU10 | EV44: =IC!EV10 | EW44: =IC!EW10 | EX44: =IC!EX10 | EY44: =IC!EY10 | ... GJ44: =IC!GJ10
B45: % yoy | DD45: =IFERROR(DD44/CY44-1,"") | DE45: =IFERROR(DE44/CZ44-1,"") | DF45: =IFERROR(DF44/DA44-1,"") | DG45: =IFERROR(DG44/DB44-1,"") | DH45: =IFERROR(DH44/DC44-1,"") | DI45: =IFERROR(DI44/DD44-1,"") | DJ45: =IFERROR(DJ44/DE44-1,"") | DK45: =IFERROR(DK44/DF44-1,"") | ... GJ45: =IFERROR(GJ44/GE44-1,"")
B46: % qoq | CZ46: =IFERROR(CZ44/CY44-1,"") | DA46: =IFERROR(DA44/CZ44-1,"") | DB46: =IFERROR(DB44/DA44-1,"") | DD46: =IFERROR(DD44/DB44-1,"") | DE46: =IFERROR(DE44/DD44-1,"") | DF46: =IFERROR(DF44/DE44-1,"") | DG46: =IFERROR(DG44/DF44-1,"") | DI46: =IFERROR(DI44/DG44-1,"") | DJ46: =IFERROR(DJ44/DI44-1,"") | DK46: =IFERROR(DK44/DJ44-1,"") | DL46: =IFERROR(DL44/DK44-1,"") | DN46: =IFERROR(DN44/DL44-1,"") | DO46: =IFERROR(DO44/DN44-1,"") | DP46: =IFERROR(DP44/DO44-1,"") | DQ46: =IFERROR(DQ44/DP44-1,"") | DS46: =IFERROR(DS44/DQ44-1,"") | DT46: =IFERROR(DT44/DS44-1,"") | DU46: =IFERROR(DU44/DT44-1,"") | DV46: =IFERROR(DV44/DU44-1,"") | DX46: =IFERROR(DX44/DV44-1,"") | DY46: =IFERROR(DY44/DX44-1,"") | DZ46: =IFERROR(DZ44/DY44-1,"") | EA46: =IFERROR(EA44/DZ44-1,"") | EC46: =IFERROR(EC44/EA44-1,"") | ED46: =IFERROR(ED44/EC44-1,"") | EE46: =IFERROR(EE44/ED44-1,"") | EF46: =IFERROR(EF44/EE44-1,"") | EH46: =IFERROR(EH44/EF44-1,"") | EI46: =IFERROR(EI44/EH44-1,"") | EJ46: =IFERROR(EJ44/EI44-1,"") | EK46: =IFERROR(EK44/EJ44-1,"") | EM46: =IFERROR(EM44/EK44-1,"") | EN46: =IFERROR(EN44/EM44-1,"") | EO46: =IFERROR(EO44/EN44-1,"") | EP46: =IFERROR(EP44/EO44-1,"") | ER46: =IFERROR(ER44/EP44-1,"") | ES46: =IFERROR(ES44/ER44-1,"") | ET46: =IFERROR(ET44/ES44-1,"") | EU46: =IFERROR(EU44/ET44-1,"") | EW46: =IFERROR(EW44/EU44-1,"") | EX46: =IFERROR(EX44/EW44-1,"") | EY46: =IFERROR(EY44/EX44-1,"") | EZ46: =IFERROR(EZ44/EY44-1,"") | FB46: =IFERROR(FB44/EZ44-1,"") | FC46: =IFERROR(FC44/FB44-1,"") | FD46: =IFERROR(FD44/FC44-1,"") | FE46: =IFERROR(FE44/FD44-1,"") | FG46: =IFERROR(FG44/FE44-1,"") | FH46: =IFERROR(FH44/FG44-1,"") | FI46: =IFERROR(FI44/FH44-1,"") | FJ46: =IFERROR(FJ44/FI44-1,"") | FL46: =IFERROR(FL44/FJ44-1,"") | FM46: =IFERROR(FM44/FL44-1,"") | FN46: =IFERROR(FN44/FM44-1,"") | FO46: =IFERROR(FO44/FN44-1,"") | FQ46: =IFERROR(FQ44/FO44-1,"") | FR46: =IFERROR(FR44/FQ44-1,"") | FS46: =IFERROR(FS44/FR44-1,"") | FT46: =IFERROR(FT44/FS44-1,"") | FV46: =IFERROR(FV44/FT44-1,"") | FW46: =IFERROR(FW44/FV44-1,"") | FX46: =IFERROR(FX44/FW44-1,"") | FY46: =IFERROR(FY44/FX44-1,"") | GA46: =IFERROR(GA44/FY44-1,"") | GB46: =IFERROR(GB44/GA44-1,"") | GC46: =IFERROR(GC44/GB44-1,"") | GD46: =IFERROR(GD44/GC44-1,"") | GF46: =IFERROR(GF44/GD44-1,"") | GG46: =IFERROR(GG44/GF44-1,"") | GH46: =IFERROR(GH44/GG44-1,"") | GI46: =IFERROR(GI44/GH44-1,"")
B47: % Total Revenue | CY47: =CY44/CY$10 | CZ47: =CZ44/CZ$10 | DA47: =DA44/DA$10 | DB47: =DB44/DB$10 | DC47: =DC44/DC$10 | DD47: =DD44/DD$10 | DE47: =DE44/DE$10 | DF47: =DF44/DF$10 | ... GJ47: =GJ44/GJ$10
B49: Product0058 | EM49: =IC!EM108 | EN49: =IC!EN108 | EO49: =IC!EO108 | EP49: =IC!EP108 | EQ49: =IC!EQ108 | ER49: =IC!ER108 | ES49: =IC!ES108 | ET49: =IC!ET108 | ... GJ49: =IC!GJ108
B50: % yoy | ER50: =IFERROR(ER49/EM49-1,"") | ES50: =IFERROR(ES49/EN49-1,"") | ET50: =IFERROR(ET49/EO49-1,"") | EU50: =IFERROR(EU49/EP49-1,"") | EV50: =IFERROR(EV49/EQ49-1,"") | EW50: =IFERROR(EW49/ER49-1,"") | EX50: =IFERROR(EX49/ES49-1,"") | EY50: =IFERROR(EY49/ET49-1,"") | ... GJ50: =IFERROR(GJ49/GE49-1,"")
B51: % qoq | ER51: =IFERROR(ER49/EP49-1,"") | ES51: =IFERROR(ES49/ER49-1,"") | ET51: =IFERROR(ET49/ES49-1,"") | EU51: =IFERROR(EU49/ET49-1,"") | EW51: =IFERROR(EW49/EU49-1,"") | EX51: =IFERROR(EX49/EW49-1,"") | EY51: =IFERROR(EY49/EX49-1,"") | EZ51: =IFERROR(EZ49/EY49-1,"") | FB51: =IFERROR(FB49/EZ49-1,"") | FC51: =IFERROR(FC49/FB49-1,"") | FD51: =IFERROR(FD49/FC49-1,"") | FE51: =IFERROR(FE49/FD49-1,"") | FG51: =IFERROR(FG49/FE49-1,"") | FH51: =IFERROR(FH49/FG49-1,"") | FI51: =IFERROR(FI49/FH49-1,"") | FJ51: =IFERROR(FJ49/FI49-1,"") | FL51: =IFERROR(FL49/FJ49-1,"") | FM51: =IFERROR(FM49/FL49-1,"") | FN51: =IFERROR(FN49/FM49-1,"") | FO51: =IFERROR(FO49/FN49-1,"") | FQ51: =IFERROR(FQ49/FO49-1,"") | FR51: =IFERROR(FR49/FQ49-1,"") | FS51: =IFERROR(FS49/FR49-1,"") | FT51: =IFERROR(FT49/FS49-1,"") | FV51: =IFERROR(FV49/FT49-1,"") | FW51: =IFERROR(FW49/FV49-1,"") | FX51: =IFERROR(FX49/FW49-1,"") | FY51: =IFERROR(FY49/FX49-1,"") | GA51: =IFERROR(GA49/FY49-1,"") | GB51: =IFERROR(GB49/GA49-1,"") | GC51: =IFERROR(GC49/GB49-1,"") | GD51: =IFERROR(GD49/GC49-1,"") | GF51: =IFERROR(GF49/GD49-1,"") | GG51: =IFERROR(GG49/GF49-1,"") | GH51: =IFERROR(GH49/GG49-1,"") | GI51: =IFERROR(GI49/GH49-1,"")
B52: % of IC | ER52: =ER49/ER$44 | ES52: =ES49/ES$44 | ET52: =ET49/ET$44 | EU52: =EU49/EU$44 | EV52: =EV49/EV$44 | EW52: =EW49/EW$44 | EX52: =EX49/EX$44 | EY52: =EY49/EY$44 | ... GJ52: =GJ49/GJ$44
B54: Server Products | DD54: =IC!DD209 | DE54: =IC!DE209 | DF54: =IC!DF209 | DG54: =IC!DG209 | DH54: =IC!DH209 | DI54: =IC!DI209 | DJ54: =IC!DJ209 | DK54: =IC!DK209 | ... GJ54: =IC!GJ209
B55: % yoy | CT55: =IFERROR(CT54/CO54-1,"") | CU55: =IFERROR(CU54/CP54-1,"") | CV55: =IFERROR(CV54/CQ54-1,"") | CW55: =IFERROR(CW54/CR54-1,"") | CX55: =IFERROR(CX54/CS54-1,"") | CY55: =IFERROR(CY54/CT54-1,"") | CZ55: =IFERROR(CZ54/CU54-1,"") | DA55: =IFERROR(DA54/CV54-1,"") | ... GJ55: =IFERROR(GJ54/GE54-1,"")
B56: % qoq | CT56: =IFERROR(CT54/CR54-1,"") | CU56: =IFERROR(CU54/CT54-1,"") | CV56: =IFERROR(CV54/CU54-1,"") | CW56: =IFERROR(CW54/CV54-1,"") | CY56: =IFERROR(CY54/CW54-1,"") | CZ56: =IFERROR(CZ54/CY54-1,"") | DA56: =IFERROR(DA54/CZ54-1,"") | DB56: =IFERROR(DB54/DA54-1,"") | DD56: =IFERROR(DD54/DB54-1,"") | DE56: =IFERROR(DE54/DD54-1,"") | DF56: =IFERROR(DF54/DE54-1,"") | DG56: =IFERROR(DG54/DF54-1,"") | DI56: =IFERROR(DI54/DG54-1,"") | DJ56: =IFERROR(DJ54/DI54-1,"") | DK56: =IFERROR(DK54/DJ54-1,"") | DL56: =IFERROR(DL54/DK54-1,"") | DN56: =IFERROR(DN54/DL54-1,"") | DO56: =IFERROR(DO54/DN54-1,"") | DP56: =IFERROR(DP54/DO54-1,"") | DQ56: =IFERROR(DQ54/DP54-1,"") | DS56: =IFERROR(DS54/DQ54-1,"") | DT56: =IFERROR(DT54/DS54-1,"") | DU56: =IFERROR(DU54/DT54-1,"") | DV56: =IFERROR(DV54/DU54-1,"") | DX56: =IFERROR(DX54/DV54-1,"") | DY56: =IFERROR(DY54/DX54-1,"") | DZ56: =IFERROR(DZ54/DY54-1,"") | EA56: =IFERROR(EA54/DZ54-1,"") | EC56: =IFERROR(EC54/EA54-1,"") | ED56: =IFERROR(ED54/EC54-1,"") | EE56: =IFERROR(EE54/ED54-1,"") | EF56: =IFERROR(EF54/EE54-1,"") | EH56: =IFERROR(EH54/EF54-1,"") | EI56: =IFERROR(EI54/EH54-1,"") | EJ56: =IFERROR(EJ54/EI54-1,"") | EK56: =IFERROR(EK54/EJ54-1,"") | EM56: =IFERROR(EM54/EK54-1,"") | EN56: =IFERROR(EN54/EM54-1,"") | EO56: =IFERROR(EO54/EN54-1,"") | EP56: =IFERROR(EP54/EO54-1,"") | ER56: =IFERROR(ER54/EP54-1,"") | ES56: =IFERROR(ES54/ER54-1,"") | ET56: =IFERROR(ET54/ES54-1,"") | EU56: =IFERROR(EU54/ET54-1,"") | EW56: =IFERROR(EW54/EU54-1,"") | EX56: =IFERROR(EX54/EW54-1,"") | EY56: =IFERROR(EY54/EX54-1,"") | EZ56: =IFERROR(EZ54/EY54-1,"") | FB56: =IFERROR(FB54/EZ54-1,"") | FC56: =IFERROR(FC54/FB54-1,"") | FD56: =IFERROR(FD54/FC54-1,"") | FE56: =IFERROR(FE54/FD54-1,"") | FG56: =IFERROR(FG54/FE54-1,"") | FH56: =IFERROR(FH54/FG54-1,"") | FI56: =IFERROR(FI54/FH54-1,"") | FJ56: =IFERROR(FJ54/FI54-1,"") | FL56: =IFERROR(FL54/FJ54-1,"") | FM56: =IFERROR(FM54/FL54-1,"") | FN56: =IFERROR(FN54/FM54-1,"") | FO56: =IFERROR(FO54/FN54-1,"") | FQ56: =IFERROR(FQ54/FO54-1,"") | FR56: =IFERROR(FR54/FQ54-1,"") | FS56: =IFERROR(FS54/FR54-1,"") | FT56: =IFERROR(FT54/FS54-1,"") | FV56: =IFERROR(FV54/FT54-1,"") | FW56: =IFERROR(FW54/FV54-1,"") | FX56: =IFERROR(FX54/FW54-1,"") | FY56: =IFERROR(FY54/FX54-1,"") | GA56: =IFERROR(GA54/FY54-1,"") | GB56: =IFERROR(GB54/GA54-1,"") | GC56: =IFERROR(GC54/GB54-1,"") | GD56: =IFERROR(GD54/GC54-1,"") | GF56: =IFERROR(GF54/GD54-1,"") | GG56: =IFERROR(GG54/GF54-1,"") | GH56: =IFERROR(GH54/GG54-1,"") | GI56: =IFERROR(GI54/GH54-1,"")
B57: % of IC | DD57: =DD54/DD$44 | DE57: =DE54/DE$44 | DF57: =DF54/DF$44 | DG57: =DG54/DG$44 | DH57: =DH54/DH$44 | DI57: =DI54/DI$44 | DJ57: =DJ54/DJ$44 | DK57: =DK54/DK$44 | ... GJ57: =GJ54/GJ$44
B59: Enterprise and Parter Services | CT59: =IC!CT224 | CU59: =IC!CU224 | CV59: =IC!CV224 | CW59: =IC!CW224 | CX59: =IC!CX224 | CY59: =IC!CY224 | CZ59: =IC!CZ224 | DA59: =IC!DA224 | ... GJ59: =IC!GJ224
B60: % yoy | CT60: =IFERROR(CT59/CO59-1,"") | CU60: =IFERROR(CU59/CP59-1,"") | CV60: =IFERROR(CV59/CQ59-1,"") | CW60: =IFERROR(CW59/CR59-1,"") | CX60: =IFERROR(CX59/CS59-1,"") | CY60: =IFERROR(CY59/CT59-1,"") | CZ60: =IFERROR(CZ59/CU59-1,"") | DA60: =IFERROR(DA59/CV59-1,"") | ... GJ60: =IFERROR(GJ59/GE59-1,"")
B61: % qoq | CT61: =IFERROR(CT59/CR59-1,"") | CU61: =IFERROR(CU59/CT59-1,"") | CV61: =IFERROR(CV59/CU59-1,"") | CW61: =IFERROR(CW59/CV59-1,"") | CY61: =IFERROR(CY59/CW59-1,"") | CZ61: =IFERROR(CZ59/CY59-1,"") | DA61: =IFERROR(DA59/CZ59-1,"") | DB61: =IFERROR(DB59/DA59-1,"") | DD61: =IFERROR(DD59/DB59-1,"") | DE61: =IFERROR(DE59/DD59-1,"") | DF61: =IFERROR(DF59/DE59-1,"") | DG61: =IFERROR(DG59/DF59-1,"") | DI61: =IFERROR(DI59/DG59-1,"") | DJ61: =IFERROR(DJ59/DI59-1,"") | DK61: =IFERROR(DK59/DJ59-1,"") | DL61: =IFERROR(DL59/DK59-1,"") | DN61: =IFERROR(DN59/DL59-1,"") | DO61: =IFERROR(DO59/DN59-1,"") | DP61: =IFERROR(DP59/DO59-1,"") | DQ61: =IFERROR(DQ59/DP59-1,"") | DS61: =IFERROR(DS59/DQ59-1,"") | DT61: =IFERROR(DT59/DS59-1,"") | DU61: =IFERROR(DU59/DT59-1,"") | DV61: =IFERROR(DV59/DU59-1,"") | DX61: =IFERROR(DX59/DV59-1,"") | DY61: =IFERROR(DY59/DX59-1,"") | DZ61: =IFERROR(DZ59/DY59-1,"") | EA61: =IFERROR(EA59/DZ59-1,"") | EC61: =IFERROR(EC59/EA59-1,"") | ED61: =IFERROR(ED59/EC59-1,"") | EE61: =IFERROR(EE59/ED59-1,"") | EF61: =IFERROR(EF59/EE59-1,"") | EH61: =IFERROR(EH59/EF59-1,"") | EI61: =IFERROR(EI59/EH59-1,"") | EJ61: =IFERROR(EJ59/EI59-1,"") | EK61: =IFERROR(EK59/EJ59-1,"") | EM61: =IFERROR(EM59/EK59-1,"") | EN61: =IFERROR(EN59/EM59-1,"") | EO61: =IFERROR(EO59/EN59-1,"") | EP61: =IFERROR(EP59/EO59-1,"") | ER61: =IFERROR(ER59/EP59-1,"") | ES61: =IFERROR(ES59/ER59-1,"") | ET61: =IFERROR(ET59/ES59-1,"") | EU61: =IFERROR(EU59/ET59-1,"") | EW61: =IFERROR(EW59/EU59-1,"") | EX61: =IFERROR(EX59/EW59-1,"") | EY61: =IFERROR(EY59/EX59-1,"") | EZ61: =IFERROR(EZ59/EY59-1,"") | FB61: =IFERROR(FB59/EZ59-1,"") | FC61: =IFERROR(FC59/FB59-1,"") | FD61: =IFERROR(FD59/FC59-1,"") | FE61: =IFERROR(FE59/FD59-1,"") | FG61: =IFERROR(FG59/FE59-1,"") | FH61: =IFERROR(FH59/FG59-1,"") | FI61: =IFERROR(FI59/FH59-1,"") | FJ61: =IFERROR(FJ59/FI59-1,"") | FL61: =IFERROR(FL59/FJ59-1,"") | FM61: =IFERROR(FM59/FL59-1,"") | FN61: =IFERROR(FN59/FM59-1,"") | FO61: =IFERROR(FO59/FN59-1,"") | FQ61: =IFERROR(FQ59/FO59-1,"") | FR61: =IFERROR(FR59/FQ59-1,"") | FS61: =IFERROR(FS59/FR59-1,"") | FT61: =IFERROR(FT59/FS59-1,"") | FV61: =IFERROR(FV59/FT59-1,"") | FW61: =IFERROR(FW59/FV59-1,"") | FX61: =IFERROR(FX59/FW59-1,"") | FY61: =IFERROR(FY59/FX59-1,"") | GA61: =IFERROR(GA59/FY59-1,"") | GB61: =IFERROR(GB59/GA59-1,"") | GC61: =IFERROR(GC59/GB59-1,"") | GD61: =IFERROR(GD59/GC59-1,"") | GF61: =IFERROR(GF59/GD59-1,"") | GG61: =IFERROR(GG59/GF59-1,"") | GH61: =IFERROR(GH59/GG59-1,"") | GI61: =IFERROR(GI59/GH59-1,"")
B62: % of IC | DD62: =DD59/DD$44 | DE62: =DE59/DE$44 | DF62: =DF59/DF$44 | DG62: =DG59/DG$44 | DH62: =DH59/DH$44 | DI62: =DI59/DI$44 | DJ62: =DJ59/DJ$44 | DK62: =DK59/DK$44 | ... GJ62: =GJ59/GJ$44
B64: Company1738 Revenue | CY64: =IFERROR(Company1738!CY50,"") | CZ64: =IFERROR(Company1738!CZ50,"") | DA64: =IFERROR(Company1738!DA50,"") | DB64: =IFERROR(Company1738!DB50,"") | DC64: =IFERROR(Company1738!DC50,"") | DD64: =IFERROR(Company1738!DD50,"") | DE64: =IFERROR(Company1738!DE50,"") | DF64: =IFERROR(Company1738!DF50,"") | ... EQ64: =IFERROR(Company1738!EQ50,"") | ER64: =Company1738!ER10 | ES64: =Company1738!ES10 | ET64: =Company1738!ET10 | EU64: =Company1738!EU10 | EV64: =Company1738!EV10 | EW64: =Company1738!EW10 | EX64: =Company1738!EX10 | EY64: =Company1738!EY10 | ... GJ64: =Company1738!GJ10
B65: % yoy | DD65: =IFERROR(DD64/CY64-1,"") | DE65: =IFERROR(DE64/CZ64-1,"") | DF65: =IFERROR(DF64/DA64-1,"") | DG65: =IFERROR(DG64/DB64-1,"") | DH65: =IFERROR(DH64/DC64-1,"") | DI65: =IFERROR(DI64/DD64-1,"") | DJ65: =IFERROR(DJ64/DE64-1,"") | DK65: =IFERROR(DK64/DF64-1,"") | ... GJ65: =IFERROR(GJ64/GE64-1,"")
B66: % qoq | CZ66: =IFERROR(CZ64/CY64-1,"") | DA66: =IFERROR(DA64/CZ64-1,"") | DB66: =IFERROR(DB64/DA64-1,"") | DD66: =IFERROR(DD64/DB64-1,"") | DE66: =IFERROR(DE64/DD64-1,"") | DF66: =IFERROR(DF64/DE64-1,"") | DG66: =IFERROR(DG64/DF64-1,"") | DI66: =IFERROR(DI64/DG64-1,"") | DJ66: =IFERROR(DJ64/DI64-1,"") | DK66: =IFERROR(DK64/DJ64-1,"") | DL66: =IFERROR(DL64/DK64-1,"") | DN66: =IFERROR(DN64/DL64-1,"") | DO66: =IFERROR(DO64/DN64-1,"") | DP66: =IFERROR(DP64/DO64-1,"") | DQ66: =IFERROR(DQ64/DP64-1,"") | DS66: =IFERROR(DS64/DQ64-1,"") | DT66: =IFERROR(DT64/DS64-1,"") | DU66: =IFERROR(DU64/DT64-1,"") | DV66: =IFERROR(DV64/DU64-1,"") | DX66: =IFERROR(DX64/DV64-1,"") | DY66: =IFERROR(DY64/DX64-1,"") | DZ66: =IFERROR(DZ64/DY64-1,"") | EA66: =IFERROR(EA64/DZ64-1,"") | EC66: =IFERROR(EC64/EA64-1,"") | ED66: =IFERROR(ED64/EC64-1,"") | EE66: =IFERROR(EE64/ED64-1,"") | EF66: =IFERROR(EF64/EE64-1,"") | EH66: =IFERROR(EH64/EF64-1,"") | EI66: =IFERROR(EI64/EH64-1,"") | EJ66: =IFERROR(EJ64/EI64-1,"") | EK66: =IFERROR(EK64/EJ64-1,"") | EM66: =IFERROR(EM64/EK64-1,"") | EN66: =IFERROR(EN64/EM64-1,"") | EO66: =IFERROR(EO64/EN64-1,"") | EP66: =IFERROR(EP64/EO64-1,"") | ER66: =IFERROR(ER64/EP64-1,"") | ES66: =IFERROR(ES64/ER64-1,"") | ET66: =IFERROR(ET64/ES64-1,"") | EU66: =IFERROR(EU64/ET64-1,"") | EW66: =IFERROR(EW64/EU64-1,"") | EX66: =IFERROR(EX64/EW64-1,"") | EY66: =IFERROR(EY64/EX64-1,"") | EZ66: =IFERROR(EZ64/EY64-1,"") | FB66: =IFERROR(FB64/EZ64-1,"") | FC66: =IFERROR(FC64/FB64-1,"") | FD66: =IFERROR(FD64/FC64-1,"") | FE66: =IFERROR(FE64/FD64-1,"") | FG66: =IFERROR(FG64/FE64-1,"") | FH66: =IFERROR(FH64/FG64-1,"") | FI66: =IFERROR(FI64/FH64-1,"") | FJ66: =IFERROR(FJ64/FI64-1,"") | FL66: =IFERROR(FL64/FJ64-1,"") | FM66: =IFERROR(FM64/FL64-1,"") | FN66: =IFERROR(FN64/FM64-1,"") | FO66: =IFERROR(FO64/FN64-1,"") | FQ66: =IFERROR(FQ64/FO64-1,"") | FR66: =IFERROR(FR64/FQ64-1,"") | FS66: =IFERROR(FS64/FR64-1,"") | FT66: =IFERROR(FT64/FS64-1,"") | FV66: =IFERROR(FV64/FT64-1,"") | FW66: =IFERROR(FW64/FV64-1,"") | FX66: =IFERROR(FX64/FW64-1,"") | FY66: =IFERROR(FY64/FX64-1,"") | GA66: =IFERROR(GA64/FY64-1,"") | GB66: =IFERROR(GB64/GA64-1,"") | GC66: =IFERROR(GC64/GB64-1,"") | GD66: =IFERROR(GD64/GC64-1,"") | GF66: =IFERROR(GF64/GD64-1,"") | GG66: =IFERROR(GG64/GF64-1,"") | GH66: =IFERROR(GH64/GG64-1,"") | GI66: =IFERROR(GI64/GH64-1,"")
B67: % Total Revenue | CY67: =CY64/CY$10 | CZ67: =CZ64/CZ$10 | DA67: =DA64/DA$10 | DB67: =DB64/DB$10 | DC67: =DC64/DC$10 | DD67: =DD64/DD$10 | DE67: =DE64/DE$10 | DF67: =DF64/DF$10 | ... GJ67: =GJ64/GJ$10
B69: Gaming | DG69: =Company1738!DG89 | DI69: =Company1738!DI89 | DJ69: =Company1738!DJ89 | DK69: =Company1738!DK89 | DL69: =Company1738!DL89 | DM69: =Company1738!DM89 | DN69: =Company1738!DN89 | DO69: =Company1738!DO89 | DP69: =Company1738!DP89 | ... GJ69: =Company1738!GJ89
B70: % yoy | CT70: =IFERROR(CT69/CO69-1,"") | CU70: =IFERROR(CU69/CP69-1,"") | CV70: =IFERROR(CV69/CQ69-1,"") | CW70: =IFERROR(CW69/CR69-1,"") | CX70: =IFERROR(CX69/CS69-1,"") | CY70: =IFERROR(CY69/CT69-1,"") | CZ70: =IFERROR(CZ69/CU69-1,"") | DA70: =IFERROR(DA69/CV69-1,"") | ... GJ70: =IFERROR(GJ69/GE69-1,"")
B71: % qoq | CT71: =IFERROR(CT69/CR69-1,"") | CU71: =IFERROR(CU69/CT69-1,"") | CV71: =IFERROR(CV69/CU69-1,"") | CW71: =IFERROR(CW69/CV69-1,"") | CY71: =IFERROR(CY69/CW69-1,"") | CZ71: =IFERROR(CZ69/CY69-1,"") | DA71: =IFERROR(DA69/CZ69-1,"") | DB71: =IFERROR(DB69/DA69-1,"") | DD71: =IFERROR(DD69/DB69-1,"") | DE71: =IFERROR(DE69/DD69-1,"") | DF71: =IFERROR(DF69/DE69-1,"") | DG71: =IFERROR(DG69/DF69-1,"") | DI71: =IFERROR(DI69/DG69-1,"") | DJ71: =IFERROR(DJ69/DI69-1,"") | DK71: =IFERROR(DK69/DJ69-1,"") | DL71: =IFERROR(DL69/DK69-1,"") | DN71: =IFERROR(DN69/DL69-1,"") | DO71: =IFERROR(DO69/DN69-1,"") | DP71: =IFERROR(DP69/DO69-1,"") | DQ71: =IFERROR(DQ69/DP69-1,"") | DS71: =IFERROR(DS69/DQ69-1,"") | DT71: =IFERROR(DT69/DS69-1,"") | DU71: =IFERROR(DU69/DT69-1,"") | DV71: =IFERROR(DV69/DU69-1,"") | DX71: =IFERROR(DX69/DV69-1,"") | DY71: =IFERROR(DY69/DX69-1,"") | DZ71: =IFERROR(DZ69/DY69-1,"") | EA71: =IFERROR(EA69/DZ69-1,"") | EC71: =IFERROR(EC69/EA69-1,"") | ED71: =IFERROR(ED69/EC69-1,"") | EE71: =IFERROR(EE69/ED69-1,"") | EF71: =IFERROR(EF69/EE69-1,"") | EH71: =IFERROR(EH69/EF69-1,"") | EI71: =IFERROR(EI69/EH69-1,"") | EJ71: =IFERROR(EJ69/EI69-1,"") | EK71: =IFERROR(EK69/EJ69-1,"") | EM71: =IFERROR(EM69/EK69-1,"") | EN71: =IFERROR(EN69/EM69-1,"") | EO71: =IFERROR(EO69/EN69-1,"") | EP71: =IFERROR(EP69/EO69-1,"") | ER71: =IFERROR(ER69/EP69-1,"") | ES71: =IFERROR(ES69/ER69-1,"") | ET71: =IFERROR(ET69/ES69-1,"") | EU71: =IFERROR(EU69/ET69-1,"") | EW71: =IFERROR(EW69/EU69-1,"") | EX71: =IFERROR(EX69/EW69-1,"") | EY71: =IFERROR(EY69/EX69-1,"") | EZ71: =IFERROR(EZ69/EY69-1,"") | FB71: =IFERROR(FB69/EZ69-1,"") | FC71: =IFERROR(FC69/FB69-1,"") | FD71: =IFERROR(FD69/FC69-1,"") | FE71: =IFERROR(FE69/FD69-1,"") | FG71: =IFERROR(FG69/FE69-1,"") | FH71: =IFERROR(FH69/FG69-1,"") | FI71: =IFERROR(FI69/FH69-1,"") | FJ71: =IFERROR(FJ69/FI69-1,"") | FL71: =IFERROR(FL69/FJ69-1,"") | FM71: =IFERROR(FM69/FL69-1,"") | FN71: =IFERROR(FN69/FM69-1,"") | FO71: =IFERROR(FO69/FN69-1,"") | FQ71: =IFERROR(FQ69/FO69-1,"") | FR71: =IFERROR(FR69/FQ69-1,"") | FS71: =IFERROR(FS69/FR69-1,"") | FT71: =IFERROR(FT69/FS69-1,"") | FV71: =IFERROR(FV69/FT69-1,"") | FW71: =IFERROR(FW69/FV69-1,"") | FX71: =IFERROR(FX69/FW69-1,"") | FY71: =IFERROR(FY69/FX69-1,"") | GA71: =IFERROR(GA69/FY69-1,"") | GB71: =IFERROR(GB69/GA69-1,"") | GC71: =IFERROR(GC69/GB69-1,"") | GD71: =IFERROR(GD69/GC69-1,"") | GF71: =IFERROR(GF69/GD69-1,"") | GG71: =IFERROR(GG69/GF69-1,"") | GH71: =IFERROR(GH69/GG69-1,"") | GI71: =IFERROR(GI69/GH69-1,"")
B72: % of Company1738 | DG72: =DG69/DG$64 | DI72: =DI69/DI$64 | DJ72: =DJ69/DJ$64 | DK72: =DK69/DK$64 | DL72: =DL69/DL$64 | DM72: =DM69/DM$64 | DN72: =DN69/DN$64 | DO72: =DO69/DO$64 | DP72: =DP69/DP$64 | ... GJ72: =GJ69/GJ$64
B74: Windows and OEM | CY74: =Company1738!CY143 | CZ74: =Company1738!CZ143 | DA74: =Company1738!DA143 | DB74: =Company1738!DB143 | DC74: =Company1738!DC143 | DD74: =Company1738!DD143 | DE74: =Company1738!DE143 | DF74: =Company1738!DF143 | ... GJ74: =Company1738!GJ143
B75: % yoy | CY75: =IFERROR(CY74/CT74-1,"") | CZ75: =IFERROR(CZ74/CU74-1,"") | DA75: =IFERROR(DA74/CV74-1,"") | DB75: =IFERROR(DB74/CW74-1,"") | DC75: =IFERROR(DC74/CX74-1,"") | DD75: =IFERROR(DD74/CY74-1,"") | DE75: =IFERROR(DE74/CZ74-1,"") | DF75: =IFERROR(DF74/DA74-1,"") | ... GJ75: =IFERROR(GJ74/GE74-1,"")
B76: % qoq | CY76: =IFERROR(CY74/CW74-1,"") | CZ76: =IFERROR(CZ74/CY74-1,"") | DA76: =IFERROR(DA74/CZ74-1,"") | DB76: =IFERROR(DB74/DA74-1,"") | DD76: =IFERROR(DD74/DB74-1,"") | DE76: =IFERROR(DE74/DD74-1,"") | DF76: =IFERROR(DF74/DE74-1,"") | DG76: =IFERROR(DG74/DF74-1,"") | DI76: =IFERROR(DI74/DG74-1,"") | DJ76: =IFERROR(DJ74/DI74-1,"") | DK76: =IFERROR(DK74/DJ74-1,"") | DL76: =IFERROR(DL74/DK74-1,"") | DN76: =IFERROR(DN74/DL74-1,"") | DO76: =IFERROR(DO74/DN74-1,"") | DP76: =IFERROR(DP74/DO74-1,"") | DQ76: =IFERROR(DQ74/DP74-1,"") | DS76: =IFERROR(DS74/DQ74-1,"") | DT76: =IFERROR(DT74/DS74-1,"") | DU76: =IFERROR(DU74/DT74-1,"") | DV76: =IFERROR(DV74/DU74-1,"") | DX76: =IFERROR(DX74/DV74-1,"") | DY76: =IFERROR(DY74/DX74-1,"") | DZ76: =IFERROR(DZ74/DY74-1,"") | EA76: =IFERROR(EA74/DZ74-1,"") | EC76: =IFERROR(EC74/EA74-1,"") | ED76: =IFERROR(ED74/EC74-1,"") | EE76: =IFERROR(EE74/ED74-1,"") | EF76: =IFERROR(EF74/EE74-1,"") | EH76: =IFERROR(EH74/EF74-1,"") | EI76: =IFERROR(EI74/EH74-1,"") | EJ76: =IFERROR(EJ74/EI74-1,"") | EK76: =IFERROR(EK74/EJ74-1,"") | EM76: =IFERROR(EM74/EK74-1,"") | EN76: =IFERROR(EN74/EM74-1,"") | EO76: =IFERROR(EO74/EN74-1,"") | EP76: =IFERROR(EP74/EO74-1,"") | ER76: =IFERROR(ER74/EP74-1,"") | ES76: =IFERROR(ES74/ER74-1,"") | ET76: =IFERROR(ET74/ES74-1,"") | EU76: =IFERROR(EU74/ET74-1,"") | EW76: =IFERROR(EW74/EU74-1,"") | EX76: =IFERROR(EX74/EW74-1,"") | EY76: =IFERROR(EY74/EX74-1,"") | EZ76: =IFERROR(EZ74/EY74-1,"") | FB76: =IFERROR(FB74/EZ74-1,"") | FC76: =IFERROR(FC74/FB74-1,"") | FD76: =IFERROR(FD74/FC74-1,"") | FE76: =IFERROR(FE74/FD74-1,"") | FG76: =IFERROR(FG74/FE74-1,"") | FH76: =IFERROR(FH74/FG74-1,"") | FI76: =IFERROR(FI74/FH74-1,"") | FJ76: =IFERROR(FJ74/FI74-1,"") | FL76: =IFERROR(FL74/FJ74-1,"") | FM76: =IFERROR(FM74/FL74-1,"") | FN76: =IFERROR(FN74/FM74-1,"") | FO76: =IFERROR(FO74/FN74-1,"") | FQ76: =IFERROR(FQ74/FO74-1,"") | FR76: =IFERROR(FR74/FQ74-1,"") | FS76: =IFERROR(FS74/FR74-1,"") | FT76: =IFERROR(FT74/FS74-1,"") | FV76: =IFERROR(FV74/FT74-1,"") | FW76: =IFERROR(FW74/FV74-1,"") | FX76: =IFERROR(FX74/FW74-1,"") | FY76: =IFERROR(FY74/FX74-1,"") | GA76: =IFERROR(GA74/FY74-1,"") | GB76: =IFERROR(GB74/GA74-1,"") | GC76: =IFERROR(GC74/GB74-1,"") | GD76: =IFERROR(GD74/GC74-1,"") | GF76: =IFERROR(GF74/GD74-1,"") | GG76: =IFERROR(GG74/GF74-1,"") | GH76: =IFERROR(GH74/GG74-1,"") | GI76: =IFERROR(GI74/GH74-1,"")
B77: % of Company1738 | CY77: =CY74/CY$64 | CZ77: =CZ74/CZ$64 | DA77: =DA74/DA$64 | DB77: =DB74/DB$64 | DC77: =DC74/DC$64 | DD77: =DD74/DD$64 | DE77: =DE74/DE$64 | DF77: =DF74/DF$64 | ... GJ77: =GJ74/GJ$64
B79: Total Windows | DM79: =Company1738!DM126 | DN79: =Company1738!DN126 | DO79: =Company1738!DO126 | DP79: =Company1738!DP126 | DQ79: =Company1738!DQ126 | DR79: =Company1738!DR126 | DS79: =Company1738!DS126 | DT79: =Company1738!DT126 | ... GJ79: =Company1738!GJ126
B80: % yoy | CT80: =IFERROR(CT79/CO79-1,"") | CU80: =IFERROR(CU79/CP79-1,"") | CV80: =IFERROR(CV79/CQ79-1,"") | CW80: =IFERROR(CW79/CR79-1,"") | CX80: =IFERROR(CX79/CS79-1,"") | CY80: =IFERROR(CY79/CT79-1,"") | CZ80: =IFERROR(CZ79/CU79-1,"") | DA80: =IFERROR(DA79/CV79-1,"") | ... GJ80: =IFERROR(GJ79/GE79-1,"")
B81: % qoq | CT81: =IFERROR(CT79/CR79-1,"") | CU81: =IFERROR(CU79/CT79-1,"") | CV81: =IFERROR(CV79/CU79-1,"") | CW81: =IFERROR(CW79/CV79-1,"") | CY81: =IFERROR(CY79/CW79-1,"") | CZ81: =IFERROR(CZ79/CY79-1,"") | DA81: =IFERROR(DA79/CZ79-1,"") | DB81: =IFERROR(DB79/DA79-1,"") | DD81: =IFERROR(DD79/DB79-1,"") | DE81: =IFERROR(DE79/DD79-1,"") | DF81: =IFERROR(DF79/DE79-1,"") | DG81: =IFERROR(DG79/DF79-1,"") | DI81: =IFERROR(DI79/DG79-1,"") | DJ81: =IFERROR(DJ79/DI79-1,"") | DK81: =IFERROR(DK79/DJ79-1,"") | DL81: =IFERROR(DL79/DK79-1,"") | DN81: =IFERROR(DN79/DL79-1,"") | DO81: =IFERROR(DO79/DN79-1,"") | DP81: =IFERROR(DP79/DO79-1,"") | DQ81: =IFERROR(DQ79/DP79-1,"") | DS81: =IFERROR(DS79/DQ79-1,"") | DT81: =IFERROR(DT79/DS79-1,"") | DU81: =IFERROR(DU79/DT79-1,"") | DV81: =IFERROR(DV79/DU79-1,"") | DX81: =IFERROR(DX79/DV79-1,"") | DY81: =IFERROR(DY79/DX79-1,"") | DZ81: =IFERROR(DZ79/DY79-1,"") | EA81: =IFERROR(EA79/DZ79-1,"") | EC81: =IFERROR(EC79/EA79-1,"") | ED81: =IFERROR(ED79/EC79-1,"") | EE81: =IFERROR(EE79/ED79-1,"") | EF81: =IFERROR(EF79/EE79-1,"") | EH81: =IFERROR(EH79/EF79-1,"") | EI81: =IFERROR(EI79/EH79-1,"") | EJ81: =IFERROR(EJ79/EI79-1,"") | EK81: =IFERROR(EK79/EJ79-1,"") | EM81: =IFERROR(EM79/EK79-1,"") | EN81: =IFERROR(EN79/EM79-1,"") | EO81: =IFERROR(EO79/EN79-1,"") | EP81: =IFERROR(EP79/EO79-1,"") | ER81: =IFERROR(ER79/EP79-1,"") | ES81: =IFERROR(ES79/ER79-1,"") | ET81: =IFERROR(ET79/ES79-1,"") | EU81: =IFERROR(EU79/ET79-1,"") | EW81: =IFERROR(EW79/EU79-1,"") | EX81: =IFERROR(EX79/EW79-1,"") | EY81: =IFERROR(EY79/EX79-1,"") | EZ81: =IFERROR(EZ79/EY79-1,"") | FB81: =IFERROR(FB79/EZ79-1,"") | FC81: =IFERROR(FC79/FB79-1,"") | FD81: =IFERROR(FD79/FC79-1,"") | FE81: =IFERROR(FE79/FD79-1,"") | FG81: =IFERROR(FG79/FE79-1,"") | FH81: =IFERROR(FH79/FG79-1,"") | FI81: =IFERROR(FI79/FH79-1,"") | FJ81: =IFERROR(FJ79/FI79-1,"") | FL81: =IFERROR(FL79/FJ79-1,"") | FM81: =IFERROR(FM79/FL79-1,"") | FN81: =IFERROR(FN79/FM79-1,"") | FO81: =IFERROR(FO79/FN79-1,"") | FQ81: =IFERROR(FQ79/FO79-1,"") | FR81: =IFERROR(FR79/FQ79-1,"") | FS81: =IFERROR(FS79/FR79-1,"") | FT81: =IFERROR(FT79/FS79-1,"") | FV81: =IFERROR(FV79/FT79-1,"") | FW81: =IFERROR(FW79/FV79-1,"") | FX81: =IFERROR(FX79/FW79-1,"") | FY81: =IFERROR(FY79/FX79-1,"") | GA81: =IFERROR(GA79/FY79-1,"") | GB81: =IFERROR(GB79/GA79-1,"") | GC81: =IFERROR(GC79/GB79-1,"") | GD81: =IFERROR(GD79/GC79-1,"") | GF81: =IFERROR(GF79/GD79-1,"") | GG81: =IFERROR(GG79/GF79-1,"") | GH81: =IFERROR(GH79/GG79-1,"") | GI81: =IFERROR(GI79/GH79-1,"")
B82: % of Company1738 | DM82: =DM79/DM$64 | DN82: =DN79/DN$64 | DO82: =DO79/DO$64 | DP82: =DP79/DP$64 | DQ82: =DQ79/DQ$64 | DR82: =DR79/DR$64 | DS82: =DS79/DS$64 | DT82: =DT79/DT$64 | ... GJ82: =GJ79/GJ$64
B84: Search and Advertising | ER84: =Company1738!ER221 | ES84: =Company1738!ES221 | ET84: =Company1738!ET221 | EU84: =Company1738!EU221 | EV84: =Company1738!EV221 | EW84: =Company1738!EW221 | EX84: =Company1738!EX221 | EY84: =Company1738!EY221 | ... GJ84: =Company1738!GJ221
B85: % yoy | CT85: =IFERROR(CT84/CO84-1,"") | CU85: =IFERROR(CU84/CP84-1,"") | CV85: =IFERROR(CV84/CQ84-1,"") | CW85: =IFERROR(CW84/CR84-1,"") | CX85: =IFERROR(CX84/CS84-1,"") | CY85: =IFERROR(CY84/CT84-1,"") | CZ85: =IFERROR(CZ84/CU84-1,"") | DA85: =IFERROR(DA84/CV84-1,"") | ... DL85: =IFERROR(DL84/DG84-1,"") | ER85: =IFERROR(ER84/EM84-1,"") | ES85: =IFERROR(ES84/EN84-1,"") | ET85: =IFERROR(ET84/EO84-1,"") | EU85: =IFERROR(EU84/EP84-1,"") | EV85: =IFERROR(EV84/EQ84-1,"") | EW85: =IFERROR(EW84/ER84-1,"") | EX85: =IFERROR(EX84/ES84-1,"") | EY85: =IFERROR(EY84/ET84-1,"") | ... GJ85: =IFERROR(GJ84/GE84-1,"")
B86: % qoq | CT86: =IFERROR(CT84/CR84-1,"") | CU86: =IFERROR(CU84/CT84-1,"") | CV86: =IFERROR(CV84/CU84-1,"") | CW86: =IFERROR(CW84/CV84-1,"") | CY86: =IFERROR(CY84/CW84-1,"") | CZ86: =IFERROR(CZ84/CY84-1,"") | DA86: =IFERROR(DA84/CZ84-1,"") | DB86: =IFERROR(DB84/DA84-1,"") | DD86: =IFERROR(DD84/DB84-1,"") | DE86: =IFERROR(DE84/DD84-1,"") | DF86: =IFERROR(DF84/DE84-1,"") | DG86: =IFERROR(DG84/DF84-1,"") | DI86: =IFERROR(DI84/DG84-1,"") | DJ86: =IFERROR(DJ84/DI84-1,"") | DK86: =IFERROR(DK84/DJ84-1,"") | DL86: =IFERROR(DL84/DK84-1,"") | ER86: =IFERROR(ER84/EP84-1,"") | ES86: =IFERROR(ES84/ER84-1,"") | ET86: =IFERROR(ET84/ES84-1,"") | EU86: =IFERROR(EU84/ET84-1,"") | EW86: =IFERROR(EW84/EU84-1,"") | EX86: =IFERROR(EX84/EW84-1,"") | EY86: =IFERROR(EY84/EX84-1,"") | EZ86: =IFERROR(EZ84/EY84-1,"") | FB86: =IFERROR(FB84/EZ84-1,"") | FC86: =IFERROR(FC84/FB84-1,"") | FD86: =IFERROR(FD84/FC84-1,"") | FE86: =IFERROR(FE84/FD84-1,"") | FG86: =IFERROR(FG84/FE84-1,"") | FH86: =IFERROR(FH84/FG84-1,"") | FI86: =IFERROR(FI84/FH84-1,"") | FJ86: =IFERROR(FJ84/FI84-1,"") | FL86: =IFERROR(FL84/FJ84-1,"") | FM86: =IFERROR(FM84/FL84-1,"") | FN86: =IFERROR(FN84/FM84-1,"") | FO86: =IFERROR(FO84/FN84-1,"") | FQ86: =IFERROR(FQ84/FO84-1,"") | FR86: =IFERROR(FR84/FQ84-1,"") | FS86: =IFERROR(FS84/FR84-1,"") | FT86: =IFERROR(FT84/FS84-1,"") | FV86: =IFERROR(FV84/FT84-1,"") | FW86: =IFERROR(FW84/FV84-1,"") | FX86: =IFERROR(FX84/FW84-1,"") | FY86: =IFERROR(FY84/FX84-1,"") | GA86: =IFERROR(GA84/FY84-1,"") | GB86: =IFERROR(GB84/GA84-1,"") | GC86: =IFERROR(GC84/GB84-1,"") | GD86: =IFERROR(GD84/GC84-1,"") | GF86: =IFERROR(GF84/GD84-1,"") | GG86: =IFERROR(GG84/GF84-1,"") | GH86: =IFERROR(GH84/GG84-1,"") | GI86: =IFERROR(GI84/GH84-1,"")
B87: % of Company1738 | ER87: =ER84/ER$64 | ES87: =ES84/ES$64 | ET87: =ET84/ET$64 | EU87: =EU84/EU$64 | EV87: =EV84/EV$64 | EW87: =EW84/EW$64 | EX87: =EX84/EX$64 | EY87: =EY84/EY$64 | ... GJ87: =GJ84/GJ$64

Sheet Leading Indicators
B2: Microsoft, Inc.
B3: Fiscal Year Ends Jun. 30
B4: ($ millions, except per share amounts) | ER4: Resegmenting
C6: =Dates!C3 | H6: =Dates!H3 | M6: =Dates!M3 | R6: =Dates!R3 | W6: =Dates!W3 | AB6: =Dates!AB3 | AG6: =Dates!AG3 | AL6: =Dates!AL3 | AQ6: =Dates!AQ3 | AV6: =Dates!AV3 | BA6: =Dates!BA3 | BF6: =Dates!BF3 | BK6: =Dates!BK3 | BP6: =Dates!BP3 | BU6: =Dates!BU3 | BZ6: =Dates!BZ3 | CE6: =Dates!CE3 | CJ6: =Dates!CJ3 | CO6: =Dates!CO3 | CT6: =Dates!CT3 | CY6: =Dates!CY3 | DD6: =Dates!DD3 | DI6: =Dates!DI3 | DN6: =Dates!DN3 | DS6: =Dates!DS3 | DX6: =Dates!DX3 | EC6: =Dates!EC3 | EH6: =Dates!EH3 | EM6: =Dates!EM3 | ER6: =Dates!ER3 | EW6: =Dates!EW3 | FB6: =Dates!FB3 | FG6: =Dates!FG3 | FL6: =Dates!FL3 | FQ6: =Dates!FQ3 | FV6: =Dates!FV3 | GA6: =Dates!GA3 | GF6: =Dates!GF3
C7: =Dates!C4 | D7: =Dates!D4 | E7: =Dates!E4 | F7: =Dates!F4 | G7: =Dates!G4 | H7: =Dates!H4 | I7: =Dates!I4 | J7: =Dates!J4 | ... GJ7: =Dates!GJ4
C8: =Dates!C5 | D8: =Dates!D5 | E8: =Dates!E5 | F8: =Dates!F5 | G8: =Dates!G5 | H8: =Dates!H5 | I8: =Dates!I5 | J8: =Dates!J5 | ... GJ8: =Dates!GJ5
B10: Inputs
B12: PBP Revenue | CY12: =IFERROR(PBP!CY50,"") | CZ12: =IFERROR(PBP!CZ50,"") | DA12: =IFERROR(PBP!DA50,"") | DB12: =IFERROR(PBP!DB50,"") | DC12: =IFERROR(PBP!DC50,"") | DD12: =IFERROR(PBP!DD50,"") | DE12: =IFERROR(PBP!DE50,"") | DF12: =IFERROR(PBP!DF50,"") | ... EQ12: =IFERROR(PBP!EQ50,"") | ER12: =PBP!ER10 | ES12: =PBP!ES10 | ET12: =PBP!ET10 | EU12: =PBP!EU10 | EV12: =PBP!EV10 | EW12: =PBP!EW10 | EX12: =PBP!EX10 | EY12: =PBP!EY10 | ... GJ12: =PBP!GJ10
B13: IC Revenue | CY13: =IFERROR(IC!CY50,"") | CZ13: =IFERROR(IC!CZ50,"") | DA13: =IFERROR(IC!DA50,"") | DB13: =IFERROR(IC!DB50,"") | DC13: =IFERROR(IC!DC50,"") | DD13: =IFERROR(IC!DD50,"") | DE13: =IFERROR(IC!DE50,"") | DF13: =IFERROR(IC!DF50,"") | ... EQ13: =IFERROR(IC!EQ50,"") | ER13: =IC!ER10 | ES13: =IC!ES10 | ET13: =IC!ET10 | EU13: =IC!EU10 | EV13: =IC!EV10 | EW13: =IC!EW10 | EX13: =IC!EX10 | EY13: =IC!EY10 | ... GJ13: =IC!GJ10
B14: Company1738 Revenue | CY14: =IFERROR(Company1738!CY50,"") | CZ14: =IFERROR(Company1738!CZ50,"") | DA14: =IFERROR(Company1738!DA50,"") | DB14: =IFERROR(Company1738!DB50,"") | DC14: =IFERROR(Company1738!DC50,"") | DD14: =IFERROR(Company1738!DD50,"") | DE14: =IFERROR(Company1738!DE50,"") | DF14: =IFERROR(Company1738!DF50,"") | ... EQ14: =IFERROR(Company1738!EQ50,"") | ER14: =Company1738!ER10 | ES14: =Company1738!ES10 | ET14: =Company1738!ET10 | EU14: =Company1738!EU10 | EV14: =Company1738!EV10 | EW14: =Company1738!EW10 | EX14: =Company1738!EX10 | EY14: =Company1738!EY10 | ... GJ14: =Company1738!GJ10
A15: TREV | B15: Total Revenue | CY15: =SUM(CY12:CY14) | CZ15: =SUM(CZ12:CZ14) | DA15: =SUM(DA12:DA14) | DB15: =SUM(DB12:DB14) | DC15: =SUM(DC12:DC14) | DD15: =SUM(DD12:DD14) | DE15: =SUM(DE12:DE14) | DF15: =SUM(DF12:DF14) | ... GJ15: =SUM(GJ12:GJ14)
B17: Microsoft Cloud Revenue | DG17: ='Ticker0024 Cloud'!DG10 | DH17: ='Ticker0024 Cloud'!DH10 | DI17: ='Ticker0024 Cloud'!DI10 | DJ17: ='Ticker0024 Cloud'!DJ10 | DK17: ='Ticker0024 Cloud'!DK10 | DL17: ='Ticker0024 Cloud'!DL10 | DM17: ='Ticker0024 Cloud'!DM10 | DN17: ='Ticker0024 Cloud'!DN10 | ... GJ17: ='Ticker0024 Cloud'!GJ10
B18: % of Total Revenue | DG18: =IFERROR(DG17/DG15,"") | DI18: =IFERROR(DI17/DI15,"") | DJ18: =IFERROR(DJ17/DJ15,"") | DK18: =IFERROR(DK17/DK15,"") | DL18: =IFERROR(DL17/DL15,"") | DM18: =IFERROR(DM17/DM15,"") | DN18: =IFERROR(DN17/DN15,"") | DO18: =IFERROR(DO17/DO15,"") | DP18: =IFERROR(DP17/DP15,"") | ... GJ18: =IFERROR(GJ17/GJ15,"")
B19: Microsoft Cloud NTM Revenue | DF19: =DG17+DI17+DJ17+DK17 | DG19: =DI17+DJ17+DK17+DL17 | DH19: =DM17 | DI19: =DJ17+DK17+DL17+DN17 | DJ19: =DK17+DL17+DN17+DO17 | DK19: =DL17+DN17+DO17+DP17 | DL19: =DN17+DO17+DP17+DQ17 | DM19: =DR17 | DN19: =DO17+DP17+DQ17+DS17 | DO19: =DP17+DQ17+DS17+DT17 | DP19: =DQ17+DS17+DT17+DU17 | DQ19: =DS17+DT17+DU17+DV17 | DR19: =DW17 | DS19: =DT17+DU17+DV17+DX17 | DT19: =DU17+DV17+DX17+DY17 | DU19: =DV17+DX17+DY17+DZ17 | DV19: =DX17+DY17+DZ17+EA17 | DW19: =EB17 | DX19: =DY17+DZ17+EA17+EC17 | DY19: =DZ17+EA17+EC17+ED17 | DZ19: =EA17+EC17+ED17+EE17 | EA19: =EC17+ED17+EE17+EF17 | EB19: =EG17 | EC19: =ED17+EE17+EF17+EH17 | ED19: =EE17+EF17+EH17+EI17 | EE19: =EF17+EH17+EI17+EJ17 | EF19: =EH17+EI17+EJ17+EK17 | EG19: =EL17 | EH19: =EI17+EJ17+EK17+EM17 | EI19: =EJ17+EK17+EM17+EN17 | EJ19: =EK17+EM17+EN17+EO17 | EK19: =EM17+EN17+EO17+EP17 | EL19: =EQ17 | EM19: =EN17+EO17+EP17+ER17 | EN19: =EO17+EP17+ER17+ES17 | EO19: =EP17+ER17+ES17+ET17 | EP19: =ER17+ES17+ET17+EU17 | EQ19: =EV17 | ER19: =ES17+ET17+EU17+EW17 | ES19: =ET17+EU17+EW17+EX17 | ET19: =EU17+EW17+EX17+EY17 | EU19: =EW17+EX17+EY17+EZ17 | EV19: =FA17 | EW19: =EX17+EY17+EZ17+FB17 | EX19: =EY17+EZ17+FA17+FC17 | EY19: =EZ17+FA17+FB17+FD17 | EZ19: =FB17+FC17+FD17+FE17 | FA19: =FF17 | FB19: =FC17+FD17+FE17+FG17 | FC19: =FD17+FE17+FG17+FH17 | FD19: =FE17+FG17+FH17+FI17 | FE19: =FG17+FH17+FI17+FJ17 | FF19: =FK17 | FG19: =FH17+FI17+FJ17+FL17 | FH19: =FI17+FJ17+FL17+FM17 | FI19: =FJ17+FL17+FM17+FN17 | FJ19: =FL17+FM17+FN17+FO17 | FK19: =FP17 | FL19: =FM17+FN17+FO17+FQ17 | FM19: =FN17+FO17+FQ17+FR17 | FN19: =FO17+FQ17+FR17+FS17 | FO19: =FQ17+FR17+FS17+FT17 | FP19: =FU17 | FQ19: =FR17+FS17+FT17+FV17 | FR19: =FS17+FT17+FV17+FW17 | FS19: =FT17+FV17+FW17+FX17 | FT19: =FV17+FW17+FX17+FY17 | FU19: =FZ17 | FV19: =FW17+FX17+FY17+GA17 | FW19: =FX17+FY17+GA17+GB17 | FX19: =FY17+GA17+GB17+GC17 | FY19: =GA17+GB17+GC17+GD17 | FZ19: =GE17
B21: PBP NTM Revenue | CY21: =CZ12+DA12+DB12+DD12 | CZ21: =DA12+DB12+DD12+DE12 | DA21: =DB12+DD12+DE12+DF12 | DB21: =DD12+DE12+DF12+DG12 | DC21: =DH12 | DD21: =DE12+DF12+DG12+DI12 | DE21: =DF12+DG12+DI12+DJ12 | DF21: =DG12+DI12+DJ12+DK12 | DG21: =DI12+DJ12+DK12+DL12 | DH21: =DM12 | DI21: =DJ12+DK12+DL12+DN12 | DJ21: =DK12+DL12+DN12+DO12 | DK21: =DL12+DN12+DO12+DP12 | DL21: =DN12+DO12+DP12+DQ12 | DM21: =DR12 | DN21: =DO12+DP12+DQ12+DS12 | DO21: =DP12+DQ12+DS12+DT12 | DP21: =DQ12+DS12+DT12+DU12 | DQ21: =DS12+DT12+DU12+DV12 | DR21: =DW12 | DS21: =DT12+DU12+DV12+DX12 | DT21: =DU12+DV12+DX12+DY12 | DU21: =DV12+DX12+DY12+DZ12 | DV21: =DX12+DY12+DZ12+EA12 | DW21: =EB12 | DX21: =DY12+DZ12+EA12+EC12 | DY21: =DZ12+EA12+EC12+ED12 | DZ21: =EA12+EC12+ED12+EE12 | EA21: =EC12+ED12+EE12+EF12 | EB21: =EG12 | EC21: =ED12+EE12+EF12+EH12 | ED21: =EE12+EF12+EH12+EI12 | EE21: =EF12+EH12+EI12+EJ12 | EF21: =EH12+EI12+EJ12+EK12 | EG21: =EL12 | EH21: =EI12+EJ12+EK12+EM12 | EI21: =EJ12+EK12+EM12+EN12 | EJ21: =EK12+EM12+EN12+EO12 | EK21: =EM12+EN12+EO12+EP12 | EL21: =EQ12 | EM21: =EN12+EO12+EP12+ER12 | EN21: =EO12+EP12+ER12+ES12 | EO21: =EP12+ER12+ES12+ET12 | EP21: =ER12+ES12+ET12+EU12 | EQ21: =EV12 | ER21: =ES12+ET12+EU12+EW12 | ES21: =ET12+EU12+EW12+EX12 | ET21: =EU12+EW12+EX12+EY12 | EU21: =EW12+EX12+EY12+EZ12 | EV21: =FA12 | EW21: =EX12+EY12+EZ12+FB12 | EX21: =EY12+EZ12+FA12+FC12 | EY21: =EZ12+FA12+FB12+FD12 | EZ21: =FB12+FC12+FD12+FE12 | FA21: =FF12 | FB21: =FC12+FD12+FE12+FG12 | FC21: =FD12+FE12+FG12+FH12 | FD21: =FE12+FG12+FH12+FI12 | FE21: =FG12+FH12+FI12+FJ12 | FF21: =FK12 | FG21: =FH12+FI12+FJ12+FL12 | FH21: =FI12+FJ12+FL12+FM12 | FI21: =FJ12+FL12+FM12+FN12 | FJ21: =FL12+FM12+FN12+FO12 | FK21: =FP12 | FL21: =FM12+FN12+FO12+FQ12 | FM21: =FN12+FO12+FQ12+FR12 | FN21: =FO12+FQ12+FR12+FS12 | FO21: =FQ12+FR12+FS12+FT12 | FP21: =FU12 | FQ21: =FR12+FS12+FT12+FV12 | FR21: =FS12+FT12+FV12+FW12 | FS21: =FT12+FV12+FW12+FX12 | FT21: =FV12+FW12+FX12+FY12 | FU21: =FZ12 | FV21: =FW12+FX12+FY12+GA12 | FW21: =FX12+FY12+GA12+GB12 | FX21: =FY12+GA12+GB12+GC12 | FY21: =GA12+GB12+GC12+GD12 | FZ21: =GE12
B22: IC NTM Revenue | CY22: =CZ13+DA13+DB13+DD13 | CZ22: =DA13+DB13+DD13+DE13 | DA22: =DB13+DD13+DE13+DF13 | DB22: =DD13+DE13+DF13+DG13 | DC22: =DH13 | DD22: =DE13+DF13+DG13+DI13 | DE22: =DF13+DG13+DI13+DJ13 | DF22: =DG13+DI13+DJ13+DK13 | DG22: =DI13+DJ13+DK13+DL13 | DH22: =DM13 | DI22: =DJ13+DK13+DL13+DN13 | DJ22: =DK13+DL13+DN13+DO13 | DK22: =DL13+DN13+DO13+DP13 | DL22: =DN13+DO13+DP13+DQ13 | DM22: =DR13 | DN22: =DO13+DP13+DQ13+DS13 | DO22: =DP13+DQ13+DS13+DT13 | DP22: =DQ13+DS13+DT13+DU13 | DQ22: =DS13+DT13+DU13+DV13 | DR22: =DW13 | DS22: =DT13+DU13+DV13+DX13 | DT22: =DU13+DV13+DX13+DY13 | DU22: =DV13+DX13+DY13+DZ13 | DV22: =DX13+DY13+DZ13+EA13 | DW22: =EB13 | DX22: =DY13+DZ13+EA13+EC13 | DY22: =DZ13+EA13+EC13+ED13 | DZ22: =EA13+EC13+ED13+EE13 | EA22: =EC13+ED13+EE13+EF13 | EB22: =EG13 | EC22: =ED13+EE13+EF13+EH13 | ED22: =EE13+EF13+EH13+EI13 | EE22: =EF13+EH13+EI13+EJ13 | EF22: =EH13+EI13+EJ13+EK13 | EG22: =EL13 | EH22: =EI13+EJ13+EK13+EM13 | EI22: =EJ13+EK13+EM13+EN13 | EJ22: =EK13+EM13+EN13+EO13 | EK22: =EM13+EN13+EO13+EP13 | EL22: =EQ13 | EM22: =EN13+EO13+EP13+ER13 | EN22: =EO13+EP13+ER13+ES13 | EO22: =EP13+ER13+ES13+ET13 | EP22: =ER13+ES13+ET13+EU13 | EQ22: =EV13 | ER22: =ES13+ET13+EU13+EW13 | ES22: =ET13+EU13+EW13+EX13 | ET22: =EU13+EW13+EX13+EY13 | EU22: =EW13+EX13+EY13+EZ13 | EV22: =FA13 | EW22: =EX13+EY13+EZ13+FB13 | EX22: =EY13+EZ13+FA13+FC13 | EY22: =EZ13+FA13+FB13+FD13 | EZ22: =FB13+FC13+FD13+FE13 | FA22: =FF13 | FB22: =FC13+FD13+FE13+FG13 | FC22: =FD13+FE13+FG13+FH13 | FD22: =FE13+FG13+FH13+FI13 | FE22: =FG13+FH13+FI13+FJ13 | FF22: =FK13 | FG22: =FH13+FI13+FJ13+FL13 | FH22: =FI13+FJ13+FL13+FM13 | FI22: =FJ13+FL13+FM13+FN13 | FJ22: =FL13+FM13+FN13+FO13 | FK22: =FP13 | FL22: =FM13+FN13+FO13+FQ13 | FM22: =FN13+FO13+FQ13+FR13 | FN22: =FO13+FQ13+FR13+FS13 | FO22: =FQ13+FR13+FS13+FT13 | FP22: =FU13 | FQ22: =FR13+FS13+FT13+FV13 | FR22: =FS13+FT13+FV13+FW13 | FS22: =FT13+FV13+FW13+FX13 | FT22: =FV13+FW13+FX13+FY13 | FU22: =FZ13 | FV22: =FW13+FX13+FY13+GA13 | FW22: =FX13+FY13+GA13+GB13 | FX22: =FY13+GA13+GB13+GC13 | FY22: =GA13+GB13+GC13+GD13 | FZ22: =GE13
B23: Company1738 NTM Revenue | CY23: =CZ14+DA14+DB14+DD14 | CZ23: =DA14+DB14+DD14+DE14 | DA23: =DB14+DD14+DE14+DF14 | DB23: =DD14+DE14+DF14+DG14 | DC23: =DH14 | DD23: =DE14+DF14+DG14+DI14 | DE23: =DF14+DG14+DI14+DJ14 | DF23: =DG14+DI14+DJ14+DK14 | DG23: =DI14+DJ14+DK14+DL14 | DH23: =DM14 | DI23: =DJ14+DK14+DL14+DN14 | DJ23: =DK14+DL14+DN14+DO14 | DK23: =DL14+DN14+DO14+DP14 | DL23: =DN14+DO14+DP14+DQ14 | DM23: =DR14 | DN23: =DO14+DP14+DQ14+DS14 | DO23: =DP14+DQ14+DS14+DT14 | DP23: =DQ14+DS14+DT14+DU14 | DQ23: =DS14+DT14+DU14+DV14 | DR23: =DW14 | DS23: =DT14+DU14+DV14+DX14 | DT23: =DU14+DV14+DX14+DY14 | DU23: =DV14+DX14+DY14+DZ14 | DV23: =DX14+DY14+DZ14+EA14 | DW23: =EB14 | DX23: =DY14+DZ14+EA14+EC14 | DY23: =DZ14+EA14+EC14+ED14 | DZ23: =EA14+EC14+ED14+EE14 | EA23: =EC14+ED14+EE14+EF14 | EB23: =EG14 | EC23: =ED14+EE14+EF14+EH14 | ED23: =EE14+EF14+EH14+EI14 | EE23: =EF14+EH14+EI14+EJ14 | EF23: =EH14+EI14+EJ14+EK14 | EG23: =EL14 | EH23: =EI14+EJ14+EK14+EM14 | EI23: =EJ14+EK14+EM14+EN14 | EJ23: =EK14+EM14+EN14+EO14 | EK23: =EM14+EN14+EO14+EP14 | EL23: =EQ14 | EM23: =EN14+EO14+EP14+ER14 | EN23: =EO14+EP14+ER14+ES14 | EO23: =EP14+ER14+ES14+ET14 | EP23: =ER14+ES14+ET14+EU14 | EQ23: =EV14 | ER23: =ES14+ET14+EU14+EW14 | ES23: =ET14+EU14+EW14+EX14 | ET23: =EU14+EW14+EX14+EY14 | EU23: =EW14+EX14+EY14+EZ14 | EV23: =FA14 | EW23: =EX14+EY14+EZ14+FB14 | EX23: =EY14+EZ14+FA14+FC14 | EY23: =EZ14+FA14+FB14+FD14 | EZ23: =FB14+FC14+FD14+FE14 | FA23: =FF14 | FB23: =FC14+FD14+FE14+FG14 | FC23: =FD14+FE14+FG14+FH14 | FD23: =FE14+FG14+FH14+FI14 | FE23: =FG14+FH14+FI14+FJ14 | FF23: =FK14 | FG23: =FH14+FI14+FJ14+FL14 | FH23: =FI14+FJ14+FL14+FM14 | FI23: =FJ14+FL14+FM14+FN14 | FJ23: =FL14+FM14+FN14+FO14 | FK23: =FP14 | FL23: =FM14+FN14+FO14+FQ14 | FM23: =FN14+FO14+FQ14+FR14 | FN23: =FO14+FQ14+FR14+FS14 | FO23: =FQ14+FR14+FS14+FT14 | FP23: =FU14 | FQ23: =FR14+FS14+FT14+FV14 | FR23: =FS14+FT14+FV14+FW14 | FS23: =FT14+FV14+FW14+FX14 | FT23: =FV14+FW14+FX14+FY14 | FU23: =FZ14 | FV23: =FW14+FX14+FY14+GA14 | FW23: =FX14+FY14+GA14+GB14 | FX23: =FY14+GA14+GB14+GC14 | FY23: =GA14+GB14+GC14+GD14 | FZ23: =GE14
B24: NTM Revenue | CY24: =CZ15+DA15+DB15+DD15 | CZ24: =DA15+DB15+DD15+DE15 | DA24: =DB15+DD15+DE15+DF15 | DB24: =DD15+DE15+DF15+DG15 | DC24: =DH15 | DD24: =DE15+DF15+DG15+DI15 | DE24: =DF15+DG15+DI15+DJ15 | DF24: =DG15+DI15+DJ15+DK15 | DG24: =DI15+DJ15+DK15+DL15 | DH24: =DM15 | DI24: =DJ15+DK15+DL15+DN15 | DJ24: =DK15+DL15+DN15+DO15 | DK24: =DL15+DN15+DO15+DP15 | DL24: =DN15+DO15+DP15+DQ15 | DM24: =DR15 | DN24: =DO15+DP15+DQ15+DS15 | DO24: =DP15+DQ15+DS15+DT15 | DP24: =DQ15+DS15+DT15+DU15 | DQ24: =DS15+DT15+DU15+DV15 | DR24: =DW15 | DS24: =DT15+DU15+DV15+DX15 | DT24: =DU15+DV15+DX15+DY15 | DU24: =DV15+DX15+DY15+DZ15 | DV24: =DX15+DY15+DZ15+EA15 | DW24: =EB15 | DX24: =DY15+DZ15+EA15+EC15 | DY24: =DZ15+EA15+EC15+ED15 | DZ24: =EA15+EC15+ED15+EE15 | EA24: =EC15+ED15+EE15+EF15 | EB24: =EG15 | EC24: =ED15+EE15+EF15+EH15 | ED24: =EE15+EF15+EH15+EI15 | EE24: =EF15+EH15+EI15+EJ15 | EF24: =EH15+EI15+EJ15+EK15 | EG24: =EL15 | EH24: =EI15+EJ15+EK15+EM15 | EI24: =EJ15+EK15+EM15+EN15 | EJ24: =EK15+EM15+EN15+EO15 | EK24: =EM15+EN15+EO15+EP15 | EL24: =EQ15 | EM24: =EN15+EO15+EP15+ER15 | EN24: =EO15+EP15+ER15+ES15 | EO24: =EP15+ER15+ES15+ET15 | EP24: =ER15+ES15+ET15+EU15 | EQ24: =EV15 | ER24: =ES15+ET15+EU15+EW15 | ES24: =ET15+EU15+EW15+EX15 | ET24: =EU15+EW15+EX15+EY15 | EU24: =EW15+EX15+EY15+EZ15 | EV24: =FA15 | EW24: =EX15+EY15+EZ15+FB15 | EX24: =EY15+EZ15+FB15+FC15 | EY24: =EZ15+FB15+FC15+FD15 | EZ24: =FB15+FC15+FD15+FE15 | FA24: =FF15 | FB24: =FC15+FD15+FE15+FG15 | FC24: =FD15+FE15+FG15+FH15 | FD24: =FE15+FG15+FH15+FI15 | FE24: =FG15+FH15+FI15+FJ15 | FF24: =FK15 | FG24: =FH15+FI15+FJ15+FL15 | FH24: =FI15+FJ15+FL15+FM15 | FI24: =FJ15+FL15+FM15+FN15 | FJ24: =FL15+FM15+FN15+FO15 | FK24: =FP15 | FL24: =FM15+FN15+FO15+FQ15 | FM24: =FN15+FO15+FQ15+FR15 | FN24: =FO15+FQ15+FR15+FS15 | FO24: =FQ15+FR15+FS15+FT15 | FP24: =FU15 | FQ24: =FR15+FS15+FT15+FV15 | FR24: =FS15+FT15+FV15+FW15 | FS24: =FT15+FV15+FW15+FX15 | FT24: =FV15+FW15+FX15+FY15 | FU24: =FZ15 | FV24: =FW15+FX15+FY15+GA15 | FW24: =FX15+FY15+GA15+GB15 | FX24: =FY15+GA15+GB15+GC15 | FY24: =GA15+GB15+GC15+GD15 | FZ24: =GE15
B26: PBP Unearned Revenue | DD26: =PBP!DD80 | DE26: =PBP!DE80 | DF26: =PBP!DF80 | DG26: =PBP!DG80 | DH26: =PBP!DH80 | DI26: =PBP!DI80 | DJ26: =PBP!DJ80 | DK26: =PBP!DK80 | ... ET26: =PBP!ET80 | EU26: =PBP!EU45 | EV26: =PBP!EV45 | EW26: =PBP!EW45 | EX26: =PBP!EX45 | EY26: =PBP!EY45 | EZ26: =PBP!EZ45 | FA26: =PBP!FA80
B27: IC Unearned Revenue | DD27: =IC!DD80 | DE27: =IC!DE80 | DF27: =IC!DF80 | DG27: =IC!DG80 | DH27: =IC!DH80 | DI27: =IC!DI80 | DJ27: =IC!DJ80 | DK27: =IC!DK80 | ... ET27: =IC!ET80 | EU27: =IC!EU45 | EV27: =IC!EV45 | EW27: =IC!EW45 | EX27: =IC!EX45 | EY27: =IC!EY45 | EZ27: =IC!EZ45 | FA27: =IC!FA80
B28: Company1738 Unearned Revenue | DD28: =Company1738!DD80 | DE28: =Company1738!DE80 | DF28: =Company1738!DF80 | DG28: =Company1738!DG80 | DH28: =Company1738!DH80 | DI28: =Company1738!DI80 | DJ28: =Company1738!DJ80 | DK28: =Company1738!DK80 | ... ET28: =Company1738!ET80 | EU28: =Company1738!EU45 | EV28: =Company1738!EV45 | EW28: =Company1738!EW45 | EX28: =Company1738!EX45 | EY28: =Company1738!EY45 | EZ28: =Company1738!EZ45 | FA28: =Company1738!FA80
A29: COGS | B29: Total Unearned Revenue | DD29: =SUM(DD26:DD28) | DE29: =SUM(DE26:DE28) | DF29: =SUM(DF26:DF28) | DG29: =SUM(DG26:DG28) | DH29: =SUM(DH26:DH28) | DI29: =SUM(DI26:DI28) | DJ29: =SUM(DJ26:DJ28) | DK29: =SUM(DK26:DK28) | ... FA29: =SUM(FA26:FA28)
B31: ST Unearned Revenue (B/S) | H31: =BS!H33 | I31: =BS!I33 | J31: =BS!J33 | K31: =BS!K33 | L31: =BS!L33 | M31: =BS!M33 | N31: =BS!N33 | O31: =BS!O33 | ... GJ31: =BS!GJ33
B32: LT Unearned Revenue (B/S) | H32: =BS!H40 | I32: =BS!I40 | J32: =BS!J40 | K32: =BS!K40 | L32: =BS!L40 | M32: =BS!M40 | N32: =BS!N40 | O32: =BS!O40 | ... GJ32: =BS!GJ40
B34: Change in Deferred Revenue (C/F) | DI34: =CF!DI27 | DJ34: =CF!DJ27 | DK34: =CF!DK27 | DL34: =CF!DL27 | DM34: =CF!DM27 | DN34: =CF!DN27 | DO34: =CF!DO27 | DP34: =CF!DP27 | ... GJ34: =CF!GJ27
B35: Total Billings | DI35: =DI34+DI15 | DJ35: =DJ34+DJ15 | DK35: =DK34+DK15 | DL35: =DL34+DL15 | DM35: =DM34+DM15 | DN35: =DN34+DN15 | DO35: =DO34+DO15 | DP35: =DP34+DP15 | ... GJ35: =GJ34+GJ15
A37: GP | B37: Commerical Total RPO | DS37: ='Ticker0024 Cloud'!DS28 | DT37: ='Ticker0024 Cloud'!DT28 | DU37: ='Ticker0024 Cloud'!DU28 | DV37: ='Ticker0024 Cloud'!DV28 | DW37: ='Ticker0024 Cloud'!DW28 | DX37: ='Ticker0024 Cloud'!DX28 | DY37: ='Ticker0024 Cloud'!DY28 | DZ37: ='Ticker0024 Cloud'!DZ28 | ... FA37: ='Ticker0024 Cloud'!FA28
B38: % yoy | DX38: =DX37/DS37-1 | DY38: =DY37/DT37-1 | DZ38: =DZ37/DU37-1 | EA38: =EA37/DV37-1 | EB38: =EB37/DW37-1 | EC38: =EC37/DX37-1 | ED38: =ED37/DY37-1 | EE38: =EE37/DZ37-1 | ... FA38: =FA37/EV37-1
B39: % qoq | DT39: =DT37/DS37-1 | DU39: =DU37/DT37-1 | DV39: =DV37/DU37-1 | DX39: =DX37/DV37-1 | DY39: =DY37/DX37-1 | DZ39: =DZ37/DY37-1 | EA39: =EA37/DZ37-1 | EC39: =EC37/EA37-1 | ED39: =ED37/EC37-1 | EE39: =EE37/ED37-1 | EF39: =EF37/EE37-1 | EH39: =EH37/EF37-1 | EI39: =EI37/EH37-1 | EJ39: =EJ37/EI37-1 | EK39: =EK37/EJ37-1 | EM39: =EM37/EK37-1 | EN39: =EN37/EM37-1 | EO39: =EO37/EN37-1 | EP39: =EP37/EO37-1 | ER39: =ER37/EP37-1 | ES39: =ES37/ER37-1 | ET39: =ET37/ES37-1 | EU39: =EU37/ET37-1 | EW39: =EW37/EU37-1 | EX39: =EX37/EW37-1 | EY39: =EY37/EX37-1 | EZ39: =EZ37/EY37-1
B40: Commercial cRPO | DS40: ='Ticker0024 Cloud'!DS35 | DT40: ='Ticker0024 Cloud'!DT35 | DU40: ='Ticker0024 Cloud'!DU35 | DV40: ='Ticker0024 Cloud'!DV35 | DW40: ='Ticker0024 Cloud'!DW35 | DX40: ='Ticker0024 Cloud'!DX35 | DY40: ='Ticker0024 Cloud'!DY35 | DZ40: ='Ticker0024 Cloud'!DZ35 | ... FA40: ='Ticker0024 Cloud'!FA35
B42: Total RPO | DN42: 59000 | DO42: 61000 | DP42: 61000 | DQ42: 73000 | DR42: =DQ42 | DS42: 71000 | DT42: 72000 | DU42: 75000 | DV42: 91000 | DW42: =DV42 | DX42: 89000 | DY42: 93000 | DZ42: 93000 | EA42: 111000 | EB42: =EA42 | EC42: 111000 | ED42: 117000 | EE42: 121000 | EF42: 146000 | EG42: =EF42 | EH42: 142000 | EI42: 152000 | EJ42: 160000 | EK42: 193000 | EL42: =EK42 | EM42: 183000 | EN42: 193000 | EO42: 201000 | EP42: 229000 | EQ42: =EP42 | ER42: 216000 | ES42: 229000 | ET42: 242000 | EU42: 275000 | EV42: =EU42 | EW42: 266000 | EX42: 304000 | EY42: 321000 | EZ42: 375000 | FA42: =EZ42
B43: % yoy | DS43: =DS42/DN42-1 | DT43: =DT42/DO42-1 | DU43: =DU42/DP42-1 | DV43: =DV42/DQ42-1 | DW43: =DW42/DR42-1 | DX43: =DX42/DS42-1 | DY43: =DY42/DT42-1 | DZ43: =DZ42/DU42-1 | ... FA43: =FA42/EV42-1
B44: % qoq | DO44: =DO42/DN42-1 | DP44: =DP42/DO42-1 | DQ44: =DQ42/DP42-1 | DS44: =DS42/DQ42-1 | DT44: =DT42/DS42-1 | DU44: =DU42/DT42-1 | DV44: =DV42/DU42-1 | DX44: =DX42/DV42-1 | DY44: =DY42/DX42-1 | DZ44: =DZ42/DY42-1 | EA44: =EA42/DZ42-1 | EC44: =EC42/EA42-1 | ED44: =ED42/EC42-1 | EE44: =EE42/ED42-1 | EF44: =EF42/EE42-1 | EH44: =EH42/EF42-1 | EI44: =EI42/EH42-1 | EJ44: =EJ42/EI42-1 | EK44: =EK42/EJ42-1 | EM44: =EM42/EK42-1 | EN44: =EN42/EM42-1 | EO44: =EO42/EN42-1 | EP44: =EP42/EO42-1 | ER44: =ER42/EP42-1 | ES44: =ES42/ER42-1 | ET44: =ET42/ES42-1 | EU44: =EU42/ET42-1 | EW44: =EW42/EU42-1 | EX44: =EX42/EW42-1 | EY44: =EY42/EX42-1 | EZ44: =EZ42/EY42-1
B45: % Recognized in the NTM | DN45: 0.6 | DO45: 0.6 | DP45: 0.6 | DQ45: 0.6 | DR45: =DQ45 | DS45: 0.6 | DT45: 0.6 | DU45: 0.55 | DV45: 0.5 | DW45: =DV45 | DX45: 0.5 | DY45: 0.5 | DZ45: 0.5 | EA45: 0.5 | EB45: =EA45 | EC45: 0.5 | ED45: 0.5 | EE45: 0.5 | EF45: 0.5 | EG45: =EF45 | EH45: 0.5 | EI45: 0.45 | EJ45: 0.5 | EK45: 0.45 | EL45: =EK45 | EM45: 0.45 | EN45: 0.45 | EO45: 0.45 | EP45: 0.45 | EQ45: =EP45 | ER45: 0.45 | ES45: 0.45 | ET45: 0.45 | EU45: 0.45 | EV45: =EU45 | EW45: 0.45 | EX45: 0.4 | EY45: 0.4 | EZ45: 0.4
B46: Total cRPO | DN46: =DN42*DN45 | DO46: =DO42*DO45 | DP46: =DP42*DP45 | DQ46: =DQ42*DQ45 | DR46: =DR42*DR45 | DS46: =DS42*DS45 | DT46: =DT42*DT45 | DU46: =DU42*DU45 | ... FA46: =FA42*FA45
A48: EPSB | B48: Unearned Revenue
A49: EPSBYY | B49: PBP Unearned Revenue | DD49: =DD26 | DE49: =DE26 | DF49: =DF26 | DG49: =DG26 | DH49: =DH26 | DI49: =DI26 | DJ49: =DJ26 | DK49: =DK26 | ... FA49: =FA26
B50: % yoy | DI50: =DI49/DD49-1 | DJ50: =DJ49/DE49-1 | DK50: =DK49/DF49-1 | DL50: =DL49/DG49-1 | DM50: =DM49/DH49-1 | DN50: =DN49/DI49-1 | DO50: =DO49/DJ49-1 | DP50: =DP49/DK49-1 | ... FA50: =FA49/EV49-1
B51: % qoq | DE51: =DE49/DD49-1 | DF51: =DF49/DE49-1 | DG51: =DG49/DF49-1 | DI51: =DI49/DG49-1 | DJ51: =DJ49/DI49-1 | DK51: =DK49/DJ49-1 | DL51: =DL49/DK49-1 | DN51: =DN49/DL49-1 | DO51: =DO49/DN49-1 | DP51: =DP49/DO49-1 | DQ51: =DQ49/DP49-1 | DS51: =DS49/DQ49-1 | DT51: =DT49/DS49-1 | DU51: =DU49/DT49-1 | DV51: =DV49/DU49-1 | DX51: =DX49/DV49-1 | DY51: =DY49/DX49-1 | DZ51: =DZ49/DY49-1 | EA51: =EA49/DZ49-1 | EC51: =EC49/EA49-1 | ED51: =ED49/EC49-1 | EE51: =EE49/ED49-1 | EF51: =EF49/EE49-1 | EH51: =EH49/EF49-1 | EI51: =EI49/EH49-1 | EJ51: =EJ49/EI49-1 | EK51: =EK49/EJ49-1 | EM51: =EM49/EK49-1 | EN51: =EN49/EM49-1 | EO51: =EO49/EN49-1 | EP51: =EP49/EO49-1 | ER51: =ER49/EP49-1 | ES51: =ES49/ER49-1 | ET51: =ET49/ES49-1 | EU51: =EU49/ET49-1 | EW51: =EW49/EU49-1 | EX51: =EX49/EW49-1 | EY51: =EY49/EX49-1 | EZ51: =EZ49/EY49-1
B52: % Total Unearned Revenue | DD52: =DD49/DD$29 | DE52: =DE49/DE$29 | DF52: =DF49/DF$29 | DG52: =DG49/DG$29 | DH52: =DH49/DH$29 | DI52: =DI49/DI$29 | DJ52: =DJ49/DJ$29 | DK52: =DK49/DK$29 | ... FA52: =FA49/FA$29
B53: % of PBP NTM Revenue | DD53: =DD49/DD21 | DE53: =DE49/DE21 | DF53: =DF49/DF21 | DG53: =DG49/DG21 | DH53: =DH49/DH21 | DI53: =DI49/DI21 | DJ53: =DJ49/DJ21 | DK53: =DK49/DK21 | ... FA53: =FA49/FA21
B54: % of PBP Total Revenue | DD54: =DD49/DD15 | DE54: =DE49/DE15 | DF54: =DF49/DF15 | DG54: =DG49/DG15 | DH54: =DH49/DH15 | DI54: =DI49/DI15 | DJ54: =DJ49/DJ15 | DK54: =DK49/DK15 | ... FA54: =FA49/FA15
A55: EPS
A56: EPSBYY | B56: IC Unearned Revenue | DD56: =DD27 | DE56: =DE27 | DF56: =DF27 | DG56: =DG27 | DH56: =DH27 | DI56: =DI27 | DJ56: =DJ27 | DK56: =DK27 | ... FA56: =FA27
B57: % yoy | DI57: =DI56/DD56-1 | DJ57: =DJ56/DE56-1 | DK57: =DK56/DF56-1 | DL57: =DL56/DG56-1 | DM57: =DM56/DH56-1 | DN57: =DN56/DI56-1 | DO57: =DO56/DJ56-1 | DP57: =DP56/DK56-1 | ... FA57: =FA56/EV56-1
B58: % qoq | DE58: =DE56/DD56-1 | DF58: =DF56/DE56-1 | DG58: =DG56/DF56-1 | DI58: =DI56/DG56-1 | DJ58: =DJ56/DI56-1 | DK58: =DK56/DJ56-1 | DL58: =DL56/DK56-1 | DN58: =DN56/DL56-1 | DO58: =DO56/DN56-1 | DP58: =DP56/DO56-1 | DQ58: =DQ56/DP56-1 | DS58: =DS56/DQ56-1 | DT58: =DT56/DS56-1 | DU58: =DU56/DT56-1 | DV58: =DV56/DU56-1 | DX58: =DX56/DV56-1 | DY58: =DY56/DX56-1 | DZ58: =DZ56/DY56-1 | EA58: =EA56/DZ56-1 | EC58: =EC56/EA56-1 | ED58: =ED56/EC56-1 | EE58: =EE56/ED56-1 | EF58: =EF56/EE56-1 | EH58: =EH56/EF56-1 | EI58: =EI56/EH56-1 | EJ58: =EJ56/EI56-1 | EK58: =EK56/EJ56-1 | EM58: =EM56/EK56-1 | EN58: =EN56/EM56-1 | EO58: =EO56/EN56-1 | EP58: =EP56/EO56-1 | ER58: =ER56/EP56-1 | ES58: =ES56/ER56-1 | ET58: =ET56/ES56-1 | EU58: =EU56/ET56-1 | EW58: =EW56/EU56-1 | EX58: =EX56/EW56-1 | EY58: =EY56/EX56-1 | EZ58: =EZ56/EY56-1
B59: % Total Unearned Revenue | DD59: =DD56/DD$29 | DE59: =DE56/DE$29 | DF59: =DF56/DF$29 | DG59: =DG56/DG$29 | DH59: =DH56/DH$29 | DI59: =DI56/DI$29 | DJ59: =DJ56/DJ$29 | DK59: =DK56/DK$29 | ... FA59: =FA56/FA$29
B60: % of IC NTM Revenue | DD60: =DD56/DD22 | DE60: =DE56/DE22 | DF60: =DF56/DF22 | DG60: =DG56/DG22 | DH60: =DH56/DH22 | DI60: =DI56/DI22 | DJ60: =DJ56/DJ22 | DK60: =DK56/DK22 | ... FA60: =FA56/FA22
B61: % of IC Total Revenue | DD61: =DD56/DD13 | DE61: =DE56/DE13 | DF61: =DF56/DF13 | DG61: =DG56/DG13 | DH61: =DH56/DH13 | DI61: =DI56/DI13 | DJ61: =DJ56/DJ13 | DK61: =DK56/DK13 | ... FA61: =FA56/FA13
A62: EPSYY
A63: EPSBYY | B63: Company1738 Unearned Revenue | DD63: =DD28 | DE63: =DE28 | DF63: =DF28 | DG63: =DG28 | DH63: =DH28 | DI63: =DI28 | DJ63: =DJ28 | DK63: =DK28 | ... FA63: =FA28
B64: % yoy | DI64: =DI63/DD63-1 | DJ64: =DJ63/DE63-1 | DK64: =DK63/DF63-1 | DL64: =DL63/DG63-1 | DM64: =DM63/DH63-1 | DN64: =DN63/DI63-1 | DO64: =DO63/DJ63-1 | DP64: =DP63/DK63-1 | ... FA64: =FA63/EV63-1
B65: % qoq | DE65: =DE63/DD63-1 | DF65: =DF63/DE63-1 | DG65: =DG63/DF63-1 | DI65: =DI63/DG63-1 | DJ65: =DJ63/DI63-1 | DK65: =DK63/DJ63-1 | DL65: =DL63/DK63-1 | DN65: =DN63/DL63-1 | DO65: =DO63/DN63-1 | DP65: =DP63/DO63-1 | DQ65: =DQ63/DP63-1 | DS65: =DS63/DQ63-1 | DT65: =DT63/DS63-1 | DU65: =DU63/DT63-1 | DV65: =DV63/DU63-1 | DX65: =DX63/DV63-1 | DY65: =DY63/DX63-1 | DZ65: =DZ63/DY63-1 | EA65: =EA63/DZ63-1 | EC65: =EC63/EA63-1 | ED65: =ED63/EC63-1 | EE65: =EE63/ED63-1 | EF65: =EF63/EE63-1 | EH65: =EH63/EF63-1 | EI65: =EI63/EH63-1 | EJ65: =EJ63/EI63-1 | EK65: =EK63/EJ63-1 | EM65: =EM63/EK63-1 | EN65: =EN63/EM63-1 | EO65: =EO63/EN63-1 | EP65: =EP63/EO63-1 | ER65: =ER63/EP63-1 | ES65: =ES63/ER63-1 | ET65: =ET63/ES63-1 | EU65: =EU63/ET63-1 | EW65: =EW63/EU63-1 | EX65: =EX63/EW63-1 | EY65: =EY63/EX63-1 | EZ65: =EZ63/EY63-1
B66: % Total Unearned Revenue | DD66: =DD63/DD$29 | DE66: =DE63/DE$29 | DF66: =DF63/DF$29 | DG66: =DG63/DG$29 | DH66: =DH63/DH$29 | DI66: =DI63/DI$29 | DJ66: =DJ63/DJ$29 | DK66: =DK63/DK$29 | ... FA66: =FA63/FA$29
B67: % of Company1738 NTM Revenue | DD67: =DD63/DD23 | DE67: =DE63/DE23 | DF67: =DF63/DF23 | DG67: =DG63/DG23 | DH67: =DH63/DH23 | DI67: =DI63/DI23 | DJ67: =DJ63/DJ23 | DK67: =DK63/DK23 | ... FA67: =FA63/FA23
B68: % of Company1738 Total Revenue | DD68: =DD63/DD14 | DE68: =DE63/DE14 | DF68: =DF63/DF14 | DG68: =DG63/DG14 | DH68: =DH63/DH14 | DI68: =DI63/DI14 | DJ68: =DJ63/DJ14 | DK68: =DK63/DK14 | ... FA68: =FA63/FA14
A70: EPSBYY | B70: Total Unearned Revenue | DD70: =DD29 | DE70: =DE29 | DF70: =DF29 | DG70: =DG29 | DH70: =DH29 | DI70: =DI29 | DJ70: =DJ29 | DK70: =DK29 | ... FA70: =FA29
B71: % yoy | DI71: =DI70/DD70-1 | DJ71: =DJ70/DE70-1 | DK71: =DK70/DF70-1 | DL71: =DL70/DG70-1 | DM71: =DM70/DH70-1 | DN71: =DN70/DI70-1 | DO71: =DO70/DJ70-1 | DP71: =DP70/DK70-1 | ... FA71: =FA70/EV70-1
B72: % qoq | DE72: =DE70/DD70-1 | DF72: =DF70/DE70-1 | DG72: =DG70/DF70-1 | DI72: =DI70/DG70-1 | DJ72: =DJ70/DI70-1 | DK72: =DK70/DJ70-1 | DL72: =DL70/DK70-1 | DN72: =DN70/DL70-1 | DO72: =DO70/DN70-1 | DP72: =DP70/DO70-1 | DQ72: =DQ70/DP70-1 | DS72: =DS70/DQ70-1 | DT72: =DT70/DS70-1 | DU72: =DU70/DT70-1 | DV72: =DV70/DU70-1 | DX72: =DX70/DV70-1 | DY72: =DY70/DX70-1 | DZ72: =DZ70/DY70-1 | EA72: =EA70/DZ70-1 | EC72: =EC70/EA70-1 | ED72: =ED70/EC70-1 | EE72: =EE70/ED70-1 | EF72: =EF70/EE70-1 | EH72: =EH70/EF70-1 | EI72: =EI70/EH70-1 | EJ72: =EJ70/EI70-1 | EK72: =EK70/EJ70-1 | EM72: =EM70/EK70-1 | EN72: =EN70/EM70-1 | EO72: =EO70/EN70-1 | EP72: =EP70/EO70-1 | ER72: =ER70/EP70-1 | ES72: =ES70/ER70-1 | ET72: =ET70/ES70-1 | EU72: =EU70/ET70-1 | EW72: =EW70/EU70-1 | EX72: =EX70/EW70-1 | EY72: =EY70/EX70-1 | EZ72: =EZ70/EY70-1
B73: % of NTM Revenue | DD73: =DD70/DD24 | DE73: =DE70/DE24 | DF73: =DF70/DF24 | DG73: =DG70/DG24 | DH73: =DH70/DH24 | DI73: =DI70/DI24 | DJ73: =DJ70/DJ24 | DK73: =DK70/DK24 | ... FA73: =FA70/FA24
B74: % of Total Revenue | DD74: =DD70/DD15 | DE74: =DE70/DE15 | DF74: =DF70/DF15 | DG74: =DG70/DG15 | DH74: =DH70/DH15 | DI74: =DI70/DI15 | DJ74: =DJ70/DJ15 | DK74: =DK70/DK15 | ... FA74: =FA70/FA15
B76: RPO
B77: Total RPO | DN77: =DN42 | DO77: =DO42 | DP77: =DP42 | DQ77: =DQ42 | DR77: =DR42 | DS77: =DS42 | DT77: =DT42 | DU77: =DU42 | ... FA77: =FA42
B78: % yoy | DS78: =DS77/DN77-1 | DT78: =DT77/DO77-1 | DU78: =DU77/DP77-1 | DV78: =DV77/DQ77-1 | DW78: =DW77/DR77-1 | DX78: =DX77/DS77-1 | DY78: =DY77/DT77-1 | DZ78: =DZ77/DU77-1 | ... FA78: =FA77/EV77-1
B79: % qoq | DO79: =DO77/DN77-1 | DP79: =DP77/DO77-1 | DQ79: =DQ77/DP77-1 | DS79: =DS77/DQ77-1 | DT79: =DT77/DS77-1 | DU79: =DU77/DT77-1 | DV79: =DV77/DU77-1 | DX79: =DX77/DV77-1 | DY79: =DY77/DX77-1 | DZ79: =DZ77/DY77-1 | EA79: =EA77/DZ77-1 | EC79: =EC77/EA77-1 | ED79: =ED77/EC77-1 | EE79: =EE77/ED77-1 | EF79: =EF77/EE77-1 | EH79: =EH77/EF77-1 | EI79: =EI77/EH77-1 | EJ79: =EJ77/EI77-1 | EK79: =EK77/EJ77-1 | EM79: =EM77/EK77-1 | EN79: =EN77/EM77-1 | EO79: =EO77/EN77-1 | EP79: =EP77/EO77-1 | ER79: =ER77/EP77-1 | ES79: =ES77/ER77-1 | ET79: =ET77/ES77-1 | EU79: =EU77/ET77-1 | EW79: =EW77/EU77-1 | EX79: =EX77/EW77-1 | EY79: =EY77/EX77-1 | EZ79: =EZ77/EY77-1
B80: Net New RPO (yoy) | DN80: =DN77-DI77 | DO80: =DO77-DJ77 | DP80: =DP77-DK77 | DQ80: =DQ77-DL77 | DR80: =DR77-DM77 | DS80: =DS77-DN77 | DT80: =DT77-DO77 | DU80: =DU77-DP77 | ... FA80: =FA77-EV77
B81: Net New RPO (qoq) | DN81: =DN77-DL77 | DO81: =DO77-DN77 | DP81: =DP77-DO77 | DQ81: =DQ77-DP77 | DS81: =DS77-DQ77 | DT81: =DT77-DS77 | DU81: =DU77-DT77 | DV81: =DV77-DU77 | DX81: =DX77-DV77 | DY81: =DY77-DX77 | DZ81: =DZ77-DY77 | EA81: =EA77-DZ77 | EC81: =EC77-EA77 | ED81: =ED77-EC77 | EE81: =EE77-ED77 | EF81: =EF77-EE77 | EH81: =EH77-EF77 | EI81: =EI77-EH77 | EJ81: =EJ77-EI77 | EK81: =EK77-EJ77 | EM81: =EM77-EK77 | EN81: =EN77-EM77 | EO81: =EO77-EN77 | EP81: =EP77-EO77 | ER81: =ER77-EP77 | ES81: =ES77-ER77 | ET81: =ET77-ES77 | EU81: =EU77-ET77 | EW81: =EW77-EU77 | EX81: =EX77-EW77 | EY81: =EY77-EX77 | EZ81: =EZ77-EY77
B83: Total cRPO | DN83: =DN46 | DO83: =DO46 | DP83: =DP46 | DQ83: =DQ46 | DR83: =DR46 | DS83: =DS46 | DT83: =DT46 | DU83: =DU46 | ... FA83: =FA46
B84: % yoy | DS84: =DS83/DN83-1 | DT84: =DT83/DO83-1 | DU84: =DU83/DP83-1 | DV84: =DV83/DQ83-1 | DW84: =DW83/DR83-1 | DX84: =DX83/DS83-1 | DY84: =DY83/DT83-1 | DZ84: =DZ83/DU83-1 | ... FA84: =FA83/EV83-1
B85: % qoq | DO85: =DO83/DN83-1 | DP85: =DP83/DO83-1 | DQ85: =DQ83/DP83-1 | DS85: =DS83/DQ83-1 | DT85: =DT83/DS83-1 | DU85: =DU83/DT83-1 | DV85: =DV83/DU83-1 | DX85: =DX83/DV83-1 | DY85: =DY83/DX83-1 | DZ85: =DZ83/DY83-1 | EA85: =EA83/DZ83-1 | EC85: =EC83/EA83-1 | ED85: =ED83/EC83-1 | EE85: =EE83/ED83-1 | EF85: =EF83/EE83-1 | EH85: =EH83/EF83-1 | EI85: =EI83/EH83-1 | EJ85: =EJ83/EI83-1 | EK85: =EK83/EJ83-1 | EM85: =EM83/EK83-1 | EN85: =EN83/EM83-1 | EO85: =EO83/EN83-1 | EP85: =EP83/EO83-1 | ER85: =ER83/EP83-1 | ES85: =ES83/ER83-1 | ET85: =ET83/ES83-1 | EU85: =EU83/ET83-1 | EW85: =EW83/EU83-1 | EX85: =EX83/EW83-1 | EY85: =EY83/EX83-1 | EZ85: =EZ83/EY83-1
B86: Net New cRPO (yoy) | DN86: =DN83-DI83 | DO86: =DO83-DJ83 | DP86: =DP83-DK83 | DQ86: =DQ83-DL83 | DR86: =DR83-DM83 | DS86: =DS83-DN83 | DT86: =DT83-DO83 | DU86: =DU83-DP83 | ... FA86: =FA83-EV83
B87: Net New cRPO (qoq) | DN87: =DN83-DL83 | DO87: =DO83-DN83 | DP87: =DP83-DO83 | DQ87: =DQ83-DP83 | DS87: =DS83-DQ83 | DT87: =DT83-DS83 | DU87: =DU83-DT83 | DV87: =DV83-DU83 | DX87: =DX83-DV83 | DY87: =DY83-DX83 | DZ87: =DZ83-DY83 | EA87: =EA83-DZ83 | EC87: =EC83-EA83 | ED87: =ED83-EC83 | EE87: =EE83-ED83 | EF87: =EF83-EE83 | EH87: =EH83-EF83 | EI87: =EI83-EH83 | EJ87: =EJ83-EI83 | EK87: =EK83-EJ83 | EM87: =EM83-EK83 | EN87: =EN83-EM83 | EO87: =EO83-EN83 | EP87: =EP83-EO83 | ER87: =ER83-EP83 | ES87: =ES83-ER83 | ET87: =ET83-ES83 | EU87: =EU83-ET83 | EW87: =EW83-EU83 | EX87: =EX83-EW83 | EY87: =EY83-EX83 | EZ87: =EZ83-EY83
B88: % of NTM Revenue | DN88: =DN83/DN24 | DO88: =DO83/DO24 | DP88: =DP83/DP24 | DQ88: =DQ83/DQ24 | DR88: =DR83/DR24 | DS88: =DS83/DS24 | DT88: =DT83/DT24 | DU88: =DU83/DU24 | ... FA88: =FA83/FA24
B89: % of Total RPO | DN89: =DN83/DN$77 | DO89: =DO83/DO$77 | DP89: =DP83/DP$77 | DQ89: =DQ83/DQ$77 | DR89: =DR83/DR$77 | DS89: =DS83/DS$77 | DT89: =DT83/DT$77 | DU89: =DU83/DU$77 | ... FA89: =FA83/FA$77
B91: Commercial RPO | DS91: =DS37 | DT91: =DT37 | DU91: =DU37 | DV91: =DV37 | DW91: =DW37 | DX91: =DX37 | DY91: =DY37 | DZ91: =DZ37 | ... FA91: =FA37
B92: % yoy | DX92: =DX91/DS91-1 | DY92: =DY91/DT91-1 | DZ92: =DZ91/DU91-1 | EA92: =EA91/DV91-1 | EB92: =EB91/DW91-1 | EC92: =EC91/DX91-1 | ED92: =ED91/DY91-1 | EE92: =EE91/DZ91-1 | ... FA92: =FA91/EV91-1
B93: % qoq | DT93: =DT91/DS91-1 | DU93: =DU91/DT91-1 | DV93: =DV91/DU91-1 | DX93: =DX91/DV91-1 | DY93: =DY91/DX91-1 | DZ93: =DZ91/DY91-1 | EA93: =EA91/DZ91-1 | EC93: =EC91/EA91-1 | ED93: =ED91/EC91-1 | EE93: =EE91/ED91-1 | EF93: =EF91/EE91-1 | EH93: =EH91/EF91-1 | EI93: =EI91/EH91-1 | EJ93: =EJ91/EI91-1 | EK93: =EK91/EJ91-1 | EM93: =EM91/EK91-1 | EN93: =EN91/EM91-1 | EO93: =EO91/EN91-1 | EP93: =EP91/EO91-1 | ER93: =ER91/EP91-1 | ES93: =ES91/ER91-1 | ET93: =ET91/ES91-1 | EU93: =EU91/ET91-1 | EW93: =EW91/EU91-1 | EX93: =EX91/EW91-1 | EY93: =EY91/EX91-1 | EZ93: =EZ91/EY91-1
B94: Net New RPO (yoy) | DS94: =DS91-DN91 | DT94: =DT91-DO91 | DU94: =DU91-DP91 | DV94: =DV91-DQ91 | DW94: =DW91-DR91 | DX94: =DX91-DS91 | DY94: =DY91-DT91 | DZ94: =DZ91-DU91 | ... FA94: =FA91-EV91
B95: Net New RPO (qoq) | DS95: =DS91-DQ91 | DT95: =DT91-DS91 | DU95: =DU91-DT91 | DV95: =DV91-DU91 | DX95: =DX91-DV91 | DY95: =DY91-DX91 | DZ95: =DZ91-DY91 | EA95: =EA91-DZ91 | EC95: =EC91-EA91 | ED95: =ED91-EC91 | EE95: =EE91-ED91 | EF95: =EF91-EE91 | EH95: =EH91-EF91 | EI95: =EI91-EH91 | EJ95: =EJ91-EI91 | EK95: =EK91-EJ91 | EM95: =EM91-EK91 | EN95: =EN91-EM91 | EO95: =EO91-EN91 | EP95: =EP91-EO91 | ER95: =ER91-EP91 | ES95: =ES91-ER91 | ET95: =ET91-ES91 | EU95: =EU91-ET91 | EW95: =EW91-EU91 | EX95: =EX91-EW91 | EY95: =EY91-EX91 | EZ95: =EZ91-EY91
B96: % of Total RPO | DS96: =DS91/DS77 | DT96: =DT91/DT77 | DU96: =DU91/DU77 | DV96: =DV91/DV77 | DW96: =DW91/DW77 | DX96: =DX91/DX77 | DY96: =DY91/DY77 | DZ96: =DZ91/DZ77 | ... FA96: =FA91/FA77
B98: Commercial cRPO (estimate) | DS98: =DS40 | DT98: =DT40 | DU98: =DU40 | DV98: =DV40 | DW98: =DW40 | DX98: =DX40 | DY98: =DY40 | DZ98: =DZ40 | ... FA98: =FA40
B99: % yoy | DX99: =DX98/DS98-1 | DY99: =DY98/DT98-1 | DZ99: =DZ98/DU98-1 | EA99: =EA98/DV98-1 | EB99: =EB98/DW98-1 | EC99: =EC98/DX98-1 | ED99: =ED98/DY98-1 | EE99: =EE98/DZ98-1 | ... FA99: =FA98/EV98-1
B100: % qoq | DT100: =DT98/DS98-1 | DU100: =DU98/DT98-1 | DV100: =DV98/DU98-1 | DX100: =DX98/DV98-1 | DY100: =DY98/DX98-1 | DZ100: =DZ98/DY98-1 | EA100: =EA98/DZ98-1 | EC100: =EC98/EA98-1 | ED100: =ED98/EC98-1 | EE100: =EE98/ED98-1 | EF100: =EF98/EE98-1 | EH100: =EH98/EF98-1 | EI100: =EI98/EH98-1 | EJ100: =EJ98/EI98-1 | EK100: =EK98/EJ98-1 | EM100: =EM98/EK98-1 | EN100: =EN98/EM98-1 | EO100: =EO98/EN98-1 | EP100: =EP98/EO98-1 | ER100: =ER98/EP98-1 | ES100: =ES98/ER98-1 | ET100: =ET98/ES98-1 | EU100: =EU98/ET98-1 | EW100: =EW98/EU98-1 | EX100: =EX98/EW98-1 | EY100: =EY98/EX98-1 | EZ100: =EZ98/EY98-1
B101: Net New cRPO (yoy) | DS101: =DS98-DN98 | DT101: =DT98-DO98 | DU101: =DU98-DP98 | DV101: =DV98-DQ98 | DW101: =DW98-DR98 | DX101: =DX98-DS98 | DY101: =DY98-DT98 | DZ101: =DZ98-DU98 | ... FA101: =FA98-EV98
B102: Net New cRPO (qoq) | DS102: =DS98-DQ98 | DT102: =DT98-DS98 | DU102: =DU98-DT98 | DV102: =DV98-DU98 | DX102: =DX98-DV98 | DY102: =DY98-DX98 | DZ102: =DZ98-DY98 | EA102: =EA98-DZ98 | EC102: =EC98-EA98 | ED102: =ED98-EC98 | EE102: =EE98-ED98 | EF102: =EF98-EE98 | EH102: =EH98-EF98 | EI102: =EI98-EH98 | EJ102: =EJ98-EI98 | EK102: =EK98-EJ98 | EM102: =EM98-EK98 | EN102: =EN98-EM98 | EO102: =EO98-EN98 | EP102: =EP98-EO98 | ER102: =ER98-EP98 | ES102: =ES98-ER98 | ET102: =ET98-ES98 | EU102: =EU98-ET98 | EW102: =EW98-EU98 | EX102: =EX98-EW98 | EY102: =EY98-EX98 | EZ102: =EZ98-EY98
B103: % of Microsoft Cloud NTM Revenue | DS103: =DS98/DS19 | DT103: =DT98/DT19 | DU103: =DU98/DU19 | DV103: =DV98/DV19 | DW103: =DW98/DW19 | DX103: =DX98/DX19 | DY103: =DY98/DY19 | DZ103: =DZ98/DZ19 | ... FA103: =FA98/FA19
B104: % of Total RPO | DS104: =DS98/DS$77 | DT104: =DT98/DT$77 | DU104: =DU98/DU$77 | DV104: =DV98/DV$77 | DW104: =DW98/DW$77 | DX104: =DX98/DX$77 | DY104: =DY98/DY$77 | DZ104: =DZ98/DZ$77 | ... FA104: =FA98/FA$77
B106: Miscellaneous
B107: Operations | DH107: 38000 | DM107: 39000 | DR107: 42000 | DW107: 47000 | EB107: 56000 | EG107: 67000 | EL107: 85000 | EQ107: 89000 | EV107: 86000 | FA107: 89000
B108: Research and Development | DH108: 37000 | DM108: 40000 | DR108: 42000 | DW108: 47000 | EB108: 55000 | EG108: 60000 | EL108: 73000 | EQ108: 72000 | EV108: 81000 | FA108: 80000
B109: Sales and Marketing | DH109: 29000 | DM109: 34000 | DR109: 36000 | DW109: 38000 | EB109: 40000 | EG109: 40000 | EL109: 47000 | EQ109: 45000 | EV109: 45000 | FA109: 44000
B110: General and Administration | DH110: 10000 | DM110: 11000 | DR110: 11000 | DW110: 12000 | EB110: 12000 | EG110: 14000 | EL110: 16000 | EQ110: 15000 | EV110: 16000 | FA110: 15000
B111: Employees | DH111: =SUM(DH107:DH110) | DM111: =SUM(DM107:DM110) | DR111: =SUM(DR107:DR110) | DW111: =SUM(DW107:DW110) | EB111: =SUM(EB107:EB110) | EG111: =SUM(EG107:EG110) | EL111: =SUM(EL107:EL110) | EQ111: =SUM(EQ107:EQ110) | EV111: =SUM(EV107:EV110) | FA111: =SUM(FA107:FA110)
B112: % yoy | DM112: =DM111/DH111-1 | DR112: =DR111/DM111-1 | DW112: =DW111/DR111-1 | EB112: =EB111/DW111-1 | EG112: =EG111/EB111-1 | EL112: =EL111/EG111-1 | EQ112: =EQ111/EL111-1 | ET112: -0.01 | EV112: =EV111/EQ111-1 | EX112: 0.02 | EY112: 0.02 | FA112: =FA111/EV111-1
B113: Revenue per Employee (mm) | DH113: =DH15/DH111 | DM113: =DM15/DM111 | DR113: =DR15/DR111 | DW113: =DW15/DW111 | EB113: =EB15/EB111 | EG113: =EG15/EG111 | EL113: =EL15/EL111 | EQ113: =EQ15/EQ111 | EV113: =IFERROR(EV15/EV111,"") | FA113: =IFERROR(FA15/FA111,"")
B115: United States Sales | DI115: 11215 | DJ115: 14115 | DK115: 12298 | DL115: =DM115-DK115-DJ115-DI115 | DM115: 51078 | DN115: 12527 | DO115: 15110 | DP115: 13457 | DQ115: =DR115-DP115-DO115-DN115 | DR115: 55926 | DS115: 14740 | DT115: 16787 | DU115: 15372 | DV115: =DW115-DU115-DT115-DS115 | DW115: 64199 | DX115: 17270 | DY115: 19149 | DZ115: 17428 | EA115: =EB115-DZ115-DY115-DX115 | EB115: 73160 | EC115: 19025 | ED115: 21836 | EE115: 20373 | EF115: =EG115-EE115-ED115-EC115 | EG115: 83953 | EH115: 22830 | EI115: 26463 | EJ115: 24771 | EK115: =EL115-EJ115-EI115-EH115 | EL115: 100218 | EM115: 25867 | EN115: 26976 | EO115: 26007 | EP115: =EQ115-EO115-EN115-EM115 | EQ115: 106744 | ER115: 28812 | ES115: 32295 | ET115: 31437 | EU115: =EV115-ET115-ES115-ER115 | EV115: 124704 | EW115: 33913 | EX115: 35537 | EY115: 36084 | EZ115: =FA115-EY115-EX115-EW115 | FA115: 230069
B116: % US Sales | DI116: =DI115/(DI115+DI117) | DJ116: =DJ115/(DJ115+DJ117) | DK116: =DK115/(DK115+DK117) | DL116: =DL115/(DL115+DL117) | DM116: =DM115/(DM115+DM117) | DN116: =DN115/(DN115+DN117) | DO116: =DO115/(DO115+DO117) | DP116: =DP115/(DP115+DP117) | ... FA116: =FA115/(FA115+FA117)
B117: Other Countries Sales | DI117: 10713 | DJ117: 11711 | DK117: 10914 | DL117: =DM117-DK117-DJ117-DI117 | DM117: 45493 | DN117: 12011 | DO117: 13808 | DP117: 13362 | DQ117: =DR117-DP117-DO117-DN117 | DR117: 54434 | DS117: 14344 | DT117: 15684 | DU117: 15199 | DV117: =DW117-DU117-DT117-DS117 | DW117: 61644 | DX117: 15785 | DY117: 17757 | DZ117: 17593 | EA117: =EB117-DZ117-DY117-DX117 | EB117: 69855 | EC117: 18129 | ED117: 21240 | EE117: 21333 | EF117: =EG117-EE117-ED117-EC117 | EG117: 84135 | EH117: 22487 | EI117: 25265 | EJ117: 24589 | EK117: =EL117-EJ117-EI117-EH117 | EL117: 98052 | EM117: 24255 | EN117: 25771 | EO117: 26850 | EP117: =EQ117-EO117-EN117-EM117 | EQ117: 105171 | ER117: 27705 | ES117: 29725 | ET117: 30421 | EU117: =EV117-ET117-ES117-ER117 | EV117: 120418 | EW117: 31672 | EX117: 34095 | EY117: 33982 | EZ117: =FA117-EY117-EX117-EW117 | FA117: 141833
B118: % Other Sales | DI118: =DI117/(DI117+DI115) | DJ118: =DJ117/(DJ117+DJ115) | DK118: =DK117/(DK117+DK115) | DL118: =DL117/(DL117+DL115) | DM118: =DM117/(DM117+DM115) | DN118: =DN117/(DN117+DN115) | DO118: =DO117/(DO117+DO115) | DP118: =DP117/(DP117+DP115) | ... FA118: =FA117/(FA117+FA115)
B119: Total Revenue | DI119: =DI115+DI117 | DJ119: =DJ115+DJ117 | DK119: =DK115+DK117 | DL119: =DL115+DL117 | DM119: =DM115+DM117 | DN119: =DN115+DN117 | DO119: =DO115+DO117 | DP119: =DP115+DP117 | ... FA119: =FA115+FA117
...

Sheet IS
B2: Microsoft, Inc.
B3: Fiscal Year Ends Jun. 30
B4: ($ millions, except per share amounts) | AI4: Company0935 Merchant Revenue Accounting Change - Restated | AS4: SFAS 123 Adoption - Restated
C6: =Dates!C3 | H6: =Dates!H3 | M6: =Dates!M3 | R6: =Dates!R3 | W6: =Dates!W3 | AB6: =Dates!AB3 | AG6: =Dates!AG3 | AL6: =Dates!AL3 | AQ6: =Dates!AQ3 | AV6: =Dates!AV3 | BA6: =Dates!BA3 | BF6: =Dates!BF3 | BK6: =Dates!BK3 | BP6: =Dates!BP3 | BU6: =Dates!BU3 | BZ6: =Dates!BZ3 | CE6: =Dates!CE3 | CJ6: =Dates!CJ3 | CO6: =Dates!CO3 | CT6: =Dates!CT3 | CY6: =Dates!CY3 | DD6: =Dates!DD3 | DI6: =Dates!DI3 | DN6: =Dates!DN3 | DS6: =Dates!DS3 | DX6: =Dates!DX3 | EC6: =Dates!EC3 | EH6: =Dates!EH3 | EM6: =Dates!EM3 | ER6: =Dates!ER3 | EW6: =Dates!EW3 | FB6: =Dates!FB3 | FG6: =Dates!FG3 | FL6: =Dates!FL3 | FQ6: =Dates!FQ3 | FV6: =Dates!FV3 | GA6: =Dates!GA3 | GF6: =Dates!GF3
C7: =Dates!C4 | D7: =Dates!D4 | E7: =Dates!E4 | F7: =Dates!F4 | G7: =Dates!G4 | H7: =Dates!H4 | I7: =Dates!I4 | J7: =Dates!J4 | ... GJ7: =Dates!GJ4
C8: =Dates!C5 | D8: =Dates!D5 | E8: =Dates!E5 | F8: =Dates!F5 | G8: =Dates!G5 | H8: =Dates!H5 | I8: =Dates!I5 | J8: =Dates!J5 | ... GJ8: =Dates!GJ5
B10: Product Revenue | DI10: 14968 | DJ10: 18273 | DK10: 14513 | DL10: 16057 | DM10: =SUM(DI10:DL10) | DN10: 14298 | DO10: 17926 | DP10: 15114 | DQ10: 17159 | DR10: =SUM(DN10:DQ10) | DS10: 17299 | DT10: 16219 | DU10: 15448 | DV10: 17103 | DW10: =SUM(DS10:DV10) | DX10: 15768 | DY10: 18255 | DZ10: 15871 | EA10: 18147 | EB10: =SUM(DX10:EA10) | EC10: 15803 | ED10: 19460 | EE10: 16873 | EF10: 18938 | EG10: =SUM(EC10:EF10) | EH10: 16631 | EI10: 20779 | EJ10: 17366 | EK10: 17956 | EL10: =SUM(EH10:EK10) | EM10: 15741 | EN10: 16517 | EO10: 15588 | EP10: 16853 | EQ10: =SUM(EM10:EP10) | ER10: 15535 | ES10: 18941 | ET10: 17080 | EU10: 13217 | EV10: =SUM(ER10:EU10) | EW10: 15272 | EX10: 16219 | EY10: 15319 | EZ10: 17136 | FA10: =SUM(EW10:EZ10)
B11: % yoy | H11: =IFERROR(H10/C10-1,"") | I11: =IFERROR(I10/D10-1,"") | J11: =IFERROR(J10/E10-1,"") | K11: =IFERROR(K10/F10-1,"") | L11: =IFERROR(L10/G10-1,"") | M11: =IFERROR(M10/H10-1,"") | N11: =IFERROR(N10/I10-1,"") | O11: =IFERROR(O10/J10-1,"") | ... DC11: =IFERROR(DC10/CX10-1,"") | DI11: =IFERROR(DI10/DD10-1,"") | DJ11: =IFERROR(DJ10/DE10-1,"") | DK11: =IFERROR(DK10/DF10-1,"") | DL11: =IFERROR(DL10/DG10-1,"") | DM11: =IFERROR(DM10/DH10-1,"") | DN11: =IFERROR(DN10/DI10-1,"") | DO11: =IFERROR(DO10/DJ10-1,"") | DP11: =IFERROR(DP10/DK10-1,"") | ... FA11: =IFERROR(FA10/EV10-1,"")
B12: % qoq | H12: =IFERROR(H10/F10-1,"") | I12: =IFERROR(I10/H10-1,"") | J12: =IFERROR(J10/I10-1,"") | K12: =IFERROR(K10/J10-1,"") | M12: =IFERROR(M10/K10-1,"") | N12: =IFERROR(N10/M10-1,"") | O12: =IFERROR(O10/N10-1,"") | P12: =IFERROR(P10/O10-1,"") | R12: =IFERROR(R10/P10-1,"") | S12: =IFERROR(S10/R10-1,"") | T12: =IFERROR(T10/S10-1,"") | U12: =IFERROR(U10/T10-1,"") | W12: =IFERROR(W10/U10-1,"") | X12: =IFERROR(X10/W10-1,"") | Y12: =IFERROR(Y10/X10-1,"") | Z12: =IFERROR(Z10/Y10-1,"") | AB12: =IFERROR(AB10/Z10-1,"") | AC12: =IFERROR(AC10/AB10-1,"") | AD12: =IFERROR(AD10/AC10-1,"") | AE12: =IFERROR(AE10/AD10-1,"") | AG12: =IFERROR(AG10/AE10-1,"") | AH12: =IFERROR(AH10/AG10-1,"") | AI12: =IFERROR(AI10/AH10-1,"") | AJ12: =IFERROR(AJ10/AI10-1,"") | AL12: =IFERROR(AL10/AJ10-1,"") | AM12: =IFERROR(AM10/AL10-1,"") | AN12: =IFERROR(AN10/AM10-1,"") | AO12: =IFERROR(AO10/AN10-1,"") | AQ12: =IFERROR(AQ10/AO10-1,"") | AR12: =IFERROR(AR10/AQ10-1,"") | AS12: =IFERROR(AS10/AR10-1,"") | AT12: =IFERROR(AT10/AS10-1,"") | AV12: =IFERROR(AV10/AT10-1,"") | AW12: =IFERROR(AW10/AV10-1,"") | AX12: =IFERROR(AX10/AW10-1,"") | AY12: =IFERROR(AY10/AX10-1,"") | BA12: =IFERROR(BA10/AY10-1,"") | BB12: =IFERROR(BB10/BA10-1,"") | BC12: =IFERROR(BC10/BB10-1,"") | BD12: =IFERROR(BD10/BC10-1,"") | BF12: =IFERROR(BF10/BD10-1,"") | BG12: =IFERROR(BG10/BF10-1,"") | BH12: =IFERROR(BH10/BG10-1,"") | BI12: =IFERROR(BI10/BH10-1,"") | BK12: =IFERROR(BK10/BI10-1,"") | BL12: =IFERROR(BL10/BK10-1,"") | BM12: =IFERROR(BM10/BL10-1,"") | BN12: =IFERROR(BN10/BM10-1,"") | BP12: =IFERROR(BP10/BN10-1,"") | BQ12: =IFERROR(BQ10/BP10-1,"") | BR12: =IFERROR(BR10/BQ10-1,"") | BS12: =IFERROR(BS10/BR10-1,"") | BU12: =IFERROR(BU10/BS10-1,"") | BV12: =IFERROR(BV10/BU10-1,"") | BW12: =IFERROR(BW10/BV10-1,"") | BX12: =IFERROR(BX10/BW10-1,"") | BZ12: =IFERROR(BZ10/BX10-1,"") | CA12: =IFERROR(CA10/BZ10-1,"") | CB12: =IFERROR(CB10/CA10-1,"") | CC12: =IFERROR(CC10/CB10-1,"") | CE12: =IFERROR(CE10/CC10-1,"") | CF12: =IFERROR(CF10/CE10-1,"") | CG12: =IFERROR(CG10/CF10-1,"") | CH12: =IFERROR(CH10/CG10-1,"") | CJ12: =IFERROR(CJ10/CH10-1,"") | CK12: =IFERROR(CK10/CJ10-1,"") | CL12: =IFERROR(CL10/CK10-1,"") | CM12: =IFERROR(CM10/CL10-1,"") | CO12: =IFERROR(CO10/CM10-1,"") | CP12: =IFERROR(CP10/CO10-1,"") | CQ12: =IFERROR(CQ10/CP10-1,"") | CR12: =IFERROR(CR10/CQ10-1,"") | CT12: =IFERROR(CT10/CR10-1,"") | CU12: =IFERROR(CU10/CT10-1,"") | CV12: =IFERROR(CV10/CU10-1,"") | CW12: =IFERROR(CW10/CV10-1,"") | CY12: =IFERROR(CY10/CW10-1,"") | CZ12: =IFERROR(CZ10/CY10-1,"") | DA12: =IFERROR(DA10/CZ10-1,"") | DB12: =IFERROR(DB10/DA10-1,"") | DI12: =IFERROR(DI10/DG10-1,"") | DJ12: =IFERROR(DJ10/DI10-1,"") | DK12: =IFERROR(DK10/DJ10-1,"") | DL12: =IFERROR(DL10/DK10-1,"") | DN12: =IFERROR(DN10/DL10-1,"") | DO12: =IFERROR(DO10/DN10-1,"") | DP12: =IFERROR(DP10/DO10-1,"") | DQ12: =IFERROR(DQ10/DP10-1,"") | DS12: =IFERROR(DS10/DQ10-1,"") | DT12: =IFERROR(DT10/DS10-1,"") | DU12: =IFERROR(DU10/DT10-1,"") | DV12: =IFERROR(DV10/DU10-1,"") | DX12: =IFERROR(DX10/DV10-1,"") | DY12: =IFERROR(DY10/DX10-1,"") | DZ12: =IFERROR(DZ10/DY10-1,"") | EA12: =IFERROR(EA10/DZ10-1,"") | EC12: =IFERROR(EC10/EA10-1,"") | ED12: =IFERROR(ED10/EC10-1,"") | EE12: =IFERROR(EE10/ED10-1,"") | EF12: =IFERROR(EF10/EE10-1,"") | EH12: =IFERROR(EH10/EF10-1,"") | EI12: =IFERROR(EI10/EH10-1,"") | EJ12: =IFERROR(EJ10/EI10-1,"") | EK12: =IFERROR(EK10/EJ10-1,"") | EM12: =IFERROR(EM10/EK10-1,"") | EN12: =IFERROR(EN10/EM10-1,"") | EO12: =IFERROR(EO10/EN10-1,"") | EP12: =IFERROR(EP10/EO10-1,"") | ER12: =IFERROR(ER10/EP10-1,"") | ES12: =IFERROR(ES10/ER10-1,"") | ET12: =IFERROR(ET10/ES10-1,"") | EU12: =IFERROR(EU10/ET10-1,"") | EW12: =IFERROR(EW10/EU10-1,"") | EX12: =IFERROR(EX10/EW10-1,"") | EY12: =IFERROR(EY10/EX10-1,"") | EZ12: =IFERROR(EZ10/EY10-1,"")
B13: Net New Revenue (yoy) | DN13: =DN10-DI10 | DO13: =DO10-DJ10 | DP13: =DP10-DK10 | DQ13: =DQ10-DL10 | DR13: =DR10-DM10 | DS13: =DS10-DN10 | DT13: =DT10-DO10 | DU13: =DU10-DP10 | ... FA13: =FA10-EV10
B14: Net New Revenue (qoq) | DJ14: =DJ10-DI10 | DK14: =DK10-DJ10 | DL14: =DL10-DK10 | DN14: =DN10-DL10 | DO14: =DO10-DN10 | DP14: =DP10-DO10 | DQ14: =DQ10-DP10 | DS14: =DS10-DQ10 | DT14: =DT10-DS10 | DU14: =DU10-DT10 | DV14: =DV10-DU10 | DX14: =DX10-DV10 | DY14: =DY10-DX10 | DZ14: =DZ10-DY10 | EA14: =EA10-DZ10 | EC14: =EC10-EA10 | ED14: =ED10-EC10 | EE14: =EE10-ED10 | EF14: =EF10-EE10 | EH14: =EH10-EF10 | EI14: =EI10-EH10 | EJ14: =EJ10-EI10 | EK14: =EK10-EJ10 | EM14: =EM10-EK10 | EN14: =EN10-EM10 | EO14: =EO10-EN10 | EP14: =EP10-EO10 | ER14: =ER10-EP10 | ES14: =ES10-ER10 | ET14: =ET10-ES10 | EU14: =EU10-ET10 | EW14: =EW10-EU10 | EX14: =EX10-EW10 | EY14: =EY10-EX10 | EZ14: =EZ10-EY10
B15: % of Total Revenue | DI15: =IFERROR(DI10/DI$24,"") | DJ15: =IFERROR(DJ10/DJ$24,"") | DK15: =IFERROR(DK10/DK$24,"") | DL15: =IFERROR(DL10/DL$24,"") | DM15: =IFERROR(DM10/DM$24,"") | DN15: =IFERROR(DN10/DN$24,"") | DO15: =IFERROR(DO10/DO$24,"") | DP15: =IFERROR(DP10/DP$24,"") | ... FA15: =IFERROR(FA10/FA$24,"")
B17: Service and Other Revenue | DI17: 6960 | DJ17: 7553 | DK17: 8699 | DL17: 9548 | DM17: =SUM(DI17:DL17) | DN17: 10240 | DO17: 10992 | DP17: 11705 | DQ17: 12926 | DR17: =SUM(DN17:DQ17) | DS17: 11785 | DT17: 16252 | DU17: 15123 | DV17: 16614 | DW17: =SUM(DS17:DV17) | DX17: 17287 | DY17: 18651 | DZ17: 19150 | EA17: 19886 | EB17: =SUM(DX17:EA17) | EC17: 21351 | ED17: 23616 | EE17: 24833 | EF17: 27214 | EG17: =SUM(EC17:EF17) | EH17: 28686 | EI17: 30949 | EJ17: 31994 | EK17: 33909 | EL17: =SUM(EH17:EK17) | EM17: 34381 | EN17: 36230 | EO17: 37269 | EP17: 39336 | EQ17: =SUM(EM17:EP17) | ER17: 40982 | ES17: 43079 | ET17: 44778 | EU17: 51510 | EV17: =SUM(ER17:EU17) | EW17: 50313 | EX17: 53413 | EY17: 54747 | EZ17: 59305 | FA17: =SUM(EW17:EZ17)
B18: % yoy | H18: =IFERROR(H17/C17-1,"") | I18: =IFERROR(I17/D17-1,"") | J18: =IFERROR(J17/E17-1,"") | K18: =IFERROR(K17/F17-1,"") | L18: =IFERROR(L17/G17-1,"") | M18: =IFERROR(M17/H17-1,"") | N18: =IFERROR(N17/I17-1,"") | O18: =IFERROR(O17/J17-1,"") | ... DC18: =IFERROR(DC17/CX17-1,"") | DI18: =IFERROR(DI17/DD17-1,"") | DJ18: =IFERROR(DJ17/DE17-1,"") | DK18: =IFERROR(DK17/DF17-1,"") | DL18: =IFERROR(DL17/DG17-1,"") | DM18: =IFERROR(DM17/DH17-1,"") | DN18: =IFERROR(DN17/DI17-1,"") | DO18: =IFERROR(DO17/DJ17-1,"") | DP18: =IFERROR(DP17/DK17-1,"") | ... FA18: =IFERROR(FA17/EV17-1,"")
B19: % qoq | H19: =IFERROR(H17/F17-1,"") | I19: =IFERROR(I17/H17-1,"") | J19: =IFERROR(J17/I17-1,"") | K19: =IFERROR(K17/J17-1,"") | M19: =IFERROR(M17/K17-1,"") | N19: =IFERROR(N17/M17-1,"") | O19: =IFERROR(O17/N17-1,"") | P19: =IFERROR(P17/O17-1,"") | R19: =IFERROR(R17/P17-1,"") | S19: =IFERROR(S17/R17-1,"") | T19: =IFERROR(T17/S17-1,"") | U19: =IFERROR(U17/T17-1,"") | W19: =IFERROR(W17/U17-1,"") | X19: =IFERROR(X17/W17-1,"") | Y19: =IFERROR(Y17/X17-1,"") | Z19: =IFERROR(Z17/Y17-1,"") | AB19: =IFERROR(AB17/Z17-1,"") | AC19: =IFERROR(AC17/AB17-1,"") | AD19: =IFERROR(AD17/AC17-1,"") | AE19: =IFERROR(AE17/AD17-1,"") | AG19: =IFERROR(AG17/AE17-1,"") | AH19: =IFERROR(AH17/AG17-1,"") | AI19: =IFERROR(AI17/AH17-1,"") | AJ19: =IFERROR(AJ17/AI17-1,"") | AL19: =IFERROR(AL17/AJ17-1,"") | AM19: =IFERROR(AM17/AL17-1,"") | AN19: =IFERROR(AN17/AM17-1,"") | AO19: =IFERROR(AO17/AN17-1,"") | AQ19: =IFERROR(AQ17/AO17-1,"") | AR19: =IFERROR(AR17/AQ17-1,"") | AS19: =IFERROR(AS17/AR17-1,"") | AT19: =IFERROR(AT17/AS17-1,"") | AV19: =IFERROR(AV17/AT17-1,"") | AW19: =IFERROR(AW17/AV17-1,"") | AX19: =IFERROR(AX17/AW17-1,"") | AY19: =IFERROR(AY17/AX17-1,"") | BA19: =IFERROR(BA17/AY17-1,"") | BB19: =IFERROR(BB17/BA17-1,"") | BC19: =IFERROR(BC17/BB17-1,"") | BD19: =IFERROR(BD17/BC17-1,"") | BF19: =IFERROR(BF17/BD17-1,"") | BG19: =IFERROR(BG17/BF17-1,"") | BH19: =IFERROR(BH17/BG17-1,"") | BI19: =IFERROR(BI17/BH17-1,"") | BK19: =IFERROR(BK17/BI17-1,"") | BL19: =IFERROR(BL17/BK17-1,"") | BM19: =IFERROR(BM17/BL17-1,"") | BN19: =IFERROR(BN17/BM17-1,"") | BP19: =IFERROR(BP17/BN17-1,"") | BQ19: =IFERROR(BQ17/BP17-1,"") | BR19: =IFERROR(BR17/BQ17-1,"") | BS19: =IFERROR(BS17/BR17-1,"") | BU19: =IFERROR(BU17/BS17-1,"") | BV19: =IFERROR(BV17/BU17-1,"") | BW19: =IFERROR(BW17/BV17-1,"") | BX19: =IFERROR(BX17/BW17-1,"") | BZ19: =IFERROR(BZ17/BX17-1,"") | CA19: =IFERROR(CA17/BZ17-1,"") | CB19: =IFERROR(CB17/CA17-1,"") | CC19: =IFERROR(CC17/CB17-1,"") | CE19: =IFERROR(CE17/CC17-1,"") | CF19: =IFERROR(CF17/CE17-1,"") | CG19: =IFERROR(CG17/CF17-1,"") | CH19: =IFERROR(CH17/CG17-1,"") | CJ19: =IFERROR(CJ17/CH17-1,"") | CK19: =IFERROR(CK17/CJ17-1,"") | CL19: =IFERROR(CL17/CK17-1,"") | CM19: =IFERROR(CM17/CL17-1,"") | CO19: =IFERROR(CO17/CM17-1,"") | CP19: =IFERROR(CP17/CO17-1,"") | CQ19: =IFERROR(CQ17/CP17-1,"") | CR19: =IFERROR(CR17/CQ17-1,"") | CT19: =IFERROR(CT17/CR17-1,"") | CU19: =IFERROR(CU17/CT17-1,"") | CV19: =IFERROR(CV17/CU17-1,"") | CW19: =IFERROR(CW17/CV17-1,"") | CY19: =IFERROR(CY17/CW17-1,"") | CZ19: =IFERROR(CZ17/CY17-1,"") | DA19: =IFERROR(DA17/CZ17-1,"") | DB19: =IFERROR(DB17/DA17-1,"") | DI19: =IFERROR(DI17/DG17-1,"") | DJ19: =IFERROR(DJ17/DI17-1,"") | DK19: =IFERROR(DK17/DJ17-1,"") | DL19: =IFERROR(DL17/DK17-1,"") | DN19: =IFERROR(DN17/DL17-1,"") | DO19: =IFERROR(DO17/DN17-1,"") | DP19: =IFERROR(DP17/DO17-1,"") | DQ19: =IFERROR(DQ17/DP17-1,"") | DS19: =IFERROR(DS17/DQ17-1,"") | DT19: =IFERROR(DT17/DS17-1,"") | DU19: =IFERROR(DU17/DT17-1,"") | DV19: =IFERROR(DV17/DU17-1,"") | DX19: =IFERROR(DX17/DV17-1,"") | DY19: =IFERROR(DY17/DX17-1,"") | DZ19: =IFERROR(DZ17/DY17-1,"") | EA19: =IFERROR(EA17/DZ17-1,"") | EC19: =IFERROR(EC17/EA17-1,"") | ED19: =IFERROR(ED17/EC17-1,"") | EE19: =IFERROR(EE17/ED17-1,"") | EF19: =IFERROR(EF17/EE17-1,"") | EH19: =IFERROR(EH17/EF17-1,"") | EI19: =IFERROR(EI17/EH17-1,"") | EJ19: =IFERROR(EJ17/EI17-1,"") | EK19: =IFERROR(EK17/EJ17-1,"") | EM19: =IFERROR(EM17/EK17-1,"") | EN19: =IFERROR(EN17/EM17-1,"") | EO19: =IFERROR(EO17/EN17-1,"") | EP19: =IFERROR(EP17/EO17-1,"") | ER19: =IFERROR(ER17/EP17-1,"") | ES19: =IFERROR(ES17/ER17-1,"") | ET19: =IFERROR(ET17/ES17-1,"") | EU19: =IFERROR(EU17/ET17-1,"") | EW19: =IFERROR(EW17/EU17-1,"") | EX19: =IFERROR(EX17/EW17-1,"") | EY19: =IFERROR(EY17/EX17-1,"") | EZ19: =IFERROR(EZ17/EY17-1,"")
B20: Net New Revenue (yoy) | DN20: =DN17-DI17 | DO20: =DO17-DJ17 | DP20: =DP17-DK17 | DQ20: =DQ17-DL17 | DR20: =DR17-DM17 | DS20: =DS17-DN17 | DT20: =DT17-DO17 | DU20: =DU17-DP17 | ... FA20: =FA17-EV17
B21: Net New Revenue (qoq) | DJ21: =DJ17-DI17 | DK21: =DK17-DJ17 | DL21: =DL17-DK17 | DN21: =DN17-DL17 | DO21: =DO17-DN17 | DP21: =DP17-DO17 | DQ21: =DQ17-DP17 | DS21: =DS17-DQ17 | DT21: =DT17-DS17 | DU21: =DU17-DT17 | DV21: =DV17-DU17 | DX21: =DX17-DV17 | DY21: =DY17-DX17 | DZ21: =DZ17-DY17 | EA21: =EA17-DZ17 | EC21: =EC17-EA17 | ED21: =ED17-EC17 | EE21: =EE17-ED17 | EF21: =EF17-EE17 | EH21: =EH17-EF17 | EI21: =EI17-EH17 | EJ21: =EJ17-EI17 | EK21: =EK17-EJ17 | EM21: =EM17-EK17 | EN21: =EN17-EM17 | EO21: =EO17-EN17 | EP21: =EP17-EO17 | ER21: =ER17-EP17 | ES21: =ES17-ER17 | ET21: =ET17-ES17 | EU21: =EU17-ET17 | EW21: =EW17-EU17 | EX21: =EX17-EW17 | EY21: =EY17-EX17 | EZ21: =EZ17-EY17
B22: % of Total Revenue | DI22: =IFERROR(DI17/DI$24,"") | DJ22: =IFERROR(DJ17/DJ$24,"") | DK22: =IFERROR(DK17/DK$24,"") | DL22: =IFERROR(DL17/DL$24,"") | DM22: =IFERROR(DM17/DM$24,"") | DN22: =IFERROR(DN17/DN$24,"") | DO22: =IFERROR(DO17/DO$24,"") | DP22: =IFERROR(DP17/DP$24,"") | ... FA22: =IFERROR(FA17/FA$24,"")
A24: TREV | B24: Total Revenue | C24: 1247 | D24: 1482 | E24: 1587 | F24: 1621 | G24: =SUM(C24:F24) | H24: 2016 | I24: 2195 | J24: 2205 | K24: 2255 | L24: =SUM(H24:K24) | M24: 2295 | N24: 2680 | O24: 3208 | P24: 3175 | Q24: =SUM(M24:P24) | R24: 3130 | S24: 3585 | T24: 3774 | U24: 3995 | V24: =SUM(R24:U24) | W24: 4193 | X24: 5195 | Y24: 4595 | Z24: 5764 | AA24: =SUM(W24:Z24) | AB24: 5384 | AC24: 6112 | AD24: 5656 | AE24: 5804 | AF24: =SUM(AB24:AE24) | AG24: 5766 | AH24: 6550 | AI24: 6403 | AJ24: 6577 | AK24: =SUM(AG24:AJ24) | AL24: 6126 | AM24: 7741 | AN24: 7245 | AO24: 7253 | AP24: =SUM(AL24:AO24) | AQ24: 7746 | AR24: 8541 | AS24: 7835 | AT24: 8065 | AU24: =SUM(AQ24:AT24) | AV24: 8215 | AW24: 10153 | AX24: 9175 | AY24: 9292 | AZ24: =SUM(AV24:AY24) | BA24: 9189 | BB24: 10818 | BC24: 9620 | BD24: 10161 | BE24: =SUM(BA24:BD24) | BF24: 9741 | BG24: 11837 | BH24: 10900 | BI24: 11804 | BJ24: =SUM(BF24:BI24) | BK24: 10811 | BL24: 12542 | BM24: 14398 | BN24: 13371 | BO24: =SUM(BK24:BN24) | BP24: 13762 | BQ24: 16367 | BR24: 14454 | BS24: 15837 | BT24: =SUM(BP24:BS24) | BU24: 15061 | BV24: 16629 | BW24: 13648 | BX24: 13099 | BY24: =SUM(BU24:BX24) | BZ24: 12920 | CA24: 19022 | CB24: 14503 | CC24: 16039 | CD24: =SUM(BZ24:CC24) | CE24: 16195 | CF24: 19953 | CG24: 16428 | CH24: 17367 | CI24: =SUM(CE24:CH24) | CJ24: 17372 | CK24: 20885 | CL24: 17407 | CM24: 18059 | CN24: =SUM(CJ24:CM24) | CO24: 16008 | CP24: 21456 | CQ24: 20489 | CR24: 19896 | CS24: =SUM(CO24:CR24) | CT24: 18529 | CU24: 24519 | CV24: 20403 | CW24: 23382 | CX24: =SUM(CT24:CW24) | CY24: 23201 | CZ24: 26470 | DA24: 21729 | DB24: 22180 | DC24: =SUM(CY24:DB24) | DD24: 20379 | DE24: 23796 | DF24: 20531 | DG24: 20614 | DH24: =SUM(DD24:DG24) | DI24: =DI17+DI10 | DJ24: =DJ17+DJ10 | DK24: =DK17+DK10 | DL24: =DL17+DL10 | DM24: =SUM(DI24:DL24) | DN24: =DN17+DN10 | DO24: =DO17+DO10 | DP24: =DP17+DP10 | DQ24: =DQ17+DQ10 | DR24: =SUM(DN24:DQ24) | DS24: =DS17+DS10 | DT24: =DT17+DT10 | DU24: =DU17+DU10 | DV24: =DV17+DV10 | DW24: =SUM(DS24:DV24) | DX24: =DX17+DX10 | DY24: =DY17+DY10 | DZ24: =DZ17+DZ10 | EA24: =EA17+EA10 | EB24: =SUM(DX24:EA24) | EC24: =EC17+EC10 | ED24: =ED17+ED10 | EE24: =EE17+EE10 | EF24: =EF17+EF10 | EG24: =SUM(EC24:EF24) | EH24: =EH17+EH10 | EI24: =EI17+EI10 | EJ24: =EJ17+EJ10 | EK24: =EK17+EK10 | EL24: =SUM(EH24:EK24) | EM24: =EM17+EM10 | EN24: =EN17+EN10 | EO24: =EO17+EO10 | EP24: =EP17+EP10 | EQ24: =SUM(EM24:EP24) | ER24: =ER17+ER10 | ES24: =ES17+ES10 | ET24: =ET17+ET10 | EU24: =EU17+EU10 | EV24: =SUM(ER24:EU24) | EW24: =EW17+EW10 | EX24: =EX17+EX10 | EY24: =EY17+EY10 | EZ24: =EZ17+EZ10 | FA24: =SUM(EW24:EZ24) | FB24: =PBP!FB10+IC!FB10+Company1738!FB10 | FC24: =PBP!FC10+IC!FC10+Company1738!FC10 | FD24: =PBP!FD10+IC!FD10+Company1738!FD10 | FE24: =PBP!FE10+IC!FE10+Company1738!FE10 | FF24: =SUM(FB24:FE24) | FG24: =PBP!FG10+IC!FG10+Company1738!FG10 | FH24: =PBP!FH10+IC!FH10+Company1738!FH10 | FI24: =PBP!FI10+IC!FI10+Company1738!FI10 | FJ24: =PBP!FJ10+IC!FJ10+Company1738!FJ10 | FK24: =SUM(FG24:FJ24) | FL24: =PBP!FL10+IC!FL10+Company1738!FL10 | FM24: =PBP!FM10+IC!FM10+Company1738!FM10 | FN24: =PBP!FN10+IC!FN10+Company1738!FN10 | FO24: =PBP!FO10+IC!FO10+Company1738!FO10 | FP24: =SUM(FL24:FO24) | FQ24: =PBP!FQ10+IC!FQ10+Company1738!FQ10 | FR24: =PBP!FR10+IC!FR10+Company1738!FR10 | FS24: =PBP!FS10+IC!FS10+Company1738!FS10 | FT24: =PBP!FT10+IC!FT10+Company1738!FT10 | FU24: =SUM(FQ24:FT24) | FV24: =PBP!FV10+IC!FV10+Company1738!FV10 | FW24: =PBP!FW10+IC!FW10+Company1738!FW10 | FX24: =PBP!FX10+IC!FX10+Company1738!FX10 | FY24: =PBP!FY10+IC!FY10+Company1738!FY10 | FZ24: =SUM(FV24:FY24) | GA24: =PBP!GA10+IC!GA10+Company1738!GA10 | GB24: =PBP!GB10+IC!GB10+Company1738!GB10 | GC24: =PBP!GC10+IC!GC10+Company1738!GC10 | GD24: =PBP!GD10+IC!GD10+Company1738!GD10 | GE24: =SUM(GA24:GD24) | GF24: =PBP!GF10+IC!GF10+Company1738!GF10 | GG24: =PBP!GG10+IC!GG10+Company1738!GG10 | GH24: =PBP!GH10+IC!GH10+Company1738!GH10 | GI24: =PBP!GI10+IC!GI10+Company1738!GI10 | GJ24: =SUM(GF24:GI24)
A25: TREVYY | B25: % yoy | H25: =IFERROR(H24/C24-1,"") | I25: =IFERROR(I24/D24-1,"") | J25: =IFERROR(J24/E24-1,"") | K25: =IFERROR(K24/F24-1,"") | L25: =IFERROR(L24/G24-1,"") | M25: =IFERROR(M24/H24-1,"") | N25: =IFERROR(N24/I24-1,"") | O25: =IFERROR(O24/J24-1,"") | ... GJ25: =IFERROR(GJ24/GE24-1,"")
A26: TREVCC | B26: % yoy CC | DA26: 0.09 | DB26: -0.02 | DD26: -0.02 | DE26: 0.03 | DF26: 0.05 | DG26: 0.05 | DI26: 0.05 | DJ26: 0.04 | DK26: 0.07 | DL26: 0.1 | DM26: 0.05 | DN26: 0.11 | DO26: 0.11 | DP26: 0.13 | DQ26: 0.15 | DS26: 0.18 | DT26: 0.13 | DU26: 0.16 | DV26: 0.14 | DX26: 0.15 | DY26: 0.15 | DZ26: 0.16 | EA26: 0.15 | EC26: 0.12 | ED26: 0.15 | EE26: 0.16 | EF26: 0.17 | EH26: 0.2 | EI26: 0.2 | EJ26: 0.21 | EK26: 0.16 | EM26: 0.16 | EN26: 0.07 | EO26: 0.1 | EP26: 0.1 | ER26: 0.12 | ES26: 0.16 | ET26: 0.17 | EU26: 0.16 | EW26: 0.16 | EY26: 0.15 | EZ26: 0.17 | FA26: 0.15 | FB26: =FB25-2%
A27: TREVQQ | B27: % qoq | H27: =IFERROR(H24/F24-1,"") | I27: =IFERROR(I24/H24-1,"") | J27: =IFERROR(J24/I24-1,"") | K27: =IFERROR(K24/J24-1,"") | M27: =IFERROR(M24/K24-1,"") | N27: =IFERROR(N24/M24-1,"") | O27: =IFERROR(O24/N24-1,"") | P27: =IFERROR(P24/O24-1,"") | R27: =IFERROR(R24/P24-1,"") | S27: =IFERROR(S24/R24-1,"") | T27: =IFERROR(T24/S24-1,"") | U27: =IFERROR(U24/T24-1,"") | W27: =IFERROR(W24/U24-1,"") | X27: =IFERROR(X24/W24-1,"") | Y27: =IFERROR(Y24/X24-1,"") | Z27: =IFERROR(Z24/Y24-1,"") | AB27: =IFERROR(AB24/Z24-1,"") | AC27: =IFERROR(AC24/AB24-1,"") | AD27: =IFERROR(AD24/AC24-1,"") | AE27: =IFERROR(AE24/AD24-1,"") | AG27: =IFERROR(AG24/AE24-1,"") | AH27: =IFERROR(AH24/AG24-1,"") | AI27: =IFERROR(AI24/AH24-1,"") | AJ27: =IFERROR(AJ24/AI24-1,"") | AL27: =IFERROR(AL24/AJ24-1,"") | AM27: =IFERROR(AM24/AL24-1,"") | AN27: =IFERROR(AN24/AM24-1,"") | AO27: =IFERROR(AO24/AN24-1,"") | AQ27: =IFERROR(AQ24/AO24-1,"") | AR27: =IFERROR(AR24/AQ24-1,"") | AS27: =IFERROR(AS24/AR24-1,"") | AT27: =IFERROR(AT24/AS24-1,"") | AV27: =IFERROR(AV24/AT24-1,"") | AW27: =IFERROR(AW24/AV24-1,"") | AX27: =IFERROR(AX24/AW24-1,"") | AY27: =IFERROR(AY24/AX24-1,"") | BA27: =IFERROR(BA24/AY24-1,"") | BB27: =IFERROR(BB24/BA24-1,"") | BC27: =IFERROR(BC24/BB24-1,"") | BD27: =IFERROR(BD24/BC24-1,"") | BF27: =IFERROR(BF24/BD24-1,"") | BG27: =IFERROR(BG24/BF24-1,"") | BH27: =IFERROR(BH24/BG24-1,"") | BI27: =IFERROR(BI24/BH24-1,"") | BK27: =IFERROR(BK24/BI24-1,"") | BL27: =IFERROR(BL24/BK24-1,"") | BM27: =IFERROR(BM24/BL24-1,"") | BN27: =IFERROR(BN24/BM24-1,"") | BP27: =IFERROR(BP24/BN24-1,"") | BQ27: =IFERROR(BQ24/BP24-1,"") | BR27: =IFERROR(BR24/BQ24-1,"") | BS27: =IFERROR(BS24/BR24-1,"") | BU27: =IFERROR(BU24/BS24-1,"") | BV27: =IFERROR(BV24/BU24-1,"") | BW27: =IFERROR(BW24/BV24-1,"") | BX27: =IFERROR(BX24/BW24-1,"") | BZ27: =IFERROR(BZ24/BX24-1,"") | CA27: =IFERROR(CA24/BZ24-1,"") | CB27: =IFERROR(CB24/CA24-1,"") | CC27: =IFERROR(CC24/CB24-1,"") | CE27: =IFERROR(CE24/CC24-1,"") | CF27: =IFERROR(CF24/CE24-1,"") | CG27: =IFERROR(CG24/CF24-1,"") | CH27: =IFERROR(CH24/CG24-1,"") | CJ27: =IFERROR(CJ24/CH24-1,"") | CK27: =IFERROR(CK24/CJ24-1,"") | CL27: =IFERROR(CL24/CK24-1,"") | CM27: =IFERROR(CM24/CL24-1,"") | CO27: =IFERROR(CO24/CM24-1,"") | CP27: =IFERROR(CP24/CO24-1,"") | CQ27: =IFERROR(CQ24/CP24-1,"") | CR27: =IFERROR(CR24/CQ24-1,"") | CT27: =IFERROR(CT24/CR24-1,"") | CU27: =IFERROR(CU24/CT24-1,"") | CV27: =IFERROR(CV24/CU24-1,"") | CW27: =IFERROR(CW24/CV24-1,"") | CY27: =IFERROR(CY24/CW24-1,"") | CZ27: =IFERROR(CZ24/CY24-1,"") | DA27: =IFERROR(DA24/CZ24-1,"") | DB27: =IFERROR(DB24/DA24-1,"") | DD27: =IFERROR(DD24/DB24-1,"") | DE27: =IFERROR(DE24/DD24-1,"") | DF27: =IFERROR(DF24/DE24-1,"") | DG27: =IFERROR(DG24/DF24-1,"") | DI27: =IFERROR(DI24/DG24-1,"") | DJ27: =IFERROR(DJ24/DI24-1,"") | DK27: =IFERROR(DK24/DJ24-1,"") | DL27: =IFERROR(DL24/DK24-1,"") | DN27: =IFERROR(DN24/DL24-1,"") | DO27: =IFERROR(DO24/DN24-1,"") | DP27: =IFERROR(DP24/DO24-1,"") | DQ27: =IFERROR(DQ24/DP24-1,"") | DS27: =IFERROR(DS24/DQ24-1,"") | DT27: =IFERROR(DT24/DS24-1,"") | DU27: =IFERROR(DU24/DT24-1,"") | DV27: =IFERROR(DV24/DU24-1,"") | DX27: =IFERROR(DX24/DV24-1,"") | DY27: =IFERROR(DY24/DX24-1,"") | DZ27: =IFERROR(DZ24/DY24-1,"") | EA27: =IFERROR(EA24/DZ24-1,"") | EC27: =IFERROR(EC24/EA24-1,"") | ED27: =IFERROR(ED24/EC24-1,"") | EE27: =IFERROR(EE24/ED24-1,"") | EF27: =IFERROR(EF24/EE24-1,"") | EH27: =IFERROR(EH24/EF24-1,"") | EI27: =IFERROR(EI24/EH24-1,"") | EJ27: =IFERROR(EJ24/EI24-1,"") | EK27: =IFERROR(EK24/EJ24-1,"") | EM27: =IFERROR(EM24/EK24-1,"") | EN27: =IFERROR(EN24/EM24-1,"") | EO27: =IFERROR(EO24/EN24-1,"") | EP27: =IFERROR(EP24/EO24-1,"") | ER27: =IFERROR(ER24/EP24-1,"") | ES27: =IFERROR(ES24/ER24-1,"") | ET27: =IFERROR(ET24/ES24-1,"") | EU27: =IFERROR(EU24/ET24-1,"") | EW27: =IFERROR(EW24/EU24-1,"") | EX27: =IFERROR(EX24/EW24-1,"") | EY27: =IFERROR(EY24/EX24-1,"") | EZ27: =IFERROR(EZ24/EY24-1,"") | FB27: =IFERROR(FB24/EZ24-1,"") | FC27: =IFERROR(FC24/FB24-1,"") | FD27: =IFERROR(FD24/FC24-1,"") | FE27: =IFERROR(FE24/FD24-1,"") | FG27: =IFERROR(FG24/FE24-1,"") | FH27: =IFERROR(FH24/FG24-1,"") | FI27: =IFERROR(FI24/FH24-1,"") | FJ27: =IFERROR(FJ24/FI24-1,"") | FL27: =IFERROR(FL24/FJ24-1,"") | FM27: =IFERROR(FM24/FL24-1,"") | FN27: =IFERROR(FN24/FM24-1,"") | FO27: =IFERROR(FO24/FN24-1,"") | FQ27: =IFERROR(FQ24/FO24-1,"") | FR27: =IFERROR(FR24/FQ24-1,"") | FS27: =IFERROR(FS24/FR24-1,"") | FT27: =IFERROR(FT24/FS24-1,"") | FV27: =IFERROR(FV24/FT24-1,"") | FW27: =IFERROR(FW24/FV24-1,"") | FX27: =IFERROR(FX24/FW24-1,"") | FY27: =IFERROR(FY24/FX24-1,"") | GA27: =IFERROR(GA24/FY24-1,"") | GB27: =IFERROR(GB24/GA24-1,"") | GC27: =IFERROR(GC24/GB24-1,"") | GD27: =IFERROR(GD24/GC24-1,"") | GF27: =IFERROR(GF24/GD24-1,"") | GG27: =IFERROR(GG24/GF24-1,"") | GH27: =IFERROR(GH24/GG24-1,"") | GI27: =IFERROR(GI24/GH24-1,"")
B28: Net New Revenue (yoy) | H28: =H24-C24 | I28: =I24-D24 | J28: =J24-E24 | K28: =K24-F24 | L28: =L24-G24 | M28: =M24-H24 | N28: =N24-I24 | O28: =O24-J24 | ... GJ28: =GJ24-GE24
B29: Net New Revenue (qoq) | D29: =D24-C24 | E29: =E24-D24 | F29: =F24-E24 | H29: =H24-F24 | I29: =I24-H24 | J29: =J24-I24 | K29: =K24-J24 | M29: =M24-K24 | N29: =N24-M24 | O29: =O24-N24 | P29: =P24-O24 | R29: =R24-P24 | S29: =S24-R24 | T29: =T24-S24 | U29: =U24-T24 | W29: =W24-U24 | X29: =X24-W24 | Y29: =Y24-X24 | Z29: =Z24-Y24 | AB29: =AB24-Z24 | AC29: =AC24-AB24 | AD29: =AD24-AC24 | AE29: =AE24-AD24 | AG29: =AG24-AE24 | AH29: =AH24-AG24 | AI29: =AI24-AH24 | AJ29: =AJ24-AI24 | AL29: =AL24-AJ24 | AM29: =AM24-AL24 | AN29: =AN24-AM24 | AO29: =AO24-AN24 | AQ29: =AQ24-AO24 | AR29: =AR24-AQ24 | AS29: =AS24-AR24 | AT29: =AT24-AS24 | AV29: =AV24-AT24 | AW29: =AW24-AV24 | AX29: =AX24-AW24 | AY29: =AY24-AX24 | BA29: =BA24-AY24 | BB29: =BB24-BA24 | BC29: =BC24-BB24 | BD29: =BD24-BC24 | BF29: =BF24-BD24 | BG29: =BG24-BF24 | BH29: =BH24-BG24 | BI29: =BI24-BH24 | BK29: =BK24-BI24 | BL29: =BL24-BK24 | BM29: =BM24-BL24 | BN29: =BN24-BM24 | BP29: =BP24-BN24 | BQ29: =BQ24-BP24 | BR29: =BR24-BQ24 | BS29: =BS24-BR24 | BU29: =BU24-BS24 | BV29: =BV24-BU24 | BW29: =BW24-BV24 | BX29: =BX24-BW24 | BZ29: =BZ24-BX24 | CA29: =CA24-BZ24 | CB29: =CB24-CA24 | CC29: =CC24-CB24 | CE29: =CE24-CC24 | CF29: =CF24-CE24 | CG29: =CG24-CF24 | CH29: =CH24-CG24 | CJ29: =CJ24-CH24 | CK29: =CK24-CJ24 | CL29: =CL24-CK24 | CM29: =CM24-CL24 | CO29: =CO24-CM24 | CP29: =CP24-CO24 | CQ29: =CQ24-CP24 | CR29: =CR24-CQ24 | CT29: =CT24-CR24 | CU29: =CU24-CT24 | CV29: =CV24-CU24 | CW29: =CW24-CV24 | CY29: =CY24-CW24 | CZ29: =CZ24-CY24 | DA29: =DA24-CZ24 | DB29: =DB24-DA24 | DD29: =DD24-DB24 | DE29: =DE24-DD24 | DF29: =DF24-DE24 | DG29: =DG24-DF24 | DI29: =DI24-DG24 | DJ29: =DJ24-DI24 | DK29: =DK24-DJ24 | DL29: =DL24-DK24 | DN29: =DN24-DL24 | DO29: =DO24-DN24 | DP29: =DP24-DO24 | DQ29: =DQ24-DP24 | DS29: =DS24-DQ24 | DT29: =DT24-DS24 | DU29: =DU24-DT24 | DV29: =DV24-DU24 | DX29: =DX24-DV24 | DY29: =DY24-DX24 | DZ29: =DZ24-DY24 | EA29: =EA24-DZ24 | EC29: =EC24-EA24 | ED29: =ED24-EC24 | EE29: =EE24-ED24 | EF29: =EF24-EE24 | EH29: =EH24-EF24 | EI29: =EI24-EH24 | EJ29: =EJ24-EI24 | EK29: =EK24-EJ24 | EM29: =EM24-EK24 | EN29: =EN24-EM24 | EO29: =EO24-EN24 | EP29: =EP24-EO24 | ER29: =ER24-EP24 | ES29: =ES24-ER24 | ET29: =ET24-ES24 | EU29: =EU24-ET24 | EW29: =EW24-EU24 | EX29: =EX24-EW24 | EY29: =EY24-EX24 | EZ29: =EZ24-EY24 | FB29: =FB24-EZ24 | FC29: =FC24-FB24 | FD29: =FD24-FC24 | FE29: =FE24-FD24 | FG29: =FG24-FE24 | FH29: =FH24-FG24 | FI29: =FI24-FH24 | FJ29: =FJ24-FI24 | FL29: =FL24-FJ24 | FM29: =FM24-FL24 | FN29: =FN24-FM24 | FO29: =FO24-FN24 | FQ29: =FQ24-FO24 | FR29: =FR24-FQ24 | FS29: =FS24-FR24 | FT29: =FT24-FS24 | FV29: =FV24-FT24 | FW29: =FW24-FV24 | FX29: =FX24-FW24 | FY29: =FY24-FX24 | GA29: =GA24-FY24 | GB29: =GB24-GA24 | GC29: =GC24-GB24 | GD29: =GD24-GC24 | GF29: =GF24-GD24 | GG29: =GG24-GF24 | GH29: =GH24-GG24 | GI29: =GI24-GH24
B31: Product Cost of Revenue | DI31: 3581 | DJ31: 5378 | DK31: 3075 | DL31: 3141 | DM31: =SUM(DI31:DL31) | DN31: 2980 | DO31: 5498 | DP31: 3425 | DQ31: 3517 | DR31: =SUM(DN31:DQ31) | DS31: 3649 | DT31: 5885 | DU31: 3441 | DV31: 3298 | DW31: =SUM(DS31:DV31) | DX31: 3305 | DY31: 4966 | DZ31: 3376 | EA31: 4370 | EB31: =SUM(DX31:EA31) | EC31: 3597 | ED31: 6058 | EE31: 4277 | EF31: 4287 | EG31: =SUM(EC31:EF31) | EH31: 3792 | EI31: 6331 | EJ31: 4584 | EK31: 4357 | EL31: =SUM(EH31:EK31) | EM31: 4302 | EN31: 5690 | EO31: 3941 | EP31: 3871 | EQ31: =SUM(EM31:EP31) | ER31: 3531 | ES31: 5964 | ET31: 4339 | EU31: 1438 | EV31: =SUM(ER31:EU31) | EW31: 3294 | EX31: 3856 | EY31: 3037 | EZ31: 3314 | FA31: =SUM(EW31:EZ31)
B32: % yoy | H32: =IFERROR(H31/C31-1,"") | I32: =IFERROR(I31/D31-1,"") | J32: =IFERROR(J31/E31-1,"") | K32: =IFERROR(K31/F31-1,"") | L32: =IFERROR(L31/G31-1,"") | M32: =IFERROR(M31/H31-1,"") | N32: =IFERROR(N31/I31-1,"") | O32: =IFERROR(O31/J31-1,"") | ... DC32: =IFERROR(DC31/CX31-1,"") | DI32: =IFERROR(DI31/DD31-1,"") | DJ32: =IFERROR(DJ31/DE31-1,"") | DK32: =IFERROR(DK31/DF31-1,"") | DL32: =IFERROR(DL31/DG31-1,"") | DM32: =IFERROR(DM31/DH31-1,"") | DN32: =IFERROR(DN31/DI31-1,"") | DO32: =IFERROR(DO31/DJ31-1,"") | DP32: =IFERROR(DP31/DK31-1,"") | ... FA32: =IFERROR(FA31/EV31-1,"")
B33: % qoq | H33: =IFERROR(H31/F31-1,"") | I33: =IFERROR(I31/H31-1,"") | J33: =IFERROR(J31/I31-1,"") | K33: =IFERROR(K31/J31-1,"") | M33: =IFERROR(M31/K31-1,"") | N33: =IFERROR(N31/M31-1,"") | O33: =IFERROR(O31/N31-1,"") | P33: =IFERROR(P31/O31-1,"") | R33: =IFERROR(R31/P31-1,"") | S33: =IFERROR(S31/R31-1,"") | T33: =IFERROR(T31/S31-1,"") | U33: =IFERROR(U31/T31-1,"") | W33: =IFERROR(W31/U31-1,"") | X33: =IFERROR(X31/W31-1,"") | Y33: =IFERROR(Y31/X31-1,"") | Z33: =IFERROR(Z31/Y31-1,"") | AB33: =IFERROR(AB31/Z31-1,"") | AC33: =IFERROR(AC31/AB31-1,"") | AD33: =IFERROR(AD31/AC31-1,"") | AE33: =IFERROR(AE31/AD31-1,"") | AG33: =IFERROR(AG31/AE31-1,"") | AH33: =IFERROR(AH31/AG31-1,"") | AI33: =IFERROR(AI31/AH31-1,"") | AJ33: =IFERROR(AJ31/AI31-1,"") | AL33: =IFERROR(AL31/AJ31-1,"") | AM33: =IFERROR(AM31/AL31-1,"") | AN33: =IFERROR(AN31/AM31-1,"") | AO33: =IFERROR(AO31/AN31-1,"") | AQ33: =IFERROR(AQ31/AO31-1,"") | AR33: =IFERROR(AR31/AQ31-1,"") | AS33: =IFERROR(AS31/AR31-1,"") | AT33: =IFERROR(AT31/AS31-1,"") | AV33: =IFERROR(AV31/AT31-1,"") | AW33: =IFERROR(AW31/AV31-1,"") | AX33: =IFERROR(AX31/AW31-1,"") | AY33: =IFERROR(AY31/AX31-1,"") | BA33: =IFERROR(BA31/AY31-1,"") | BB33: =IFERROR(BB31/BA31-1,"") | BC33: =IFERROR(BC31/BB31-1,"") | BD33: =IFERROR(BD31/BC31-1,"") | BF33: =IFERROR(BF31/BD31-1,"") | BG33: =IFERROR(BG31/BF31-1,"") | BH33: =IFERROR(BH31/BG31-1,"") | BI33: =IFERROR(BI31/BH31-1,"") | BK33: =IFERROR(BK31/BI31-1,"") | BL33: =IFERROR(BL31/BK31-1,"") | BM33: =IFERROR(BM31/BL31-1,"") | BN33: =IFERROR(BN31/BM31-1,"") | BP33: =IFERROR(BP31/BN31-1,"") | BQ33: =IFERROR(BQ31/BP31-1,"") | BR33: =IFERROR(BR31/BQ31-1,"") | BS33: =IFERROR(BS31/BR31-1,"") | BU33: =IFERROR(BU31/BS31-1,"") | BV33: =IFERROR(BV31/BU31-1,"") | BW33: =IFERROR(BW31/BV31-1,"") | BX33: =IFERROR(BX31/BW31-1,"") | BZ33: =IFERROR(BZ31/BX31-1,"") | CA33: =IFERROR(CA31/BZ31-1,"") | CB33: =IFERROR(CB31/CA31-1,"") | CC33: =IFERROR(CC31/CB31-1,"") | CE33: =IFERROR(CE31/CC31-1,"") | CF33: =IFERROR(CF31/CE31-1,"") | CG33: =IFERROR(CG31/CF31-1,"") | CH33: =IFERROR(CH31/CG31-1,"") | CJ33: =IFERROR(CJ31/CH31-1,"") | CK33: =IFERROR(CK31/CJ31-1,"") | CL33: =IFERROR(CL31/CK31-1,"") | CM33: =IFERROR(CM31/CL31-1,"") | CO33: =IFERROR(CO31/CM31-1,"") | CP33: =IFERROR(CP31/CO31-1,"") | CQ33: =IFERROR(CQ31/CP31-1,"") | CR33: =IFERROR(CR31/CQ31-1,"") | CT33: =IFERROR(CT31/CR31-1,"") | CU33: =IFERROR(CU31/CT31-1,"") | CV33: =IFERROR(CV31/CU31-1,"") | CW33: =IFERROR(CW31/CV31-1,"") | CY33: =IFERROR(CY31/CW31-1,"") | CZ33: =IFERROR(CZ31/CY31-1,"") | DA33: =IFERROR(DA31/CZ31-1,"") | DB33: =IFERROR(DB31/DA31-1,"") | DI33: =IFERROR(DI31/DG31-1,"") | DJ33: =IFERROR(DJ31/DI31-1,"") | DK33: =IFERROR(DK31/DJ31-1,"") | DL33: =IFERROR(DL31/DK31-1,"") | DN33: =IFERROR(DN31/DL31-1,"") | DO33: =IFERROR(DO31/DN31-1,"") | DP33: =IFERROR(DP31/DO31-1,"") | DQ33: =IFERROR(DQ31/DP31-1,"") | DS33: =IFERROR(DS31/DQ31-1,"") | DT33: =IFERROR(DT31/DS31-1,"") | DU33: =IFERROR(DU31/DT31-1,"") | DV33: =IFERROR(DV31/DU31-1,"") | DX33: =IFERROR(DX31/DV31-1,"") | DY33: =IFERROR(DY31/DX31-1,"") | DZ33: =IFERROR(DZ31/DY31-1,"") | EA33: =IFERROR(EA31/DZ31-1,"") | EC33: =IFERROR(EC31/EA31-1,"") | ED33: =IFERROR(ED31/EC31-1,"") | EE33: =IFERROR(EE31/ED31-1,"") | EF33: =IFERROR(EF31/EE31-1,"") | EH33: =IFERROR(EH31/EF31-1,"") | EI33: =IFERROR(EI31/EH31-1,"") | EJ33: =IFERROR(EJ31/EI31-1,"") | EK33: =IFERROR(EK31/EJ31-1,"") | EM33: =IFERROR(EM31/EK31-1,"") | EN33: =IFERROR(EN31/EM31-1,"") | EO33: =IFERROR(EO31/EN31-1,"") | EP33: =IFERROR(EP31/EO31-1,"") | ER33: =IFERROR(ER31/EP31-1,"") | ES33: =IFERROR(ES31/ER31-1,"") | ET33: =IFERROR(ET31/ES31-1,"") | EU33: =IFERROR(EU31/ET31-1,"") | EW33: =IFERROR(EW31/EU31-1,"") | EX33: =IFERROR(EX31/EW31-1,"") | EY33: =IFERROR(EY31/EX31-1,"") | EZ33: =IFERROR(EZ31/EY31-1,"")
B34: Net New Cost (yoy) | DN34: =DN31-DI31 | DO34: =DO31-DJ31 | DP34: =DP31-DK31 | DQ34: =DQ31-DL31 | DR34: =DR31-DM31 | DS34: =DS31-DN31 | DT34: =DT31-DO31 | DU34: =DU31-DP31 | ... FA34: =FA31-EV31
B35: Net New Cost (qoq) | DJ35: =DJ31-DI31 | DK35: =DK31-DJ31 | DL35: =DL31-DK31 | DN35: =DN31-DL31 | DO35: =DO31-DN31 | DP35: =DP31-DO31 | DQ35: =DQ31-DP31 | DS35: =DS31-DQ31 | DT35: =DT31-DS31 | DU35: =DU31-DT31 | DV35: =DV31-DU31 | DX35: =DX31-DV31 | DY35: =DY31-DX31 | DZ35: =DZ31-DY31 | EA35: =EA31-DZ31 | EC35: =EC31-EA31 | ED35: =ED31-EC31 | EE35: =EE31-ED31 | EF35: =EF31-EE31 | EH35: =EH31-EF31 | EI35: =EI31-EH31 | EJ35: =EJ31-EI31 | EK35: =EK31-EJ31 | EM35: =EM31-EK31 | EN35: =EN31-EM31 | EO35: =EO31-EN31 | EP35: =EP31-EO31 | ER35: =ER31-EP31 | ES35: =ES31-ER31 | ET35: =ET31-ES31 | EU35: =EU31-ET31 | EW35: =EW31-EU31 | EX35: =EX31-EW31 | EY35: =EY31-EX31 | EZ35: =EZ31-EY31
B36: % of Product Revenue | C36: =IFERROR(C31/C10,"") | D36: =IFERROR(D31/D10,"") | E36: =IFERROR(E31/E10,"") | F36: =IFERROR(F31/F10,"") | G36: =IFERROR(G31/G10,"") | H36: =IFERROR(H31/H10,"") | I36: =IFERROR(I31/I10,"") | J36: =IFERROR(J31/J10,"") | ... DC36: =IFERROR(DC31/DC10,"") | DI36: =IFERROR(DI31/DI10,"") | DJ36: =IFERROR(DJ31/DJ10,"") | DK36: =IFERROR(DK31/DK10,"") | DL36: =IFERROR(DL31/DL10,"") | DM36: =IFERROR(DM31/DM10,"") | DN36: =IFERROR(DN31/DN10,"") | DO36: =IFERROR(DO31/DO10,"") | DP36: =IFERROR(DP31/DP10,"") | ... FA36: =IFERROR(FA31/FA10,"")
B38: Service and Other Cost of Revenue | DI38: 4263 | DJ38: 4523 | DK38: 4985 | DL38: 5315 | DM38: =SUM(DI38:DL38) | DN38: 5298 | DO38: 5566 | DP38: 5844 | DQ38: 6225 | DR38: =SUM(DN38:DQ38) | DS38: 6256 | DT38: 6538 | DU38: 6729 | DV38: 7114 | DW38: =SUM(DS38:DV38) | DX38: 7101 | DY38: 7392 | DZ38: 7599 | EA38: 7969 | EB38: =SUM(DX38:EA38) | EC38: 7405 | ED38: 8136 | EE38: 8768 | EF38: 9704 | EG38: =SUM(EC38:EF38) | EH38: 9854 | EI38: 10629 | EJ38: 11031 | EK38: 12072 | EL38: =SUM(EH38:EK38) | EM38: 11150 | EN38: 11798 | EO38: 12187 | EP38: 12924 | EQ38: =SUM(EM38:EP38) | ER38: 12771 | ES38: 13659 | ET38: 14166 | EU38: 18246 | EV38: =SUM(ER38:EU38) | EW38: 16805 | EX38: 17943 | EY38: 18882 | EZ38: 20700 | FA38: =SUM(EW38:EZ38)
B39: % yoy | H39: =IFERROR(H38/C38-1,"") | I39: =IFERROR(I38/D38-1,"") | J39: =IFERROR(J38/E38-1,"") | K39: =IFERROR(K38/F38-1,"") | L39: =IFERROR(L38/G38-1,"") | M39: =IFERROR(M38/H38-1,"") | N39: =IFERROR(N38/I38-1,"") | O39: =IFERROR(O38/J38-1,"") | ... DC39: =IFERROR(DC38/CX38-1,"") | DI39: =IFERROR(DI38/DD38-1,"") | DJ39: =IFERROR(DJ38/DE38-1,"") | DK39: =IFERROR(DK38/DF38-1,"") | DL39: =IFERROR(DL38/DG38-1,"") | DM39: =IFERROR(DM38/DH38-1,"") | DN39: =IFERROR(DN38/DI38-1,"") | DO39: =IFERROR(DO38/DJ38-1,"") | DP39: =IFERROR(DP38/DK38-1,"") | ... FA39: =IFERROR(FA38/EV38-1,"")
B40: % qoq | H40: =IFERROR(H38/F38-1,"") | I40: =IFERROR(I38/H38-1,"") | J40: =IFERROR(J38/I38-1,"") | K40: =IFERROR(K38/J38-1,"") | M40: =IFERROR(M38/K38-1,"") | N40: =IFERROR(N38/M38-1,"") | O40: =IFERROR(O38/N38-1,"") | P40: =IFERROR(P38/O38-1,"") | R40: =IFERROR(R38/P38-1,"") | S40: =IFERROR(S38/R38-1,"") | T40: =IFERROR(T38/S38-1,"") | U40: =IFERROR(U38/T38-1,"") | W40: =IFERROR(W38/U38-1,"") | X40: =IFERROR(X38/W38-1,"") | Y40: =IFERROR(Y38/X38-1,"") | Z40: =IFERROR(Z38/Y38-1,"") | AB40: =IFERROR(AB38/Z38-1,"") | AC40: =IFERROR(AC38/AB38-1,"") | AD40: =IFERROR(AD38/AC38-1,"") | AE40: =IFERROR(AE38/AD38-1,"") | AG40: =IFERROR(AG38/AE38-1,"") | AH40: =IFERROR(AH38/AG38-1,"") | AI40: =IFERROR(AI38/AH38-1,"") | AJ40: =IFERROR(AJ38/AI38-1,"") | AL40: =IFERROR(AL38/AJ38-1,"") | AM40: =IFERROR(AM38/AL38-1,"") | AN40: =IFERROR(AN38/AM38-1,"") | AO40: =IFERROR(AO38/AN38-1,"") | AQ40: =IFERROR(AQ38/AO38-1,"") | AR40: =IFERROR(AR38/AQ38-1,"") | AS40: =IFERROR(AS38/AR38-1,"") | AT40: =IFERROR(AT38/AS38-1,"") | AV40: =IFERROR(AV38/AT38-1,"") | AW40: =IFERROR(AW38/AV38-1,"") | AX40: =IFERROR(AX38/AW38-1,"") | AY40: =IFERROR(AY38/AX38-1,"") | BA40: =IFERROR(BA38/AY38-1,"") | BB40: =IFERROR(BB38/BA38-1,"") | BC40: =IFERROR(BC38/BB38-1,"") | BD40: =IFERROR(BD38/BC38-1,"") | BF40: =IFERROR(BF38/BD38-1,"") | BG40: =IFERROR(BG38/BF38-1,"") | BH40: =IFERROR(BH38/BG38-1,"") | BI40: =IFERROR(BI38/BH38-1,"") | BK40: =IFERROR(BK38/BI38-1,"") | BL40: =IFERROR(BL38/BK38-1,"") | BM40: =IFERROR(BM38/BL38-1,"") | BN40: =IFERROR(BN38/BM38-1,"") | BP40: =IFERROR(BP38/BN38-1,"") | BQ40: =IFERROR(BQ38/BP38-1,"") | BR40: =IFERROR(BR38/BQ38-1,"") | BS40: =IFERROR(BS38/BR38-1,"") | BU40: =IFERROR(BU38/BS38-1,"") | BV40: =IFERROR(BV38/BU38-1,"") | BW40: =IFERROR(BW38/BV38-1,"") | BX40: =IFERROR(BX38/BW38-1,"") | BZ40: =IFERROR(BZ38/BX38-1,"") | CA40: =IFERROR(CA38/BZ38-1,"") | CB40: =IFERROR(CB38/CA38-1,"") | CC40: =IFERROR(CC38/CB38-1,"") | CE40: =IFERROR(CE38/CC38-1,"") | CF40: =IFERROR(CF38/CE38-1,"") | CG40: =IFERROR(CG38/CF38-1,"") | CH40: =IFERROR(CH38/CG38-1,"") | CJ40: =IFERROR(CJ38/CH38-1,"") | CK40: =IFERROR(CK38/CJ38-1,"") | CL40: =IFERROR(CL38/CK38-1,"") | CM40: =IFERROR(CM38/CL38-1,"") | CO40: =IFERROR(CO38/CM38-1,"") | CP40: =IFERROR(CP38/CO38-1,"") | CQ40: =IFERROR(CQ38/CP38-1,"") | CR40: =IFERROR(CR38/CQ38-1,"") | CT40: =IFERROR(CT38/CR38-1,"") | CU40: =IFERROR(CU38/CT38-1,"") | CV40: =IFERROR(CV38/CU38-1,"") | CW40: =IFERROR(CW38/CV38-1,"") | CY40: =IFERROR(CY38/CW38-1,"") | CZ40: =IFERROR(CZ38/CY38-1,"") | DA40: =IFERROR(DA38/CZ38-1,"") | DB40: =IFERROR(DB38/DA38-1,"") | DI40: =IFERROR(DI38/DG38-1,"") | DJ40: =IFERROR(DJ38/DI38-1,"") | DK40: =IFERROR(DK38/DJ38-1,"") | DL40: =IFERROR(DL38/DK38-1,"") | DN40: =IFERROR(DN38/DL38-1,"") | DO40: =IFERROR(DO38/DN38-1,"") | DP40: =IFERROR(DP38/DO38-1,"") | DQ40: =IFERROR(DQ38/DP38-1,"") | DS40: =IFERROR(DS38/DQ38-1,"") | DT40: =IFERROR(DT38/DS38-1,"") | DU40: =IFERROR(DU38/DT38-1,"") | DV40: =IFERROR(DV38/DU38-1,"") | DX40: =IFERROR(DX38/DV38-1,"") | DY40: =IFERROR(DY38/DX38-1,"") | DZ40: =IFERROR(DZ38/DY38-1,"") | EA40: =IFERROR(EA38/DZ38-1,"") | EC40: =IFERROR(EC38/EA38-1,"") | ED40: =IFERROR(ED38/EC38-1,"") | EE40: =IFERROR(EE38/ED38-1,"") | EF40: =IFERROR(EF38/EE38-1,"") | EH40: =IFERROR(EH38/EF38-1,"") | EI40: =IFERROR(EI38/EH38-1,"") | EJ40: =IFERROR(EJ38/EI38-1,"") | EK40: =IFERROR(EK38/EJ38-1,"") | EM40: =IFERROR(EM38/EK38-1,"") | EN40: =IFERROR(EN38/EM38-1,"") | EO40: =IFERROR(EO38/EN38-1,"") | EP40: =IFERROR(EP38/EO38-1,"") | ER40: =IFERROR(ER38/EP38-1,"") | ES40: =IFERROR(ES38/ER38-1,"") | ET40: =IFERROR(ET38/ES38-1,"") | EU40: =IFERROR(EU38/ET38-1,"") | EW40: =IFERROR(EW38/EU38-1,"") | EX40: =IFERROR(EX38/EW38-1,"") | EY40: =IFERROR(EY38/EX38-1,"") | EZ40: =IFERROR(EZ38/EY38-1,"")
B41: Net New Cost (yoy) | DN41: =DN38-DI38 | DO41: =DO38-DJ38 | DP41: =DP38-DK38 | DQ41: =DQ38-DL38 | DR41: =DR38-DM38 | DS41: =DS38-DN38 | DT41: =DT38-DO38 | DU41: =DU38-DP38 | ... FA41: =FA38-EV38
B42: Net New Cost (qoq) | DJ42: =DJ38-DI38 | DK42: =DK38-DJ38 | DL42: =DL38-DK38 | DN42: =DN38-DL38 | DO42: =DO38-DN38 | DP42: =DP38-DO38 | DQ42: =DQ38-DP38 | DS42: =DS38-DQ38 | DT42: =DT38-DS38 | DU42: =DU38-DT38 | DV42: =DV38-DU38 | DX42: =DX38-DV38 | DY42: =DY38-DX38 | DZ42: =DZ38-DY38 | EA42: =EA38-DZ38 | EC42: =EC38-EA38 | ED42: =ED38-EC38 | EE42: =EE38-ED38 | EF42: =EF38-EE38 | EH42: =EH38-EF38 | EI42: =EI38-EH38 | EJ42: =EJ38-EI38 | EK42: =EK38-EJ38 | EM42: =EM38-EK38 | EN42: =EN38-EM38 | EO42: =EO38-EN38 | EP42: =EP38-EO38 | ER42: =ER38-EP38 | ES42: =ES38-ER38 | ET42: =ET38-ES38 | EU42: =EU38-ET38 | EW42: =EW38-EU38 | EX42: =EX38-EW38 | EY42: =EY38-EX38 | EZ42: =EZ38-EY38
B43: % of Service Revenue | C43: =IFERROR(C38/C17,"") | D43: =IFERROR(D38/D17,"") | E43: =IFERROR(E38/E17,"") | F43: =IFERROR(F38/F17,"") | G43: =IFERROR(G38/G17,"") | H43: =IFERROR(H38/H17,"") | I43: =IFERROR(I38/I17,"") | J43: =IFERROR(J38/J17,"") | ... FA43: =IFERROR(FA38/FA17,"")
A45: COGS | B45: Total Cost of Revenue | C45: 186 | D45: 222 | E45: 235 | F45: 234 | G45: =SUM(C45:F45) | H45: 322 | I45: 330 | J45: 295 | K45: 241 | L45: =SUM(H45:K45) | M45: 250 | N45: 296 | O45: 297 | P45: 242 | Q45: =SUM(M45:P45) | R45: 253 | S45: 313 | T45: 317 | U45: 314 | V45: =SUM(R45:U45) | W45: 649 | X45: 788 | Y45: 708 | Z45: 669 | AA45: =SUM(W45:Z45) | AB45: 712 | AC45: 756 | AD45: 752 | AE45: 782 | AF45: =SUM(AB45:AE45) | AG45: 825 | AH45: 864 | AI45: 899 | AJ45: 867 | AK45: =SUM(AG45:AJ45) | AL45: 884 | AM45: 1544 | AN45: 1395 | AO45: 1368 | AP45: =SUM(AL45:AO45) | AQ45: 1344 | AR45: 2137 | AS45: 1274 | AT45: 1304 | AU45: =SUM(AQ45:AT45) | AV45: 1480 | AW45: 2344 | AX45: 1411 | AY45: 1481 | AZ45: =SUM(AV45:AY45) | BA45: 1405 | BB45: 1875 | BC45: 1363 | BD45: =6200-BC45-BB45-BA45 | BE45: =SUM(BA45:BD45) | BF45: 1253 | BG45: 2239 | BH45: 2028 | BI45: 2130 | BJ45: =SUM(BF45:BI45) | BK45: 1696 | BL45: 3620 | BM45: 2140 | BN45: 3237 | BO45: =SUM(BK45:BN45) | BP45: 2675 | BQ45: 3543 | BR45: 2514 | BS45: 2866 | BT45: =SUM(BP45:BS45) | BU45: 2848 | BV45: 3907 | BW45: 2814 | BX45: 2586 | BY45: =SUM(BU45:BX45) | BZ45: 2842 | CA45: 3628 | CB45: 2755 | CC45: 3170 | CD45: =SUM(BZ45:CC45) | CE45: 3139 | CF45: 4833 | CG45: 3897 | CH45: 3708 | CI45: =SUM(CE45:CH45) | CJ45: 3777 | CK45: 5638 | CL45: 3952 | CM45: 4163 | CN45: =SUM(CJ45:CM45) | CO45: 4168 | CP45: 5692 | CQ45: 4787 | CR45: 5602 | CS45: =SUM(CO45:CR45) | CT45: 5145 | CU45: 8322 | CV45: 5978 | CW45: 7633 | CX45: =SUM(CT45:CW45) | CY45: 8273 | CZ45: 10136 | DA45: 7161 | DB45: 7468 | DC45: =SUM(CY45:DB45) | DD45: 7207 | DE45: 9872 | DF45: 7722 | DG45: 7979 | DH45: =SUM(DD45:DG45) | DI45: =DI38+DI31 | DJ45: =DJ38+DJ31 | DK45: =DK38+DK31 | DL45: =DL38+DL31 | DM45: =SUM(DI45:DL45) | DN45: =DN38+DN31 | DO45: =DO38+DO31 | DP45: =DP38+DP31 | DQ45: =DQ38+DQ31 | DR45: =SUM(DN45:DQ45) | DS45: =DS38+DS31 | DT45: =DT38+DT31 | DU45: =DU38+DU31 | DV45: =DV38+DV31 | DW45: =SUM(DS45:DV45) | DX45: =DX38+DX31 | DY45: =DY38+DY31 | DZ45: =DZ38+DZ31 | EA45: =EA38+EA31 | EB45: =SUM(DX45:EA45) | EC45: =EC38+EC31 | ED45: =ED38+ED31 | EE45: =EE38+EE31 | EF45: =EF38+EF31 | EG45: =SUM(EC45:EF45) | EH45: =EH38+EH31 | EI45: =EI38+EI31 | EJ45: =EJ38+EJ31 | EK45: =EK38+EK31 | EL45: =SUM(EH45:EK45) | EM45: =EM38+EM31 | EN45: =EN38+EN31 | EO45: =EO38+EO31 | EP45: =EP38+EP31 | EQ45: =SUM(EM45:EP45) | ER45: =ER38+ER31 | ES45: =ES38+ES31 | ET45: =ET38+ET31 | EU45: =EU38+EU31 | EV45: =SUM(ER45:EU45) | EW45: =EW38+EW31 | EX45: =EX38+EX31 | EY45: =EY38+EY31 | EZ45: =EZ38+EZ31 | FA45: =SUM(EW45:EZ45) | FB45: =FB24-FB66 | FC45: =FC24-FC66 | FD45: =FD24-FD66 | FE45: =FE24-FE66 | FF45: =SUM(FB45:FE45) | FG45: =FG24-FG66 | FH45: =FH24-FH66 | FI45: =FI24-FI66 | FJ45: =FJ24-FJ66 | FK45: =SUM(FG45:FJ45) | FL45: =FL24-FL66 | FM45: =FM24-FM66 | FN45: =FN24-FN66 | FO45: =FO24-FO66 | FP45: =SUM(FL45:FO45) | FQ45: =FQ24-FQ66 | FR45: =FR24-FR66 | FS45: =FS24-FS66 | FT45: =FT24-FT66 | FU45: =SUM(FQ45:FT45) | FV45: =FV24-FV66 | FW45: =FW24-FW66 | FX45: =FX24-FX66 | FY45: =FY24-FY66 | FZ45: =SUM(FV45:FY45) | GA45: =GA24-GA66 | GB45: =GB24-GB66 | GC45: =GC24-GC66 | GD45: =GD24-GD66 | GE45: =SUM(GA45:GD45) | GF45: =GF24-GF66 | GG45: =GG24-GG66 | GH45: =GH24-GH66 | GI45: =GI24-GI66 | GJ45: =SUM(GF45:GI45)
A46: COGSYY | B46: % yoy | H46: =IFERROR(H45/C45-1,"") | I46: =IFERROR(I45/D45-1,"") | J46: =IFERROR(J45/E45-1,"") | K46: =IFERROR(K45/F45-1,"") | L46: =IFERROR(L45/G45-1,"") | M46: =IFERROR(M45/H45-1,"") | N46: =IFERROR(N45/I45-1,"") | O46: =IFERROR(O45/J45-1,"") | ... GJ46: =IFERROR(GJ45/GE45-1,"")
A47: COGSQQ | B47: % qoq | H47: =IFERROR(H45/F45-1,"") | I47: =IFERROR(I45/H45-1,"") | J47: =IFERROR(J45/I45-1,"") | K47: =IFERROR(K45/J45-1,"") | M47: =IFERROR(M45/K45-1,"") | N47: =IFERROR(N45/M45-1,"") | O47: =IFERROR(O45/N45-1,"") | P47: =IFERROR(P45/O45-1,"") | R47: =IFERROR(R45/P45-1,"") | S47: =IFERROR(S45/R45-1,"") | T47: =IFERROR(T45/S45-1,"") | U47: =IFERROR(U45/T45-1,"") | W47: =IFERROR(W45/U45-1,"") | X47: =IFERROR(X45/W45-1,"") | Y47: =IFERROR(Y45/X45-1,"") | Z47: =IFERROR(Z45/Y45-1,"") | AB47: =IFERROR(AB45/Z45-1,"") | AC47: =IFERROR(AC45/AB45-1,"") | AD47: =IFERROR(AD45/AC45-1,"") | AE47: =IFERROR(AE45/AD45-1,"") | AG47: =IFERROR(AG45/AE45-1,"") | AH47: =IFERROR(AH45/AG45-1,"") | AI47: =IFERROR(AI45/AH45-1,"") | AJ47: =IFERROR(AJ45/AI45-1,"") | AL47: =IFERROR(AL45/AJ45-1,"") | AM47: =IFERROR(AM45/AL45-1,"") | AN47: =IFERROR(AN45/AM45-1,"") | AO47: =IFERROR(AO45/AN45-1,"") | AQ47: =IFERROR(AQ45/AO45-1,"") | AR47: =IFERROR(AR45/AQ45-1,"") | AS47: =IFERROR(AS45/AR45-1,"") | AT47: =IFERROR(AT45/AS45-1,"") | AV47: =IFERROR(AV45/AT45-1,"") | AW47: =IFERROR(AW45/AV45-1,"") | AX47: =IFERROR(AX45/AW45-1,"") | AY47: =IFERROR(AY45/AX45-1,"") | BA47: =IFERROR(BA45/AY45-1,"") | BB47: =IFERROR(BB45/BA45-1,"") | BC47: =IFERROR(BC45/BB45-1,"") | BD47: =IFERROR(BD45/BC45-1,"") | BF47: =IFERROR(BF45/BD45-1,"") | BG47: =IFERROR(BG45/BF45-1,"") | BH47: =IFERROR(BH45/BG45-1,"") | BI47: =IFERROR(BI45/BH45-1,"") | BK47: =IFERROR(BK45/BI45-1,"") | BL47: =IFERROR(BL45/BK45-1,"") | BM47: =IFERROR(BM45/BL45-1,"") | BN47: =IFERROR(BN45/BM45-1,"") | BP47: =IFERROR(BP45/BN45-1,"") | BQ47: =IFERROR(BQ45/BP45-1,"") | BR47: =IFERROR(BR45/BQ45-1,"") | BS47: =IFERROR(BS45/BR45-1,"") | BU47: =IFERROR(BU45/BS45-1,"") | BV47: =IFERROR(BV45/BU45-1,"") | BW47: =IFERROR(BW45/BV45-1,"") | BX47: =IFERROR(BX45/BW45-1,"") | BZ47: =IFERROR(BZ45/BX45-1,"") | CA47: =IFERROR(CA45/BZ45-1,"") | CB47: =IFERROR(CB45/CA45-1,"") | CC47: =IFERROR(CC45/CB45-1,"") | CE47: =IFERROR(CE45/CC45-1,"") | CF47: =IFERROR(CF45/CE45-1,"") | CG47: =IFERROR(CG45/CF45-1,"") | CH47: =IFERROR(CH45/CG45-1,"") | CJ47: =IFERROR(CJ45/CH45-1,"") | CK47: =IFERROR(CK45/CJ45-1,"") | CL47: =IFERROR(CL45/CK45-1,"") | CM47: =IFERROR(CM45/CL45-1,"") | CO47: =IFERROR(CO45/CM45-1,"") | CP47: =IFERROR(CP45/CO45-1,"") | CQ47: =IFERROR(CQ45/CP45-1,"") | CR47: =IFERROR(CR45/CQ45-1,"") | CT47: =IFERROR(CT45/CR45-1,"") | CU47: =IFERROR(CU45/CT45-1,"") | CV47: =IFERROR(CV45/CU45-1,"") | CW47: =IFERROR(CW45/CV45-1,"") | CY47: =IFERROR(CY45/CW45-1,"") | CZ47: =IFERROR(CZ45/CY45-1,"") | DA47: =IFERROR(DA45/CZ45-1,"") | DB47: =IFERROR(DB45/DA45-1,"") | DD47: =IFERROR(DD45/DB45-1,"") | DE47: =IFERROR(DE45/DD45-1,"") | DF47: =IFERROR(DF45/DE45-1,"") | DG47: =IFERROR(DG45/DF45-1,"") | DI47: =IFERROR(DI45/DG45-1,"") | DJ47: =IFERROR(DJ45/DI45-1,"") | DK47: =IFERROR(DK45/DJ45-1,"") | DL47: =IFERROR(DL45/DK45-1,"") | DN47: =IFERROR(DN45/DL45-1,"") | DO47: =IFERROR(DO45/DN45-1,"") | DP47: =IFERROR(DP45/DO45-1,"") | DQ47: =IFERROR(DQ45/DP45-1,"") | DS47: =IFERROR(DS45/DQ45-1,"") | DT47: =IFERROR(DT45/DS45-1,"") | DU47: =IFERROR(DU45/DT45-1,"") | DV47: =IFERROR(DV45/DU45-1,"") | DX47: =IFERROR(DX45/DV45-1,"") | DY47: =IFERROR(DY45/DX45-1,"") | DZ47: =IFERROR(DZ45/DY45-1,"") | EA47: =IFERROR(EA45/DZ45-1,"") | EC47: =IFERROR(EC45/EA45-1,"") | ED47: =IFERROR(ED45/EC45-1,"") | EE47: =IFERROR(EE45/ED45-1,"") | EF47: =IFERROR(EF45/EE45-1,"") | EH47: =IFERROR(EH45/EF45-1,"") | EI47: =IFERROR(EI45/EH45-1,"") | EJ47: =IFERROR(EJ45/EI45-1,"") | EK47: =IFERROR(EK45/EJ45-1,"") | EM47: =IFERROR(EM45/EK45-1,"") | EN47: =IFERROR(EN45/EM45-1,"") | EO47: =IFERROR(EO45/EN45-1,"") | EP47: =IFERROR(EP45/EO45-1,"") | ER47: =IFERROR(ER45/EP45-1,"") | ES47: =IFERROR(ES45/ER45-1,"") | ET47: =IFERROR(ET45/ES45-1,"") | EU47: =IFERROR(EU45/ET45-1,"") | EW47: =IFERROR(EW45/EU45-1,"") | EX47: =IFERROR(EX45/EW45-1,"") | EY47: =IFERROR(EY45/EX45-1,"") | EZ47: =IFERROR(EZ45/EY45-1,"") | FB47: =IFERROR(FB45/EZ45-1,"") | FC47: =IFERROR(FC45/FB45-1,"") | FD47: =IFERROR(FD45/FC45-1,"") | FE47: =IFERROR(FE45/FD45-1,"") | FG47: =IFERROR(FG45/FE45-1,"") | FH47: =IFERROR(FH45/FG45-1,"") | FI47: =IFERROR(FI45/FH45-1,"") | FJ47: =IFERROR(FJ45/FI45-1,"") | FL47: =IFERROR(FL45/FJ45-1,"") | FM47: =IFERROR(FM45/FL45-1,"") | FN47: =IFERROR(FN45/FM45-1,"") | FO47: =IFERROR(FO45/FN45-1,"") | FQ47: =IFERROR(FQ45/FO45-1,"") | FR47: =IFERROR(FR45/FQ45-1,"") | FS47: =IFERROR(FS45/FR45-1,"") | FT47: =IFERROR(FT45/FS45-1,"") | FV47: =IFERROR(FV45/FT45-1,"") | FW47: =IFERROR(FW45/FV45-1,"") | FX47: =IFERROR(FX45/FW45-1,"") | FY47: =IFERROR(FY45/FX45-1,"") | GA47: =IFERROR(GA45/FY45-1,"") | GB47: =IFERROR(GB45/GA45-1,"") | GC47: =IFERROR(GC45/GB45-1,"") | GD47: =IFERROR(GD45/GC45-1,"") | GF47: =IFERROR(GF45/GD45-1,"") | GG47: =IFERROR(GG45/GF45-1,"") | GH47: =IFERROR(GH45/GG45-1,"") | GI47: =IFERROR(GI45/GH45-1,"")
B48: Net New Cost (yoy) | H48: =H45-C45 | I48: =I45-D45 | J48: =J45-E45 | K48: =K45-F45 | L48: =L45-G45 | M48: =M45-H45 | N48: =N45-I45 | O48: =O45-J45 | ... GJ48: =GJ45-GE45
B49: Net New Cost (qoq) | D49: =D45-C45 | E49: =E45-D45 | F49: =F45-E45 | H49: =H45-F45 | I49: =I45-H45 | J49: =J45-I45 | K49: =K45-J45 | M49: =M45-K45 | N49: =N45-M45 | O49: =O45-N45 | P49: =P45-O45 | R49: =R45-P45 | S49: =S45-R45 | T49: =T45-S45 | U49: =U45-T45 | W49: =W45-U45 | X49: =X45-W45 | Y49: =Y45-X45 | Z49: =Z45-Y45 | AB49: =AB45-Z45 | AC49: =AC45-AB45 | AD49: =AD45-AC45 | AE49: =AE45-AD45 | AG49: =AG45-AE45 | AH49: =AH45-AG45 | AI49: =AI45-AH45 | AJ49: =AJ45-AI45 | AL49: =AL45-AJ45 | AM49: =AM45-AL45 | AN49: =AN45-AM45 | AO49: =AO45-AN45 | AQ49: =AQ45-AO45 | AR49: =AR45-AQ45 | AS49: =AS45-AR45 | AT49: =AT45-AS45 | AV49: =AV45-AT45 | AW49: =AW45-AV45 | AX49: =AX45-AW45 | AY49: =AY45-AX45 | BA49: =BA45-AY45 | BB49: =BB45-BA45 | BC49: =BC45-BB45 | BD49: =BD45-BC45 | BF49: =BF45-BD45 | BG49: =BG45-BF45 | BH49: =BH45-BG45 | BI49: =BI45-BH45 | BK49: =BK45-BI45 | BL49: =BL45-BK45 | BM49: =BM45-BL45 | BN49: =BN45-BM45 | BP49: =BP45-BN45 | BQ49: =BQ45-BP45 | BR49: =BR45-BQ45 | BS49: =BS45-BR45 | BU49: =BU45-BS45 | BV49: =BV45-BU45 | BW49: =BW45-BV45 | BX49: =BX45-BW45 | BZ49: =BZ45-BX45 | CA49: =CA45-BZ45 | CB49: =CB45-CA45 | CC49: =CC45-CB45 | CE49: =CE45-CC45 | CF49: =CF45-CE45 | CG49: =CG45-CF45 | CH49: =CH45-CG45 | CJ49: =CJ45-CH45 | CK49: =CK45-CJ45 | CL49: =CL45-CK45 | CM49: =CM45-CL45 | CO49: =CO45-CM45 | CP49: =CP45-CO45 | CQ49: =CQ45-CP45 | CR49: =CR45-CQ45 | CT49: =CT45-CR45 | CU49: =CU45-CT45 | CV49: =CV45-CU45 | CW49: =CW45-CV45 | CY49: =CY45-CW45 | CZ49: =CZ45-CY45 | DA49: =DA45-CZ45 | DB49: =DB45-DA45 | DD49: =DD45-DB45 | DE49: =DE45-DD45 | DF49: =DF45-DE45 | DG49: =DG45-DF45 | DI49: =DI45-DG45 | DJ49: =DJ45-DI45 | DK49: =DK45-DJ45 | DL49: =DL45-DK45 | DN49: =DN45-DL45 | DO49: =DO45-DN45 | DP49: =DP45-DO45 | DQ49: =DQ45-DP45 | DS49: =DS45-DQ45 | DT49: =DT45-DS45 | DU49: =DU45-DT45 | DV49: =DV45-DU45 | DX49: =DX45-DV45 | DY49: =DY45-DX45 | DZ49: =DZ45-DY45 | EA49: =EA45-DZ45 | EC49: =EC45-EA45 | ED49: =ED45-EC45 | EE49: =EE45-ED45 | EF49: =EF45-EE45 | EH49: =EH45-EF45 | EI49: =EI45-EH45 | EJ49: =EJ45-EI45 | EK49: =EK45-EJ45 | EM49: =EM45-EK45 | EN49: =EN45-EM45 | EO49: =EO45-EN45 | EP49: =EP45-EO45 | ER49: =ER45-EP45 | ES49: =ES45-ER45 | ET49: =ET45-ES45 | EU49: =EU45-ET45 | EW49: =EW45-EU45 | EX49: =EX45-EW45 | EY49: =EY45-EX45 | EZ49: =EZ45-EY45 | FB49: =FB45-EZ45 | FC49: =FC45-FB45 | FD49: =FD45-FC45 | FE49: =FE45-FD45 | FG49: =FG45-FE45 | FH49: =FH45-FG45 | FI49: =FI45-FH45 | FJ49: =FJ45-FI45 | FL49: =FL45-FJ45 | FM49: =FM45-FL45 | FN49: =FN45-FM45 | FO49: =FO45-FN45 | FQ49: =FQ45-FO45 | FR49: =FR45-FQ45 | FS49: =FS45-FR45 | FT49: =FT45-FS45 | FV49: =FV45-FT45 | FW49: =FW45-FV45 | FX49: =FX45-FW45 | FY49: =FY45-FX45 | GA49: =GA45-FY45 | GB49: =GB45-GA45 | GC49: =GC45-GB45 | GD49: =GD45-GC45 | GF49: =GF45-GD45 | GG49: =GG45-GF45 | GH49: =GH45-GG45 | GI49: =GI45-GH45
A51: COGS | B51: PBP Gross Profit | CY51: =PBP!CY58 | CZ51: =PBP!CZ58 | DA51: =PBP!DA58 | DB51: =PBP!DB58 | DC51: =PBP!DC58 | DD51: =PBP!DD58 | DE51: =PBP!DE58 | DF51: =PBP!DF58 | ... EQ51: =PBP!EQ58 | ER51: =PBP!ER23 | ES51: =PBP!ES23 | ET51: =PBP!ET23 | EU51: =PBP!EU23 | EV51: =PBP!EV23 | EW51: =PBP!EW23 | EX51: =PBP!EX23 | EY51: =PBP!EY23 | ... GJ51: =PBP!GJ23
A52: COGSYY | B52: % yoy | CY52: =IFERROR(CY51/CT51-1,"") | CZ52: =IFERROR(CZ51/CU51-1,"") | DA52: =IFERROR(DA51/CV51-1,"") | DB52: =IFERROR(DB51/CW51-1,"") | DC52: =IFERROR(DC51/CX51-1,"") | DD52: =IFERROR(DD51/CY51-1,"") | DE52: =IFERROR(DE51/CZ51-1,"") | DF52: =IFERROR(DF51/DA51-1,"") | ... GJ52: =IFERROR(GJ51/GE51-1,"")
A53: COGSQQ | B53: % qoq | CY53: =IFERROR(CY51/CW51-1,"") | CZ53: =IFERROR(CZ51/CY51-1,"") | DA53: =IFERROR(DA51/CZ51-1,"") | DB53: =IFERROR(DB51/DA51-1,"") | DD53: =IFERROR(DD51/DB51-1,"") | DE53: =IFERROR(DE51/DD51-1,"") | DF53: =IFERROR(DF51/DE51-1,"") | DG53: =IFERROR(DG51/DF51-1,"") | DI53: =IFERROR(DI51/DG51-1,"") | DJ53: =IFERROR(DJ51/DI51-1,"") | DK53: =IFERROR(DK51/DJ51-1,"") | DL53: =IFERROR(DL51/DK51-1,"") | DN53: =IFERROR(DN51/DL51-1,"") | DO53: =IFERROR(DO51/DN51-1,"") | DP53: =IFERROR(DP51/DO51-1,"") | DQ53: =IFERROR(DQ51/DP51-1,"") | DS53: =IFERROR(DS51/DQ51-1,"") | DT53: =IFERROR(DT51/DS51-1,"") | DU53: =IFERROR(DU51/DT51-1,"") | DV53: =IFERROR(DV51/DU51-1,"") | DX53: =IFERROR(DX51/DV51-1,"") | DY53: =IFERROR(DY51/DX51-1,"") | DZ53: =IFERROR(DZ51/DY51-1,"") | EA53: =IFERROR(EA51/DZ51-1,"") | EC53: =IFERROR(EC51/EA51-1,"") | ED53: =IFERROR(ED51/EC51-1,"") | EE53: =IFERROR(EE51/ED51-1,"") | EF53: =IFERROR(EF51/EE51-1,"") | EH53: =IFERROR(EH51/EF51-1,"") | EI53: =IFERROR(EI51/EH51-1,"") | EJ53: =IFERROR(EJ51/EI51-1,"") | EK53: =IFERROR(EK51/EJ51-1,"") | EM53: =IFERROR(EM51/EK51-1,"") | EN53: =IFERROR(EN51/EM51-1,"") | EO53: =IFERROR(EO51/EN51-1,"") | EP53: =IFERROR(EP51/EO51-1,"") | ER53: =IFERROR(ER51/EP51-1,"") | ES53: =IFERROR(ES51/ER51-1,"") | ET53: =IFERROR(ET51/ES51-1,"") | EU53: =IFERROR(EU51/ET51-1,"") | EW53: =IFERROR(EW51/EU51-1,"") | EX53: =IFERROR(EX51/EV51-1,"") | EY53: =IFERROR(EY51/EX51-1,"") | EZ53: =IFERROR(EZ51/EY51-1,"") | FB53: =IFERROR(FB51/EZ51-1,"") | FC53: =IFERROR(FC51/FB51-1,"") | FD53: =IFERROR(FD51/FC51-1,"") | FE53: =IFERROR(FE51/FD51-1,"") | FG53: =IFERROR(FG51/FE51-1,"") | FH53: =IFERROR(FH51/FG51-1,"") | FI53: =IFERROR(FI51/FH51-1,"") | FJ53: =IFERROR(FJ51/FI51-1,"") | FL53: =IFERROR(FL51/FJ51-1,"") | FM53: =IFERROR(FM51/FL51-1,"") | FN53: =IFERROR(FN51/FM51-1,"") | FO53: =IFERROR(FO51/FN51-1,"") | FQ53: =IFERROR(FQ51/FO51-1,"") | FR53: =IFERROR(FR51/FQ51-1,"") | FS53: =IFERROR(FS51/FR51-1,"") | FT53: =IFERROR(FT51/FS51-1,"") | FV53: =IFERROR(FV51/FT51-1,"") | FW53: =IFERROR(FW51/FV51-1,"") | FX53: =IFERROR(FX51/FW51-1,"") | FY53: =IFERROR(FY51/FX51-1,"") | GA53: =IFERROR(GA51/FY51-1,"") | GB53: =IFERROR(GB51/GA51-1,"") | GC53: =IFERROR(GC51/GB51-1,"") | GD53: =IFERROR(GD51/GC51-1,"") | GF53: =IFERROR(GF51/GD51-1,"") | GG53: =IFERROR(GG51/GF51-1,"") | GH53: =IFERROR(GH51/GG51-1,"") | GI53: =IFERROR(GI51/GH51-1,"")
B54: Gross Margin | CY54: =PBP!CY63 | CZ54: =PBP!CZ63 | DA54: =PBP!DA63 | DB54: =PBP!DB63 | DC54: =PBP!DC63 | DD54: =PBP!DD63 | DE54: =PBP!DE63 | DF54: =PBP!DF63 | ... EQ54: =PBP!EQ63 | ER54: =PBP!ER28 | ES54: =PBP!ES28 | ET54: =PBP!ET28 | EU54: =PBP!EU28 | EV54: =PBP!EV28 | EW54: =PBP!EW28 | EX54: =PBP!EX28 | EY54: =PBP!EY28 | ... GJ54: =PBP!GJ28
A56: COGS | B56: IC Gross Profit | CY56: =IC!CY58 | CZ56: =IC!CZ58 | DA56: =IC!DA58 | DB56: =IC!DB58 | DC56: =IC!DC58 | DD56: =IC!DD58 | DE56: =IC!DE58 | DF56: =IC!DF58 | ... EQ56: =IC!EQ58 | ER56: =IC!ER23 | ES56: =IC!ES23 | ET56: =IC!ET23 | EU56: =IC!EU23 | EV56: =IC!EV23 | EW56: =IC!EW23 | EX56: =IC!EX23 | EY56: =IC!EY23 | ... GJ56: =IC!GJ23
A57: COGSYY | B57: % yoy | CY57: =IFERROR(CY56/CT56-1,"") | CZ57: =IFERROR(CZ56/CU56-1,"") | DA57: =IFERROR(DA56/CV56-1,"") | DB57: =IFERROR(DB56/CW56-1,"") | DC57: =IFERROR(DC56/CX56-1,"") | DD57: =IFERROR(DD56/CY56-1,"") | DE57: =IFERROR(DE56/CZ56-1,"") | DF57: =IFERROR(DF56/DA56-1,"") | ... GJ57: =IFERROR(GJ56/GE56-1,"")
A58: COGSQQ | B58: % qoq | CY58: =IFERROR(CY56/CW56-1,"") | CZ58: =IFERROR(CZ56/CY56-1,"") | DA58: =IFERROR(DA56/CZ56-1,"") | DB58: =IFERROR(DB56/DA56-1,"") | DD58: =IFERROR(DD56/DB56-1,"") | DE58: =IFERROR(DE56/DD56-1,"") | DF58: =IFERROR(DF56/DE56-1,"") | DG58: =IFERROR(DG56/DF56-1,"") | DI58: =IFERROR(DI56/DG56-1,"") | DJ58: =IFERROR(DJ56/DI56-1,"") | DK58: =IFERROR(DK56/DJ56-1,"") | DL58: =IFERROR(DL56/DK56-1,"") | DN58: =IFERROR(DN56/DL56-1,"") | DO58: =IFERROR(DO56/DN56-1,"") | DP58: =IFERROR(DP56/DO56-1,"") | DQ58: =IFERROR(DQ56/DP56-1,"") | DS58: =IFERROR(DS56/DQ56-1,"") | DT58: =IFERROR(DT56/DS56-1,"") | DU58: =IFERROR(DU56/DT56-1,"") | DV58: =IFERROR(DV56/DU56-1,"") | DX58: =IFERROR(DX56/DV56-1,"") | DY58: =IFERROR(DY56/DX56-1,"") | DZ58: =IFERROR(DZ56/DY56-1,"") | EA58: =IFERROR(EA56/DZ56-1,"") | EC58: =IFERROR(EC56/EA56-1,"") | ED58: =IFERROR(ED56/EC56-1,"") | EE58: =IFERROR(EE56/ED56-1,"") | EF58: =IFERROR(EF56/EE56-1,"") | EH58: =IFERROR(EH56/EF56-1,"") | EI58: =IFERROR(EI56/EH56-1,"") | EJ58: =IFERROR(EJ56/EI56-1,"") | EK58: =IFERROR(EK56/EJ56-1,"") | EM58: =IFERROR(EM56/EK56-1,"") | EN58: =IFERROR(EN56/EM56-1,"") | EO58: =IFERROR(EO56/EN56-1,"") | EP58: =IFERROR(EP56/EO56-1,"") | ER58: =IFERROR(ER56/EP56-1,"") | ES58: =IFERROR(ES56/ER56-1,"") | ET58: =IFERROR(ET56/ES56-1,"") | EU58: =IFERROR(EU56/ET56-1,"") | EW58: =IFERROR(EW56/EU56-1,"") | EX58: =IFERROR(EX56/EV56-1,"") | EY58: =IFERROR(EY56/EX56-1,"") | EZ58: =IFERROR(EZ56/EY56-1,"") | FB58: =IFERROR(FB56/EZ56-1,"") | FC58: =IFERROR(FC56/FB56-1,"") | FD58: =IFERROR(FD56/FC56-1,"") | FE58: =IFERROR(FE56/FD56-1,"") | FG58: =IFERROR(FG56/FE56-1,"") | FH58: =IFERROR(FH56/FG56-1,"") | FI58: =IFERROR(FI56/FH56-1,"") | FJ58: =IFERROR(FJ56/FI56-1,"") | FL58: =IFERROR(FL56/FJ56-1,"") | FM58: =IFERROR(FM56/FL56-1,"") | FN58: =IFERROR(FN56/FM56-1,"") | FO58: =IFERROR(FO56/FN56-1,"") | FQ58: =IFERROR(FQ56/FO56-1,"") | FR58: =IFERROR(FR56/FQ56-1,"") | FS58: =IFERROR(FS56/FR56-1,"") | FT58: =IFERROR(FT56/FS56-1,"") | FV58: =IFERROR(FV56/FT56-1,"") | FW58: =IFERROR(FW56/FV56-1,"") | FX58: =IFERROR(FX56/FW56-1,"") | FY58: =IFERROR(FY56/FX56-1,"") | GA58: =IFERROR(GA56/FY56-1,"") | GB58: =IFERROR(GB56/GA56-1,"") | GC58: =IFERROR(GC56/GB56-1,"") | GD58: =IFERROR(GD56/GC56-1,"") | GF58: =IFERROR(GF56/GD56-1,"") | GG58: =IFERROR(GG56/GF56-1,"") | GH58: =IFERROR(GH56/GG56-1,"") | GI58: =IFERROR(GI56/GH56-1,"")
B59: Gross Margin | CY59: =IC!CY63 | CZ59: =IC!CZ63 | DA59: =IC!DA63 | DB59: =IC!DB63 | DC59: =IC!DC63 | DD59: =IC!DD63 | DE59: =IC!DE63 | DF59: =IC!DF63 | ... EQ59: =IC!EQ63 | ER59: =IC!ER28 | ES59: =IC!ES28 | ET59: =IC!ET28 | EU59: =IC!EU28 | EV59: =IC!EV28 | EW59: =IC!EW28 | EX59: =IC!EX28 | EY59: =IC!EY28 | ... GJ59: =IC!GJ28
A61: COGS | B61: Company1738 Gross Profit | CY61: =Company1738!CY58 | CZ61: =Company1738!CZ58 | DA61: =Company1738!DA58 | DB61: =Company1738!DB58 | DC61: =Company1738!DC58 | DD61: =Company1738!DD58 | DE61: =Company1738!DE58 | DF61: =Company1738!DF58 | ... EQ61: =Company1738!EQ58 | ER61: =Company1738!ER23 | ES61: =Company1738!ES23 | ET61: =Company1738!ET23 | EU61: =Company1738!EU23 | EV61: =Company1738!EV23 | EW61: =Company1738!EW23 | EX61: =Company1738!EX23 | EY61: =Company1738!EY23 | ... GJ61: =Company1738!GJ23
A62: COGSYY | B62: % yoy | CY62: =IFERROR(CY61/CT61-1,"") | CZ62: =IFERROR(CZ61/CU61-1,"") | DA62: =IFERROR(DA61/CV61-1,"") | DB62: =IFERROR(DB61/CW61-1,"") | DC62: =IFERROR(DC61/CX61-1,"") | DD62: =IFERROR(DD61/CY61-1,"") | DE62: =IFERROR(DE61/CZ61-1,"") | DF62: =IFERROR(DF61/DA61-1,"") | ... GJ62: =IFERROR(GJ61/GE61-1,"")
A63: COGSQQ | B63: % qoq | CY63: =IFERROR(CY61/CW61-1,"") | CZ63: =IFERROR(CZ61/CY61-1,"") | DA63: =IFERROR(DA61/CZ61-1,"") | DB63: =IFERROR(DB61/DA61-1,"") | DD63: =IFERROR(DD61/DB61-1,"") | DE63: =IFERROR(DE61/DD61-1,"") | DF63: =IFERROR(DF61/DE61-1,"") | DG63: =IFERROR(DG61/DF61-1,"") | DI63: =IFERROR(DI61/DG61-1,"") | DJ63: =IFERROR(DJ61/DI61-1,"") | DK63: =IFERROR(DK61/DJ61-1,"") | DL63: =IFERROR(DL61/DK61-1,"") | DN63: =IFERROR(DN61/DL61-1,"") | DO63: =IFERROR(DO61/DN61-1,"") | DP63: =IFERROR(DP61/DO61-1,"") | DQ63: =IFERROR(DQ61/DP61-1,"") | DS63: =IFERROR(DS61/DQ61-1,"") | DT63: =IFERROR(DT61/DS61-1,"") | DU63: =IFERROR(DU61/DT61-1,"") | DV63: =IFERROR(DV61/DU61-1,"") | DX63: =IFERROR(DX61/DV61-1,"") | DY63: =IFERROR(DY61/DX61-1,"") | DZ63: =IFERROR(DZ61/DY61-1,"") | EA63: =IFERROR(EA61/DZ61-1,"") | EC63: =IFERROR(EC61/EA61-1,"") | ED63: =IFERROR(ED61/EC61-1,"") | EE63: =IFERROR(EE61/ED61-1,"") | EF63: =IFERROR(EF61/EE61-1,"") | EH63: =IFERROR(EH61/EF61-1,"") | EI63: =IFERROR(EI61/EH61-1,"") | EJ63: =IFERROR(EJ61/EI61-1,"") | EK63: =IFERROR(EK61/EJ61-1,"") | EM63: =IFERROR(EM61/EK61-1,"") | EN63: =IFERROR(EN61/EM61-1,"") | EO63: =IFERROR(EO61/EN61-1,"") | EP63: =IFERROR(EP61/EO61-1,"") | ER63: =IFERROR(ER61/EP61-1,"") | ES63: =IFERROR(ES61/ER61-1,"") | ET63: =IFERROR(ET61/ES61-1,"") | EU63: =IFERROR(EU61/ET61-1,"") | EW63: =IFERROR(EW61/EU61-1,"") | EX63: =IFERROR(EX61/EV61-1,"") | EY63: =IFERROR(EY61/EX61-1,"") | EZ63: =IFERROR(EZ61/EY61-1,"") | FB63: =IFERROR(FB61/EZ61-1,"") | FC63: =IFERROR(FC61/FB61-1,"") | FD63: =IFERROR(FD61/FC61-1,"") | FE63: =IFERROR(FE61/FD61-1,"") | FG63: =IFERROR(FG61/FE61-1,"") | FH63: =IFERROR(FH61/FG61-1,"") | FI63: =IFERROR(FI61/FH61-1,"") | FJ63: =IFERROR(FJ61/FI61-1,"") | FL63: =IFERROR(FL61/FJ61-1,"") | FM63: =IFERROR(FM61/FL61-1,"") | FN63: =IFERROR(FN61/FM61-1,"") | FO63: =IFERROR(FO61/FN61-1,"") | FQ63: =IFERROR(FQ61/FO61-1,"") | FR63: =IFERROR(FR61/FQ61-1,"") | FS63: =IFERROR(FS61/FR61-1,"") | FT63: =IFERROR(FT61/FS61-1,"") | FV63: =IFERROR(FV61/FT61-1,"") | FW63: =IFERROR(FW61/FV61-1,"") | FX63: =IFERROR(FX61/FW61-1,"") | FY63: =IFERROR(FY61/FX61-1,"") | GA63: =IFERROR(GA61/FY61-1,"") | GB63: =IFERROR(GB61/GA61-1,"") | GC63: =IFERROR(GC61/GB61-1,"") | GD63: =IFERROR(GD61/GC61-1,"") | GF63: =IFERROR(GF61/GD61-1,"") | GG63: =IFERROR(GG61/GF61-1,"") | GH63: =IFERROR(GH61/GG61-1,"") | GI63: =IFERROR(GI61/GH61-1,"")
B64: Gross Margin | CY64: =Company1738!CY63 | CZ64: =Company1738!CZ63 | DA64: =Company1738!DA63 | DB64: =Company1738!DB63 | DC64: =Company1738!DC63 | DD64: =Company1738!DD63 | DE64: =Company1738!DE63 | DF64: =Company1738!DF63 | ... EQ64: =Company1738!EQ63 | ER64: =Company1738!ER28 | ES64: =Company1738!ES28 | ET64: =Company1738!ET28 | EU64: =Company1738!EU28 | EV64: =Company1738!EV28 | EW64: =Company1738!EW28 | EX64: =Company1738!EX28 | EY64: =Company1738!EY28 | ... GJ64: =Company1738!GJ28
A66: GP | B66: Gross Profit | C66: =C24-C45 | D66: =D24-D45 | E66: =E24-E45 | F66: =F24-F45 | G66: =SUM(C66:F66) | H66: =H24-H45 | I66: =I24-I45 | J66: =J24-J45 | K66: =K24-K45 | L66: =SUM(H66:K66) | M66: =M24-M45 | N66: =N24-N45 | O66: =O24-O45 | P66: =P24-P45 | Q66: =SUM(M66:P66) | R66: =R24-R45 | S66: =S24-S45 | T66: =T24-T45 | U66: =U24-U45 | V66: =SUM(R66:U66) | W66: =W24-W45 | X66: =X24-X45 | Y66: =Y24-Y45 | Z66: =Z24-Z45 | AA66: =SUM(W66:Z66) | AB66: =AB24-AB45 | AC66: =AC24-AC45 | AD66: =AD24-AD45 | AE66: =AE24-AE45 | AF66: =SUM(AB66:AE66) | AG66: =AG24-AG45 | AH66: =AH24-AH45 | AI66: =AI24-AI45 | AJ66: =AJ24-AJ45 | AK66: =SUM(AG66:AJ66) | AL66: =AL24-AL45 | AM66: =AM24-AM45 | AN66: =AN24-AN45 | AO66: =AO24-AO45 | AP66: =SUM(AL66:AO66) | AQ66: =AQ24-AQ45 | AR66: =AR24-AR45 | AS66: =AS24-AS45 | AT66: =AT24-AT45 | AU66: =SUM(AQ66:AT66) | AV66: =AV24-AV45 | AW66: =AW24-AW45 | AX66: =AX24-AX45 | AY66: =AY24-AY45 | AZ66: =SUM(AV66:AY66) | BA66: =BA24-BA45 | BB66: =BB24-BB45 | BC66: =BC24-BC45 | BD66: =BD24-BD45 | BE66: =SUM(BA66:BD66) | BF66: =BF24-BF45 | BG66: =BG24-BG45 | BH66: =BH24-BH45 | BI66: =BI24-BI45 | BJ66: =SUM(BF66:BI66) | BK66: =BK24-BK45 | BL66: =BL24-BL45 | BM66: =BM24-BM45 | BN66: =BN24-BN45 | BO66: =SUM(BK66:BN66) | BP66: =BP24-BP45 | BQ66: =BQ24-BQ45 | BR66: =BR24-BR45 | BS66: =BS24-BS45 | BT66: =SUM(BP66:BS66) | BU66: =BU24-BU45 | BV66: =BV24-BV45 | BW66: =BW24-BW45 | BX66: =BX24-BX45 | BY66: =SUM(BU66:BX66) | BZ66: =BZ24-BZ45 | CA66: =CA24-CA45 | CB66: =CB24-CB45 | CC66: =CC24-CC45 | CD66: =SUM(BZ66:CC66) | CE66: =CE24-CE45 | CF66: =CF24-CF45 | CG66: =CG24-CG45 | CH66: =CH24-CH45 | CI66: =SUM(CE66:CH66) | CJ66: =CJ24-CJ45 | CK66: =CK24-CK45 | CL66: =CL24-CL45 | CM66: =CM24-CM45 | CN66: =SUM(CJ66:CM66) | CO66: =CO24-CO45 | CP66: =CP24-CP45 | CQ66: =CQ24-CQ45 | CR66: =CR24-CR45 | CS66: =SUM(CO66:CR66) | CT66: =CT24-CT45 | CU66: =CU24-CU45 | CV66: =CV24-CV45 | CW66: =CW24-CW45 | CX66: =SUM(CT66:CW66) | CY66: =CY24-CY45 | CZ66: =CZ24-CZ45 | DA66: =DA24-DA45 | DB66: =DB24-DB45 | DC66: =SUM(CY66:DB66) | DD66: =DD24-DD45 | DE66: =DE24-DE45 | DF66: =DF24-DF45 | DG66: =DG24-DG45 | DH66: =SUM(DD66:DG66) | DI66: =DI24-DI45 | DJ66: =DJ24-DJ45 | DK66: =DK24-DK45 | DL66: =DL24-DL45 | DM66: =SUM(DI66:DL66) | DN66: =DN24-DN45 | DO66: =DO24-DO45 | DP66: =DP24-DP45 | DQ66: =DQ24-DQ45 | DR66: =SUM(DN66:DQ66) | DS66: =DS24-DS45 | DT66: =DT24-DT45 | DU66: =DU24-DU45 | DV66: =DV24-DV45 | DW66: =SUM(DS66:DV66) | DX66: =DX24-DX45 | DY66: =DY24-DY45 | DZ66: =DZ24-DZ45 | EA66: =EA24-EA45 | EB66: =SUM(DX66:EA66) | EC66: =EC24-EC45 | ED66: =ED24-ED45 | EE66: =EE24-EE45 | EF66: =EF24-EF45 | EG66: =SUM(EC66:EF66) | EH66: =EH24-EH45 | EI66: =EI24-EI45 | EJ66: =EJ24-EJ45 | EK66: =EK24-EK45 | EL66: =SUM(EH66:EK66) | EM66: =EM24-EM45 | EN66: =EN24-EN45 | EO66: =EO24-EO45 | EP66: =EP24-EP45 | EQ66: =SUM(EM66:EP66) | ER66: =ER24-ER45 | ES66: =ES24-ES45 | ET66: =ET24-ET45 | EU66: =EU24-EU45 | EV66: =SUM(ER66:EU66) | EW66: =EW24-EW45 | EX66: =EX24-EX45 | EY66: =EY24-EY45 | EZ66: =EZ24-EZ45 | FA66: =SUM(EW66:EZ66) | FB66: =FB51+FB56+FB61 | FC66: =FC51+FC56+FC61 | FD66: =FD51+FD56+FD61 | FE66: =FE51+FE56+FE61 | FF66: =FF51+FF56+FF61 | FG66: =FG51+FG56+FG61 | FH66: =FH51+FH56+FH61 | FI66: =FI51+FI56+FI61 | ... GJ66: =GJ51+GJ56+GJ61
A67: GPYY | B67: % yoy | H67: =IFERROR(H66/C66-1,"") | I67: =IFERROR(I66/D66-1,"") | J67: =IFERROR(J66/E66-1,"") | K67: =IFERROR(K66/F66-1,"") | L67: =IFERROR(L66/G66-1,"") | M67: =IFERROR(M66/H66-1,"") | N67: =IFERROR(N66/I66-1,"") | O67: =IFERROR(O66/J66-1,"") | ... GJ67: =IFERROR(GJ66/GE66-1,"")
A68: GPQQ | B68: % qoq | H68: =IFERROR(H66/F66-1,"") | I68: =IFERROR(I66/H66-1,"") | J68: =IFERROR(J66/I66-1,"") | K68: =IFERROR(K66/J66-1,"") | M68: =IFERROR(M66/K66-1,"") | N68: =IFERROR(N66/M66-1,"") | O68: =IFERROR(O66/N66-1,"") | P68: =IFERROR(P66/O66-1,"") | R68: =IFERROR(R66/P66-1,"") | S68: =IFERROR(S66/R66-1,"") | T68: =IFERROR(T66/S66-1,"") | U68: =IFERROR(U66/T66-1,"") | W68: =IFERROR(W66/U66-1,"") | X68: =IFERROR(X66/W66-1,"") | Y68: =IFERROR(Y66/X66-1,"") | Z68: =IFERROR(Z66/Y66-1,"") | AB68: =IFERROR(AB66/Z66-1,"") | AC68: =IFERROR(AC66/AB66-1,"") | AD68: =IFERROR(AD66/AC66-1,"") | AE68: =IFERROR(AE66/AD66-1,"") | AG68: =IFERROR(AG66/AE66-1,"") | AH68: =IFERROR(AH66/AG66-1,"") | AI68: =IFERROR(AI66/AH66-1,"") | AJ68: =IFERROR(AJ66/AI66-1,"") | AL68: =IFERROR(AL66/AJ66-1,"") | AM68: =IFERROR(AM66/AL66-1,"") | AN68: =IFERROR(AN66/AM66-1,"") | AO68: =IFERROR(AO66/AN66-1,"") | AQ68: =IFERROR(AQ66/AO66-1,"") | AR68: =IFERROR(AR66/AQ66-1,"") | AS68: =IFERROR(AS66/AR66-1,"") | AT68: =IFERROR(AT66/AS66-1,"") | AV68: =IFERROR(AV66/AT66-1,"") | AW68: =IFERROR(AW66/AV66-1,"") | AX68: =IFERROR(AX66/AW66-1,"") | AY68: =IFERROR(AY66/AX66-1,"") | BA68: =IFERROR(BA66/AY66-1,"") | BB68: =IFERROR(BB66/BA66-1,"") | BC68: =IFERROR(BC66/BB66-1,"") | BD68: =IFERROR(BD66/BC66-1,"") | BF68: =IFERROR(BF66/BD66-1,"") | BG68: =IFERROR(BG66/BF66-1,"") | BH68: =IFERROR(BH66/BG66-1,"") | BI68: =IFERROR(BI66/BH66-1,"") | BK68: =IFERROR(BK66/BI66-1,"") | BL68: =IFERROR(BL66/BK66-1,"") | BM68: =IFERROR(BM66/BL66-1,"") | BN68: =IFERROR(BN66/BM66-1,"") | BP68: =IFERROR(BP66/BN66-1,"") | BQ68: =IFERROR(BQ66/BP66-1,"") | BR68: =IFERROR(BR66/BQ66-1,"") | BS68: =IFERROR(BS66/BR66-1,"") | BU68: =IFERROR(BU66/BS66-1,"") | BV68: =IFERROR(BV66/BU66-1,"") | BW68: =IFERROR(BW66/BV66-1,"") | BX68: =IFERROR(BX66/BW66-1,"") | BZ68: =IFERROR(BZ66/BX66-1,"") | CA68: =IFERROR(CA66/BZ66-1,"") | CB68: =IFERROR(CB66/CA66-1,"") | CC68: =IFERROR(CC66/CB66-1,"") | CE68: =IFERROR(CE66/CC66-1,"") | CF68: =IFERROR(CF66/CE66-1,"") | CG68: =IFERROR(CG66/CF66-1,"") | CH68: =IFERROR(CH66/CG66-1,"") | CJ68: =IFERROR(CJ66/CH66-1,"") | CK68: =IFERROR(CK66/CJ66-1,"") | CL68: =IFERROR(CL66/CK66-1,"") | CM68: =IFERROR(CM66/CL66-1,"") | CO68: =IFERROR(CO66/CM66-1,"") | CP68: =IFERROR(CP66/CO66-1,"") | CQ68: =IFERROR(CQ66/CP66-1,"") | CR68: =IFERROR(CR66/CQ66-1,"") | CT68: =IFERROR(CT66/CR66-1,"") | CU68: =IFERROR(CU66/CT66-1,"") | CV68: =IFERROR(CV66/CU66-1,"") | CW68: =IFERROR(CW66/CV66-1,"") | CY68: =IFERROR(CY66/CW66-1,"") | CZ68: =IFERROR(CZ66/CY66-1,"") | DA68: =IFERROR(DA66/CZ66-1,"") | DB68: =IFERROR(DB66/DA66-1,"") | DD68: =IFERROR(DD66/DB66-1,"") | DE68: =IFERROR(DE66/DD66-1,"") | DF68: =IFERROR(DF66/DE66-1,"") | DG68: =IFERROR(DG66/DF66-1,"") | DI68: =IFERROR(DI66/DG66-1,"") | DJ68: =IFERROR(DJ66/DI66-1,"") | DK68: =IFERROR(DK66/DJ66-1,"") | DL68: =IFERROR(DL66/DK66-1,"") | DN68: =IFERROR(DN66/DL66-1,"") | DO68: =IFERROR(DO66/DN66-1,"") | DP68: =IFERROR(DP66/DO66-1,"") | DQ68: =IFERROR(DQ66/DP66-1,"") | DS68: =IFERROR(DS66/DQ66-1,"") | DT68: =IFERROR(DT66/DS66-1,"") | DU68: =IFERROR(DU66/DT66-1,"") | DV68: =IFERROR(DV66/DU66-1,"") | DX68: =IFERROR(DX66/DV66-1,"") | DY68: =IFERROR(DY66/DX66-1,"") | DZ68: =IFERROR(DZ66/DY66-1,"") | EA68: =IFERROR(EA66/DZ66-1,"") | EC68: =IFERROR(EC66/EA66-1,"") | ED68: =IFERROR(ED66/EC66-1,"") | EE68: =IFERROR(EE66/ED66-1,"") | EF68: =IFERROR(EF66/EE66-1,"") | EH68: =IFERROR(EH66/EF66-1,"") | EI68: =IFERROR(EI66/EH66-1,"") | EJ68: =IFERROR(EJ66/EI66-1,"") | EK68: =IFERROR(EK66/EJ66-1,"") | EM68: =IFERROR(EM66/EK66-1,"") | EN68: =IFERROR(EN66/EM66-1,"") | EO68: =IFERROR(EO66/EN66-1,"") | EP68: =IFERROR(EP66/EO66-1,"") | ER68: =IFERROR(ER66/EP66-1,"") | ES68: =IFERROR(ES66/ER66-1,"") | ET68: =IFERROR(ET66/ES66-1,"") | EU68: =IFERROR(EU66/ET66-1,"") | EW68: =IFERROR(EW66/EU66-1,"") | EX68: =IFERROR(EX66/EW66-1,"") | EY68: =IFERROR(EY66/EX66-1,"") | EZ68: =IFERROR(EZ66/EY66-1,"") | FB68: =IFERROR(FB66/EZ66-1,"") | FC68: =IFERROR(FC66/FB66-1,"") | FD68: =IFERROR(FD66/FC66-1,"") | FE68: =IFERROR(FE66/FD66-1,"") | FG68: =IFERROR(FG66/FE66-1,"") | FH68: =IFERROR(FH66/FG66-1,"") | FI68: =IFERROR(FI66/FH66-1,"") | FJ68: =IFERROR(FJ66/FI66-1,"") | FL68: =IFERROR(FL66/FJ66-1,"") | FM68: =IFERROR(FM66/FL66-1,"") | FN68: =IFERROR(FN66/FM66-1,"") | FO68: =IFERROR(FO66/FN66-1,"") | FQ68: =IFERROR(FQ66/FO66-1,"") | FR68: =IFERROR(FR66/FQ66-1,"") | FS68: =IFERROR(FS66/FR66-1,"") | FT68: =IFERROR(FT66/FS66-1,"") | FV68: =IFERROR(FV66/FT66-1,"") | FW68: =IFERROR(FW66/FV66-1,"") | FX68: =IFERROR(FX66/FW66-1,"") | FY68: =IFERROR(FY66/FX66-1,"") | GA68: =IFERROR(GA66/FY66-1,"") | GB68: =IFERROR(GB66/GA66-1,"") | GC68: =IFERROR(GC66/GB66-1,"") | GD68: =IFERROR(GD66/GC66-1,"") | GF68: =IFERROR(GF66/GD66-1,"") | GG68: =IFERROR(GG66/GF66-1,"") | GH68: =IFERROR(GH66/GG66-1,"") | GI68: =IFERROR(GI66/GH66-1,"")
B69: Net New Profit (yoy) | H69: =H66-C66 | I69: =I66-D66 | J69: =J66-E66 | K69: =K66-F66 | L69: =L66-G66 | M69: =M66-H66 | N69: =N66-I66 | O69: =O66-J66 | ... GJ69: =GJ66-GE66
B70: Net New Profit (qoq) | D70: =D66-C66 | E70: =E66-D66 | F70: =F66-E66 | H70: =H66-F66 | I70: =I66-H66 | J70: =J66-I66 | K70: =K66-J66 | M70: =M66-K66 | N70: =N66-M66 | O70: =O66-N66 | P70: =P66-O66 | R70: =R66-P66 | S70: =S66-R66 | T70: =T66-S66 | U70: =U66-T66 | W70: =W66-U66 | X70: =X66-W66 | Y70: =Y66-X66 | Z70: =Z66-Y66 | AB70: =AB66-Z66 | AC70: =AC66-AB66 | AD70: =AD66-AC66 | AE70: =AE66-AD66 | AG70: =AG66-AE66 | AH70: =AH66-AG66 | AI70: =AI66-AH66 | AJ70: =AJ66-AI66 | AL70: =AL66-AJ66 | AM70: =AM66-AL66 | AN70: =AN66-AM66 | AO70: =AO66-AN66 | AQ70: =AQ66-AO66 | AR70: =AR66-AQ66 | AS70: =AS66-AR66 | AT70: =AT66-AS66 | AV70: =AV66-AT66 | AW70: =AW66-AV66 | AX70: =AX66-AW66 | AY70: =AY66-AX66 | BA70: =BA66-AY66 | BB70: =BB66-BA66 | BC70: =BC66-BB66 | BD70: =BD66-BC66 | BF70: =BF66-BD66 | BG70: =BG66-BF66 | BH70: =BH66-BG66 | BI70: =BI66-BH66 | BK70: =BK66-BI66 | BL70: =BL66-BK66 | BM70: =BM66-BL66 | BN70: =BN66-BM66 | BP70: =BP66-BN66 | BQ70: =BQ66-BP66 | BR70: =BR66-BQ66 | BS70: =BS66-BR66 | BU70: =BU66-BS66 | BV70: =BV66-BU66 | BW70: =BW66-BV66 | BX70: =BX66-BW66 | BZ70: =BZ66-BX66 | CA70: =CA66-BZ66 | CB70: =CB66-CA66 | CC70: =CC66-CB66 | CE70: =CE66-CC66 | CF70: =CF66-CE66 | CG70: =CG66-CF66 | CH70: =CH66-CG66 | CJ70: =CJ66-CH66 | CK70: =CK66-CJ66 | CL70: =CL66-CK66 | CM70: =CM66-CL66 | CO70: =CO66-CM66 | CP70: =CP66-CO66 | CQ70: =CQ66-CP66 | CR70: =CR66-CQ66 | CT70: =CT66-CR66 | CU70: =CU66-CT66 | CV70: =CV66-CU66 | CW70: =CW66-CV66 | CY70: =CY66-CW66 | CZ70: =CZ66-CY66 | DA70: =DA66-CZ66 | DB70: =DB66-DA66 | DD70: =DD66-DB66 | DE70: =DE66-DD66 | DF70: =DF66-DE66 | DG70: =DG66-DF66 | DI70: =DI66-DG66 | DJ70: =DJ66-DI66 | DK70: =DK66-DJ66 | DL70: =DL66-DK66 | DN70: =DN66-DL66 | DO70: =DO66-DN66 | DP70: =DP66-DO66 | DQ70: =DQ66-DP66 | DS70: =DS66-DQ66 | DT70: =DT66-DS66 | DU70: =DU66-DT66 | DV70: =DV66-DU66 | DX70: =DX66-DV66 | DY70: =DY66-DX66 | DZ70: =DZ66-DY66 | EA70: =EA66-DZ66 | EC70: =EC66-EA66 | ED70: =ED66-EC66 | EE70: =EE66-ED66 | EF70: =EF66-EE66 | EH70: =EH66-EF66 | EI70: =EI66-EH66 | EJ70: =EJ66-EI66 | EK70: =EK66-EJ66 | EM70: =EM66-EK66 | EN70: =EN66-EM66 | EO70: =EO66-EN66 | EP70: =EP66-EO66 | ER70: =ER66-EP66 | ES70: =ES66-ER66 | ET70: =ET66-ES66 | EU70: =EU66-ET66 | EW70: =EW66-EU66 | EX70: =EX66-EW66 | EY70: =EY66-EX66 | EZ70: =EZ66-EY66 | FB70: =FB66-EZ66 | FC70: =FC66-FB66 | FD70: =FD66-FC66 | FE70: =FE66-FD66 | FG70: =FG66-FE66 | FH70: =FH66-FG66 | FI70: =FI66-FH66 | FJ70: =FJ66-FI66 | FL70: =FL66-FJ66 | FM70: =FM66-FL66 | FN70: =FN66-FM66 | FO70: =FO66-FN66 | FQ70: =FQ66-FO66 | FR70: =FR66-FQ66 | FS70: =FS66-FR66 | FT70: =FT66-FS66 | FV70: =FV66-FT66 | FW70: =FW66-FV66 | FX70: =FX66-FW66 | FY70: =FY66-FX66 | GA70: =GA66-FY66 | GB70: =GB66-GA66 | GC70: =GC66-GB66 | GD70: =GD66-GC66 | GF70: =GF66-GD66 | GG70: =GG66-GF66 | GH70: =GH66-GG66 | GI70: =GI66-GH66
A71: GPM | B71: % gross margin | C71: =IFERROR(C66/C$24,"") | D71: =IFERROR(D66/D$24,"") | E71: =IFERROR(E66/E$24,"") | F71: =IFERROR(F66/F$24,"") | G71: =IFERROR(G66/G$24,"") | H71: =IFERROR(H66/H$24,"") | I71: =IFERROR(I66/I$24,"") | J71: =IFERROR(J66/J$24,"") | ... GJ71: =IFERROR(GJ66/GJ$24,"")
B73: COGS (ex. Depreciation) | BF73: =BF45-BS!BF137 | BG73: =BG45-BS!BG137 | BH73: =BH45-BS!BH137 | BI73: =BI45-BS!BI137 | BJ73: =BJ45-BS!BJ137 | BK73: =BK45-BS!BK137 | BL73: =BL45-BS!BL137 | BM73: =BM45-BS!BM137 | ... GJ73: =GJ45-BS!GJ137
B74: GM (ex. Depreciation) | BF74: =(BF24-BF73)/BF24 | BG74: =(BG24-BG73)/BG24 | BH74: =(BH24-BH73)/BH24 | BI74: =(BI24-BI73)/BI24 | BJ74: =(BJ24-BJ73)/BJ24 | BK74: =(BK24-BK73)/BK24 | BL74: =(BL24-BL73)/BL24 | BM74: =(BM24-BM73)/BM24 | ... GJ74: =(GJ24-GJ73)/GJ24
B76: Research & Development | C76: 178 | D76: 199 | E76: 219 | F76: 264 | G76: =SUM(C76:F76) | H76: 302 | I76: 313 | J76: 364 | K76: 453 | L76: =SUM(H76:K76) | M76: 432 | N76: 485 | O76: 492 | P76: 516 | Q76: =SUM(M76:P76) | R76: 567 | S76: 627 | T76: 597 | U76: 711 | V76: =SUM(R76:U76) | W76: 651 | X76: 715 | Y76: 664 | Z76: 940 | AA76: =SUM(W76:Z76) | AB76: 834 | AC76: 911 | AD76: 990 | AE76: 1040 | AF76: =SUM(AB76:AE76) | AG76: 956 | AH76: 990 | AI76: 1069 | AJ76: 1364 | AK76: =SUM(AG76:AJ76) | AL76: 1013 | AM76: 1044 | AN76: 1066 | AO76: 1184 | AP76: =SUM(AL76:AO76) | AQ76: 1707 | AR76: 1515 | AS76: 1692 | AT76: 1681 | AU76: =SUM(AQ76:AT76) | AV76: 1611 | AW76: 2971 | AX76: 1538 | AY76: 1659 | AZ76: =SUM(AV76:AY76) | BA76: 1530 | BB76: 1421 | BC76: 1482 | BD76: =6184-BC76-BB76-BA76 | BE76: =SUM(BA76:BD76) | BF76: 1515 | BG76: 1591 | BH76: 1617 | BI76: 1861 | BJ76: =SUM(BF76:BI76) | BK76: 1786 | BL76: 1637 | BM76: 1750 | BN76: 1948 | BO76: =SUM(BK76:BN76) | BP76: 1837 | BQ76: 1885 | BR76: 2035 | BS76: 2407 | BT76: =SUM(BP76:BS76) | BU76: 2283 | BV76: 2290 | BW76: 2212 | BX76: 2225 | BY76: =SUM(BU76:BX76) | BZ76: 2065 | CA76: 2079 | CB76: 2220 | CC76: 2350 | CD76: =SUM(BZ76:CC76) | CE76: 2196 | CF76: 2185 | CG76: 2269 | CH76: 2393 | CI76: =SUM(CE76:CH76) | CJ76: 2329 | CK76: 2371 | CL76: 2517 | CM76: 2594 | CN76: =SUM(CJ76:CM76) | CO76: 2460 | CP76: 2528 | CQ76: 2640 | CR76: 2783 | CS76: =SUM(CO76:CR76) | CT76: 2767 | CU76: 2748 | CV76: 2743 | CW76: 3123 | CX76: =SUM(CT76:CW76) | CY76: 3065 | CZ76: 2903 | DA76: 2984 | DB76: 3094 | DC76: =SUM(CY76:DB76) | DD76: 2962 | DE76: 2900 | DF76: 2980 | DG76: 3146 | DH76: =SUM(DD76:DG76) | DI76: 3106 | DJ76: 3062 | DK76: 3355 | DL76: 3514 | DM76: =SUM(DI76:DL76) | DN76: 3574 | DO76: 3504 | DP76: 3715 | DQ76: 3933 | DR76: =SUM(DN76:DQ76) | DS76: 3977 | DT76: 4070 | DU76: 4316 | DV76: 4513 | DW76: =SUM(DS76:DV76) | DX76: 4565 | DY76: 4603 | DZ76: 4887 | EA76: 5214 | EB76: =SUM(DX76:EA76) | EC76: 4926 | ED76: 4899 | EE76: 5204 | EF76: 5687 | EG76: =SUM(EC76:EF76) | EH76: 5599 | EI76: 5758 | EJ76: 6306 | EK76: 6849 | EL76: =SUM(EH76:EK76) | EM76: 6628 | EN76: 6844 | EO76: 6984 | EP76: 6739 | EQ76: =SUM(EM76:EP76) | ER76: 6659 | ES76: 7142 | ET76: 7653 | EU76: 8056 | EV76: =SUM(ER76:EU76) | EW76: 7544 | EX76: 7917 | EY76: 8198 | EZ76: 8829 | FA76: =SUM(EW76:EZ76) | FB76: =FB$24*FB81 | FC76: =FC$24*FC81 | FD76: =FD$24*FD81 | FE76: =FE$24*FE81 | FF76: =SUM(FB76:FE76) | FG76: =FG$24*FG81 | FH76: =FH$24*FH81 | FI76: =FI$24*FI81 | FJ76: =FJ$24*FJ81 | FK76: =SUM(FG76:FJ76) | FL76: =FL$24*FL81 | FM76: =FM$24*FM81 | FN76: =FN$24*FN81 | FO76: =FO$24*FO81 | FP76: =SUM(FL76:FO76) | FQ76: =FQ$24*FQ81 | FR76: =FR$24*FR81 | FS76: =FS$24*FS81 | FT76: =FT$24*FT81 | FU76: =SUM(FQ76:FT76) | FV76: =FV$24*FV81 | FW76: =FW$24*FW81 | FX76: =FX$24*FX81 | FY76: =FY$24*FY81 | FZ76: =SUM(FV76:FY76) | GA76: =GA$24*GA81 | GB76: =GB$24*GB81 | GC76: =GC$24*GC81 | GD76: =GD$24*GD81 | GE76: =SUM(GA76:GD76) | GF76: =GF$24*GF81 | GG76: =GG$24*GG81 | GH76: =GH$24*GH81 | GI76: =GI$24*GI81 | GJ76: =SUM(GF76:GI76)
B77: % yoy | H77: =IFERROR(H76/C76-1,"") | I77: =IFERROR(I76/D76-1,"") | J77: =IFERROR(J76/E76-1,"") | K77: =IFERROR(K76/F76-1,"") | L77: =IFERROR(L76/G76-1,"") | M77: =IFERROR(M76/H76-1,"") | N77: =IFERROR(N76/I76-1,"") | O77: =IFERROR(O76/J76-1,"") | ... GJ77: =IFERROR(GJ76/GE76-1,"")
B78: % qoq | H78: =IFERROR(H76/F76-1,"") | I78: =IFERROR(I76/H76-1,"") | J78: =IFERROR(J76/I76-1,"") | K78: =IFERROR(K76/J76-1,"") | M78: =IFERROR(M76/K76-1,"") | N78: =IFERROR(N76/M76-1,"") | O78: =IFERROR(O76/N76-1,"") | P78: =IFERROR(P76/O76-1,"") | R78: =IFERROR(R76/P76-1,"") | S78: =IFERROR(S76/R76-1,"") | T78: =IFERROR(T76/S76-1,"") | U78: =IFERROR(U76/T76-1,"") | W78: =IFERROR(W76/U76-1,"") | X78: =IFERROR(X76/W76-1,"") | Y78: =IFERROR(Y76/X76-1,"") | Z78: =IFERROR(Z76/Y76-1,"") | AB78: =IFERROR(AB76/Z76-1,"") | AC78: =IFERROR(AC76/AB76-1,"") | AD78: =IFERROR(AD76/AC76-1,"") | AE78: =IFERROR(AE76/AD76-1,"") | AG78: =IFERROR(AG76/AE76-1,"") | AH78: =IFERROR(AH76/AG76-1,"") | AI78: =IFERROR(AI76/AH76-1,"") | AJ78: =IFERROR(AJ76/AI76-1,"") | AL78: =IFERROR(AL76/AJ76-1,"") | AM78: =IFERROR(AM76/AL76-1,"") | AN78: =IFERROR(AN76/AM76-1,"") | AO78: =IFERROR(AO76/AN76-1,"") | AQ78: =IFERROR(AQ76/AO76-1,"") | AR78: =IFERROR(AR76/AQ76-1,"") | AS78: =IFERROR(AS76/AR76-1,"") | AT78: =IFERROR(AT76/AS76-1,"") | AV78: =IFERROR(AV76/AT76-1,"") | AW78: =IFERROR(AW76/AV76-1,"") | AX78: =IFERROR(AX76/AW76-1,"") | AY78: =IFERROR(AY76/AX76-1,"") | BA78: =IFERROR(BA76/AY76-1,"") | BB78: =IFERROR(BB76/BA76-1,"") | BC78: =IFERROR(BC76/BB76-1,"") | BD78: =IFERROR(BD76/BC76-1,"") | BF78: =IFERROR(BF76/BD76-1,"") | BG78: =IFERROR(BG76/BF76-1,"") | BH78: =IFERROR(BH76/BG76-1,"") | BI78: =IFERROR(BI76/BH76-1,"") | BK78: =IFERROR(BK76/BI76-1,"") | BL78: =IFERROR(BL76/BK76-1,"") | BM78: =IFERROR(BM76/BL76-1,"") | BN78: =IFERROR(BN76/BM76-1,"") | BP78: =IFERROR(BP76/BN76-1,"") | BQ78: =IFERROR(BQ76/BP76-1,"") | BR78: =IFERROR(BR76/BQ76-1,"") | BS78: =IFERROR(BS76/BR76-1,"") | BU78: =IFERROR(BU76/BS76-1,"") | BV78: =IFERROR(BV76/BU76-1,"") | BW78: =IFERROR(BW76/BV76-1,"") | BX78: =IFERROR(BX76/BW76-1,"") | BZ78: =IFERROR(BZ76/BX76-1,"") | CA78: =IFERROR(CA76/BZ76-1,"") | CB78: =IFERROR(CB76/CA76-1,"") | CC78: =IFERROR(CC76/CB76-1,"") | CE78: =IFERROR(CE76/CC76-1,"") | CF78: =IFERROR(CF76/CE76-1,"") | CG78: =IFERROR(CG76/CF76-1,"") | CH78: =IFERROR(CH76/CG76-1,"") | CJ78: =IFERROR(CJ76/CH76-1,"") | CK78: =IFERROR(CK76/CJ76-1,"") | CL78: =IFERROR(CL76/CK76-1,"") | CM78: =IFERROR(CM76/CL76-1,"") | CO78: =IFERROR(CO76/CM76-1,"") | CP78: =IFERROR(CP76/CO76-1,"") | CQ78: =IFERROR(CQ76/CP76-1,"") | CR78: =IFERROR(CR76/CQ76-1,"") | CT78: =IFERROR(CT76/CR76-1,"") | CU78: =IFERROR(CU76/CT76-1,"") | CV78: =IFERROR(CV76/CU76-1,"") | CW78: =IFERROR(CW76/CV76-1,"") | CY78: =IFERROR(CY76/CW76-1,"") | CZ78: =IFERROR(CZ76/CY76-1,"") | DA78: =IFERROR(DA76/CZ76-1,"") | DB78: =IFERROR(DB76/DA76-1,"") | DD78: =IFERROR(DD76/DB76-1,"") | DE78: =IFERROR(DE76/DD76-1,"") | DF78: =IFERROR(DF76/DE76-1,"") | DG78: =IFERROR(DG76/DF76-1,"") | DI78: =IFERROR(DI76/DG76-1,"") | DJ78: =IFERROR(DJ76/DI76-1,"") | DK78: =IFERROR(DK76/DJ76-1,"") | DL78: =IFERROR(DL76/DK76-1,"") | DN78: =IFERROR(DN76/DL76-1,"") | DO78: =IFERROR(DO76/DN76-1,"") | DP78: =IFERROR(DP76/DO76-1,"") | DQ78: =IFERROR(DQ76/DP76-1,"") | DS78: =IFERROR(DS76/DQ76-1,"") | DT78: =IFERROR(DT76/DS76-1,"") | DU78: =IFERROR(DU76/DT76-1,"") | DV78: =IFERROR(DV76/DU76-1,"") | DX78: =IFERROR(DX76/DV76-1,"") | DY78: =IFERROR(DY76/DX76-1,"") | DZ78: =IFERROR(DZ76/DY76-1,"") | EA78: =IFERROR(EA76/DZ76-1,"") | EC78: =IFERROR(EC76/EA76-1,"") | ED78: =IFERROR(ED76/EC76-1,"") | EE78: =IFERROR(EE76/ED76-1,"") | EF78: =IFERROR(EF76/EE76-1,"") | EH78: =IFERROR(EH76/EF76-1,"") | EI78: =IFERROR(EI76/EH76-1,"") | EJ78: =IFERROR(EJ76/EI76-1,"") | EK78: =IFERROR(EK76/EJ76-1,"") | EM78: =IFERROR(EM76/EK76-1,"") | EN78: =IFERROR(EN76/EM76-1,"") | EO78: =IFERROR(EO76/EN76-1,"") | EP78: =IFERROR(EP76/EO76-1,"") | ER78: =IFERROR(ER76/EP76-1,"") | ES78: =IFERROR(ES76/ER76-1,"") | ET78: =IFERROR(ET76/ES76-1,"") | EU78: =IFERROR(EU76/ET76-1,"") | EW78: =IFERROR(EW76/EU76-1,"") | EX78: =IFERROR(EX76/EW76-1,"") | EY78: =IFERROR(EY76/EX76-1,"") | EZ78: =IFERROR(EZ76/EY76-1,"") | FB78: =IFERROR(FB76/EZ76-1,"") | FC78: =IFERROR(FC76/FB76-1,"") | FD78: =IFERROR(FD76/FC76-1,"") | FE78: =IFERROR(FE76/FD76-1,"") | FG78: =IFERROR(FG76/FE76-1,"") | FH78: =IFERROR(FH76/FG76-1,"") | FI78: =IFERROR(FI76/FH76-1,"") | FJ78: =IFERROR(FJ76/FI76-1,"") | FL78: =IFERROR(FL76/FJ76-1,"") | FM78: =IFERROR(FM76/FL76-1,"") | FN78: =IFERROR(FN76/FM76-1,"") | FO78: =IFERROR(FO76/FN76-1,"") | FQ78: =IFERROR(FQ76/FO76-1,"") | FR78: =IFERROR(FR76/FQ76-1,"") | FS78: =IFERROR(FS76/FR76-1,"") | FT78: =IFERROR(FT76/FS76-1,"") | FV78: =IFERROR(FV76/FT76-1,"") | FW78: =IFERROR(FW76/FV76-1,"") | FX78: =IFERROR(FX76/FW76-1,"") | FY78: =IFERROR(FY76/FX76-1,"") | GA78: =IFERROR(GA76/FY76-1,"") | GB78: =IFERROR(GB76/GA76-1,"") | GC78: =IFERROR(GC76/GB76-1,"") | GD78: =IFERROR(GD76/GC76-1,"") | GF78: =IFERROR(GF76/GD76-1,"") | GG78: =IFERROR(GG76/GF76-1,"") | GH78: =IFERROR(GH76/GG76-1,"") | GI78: =IFERROR(GI76/GH76-1,"")
B79: Net New Expense (yoy) | H79: =H76-C76 | I79: =I76-D76 | J79: =J76-E76 | K79: =K76-F76 | L79: =L76-G76 | M79: =M76-H76 | N79: =N76-I76 | O79: =O76-J76 | ... GJ79: =GJ76-GE76
B80: Net New Expense (qoq) | D80: =D76-C76 | E80: =E76-D76 | F80: =F76-E76 | H80: =H76-F76 | I80: =I76-H76 | J80: =J76-I76 | K80: =K76-J76 | M80: =M76-K76 | N80: =N76-M76 | O80: =O76-N76 | P80: =P76-O76 | R80: =R76-P76 | S80: =S76-R76 | T80: =T76-S76 | U80: =U76-T76 | W80: =W76-U76 | X80: =X76-W76 | Y80: =Y76-X76 | Z80: =Z76-Y76 | AB80: =AB76-Z76 | AC80: =AC76-AB76 | AD80: =AD76-AC76 | AE80: =AE76-AD76 | AG80: =AG76-AE76 | AH80: =AH76-AG76 | AI80: =AI76-AH76 | AJ80: =AJ76-AI76 | AL80: =AL76-AJ76 | AM80: =AM76-AL76 | AN80: =AN76-AM76 | AO80: =AO76-AN76 | AQ80: =AQ76-AO76 | AR80: =AR76-AQ76 | AS80: =AS76-AR76 | AT80: =AT76-AS76 | AV80: =AV76-AT76 | AW80: =AW76-AV76 | AX80: =AX76-AW76 | AY80: =AY76-AX76 | BA80: =BA76-AY76 | BB80: =BB76-BA76 | BC80: =BC76-BB76 | BD80: =BD76-BC76 | BF80: =BF76-BD76 | BG80: =BG76-BF76 | BH80: =BH76-BG76 | BI80: =BI76-BH76 | BK80: =BK76-BI76 | BL80: =BL76-BK76 | BM80: =BM76-BL76 | BN80: =BN76-BM76 | BP80: =BP76-BN76 | BQ80: =BQ76-BP76 | BR80: =BR76-BQ76 | BS80: =BS76-BR76 | BU80: =BU76-BS76 | BV80: =BV76-BU76 | BW80: =BW76-BV76 | BX80: =BX76-BW76 | BZ80: =BZ76-BX76 | CA80: =CA76-BZ76 | CB80: =CB76-CA76 | CC80: =CC76-CB76 | CE80: =CE76-CC76 | CF80: =CF76-CE76 | CG80: =CG76-CF76 | CH80: =CH76-CG76 | CJ80: =CJ76-CH76 | CK80: =CK76-CJ76 | CL80: =CL76-CK76 | CM80: =CM76-CL76 | CO80: =CO76-CM76 | CP80: =CP76-CO76 | CQ80: =CQ76-CP76 | CR80: =CR76-CQ76 | CT80: =CT76-CR76 | CU80: =CU76-CT76 | CV80: =CV76-CU76 | CW80: =CW76-CV76 | CY80: =CY76-CW76 | CZ80: =CZ76-CY76 | DA80: =DA76-CZ76 | DB80: =DB76-DA76 | DD80: =DD76-DB76 | DE80: =DE76-DD76 | DF80: =DF76-DE76 | DG80: =DG76-DF76 | DI80: =DI76-DG76 | DJ80: =DJ76-DI76 | DK80: =DK76-DJ76 | DL80: =DL76-DK76 | DN80: =DN76-DL76 | DO80: =DO76-DN76 | DP80: =DP76-DO76 | DQ80: =DQ76-DP76 | DS80: =DS76-DQ76 | DT80: =DT76-DS76 | DU80: =DU76-DT76 | DV80: =DV76-DU76 | DX80: =DX76-DV76 | DY80: =DY76-DX76 | DZ80: =DZ76-DY76 | EA80: =EA76-DZ76 | EC80: =EC76-EA76 | ED80: =ED76-EC76 | EE80: =EE76-ED76 | EF80: =EF76-EE76 | EH80: =EH76-EF76 | EI80: =EI76-EH76 | EJ80: =EJ76-EI76 | EK80: =EK76-EJ76 | EM80: =EM76-EK76 | EN80: =EN76-EM76 | EO80: =EO76-EN76 | EP80: =EP76-EO76 | ER80: =ER76-EP76 | ES80: =ES76-ER76 | ET80: =ET76-ES76 | EU80: =EU76-ET76 | EW80: =EW76-EU76 | EX80: =EX76-EW76 | EY80: =EY76-EX76 | EZ80: =EZ76-EY76 | FB80: =FB76-EZ76 | FC80: =FC76-FB76 | FD80: =FD76-FC76 | FE80: =FE76-FD76 | FG80: =FG76-FE76 | FH80: =FH76-FG76 | FI80: =FI76-FH76 | FJ80: =FJ76-FI76 | FL80: =FL76-FJ76 | FM80: =FM76-FL76 | FN80: =FN76-FM76 | FO80: =FO76-FN76 | FQ80: =FQ76-FO76 | FR80: =FR76-FQ76 | FS80: =FS76-FR76 | FT80: =FT76-FS76 | FV80: =FV76-FT76 | FW80: =FW76-FV76 | FX80: =FX76-FW76 | FY80: =FY76-FX76 | GA80: =GA76-FY76 | GB80: =GB76-GA76 | GC80: =GC76-GB76 | GD80: =GD76-GC76 | GF80: =GF76-GD76 | GG80: =GG76-GF76 | GH80: =GH76-GG76 | GI80: =GI76-GH76
B81: % of Total Revenue | C81: =IFERROR(C76/C$24,"") | D81: =IFERROR(D76/D$24,"") | E81: =IFERROR(E76/E$24,"") | F81: =IFERROR(F76/F$24,"") | G81: =IFERROR(G76/G$24,"") | H81: =IFERROR(H76/H$24,"") | I81: =IFERROR(I76/I$24,"") | J81: =IFERROR(J76/J$24,"") | ... FA81: =IFERROR(FA76/FA$24,"") | FB81: =EW81-0.75% | FC81: =EX81-0.9% | FD81: =EY81-0.9% | FE81: =EZ81-0.9% | FF81: =IFERROR(FF76/FF$24,"--") | FG81: =FB81-0.25% | FH81: =FC81-0.25% | FI81: =FD81-0.25% | FJ81: =FE81-0.25% | FK81: =IFERROR(FK76/FK$24,"--") | FL81: =FG81-0.2% | FM81: =FH81-0.2% | FN81: =FI81-0.2% | FO81: =FJ81-0.2% | FP81: =IFERROR(FP76/FP$24,"--") | FQ81: =FL81-0.2% | FR81: =FM81-0.2% | FS81: =FN81-0.2% | FT81: =FO81-0.2% | FU81: =IFERROR(FU76/FU$24,"--") | FV81: =FQ81-0.2% | FW81: =FR81-0.2% | FX81: =FS81-0.2% | FY81: =FT81-0.2% | FZ81: =IFERROR(FZ76/FZ$24,"--") | GA81: =FV81-0.2% | GB81: =FW81-0.2% | GC81: =FX81-0.2% | GD81: =FY81-0.2% | GE81: =IFERROR(GE76/GE$24,"--") | GF81: =GA81-0.2% | GG81: =GB81-0.2% | GH81: =GC81-0.2% | GI81: =GD81-0.2% | GJ81: =IFERROR(GJ76/GJ$24,"--")
B83: Sales & Marketing | C83: 395 | D83: 479 | E83: 516 | F83: 505 | G83: =SUM(C83:F83) | H83: 621 | I83: 690 | J83: 685 | K83: 661 | L83: =SUM(H83:K83) | M83: 625 | N83: 737 | O83: 750 | P83: 744 | Q83: =SUM(M83:P83) | R83: 788 | S83: 876 | T83: 829 | U83: 919 | V83: =SUM(R83:U83) | W83: 688 | X83: 794 | Y83: 849 | Z83: 900 | AA83: =SUM(W83:Z83) | AB83: 903 | AC83: 1027 | AD83: 1042 | AE83: 1169 | AF83: =SUM(AB83:AE83) | AG83: 1038 | AH83: 1290 | AI83: 1198 | AJ83: 1359 | AK83: =SUM(AG83:AJ83) | AL83: 1145 | AM83: 1479 | AN83: 1240 | AO83: 1543 | AP83: =SUM(AL83:AO83) | AQ83: 1415 | AR83: 2159 | AS83: 1700 | AT83: 2288 | AU83: =SUM(AQ83:AT83) | AV83: 1505 | AW83: 2467 | AX83: 1928 | AY83: 2409 | AZ83: =SUM(AV83:AY83) | BA83: 1664 | BB83: 2122 | BC83: 2070 | BD83: =8677-BC83-BB83-BA83 | BE83: =SUM(BA83:BD83) | BF83: 1945 | BG83: 2689 | BH83: 2362 | BI83: 2822 | BJ83: =SUM(BF83:BI83) | BK83: 2191 | BL83: 2999 | BM83: 2936 | BN83: 3329 | BO83: =SUM(BK83:BN83) | BP83: 2614 | BQ83: 3392 | BR83: 3155 | BS83: 3878 | BT83: =SUM(BP83:BS83) | BU83: 3044 | BV83: 3662 | BW83: 2981 | BX83: 3192 | BY83: =SUM(BU83:BX83) | BZ83: 2790 | CA83: 3619 | CB83: 3203 | CC83: 3602 | CD83: =SUM(BZ83:CC83) | CE83: 2806 | CF83: 3825 | CG83: 3393 | CH83: 3916 | CI83: =SUM(CE83:CH83) | CJ83: 2900 | CK83: 3762 | CL83: 3414 | CM83: 3781 | CN83: =SUM(CJ83:CM83) | CO83: 2945 | CP83: 4309 | CQ83: 3794 | CR83: 4228 | CS83: =SUM(CO83:CR83) | CT83: 3304 | CU83: 4283 | CV83: 3542 | CW83: 4682 | CX83: =SUM(CT83:CW83) | CY83: 3728 | CZ83: 4315 | DA83: 3709 | DB83: 3961 | DC83: =SUM(CY83:DB83) | DD83: 3333 | DE83: 3960 | DF83: 3406 | DG83: 3998 | DH83: =SUM(DD83:DG83) | DI83: 3218 | DJ83: 4079 | DK83: 3872 | DL83: 4292 | DM83: =SUM(DI83:DL83) | DN83: 3812 | DO83: 4562 | DP83: 4335 | DQ83: 4760 | DR83: =SUM(DN83:DQ83) | DS83: 4098 | DT83: 4588 | DU83: 4565 | DV83: 4962 | DW83: =SUM(DS83:DV83) | DX83: 4337 | DY83: 4933 | DZ83: 4911 | EA83: 5417 | EB83: =SUM(DX83:EA83) | EC83: 4231 | ED83: 4947 | EE83: 5082 | EF83: 5857 | EG83: =SUM(EC83:EF83) | EH83: 4547 | EI83: 5379 | EJ83: 5595 | EK83: 6304 | EL83: =SUM(EH83:EK83) | EM83: 5126 | EN83: 5679 | EO83: 5750 | EP83: 6204 | EQ83: =SUM(EM83:EP83) | ER83: 5187 | ES83: 6246 | ET83: 6207 | EU83: 6816 | EV83: =SUM(ER83:EU83) | EW83: 5717 | EX83: 6440 | EY83: 6212 | EZ83: 7285 | FA83: =SUM(EW83:EZ83) | FB83: =FB$24*FB88 | FC83: =FC$24*FC88 | FD83: =FD$24*FD88 | FE83: =FE$24*FE88 | FF83: =SUM(FB83:FE83) | FG83: =FG$24*FG88 | FH83: =FH$24*FH88 | FI83: =FI$24*FI88 | FJ83: =FJ$24*FJ88 | FK83: =SUM(FG83:FJ83) | FL83: =FL$24*FL88 | FM83: =FM$24*FM88 | FN83: =FN$24*FN88 | FO83: =FO$24*FO88 | FP83: =SUM(FL83:FO83) | FQ83: =FQ$24*FQ88 | FR83: =FR$24*FR88 | FS83: =FS$24*FS88 | FT83: =FT$24*FT88 | FU83: =SUM(FQ83:FT83) | FV83: =FV$24*FV88 | FW83: =FW$24*FW88 | FX83: =FX$24*FX88 | FY83: =FY$24*FY88 | FZ83: =SUM(FV83:FY83) | GA83: =GA$24*GA88 | GB83: =GB$24*GB88 | GC83: =GC$24*GC88 | GD83: =GD$24*GD88 | GE83: =SUM(GA83:GD83) | GF83: =GF$24*GF88 | GG83: =GG$24*GG88 | GH83: =GH$24*GH88 | GI83: =GI$24*GI88 | GJ83: =SUM(GF83:GI83)
B84: % yoy | H84: =IFERROR(H83/C83-1,"") | I84: =IFERROR(I83/D83-1,"") | J84: =IFERROR(J83/E83-1,"") | K84: =IFERROR(K83/F83-1,"") | L84: =IFERROR(L83/G83-1,"") | M84: =IFERROR(M83/H83-1,"") | N84: =IFERROR(N83/I83-1,"") | O84: =IFERROR(O83/J83-1,"") | ... GJ84: =IFERROR(GJ83/GE83-1,"")
B85: % qoq | H85: =IFERROR(H83/F83-1,"") | I85: =IFERROR(I83/H83-1,"") | J85: =IFERROR(J83/I83-1,"") | K85: =IFERROR(K83/J83-1,"") | M85: =IFERROR(M83/K83-1,"") | N85: =IFERROR(N83/M83-1,"") | O85: =IFERROR(O83/N83-1,"") | P85: =IFERROR(P83/O83-1,"") | R85: =IFERROR(R83/P83-1,"") | S85: =IFERROR(S83/R83-1,"") | T85: =IFERROR(T83/S83-1,"") | U85: =IFERROR(U83/T83-1,"") | W85: =IFERROR(W83/U83-1,"") | X85: =IFERROR(X83/W83-1,"") | Y85: =IFERROR(Y83/X83-1,"") | Z85: =IFERROR(Z83/Y83-1,"") | AB85: =IFERROR(AB83/Z83-1,"") | AC85: =IFERROR(AC83/AB83-1,"") | AD85: =IFERROR(AD83/AC83-1,"") | AE85: =IFERROR(AE83/AD83-1,"") | AG85: =IFERROR(AG83/AE83-1,"") | AH85: =IFERROR(AH83/AG83-1,"") | AI85: =IFERROR(AI83/AH83-1,"") | AJ85: =IFERROR(AJ83/AI83-1,"") | AL85: =IFERROR(AL83/AJ83-1,"") | AM85: =IFERROR(AM83/AL83-1,"") | AN85: =IFERROR(AN83/AM83-1,"") | AO85: =IFERROR(AO83/AN83-1,"") | AQ85: =IFERROR(AQ83/AO83-1,"") | AR85: =IFERROR(AR83/AQ83-1,"") | AS85: =IFERROR(AS83/AR83-1,"") | AT85: =IFERROR(AT83/AS83-1,"") | AV85: =IFERROR(AV83/AT83-1,"") | AW85: =IFERROR(AW83/AV83-1,"") | AX85: =IFERROR(AX83/AW83-1,"") | AY85: =IFERROR(AY83/AX83-1,"") | BA85: =IFERROR(BA83/AY83-1,"") | BB85: =IFERROR(BB83/BA83-1,"") | BC85: =IFERROR(BC83/BB83-1,"") | BD85: =IFERROR(BD83/BC83-1,"") | BF85: =IFERROR(BF83/BD83-1,"") | BG85: =IFERROR(BG83/BF83-1,"") | BH85: =IFERROR(BH83/BG83-1,"") | BI85: =IFERROR(BI83/BH83-1,"") | BK85: =IFERROR(BK83/BI83-1,"") | BL85: =IFERROR(BL83/BK83-1,"") | BM85: =IFERROR(BM83/BL83-1,"") | BN85: =IFERROR(BN83/BM83-1,"") | BP85: =IFERROR(BP83/BN83-1,"") | BQ85: =IFERROR(BQ83/BP83-1,"") | BR85: =IFERROR(BR83/BQ83-1,"") | BS85: =IFERROR(BS83/BR83-1,"") | BU85: =IFERROR(BU83/BS83-1,"") | BV85: =IFERROR(BV83/BU83-1,"") | BW85: =IFERROR(BW83/BV83-1,"") | BX85: =IFERROR(BX83/BW83-1,"") | BZ85: =IFERROR(BZ83/BX83-1,"") | CA85: =IFERROR(CA83/BZ83-1,"") | CB85: =IFERROR(CB83/CA83-1,"") | CC85: =IFERROR(CC83/CB83-1,"") | CE85: =IFERROR(CE83/CC83-1,"") | CF85: =IFERROR(CF83/CE83-1,"") | CG85: =IFERROR(CG83/CF83-1,"") | CH85: =IFERROR(CH83/CG83-1,"") | CJ85: =IFERROR(CJ83/CH83-1,"") | CK85: =IFERROR(CK83/CJ83-1,"") | CL85: =IFERROR(CL83/CK83-1,"") | CM85: =IFERROR(CM83/CL83-1,"") | CO85: =IFERROR(CO83/CM83-1,"") | CP85: =IFERROR(CP83/CO83-1,"") | CQ85: =IFERROR(CQ83/CP83-1,"") | CR85: =IFERROR(CR83/CQ83-1,"") | CT85: =IFERROR(CT83/CR83-1,"") | CU85: =IFERROR(CU83/CT83-1,"") | CV85: =IFERROR(CV83/CU83-1,"") | CW85: =IFERROR(CW83/CV83-1,"") | CY85: =IFERROR(CY83/CW83-1,"") | CZ85: =IFERROR(CZ83/CY83-1,"") | DA85: =IFERROR(DA83/CZ83-1,"") | DB85: =IFERROR(DB83/DA83-1,"") | DD85: =IFERROR(DD83/DB83-1,"") | DE85: =IFERROR(DE83/DD83-1,"") | DF85: =IFERROR(DF83/DE83-1,"") | DG85: =IFERROR(DG83/DF83-1,"") | DI85: =IFERROR(DI83/DG83-1,"") | DJ85: =IFERROR(DJ83/DI83-1,"") | DK85: =IFERROR(DK83/DJ83-1,"") | DL85: =IFERROR(DL83/DK83-1,"") | DN85: =IFERROR(DN83/DL83-1,"") | DO85: =IFERROR(DO83/DN83-1,"") | DP85: =IFERROR(DP83/DO83-1,"") | DQ85: =IFERROR(DQ83/DP83-1,"") | DS85: =IFERROR(DS83/DQ83-1,"") | DT85: =IFERROR(DT83/DS83-1,"") | DU85: =IFERROR(DU83/DT83-1,"") | DV85: =IFERROR(DV83/DU83-1,"") | DX85: =IFERROR(DX83/DV83-1,"") | DY85: =IFERROR(DY83/DX83-1,"") | DZ85: =IFERROR(DZ83/DY83-1,"") | EA85: =IFERROR(EA83/DZ83-1,"") | EC85: =IFERROR(EC83/EA83-1,"") | ED85: =IFERROR(ED83/EC83-1,"") | EE85: =IFERROR(EE83/ED83-1,"") | EF85: =IFERROR(EF83/EE83-1,"") | EH85: =IFERROR(EH83/EF83-1,"") | EI85: =IFERROR(EI83/EH83-1,"") | EJ85: =IFERROR(EJ83/EI83-1,"") | EK85: =IFERROR(EK83/EJ83-1,"") | EM85: =IFERROR(EM83/EK83-1,"") | EN85: =IFERROR(EN83/EM83-1,"") | EO85: =IFERROR(EO83/EN83-1,"") | EP85: =IFERROR(EP83/EO83-1,"") | ER85: =IFERROR(ER83/EP83-1,"") | ES85: =IFERROR(ES83/ER83-1,"") | ET85: =IFERROR(ET83/ES83-1,"") | EU85: =IFERROR(EU83/ET83-1,"") | EW85: =IFERROR(EW83/EU83-1,"") | EX85: =IFERROR(EX83/EW83-1,"") | EY85: =IFERROR(EY83/EX83-1,"") | EZ85: =IFERROR(EZ83/EY83-1,"") | FB85: =IFERROR(FB83/EZ83-1,"") | FC85: =IFERROR(FC83/FB83-1,"") | FD85: =IFERROR(FD83/FC83-1,"") | FE85: =IFERROR(FE83/FD83-1,"") | FG85: =IFERROR(FG83/FE83-1,"") | FH85: =IFERROR(FH83/FG83-1,"") | FI85: =IFERROR(FI83/FH83-1,"") | FJ85: =IFERROR(FJ83/FI83-1,"") | FL85: =IFERROR(FL83/FJ83-1,"") | FM85: =IFERROR(FM83/FL83-1,"") | FN85: =IFERROR(FN83/FM83-1,"") | FO85: =IFERROR(FO83/FN83-1,"") | FQ85: =IFERROR(FQ83/FO83-1,"") | FR85: =IFERROR(FR83/FQ83-1,"") | FS85: =IFERROR(FS83/FR83-1,"") | FT85: =IFERROR(FT83/FS83-1,"") | FV85: =IFERROR(FV83/FT83-1,"") | FW85: =IFERROR(FW83/FV83-1,"") | FX85: =IFERROR(FX83/FW83-1,"") | FY85: =IFERROR(FY83/FX83-1,"") | GA85: =IFERROR(GA83/FY83-1,"") | GB85: =IFERROR(GB83/GA83-1,"") | GC85: =IFERROR(GC83/GB83-1,"") | GD85: =IFERROR(GD83/GC83-1,"") | GF85: =IFERROR(GF83/GD83-1,"") | GG85: =IFERROR(GG83/GF83-1,"") | GH85: =IFERROR(GH83/GG83-1,"") | GI85: =IFERROR(GI83/GH83-1,"")
B86: Net New Expense (yoy) | H86: =H83-C83 | I86: =I83-D83 | J86: =J83-E83 | K86: =K83-F83 | L86: =L83-G83 | M86: =M83-H83 | N86: =N83-I83 | O86: =O83-J83 | ... GJ86: =GJ83-GE83
B87: Net New Expense (qoq) | D87: =D83-C83 | E87: =E83-D83 | F87: =F83-E83 | H87: =H83-F83 | I87: =I83-H83 | J87: =J83-I83 | K87: =K83-J83 | M87: =M83-K83 | N87: =N83-M83 | O87: =O83-N83 | P87: =P83-O83 | R87: =R83-P83 | S87: =S83-R83 | T87: =T83-S83 | U87: =U83-T83 | W87: =W83-U83 | X87: =X83-W83 | Y87: =Y83-X83 | Z87: =Z83-Y83 | AB87: =AB83-Z83 | AC87: =AC83-AB83 | AD87: =AD83-AC83 | AE87: =AE83-AD83 | AG87: =AG83-AE83 | AH87: =AH83-AG83 | AI87: =AI83-AH83 | AJ87: =AJ83-AI83 | AL87: =AL83-AJ83 | AM87: =AM83-AL83 | AN87: =AN83-AM83 | AO87: =AO83-AN83 | AQ87: =AQ83-AO83 | AR87: =AR83-AQ83 | AS87: =AS83-AR83 | AT87: =AT83-AS83 | AV87: =AV83-AT83 | AW87: =AW83-AV83 | AX87: =AX83-AW83 | AY87: =AY83-AX83 | BA87: =BA83-AY83 | BB87: =BB83-BA83 | BC87: =BC83-BB83 | BD87: =BD83-BC83 | BF87: =BF83-BD83 | BG87: =BG83-BF83 | BH87: =BH83-BG83 | BI87: =BI83-BH83 | BK87: =BK83-BI83 | BL87: =BL83-BK83 | BM87: =BM83-BL83 | BN87: =BN83-BM83 | BP87: =BP83-BN83 | BQ87: =BQ83-BP83 | BR87: =BR83-BQ83 | BS87: =BS83-BR83 | BU87: =BU83-BS83 | BV87: =BV83-BU83 | BW87: =BW83-BV83 | BX87: =BX83-BW83 | BZ87: =BZ83-BX83 | CA87: =CA83-BZ83 | CB87: =CB83-CA83 | CC87: =CC83-CB83 | CE87: =CE83-CC83 | CF87: =CF83-CE83 | CG87: =CG83-CF83 | CH87: =CH83-CG83 | CJ87: =CJ83-CH83 | CK87: =CK83-CJ83 | CL87: =CL83-CK83 | CM87: =CM83-CL83 | CO87: =CO83-CM83 | CP87: =CP83-CO83 | CQ87: =CQ83-CP83 | CR87: =CR83-CQ83 | CT87: =CT83-CR83 | CU87: =CU83-CT83 | CV87: =CV83-CU83 | CW87: =CW83-CV83 | CY87: =CY83-CW83 | CZ87: =CZ83-CY83 | DA87: =DA83-CZ83 | DB87: =DB83-DA83 | DD87: =DD83-DB83 | DE87: =DE83-DD83 | DF87: =DF83-DE83 | DG87: =DG83-DF83 | DI87: =DI83-DG83 | DJ87: =DJ83-DI83 | DK87: =DK83-DJ83 | DL87: =DL83-DK83 | DN87: =DN83-DL83 | DO87: =DO83-DN83 | DP87: =DP83-DO83 | DQ87: =DQ83-DP83 | DS87: =DS83-DQ83 | DT87: =DT83-DS83 | DU87: =DU83-DT83 | DV87: =DV83-DU83 | DX87: =DX83-DV83 | DY87: =DY83-DX83 | DZ87: =DZ83-DY83 | EA87: =EA83-DZ83 | EC87: =EC83-EA83 | ED87: =ED83-EC83 | EE87: =EE83-ED83 | EF87: =EF83-EE83 | EH87: =EH83-EF83 | EI87: =EI83-EH83 | EJ87: =EJ83-EI83 | EK87: =EK83-EJ83 | EM87: =EM83-EK83 | EN87: =EN83-EM83 | EO87: =EO83-EN83 | EP87: =EP83-EO83 | ER87: =ER83-EP83 | ES87: =ES83-ER83 | ET87: =ET83-ES83 | EU87: =EU83-ET83 | EW87: =EW83-EU83 | EX87: =EX83-EW83 | EY87: =EY83-EX83 | EZ87: =EZ83-EY83 | FB87: =FB83-EZ83 | FC87: =FC83-FB83 | FD87: =FD83-FC83 | FE87: =FE83-FD83 | FG87: =FG83-FE83 | FH87: =FH83-FG83 | FI87: =FI83-FH83 | FJ87: =FJ83-FI83 | FL87: =FL83-FJ83 | FM87: =FM83-FL83 | FN87: =FN83-FM83 | FO87: =FO83-FN83 | FQ87: =FQ83-FO83 | FR87: =FR83-FQ83 | FS87: =FS83-FR83 | FT87: =FT83-FS83 | FV87: =FV83-FT83 | FW87: =FW83-FV83 | FX87: =FX83-FW83 | FY87: =FY83-FX83 | GA87: =GA83-FY83 | GB87: =GB83-GA83 | GC87: =GC83-GB83 | GD87: =GD83-GC83 | GF87: =GF83-GD83 | GG87: =GG83-GF83 | GH87: =GH83-GG83 | GI87: =GI83-GH83
B88: % of Total Revenue | C88: =IFERROR(C83/C$24,"") | D88: =IFERROR(D83/D$24,"") | E88: =IFERROR(E83/E$24,"") | F88: =IFERROR(F83/F$24,"") | G88: =IFERROR(G83/G$24,"") | H88: =IFERROR(H83/H$24,"") | I88: =IFERROR(I83/I$24,"") | J88: =IFERROR(J83/J$24,"") | ... FA88: =IFERROR(FA83/FA$24,"") | FB88: =EW88-0.75% | FC88: =EX88-0.9% | FD88: =EY88-0.9% | FE88: =EZ88-0.9% | FF88: =IFERROR(FF83/FF$24,"--") | FG88: =FB88-0.25% | FH88: =FC88-0.25% | FI88: =FD88-0.25% | FJ88: =FE88-0.25% | FK88: =IFERROR(FK83/FK$24,"--") | FL88: =FG88-0.2% | FM88: =FH88-0.2% | FN88: =FI88-0.2% | FO88: =FJ88-0.2% | FP88: =IFERROR(FP83/FP$24,"--") | FQ88: =FL88-0.2% | FR88: =FM88-0.2% | FS88: =FN88-0.2% | FT88: =FO88-0.2% | FU88: =IFERROR(FU83/FU$24,"--") | FV88: =FQ88-0.2% | FW88: =FR88-0.2% | FX88: =FS88-0.2% | FY88: =FT88-0.2% | FZ88: =IFERROR(FZ83/FZ$24,"--") | GA88: =FV88-0.2% | GB88: =FW88-0.2% | GC88: =FX88-0.2% | GD88: =FY88-0.2% | GE88: =IFERROR(GE83/GE$24,"--") | GF88: =GA88-0.2% | GG88: =GB88-0.2% | GH88: =GC88-0.2% | GI88: =GD88-0.2% | GJ88: =IFERROR(GJ83/GJ$24,"--")
B90: General & Administrative | C90: 51 | D90: 62 | E90: 68 | F90: 86 | G90: =SUM(C90:F90) | H90: 63 | I90: 76 | J90: 87 | K90: 90 | L90: =SUM(H90:K90) | M90: 86 | N90: 81 | O90: 101 | P90: 94 | Q90: =SUM(M90:P90) | R90: 95 | S90: 106 | T90: 104 | U90: 128 | V90: =SUM(R90:U90) | W90: 99 | X90: 149 | Y90: 144 | Z90: 297 | AA90: =SUM(W90:Z90) | AB90: 143 | AC90: 506 | AD90: 176 | AE90: 184 | AF90: =SUM(AB90:AE90) | AG90: 170 | AH90: 212 | AI90: 239 | AJ90: 236 | AK90: =SUM(AG90:AJ90) | AL90: 187 | AM90: 833 | AN90: 246 | AO90: 284 | AP90: =SUM(AL90:AO90) | AQ90: 252 | AR90: 497 | AS90: 425 | AT90: 1252 | AU90: =SUM(AQ90:AT90) | AV90: 471 | AW90: 896 | AX90: 3020 | AY90: 610 | AZ90: =SUM(AV90:AY90) | BA90: 1096 | BB90: 651 | BC90: 1376 | BD90: =4166-BC90-BB90-BA90 | BE90: =SUM(BA90:BD90) | BF90: 982 | BG90: 661 | BH90: 1005 | BI90: 1110 | BJ90: =SUM(BF90:BI90) | BK90: 664 | BL90: 814 | BM90: 983 | BN90: 868 | BO90: =SUM(BK90:BN90) | BP90: 718 | BQ90: 1066 | BR90: 2341 | BS90: 1002 | BT90: =SUM(BP90:BS90) | BU90: 887 | BV90: 831 | BW90: 913 | BX90: 1069 | BY90: =SUM(BU90:BX90) | BZ90: 741 | CA90: 1124 | CB90: 1152 | CC90: 987 | CD90: =SUM(BZ90:CC90) | CE90: 938 | CF90: 945 | CG90: 1160 | CH90: 1179 | CI90: =SUM(CE90:CH90) | CJ90: 1163 | CK90: 1120 | CL90: 1150 | CM90: 1136 | CN90: =SUM(CJ90:CM90) | CO90: 1127 | CP90: 1156 | CQ90: 1656 | CR90: 1210 | CS90: =SUM(CO90:CR90) | CT90: 979 | CU90: 1197 | CV90: 1166 | CW90: 1335 | CX90: =SUM(CT90:CW90) | CY90: 1151 | CZ90: 1097 | DA90: 1091 | DB90: 1272 | DC90: =SUM(CY90:DB90) | DD90: 1084 | DE90: 1038 | DF90: 1140 | DG90: 1301 | DH90: =SUM(DD90:DG90) | DI90: 1045 | DJ90: 879 | DK90: 1202 | DL90: 1355 | DM90: =SUM(DI90:DL90) | DN90: 1166 | DO90: 1109 | DP90: 1208 | DQ90: 1271 | DR90: =SUM(DN90:DQ90) | DS90: 1149 | DT90: 1132 | DU90: 1179 | DV90: 1425 | DW90: =SUM(DS90:DV90) | DX90: 1061 | DY90: 1121 | DZ90: 1273 | EA90: 1656 | EB90: =SUM(DX90:EA90) | EC90: 1119 | ED90: 1139 | EE90: 1327 | EF90: 1522 | EG90: =SUM(EC90:EF90) | EH90: 1287 | EI90: 1384 | EJ90: 1480 | EK90: 1749 | EL90: =SUM(EH90:EK90) | EM90: 1398 | EN90: 2337 | EO90: 1643 | EP90: 2197 | EQ90: =SUM(EM90:EP90) | ER90: 1474 | ES90: 1977 | ET90: 1912 | EU90: 2246 | EV90: =SUM(ER90:EU90) | EW90: 1673 | EX90: 1823 | EY90: 1737 | EZ90: 1990 | FA90: =SUM(EW90:EZ90) | FB90: =FB$24*FB95 | FC90: =FC$24*FC95 | FD90: =FD$24*FD95 | FE90: =FE$24*FE95 | FF90: =SUM(FB90:FE90) | FG90: =FG$24*FG95 | FH90: =FH$24*FH95 | FI90: =FI$24*FI95 | FJ90: =FJ$24*FJ95 | FK90: =SUM(FG90:FJ90) | FL90: =FL$24*FL95 | FM90: =FM$24*FM95 | FN90: =FN$24*FN95 | FO90: =FO$24*FO95 | FP90: =SUM(FL90:FO90) | FQ90: =FQ$24*FQ95 | FR90: =FR$24*FR95 | FS90: =FS$24*FS95 | FT90: =FT$24*FT95 | FU90: =SUM(FQ90:FT90) | FV90: =FV$24*FV95 | FW90: =FW$24*FW95 | FX90: =FX$24*FX95 | FY90: =FY$24*FY95 | FZ90: =SUM(FV90:FY90) | GA90: =GA$24*GA95 | GB90: =GB$24*GB95 | GC90: =GC$24*GC95 | GD90: =GD$24*GD95 | GE90: =SUM(GA90:GD90) | GF90: =GF$24*GF95 | GG90: =GG$24*GG95 | GH90: =GH$24*GH95 | GI90: =GI$24*GI95 | GJ90: =SUM(GF90:GI90)
B91: % yoy | H91: =IFERROR(H90/C90-1,"") | I91: =IFERROR(I90/D90-1,"") | J91: =IFERROR(J90/E90-1,"") | K91: =IFERROR(K90/F90-1,"") | L91: =IFERROR(L90/G90-1,"") | M91: =IFERROR(M90/H90-1,"") | N91: =IFERROR(N90/I90-1,"") | O91: =IFERROR(O90/J90-1,"") | ... GJ91: =IFERROR(GJ90/GE90-1,"")
