Workbook
Name Buyer_Diversification: WACC!$F$11
Name CapEx_Pct_Revenue: DCF!$J$16
Name Company_Name: 'Company0462-GAAP'!$F$8
Name Cost_of_Debt: WACC!$F$8
Name Cost_of_Preferred: WACC!$F$9
Name DA_Pct_Revenue: DCF!$J$15
Name Equity_Risk_Premium: WACC!$F$7
Name FCF_Decline_Rate: DCF!$T$21
Name Market_Correlation: WACC!$F$10
Name Min_Op_Margin: DCF!$J$13
Name Min_Rev_Growth: DCF!$J$10
Name Op_Margin_Change: DCF!$J$12
Name PrivCo_Discount: 'Company0462-GAAP'!$F$10
Name Rev_Growth_Decline: DCF!$J$9
Name Risk_Free_Rate: WACC!$F$6
Name Tax_Rate: 'Company0462-GAAP'!$F$7
Name Terminal_Growth_Rate: DCF!$J$21
Name Terminal_Multiple: DCF!$E$21
Name TV_Discount: DCF!$E$11
Name TV_Liquidation_Discount: DCF!$E$13
Name WACC: WACC!$L$35
Name WC_Pct_Change_in_Rev: DCF!$J$17

Sheet Company0462-Internal
B2: ="Sample Private Company Financial Statements - "&Company_Name -> Sample Private Company Financial Statements - Capital Capable Media LLC
B3: ($ USD as Stated)
G5: Historical | L5: Projected
B6: Revenue and Expense Drivers: | F6: Units: | G6: Year 1 | H6: Year 2 | I6: Year 3 | J6: Year 4 | K6: Year 5 | L6: Year 6 | M6: Year 7 | N6: Year 8 | O6: Year 9 | P6: Year 10
C8: Course Sign-Ups: | F8: # Customers | G8: 1011 | H8: 2051 | I8: 2978 | J8: 4000 | K8: 4500 | L8: 4800 | M8: 5200 | N8: 5600 | O8: 6000 | P8: 6500
C9: Average Customer Value: | F9: $ / Customer | G9: =+G79/G8 -> 107.23973 | H9: =+H79/H8 -> 128.3067 | I9: =+I79/I8 -> 145.64084 | J9: =+J79/J8 -> 145.75753 | K9: =+K79/K8 -> 163.26105 | L9: 175 | M9: 190 | N9: 210 | O9: 225 | P9: 240
C11: Revenue Growth Rates:
C12: Product Sales Referred by Affiliates: | F12: % | G12: =IFERROR(+G80/F80-1,"N/A") -> N/A | H12: =IFERROR(+H80/G80-1,"N/A") -> 0.30303086 | I12: =IFERROR(+I80/H80-1,"N/A") -> 0.16065863 | J12: =IFERROR(+J80/I80-1,"N/A") -> -0.38024395 | K12: =IFERROR(+K80/J80-1,"N/A") -> 0.26009731 | L12: 0.25 | M12: 0.2 | N12: 0.15 | O12: 0.1 | P12: 0.08
C13: Coaching & Resume Editing Services: | F13: % | G13: =IFERROR(+G81/F81-1,"N/A") -> N/A | H13: =IFERROR(+H81/G81-1,"N/A") -> 0.23227805 | I13: =IFERROR(+I81/H81-1,"N/A") -> 0.23451872 | J13: =IFERROR(+J81/I81-1,"N/A") -> 0.10178854 | K13: =IFERROR(+K81/J81-1,"N/A") -> 0.10258514 | L13: 0.1 | M13: 0.1 | N13: 0.08 | O13: 0.08 | P13: 0.04
C14: Sales to Institutions: | F14: % | G14: =IFERROR(+G82/F82-1,"N/A") -> N/A | H14: =IFERROR(+H82/G82-1,"N/A") -> 1.3805371 | I14: =IFERROR(+I82/H82-1,"N/A") -> 0.50885621 | J14: =IFERROR(+J82/I82-1,"N/A") -> 0.73531695 | K14: =IFERROR(+K82/J82-1,"N/A") -> 0.44011121 | L14: 0.4 | M14: 0.35 | N14: 0.3 | O14: 0.3 | P14: 0.23
C15: Commissions from Other Products: | F15: % | G15: =IFERROR(+G83/F83-1,"N/A") -> N/A | H15: =IFERROR(+H83/G83-1,"N/A") -> 0.26961981 | I15: =IFERROR(+I83/H83-1,"N/A") -> 0.25738018 | J15: =IFERROR(+J83/I83-1,"N/A") -> -0.25629274 | K15: =IFERROR(+K83/J83-1,"N/A") -> 0.26009731 | L15: 0.15 | M15: 0.1 | N15: 0.1 | O15: 0.08 | P15: 0.06
C17: Expense Percentages:
C18: Commission Rate - Affiliates: | F18: % | G18: =IFERROR(-G87/G80,"N/A") -> 0.5 | H18: =IFERROR(-H87/H80,"N/A") -> 0.5 | I18: =IFERROR(-I87/I80,"N/A") -> 0.5 | J18: =IFERROR(-J87/J80,"N/A") -> 0.5 | K18: =IFERROR(-K87/K80,"N/A") -> 0.5 | L18: 0.5 | M18: =+L18 -> 0.5 | N18: =+M18 -> 0.5 | O18: =+N18 -> 0.5 | P18: =+O18 -> 0.5
C19: Commission Rate - Coaches: | F19: % | G19: =IFERROR(-G88/G81,"N/A") -> 0.5 | H19: =IFERROR(-H88/H81,"N/A") -> 0.5 | I19: =IFERROR(-I88/I81,"N/A") -> 0.5 | J19: =IFERROR(-J88/J81,"N/A") -> 0.5 | K19: =IFERROR(-K88/K81,"N/A") -> 0.5 | L19: 0.5 | M19: =+L19 -> 0.5 | N19: =+M19 -> 0.5 | O19: =+N19 -> 0.5 | P19: =+O19 -> 0.5
C20: Commission Rate - Sales Reps: | F20: % | G20: =IFERROR(-G89/G82,"N/A") -> 0 | H20: =IFERROR(-H89/H82,"N/A") -> 0.4 | I20: =IFERROR(-I89/I82,"N/A") -> 0.4 | J20: =IFERROR(-J89/J82,"N/A") -> 0.4 | K20: =IFERROR(-K89/K82,"N/A") -> 0.4 | L20: 0.4 | M20: =+L20 -> 0.4 | N20: =+M20 -> 0.4 | O20: =+N20 -> 0.4 | P20: =+O20 -> 0.4
C22: Payment Fees % Gross Sales: | F22: % | G22: =IFERROR(-G95/G$84,"N/A") -> 0.029 | H22: =IFERROR(-H95/H$84,"N/A") -> 0.028 | I22: =IFERROR(-I95/I$84,"N/A") -> 0.028 | J22: =IFERROR(-J95/J$84,"N/A") -> 0.028 | K22: =IFERROR(-K95/K$84,"N/A") -> 0.028 | L22: 0.028 | M22: 0.028 | N22: 0.029 | O22: 0.029 | P22: 0.03
C23: Refunds % Gross Sales: | F23: % | G23: =IFERROR(-G96/G$84,"N/A") -> 0.03 | H23: =IFERROR(-H96/H$84,"N/A") -> 0.031 | I23: =IFERROR(-I96/I$84,"N/A") -> 0.035 | J23: =IFERROR(-J96/J$84,"N/A") -> 0.04 | K23: =IFERROR(-K96/K$84,"N/A") -> 0.041 | L23: 0.045 | M23: 0.045 | N23: 0.05 | O23: 0.05 | P23: 0.06
C25: Tax & Legal Fees % Gross Sales: | F25: % | G25: =IFERROR(-G102/G$84,"N/A") -> 0.0058799456 | H25: =IFERROR(-H102/H$84,"N/A") -> 0.0037050119 | I25: =IFERROR(-I102/I$84,"N/A") -> 0.0024555102 | J25: =IFERROR(-J102/J$84,"N/A") -> 0.0026413729 | K25: =IFERROR(-K102/K$84,"N/A") -> 0.0023581865 | L25: 0.002 | M25: 0.002 | N25: 0.003 | O25: 0.003 | P25: 0.003
C26: Online Advertising % Gross Sales: | F26: % | G26: =IFERROR(-G104/G$84,"N/A") -> 0 | H26: =IFERROR(-H104/H$84,"N/A") -> 0.024700079 | I26: =IFERROR(-I104/I$84,"N/A") -> 0.032740137 | J26: =IFERROR(-J104/J$84,"N/A") -> 0.026413729 | K26: =IFERROR(-K104/K$84,"N/A") -> 0.031442487 | L26: 0.031 | M26: 0.033 | N26: 0.035 | O26: 0.035 | P26: 0.037
C27: IT Infrastructure % Gross Sales: | F27: % | G27: =IFERROR(-G108/G$84,"N/A") -> 0.009407913 | H27: =IFERROR(-H108/H$84,"N/A") -> 0.01235004 | I27: =IFERROR(-I108/I$84,"N/A") -> 0.016370068 | J27: =IFERROR(-J108/J$84,"N/A") -> 0.019810297 | K27: =IFERROR(-K108/K$84,"N/A") -> 0.020961658 | L27: 0.022 | M27: 0.024 | N27: 0.024 | O27: 0.026 | P27: 0.026
C28: Travel & Moving % Gross Sales: | F28: % | G28: =IFERROR(-G109/G$84,"N/A") -> 0.027132421 | H28: =IFERROR(-H109/H$84,"N/A") -> 0.02173113 | I28: =IFERROR(-I109/I$84,"N/A") -> 0.0098416851 | J28: =IFERROR(-J109/J$84,"N/A") -> 0.0067658766 | K28: =IFERROR(-K109/K$84,"N/A") -> 0.0070881846 | L28: 0.007 | M28: 0.006 | N28: 0.005 | O28: 0.004 | P28: 0.004
C29: Depr. & Amort. % Gross Sales: | F29: % | G29: =IFERROR(-G110/G$84,"N/A") -> 0.0026718473 | H29: =IFERROR(-H110/H$84,"N/A") -> 0.0019562463 | I29: =IFERROR(-I110/I$84,"N/A") -> 0.0016550139 | J29: =IFERROR(-J110/J$84,"N/A") -> 0.0020114054 | K29: =IFERROR(-K110/K$84,"N/A") -> 0.0021213198 | L29: 0.002 | M29: 0.002 | N29: 0.003 | O29: 0.004 | P29: 0.004
C31: Effective Tax Rate: | F31: % | G31: =IFERROR(-G117/G115,"N/A") -> 0.25 | H31: =IFERROR(-H117/H115,"N/A") -> 0.27 | I31: =IFERROR(-I117/I115,"N/A") -> 0.28 | J31: =IFERROR(-J117/J115,"N/A") -> 0.29 | K31: =IFERROR(-K117/K115,"N/A") -> 0.3 | L31: 0.3 | M31: =+L31 -> 0.3 | N31: =+M31 -> 0.3 | O31: =+N31 -> 0.3 | P31: =+O31 -> 0.3
C33: Full-Time Equivalents (FTEs):
C34: Customer Support: | F34: # FTEs | G34: 0 | H34: 0 | I34: 0.5 | J34: 0.75 | K34: 1 | L34: 1 | M34: 1.5 | N34: 1.5 | O34: 2 | P34: 2
C35: Web Design & Development: | F35: # FTEs | G35: 0 | H35: 0.5 | I35: 1 | J35: 1 | K35: 1 | L35: 1.5 | M35: 1.5 | N35: 2 | O35: 2 | P35: 2
C36: Sales Reps: | F36: # FTEs | G36: 0 | H36: 0.5 | I36: 0.5 | J36: 0.5 | K36: 0.5 | L36: 0.5 | M36: 1 | N36: 1 | O36: 1 | P36: 1
C37: Marketing Staff: | F37: # FTEs | G37: 0 | H37: 0 | I37: 0.5 | J37: 0.75 | K37: 1 | L37: 1 | M37: 1 | N37: 1 | O37: 1.25 | P37: 1.5
C38: Product Creation: | F38: # FTEs | G38: 0 | H38: 0 | I38: 0.5 | J38: 0.5 | K38: 1 | L38: 1 | M38: 1 | N38: 2 | O38: 2 | P38: 2
C39: Content Creation: | F39: # FTEs | G39: 0 | H39: 0 | I39: 0.5 | J39: 0.5 | K39: 0.5 | L39: 0.5 | M39: 0.75 | N39: 0.75 | O39: 1 | P39: 1
C40: Total FTEs: | G40: =SUM(G34:G39) -> 0 | H40: =SUM(H34:H39) -> 1 | I40: =SUM(I34:I39) -> 3.5 | J40: =SUM(J34:J39) -> 4 | K40: =SUM(K34:K39) -> 5 | L40: =SUM(L34:L39) -> 5.5 | M40: =SUM(M34:M39) -> 6.75 | N40: =SUM(N34:N39) -> 8.25 | ... P40: =SUM(P34:P39) -> 9.5
C42: Average Expense per FTE:
C43: =+C34 -> Customer Support: | F43: $ / FTE | G43: =IFERROR(-G103/G34,"N/A") -> N/A | H43: =IFERROR(-H103/H34,"N/A") -> N/A | I43: =IFERROR(-I103/I34,"N/A") -> 60000 | J43: =IFERROR(-J103/J34,"N/A") -> 60000 | K43: =IFERROR(-K103/K34,"N/A") -> 60000 | L43: =+K43*(1+L$50) -> 62400 | M43: =+L43*(1+M$50) -> 64896 | N43: =+M43*(1+N$50) -> 67491.84 | O43: =+N43*(1+O$50) -> 70191.514 | P43: =+O43*(1+P$50) -> 72999.174
C44: =+C35 -> Web Design & Development: | F44: $ / FTE | G44: =IFERROR(-G105/G35,"N/A") -> N/A | H44: =IFERROR(-H105/H35,"N/A") -> 60000 | I44: =IFERROR(-I105/I35,"N/A") -> 60000 | J44: =IFERROR(-J105/J35,"N/A") -> 60000 | K44: =IFERROR(-K105/K35,"N/A") -> 60000 | L44: =+K44*(1+L$50) -> 62400 | M44: =+L44*(1+M$50) -> 64896 | N44: =+M44*(1+N$50) -> 67491.84 | O44: =+N44*(1+O$50) -> 70191.514 | P44: =+O44*(1+P$50) -> 72999.174
C45: =+C36 -> Sales Reps: | F45: $ / FTE | G45: =IFERROR(-G106/G36,"N/A") -> N/A | H45: =IFERROR(-H106/H36,"N/A") -> 20000 | I45: =IFERROR(-I106/I36,"N/A") -> 24000 | J45: =IFERROR(-J106/J36,"N/A") -> 24000 | K45: =IFERROR(-K106/K36,"N/A") -> 24000 | L45: =+K45*(1+L$50) -> 24960 | M45: =+L45*(1+M$50) -> 25958.4 | N45: =+M45*(1+N$50) -> 26996.736 | O45: =+N45*(1+O$50) -> 28076.605 | P45: =+O45*(1+P$50) -> 29199.67
C46: =+C37 -> Marketing Staff: | F46: $ / FTE | G46: =IFERROR(-G107/G37,"N/A") -> N/A | H46: =IFERROR(-H107/H37,"N/A") -> N/A | I46: =IFERROR(-I107/I37,"N/A") -> 80000 | J46: =IFERROR(-J107/J37,"N/A") -> 80000 | K46: =IFERROR(-K107/K37,"N/A") -> 80000 | L46: =+K46*(1+L$50) -> 83200 | M46: =+L46*(1+M$50) -> 86528 | N46: =+M46*(1+N$50) -> 89989.12 | O46: =+N46*(1+O$50) -> 93588.685 | P46: =+O46*(1+P$50) -> 97332.232
C47: =+C38 -> Product Creation: | F47: $ / FTE | G47: =IFERROR(-G111/G38,"N/A") -> N/A | H47: =IFERROR(-H111/H38,"N/A") -> N/A | I47: =IFERROR(-I111/I38,"N/A") -> 80000 | J47: =IFERROR(-J111/J38,"N/A") -> 80000 | K47: =IFERROR(-K111/K38,"N/A") -> 80000 | L47: =+K47*(1+L$50) -> 83200 | M47: =+L47*(1+M$50) -> 86528 | N47: =+M47*(1+N$50) -> 89989.12 | O47: =+N47*(1+O$50) -> 93588.685 | P47: =+O47*(1+P$50) -> 97332.232
C48: =+C39 -> Content Creation: | F48: $ / FTE | G48: =IFERROR(-G112/G39,"N/A") -> N/A | H48: =IFERROR(-H112/H39,"N/A") -> N/A | I48: =IFERROR(-I112/I39,"N/A") -> 60000 | J48: =IFERROR(-J112/J39,"N/A") -> 60000 | K48: =IFERROR(-K112/K39,"N/A") -> 60000 | L48: =+K48*(1+L$50) -> 62400 | M48: =+L48*(1+M$50) -> 64896 | N48: =+M48*(1+N$50) -> 67491.84 | O48: =+N48*(1+O$50) -> 70191.514 | P48: =+O48*(1+P$50) -> 72999.174
C50: Salary Growth Rate: | F50: % | L50: 0.04 | M50: 0.04 | N50: 0.04 | O50: 0.04 | P50: 0.04
G52: =+$G$5 -> Historical | L52: =+$L$5 -> Projected
B53: BS and CFS Drivers: | F53: =+$F$6 -> Units: | G53: =+$G$6 -> Year 1 | H53: =+$H$6 -> Year 2 | I53: =+$I$6 -> Year 3 | J53: =+$J$6 -> Year 4 | K53: =+$K$6 -> Year 5 | L53: =+$L$6 -> Year 6 | M53: =+$M$6 -> Year 7 | N53: =+$N$6 -> Year 8 | O53: =+$O$6 -> Year 9 | P53: =+$P$6 -> Year 10
C55: Accounts Receivable % Gross Sales: | F55: % | G55: =IFERROR(+G140/G84,"N/A") -> 0 | H55: =IFERROR(+H140/H84,"N/A") -> 0.005 | I55: =IFERROR(+I140/I84,"N/A") -> 0.01 | J55: =IFERROR(+J140/J84,"N/A") -> 0.01 | K55: =IFERROR(+K140/K84,"N/A") -> 0.012 | L55: 0.012 | M55: 0.013 | N55: 0.014 | O55: 0.015 | P55: 0.016
C56: Accounts Payable % OpEx: | F56: % | G56: =IFERROR(-G152/G$113,"N/A") -> 0.005 | H56: =IFERROR(-H152/H$113,"N/A") -> 0.009 | I56: =IFERROR(-I152/I$113,"N/A") -> 0.013 | J56: =IFERROR(-J152/J$113,"N/A") -> 0.018 | K56: =IFERROR(-K152/K$113,"N/A") -> 0.021 | L56: 0.022 | M56: 0.024 | N56: 0.024 | O56: 0.026 | P56: 0.026
C57: Accrued Expenses % OpEx: | F57: % | G57: =IFERROR(-G153/G$113,"N/A") -> 0.01 | H57: =IFERROR(-H153/H$113,"N/A") -> 0.01 | I57: =IFERROR(-I153/I$113,"N/A") -> 0.015 | J57: =IFERROR(-J153/J$113,"N/A") -> 0.015 | K57: =IFERROR(-K153/K$113,"N/A") -> 0.015 | L57: 0.017 | M57: 0.017 | N57: 0.019 | O57: 0.019 | P57: 0.02
C58: Deferred Revenue % Gross Sales: | F58: % | G58: =IFERROR(+G157/G84,"N/A") -> 0 | H58: =IFERROR(+H157/H84,"N/A") -> 0.002 | I58: =IFERROR(+I157/I84,"N/A") -> 0.005 | J58: =IFERROR(+J157/J84,"N/A") -> 0.0075 | K58: =IFERROR(+K157/K84,"N/A") -> 0.01 | L58: 0.012 | M58: 0.014 | N58: 0.015 | O58: 0.017 | P58: 0.019
C60: CapEx % Revenue: | F60: % | G60: =IFERROR(-G181/G84,"N/A") -> 0.004 | H60: =IFERROR(-H181/H84,"N/A") -> 0.005 | I60: =IFERROR(-I181/I84,"N/A") -> 0.005 | J60: =IFERROR(-J181/J84,"N/A") -> 0.005 | K60: =IFERROR(-K181/K84,"N/A") -> 0.006 | L60: 0.006 | M60: 0.007 | N60: 0.007 | O60: 0.008 | P60: 0.008
C61: Sales / (Purchases) of Other Assets: | F61: $ | G61: =+G182 -> -127 | H61: =+H182 -> -254 | I61: =+I182 -> -321 | J61: =+J182 -> -423 | K61: =+K182 -> -501 | L61: -500 | M61: -600 | N61: -750 | O61: -900 | P61: -1100
C63: Change in Other Non-Current Liabilities: | F63: $ | G63: =+G186 -> 53 | H63: =+H186 -> 102 | I63: =+I186 -> 1211 | J63: =+J186 -> 2310 | K63: =+K186 -> 3123 | L63: 3500 | M63: 3800 | N63: 4100 | O63: 4400 | P63: 4700
C64: Owner Draw % Gross Sales: | F64: $ | G64: =-G187/G84 -> 0.37631652 | H64: =-H187/H84 -> 0.24700079 | I64: =-I187/I84 -> 0.19644082 | J64: =-J187/J84 -> 0.19810297 | K64: =-K187/K84 -> 0.20961658 | L64: 0.2 | M64: =+L64 -> 0.2 | N64: =+M64 -> 0.2 | O64: =+N64 -> 0.2 | P64: =+O64 -> 0.2
C66: Dividends or Owner Draw: | F66: $ | G66: =-G187 -> 80000 | H66: =-H187 -> 100000 | I66: =-I187 -> 120000 | J66: =-J187 -> 150000 | K66: =-K187 -> 200000 | L66: =-L187 -> 222575.84 | M66: =-M187 -> 264169.16 | N66: =-N187 -> 314588.95 | ... P66: =-P187 -> 420254.79
C68: Owner Draw - G&A Allocation: | F68: % | G68: 0.25 | H68: 0.2 | I68: 0.15 | J68: 0.1 | K68: 0.1 | L68: 0.05 | M68: 0.05 | N68: 0.05 | O68: 0.05 | P68: 0.05
C69: Owner Draw - S&M Allocation: | F69: % | G69: 0.5 | H69: 0.5 | I69: 0.5 | J69: 0.55 | K69: 0.55 | L69: 0.6 | M69: 0.65 | N69: 0.65 | O69: 0.65 | P69: 0.65
C70: Owner Draw - R&D Allocation: | F70: % | G70: 0.25 | H70: 0.3 | I70: 0.35 | J70: 0.35 | K70: 0.35 | L70: 0.35 | M70: 0.3 | N70: 0.3 | O70: 0.3 | P70: 0.3
C72: Owner Draw - G&A Allocation: | F72: $ | G72: =+G$66*G68 -> 20000 | H72: =+H$66*H68 -> 20000 | I72: =+I$66*I68 -> 18000 | J72: =+J$66*J68 -> 15000 | K72: =+K$66*K68 -> 20000 | L72: =+L$66*L68 -> 11128.792 | M72: =+M$66*M68 -> 13208.458 | N72: =+N$66*N68 -> 15729.447 | ... P72: =+P$66*P68 -> 21012.739
C73: Owner Draw - S&M Allocation: | F73: $ | G73: =+G$66*G69 -> 40000 | H73: =+H$66*H69 -> 50000 | I73: =+I$66*I69 -> 60000 | J73: =+J$66*J69 -> 82500 | K73: =+K$66*K69 -> 110000 | L73: =+L$66*L69 -> 133545.5 | M73: =+M$66*M69 -> 171709.96 | N73: =+N$66*N69 -> 204482.82 | ... P73: =+P$66*P69 -> 273165.61
C74: Owner Draw - R&D Allocation: | F74: $ | G74: =+G$66*G70 -> 20000 | H74: =+H$66*H70 -> 30000 | I74: =+I$66*I70 -> 42000 | J74: =+J$66*J70 -> 52500 | K74: =+K$66*K70 -> 70000 | L74: =+L$66*L70 -> 77901.542 | M74: =+M$66*M70 -> 79250.749 | N74: =+N$66*N70 -> 94376.685 | ... P74: =+P$66*P70 -> 126076.44
G76: =+$G$5 -> Historical | L76: =+$L$5 -> Projected
B77: Income Statement: | F77: =+$F$6 -> Units: | G77: =+$G$6 -> Year 1 | H77: =+$H$6 -> Year 2 | I77: =+$I$6 -> Year 3 | J77: =+$J$6 -> Year 4 | K77: =+$K$6 -> Year 5 | L77: =+$L$6 -> Year 6 | M77: =+$M$6 -> Year 7 | N77: =+$N$6 -> Year 8 | O77: =+$O$6 -> Year 9 | P77: =+$P$6 -> Year 10
C78: Gross Sales by Category:
C79: (+) Online Courses: | F79: $ | G79: 108419.37 | H79: 263157.05 | I79: 433718.41 | J79: 583030.14 | K79: 734674.71 | L79: =+L8*L9 -> 840000 | M79: =+M8*M9 -> 988000 | N79: =+N8*N9 -> 1176000 | O79: =+O8*O9 -> 1350000 | P79: =+P8*P9 -> 1560000
C80: (+) Product Sales Referred by Affiliates: | F80: $ | G80: 40391.53 | H80: 52631.41 | I80: 61087.1 | J80: 37859.1 | K80: 47706.15 | L80: =+K80*(1+L12) -> 59632.688 | M80: =+L80*(1+M12) -> 71559.225 | N80: =+M80*(1+N12) -> 82293.109 | O80: =+N80*(1+O12) -> 90522.42 | P80: =+O80*(1+P12) -> 97764.213
C81: (+) Coaching & Resume Editing Services: | F81: $ | G81: 36139.79 | H81: 44534.27 | I81: 54978.39 | J81: 60574.56 | K81: 66788.61 | L81: =+K81*(1+L13) -> 73467.471 | M81: =+L81*(1+M13) -> 80814.218 | N81: =+M81*(1+N13) -> 87279.356 | O81: =+N81*(1+O13) -> 94261.704 | P81: =+O81*(1+P13) -> 98032.172
C82: (+) Sales to Institutions: | F82: $ | G82: 8503.48 | H82: 20242.85 | I82: 30543.55 | J82: 53002.74 | K82: 76329.84 | L82: =+K82*(1+L14) -> 106861.78 | M82: =+L82*(1+M14) -> 144263.4 | N82: =+M82*(1+N14) -> 187542.42 | O82: =+N82*(1+O14) -> 243805.14 | P82: =+O82*(1+P14) -> 299880.32
C83: (+) Commissions from Other Products: | F83: $ | G83: 19132.83 | H83: 24291.42 | I83: 30543.55 | J83: 22715.46 | K83: 28623.69 | L83: =+K83*(1+L15) -> 32917.243 | M83: =+L83*(1+M15) -> 36208.968 | N83: =+M83*(1+N15) -> 39829.865 | O83: =+N83*(1+O15) -> 43016.254 | P83: =+O83*(1+P15) -> 45597.229
C84: Total Gross Sales: | F84: $ | G84: =SUM(G79:G83) -> 212587 | H84: =SUM(H79:H83) -> 404857 | I84: =SUM(I79:I83) -> 610871 | J84: =SUM(J79:J83) -> 757182 | K84: =SUM(K79:K83) -> 954123 | L84: =SUM(L79:L83) -> 1112879.2 | M84: =SUM(M79:M83) -> 1320845.8 | N84: =SUM(N79:N83) -> 1572944.7 | ... P84: =SUM(P79:P83) -> 2101273.9
C86: Commissions by Category:
C87: (-) Commissions Paid to Affiliates: | F87: $ | G87: -20195.765 | H87: -26315.705 | I87: -30543.55 | J87: -18929.55 | K87: -23853.075 | L87: =-L80*L18 -> -29816.344 | M87: =-M80*M18 -> -35779.612 | N87: =-N80*N18 -> -41146.554 | O87: =-O80*O18 -> -45261.21 | P87: =-P80*P18 -> -48882.107
C88: (-) Commissions Paid to Coaches: | F88: $ | G88: -18069.895 | H88: -22267.135 | I88: -27489.195 | J88: -30287.28 | K88: -33394.305 | L88: =-L81*L19 -> -36733.736 | M88: =-M81*M19 -> -40407.109 | N88: =-N81*N19 -> -43639.678 | O88: =-O81*O19 -> -47130.852 | P88: =-P81*P19 -> -49016.086
C89: (-) Commissions Paid to Sales Reps: | F89: $ | G89: 0 | H89: -8097.14 | I89: -12217.42 | J89: -21201.096 | K89: -30531.936 | L89: =-L82*L20 -> -42744.71 | M89: =-M82*M20 -> -57705.359 | N89: =-N82*N20 -> -75016.967 | O89: =-O82*O20 -> -97522.057 | P89: =-P82*P20 -> -119952.13
C90: Total Commissions: | F90: $ | G90: =SUM(G87:G89) -> -38265.66 | H90: =SUM(H87:H89) -> -56679.98 | I90: =SUM(I87:I89) -> -70250.165 | J90: =SUM(J87:J89) -> -70417.926 | K90: =SUM(K87:K89) -> -87779.316 | L90: =SUM(L87:L89) -> -109294.79 | M90: =SUM(M87:M89) -> -133892.08 | N90: =SUM(N87:N89) -> -159803.2 | ... P90: =SUM(P87:P89) -> -217850.32
C92: Gross Sales Less Commissions: | F92: $ | G92: =+G84+G90 -> 174321.34 | H92: =+H84+H90 -> 348177.02 | I92: =+I84+I90 -> 540620.84 | J92: =+J84+J90 -> 686764.07 | K92: =+K84+K90 -> 866343.68 | L92: =+L84+L90 -> 1003584.4 | M92: =+M84+M90 -> 1186953.7 | N92: =+N84+N90 -> 1413141.5 | ... P92: =+P84+P90 -> 1883423.6
C94: Fees & Refunds:
C95: (-) Payment Fees: | F95: $ | G95: -6165.023 | H95: -11335.996 | I95: -17104.388 | J95: -21201.096 | K95: -26715.444 | L95: =-L$84*L22 -> -31160.617 | M95: =-M$84*M22 -> -36983.683 | N95: =-N$84*N22 -> -45615.398 | O95: =-O$84*O22 -> -52826.56 | P95: =-P$84*P22 -> -63038.218
C96: (-) Refunds: | F96: $ | G96: -6377.61 | H96: -12550.567 | I96: -21380.485 | J96: -30287.28 | K96: -39119.043 | L96: =-L$84*L23 -> -50079.563 | M96: =-M$84*M23 -> -59438.061 | N96: =-N$84*N23 -> -78647.237 | O96: =-O$84*O23 -> -91080.276 | P96: =-P$84*P23 -> -126076.44
C97: Total Fees & Refunds: | F97: $ | G97: =SUM(G95:G96) -> -12542.633 | H97: =SUM(H95:H96) -> -23886.563 | I97: =SUM(I95:I96) -> -38484.873 | J97: =SUM(J95:J96) -> -51488.376 | K97: =SUM(K95:K96) -> -65834.487 | L97: =SUM(L95:L96) -> -81240.18 | M97: =SUM(M95:M96) -> -96421.744 | N97: =SUM(N95:N96) -> -124262.63 | ... P97: =SUM(P95:P96) -> -189114.65
C99: Net Sales After Fees and Refunds: | F99: $ | G99: =+G92+G97 -> 161778.71 | H99: =+H92+H97 -> 324290.46 | I99: =+I92+I97 -> 502135.96 | J99: =+J92+J97 -> 635275.7 | K99: =+K92+K97 -> 800509.2 | L99: =+L92+L97 -> 922344.21 | M99: =+M92+M97 -> 1090532 | N99: =+N92+N97 -> 1288878.9 | ... P99: =+P92+P97 -> 1694309
C101: Operating Expenses:
C102: (-) Tax, Bookkeeping & Legal Fees: | F102: $ | G102: -1250 | H102: -1500 | I102: -1500 | J102: -2000 | K102: -2250 | L102: =-L$84*L25 -> -2225.7584 | M102: =-M$84*M25 -> -2641.6916 | N102: =-N$84*N25 -> -4718.8342 | O102: =-O$84*O25 -> -5464.8166 | P102: =-P$84*P25 -> -6303.8218
C103: (-) Customer Support: | F103: $ | G103: 0 | H103: -30000 | I103: -30000 | J103: -45000 | K103: -60000 | L103: =-L34*L43 -> -62400 | M103: =-M34*M43 -> -97344 | N103: =-N34*N43 -> -101237.76 | O103: =-O34*O43 -> -140383.03 | P103: =-P34*P43 -> -145998.35
C104: (-) Online Advertising: | F104: $ | G104: 0 | H104: -10000 | I104: -20000 | J104: -20000 | K104: -30000 | L104: =-L$84*L26 -> -34499.255 | M104: =-M$84*M26 -> -43587.912 | N104: =-N$84*N26 -> -55053.066 | O104: =-O$84*O26 -> -63756.193 | P104: =-P$84*P26 -> -77747.136
C105: (-) Web Design & Development: | F105: $ | G105: -10000 | H105: -30000 | I105: -60000 | J105: -60000 | K105: -60000 | L105: =-L35*L44 -> -93600 | M105: =-M35*M44 -> -97344 | N105: =-N35*N44 -> -134983.68 | O105: =-O35*O44 -> -140383.03 | P105: =-P35*P44 -> -145998.35
C106: (-) Sales Reps - Base Salaries: | F106: $ | G106: 0 | H106: -10000 | I106: -12000 | J106: -12000 | K106: -12000 | L106: =-L36*L45 -> -12480 | M106: =-M36*M45 -> -25958.4 | N106: =-N36*N45 -> -26996.736 | O106: =-O36*O45 -> -28076.605 | P106: =-P36*P45 -> -29199.67
C107: (-) Marketing Staff: | F107: $ | G107: 0 | H107: 0 | I107: -40000 | J107: -60000 | K107: -80000 | L107: =-L37*L46 -> -83200 | M107: =-M37*M46 -> -86528 | N107: =-N37*N46 -> -89989.12 | O107: =-O37*O46 -> -116985.86 | P107: =-P37*P46 -> -145998.35
C108: (-) IT Infrastructure: | F108: $ | G108: -2000 | H108: -5000 | I108: -10000 | J108: -15000 | K108: -20000 | L108: =-L$84*L27 -> -24483.342 | M108: =-M$84*M27 -> -31700.299 | N108: =-N$84*N27 -> -37750.674 | O108: =-O$84*O27 -> -47361.744 | P108: =-P$84*P27 -> -54633.122
C109: (-) Travel & Moving Expenses: | F109: $ | G109: -5768 | H109: -8798 | I109: -6012 | J109: -5123 | K109: -6763 | L109: =-L$84*L28 -> -7790.1542 | M109: =-M$84*M28 -> -7925.0749 | N109: =-N$84*N28 -> -7864.7237 | O109: =-O$84*O28 -> -7286.4221 | P109: =-P$84*P28 -> -8405.0958
C110: (-) Depreciation & Amortization: | F110: $ | G110: -568 | H110: -792 | I110: -1011 | J110: -1523 | K110: -2024 | L110: =-L$84*L29 -> -2225.7584 | M110: =-M$84*M29 -> -2641.6916 | N110: =-N$84*N29 -> -4718.8342 | O110: =-O$84*O29 -> -7286.4221 | P110: =-P$84*P29 -> -8405.0958
C111: (-) Product Creation: | F111: $ | G111: 0 | H111: 0 | I111: -40000 | J111: -40000 | K111: -80000 | L111: =-L38*L47 -> -83200 | M111: =-M38*M47 -> -86528 | N111: =-N38*N47 -> -179978.24 | O111: =-O38*O47 -> -187177.37 | P111: =-P38*P47 -> -194664.46
C112: (-) Content Creation: | F112: $ | G112: 0 | H112: 0 | I112: -30000 | J112: -30000 | K112: -30000 | L112: =-L39*L48 -> -31200 | M112: =-M39*M48 -> -48672 | N112: =-N39*N48 -> -50618.88 | O112: =-O39*O48 -> -70191.514 | P112: =-P39*P48 -> -72999.174
C113: Total Operating Expenses: | F113: $ | G113: =SUM(G102:G112) -> -19586 | H113: =SUM(H102:H112) -> -96090 | I113: =SUM(I102:I112) -> -250523 | J113: =SUM(J102:J112) -> -290646 | K113: =SUM(K102:K112) -> -383037 | L113: =SUM(L102:L112) -> -437304.27 | M113: =SUM(M102:M112) -> -530871.07 | N113: =SUM(N102:N112) -> -693910.55 | ... P113: =SUM(P102:P112) -> -890352.62
C115: Operating Income: | F115: $ | G115: =+G99+G113 -> 142192.71 | H115: =+H99+H113 -> 228200.46 | I115: =+I99+I113 -> 251612.96 | J115: =+J99+J113 -> 344629.7 | K115: =+K99+K113 -> 417472.2 | L115: =+L99+L113 -> 485039.94 | M115: =+M99+M113 -> 559660.91 | N115: =+N99+N113 -> 594968.36 | ... P115: =+P99+P113 -> 803956.34
C117: (-) Income Taxes: | F117: $ | G117: -35548.177 | H117: -61614.123 | I117: -70451.629 | J117: -99942.612 | K117: -125241.66 | L117: =-L115*L31 -> -145511.98 | M117: =-M115*M31 -> -167898.27 | N117: =-N115*N31 -> -178490.51 | O117: =-O115*O31 -> -202029.47 | P117: =-P115*P31 -> -241186.9
C119: Net Income: | F119: $ | G119: =+G115+G117 -> 106644.53 | H119: =+H115+H117 -> 166586.33 | I119: =+I115+I117 -> 181161.33 | J119: =+J115+J117 -> 244687.09 | K119: =+K115+K117 -> 292230.54 | L119: =+L115+L117 -> 339527.96 | M119: =+M115+M117 -> 391762.64 | N119: =+N115+N117 -> 416477.85 | ... P119: =+P115+P117 -> 562769.44
G121: =+$G$5 -> Historical | L121: =+$L$5 -> Projected
B122: Key Metrics and Ratios: | F122: =+$F$6 -> Units: | G122: =+$G$6 -> Year 1 | H122: =+$H$6 -> Year 2 | I122: =+$I$6 -> Year 3 | J122: =+$J$6 -> Year 4 | K122: =+$K$6 -> Year 5 | L122: =+$L$6 -> Year 6 | M122: =+$M$6 -> Year 7 | N122: =+$N$6 -> Year 8 | O122: =+$O$6 -> Year 9 | P122: =+$P$6 -> Year 10
C124: (+) Operating Income: | F124: $ | G124: =+G115 -> 142192.71 | H124: =+H115 -> 228200.46 | I124: =+I115 -> 251612.96 | J124: =+J115 -> 344629.7 | K124: =+K115 -> 417472.2 | L124: =+L115 -> 485039.94 | M124: =+M115 -> 559660.91 | N124: =+N115 -> 594968.36 | ... P124: =+P115 -> 803956.34
C125: (+) Depreciation & Amortization: | F125: $ | G125: =-G110 -> 568 | H125: =-H110 -> 792 | I125: =-I110 -> 1011 | J125: =-J110 -> 1523 | K125: =-K110 -> 2024 | L125: =-L110 -> 2225.7584 | M125: =-M110 -> 2641.6916 | N125: =-N110 -> 4718.8342 | ... P125: =-P110 -> 8405.0958
C126: EBITDA: | F126: $ | G126: =SUM(G124:G125) -> 142760.71 | H126: =SUM(H124:H125) -> 228992.46 | I126: =SUM(I124:I125) -> 252623.96 | J126: =SUM(J124:J125) -> 346152.7 | K126: =SUM(K124:K125) -> 419496.2 | L126: =SUM(L124:L125) -> 487265.7 | M126: =SUM(M124:M125) -> 562302.61 | N126: =SUM(N124:N125) -> 599687.2 | ... P126: =SUM(P124:P125) -> 812361.43
C128: Revenue Growth: | F128: % | G128: =IFERROR(+G84/F84-1,"N/A") -> N/A | H128: =IFERROR(+H84/G84-1,"N/A") -> 0.90442972 | I128: =IFERROR(+I84/H84-1,"N/A") -> 0.50885621 | J128: =IFERROR(+J84/I84-1,"N/A") -> 0.23951211 | K128: =IFERROR(+K84/J84-1,"N/A") -> 0.26009731 | L128: =IFERROR(+L84/K84-1,"N/A") -> 0.16638964 | M128: =IFERROR(+M84/L84-1,"N/A") -> 0.1868726 | N128: =IFERROR(+N84/M84-1,"N/A") -> 0.19086175 | ... P128: =IFERROR(+P84/O84-1,"N/A") -> 0.15352853
C129: Operating Margin: | F129: % | G129: =IFERROR(+G115/G84,"N/A") -> 0.66886831 | H129: =IFERROR(+H115/H84,"N/A") -> 0.56365694 | I129: =IFERROR(+I115/I84,"N/A") -> 0.41189214 | J129: =IFERROR(+J115/J84,"N/A") -> 0.45514777 | K129: =IFERROR(+K115/K84,"N/A") -> 0.43754547 | L129: =IFERROR(+L115/L84,"N/A") -> 0.43584241 | M129: =IFERROR(+M115/M84,"N/A") -> 0.42371404 | N129: =IFERROR(+N115/N84,"N/A") -> 0.37825128 | ... P129: =IFERROR(+P115/P84,"N/A") -> 0.38260425
C130: EBITDA Margin: | F130: % | G130: =IFERROR(+G126/G84,"N/A") -> 0.67154016 | H130: =IFERROR(+H126/H84,"N/A") -> 0.56561318 | I130: =IFERROR(+I126/I84,"N/A") -> 0.41354715 | J130: =IFERROR(+J126/J84,"N/A") -> 0.45715917 | K130: =IFERROR(+K126/K84,"N/A") -> 0.43966679 | L130: =IFERROR(+L126/L84,"N/A") -> 0.43784241 | M130: =IFERROR(+M126/M84,"N/A") -> 0.42571404 | N130: =IFERROR(+N126/N84,"N/A") -> 0.38125128 | ... P130: =IFERROR(+P126/P84,"N/A") -> 0.38660425
...

Sheet Company0462-GAAP
B2: ="Sample Private Company Financial Statements - "&Company_Name&" - U.S. GAAP / IFRS-Compliant" -> Sample Private Company Financial Statements - Capital Capable Media LLC - U.S. GAAP / IFRS-Compliant
B3: ($ USD as Stated)
B5: Assumptions:
C7: Potential Buyer's Tax Rate: | F7: 0.35
C8: Company Name: | F8: Capital Capable Media LLC
C10: Private Company Discount: | F10: 0.3
G12: Historical | L12: Projected
B13: Income Statement: | F13: Units: | G13: Year 1 | H13: Year 2 | I13: Year 3 | J13: Year 4 | K13: Year 5 | L13: Year 6 | M13: Year 7 | N13: Year 8 | O13: Year 9 | P13: Year 10
C15: Gross Sales: | F15: $ | G15: ='Company0462-Internal'!G84 -> 212587 | H15: ='Company0462-Internal'!H84 -> 404857 | I15: ='Company0462-Internal'!I84 -> 610871 | J15: ='Company0462-Internal'!J84 -> 757182 | K15: ='Company0462-Internal'!K84 -> 954123 | L15: ='Company0462-Internal'!L84 -> 1112879.2 | M15: ='Company0462-Internal'!M84 -> 1320845.8 | N15: ='Company0462-Internal'!N84 -> 1572944.7 | ... P15: ='Company0462-Internal'!P84 -> 2101273.9
C16: (-) Allowances & Refunds: | F16: $ | G16: ='Company0462-Internal'!G96 -> -6377.61 | H16: ='Company0462-Internal'!H96 -> -12550.567 | I16: ='Company0462-Internal'!I96 -> -21380.485 | J16: ='Company0462-Internal'!J96 -> -30287.28 | K16: ='Company0462-Internal'!K96 -> -39119.043 | L16: ='Company0462-Internal'!L96 -> -50079.563 | M16: ='Company0462-Internal'!M96 -> -59438.061 | N16: ='Company0462-Internal'!N96 -> -78647.237 | ... P16: ='Company0462-Internal'!P96 -> -126076.44
C17: Net Sales: | F17: $ | G17: =SUM(G15:G16) -> 206209.39 | H17: =SUM(H15:H16) -> 392306.43 | I17: =SUM(I15:I16) -> 589490.52 | J17: =SUM(J15:J16) -> 726894.72 | K17: =SUM(K15:K16) -> 915003.96 | L17: =SUM(L15:L16) -> 1062799.6 | M17: =SUM(M15:M16) -> 1261407.7 | N17: =SUM(N15:N16) -> 1494297.5 | ... P17: =SUM(P15:P16) -> 1975197.5
C19: Operating Expenses:
C20: (+) General & Administrative: | F20: $ | G20: =-'Company0462-Internal'!G95-'Company0462-Internal'!G102-'Company0462-Internal'!G103-'Company0462-Internal'!G105-'Company0462-Internal'!G108+'Company0462-Internal'!G72 -> 39415.023 | H20: =-'Company0462-Internal'!H95-'Company0462-Internal'!H102-'Company0462-Internal'!H103-'Company0462-Internal'!H105-'Company0462-Internal'!H108+'Company0462-Internal'!H72 -> 97835.996 | I20: =-'Company0462-Internal'!I95-'Company0462-Internal'!I102-'Company0462-Internal'!I103-'Company0462-Internal'!I105-'Company0462-Internal'!I108+'Company0462-Internal'!I72 -> 136604.39 | J20: =-'Company0462-Internal'!J95-'Company0462-Internal'!J102-'Company0462-Internal'!J103-'Company0462-Internal'!J105-'Company0462-Internal'!J108+'Company0462-Internal'!J72 -> 158201.1 | K20: =-'Company0462-Internal'!K95-'Company0462-Internal'!K102-'Company0462-Internal'!K103-'Company0462-Internal'!K105-'Company0462-Internal'!K108+'Company0462-Internal'!K72 -> 188965.44 | L20: =-'Company0462-Internal'!L95-'Company0462-Internal'!L102-'Company0462-Internal'!L103-'Company0462-Internal'!L105-'Company0462-Internal'!L108+'Company0462-Internal'!L72 -> 224998.51 | M20: =-'Company0462-Internal'!M95-'Company0462-Internal'!M102-'Company0462-Internal'!M103-'Company0462-Internal'!M105-'Company0462-Internal'!M108+'Company0462-Internal'!M72 -> 279222.13 | N20: =-'Company0462-Internal'!N95-'Company0462-Internal'!N102-'Company0462-Internal'!N103-'Company0462-Internal'!N105-'Company0462-Internal'!N108+'Company0462-Internal'!N72 -> 340035.79 | ... P20: =-'Company0462-Internal'!P95-'Company0462-Internal'!P102-'Company0462-Internal'!P103-'Company0462-Internal'!P105-'Company0462-Internal'!P108+'Company0462-Internal'!P72 -> 436984.6
C21: (+) Sales & Marketing: | F21: $ | G21: =-'Company0462-Internal'!G90-'Company0462-Internal'!G104-'Company0462-Internal'!G106-'Company0462-Internal'!G107+'Company0462-Internal'!G73 -> 78265.66 | H21: =-'Company0462-Internal'!H90-'Company0462-Internal'!H104-'Company0462-Internal'!H106-'Company0462-Internal'!H107+'Company0462-Internal'!H73 -> 126679.98 | I21: =-'Company0462-Internal'!I90-'Company0462-Internal'!I104-'Company0462-Internal'!I106-'Company0462-Internal'!I107+'Company0462-Internal'!I73 -> 202250.17 | J21: =-'Company0462-Internal'!J90-'Company0462-Internal'!J104-'Company0462-Internal'!J106-'Company0462-Internal'!J107+'Company0462-Internal'!J73 -> 244917.93 | K21: =-'Company0462-Internal'!K90-'Company0462-Internal'!K104-'Company0462-Internal'!K106-'Company0462-Internal'!K107+'Company0462-Internal'!K73 -> 319779.32 | L21: =-'Company0462-Internal'!L90-'Company0462-Internal'!L104-'Company0462-Internal'!L106-'Company0462-Internal'!L107+'Company0462-Internal'!L73 -> 373019.55 | M21: =-'Company0462-Internal'!M90-'Company0462-Internal'!M104-'Company0462-Internal'!M106-'Company0462-Internal'!M107+'Company0462-Internal'!M73 -> 461676.35 | N21: =-'Company0462-Internal'!N90-'Company0462-Internal'!N104-'Company0462-Internal'!N106-'Company0462-Internal'!N107+'Company0462-Internal'!N73 -> 536324.94 | ... P21: =-'Company0462-Internal'!P90-'Company0462-Internal'!P104-'Company0462-Internal'!P106-'Company0462-Internal'!P107+'Company0462-Internal'!P73 -> 743961.09
C22: (+) Research & Development: | F22: $ | G22: =-'Company0462-Internal'!G111-'Company0462-Internal'!G112+'Company0462-Internal'!G74 -> 20000 | H22: =-'Company0462-Internal'!H111-'Company0462-Internal'!H112+'Company0462-Internal'!H74 -> 30000 | I22: =-'Company0462-Internal'!I111-'Company0462-Internal'!I112+'Company0462-Internal'!I74 -> 112000 | J22: =-'Company0462-Internal'!J111-'Company0462-Internal'!J112+'Company0462-Internal'!J74 -> 122500 | K22: =-'Company0462-Internal'!K111-'Company0462-Internal'!K112+'Company0462-Internal'!K74 -> 180000 | L22: =-'Company0462-Internal'!L111-'Company0462-Internal'!L112+'Company0462-Internal'!L74 -> 192301.54 | M22: =-'Company0462-Internal'!M111-'Company0462-Internal'!M112+'Company0462-Internal'!M74 -> 214450.75 | N22: =-'Company0462-Internal'!N111-'Company0462-Internal'!N112+'Company0462-Internal'!N74 -> 324973.8 | ... P22: =-'Company0462-Internal'!P111-'Company0462-Internal'!P112+'Company0462-Internal'!P74 -> 393740.07
C23: (+) Depreciation & Amortization: | F23: $ | G23: =-'Company0462-Internal'!G110 -> 568 | H23: =-'Company0462-Internal'!H110 -> 792 | I23: =-'Company0462-Internal'!I110 -> 1011 | J23: =-'Company0462-Internal'!J110 -> 1523 | K23: =-'Company0462-Internal'!K110 -> 2024 | L23: =-'Company0462-Internal'!L110 -> 2225.7584 | M23: =-'Company0462-Internal'!M110 -> 2641.6916 | N23: =-'Company0462-Internal'!N110 -> 4718.8342 | ... P23: =-'Company0462-Internal'!P110 -> 8405.0958
C24: Total Operating Expenses: | F24: $ | G24: =SUM(G20:G23) -> 138248.68 | H24: =SUM(H20:H23) -> 255307.98 | I24: =SUM(I20:I23) -> 451865.55 | J24: =SUM(J20:J23) -> 527142.02 | K24: =SUM(K20:K23) -> 690768.76 | L24: =SUM(L20:L23) -> 792545.36 | M24: =SUM(M20:M23) -> 957990.92 | N24: =SUM(N20:N23) -> 1206053.4 | ... P24: =SUM(P20:P23) -> 1583090.9
C26: Operating Income: | F26: $ | G26: =+G17-G24 -> 67960.707 | H26: =+H17-H24 -> 136998.46 | I26: =+I17-I24 -> 137624.96 | J26: =+J17-J24 -> 199752.7 | K26: =+K17-K24 -> 224235.2 | L26: =+L17-L24 -> 270254.26 | M26: =+M17-M24 -> 303416.83 | N26: =+N17-N24 -> 288244.14 | ... P26: =+P17-P24 -> 392106.65
C27: (+) Net Interest Income / (-) Expense: | F27: $ | G27: 0 | H27: 0 | I27: 0 | J27: 0 | K27: 0 | L27: 0 | M27: 0 | N27: 0 | O27: 0 | P27: 0
C28: Pre-Tax Income: | F28: $ | G28: =SUM(G26:G27) -> 67960.707 | H28: =SUM(H26:H27) -> 136998.46 | I28: =SUM(I26:I27) -> 137624.96 | J28: =SUM(J26:J27) -> 199752.7 | K28: =SUM(K26:K27) -> 224235.2 | L28: =SUM(L26:L27) -> 270254.26 | M28: =SUM(M26:M27) -> 303416.83 | N28: =SUM(N26:N27) -> 288244.14 | ... P28: =SUM(P26:P27) -> 392106.65
C30: Income Taxes: | F30: $ | G30: =-'Company0462-Internal'!G117 -> 35548.177 | H30: =-'Company0462-Internal'!H117 -> 61614.123 | I30: =-'Company0462-Internal'!I117 -> 70451.629 | J30: =-'Company0462-Internal'!J117 -> 99942.612 | K30: =-'Company0462-Internal'!K117 -> 125241.66 | L30: =+L28*Tax_Rate -> 94588.991 | M30: =+M28*Tax_Rate -> 106195.89 | N30: =+N28*Tax_Rate -> 100885.45 | O30: =+O28*Tax_Rate -> 110738.91 | P30: =+P28*Tax_Rate -> 137237.33
C32: Net Income: | F32: $ | G32: =+G28-G30 -> 32412.53 | H32: =+H28-H30 -> 75384.334 | I32: =+I28-I30 -> 67173.333 | J32: =+J28-J30 -> 99810.086 | K32: =+K28-K30 -> 98993.538 | L32: =+L28-L30 -> 175665.27 | M32: =+M28-M30 -> 197220.94 | N32: =+N28-N30 -> 187358.69 | ... P32: =+P28-P30 -> 254869.32
G34: =+$G$12 -> Historical | L34: =+$L$12 -> Projected
B35: Key Metrics and Ratios: | F35: =+$F$13 -> Units: | G35: =+$G$13 -> Year 1 | H35: =+$H$13 -> Year 2 | I35: =+$I$13 -> Year 3 | J35: =+$J$13 -> Year 4 | K35: =+$K$13 -> Year 5 | L35: =+$L$13 -> Year 6 | M35: =+$M$13 -> Year 7 | N35: =+$N$13 -> Year 8 | O35: =+$O$13 -> Year 9 | P35: =+$P$13 -> Year 10
C37: (+) Operating Income: | F37: $ | G37: =+G26 -> 67960.707 | H37: =+H26 -> 136998.46 | I37: =+I26 -> 137624.96 | J37: =+J26 -> 199752.7 | K37: =+K26 -> 224235.2 | L37: =+L26 -> 270254.26 | M37: =+M26 -> 303416.83 | N37: =+N26 -> 288244.14 | ... P37: =+P26 -> 392106.65
C38: (+) Depreciation & Amortization: | F38: $ | G38: =+G23 -> 568 | H38: =+H23 -> 792 | I38: =+I23 -> 1011 | J38: =+J23 -> 1523 | K38: =+K23 -> 2024 | L38: =+L23 -> 2225.7584 | M38: =+M23 -> 2641.6916 | N38: =+N23 -> 4718.8342 | ... P38: =+P23 -> 8405.0958
C39: EBITDA: | F39: $ | G39: =SUM(G37:G38) -> 68528.707 | H39: =SUM(H37:H38) -> 137790.46 | I39: =SUM(I37:I38) -> 138635.96 | J39: =SUM(J37:J38) -> 201275.7 | K39: =SUM(K37:K38) -> 226259.2 | L39: =SUM(L37:L38) -> 272480.02 | M39: =SUM(M37:M38) -> 306058.52 | N39: =SUM(N37:N38) -> 292962.97 | ... P39: =SUM(P37:P38) -> 400511.74
C41: Revenue Growth: | F41: % | G41: =IFERROR(+G17/F17-1,"N/A") -> N/A | H41: =IFERROR(+H17/G17-1,"N/A") -> 0.90246639 | I41: =IFERROR(+I17/H17-1,"N/A") -> 0.5026277 | J41: =IFERROR(+J17/I17-1,"N/A") -> 0.23308976 | K41: =IFERROR(+K17/J17-1,"N/A") -> 0.25878471 | L41: =IFERROR(+L17/K17-1,"N/A") -> 0.16152461 | M41: =IFERROR(+M17/L17-1,"N/A") -> 0.1868726 | N41: =IFERROR(+N17/M17-1,"N/A") -> 0.18462687 | ... P41: =IFERROR(+P17/O17-1,"N/A") -> 0.14138613
C42: Operating Margin: | F42: % | G42: =IFERROR(+G37/G17,"N/A") -> 0.32957135 | H42: =IFERROR(+H37/H17,"N/A") -> 0.34921287 | I42: =IFERROR(+I37/I17,"N/A") -> 0.23346425 | J42: =IFERROR(+J37/J17,"N/A") -> 0.27480279 | K42: =IFERROR(+K37/K17,"N/A") -> 0.24506473 | L42: =IFERROR(+L37/L17,"N/A") -> 0.25428524 | M42: =IFERROR(+M37/M17,"N/A") -> 0.24053826 | N42: =IFERROR(+N37/N17,"N/A") -> 0.19289608 | ... P42: =IFERROR(+P37/P17,"N/A") -> 0.19851516
C43: EBITDA Margin: | F43: % | G43: =IFERROR(+G39/G17,"N/A") -> 0.33232583 | H43: =IFERROR(+H39/H17,"N/A") -> 0.3512317 | I43: =IFERROR(+I39/I17,"N/A") -> 0.23517929 | J43: =IFERROR(+J39/J17,"N/A") -> 0.27689801 | K43: =IFERROR(+K39/K17,"N/A") -> 0.24727674 | L43: =IFERROR(+L39/L17,"N/A") -> 0.25637949 | M43: =IFERROR(+M39/M17,"N/A") -> 0.2426325 | N43: =IFERROR(+N39/N17,"N/A") -> 0.19605398 | ... P43: =IFERROR(+P39/P17,"N/A") -> 0.20277048
C44: Net Margin: | F44: % | G44: =IFERROR(+G32/G17,"N/A") -> 0.15718261 | H44: =IFERROR(+H32/H17,"N/A") -> 0.19215676 | I44: =IFERROR(+I32/I17,"N/A") -> 0.11395151 | J44: =IFERROR(+J32/J17,"N/A") -> 0.13731024 | K44: =IFERROR(+K32/K17,"N/A") -> 0.10818919 | L44: =IFERROR(+L32/L17,"N/A") -> 0.16528541 | M44: =IFERROR(+M32/M17,"N/A") -> 0.15634987 | N44: =IFERROR(+N32/N17,"N/A") -> 0.12538245 | ... P44: =IFERROR(+P32/P17,"N/A") -> 0.12903485
C46: Effective Tax Rate: | F46: % | G46: =IFERROR(+G30/G28,"N/A") -> 0.52306955 | H46: =IFERROR(+H30/H28,"N/A") -> 0.44974319 | I46: =IFERROR(+I30/I28,"N/A") -> 0.51191025 | J46: =IFERROR(+J30/J28,"N/A") -> 0.50033173 | K46: =IFERROR(+K30/K28,"N/A") -> 0.5585281 | L46: =IFERROR(+L30/L28,"N/A") -> 0.35 | M46: =IFERROR(+M30/M28,"N/A") -> 0.35 | N46: =IFERROR(+N30/N28,"N/A") -> 0.35 | ... P46: =IFERROR(+P30/P28,"N/A") -> 0.35
G48: =+$G$12 -> Historical | L48: =+$L$12 -> Projected
B49: Balance Sheet: | F49: =+$F$13 -> Units: | G49: =+$G$13 -> Year 1 | H49: =+$H$13 -> Year 2 | I49: =+$I$13 -> Year 3 | J49: =+$J$13 -> Year 4 | K49: =+$K$13 -> Year 5 | L49: =+$L$13 -> Year 6 | M49: =+$M$13 -> Year 7 | N49: =+$N$13 -> Year 8 | O49: =+$O$13 -> Year 9 | P49: =+$P$13 -> Year 10
B50: ASSETS:
C51: Current Assets:
C52: Cash & Cash Equivalents: | F52: $ | G52: =+G104 -> 58116 | H52: =+H104 -> 132433.4 | I52: =+I104 -> 201802.53 | J52: =+J104 -> 304974.77 | K52: =+K104 -> 407072.3 | L52: =+L104 -> 586459.83 | M52: =+M104 -> 786308.23 | N52: =+N104 -> 979049.68 | ... P52: =+P104 -> 1446834.4
C53: Accounts Receivable: | F53: $ | G53: =+'Company0462-Internal'!G140 -> 0 | H53: =+'Company0462-Internal'!H140 -> 2024.285 | I53: =+'Company0462-Internal'!I140 -> 6108.71 | J53: =+'Company0462-Internal'!J140 -> 7571.82 | K53: =+'Company0462-Internal'!K140 -> 11449.476 | L53: =+'Company0462-Internal'!L140 -> 13354.55 | M53: =+'Company0462-Internal'!M140 -> 17170.996 | N53: =+'Company0462-Internal'!N140 -> 22021.226 | ... P53: =+'Company0462-Internal'!P140 -> 33620.383
C54: Total Current Assets: | F54: $ | G54: =SUM(G52:G53) -> 58116 | H54: =SUM(H52:H53) -> 134457.68 | I54: =SUM(I52:I53) -> 207911.24 | J54: =SUM(J52:J53) -> 312546.59 | K54: =SUM(K52:K53) -> 418521.77 | L54: =SUM(L52:L53) -> 599814.38 | M54: =SUM(M52:M53) -> 803479.23 | N54: =SUM(N52:N53) -> 1001070.9 | ... P54: =SUM(P52:P53) -> 1480454.8
C56: Long-Term Assets:
C57: Plants, Property & Equipment: | F57: $ | G57: =+'Company0462-Internal'!G144 -> 10038 | H57: =+'Company0462-Internal'!H144 -> 11270.285 | I57: =+'Company0462-Internal'!I144 -> 13313.64 | J57: =+'Company0462-Internal'!J144 -> 15576.55 | K57: =+'Company0462-Internal'!K144 -> 19277.288 | L57: =+K57-L86-L94 -> 23728.805 | M57: =+L57-M86-M94 -> 30333.034 | N57: =+M57-N86-N94 -> 36624.813 | O57: =+N57-O86-O94 -> 43911.235 | P57: =+O57-P86-P94 -> 52316.331
C58: Other Assets: | F58: $ | G58: =+'Company0462-Internal'!G145 -> 127 | H58: =+'Company0462-Internal'!H145 -> 381 | I58: =+'Company0462-Internal'!I145 -> 702 | J58: =+'Company0462-Internal'!J145 -> 1125 | K58: =+'Company0462-Internal'!K145 -> 1626 | L58: =+K58-L95 -> 2126 | M58: =+L58-M95 -> 2726 | N58: =+M58-N95 -> 3476 | O58: =+N58-O95 -> 4376 | P58: =+O58-P95 -> 5476
C59: Total Long-Term Assets: | F59: $ | G59: =SUM(G57:G58) -> 10165 | H59: =SUM(H57:H58) -> 11651.285 | I59: =SUM(I57:I58) -> 14015.64 | J59: =SUM(J57:J58) -> 16701.55 | K59: =SUM(K57:K58) -> 20903.288 | L59: =SUM(L57:L58) -> 25854.805 | M59: =SUM(M57:M58) -> 33059.034 | N59: =SUM(N57:N58) -> 40100.813 | ... P59: =SUM(P57:P58) -> 57792.331
C61: Total Assets: | F61: $ | G61: =+G54+G59 -> 68281 | H61: =+H54+H59 -> 146108.97 | I61: =+I54+I59 -> 221926.88 | J61: =+J54+J59 -> 329248.14 | K61: =+K54+K59 -> 439425.06 | L61: =+L54+L59 -> 625669.19 | M61: =+M54+M59 -> 836538.26 | N61: =+N54+N59 -> 1041171.7 | ... P61: =+P54+P59 -> 1538247.1
B63: LIABILITIES & EQUITY:
C64: Current Liabilities:
C65: Accounts Payable: | F65: $ | G65: =+'Company0462-Internal'!G152 -> 97.93 | H65: =+'Company0462-Internal'!H152 -> 864.81 | I65: =+'Company0462-Internal'!I152 -> 3256.799 | J65: =+'Company0462-Internal'!J152 -> 5231.628 | K65: =+'Company0462-Internal'!K152 -> 8043.777 | L65: =+'Company0462-Internal'!L152 -> 9620.6939 | M65: =+'Company0462-Internal'!M152 -> 12740.906 | N65: =+'Company0462-Internal'!N152 -> 16653.853 | ... P65: =+'Company0462-Internal'!P152 -> 23149.168
C66: Accrued Expenses: | F66: $ | G66: =+'Company0462-Internal'!G153 -> 195.86 | H66: =+'Company0462-Internal'!H153 -> 960.9 | I66: =+'Company0462-Internal'!I153 -> 3757.845 | J66: =+'Company0462-Internal'!J153 -> 4359.69 | K66: =+'Company0462-Internal'!K153 -> 5745.555 | L66: =+'Company0462-Internal'!L153 -> 7434.1725 | M66: =+'Company0462-Internal'!M153 -> 9024.8082 | N66: =+'Company0462-Internal'!N153 -> 13184.3 | ... P66: =+'Company0462-Internal'!P153 -> 17807.052
C67: Total Current Liabilities: | F67: $ | G67: =SUM(G65:G66) -> 293.79 | H67: =SUM(H65:H66) -> 1825.71 | I67: =SUM(I65:I66) -> 7014.644 | J67: =SUM(J65:J66) -> 9591.318 | K67: =SUM(K65:K66) -> 13789.332 | L67: =SUM(L65:L66) -> 17054.866 | M67: =SUM(M65:M66) -> 21765.714 | N67: =SUM(N65:N66) -> 29838.154 | ... P67: =SUM(P65:P66) -> 40956.221
C69: Long-Term Liabilities:
C70: Deferred Revenue: | F70: $ | G70: =+'Company0462-Internal'!G157 -> 0 | H70: =+'Company0462-Internal'!H157 -> 809.714 | I70: =+'Company0462-Internal'!I157 -> 3054.355 | J70: =+'Company0462-Internal'!J157 -> 5678.865 | K70: =+'Company0462-Internal'!K157 -> 9541.23 | L70: =+'Company0462-Internal'!L157 -> 13354.55 | M70: =+'Company0462-Internal'!M157 -> 18491.841 | N70: =+'Company0462-Internal'!N157 -> 23594.171 | ... P70: =+'Company0462-Internal'!P157 -> 39924.205
C71: Other Non-Current Liabilities: | F71: $ | G71: =+'Company0462-Internal'!G158 -> 53 | H71: =+'Company0462-Internal'!H158 -> 155 | I71: =+'Company0462-Internal'!I158 -> 1366 | J71: =+'Company0462-Internal'!J158 -> 3676 | K71: =+'Company0462-Internal'!K158 -> 6799 | L71: =+K71+L99 -> 10299 | M71: =+L71+M99 -> 14099 | N71: =+M71+N99 -> 18199 | O71: =+N71+O99 -> 22599 | P71: =+O71+P99 -> 27299
C72: Total Long-Term Liabilities: | F72: $ | G72: =SUM(G70:G71) -> 53 | H72: =SUM(H70:H71) -> 964.714 | I72: =SUM(I70:I71) -> 4420.355 | J72: =SUM(J70:J71) -> 9354.865 | K72: =SUM(K70:K71) -> 16340.23 | L72: =SUM(L70:L71) -> 23653.55 | M72: =SUM(M70:M71) -> 32590.841 | N72: =SUM(N70:N71) -> 41793.171 | ... P72: =SUM(P70:P71) -> 67223.205
C74: Total Liabilities: | F74: $ | G74: =+G67+G72 -> 346.79 | H74: =+H67+H72 -> 2790.424 | I74: =+I67+I72 -> 11434.999 | J74: =+J67+J72 -> 18946.183 | K74: =+K67+K72 -> 30129.562 | L74: =+L67+L72 -> 40708.417 | M74: =+M67+M72 -> 54356.555 | N74: =+N67+N72 -> 71631.325 | ... P74: =+P67+P72 -> 108179.43
C76: Equity: | F76: $ | G76: =+'Company0462-Internal'!G163-'Company0462-Internal'!G109 -> 67934.21 | H76: =+G76+H85 -> 143318.54 | I76: =+H76+I85 -> 210491.88 | J76: =+I76+J85 -> 310301.96 | K76: =+J76+K85 -> 409295.5 | L76: =+K76+L85 -> 584960.77 | M76: =+L76+M85 -> 782181.71 | N76: =+M76+N85 -> 969540.4 | O76: =+N76+O85 -> 1175198.4 | P76: =+O76+P85 -> 1430067.7
C78: TOTAL LIABILITIES & EQUITY: | F78: $ | G78: =+G74+G76 -> 68281 | H78: =+H74+H76 -> 146108.97 | I78: =+I74+I76 -> 221926.88 | J78: =+J74+J76 -> 329248.14 | K78: =+K74+K76 -> 439425.06 | L78: =+L74+L76 -> 625669.19 | M78: =+M74+M76 -> 836538.26 | N78: =+N74+N76 -> 1041171.7 | ... P78: =+P74+P76 -> 1538247.1
C80: Balance Sheet Check: | G80: =+G61-G78 -> 0 | H80: =+H61-H78 -> 0 | I80: =+I61-I78 -> 0 | J80: =+J61-J78 -> 0 | K80: =+K61-K78 -> 0 | L80: =+L61-L78 -> 0 | M80: =+M61-M78 -> 0 | N80: =+N61-N78 -> 0 | ... P80: =+P61-P78 -> 0
G82: =+$G$12 -> Historical | L82: =+$L$12 -> Projected
B83: Cash Flow Statement: | F83: =+$F$13 -> Units: | G83: =+$G$13 -> Year 1 | H83: =+$H$13 -> Year 2 | I83: =+$I$13 -> Year 3 | J83: =+$J$13 -> Year 4 | K83: =+$K$13 -> Year 5 | L83: =+$L$13 -> Year 6 | M83: =+$M$13 -> Year 7 | N83: =+$N$13 -> Year 8 | O83: =+$O$13 -> Year 9 | P83: =+$P$13 -> Year 10
C84: CASH FLOWS FROM OPERATING ACTIVITIES:
C85: Net Income: | F85: $ | G85: =+G32 -> 32412.53 | H85: =+H32 -> 75384.334 | I85: =+I32 -> 67173.333 | J85: =+J32 -> 99810.086 | K85: =+K32 -> 98993.538 | L85: =+L32 -> 175665.27 | M85: =+M32 -> 197220.94 | N85: =+N32 -> 187358.69 | ... P85: =+P32 -> 254869.32
C86: (+) Depreciation & Amortization: | F86: $ | G86: =+G23 -> 568 | H86: =+H23 -> 792 | I86: =+I23 -> 1011 | J86: =+J23 -> 1523 | K86: =+K23 -> 2024 | L86: =+L23 -> 2225.7584 | M86: =+M23 -> 2641.6916 | N86: =+N23 -> 4718.8342 | ... P86: =+P23 -> 8405.0958
C87: (+/-) Change in Accounts Receivable: | F87: $ | G87: =+'Company0462-Internal'!G174 -> 0 | H87: =+'Company0462-Internal'!H174 -> -2024.285 | I87: =+'Company0462-Internal'!I174 -> -4084.425 | J87: =+'Company0462-Internal'!J174 -> -1463.11 | K87: =+'Company0462-Internal'!K174 -> -3877.656 | L87: =+K53-L53 -> -1905.0741 | M87: =+L53-M53 -> -3816.4454 | N87: =+M53-N53 -> -4850.2309 | O87: =+N53-O53 -> -5302.8563 | P87: =+O53-P53 -> -6296.3002
C88: (+/-) Change in Accounts Payable: | F88: $ | G88: =+'Company0462-Internal'!G175 -> 97.93 | H88: =+'Company0462-Internal'!H175 -> 766.88 | I88: =+'Company0462-Internal'!I175 -> 2391.989 | J88: =+'Company0462-Internal'!J175 -> 1974.829 | K88: =+'Company0462-Internal'!K175 -> 2812.149 | L88: =+L65-K65 -> 1576.9169 | M88: =+M65-L65 -> 3120.2118 | N88: =+N65-M65 -> 3912.9475 | O88: =+O65-N65 -> 4519.3248 | P88: =+P65-O65 -> 1975.9903
C89: (+/-) Change in Accrued Expenses: | F89: $ | G89: =+'Company0462-Internal'!G176 -> 195.86 | H89: =+'Company0462-Internal'!H176 -> 765.04 | I89: =+'Company0462-Internal'!I176 -> 2796.945 | J89: =+'Company0462-Internal'!J176 -> 601.845 | K89: =+'Company0462-Internal'!K176 -> 1385.865 | L89: =+L66-K66 -> 1688.6175 | M89: =+M66-L66 -> 1590.6356 | N89: =+N66-M66 -> 4159.4922 | O89: =+O66-N66 -> 2288.4065 | P89: =+P66-O66 -> 2334.3456
C90: (+/-) Change in Deferred Revenue: | F90: $ | G90: =+'Company0462-Internal'!G177 -> 0 | H90: =+'Company0462-Internal'!H177 -> 809.714 | I90: =+'Company0462-Internal'!I177 -> 2244.641 | J90: =+'Company0462-Internal'!J177 -> 2624.51 | K90: =+'Company0462-Internal'!K177 -> 3862.365 | L90: =+L70-K70 -> 3813.3201 | M90: =+M70-L70 -> 5137.2912 | N90: =+N70-M70 -> 5102.3299 | O90: =+O70-N70 -> 7373.1226 | P90: =+P70-O70 -> 8956.911
C91: Cash Flow from Operations: | F91: $ | G91: =SUM(G85:G90) -> 33274.32 | H91: =SUM(H85:H90) -> 76493.683 | I91: =SUM(I85:I90) -> 71533.483 | J91: =SUM(J85:J90) -> 105071.16 | K91: =SUM(K85:K90) -> 105200.26 | L91: =SUM(L85:L90) -> 183064.81 | M91: =SUM(M85:M90) -> 205894.32 | N91: =SUM(N85:N90) -> 200402.06 | ... P91: =SUM(P85:P90) -> 270245.36
C93: CASH FLOWS FROM INVESTING ACTIVITIES:
C94: (-) Capital Expenditures (CapEx): | F94: $ | G94: =+'Company0462-Internal'!G181 -> -850.348 | H94: =+'Company0462-Internal'!H181 -> -2024.285 | I94: =+'Company0462-Internal'!I181 -> -3054.355 | J94: =+'Company0462-Internal'!J181 -> -3785.91 | K94: =+'Company0462-Internal'!K181 -> -5724.738 | L94: =+'Company0462-Internal'!L181 -> -6677.2751 | M94: =+'Company0462-Internal'!M181 -> -9245.9207 | N94: =+'Company0462-Internal'!N181 -> -11010.613 | ... P94: =+'Company0462-Internal'!P181 -> -16810.192
C95: (+) Sales / (-) Purchases of Other Assets: | F95: $ | G95: =+'Company0462-Internal'!G182 -> -127 | H95: =+'Company0462-Internal'!H182 -> -254 | I95: =+'Company0462-Internal'!I182 -> -321 | J95: =+'Company0462-Internal'!J182 -> -423 | K95: =+'Company0462-Internal'!K182 -> -501 | L95: =+'Company0462-Internal'!L182 -> -500 | M95: =+'Company0462-Internal'!M182 -> -600 | N95: =+'Company0462-Internal'!N182 -> -750 | ... P95: =+'Company0462-Internal'!P182 -> -1100
C96: Cash Flow from Investing: | F96: $ | G96: =SUM(G94:G95) -> -977.348 | H96: =SUM(H94:H95) -> -2278.285 | I96: =SUM(I94:I95) -> -3375.355 | J96: =SUM(J94:J95) -> -4208.91 | K96: =SUM(K94:K95) -> -6225.738 | L96: =SUM(L94:L95) -> -7177.2751 | M96: =SUM(M94:M95) -> -9845.9207 | N96: =SUM(N94:N95) -> -11760.613 | ... P96: =SUM(P94:P95) -> -17910.192
C98: CASH FLOW FROM FINANCING ACTIVITIES:
C99: (+/-) Change in Other Non-Current Liab.: | F99: $ | G99: =+'Company0462-Internal'!G186 -> 53 | H99: =+'Company0462-Internal'!H186 -> 102 | I99: =+'Company0462-Internal'!I186 -> 1211 | J99: =+'Company0462-Internal'!J186 -> 2310 | K99: =+'Company0462-Internal'!K186 -> 3123 | L99: =+'Company0462-Internal'!L186 -> 3500 | M99: =+'Company0462-Internal'!M186 -> 3800 | N99: =+'Company0462-Internal'!N186 -> 4100 | ... P99: =+'Company0462-Internal'!P186 -> 4700
C100: Cash Flow from Financing: | F100: $ | G100: =SUM(G99) -> 53 | H100: =SUM(H99) -> 102 | I100: =SUM(I99) -> 1211 | J100: =SUM(J99) -> 2310 | K100: =SUM(K99) -> 3123 | L100: =SUM(L99) -> 3500 | M100: =SUM(M99) -> 3800 | N100: =SUM(N99) -> 4100 | ... P100: =SUM(P99) -> 4700
C102: Net Change in Cash: | F102: $ | G102: =+G91+G96+G100 -> 32349.972 | H102: =+H91+H96+H100 -> 74317.398 | I102: =+I91+I96+I100 -> 69369.128 | J102: =+J91+J96+J100 -> 103172.25 | K102: =+K91+K96+K100 -> 102097.52 | L102: =+L91+L96+L100 -> 179387.53 | M102: =+M91+M96+M100 -> 199848.4 | N102: =+N91+N96+N100 -> 192741.45 | ... P102: =+P91+P96+P100 -> 257035.17
C103: Beginning Cash Balance: | F103: $ | G103: =+'Company0462-Internal'!G191 -> 25766.028 | H103: =+G104 -> 58116 | I103: =+H104 -> 132433.4 | J103: =+I104 -> 201802.53 | K103: =+J104 -> 304974.77 | L103: =+K104 -> 407072.3 | M103: =+L104 -> 586459.83 | N103: =+M104 -> 786308.23 | O103: =+N104 -> 979049.68 | P103: =+O104 -> 1189799.2
C104: Ending Cash Balance: | F104: $ | G104: =+G102+G103 -> 58116 | H104: =+H102+H103 -> 132433.4 | I104: =+I102+I103 -> 201802.53 | J104: =+J102+J103 -> 304974.77 | K104: =+K102+K103 -> 407072.3 | L104: =+L102+L103 -> 586459.83 | M104: =+M102+M103 -> 786308.23 | N104: =+N102+N103 -> 979049.68 | ... P104: =+P102+P103 -> 1446834.4

Sheet DCF
B2: ="Private Company DCF Analysis - "&Company_Name -> Private Company DCF Analysis - Capital Capable Media LLC
B3: ($ USD as Stated)
B5: ="DCF Assumptions - "&Company_Name&":" -> DCF Assumptions - Capital Capable Media LLC:
B7: Financial Assumptions for DCF: | G7: Operating Assumptions for Extended Projection Period:
B9: Discount Rate: | E9: =+WACC -> 0.15288175 | G9: Annual Change in Revenue Growth: | J9: -0.01
G10: Minimum Revenue Growth: | J10: 0.045
B11: "Going Concern" Discount to Terminal Value: | E11: 0.185
G12: Annual Change in EBIT Margin: | J12: -0.0025
B13: Discount to Liquidation Value Terminal Value: | E13: 0.25 | G13: Minimum EBIT Margin: | J13: 0.178
G15: Depreciation & Amortization % Revenue: | J15: 0.01
G16: CapEx % Revenue: | J16: 0.02
G17: Change in WC % Change in Revenue: | J17: 0.02
B19: Terminal Value - Multiples Method: | G19: Terminal Value - Perpetuity Growth Method: | L19: Terminal Value - Liquidation Value Method: | Q19: Terminal Value - "Cease Operations" Method:
B21: Baseline Terminal EBITDA Multiple: | E21: 5.6970458 | G21: Baseline Terminal FCF Growth Rate: | J21: 0.03 | L21: Final Projection Year Liquidation Value: | O21: =+'Company0462-GAAP'!P61-'Company0462-GAAP'!P74 -> 1430067.7 | Q21: FCF Growth / (Decline) Rate: | T21: -0.1
B22: Baseline Terminal Value: | E22: =+Terminal_Multiple*(L45+L52) -> 3738513.2 | G22: Baseline Terminal Value: | J22: =+L56*(1+Terminal_Growth_Rate)/(E9-Terminal_Growth_Rate)*(1+E9)^0.5 -> 3392192.5 | L22: Cumulative FCF Beyond Final Year: | O22: =SUM(H56:L56) -> 1614432.1
B23: Terminal Value After "Going Concern" Discount: | E23: =+E22*(1-TV_Discount) -> 3046888.3 | G23: Terminal Value After "Going Concern" Discount: | J23: =+J22*(1-TV_Discount) -> 2764636.9 | L23: Terminal Value Based on Asset Liquidation: | O23: =+O21+O22 -> 3044499.8
B24: Implied Terminal FCF Growth Rate: | E24: =(E23*E9-L56*(1+E9)^0.5)/(L56*(1+E9)^0.5+E23) -> 0.017706639 | G24: Implied Terminal EBITDA Multiple: | J24: =+J23/(+L45+L52) -> 4.212975 | L24: Terminal Value After Discount: | O24: =+O23*(1-TV_Liquidation_Discount) -> 2283374.8
B26: (+) PV of Terminal Value: | E26: =+E23/((1+E9)^L60) -> 734528.87 | G26: =+$B$26 -> (+) PV of Terminal Value: | J26: =+J23/((1+E9)^L60) -> 666485.09 | L26: =+$B$26 -> (+) PV of Terminal Value: | O26: =+O24/((1+E9)^L60) -> 550464.8 | Q26: =+$B$26 -> (+) PV of Terminal Value: | T26: =SUM(M58:V58) -> 530645.27
B27: (+) Sum of PV of Free Cash Flows: | E27: =SUM(C58:L58) -> 1268581 | G27: =+$B$27 -> (+) Sum of PV of Free Cash Flows: | J27: =SUM(C58:L58) -> 1268581 | L27: =+$B$27 -> (+) Sum of PV of Free Cash Flows: | O27: =SUM(C58:L58) -> 1268581 | Q27: =+$B$27 -> (+) Sum of PV of Free Cash Flows: | T27: =SUM(C58:L58) -> 1268581
B28: Implied Enterprise Value: | E28: =SUM(E26:E27) -> 2003109.9 | G28: =+$B$28 -> Implied Enterprise Value: | J28: =SUM(J26:J27) -> 1935066.1 | L28: =+$B$28 -> Implied Enterprise Value: | O28: =SUM(O26:O27) -> 1819045.8 | Q28: =+$B$28 -> Implied Enterprise Value: | T28: =SUM(T26:T27) -> 1799226.3
B30: % of Implied EV from Terminal Value: | E30: =+E26/E28 -> 0.36669424 | G30: =+$B$30 -> % of Implied EV from Terminal Value: | J30: =+J26/J28 -> 0.34442497 | L30: =+$B$30 -> % of Implied EV from Terminal Value: | O30: =+O26/O28 -> 0.30261183 | Q30: =+$B$30 -> % of Implied EV from Terminal Value: | T30: =+T26/T28 -> 0.2949297
B32: (+) Cash & Cash-Equivalents: | E32: ='Company0462-GAAP'!K52 -> 407072.3 | G32: =+$B$32 -> (+) Cash & Cash-Equivalents: | J32: =+E32 -> 407072.3 | L32: =+$B$32 -> (+) Cash & Cash-Equivalents: | O32: =+J32 -> 407072.3 | Q32: =+$B$32 -> (+) Cash & Cash-Equivalents: | T32: =+O32 -> 407072.3
B33: (+) Equity Investments: | E33: 0 | G33: =+$B$33 -> (+) Equity Investments: | J33: =+E33 -> 0 | L33: =+$B$33 -> (+) Equity Investments: | O33: =+J33 -> 0 | Q33: =+$B$33 -> (+) Equity Investments: | T33: =+O33 -> 0
B34: (+) Other Non-Core Assets, Net: | E34: 0 | G34: =+$B$34 -> (+) Other Non-Core Assets, Net: | J34: =+E34 -> 0 | L34: =+$B$34 -> (+) Other Non-Core Assets, Net: | O34: =+J34 -> 0 | Q34: =+$B$34 -> (+) Other Non-Core Assets, Net: | T34: =+O34 -> 0
B35: (-) Total Debt: | E35: 0 | G35: =+$B$35 -> (-) Total Debt: | J35: =+E35 -> 0 | L35: =+$B$35 -> (-) Total Debt: | O35: =+J35 -> 0 | Q35: =+$B$35 -> (-) Total Debt: | T35: =+O35 -> 0
B36: (-) Noncontrolling Interests: | E36: 0 | G36: =+$B$36 -> (-) Noncontrolling Interests: | J36: =+E36 -> 0 | L36: =+$B$36 -> (-) Noncontrolling Interests: | O36: =+J36 -> 0 | Q36: =+$B$36 -> (-) Noncontrolling Interests: | T36: =+O36 -> 0
B37: Implied Equity Value: | E37: =+E28+SUM(E32:E36) -> 2410182.2 | G37: =+$B$37 -> Implied Equity Value: | J37: =+J28+SUM(J32:J36) -> 2342138.4 | L37: =+$B$37 -> Implied Equity Value: | O37: =+O28+SUM(O32:O36) -> 2226118.1 | Q37: =+$B$37 -> Implied Equity Value: | T37: =+T28+SUM(T32:T36) -> 2206298.6
C39: Unlevered Free Cash Flow Projections:
B40: FCF Projections: | C40: =+'Company0462-GAAP'!L13 -> Year 6 | D40: =+'Company0462-GAAP'!M13 -> Year 7 | E40: =+'Company0462-GAAP'!N13 -> Year 8 | F40: =+'Company0462-GAAP'!O13 -> Year 9 | G40: =+'Company0462-GAAP'!P13 -> Year 10 | H40: Year 11 | I40: Year 12 | J40: Year 13 | K40: Year 14 | L40: Year 15 | M40: Year 16 | N40: Year 17 | O40: Year 18 | P40: Year 19 | Q40: Year 20 | R40: Year 21 | S40: Year 22 | T40: Year 23 | U40: Year 24 | V40: Year 25
B42: Revenue: | C42: =+'Company0462-GAAP'!L17 -> 1062799.6 | D42: =+'Company0462-GAAP'!M17 -> 1261407.7 | E42: =+'Company0462-GAAP'!N17 -> 1494297.5 | F42: =+'Company0462-GAAP'!O17 -> 1730525.2 | G42: =+'Company0462-GAAP'!P17 -> 1975197.5 | H42: =+G42*(1+H43) -> 2234711 | I42: =+H42*(1+I43) -> 2505974 | J42: =+I42*(1+J43) -> 2785104.7 | K42: =+J42*(1+K43) -> 3067475.7 | L42: =+K42*(1+L43) -> 3347800.4 | M42: =+L42*(1+M43) -> 3620264.9 | N42: =+M42*(1+N43) -> 3878701.6 | O42: =+N42*(1+O43) -> 4116800 | ... Q42: =+P42*(1+Q43) -> 4523122
B43: Growth Rate: | C43: =IFERROR(+C42/'Company0462-GAAP'!K17-1,"N/A") -> 0.16152461 | D43: =IFERROR(+D42/C42-1,"N/A") -> 0.1868726 | E43: =IFERROR(+E42/D42-1,"N/A") -> 0.18462687 | F43: =IFERROR(+F42/E42-1,"N/A") -> 0.15808615 | G43: =IFERROR(+G42/F42-1,"N/A") -> 0.14138613 | H43: =MAX(+G43+Rev_Growth_Decline,Min_Rev_Growth) -> 0.13138613 | I43: =MAX(+H43+Rev_Growth_Decline,Min_Rev_Growth) -> 0.12138613 | J43: =MAX(+I43+Rev_Growth_Decline,Min_Rev_Growth) -> 0.11138613 | K43: =MAX(+J43+Rev_Growth_Decline,Min_Rev_Growth) -> 0.10138613 | L43: =MAX(+K43+Rev_Growth_Decline,Min_Rev_Growth) -> 0.091386125 | M43: =MAX(+L43+Rev_Growth_Decline,Min_Rev_Growth) -> 0.081386125 | N43: =MAX(+M43+Rev_Growth_Decline,Min_Rev_Growth) -> 0.071386125 | O43: =MAX(+N43+Rev_Growth_Decline,Min_Rev_Growth) -> 0.061386125 | ... Q43: =MAX(+P43+Rev_Growth_Decline,Min_Rev_Growth) -> 0.045
B45: Operating Income (EBIT): | C45: ='Company0462-GAAP'!L26 -> 270254.26 | D45: ='Company0462-GAAP'!M26 -> 303416.83 | E45: ='Company0462-GAAP'!N26 -> 288244.14 | F45: ='Company0462-GAAP'!O26 -> 316396.89 | G45: ='Company0462-GAAP'!P26 -> 392106.65 | H45: =+H46*H42 -> 438037.24 | I45: =+I46*I42 -> 484943.95 | J45: =+J46*J42 -> 531997.22 | K45: =+K46*K42 -> 578265.66 | L45: =+L46*L42 -> 622741.62 | M45: =+M46*M42 -> 664373.49 | N45: =+N46*N42 -> 702103.78 | O45: =+O46*O42 -> 734911.21 | ... Q45: =+Q46*Q42 -> 805115.72
B46: Operating Margin: | C46: =IFERROR(+C45/C42,"N/A") -> 0.25428524 | D46: =IFERROR(+D45/D42,"N/A") -> 0.24053826 | E46: =IFERROR(+E45/E42,"N/A") -> 0.19289608 | F46: =IFERROR(+F45/F42,"N/A") -> 0.18283286 | G46: =IFERROR(+G45/G42,"N/A") -> 0.19851516 | H46: =MAX(+G46+Op_Margin_Change,Min_Op_Margin) -> 0.19601516 | I46: =MAX(+H46+Op_Margin_Change,Min_Op_Margin) -> 0.19351516 | J46: =MAX(+I46+Op_Margin_Change,Min_Op_Margin) -> 0.19101516 | K46: =MAX(+J46+Op_Margin_Change,Min_Op_Margin) -> 0.18851516 | L46: =MAX(+K46+Op_Margin_Change,Min_Op_Margin) -> 0.18601516 | M46: =MAX(+L46+Op_Margin_Change,Min_Op_Margin) -> 0.18351516 | N46: =MAX(+M46+Op_Margin_Change,Min_Op_Margin) -> 0.18101516 | O46: =MAX(+N46+Op_Margin_Change,Min_Op_Margin) -> 0.17851516 | ... Q46: =MAX(+P46+Op_Margin_Change,Min_Op_Margin) -> 0.178
B48: (-) Taxes: | C48: =-C45*Tax_Rate -> -94588.991 | D48: =-D45*Tax_Rate -> -106195.89 | E48: =-E45*Tax_Rate -> -100885.45 | F48: =-F45*Tax_Rate -> -110738.91 | G48: =-G45*Tax_Rate -> -137237.33 | H48: =-H45*Tax_Rate -> -153313.03 | I48: =-I45*Tax_Rate -> -169730.38 | J48: =-J45*Tax_Rate -> -186199.03 | ... Q48: =-Q45*Tax_Rate -> -281790.5
B50: NOPAT: | C50: =+C45+C48 -> 175665.27 | D50: =+D45+D48 -> 197220.94 | E50: =+E45+E48 -> 187358.69 | F50: =+F45+F48 -> 205657.98 | G50: =+G45+G48 -> 254869.32 | H50: =+H45+H48 -> 284724.21 | I50: =+I45+I48 -> 315213.57 | J50: =+J45+J48 -> 345798.19 | ... Q50: =+Q45+Q48 -> 523325.22
B52: (+) Depreciation & Amortization: | C52: ='Company0462-GAAP'!L86 -> 2225.7584 | D52: ='Company0462-GAAP'!M86 -> 2641.6916 | E52: ='Company0462-GAAP'!N86 -> 4718.8342 | F52: ='Company0462-GAAP'!O86 -> 7286.4221 | G52: ='Company0462-GAAP'!P86 -> 8405.0958 | H52: =+H42*DA_Pct_Revenue -> 22347.11 | I52: =+I42*DA_Pct_Revenue -> 25059.74 | J52: =+J42*DA_Pct_Revenue -> 27851.047 | K52: =+K42*DA_Pct_Revenue -> 30674.757 | L52: =+L42*DA_Pct_Revenue -> 33478.004 | M52: =+M42*DA_Pct_Revenue -> 36202.649 | N52: =+N42*DA_Pct_Revenue -> 38787.016 | O52: =+O42*DA_Pct_Revenue -> 41168 | ... Q52: =+Q42*DA_Pct_Revenue -> 45231.22
B53: (+/-) Change in WC: | C53: =SUM('Company0462-GAAP'!L87:L90) -> 5173.7804 | D53: =SUM('Company0462-GAAP'!M87:M90) -> 6031.6932 | E53: =SUM('Company0462-GAAP'!N87:N90) -> 8324.5387 | F53: =SUM('Company0462-GAAP'!O87:O90) -> 8877.9976 | G53: =SUM('Company0462-GAAP'!P87:P90) -> 6970.9467 | H53: =(+H42-G42)*WC_Pct_Change_in_Rev -> 5190.2709 | I53: =(+I42-H42)*WC_Pct_Change_in_Rev -> 5425.2583 | J53: =(+J42-I42)*WC_Pct_Change_in_Rev -> 5582.6146 | K53: =(+K42-J42)*WC_Pct_Change_in_Rev -> 5647.4195 | L53: =(+L42-K42)*WC_Pct_Change_in_Rev -> 5606.4943 | M53: =(+M42-L42)*WC_Pct_Change_in_Rev -> 5449.29 | N53: =(+N42-M42)*WC_Pct_Change_in_Rev -> 5168.7337 | O53: =(+O42-N42)*WC_Pct_Change_in_Rev -> 4761.9692 | ... Q53: =(+Q42-P42)*WC_Pct_Change_in_Rev -> 3895.5118
B54: (-) CapEx: | C54: ='Company0462-GAAP'!L94 -> -6677.2751 | D54: ='Company0462-GAAP'!M94 -> -9245.9207 | E54: ='Company0462-GAAP'!N94 -> -11010.613 | F54: ='Company0462-GAAP'!O94 -> -14572.844 | G54: ='Company0462-GAAP'!P94 -> -16810.192 | H54: =-H42*CapEx_Pct_Revenue -> -44694.221 | I54: =-I42*CapEx_Pct_Revenue -> -50119.479 | J54: =-J42*CapEx_Pct_Revenue -> -55702.094 | K54: =-K42*CapEx_Pct_Revenue -> -61349.513 | L54: =-L42*CapEx_Pct_Revenue -> -66956.008 | M54: =-M42*CapEx_Pct_Revenue -> -72405.298 | N54: =-N42*CapEx_Pct_Revenue -> -77574.031 | O54: =-O42*CapEx_Pct_Revenue -> -82336.001 | ... Q54: =-Q42*CapEx_Pct_Revenue -> -90462.441
B56: Unlevered FCF: | C56: =+C50+SUM(C52:C54) -> 176387.53 | D56: =+D50+SUM(D52:D54) -> 196648.4 | E56: =+E50+SUM(E52:E54) -> 189391.45 | F56: =+F50+SUM(F52:F54) -> 207249.55 | G56: =+G50+SUM(G52:G54) -> 253435.17 | H56: =+H50+SUM(H52:H54) -> 267567.37 | I56: =+I50+SUM(I52:I54) -> 295579.09 | J56: =+J50+SUM(J52:J54) -> 323529.76 | ... Q56: =+Q50+SUM(Q52:Q54) -> 481989.51 | R56: =MAX(+Q56*(1+FCF_Decline_Rate),0) -> 433790.56 | S56: =MAX(+R56*(1+FCF_Decline_Rate),0) -> 390411.5 | T56: =MAX(+S56*(1+FCF_Decline_Rate),0) -> 351370.35 | U56: =MAX(+T56*(1+FCF_Decline_Rate),0) -> 316233.32 | V56: =MAX(+U56*(1+FCF_Decline_Rate),0) -> 284609.99
B57: Growth Rate: | C57: =IFERROR(+C56/B56-1,"N/A") -> N/A | D57: =IFERROR(+D56/C56-1,"N/A") -> 0.11486566 | E57: =IFERROR(+E56/D56-1,"N/A") -> -0.036903187 | F57: =IFERROR(+F56/E56-1,"N/A") -> 0.094292019 | G57: =IFERROR(+G56/F56-1,"N/A") -> 0.22285027 | H57: =IFERROR(+H56/G56-1,"N/A") -> 0.05576257 | I57: =IFERROR(+I56/H56-1,"N/A") -> 0.10469034 | J57: =IFERROR(+J56/I56-1,"N/A") -> 0.094562414 | ... V57: =IFERROR(+V56/U56-1,"N/A") -> -0.1
B58: PV of FCF: | C58: =+C56/((1+$E$9)^C61) -> 164276.52 | D58: =+D56/((1+$E$9)^D61) -> 158859.53 | E58: =+E56/((1+$E$9)^E61) -> 132708.41 | F58: =+F56/((1+$E$9)^F61) -> 125964.14 | G58: =+G56/((1+$E$9)^G61) -> 133608.91 | H58: =+H56/((1+$E$9)^H61) -> 122353.65 | I58: =+I56/((1+$E$9)^I61) -> 117239.17 | J58: =+J56/((1+$E$9)^J61) -> 111308.54 | ... V58: =+V56/((1+$E$9)^V61) -> 17760.173
B60: Discount Period: | C60: 1 | D60: =+C60+1 -> 2 | E60: =+D60+1 -> 3 | F60: =+E60+1 -> 4 | G60: =+F60+1 -> 5 | H60: =+G60+1 -> 6 | I60: =+H60+1 -> 7 | J60: =+I60+1 -> 8 | K60: =+J60+1 -> 9 | ... V60: =+U60+1 -> 20
B61: Mid-Year: | C61: =+C60/2 -> 0.5 | D61: =+D60-0.5 -> 1.5 | E61: =+E60-0.5 -> 2.5 | F61: =+F60-0.5 -> 3.5 | G61: =+G60-0.5 -> 4.5 | H61: =+H60-0.5 -> 5.5 | I61: =+I60-0.5 -> 6.5 | J61: =+J60-0.5 -> 7.5 | K61: =+K60-0.5 -> 8.5 | ... V61: =+V60-0.5 -> 19.5
B63: Sensitivity - Terminal FCF Growth Rate vs. Discount Rate and Implied Equity Value from DCF Analysis:
D65: Terminal FCF Growth Rate:
C66: =+$J$37 -> 2342138.4 | D66: 0 | E66: =+D66+0.5% -> 0.005 | F66: =+E66+0.5% -> 0.01 | G66: =+F66+0.5% -> 0.015 | H66: =+G66+0.5% -> 0.02 | I66: =+H66+0.5% -> 0.025 | J66: =+I66+0.5% -> 0.03 | K66: =+J66+0.5% -> 0.035 | L66: =+K66+0.5% -> 0.04
B67: Discount Rate (WACC): | C67: 0.13 | D67: 2230849.7 | E67: 2252491.2 | F67: 2275647.3 | G67: 2300482.8 | H67: 2327187.3 | I67: 2355980.1 | J67: 2387116 | K67: 2420893.1 | L67: 2457662.5
C68: =+C67+0.5% -> 0.135 | D68: 2227658.9 | E68: 2249176 | F68: 2272199 | G68: 2296891.8 | H68: 2323442.9 | I68: 2352070.2 | J68: 2383027.1 | K68: 2416610.1 | L68: 2453168.2
C69: =+C68+0.5% -> 0.14 | D69: 2224468.1 | E69: 2245860.8 | F69: 2268750.8 | G69: 2293300.9 | H69: 2319698.4 | I69: 2348160.2 | J69: 2378938.2 | K69: 2412327.1 | L69: 2448673.9
C70: =+C69+0.5% -> 0.145 | D70: 2221277.3 | E70: 2242545.7 | F70: 2265302.6 | G70: 2289709.9 | H70: 2315954 | I70: 2344250.3 | J70: 2374849.4 | K70: 2408044.1 | L70: 2444179.6
C71: 0.14844063 | D71: 2219081.7 | E71: 2240264.4 | F71: 2262929.7 | G71: 2287238.8 | H71: 2313377.3 | I71: 2341559.8 | J71: 2372035.7 | K71: 2405096.9 | L71: 2441086.9
C72: 0.15 | D72: 2218086.6 | E72: 2239230.5 | F72: 2261854.3 | G72: 2286118.9 | H72: 2312209.5 | I72: 2340340.4 | J72: 2370760.5 | K72: 2403761.2 | L72: 2439685.3
C73: =+C72+0.5% -> 0.155 | D73: 2214895.8 | E73: 2235915.4 | F73: 2258406.1 | G73: 2282527.9 | H73: 2308465.1 | I73: 2336430.5 | J73: 2366671.6 | K73: 2399478.2 | L73: 2435191
C74: =+C73+0.5% -> 0.16 | D74: 2211705 | E74: 2232600.2 | F74: 2254957.8 | G74: 2278937 | H74: 2304720.6 | I74: 2332520.5 | J74: 2362582.8 | K74: 2395195.2 | L74: 2430696.7
C75: =+C74+0.5% -> 0.165 | D75: 2208514.2 | E75: 2229285 | F75: 2251509.6 | G75: 2275346 | H75: 2300976.2 | I75: 2328610.6 | J75: 2358493.9 | K75: 2390912.2 | L75: 2426202.4
B77: Sensitivity - Terminal EBITDA Multiple vs. Discount Rate and Implied Equity Value from DCF Analysis:
D79: Terminal EBITDA Multiple:
C80: =+$E$37 -> 2410182.2 | D80: 4 | E80: =+D80+0.5 -> 4.5 | F80: =+E80+0.5 -> 5 | G80: =+F80+0.5 -> 5.5 | H80: 5.6970458 | I80: 6 | J80: =+I80+0.5 -> 6.5 | K80: =+J80+0.5 -> 7 | L80: =+K80+0.5 -> 7.5
B81: Discount Rate (WACC): | C81: =+C67 -> 0.13 | D81: 2429510.4 | E81: 2508286.1 | F81: 2587061.9 | G81: 2665837.6 | H81: 2696882.4 | I81: 2744613.3 | J81: 2823389 | K81: 2902164.8 | L81: 2980940.5
C82: =+C68 -> 0.135 | D82: 2373675.5 | E82: 2449048.9 | F82: 2524422.3 | G82: 2599795.7 | H82: 2629499.8 | I82: 2675169.2 | J82: 2750542.6 | K82: 2825916 | L82: 2901289.4
C83: =+C69 -> 0.14 | D83: 2320052 | E83: 2392184.1 | F83: 2464316.1 | G83: 2536448.2 | H83: 2564874.8 | I83: 2608580.3 | J83: 2680712.3 | K83: 2752844.4 | L83: 2824976.4
C84: =+C70 -> 0.145 | D84: 2268537.2 | E84: 2337580.6 | F84: 2406624 | G84: 2475667.3 | H84: 2502876.7 | I84: 2544710.7 | J84: 2613754.1 | K84: 2682797.4 | L84: 2751840.8
C85: =+C71 -> 0.14844063 | D85: 2234262.3 | E85: 2301264.9 | F85: 2368267.4 | G85: 2435270 | H85: 2461675.1 | I85: 2502272.5 | J85: 2569275.1 | K85: 2636277.6 | L85: 2703280.2
C86: =+C72 -> 0.15 | D86: 2219033.6 | E86: 2285133.1 | F86: 2351232.7 | G86: 2417332.2 | H86: 2443381.5 | I86: 2483431.8 | J86: 2549531.3 | K86: 2615630.8 | L86: 2681730.4
C87: =+C73 -> 0.155 | D87: 2171448.7 | E87: 2234741.9 | F87: 2298035.1 | G87: 2361328.3 | H87: 2386271.6 | I87: 2424621.5 | J87: 2487914.7 | K87: 2551207.8 | L87: 2614501
C88: =+C74 -> 0.16 | D88: 2125694.8 | E88: 2186312.2 | F88: 2246929.5 | G88: 2307546.9 | H88: 2331435.7 | I88: 2368164.2 | J88: 2428781.6 | K88: 2489398.9 | L88: 2550016.3
C89: =+C75 -> 0.165 | D89: 2081688.8 | E89: 2139754.2 | F89: 2197819.6 | G89: 2255885.1 | H89: 2278768.2 | I89: 2313950.5 | J89: 2372015.9 | K89: 2430081.3 | L89: 2488146.7
B91: Sensitivity - Discount to Liquidation Value vs. Discount Rate and Implied Equity Value from DCF Analysis:
D93: Discount to Liquidation Value Terminal Value:
C94: =+$O$37 -> 2226118.1 | D94: 0 | E94: =+D94+5% -> 0.05 | F94: =+E94+5% -> 0.1 | G94: =+F94+5% -> 0.15 | H94: =+G94+5% -> 0.2 | I94: =+H94+5% -> 0.25 | J94: =+I94+5% -> 0.3 | K94: =+J94+5% -> 0.35 | L94: =+K94+5% -> 0.4
B95: Discount Rate (WACC): | C95: =+C81 -> 0.13 | D95: 2696178.8 | E95: 2651335.1 | F95: 2606491.4 | G95: 2561647.7 | H95: 2516804 | I95: 2471960.3 | J95: 2427116.6 | K95: 2382272.9 | L95: 2337429.1
C96: =+C82 -> 0.135 | D96: 2628826.5 | E96: 2585919.6 | F96: 2543012.7 | G96: 2500105.8 | H96: 2457198.9 | I96: 2414291.9 | J96: 2371385 | K96: 2328478.1 | L96: 2285571.2
C97: =+C83 -> 0.14 | D97: 2564230.5 | E97: 2523168.8 | F97: 2482107 | G97: 2441045.3 | H97: 2399983.6 | I97: 2358921.8 | J97: 2317860.1 | K97: 2276798.3 | L97: 2235736.6
C98: =+C84 -> 0.145 | D98: 2502260 | E98: 2462956.6 | F98: 2423653.1 | G98: 2384349.6 | H98: 2345046.1 | I98: 2305742.6 | J98: 2266439.1 | K98: 2227135.6 | L98: 2187832.1
C99: =+C85 -> 0.14844063 | D99: 2461076.7 | E99: 2422934.9 | F99: 2384793.2 | G99: 2346651.5 | H99: 2308509.7 | I99: 2270368 | J99: 2232226.2 | K99: 2194084.5 | L99: 2155942.8
C100: =+C86 -> 0.15 | D100: 2442791.1 | E100: 2405163.4 | F100: 2367535.7 | G100: 2329908 | H100: 2292280.3 | I100: 2254652.6 | J100: 2217024.9 | K100: 2179397.3 | L100: 2141769.6
C101: =+C87 -> 0.155 | D101: 2385706.3 | E101: 2349676.1 | F101: 2313645.9 | G101: 2277615.8 | H101: 2241585.6 | I101: 2205555.5 | J101: 2169525.3 | K101: 2133495.2 | L101: 2097465
C102: =+C88 -> 0.16 | D102: 2330894.2 | E102: 2296387.3 | F102: 2261880.4 | G102: 2227373.5 | H102: 2192866.6 | I102: 2158359.7 | J102: 2123852.8 | K102: 2089345.9 | L102: 2054839
C103: =+C89 -> 0.165 | D103: 2278249.5 | E103: 2245195.3 | F103: 2212141.1 | G103: 2179086.9 | H103: 2146032.7 | I103: 2112978.5 | J103: 2079924.3 | K103: 2046870.1 | L103: 2013815.9
B105: Sensitivity - Annual FCF Growth Rate Past Year 15 vs. Discount Rate and Implied Equity Value from DCF Analysis:
D107: Annual FCF Growth Rate Past Year 15:
C108: =+$T$37 -> 2206298.6 | D108: -0.4 | E108: =+D108+5% -> -0.35 | F108: =+E108+5% -> -0.3 | G108: =+F108+5% -> -0.25 | H108: =+G108+5% -> -0.2 | I108: =+H108+5% -> -0.15 | J108: =+I108+5% -> -0.1 | K108: =+J108+5% -> -0.05 | L108: =+K108+5% -> -6.9388939e-17
B109: Discount Rate (WACC): | C109: =+C95 -> 0.13 | D109: 2369337.2 | E109: 2384459.2 | F109: 2401705.4 | G109: 2421372.3 | H109: 2443787.1 | I109: 2469309.9 | J109: 2498334.7 | K109: 2531291.5 | L109: 2568647.9
C110: =+C96 -> 0.135 | D110: 2308991.8 | E110: 2323011.7 | F110: 2338991.6 | G110: 2357204.3 | H110: 2377950.9 | I110: 2401562.4 | J110: 2428401.2 | K110: 2458862.9 | L110: 2493377.3
C111: =+C97 -> 0.14 | D111: 2251503.9 | E111: 2264506.9 | F111: 2279319 | G111: 2296191.3 | H111: 2315400.9 | I111: 2337252.5 | J111: 2362079.4 | K111: 2390245.5 | L111: 2422146.2
C112: =+C98 -> 0.145 | D112: 2196709.1 | E112: 2208773.2 | F112: 2222507.8 | G112: 2238144.2 | H112: 2255937.3 | I112: 2276167.7 | J112: 2299142.2 | K112: 2325195.5 | L112: 2354691.6
C113: =+C99 -> 0.14844063 | D113: 2160487 | E113: 2171947.1 | F113: 2184989 | G113: 2199831 | H113: 2216714.2 | I113: 2235903.5 | J113: 2257688.9 | K113: 2282386.5 | L113: 2310340.1
C114: =+C100 -> 0.15 | D114: 2144453.5 | E114: 2155650.5 | F114: 2168390.7 | G114: 2182886.9 | H114: 2199374.1 | I114: 2218110.5 | J114: 2239378.7 | K114: 2263486.7 | L114: 2290769.6
C115: =+C101 -> 0.155 | D115: 2094593.3 | E115: 2104989.4 | F115: 2116811.3 | G115: 2130255.4 | H115: 2145538.1 | I115: 2162897.2 | J115: 2182593 | K115: 2204909.2 | L115: 2230154.3
C116: =+C102 -> 0.16 | D116: 2046994.2 | E116: 2056649.9 | F116: 2067623.7 | G116: 2080096.5 | H116: 2094267.8 | I116: 2110356.7 | J116: 2128603 | K116: 2149268.2 | L116: 2172636.3
C117: =+C103 -> 0.165 | D117: 2001530.1 | E117: 2010501.4 | F117: 2020691.5 | G117: 2032267.3 | H117: 2045412.7 | I117: 2060329.7 | J117: 2077239.3 | K117: 2096382.6 | L117: 2118021.2

Sheet WACC
B2: ="Private Company WACC Analysis - "&Company_Name -> Private Company WACC Analysis - Capital Capable Media LLC
B3: =+'Company0462-GAAP'!$B$3 -> ($ USD as Stated)
B5: Discount Rate Calculations - Assumptions
B6: Risk-Free Rate: | F6: 0.03
B7: Equity Risk Premium: | F7: 0.075
B8: Pre-Tax Cost of Debt: | F8: =+Risk_Free_Rate+0.4% -> 0.034
B9: Cost of Preferred Stock: | F9: 0
B10: Market Correlation (R^2) for Education Companies: | F10: 0.1988
B11: Adjustment for Portfolio Diversification of Potential Buyer: | F11: 0.325
B13: Comparable Companies - Unlevered Beta Calculation
D14: Levered | G14: Preferred | I14: Equity | L14: Unlevered
B15: Name | C15: Ticker | D15: Beta | E15: Debt | F15: % Debt | G15: Stock | H15: % Preferred | I15: Value | J15: % Equity | K15: Tax Rate | L15: Beta
B16: =+'Public Comps'!B8 -> Nord Anglia Education Inc | C16: =+'Public Comps'!C8 -> NYSE:Company1891 | D16: =+'Public Comps'!U8 -> 0.32 | E16: =+'Public Comps'!F8 -> 522.4 | F16: =+E16/($E16+$G16+$I16) -> 0.2134774 | G16: =+'Public Comps'!G8 -> 0 | H16: =+G16/($E16+$G16+$I16) -> 0 | I16: =+'Public Comps'!E8 -> 1924.6975 | J16: =+I16/($E16+$G16+$I16) -> 0.7865226 | K16: 0.4 | L16: =IFERROR(D16/(1+(E16/I16)*(1-K16)+G16/I16),"N/A") -> 0.2751856
B17: =+'Public Comps'!B9 -> Company2600 Education Inc | C17: =+'Public Comps'!C9 -> NASDAQ:Company2494 | D17: =+'Public Comps'!U9 -> 1.55 | E17: =+'Public Comps'!F9 -> 118.75 | F17: =+E17/($E17+$G17+$I17) -> 0.15034272 | G17: =+'Public Comps'!G9 -> 0 | H17: =+G17/($E17+$G17+$I17) -> 0 | I17: =+'Public Comps'!E9 -> 671.112 | J17: =+I17/($E17+$G17+$I17) -> 0.84965728 | K17: 0.4 | L17: =IFERROR(D17/(1+(E17/I17)*(1-K17)+G17/I17),"N/A") -> 1.401235
B18: =+'Public Comps'!B10 -> Capella Education Company | C18: =+'Public Comps'!C10 -> NASDAQ:Company0593 | D18: =+'Public Comps'!U10 -> 1.11 | E18: =+'Public Comps'!F10 -> 0 | F18: =+E18/($E18+$G18+$I18) -> 0 | G18: =+'Public Comps'!G10 -> 0 | H18: =+G18/($E18+$G18+$I18) -> 0 | I18: =+'Public Comps'!E10 -> 800.496 | J18: =+I18/($E18+$G18+$I18) -> 1 | K18: 0.4 | L18: =IFERROR(D18/(1+(E18/I18)*(1-K18)+G18/I18),"N/A") -> 1.11
B19: =+'Public Comps'!B11 -> American Public Education, Inc. | C19: =+'Public Comps'!C11 -> NASDAQ:Company0117 | D19: =+'Public Comps'!U11 -> 1.15 | E19: =+'Public Comps'!F11 -> 0 | F19: =+E19/($E19+$G19+$I19) -> 0 | G19: =+'Public Comps'!G11 -> 0 | H19: =+G19/($E19+$G19+$I19) -> 0 | I19: =+'Public Comps'!E11 -> 595.1248 | J19: =+I19/($E19+$G19+$I19) -> 1 | K19: 0.4 | L19: =IFERROR(D19/(1+(E19/I19)*(1-K19)+G19/I19),"N/A") -> 1.15
B20: =+'Public Comps'!B12 -> Lincoln Educational Services Corp | C20: =+'Public Comps'!C12 -> NASDAQ:Company1557 | D20: =+'Public Comps'!U12 -> 2.11 | E20: =+'Public Comps'!F12 -> 43.904 | F20: =+E20/($E20+$G20+$I20) -> 0.45348813 | G20: =+'Public Comps'!G12 -> 0 | H20: =+G20/($E20+$G20+$I20) -> 0 | I20: =+'Public Comps'!E12 -> 52.91 | J20: =+I20/($E20+$G20+$I20) -> 0.54651187 | K20: 0.4 | L20: =IFERROR(D20/(1+(E20/I20)*(1-K20)+G20/I20),"N/A") -> 1.4086652
B21: =+'Public Comps'!B13 -> National American University Holdings Inc | C21: =+'Public Comps'!C13 -> NASDAQ:Company1849 | D21: =+'Public Comps'!U13 -> 1.25 | E21: =+'Public Comps'!F13 -> 12.303 | F21: =+E21/($E21+$G21+$I21) -> 0.13034247 | G21: =+'Public Comps'!G13 -> 0 | H21: =+G21/($E21+$G21+$I21) -> 0 | I21: =+'Public Comps'!E13 -> 82.0868 | J21: =+I21/($E21+$G21+$I21) -> 0.86965753 | K21: 0.4 | L21: =IFERROR(D21/(1+(E21/I21)*(1-K21)+G21/I21),"N/A") -> 1.1468661
B23: Median: | D23: =MEDIAN(D16:D21) -> 1.2 | E23: =MEDIAN(E16:E21) -> 28.1035 | F23: =MEDIAN(F16:F21) -> 0.1403426 | G23: =MEDIAN(G16:G21) -> 0 | H23: =MEDIAN(H16:H21) -> 0 | I23: =MEDIAN(I16:I21) -> 633.1184 | J23: =MEDIAN(J16:J21) -> 0.8596574 | K23: =MEDIAN(K16:K21) -> 0.4 | L23: =MEDIAN(L16:L21) -> 1.148433
B24: Median "Total" Unlevered Beta: | L24: =+L23/SQRT(Market_Correlation)*(1-Buyer_Diversification) -> 1.7386063
B26: =TEXT(Company_Name,"")& " - Levered Beta & WACC Calculation" -> Capital Capable Media LLC - Levered Beta & WACC Calculation
D27: Unlevered | G27: Preferred | I27: Equity | L27: Levered
C28: Ticker | D28: Beta | E28: Debt | F28: % Debt | G28: Stock | H28: % Preferred | I28: Value | J28: % Equity | K28: Tax Rate | L28: Beta
B29: "Optimal" Capital Structure: | C29: N/A | D29: =+L24 -> 1.7386063 | F29: =+F23 -> 0.1403426 | H29: =+H23 -> 0 | J29: =+J23 -> 0.8596574 | K29: =Tax_Rate -> 0.35 | L29: =D29*(1+(F29/J29)*(1-Tax_Rate)+(H29/J29)) -> 1.9230988
B31: Cost of Equity Based on Comparables and "Optimal" Capital Structure: | L31: =+Risk_Free_Rate+Equity_Risk_Premium*L29 -> 0.17423241
B33: WACC = Cost of Equity * % Equity + Cost of Debt * % Debt * (1 - Tax Rate) + Cost of Preferred Stock * % Preferred Stock
B35: WACC, "Optimal" Capital Structure: | L35: =+L31*J29+Cost_of_Debt*F29*(1-Tax_Rate)+Cost_of_Preferred*H29 -> 0.15288175

Sheet Public Comps
B2: Comparable Public Companies - U.S.-Based, For-Profit Education Companies with Less Than $500 Million USD in LTM Revenue
B3: ($ USD in Millions Except Per Share Amounts in USD as Stated)
B5: Operating Statistics | E5: Capitalization
D6: Share | E6: Equity | G6: Preferred | H6: Enterprise | I6: Revenue | L6: EBITDA | O6: EBITDA Margin | R6: Net Income
B7: Company Name | C7: Ticker | D7: Price | E7: Value | F7: Debt | G7: Stock | H7: Value | I7: LTM | J7: Forward Year 1 | K7: Forward Year 2 | L7: =+$I$7 -> LTM | M7: =+$J$7 -> Forward Year 1 | N7: =+$K$7 -> Forward Year 2 | O7: =+$I$7 -> LTM | P7: =+$J$7 -> Forward Year 1 | Q7: =+$K$7 -> Forward Year 2 | R7: =+$I$7 -> LTM | S7: =+$J$7 -> Forward Year 1 | T7: =+$K$7 -> Forward Year 2 | U7: Beta
B8: Nord Anglia Education Inc | C8: NYSE:Company1891 | D8: 19.69 | E8: 1924.6975 | F8: 522.4 | G8: 0 | H8: 2280.3975 | I8: 474.6 | J8: 542.5 | K8: 616.1 | L8: 127.4 | M8: 143.6 | N8: 169.6 | O8: =IFERROR(+L8/I8,"N/A") -> 0.26843658 | P8: =IFERROR(+M8/J8,"N/A") -> 0.26470046 | Q8: =IFERROR(+N8/K8,"N/A") -> 0.27527999 | R8: 26.3925 | S8: 61.5825 | T8: 78.2 | U8: 0.32
B9: Company2600 Education Inc | C9: NASDAQ:Company2494 | D9: 62.14 | E9: 671.112 | F9: 118.75 | G9: 0 | H9: 627.582 | I9: 446.041 | J9: 431.62 | K9: 443.6 | L9: 102.377 | M9: 95.6 | N9: 104.3 | O9: =IFERROR(+L9/I9,"N/A") -> 0.22952374 | P9: =IFERROR(+M9/J9,"N/A") -> 0.22149113 | Q9: =IFERROR(+N9/K9,"N/A") -> 0.23512173 | R9: 46.36 | S9: 36.828 | T9: 41.472 | U9: 1.55
B10: Capella Education Company | C10: NASDAQ:Company0593 | D10: 65.4 | E10: 800.496 | F10: 0 | G10: 0 | H10: 633.444 | I10: 421.967 | J10: 440.8 | K10: 463.93 | L10: 90.583 | M10: 95 | N10: 99.1 | O10: =IFERROR(+L10/I10,"N/A") -> 0.21466845 | P10: =IFERROR(+M10/J10,"N/A") -> 0.21551724 | Q10: =IFERROR(+N10/K10,"N/A") -> 0.21360981 | R10: 37.943 | S10: 42.228 | T10: 46.512 | U10: 1.11
B11: American Public Education, Inc. | C11: NASDAQ:Company0117 | D11: 34.48 | E11: 595.1248 | F11: 0 | G11: 0 | H11: 474.2958 | I11: 348.72 | J11: 368.86 | K11: 385.2 | L11: 74.1 | M11: 75.3 | N11: 80.1 | O11: =IFERROR(+L11/I11,"N/A") -> 0.2124914 | P11: =IFERROR(+M11/J11,"N/A") -> 0.20414249 | Q11: =IFERROR(+N11/K11,"N/A") -> 0.20794393 | R11: 37.7994 | S11: 40.9062 | T11: 43.4952 | U11: 1.15
B12: Lincoln Educational Services Corp | C12: NASDAQ:Company1557 | D12: 2.2 | E12: 52.91 | F12: 43.904 | G12: 0 | H12: 77.802 | I12: 330.249 | J12: 320 | K12: 339.06 | L12: -34.301 | M12: -45 | N12: -15.6 | O12: =IFERROR(+L12/I12,"N/A") -> -0.10386405 | P12: =IFERROR(+M12/J12,"N/A") -> -0.140625 | Q12: =IFERROR(+N12/K12,"N/A") -> -0.046009556 | R12: -75.39 | S12: -18.759 | T12: -3.367 | U12: 2.11
B13: National American University Holdings Inc | C13: NASDAQ:Company1849 | D13: 3.26 | E13: 82.0868 | F13: 12.303 | G13: 0 | H13: 74.6548 | I13: 127.753 | J13: 119.63 | K13: 124.21 | L13: 12.723 | M13: 11.1 | N13: 15.2 | O13: =IFERROR(+L13/I13,"N/A") -> 0.099590616 | P13: =IFERROR(+M13/J13,"N/A") -> 0.09278609 | Q13: =IFERROR(+N13/K13,"N/A") -> 0.1223734 | R13: 3.468 | S13: 6.0432 | T13: 6.7986 | U13: 1.25
B15: Maximum | D15: =MAX(D8:D13) -> 65.4 | E15: =MAX(E8:E13) -> 1924.6975 | F15: =MAX(F8:F13) -> 522.4 | G15: =MAX(G8:G13) -> 0 | H15: =MAX(H8:H13) -> 2280.3975 | I15: =MAX(I8:I13) -> 474.6 | J15: =MAX(J8:J13) -> 542.5 | K15: =MAX(K8:K13) -> 616.1 | ... U15: =MAX(U8:U13) -> 2.11
B16: 75th Percentile | D16: =QUARTILE(D8:D13,3) -> 55.225 | E16: =QUARTILE(E8:E13,3) -> 768.15 | F16: =QUARTILE(F8:F13,3) -> 100.0385 | G16: =QUARTILE(G8:G13,3) -> 0 | H16: =QUARTILE(H8:H13,3) -> 631.9785 | I16: =QUARTILE(I8:I13,3) -> 440.0225 | J16: =QUARTILE(J8:J13,3) -> 438.505 | K16: =QUARTILE(K8:K13,3) -> 458.8475 | ... U16: =QUARTILE(U8:U13,3) -> 1.475
B17: Median | D17: =MEDIAN(D8:D13) -> 27.085 | E17: =MEDIAN(E8:E13) -> 633.1184 | F17: =MEDIAN(F8:F13) -> 28.1035 | G17: =MEDIAN(G8:G13) -> 0 | H17: =MEDIAN(H8:H13) -> 550.9389 | I17: =MEDIAN(I8:I13) -> 385.3435 | J17: =MEDIAN(J8:J13) -> 400.24 | K17: =MEDIAN(K8:K13) -> 414.4 | ... U17: =MEDIAN(U8:U13) -> 1.2
B18: 25th Percentile | D18: =QUARTILE(D8:D13,1) -> 7.3675 | E18: =QUARTILE(E8:E13,1) -> 210.3463 | F18: =QUARTILE(F8:F13,1) -> 3.07575 | G18: =QUARTILE(G8:G13,1) -> 0 | H18: =QUARTILE(H8:H13,1) -> 176.92545 | I18: =QUARTILE(I8:I13,1) -> 334.86675 | J18: =QUARTILE(J8:J13,1) -> 332.215 | K18: =QUARTILE(K8:K13,1) -> 350.595 | ... U18: =QUARTILE(U8:U13,1) -> 1.12
B19: Minimum | D19: =MIN(D8:D13) -> 2.2 | E19: =MIN(E8:E13) -> 52.91 | F19: =MIN(F8:F13) -> 0 | G19: =MIN(G8:G13) -> 0 | H19: =MIN(H8:H13) -> 74.6548 | I19: =MIN(I8:I13) -> 127.753 | J19: =MIN(J8:J13) -> 119.63 | K19: =MIN(K8:K13) -> 124.21 | ... U19: =MIN(U8:U13) -> 0.32
B21: Valuation Statistics | E21: Capitalization | I21: Enterprise Value / | L21: Enterprise Value /
D22: =+$D$6 -> Share | E22: =+$E$6 -> Equity | G22: =+$G$6 -> Preferred | H22: =+$H$6 -> Enterprise | I22: Revenue | L22: EBITDA | O22: Price / Earnings Multiple
B23: =+$B$7 -> Company Name | C23: =+$C$7 -> Ticker | D23: =+$D$7 -> Price | E23: =+$E$7 -> Value | F23: =+$F$7 -> Debt | G23: =+$G$7 -> Stock | H23: =+$H$7 -> Value | I23: =+$I$7 -> LTM | J23: =+$J$7 -> Forward Year 1 | K23: =+$K$7 -> Forward Year 2 | L23: =+$I$7 -> LTM | M23: =+$J$7 -> Forward Year 1 | N23: =+$K$7 -> Forward Year 2 | O23: =+$I$7 -> LTM | P23: =+$J$7 -> Forward Year 1 | Q23: =+$K$7 -> Forward Year 2
B24: =+B8 -> Nord Anglia Education Inc | C24: =+C8 -> NYSE:Company1891 | D24: =+D8 -> 19.69 | E24: =+E8 -> 1924.6975 | F24: =+F8 -> 522.4 | G24: =+G8 -> 0 | H24: =+H8 -> 2280.3975 | I24: =IFERROR(IF(OR(+$H24/I8<0,+$H24/I8>=100),"NM",+$H24/I8),"N/A") -> 4.8048831 | J24: =IFERROR(IF(OR(+$H24/J8<0,+$H24/J8>=100),"NM",+$H24/J8),"N/A") -> 4.2034977 | K24: =IFERROR(IF(OR(+$H24/K8<0,+$H24/K8>=100),"NM",+$H24/K8),"N/A") -> 3.7013431 | L24: =IFERROR(IF(OR(+$H24/L8<0,+$H24/L8>=100),"NM",+$H24/L8),"N/A") -> 17.899509 | M24: =IFERROR(IF(OR(+$H24/M8<0,+$H24/M8>=100),"NM",+$H24/M8),"N/A") -> 15.880205 | N24: =IFERROR(IF(OR(+$H24/N8<0,+$H24/N8>=100),"NM",+$H24/N8),"N/A") -> 13.44574 | O24: =IFERROR(IF(OR(+$E24/R8<0,+$E24/R8>=100),"NM",+$E24/R8),"N/A") -> 72.925926 | P24: =IFERROR(IF(OR(+$E24/S8<0,+$E24/S8>=100),"NM",+$E24/S8),"N/A") -> 31.253968 | Q24: =IFERROR(IF(OR(+$E24/T8<0,+$E24/T8>=100),"NM",+$E24/T8),"N/A") -> 24.6125
B25: =+B9 -> Company2600 Education Inc | C25: =+C9 -> NASDAQ:Company2494 | D25: =+D9 -> 62.14 | E25: =+E9 -> 671.112 | F25: =+F9 -> 118.75 | G25: =+G9 -> 0 | H25: =+H9 -> 627.582 | I25: =IFERROR(IF(OR(+$H25/I9<0,+$H25/I9>=100),"NM",+$H25/I9),"N/A") -> 1.4070052 | J25: =IFERROR(IF(OR(+$H25/J9<0,+$H25/J9>=100),"NM",+$H25/J9),"N/A") -> 1.4540151 | K25: =IFERROR(IF(OR(+$H25/K9<0,+$H25/K9>=100),"NM",+$H25/K9),"N/A") -> 1.4147475 | L25: =IFERROR(IF(OR(+$H25/L9<0,+$H25/L9>=100),"NM",+$H25/L9),"N/A") -> 6.1301073 | M25: =IFERROR(IF(OR(+$H25/M9<0,+$H25/M9>=100),"NM",+$H25/M9),"N/A") -> 6.5646653 | N25: =IFERROR(IF(OR(+$H25/N9<0,+$H25/N9>=100),"NM",+$H25/N9),"N/A") -> 6.0170853 | O25: =IFERROR(IF(OR(+$E25/R9<0,+$E25/R9>=100),"NM",+$E25/R9),"N/A") -> 14.4761 | P25: =IFERROR(IF(OR(+$E25/S9<0,+$E25/S9>=100),"NM",+$E25/S9),"N/A") -> 18.222874 | Q25: =IFERROR(IF(OR(+$E25/T9<0,+$E25/T9>=100),"NM",+$E25/T9),"N/A") -> 16.182292
B26: =+B10 -> Capella Education Company | C26: =+C10 -> NASDAQ:Company0593 | D26: =+D10 -> 65.4 | E26: =+E10 -> 800.496 | F26: =+F10 -> 0 | G26: =+G10 -> 0 | H26: =+H10 -> 633.444 | I26: =IFERROR(IF(OR(+$H26/I10<0,+$H26/I10>=100),"NM",+$H26/I10),"N/A") -> 1.5011695 | J26: =IFERROR(IF(OR(+$H26/J10<0,+$H26/J10>=100),"NM",+$H26/J10),"N/A") -> 1.4370327 | K26: =IFERROR(IF(OR(+$H26/K10<0,+$H26/K10>=100),"NM",+$H26/K10),"N/A") -> 1.365387 | L26: =IFERROR(IF(OR(+$H26/L10<0,+$H26/L10>=100),"NM",+$H26/L10),"N/A") -> 6.9929678 | M26: =IFERROR(IF(OR(+$H26/M10<0,+$H26/M10>=100),"NM",+$H26/M10),"N/A") -> 6.6678316 | N26: =IFERROR(IF(OR(+$H26/N10<0,+$H26/N10>=100),"NM",+$H26/N10),"N/A") -> 6.3919677 | O26: =IFERROR(IF(OR(+$E26/R10<0,+$E26/R10>=100),"NM",+$E26/R10),"N/A") -> 21.09733 | P26: =IFERROR(IF(OR(+$E26/S10<0,+$E26/S10>=100),"NM",+$E26/S10),"N/A") -> 18.956522 | Q26: =IFERROR(IF(OR(+$E26/T10<0,+$E26/T10>=100),"NM",+$E26/T10),"N/A") -> 17.210526
B27: =+B11 -> American Public Education, Inc. | C27: =+C11 -> NASDAQ:Company0117 | D27: =+D11 -> 34.48 | E27: =+E11 -> 595.1248 | F27: =+F11 -> 0 | G27: =+G11 -> 0 | H27: =+H11 -> 474.2958 | I27: =IFERROR(IF(OR(+$H27/I11<0,+$H27/I11>=100),"NM",+$H27/I11),"N/A") -> 1.360105 | J27: =IFERROR(IF(OR(+$H27/J11<0,+$H27/J11>=100),"NM",+$H27/J11),"N/A") -> 1.2858423 | K27: =IFERROR(IF(OR(+$H27/K11<0,+$H27/K11>=100),"NM",+$H27/K11),"N/A") -> 1.2312975 | L27: =IFERROR(IF(OR(+$H27/L11<0,+$H27/L11>=100),"NM",+$H27/L11),"N/A") -> 6.400753 | M27: =IFERROR(IF(OR(+$H27/M11<0,+$H27/M11>=100),"NM",+$H27/M11),"N/A") -> 6.298749 | N27: =IFERROR(IF(OR(+$H27/N11<0,+$H27/N11>=100),"NM",+$H27/N11),"N/A") -> 5.9212959 | O27: =IFERROR(IF(OR(+$E27/R11<0,+$E27/R11>=100),"NM",+$E27/R11),"N/A") -> 15.744292 | P27: =IFERROR(IF(OR(+$E27/S11<0,+$E27/S11>=100),"NM",+$E27/S11),"N/A") -> 14.548523 | Q27: =IFERROR(IF(OR(+$E27/T11<0,+$E27/T11>=100),"NM",+$E27/T11),"N/A") -> 13.68254
B28: =+B12 -> Lincoln Educational Services Corp | C28: =+C12 -> NASDAQ:Company1557 | D28: =+D12 -> 2.2 | E28: =+E12 -> 52.91 | F28: =+F12 -> 43.904 | G28: =+G12 -> 0 | H28: =+H12 -> 77.802 | I28: =IFERROR(IF(OR(+$H28/I12<0,+$H28/I12>=100),"NM",+$H28/I12),"N/A") -> 0.23558588 | J28: =IFERROR(IF(OR(+$H28/J12<0,+$H28/J12>=100),"NM",+$H28/J12),"N/A") -> 0.24313125 | K28: =IFERROR(IF(OR(+$H28/K12<0,+$H28/K12>=100),"NM",+$H28/K12),"N/A") -> 0.22946381 | L28: =IFERROR(IF(OR(+$H28/L12<0,+$H28/L12>=100),"NM",+$H28/L12),"N/A") -> NM | M28: =IFERROR(IF(OR(+$H28/M12<0,+$H28/M12>=100),"NM",+$H28/M12),"N/A") -> NM | N28: =IFERROR(IF(OR(+$H28/N12<0,+$H28/N12>=100),"NM",+$H28/N12),"N/A") -> NM | O28: =IFERROR(IF(OR(+$E28/R12<0,+$E28/R12>=100),"NM",+$E28/R12),"N/A") -> NM | P28: =IFERROR(IF(OR(+$E28/S12<0,+$E28/S12>=100),"NM",+$E28/S12),"N/A") -> NM | Q28: =IFERROR(IF(OR(+$E28/T12<0,+$E28/T12>=100),"NM",+$E28/T12),"N/A") -> NM
B29: =+B13 -> National American University Holdings Inc | C29: =+C13 -> NASDAQ:Company1849 | D29: =+D13 -> 3.26 | E29: =+E13 -> 82.0868 | F29: =+F13 -> 12.303 | G29: =+G13 -> 0 | H29: =+H13 -> 74.6548 | I29: =IFERROR(IF(OR(+$H29/I13<0,+$H29/I13>=100),"NM",+$H29/I13),"N/A") -> 0.58436827 | J29: =IFERROR(IF(OR(+$H29/J13<0,+$H29/J13>=100),"NM",+$H29/J13),"N/A") -> 0.62404748 | K29: =IFERROR(IF(OR(+$H29/K13<0,+$H29/K13>=100),"NM",+$H29/K13),"N/A") -> 0.60103695 | L29: =IFERROR(IF(OR(+$H29/L13<0,+$H29/L13>=100),"NM",+$H29/L13),"N/A") -> 5.8677042 | M29: =IFERROR(IF(OR(+$H29/M13<0,+$H29/M13>=100),"NM",+$H29/M13),"N/A") -> 6.7256577 | N29: =IFERROR(IF(OR(+$H29/N13<0,+$H29/N13>=100),"NM",+$H29/N13),"N/A") -> 4.9115 | O29: =IFERROR(IF(OR(+$E29/R13<0,+$E29/R13>=100),"NM",+$E29/R13),"N/A") -> 23.669781 | P29: =IFERROR(IF(OR(+$E29/S13<0,+$E29/S13>=100),"NM",+$E29/S13),"N/A") -> 13.583333 | Q29: =IFERROR(IF(OR(+$E29/T13<0,+$E29/T13>=100),"NM",+$E29/T13),"N/A") -> 12.074074
B31: Maximum | D31: =MAX(D24:D29) -> 65.4 | E31: =MAX(E24:E29) -> 1924.6975 | F31: =MAX(F24:F29) -> 522.4 | G31: =MAX(G24:G29) -> 0 | H31: =MAX(H24:H29) -> 2280.3975 | I31: =MAX(I24:I29) -> 4.8048831 | J31: =MAX(J24:J29) -> 4.2034977 | K31: =MAX(K24:K29) -> 3.7013431 | ... Q31: =MAX(Q24:Q29) -> 24.6125
B32: 75th Percentile | D32: =QUARTILE(D24:D29,3) -> 55.225 | E32: =QUARTILE(E24:E29,3) -> 768.15 | F32: =QUARTILE(F24:F29,3) -> 100.0385 | G32: =QUARTILE(G24:G29,3) -> 0 | H32: =QUARTILE(H24:H29,3) -> 631.9785 | I32: =QUARTILE(I24:I29,3) -> 1.4776284 | J32: =QUARTILE(J24:J29,3) -> 1.4497695 | K32: =QUARTILE(K24:K29,3) -> 1.4024074 | ... Q32: =QUARTILE(Q24:Q29,3) -> 17.210526
B33: Median | D33: =MEDIAN(D24:D29) -> 27.085 | E33: =MEDIAN(E24:E29) -> 633.1184 | F33: =MEDIAN(F24:F29) -> 28.1035 | G33: =MEDIAN(G24:G29) -> 0 | H33: =MEDIAN(H24:H29) -> 550.9389 | I33: =MEDIAN(I24:I29) -> 1.3835551 | J33: =MEDIAN(J24:J29) -> 1.3614375 | K33: =MEDIAN(K24:K29) -> 1.2983423 | ... Q33: =MEDIAN(Q24:Q29) -> 16.182292
B34: 25th Percentile | D34: =QUARTILE(D24:D29,1) -> 7.3675 | E34: =QUARTILE(E24:E29,1) -> 210.3463 | F34: =QUARTILE(F24:F29,1) -> 3.07575 | G34: =QUARTILE(G24:G29,1) -> 0 | H34: =QUARTILE(H24:H29,1) -> 176.92545 | I34: =QUARTILE(I24:I29,1) -> 0.77830244 | J34: =QUARTILE(J24:J29,1) -> 0.78949619 | K34: =QUARTILE(K24:K29,1) -> 0.75860209 | ... Q34: =QUARTILE(Q24:Q29,1) -> 13.68254
B35: Minimum | D35: =MIN(D24:D29) -> 2.2 | E35: =MIN(E24:E29) -> 52.91 | F35: =MIN(F24:F29) -> 0 | G35: =MIN(G24:G29) -> 0 | H35: =MIN(H24:H29) -> 74.6548 | I35: =MIN(I24:I29) -> 0.23558588 | J35: =MIN(J24:J29) -> 0.24313125 | K35: =MIN(K24:K29) -> 0.22946381 | ... Q35: =MIN(Q24:Q29) -> 12.074074

Sheet ValSum
B2: ="Valuation Summary - "&Company_Name -> Valuation Summary - Capital Capable Media LLC
B3: =+'Company0462-GAAP'!$B$3 -> ($ USD as Stated)
B5: ="Valuation Statistics - "&TEXT(Company_Name,"") -> Valuation Statistics - Capital Capable Media LLC | C5: =TEXT(Company_Name,"")&" - Range of Valuation Multiples" -> Capital Capable Media LLC - Range of Valuation Multiples | J5: =TEXT(Company_Name,"")&" - Range of Implied Equity Values" -> Capital Capable Media LLC - Range of Implied Equity Values
D7: 75th | F7: 25th | H7: Applicable | I7: Private | K7: 25th | M7: 75th
C8: Maximum | D8: Percentile | E8: Median | F8: Percentile | G8: Minimum | H8: Company | I8: Company | J8: Minimum | K8: Percentile | L8: Median | M8: Percentile | N8: Maximum
B9: Methodology Name | C9: Multiple | D9: Multiple | E9: Multiple | F9: Multiple | G9: Multiple | H9: Figure | I9: Discount | J9: Multiple | K9: Multiple | L9: Multiple | M9: Multiple | N9: Multiple
B11: Public Company Comparables:
B12: LTM EV / Revenue: | C12: {=TRANSPOSE('Public Comps'!I31:I35)} -> 4.8048831 | D12: 1.4776284 | E12: 1.3835551 | F12: 0.77830244 | G12: 0.23558588 | H12: =+'Company0462-GAAP'!K17 -> 915003.96 | I12: =PrivCo_Discount -> 0.3 | J12: =+J38 -> 557965.7 | K12: =+K38 -> 905577.17 | L12: =+L38 -> 1293243.2 | M12: =+M38 -> 1353497.4 | N12: =+N38 -> 3484613.2
B13: =TEXT('Public Comps'!$J$7,"yyyy-mm-dd")&" EV / Revenue:" -> Forward Year 1 EV / Revenue: | C13: {=TRANSPOSE('Public Comps'!J31:J35)} -> 4.2034977 | D13: 1.4497695 | E13: 1.3614375 | F13: 0.78949619 | G13: 0.24313125 | H13: =+'Company0462-GAAP'!L17 -> 1062799.6 | I13: =PrivCo_Discount -> 0.3 | J13: =+J39 -> 587952.16 | K13: =+K39 -> 994425.67 | L13: =+L39 -> 1419927 | M13: =+M39 -> 1485642.4 | N13: =+N39 -> 3534305.3
B14: =TEXT('Public Comps'!$K$7,"yyyy-mm-dd")&" EV / Revenue:" -> Forward Year 2 EV / Revenue: | C14: {=TRANSPOSE('Public Comps'!K31:K35)} -> 3.7013431 | D14: 1.4024074 | E14: 1.2983423 | F14: 0.75860209 | G14: 0.22946381 | H14: =+'Company0462-GAAP'!M17 -> 1261407.7 | I14: =PrivCo_Discount -> 0.3 | J14: =+J40 -> 609685.5 | K14: =+K40 -> 1076906.9 | L14: =+L40 -> 1553489.6 | M14: =+M40 -> 1645377.6 | N14: =+N40 -> 3675304.3
B15: LTM EV / EBITDA: | C15: {=TRANSPOSE('Public Comps'!L31:L35)} -> 17.899509 | D15: 6.9929678 | E15: 6.400753 | F15: 6.1301073 | G15: 5.8677042 | H15: =+'Company0462-GAAP'!K39 -> 226259.2 | I15: =PrivCo_Discount -> 0.3 | J15: =+J41 -> 1336407.7 | K15: =+K41 -> 1377967.5 | L15: =+L41 -> 1420832.8 | M15: =+M41 -> 1514628.6 | N15: =+N41 -> 3242022.3
B16: =TEXT('Public Comps'!$J$7,"yyyy-mm-dd")&" EV / EBITDA:" -> Forward Year 1 EV / EBITDA: | C16: {=TRANSPOSE('Public Comps'!M31:M35)} -> 15.880205 | D16: 6.7256577 | E16: 6.6678316 | F16: 6.5646653 | G16: 6.298749 | H16: =+'Company0462-GAAP'!L39 -> 272480.02 | I16: =PrivCo_Discount -> 0.3 | J16: =+J42 -> 1608470.6 | K16: =+K42 -> 1659190.4 | L16: =+L42 -> 1678867.9 | M16: =+M42 -> 1689897.4 | N16: =+N42 -> 3435999.4
B17: =TEXT('Public Comps'!$K$7,"yyyy-mm-dd")&" EV / EBITDA:" -> Forward Year 2 EV / EBITDA: | C17: {=TRANSPOSE('Public Comps'!N31:N35)} -> 13.44574 | D17: 6.3919677 | E17: 6.0170853 | F17: 5.9212959 | G17: 4.9115 | H17: =+'Company0462-GAAP'!M39 -> 306058.52 | I17: =PrivCo_Discount -> 0.3 | J17: =+J43 -> 1459316.8 | K17: =+K43 -> 1675656.4 | L17: =+L43 -> 1696178.5 | M17: =+M43 -> 1776493.6 | N17: =+N43 -> 3287700.6
B18: LTM Price / Earnings: | C18: {=TRANSPOSE('Public Comps'!O31:O35)} -> 72.925926 | D18: 23.669781 | E18: 21.09733 | F18: 15.744292 | G18: 14.4761 | H18: =+'Company0462-GAAP'!K32 -> 98993.538 | I18: =PrivCo_Discount -> 0.3 | J18: =+J44 -> 1003128.3 | K18: =+K44 -> 1091008.2 | L18: =+L44 -> 1461949.6 | M18: =+M44 -> 1640208.7 | N18: =+N44 -> 5053436.8
B19: =TEXT('Public Comps'!$J$7,"yyyy-mm-dd")&" Price / Earnings:" -> Forward Year 1 Price / Earnings: | C19: {=TRANSPOSE('Public Comps'!P31:P35)} -> 31.253968 | D19: 18.956522 | E19: 18.222874 | F19: 14.548523 | G19: 13.583333 | H19: =+'Company0462-GAAP'!L32 -> 175665.27 | I19: =PrivCo_Discount -> 0.3 | J19: =+J45 -> 1670283.9 | K19: =+K45 -> 1788969.2 | L19: =+L45 -> 2240788.2 | M19: =+M45 -> 2331001.7 | N19: =+N45 -> 3843165.7
B20: =TEXT('Public Comps'!$K$7,"yyyy-mm-dd")&" Price / Earnings:" -> Forward Year 2 Price / Earnings: | C20: {=TRANSPOSE('Public Comps'!Q31:Q35)} -> 24.6125 | D20: 17.210526 | E20: 16.182292 | F20: 13.68254 | G20: 12.074074 | H20: =+'Company0462-GAAP'!M32 -> 197220.94 | I20: =PrivCo_Discount -> 0.3 | J20: =+J46 -> 1666882.2 | K20: =+K46 -> 1888938.3 | L20: =+L46 -> 2234040.7 | M20: =+M46 -> 2375993.3 | N20: =+N46 -> 3397870.2
B22: Precedent Transactions:
B23: LTM EV / Revenue: | C23: 2.5 | D23: 1.7 | E23: 1.5 | F23: 1.4 | G23: 0.9 | H23: =+'Company0462-GAAP'!K17 -> 915003.96 | I23: =PrivCo_Discount -> 0.3 | J23: =+J51 -> 983524.79 | K23: =+K51 -> 1303776.2 | L23: =+L51 -> 1367826.5 | M23: =+M51 -> 1495927 | N23: =+N51 -> 2008329.2
B24: LTM EV / EBITDA: | C24: 13.5 | D24: 12.1 | E24: 11.1 | F24: 10.1 | G24: 8 | H24: =+'Company0462-GAAP'!K39 -> 226259.2 | I24: =PrivCo_Discount -> 0.3 | J24: =+J52 -> 1674123.8 | K24: =+K52 -> 2006724.8 | L24: =+L52 -> 2165106.3 | M24: =+M52 -> 2323487.7 | N24: =+N52 -> 2545221.7
B26: Discounted Cash Flow Analysis:
B27: 13.5% - 15.5% Discount Rate, 2.0% - 4.0% Terminal FCF Growth Rate: | J27: =+DCF!H68 -> 2323442.9 | K27: =+DCF!I69 -> 2348160.2 | L27: =+DCF!J71 -> 2372035.7 | M27: =+DCF!K72 -> 2403761.2 | N27: =+DCF!L73 -> 2435191
H29: Implied Enterprise Value or Equity Value at a Range of Multiples:
G31: Enterprise Value --> | J31: =+G12*$H12*(1-$I12) -> 150893.41 | K31: =+F12*$H12*(1-$I12) -> 498504.87 | L31: =+E12*$H12*(1-$I12) -> 886170.85 | M31: =+D12*$H12*(1-$I12) -> 946425.11 | N31: =+C12*$H12*(1-$I12) -> 3077540.9
G32: Enterprise Value --> | J32: =+G13*$H13*(1-$I13) -> 180879.86 | K32: =+F13*$H13*(1-$I13) -> 587353.37 | L32: =+E13*$H13*(1-$I13) -> 1012854.7 | M32: =+D13*$H13*(1-$I13) -> 1078570.1 | N32: =+C13*$H13*(1-$I13) -> 3127233
G33: Enterprise Value --> | J33: =+G14*$H14*(1-$I14) -> 202613.2 | K33: =+F14*$H14*(1-$I14) -> 669834.59 | L33: =+E14*$H14*(1-$I14) -> 1146417.3 | M33: =+D14*$H14*(1-$I14) -> 1238305.3 | N33: =+C14*$H14*(1-$I14) -> 3268232
G34: Enterprise Value --> | J34: =+G15*$H15*(1-$I15) -> 929335.42 | K34: =+F15*$H15*(1-$I15) -> 970895.22 | L34: =+E15*$H15*(1-$I15) -> 1013760.5 | M34: =+D15*$H15*(1-$I15) -> 1107556.3 | N34: =+C15*$H15*(1-$I15) -> 2834950
G35: Enterprise Value --> | J35: =+G16*$H16*(1-$I16) -> 1201398.3 | K35: =+F16*$H16*(1-$I16) -> 1252118.1 | L35: =+E16*$H16*(1-$I16) -> 1271795.6 | M35: =+D16*$H16*(1-$I16) -> 1282825.1 | N35: =+C16*$H16*(1-$I16) -> 3028927.1
G36: Enterprise Value --> | J36: =+G17*$H17*(1-$I17) -> 1052244.5 | K36: =+F17*$H17*(1-$I17) -> 1268584.1 | L36: =+E17*$H17*(1-$I17) -> 1289106.2 | M36: =+D17*$H17*(1-$I17) -> 1369421.3 | N36: =+C17*$H17*(1-$I17) -> 2880628.3
G38: Equity Value --> | J38: =+J31+'Company0462-GAAP'!$K$52 -> 557965.7 | K38: =+K31+'Company0462-GAAP'!$K$52 -> 905577.17 | L38: =+L31+'Company0462-GAAP'!$K$52 -> 1293243.2 | M38: =+M31+'Company0462-GAAP'!$K$52 -> 1353497.4 | N38: =+N31+'Company0462-GAAP'!$K$52 -> 3484613.2
G39: Equity Value --> | J39: =+J32+'Company0462-GAAP'!$K$52 -> 587952.16 | K39: =+K32+'Company0462-GAAP'!$K$52 -> 994425.67 | L39: =+L32+'Company0462-GAAP'!$K$52 -> 1419927 | M39: =+M32+'Company0462-GAAP'!$K$52 -> 1485642.4 | N39: =+N32+'Company0462-GAAP'!$K$52 -> 3534305.3
G40: Equity Value --> | J40: =+J33+'Company0462-GAAP'!$K$52 -> 609685.5 | K40: =+K33+'Company0462-GAAP'!$K$52 -> 1076906.9 | L40: =+L33+'Company0462-GAAP'!$K$52 -> 1553489.6 | M40: =+M33+'Company0462-GAAP'!$K$52 -> 1645377.6 | N40: =+N33+'Company0462-GAAP'!$K$52 -> 3675304.3
G41: Equity Value --> | J41: =+J34+'Company0462-GAAP'!$K$52 -> 1336407.7 | K41: =+K34+'Company0462-GAAP'!$K$52 -> 1377967.5 | L41: =+L34+'Company0462-GAAP'!$K$52 -> 1420832.8 | M41: =+M34+'Company0462-GAAP'!$K$52 -> 1514628.6 | N41: =+N34+'Company0462-GAAP'!$K$52 -> 3242022.3
G42: Equity Value --> | J42: =+J35+'Company0462-GAAP'!$K$52 -> 1608470.6 | K42: =+K35+'Company0462-GAAP'!$K$52 -> 1659190.4 | L42: =+L35+'Company0462-GAAP'!$K$52 -> 1678867.9 | M42: =+M35+'Company0462-GAAP'!$K$52 -> 1689897.4 | N42: =+N35+'Company0462-GAAP'!$K$52 -> 3435999.4
G43: Equity Value --> | J43: =+J36+'Company0462-GAAP'!$K$52 -> 1459316.8 | K43: =+K36+'Company0462-GAAP'!$K$52 -> 1675656.4 | L43: =+L36+'Company0462-GAAP'!$K$52 -> 1696178.5 | M43: =+M36+'Company0462-GAAP'!$K$52 -> 1776493.6 | N43: =+N36+'Company0462-GAAP'!$K$52 -> 3287700.6
G44: Equity Value --> | J44: =+G18*$H18*(1-$I18) -> 1003128.3 | K44: =+F18*$H18*(1-$I18) -> 1091008.2 | L44: =+E18*$H18*(1-$I18) -> 1461949.6 | M44: =+D18*$H18*(1-$I18) -> 1640208.7 | N44: =+C18*$H18*(1-$I18) -> 5053436.8
G45: Equity Value --> | J45: =+G19*$H19*(1-$I19) -> 1670283.9 | K45: =+F19*$H19*(1-$I19) -> 1788969.2 | L45: =+E19*$H19*(1-$I19) -> 2240788.2 | M45: =+D19*$H19*(1-$I19) -> 2331001.7 | N45: =+C19*$H19*(1-$I19) -> 3843165.7
G46: Equity Value --> | J46: =+G20*$H20*(1-$I20) -> 1666882.2 | K46: =+F20*$H20*(1-$I20) -> 1888938.3 | L46: =+E20*$H20*(1-$I20) -> 2234040.7 | M46: =+D20*$H20*(1-$I20) -> 2375993.3 | N46: =+C20*$H20*(1-$I20) -> 3397870.2
G48: Enterprise Value --> | J48: =+G23*$H23*(1-$I23) -> 576452.49 | K48: =+F23*$H23*(1-$I23) -> 896703.88 | L48: =+E23*$H23*(1-$I23) -> 960754.15 | M48: =+D23*$H23*(1-$I23) -> 1088854.7 | N48: =+C23*$H23*(1-$I23) -> 1601256.9
G49: Enterprise Value --> | J49: =+G24*$H24*(1-$I24) -> 1267051.5 | K49: =+F24*$H24*(1-$I24) -> 1599652.5 | L49: =+E24*$H24*(1-$I24) -> 1758034 | M49: =+D24*$H24*(1-$I24) -> 1916415.4 | N49: =+C24*$H24*(1-$I24) -> 2138149.4
G51: Equity Value --> | J51: =+J48+'Company0462-GAAP'!$K$52 -> 983524.79 | K51: =+K48+'Company0462-GAAP'!$K$52 -> 1303776.2 | L51: =+L48+'Company0462-GAAP'!$K$52 -> 1367826.5 | M51: =+M48+'Company0462-GAAP'!$K$52 -> 1495927 | N51: =+N48+'Company0462-GAAP'!$K$52 -> 2008329.2
G52: Equity Value --> | J52: =+J49+'Company0462-GAAP'!$K$52 -> 1674123.8 | K52: =+K49+'Company0462-GAAP'!$K$52 -> 2006724.8 | L52: =+L49+'Company0462-GAAP'!$K$52 -> 2165106.3 | M52: =+M49+'Company0462-GAAP'!$K$52 -> 2323487.7 | N52: =+N49+'Company0462-GAAP'!$K$52 -> 2545221.7

Sheet ValGraph
I25: Min | J25: 25th | K25: Median | L25: 75th | M25: Max | N25: Min Point | O25: 25th Point | P25: Median Point | Q25: 75th Point | R25: Max Point
B27: =+ValSum!B27 -> 13.5% - 15.5% Discount Rate, 2.0% - 4.0% Terminal FCF Growth Rate:
B29: =+ValSum!B24 -> LTM EV / EBITDA:
B30: =+ValSum!B23 -> LTM EV / Revenue:
B32: =+ValSum!B20 -> Forward Year 2 Price / Earnings:
B33: =+ValSum!B19 -> Forward Year 1 Price / Earnings:
B34: =+ValSum!B18 -> LTM Price / Earnings:
B35: =+ValSum!B17 -> Forward Year 2 EV / EBITDA:
B36: =+ValSum!B16 -> Forward Year 1 EV / EBITDA:
B37: =+ValSum!B15 -> LTM EV / EBITDA:
B38: =+ValSum!B14 -> Forward Year 2 EV / Revenue:
B39: =+ValSum!B13 -> Forward Year 1 EV / Revenue:
B40: =+ValSum!B12 -> LTM EV / Revenue:
