Workbook
Name A_ALL_Ticker0009: #REF!
Name A_ALL_KEYWORDS_TYPE_ScalarContributed_EQTY_200001266: #REF!,#REF!,#REF!,#REF!,#REF!
Name A_ALL_KEYWORDS_TYPE_ScalarContributed_ISSR_208000403: #REF!,#REF!
Name A_ALL_KEYWORDS_TYPE_ScalarReference_EQTY_200001266: #REF!
Name A_ALL_KEYWORDS_TYPE_ScalarReference_ISSR_208000403: #REF!
Name A_ALL_KEYWORDS_TYPE_Vector_EQTY_200001266: #REF!,#REF!,#REF!,#REF!,#REF!,#REF!,#REF!
Name A_ALL_KEYWORDS_TYPE_Vector_ISSR_208000403: #REF!,#REF!,#REF!,#REF!,#REF!,#REF!,#REF!,#REF!,#REF!
Name A_ALL_LMT: #REF!
Name A_ALL_LMT_: #REF!
Name A_ALL_SECTION_KEYWORDS_EQTY_200001266_1314: #REF!
Name A_ALL_SECTION_KEYWORDS_EQTY_200001266_1319: #REF!
Name A_ALL_SECTION_KEYWORDS_EQTY_200001266_131E: #REF!
Name A_ALL_SECTION_KEYWORDS_EQTY_200001266_131O: #REF!
Name A_ALL_SECTION_KEYWORDS_EQTY_200001266_13A: #REF!
Name A_ALL_SECTION_KEYWORDS_EQTY_200001266_13K: #REF!
Name A_ALL_SECTION_KEYWORDS_EQTY_200001266_13U: #REF!
Name A_ALL_SECTION_KEYWORDS_EQTY_200001266_13V: #REF!
Name A_ALL_SECTION_KEYWORDS_EQTY_200001266_13W: #REF!
Name A_ALL_SECTION_KEYWORDS_EQTY_200001266_Reference_Data: #REF!
Name A_ALL_SECTION_KEYWORDS_ISSR_208000403_1314: #REF!
Name A_ALL_SECTION_KEYWORDS_ISSR_208000403_13168: #REF!
Name A_ALL_SECTION_KEYWORDS_ISSR_208000403_1316S: #REF!
Name A_ALL_SECTION_KEYWORDS_ISSR_208000403_1316T: #REF!
Name A_ALL_SECTION_KEYWORDS_ISSR_208000403_1316U: #REF!
Name A_ALL_SECTION_KEYWORDS_ISSR_208000403_1319: #REF!
Name A_ALL_SECTION_KEYWORDS_ISSR_208000403_131E: #REF!
Name A_ALL_SECTION_KEYWORDS_ISSR_208000403_131J: #REF!
Name A_ALL_SECTION_KEYWORDS_ISSR_208000403_131O: #REF!
Name A_ALL_SECTION_KEYWORDS_ISSR_208000403_136E: #REF!,#REF!
Name A_ALL_SECTION_KEYWORDS_ISSR_208000403_13A: #REF!
Name A_ALL_SECTION_KEYWORDS_ISSR_208000403_13U: #REF!
Name A_ALL_SECTION_KEYWORDS_ISSR_208000403_13V: #REF!
Name A_ALL_SECTION_KEYWORDS_ISSR_208000403_Reference_Data: #REF!
Name A_ALL_SECTIONS_EQTY_200001266: #REF!,#REF!,#REF!,#REF!,#REF!,#REF!,#REF!,#REF!,#REF!,#REF!
Name A_CURRENCY_EQTY_200001266_PRI: #REF!
Name A_CURRENCY_EQTY_200001266_PUB: #REF!
Name A_CURRENCY_EQTY_200001266_REP: #REF!
Name A_CURRENCY_ISSR_208000403_REP: #REF!
Name A_KEYWORD_EQTY_200001266_AMER_LIST: #REF!
Name A_KEYWORD_EQTY_200001266_BETA_ANALYST: #REF!
Name A_KEYWORD_EQTY_200001266_BVPS: #REF!
Name A_KEYWORD_EQTY_200001266_BVPS_PUB: #REF!
Name A_KEYWORD_EQTY_200001266_CEEE_EPS: #REF!
Name A_KEYWORD_EQTY_200001266_CF_NI_PRE_PREF: #REF!
Name A_KEYWORD_EQTY_200001266_COMMON_DIV_PAID: #REF!
Name A_KEYWORD_EQTY_200001266_CURRENCY_ISO: #REF!
Name A_KEYWORD_EQTY_200001266_DILUTE_SHARES: #REF!
Name A_KEYWORD_EQTY_200001266_DPS: #REF!
Name A_KEYWORD_EQTY_200001266_DPS_PUB: #REF!
Name A_KEYWORD_EQTY_200001266_EBIT_PUB: #REF!
Name A_KEYWORD_EQTY_200001266_EBITDA_PUB: #REF!
Name A_KEYWORD_EQTY_200001266_EPS: #REF!
Name A_KEYWORD_EQTY_200001266_EPS_EX_ESO_B: #REF!
Name A_KEYWORD_EQTY_200001266_EPS_EX_ESO_D: #REF!
Name A_KEYWORD_EQTY_200001266_EPS_FUL_DIL: #REF!
Name A_KEYWORD_EQTY_200001266_EPS_POST_BASIC: #REF!
Name A_KEYWORD_EQTY_200001266_EPS_PUB: #REF!
Name A_KEYWORD_EQTY_200001266_EPS_PUB_EX_ESO: #REF!
Name A_KEYWORD_EQTY_200001266_EQ_PUB: #REF!
Name A_KEYWORD_EQTY_200001266_ESO_POST_TAX: #REF!

Sheet Cover
D7: Company1067 Model
D8: 45936
B16: Person0823, CFA
B17: (212) 357-0954
B18: person@example.com
B20: Person0086, CFA
B21: (212) 934-0385
B22: person@example.com
B24: Person0248
B25: (212) 357-6166
B26: person@example.com
B28: Person1182
B29: (801) 744-0681
B30: person@example.com

Sheet data
B3: Company1067 Raw Data | C3: 1997 | D3: 1998 | E3: 1999 | F3: 2000 | G3: 2001 | H3: 2002 | I3: 2003 | J3: 1Q04 | K3: 2Q04 | L3: 3Q04 | M3: 4Q04 | N3: 2004 | O3: 1Q05 | P3: 2Q05 | Q3: 3Q05 | R3: 4Q05 | S3: 2005 | T3: 1Q06 | U3: 2Q06 | V3: 3Q06 | W3: 4Q06 | X3: 2006 | Y3: 1Q07 | Z3: 2Q07 | AA3: 3Q07 | AB3: 4Q07 | AC3: 2007 | AD3: 1Q08 | AE3: 2Q08 | AF3: 3Q08 | AG3: 4Q08 | AH3: 2008 | AI3: 1Q09 | AJ3: 2Q09 | AK3: 3Q09 | AL3: 4Q09 | AM3: 2009 | AN3: 1Q10 | AO3: 2Q10 | AP3: 3Q10 | AQ3: 4Q10 | AR3: 2010 | AS3: 1Q11 | AT3: 2Q11 | AU3: 3Q11 | AV3: 4Q11 | AW3: 2011 | AX3: 1Q12 | AY3: 2Q12 | AZ3: 3Q12 | BA3: 4Q12 | BB3: 2012 | BC3: 1Q13 | BD3: 2Q13 | BE3: 3Q13 | BF3: 4Q13 | BG3: 2013 | BH3: 1Q14 | BI3: 2Q14 | BJ3: 3Q14 | BK3: 4Q14 | BL3: 2014 | BM3: 1Q15 | BN3: 2Q15 | BO3: 3Q15 | BP3: 4Q15 | BQ3: 2015 | BR3: 1Q16 | BS3: 2Q16 | BT3: 3Q16 | BU3: 4Q16 | BV3: 2016 | BW3: 1Q17 | BX3: 2Q17 | BY3: 3Q17 | BZ3: 4Q17 | CA3: 2017 | CB3: 1Q18 | CC3: 2Q18 | CD3: 3Q18 | CE3: 4Q18 | CF3: 2018 | CG3: 1Q19 | CH3: 2Q19 | CI3: 3Q19 | CJ3: 4Q19 | CK3: 2019 | CL3: 1Q20 | CM3: 2Q20 | CN3: 3Q20 | CO3: 4Q20 | CP3: 2020 | CQ3: 1Q21 | CR3: 2Q21 | CS3: 3Q21 | CT3: 4Q21 | CU3: 2021 | CV3: 1Q22 | CW3: 2Q22 | CX3: 3Q22 | CY3: 4Q22 | CZ3: 2022 | DA3: 1Q23 | DB3: 2Q23 | DC3: 3Q23 | DD3: 4Q23 | DE3: 2023 | DF3: 1Q24 | DG3: 2Q24 | DH3: 3Q24 | DI3: 4Q24 | DJ3: 2024 | DK3: 1Q25 | DL3: 2Q25 | DM3: 3Q25 | DN3: 4Q25 | DO3: 2025 | DP3: 1Q26 | DQ3: 2Q26 | DR3: 3Q26 | DS3: 4Q26 | DT3: 2026 | DU3: 2027 | DV3: 2028
B4: ($ mn) | C4: 35795 | D4: 36160 | E4: 36525 | F4: 36891 | G4: 37256 | H4: 37621 | I4: 37986 | J4: 38077 | K4: 38168 | L4: 38260 | M4: 38352 | N4: 38352 | O4: 38442 | P4: 38533 | Q4: 38625 | R4: 38717 | S4: 38717 | T4: 38807 | U4: 38898 | V4: 38990 | W4: 39082 | X4: 39082 | Y4: 39172 | Z4: 39263 | AA4: 39355 | AB4: 39447 | AC4: 39447 | AD4: 39538 | AE4: 39629 | AF4: 39721 | AG4: 39813 | AH4: 39813 | AI4: 39903 | AJ4: 39994 | AK4: 40086 | AL4: 40178 | AM4: 40178 | AN4: 40268 | AO4: 40359 | AP4: 40451 | AQ4: 40543 | AR4: 40543 | AS4: 40633 | AT4: 40724 | AU4: 40816 | AV4: 40908 | AW4: 40908 | AX4: 40999 | AY4: 41090 | AZ4: 41182 | BA4: 41274 | BB4: 41274 | BC4: 41364 | BD4: 41455 | BE4: 41547 | BF4: 41639 | BG4: 41639 | BH4: 41729 | BI4: 41820 | BJ4: 41912 | BK4: 42004 | BL4: 42004 | BM4: 42094 | BN4: 42185 | BO4: 42277 | BP4: 42369 | BQ4: 42369 | BR4: 42460 | BS4: 42551 | BT4: 42643 | BU4: 42735 | BV4: 42735 | BW4: 42825 | BX4: 42916 | BY4: 43008 | BZ4: 43100 | CA4: 43100 | CB4: 43190 | CC4: 43281 | CD4: 43373 | CE4: 43465 | CF4: 43465 | CG4: 43555 | CH4: 43646 | CI4: 43738 | CJ4: 43830 | CK4: 43830 | CL4: 43921 | CM4: 44012 | CN4: 44104 | CO4: 44196 | CP4: 44196 | CQ4: 44286 | CR4: 44377 | CS4: 44469 | CT4: 44561 | CU4: 44561 | CV4: 44651 | CW4: 44742 | CX4: 44834 | CY4: 44926 | CZ4: 44926 | DA4: 45016 | DB4: 45107 | DC4: 45199 | DD4: 45291 | DE4: 45291 | DF4: 45382 | DG4: 45473 | DH4: 45565 | DI4: 45657 | DJ4: 45657 | DK4: 45747 | DL4: 45838 | DM4: 45930 | DN4: 46022 | DO4: 46022 | DP4: 46112 | DQ4: 46203 | DR4: 46295 | DS4: 46387 | DT4: 46387 | DU4: 46752 | DV4: 47118
B6: Income Statement
B7: Sales of goods | CL7: 12339 | CM7: 10720 | CN7: 12306 | CO7: =CP7-SUM(CL7:CN7) -> 2219 | CP7: 37584 | CQ7: 10349 | CR7: 11105 | CS7: 11530 | CT7: =CU7-SUM(CQ7:CS7) -> 1216 | CU7: 34200 | CV7: 4608 | CW7: 5266 | CX7: 5731 | CY7: =CZ7-SUM(CV7:CX7) -> 6729 | CZ7: 22334 | DA7: 5287 | DB7: 6688 | DC7: 6939 | DD7: =DE7-SUM(DA7:DC7) -> 7879 | DE7: 26793 | DF7: 5935 | DG7: 2175 | DH7: 2448 | DI7: 3230 | DK7: 2653 | DL7: 2842
B8: Sales of services | CL8: 6452 | CM8: 5329 | CN8: 5560 | CO8: =CP8-SUM(CL8:CN8) -> 18044 | CP8: 35385 | CQ8: 5967 | CR8: 6365 | CS8: 6283 | CT8: =CU8-SUM(CQ8:CS8) -> 18275 | CU8: 36890 | CV8: 7302 | CW8: 8096 | CX8: 8095 | CY8: =CZ8-SUM(CV8:CX8) -> 9315 | CZ8: 32808 | DA8: 8407 | DB8: 9163 | DC8: 9565 | DD8: =DE8-SUM(DA8:DC8) -> 10637 | DE8: 37772 | DF8: 9239 | DG8: 6047 | DH8: 6495 | DI8: 6649 | DK8: 6347 | DL8: 7308
B9: Sales of equipment and services | CL9: =SUM(CL7:CL8) -> 18791 | CM9: =SUM(CM7:CM8) -> 16049 | CN9: =SUM(CN7:CN8) -> 17866 | CO9: =SUM(CO7:CO8) -> 20263 | CP9: =SUM(CP7:CP8) -> 72969 | CQ9: =SUM(CQ7:CQ8) -> 16316 | CR9: =SUM(CR7:CR8) -> 17470 | CS9: =SUM(CS7:CS8) -> 17813 | ... DI9: =SUM(DI7:DI8) -> 9879 | DK9: =SUM(DK7:DK8) -> 9000 | DL9: =SUM(DL7:DL8) -> 10150
B10: Insurance revenues | CL10: 699 | CM10: 756 | CN10: 663 | CO10: =CP10-SUM(CL10:CN10) -> 747 | CP10: 2865 | CQ10: 803 | CR10: 810 | CS10: 616 | CT10: =CU10-SUM(CQ10:CS10) -> 877 | CU10: 3106 | CV10: 764 | CW10: 766 | CX10: 645 | CY10: =CZ10-SUM(CV10:CX10) -> 782 | CZ10: 2957 | DA10: 791 | DB10: 847 | DC10: 842 | DD10: =DE10-SUM(DA10:DC10) -> 909 | DE10: 3389 | DF10: 879 | DG10: 871 | DH10: 899 | DI10: 933 | DK10: 934 | DL10: =872+1 -> 873
B11: Net Sales | J11: =SUM(J7:J8) -> 0 | K11: =SUM(K7:K8) -> 0 | L11: =SUM(L7:L8) -> 0 | M11: =SUM(M7:M8) -> 0 | N11: =SUM(N7:N8) -> 0 | O11: =SUM(O7:O8) -> 0 | P11: =SUM(P7:P8) -> 0 | Q11: =SUM(Q7:Q8) -> 0 | ... CK11: =SUM(CK7:CK8) -> 0 | CL11: =SUM(CL9:CL10) -> 19490 | CM11: =SUM(CM9:CM10) -> 16805 | CN11: =SUM(CN9:CN10) -> 18529 | CO11: =SUM(CO9:CO10) -> 21010 | CP11: =SUM(CP9:CP10) -> 75834 | CQ11: =SUM(CQ9:CQ10) -> 17119 | CR11: =SUM(CR9:CR10) -> 18280 | CS11: =SUM(CS9:CS10) -> 18429 | ... DI11: =SUM(DI9:DI10) -> 10812 | DK11: =SUM(DK9:DK10) -> 9934 | DL11: =SUM(DL9:DL10) -> 11023
B12: Cost of goods | CL12: -9930 | CM12: -9787 | CN12: -10555 | CO12: =CP12-SUM(CL12:CN12) -> -4970 | CP12: -35242 | CQ12: -8679 | CR12: -9086 | CS12: -9127 | CT12: =CU12-SUM(CQ12:CS12) -> -4507 | CU12: -31399 | CV12: -5148 | CW12: -5529 | CX12: -6488 | CY12: =CZ12-SUM(CV12:CX12) -> -6578 | CZ12: -23743 | DA12: -5605 | DB12: -6940 | DC12: -7065 | DD12: =DE12-SUM(DA12:DC12) -> -8073 | DE12: -27683 | DF12: -6024 | DG12: -2302 | DH12: -2625 | DI12: -2950 | DK12: -2335 | DL12: -2754
B13: Cost of services | CL13: -4497 | CM13: -3846 | CN13: -3486 | CO13: =CP13-SUM(CL13:CN13) -> -10800 | CP13: -22629 | CQ13: -3859 | CR13: -4532 | CS13: -4275 | CT13: =CU13-SUM(CQ13:CS13) -> -9831 | CU13: -22497 | CV13: -4626 | CW13: -4996 | CX13: -5046 | CY13: =CZ13-SUM(CV13:CX13) -> -5861 | CZ13: -20529 | DA13: -5124 | DB13: -5422 | DC13: -5839 | DD13: =DE13-SUM(DA13:DC13) -> -6324 | DE13: -22709 | DF13: -5596 | DG13: -3273 | DH13: -3601 | DI13: -3811 | DK13: -3660 | DL13: -4092
B14: Unallocated Corporate Costs
B15: Cost of sales | C15: =SUM(C12:C13) -> 0 | D15: =SUM(D12:D13) -> 0 | E15: =SUM(E12:E13) -> 0 | F15: =SUM(F12:F13) -> 0 | G15: =SUM(G12:G13) -> 0 | H15: =SUM(H12:H13) -> 0 | I15: =SUM(I12:I13) -> 0 | J15: =SUM(J12:J13) -> 0 | ... DI15: =SUM(DI12:DI13) -> -6761 | DK15: =SUM(DK12:DK13) -> -5995 | DL15: =SUM(DL12:DL13) -> -6846
B16: Gross Profit | C16: =C11+C15 -> 0 | D16: =D11+D15 -> 0 | E16: =E11+E15 -> 0 | F16: =F11+F15 -> 0 | G16: =G11+G15 -> 0 | H16: =H11+H15 -> 0 | I16: =I11+I15 -> 0 | J16: =J11+J15 -> 0 | ... CK16: =CK11+CK15 -> 0 | CL16: =SUM(CL15,CL11) -> 5063 | CM16: =SUM(CM15,CM11) -> 3172 | CN16: =SUM(CN15,CN11) -> 4488 | CO16: =SUM(CO15,CO11) -> 5240 | CP16: =SUM(CP15,CP11) -> 17963 | CQ16: =SUM(CQ15,CQ11) -> 4581 | CR16: =SUM(CR15,CR11) -> 4662 | CS16: =SUM(CS15,CS11) -> 5027 | ... DI16: =SUM(DI15,DI11) -> 4051 | DK16: =SUM(DK15,DK11) -> 3939 | DL16: =SUM(DL15,DL11) -> 4177
B17: Selling, general and andministrative expenses | CL17: -3061 | CM17: -3068 | CN17: -3215 | CO17: =CP17-SUM(CL17:CN17) -> -3248 | CP17: -12592 | CQ17: -2891 | CR17: -2866 | CS17: -2747 | CT17: =CU17-SUM(CQ17:CS17) -> -3203 | CU17: -11707 | CV17: =-2725-99 -> -2824 | CW17: =-1817-148 -> -1965 | CX17: =-1966-171 -> -2137 | CY17: =CZ17-SUM(CV17:CX17) -> -2962 | CZ17: =-9173-715 -> -9888 | DA17: =-2142-205 -> -2347 | DB17: =-2358-226 -> -2584 | DC17: =-2171-227 -> -2398 | DD17: =DE17-SUM(DA17:DC17) -> -2844 | DE17: =-9195-978 -> -10173 | DF17: -2269 | DG17: -924 | DH17: -1330 | DI17: -1157 | DK17: -876 | DL17: -1020
B18: Research and development expenses | CL18: -723 | CM18: -611 | CN18: -595 | CO18: =CP18-SUM(CL18:CN18) -> -636 | CP18: -2565 | CQ18: -561 | CR18: -604 | CS18: -627 | CT18: =CU18-SUM(CQ18:CS18) -> -705 | CU18: -2497 | CV18: -403 | CW18: -439 | CX18: -426 | CY18: =CZ18-SUM(CV18:CX18) -> -518 | CZ18: -1786 | DA18: -431 | DB18: -455 | DC18: -471 | DD18: =DE18-SUM(DA18:DC18) -> -550 | DE18: -1907 | DF18: -507 | DG18: -300 | DH18: -331 | DI18: -385 | DK18: -359 | DL18: -359
B19: EBIT | C19: =C16+C18 -> 0 | D19: =D16+D18 -> 0 | E19: =E16+E18 -> 0 | F19: =F16+F18 -> 0 | G19: =G16+G18 -> 0 | H19: =H16+H18 -> 0 | I19: =I16+I18 -> 0 | J19: =J18+J16 -> 0 | K19: =K18+K16 -> 0 | L19: =L18+L16 -> 0 | M19: =M18+M16 -> 0 | N19: =N18+N16 -> 0 | O19: =O18+O16 -> 0 | P19: =P18+P16 -> 0 | Q19: =Q18+Q16 -> 0 | ... CK19: =CK18+CK16 -> 0 | CL19: =SUM(CL16:CL18) -> 1279 | CM19: =SUM(CM16:CM18) -> -507 | CN19: =SUM(CN16:CN18) -> 678 | CO19: =SUM(CO16:CO18) -> 1356 | CP19: =SUM(CP16:CP18) -> 2806 | CQ19: =SUM(CQ16:CQ18) -> 1129 | CR19: =SUM(CR16:CR18) -> 1192 | CS19: =SUM(CS16:CS18) -> 1653 | ... DI19: =SUM(DI16:DI18) -> 2509 | DK19: =SUM(DK16:DK18) -> 2704 | DL19: =SUM(DL16:DL18) -> 2798
B20: Interest expense | N20: =SUM(J20:M20) -> 0 | S20: =SUM(O20:R20) -> 0 | X20: =SUM(T20:W20) -> 0 | AC20: =SUM(Y20:AB20) -> 0 | AH20: =SUM(AD20:AG20) -> 0 | AM20: =SUM(AI20:AL20) -> 0 | AR20: =SUM(AN20:AQ20) -> 0 | AW20: =SUM(AS20:AV20) -> 0 | BB20: =SUM(AX20:BA20) -> 0 | BG20: =SUM(BC20:BF20) -> 0 | BL20: =SUM(BH20:BK20) -> 0 | BQ20: =SUM(BM20:BP20) -> 0 | BV20: =SUM(BR20:BU20) -> 0 | CA20: =SUM(BW20:BZ20) -> 0 | CF20: =SUM(CB20:CE20) -> 0 | CK20: =SUM(CG20:CJ20) -> 0 | CL20: -561 | CM20: -561 | CN20: -526 | CO20: =CP20-SUM(CL20:CN20) -> -420 | CP20: -2068 | CQ20: -500 | CR20: -488 | CS20: -462 | CT20: =CU20-SUM(CQ20:CS20) -> -426 | CU20: -1876 | CV20: -387 | CW20: -368 | CX20: -374 | CY20: =CZ20-SUM(CV20:CX20) -> -348 | CZ20: -1477 | DA20: -269 | DB20: -267 | DC20: -286 | DD20: =DE20-SUM(DA20:DC20) -> -296 | DE20: -1118 | DF20: -278 | DG20: -248 | DH20: -251 | DI20: -224 | DK20: -210 | DL20: -158
B21: Non-operating benefit income | N21: =SUM(J21:M21) -> 0 | S21: =SUM(O21:R21) -> 0 | X21: =SUM(T21:W21) -> 0 | AC21: =SUM(Y21:AB21) -> 0 | AH21: =SUM(AD21:AG21) -> 0 | AM21: =SUM(AI21:AL21) -> 0 | AR21: =SUM(AN21:AQ21) -> 0 | AW21: =SUM(AS21:AV21) -> 0 | BB21: =SUM(AX21:BA21) -> 0 | BG21: =SUM(BC21:BF21) -> 0 | BL21: =SUM(BH21:BK21) -> 0 | BQ21: =SUM(BM21:BP21) -> 0 | BV21: =SUM(BR21:BU21) -> 0 | CA21: =SUM(BW21:BZ21) -> 0 | CF21: =SUM(CB21:CE21) -> 0 | CK21: =SUM(CG21:CJ21) -> 0 | CL21: -618 | CM21: -598 | CN21: -605 | CO21: =CP21-SUM(CL21:CN21) -> -609 | CP21: =-2430 -> -2430 | CQ21: -430 | CR21: -517 | CS21: -427 | CT21: =CU21-SUM(CQ21:CS21) -> -408 | CU21: -1782 | CV21: 105 | CW21: 101 | CX21: 96 | CY21: =CZ21-SUM(CV21:CX21) -> 107 | CZ21: 409 | DA21: 385 | DB21: 402 | DC21: 396 | DD21: =DE21-SUM(DA21:DC21) -> 402 | DE21: 1585 | DF21: 362 | DG21: 204 | DH21: 207 | DI21: 213 | DK21: 201 | DL21: 197
B22: Other non-operating income (expense), net | N22: =SUM(J22:M22) -> 0 | S22: =SUM(O22:R22) -> 0 | X22: =SUM(T22:W22) -> 0 | AC22: =SUM(Y22:AB22) -> 0 | AH22: =SUM(AD22:AG22) -> 0 | AM22: =SUM(AI22:AL22) -> 0 | AR22: =SUM(AN22:AQ22) -> 0 | AW22: =SUM(AS22:AV22) -> 0 | BB22: =SUM(AX22:BA22) -> 0 | BG22: =SUM(BC22:BF22) -> 0 | BL22: =SUM(BH22:BK22) -> 0 | BQ22: =SUM(BM22:BP22) -> 0 | BV22: =SUM(BR22:BU22) -> 0 | CA22: =SUM(BW22:BZ22) -> 0 | CF22: =SUM(CB22:CE22) -> 0 | CK22: =SUM(CG22:CJ22) -> 0 | CL22: =-636-25+6869 -> 6208 | CM22: =2078-65-877-205-564 -> 367 | CN22: =-624-25-517 -> -1166 | CO22: =CP22-SUM(CL22:CN22) -> 2253 | CP22: =-159-301-2397+11396-877 -> 7662 | CQ22: =-555-32+626 -> 39 | CR22: =-1416-30+706-483 -> -1223 | CS22: =-643-28+491 -> -180 | CT22: =CU22-SUM(CQ22:CS22) -> -4756 | CU22: =-136-2283-6524+2823 -> -6120 | CV22: =49-620 -> -571 | CW22: =-1227-669 -> -1896 | CX22: =-504+178 -> -326 | CY22: =CZ22-SUM(CV22:CX22) -> 908 | CZ22: =1172-2592-465 -> -1885 | DA22: =-684+6081 -> 5397 | DB22: =692-735 -> -43 | DC22: =-710-673 -> -1383 | DD22: =DE22-SUM(DA22:DC22) -> 272 | DE22: =-2886+7129 -> 4243 | DF22: =-355-627+1109 -> 127 | DG22: =-75-667-63+2 -> -803 | DH22: =-74-714-251+1021 -> -18 | DI22: =-84-421+299+1 -> -205 | DK22: =+-51-701+302 -> -450 | DL22: =+-47-698+298-1 -> -448
B23: EBT | C23: =SUM(C19:C22) -> 0 | D23: =SUM(D19:D22) -> 0 | E23: =SUM(E19:E22) -> 0 | F23: =SUM(F19:F22) -> 0 | G23: =SUM(G19:G22) -> 0 | H23: =SUM(H19:H22) -> 0 | I23: =SUM(I19:I22) -> 0 | J23: =SUM(J19:J22) -> 0 | ... DI23: =SUM(DI19:DI22) -> 2293 | DK23: =SUM(DK19:DK22) -> 2245 | DL23: =SUM(DL19:DL22) -> 2389
B24: Income tax expense | N24: =SUM(J24:M24) -> 0 | S24: =SUM(O24:R24) -> 0 | X24: =SUM(T24:W24) -> 0 | AC24: =SUM(Y24:AB24) -> 0 | AH24: =SUM(AD24:AG24) -> 0 | AM24: =SUM(AI24:AL24) -> 0 | AR24: =SUM(AN24:AQ24) -> 0 | AW24: =SUM(AS24:AV24) -> 0 | BB24: =SUM(AX24:BA24) -> 0 | BG24: =SUM(BC24:BF24) -> 0 | BL24: =SUM(BH24:BK24) -> 0 | BQ24: =SUM(BM24:BP24) -> 0 | BV24: =SUM(BR24:BU24) -> 0 | CA24: =SUM(BW24:BZ24) -> 0 | CF24: =SUM(CB24:CE24) -> 0 | CK24: =SUM(CG24:CJ24) -> 0 | CL24: -54 | CM24: 160 | CN24: 483 | CO24: =CP24-SUM(CL24:CN24) -> -102 | CP24: 487 | CQ24: -142 | CR24: 466 | CS24: -2 | CT24: =CU24-SUM(CQ24:CS24) -> -36 | CU24: 286 | CV24: -29 | CW24: -161 | CX24: -13 | CY24: =CZ24-SUM(CV24:CX24) -> 206 | CZ24: 3 | DA24: -271 | DB24: -333 | DC24: -138 | DD24: =DE24-SUM(DA24:DC24) -> -420 | DE24: -1162 | DF24: -318 | DG24: -125 | DH24: -198 | DI24: -396 | DK24: -283 | DL24: =+-388-1 -> -389
B25: Net income, continuing ops. | C25: =SUM(C23:C24) -> 0 | D25: =SUM(D23:D24) -> 0 | E25: =SUM(E23:E24) -> 0 | F25: =SUM(F23:F24) -> 0 | G25: =SUM(G23:G24) -> 0 | H25: =SUM(H23:H24) -> 0 | I25: =SUM(I23:I24) -> 0 | J25: =SUM(J23:J24) -> 0 | ... DI25: =SUM(DI23:DI24) -> 1897 | DK25: =SUM(DK23:DK24) -> 1962 | DL25: =SUM(DL23:DL24) -> 2000
B26: Earnings (loss) from discontinued ops. | CL26: -21 | CM26: -993 | CN26: -58 | CO26: =CP26-SUM(CL26:CN26) -> 161 | CP26: -911 | CQ26: -2894 | CR26: -564 | CS26: 602 | CT26: =CU26-SUM(CQ26:CS26) -> -339 | CU26: -3195 | CV26: 101 | CW26: 264 | CX26: 409 | CY26: =CZ26-SUM(CV26:CX26) -> 428 | CZ26: 1202 | DA26: 1257 | DB26: -1019 | DC26: 173 | DD26: =DE26-SUM(DA26:DC26) -> 3 | DE26: 414 | DF26: 14 | DG26: -54 | DH26: 147 | DI26: -6 | DK26: 10 | DL26: 21
B27: Net income (loss) | CL27: =SUM(CL25:CL26) -> 6233 | CM27: =SUM(CM25:CM26) -> -2132 | CN27: =SUM(CN25:CN26) -> -1194 | CO27: =SUM(CO25:CO26) -> 2639 | CP27: =SUM(CP25:CP26) -> 5546 | CQ27: =SUM(CQ25:CQ26) -> -2798 | CR27: =SUM(CR25:CR26) -> -1134 | CS27: =SUM(CS25:CS26) -> 1184 | ... DO27: =SUM(DO25:DO26) -> 0 | DT27: =SUM(DT25:DT26) -> 0 | DU27: =SUM(DU25:DU26) -> 0 | DV27: =SUM(DV25:DV26) -> 0
B28: Net income (loss) attributable to noncontrolling interests | CL28: -34 | CM28: 145 | CN28: 51 | CO28: =CP28-SUM(CL28:CN28) -> -4 | CP28: 158 | CQ28: -5 | CR28: 3 | CS28: 73 | CT28: =CU28-SUM(CQ28:CS28) -> 0 | CU28: 71 | CV28: -28 | CW28: -19 | CX28: -4 | CY28: =CZ28-SUM(CV28:CX28) -> -16 | CZ28: -67 | DA28: 27 | DB28: -4 | DC28: 14 | DD28: =DE28-SUM(DA28:DC28) -> 0 | DE28: 37 | DF28: -27 | DG28: -2 | DH28: 10 | DI28: 8 | DK28: 5 | DL28: 7
B29: Net income attributable to the company | C29: =SUM(C25:C28) -> 0 | D29: =SUM(D25:D28) -> 0 | E29: =SUM(E25:E28) -> 0 | F29: =SUM(F25:F28) -> 0 | G29: =SUM(G25:G28) -> 0 | H29: =SUM(H25:H28) -> 0 | I29: =SUM(I25:I28) -> 0 | J29: =SUM(J25:J28) -> 0 | ... CK29: =SUM(CK25:CK28) -> 0 | CL29: =SUM(CL27:CL28) -> 6199 | CM29: =SUM(CM27:CM28) -> -1987 | CN29: =SUM(CN27:CN28) -> -1143 | CO29: =SUM(CO27:CO28) -> 2635 | CP29: =SUM(CP27:CP28) -> 5704 | CQ29: =SUM(CQ27:CQ28) -> -2803 | CR29: =SUM(CR27:CR28) -> -1131 | CS29: =SUM(CS27:CS28) -> 1257 | ... DI29: =SUM(DI27:DI28) -> 1899 | DK29: =SUM(DK27:DK28) -> 1977 | DL29: =SUM(DL27:DL28) -> 2028
B30: Preferred stock dividends | CL30: -43 | CM30: -192 | CN30: -46 | CO30: =CP30-SUM(CL30:CN30) -> -193 | CP30: -474 | CQ30: -72 | CR30: -57 | CS30: -52 | CT30: =CU30-SUM(CQ30:CS30) -> -56 | CU30: -237 | CV30: -52 | CW30: -67 | CX30: -73 | CY30: =CZ30-SUM(CV30:CX30) -> -97 | CZ30: -289 | DA30: -145 | DB30: -58 | DC30: -91 | DD30: =DE30-SUM(DA30:DC30) -> -1 | DE30: -295 | DF30: 0 | DG30: 0 | DH30: 0 | DI30: 0 | DK30: 0 | DL30: 0
B31: Net income (loss) attributable to Ticker0009 common shareholders | CL31: =SUM(CL29:CL30) -> 6156 | CM31: =SUM(CM29:CM30) -> -2179 | CN31: =SUM(CN29:CN30) -> -1189 | CO31: =SUM(CO29:CO30) -> 2442 | CP31: =SUM(CP29:CP30) -> 5230 | CQ31: =SUM(CQ29:CQ30) -> -2875 | CR31: =SUM(CR29:CR30) -> -1188 | CS31: =SUM(CS29:CS30) -> 1205 | ... DI31: =SUM(DI29:DI30) -> 1899 | DK31: =SUM(DK29:DK30) -> 1977 | DL31: =SUM(DL29:DL30) -> 2028
B32: Earnings (loss) from discontinued ops. attributable to Ticker0009 common shareholders | CL32: -21 | CM32: -993 | CN32: -58 | CO32: =CP32-SUM(CL32:CN32) -> 161 | CP32: -911 | CQ32: -2894 | CR32: -564 | CS32: 602 | CT32: =CU32-SUM(CQ32:CS32) -> -339 | CU32: -3195 | CV32: 88 | CW32: 252 | CX32: 403 | CY32: =CZ32-SUM(CV32:CX32) -> 408 | CZ32: 1151 | DA32: 1257 | DB32: -1019 | DC32: 173 | DD32: =DE32-SUM(DA32:DC32) -> 3 | DE32: 414 | DF32: 14 | DG32: -54 | DH32: 147 | DI32: -6 | DK32: -6 | DL32: 0
B33: Net income reported | CL33: =CL31-CL32 -> 6177 | CM33: =CM31-CM32 -> -1186 | CN33: =CN31-CN32 -> -1131 | CO33: =CP33-SUM(CL33:CN33) -> 2281 | CP33: =CP31-CP32 -> 6141 | CQ33: =CQ31-CQ32 -> 19 | CR33: =CR31-CR32 -> -624 | CS33: =CS31-CS32 -> 603 | CT33: =CU33-SUM(CQ33:CS33) -> -3560 | CU33: =CU31-CU32 -> -3562 | CV33: =CV31-CV32 -> -1276 | CW33: =CW31-CW32 -> -1199 | CX33: =CX31-CX32 -> -314 | CY33: =CZ33-SUM(CV33:CX33) -> 1687 | CZ33: =CZ31-CZ32 -> -1102 | DA33: =DA31-DA32 -> 6102 | DB33: =DB31-DB32 -> 994 | DC33: =DC31-DC32 -> 85 | DD33: =DE33-SUM(DA33:DC33) -> 1591 | DE33: =DE31-DE32 -> 8772 | DF33: =DF31-DF32 -> 1523 | DG33: =DG31-DG32 -> 1320 | DH33: =DH31-DH32 -> 1705 | DI33: =DI31-DI32 -> 1905 | DK33: =DK31-DK32 -> 1983 | DL33: =DL31-DL32 -> 2028
B35: Basic EPS, continuing ops. | C35: =C25/C44 -> #DIV/0! | D35: =D25/D44 -> #DIV/0! | E35: =E25/E44 -> #DIV/0! | F35: =F25/F44 -> #DIV/0! | G35: =G25/G44 -> #DIV/0! | H35: =H25/H44 -> #DIV/0! | I35: =I25/I44 -> #DIV/0! | J35: =J25/J44 -> #DIV/0! | ... M35: =M25/M44 -> #DIV/0! | O35: =O25/O44 -> #DIV/0! | P35: =P25/P44 -> #DIV/0! | Q35: =Q25/Q44 -> #DIV/0! | R35: =R25/R44 -> #DIV/0! | T35: =T25/T44 -> #DIV/0! | U35: =U25/U44 -> #DIV/0! | V35: =V25/V44 -> #DIV/0! | W35: =W25/W44 -> #DIV/0! | Y35: =Y25/Y44 -> #DIV/0! | Z35: =Z25/Z44 -> #DIV/0! | AA35: =AA25/AA44 -> #DIV/0! | AB35: =AB25/AB44 -> #DIV/0! | AD35: =AD25/AD44 -> #DIV/0! | AE35: =AE25/AE44 -> #DIV/0! | AF35: =AF25/AF44 -> #DIV/0! | AG35: =AG25/AG44 -> #DIV/0! | AI35: =AI25/AI44 -> #DIV/0! | AJ35: =AJ25/AJ44 -> #DIV/0! | AK35: =AK25/AK44 -> #DIV/0! | AL35: =AL25/AL44 -> #DIV/0! | AN35: =AN25/AN44 -> #DIV/0! | AO35: =AO25/AO44 -> #DIV/0! | AP35: =AP25/AP44 -> #DIV/0! | AQ35: =AQ25/AQ44 -> #DIV/0! | AS35: =AS25/AS44 -> #DIV/0! | AT35: =AT25/AT44 -> #DIV/0! | AU35: =AU25/AU44 -> #DIV/0! | AV35: =AV25/AV44 -> #DIV/0! | AX35: =AX25/AX44 -> #DIV/0! | AY35: =AY25/AY44 -> #DIV/0! | AZ35: =AZ25/AZ44 -> #DIV/0! | BA35: =BA25/BA44 -> #DIV/0! | BC35: =BC25/BC44 -> #DIV/0! | BD35: =BD25/BD44 -> #DIV/0! | BE35: =BE25/BE44 -> #DIV/0! | BF35: =BF25/BF44 -> #DIV/0! | BH35: =BH25/BH44 -> #DIV/0! | BI35: =BI25/BI44 -> #DIV/0! | BJ35: =BJ25/BJ44 -> #DIV/0! | BK35: =BK25/BK44 -> #DIV/0! | BM35: =BM25/BM44 -> #DIV/0! | BN35: =BN25/BN44 -> #DIV/0! | BO35: =BO25/BO44 -> #DIV/0! | BP35: =BP25/BP44 -> #DIV/0! | BR35: =BR25/BR44 -> #DIV/0! | BS35: =BS25/BS44 -> #DIV/0! | BT35: =BT25/BT44 -> #DIV/0! | BU35: =BU25/BU44 -> #DIV/0! | BW35: =BW25/BW44 -> #DIV/0! | BX35: =BX25/BX44 -> #DIV/0! | BY35: =BY25/BY44 -> #DIV/0! | BZ35: =BZ25/BZ44 -> #DIV/0! | CB35: =CB25/CB44 -> #DIV/0! | CC35: =CC25/CC44 -> #DIV/0! | CD35: =CD25/CD44 -> #DIV/0! | CE35: =CE25/CE44 -> #DIV/0! | CG35: =CG25/CG44 -> #DIV/0! | CH35: =CH25/CH44 -> #DIV/0! | CI35: =CI25/CI44 -> #DIV/0! | CJ35: =CJ25/CJ44 -> #DIV/0! | CL35: =CL31/CL44 -> 0.70229935 | CM35: =CM31/CM44 -> -0.24814085 | CN35: =CN31/CN44 -> -0.13573256 | CO35: =CO31/CO44 -> 2.2287395 | CP35: =CP31/CP44 -> 4.7732628 | CQ35: =CQ31/CQ44 -> -0.32749944 | CR35: =CR31/CR44 -> -0.13528744 | CS35: =CS31/CS44 -> 1.0973129 | ... CU35: =CU31/CU44 -> -6.1481644 | CV35: =(CV25+CV30)/CV44 -> -1.145671 | CW35: =(CW25+CW30)/CW44 -> -1.0870427 | CX35: =(CX25+CX30)/CX44 -> -0.28920034 | CY35: =(CY25+CY30)/CY44 -> 1.5453126 | CZ35: =(CZ25+CZ30)/CZ44 -> -0.99715361 | DA35: =(DA25+DA30)/DA44 -> 5.5787172 | DB35: =(DB25+DB30)/DB44 -> 0.91696067 | DC35: =(DC25+DC30)/DC44 -> 0.065234207 | ... DI35: =(DI25+DI30)/DI44 -> 1.7668006 | DK35: =(DK25+DK30)/DK44 -> 1.839858 | DL35: =(DL25+DL30)/DL44 -> 1.8860107
B36: Discontinued ops. & non recurring items | C36: =C28/C44 -> #DIV/0! | D36: =D28/D44 -> #DIV/0! | E36: =E28/E44 -> #DIV/0! | F36: =F28/F44 -> #DIV/0! | G36: =G28/G44 -> #DIV/0! | H36: =H28/H44 -> #DIV/0! | I36: =I28/I44 -> #DIV/0! | J36: =J28/J44 -> #DIV/0! | ... CU36: =CU28/CU44 -> 0.064602586 | CV36: =(CV28+CV26)/CV44 -> 0.066323542 | CW36: =(CW28+CW26)/CW44 -> 0.22342739 | CX36: =(CX28+CX26)/CX44 -> 0.37065234 | CY36: =(CY28+CY26)/CY44 -> 0.378294 | CZ36: =(CZ28+CZ26)/CZ44 -> 1.0421449 | DA36: =(DA28+DA26)/DA44 -> 1.1791066 | DB36: =(DB28+DB26)/DB44 -> -0.93993063 | DC36: =(DC28+DC26)/DC44 -> 0.17181404 | ... DI36: =(DI28+DI26)/DI44 -> 0.0018627313 | DK36: =(DK28+DK26)/DK44 -> 0.014066193 | DL36: =(DL28+DL26)/DL44 -> 0.026404149
B37: Basic EPS, reported | C37: =SUM(C35:C36) -> #DIV/0! | D37: =SUM(D35:D36) -> #DIV/0! | E37: =SUM(E35:E36) -> #DIV/0! | F37: =SUM(F35:F36) -> #DIV/0! | G37: =SUM(G35:G36) -> #DIV/0! | H37: =SUM(H35:H36) -> #DIV/0! | I37: =SUM(I35:I36) -> #DIV/0! | J37: =SUM(J35:J36) -> #DIV/0! | ... DI37: =SUM(DI35:DI36) -> 1.7686633 | DK37: =SUM(DK35:DK36) -> 1.8539242 | DL37: =SUM(DL35:DL36) -> 1.9124148
B39: Diluted EPS, continuing ops. | C39: =C25/C45 -> #DIV/0! | D39: =D25/D45 -> #DIV/0! | E39: =E25/E45 -> #DIV/0! | F39: =F25/F45 -> #DIV/0! | G39: =G25/G45 -> #DIV/0! | H39: =H25/H45 -> #DIV/0! | I39: =I25/I45 -> #DIV/0! | J39: =J25/J45 -> #DIV/0! | ... M39: =M25/M45 -> #DIV/0! | O39: =O25/O45 -> #DIV/0! | P39: =P25/P45 -> #DIV/0! | Q39: =Q25/Q45 -> #DIV/0! | R39: =R25/R45 -> #DIV/0! | T39: =T25/T45 -> #DIV/0! | U39: =U25/U45 -> #DIV/0! | V39: =V25/V45 -> #DIV/0! | W39: =W25/W45 -> #DIV/0! | Y39: =Y25/Y45 -> #DIV/0! | Z39: =Z25/Z45 -> #DIV/0! | AA39: =AA25/AA45 -> #DIV/0! | AB39: =AB25/AB45 -> #DIV/0! | AD39: =AD25/AD45 -> #DIV/0! | AE39: =AE25/AE45 -> #DIV/0! | AF39: =AF25/AF45 -> #DIV/0! | AG39: =AG25/AG45 -> #DIV/0! | AI39: =AI25/AI45 -> #DIV/0! | AJ39: =AJ25/AJ45 -> #DIV/0! | AK39: =AK25/AK45 -> #DIV/0! | AL39: =AL25/AL45 -> #DIV/0! | AN39: =AN25/AN45 -> #DIV/0! | AO39: =AO25/AO45 -> #DIV/0! | AP39: =AP25/AP45 -> #DIV/0! | AQ39: =AQ25/AQ45 -> #DIV/0! | AS39: =AS25/AS45 -> #DIV/0! | AT39: =AT25/AT45 -> #DIV/0! | AU39: =AU25/AU45 -> #DIV/0! | AV39: =AV25/AV45 -> #DIV/0! | AX39: =AX25/AX45 -> #DIV/0! | AY39: =AY25/AY45 -> #DIV/0! | AZ39: =AZ25/AZ45 -> #DIV/0! | BA39: =BA25/BA45 -> #DIV/0! | BC39: =BC25/BC45 -> #DIV/0! | BD39: =BD25/BD45 -> #DIV/0! | BE39: =BE25/BE45 -> #DIV/0! | BF39: =BF25/BF45 -> #DIV/0! | BH39: =BH25/BH45 -> #DIV/0! | BI39: =BI25/BI45 -> #DIV/0! | BJ39: =BJ25/BJ45 -> #DIV/0! | BK39: =BK25/BK45 -> #DIV/0! | BM39: =BM25/BM45 -> #DIV/0! | BN39: =BN25/BN45 -> #DIV/0! | BO39: =BO25/BO45 -> #DIV/0! | BP39: =BP25/BP45 -> #DIV/0! | BR39: =BR25/BR45 -> #DIV/0! | BS39: =BS25/BS45 -> #DIV/0! | BT39: =BT25/BT45 -> #DIV/0! | BU39: =BU25/BU45 -> #DIV/0! | BW39: =BW25/BW45 -> #DIV/0! | BX39: =BX25/BX45 -> #DIV/0! | BY39: =BY25/BY45 -> #DIV/0! | BZ39: =BZ25/BZ45 -> #DIV/0! | CB39: =CB25/CB45 -> #DIV/0! | CC39: =CC25/CC45 -> #DIV/0! | CD39: =CD25/CD45 -> #DIV/0! | CE39: =CE25/CE45 -> #DIV/0! | CG39: =CG25/CG45 -> #DIV/0! | CH39: =CH25/CH45 -> #DIV/0! | CI39: =CI25/CI45 -> #DIV/0! | CJ39: =CJ25/CJ45 -> #DIV/0! | CL39: =CL31/CL45 -> 0.70229935 | CM39: =CM31/CM45 -> -0.24814085 | CN39: =CN31/CN45 -> -0.13573256 | CO39: =CO31/CO45 -> 2.2287395 | CP39: =CP31/CP45 -> 4.7732628 | CQ39: =CQ31/CQ45 -> -0.32749944 | CR39: =CR31/CR45 -> -0.13528744 | CS39: =CS31/CS45 -> 1.0973129 | ... CU39: =CU31/CU45 -> -6.1481644 | CV39: =(CV25+CV30)/CV45 -> -1.145671 | CW39: =(CW25+CW30)/CW45 -> -1.0870427 | CX39: =(CX25+CX30)/CX45 -> -0.28920034 | CY39: =(CY25+CY30)/CY45 -> 1.5453126 | CZ39: =(CZ25+CZ30)/CZ45 -> -0.99715361 | DA39: =(DA25+DA30)/DA45 -> 5.5787172 | DB39: =(DB25+DB30)/DB45 -> 0.91696067 | DC39: =(DC25+DC30)/DC45 -> 0.065234207 | ... DI39: =(DI25+DI30)/DI45 -> 1.7504971 | DK39: =(DK25+DK30)/DK45 -> 1.839858 | DL39: =(DL25+DL30)/DL45 -> 1.8860107
B40: Discontinued ops. & non recurring items | C40: =C28/C45 -> #DIV/0! | D40: =D28/D45 -> #DIV/0! | E40: =E28/E45 -> #DIV/0! | F40: =F28/F45 -> #DIV/0! | G40: =G28/G45 -> #DIV/0! | H40: =H28/H45 -> #DIV/0! | I40: =I28/I45 -> #DIV/0! | J40: =J28/J45 -> #DIV/0! | ... CU40: =CU28/CU45 -> 0.064602586 | CV40: =(CV26+CV28)/CV45 -> 0.066323542 | CW40: =(CW26+CW28)/CW45 -> 0.22342739 | CX40: =(CX26+CX28)/CX45 -> 0.37065234 | CY40: =(CY26+CY28)/CY45 -> 0.378294 | CZ40: =(CZ26+CZ28)/CZ45 -> 1.0421449 | DA40: =(DA26+DA28)/DA45 -> 1.1791066 | DB40: =(DB26+DB28)/DB45 -> -0.93993063 | DC40: =(DC26+DC28)/DC45 -> 0.17181404 | ... DI40: =(DI26+DI28)/DI45 -> 0.0018455425 | DK40: =(DK26+DK28)/DK45 -> 0.014066193 | DL40: =(DL26+DL28)/DL45 -> 0.026404149
B41: Diluted EPS, reported | C41: =SUM(C39:C40) -> #DIV/0! | D41: =SUM(D39:D40) -> #DIV/0! | E41: =SUM(E39:E40) -> #DIV/0! | F41: =SUM(F39:F40) -> #DIV/0! | G41: =SUM(G39:G40) -> #DIV/0! | H41: =SUM(H39:H40) -> #DIV/0! | I41: =SUM(I39:I40) -> #DIV/0! | J41: =SUM(J39:J40) -> #DIV/0! | ... DI41: =SUM(DI39:DI40) -> 1.7523426 | DK41: =SUM(DK39:DK40) -> 1.8539242 | DL41: =SUM(DL39:DL40) -> 1.9124148
B43: Common shares outstanding
B44: Basic | N44: =N29/N35 -> #DIV/0! | S44: =S29/S35 -> #DIV/0! | X44: =X29/X35 -> #DIV/0! | AC44: =AC29/AC35 -> #DIV/0! | AH44: =AH29/AH35 -> #DIV/0! | AM44: =AM29/AM35 -> #DIV/0! | AR44: =AR29/AR35 -> #DIV/0! | AW44: =AW29/AW35 -> #DIV/0! | BB44: =BB29/BB35 -> #DIV/0! | BG44: =BG29/BG35 -> #DIV/0! | BL44: =BL29/BL35 -> #DIV/0! | BQ44: =BQ29/BQ35 -> #DIV/0! | BV44: =BV29/BV35 -> #DIV/0! | CA44: =CA29/CA35 -> #DIV/0! | CF44: =CF29/CF35 -> #DIV/0! | CK44: =CK29/CK35 -> #DIV/0! | CL44: 8765.493 | CM44: 8781.303 | CN44: =8759.873 -> 8759.873 | CO44: 1095.6866 | CP44: 1095.6866 | CQ44: 8778.641 | CR44: 8781.303 | CS44: 1098.1371 | CT44: 1099.0272 | CU44: 1099.0272 | CV44: 1100.665 | CW44: 1096.5531 | CX44: 1092.6681 | CY44: =CZ44 -> 1089.1 | CZ44: 1089.1 | DA44: 1088.96 | DB44: 1088.3782 | DC44: 1088.386 | DD44: =DE44 -> 1088.416 | DE44: 1088.416 | DF44: 1091 | DG44: 1089 | DH44: 1083 | DI44: 1073.6922 | DK44: 1066.3866 | DL44: 1060.4394
B45: Diluted | N45: =N29/N39 -> #DIV/0! | S45: =S29/S39 -> #DIV/0! | X45: =X29/X39 -> #DIV/0! | AC45: =AC29/AC39 -> #DIV/0! | AH45: =AH29/AH39 -> #DIV/0! | AM45: =AM29/AM39 -> #DIV/0! | AR45: =AR29/AR39 -> #DIV/0! | AW45: =AW29/AW39 -> #DIV/0! | BB45: =BB29/BB39 -> #DIV/0! | BG45: =BG29/BG39 -> #DIV/0! | BL45: =BL29/BL39 -> #DIV/0! | BQ45: =BQ29/BQ39 -> #DIV/0! | BV45: =BV29/BV39 -> #DIV/0! | CA45: =CA29/CA39 -> #DIV/0! | CF45: =CF29/CF39 -> #DIV/0! | CK45: =CK29/CK39 -> #DIV/0! | CL45: 8765.493 | CM45: 8781.303 | CN45: 8759.873 | CO45: 1095.6866 | CP45: 1095.6866 | CQ45: 8778.641 | CR45: 8781.303 | CS45: 1098.1371 | CT45: 1099.0272 | CU45: 1099.0272 | CV45: 1100.665 | CW45: 1096.5531 | CX45: 1092.6681 | CY45: =CZ45 -> 1089.1 | CZ45: 1089.1 | DA45: 1088.96 | DB45: 1088.3782 | DC45: 1088.386 | DD45: =DE45 -> 1088.416 | DE45: 1088.416 | DF45: 1103 | DG45: 1100 | DH45: 1093 | DI45: =+DI44+10 -> 1083.6922 | DK45: =+DK44 -> 1066.3866 | DL45: 1060.4394
B47: Check | C47: =IF(ROUND(C25/C44,2)=ROUND(C35,2),"","check") -> #DIV/0! | D47: =IF(ROUND(D25/D44,2)=ROUND(D35,2),"","check") -> #DIV/0! | E47: =IF(ROUND(E25/E44,2)=ROUND(E35,2),"","check") -> #DIV/0! | F47: =IF(ROUND(F25/F44,2)=ROUND(F35,2),"","check") -> #DIV/0! | G47: =IF(ROUND(G25/G44,2)=ROUND(G35,2),"","check") -> #DIV/0! | H47: =IF(ROUND(H25/H44,2)=ROUND(H35,2),"","check") -> #DIV/0! | I47: =IF(ROUND(I25/I44,2)=ROUND(I35,2),"","check") -> #DIV/0! | J47: =IF(ROUND(J25/J44,2)=ROUND(J35,2),"","check") -> #DIV/0! | ... AK47: =IF(ROUND(AK25/AK44,2)=ROUND(AK35,2),"","check") -> #DIV/0!
B49: Balance Sheet
B50: Assets
B51: Cash, Cash Equivalents, and restricted cash | CO51: 36530 | CP51: =CO51 -> 36530 | CQ51: 31783 | CR51: 22460 | CS51: 24955 | CT51: 15770 | CU51: =CT51 -> 15770 | CV51: 12842 | CW51: 13190 | CX51: 12595 | CY51: 15810 | CZ51: =CY51 -> 15810 | DA51: 12001 | DB51: 12766 | DC51: 13127 | DD51: 16967 | DE51: =DD51 -> 16967 | DF51: 18447 | DG51: 12107 | DH51: 13724 | DI51: 13619 | DJ51: =DI51 -> 13619 | DK51: 12405 | DL51: 10861
B52: Investment securities | CO52: 7319 | CP52: =CO52 -> 7319 | CQ52: 6741 | CR52: 6134 | CS52: 5300 | CT52: 12297 | CU52: =CT52 -> 12297 | CV52: 10779 | CW52: 6745 | CX52: 6297 | CY52: 7609 | CZ52: =CY52 -> 7609 | DA52: 12814 | DB52: 10885 | DC52: 7054 | DD52: 5706 | DE52: =DD52 -> 5706 | DF52: 3737 | DG52: 3338 | DH52: 2232 | DI52: 982 | DJ52: =DI52 -> 982 | DK52: 1000 | DL52: 998
B53: Current Receivables | CO53: 16691 | CP53: =CO53 -> 16691 | CQ53: 15381 | CR53: 15190 | CS53: 14874 | CT53: 15620 | CU53: =CT53 -> 15620 | CV53: 16050 | CW53: 16283 | CX53: 17197 | CY53: 14831 | CZ53: =CY53 -> 14831 | DA53: 14212 | DB53: 14767 | DC53: 14546 | DD53: 15466 | DE53: =DD53 -> 15466 | DF53: 15100 | DG53: 8370 | DH53: 8936 | DI53: 9327 | DJ53: =DI53 -> 9327 | DK53: 9653 | DL53: 10512
B54: Financing Receivables, net | CO54: 326 | CP54: =CO54 -> 326 | CQ54: 306 | CR54: 316 | CS54: 271 | CT54: 0 | CU54: =CT54 -> 0 | CV54: 0 | CW54: 0 | CX54: 0 | CY54: 0 | CZ54: =CY54 -> 0 | DE54: =DD54 -> 0 | DJ54: =DI54 -> 0
B55: Inventories, including deferred inventory costs | CO55: 15890 | CP55: =CO55 -> 15890 | CQ55: 16530 | CR55: 17016 | CS55: 16790 | CT55: 15847 | CU55: =CT55 -> 15847 | CV55: 16570 | CW55: 17553 | CX55: 17536 | CY55: 14891 | CZ55: =CY55 -> 14891 | DA55: 16198 | DB55: 16789 | DC55: 17020 | DD55: 16528 | DE55: =DD55 -> 16528 | DF55: 17603 | DG55: 9469 | DH55: 9718 | DI55: 9763 | DJ55: =DI55 -> 9763 | DK55: 10504 | DL55: 11297
B56: Current Contract assets | CO56: 5764 | CP56: =CO56 -> 5764 | CQ56: 5821 | CR56: 5431 | CS56: 5238 | CT56: 4881 | CU56: =CT56 -> 4881 | CV56: 4246 | CW56: 4241 | CX56: 3701 | CY56: 2468 | CZ56: =CY56 -> 2468 | DA56: 2244 | DB56: 2037 | DC56: 1875 | DD56: 1500 | DE56: =DD56 -> 1500 | DF56: 1547 | DG56: 2719 | DH56: 2884 | DI56: 2982 | DJ56: =DI56 -> 2982 | DK56: 2940 | DL56: 3059
B57: All other Current assets | CO57: =1109+1549 -> 2658 | CP57: =CO57 -> 2658 | CQ57: =1339+1376 -> 2715 | CR57: =1363+1315 -> 2678 | CS57: =1186+1191 -> 2377 | CT57: 1933 | CU57: =CT57 -> 1933 | CV57: 2065 | CW57: 1879 | CX57: 2059 | CY57: 1400 | CZ57: =CY57 -> 1400 | DA57: 1464 | DB57: 1638 | DC57: 1438 | DD57: 1647 | DE57: =DD57 -> 1647 | DF57: 1650 | DG57: =1210+2 -> 1212 | DH57: 1156 | DI57: 962 | DJ57: =DI57 -> 962 | DK57: 1073 | DL57: =1073+1 -> 1074
B58: Assets of discontinued ops. / held for sale | CO58: 0 | CP58: =CO58 -> 0 | CQ58: 33922 | CR58: 33186 | CS58: 33782 | CT58: 0 | CU58: =CT58 -> 0 | CV58: 747 | CW58: 767 | CX58: 696 | CY58: 1374 | CZ58: =CY58 -> 1374 | DA58: 1353 | DB58: 1331 | DC58: 1375 | DD58: 1985 | DE58: =DD58 -> 1985 | DF58: 1507 | DG58: 137 | DJ58: =DI58 -> 0
B59: Total Current Assets | C59: =SUM(C51:C58) -> 0 | D59: =SUM(D51:D58) -> 0 | E59: =SUM(E51:E58) -> 0 | F59: =SUM(F51:F58) -> 0 | G59: =SUM(G51:G58) -> 0 | H59: =SUM(H51:H58) -> 0 | I59: =SUM(I51:I58) -> 0 | J59: =SUM(J51:J58) -> 0 | ... L59: =SUM(L51:L58) -> 0 | M59: =N59 -> 0 | N59: =SUM(N51:N58) -> 0 | O59: =SUM(O51:O58) -> 0 | P59: =SUM(P51:P58) -> 0 | Q59: =SUM(Q51:Q58) -> 0 | R59: =S59 -> 0 | S59: =SUM(S51:S58) -> 0 | T59: =SUM(T51:T58) -> 0 | U59: =SUM(U51:U58) -> 0 | V59: =SUM(V51:V58) -> 0 | W59: =X59 -> 0 | X59: =SUM(X51:X58) -> 0 | Y59: =SUM(Y51:Y58) -> 0 | Z59: =SUM(Z51:Z58) -> 0 | AA59: =SUM(AA51:AA58) -> 0 | AB59: =AC59 -> 0 | AC59: =SUM(AC51:AC58) -> 0 | AD59: =SUM(AD51:AD58) -> 0 | AE59: =SUM(AE51:AE58) -> 0 | AF59: =SUM(AF51:AF58) -> 0 | AG59: =AH59 -> 0 | AH59: =SUM(AH51:AH58) -> 0 | AI59: =SUM(AI51:AI58) -> 0 | AJ59: =SUM(AJ51:AJ58) -> 0 | AK59: =SUM(AK51:AK58) -> 0 | AL59: =SUM(AL51:AL58) -> 0 | AM59: =SUM(AM51:AM58) -> 0 | AN59: =SUM(AN51:AN58) -> 0 | AO59: =SUM(AO51:AO58) -> 0 | ... CO59: =SUM(CO51:CO58) -> 85178 | CP59: =CO59 -> 85178 | CQ59: =SUM(CQ51:CQ58) -> 113199 | CR59: =SUM(CR51:CR58) -> 102411 | CS59: =SUM(CS51:CS58) -> 103587 | CT59: =SUM(CT51:CT58) -> 66348 | CU59: =CT59 -> 66348 | CV59: =SUM(CV51:CV58) -> 63299 | CW59: =SUM(CW51:CW58) -> 60658 | CX59: =SUM(CX51:CX58) -> 60081 | CY59: =SUM(CY51:CY58) -> 58383 | CZ59: =CY59 -> 58383 | DA59: =SUM(DA51:DA58) -> 60286 | DB59: =SUM(DB51:DB58) -> 60213 | DC59: =SUM(DC51:DC58) -> 56435 | DD59: =SUM(DD51:DD58) -> 59799 | DE59: =DD59 -> 59799 | DF59: =SUM(DF51:DF58) -> 59591 | DG59: =SUM(DG51:DG58) -> 37352 | DH59: =SUM(DH51:DH58) -> 38650 | DI59: =SUM(DI51:DI58) -> 37635 | DJ59: =DI59 -> 37635 | DK59: =SUM(DK51:DK58) -> 37575 | DL59: =SUM(DL51:DL58) -> 37801
B60: Investment securities | CO60: 42549 | CP60: =CO60 -> 42549 | CQ60: 40786 | CR60: 42665 | CS60: 42394 | CT60: 42209 | CU60: =CT60 -> 42209 | CV60: 39845 | CW60: 36195 | CX60: 33624 | CY60: 36027 | CZ60: =CY60 -> 36027 | DA60: 38262 | DB60: 37392 | DC60: 35528 | DD60: 38000 | DE60: =DD60 -> 38000 | DF60: 38705 | DG60: 38129 | DH60: 39514 | DI60: 37741 | DJ60: =DI60 -> 37741 | DK60: 38010 | DL60: 37887
B61: Property, Plant and Equipment, Net | CO61: 16699 | CP61: =CO61 -> 16699 | CQ61: 16296 | CR61: 16169 | CS61: 15873 | CT61: 15609 | CU61: =CT61 -> 15609 | CV61: 15036 | CW61: 14790 | CX61: 14295 | CY61: 12192 | CZ61: =CY61 -> 12192 | DA61: 12170 | DB61: 12374 | DC61: 12203 | DD61: 12494 | DE61: =DD61 -> 12494 | DF61: 12345 | DG61: 7095 | DH61: 7254 | DI61: 7277 | DJ61: =DI61 -> 7277 | DK61: 7426 | DL61: 7523
B62: Goodwill | CO62: 25524 | CP62: =CO62 -> 25524 | CQ62: 25320 | CR62: 25491 | CS62: 25333 | CT62: 26182 | CU62: =CT62 -> 26182 | CV62: 26047 | CW62: 25790 | CX62: 25275 | CY62: 12999 | CZ62: =CY62 -> 12999 | DA62: 13107 | DB62: 13345 | DC62: 13177 | DD62: 13385 | DE62: =DD62 -> 13385 | DF62: 13304 | DG62: 8859 | DH62: 8754 | DI62: 8538 | DJ62: =DI62 -> 8538 | DK62: 8696 | DL62: 9006
B63: Other Intangible assets, Net | CO63: 9671 | CP63: =CO63 -> 9671 | CQ63: 9395 | CR63: 9460 | CS63: 9187 | CT63: 9330 | CU63: =CT63 -> 9330 | CV63: 8290 | CW63: 8026 | CX63: 7725 | CY63: 6105 | CZ63: =CY63 -> 6105 | DA63: 5990 | DB63: 5954 | DC63: 5790 | DD63: 5695 | DE63: =DD63 -> 5695 | DF63: 5547 | DG63: 4394 | DH63: 4371 | DI63: 4257 | DJ63: =DI63 -> 4257 | DK63: 4277 | DL63: 4336
B64: Contract and other deferred assets | CO64: 5888 | CP64: =CO64 -> 5888 | CQ64: 5985 | CR64: 6131 | CS64: 6119 | CT64: 6124 | CU64: =CT64 -> 6124 | CV64: 6159 | CW64: 6189 | CX64: 6221 | CY64: 5776 | CZ64: =CY64 -> 5776 | DA64: 5631 | DB64: 5440 | DC64: 5427 | DD64: 5406 | DE64: =DD64 -> 5406 | DF64: 5431 | DG64: 4801 | DH64: 4823 | DI64: 4831 | DJ64: =DI64 -> 4831 | DK64: 4835 | DL64: 4803
B65: All other assets | CO65: =11038+4661+1 -> 15700 | CP65: =CO65 -> 15700 | CQ65: =12308+4634 -> 16942 | CR65: =12640+4672-1 -> 17311 | CS65: =12651+4668 -> 17319 | CT65: 19040 | CU65: =CT65 -> 19040 | CV65: 19767 | CW65: 19737 | CX65: 19167 | CY65: 15477 | CZ65: =CY65 -> 15477 | DA65: 15888 | DB65: 16172 | DC65: 16307 | DD65: 15997 | DE65: =DD65 -> 15997 | DF65: 16995 | DG65: 13405 | DH65: 13836 | DI65: 13910 | DJ65: =DI65 -> 13910 | DK65: 14453 | DL65: 15002
B66: Deferred Income Taxes | CO66: 14253 | CP66: =CO66 -> 14253 | CQ66: 14232 | CR66: 14864 | CS66: 14466 | CT66: 10855 | CU66: =CT66 -> 10855 | CV66: 10583 | CW66: 10956 | CX66: 11504 | CY66: 10001 | CZ66: =CY66 -> 10001 | DA66: 10344 | DB66: 10354 | DC66: 10235 | DD66: 10575 | DE66: =DD66 -> 10575 | DF66: 10316 | DG66: 7338 | DH66: 7491 | DI66: 7111 | DJ66: =DI66 -> 7111 | DK66: 6956 | DL66: 6890
B67: Assets of discontinued ops. | CO67: 40749 | CP67: =CO67 -> 40749 | CQ67: 3009 | CR67: 3057 | CS67: 2855 | CT67: 3177 | CU67: =CT67 -> 3177 | CV67: 2935 | CW67: 3199 | CX67: 2985 | CY67: 31891 | CZ67: =CY67 -> 31891 | DA67: 2794 | DB67: 1762 | DC67: 1560 | DD67: 1694 | DE67: =DD67 -> 1694 | DF67: 1708 | DG67: 1817 | DH67: 2006 | DI67: =1841-1 -> 1840 | DJ67: =DI67 -> 1840 | DK67: 1895 | DL67: =2007+1 -> 2008
B68: Total Assets | C68: =SUM(C59:C66) -> 0 | D68: =SUM(D59:D66) -> 0 | E68: =SUM(E59:E66) -> 0 | F68: =SUM(F59:F66) -> 0 | G68: =SUM(G59:G66) -> 0 | H68: =SUM(H59:H66) -> 0 | I68: =SUM(I59:I66) -> 0 | J68: =SUM(J59:J66) -> 0 | ... L68: =SUM(L59:L66) -> 0 | M68: =N68 -> 0 | N68: =SUM(N59:N66) -> 0 | O68: =SUM(O59:O66) -> 0 | P68: =SUM(P59:P66) -> 0 | Q68: =SUM(Q59:Q66) -> 0 | R68: =S68 -> 0 | S68: =SUM(S59:S66) -> 0 | T68: =SUM(T59:T66) -> 0 | U68: =SUM(U59:U66) -> 0 | V68: =SUM(V59:V66) -> 0 | W68: =X68 -> 0 | X68: =SUM(X59:X66) -> 0 | Y68: =SUM(Y59:Y66) -> 0 | Z68: =SUM(Z59:Z66) -> 0 | AA68: =SUM(AA59:AA66) -> 0 | AB68: =AC68 -> 0 | AC68: =SUM(AC59:AC66) -> 0 | AD68: =SUM(AD59:AD66) -> 0 | AE68: =SUM(AE59:AE66) -> 0 | AF68: =SUM(AF59:AF66) -> 0 | AG68: =AH68 -> 0 | AH68: =SUM(AH59:AH66) -> 0 | AI68: =SUM(AI59:AI66) -> 0 | AJ68: =SUM(AJ59:AJ66) -> 0 | AK68: =SUM(AK59:AK66) -> 0 | AL68: =SUM(AL59:AL66) -> 0 | AM68: =SUM(AM59:AM66) -> 0 | AN68: =SUM(AN59:AN66) -> 0 | AO68: =SUM(AO59:AO66) -> 0 | ... CK68: =SUM(CK59:CK66) -> 0 | CL68: =SUM(CL59:CL67) -> 0 | CM68: =SUM(CM59:CM66) -> 0 | CN68: =SUM(CN59:CN66) -> 0 | CO68: =SUM(CO59:CO67) -> 256211 | CP68: =CO68 -> 256211 | CQ68: =SUM(CQ59:CQ67) -> 245164 | CR68: =SUM(CR59:CR67) -> 237559 | CS68: =SUM(CS59:CS67) -> 237133 | CT68: =SUM(CT59:CT67) -> 198874 | CU68: =CT68 -> 198874 | CV68: =SUM(CV59:CV67) -> 191961 | CW68: =SUM(CW59:CW67) -> 185540 | CX68: =SUM(CX59:CX67) -> 180877 | CY68: =SUM(CY59:CY67) -> 188851 | CZ68: =CY68 -> 188851 | DA68: =SUM(DA59:DA67) -> 164472 | DB68: =SUM(DB59:DB67) -> 163006 | DC68: =SUM(DC59:DC67) -> 156662 | DD68: =SUM(DD59:DD67) -> 163045 | DE68: =DD68 -> 163045 | DF68: =SUM(DF59:DF67) -> 163942 | DG68: =SUM(DG59:DG67) -> 123190 | DH68: =SUM(DH59:DH67) -> 126699 | DI68: =SUM(DI59:DI67) -> 123140 | DJ68: =DI68 -> 123140 | DK68: =SUM(DK59:DK67) -> 124123 | DL68: =SUM(DL59:DL67) -> 125256
B70: Liabilities and Stockholders' Equity
B71: Short-term borrowings | CO71: 4713 | CP71: =CO71 -> 4713 | CQ71: 4468 | CR71: 4293 | CS71: 5459 | CT71: 4361 | CU71: =CT71 -> 4361 | CV71: 4985 | CW71: 4947 | CX71: 4285 | CY71: 3739 | CZ71: =CY71 -> 3739 | DA71: 2262 | DB71: 1882 | DC71: 1334 | DD71: 1253 | DE71: =DD71 -> 1253 | DF71: 1032 | DG71: 1700 | DH71: 1681 | DI71: 2039 | DJ71: =DI71 -> 2039 | DK71: 2084 | DL71: 1889
B72: Accounts Payable and equipment project accruals | CO72: 16458 | CP72: =CO72 -> 16458 | CQ72: 16090 | CR72: 16653 | CS72: 16172 | CT72: 16243 | CU72: =CT72 -> 16243 | CV72: 16206 | CW72: 17030 | CX72: 17331 | CY72: 15399 | CZ72: =CY72 -> 15399 | DA72: 15063 | DB72: 15515 | DC72: 15785 | DD72: 15408 | DE72: =DD72 -> 15408 | DF72: 15184 | DG72: 7707 | DH72: 7829 | DI72: 7909 | DJ72: =DI72 -> 7909 | DK72: 8625 | DL72: 9495
B73: Progress collections and deferred income | CO73: 18371 | CP73: =CO73 -> 18371 | CQ73: 17993 | CR73: 17201 | CS73: 16909 | CT73: 17372 | CU73: =CT73 -> 17372 | CV73: 16206 | CW73: 16360 | CX73: 16445 | CY73: 16216 | CZ73: =CY73 -> 16216 | DA73: 16586 | DB73: 17142 | DC73: 17185 | DD73: 19677 | DE73: =DD73 -> 19677 | DF73: 20718 | DG73: 6465 | DH73: 6477 | DI73: 6695 | DJ73: =DI73 -> 6695 | DK73: 6842 | DL73: 7026
B74: All other current liabilities | CO74: 15071 | CP74: =CO74 -> 15071 | CQ74: 14139 | CR74: =13569+1 -> 13570 | CS74: =14349-1 -> 14348 | CT74: 13977 | CU74: =CT74 -> 13977 | CV74: 14216 | CW74: 13909 | CX74: 15094 | CY74: 12130 | CZ74: =CY74 -> 12130 | DA74: 12313 | DB74: 11620 | DC74: 12026 | DD74: 12712 | DE74: =DD74 -> 12712 | DF74: 12342 | DG74: =8671+3639+4506+1 -> 16817 | DH74: =9047+4073+4986 -> 18106 | DI74: =9353+3475+4920+1 -> 17749 | DJ74: =DI74 -> 17749 | DK74: =9624+3555+4211 -> 17390 | DL74: =9738+3923+4395 -> 18056
B75: Liabilities of discontinued ops. / held for sale | CO75: 0 | CP75: =CO75 -> 0 | CQ75: 4991 | CR75: 4922 | CS75: 4788 | CT75: 0 | CU75: =CT75 -> 0 | CV75: 1732 | CW75: 1638 | CX75: 1503 | CY75: 1944 | CZ75: =CY75 -> 1944 | DA75: 1953 | DB75: 1949 | DC75: 1835 | DD75: 1826 | DE75: =DD75 -> 1826 | DF75: 1811 | DG75: 61 | DH75: 0 | DJ75: =DI75 -> 0
B76: Total Current Liabilities | C76: =SUM(C72:C75) -> 0 | D76: =SUM(D72:D75) -> 0 | E76: =SUM(E72:E75) -> 0 | F76: =SUM(F72:F75) -> 0 | G76: =SUM(G72:G75) -> 0 | H76: =SUM(H72:H75) -> 0 | I76: =SUM(I72:I75) -> 0 | J76: =SUM(J72:J75) -> 0 | ... L76: =SUM(L72:L75) -> 0 | M76: =N76 -> 0 | N76: =SUM(N72:N75) -> 0 | O76: =SUM(O72:O75) -> 0 | P76: =SUM(P72:P75) -> 0 | Q76: =SUM(Q72:Q75) -> 0 | R76: =S76 -> 0 | S76: =SUM(S72:S75) -> 0 | T76: =SUM(T72:T75) -> 0 | U76: =SUM(U72:U75) -> 0 | V76: =SUM(V72:V75) -> 0 | W76: =X76 -> 0 | X76: =SUM(X72:X75) -> 0 | Y76: =SUM(Y72:Y75) -> 0 | Z76: =SUM(Z72:Z75) -> 0 | AA76: =SUM(AA72:AA75) -> 0 | AB76: =AC76 -> 0 | AC76: =SUM(AC72:AC75) -> 0 | AD76: =SUM(AD72:AD75) -> 0 | AE76: =SUM(AE72:AE75) -> 0 | AF76: =SUM(AF72:AF75) -> 0 | AG76: =AH76 -> 0 | AH76: =SUM(AH72:AH75) -> 0 | AI76: =SUM(AI72:AI75) -> 0 | AJ76: =SUM(AJ72:AJ75) -> 0 | AK76: =SUM(AK72:AK75) -> 0 | AL76: =SUM(AL72:AL75) -> 0 | AM76: =SUM(AM72:AM75) -> 0 | AN76: =SUM(AN72:AN75) -> 0 | AO76: =SUM(AO72:AO75) -> 0 | ... CK76: =SUM(CK72:CK75) -> 0 | CL76: =SUM(CL71:CL75) -> 0 | CM76: =SUM(CM72:CM75) -> 0 | CN76: =SUM(CN72:CN75) -> 0 | CO76: =SUM(CO71:CO75) -> 54613 | CP76: =SUM(CP71:CP75) -> 54613 | CQ76: =SUM(CQ71:CQ75) -> 57681 | CR76: =SUM(CR71:CR75) -> 56639 | CS76: =SUM(CS71:CS75) -> 57676 | CT76: =SUM(CT71:CT75) -> 51953 | CU76: =SUM(CU71:CU75) -> 51953 | CV76: =SUM(CV71:CV75) -> 53345 | ... DL76: =SUM(DL71:DL75) -> 36466
B77: Deferred income | CO77: 1801 | CP77: =CO77 -> 1801 | CQ77: 1748 | CR77: 1779 | CS77: 1839 | CT77: 1989 | CU77: =CT77 -> 1989 | CV77: 1953 | CW77: 1916 | CX77: 1842 | CY77: 1409 | CZ77: =CY77 -> 1409 | DA77: 1500 | DB77: 1384 | DC77: 1337 | DD77: 1339 | DE77: =DD77 -> 1339 | DF77: 1297 | DG77: 960 | DH77: 972 | DI77: 1013 | DJ77: =DI77 -> 1013 | DK77: 1054 | DL77: 1040
B78: Long-term borrowings | CO78: 70189 | CP78: =CO78 -> 70189 | CQ78: 66890 | CR78: 59231 | CS78: 57429 | CT78: 30824 | CU78: =CT78 -> 30824 | CV78: 28649 | CW78: 27571 | CX78: 26121 | CY78: 20320 | CZ78: =CY78 -> 20320 | DA78: 20159 | DB78: 19900 | DC78: 19488 | DD78: 19711 | DE78: =DD78 -> 19711 | DF78: 19493 | DG78: 17973 | DH78: 18240 | DI78: 17234 | DJ78: =DI78 -> 17234 | DK78: 17487 | DL78: 16998
B79: Insurance liabilities and annuity benefits | CO79: 42191 | CP79: =CO79 -> 42191 | CQ79: 39562 | CR79: 40795 | CS79: 37705 | CT79: 37166 | CU79: =CT79 -> 37166 | CV79: 33626 | CW79: 33551 | CX79: 33435 | CY79: 36845 | CZ79: =CY79 -> 36845 | DA79: 39082 | DB79: 38673 | DC79: 35832 | DD79: 39624 | DE79: =DD79 -> 39624 | DF79: 37934 | DG79: 37215 | DH79: 39147 | DI79: 36209 | DJ79: =DI79 -> 36209 | DK79: 36424 | DL79: 36745
B80: Non-current compensation and benefits | CO80: 29677 | CP80: =CO80 -> 29677 | CQ80: 29104 | CR80: 28805 | CS80: 28415 | CT80: 21202 | CU80: =CT80 -> 21202 | CV80: 20636 | CW80: 19758 | CX80: 19201 | CY80: 10400 | CZ80: =CY80 -> 10400 | DA80: 10244 | DB80: 9941 | DC80: 9718 | DD80: 11214 | DE80: =DD80 -> 11214 | DF80: 11002 | DG80: 7248 | DH80: 7169 | DI80: 7035 | DJ80: =DI80 -> 7035 | DK80: 6872 | DL80: 6796
B81: All other liabilities | CO81: =15484 -> 15484 | CP81: =CO81 -> 15484 | CQ81: 14822 | CR81: =15245+1 -> 15246 | CS81: 14999 | CT81: 13240 | CU81: =CT81 -> 13240 | CV81: 12477 | CW81: 11885 | CX81: 11767 | CY81: 11063 | CZ81: =CY81 -> 11063 | DA81: 10937 | DB81: 11067 | DC81: 11177 | DD81: 10508 | DE81: =DD81 -> 10508 | DF81: 10855 | DG81: 6534 | DH81: 6647 | DI81: 6376 | DJ81: =DI81 -> 6376 | DK81: 6538 | DL81: 6504
B82: Liabilities of discontinued ops. | CO82: 5182 | CP82: =CO82 -> 5182 | CQ82: 204 | CR82: 17 | CS82: 109 | CT82: 887 | CU82: =CT82 -> 887 | CV82: 993 | CW82: 1032 | CX82: 1103 | CY82: 24474 | CZ82: =CY82 -> 24474 | DA82: 1551 | DB82: 1565 | DC82: 1112 | DD82: 1193 | DE82: =DD82 -> 1193 | DF82: 1169 | DG82: 1667 | DH82: 1328 | DI82: 1317 | DJ82: =DI82 -> 1317 | DK82: 1339 | DL82: 1362
B83: Total Liabilities | C83: =SUM(C76:C82) -> 0 | D83: =SUM(D76:D82) -> 0 | E83: =SUM(E76:E82) -> 0 | F83: =SUM(F76:F82) -> 0 | G83: =SUM(G76:G82) -> 0 | H83: =SUM(H76:H82) -> 0 | I83: =SUM(I76:I82) -> 0 | J83: =SUM(J76:J82) -> 0 | ... DL83: =SUM(DL76:DL82) -> 105911
B84: Preferred stock | CO84: 6 | CP84: =CO84 -> 6 | CQ84: 6 | CR84: 6 | CS84: 6 | CT84: 6 | CU84: =CT84 -> 6 | CV84: 6 | CW84: 6 | CX84: 6 | CY84: 6 | CZ84: =CY84 -> 6 | DA84: 3 | DB84: 3 | DC84: 0 | DD84: 0 | DE84: =DD84 -> 0 | DF84: 0 | DG84: 0 | DH84: 0 | DI84: 0 | DJ84: =DI84 -> 0 | DK84: 0 | DL84: 0
B85: Common Stock | CO85: 702 | CP85: =CO85 -> 702 | CQ85: 702 | CR85: 702 | CS85: 15 | CT85: 15 | CU85: =CT85 -> 15 | CV85: 15 | CW85: 15 | CX85: 15 | CY85: 15 | CZ85: =CY85 -> 15 | DA85: 15 | DB85: 15 | DC85: 15 | DD85: 15 | DE85: =DD85 -> 15 | DF85: 15 | DG85: 15 | DH85: 15 | DI85: 15 | DJ85: =DI85 -> 15 | DK85: 15 | DL85: 15
B86: Accumulated Other Comprehensive Income (Loss) | CO86: -9749 | CP86: =CO86 -> -9749 | CQ86: -8893 | CR86: -7820 | CS86: -5078 | CT86: 1582 | CU86: =CT86 -> 1582 | CV86: 1341 | CW86: -1852 | CX86: -4405 | CY86: -2272 | CZ86: =CY86 -> -2272 | DA86: -3289 | DB86: -3573 | DC86: -3351 | DD86: -6150 | DE86: =DD86 -> -6150 | DF86: -5603 | DG86: -4035 | DH86: -4375 | DI86: -3861 | DJ86: =DI86 -> -3861 | DK86: -3733 | DL86: -4024
B87: Other capital | CO87: 34307 | CP87: =CO87 -> 34307 | CQ87: 34042 | CR87: =34032-1 -> 34031 | CS87: =34751-1 -> 34750 | CT87: 34691 | CU87: =CT87 -> 34691 | CV87: 34391 | CW87: 34382 | CX87: 34254 | CY87: 34173 | CZ87: =CY87 -> 34173 | DA87: 30729 | DB87: 30426 | DC87: 27229 | DD87: 26962 | DE87: =DD87 -> 26962 | DF87: 25887 | DG87: 25282 | DH87: 24406 | DI87: 24266 | DJ87: =DI87 -> 24266 | DK87: 23912 | DL87: 23839
B88: Retained Earnings | CO88: 92247 | CP88: =CO88 -> 92247 | CQ88: 89276 | CR88: 87993 | CS88: 89098 | CT88: 85110 | CU88: =CT88 -> 85110 | CV88: 83927 | CW88: 82981 | CX88: 82655 | CY88: 82983 | CZ88: =CY88 -> 82983 | DA88: 84955 | DB88: 84848 | DC88: 85017 | DD88: 86527 | DE88: =DD88 -> 86527 | DF88: 88065 | DG88: 77349 | DH88: 78889 | DI88: 80488 | DJ88: =DI88 -> 80488 | DK88: 82081 | DL88: 83726
B89: Less common stock held in treasury | CO89: -81961 | CP89: =CO89 -> -81961 | CQ89: -81548 | CR89: -81425 | CS89: -81314 | CT89: -81093 | CU89: =CT89 -> -81093 | CV89: -80673 | CW89: -80883 | CX89: -81049 | CY89: -81209 | CZ89: =CY89 -> -81209 | DA89: -80762 | DB89: -80524 | DC89: -80244 | DD89: -79976 | DE89: =DD89 -> -79976 | DF89: -78508 | DG89: -80013 | DH89: -80061 | DI89: -81566 | DJ89: =DI89 -> -81566 | DK89: -83024 | DL89: -84421
B90: Total Ticker0009 Stockholders' Equity | C90: =SUM(C84:C89) -> 0 | D90: =SUM(D84:D89) -> 0 | E90: =SUM(E84:E89) -> 0 | F90: =SUM(F84:F89) -> 0 | G90: =SUM(G84:G89) -> 0 | H90: =SUM(H84:H89) -> 0 | I90: =SUM(I84:I89) -> 0 | J90: =SUM(J84:J89) -> 0 | ... DL90: =SUM(DL84:DL89) -> 19135
B91: Noncontrolling interests | CO91: 1522 | CP91: =CO91 -> 1522 | CQ91: 1568 | CR91: 1560 | CS91: 1484 | CT91: 1302 | CU91: =CT91 -> 1302 | CV91: 1275 | CW91: 1294 | CX91: 1274 | CY91: 1216 | CZ91: =CY91 -> 1216 | DA91: 1171 | DB91: 1173 | DC91: 1167 | DD91: 1202 | DE91: =DD91 -> 1202 | DF91: 1249 | DG91: 245 | DH91: 229 | DI91: =223-1 -> 222 | DJ91: =DI91 -> 222 | DK91: 217 | DL91: 210
B92: Total equity | C92: =SUM(C90:C91) -> 0 | D92: =SUM(D90:D91) -> 0 | E92: =SUM(E90:E91) -> 0 | F92: =SUM(F90:F91) -> 0 | G92: =SUM(G90:G91) -> 0 | H92: =SUM(H90:H91) -> 0 | I92: =SUM(I90:I91) -> 0 | J92: =SUM(J90:J91) -> 0 | ... DL92: =SUM(DL90:DL91) -> 19345
B93: Total Liabilities and Shareholder's Equity | C93: =C83+C92 -> 0 | D93: =D83+D92 -> 0 | E93: =E83+E92 -> 0 | F93: =F83+F92 -> 0 | G93: =G83+G92 -> 0 | H93: =H83+H92 -> 0 | I93: =I83+I92 -> 0 | J93: =J83+J92 -> 0 | ... DL93: =DL83+DL92 -> 125256
B95: Check | C95: =IF(ROUND(C93,0)=ROUND(C68,0),"","check") | D95: =IF(ROUND(D93,0)=ROUND(D68,0),"","check") | E95: =IF(ROUND(E93,0)=ROUND(E68,0),"","check") | F95: =IF(ROUND(F93,0)=ROUND(F68,0),"","check") | G95: =IF(ROUND(G93,0)=ROUND(G68,0),"","check") | H95: =IF(ROUND(H93,0)=ROUND(H68,0),"","check") | I95: =IF(ROUND(I93,0)=ROUND(I68,0),"","check") | J95: =IF(ROUND(J93,0)=ROUND(J68,0),"","check") | ... AK95: =IF(ROUND(AK93,0)=ROUND(AK68,0),"","check") | DK95: =+IF(DK93=DK68,"True",DK93-DK68) -> True | DL95: =+IF(DL93=DL68,"True",DL93-DL68) -> True
B97: Cash Flow YTD
B98: Operating Activities
B99: Net earnings | CL99: 6233 | CM99: 4101 | CN99: 2907 | CO99: 5546 | CP99: =CO99 -> 5546 | CQ99: -2798 | CR99: -3933 | CS99: =-2748 -> -2748 | CT99: -6591 | CU99: =CT99 -> -6591 | CV99: -1108 | CW99: -1971 | CX99: -1806 | CY99: 407 | CZ99: =CY99 -> 407 | DA99: 7478 | DB99: 7518 | DC99: 7852 | DD99: 9443 | DE99: =DD99 -> 9443 | DF99: 1563 | DG99: 2833 | DH99: 4676 | DI99: 6566 | DJ99: =DI99 -> 6566 | DK99: 1972 | DL99: 3993
B100: (Earnings) loss from discontinued ops. | CL100: 21 | CM100: 1015 | CN100: 1072 | CO100: 911 | CP100: =CO100 -> 911 | CQ100: 2894 | CR100: 3458 | CS100: 2856 | CT100: 3195 | CU100: =CT100 -> 3195 | CV100: -101 | CW100: -365 | CX100: -775 | CY100: -1202 | CZ100: =CY100 -> -1202 | DA100: -1257 | DB100: -239 | DC100: -412 | DD100: -414 | DE100: =DD100 -> -414 | DF100: -14 | DG100: 232 | DH100: 85 | DI100: 91 | DJ100: =DI100 -> 91 | DK100: -10 | DL100: -31
B101: Depreciation and amortization of PP&E | CL101: 461 | CM101: 921 | CN101: 1664 | CO101: 2128 | CP101: =CO101 -> 2128 | CQ101: 452 | CR101: 935 | CS101: 1390 | CT101: 1871 | CU101: =CT101 -> 1871 | CV101: 403 | CW101: 783 | CX101: 1130 | CY101: 1564 | CZ101: =CY101 -> 1564 | DA101: 367 | DB101: 719 | DC101: 1097 | DD101: 1473 | DE101: =DD101 -> 1473 | DF101: 378 | DG101: 401 | DH101: 625 | DI101: 834 | DJ101: =DI101 -> 834 | DK101: 210 | DL101: 428
B102: Amortization of intangible assets | CL102: 318 | CM102: 617 | CN102: 1036 | CO102: 1336 | CP102: =CO102 -> 1336 | CQ102: 301 | CR102: 589 | CS102: 860 | CT102: 1138 | CU102: =CT102 -> 1138 | CV102: 922 | CW102: 1058 | CX102: 1193 | CY102: 1338 | CZ102: =CY102 -> 1338 | DA102: 140 | DB102: 299 | DC102: 448 | DD102: 606 | DE102: =DD102 -> 606 | DF102: 145 | DG102: 172 | DH102: 261 | DI102: 350 | DJ102: =DI102 -> 350 | DK102: 89 | DL102: 182
B103: (Gains) losses on purchase and sales of business interests | CL103: -12372 | CM103: -12425 | CN103: -12446 | CO103: -12469 | CP103: =CO103 -> -12469 | CQ103: -3 | CR103: 2 | CS103: 155 | CT103: 40 | CU103: =CT103 -> 40 | CV103: -15 | CW103: -19 | CX103: -42 | CY103: -60 | CZ103: =CY103 -> -60 | DA103: 52 | DB103: 13 | DC103: -103 | DD103: -104 | DE103: =DD103 -> -104 | DF103: -9 | DG103: 0 | DH103: 0 | DI103: 0 | DJ103: =DI103 -> 0 | DK103: 0 | DL103: 0
B104: (Gains) losses on equity securities | CL104: 5873 | CM104: 4018 | CN104: 4781 | CO104: 2085 | CP104: =CO104 -> 2085 | CQ104: -296 | CR104: -694 | CS104: -1035 | CT104: -1656 | CU104: =CT104 -> -1656 | CV104: 203 | CW104: 1965 | CX104: 2145 | CY104: 113 | CZ104: =CY104 -> 113 | DA104: -5906 | DB104: -6282 | DC104: -5181 | DD104: -5842 | DE104: =DD104 -> -5842 | DF104: -665 | DG104: -314 | DH104: -723 | DI104: -719 | DJ104: =DI104 -> -719 | DK104: -43 | DL104: -109
B105: Principal pension plan cost | CL105: 877 | CM105: 1798 | CN105: 2681 | CO105: 3559 | CP105: =CO105 -> 3559 | CQ105: 658 | CR105: 1329 | CS105: 1990 | CT105: 2650 | CU105: =CT105 -> 2650 | CV105: 94 | CW105: 180 | CX105: 269 | CY105: 376 | CZ105: =CY105 -> 376 | DA105: -271 | DB105: -556 | DC105: -834 | DD105: -1108 | DE105: =DD105 -> -1108 | DF105: -256 | DG105: -328 | DH105: -491 | DI105: -653 | DJ105: =DI105 -> -653 | DK105: -161 | DL105: -324
B106: Principal pension plans employer contributions | CL106: -70 | CM106: -144 | CN106: -226 | CO106: -2806 | CP106: =CO106 -> -2806 | CQ106: -74 | CR106: -154 | CS106: -232 | CT106: -326 | CU106: =CT106 -> -326 | CV106: -49 | CW106: -100 | CX106: -152 | CY106: -204 | CZ106: =CY106 -> -204 | DA106: -52 | DB106: -104 | DC106: -156 | DD106: -212 | DE106: =DD106 -> -212 | DF106: -53 | DG106: -94 | DH106: -142 | DI106: -210 | DJ106: =DI106 -> -210 | DK106: -48 | DL106: -95
B107: Other postretirement benefit plans (net) | CL107: -254 | CM107: -488 | CN107: -712 | CO107: -893 | CP107: =CO107 -> -893 | CQ107: -289 | CR107: -497 | CS107: -772 | CT107: -1144 | CU107: =CT107 -> -1144 | CV107: -224 | CW107: -433 | CX107: -617 | CY107: -755 | CZ107: =CY107 -> -755 | DA107: -181 | DB107: -343 | DC107: -496 | DD107: -644 | DE107: =DD107 -> -644 | DF107: -133 | DG107: -155 | DH107: -221 | DI107: -299 | DJ107: =DI107 -> -299 | DK107: -74 | DL107: -133
B108: Provision (benefit) for income taxes | CL108: 54 | CM108: -106 | CN108: -589 | CO108: -487 | CP108: =CO108 -> -487 | CQ108: 142 | CR108: -325 | CS108: -323 | CT108: -286 | CU108: =CT108 -> -286 | CV108: 29 | CW108: 190 | CX108: 203 | CY108: -3 | CZ108: =CY108 -> -3 | DA108: 271 | DB108: 603 | DC108: 741 | DD108: 1162 | DE108: =DD108 -> 1162 | DF108: 318 | DG108: 369 | DH108: 567 | DI108: 962 | DJ108: =DI108 -> 962 | DK108: 283 | DL108: 671
B109: Cash recovered (paid) during the year for income taxes | CL109: -310 | CM109: -622 | CN109: -1138 | CO109: -1441 | CP109: =CO109 -> -1441 | CQ109: -322 | CR109: -837 | CS109: -1048 | CT109: -1165 | CU109: =CT109 -> -1165 | CV109: -24 | CW109: -174 | CX109: -295 | CY109: -430 | CZ109: =CY109 -> -430 | DA109: -172 | DB109: -521 | DC109: -806 | DD109: -1148 | DE109: =DD109 -> -1148 | DF109: -105 | DG109: 91 | DH109: -42 | DI109: -334 | DJ109: =DI109 -> -334 | DK109: -112 | DL109: -253
B110: All other operating activities | CL110: 892 | CM110: =877+886-1 -> 1762 | CN110: =1912+877 -> 2789 | CO110: =877-109+1897+301 -> 2966 | CP110: =CO110 -> 2966 | CQ110: -2719 | CR110: =-1664+2 -> -1662 | CS110: -1132 | CT110: =-1317-1143+6524 -> 4064 | CU110: =CT110 -> 4064 | CV110: =-155+89 -> -66 | CW110: =-223-481 -> -704 | CX110: =-154+232 -> 78 | CY110: =465-154+998 -> 1309 | CZ110: =CY110 -> 1309 | DA110: =3+125 -> 128 | DB110: =3-256 -> -253 | DC110: =3+180 -> 183 | DD110: =3+717 -> 720 | DE110: =DD110 -> 720 | DF110: -297 | DG110: =-102-528 -> -630 | DH110: =331-105+251+-2 -> 475 | DI110: =251+1 -> 252 | DJ110: =DI110 -> 252 | DK110: =-746+132+80-1 -> -535 | DL110: =447-417 -> 30
B111: Changes in operating assets and liabilities: | C111: =SUM(C112:C116) -> 0 | D111: =SUM(D112:D116) -> 0 | E111: =SUM(E112:E116) -> 0 | F111: =SUM(F112:F116) -> 0 | G111: =SUM(G112:G116) -> 0 | H111: =SUM(H112:H116) -> 0 | I111: =SUM(I112:I116) -> 0 | J111: =SUM(J112:J116) -> 0 | ... L111: =SUM(L112:L116) -> 0 | M111: =N111 -> 0 | N111: =SUM(N112:N116) -> 0 | O111: =SUM(O112:O116) -> 0 | P111: =SUM(P112:P116) -> 0 | Q111: =SUM(Q112:Q116) -> 0 | R111: =S111 -> 0 | S111: =SUM(S112:S116) -> 0 | T111: =SUM(T112:T116) -> 0 | U111: =SUM(U112:U116) -> 0 | V111: =SUM(V112:V116) -> 0 | W111: =X111 -> 0 | X111: =SUM(X112:X116) -> 0 | Y111: =SUM(Y112:Y116) -> 0 | Z111: =SUM(Z112:Z116) -> 0 | AA111: =SUM(AA112:AA116) -> 0 | AB111: =AC111 -> 0 | AC111: =SUM(AC112:AC116) -> 0 | AD111: =SUM(AD112:AD116) -> 0 | AE111: =SUM(AE112:AE116) -> 0 | AF111: =SUM(AF112:AF116) -> 0 | AG111: =AH111 -> 0 | AH111: =SUM(AH112:AH116) -> 0 | AI111: =SUM(AI112:AI116) -> 0 | AJ111: =SUM(AJ112:AJ116) -> 0 | AK111: =SUM(AK112:AK116) -> 0 | AL111: =SUM(AL112:AL116) -> 0 | AM111: =AL111 -> 0 | AN111: =SUM(AN112:AN116) -> 0 | AO111: =SUM(AO112:AO116) -> 0 | AP111: =SUM(AP112:AP116) -> 0 | AQ111: =SUM(AQ112:AQ116) -> 0 | AR111: =AQ111 -> 0 | AS111: =SUM(AS112:AS116) -> 0 | AT111: =SUM(AT112:AT116) -> 0 | AU111: =SUM(AU112:AU116) -> 0 | AV111: =SUM(AV112:AV116) -> 0 | AW111: =AV111 -> 0 | AX111: =SUM(AX112:AX116) -> 0 | AY111: =SUM(AY112:AY116) -> 0 | AZ111: =SUM(AZ112:AZ116) -> 0 | BA111: =SUM(BA112:BA116) -> 0 | BB111: =BA111 -> 0 | BC111: =SUM(BC112:BC116) -> 0 | BD111: =SUM(BD112:BD116) -> 0 | BE111: =SUM(BE112:BE116) -> 0 | BF111: =SUM(BF112:BF116) -> 0 | BG111: =BF111 -> 0 | BH111: =SUM(BH112:BH116) -> 0 | BI111: =SUM(BI112:BI116) -> 0 | BJ111: =SUM(BJ112:BJ116) -> 0 | BK111: =SUM(BK112:BK116) -> 0 | BL111: =BK111 -> 0 | BM111: =SUM(BM112:BM116) -> 0 | BN111: =SUM(BN112:BN116) -> 0 | BO111: =SUM(BO112:BO116) -> 0 | BP111: =SUM(BP112:BP116) -> 0 | BQ111: =BP111 -> 0 | BR111: =SUM(BR112:BR116) -> 0 | BS111: =SUM(BS112:BS116) -> 0 | BT111: =SUM(BT112:BT116) -> 0 | BU111: =SUM(BU112:BU116) -> 0 | BV111: =BU111 -> 0 | BW111: =SUM(BW112:BW116) -> 0 | BX111: =SUM(BX112:BX116) -> 0 | BY111: =SUM(BY112:BY116) -> 0 | BZ111: =SUM(BZ112:BZ116) -> 0 | CA111: =BZ111 -> 0 | CB111: =SUM(CB112:CB116) -> 0 | CC111: =SUM(CC112:CC116) -> 0 | CD111: =SUM(CD112:CD116) -> 0 | CE111: =SUM(CE112:CE116) -> 0 | CF111: =CE111 -> 0 | CG111: =SUM(CG112:CG116) -> 0 | CH111: =SUM(CH112:CH116) -> 0 | CI111: =SUM(CI112:CI116) -> 0 | CJ111: =SUM(CJ112:CJ116) -> 0 | CK111: =CJ111 -> 0 | CL111: =SUM(CL112:CL116) -> -2642 | CM111: =SUM(CM112:CM116) -> -2868 | CN111: =SUM(CN112:CN116) -> -3697 | CO111: =SUM(CO112:CO116) -> 588 | CP111: =CO111 -> 588 | CQ111: =SUM(CQ112:CQ116) -> -585 | CR111: =SUM(CR112:CR116) -> -1202 | CS111: =SUM(CS112:CS116) -> -1488 | CT111: =SUM(CT112:CT116) -> -902 | CU111: =CT111 -> -902 | CV111: =SUM(CV112:CV116) -> -989 | CW111: =SUM(CW112:CW116) -> -841 | CX111: =SUM(CX112:CX116) -> -951 | CY111: =SUM(CY112:CY116) -> 1592 | CZ111: =CY111 -> 1592 | DA111: =SUM(DA112:DA116) -> -444 | DB111: =SUM(DB112:DB116) -> -390 | DC111: =SUM(DC112:DC116) -> 18 | DD111: =SUM(DD112:DD116) -> 1638 | DE111: =DD111 -> 1638 | DF111: =SUM(DF112:DF116) -> 153 | DG111: =SUM(DG112:DG116) -> 9 | DH111: =SUM(DH112:DH116) -> -571 | DI111: =SUM(DI112:DI116) -> -1023 | DJ111: =DI111 -> -1023 | DK111: =SUM(DK112:DK116) -> -28 | DL111: =SUM(DL112:DL116) -> -468
...

Sheet Aerospace
B3: Ticker0009 Revenue Build | C3: 1997 | D3: 1998 | E3: 1999 | F3: 2000 | G3: 2001 | H3: 2002 | I3: 2003 | J3: 1Q04 | K3: 2Q04 | L3: 3Q04 | M3: 4Q04 | N3: 2004 | O3: 1Q05 | P3: 2Q05 | Q3: 3Q05 | R3: 4Q05 | S3: 2005 | T3: 1Q06 | U3: 2Q06 | V3: 3Q06 | W3: 4Q06 | X3: 2006 | Y3: 1Q07 | Z3: 2Q07 | AA3: 3Q07 | AB3: 4Q07 | AC3: 2007 | AD3: 1Q08 | AE3: 2Q08 | AF3: 3Q08 | AG3: 4Q08 | AH3: 2008 | AI3: 1Q09 | AJ3: 2Q09 | AK3: 3Q09 | AL3: 4Q09 | AM3: 2009 | AN3: 1Q10 | AO3: 2Q10 | AP3: 3Q10 | AQ3: 4Q10 | AR3: 2010 | AS3: 1Q11 | AT3: 2Q11 | AU3: 3Q11 | AV3: 4Q11 | AW3: 2011 | AX3: 1Q12 | AY3: 2Q12 | AZ3: 3Q12 | BA3: 4Q12 | BB3: 2012 | BC3: 1Q13 | BD3: 2Q13 | BE3: 3Q13 | BF3: 4Q13 | BG3: 2013 | BH3: 1Q14 | BI3: 2Q14 | BJ3: 3Q14 | BK3: 4Q14 | BL3: 2014 | BM3: 1Q15 | BN3: 2Q15 | BO3: 3Q15 | BP3: 4Q15 | BQ3: 2015 | BR3: 1Q16 | BS3: 2Q16 | BT3: 3Q16 | BU3: 4Q16 | BV3: 2016 | BW3: 1Q17 | BX3: 2Q17 | BY3: 3Q17 | BZ3: 4Q17 | CA3: 2017 | CB3: 1Q18 | CC3: 2Q18 | CD3: 3Q18 | CE3: 4Q18 | CF3: 2018 | CG3: 1Q19 | CH3: 2Q19 | CI3: 3Q19 | CJ3: 4Q19 | CK3: 2019 | CL3: 1Q20 | CM3: 2Q20 | CN3: 3Q20 | CO3: 4Q20 | CP3: 2020 | CQ3: 1Q21 | CR3: 2Q21 | CS3: 3Q21 | CT3: 4Q21 | CU3: 2021 | CV3: 1Q22 | CW3: 2Q22 | CX3: 3Q22 | CY3: 4Q22 | CZ3: 2022 | DA3: 1Q23 | DB3: 2Q23 | DC3: 3Q23 | DD3: 4Q23 | DE3: 2023 | DF3: 1Q24 | DG3: 2Q24 | DH3: 3Q24 | DI3: 4Q24 | DJ3: 2024 | DK3: 1Q25 | DL3: 2Q25 | DM3: 3Q25E | DN3: 4Q25E | DO3: 2025 | DP3: 1Q26E | DQ3: 2Q26E | DR3: 3Q26E | DS3: 4Q26E | DT3: 2026 | DU3: 2027 | DV3: 2028
B4: ($ mn) | C4: 35795 | D4: 36160 | E4: 36525 | F4: 36891 | G4: 37256 | H4: 37621 | I4: 37986 | J4: 38077 | K4: 38168 | L4: 38260 | M4: 38352 | N4: 38352 | O4: 38442 | P4: 38533 | Q4: 38625 | R4: 38717 | S4: 38717 | T4: 38807 | U4: 38898 | V4: 38990 | W4: 39082 | X4: 39082 | Y4: 39172 | Z4: 39263 | AA4: 39355 | AB4: 39447 | AC4: 39447 | AD4: 39538 | AE4: 39629 | AF4: 39721 | AG4: 39813 | AH4: 39813 | AI4: 39903 | AJ4: 39994 | AK4: 40086 | AL4: 40178 | AM4: 40178 | AN4: 40268 | AO4: 40359 | AP4: 40451 | AQ4: 40543 | AR4: 40543 | AS4: 40633 | AT4: 40724 | AU4: 40816 | AV4: 40908 | AW4: 40908 | AX4: 40999 | AY4: 41090 | AZ4: 41182 | BA4: 41274 | BB4: 41274 | BC4: 41364 | BD4: 41455 | BE4: 41547 | BF4: 41639 | BG4: 41639 | BH4: 41729 | BI4: 41820 | BJ4: 41912 | BK4: 42004 | BL4: 42004 | BM4: 42094 | BN4: 42185 | BO4: 42277 | BP4: 42369 | BQ4: 42369 | BR4: 42460 | BS4: 42551 | BT4: 42643 | BU4: 42735 | BV4: 42735 | BW4: 42825 | BX4: 42916 | BY4: 43008 | BZ4: 43100 | CA4: 43100 | CB4: 43190 | CC4: 43281 | CD4: 43373 | CE4: 43465 | CF4: 43465 | CG4: 43555 | CH4: 43646 | CI4: 43738 | CJ4: 43830 | CK4: 43830 | CL4: 43921 | CM4: 44012 | CN4: 44104 | CO4: 44196 | CP4: 44196 | CQ4: 44286 | CR4: 44377 | CS4: 44469 | CT4: 44561 | CU4: 44561 | CV4: 44651 | CW4: 44742 | CX4: 44834 | CY4: 44926 | CZ4: 44926 | DA4: 45016 | DB4: 45107 | DC4: 45199 | DD4: 45291 | DE4: 45291 | DF4: 45382 | DG4: 45473 | DH4: 45565 | DI4: 45657 | DJ4: 45657 | DK4: 45747 | DL4: 45838 | DM4: 45930 | DN4: 46022 | DO4: 46022 | DP4: 46112 | DQ4: 46203 | DR4: 46295 | DS4: 46387 | DT4: 46387 | DU4: 46752 | DV4: 47118
B6: Segment revenues
B7: Revenues | H7: 11141 | I7: 10509 | N7: 11094 | S7: 11826 | T7: 3010 | U7: 3287 | V7: 3133 | W7: 3587 | X7: =T7+U7+V7+W7 -> 13017 | Y7: 3451 | Z7: 4079 | AA7: 4240 | AB7: 5049 | AC7: =Y7+Z7+AA7+AB7 -> 16819 | AD7: 4320 | AE7: 4923 | AF7: 4841 | AG7: 5155 | AH7: =AD7+AE7+AF7+AG7 -> 19239 | AI7: 4817 | AJ7: 4619 | AK7: 4542 | AL7: 4750 | AM7: =AI7+AJ7+AK7+AL7 -> 18728 | AN7: 4165 | AO7: 4259 | AP7: 4391 | AQ7: 4804 | AR7: =AN7+AO7+AP7+AQ7 -> 17619 | AS7: 4368 | AT7: 4732 | AU7: 4835 | AV7: 4924 | AW7: =AS7+AT7+AU7+AV7 -> 18859 | AX7: 4891 | AY7: 4855 | AZ7: 4781 | BA7: 5467 | BB7: =AX7+AY7+AZ7+BA7 -> 19994 | BC7: 5074 | BD7: 5303 | BE7: 5364 | BF7: 6170 | BG7: =BC7+BD7+BE7+BF7 -> 21911 | BH7: 5778 | BI7: 6090 | BJ7: 5698 | BK7: 6424 | BL7: =BH7+BI7+BJ7+BK7 -> 23990 | BM7: 5674 | BN7: 6252 | BO7: 6001 | BP7: 6734 | BQ7: =BM7+BN7+BO7+BP7 -> 24661 | BR7: 6262 | BS7: 6511 | BT7: 6300 | BU7: 7187 | BV7: =BR7+BS7+BT7+BU7 -> 26260 | BW7: 6673 | BX7: 6634 | BY7: 6696 | BZ7: 7010 | CA7: =BW7+BX7+BY7+BZ7 -> 27013 | CB7: 7112 | CC7: 7519 | CD7: 7480 | CE7: 8456 | CF7: =CB7+CC7+CD7+CE7 -> 30567 | CG7: 7954 | CH7: 7877 | CI7: 8109 | CJ7: 8936 | CK7: =CG7+CH7+CI7+CJ7 -> 32876 | CL7: 6892 | CM7: 4384 | CN7: 4919 | CO7: 5847 | CP7: =CL7+CM7+CN7+CO7 -> 22042 | CQ7: 4992 | CR7: 4840 | CS7: 5398 | CT7: 6080 | CU7: =CQ7+CR7+CS7+CT7 -> 21310 | CV7: 5603 | CW7: 6127 | CX7: 6705 | CY7: 7615 | CZ7: =CV7+CW7+CX7+CY7 -> 26050 | DA7: 6981 | DB7: 7860 | DC7: 8409 | DD7: 8520 | DE7: =DA7+DB7+DC7+DD7 -> 31770 | DF7: =SEG!DF11 -> 8076 | DG7: =SEG!DG11 -> 8223 | DH7: =SEG!DH11 -> 8943 | DI7: =SEG!DI11 -> 9879 | DJ7: =SEG!DJ11 -> 35121 | DK7: =SEG!DK11 -> 9001 | DL7: =SEG!DL11 -> 10151 | DM7: =SEG!DM11 -> 10065.86 | ... DV7: =SEG!DV11 -> 52592.722
B8: Operating expenses | H8: =H7-H9 -> 9081 | I8: =I7-I9 -> 8361 | N8: =N7-N9 -> 8856.1 | S8: =S7-S9 -> 9301 | T8: =T7-T9 -> 2383 | U8: =U7-U9 -> 2559 | V8: =V7-V9 -> 2444 | W8: =W7-W9 -> 2829 | X8: =X7-X9 -> 10215 | Y8: =Y7-Y9 -> 2752 | Z8: =Z7-Z9 -> 3251 | ... DV8: =DV7-DV9 -> 40686.573
B9: EBIT (GAAP) | H9: 2060 | I9: 2148 | N9: 2237.9 | S9: 2525 | T9: 627 | U9: 728 | V9: 689 | W9: 758 | X9: =W9+V9+U9+T9 -> 2802 | Y9: 699 | Z9: 828 | AA9: 736 | AB9: 959 | AC9: =AB9+AA9+Z9+Y9 -> 3222 | AD9: 775 | AE9: 914 | AF9: 834 | AG9: 1161 | AH9: =AD9+AE9+AF9+AG9 -> 3684 | AI9: =1080 -> 1080 | AJ9: 923 | AK9: 970 | AL9: 950 | AM9: =AI9+AJ9+AK9+AL9 -> 3923 | AN9: 799 | AO9: 879 | AP9: 805 | AQ9: 821 | AR9: =AN9+AO9+AP9+AQ9 -> 3304 | AS9: 841 | AT9: 959 | AU9: 862 | AV9: 850 | AW9: =AS9+AT9+AU9+AV9 -> 3512 | AX9: 862 | AY9: 922 | AZ9: 924 | BA9: 1039 | BB9: =AX9+AY9+AZ9+BA9 -> 3747 | BC9: 936 | BD9: =BD11+BD10 -> 1067 | BE9: =BE11+BE10 -> 1091 | BF9: =BF11+BF10 -> 1251 | BG9: =BC9+BD9+BE9+BF9 -> 4345 | BH9: =BH11+BH10 -> 1115 | BI9: =BI11+BI10 -> 1197 | BJ9: =BJ11+BJ10 -> 1264 | BK9: =BK11+BK10 -> 1397 | BL9: =BH9+BI9+BJ9+BK9 -> 4973 | BM9: =BM11+BM10 -> 1314 | BN9: =BN11+BN10 -> 1269 | BO9: =BO11+BO10 -> 1353 | BP9: =BP11+BP10 -> 1571 | BQ9: =BM9+BN9+BO9+BP9 -> 5507 | BR9: =BR11+BR10 -> 1524 | BS9: =BS11+BS10 -> 1348 | BT9: =BT11+BT10 -> 1494 | BU9: =BU11+BU10 -> 1749 | BV9: =BR9+BS9+BT9+BU9 -> 6115 | BW9: =BW11+BW10 -> 1273 | BX9: =BX11+BX10 -> 1374 | BY9: =BY11+BY10 -> 1335 | BZ9: =BZ11+BZ10 -> 1388 | CA9: =BW9+BX9+BY9+BZ9 -> 5370 | CB9: =CB11+CB10 -> 1603 | CC9: =CC11+CC10 -> 1475 | CD9: =CD11+CD10 -> 1665 | CE9: =CE11+CE10 -> 1723 | CF9: =CB9+CC9+CD9+CE9 -> 6466 | CG9: =CG11+CG10 -> 1660 | CH9: =CH11+CH10 -> 1385 | CI9: =CI11+CI10 -> 1718 | CJ9: 2056 | CK9: =CG9+CH9+CI9+CJ9 -> 6819 | CL9: 1002.9277 | CM9: -686.9981 | CN9: 349.55532 | CO9: 563.79383 | CP9: =CL9+CM9+CN9+CO9 -> 1229.2788 | CQ9: 641 | CR9: 176 | CS9: 846 | CT9: 1218 | CU9: =SUM(CQ9:CT9) -> 2881 | CV9: 908 | CW9: 1148 | CX9: 1284 | CY9: 1434 | CZ9: =SUM(CV9:CY9) -> 4774 | DA9: 1326 | DB9: 1479 | DC9: 1712 | DD9: 1598 | DE9: =SUM(DA9:DD9) -> 6115 | DF9: =DF20*DF7 -> 1550 | DG9: =DG20*DG7 -> 1897 | DH9: =DH20*DH7 -> 1818 | DI9: =DI20*DI7 -> 1988 | DJ9: =SUM(DF9:DI9) -> 7253 | DK9: =DK20*DK7 -> 2146 | DL9: =DL20*DL7 -> 2337 | DM9: =DM20*DM7 -> 2141.2269 | DN9: =DN20*DN7 -> 2037.9232 | DO9: =SUM(DK9:DN9) -> 8662.1501 | DP9: =DP20*DP7 -> 2378.8568 | DQ9: =DQ20*DQ7 -> 2595.7158 | DR9: =DR20*DR7 -> 2502.9031 | DS9: =DS20*DS7 -> 2588.8442 | DT9: =SUM(DP9:DS9) -> 10066.32 | DU9: =DU20*DU7 -> 11037.298 | DV9: =DV20*DV7 -> 11906.149
B10: Non-recurring (charges) / gains | BG10: 0 | BH10: 0 | BI10: 0 | BJ10: 0 | BK10: 0 | BL10: 0 | BM10: 0 | BN10: 0 | BO10: 0 | BP10: 0 | BQ10: 0 | BR10: 0 | BS10: 0 | BT10: 0 | BU10: 0 | BV10: =BR10+BS10+BT10+BU10 -> 0 | BW10: 0 | BX10: 0 | BY10: 0 | BZ10: 0 | CA10: =BW10+BX10+BY10+BZ10 -> 0 | CB10: 0 | CC10: 0 | CD10: 0 | CE10: 0 | CF10: =CB10+CC10+CD10+CE10 -> 0 | CG10: 0 | CH10: 0 | CI10: 0 | CJ10: 0 | CK10: =CG10+CH10+CI10+CJ10 -> 0 | CL10: -2.371735 | CM10: -7.0771482 | CN10: -6.2017299 | CO10: -10.008453 | CP10: =SUM(CL10:CO10) -> -25.659066 | CQ10: 0 | CR10: 0 | CS10: 0 | CT10: 0 | CU10: =SUM(CQ10:CT10) -> 0 | CV10: 0 | CW10: 0 | CX10: 0 | CY10: 0 | CZ10: =SUM(CV10:CY10) -> 0 | DA10: 0 | DB10: 0 | DC10: 0 | DD10: 0 | DE10: =SUM(DA10:DD10) -> 0 | DF10: 0 | DG10: 0 | DH10: 0 | DI10: 0 | DJ10: =SUM(DF10:DI10) -> 0 | DK10: 0 | DL10: 0 | DM10: 0 | DN10: 0 | DO10: =SUM(DG10:DJ10) -> 0 | DP10: 0 | DQ10: 0 | DR10: 0 | DS10: 0 | DT10: =SUM(DL10:DO10) -> 0 | DU10: =SUM(DI10:DT10) -> 0 | DV10: =SUM(DJ10:DU10) -> 0
B11: EBIT-adjusted | H11: =H9-H10 -> 2060 | I11: =I9-I10 -> 2148 | N11: =N9-N10 -> 2237.9 | S11: =S9-S10 -> 2525 | T11: =T9-T10 -> 627 | U11: =U9-U10 -> 728 | V11: =V9-V10 -> 689 | W11: =W9-W10 -> 758 | X11: =X9-X10 -> 2802 | Y11: =Y9-Y10 -> 699 | Z11: =Z9-Z10 -> 828 | ... BC11: =BC9-BC10 -> 936 | BD11: 1067 | BE11: 1091 | BF11: 1251 | BG11: =BG9-BG10 -> 4345 | BH11: 1115 | BI11: 1197 | BJ11: 1264 | BK11: 1397 | BL11: =BL9-BL10 -> 4973 | BM11: 1314 | BN11: 1269 | BO11: 1353 | BP11: 1571 | BQ11: =BQ9-BQ10 -> 5507 | BR11: 1524 | BS11: 1348 | BT11: 1494 | BU11: 1749 | BV11: =BR11+BS11+BT11+BU11 -> 6115 | BW11: 1273 | BX11: 1374 | BY11: 1335 | BZ11: 1388 | CA11: =BW11+BX11+BY11+BZ11 -> 5370 | CB11: 1603 | CC11: 1475 | CD11: 1665 | CE11: 1723 | CF11: =CB11+CC11+CD11+CE11 -> 6466 | CG11: 1660 | CH11: 1385 | CI11: 1718 | CJ11: 2056 | CK11: =CG11+CH11+CI11+CJ11 -> 6819 | CL11: 1005.2995 | CM11: -679.92095 | CN11: 355.75705 | CO11: 573.80228 | CP11: =CL11+CM11+CN11+CO11 -> 1254.9379 | CQ11: =CQ9-CQ10 -> 641 | CR11: =CR9-CR10 -> 176 | CS11: =CS9-CS10 -> 846 | CT11: =CT9-CT10 -> 1218 | CU11: =SUM(CQ11:CT11) -> 2881 | CV11: =CV9-CV10 -> 908 | CW11: =CW9-CW10 -> 1148 | CX11: =CX9-CX10 -> 1284 | CY11: =CY9-CY10 -> 1434 | CZ11: =SUM(CV11:CY11) -> 4774 | DA11: =DA9-DA10 -> 1326 | DB11: =DB9-DB10 -> 1479 | DC11: =DC9-DC10 -> 1712 | DD11: =DD9-DD10 -> 1598 | DE11: =SUM(DA11:DD11) -> 6115 | DF11: =DF9-DF10 -> 1550 | DG11: =DG9-DG10 -> 1897 | DH11: =DH9-DH10 -> 1818 | DI11: =DI9-DI10 -> 1988 | DJ11: =SUM(DF11:DI11) -> 7253 | DK11: =DK9-DK10 -> 2146 | DL11: =DL9-DL10 -> 2337 | DM11: =DM9-DM10 -> 2141.2269 | DN11: =DN9-DN10 -> 2037.9232 | DO11: =SUM(DK11:DN11) -> 8662.1501 | DP11: =DP9-DP10 -> 2378.8568 | DQ11: =DQ9-DQ10 -> 2595.7158 | DR11: =DR9-DR10 -> 2502.9031 | DS11: =DS9-DS10 -> 2588.8442 | DT11: =SUM(DP11:DS11) -> 10066.32 | DU11: =DU9+DU10 -> 11037.298 | DV11: =DV9+DV10 -> 11906.149
B13: Revenue growth factors
B14: Organic | AG14: 0.08 | AH14: =Aerospace!AH17-Aerospace!AH16-Aerospace!AH15 -> 0.13307222 | AI14: 0 | AJ14: 0 | AK14: 0 | AL14: 0 | AM14: =Aerospace!AM17-Aerospace!AM16-Aerospace!AM15 -> -0.019700458 | AN14: 0.03 | AO14: 0.03 | AP14: 0.03 | AQ14: 0.03 | AR14: =Aerospace!AR17-Aerospace!AR16-Aerospace!AR15 -> -0.052389967 | AS14: 0 | AT14: 0 | AU14: 0 | AV14: 0 | AW14: =(1100+200-100)/AR7 -> 0.068108292 | BB14: =(800+400)/AW7 -> 0.063630097 | BC14: =BC17 -> 0.037415661 | BD14: =BD17 -> 0.092276004 | BE14: 0.1 | BF14: 0.07 | BG14: =+SUMPRODUCT(BC14:BF14,AX$7:BA$7)/BB$7 -> 0.074611884 | BH14: 0.102 | BI14: 0.1 | BJ14: 0.042 | BK14: 0.05 | BL14: =+SUMPRODUCT(BH14:BK14,BC$7:BF$7)/BG$7 -> 0.072184565 | BM14: -0.01 | BN14: 0.04 | BO14: 0.053 | BP14: 0.05 | BQ14: =+SUMPRODUCT(BM14:BP14,BH$7:BK$7)/BL$7 -> 0.033722968 | BR14: 0.104 | BS14: 0.04 | BT14: 0.05 | BU14: 0.06 | BV14: =+SUMPRODUCT(BR14:BU14,BM$7:BP$7)/BQ$7 -> 0.062619764 | BW14: =6752/BR7-1 -> 0.07824976 | BX14: 0.003 | BY14: 0.08 | BZ14: 0.004 | CA14: =+SUMPRODUCT(BW14:BZ14,BR$7:BU$7)/BV$7 -> 0.039690823 | CB14: 0.06 | CC14: 0.13 | CD14: 0.12 | CE14: 0.21 | CF14: =+SUMPRODUCT(CB14:CE14,BW$7:BZ$7)/CA$7 -> 0.13098952 | CG14: =7961/7112-1 -> 0.1193757 | CH14: =7885/7413-1 -> 0.063671928 | CI14: =8086/7363-1 -> 0.098193671 | CJ14: =8941/8361-1 -> 0.069369693 | CK14: =+SUMPRODUCT(CG14:CJ14,CB$7:CE$7)/CF$7 -> 0.08665646 | CL14: =6882/7774-1 -> -0.11474145 | CM14: =4389/7831-1 -> -0.43953518 | CN14: =4913/8036-1 -> -0.38862618 | CO14: =5848/8866-1 -> -0.34040153 | CP14: =+SUMPRODUCT(CL14:CO14,CG$7:CJ$7)/CK$7 -> -0.32145242 | CQ14: =4992/6892-1 -> -0.27568195 | CR14: =4828/4372-1 -> 0.10430009 | CS14: =5408/4908-1 -> 0.10187449 | CT14: =6072/5847-1 -> 0.038481272 | CU14: =+SUMPRODUCT(CQ14:CT14,CL$7:CO$7)/CP$7 -> -0.032511922 | CV14: =5612/4991-1 -> 0.12442396 | CW14: =6146/4839-1 -> 0.27009713 | CX14: =6726/5398-1 -> 0.24601704 | CY14: =7645/6082-1 -> 0.25698783 | CZ14: =+SUMPRODUCT(CV14:CY14,CQ$7:CT$7)/CU$7 -> 0.22613236 | DA14: =6987/5604-1 -> 0.24678801 | DB14: =7858/6130-1 -> 0.28189233 | DC14: =8401/6710-1 -> 0.25201192 | DD14: =8510/7624-1 -> 0.11621196 | DE14: =+SUMPRODUCT(DA14:DD14,CV$7:CY$7)/CZ$7 -> 0.21821887 | DF14: =DF102 -> 0.1469127 | DG14: =DG102 -> 0.035917541 | DH14: =DH102 -> 0.056967262 | DI14: =DI102 -> 0.15584416 | DJ14: =+SUMPRODUCT(DF14:DI14,DA$7:DD$7)/DE$7 -> 0.09804027 | DK14: =DK102 -> 0.11398515 | DL14: =DL102 -> 0.23928702 | DM14: =DM102 -> 0.12555742 | DN14: =DN102 -> 0.07353882 | DO14: =+SUMPRODUCT(DK14:DN14,DF$7:DI$7)/DJ$7 -> 0.13489227 | DP14: =DP102 -> 0.13802689 | DQ14: =DQ102 -> 0.13040587 | DR14: =DR102 -> 0.12859414 | DS14: =DS102 -> 0.15470856 | DT14: =+SUMPRODUCT(DP14:DS14,DK$7:DN$7)/DO$7 -> 0.13814259 | DU14: =DU102 -> 0.085526392 | DV14: =DV102 -> 0.068933765
B15: Acquisitions/ divestitures | AG15: 0 | AI15: 0 | AJ15: 0 | AK15: 0 | AL15: 0 | AM15: =AVERAGE(AI15:AL15) -> 0 | AN15: 0.0088343379 | AO15: -0.0097138179 | AP15: -0.014711018 | AQ15: -0.011714222 | AS15: 0 | AT15: 0 | AU15: 0 | AV15: 0 | AW15: 0 | AX15: 0 | AY15: 0 | AZ15: 0 | BA15: 0 | BC15: 0 | BD15: 0 | BE15: 0.022 | BF15: =BF17-BF14 -> 0.05858972 | BG15: =+SUMPRODUCT(BC15:BF15,AX$7:BA$7)/BB$7 -> 0.021280984 | BH15: 0.043 | BI15: =((3/12)*1300)/BD7 -> 0.061286064 | BJ15: =((1/12)*1300)/BE7 -> 0.020196371 | BK15: 0 | BL15: =+SUMPRODUCT(BH15:BK15,BC$7:BF$7)/BG$7 -> 0.029734623 | BM15: 0 | BN15: 0 | BO15: 0 | BP15: 0 | BQ15: =+SUMPRODUCT(BM15:BP15,BH$7:BK$7)/BL$7 -> 0 | BR15: 0 | BS15: 0 | BT15: 0 | BU15: 0 | BV15: =+SUMPRODUCT(BR15:BU15,BM$7:BP$7)/BQ$7 -> 0 | BW15: 0 | BX15: 0 | BY15: 0 | BZ15: 0 | CA15: =+SUMPRODUCT(BW15:BZ15,BR$7:BU$7)/BV$7 -> 0 | CB15: 0 | CC15: 0 | CD15: 0 | CE15: 0 | CF15: =+SUMPRODUCT(CB15:CE15,BW$7:BZ$7)/CA$7 -> 0 | CG15: 0 | CH15: =(0-105)/CC7 -> -0.013964623 | CI15: =(25-117)/CD7 -> -0.012299465 | CJ15: =(0-95)/CE7 -> -0.011234626 | CK15: =+SUMPRODUCT(CG15:CJ15,CB$7:CE$7)/CF$7 -> -0.0095527857 | CL15: =(13-180)/CG7 -> -0.020995725 | CM15: =(0-46)/CH7 -> -0.0058397867 | CN15: =(0-73)/CI7 -> -0.0090023431 | CO15: =(0-70)/CJ7 -> -0.0078334825 | CP15: =+SUMPRODUCT(CL15:CO15,CG$7:CJ$7)/CK$7 -> -0.010828568 | CQ15: =(0-25)/CL7 -> -0.0036273941 | CR15: =(0-11)/CM7 -> -0.0025091241 | CS15: =(0-12)/CN7 -> -0.0024395202 | CT15: =(0-0)/CO7 -> 0 | CU15: =+SUMPRODUCT(CQ15:CT15,CL$7:CO$7)/CP$7 -> -0.0021776608 | CV15: =(0-0)/CQ7 -> 0 | CW15: =(0-0)/CR7 -> 0 | CX15: =(0-0)/CS7 -> 0 | CY15: 0 | CZ15: =+SUMPRODUCT(CV15:CY15,CQ$7:CT$7)/CU$7 -> 0 | DA15: =(0-0)/CV7 -> 0 | DB15: 0 | DC15: 0 | DD15: 0 | DE15: =+SUMPRODUCT(DA15:DD15,CV$7:CY$7)/CZ$7 -> 0 | DF15: 0 | DG15: 0 | DH15: 0 | DI15: 0 | DJ15: =+SUMPRODUCT(DF15:DI15,DA$7:DD$7)/DE$7 -> 0 | DK15: 0 | DL15: 0 | DM15: 0 | DN15: 0 | DO15: =+SUMPRODUCT(DK15:DN15,DF$7:DI$7)/DJ$7 -> 0 | DP15: 0 | DQ15: 0 | DR15: 0 | DS15: 0 | DT15: =+SUMPRODUCT(DP15:DS15,DK$7:DN$7)/DO$7 -> 0 | DU15: 0 | DV15: 0
B16: Currency | AG16: -0.013941212 | AH16: 0.01081267 | AI16: -0.019402314 | AJ16: -0.018985538 | AK16: -0.0073645414 | AL16: 0.018311695 | AM16: =AVERAGE(AI16:AL16) -> -0.0068601743 | AN16: 0.0088343379 | AO16: -0.0097138179 | AP16: -0.014711018 | AQ16: -0.011714222 | AR16: =AVERAGE(AN16:AQ16) -> -0.0068261801 | AS16: 0 | AT16: 0 | AU16: 0 | AV16: 0 | AW16: 0 | BG16: =+SUMPRODUCT(BC16:BF16,AX$7:BA$7)/BB$7 -> 0 | BH16: -0.006 | BL16: =+SUMPRODUCT(BH16:BK16,BC$7:BF$7)/BG$7 -> -0.0013894391 | BM16: -0.01 | BN16: -0.01 | BO16: 0 | BP16: 0 | BQ16: =+SUMPRODUCT(BM16:BP16,BH$7:BK$7)/BL$7 -> -0.0049470613 | BR16: 0 | BS16: 0 | BT16: 0 | BU16: 0.01 | BV16: =+SUMPRODUCT(BR16:BU16,BM$7:BP$7)/BQ$7 -> 0.0027306273 | BW16: 0.011 | BX16: 0 | BY16: 0.002 | BZ16: 0 | CA16: =+SUMPRODUCT(BW16:BZ16,BR$7:BU$7)/BV$7 -> 0.0031028941 | CB16: 0.006 | CC16: 0.003 | CD16: 0 | CE16: -0.004 | CF16: =+SUMPRODUCT(CB16:CE16,BW$7:BZ$7)/CA$7 -> 0.0011809129 | CG16: =-7/CB7 -> -0.00098425197 | CH16: =-8/CC7 -> -0.0010639713 | CI16: =-3/CD7 -> -0.00040106952 | CJ16: =-5/CE7 -> -0.00059129612 | CK16: =+SUMPRODUCT(CG16:CJ16,CB$7:CE$7)/CF$7 -> -0.00075244545 | CL16: =-2/CG7 -> -0.00025144581 | CM16: =-5/CH7 -> -0.00063475943 | CN16: =6/CI7 -> 0.00073991861 | CO16: =-1/CJ7 -> -0.00011190689 | CP16: =+SUMPRODUCT(CL16:CO16,CG$7:CJ$7)/CK$7 -> -6.0834651e-05 | CQ16: =10/CL7 -> 0.0014509576 | CR16: =12/CM7 -> 0.0027372263 | CS16: =-9/CN7 -> -0.0018296402 | CT16: =8/CO7 -> 0.001368223 | CU16: =+SUMPRODUCT(CQ16:CT16,CL$7:CO$7)/CP$7 -> 0.00095272661 | CV16: =(-9-1)/CQ7 -> -0.0020032051 | CW16: =-19/CR7 -> -0.0039256198 | CX16: =-22/CS7 -> -0.0040755835 | CY16: =(-29-1)/CT7 -> -0.0049342105 | CZ16: =+SUMPRODUCT(CV16:CY16,CQ$7:CT$7)/CU$7 -> -0.0038010324 | DA16: =(-6-1)/CV7 -> -0.0012493307 | DB16: =(2-3)/CW7 -> -0.00016321201 | DC16: =(8--5)/CX7 -> 0.0019388516 | DD16: =(10--9)/CY7 -> 0.0024950755 | DE16: =+SUMPRODUCT(DA16:DD16,CV$7:CY$7)/CZ$7 -> 0.00092130518 | DF16: 0 | DG16: 0 | DH16: 0 | DI16: 0 | DJ16: =+SUMPRODUCT(DF16:DI16,DA$7:DD$7)/DE$7 -> 0 | DK16: 0 | DL16: 0 | DM16: 0 | DN16: 0 | DO16: =+SUMPRODUCT(DK16:DN16,DF$7:DI$7)/DJ$7 -> 0 | DP16: 0 | DQ16: 0 | DR16: 0 | DS16: 0 | DT16: =+SUMPRODUCT(DP16:DS16,DK$7:DN$7)/DO$7 -> 0 | DU16: 0 | DV16: 0
B17: Total | I17: =I7/H7-1 -> -0.056727403 | N17: =N7/I7-1 -> 0.055666572 | S17: =S7/N7-1 -> 0.065981612 | X17: =X7/S7-1 -> 0.1007103 | Y17: =Y7/T7-1 -> 0.14651163 | Z17: =Z7/U7-1 -> 0.24094919 | AA17: =AA7/V7-1 -> 0.35333546 | AB17: =AB7/W7-1 -> 0.40758294 | AC17: =AC7/X7-1 -> 0.29207959 | AD17: =AD7/Y7-1 -> 0.25181107 | AE17: =AE7/Z7-1 -> 0.20691346 | ... BD17: =BD7/AY7-1 -> 0.092276004 | BE17: =SUM(BE14:BE16) -> 0.122 | BF17: =BF7/BA7-1 -> 0.12858972 | BG17: =SUM(BG14:BG16) -> 0.095892868 | BH17: =SUM(BH14:BH16) -> 0.139 | BI17: =SUM(BI14:BI16) -> 0.16128606 | BJ17: =SUM(BJ14:BJ16) -> 0.062196371 | BK17: =SUM(BK14:BK16) -> 0.05 | BL17: =SUM(BL14:BL16) -> 0.10052975 | BM17: =BM7/BH7-1 -> -0.017999308 | BN17: =SUM(BN14:BN16) -> 0.03 | BO17: =SUM(BO14:BO16) -> 0.053 | BP17: =SUM(BP14:BP16) -> 0.05 | BQ17: =SUM(BQ14:BQ16) -> 0.028775907 | BR17: =SUM(BR14:BR16) -> 0.104 | BS17: =SUM(BS14:BS16) -> 0.04 | BT17: =SUM(BT14:BT16) -> 0.05 | BU17: =SUM(BU14:BU16) -> 0.07 | ... DV17: =SUM(DV14:DV16) -> 0.068933765
B19: Operating income | CL19: Op margin now includes restructuring expense
B20: Operating margin | H20: =Aerospace!H9/Aerospace!H7 -> 0.18490261 | I20: =Aerospace!I9/Aerospace!I7 -> 0.20439623 | N20: =Aerospace!N9/Aerospace!N7 -> 0.20172165 | S20: =Aerospace!S9/Aerospace!S7 -> 0.2135126 | T20: =Aerospace!T9/Aerospace!T7 -> 0.20830565 | U20: =Aerospace!U9/Aerospace!U7 -> 0.22147855 | V20: =Aerospace!V9/Aerospace!V7 -> 0.21991701 | W20: =Aerospace!W9/Aerospace!W7 -> 0.21131865 | X20: =Aerospace!X9/Aerospace!X7 -> 0.21525697 | Y20: =Aerospace!Y9/Aerospace!Y7 -> 0.20254999 | Z20: =Aerospace!Z9/Aerospace!Z7 -> 0.20299093 | ... AW20: =Aerospace!AW9/Aerospace!AW7 -> 0.18622408 | AX20: =Aerospace!AX11/Aerospace!AX7 -> 0.17624208 | AY20: =Aerospace!AY11/Aerospace!AY7 -> 0.18990731 | AZ20: =Aerospace!AZ11/Aerospace!AZ7 -> 0.19326501 | BA20: =Aerospace!BA11/Aerospace!BA7 -> 0.19004939 | BB20: =Aerospace!BB11/Aerospace!BB7 -> 0.18740622 | BC20: =Aerospace!BC11/Aerospace!BC7 -> 0.18446985 | BD20: =Aerospace!BD11/Aerospace!BD7 -> 0.20120686 | BE20: =Aerospace!BE11/Aerospace!BE7 -> 0.20339299 | ... CK20: =Aerospace!CK11/Aerospace!CK7 -> 0.20741574 | CL20: =Aerospace!CL9/Aerospace!CL7 -> 0.14552057 | CM20: =Aerospace!CM9/Aerospace!CM7 -> -0.15670577 | CN20: =Aerospace!CN9/Aerospace!CN7 -> 0.071062272 | CO20: =Aerospace!CO9/Aerospace!CO7 -> 0.096424462 | CP20: =Aerospace!CP9/Aerospace!CP7 -> 0.055769839 | CQ20: =Aerospace!CQ9/Aerospace!CQ7 -> 0.12840545 | CR20: =Aerospace!CR9/Aerospace!CR7 -> 0.036363636 | CS20: =Aerospace!CS9/Aerospace!CS7 -> 0.15672471 | ... DE20: =Aerospace!DE9/Aerospace!DE7 -> 0.19247718 | DF20: =SEG!DF89 -> 0.1919267 | DG20: =SEG!DG89 -> 0.23069439 | DH20: =SEG!DH89 -> 0.20328749 | DI20: =SEG!DI89 -> 0.20123494 | DJ20: =Aerospace!DJ9/Aerospace!DJ7 -> 0.20651462 | DK20: =SEG!DK89 -> 0.23841795 | DL20: =SEG!DL89 -> 0.23022362 | DM20: =SEG!DM89 -> 0.2127217 | DN20: =SEG!DN89 -> 0.19215738 | DO20: =SEG!DO89 -> 0.21751435 | DP20: =SEG!DP89 -> 0.23223358 | DQ20: =SEG!DQ89 -> 0.22621109 | DR20: =SEG!DR89 -> 0.22032073 | ... DV20: =SEG!DV89 -> 0.22638396
B24: Growth rates
B25: Yr/Yr Growth Rates
B26: Revenue | I26: =Aerospace!I7/Aerospace!H7-1 -> -0.056727403 | N26: =Aerospace!N7/Aerospace!I7-1 -> 0.055666572 | S26: =Aerospace!S7/Aerospace!N7-1 -> 0.065981612 | X26: =Aerospace!X7/Aerospace!S7-1 -> 0.1007103 | Y26: =Aerospace!Y7/Aerospace!T7-1 -> 0.14651163 | Z26: =Aerospace!Z7/Aerospace!U7-1 -> 0.24094919 | AA26: =Aerospace!AA7/Aerospace!V7-1 -> 0.35333546 | AB26: =Aerospace!AB7/Aerospace!W7-1 -> 0.40758294 | AC26: =Aerospace!AC7/Aerospace!X7-1 -> 0.29207959 | AD26: =Aerospace!AD7/Aerospace!Y7-1 -> 0.25181107 | AE26: =Aerospace!AE7/Aerospace!Z7-1 -> 0.20691346 | ... DN26: =Aerospace!DN7/Aerospace!DI7-1 -> 0.07353882 | DO26: =Aerospace!DO7/Aerospace!DF7-1 -> 3.9310736 | DP26: =Aerospace!DP7/Aerospace!DK7-1 -> 0.13802689 | DQ26: =Aerospace!DQ7/Aerospace!DL7-1 -> 0.13040587 | DR26: =Aerospace!DR7/Aerospace!DM7-1 -> 0.12859414 | DS26: =Aerospace!DS7/Aerospace!DN7-1 -> 0.15470856 | DT26: =Aerospace!DT7/Aerospace!DK7-1 -> 4.0355128 | DU26: =Aerospace!DU7/Aerospace!DH7-1 -> 4.5016331 | DV26: =Aerospace!DV7/Aerospace!DI7-1 -> 4.3236888
B27: EBIT | I27: =Aerospace!I9/Aerospace!H9-1 -> 0.042718447 | N27: =Aerospace!N9/Aerospace!I9-1 -> 0.041852886 | S27: =Aerospace!S9/Aerospace!N9-1 -> 0.12828991 | X27: =Aerospace!X9/Aerospace!S9-1 -> 0.10970297 | Y27: =Aerospace!Y9/Aerospace!T9-1 -> 0.11483254 | Z27: =Aerospace!Z9/Aerospace!U9-1 -> 0.13736264 | AA27: =Aerospace!AA9/Aerospace!V9-1 -> 0.068214804 | AB27: =Aerospace!AB9/Aerospace!W9-1 -> 0.2651715 | AC27: =Aerospace!AC9/Aerospace!X9-1 -> 0.14989293 | AD27: =Aerospace!AD9/Aerospace!Y9-1 -> 0.10872675 | AE27: =Aerospace!AE9/Aerospace!Z9-1 -> 0.10386473 | ... DN27: =Aerospace!DN9/Aerospace!DI9-1 -> 0.025112274 | DO27: =Aerospace!DO9/Aerospace!DF9-1 -> 4.5884839 | DP27: =Aerospace!DP9/Aerospace!DK9-1 -> 0.10850738 | DQ27: =Aerospace!DQ9/Aerospace!DL9-1 -> 0.11070421 | DR27: =Aerospace!DR9/Aerospace!DM9-1 -> 0.16891075 | DS27: =Aerospace!DS9/Aerospace!DN9-1 -> 0.27033453 | DT27: =Aerospace!DT9/Aerospace!DK9-1 -> 3.6907362 | DU27: =Aerospace!DU9/Aerospace!DH9-1 -> 5.0711211 | DV27: =Aerospace!DV9/Aerospace!DI9-1 -> 4.9890084
B29: Qtr/Qtr Growth Rates
B30: Revenue | U30: =Aerospace!U7/Aerospace!T7-1 -> 0.092026578 | V30: =Aerospace!V7/Aerospace!U7-1 -> -0.046851232 | W30: =Aerospace!W7/Aerospace!V7-1 -> 0.14490903 | Y30: =Aerospace!Y7/Aerospace!W7-1 -> -0.037914692 | Z30: =Aerospace!Z7/Aerospace!Y7-1 -> 0.18197624 | AA30: =Aerospace!AA7/Aerospace!Z7-1 -> 0.039470458 | AB30: =Aerospace!AB7/Aerospace!AA7-1 -> 0.19080189 | AD30: =Aerospace!AD7/Aerospace!AB7-1 -> -0.14438503 | AE30: =Aerospace!AE7/Aerospace!AD7-1 -> 0.13958333 | AF30: =Aerospace!AF7/Aerospace!AE7-1 -> -0.01665651 | AG30: =Aerospace!AG7/Aerospace!AF7-1 -> 0.064862632 | AI30: =Aerospace!AI7/Aerospace!AG7-1 -> -0.06556741 | AJ30: =Aerospace!AJ7/Aerospace!AI7-1 -> -0.041104422 | AK30: =Aerospace!AK7/Aerospace!AJ7-1 -> -0.016670275 | AL30: =Aerospace!AL7/Aerospace!AK7-1 -> 0.045794804 | AN30: =Aerospace!AN7/Aerospace!AL7-1 -> -0.12315789 | AO30: =Aerospace!AO7/Aerospace!AN7-1 -> 0.022569028 | AP30: =Aerospace!AP7/Aerospace!AO7-1 -> 0.030993191 | AQ30: =Aerospace!AQ7/Aerospace!AP7-1 -> 0.094056024 | AS30: =Aerospace!AS7/Aerospace!AQ7-1 -> -0.090757702 | AT30: =Aerospace!AT7/Aerospace!AS7-1 -> 0.083333333 | AU30: =Aerospace!AU7/Aerospace!AT7-1 -> 0.021766695 | AV30: =Aerospace!AV7/Aerospace!AU7-1 -> 0.018407446 | AX30: =Aerospace!AX7/Aerospace!AV7-1 -> -0.0067018684 | AY30: =Aerospace!AY7/Aerospace!AX7-1 -> -0.007360458 | AZ30: =Aerospace!AZ7/Aerospace!AY7-1 -> -0.015242019 | BA30: =Aerospace!BA7/Aerospace!AZ7-1 -> 0.14348463 | BC30: =Aerospace!BC7/Aerospace!BA7-1 -> -0.071885861 | BD30: =Aerospace!BD7/Aerospace!BC7-1 -> 0.045132046 | BE30: =Aerospace!BE7/Aerospace!BD7-1 -> 0.011502923 | BF30: =Aerospace!BF7/Aerospace!BE7-1 -> 0.150261 | BH30: =Aerospace!BH7/Aerospace!BF7-1 -> -0.063533225 | BI30: =Aerospace!BI7/Aerospace!BH7-1 -> 0.053997923 | BJ30: =Aerospace!BJ7/Aerospace!BI7-1 -> -0.064367816 | BK30: =Aerospace!BK7/Aerospace!BJ7-1 -> 0.12741313 | BM30: =Aerospace!BM7/Aerospace!BK7-1 -> -0.11674969 | BN30: =Aerospace!BN7/Aerospace!BM7-1 -> 0.10186817 | BO30: =Aerospace!BO7/Aerospace!BN7-1 -> -0.040147153 | BP30: =Aerospace!BP7/Aerospace!BO7-1 -> 0.12214631 | BR30: =Aerospace!BR7/Aerospace!BP7-1 -> -0.07009207 | BS30: =Aerospace!BS7/Aerospace!BR7-1 -> 0.039763654 | BT30: =Aerospace!BT7/Aerospace!BS7-1 -> -0.032406696 | BU30: =Aerospace!BU7/Aerospace!BT7-1 -> 0.14079365 | BW30: =Aerospace!BW7/Aerospace!BU7-1 -> -0.071518019 | BX30: =Aerospace!BX7/Aerospace!BW7-1 -> -0.0058444478 | BY30: =Aerospace!BY7/Aerospace!BX7-1 -> 0.0093457944 | BZ30: =Aerospace!BZ7/Aerospace!BY7-1 -> 0.046893668 | CB30: =Aerospace!CB7/Aerospace!BZ7-1 -> 0.014550642 | CC30: =Aerospace!CC7/Aerospace!CB7-1 -> 0.057227222 | CD30: =Aerospace!CD7/Aerospace!CC7-1 -> -0.00518686 | CE30: =Aerospace!CE7/Aerospace!CD7-1 -> 0.13048128 | CG30: =Aerospace!CG7/Aerospace!CE7-1 -> -0.059366131 | CH30: =Aerospace!CH7/Aerospace!CG7-1 -> -0.0096806638 | CI30: =Aerospace!CI7/Aerospace!CH7-1 -> 0.029452837 | CJ30: =Aerospace!CJ7/Aerospace!CI7-1 -> 0.10198545 | CL30: =Aerospace!CL7/Aerospace!CJ7-1 -> -0.22873769 | CM30: =Aerospace!CM7/Aerospace!CL7-1 -> -0.36390017 | CN30: =Aerospace!CN7/Aerospace!CM7-1 -> 0.12203467 | CO30: =Aerospace!CO7/Aerospace!CN7-1 -> 0.18865623 | CQ30: =Aerospace!CQ7/Aerospace!CO7-1 -> -0.14622884 | CR30: =Aerospace!CR7/Aerospace!CQ7-1 -> -0.030448718 | CS30: =Aerospace!CS7/Aerospace!CR7-1 -> 0.11528926 | CT30: =Aerospace!CT7/Aerospace!CS7-1 -> 0.12634309 | CV30: =Aerospace!CV7/Aerospace!CT7-1 -> -0.078453947 | CW30: =Aerospace!CW7/Aerospace!CV7-1 -> 0.093521328 | CX30: =Aerospace!CX7/Aerospace!CW7-1 -> 0.094336543 | CY30: =Aerospace!CY7/Aerospace!CX7-1 -> 0.13571961 | DA30: =Aerospace!DA7/Aerospace!CY7-1 -> -0.08325673 | DB30: =Aerospace!DB7/Aerospace!DA7-1 -> 0.12591319 | DC30: =Aerospace!DC7/Aerospace!DB7-1 -> 0.069847328 | DD30: =Aerospace!DD7/Aerospace!DC7-1 -> 0.013200143 | DF30: =Aerospace!DF7/Aerospace!DD7-1 -> -0.052112676 | DG30: =Aerospace!DG7/Aerospace!DE7-1 -> -0.74117092 | DH30: =Aerospace!DH7/Aerospace!DG7-1 -> 0.087559285 | DI30: =Aerospace!DI7/Aerospace!DH7-1 -> 0.10466286 | DK30: =Aerospace!DK7/Aerospace!DI7-1 -> -0.088875392 | DL30: =Aerospace!DL7/Aerospace!DK7-1 -> 0.12776358 | DM30: =Aerospace!DM7/Aerospace!DL7-1 -> -0.008387351 | DN30: =Aerospace!DN7/Aerospace!DM7-1 -> 0.053609925 | DP30: =Aerospace!DP7/Aerospace!DN7-1 -> -0.034143637 | DQ30: =Aerospace!DQ7/Aerospace!DP7-1 -> 0.1202113 | DR30: =Aerospace!DR7/Aerospace!DQ7-1 -> -0.0099766357 | DS30: =Aerospace!DS7/Aerospace!DR7-1 -> 0.077989293
B31: EBIT | U31: =Aerospace!U9/Aerospace!T9-1 -> 0.16108453 | V31: =Aerospace!V9/Aerospace!U9-1 -> -0.053571429 | W31: =Aerospace!W9/Aerospace!V9-1 -> 0.10014514 | Y31: =Aerospace!Y9/Aerospace!W9-1 -> -0.077836412 | Z31: =Aerospace!Z9/Aerospace!Y9-1 -> 0.18454936 | AA31: =Aerospace!AA9/Aerospace!Z9-1 -> -0.11111111 | AB31: =Aerospace!AB9/Aerospace!AA9-1 -> 0.30298913 | AD31: =Aerospace!AD9/Aerospace!AB9-1 -> -0.19186653 | AE31: =Aerospace!AE9/Aerospace!AD9-1 -> 0.17935484 | AF31: =Aerospace!AF9/Aerospace!AE9-1 -> -0.087527352 | AG31: =Aerospace!AG9/Aerospace!AF9-1 -> 0.39208633 | AI31: =Aerospace!AI9/Aerospace!AG9-1 -> -0.069767442 | AJ31: =Aerospace!AJ9/Aerospace!AI9-1 -> -0.14537037 | AK31: =Aerospace!AK9/Aerospace!AJ9-1 -> 0.05092091 | AL31: =Aerospace!AL9/Aerospace!AK9-1 -> -0.020618557 | AN31: =Aerospace!AN9/Aerospace!AL9-1 -> -0.15894737 | AO31: =Aerospace!AO9/Aerospace!AN9-1 -> 0.10012516 | AP31: =Aerospace!AP9/Aerospace!AO9-1 -> -0.084186576 | AQ31: =Aerospace!AQ9/Aerospace!AP9-1 -> 0.019875776 | AS31: =Aerospace!AS9/Aerospace!AQ9-1 -> 0.024360536 | AT31: =Aerospace!AT9/Aerospace!AS9-1 -> 0.14030916 | AU31: =Aerospace!AU9/Aerospace!AT9-1 -> -0.10114703 | AV31: =Aerospace!AV9/Aerospace!AU9-1 -> -0.013921114 | AX31: =Aerospace!AX9/Aerospace!AV9-1 -> 0.014117647 | AY31: =Aerospace!AY9/Aerospace!AX9-1 -> 0.069605568 | AZ31: =Aerospace!AZ9/Aerospace!AY9-1 -> 0.0021691974 | BA31: =Aerospace!BA9/Aerospace!AZ9-1 -> 0.12445887 | BC31: =Aerospace!BC9/Aerospace!BA9-1 -> -0.099133782 | BD31: =Aerospace!BD9/Aerospace!BC9-1 -> 0.13995726 | BE31: =Aerospace!BE9/Aerospace!BD9-1 -> 0.022492971 | BF31: =Aerospace!BF9/Aerospace!BE9-1 -> 0.14665445 | BH31: =Aerospace!BH9/Aerospace!BF9-1 -> -0.10871303 | BI31: =Aerospace!BI9/Aerospace!BH9-1 -> 0.073542601 | BJ31: =Aerospace!BJ9/Aerospace!BI9-1 -> 0.055973266 | BK31: =Aerospace!BK9/Aerospace!BJ9-1 -> 0.10522152 | BM31: =Aerospace!BM9/Aerospace!BK9-1 -> -0.059413028 | BN31: =Aerospace!BN9/Aerospace!BM9-1 -> -0.034246575 | BO31: =Aerospace!BO9/Aerospace!BN9-1 -> 0.066193853 | BP31: =Aerospace!BP9/Aerospace!BO9-1 -> 0.16112343 | BR31: =Aerospace!BR9/Aerospace!BP9-1 -> -0.02991725 | BS31: =Aerospace!BS9/Aerospace!BR9-1 -> -0.11548556 | BT31: =Aerospace!BT9/Aerospace!BS9-1 -> 0.10830861 | BU31: =Aerospace!BU9/Aerospace!BT9-1 -> 0.17068273 | BW31: =Aerospace!BW9/Aerospace!BU9-1 -> -0.27215552 | BX31: =Aerospace!BX9/Aerospace!BW9-1 -> 0.079340141 | BY31: =Aerospace!BY9/Aerospace!BX9-1 -> -0.028384279 | BZ31: =Aerospace!BZ9/Aerospace!BY9-1 -> 0.039700375 | CB31: =Aerospace!CB9/Aerospace!BZ9-1 -> 0.15489914 | CC31: =Aerospace!CC9/Aerospace!CB9-1 -> -0.079850281 | CD31: =Aerospace!CD9/Aerospace!CC9-1 -> 0.12881356 | CE31: =Aerospace!CE9/Aerospace!CD9-1 -> 0.034834835 | CG31: =Aerospace!CG9/Aerospace!CE9-1 -> -0.036564132 | CH31: =Aerospace!CH9/Aerospace!CG9-1 -> -0.16566265 | CI31: =Aerospace!CI9/Aerospace!CH9-1 -> 0.24043321 | CJ31: =Aerospace!CJ9/Aerospace!CI9-1 -> 0.1967404 | CL31: =Aerospace!CL9/Aerospace!CJ9-1 -> -0.51219468 | CM31: =Aerospace!CM9/Aerospace!CL9-1 -> -1.6849926 | CN31: =Aerospace!CN9/Aerospace!CM9-1 -> -1.5088156 | CO31: =Aerospace!CO9/Aerospace!CN9-1 -> 0.61288873 | CQ31: =Aerospace!CQ9/Aerospace!CO9-1 -> 0.13694043 | CR31: =Aerospace!CR9/Aerospace!CQ9-1 -> -0.72542902 | CS31: =Aerospace!CS9/Aerospace!CR9-1 -> 3.8068182 | CT31: =Aerospace!CT9/Aerospace!CS9-1 -> 0.43971631 | CV31: =Aerospace!CV9/Aerospace!CT9-1 -> -0.2545156 | CW31: =Aerospace!CW9/Aerospace!CV9-1 -> 0.26431718 | CX31: =Aerospace!CX9/Aerospace!CW9-1 -> 0.1184669 | CY31: =Aerospace!CY9/Aerospace!CX9-1 -> 0.11682243 | DA31: =Aerospace!DA9/Aerospace!CY9-1 -> -0.075313808 | DB31: =Aerospace!DB9/Aerospace!DA9-1 -> 0.11538462 | DC31: =Aerospace!DC9/Aerospace!DB9-1 -> 0.15753888 | DD31: =Aerospace!DD9/Aerospace!DC9-1 -> -0.066588785 | DF31: =Aerospace!DF9/Aerospace!DD9-1 -> -0.030037547 | DG31: =Aerospace!DG9/Aerospace!DE9-1 -> -0.68977923 | DH31: =Aerospace!DH9/Aerospace!DG9-1 -> -0.041644702 | DI31: =Aerospace!DI9/Aerospace!DH9-1 -> 0.093509351 | DK31: =Aerospace!DK9/Aerospace!DI9-1 -> 0.079476861 | DL31: =Aerospace!DL9/Aerospace!DK9-1 -> 0.089002796 | DM31: =Aerospace!DM9/Aerospace!DL9-1 -> -0.083771125 | DN31: =Aerospace!DN9/Aerospace!DM9-1 -> -0.048245088 | DP31: =Aerospace!DP9/Aerospace!DN9-1 -> 0.16729465 | DQ31: =Aerospace!DQ9/Aerospace!DP9-1 -> 0.091160975 | DR31: =Aerospace!DR9/Aerospace!DQ9-1 -> -0.035756084 | DS31: =Aerospace!DS9/Aerospace!DR9-1 -> 0.034336559
B33: Regional Sales Exposure
B34: $
B35: US | BL35: =BL42*BL$7 -> 9835.9 | BM35: =BM42*BM$7 -> 2326.34 | BN35: =BN42*BN$7 -> 2563.32 | BO35: =BO42*BO$7 -> 2460.41 | BP35: =BP42*BP$7 -> 2760.94 | BQ35: =BQ42*BQ$7 -> 9617.79 | BR35: =BR42*BR$7 -> 2442.18 | BS35: =BS42*BS$7 -> 2539.29 | ... DV35: =DV42*DV$7 -> 22325.006
B36: Europe | BL36: =BL43*BL$7 -> 4078.3 | BM36: =BM43*BM$7 -> 964.58 | BN36: =BN43*BN$7 -> 1062.84 | BO36: =BO43*BO$7 -> 1020.17 | BP36: =BP43*BP$7 -> 1144.78 | BQ36: =BQ43*BQ$7 -> 3945.76 | BR36: =BR43*BR$7 -> 1001.92 | BS36: =BS43*BS$7 -> 1041.76 | ... DV36: =DV43*DV$7 -> 11960.416
B37: Asia | BL37: =BL44*BL$7 -> 5037.9 | BM37: =BM44*BM$7 -> 1191.54 | BN37: =BN44*BN$7 -> 1312.92 | BO37: =BO44*BO$7 -> 1260.21 | BP37: =BP44*BP$7 -> 1414.14 | BQ37: =BQ44*BQ$7 -> 5425.42 | BR37: =BR44*BR$7 -> 1377.64 | BS37: =BS44*BS$7 -> 1432.42 | ... DV37: =DV44*DV$7 -> 9604.752
B38: Other Americas | BL38: =BL45*BL$7 -> 1199.5 | BM38: =BM45*BM$7 -> 283.7 | BN38: =BN45*BN$7 -> 312.6 | BO38: =BO45*BO$7 -> 300.05 | BP38: =BP45*BP$7 -> 336.7 | BQ38: =BQ45*BQ$7 -> 1972.88 | BR38: =BR45*BR$7 -> 500.96 | BS38: =BS45*BS$7 -> 520.88 | ... DV38: =DV45*DV$7 -> 3087.36
B39: MEA | BL39: =BL46*BL$7 -> 3838.4 | BM39: =BM46*BM$7 -> 907.84 | BN39: =BN46*BN$7 -> 1000.32 | BO39: =BO46*BO$7 -> 960.16 | BP39: =BP46*BP$7 -> 1077.44 | BQ39: =BQ46*BQ$7 -> 3699.15 | BR39: =BR46*BR$7 -> 939.3 | BS39: =BS46*BS$7 -> 976.65 | ... DV39: =DV46*DV$7 -> 5616.8431
B41: %
B42: US | BL42: 0.41 | BM42: =BL42 -> 0.41 | BN42: =BM42 -> 0.41 | BO42: =BN42 -> 0.41 | BP42: =BO42 -> 0.41 | BQ42: 0.39 | BR42: =BQ42 -> 0.39 | BS42: =BR42 -> 0.39 | BT42: =BS42 -> 0.39 | BU42: =BT42 -> 0.39 | BV42: =10.6/26.3 -> 0.40304183 | BW42: =BV42 -> 0.40304183 | BX42: =BW42 -> 0.40304183 | BY42: =BX42 -> 0.40304183 | BZ42: =BY42 -> 0.40304183 | CA42: =10.8/27 -> 0.4 | CB42: =CA42 -> 0.4 | CC42: =CB42 -> 0.4 | CD42: =CC42 -> 0.4 | CE42: =CD42 -> 0.4 | CF42: =12.5/30.6 -> 0.40849673 | CG42: =$CK42 -> 0.40729483 | CH42: =$CK42 -> 0.40729483 | CI42: =$CK42 -> 0.40729483 | CJ42: =$CK42 -> 0.40729483 | CK42: =13.4/32.9 -> 0.40729483 | CL42: =$CP42 -> 0.50989021 | CM42: =$CP42 -> 0.50989021 | CN42: =$CP42 -> 0.50989021 | CO42: =$CP42 -> 0.50989021 | CP42: =11.239/22.042 -> 0.50989021 | CQ42: =$CU42 -> 0.4540122 | CR42: =$CU42 -> 0.4540122 | CS42: =$CU42 -> 0.4540122 | CT42: =$CU42 -> 0.4540122 | CU42: =9.675/21.31 -> 0.4540122 | CV42: =$CZ42 -> 0.41159309 | CW42: =$CZ42 -> 0.41159309 | CX42: =$CZ42 -> 0.41159309 | CY42: =$CZ42 -> 0.41159309 | CZ42: =10.722/26.05 -> 0.41159309 | DA42: =$DE42 -> 0.42448851 | DB42: =$DE42 -> 0.42448851 | DC42: =$DE42 -> 0.42448851 | DD42: =$DE42 -> 0.42448851 | DE42: =13.486/31.77 -> 0.42448851 | DF42: =DE42 -> 0.42448851 | DG42: =DF42 -> 0.42448851 | DH42: =DG42 -> 0.42448851 | DI42: =DH42 -> 0.42448851 | DJ42: =DI42 -> 0.42448851 | DK42: =DJ42 -> 0.42448851 | DL42: =DK42 -> 0.42448851 | DM42: =DL42 -> 0.42448851 | DN42: =DM42 -> 0.42448851 | DO42: =DJ42 -> 0.42448851 | DP42: =DO42 -> 0.42448851 | DQ42: =DP42 -> 0.42448851 | DR42: =DQ42 -> 0.42448851 | DS42: =DR42 -> 0.42448851 | DT42: =DO42 -> 0.42448851 | DU42: =DT42 -> 0.42448851 | DV42: =DU42 -> 0.42448851
B43: Europe | BL43: 0.17 | BM43: =BL43 -> 0.17 | BN43: =BM43 -> 0.17 | BO43: =BN43 -> 0.17 | BP43: =BO43 -> 0.17 | BQ43: 0.16 | BR43: =BQ43 -> 0.16 | BS43: =BR43 -> 0.16 | BT43: =BS43 -> 0.16 | BU43: =BT43 -> 0.16 | BV43: =4.5/26.3 -> 0.17110266 | BW43: =BV43 -> 0.17110266 | BX43: =BW43 -> 0.17110266 | BY43: =BX43 -> 0.17110266 | BZ43: =BY43 -> 0.17110266 | CA43: =6.3/27 -> 0.23333333 | CB43: =CA43 -> 0.23333333 | CC43: =CB43 -> 0.23333333 | CD43: =CC43 -> 0.23333333 | CE43: =CD43 -> 0.23333333 | CF43: =7/30.6 -> 0.22875817 | CG43: =$CK43 -> 0.22796353 | CH43: =$CK43 -> 0.22796353 | CI43: =$CK43 -> 0.22796353 | CJ43: =$CK43 -> 0.22796353 | CK43: =7.5/32.9 -> 0.22796353 | CL43: =$CP43 -> 0.1945377 | CM43: =$CP43 -> 0.1945377 | CN43: =$CP43 -> 0.1945377 | CO43: =$CP43 -> 0.1945377 | CP43: =4.288/22.042 -> 0.1945377 | CQ43: =$CU43 -> 0.1839512 | CR43: =$CU43 -> 0.1839512 | CS43: =$CU43 -> 0.1839512 | CT43: =$CU43 -> 0.1839512 | CU43: =3.92/21.31 -> 0.1839512 | CV43: =$CZ43 -> 0.23082534 | CW43: =$CZ43 -> 0.23082534 | CX43: =$CZ43 -> 0.23082534 | CY43: =$CZ43 -> 0.23082534 | CZ43: =6.013/26.05 -> 0.23082534 | DA43: =$DE43 -> 0.2274158 | DB43: =$DE43 -> 0.2274158 | DC43: =$DE43 -> 0.2274158 | DD43: =$DE43 -> 0.2274158 | DE43: =7.225/31.77 -> 0.2274158 | DF43: =DE43 -> 0.2274158 | DG43: =DF43 -> 0.2274158 | DH43: =DG43 -> 0.2274158 | DI43: =DH43 -> 0.2274158 | DJ43: =DI43 -> 0.2274158 | DK43: =DJ43 -> 0.2274158 | DL43: =DK43 -> 0.2274158 | DM43: =DL43 -> 0.2274158 | DN43: =DM43 -> 0.2274158 | DO43: =DJ43 -> 0.2274158 | DP43: =DO43 -> 0.2274158 | DQ43: =DP43 -> 0.2274158 | DR43: =DQ43 -> 0.2274158 | DS43: =DR43 -> 0.2274158 | DT43: =DO43 -> 0.2274158 | DU43: =DT43 -> 0.2274158 | DV43: =DU43 -> 0.2274158
B44: Asia | BL44: 0.21 | BM44: =BL44 -> 0.21 | BN44: =BM44 -> 0.21 | BO44: =BN44 -> 0.21 | BP44: =BO44 -> 0.21 | BQ44: 0.22 | BR44: =BQ44 -> 0.22 | BS44: =BR44 -> 0.22 | BT44: =BS44 -> 0.22 | BU44: =BT44 -> 0.22 | BV44: =5.1/26.3 -> 0.19391635 | BW44: =BV44 -> 0.19391635 | BX44: =BW44 -> 0.19391635 | BY44: =BX44 -> 0.19391635 | BZ44: =BY44 -> 0.19391635 | CA44: =5.2/27 -> 0.19259259 | CB44: =CA44 -> 0.19259259 | CC44: =CB44 -> 0.19259259 | CD44: =CC44 -> 0.19259259 | CE44: =CD44 -> 0.19259259 | CF44: =5.8/30.6 -> 0.18954248 | CG44: =$CK44 -> 0.2006079 | CH44: =$CK44 -> 0.2006079 | CI44: =$CK44 -> 0.2006079 | CJ44: =$CK44 -> 0.2006079 | CK44: =6.6/32.9 -> 0.2006079 | CL44: =$CP44 -> 0.1778423 | CM44: =$CP44 -> 0.1778423 | CN44: =$CP44 -> 0.1778423 | CO44: =$CP44 -> 0.1778423 | CP44: =3.92/22.042 -> 0.1778423 | CQ44: =$CU44 -> 0.19601126 | CR44: =$CU44 -> 0.19601126 | CS44: =$CU44 -> 0.19601126 | CT44: =$CU44 -> 0.19601126 | CU44: =(1.758+2.419)/21.31 -> 0.19601126 | CV44: =$CZ44 -> 0.18752399 | CW44: =$CZ44 -> 0.18752399 | CX44: =$CZ44 -> 0.18752399 | CY44: =$CZ44 -> 0.18752399 | CZ44: =(2.154+2.731)/26.05 -> 0.18752399 | DA44: =$DE44 -> 0.18262512 | DB44: =$DE44 -> 0.18262512 | DC44: =$DE44 -> 0.18262512 | DD44: =$DE44 -> 0.18262512 | DE44: =(3.195+2.607)/31.77 -> 0.18262512 | DF44: =DE44 -> 0.18262512 | DG44: =DF44 -> 0.18262512 | DH44: =DG44 -> 0.18262512 | DI44: =DH44 -> 0.18262512 | DJ44: =DI44 -> 0.18262512 | DK44: =DJ44 -> 0.18262512 | DL44: =DK44 -> 0.18262512 | DM44: =DL44 -> 0.18262512 | DN44: =DM44 -> 0.18262512 | DO44: =DJ44 -> 0.18262512 | DP44: =DO44 -> 0.18262512 | DQ44: =DP44 -> 0.18262512 | DR44: =DQ44 -> 0.18262512 | DS44: =DR44 -> 0.18262512 | DT44: =DO44 -> 0.18262512 | DU44: =DT44 -> 0.18262512 | DV44: =DU44 -> 0.18262512
B45: Other Americas | BL45: 0.05 | BM45: =BL45 -> 0.05 | BN45: =BM45 -> 0.05 | BO45: =BN45 -> 0.05 | BP45: =BO45 -> 0.05 | BQ45: 0.08 | BR45: =BQ45 -> 0.08 | BS45: =BR45 -> 0.08 | BT45: =BS45 -> 0.08 | BU45: =BT45 -> 0.08 | BV45: =1.6/26.3 -> 0.060836502 | BW45: =BV45 -> 0.060836502 | BX45: =BW45 -> 0.060836502 | BY45: =BX45 -> 0.060836502 | BZ45: =BY45 -> 0.060836502 | CA45: =1.1/27 -> 0.040740741 | CB45: =CA45 -> 0.040740741 | CC45: =CB45 -> 0.040740741 | CD45: =CC45 -> 0.040740741 | CE45: =CD45 -> 0.040740741 | CF45: =1.5/30.6 -> 0.049019608 | CG45: =$CK45 -> 0.048632219 | CH45: =$CK45 -> 0.048632219 | CI45: =$CK45 -> 0.048632219 | CJ45: =$CK45 -> 0.048632219 | CK45: =1.6/32.9 -> 0.048632219 | CL45: =$CP45 -> 0.040014518 | CM45: =$CP45 -> 0.040014518 | CN45: =$CP45 -> 0.040014518 | CO45: =$CP45 -> 0.040014518 | CP45: =0.882/22.042 -> 0.040014518 | CQ45: =$CU45 -> 0.061473487 | CR45: =$CU45 -> 0.061473487 | CS45: =$CU45 -> 0.061473487 | CT45: =$CU45 -> 0.061473487 | CU45: =1.31/21.31 -> 0.061473487 | CV45: =$CZ45 -> 0.065758157 | CW45: =$CZ45 -> 0.065758157 | CX45: =$CZ45 -> 0.065758157 | CY45: =$CZ45 -> 0.065758157 | CZ45: =1.713/26.05 -> 0.065758157 | DA45: =$DE45 -> 0.058703179 | DB45: =$DE45 -> 0.058703179 | DC45: =$DE45 -> 0.058703179 | DD45: =$DE45 -> 0.058703179 | DE45: =1.865/31.77 -> 0.058703179 | DF45: =DE45 -> 0.058703179 | DG45: =DF45 -> 0.058703179 | DH45: =DG45 -> 0.058703179 | DI45: =DH45 -> 0.058703179 | DJ45: =DI45 -> 0.058703179 | DK45: =DJ45 -> 0.058703179 | DL45: =DK45 -> 0.058703179 | DM45: =DL45 -> 0.058703179 | DN45: =DM45 -> 0.058703179 | DO45: =DJ45 -> 0.058703179 | DP45: =DO45 -> 0.058703179 | DQ45: =DP45 -> 0.058703179 | DR45: =DQ45 -> 0.058703179 | DS45: =DR45 -> 0.058703179 | DT45: =DO45 -> 0.058703179 | DU45: =DT45 -> 0.058703179 | DV45: =DU45 -> 0.058703179
B46: MEA | BL46: 0.16 | BM46: =BL46 -> 0.16 | BN46: =BM46 -> 0.16 | BO46: =BN46 -> 0.16 | BP46: =BO46 -> 0.16 | BQ46: 0.15 | BR46: =BQ46 -> 0.15 | BS46: =BR46 -> 0.15 | BT46: =BS46 -> 0.15 | BU46: =BT46 -> 0.15 | BV46: =4.5/26.3 -> 0.17110266 | BW46: =BV46 -> 0.17110266 | BX46: =BW46 -> 0.17110266 | BY46: =BX46 -> 0.17110266 | BZ46: =BY46 -> 0.17110266 | CA46: =3.6/27 -> 0.13333333 | CB46: =CA46 -> 0.13333333 | CC46: =CB46 -> 0.13333333 | CD46: =CC46 -> 0.13333333 | CE46: =CD46 -> 0.13333333 | CF46: =3.8/30.6 -> 0.12418301 | CG46: =$CK46 -> 0.11550152 | CH46: =$CK46 -> 0.11550152 | CI46: =$CK46 -> 0.11550152 | CJ46: =$CK46 -> 0.11550152 | CK46: =3.8/32.9 -> 0.11550152 | CL46: =$CP46 -> 0.077715271 | CM46: =$CP46 -> 0.077715271 | CN46: =$CP46 -> 0.077715271 | CO46: =$CP46 -> 0.077715271 | CP46: =1.713/22.042 -> 0.077715271 | CQ46: =$CU46 -> 0.10455185 | CR46: =$CU46 -> 0.10455185 | CS46: =$CU46 -> 0.10455185 | CT46: =$CU46 -> 0.10455185 | CU46: =2.228/21.31 -> 0.10455185 | CV46: =$CZ46 -> 0.1043762 | CW46: =$CZ46 -> 0.1043762 | CX46: =$CZ46 -> 0.1043762 | CY46: =$CZ46 -> 0.1043762 | CZ46: =2.719/26.05 -> 0.1043762 | DA46: =$DE46 -> 0.10679887 | DB46: =$DE46 -> 0.10679887 | DC46: =$DE46 -> 0.10679887 | DD46: =$DE46 -> 0.10679887 | DE46: =3.393/31.77 -> 0.10679887 | DF46: =DE46 -> 0.10679887 | DG46: =DF46 -> 0.10679887 | DH46: =DG46 -> 0.10679887 | DI46: =DH46 -> 0.10679887 | DJ46: =DI46 -> 0.10679887 | DK46: =DJ46 -> 0.10679887 | DL46: =DK46 -> 0.10679887 | DM46: =DL46 -> 0.10679887 | DN46: =DM46 -> 0.10679887 | DO46: =DJ46 -> 0.10679887 | DP46: =DO46 -> 0.10679887 | DQ46: =DP46 -> 0.10679887 | DR46: =DQ46 -> 0.10679887 | DS46: =DR46 -> 0.10679887 | DT46: =DO46 -> 0.10679887 | DU46: =DT46 -> 0.10679887 | DV46: =DU46 -> 0.10679887
B47: Total | BL47: =SUM(BL42:BL46) -> 1 | BM47: =BL47 -> 1 | BN47: =BM47 -> 1 | BO47: =BN47 -> 1 | BP47: =BO47 -> 1 | BQ47: =SUM(BQ42:BQ46) -> 1 | BR47: =BQ47 -> 1 | BS47: =BR47 -> 1 | BT47: =BS47 -> 1 | BU47: =BT47 -> 1 | BV47: =SUM(BV42:BV46) -> 1 | BW47: =SUM(BW42:BW46) -> 1 | BX47: =SUM(BX42:BX46) -> 1 | BY47: =SUM(BY42:BY46) -> 1 | BZ47: =SUM(BZ42:BZ46) -> 1 | CA47: =SUM(CA42:CA46) -> 1 | CB47: =SUM(CB42:CB46) -> 1 | CC47: =SUM(CC42:CC46) -> 1 | ... DV47: =SUM(DV42:DV46) -> 1.0000315
B49: Orders
B50: Orders (units)
B51: Commercial Engines | BH51: 796 | BI51: 1061 | BJ51: 1376 | BK51: 1568 | BL51: =SUM(BH51:BK51) -> 4801 | BM51: 1219 | BN51: 981 | BO51: 883 | BP51: 515 | BQ51: =SUM(BM51:BP51) -> 3598 | BR51: 702 | BS51: 753 | BT51: 625 | BU51: 578 | BV51: =SUM(BR51:BU51) -> 2658 | BW51: 870 | BX51: 644 | BY51: 508 | BZ51: 543 | CA51: =SUM(BW51:BZ51) -> 2565 | CB51: 1175 | CC51: 959 | CD51: 1779 | CE51: 859 | CF51: =SUM(CB51:CE51) -> 4772 | CG51: 799 | CH51: 899 | CI51: 297 | CJ51: 395 | CK51: =SUM(CG51:CJ51) -> 2390 | CL51: 168 | CM51: 74 | CN51: 94 | CO51: 402 | CP51: =SUM(CL51:CO51) -> 738 | CQ51: 298 | CR51: 555 | CS51: 418 | CT51: 977 | CU51: =SUM(CQ51:CT51) -> 2248 | CV51: 553 | CW51: 569 | CX51: 181 | CY51: 824 | CZ51: =SUM(CV51:CY51) -> 2127 | DA51: 519 | DB51: 659 | DC51: 798 | DD51: 1269 | DE51: =SUM(DA51:DD51) -> 3245 | DF51: 792 | DG51: 808 | DH51: 1090 | DI51: 1229 | DJ51: =SUM(DF51:DI51) -> 3919 | DK51: 880 | DL51: 1049
B52: Product0163 Engines | BH52: 6 | BI52: 13 | BJ52: 16 | BK52: 165 | BL52: =SUM(BH52:BK52) -> 200 | BM52: 47 | BN52: 38 | BO52: 84 | BP52: 68 | BQ52: =SUM(BM52:BP52) -> 237 | BR52: 7 | BS52: 29 | BT52: 17 | BU52: 90 | BV52: =SUM(BR52:BU52) -> 143 | BW52: 12 | BX52: 22 | BY52: 25 | BZ52: 33 | CA52: =SUM(BW52:BZ52) -> 92 | CB52: 24 | CC52: 269 | CD52: 68 | CE52: 46 | CF52: =SUM(CB52:CE52) -> 407 | CG52: 30 | CH52: 21 | CI52: 99 | CJ52: 14 | CK52: =SUM(CG52:CJ52) -> 164 | CL52: - | CM52: - | CN52: - | CO52: - | CP52: - | CQ52: - | CR52: - | CS52: - | CT52: - | CU52: - | CV52: - | CW52: - | CX52: - | CZ52: - | DA52: - | DB52: - | DC52: - | DD52: - | DE52: - | DJ52: -
B53: Product0211 Engines | BH53: 0 | BI53: 0 | BJ53: 0 | BK53: 0 | BL53: =SUM(BH53:BK53) -> 0 | BM53: 415 | BN53: 218 | BO53: 342 | BP53: 0 | BQ53: =SUM(BM53:BP53) -> 975 | BR53: 443 | BS53: 265 | BT53: 204 | BU53: 255 | BV53: =SUM(BR53:BU53) -> 1167 | BW53: 653 | BX53: 368 | BY53: 54 | BZ53: 343 | CA53: =SUM(BW53:BZ53) -> 1418 | CB53: 994 | CC53: 440 | CD53: 1555 | CE53: 648 | CF53: =SUM(CB53:CE53) -> 3637 | CG53: 636 | CH53: 693 | CI53: 49 | CJ53: 190 | CK53: =SUM(CG53:CJ53) -> 1568 | CL53: 6 | CM53: 24 | CN53: 16 | CO53: 305 | CP53: =SUM(CL53:CO53) -> 351 | CQ53: 141 | CR53: 438 | CS53: 287 | CT53: 591 | CU53: =SUM(CQ53:CT53) -> 1457 | CV53: 442 | CW53: 393 | CX53: 101 | CY53: 579 | CZ53: =SUM(CV53:CY53) -> 1515 | DA53: 281 | DB53: 461 | DC53: 713 | DD53: 1053 | DE53: =SUM(DA53:DD53) -> 2508 | DF53: 594 | DG53: 615 | DH53: 714 | DI53: 1091 | DJ53: =SUM(DF53:DI53) -> 3014 | DK53: 796 | DL53: 860
B54: Other | BH54: =BH51-SUM(BH52:BH53) -> 790 | BI54: =BI51-SUM(BI52:BI53) -> 1048 | BJ54: =BJ51-SUM(BJ52:BJ53) -> 1360 | BK54: =BK51-SUM(BK52:BK53) -> 1403 | BL54: =SUM(BH54:BK54) -> 4601 | BM54: =BM51-SUM(BM52:BM53) -> 757 | BN54: =BN51-SUM(BN52:BN53) -> 725 | BO54: =BO51-SUM(BO52:BO53) -> 457 | BP54: =BP51-SUM(BP52:BP53) -> 447 | BQ54: =SUM(BM54:BP54) -> 2386 | BR54: =BR51-SUM(BR52:BR53) -> 252 | BS54: =BS51-SUM(BS52:BS53) -> 459 | BT54: =BT51-SUM(BT52:BT53) -> 404 | BU54: =BU51-SUM(BU52:BU53) -> 233 | BV54: =SUM(BR54:BU54) -> 1348 | BW54: =BW51-SUM(BW52:BW53) -> 205 | BX54: =BX51-SUM(BX52:BX53) -> 254 | BY54: =BY51-SUM(BY52:BY53) -> 429 | BZ54: =BZ51-SUM(BZ52:BZ53) -> 167 | CA54: =SUM(BW54:BZ54) -> 1055 | CB54: =CB51-SUM(CB52:CB53) -> 157 | CC54: =CC51-SUM(CC52:CC53) -> 250 | CD54: =CD51-SUM(CD52:CD53) -> 156 | CE54: =CE51-SUM(CE52:CE53) -> 165 | CF54: =SUM(CB54:CE54) -> 728 | CG54: =CG51-SUM(CG52:CG53) -> 133 | CH54: =CH51-SUM(CH52:CH53) -> 185 | CI54: =CI51-SUM(CI52:CI53) -> 149 | CJ54: =CJ51-SUM(CJ52:CJ53) -> 191 | CK54: =SUM(CG54:CJ54) -> 658 | CL54: - | CM54: - | CN54: - | CO54: - | CP54: - | CQ54: - | CR54: - | CS54: - | CT54: - | CU54: - | CV54: - | CW54: - | CX54: - | CZ54: - | DA54: - | DB54: - | DC54: - | DD54: - | DE54: - | DJ54: - | DK54: =+DK51-DK53 -> 84 | DL54: =+DL51-DL53 -> 189
B55: Military Engines | BH55: 291 | BI55: 163 | BJ55: 222 | BK55: 63 | BL55: =SUM(BH55:BK55) -> 739 | BM55: 135 | BN55: 177 | BO55: 3 | BP55: 72 | BQ55: =SUM(BM55:BP55) -> 387 | BR55: 286 | BS55: 281 | BT55: 17 | BU55: 440 | BV55: =SUM(BR55:BU55) -> 1024 | BW55: 653 | BX55: 174 | BY55: 183 | BZ55: 93 | CA55: 522 | CB55: 251 | CC55: 277 | CD55: 119 | CE55: 104 | CF55: =SUM(CB55:CE55) -> 751 | CG55: 26 | CH55: 53 | CI55: 154 | CJ55: 568 | CK55: =SUM(CG55:CJ55) -> 801 | CL55: 272 | CM55: 463 | CN55: 116 | CO55: 172 | CP55: =SUM(CL55:CO55) -> 1023 | CQ55: 181 | CR55: 98 | CS55: 389 | CT55: 55 | CU55: =SUM(CQ55:CT55) -> 723 | CV55: 19 | CW55: 14 | CX55: 126 | CY55: 373 | CZ55: =SUM(CV55:CY55) -> 532 | DA55: 156 | DB55: 355 | DC55: 132 | DD55: 88 | DE55: =SUM(DA55:DD55) -> 731 | DF55: 159 | DG55: 62 | DH55: 138 | DI55: 373 | DJ55: =SUM(DF55:DI55) -> 732 | DK55: 169 | DL55: 245
B57: Orders (units) y/y % chg
B58: Commercial Engines | BM58: =IFERROR(BM51/BH51-1,"") -> 0.53140704 | BN58: =IFERROR(BN51/BI51-1,"") -> -0.075400566 | BO58: =IFERROR(BO51/BJ51-1,"") -> -0.35828488 | BP58: =IFERROR(BP51/BK51-1,"") -> -0.67155612 | BQ58: =IFERROR(BQ51/BL51-1,"") -> -0.2505728 | BR58: =IFERROR(BR51/BM51-1,"") -> -0.42411813 | BS58: =IFERROR(BS51/BN51-1,"") -> -0.2324159 | BT58: =IFERROR(BT51/BO51-1,"") -> -0.29218573 | ... DL58: =IFERROR(DL51/DG51-1,"") -> 0.29826733
B59: Product0163 Engines | BM59: =IFERROR(BM52/BH52-1,"") -> 6.8333333 | BN59: =IFERROR(BN52/BI52-1,"") -> 1.9230769 | BO59: =IFERROR(BO52/BJ52-1,"") -> 4.25 | BP59: =IFERROR(BP52/BK52-1,"") -> -0.58787879 | BQ59: =IFERROR(BQ52/BL52-1,"") -> 0.185 | BR59: =IFERROR(BR52/BM52-1,"") -> -0.85106383 | BS59: =IFERROR(BS52/BN52-1,"") -> -0.23684211 | BT59: =IFERROR(BT52/BO52-1,"") -> -0.79761905 | ... CK59: =IFERROR(CK52/CF52-1,"") -> -0.5970516 | CL59: - | CM59: - | CN59: - | CO59: - | CP59: - | CQ59: - | CR59: - | CS59: - | CT59: - | CU59: - | CV59: - | CW59: - | CX59: - | CY59: - | CZ59: - | DA59: - | DB59: - | DC59: - | DD59: - | DE59: - | DF59: - | DG59: - | DH59: - | DI59: - | DJ59: - | DK59: - | DL59: -
B60: Product0211 Engines | BM60: =IFERROR(BM53/BH53-1,"") | BN60: =IFERROR(BN53/BI53-1,"") | BO60: =IFERROR(BO53/BJ53-1,"") | BP60: =IFERROR(BP53/BK53-1,"") | BQ60: =IFERROR(BQ53/BL53-1,"") | BR60: =IFERROR(BR53/BM53-1,"") -> 0.06746988 | BS60: =IFERROR(BS53/BN53-1,"") -> 0.21559633 | BT60: =IFERROR(BT53/BO53-1,"") -> -0.40350877 | ... DL60: =IFERROR(DL53/DG53-1,"") -> 0.39837398
B61: Other | BM61: =IFERROR(BM54/BH54-1,"") -> -0.041772152 | BN61: =IFERROR(BN54/BI54-1,"") -> -0.30820611 | BO61: =IFERROR(BO54/BJ54-1,"") -> -0.66397059 | BP61: =IFERROR(BP54/BK54-1,"") -> -0.68139701 | BQ61: =IFERROR(BQ54/BL54-1,"") -> -0.48141708 | BR61: =IFERROR(BR54/BM54-1,"") -> -0.667107 | BS61: =IFERROR(BS54/BN54-1,"") -> -0.36689655 | BT61: =IFERROR(BT54/BO54-1,"") -> -0.11597374 | ... CK61: =IFERROR(CK54/CF54-1,"") -> -0.096153846 | CL61: - | CM61: - | CN61: - | CO61: - | CP61: - | CQ61: - | CR61: - | CS61: - | CT61: - | CU61: - | CV61: - | CW61: - | CX61: - | CY61: - | CZ61: - | DA61: - | DB61: - | DC61: - | DD61: - | DE61: - | DF61: - | DG61: - | DH61: - | DI61: - | DJ61: - | DK61: - | DL61: -
B62: Military Engines | BM62: =IFERROR(BM55/BH55-1,"") -> -0.53608247 | BN62: =IFERROR(BN55/BI55-1,"") -> 0.085889571 | BO62: =IFERROR(BO55/BJ55-1,"") -> -0.98648649 | BP62: =IFERROR(BP55/BK55-1,"") -> 0.14285714 | BQ62: =IFERROR(BQ55/BL55-1,"") -> -0.47631935 | BR62: =IFERROR(BR55/BM55-1,"") -> 1.1185185 | BS62: =IFERROR(BS55/BN55-1,"") -> 0.58757062 | BT62: =IFERROR(BT55/BO55-1,"") -> 4.6666667 | ... DL62: =IFERROR(DL55/DG55-1,"") -> 2.9516129
B64: Orders y/y % chg
B65: Equipment | BF65: -0.15 | BQ65: =BQ84/BL84-1 -> -0.17575758 | BR65: =BR84/BM84-1 -> -0.33333333 | BS65: =BS84/BN84-1 -> -0.375 | BT65: =BT84/BO84-1 -> -0.25 | BU65: =BU84/BP84-1 -> -0.034482759 | BV65: =BV84/BQ84-1 -> -0.26470588 | BW65: =BW84/BR84-1 -> 0.038461538 | BX65: =BX84/BS84-1 -> 0.12 | ... DL65: =DL84/DG84-1 -> 0.028571429
B66: Services | BF66: 0.11 | BQ66: =BQ85/BL85-1 -> 0.13846154 | BR66: =BR85/BM85-1 -> 0.14285714 | BS66: =BS85/BN85-1 -> 0.083333333 | BT66: =BT85/BO85-1 -> 0.10810811 | BU66: =BU85/BP85-1 -> 0.075 | BV66: =BV85/BQ85-1 -> 0.10135135 | BW66: =BW85/BR85-1 -> 0.125 | BX66: =BX85/BS85-1 -> 0.17948718 | ... DL66: =DL85/DG85-1 -> 0.051948052
B67: Total | BQ67: =BQ86/BL86-1 -> -0.037288136 | BR67: =BR86/BM86-1 -> -0.10810811 | BS67: =BS86/BN86-1 -> -0.15789474 | BT67: =BT86/BO86-1 -> -0.046153846 | BU67: =BU86/BP86-1 -> 0.028985507 | BV67: =BV86/BQ86-1 -> -0.073943662 | BW67: =BW86/BR86-1 -> 0.090909091 | BX67: =BX86/BS86-1 -> 0.15625 | ... DL67: =DL86/DG86-1 -> 0.044642857
B69: Sales | CG69: 100
B70: Sales by sub-segment ($bn)
B71: Commercial Engines | BL71: =BL$81*BL90 -> 16.793 | BM71: =BM$81*BM90 -> 3.9718 | BN71: =BN$81*BN90 -> 4.3764 | BO71: =BO$81*BO90 -> 4.2007 | BP71: =BP$81*BP90 -> 4.7138 | BQ71: =BQ$81*BQ90 -> 18.00253 | BR71: =BR$81*BR90 -> 4.57126 | BS71: =BS$81*BS90 -> 4.81814 | ... BV71: =BV$81*BV90 -> 19.4324 | BW71: 5 | BX71: 4.9 | BY71: 4.8 | BZ71: =CA71-SUM(BW71:BY71) -> 5 | CA71: 19.7 | CB71: 5.3 | CC71: 5.534 | CD71: 5.6 | CE71: 6.3 | CF71: =SUM(CB71:CE71) -> 22.734 | CG71: 5.949 | CH71: 5.848 | CI71: 5.997 | CJ71: =CK71-SUM(CG71:CI71) -> 6.423 | CK71: 24.217 | CL71: 5.113 | CM71: 2.519 | CN71: 3.087 | CO71: =SUM(CO72:CO73) -> 3.761 | CP71: =SUM(CL71:CO71) -> 14.48 | CQ71: 3.354 | CR71: 3.115 | CS71: 3.602 | CT71: =SUM(CT72:CT73) -> 4.289 | CU71: =SUM(CQ71:CT71) -> 14.36 | CV71: 3.853 | CW71: 4.306 | CX71: 4.971 | CY71: =CZ71-SUM(CV71:CX71) -> 5.535 | CZ71: 18.665 | DA71: =data!DA153/1000 -> 5.232 | DB71: =data!DB153/1000 -> 5.737 | DC71: =data!DC153/1000 -> 6.457 | DD71: =data!DD153/1000 -> 6.429 | DE71: =data!DE153/1000 -> 23.855 | DF71: =SUM(DF72:DF73) -> 6.1 | DG71: =SUM(DG72:DG73) -> 6.1 | DH71: =SEG!DH7/1000 -> 7.003 | DI71: =SEG!DI7/1000 -> 7.65 | DJ71: =SEG!DJ7/1000 -> 26.881 | DK71: =SEG!DK7/1000 -> 6.977 | DL71: =SEG!DL7/1000 -> 7.99 | DM71: =SEG!DM7/1000 -> 7.98342 | DN71: =SEG!DN7/1000 -> 8.25588 | DO71: =SEG!DO7/1000 -> 31.2063 | ... DV71: =SEG!DV7/1000 -> 42.460546
B72: Commercial OEM | BW72: =BW91*BW$71 -> 1.9 | BX72: =BX91*BX$71 -> 1.911 | BY72: =BY91*BY$71 -> 1.872 | BZ72: =BZ91*BZ$71 -> 2 | CA72: =SUM(BW72:BZ72) -> 7.683 | CB72: =CB91*CB$71 -> 1.802 | CC72: =CC91*CC$71 -> 2.15826 | CD72: =CD91*CD$71 -> 2.184 | CE72: =CE91*CE$71 -> 2.457 | CF72: =SUM(CB72:CE72) -> 8.60126 | CG72: =CG71-CG73 -> 2.249 | CH72: =CH71-CH73 -> 2.194 | CI72: =CI71-CI73 -> 2.196 | CJ72: 2.318 | CK72: 9 | CL72: 1.819 | CM72: 1.349 | CN72: 1.456 | CO72: 1.678 | CP72: =SUM(CL72:CO72) -> 6.302 | CQ72: 1.365 | CR72: 1.758 | CS72: 1.217 | CT72: 1.425 | CU72: =SUM(CQ72:CT72) -> 5.765 | CV72: 1.133 | CW72: 1.349 | CX72: 1.469 | CY72: 1.855 | CZ72: =SUM(CV72:CY72) -> 5.806 | DA72: 1.523 | DB72: 1.818 | DC72: 1.811 | DD72: 1.875 | DE72: =SUM(DA72:DD72) -> 7.027 | DF72: 1.7 | DG72: 1.4 | DH72: 1.7 | DI72: 2.3 | DJ72: =SUM(DF72:DI72) -> 7.1 | DK72: 1.9 | DL72: 1.9
B73: Commercial AM | BW73: =BW92*BW$71 -> 3.1 | BX73: =BX92*BX$71 -> 2.989 | BY73: =BY92*BY$71 -> 2.928 | BZ73: =BZ92*BZ$71 -> 3 | CA73: =SUM(BW73:BZ73) -> 12.017 | CB73: =CB92*CB$71 -> 3.498 | CC73: =CC92*CC$71 -> 3.37574 | CD73: =CD92*CD$71 -> 3.416 | CE73: =CE92*CE$71 -> 3.843 | CF73: =SUM(CB73:CE73) -> 14.13274 | CG73: =7.354-CH73 -> 3.7 | CH73: 3.654 | CI73: 3.801 | CJ73: 4.104 | CK73: =CK71-CK72 -> 15.217 | CL73: 3.294 | CM73: 1.17 | CN73: 1.631 | CO73: 2.083 | CP73: =SUM(CL73:CO73) -> 8.178 | CQ73: 1.988 | CR73: 1.357 | CS73: 2.385 | CT73: 2.864 | CU73: =SUM(CQ73:CT73) -> 8.594 | CV73: 2.72 | CW73: 2.956 | CX73: 3.502 | CY73: 3.68 | CZ73: =SUM(CV73:CY73) -> 12.858 | DA73: 3.671 | DB73: 3.883 | DC73: 4.588 | DD73: 4.516 | DE73: =SUM(DA73:DD73) -> 16.658 | DF73: 4.4 | DG73: 4.7 | DH73: 5.3 | DI73: 5.4 | DJ73: =SUM(DF73:DI73) -> 19.8 | DK73: 5.1 | DL73: 6.1
B74: Defense (Military Engines) | BL74: =BL$81*BL93 -> 4.0783 | BM74: =BM$81*BM93 -> 0.96458 | BN74: =BN$81*BN93 -> 1.06284 | BO74: =BO$81*BO93 -> 1.02017 | BP74: =BP$81*BP93 -> 1.14478 | BQ74: =BQ$81*BQ93 -> 3.69915 | BR74: =BR$81*BR93 -> 0.87668 | BS74: =BS$81*BS93 -> 0.84643 | ... BV74: =BV$81*BV93 -> 3.4138 | BW74: 0.9 | BX74: 0.9 | BY74: 1 | BZ74: =CA74-SUM(BW74:BY74) -> 1.2 | CA74: 4 | CB74: 1 | CC74: 1.073 | CD74: 0.9 | CE74: 1.1 | CF74: =SUM(CB74:CE74) -> 4.073 | CG74: 1.036 | CH74: 0.976 | CI74: 1.061 | CJ74: 1.316 | CK74: 4.389 | CL74: 0.96 | CM74: 1.161 | CN74: 1.137 | CO74: 1.314 | CP74: =SUM(CL74:CO74) -> 4.572 | CQ74: 0.956 | CR74: 1.041 | CS74: 1.107 | CT74: 1.032 | CU74: =SUM(CQ74:CT74) -> 4.136 | CV74: 1.036 | CW74: 1.096 | CX74: 1.072 | CY74: 1.251 | CZ74: =SUM(CV74:CY74) -> 4.455 | DA74: =SEG!DA8/1000 -> 1.966 | DB74: =SEG!DB8/1000 -> 2.375 | DC74: =SEG!DC8/1000 -> 2.205 | DD74: =SEG!DD8/1000 -> 2.416 | DE74: =data!DE155/1000 -> 5.675 | DF74: =SEG!DF8/1000 -> 2.312 | DG74: =SEG!DG8/1000 -> 2.401 | DH74: =SEG!DH8/1000 -> 2.243 | DI74: =SEG!DI8/1000 -> 2.523 | DJ74: =SEG!DJ8/1000 -> 9.479 | DK74: =SEG!DK8/1000 -> 2.324 | DL74: =SEG!DL8/1000 -> 2.563 | DM74: =SEG!DM8/1000 -> 2.42244 | ... DV74: =SEG!DV8/1000 -> 11.532175
B75: Systems & Other | BL75: =BL$81*BL94 -> 3.1187 | BM75: =BM81-SUM(BM71,BM74) -> 0.73762 | BN75: =BN81-SUM(BN71,BN74) -> 0.81276 | BO75: =BO81-SUM(BO71,BO74) -> 0.78013 | BP75: =BP81-SUM(BP71,BP74) -> 0.87542 | BQ75: =SUM(BM75:BP75) -> 3.20593 | BR75: =BR81-SUM(BR71,BR74) -> 0.81406 | BS75: =BS81-SUM(BS71,BS74) -> 0.84643 | BT75: =BT81-SUM(BT71,BT74) -> 0.819 | BU75: =BU81-SUM(BU71,BU74) -> 0.93431 | BV75: =SUM(BR75:BU75) -> 3.4138 | BW75: =BW81-SUM(BW71,BW74) -> 0.773 | BX75: =BX81-SUM(BX71,BX74) -> 0.834 | BY75: =BY81-SUM(BY71,BY74) -> 0.896 | BZ75: =BZ81-SUM(BZ71,BZ74) -> 0.81 | CA75: =SUM(BW75:BZ75) -> 3.313 | CB75: =CB81-SUM(CB71,CB74) -> 0.812 | CC75: 0.911 | CD75: =CD81-SUM(CD71,CD74) -> 0.98 | CE75: =CE81-SUM(CE71,CE74) -> 1.056 | CF75: =SUM(CB75:CE75) -> 3.759 | CG75: 0.969 | CH75: =1.052+0.001 -> 1.053 | CI75: =1.05+0.001 -> 1.051 | CJ75: =CK75-SUM(CG75:CI75)+0.001 -> 1.197 | CK75: 4.269 | CL75: 0.82 | CM75: 0.703 | CN75: 0.696 | CO75: =CP75-SUM(CL75:CN75) -> 0.772 | CP75: 2.991 | CQ75: 0.682 | CR75: 0.684 | CS75: 0.689 | CT75: =CU75-SUM(CQ75:CS75) -> 0.759 | CU75: 2.814 | CV75: 0.714 | CW75: 0.725 | CX75: 0.707 | CY75: =CZ75-SUM(CV75:CX75) -> 0.829 | CZ75: 2.975 | DA75: =data!DA156/1000 -> -0.153 | DB75: =data!DB156/1000 -> -0.205 | DC75: =data!DC156/1000 -> -0.201 | DD75: =data!DD156/1000 -> -0.298 | DE75: =data!DE156/1000 -> 3.372 | DF75: =data!DF156/1000 -> -0.332 | DG75: =data!DG156/1000 -> -0.31 | DH75: =data!DH156/1000 -> -0.303 | DI75: =SEG!DI10/1000 -> -0.294 | DJ75: =SEG!DJ10/1000 -> -1.239 | DK75: =SEG!DK10/1000 -> -0.3 | DL75: =SEG!DL10/1000 -> -0.402 | DM75: =SEG!DM10/1000 -> -0.34 | DN75: =SEG!DN10/1000 -> -0.35 | DO75: =SEG!DO10/1000 -> -1.392 | DP75: =SEG!DP10/1000 -> -0.325 | ... DV75: =SEG!DV10/1000 -> -1.4
B76: Company0296 Integrated Systems | CF76: 1.6 | CP76: =14.5-CP71 -> 0.02
B77: Company0267 Aero | CF77: 1 | CP77: 0.8
B78: Avionics & Digital Systems | CF78: 0.8
B79: Additive & Other | CF79: 0.4 | CP79: 0.4
B80: Aviation Systems | CP80: 1.7
B81: Total | BL81: =BL$7/1000 -> 23.99 | BM81: =BM$7/1000 -> 5.674 | BN81: =BN$7/1000 -> 6.252 | BO81: =BO$7/1000 -> 6.001 | BP81: =BP$7/1000 -> 6.734 | BQ81: =BQ$7/1000 -> 24.661 | BR81: =BR$7/1000 -> 6.262 | BS81: =BS$7/1000 -> 6.511 | ... BZ81: =BZ$7/1000 -> 7.01 | CA81: =SUM(BW81:BZ81) -> 27.013 | CB81: =CB$7/1000 -> 7.112 | CC81: =SUM(CC71,CC74,CC75) -> 7.518 | CD81: =CD$7/1000 -> 7.48 | CE81: =CE$7/1000 -> 8.456 | CF81: =SUM(CB81:CE81) -> 30.566 | CG81: =SUM(CG71,CG74,CG75) -> 7.954 | CH81: =SUM(CH71,CH74,CH75) -> 7.877 | CI81: =SUM(CI71,CI74,CI75) -> 8.109 | CJ81: =SUM(CJ71,CJ74,CJ75) -> 8.936 | CK81: =SUM(CG81:CJ81) -> 32.876 | CL81: =SUM(CL71,CL74,CL75) -> 6.893 | CM81: =SUM(CM71,CM74,CM75) -> 4.383 | CN81: =SUM(CN71,CN74,CN75) -> 4.92 | CO81: =CO7/1000 -> 5.847 | CP81: =CP7/1000 -> 22.042 | CQ81: =CQ7/1000 -> 4.992 | CR81: =CR7/1000 -> 4.84 | CS81: =SUM(CS71,CS74,CS75) -> 5.398 | CT81: =CT7/1000 -> 6.08 | CU81: =SUM(CU71,CU74,CU75) -> 21.31 | CV81: =SUM(CV71,CV74,CV75) -> 5.603 | CW81: =SUM(CW71,CW74,CW75) -> 6.127 | CX81: =SUM(CX71,CX74,CX75) -> 6.75 | CY81: =SUM(CY71,CY74,CY75) -> 7.615 | CZ81: =SUM(CZ71,CZ74,CZ75) -> 26.095 | DA81: =SUM(DA71,DA74,DA75) -> 7.045 | DB81: =SUM(DB71,DB74,DB75) -> 7.907 | ... DV81: =SUM(DV71,DV74,DV75) -> 52.592722
B83: Orders
B84: Equipment | BG84: 16.1 | BL84: 16.5 | BM84: =7.9-BN84 -> 3.9 | BN84: 4 | BO84: 2.8 | BP84: =BQ84-SUM(BM84:BO84) -> 2.9 | BQ84: 13.6 | BR84: =5.1-BS84 -> 2.6 | BS84: 2.5 | BT84: 2.1 | BU84: =BV84-SUM(BR84:BT84) -> 2.8 | BV84: 10 | BW84: 2.7 | BX84: 2.8 | BY84: 2.2 | BZ84: =CA84-SUM(BW84:BY84) -> 2.9 | CA84: 10.6 | CB84: 3.2 | CC84: 4.5 | CD84: 4.1 | CE84: 3.5 | CF84: =SUM(CB84:CE84) -> 15.3 | CG84: 3.2 | CH84: 3.5 | CI84: 2.971 | CJ84: =CK84-SUM(CG84:CI84) -> 4.829 | CK84: 14.5 | CL84: 2.228 | CM84: 2 | CN84: 1.137 | CO84: =CP84-SUM(CL84:CN84) -> 2.754 | CP84: 8.119 | CQ84: 2.004 | CR84: 2 | CS84: 2.8 | CT84: 3 | CU84: =SUM(CQ84:CT84) -> 9.804 | CV84: 2.5 | CW84: 2.4 | CX84: 2.1 | CY84: 4.4 | CZ84: =SUM(CV84:CY84) -> 11.4 | DA84: 2.5 | DB84: 3.6 | DC84: 3.2 | DD84: 4.2 | DE84: =SUM(DA84:DD84) -> 13.5 | DF84: 4.5 | DG84: 3.5 | DH84: 4.8 | DI84: 6.8 | DJ84: =SUM(DF84:DI84) -> 19.6 | DK84: 3.9 | DL84: 3.6
B85: Services | BG85: 11.1 | BL85: 13 | BM85: =7.1-BN85 -> 3.5 | BN85: 3.6 | BO85: 3.7 | BP85: =BQ85-SUM(BM85:BO85) -> 4 | BQ85: 14.8 | BR85: =7.9-BS85 -> 4 | BS85: 3.9 | BT85: 4.1 | BU85: =BV85-SUM(BR85:BT85) -> 4.3 | BV85: 16.3 | BW85: 4.5 | BX85: 4.6 | BY85: 4.5 | BZ85: =CA85-SUM(BW85:BY85) -> 4.9 | CA85: 18.5 | CB85: 5 | CC85: 5 | CD85: =CD86-CD84 -> 4.9 | CE85: 5.3 | CF85: =SUM(CB85:CE85) -> 20.2 | CG85: 5.5 | CH85: 5.1 | CI85: 5.825 | CJ85: =CJ86-CJ84 -> 5.871 | CK85: =SUM(CG85:CJ85) -> 22.296 | CL85: 5.221 | CM85: 1.7 | CN85: 2.935 | CO85: =CP85-SUM(CL85:CN85) -> 3.615 | CP85: 13.471 | CQ85: 3.488 | CR85: 3.5 | CS85: 4.1 | CT85: 4.7 | CU85: =SUM(CQ85:CT85) -> 15.788 | CV85: 4.7 | CW85: 4.5 | CX85: 5.2 | CY85: 5.3 | CZ85: =SUM(CV85:CY85) -> 19.7 | DA85: 5.7 | DB85: 5.8 | DC85: 6.6 | DD85: 6.4 | DE85: =SUM(DA85:DD85) -> 24.5 | DF85: 6.5 | DG85: 7.7 | DH85: 7.8 | DI85: 8.7 | DJ85: =SUM(DF85:DI85) -> 30.7 | DK85: 8.4 | DL85: 8.1
B86: Total | BF86: 7 | BG86: =SUM(BG84:BG85) -> 27.2 | BL86: =SUM(BL84:BL85) -> 29.5 | BM86: =SUM(BM84:BM85) -> 7.4 | BN86: =SUM(BN84:BN85) -> 7.6 | BO86: =SUM(BO84:BO85) -> 6.5 | BP86: =SUM(BP84:BP85) -> 6.9 | BQ86: =SUM(BQ84:BQ85) -> 28.4 | BR86: =SUM(BR84:BR85) -> 6.6 | BS86: =SUM(BS84:BS85) -> 6.4 | ... BY86: =SUM(BY84:BY85) -> 6.7 | BZ86: =CA86-SUM(BW86:BY86) -> 7.8 | CA86: =SUM(CA84:CA85) -> 29.1 | CB86: =SUM(CB84:CB85) -> 8.2 | CC86: =SUM(CC84:CC85) -> 9.5 | CD86: 9 | CE86: =SUM(CE84:CE85) -> 8.8 | CF86: =SUM(CB86:CE86) -> 35.5 | CG86: =SUM(CG84:CG85) -> 8.7 | CH86: =SUM(CH84:CH85) -> 8.6 | CI86: =SUM(CI84:CI85) -> 8.796 | CJ86: 10.7 | CK86: =SUM(CG86:CJ86) -> 36.796 | CL86: =SUM(CL84:CL85) -> 7.449 | CM86: 3.739 | CN86: =SUM(CN84:CN85) -> 4.072 | CO86: =CP86-SUM(CL86:CN86) -> 6.33 | CP86: =SUM(CP84:CP85) -> 21.59 | CQ86: =SUM(CQ84:CQ85) -> 5.492 | CR86: 5.492 | CS86: =SUM(CS84:CS85) -> 6.9 | CT86: =SUM(CT84:CT85) -> 7.7 | CU86: =SUM(CQ86:CT86) -> 25.584 | CV86: =SUM(CV84:CV85) -> 7.2 | CW86: 6.918 | CX86: 7.3 | CY86: 9.682 | CZ86: =SUM(CV86:CY86) -> 31.1 | DA86: 8.213 | DB86: 9.451 | DC86: 9.793 | DD86: 10.62 | DE86: =SUM(DA86:DD86) -> 38.077 | DF86: 11 | DG86: =SUM(DG84:DG85) -> 11.2 | DH86: =SUM(DH84:DH85) -> 12.6 | DI86: =SUM(DI84:DI85) -> 15.5 | DJ86: =SUM(DF86:DI86) -> 50.3 | DK86: =SUM(DK84:DK85) -> 12.3 | DL86: =SUM(DL84:DL85) -> 11.7
B89: Sales by sub-segment % of total
B90: Commercial Engines | BL90: 0.7 | BM90: =BL90 -> 0.7 | BN90: =BM90 -> 0.7 | BO90: =BN90 -> 0.7 | BP90: =BO90 -> 0.7 | BQ90: 0.73 | BR90: 0.73 | BS90: 0.74 | BT90: 0.74 | BU90: =BT90 -> 0.74 | BV90: 0.74 | BW90: =BW71/BW$81 -> 0.74928818 | BX90: =BX71/BX$81 -> 0.73861923 | BY90: =BY71/BY$81 -> 0.71684588 | BZ90: =BZ71/BZ$81 -> 0.71326676 | CA90: =CA71/CA$81 -> 0.7292785 | CB90: =CB71/CB$81 -> 0.74521935 | CC90: =CC71/CC$81 -> 0.73610003 | CD90: =CD71/CD$81 -> 0.7486631 | ... DO90: =DO71/DO$81 -> 0.78361815 | DQ90: =DQ71/DQ$81 -> 0.79379507 | DR90: =DR71/DR$81 -> 0.80816147 | DS90: =DS71/DS$81 -> 0.79793076 | DT90: =DT71/DT$81 -> 0.79767879 | DU90: =DU71/DU$81 -> 0.80353805 | DV90: =DV71/DV$81 -> 0.80734643
B91: Commercial OEM | BW91: =100%-BW92 -> 0.38 | BX91: =100%-BX92 -> 0.39 | BY91: =100%-BY92 -> 0.39 | BZ91: =100%-BZ92 -> 0.4 | CB91: =100%-CB92 -> 0.34 | CC91: =100%-CC92 -> 0.39 | CD91: =100%-CD92 -> 0.39 | CE91: =100%-CE92 -> 0.39 | CG91: =CG72/CG$71 -> 0.37804673 | CH91: =CH72/CH$71 -> 0.375171 | CI91: =CI72/CI$71 -> 0.36618309 | CJ91: =CJ72/CJ$71 -> 0.36089055 | CK91: =CK72/CK$71 -> 0.37163976 | CL91: =CL72/CL$71 -> 0.35575983 | CM91: =CM72/CM$71 -> 0.53552997 | CN91: =CN72/CN$71 -> 0.47165533 | ... DO91: =DO72/DO$71 -> 0 | DQ91: =DQ72/DQ$71 -> 0 | DR91: =DR72/DR$71 -> 0 | DS91: =DS72/DS$71 -> 0 | DT91: =DT72/DT$71 -> 0 | DU91: =DU72/DU$71 -> 0 | DV91: =DV72/DV$71 -> 0
B92: Commercial AM | BW92: 0.62 | BX92: 0.61 | BY92: 0.61 | BZ92: 0.6 | CB92: 0.66 | CC92: 0.61 | CD92: 0.61 | CE92: 0.61 | CG92: =CG73/CG$71 -> 0.62195327 | CH92: =CH73/CH$71 -> 0.624829 | CI92: =CI73/CI$71 -> 0.63381691 | CJ92: =CJ73/CJ$71 -> 0.63895376 | CK92: =CK73/CK$71 -> 0.62836024 | CL92: =CL73/CL$71 -> 0.64424017 | CM92: =CM73/CM$71 -> 0.46447003 | CN92: =CN73/CN$71 -> 0.52834467 | ... DO92: =DO73/DO$71 -> 0 | DQ92: =DQ73/DQ$71 -> 0 | DR92: =DR73/DR$71 -> 0 | DS92: =DS73/DS$71 -> 0 | DT92: =DT73/DT$71 -> 0 | DU92: =DU73/DU$71 -> 0 | DV92: =DV73/DV$71 -> 0
B93: Military Engines | BL93: 0.17 | BM93: =BL93 -> 0.17 | BN93: =BM93 -> 0.17 | BO93: =BN93 -> 0.17 | BP93: =BO93 -> 0.17 | BQ93: 0.15 | BR93: 0.14 | BS93: 0.13 | BT93: 0.13 | BU93: =BT93 -> 0.13 | BV93: 0.13 | BW93: =BW74/BW$81 -> 0.13487187 | BX93: =BX74/BX$81 -> 0.13566476 | BY93: =BY74/BY$81 -> 0.14934289 | BZ93: =BZ74/BZ$81 -> 0.17118402 | CA93: =CA74/CA$81 -> 0.14807685 | CB93: =CB74/CB$81 -> 0.14060742 | CC93: =CC74/CC$81 -> 0.14272413 | CD93: =CD74/CD$81 -> 0.12032086 | ... DO93: =DO74/DO$81 -> 0.25133621 | DQ93: =DQ74/DQ$81 -> 0.23452799 | DR93: =DR74/DR$81 -> 0.22176739 | DS93: =DS74/DS$81 -> 0.231466 | DT93: =DT74/DT$81 -> 0.23210633 | DU93: =DU74/DU$81 -> 0.2245101 | DV93: =DV74/DV$81 -> 0.21927322
B94: Systems & Other | BL94: 0.13 | BM94: =BL94 -> 0.13 | BN94: =BM94 -> 0.13 | BO94: =BN94 -> 0.13 | BP94: =BO94 -> 0.13 | BQ94: 0.12 | BR94: 0.13 | BS94: 0.13 | BT94: 0.13 | BU94: =BT94 -> 0.13 | BV94: 0.13 | BW94: =BW75/BW$81 -> 0.11583995 | BX94: =BX75/BX$81 -> 0.12571601 | BY94: =BY75/BY$81 -> 0.13381123 | BZ94: =BZ75/BZ$81 -> 0.11554922 | CA94: =CA75/CA$81 -> 0.12264465 | CB94: =CB75/CB$81 -> 0.11417323 | CC94: =CC75/CC$81 -> 0.12117584 | CD94: =CD75/CD$81 -> 0.13101604 | ... CF94: =CF75/CF$81 -> 0.12297978 | CG94: =100%-SUM(CG90,CG93) -> 0.1218255 | CH94: =100%-SUM(CH90,CH93) -> 0.13368034 | CI94: =100%-SUM(CI90,CI93) -> 0.12960908 | CJ94: =100%-SUM(CJ90,CJ93) -> 0.13395255 | CK94: =100%-SUM(CK90,CK93) -> 0.12988198 | CL94: =100%-SUM(CL90,CL93) -> 0.11896127 | CM94: =100%-SUM(CM90,CM93) -> 0.16039243 | CN94: =100%-SUM(CN90,CN93) -> 0.14146341 | ... DO94: =100%-SUM(DO90,DO93) -> -0.034954367 | DQ94: =100%-SUM(DQ90,DQ93) -> -0.028323057 | DR94: =100%-SUM(DR90,DR93) -> -0.029928865 | DS94: =100%-SUM(DS90,DS93) -> -0.029396754 | DT94: =100%-SUM(DT90,DT93) -> -0.029785116 | DU94: =100%-SUM(DU90,DU93) -> -0.028048151 | DV94: =100%-SUM(DV90,DV93) -> -0.026619653
B96: Sales by sub-segment y/y % chg
B97: Commercial Engines | BQ97: =BQ71/BL71-1 -> 0.072025844 | BR97: =BR71/BM71-1 -> 0.15092905 | BS97: =BS71/BN71-1 -> 0.10093684 | BT97: =BT71/BO71-1 -> 0.10981503 | BU97: =BU71/BP71-1 -> 0.12825746 | BV97: =BV71/BQ71-1 -> 0.079426058 | BW97: =BW71/BR71-1 -> 0.093790334 | BX97: =BX71/BS71-1 -> 0.016989959 | ... DT97: =DT71/DO71-1 -> 0.15856454 | DU97: =DU71/DT71-1 -> 0.0935 | DV97: =DV71/DU71-1 -> 0.074
B98: Commercial OEM | CB98: =CB72/BW72-1 -> -0.051578947 | CC98: =CC72/BX72-1 -> 0.12938776 | CD98: =CD72/BY72-1 -> 0.16666667 | CE98: =CE72/BZ72-1 -> 0.2285 | CF98: =CF72/CA72-1 -> 0.11951842 | CG98: =CG72/CB72-1 -> 0.24805771 | CH98: =CH72/CC72-1 -> 0.016559636 | CI98: =CI72/CD72-1 -> 0.0054945055 | ... CO98: =CO72/CJ72-1 -> -0.27610009 | CP98: =CP$72/CK$72-1 -> -0.29977778 | CQ98: =CQ72/CL72-1 -> -0.24958769 | CR98: =CR72/CM72-1 -> 0.30318755 | CS98: =CS72/CN72-1 -> -0.16414835 | CT98: =CT72/CO72-1 -> -0.15077473 | CU98: =CU72/CP72-1 -> -0.085211044 | CV98: =CV72/CQ72-1 -> -0.16996337 | CW98: =CW72/CR72-1 -> -0.23265074 | CX98: =CX72/CS72-1 -> 0.20706656 | ... DL98: =DL72/DG72-1 -> 0.35714286
B99: Commercial AM | CB99: =CB73/BW73-1 -> 0.1283871 | CC99: =CC73/BX73-1 -> 0.12938776 | CD99: =CD73/BY73-1 -> 0.16666667 | CE99: =CE73/BZ73-1 -> 0.281 | CF99: =CF73/CA73-1 -> 0.17606225 | CG99: =CG73/CB73-1 -> 0.057747284 | CH99: =CH73/CC73-1 -> 0.082429334 | CI99: =CI73/CD73-1 -> 0.11270492 | ... CO99: =CO73/CJ73-1 -> -0.49244639 | CP99: =CP$73/CK$73-1 -> -0.46257475 | CQ99: =CQ73/CL73-1 -> -0.39647845 | CR99: =CR73/CM73-1 -> 0.15982906 | CS99: =CS73/CN73-1 -> 0.46229307 | CT99: =CT73/CO73-1 -> 0.37493999 | CU99: =CU73/CP73-1 -> 0.050868183 | CV99: =CV73/CQ73-1 -> 0.36820926 | CW99: =CW73/CR73-1 -> 1.1783346 | CX99: =CX73/CS73-1 -> 0.46834382 | ... DL99: =DL73/DG73-1 -> 0.29787234
B100: Military Engines | BQ100: =BQ74/BL74-1 -> -0.092967658 | BR100: =BR74/BM74-1 -> -0.091127745 | BS100: =BS74/BN74-1 -> -0.20361484 | BT100: =BT74/BO74-1 -> -0.19719262 | BU100: =BU74/BP74-1 -> -0.18385192 | BV100: =BV74/BQ74-1 -> -0.077139343 | BW100: =BW74/BR74-1 -> 0.026600356 | BX100: =BX74/BS74-1 -> 0.063289345 | ... DT100: =DT74/DO74-1 -> 0.051062598 | DU100: =DU74/DT74-1 -> 0.05 | DV100: =DV74/DU74-1 -> 0.044
B101: Systems & Other | BQ101: =BQ75/BL75-1 -> 0.027969987 | BR101: =BR75/BM75-1 -> 0.1036306 | BS101: =BS75/BN75-1 -> 0.041426743 | BT101: =BT75/BO75-1 -> 0.049825029 | BU101: =BU75/BP75-1 -> 0.067270567 | BV101: =BV75/BQ75-1 -> 0.06483922 | BW101: =BW75/BR75-1 -> -0.050438543 | BX101: =BX75/BS75-1 -> -0.014685207 | ... DT101: =DT75/DO75-1 -> -0.030172414 | DU101: =DU75/DT75-1 -> 0.022222222 | DV101: =DV75/DU75-1 -> 0.014492754
B102: Total Sales growth | BQ102: =BQ81/BL81-1 -> 0.027969987 | BR102: =BR81/BM81-1 -> 0.1036306 | BS102: =BS81/BN81-1 -> 0.041426743 | BT102: =BT81/BO81-1 -> 0.049825029 | BU102: =BU81/BP81-1 -> 0.067270567 | BV102: =BV81/BQ81-1 -> 0.06483922 | BW102: =BW81/BR81-1 -> 0.065633983 | BX102: =BX81/BS81-1 -> 0.018891107 | ... DT102: =DT81/DO81-1 -> 0.13814259 | DU102: =DU81/DT81-1 -> 0.085526392 | DV102: =DV81/DU81-1 -> 0.068933765
B104: Engine Builds
B105: Sales (units)
B106: Commercial Engines | BG106: 2378 | BH106: 646 | BI106: 652 | BJ106: 615 | BK106: 658 | BL106: =SUM(BH106:BK106) -> 2571 | BM106: 649 | BN106: 685 | BO106: 611 | BP106: 643 | BQ106: =SUM(BM106:BP106) -> 2588 | BR106: 677 | BS106: 724 | BT106: 654 | BU106: 692 | BV106: =SUM(BR106:BU106) -> 2747 | BW106: 627 | BX106: 627 | BY106: 641 | BZ106: 735 | CA106: =SUM(BW106:BZ106) -> 2630 | CB106: 651 | CC106: 697 | CD106: 714 | CE106: 763 | CF106: =SUM(CB106:CE106) -> 2825 | CG106: 751 | CH106: 723 | CI106: 714 | CJ106: 675 | CK106: =SUM(CG106:CJ106) -> 2863 | CL106: 530 | CM106: 362 | CN106: 391 | CO106: 437 | CP106: =SUM(CL106:CO106) -> 1720 | CQ106: 359 | CR106: 383 | CS106: 377 | CT106: 368 | CU106: =SUM(CQ106:CT106) -> 1487 | CV106: 343 | CW106: 355 | CX106: 489 | CY106: 476 | CZ106: =SUM(CV106:CY106) -> 1663 | DA106: 481 | DB106: 543 | DC106: 520 | DD106: 531 | DE106: =SUM(DA106:DD106) -> 2075 | DF106: 489 | DG106: 402 | DH106: 501 | DI106: 519 | DJ106: =SUM(DF106:DI106) -> 1911 | DK106: 444 | DL106: 551
B107: Product0163 Engines (WB) | BG107: 180 | BH107: 70 | BI107: 75 | BJ107: 65 | BK107: 77 | BL107: =SUM(BH107:BK107) -> 287 | BM107: 51 | BN107: 86 | BO107: 64 | BP107: 59 | BQ107: =SUM(BM107:BP107) -> 260 | BR107: 53 | BS107: 78 | BT107: 53 | BU107: 75 | BV107: =SUM(BR107:BU107) -> 259 | BW107: 69 | BX107: 60 | BY107: 48 | BZ107: 57 | CA107: =SUM(BW107:BZ107) -> 234 | CB107: 50 | CC107: 57 | CD107: 65 | CE107: 79 | CF107: =SUM(CB107:CE107) -> 251 | CG107: 78 | CH107: 70 | CI107: 73 | CJ107: 75 | CK107: =SUM(CG107:CJ107) -> 296 | CL107: 70 | CM107: - | CN107: - | CO107: - | CP107: - | CQ107: - | CR107: - | CS107: - | CT107: - | CU107: - | CV107: - | CW107: - | CX107: - | CY107: - | CZ107: - | DA107: - | DB107: - | DC107: - | DD107: - | DE107: - | DJ107: -
B108: Product0211 Engines (NB) | BG108: 0 | BH108: 0 | BI108: 0 | BJ108: 0 | BK108: 0 | BL108: =SUM(BH108:BK108) -> 0 | BM108: 0 | BN108: 0 | BO108: 0 | BP108: 0 | BQ108: =SUM(BM108:BP108) -> 0 | BR108: 0 | BS108: 11 | BT108: 22 | BU108: 44 | BV108: =SUM(BR108:BU108) -> 77 | BW108: 77 | BX108: 69 | BY108: 111 | BZ108: 202 | CA108: =SUM(BW108:BZ108) -> 459 | CB108: 186 | CC108: 250 | CD108: 303 | CE108: 379 | CF108: =SUM(CB108:CE108) -> 1118 | CG108: 424 | CH108: 437 | CI108: 455 | CJ108: 420 | CK108: =SUM(CG108:CJ108) -> 1736 | CL108: 272 | CM108: 178 | CN108: 172 | CO108: 193 | CP108: =SUM(CL108:CO108) -> 815 | CQ108: 188 | CR108: 211 | CS108: 226 | CT108: 220 | CU108: =SUM(CQ108:CT108) -> 845 | CV108: 239 | CW108: 226 | CX108: 347 | CY108: 324 | CZ108: =SUM(CV108:CY108) -> 1136 | DA108: 366 | DB108: 419 | DC108: 389 | DD108: 396 | DE108: =SUM(DA108:DD108) -> 1570 | DF108: 367 | DG108: 297 | DH108: 365 | DI108: 378 | DJ108: =SUM(DF108:DI108) -> 1407 | DK108: 319 | DL108: 410
B109: Other | BG109: =BG106-SUM(BG107:BG108) -> 2198 | BH109: =BH106-SUM(BH107:BH108) -> 576 | BI109: =BI106-SUM(BI107:BI108) -> 577 | BJ109: =BJ106-SUM(BJ107:BJ108) -> 550 | BK109: =BK106-SUM(BK107:BK108) -> 581 | BL109: =BL106-SUM(BL107:BL108) -> 2284 | BM109: =BM106-SUM(BM107:BM108) -> 598 | BN109: =BN106-SUM(BN107:BN108) -> 599 | ... CL109: =CL106-SUM(CL107:CL108) -> 188 | CM109: - | CN109: - | CO109: - | CP109: - | CQ109: - | CR109: - | CS109: - | CT109: - | CU109: - | CV109: - | CW109: - | CX109: - | CY109: - | CZ109: - | DA109: - | DB109: - | DC109: - | DD109: - | DE109: - | DJ109: -
B110: Product0086 (NB), disclosed by SAF | BG110: 1502 | BL110: 1560 | BQ110: 1612 | BV110: 1693 | CA110: 1444 | CF110: 1044 | CG110: 153 | CH110: =327-SUM(CG110,CI110) -> 105 | CI110: 69 | CJ110: =CK110-327 -> 64 | CK110: 391 | CL110: 54 | CM110: =123-SUM(CL110,CN110) -> 30 | CN110: 39 | CO110: =CP110-SUM(CL110:CN110) -> 27 | CP110: 150 | CQ110: - | CR110: - | CS110: - | CT110: - | CU110: - | CV110: - | CW110: - | CX110: - | CY110: - | CZ110: - | DA110: - | DB110: - | DC110: - | DD110: -
B111: Military Engines | BG111: 1071 | BH111: 248 | BI111: 261 | BJ111: 295 | BK111: 264 | BL111: =SUM(BH111:BK111) -> 1068 | BM111: 169 | BN111: 174 | BO111: 158 | BP111: 265 | BQ111: =SUM(BM111:BP111) -> 766 | BR111: 151 | BS111: 151 | BT111: 100 | BU111: 169 | BV111: =SUM(BR111:BU111) -> 571 | BW111: 120 | BX111: 137 | BY111: 145 | BZ111: 215 | CA111: =SUM(BW111:BZ111) -> 617 | CB111: 138 | CC111: 204 | CD111: 160 | CE111: 172 | CF111: =SUM(CB111:CE111) -> 674 | CG111: 161 | CH111: 143 | CI111: 186 | CJ111: 227 | CK111: =SUM(CG111:CJ111) -> 717 | CL111: 146 | CM111: 204 | CN111: 107 | CO111: 226 | CP111: =SUM(CL111:CO111) -> 683 | CQ111: 96 | CR111: 155 | CS111: 154 | CT111: 148 | CU111: =SUM(CQ111:CT111) -> 553 | CV111: 184 | CW111: 131 | CX111: 151 | CY111: 166 | CZ111: =SUM(CV111:CY111) -> 632 | DA111: 80 | DB111: 228 | DC111: 95 | DD111: 153 | DE111: =SUM(DA111:DD111) -> 556 | DF111: 125 | DG111: 87 | DH111: 94 | DI111: 184 | DJ111: =SUM(DF111:DI111) -> 490 | DK111: 131 | DL111: 160
B112: Commercial + Military | BG112: =SUM(BG111,BG106) -> 3449 | BH112: =SUM(BH111,BH106) -> 894 | BI112: =SUM(BI111,BI106) -> 913 | BJ112: =SUM(BJ111,BJ106) -> 910 | BK112: =SUM(BK111,BK106) -> 922 | BL112: =SUM(BL111,BL106) -> 3639 | BM112: =SUM(BM111,BM106) -> 818 | BN112: =SUM(BN111,BN106) -> 859 | ... DL112: =SUM(DL111,DL106) -> 711
B114: Spares Rate | BG114: 25.2 | BH114: 28.5 | BI114: 28.7 | BJ114: 30.9 | BK114: 32.7 | BL114: =AVERAGE(BH114:BK114) -> 30.2 | BM114: 36.5 | BN114: 37.2 | BO114: 37.6 | BP114: 37 | BQ114: =AVERAGE(BM114:BP114) -> 37.075 | BR114: 17.3 | BS114: 19 | BT114: 39.7 | BU114: 43.5 | BV114: =AVERAGE(BR114:BU114) -> 29.875 | BW114: 21.7 | BX114: 21.6 | BY114: 23.2 | BZ114: 27.4 | CA114: =AVERAGE(BW114:BZ114) -> 23.475 | CB114: 25.2 | CC114: 26.6 | CD114: 28 | CE114: 30.2 | CF114: =AVERAGE(CB114:CE114) -> 27.5 | CG114: 30.6 | CH114: 27 | CI114: 30 | CJ114: 36.8 | CK114: 31 | CL114: 26.9 | CM114: 13.1 | CN114: 14.4 | CO114: 17.5 | CP114: 18 | CQ114: 13.2 | CR114: 15 | CS114: 19.3 | CT114: 23.8 | CU114: 17.8 | CV114: 22.8 | CW114: 23.5 | CX114: 29.4 | CY114: 31.9 | CZ114: =AVERAGE(CV114:CY114) -> 26.9 | DA114: 31.1 | DB114: 32.6 | DC114: 42.4 | DD114: 38.3 | DE114: =AVERAGE(DA114:DD114) -> 36.1
B116: Narrowbody | CF116: =SUM(CF110,CF108)/CF106 -> 0.76530973 | CG116: =SUM(CG110,CG108)/CG106 -> 0.76830892 | CH116: =SUM(CH110,CH108)/CH106 -> 0.74965422 | CI116: =SUM(CI110,CI108)/CI106 -> 0.73389356 | CJ116: =SUM(CJ110,CJ108)/CJ106 -> 0.71703704 | CK116: =SUM(CK110,CK108)/CK106 -> 0.742927 | CL116: =SUM(CL110,CL108)/CL106 -> 0.61509434 | CM116: =SUM(CM110,CM108)/CM106 -> 0.57458564 | ... DL116: =SUM(DL110,DL108)/DL106 -> 0.74410163
B117: Widebody | CF117: =100%-CF116 -> 0.23469027 | CG117: =100%-CG116 -> 0.23169108 | CH117: =100%-CH116 -> 0.25034578 | CI117: =100%-CI116 -> 0.26610644 | CJ117: =100%-CJ116 -> 0.28296296 | CK117: =100%-CK116 -> 0.257073 | CL117: =100%-CL116 -> 0.38490566 | CM117: =100%-CM116 -> 0.42541436 | ... DL117: =100%-DL116 -> 0.25589837
B119: Sales (units) y/y % chg
B120: Commercial Engines | BL120: =IFERROR(BL106/BG106-1,"") -> 0.081160639 | BM120: =IFERROR(BM106/BH106-1,"") -> 0.0046439628 | BN120: =IFERROR(BN106/BI106-1,"") -> 0.050613497 | BO120: =IFERROR(BO106/BJ106-1,"") -> -0.006504065 | BP120: =IFERROR(BP106/BK106-1,"") -> -0.022796353 | BQ120: =IFERROR(BQ106/BL106-1,"") -> 0.0066122131 | BR120: =IFERROR(BR106/BM106-1,"") -> 0.043143297 | BS120: =IFERROR(BS106/BN106-1,"") -> 0.056934307 | ... DL120: =IFERROR(DL106/DG106-1,"") -> 0.37064677
B121: Product0163 Engines | BL121: =IFERROR(BL107/BG107-1,"") -> 0.59444444 | BM121: =IFERROR(BM107/BH107-1,"") -> -0.27142857 | BN121: =IFERROR(BN107/BI107-1,"") -> 0.14666667 | BO121: =IFERROR(BO107/BJ107-1,"") -> -0.015384615 | BP121: =IFERROR(BP107/BK107-1,"") -> -0.23376623 | BQ121: =IFERROR(BQ107/BL107-1,"") -> -0.094076655 | BR121: =IFERROR(BR107/BM107-1,"") -> 0.039215686 | BS121: =IFERROR(BS107/BN107-1,"") -> -0.093023256 | ... CL121: =IFERROR(CL107/CG107-1,"") -> -0.1025641 | CM121: - | CN121: - | CO121: - | CP121: - | CQ121: - | CR121: - | CS121: - | CT121: - | CU121: - | CV121: - | CW121: - | CX121: - | CY121: - | CZ121: - | DA121: - | DB121: - | DC121: - | DD121: - | DE121: - | DF121: - | DG121: - | DH121: - | DI121: - | DJ121: - | DK121: - | DL121: -
B122: Product0211 Engines | BL122: =IFERROR(BL108/BG108-1,"") | BM122: =IFERROR(BM108/BH108-1,"") | BN122: =IFERROR(BN108/BI108-1,"") | BO122: =IFERROR(BO108/BJ108-1,"") | BP122: =IFERROR(BP108/BK108-1,"") | BQ122: =IFERROR(BQ108/BL108-1,"") | BR122: =IFERROR(BR108/BM108-1,"") | BS122: =IFERROR(BS108/BN108-1,"") | ... DL122: =IFERROR(DL108/DG108-1,"") -> 0.38047138
B123: Other | BL123: =IFERROR(BL109/BG109-1,"") -> 0.039126479 | BM123: =IFERROR(BM109/BH109-1,"") -> 0.038194444 | BN123: =IFERROR(BN109/BI109-1,"") -> 0.03812825 | BO123: =IFERROR(BO109/BJ109-1,"") -> -0.0054545455 | BP123: =IFERROR(BP109/BK109-1,"") -> 0.0051635112 | BQ123: =IFERROR(BQ109/BL109-1,"") -> 0.019264448 | BR123: =IFERROR(BR109/BM109-1,"") -> 0.043478261 | BS123: =IFERROR(BS109/BN109-1,"") -> 0.060100167 | ... CL123: =IFERROR(CL109/CG109-1,"") -> -0.24497992 | CM123: - | CN123: - | CO123: - | CP123: - | CQ123: - | CR123: - | CS123: - | CT123: - | CU123: - | CV123: - | CW123: - | CX123: - | CY123: - | CZ123: - | DA123: - | DB123: - | DC123: - | DD123: - | DE123: - | DF123: - | DG123: - | DH123: - | DI123: - | DJ123: - | DK123: - | DL123: -
...

Sheet Revenue build
Y2: 2022 | Z2: 2023 | AA2: 2024E | AB2: 2025E | AC2: 2026E | AD2: 2027E | AE2: 2028E | AF2: 2028E | AG2: 2028E | AH2: 2028E | AI2: 2028E | AJ2: 2028E | AK2: 2028E | AL2: 2028E | AM2: 2028E | AN2: 2028E | AO2: 2028E | AP2: 2028E | AQ2: 2028E
B4: Ticker0009 Commercial Aero Build | C4: 2000 | D4: 2001 | E4: 2002 | F4: 2003 | G4: 2004 | H4: 2005 | I4: 2006 | J4: 2007 | K4: 2008 | L4: 2009 | M4: 2010 | N4: 2011 | O4: 2012 | P4: 2013 | Q4: 2014 | R4: 2015 | S4: 2016 | T4: 2017 | U4: 2018 | V4: 2019 | W4: 2020 | X4: 2021 | Y4: 2022 | Z4: 2023 | AA4: 2024 | AB4: 2025E | AC4: 2026E | AD4: 2027E | AE4: 2028E | AF4: 2029E | AG4: 2030E | AH4: 2031E | AI4: 2032E | AJ4: 2033E | AK4: 2034E | AL4: 2035E | AM4: 2036E | AN4: 20370E | AO4: 2038E | AP4: 2039E | AQ4: 2040E
B6: Engine OE build
B7: Deliveries:
A8: NB | B8: Product0086 | C8: 400 | D8: 500 | E8: 600 | F8: 650 | G8: 700 | H8: 750 | I8: 1067 | J8: 1243 | K8: 1268 | L8: 1263 | M8: 1251 | N8: 1308 | O8: 1406 | P8: 1502 | Q8: 1560 | R8: 1612 | S8: 1693 | T8: 1444 | U8: 1044 | V8: 391 | W8: 157 | X8: 107 | Y8: 60 | Z8: 52 | AA8: 50 | AB8: 50 | AC8: 50 | AD8: 50 | AE8: 50 | AF8: 0 | AG8: 0 | AH8: 0 | AI8: 0 | AJ8: 0 | AK8: 0 | AL8: 0 | AM8: 0 | AN8: 0 | AO8: 0 | AP8: 0 | AQ8: 0
A9: NB | B9: Product0211 | I9: 0 | J9: 0 | K9: 0 | L9: 0 | M9: 0 | N9: 0 | O9: 0 | P9: 0 | Q9: 0 | R9: 0 | S9: 77 | T9: 459 | U9: 1118 | V9: 1736 | W9: 815 | X9: 845 | Y9: 1136 | Z9: 1570 | AA9: 1600 | AB9: =AA9*1.15 -> 1840 | AC9: =AB9*1.12 -> 2060.8 | AD9: =AC9*1.1 -> 2266.88 | AE9: =AD9*1.1 -> 2493.568 | AF9: =AE9+50 -> 2543.568 | AG9: =AF9+50 -> 2593.568 | AH9: =AG9+50 -> 2643.568 | AI9: =AH9+50 -> 2693.568 | AJ9: 2500 | AK9: 2200 | AL9: 2000 | AM9: 1800 | AN9: 1600 | AO9: 1200 | AP9: 800 | AQ9: 600
A10: WB | B10: GE90 | C10: 25 | D10: 50 | E10: 60 | F10: 70 | G10: 80 | H10: 90 | I10: 96 | J10: 140 | K10: 116 | L10: 168 | M10: 146 | N10: 146 | O10: 160 | P10: 188 | Q10: 198 | R10: 221 | S10: 214 | T10: 162 | U10: 86 | V10: 90 | W10: 96 | X10: 96 | Y10: 96 | Z10: 104 | AA10: 100 | AB10: 80 | AC10: 60 | AD10: 50 | AE10: 40 | AF10: 0 | AG10: 0 | AH10: 0 | AI10: 0 | AJ10: 0 | AK10: 0 | AL10: 0 | AM10: 0 | AN10: 0 | AO10: 0 | AP10: 0 | AQ10: 0
A11: WB | B11: CF6-80 | C11: 15 | D11: 40 | E11: 50 | F11: 60 | G11: 70 | H11: 80 | I11: 100 | J11: 144 | K11: 110 | L11: 70 | M11: 46 | N11: 66 | O11: 167 | P11: 130 | Q11: 133 | R11: 129 | S11: 117 | T11: 84 | U11: 71 | V11: 18 | W11: 0 | X11: 0 | Y11: 0 | Z11: 0 | AA11: 0 | AB11: 0 | AC11: 0 | AD11: 0 | AE11: 0 | AF11: 0 | AG11: 0 | AH11: 0 | AI11: 0 | AJ11: 0 | AK11: 0 | AL11: 0 | AM11: 0 | AN11: 0 | AO11: 0 | AP11: 0 | AQ11: 0
A12: WB | B12: Product0165 | I12: 0 | J12: 0 | K12: 16 | L12: 16 | M12: 44 | N12: 48 | O12: 62 | P12: 96 | Q12: 76 | R12: 76 | S12: 74 | T12: 9 | U12: 0 | V12: 0 | W12: 0 | X12: 0 | Y12: 0 | Z12: 0 | AA12: 0 | AB12: 0 | AC12: 0 | AD12: 0 | AE12: 0 | AF12: 0 | AG12: 0 | AH12: 0 | AI12: 0 | AJ12: 0 | AK12: 0 | AL12: 0 | AM12: 0 | AN12: 0 | AO12: 0 | AP12: 0 | AQ12: 0
A13: WB | B13: Product0163 | O13: 150.83333 | P13: 181 | Q13: 227 | R13: 268 | S13: 281 | T13: 231 | U13: 278 | V13: 381 | W13: 273 | X13: 139 | Y13: 85 | Z13: 86 | AA13: 105 | AB13: 120 | AC13: 140 | AD13: 150 | AE13: 155 | AF13: 160 | AG13: 170 | AH13: 180 | AI13: 190 | AJ13: 200 | AK13: 180 | AL13: 160 | AM13: 140 | AN13: 100 | AO13: 100 | AP13: 80 | AQ13: 50
A14: WB | B14: Product0162 | W14: 0 | X14: 0 | Y14: 0 | Z14: 0 | AA14: 10 | AB14: 40 | AC14: 70 | AD14: 90 | AE14: 100 | AF14: =AE14+5 -> 105 | AG14: =AF14+5 -> 110 | AH14: =AG14+5 -> 115 | AI14: =AH14+5 -> 120 | AJ14: =AI14+5 -> 125 | AK14: =AJ14+5 -> 130 | AL14: =AK14+5 -> 135 | AM14: =AL14+5 -> 140 | ... AQ14: =AP14+5 -> 160
B16: Price per engine
B17: Product0086 | O17: =P17/(1+P74) -> 14.254176 | P17: =Q17/(1+Q74) -> 14.610531 | Q17: =R17/(1+R74) -> 14.975794 | R17: =S17/(1+S74) -> 15.350189 | S17: =T17/(1+T74) -> 15.733944 | T17: =U17/(1+U74) -> 16.127292 | U17: =V17/(1+V74) -> 16.530475 | V17: =W17/(1+W74) -> 16.943736 | ... Y17: =Z17/(1+Z74) -> 19.047619 | Z17: 20 | AA17: =Z17*(1+AA74) -> 21 | AB17: =AA17*(1+AB74) -> 21.63 | AC17: =AB17*(1+AC74) -> 22.2789 | AD17: =AC17*(1+AD74) -> 22.947267 | AE17: =AD17*(1+AE74) -> 23.635685 | AF17: =AE17*(1+AF74) -> 24.344756 | AG17: =AF17*(1+AG74) -> 25.075098 | AH17: =AG17*(1+AH74) -> 25.827351 | ... AQ17: =AP17*(1+AQ74) -> 33.698835
B18: Product0211 | O18: =P18/(1+P75) -> 14.665091 | P18: =Q18/(1+Q75) -> 14.665091 | Q18: =R18/(1+R75) -> 14.665091 | R18: =S18/(1+S75) -> 14.665091 | S18: =T18/(1+T75) -> 14.665091 | T18: =U18/(1+U75) -> 15.031718 | U18: =V18/(1+V75) -> 15.407511 | V18: =W18/(1+W75) -> 15.792699 | ... Y18: =Z18/(1+Z75) -> 18.518519 | Z18: 20 | AA18: =Z18*(1+AA75) -> 21.1 | AB18: =AA18*(1+AB75) -> 21.944 | AC18: =AB18*(1+AC75) -> 22.82176 | AD18: =AC18*(1+AD75) -> 23.73463 | AE18: =AD18*(1+AE75) -> 24.684016 | AF18: =AE18*(1+AF75) -> 25.671376 | AG18: =AF18*(1+AG75) -> 26.698231 | AH18: =AG18*(1+AH75) -> 27.766161 | ... AQ18: =AP18*(1+AQ75) -> 39.519904
B19: GE90 | O19: =P19/(1+P76) -> 29.330709 | P19: =Q19/(1+Q76) -> 30.063977 | Q19: =R19/(1+R76) -> 30.815576 | R19: =S19/(1+S76) -> 31.585966 | S19: =T19/(1+T76) -> 32.375615 | T19: =U19/(1+U76) -> 33.185005 | U19: =V19/(1+V76) -> 34.01463 | V19: =W19/(1+W76) -> 34.864996 | ... Y19: =Z19/(1+Z76) -> 38.461538 | Z19: 40 | AA19: =Z19*(1+AA76) -> 41.6 | AB19: =AA19*(1+AB76) -> 43.264 | AC19: =AB19*(1+AC76) -> 44.99456 | AD19: =AC19*(1+AD76) -> 46.794342 | AE19: =AD19*(1+AE76) -> 48.666116 | AF19: =AE19*(1+AF76) -> 51.099422 | AG19: =AF19*(1+AG76) -> 53.654393 | AH19: =AG19*(1+AH76) -> 56.337113 | ... AQ19: =AP19*(1+AQ76) -> 87.397352
B20: CF6-80 | O20: =P20/(1+P77) -> 30.485791 | P20: =Q20/(1+Q77) -> 31.247936 | Q20: =R20/(1+R77) -> 32.029134 | R20: =S20/(1+S77) -> 32.829863 | S20: =T20/(1+T77) -> 33.650609 | T20: =U20/(1+U77) -> 34.491875 | U20: =V20/(1+V77) -> 35.354172 | V20: =W20/(1+W77) -> 36.238026 | ... Y20: =Z20/(1+Z77) -> 39.02439 | Z20: 40 | AA20: =Z20*(1+AA77) -> 41 | AB20: =AA20*(1+AB77) -> 42.64 | AC20: =AB20*(1+AC77) -> 44.772 | AD20: =AC20*(1+AD77) -> 47.0106 | AE20: =AD20*(1+AE77) -> 49.36113 | AF20: =AE20*(1+AF77) -> 51.829187 | AG20: =AF20*(1+AG77) -> 54.420646 | AH20: =AG20*(1+AH77) -> 57.141678 | ... AQ20: =AP20*(1+AQ77) -> 88.645498
B21: Product0165 | O21: =P21/(1+P78) -> 30.485791 | P21: =Q21/(1+Q78) -> 31.247936 | Q21: =R21/(1+R78) -> 32.029134 | R21: =S21/(1+S78) -> 32.829863 | S21: =T21/(1+T78) -> 33.650609 | T21: =U21/(1+U78) -> 34.491875 | U21: =V21/(1+V78) -> 35.354172 | V21: =W21/(1+W78) -> 36.238026 | ... Y21: =Z21/(1+Z78) -> 39.02439 | Z21: 40 | AA21: =Z21*(1+AA78) -> 41 | AB21: =AA21*(1+AB78) -> 42.64 | AC21: =AB21*(1+AC78) -> 44.772 | AD21: =AC21*(1+AD78) -> 47.0106 | AE21: =AD21*(1+AE78) -> 49.36113 | AF21: =AE21*(1+AF78) -> 51.829187 | AG21: =AF21*(1+AG78) -> 54.420646 | AH21: =AG21*(1+AH78) -> 57.141678 | ... AQ21: =AP21*(1+AQ78) -> 88.645498
B22: Product0163 | O22: =P22/(1+P79) -> 28.362242 | P22: =Q22/(1+Q79) -> 29.071298 | Q22: =R22/(1+R79) -> 29.798081 | R22: =S22/(1+S79) -> 30.543033 | S22: =T22/(1+T79) -> 31.306609 | T22: =U22/(1+U79) -> 32.089274 | U22: =V22/(1+V79) -> 32.891506 | V22: =W22/(1+W79) -> 33.713793 | ... Y22: =Z22/(1+Z79) -> 38.095238 | Z22: 40 | AA22: =Z22*(1+AA79) -> 41 | AB22: =AA22*(1+AB79) -> 42.64 | AC22: =AB22*(1+AC79) -> 44.772 | AD22: =AC22*(1+AD79) -> 47.0106 | AE22: =AD22*(1+AE79) -> 49.36113 | AF22: =AE22*(1+AF79) -> 51.829187 | AG22: =AF22*(1+AG79) -> 54.420646 | AH22: =AG22*(1+AH79) -> 57.141678 | ... AQ22: =AP22*(1+AQ79) -> 88.645498
B23: Product0162 | O23: =P23/(1+P80) -> 37.143976 | P23: =Q23/(1+Q80) -> 37.143976 | Q23: =R23/(1+R80) -> 37.143976 | R23: =S23/(1+S80) -> 37.143976 | S23: =T23/(1+T80) -> 37.143976 | T23: =U23/(1+U80) -> 37.143976 | U23: =V23/(1+V80) -> 37.143976 | V23: =W23/(1+W80) -> 37.143976 | ... Y23: =Z23/(1+Z80) -> 39.02439 | Z23: 40 | AA23: =Z23*(1+AA80) -> 41 | AB23: =AA23*(1+AB80) -> 42.64 | AC23: =AB23*(1+AC80) -> 44.772 | AD23: =AC23*(1+AD80) -> 47.0106 | AE23: =AD23*(1+AE80) -> 49.36113 | AF23: =AE23*(1+AF80) -> 51.829187 | AG23: =AF23*(1+AG80) -> 54.420646 | AH23: =AG23*(1+AH80) -> 57.141678 | ... AQ23: =AP23*(1+AQ80) -> 88.645498
B25: Pricing discount
B26: Product0086 | O26: 0.75 | P26: 0.75 | Q26: 0.75 | R26: 0.85 | S26: 0.85 | T26: 0.85 | U26: 0.85 | V26: 0.85 | W26: 0.85 | X26: 0.705 | Y26: 0.705 | Z26: 0.705 | AA26: 0.71 | AB26: =AA26 -> 0.71 | AC26: =AB26 -> 0.71 | AD26: =AC26 -> 0.71 | AE26: =AD26 -> 0.71 | AF26: =AE26 -> 0.71 | AG26: =AF26 -> 0.71 | AH26: =AG26 -> 0.71 | AI26: =AH26 -> 0.71 | ... AQ26: =AP26 -> 0.71
B27: Product0211 | S27: 0.85 | T27: 0.85 | U27: 0.85 | V27: 0.85 | W27: 0.85 | X27: 0.65 | Y27: 0.65 | Z27: 0.7 | AA27: 0.7 | AB27: =AA27 -> 0.7 | AC27: =AB27 -> 0.7 | AD27: =AC27 -> 0.7 | AE27: =AD27 -> 0.7 | AF27: =AE27 -> 0.7 | AG27: =AF27 -> 0.7 | AH27: =AG27 -> 0.7 | AI27: =AH27 -> 0.7 | ... AQ27: =AP27 -> 0.7
B28: GE90 | O28: 0.5 | P28: 0.5 | Q28: 0.85 | R28: 0.85 | S28: 0.85 | T28: 0.85 | U28: 0.85 | V28: 0.85 | W28: 0.85 | X28: 0.6 | Y28: 0.5 | Z28: 0.5 | AA28: 0.55 | AB28: =AA28 -> 0.55 | AC28: =AB28 -> 0.55 | AD28: =AC28 -> 0.55 | AE28: =AD28 -> 0.55 | AF28: =AE28 -> 0.55 | AG28: =AF28 -> 0.55 | AH28: =AG28 -> 0.55 | AI28: =AH28 -> 0.55 | ... AQ28: =AP28 -> 0.55
B29: CF6-80 | O29: 0.5 | P29: 0.5 | Q29: 0.5 | R29: 0.5 | S29: 0.5 | T29: 0.5 | U29: 0.5 | V29: 0.5 | W29: 0.5 | X29: 0.5 | Y29: 0.5 | Z29: 0.5 | AA29: 0.55 | AB29: =AA29 -> 0.55 | AC29: =AB29 -> 0.55 | AD29: =AC29 -> 0.55 | AE29: =AD29 -> 0.55 | AF29: =AE29 -> 0.55 | AG29: =AF29 -> 0.55 | AH29: =AG29 -> 0.55 | AI29: =AH29 -> 0.55 | ... AQ29: =AP29 -> 0.55
B30: Product0165 | O30: 0.6 | P30: 0.6 | Q30: 0.6 | R30: 0.6 | S30: 0.6 | T30: 0.6 | U30: 0.6 | V30: 0.6 | W30: 0.6 | X30: 0.6 | Y30: 0.6 | Z30: 0.6 | AA30: 0.65 | AB30: =AA30 -> 0.65 | AC30: =AB30 -> 0.65 | AD30: =AC30 -> 0.65 | AE30: =AD30 -> 0.65 | AF30: =AE30 -> 0.65 | AG30: =AF30 -> 0.65 | AH30: =AG30 -> 0.65 | AI30: =AH30 -> 0.65 | ... AQ30: =AP30 -> 0.65
B31: Product0163 | O31: 0.5 | P31: 0.5 | Q31: 0.5 | R31: 0.5 | S31: 0.5 | T31: 0.5 | U31: 0.5 | V31: 0.5 | W31: 0.5 | X31: 0.5 | Y31: 0.5 | Z31: 0.5 | AA31: 0.55 | AB31: =AA31 -> 0.55 | AC31: =AB31 -> 0.55 | AD31: =AC31 -> 0.55 | AE31: =AD31 -> 0.55 | AF31: =AE31 -> 0.55 | AG31: =AF31 -> 0.55 | AH31: =AG31 -> 0.55 | AI31: =AH31 -> 0.55 | ... AQ31: =AP31 -> 0.55
B32: Product0162 | S32: 0.5 | T32: 0.5 | U32: 0.5 | V32: 0.5 | W32: 0.5 | X32: 0.5 | Y32: 0.5 | Z32: 0.5 | AA32: 0.55 | AB32: =AA32 -> 0.55 | AC32: =AB32 -> 0.55 | AD32: =AC32 -> 0.55 | AE32: =AD32 -> 0.55 | AF32: =AE32 -> 0.55 | AG32: =AF32 -> 0.55 | AH32: =AG32 -> 0.55 | AI32: =AH32 -> 0.55 | ... AQ32: =AP32 -> 0.55
B34: Ticker0009 share
B35: Product0086 | O35: 0.5 | P35: 0.5 | Q35: 0.5 | R35: 0.5 | S35: 0.5 | T35: 0.5 | U35: 0.5 | V35: 0.5 | W35: 0.5 | X35: 0.5 | Y35: 0.5 | Z35: 0.5 | AA35: 0.5 | AB35: 0.5 | AC35: 0.5 | AD35: 0.5 | AE35: 0.5 | AF35: 0.5 | AG35: 0.5 | AH35: 0.5 | AI35: 0.5 | AJ35: 0.5 | AK35: 0.5 | AL35: 0.5 | AM35: 0.5 | AN35: 0.5 | AO35: 0.5 | AP35: 0.5 | AQ35: 0.5
B36: Product0211 | O36: 0.5 | P36: 0.5 | Q36: 0.5 | R36: 0.5 | S36: 0.5 | T36: 0.5 | U36: 0.5 | V36: 0.5 | W36: 0.5 | X36: 0.5 | Y36: 0.5 | Z36: 0.5 | AA36: 0.5 | AB36: 0.5 | AC36: 0.5 | AD36: 0.5 | AE36: 0.5 | AF36: 0.5 | AG36: 0.5 | AH36: 0.5 | AI36: 0.5 | AJ36: 0.5 | AK36: 0.5 | AL36: 0.5 | AM36: 0.5 | AN36: 0.5 | AO36: 0.5 | AP36: 0.5 | AQ36: 0.5
B37: GE90 | O37: 0.76 | P37: 0.76 | Q37: 0.76 | R37: 0.76 | S37: 0.76 | T37: 0.76 | U37: 0.76 | V37: 0.76 | W37: 0.76 | X37: 0.76 | Y37: 0.76 | Z37: 0.76 | AA37: 0.76 | AB37: 0.76 | AC37: 0.76 | AD37: 0.76 | AE37: 0.76 | AF37: 0.76 | AG37: 0.76 | AH37: 0.76 | AI37: 0.76 | AJ37: 0.76 | AK37: 0.76 | AL37: 0.76 | AM37: 0.76 | AN37: 0.76 | AO37: 0.76 | AP37: 0.76 | AQ37: 0.76
B38: CF6-80 | O38: 0.81 | P38: 0.81 | Q38: 0.81 | R38: 0.81 | S38: 0.81 | T38: 0.81 | U38: 0.81 | V38: 0.81 | W38: 0.81 | X38: 0.81 | Y38: 0.81 | Z38: 0.81 | AA38: 0.81 | AB38: 0.81 | AC38: 0.81 | AD38: 0.81 | AE38: 0.81 | AF38: 0.81 | AG38: 0.81 | AH38: 0.81 | AI38: 0.81 | AJ38: 0.81 | AK38: 0.81 | AL38: 0.81 | AM38: 0.81 | AN38: 0.81 | AO38: 0.81 | AP38: 0.81 | AQ38: 0.81
B39: Product0165 | O39: 0.82 | P39: 0.82 | Q39: 0.82 | R39: 0.82 | S39: 0.82 | T39: 0.82 | U39: 0.82 | V39: 0.82 | W39: 0.82 | X39: 0.82 | Y39: 0.82 | Z39: 0.82 | AA39: 0.82 | AB39: 0.82 | AC39: 0.82 | AD39: 0.82 | AE39: 0.82 | AF39: 0.82 | AG39: 0.82 | AH39: 0.82 | AI39: 0.82 | AJ39: 0.82 | AK39: 0.82 | AL39: 0.82 | AM39: 0.82 | AN39: 0.82 | AO39: 0.82 | AP39: 0.82 | AQ39: 0.82
B40: Product0163 | O40: 0.92 | P40: 1 | Q40: 1 | R40: 1 | S40: 1 | T40: 1 | U40: 1 | V40: 1 | W40: 1 | X40: 1 | Y40: 1 | Z40: 1 | AA40: 1 | AB40: 1 | AC40: 1 | AD40: 1 | AE40: 1 | AF40: 1 | AG40: 1 | AH40: 1 | AI40: 1 | AJ40: 1 | AK40: 1 | AL40: 1 | AM40: 1 | AN40: 1 | AO40: 1 | AP40: 1 | AQ40: 1
B41: Product0162 | O41: 1 | P41: 1 | Q41: 1 | R41: 1 | S41: 1 | T41: 1 | U41: 1 | V41: 1 | W41: 1 | X41: 1 | Y41: 1 | Z41: 1 | AA41: 1 | AB41: 1 | AC41: 1 | AD41: 1 | AE41: 1 | AF41: 1 | AG41: 1 | AH41: 1 | AI41: 1 | AJ41: 1 | AK41: 1 | AL41: 1 | AM41: 1 | AN41: 1 | AO41: 1 | AP41: 1 | AQ41: 1
B43: Spares as % of total deliveries
B44: Product0086 | O44: 0.08 | P44: 0.08 | Q44: 0.08 | R44: 0.08 | S44: 0.08 | T44: 0.08 | U44: 0.08 | V44: 0.08 | W44: 0.08 | X44: 0.08 | Y44: 0.1 | Z44: 0.12 | AA44: 0.1 | AB44: 0.1 | AC44: 0.1 | AD44: 0.08 | AE44: 0.08 | AF44: 0.08 | AG44: 0.08 | AH44: 0.08 | AI44: 0.08 | AJ44: 0.08 | AK44: 0.08 | AL44: 0.08 | AM44: 0.08 | AN44: 0.08 | AO44: 0.08 | AP44: 0.08 | AQ44: 0.08
B45: Product0211 | O45: 0.08 | P45: 0.08 | Q45: 0.08 | R45: 0.08 | S45: 0.08 | T45: 0.08 | U45: 0.08 | V45: 0.08 | W45: 0.08 | X45: 0.08 | Y45: 0.1 | Z45: 0.12 | AA45: 0.1 | AB45: 0.1 | AC45: 0.1 | AD45: 0.08 | AE45: 0.08 | AF45: 0.08 | AG45: 0.08 | AH45: 0.08 | AI45: 0.08 | AJ45: 0.08 | AK45: 0.08 | AL45: 0.08 | AM45: 0.08 | AN45: 0.08 | AO45: 0.08 | AP45: 0.08 | AQ45: 0.08
B46: GE90 | O46: 0.08 | P46: 0.08 | Q46: 0.08 | R46: 0.08 | S46: 0.08 | T46: 0.08 | U46: 0.08 | V46: 0.08 | W46: 0.08 | X46: 0.08 | Y46: 0.1 | Z46: 0.12 | AA46: 0.1 | AB46: 0.1 | AC46: 0.1 | AD46: 0.08 | AE46: 0.08 | AF46: 0.08 | AG46: 0.08 | AH46: 0.08 | AI46: 0.08 | AJ46: 0.08 | AK46: 0.08 | AL46: 0.08 | AM46: 0.08 | AN46: 0.08 | AO46: 0.08 | AP46: 0.08 | AQ46: 0.08
B47: CF6-80 | O47: 0.08 | P47: 0.08 | Q47: 0.08 | R47: 0.08 | S47: 0.08 | T47: 0.08 | U47: 0.08 | V47: 0.08 | W47: 0.08 | X47: 0.08 | Y47: 0.1 | Z47: 0.12 | AA47: 0.1 | AB47: 0.1 | AC47: 0.1 | AD47: 0.08 | AE47: 0.08 | AF47: 0.08 | AG47: 0.08 | AH47: 0.08 | AI47: 0.08 | AJ47: 0.08 | AK47: 0.08 | AL47: 0.08 | AM47: 0.08 | AN47: 0.08 | AO47: 0.08 | AP47: 0.08 | AQ47: 0.08
B48: Product0165 | O48: 0.08 | P48: 0.08 | Q48: 0.08 | R48: 0.08 | S48: 0.08 | T48: 0.08 | U48: 0.08 | V48: 0.08 | W48: 0.08 | X48: 0.08 | Y48: 0.1 | Z48: 0.12 | AA48: 0.1 | AB48: 0.1 | AC48: 0.1 | AD48: 0.08 | AE48: 0.08 | AF48: 0.08 | AG48: 0.08 | AH48: 0.08 | AI48: 0.08 | AJ48: 0.08 | AK48: 0.08 | AL48: 0.08 | AM48: 0.08 | AN48: 0.08 | AO48: 0.08 | AP48: 0.08 | AQ48: 0.08
B49: Product0163 | O49: 0.08 | P49: 0.08 | Q49: 0.08 | R49: 0.08 | S49: 0.08 | T49: 0.08 | U49: 0.08 | V49: 0.08 | W49: 0.08 | X49: 0.08 | Y49: 0.1 | Z49: 0.12 | AA49: 0.1 | AB49: 0.1 | AC49: 0.1 | AD49: 0.08 | AE49: 0.08 | AF49: 0.08 | AG49: 0.08 | AH49: 0.08 | AI49: 0.08 | AJ49: 0.08 | AK49: 0.08 | AL49: 0.08 | AM49: 0.08 | AN49: 0.08 | AO49: 0.08 | AP49: 0.08 | AQ49: 0.08
B50: Product0162 | O50: 0.08 | P50: 0.08 | Q50: 0.08 | R50: 0.08 | S50: 0.08 | T50: 0.08 | U50: 0.08 | V50: 0.08 | W50: 0.08 | X50: 0.08 | Y50: 0.1 | Z50: 0.12 | AA50: 0.1 | AB50: 0.1 | AC50: 0.1 | AD50: 0.08 | AE50: 0.08 | AF50: 0.08 | AG50: 0.08 | AH50: 0.08 | AI50: 0.08 | AJ50: 0.08 | AK50: 0.08 | AL50: 0.08 | AM50: 0.08 | AN50: 0.08 | AO50: 0.08 | AP50: 0.08 | AQ50: 0.08
B52: Revenue by Engine
B53: Product0086 | O53: =O8*(1-O44)*O17*(1-O26)*O35 -> 2304.7578 | P53: =P8*(1-P44)*P17*(1-P26)*P35 -> 2523.677 | Q53: =Q8*(1-Q44)*Q17*(1-Q26)*Q35 -> 2686.6575 | R53: =R8*(1-R44)*R17*(1-R26)*R35 -> 1707.3708 | S53: =S8*(1-S44)*S17*(1-S26)*S35 -> 1837.9921 | T53: =T8*(1-T44)*T17*(1-T26)*T35 -> 1606.8589 | U53: =U8*(1-U44)*U17*(1-U26)*U35 -> 1190.7893 | V53: =V8*(1-V44)*V17*(1-V26)*V35 -> 457.12507 | ... AQ53: =AQ8*(1-AQ44)*AQ17*(1-AQ26)*AQ35 -> 0
B54: Product0211 | O54: =O9*(1-O45)*O18*(1-O27)*O36 -> 0 | P54: =P9*(1-P45)*P18*(1-P27)*P36 -> 0 | Q54: =Q9*(1-Q45)*Q18*(1-Q27)*Q36 -> 0 | R54: =R9*(1-R45)*R18*(1-R27)*R36 -> 0 | S54: =S9*(1-S45)*S18*(1-S27)*S36 -> 77.915627 | T54: =T9*(1-T45)*T18*(1-T27)*T36 -> 476.06954 | U54: =U9*(1-U45)*U18*(1-U27)*U36 -> 1188.5662 | V54: =V9*(1-V45)*V18*(1-V27)*V36 -> 1891.7126 | ... AQ54: =AQ9*(1-AQ45)*AQ18*(1-AQ27)*AQ36 -> 3272.2481
B55: GE90 | O55: =O10*(1-O46)*O19*(1-O28)*O37 -> 1640.6426 | P55: =P10*(1-P46)*P19*(1-P28)*P37 -> 1975.9489 | Q55: =Q10*(1-Q46)*Q19*(1-Q28)*Q37 -> 639.92365 | R55: =R10*(1-R46)*R19*(1-R28)*R37 -> 732.11468 | S55: =S10*(1-S46)*S19*(1-S28)*S37 -> 726.64866 | T55: =T10*(1-T46)*T19*(1-T28)*T37 -> 563.83182 | U55: =U10*(1-U46)*U19*(1-U28)*U37 -> 306.80108 | V55: =V10*(1-V46)*V19*(1-V28)*V37 -> 329.09767 | ... AQ55: =AQ10*(1-AQ46)*AQ19*(1-AQ28)*AQ37 -> 0
B56: CF6-80 | O56: =O11*(1-O47)*O20*(1-O29)*O38 -> 1896.954 | P56: =P11*(1-P47)*P20*(1-P29)*P38 -> 1513.5875 | Q56: =Q11*(1-Q47)*Q20*(1-Q29)*Q38 -> 1587.2294 | R56: =R11*(1-R47)*R20*(1-R29)*R38 -> 1577.9805 | S56: =S11*(1-S47)*S20*(1-S29)*S38 -> 1466.9714 | T56: =T11*(1-T47)*T20*(1-T29)*T38 -> 1079.5405 | U56: =U11*(1-U47)*U20*(1-U29)*U38 -> 935.28047 | V56: =V11*(1-V47)*V20*(1-V29)*V38 -> 243.04119 | ... AQ56: =AQ11*(1-AQ47)*AQ20*(1-AQ29)*AQ38 -> 0
B57: Product0165 | O57: =O12*(1-O48)*O21*(1-O30)*O39 -> 570.36233 | P57: =P12*(1-P48)*P21*(1-P30)*P39 -> 905.22021 | Q57: =Q12*(1-Q48)*Q21*(1-Q30)*Q39 -> 734.54848 | R57: =R12*(1-R48)*R21*(1-R30)*R39 -> 752.9122 | S57: =S12*(1-S48)*S21*(1-S30)*S39 -> 751.42618 | T57: =T12*(1-T48)*T21*(1-T30)*T39 -> 93.674413 | U57: =U12*(1-U48)*U21*(1-U30)*U39 -> 0 | V57: =V12*(1-V48)*V21*(1-V30)*V39 -> 0 | ... AQ57: =AQ12*(1-AQ48)*AQ21*(1-AQ30)*AQ39 -> 0
B58: Product0163 | O58: =O13*(1-O49)*O22*(1-O31)*O40 -> 1810.4376 | P58: =P13*(1-P49)*P22*(1-P31)*P40 -> 2420.4763 | Q58: =Q13*(1-Q49)*Q22*(1-Q31)*Q40 -> 3111.5156 | R58: =R13*(1-R49)*R22*(1-R31)*R40 -> 3765.3451 | S58: =S13*(1-S49)*S22*(1-S31)*S40 -> 4046.6923 | T58: =T13*(1-T49)*T22*(1-T31)*T40 -> 3409.8063 | U58: =U13*(1-U49)*U22*(1-U31)*U40 -> 4206.1658 | V58: =V13*(1-V49)*V22*(1-V31)*V40 -> 5908.6794 | ... AQ58: =AQ13*(1-AQ49)*AQ22*(1-AQ31)*AQ40 -> 1834.9618
B59: Product0162 | O59: =O14*(1-O50)*O23*(1-O32)*O41 -> 0 | P59: =P14*(1-P50)*P23*(1-P32)*P41 -> 0 | Q59: =Q14*(1-Q50)*Q23*(1-Q32)*Q41 -> 0 | R59: =R14*(1-R50)*R23*(1-R32)*R41 -> 0 | S59: =S14*(1-S50)*S23*(1-S32)*S41 -> 0 | T59: =T14*(1-T50)*T23*(1-T32)*T41 -> 0 | U59: =U14*(1-U50)*U23*(1-U32)*U41 -> 0 | V59: =V14*(1-V50)*V23*(1-V32)*V41 -> 0 | ... AQ59: =AQ14*(1-AQ50)*AQ23*(1-AQ32)*AQ41 -> 5871.8778
B60: Other | Q60: -27.514597 | R60: -12.881683 | S60: -357.39022 | T60: 453.21858 | U60: 773.65721 | V60: 170.344 | W60: 504.11865 | X60: -65.219679 | Y60: -378.95971 | Z60: 267.88853 | AA60: -200 | AB60: -100 | AC60: -100 | AD60: -100 | AE60: -100
B61: Ticker0009 Engine OE Revenue | O61: =SUM(O53:O60) -> 8223.1542 | P61: =SUM(P53:P60) -> 9338.9099 | Q61: =SUM(Q53:Q60) -> 8732.36 | R61: =SUM(R53:R60) -> 8522.8416 | S61: =SUM(S53:S60) -> 8550.256 | T61: =SUM(T53:T60) -> 7683 | U61: =SUM(U53:U60) -> 8601.26 | V61: =SUM(V53:V60) -> 9000 | ... AQ61: =SUM(AQ53:AQ60) -> 10979.088
B62: yoy % growth | R62: =R61/Q61-1 -> -0.023993331 | S62: =S61/R61-1 -> 0.0032165798 | T62: =T61/S61-1 -> -0.10143041 | U62: =U61/T61-1 -> 0.11951842 | V62: =V61/U61-1 -> 0.046358324 | W62: =W61/V61-1 -> -0.29977778 | X62: =X61/W61-1 -> -0.085211044 | Y62: =Y61/X61-1 -> 0.007111882 | ... AQ62: =AQ61/AP61-1 -> -0.11521964
B64: Deliveries growth
B65: Product0086 | J65: =IFERROR(J8/I8-1,"") -> 0.16494845 | K65: =IFERROR(K8/J8-1,"") -> 0.020112631 | L65: =IFERROR(L8/K8-1,"") -> -0.0039432177 | M65: =IFERROR(M8/L8-1,"") -> -0.0095011876 | N65: =IFERROR(N8/M8-1,"") -> 0.045563549 | O65: =IFERROR(O8/N8-1,"") -> 0.074923547 | P65: =IFERROR(P8/O8-1,"") -> 0.068278805 | Q65: =IFERROR(Q8/P8-1,"") -> 0.03861518 | ... AQ65: =IFERROR(AQ8/AP8-1,"")
B66: Product0211 | J66: =IFERROR(J9/I9-1,"") | K66: =IFERROR(K9/J9-1,"") | L66: =IFERROR(L9/K9-1,"") | M66: =IFERROR(M9/L9-1,"") | N66: =IFERROR(N9/M9-1,"") | O66: =IFERROR(O9/N9-1,"") | P66: =IFERROR(P9/O9-1,"") | Q66: =IFERROR(Q9/P9-1,"") | ... AQ66: =IFERROR(AQ9/AP9-1,"") -> -0.25
B67: GE90 | J67: =IFERROR(J10/I10-1,"") -> 0.45833333 | K67: =IFERROR(K10/J10-1,"") -> -0.17142857 | L67: =IFERROR(L10/K10-1,"") -> 0.44827586 | M67: =IFERROR(M10/L10-1,"") -> -0.13095238 | N67: =IFERROR(N10/M10-1,"") -> 0 | O67: =IFERROR(O10/N10-1,"") -> 0.095890411 | P67: =IFERROR(P10/O10-1,"") -> 0.175 | Q67: =IFERROR(Q10/P10-1,"") -> 0.053191489 | ... AQ67: =IFERROR(AQ10/AP10-1,"")
B68: CF6-80 | J68: =IFERROR(J11/I11-1,"") -> 0.44 | K68: =IFERROR(K11/J11-1,"") -> -0.23611111 | L68: =IFERROR(L11/K11-1,"") -> -0.36363636 | M68: =IFERROR(M11/L11-1,"") -> -0.34285714 | N68: =IFERROR(N11/M11-1,"") -> 0.43478261 | O68: =IFERROR(O11/N11-1,"") -> 1.530303 | P68: =IFERROR(P11/O11-1,"") -> -0.22155689 | Q68: =IFERROR(Q11/P11-1,"") -> 0.023076923 | ... AQ68: =IFERROR(AQ11/AP11-1,"")
B69: Product0165 | J69: =IFERROR(J12/I12-1,"") | K69: =IFERROR(K12/J12-1,"") | L69: =IFERROR(L12/K12-1,"") -> 0 | M69: =IFERROR(M12/L12-1,"") -> 1.75 | N69: =IFERROR(N12/M12-1,"") -> 0.090909091 | O69: =IFERROR(O12/N12-1,"") -> 0.29166667 | P69: =IFERROR(P12/O12-1,"") -> 0.5483871 | Q69: =IFERROR(Q12/P12-1,"") -> -0.20833333 | ... AQ69: =IFERROR(AQ12/AP12-1,"")
B70: Product0163 | J70: =IFERROR(J13/I13-1,"") | K70: =IFERROR(K13/J13-1,"") | L70: =IFERROR(L13/K13-1,"") | M70: =IFERROR(M13/L13-1,"") | N70: =IFERROR(N13/M13-1,"") | O70: =IFERROR(O13/N13-1,"") | P70: =IFERROR(P13/O13-1,"") -> 0.2 | Q70: =IFERROR(Q13/P13-1,"") -> 0.25414365 | ... AQ70: =IFERROR(AQ13/AP13-1,"") -> -0.375
B71: Product0162 | J71: =IFERROR(J14/I14-1,"") | K71: =IFERROR(K14/J14-1,"") | L71: =IFERROR(L14/K14-1,"") | M71: =IFERROR(M14/L14-1,"") | N71: =IFERROR(N14/M14-1,"") | O71: =IFERROR(O14/N14-1,"") | P71: =IFERROR(P14/O14-1,"") | Q71: =IFERROR(Q14/P14-1,"") | ... AQ71: =IFERROR(AQ14/AP14-1,"") -> 0.032258065
B73: Price per engine growth
B74: Product0086 | P74: 0.025 | Q74: 0.025 | R74: 0.025 | S74: 0.025 | T74: 0.025 | U74: 0.025 | V74: 0.025 | W74: 0.025 | X74: 0.025 | Y74: 0.07 | Z74: 0.05 | AA74: 0.05 | AB74: 0.03 | AC74: 0.03 | AD74: 0.03 | AE74: 0.03 | AF74: 0.03 | AG74: 0.03 | AH74: 0.03 | AI74: 0.03 | AJ74: 0.03 | AK74: 0.03 | AL74: 0.03 | AM74: 0.03 | AN74: 0.03 | AO74: 0.03 | AP74: 0.03 | AQ74: 0.03
B75: Product0211 | T75: 0.025 | U75: 0.025 | V75: 0.025 | W75: 0.025 | X75: 0.04 | Y75: 0.1 | Z75: 0.08 | AA75: 0.055 | AB75: 0.04 | AC75: 0.04 | AD75: 0.04 | AE75: 0.04 | AF75: 0.04 | AG75: 0.04 | AH75: 0.04 | AI75: 0.04 | AJ75: 0.04 | AK75: 0.04 | AL75: 0.04 | AM75: 0.04 | AN75: 0.04 | AO75: 0.04 | AP75: 0.04 | AQ75: 0.04
B76: GE90 | P76: 0.025 | Q76: 0.025 | R76: 0.025 | S76: 0.025 | T76: 0.025 | U76: 0.025 | V76: 0.025 | W76: 0.025 | X76: 0.025 | Y76: 0.05 | Z76: 0.04 | AA76: 0.04 | AB76: 0.04 | AC76: 0.04 | AD76: 0.04 | AE76: 0.04 | AF76: 0.05 | AG76: 0.05 | AH76: 0.05 | AI76: 0.05 | AJ76: 0.05 | AK76: 0.05 | AL76: 0.05 | AM76: 0.05 | AN76: 0.05 | AO76: 0.05 | AP76: 0.05 | AQ76: 0.05
B77: CF6-80 | P77: 0.025 | Q77: 0.025 | R77: 0.025 | S77: 0.025 | T77: 0.025 | U77: 0.025 | V77: 0.025 | W77: 0.025 | X77: 0.025 | Y77: 0.025 | Z77: 0.025 | AA77: 0.025 | AB77: 0.04 | AC77: 0.05 | AD77: 0.05 | AE77: 0.05 | AF77: 0.05 | AG77: 0.05 | AH77: 0.05 | AI77: 0.05 | AJ77: 0.05 | AK77: 0.05 | AL77: 0.05 | AM77: 0.05 | AN77: 0.05 | AO77: 0.05 | AP77: 0.05 | AQ77: 0.05
B78: Product0165 | P78: 0.025 | Q78: 0.025 | R78: 0.025 | S78: 0.025 | T78: 0.025 | U78: 0.025 | V78: 0.025 | W78: 0.025 | X78: 0.025 | Y78: 0.025 | Z78: 0.025 | AA78: 0.025 | AB78: 0.04 | AC78: 0.05 | AD78: 0.05 | AE78: 0.05 | AF78: 0.05 | AG78: 0.05 | AH78: 0.05 | AI78: 0.05 | AJ78: 0.05 | AK78: 0.05 | AL78: 0.05 | AM78: 0.05 | AN78: 0.05 | AO78: 0.05 | AP78: 0.05 | AQ78: 0.05
B79: Product0163 | P79: 0.025 | Q79: 0.025 | R79: 0.025 | S79: 0.025 | T79: 0.025 | U79: 0.025 | V79: 0.025 | W79: 0.025 | X79: 0.04 | Y79: 0.06 | Z79: 0.05 | AA79: 0.025 | AB79: 0.04 | AC79: 0.05 | AD79: 0.05 | AE79: 0.05 | AF79: 0.05 | AG79: 0.05 | AH79: 0.05 | AI79: 0.05 | AJ79: 0.05 | AK79: 0.05 | AL79: 0.05 | AM79: 0.05 | AN79: 0.05 | AO79: 0.05 | AP79: 0.05 | AQ79: 0.05
B80: Product0162 | X80: 0.025 | Y80: 0.025 | Z80: 0.025 | AA80: 0.025 | AB80: 0.04 | AC80: 0.05 | AD80: 0.05 | AE80: 0.05 | AF80: 0.05 | AG80: 0.05 | AH80: 0.05 | AI80: 0.05 | AJ80: 0.05 | AK80: 0.05 | AL80: 0.05 | AM80: 0.05 | AN80: 0.05 | AO80: 0.05 | AP80: 0.05 | AQ80: 0.05
B82: Engine Aftermarket Build | C82: 2000 | D82: 2001 | E82: 2002 | F82: 2003 | G82: 2004 | H82: 2005 | I82: 2006 | J82: 2007 | K82: 2008 | L82: 2009 | M82: 2010 | N82: 2011 | O82: 2012 | P82: 2013 | Q82: 2014 | R82: 2015 | S82: 2016 | T82: 2017 | U82: 2018 | V82: 2019 | W82: 2020 | X82: 2021 | Y82: 2022 | Z82: 2023 | AA82: 2024E | AB82: 2025E | AC82: 2026E | AD82: 2027E | AE82: 2028E | AF82: 2029E | AG82: 2030E | AH82: 2031E | AI82: 2032E | AJ82: 2033E | AK82: 2034E | AL82: 2035E | AM82: 2036E | AN82: 20370E | AO82: 2038E | AP82: 2039E | AQ82: 2040E
B84: Product0086
B85: Shop Visit 1 | M85: =(E8*0.33+D8*0.33+C8*0.33)*0.6 -> 297 | N85: =(F8*0.33+E8*0.33+D8*0.33)*0.6 -> 346.5 | O85: =(G8*0.33+F8*0.33+E8*0.33)*0.6 -> 386.1 | P85: =(H8*0.33+G8*0.33+F8*0.33)*0.6 -> 415.8 | Q85: =(I8*0.33+H8*0.33+G8*0.33)*0.6 -> 498.366 | R85: =(J8*0.33+I8*0.33+H8*0.33)*0.6 -> 605.88 | S85: =(K8*0.33+J8*0.33+I8*0.33)*0.6 -> 708.444 | T85: =(L8*0.33+K8*0.33+J8*0.33)*0.6 -> 747.252 | ... Z85: =(R8*0.33+Q8*0.33+P8*0.33)*0.6 -> 925.452 | AA85: =(S8*0.33+R8*0.33+Q8*0.33)*0.58 -> 931.161 | AB85: =(T8*0.33+S8*0.33+R8*0.33)*0.55 -> 861.9435 | AC85: =(U8*0.33+T8*0.33+S8*0.33)*0.6 -> 827.838 | AD85: =(V8*0.33+U8*0.33+T8*0.33)*0.6 -> 570.042 | AE85: =(W8*0.33+V8*0.33+U8*0.33)*0.6 -> 315.216 | AF85: =(X8*0.33+W8*0.33+V8*0.33)*0.6 -> 129.69 | AG85: =(Y8*0.33+X8*0.33+W8*0.33)*0.6 -> 64.152 | AH85: =(Z8*0.33+Y8*0.33+X8*0.33)*0.6 -> 43.362 | AI85: =(AA8*0.33+Z8*0.33+Y8*0.33)*0.6 -> 32.076 | AJ85: =(AB8*0.33+AA8*0.33+Z8*0.33)*0.6 -> 30.096 | ... AQ85: =(AI8*0.33+AH8*0.33+AG8*0.33)*0.6 -> 0
B86: Shop Visit 2 | Q86: =(E8*0.33+D8*0.33+C8*0.33)*0.6 -> 297 | R86: =(F8*0.33+E8*0.33+D8*0.33)*0.6 -> 346.5 | S86: =(G8*0.33+F8*0.33+E8*0.33)*0.6 -> 386.1 | T86: =(H8*0.33+G8*0.33+F8*0.33)*0.6 -> 415.8 | U86: =(I8*0.33+H8*0.33+G8*0.33)*0.6 -> 498.366 | V86: =(J8*0.33+I8*0.33+H8*0.33)*0.6 -> 605.88 | W86: =(K8*0.33+J8*0.33+I8*0.33)*0.6 -> 708.444 | X86: =(L8*0.33+K8*0.33+J8*0.33)*0.6 -> 747.252 | ... AA86: =(O8*0.33+N8*0.33+M8*0.33)*0.6 -> 785.07 | AB86: =(P8*0.33+O8*0.33+N8*0.33)*0.55 -> 765.204 | AC86: =(Q8*0.33+P8*0.33+O8*0.33)*0.6 -> 884.664 | AD86: =(R8*0.33+Q8*0.33+P8*0.33)*0.6 -> 925.452 | AE86: =(S8*0.33+R8*0.33+Q8*0.33)*0.6 -> 963.27 | AF86: =(T8*0.33+S8*0.33+R8*0.33)*0.6 -> 940.302 | AG86: =(U8*0.33+T8*0.33+S8*0.33)*0.6 -> 827.838 | AH86: =(V8*0.33+U8*0.33+T8*0.33)*0.6 -> 570.042 | AI86: =(W8*0.33+V8*0.33+U8*0.33)*0.6 -> 315.216 | AJ86: =(X8*0.33+W8*0.33+V8*0.33)*0.6 -> 129.69 | ... AQ86: =(AE8*0.33+AD8*0.33+AC8*0.33)*0.6 -> 29.7
B87: Shop Visit 3 | W87: =(E8*0.33+D8*0.33+C8*0.33)*0.6 -> 297 | X87: =(F8*0.33+E8*0.33+D8*0.33)*0.6 -> 346.5 | Y87: =(G8*0.33+F8*0.33+E8*0.33)*0.6 -> 386.1 | Z87: =(H8*0.33+G8*0.33+F8*0.33)*0.6 -> 415.8 | AA87: =(I8*0.33+H8*0.33+G8*0.33)*0.6 -> 498.366 | AB87: =(J8*0.33+I8*0.33+H8*0.33)*0.55 -> 555.39 | AC87: =(K8*0.33+J8*0.33+I8*0.33)*0.6 -> 708.444 | AD87: =(L8*0.33+K8*0.33+J8*0.33)*0.6 -> 747.252 | AE87: =(M8*0.33+L8*0.33+K8*0.33)*0.6 -> 748.836 | AF87: =(N8*0.33+M8*0.33+L8*0.33)*0.6 -> 756.756 | AG87: =(O8*0.33+N8*0.33+M8*0.33)*0.6 -> 785.07 | AH87: =(P8*0.33+O8*0.33+N8*0.33)*0.6 -> 834.768 | AI87: =(Q8*0.33+P8*0.33+O8*0.33)*0.6 -> 884.664 | AJ87: =(R8*0.33+Q8*0.33+P8*0.33)*0.6 -> 925.452 | ... AQ87: =(Y8*0.33+X8*0.33+W8*0.33)*0.6 -> 64.152
B89: Price of Shop Visit 1 | Q89: =R89/(1+R$100) -> 3.3369795 | R89: =S89/(1+S$100) -> 3.420404 | S89: =T89/(1+T$100) -> 3.5059141 | T89: =U89/(1+U$100) -> 3.593562 | U89: =V89/(1+V$100) -> 3.683401 | V89: =W89/(1+W$100) -> 3.775486 | W89: =X89/(1+X$100) -> 3.8698732 | X89: =Y89/(1+Y$100) -> 3.9859694 | Y89: =Z89/(1+Z$100) -> 4.4642857 | Z89: 5 | AA89: =Z89*(1+AA$100) -> 5.375 | AB89: =AA89*(1+AB$100) -> 5.75125 | AC89: =AB89*(1+AC$100) -> 6.096325 | AD89: =AC89*(1+AD$100) -> 6.4316229 | AE89: =AD89*(1+AE$100) -> 6.753204 | AF89: =AE89*(1+AF$100) -> 7.0908642 | AG89: =AF89*(1+AG$100) -> 7.4454074 | AH89: =AG89*(1+AH$100) -> 7.8176778 | ... AQ89: =AP89*(1+AQ$100) -> 12.127784
B90: Price of Shop Visit 2 | Q90: =R90/(1+R$100) -> 4.6717713 | R90: =S90/(1+S$100) -> 4.7885656 | S90: =T90/(1+T$100) -> 4.9082798 | T90: =U90/(1+U$100) -> 5.0309868 | U90: =V90/(1+V$100) -> 5.1567614 | V90: =W90/(1+W$100) -> 5.2856805 | W90: =X90/(1+X$100) -> 5.4178225 | X90: =Y90/(1+Y$100) -> 5.5803571 | Y90: =Z90/(1+Z$100) -> 6.25 | Z90: 7 | AA90: =Z90*(1+AA$100) -> 7.525 | AB90: =AA90*(1+AB$100) -> 8.05175 | AC90: =AB90*(1+AC$100) -> 8.534855 | AD90: =AC90*(1+AD$100) -> 9.004272 | AE90: =AD90*(1+AE$100) -> 9.4544856 | AF90: =AE90*(1+AF$100) -> 9.9272099 | AG90: =AF90*(1+AG$100) -> 10.42357 | AH90: =AG90*(1+AH$100) -> 10.944749 | ... AQ90: =AP90*(1+AQ$100) -> 16.978898
B91: Price of Shop Visit 3 | Q91: =R91/(1+R$100) -> 4.0043754 | R91: =S91/(1+S$100) -> 4.1044848 | S91: =T91/(1+T$100) -> 4.2070969 | T91: =U91/(1+U$100) -> 4.3122744 | U91: =V91/(1+V$100) -> 4.4200812 | V91: =W91/(1+W$100) -> 4.5305832 | W91: =X91/(1+X$100) -> 4.6438478 | X91: =Y91/(1+Y$100) -> 4.7831633 | Y91: =Z91/(1+Z$100) -> 5.3571429 | Z91: 6 | AA91: =Z91*(1+AA$100) -> 6.45 | AB91: =AA91*(1+AB$100) -> 6.9015 | AC91: =AB91*(1+AC$100) -> 7.31559 | AD91: =AC91*(1+AD$100) -> 7.7179474 | AE91: =AD91*(1+AE$100) -> 8.1038448 | AF91: =AE91*(1+AF$100) -> 8.5090371 | AG91: =AF91*(1+AG$100) -> 8.9344889 | AH91: =AG91*(1+AH$100) -> 9.3812134 | ... AQ91: =AP91*(1+AQ$100) -> 14.553341
B93: Ticker0009 share % | O93: =O35 -> 0.5 | P93: =P35 -> 0.5 | Q93: =Q35 -> 0.5 | R93: =R35 -> 0.5 | S93: =S35 -> 0.5 | T93: =T35 -> 0.5 | U93: =U35 -> 0.5 | V93: =V35 -> 0.5 | ... AQ93: =AQ35 -> 0.5
B95: Shop Visit 1 Revenue | Q95: =Q85*Q89*Q$93 -> 831.51857 | R95: =R85*R89*R$93 -> 1036.1772 | S95: =S85*S89*S$93 -> 1241.8719 | T95: =T85*T89*T$93 -> 1342.6482 | U95: =U85*U89*U$93 -> 1379.1316 | V95: =V85*V89*V$93 -> 1428.5609 | W95: =W85*W89*W$93 -> 1519.0607 | X95: =X85*X89*X$93 -> 1663.6798 | ... AQ95: =AQ85*AQ89*AQ$93 -> 0
B96: Shop Visit 2 Revenue | Q96: =Q86*Q90*Q$93 -> 693.75804 | R96: =R86*R90*R$93 -> 829.61899 | S96: =S86*S90*S$93 -> 947.54341 | T96: =T86*T90*T$93 -> 1045.9421 | U96: =U86*U90*U$93 -> 1284.9773 | V96: =V86*V90*V$93 -> 1601.244 | W96: =W86*W90*W$93 -> 1919.1119 | X96: =X86*X90*X$93 -> 2084.9665 | ... AQ96: =AQ86*AQ90*AQ$93 -> 252.13663
B97: Shop Visit 3 Revenue | Q97: =Q87*Q91*Q$93 -> 0 | R97: =R87*R91*R$93 -> 0 | S97: =S87*S91*S$93 -> 0 | T97: =T87*T91*T$93 -> 0 | U97: =U87*U91*U$93 -> 0 | V97: =V87*V91*V$93 -> 0 | W97: =W87*W91*W$93 -> 689.6114 | X97: =X87*X91*X$93 -> 828.68304 | ... AQ97: =AQ87*AQ91*AQ$93 -> 466.81297
B98: Spare Revenue | Q98: =Q8*Q17*Q35*Q44 -> 934.48955 | R98: =R8*R17*R35*R44 -> 989.78019 | S98: =S8*S17*S35*S44 -> 1065.5027 | T98: =T8*T17*T35*T44 -> 931.5124 | U98: =U8*U17*U35*U44 -> 690.31262 | V98: =V8*V17*V35*V44 -> 265.00004 | W98: =W8*W17*W35*W44 -> 109.06683 | X98: =X8*X17*X35*X44 -> 76.190476 | ... AQ98: =AQ8*AQ17*AQ35*AQ44 -> 0
B99: Total Product0086 AM Revenue | Q99: =SUM(Q95:Q98) -> 2459.7662 | R99: =SUM(R95:R98) -> 2855.5764 | S99: =SUM(S95:S98) -> 3254.918 | T99: =SUM(T95:T98) -> 3320.1027 | U99: =SUM(U95:U98) -> 3354.4215 | V99: =SUM(V95:V98) -> 3294.8049 | W99: =SUM(W95:W98) -> 4236.8508 | X99: =SUM(X95:X98) -> 4653.5199 | ... AQ99: =SUM(AQ95:AQ98) -> 718.9496
B100: Price increase | R100: 0.025 | S100: 0.025 | T100: 0.025 | U100: 0.025 | V100: 0.025 | W100: 0.025 | X100: 0.03 | Y100: 0.12 | Z100: 0.12 | AA100: 0.075 | AB100: 0.07 | AC100: 0.06 | AD100: 0.055 | AE100: 0.05 | AF100: 0.05 | AG100: 0.05 | AH100: 0.05 | AI100: 0.05 | AJ100: 0.05 | AK100: 0.05 | AL100: 0.05 | AM100: 0.05 | AN100: 0.05 | AO100: 0.05 | AP100: 0.05 | AQ100: 0.05
B102: Product0211
B103: Shop Visit 1 | M103: =E9*0.33+D9*0.33+C9*0.33 -> 0 | N103: =F9*0.33+E9*0.33+D9*0.33 -> 0 | O103: =G9*0.33+F9*0.33+E9*0.33 -> 0 | P103: =H9*0.33+G9*0.33+F9*0.33 -> 0 | Q103: =I9*0.33+H9*0.33+G9*0.33 -> 0 | R103: =J9*0.33+I9*0.33+H9*0.33 -> 0 | S103: =K9*0.33+J9*0.33+I9*0.33 -> 0 | T103: =L9*0.33+K9*0.33+J9*0.33 -> 0 | ... Z103: =R9*0.33+Q9*0.33+P9*0.33 -> 0 | AA103: =(U9*0.33+T9*0.33+S9*0.33)*0.6 -> 327.492 | AB103: =(V9*0.33+U9*0.33+T9*0.33)*0.6 -> 655.974 | AC103: =(W9*0.33+V9*0.33+U9*0.33)*0.7 -> 847.539 | AD103: =(X9*0.33+W9*0.33+V9*0.33) -> 1120.68 | AE103: =(Y9*0.33+X9*0.33+W9*0.33)*1.2 -> 1107.216 | AF103: =(Z9*0.33+Y9*0.33+X9*0.33) -> 1171.83 | AG103: =(AA9*0.33+Z9*0.33+Y9*0.33) -> 1420.98 | AH103: =(AB9*0.33+AA9*0.33+Z9*0.33) -> 1653.3 | AI103: =(AC9*0.33+AB9*0.33+AA9*0.33) -> 1815.264 | AJ103: =(AD9*0.33+AC9*0.33+AB9*0.33) -> 2035.3344 | AK103: =(AE9*0.33+AD9*0.33+AC9*0.33) -> 2251.0118 | AL103: =(AF9*0.33+AE9*0.33+AD9*0.33) -> 2410.3253 | AM103: =(AG9*0.33+AF9*0.33+AE9*0.33) -> 2518.1323 | ... AQ103: =(AK9*0.33+AJ9*0.33+AI9*0.33) -> 2439.8774
B104: Shop Visit 2 | Q104: =E9*0.33+D9*0.33+C9*0.33 -> 0 | R104: =F9*0.33+E9*0.33+D9*0.33 -> 0 | S104: =G9*0.33+F9*0.33+E9*0.33 -> 0 | T104: =H9*0.33+G9*0.33+F9*0.33 -> 0 | U104: =I9*0.33+H9*0.33+G9*0.33 -> 0 | V104: =J9*0.33+I9*0.33+H9*0.33 -> 0 | W104: =K9*0.33+J9*0.33+I9*0.33 -> 0 | X104: =L9*0.33+K9*0.33+J9*0.33 -> 0 | ... AQ104: =AE9*0.33+AD9*0.33+AC9*0.33 -> 2251.0118
B105: Shop Visit 3 | W105: =E9*0.33+D9*0.33+C9*0.33 -> 0 | X105: =F9*0.33+E9*0.33+D9*0.33 -> 0 | Y105: =G9*0.33+F9*0.33+E9*0.33 -> 0 | Z105: =H9*0.33+G9*0.33+F9*0.33 -> 0 | AA105: =I9*0.33+H9*0.33+G9*0.33 -> 0 | AB105: =J9*0.33+I9*0.33+H9*0.33 -> 0 | AC105: =K9*0.33+J9*0.33+I9*0.33 -> 0 | AD105: =L9*0.33+K9*0.33+J9*0.33 -> 0 | ... AQ105: =Y9*0.33+X9*0.33+W9*0.33 -> 922.68
B107: Price of Shop Visit 1 | Q107: =R107/(1+R$118) -> 3.3369795 | R107: =S107/(1+S$118) -> 3.420404 | S107: =T107/(1+T$118) -> 3.5059141 | T107: =U107/(1+U$118) -> 3.593562 | U107: =V107/(1+V$118) -> 3.683401 | V107: =W107/(1+W$118) -> 3.775486 | W107: =X107/(1+X$118) -> 3.8698732 | X107: =Y107/(1+Y$118) -> 3.9859694 | Y107: =Z107/(1+Z$118) -> 4.4642857 | Z107: 5 | AA107: =Z107*(1+AA$118) -> 5.375 | AB107: =AA107*(1+AB$118) -> 5.75125 | AC107: =AB107*(1+AC$118) -> 6.0388125 | AD107: =AC107*(1+AD$118) -> 6.3407531 | AE107: =AD107*(1+AE$118) -> 6.6577908 | AF107: =AE107*(1+AF$118) -> 6.9241024 | AG107: =AF107*(1+AG$118) -> 7.2010665 | AH107: =AG107*(1+AH$118) -> 7.4891092 | ... AQ107: =AP107*(1+AQ$118) -> 10.659338
B108: Price of Shop Visit 2 | Q108: =R108/(1+R$118) -> 4.6717713 | R108: =S108/(1+S$118) -> 4.7885656 | S108: =T108/(1+T$118) -> 4.9082798 | T108: =U108/(1+U$118) -> 5.0309868 | U108: =V108/(1+V$118) -> 5.1567614 | V108: =W108/(1+W$118) -> 5.2856805 | W108: =X108/(1+X$118) -> 5.4178225 | X108: =Y108/(1+Y$118) -> 5.5803571 | Y108: =Z108/(1+Z$118) -> 6.25 | Z108: 7 | AA108: =Z108*(1+AA$118) -> 7.525 | AB108: =AA108*(1+AB$118) -> 8.05175 | AC108: =AB108*(1+AC$118) -> 8.4543375 | AD108: =AC108*(1+AD$118) -> 8.8770544 | AE108: =AD108*(1+AE$118) -> 9.3209071 | AF108: =AE108*(1+AF$118) -> 9.6937434 | AG108: =AF108*(1+AG$118) -> 10.081493 | AH108: =AG108*(1+AH$118) -> 10.484753 | ... AQ108: =AP108*(1+AQ$118) -> 14.923073
B109: Price of Shop Visit 3 | Q109: =R109/(1+R$118) -> 4.0043754 | R109: =S109/(1+S$118) -> 4.1044848 | S109: =T109/(1+T$118) -> 4.2070969 | T109: =U109/(1+U$118) -> 4.3122744 | U109: =V109/(1+V$118) -> 4.4200812 | V109: =W109/(1+W$118) -> 4.5305832 | W109: =X109/(1+X$118) -> 4.6438478 | X109: =Y109/(1+Y$118) -> 4.7831633 | Y109: =Z109/(1+Z$118) -> 5.3571429 | Z109: 6 | AA109: =Z109*(1+AA$118) -> 6.45 | AB109: =AA109*(1+AB$118) -> 6.9015 | AC109: =AB109*(1+AC$118) -> 7.246575 | AD109: =AC109*(1+AD$118) -> 7.6089038 | AE109: =AD109*(1+AE$118) -> 7.9893489 | AF109: =AE109*(1+AF$118) -> 8.3089229 | AG109: =AF109*(1+AG$118) -> 8.6412798 | AH109: =AG109*(1+AH$118) -> 8.986931 | ... AQ109: =AP109*(1+AQ$118) -> 12.791205
B111: Ticker0009 share % | O111: =O36 -> 0.5 | P111: =P36 -> 0.5 | Q111: =Q36 -> 0.5 | R111: =R36 -> 0.5 | S111: =S36 -> 0.5 | T111: =T36 -> 0.5 | U111: =U36 -> 0.5 | V111: =V36 -> 0.5 | ... AQ111: =AQ36 -> 0.5
B113: Shop Visit 1 Revenue | Q113: =Q103*Q107*Q$111 -> 0 | R113: =R103*R107*R$111 -> 0 | S113: =S103*S107*S$111 -> 0 | T113: =T103*T107*T$111 -> 0 | U113: =U103*U107*U$111 -> 0 | V113: =V103*V107*V$111 -> 0 | W113: =W103*W107*W$111 -> 0 | X113: =X103*X107*X$111 -> 0 | ... AQ113: =AQ103*AQ107*AQ$111 -> 13003.739
B114: Shop Visit 2 Revenue | Q114: =Q104*Q108*Q$111 -> 0 | R114: =R104*R108*R$111 -> 0 | S114: =S104*S108*S$111 -> 0 | T114: =T104*T108*T$111 -> 0 | U114: =U104*U108*U$111 -> 0 | V114: =V104*V108*V$111 -> 0 | W114: =W104*W108*W$111 -> 0 | X114: =X104*X108*X$111 -> 0 | ... AQ114: =AQ104*AQ108*AQ$111 -> 16796.007
B115: Shop Visit 3 Revenue | Q115: =Q105*Q109*Q$111 -> 0 | R115: =R105*R109*R$111 -> 0 | S115: =S105*S109*S$111 -> 0 | T115: =T105*T109*T$111 -> 0 | U115: =U105*U109*U$111 -> 0 | V115: =V105*V109*V$111 -> 0 | W115: =W105*W109*W$111 -> 0 | X115: =X105*X109*X$111 -> 0 | ... AQ115: =AQ105*AQ109*AQ$111 -> 5901.0945
B116: Spare revenue | Q116: =Q9*Q18*Q36*Q45 -> 0 | R116: =R9*R18*R36*R45 -> 0 | S116: =S9*S18*S36*S45 -> 45.168479 | T116: =T9*T18*T36*T45 -> 275.98234 | U116: =U9*U18*U36*U45 -> 689.02389 | V116: =V9*V18*V36*V45 -> 1096.645 | W116: =W9*W18*W36*W45 -> 527.71303 | X116: =X9*X18*X36*X45 -> 569.02357 | ... AQ116: =AQ9*AQ18*AQ36*AQ45 -> 948.4777
B117: Total Product0211 AM Revenue | Q117: =SUM(Q113:Q116) -> 0 | R117: =SUM(R113:R116) -> 0 | S117: =SUM(S113:S116) -> 45.168479 | T117: =SUM(T113:T116) -> 275.98234 | U117: =SUM(U113:U116) -> 689.02389 | V117: =SUM(V113:V116) -> 1096.645 | W117: =SUM(W113:W116) -> 527.71303 | X117: =SUM(X113:X116) -> 569.02357 | ... AQ117: =SUM(AQ113:AQ116) -> 36649.317
B118: Price increase | R118: 0.025 | S118: 0.025 | T118: 0.025 | U118: 0.025 | V118: 0.025 | W118: 0.025 | X118: 0.03 | Y118: 0.12 | Z118: 0.12 | AA118: 0.075 | AB118: 0.07 | AC118: 0.05 | AD118: 0.05 | AE118: 0.05 | AF118: 0.04 | AG118: 0.04 | AH118: 0.04 | AI118: 0.04 | AJ118: 0.04 | AK118: 0.04 | AL118: 0.04 | AM118: 0.04 | AN118: 0.04 | AO118: 0.04 | AP118: 0.04 | AQ118: 0.04
B120: GE90
...

Sheet SEG
B3: Ticker0009 Segment Data | C3: 1997 | D3: 1998 | E3: 1999 | F3: 2000 | G3: 2001 | H3: 2002 | I3: 2003 | J3: 1Q04 | K3: 2Q04 | L3: 3Q04 | M3: 4Q04 | N3: 2004 | O3: 1Q05 | P3: 2Q05 | Q3: 3Q05 | R3: 4Q05 | S3: 2005 | T3: 1Q06 | U3: 2Q06 | V3: 3Q06 | W3: 4Q06 | X3: 2006 | Y3: 1Q07 | Z3: 2Q07 | AA3: 3Q07 | AB3: 4Q07 | AC3: 2007 | AD3: 1Q08 | AE3: 2Q08 | AF3: 3Q08 | AG3: 4Q08 | AH3: 2008 | AI3: 1Q09 | AJ3: 2Q09 | AK3: 3Q09 | AL3: 4Q09 | AM3: 2009 | AN3: 1Q10 | AO3: 2Q10 | AP3: 3Q10 | AQ3: 4Q10 | AR3: 2010 | AS3: 1Q11 | AT3: 2Q11 | AU3: 3Q11 | AV3: 4Q11 | AW3: 2011 | AX3: 1Q12 | AY3: 2Q12 | AZ3: 3Q12 | BA3: 4Q12 | BB3: 2012 | BC3: 1Q13 | BD3: 2Q13 | BE3: 3Q13 | BF3: 4Q13 | BG3: 2013 | BH3: 1Q14 | BI3: 2Q14 | BJ3: 3Q14 | BK3: 4Q14 | BL3: 2014 | BM3: 1Q15 | BN3: 2Q15 | BO3: 3Q15 | BP3: 4Q15 | BQ3: 2015 | BR3: 1Q16 | BS3: 2Q16 | BT3: 3Q16 | BU3: 4Q16 | BV3: 2016 | BW3: 1Q17 | BX3: 2Q17 | BY3: 3Q17 | BZ3: 4Q17 | CA3: 2017 | CB3: 1Q18 | CC3: 2Q18 | CD3: 3Q18 | CE3: 4Q18 | CF3: 2018 | CG3: 1Q19 | CH3: 2Q19 | CI3: 3Q19 | CJ3: 4Q19 | CK3: 2019 | CL3: 1Q20 | CM3: 2Q20 | CN3: 3Q20 | CO3: 4Q20 | CP3: 2020 | CQ3: 1Q21 | CR3: 2Q21 | CS3: 3Q21 | CT3: 4Q21 | CU3: 2021 | CV3: 1Q22 | CW3: 2Q22 | CX3: 3Q22 | CY3: 4Q22 | CZ3: 2022 | DA3: 1Q23 | DB3: 2Q23 | DC3: 3Q23 | DD3: 4Q23 | DE3: 2023 | DF3: 1Q24 | DG3: 2Q24 | DH3: 3Q24 | DI3: 4Q24 | DJ3: 2024 | DK3: 1Q25 | DL3: 2Q25 | DM3: 3Q25E | DN3: 4Q25E | DO3: 2025E | DP3: 1Q26E | DQ3: 2Q26E | DR3: 3Q26E | DS3: 4Q26E | DT3: 2026E | DU3: 2027E | DV3: 2028E
B4: ($ mn) | C4: 35795 | D4: 36160 | E4: 36525 | F4: 36891 | G4: 37256 | H4: 37621 | I4: 37986 | J4: 38077 | K4: 38168 | L4: 38260 | M4: 38352 | N4: 38352 | O4: 38442 | P4: 38533 | Q4: 38625 | R4: 38717 | S4: 38717 | T4: 38807 | U4: 38898 | V4: 38990 | W4: 39082 | X4: 39082 | Y4: 39172 | Z4: 39263 | AA4: 39355 | AB4: 39447 | AC4: 39447 | AD4: 39538 | AE4: 39629 | AF4: 39721 | AG4: 39813 | AH4: 39813 | AI4: 39903 | AJ4: 39994 | AK4: 40086 | AL4: 40178 | AM4: 40178 | AN4: 40268 | AO4: 40359 | AP4: 40451 | AQ4: 40543 | AR4: 40543 | AS4: 40633 | AT4: 40724 | AU4: 40816 | AV4: 40908 | AW4: 40908 | AX4: 40999 | AY4: 41090 | AZ4: 41182 | BA4: 41274 | BB4: 41274 | BC4: 41364 | BD4: 41455 | BE4: 41547 | BF4: 41639 | BG4: 41639 | BH4: 41729 | BI4: 41820 | BJ4: 41912 | BK4: 42004 | BL4: 42004 | BM4: 42094 | BN4: 42185 | BO4: 42277 | BP4: 42369 | BQ4: 42369 | BR4: 42460 | BS4: 42551 | BT4: 42643 | BU4: 42735 | BV4: 42735 | BW4: 42825 | BX4: 42916 | BY4: 43008 | BZ4: 43100 | CA4: 43100 | CB4: 43190 | CC4: 43281 | CD4: 43373 | CE4: 43465 | CF4: 43465 | CG4: 43555 | CH4: 43646 | CI4: 43738 | CJ4: 43830 | CK4: 43830 | CL4: 43921 | CM4: 44012 | CN4: 44104 | CO4: 44196 | CP4: 44196 | CQ4: 44286 | CR4: 44377 | CS4: 44469 | CT4: 44561 | CU4: 44561 | CV4: 44651 | CW4: 44742 | CX4: 44834 | CY4: 44926 | CZ4: 44926 | DA4: 45016 | DB4: 45107 | DC4: 45199 | DD4: 45291 | DE4: 45291 | DF4: 45382 | DG4: 45473 | DH4: 45565 | DI4: 45657 | DJ4: 45657 | DK4: 45747 | DL4: 45838 | DM4: 45930 | DN4: 46022 | DO4: 46022 | DP4: 46112 | DQ4: 46203 | DR4: 46295 | DS4: 46387 | DT4: 46387 | DU4: 46752 | DV4: 47118
B6: Revenue
B7: Commercial Engines & Services | J7: =Aerospace!J71 -> 0 | K7: =Aerospace!K71 -> 0 | L7: =Aerospace!L71 -> 0 | M7: =Aerospace!M71 -> 0 | N7: =SUM(J7:M7) -> 0 | O7: =Aerospace!O71 -> 0 | P7: =Aerospace!P71 -> 0 | Q7: =Aerospace!Q71 -> 0 | R7: =Aerospace!R71 -> 0 | S7: =SUM(O7:R7) -> 0 | T7: =Aerospace!T71 -> 0 | U7: =Aerospace!U71 -> 0 | V7: =Aerospace!V71 -> 0 | W7: =Aerospace!W71 -> 0 | X7: =SUM(T7:W7) -> 0 | Y7: =Aerospace!Y71 -> 0 | Z7: =Aerospace!Z71 -> 0 | AA7: =Aerospace!AA71 -> 0 | AB7: =Aerospace!AB71 -> 0 | AC7: =SUM(Y7:AB7) -> 0 | AD7: =Aerospace!AD71 -> 0 | AE7: =Aerospace!AE71 -> 0 | AF7: =Aerospace!AF71 -> 0 | AG7: =Aerospace!AG71 -> 0 | AH7: =SUM(AD7:AG7) -> 0 | AI7: =Aerospace!AI71 -> 0 | AJ7: =Aerospace!AJ71 -> 0 | AK7: =Aerospace!AK71 -> 0 | AL7: =Aerospace!AL71 -> 0 | AM7: =SUM(AI7:AL7) -> 0 | AN7: =Aerospace!AN71 -> 0 | AO7: =Aerospace!AO71 -> 0 | AP7: =Aerospace!AP71 -> 0 | AQ7: =Aerospace!AQ71 -> 0 | AR7: =SUM(AN7:AQ7) -> 0 | AS7: =Aerospace!AS71 -> 0 | AT7: =Aerospace!AT71 -> 0 | AU7: =Aerospace!AU71 -> 0 | AV7: =Aerospace!AV71 -> 0 | AW7: =SUM(AS7:AV7) -> 0 | AX7: =Aerospace!AX71 -> 0 | AY7: =Aerospace!AY71 -> 0 | AZ7: =Aerospace!AZ71 -> 0 | BA7: =Aerospace!BA71 -> 0 | BB7: =SUM(AX7:BA7) -> 0 | BC7: =Aerospace!BC71 -> 0 | BD7: =Aerospace!BD71 -> 0 | BE7: =Aerospace!BE71 -> 0 | BF7: =Aerospace!BF71 -> 0 | BG7: =SUM(BC7:BF7) -> 0 | BH7: =Aerospace!BH71 -> 0 | BI7: =Aerospace!BI71 -> 0 | BJ7: =Aerospace!BJ71 -> 0 | BK7: =Aerospace!BK71 -> 0 | BL7: =SUM(BH7:BK7) -> 0 | BM7: =Aerospace!BM71*1000 -> 3971.8 | BN7: =Aerospace!BN71*1000 -> 4376.4 | BO7: =Aerospace!BO71*1000 -> 4200.7 | BP7: =Aerospace!BP71*1000 -> 4713.8 | BQ7: =SUM(BM7:BP7) -> 17262.7 | BR7: =Aerospace!BR71*1000 -> 4571.26 | BS7: =Aerospace!BS71*1000 -> 4818.14 | BT7: =Aerospace!BT71*1000 -> 4662 | BU7: =Aerospace!BU71*1000 -> 5318.38 | BV7: =SUM(BR7:BU7) -> 19369.78 | BW7: =Aerospace!BW71*1000 -> 5000 | BX7: =Aerospace!BX71*1000 -> 4900 | BY7: =Aerospace!BY71*1000 -> 4800 | BZ7: =Aerospace!BZ71*1000 -> 5000 | CA7: =SUM(BW7:BZ7) -> 19700 | CB7: =Aerospace!CB71*1000 -> 5300 | CC7: =Aerospace!CC71*1000 -> 5534 | CD7: =Aerospace!CD71*1000 -> 5600 | CE7: =Aerospace!CE71*1000 -> 6300 | CF7: =SUM(CB7:CE7) -> 22734 | CG7: =Aerospace!CG71*1000 -> 5949 | CH7: =Aerospace!CH71*1000 -> 5848 | CI7: =Aerospace!CI71*1000 -> 5997 | CJ7: =Aerospace!CJ71*1000 -> 6423 | CK7: =SUM(CG7:CJ7) -> 24217 | CL7: =data!CL153 -> 5113 | CM7: =data!CM153 -> 2519 | CN7: =data!CN153 -> 3087 | CO7: =data!CO153 -> 3760 | CP7: =SUM(CL7:CO7) -> 14479 | CQ7: =data!CQ153 -> 3354 | CR7: =data!CR153 -> 3115 | CS7: =data!CS153 -> 3602 | CT7: =data!CT153 -> 4289 | CU7: =SUM(CQ7:CT7) -> 14360 | CV7: =data!CV153 -> 3853 | CW7: =data!CW153 -> 4306 | CX7: =data!CX153 -> 4971 | CY7: =data!CY153 -> 5535 | CZ7: =SUM(CV7:CY7) -> 18665 | DA7: =data!DA153 -> 5232 | DB7: =data!DB153 -> 5737 | DC7: =data!DC153 -> 6457 | DD7: =data!DD153 -> 6429 | DE7: =SUM(DA7:DD7) -> 23855 | DF7: =data!DF153 -> 6096 | DG7: =data!DG153 -> 6132 | DH7: =data!DH153 -> 7003 | DI7: =data!DI153 -> 7650 | DJ7: =SUM(DF7:DI7) -> 26881 | DK7: =data!DK153 -> 6977 | DL7: =data!DL153 -> 7990 | DM7: =DH7*(1+DM33) -> 7983.42 | DN7: =DI7*(1+DN33) -> 8255.88 | DO7: =SUM(DK7:DN7) -> 31206.3 | DP7: =DK7*(1+DP33) -> 8093.32 | DQ7: =DL7*(1+DQ33) -> 9108.6 | DR7: =DM7*(1+DR33) -> 9180.933 | DS7: =DN7*(1+DS33) -> 9771.6596 | DT7: =SUM(DP7:DS7) -> 36154.513 | DU7: =DT7*(1+DU33) -> 39534.959 | DV7: =DU7*(1+DV33) -> 42460.546
B8: Defense & Propulsion Technology | J8: =Aerospace!J74 -> 0 | K8: =Aerospace!K74 -> 0 | L8: =Aerospace!L74 -> 0 | M8: =Aerospace!M74 -> 0 | N8: =SUM(J8:M8) -> 0 | O8: =Aerospace!O74 -> 0 | P8: =Aerospace!P74 -> 0 | Q8: =Aerospace!Q74 -> 0 | R8: =Aerospace!R74 -> 0 | S8: =SUM(O8:R8) -> 0 | T8: =Aerospace!T74 -> 0 | U8: =Aerospace!U74 -> 0 | V8: =Aerospace!V74 -> 0 | W8: =Aerospace!W74 -> 0 | X8: =SUM(T8:W8) -> 0 | Y8: =Aerospace!Y74 -> 0 | Z8: =Aerospace!Z74 -> 0 | AA8: =Aerospace!AA74 -> 0 | AB8: =Aerospace!AB74 -> 0 | AC8: =SUM(Y8:AB8) -> 0 | AD8: =Aerospace!AD74 -> 0 | AE8: =Aerospace!AE74 -> 0 | AF8: =Aerospace!AF74 -> 0 | AG8: =Aerospace!AG74 -> 0 | AH8: =SUM(AD8:AG8) -> 0 | AI8: =Aerospace!AI74 -> 0 | AJ8: =Aerospace!AJ74 -> 0 | AK8: =Aerospace!AK74 -> 0 | AL8: =Aerospace!AL74 -> 0 | AM8: =SUM(AI8:AL8) -> 0 | AN8: =Aerospace!AN74 -> 0 | AO8: =Aerospace!AO74 -> 0 | AP8: =Aerospace!AP74 -> 0 | AQ8: =Aerospace!AQ74 -> 0 | AR8: =SUM(AN8:AQ8) -> 0 | AS8: =Aerospace!AS74 -> 0 | AT8: =Aerospace!AT74 -> 0 | AU8: =Aerospace!AU74 -> 0 | AV8: =Aerospace!AV74 -> 0 | AW8: =SUM(AS8:AV8) -> 0 | AX8: =Aerospace!AX74 -> 0 | AY8: =Aerospace!AY74 -> 0 | AZ8: =Aerospace!AZ74 -> 0 | BA8: =Aerospace!BA74 -> 0 | BB8: =SUM(AX8:BA8) -> 0 | BC8: =Aerospace!BC74 -> 0 | BD8: =Aerospace!BD74 -> 0 | BE8: =Aerospace!BE74 -> 0 | BF8: =Aerospace!BF74 -> 0 | BG8: =SUM(BC8:BF8) -> 0 | BH8: =Aerospace!BH74 -> 0 | BI8: =Aerospace!BI74 -> 0 | BJ8: =Aerospace!BJ74 -> 0 | BK8: =Aerospace!BK74 -> 0 | BL8: =SUM(BH8:BK8) -> 0 | BM8: =Aerospace!BM74*1000+Aerospace!BM75*1000 -> 1702.2 | BN8: =Aerospace!BN74*1000 -> 1062.84 | BO8: =Aerospace!BO74*1000 -> 1020.17 | BP8: =Aerospace!BP74*1000 -> 1144.78 | BQ8: =SUM(BM8:BP8) -> 4929.99 | BR8: =Aerospace!BR74*1000+Aerospace!BR75*1000 -> 1690.74 | BS8: =Aerospace!BS74*1000 -> 846.43 | BT8: =Aerospace!BT74*1000 -> 819 | BU8: =Aerospace!BU74*1000 -> 934.31 | BV8: =SUM(BR8:BU8) -> 4290.48 | BW8: =Aerospace!BW74*1000+Aerospace!BW75*1000 -> 1673 | BX8: =Aerospace!BX74*1000 -> 900 | BY8: =Aerospace!BY74*1000 -> 1000 | BZ8: =Aerospace!BZ74*1000 -> 1200 | CA8: =SUM(BW8:BZ8) -> 4773 | CB8: =Aerospace!CB74*1000+Aerospace!CB75*1000 -> 1812 | CC8: =Aerospace!CC74*1000 -> 1073 | CD8: =Aerospace!CD74*1000 -> 900 | CE8: =Aerospace!CE74*1000 -> 1100 | CF8: =SUM(CB8:CE8) -> 4885 | CG8: =Aerospace!CG74*1000+Aerospace!CG75*1000 -> 2005 | CH8: =Aerospace!CH74*1000 -> 976 | CI8: =Aerospace!CI74*1000 -> 1061 | CJ8: =Aerospace!CJ74*1000 -> 1316 | CK8: =SUM(CG8:CJ8) -> 5358 | CL8: =data!CL154 -> 1780 | CM8: =data!CM154 -> 1864 | CN8: =data!CN154 -> 1833 | CO8: =data!CO154 -> 2086 | CP8: =SUM(CL8:CO8) -> 7563 | CQ8: =data!CQ154 -> 1638 | CR8: =data!CR154 -> 1724 | CS8: =data!CS154 -> 1796 | CT8: =data!CT154 -> 1792 | CU8: =SUM(CQ8:CT8) -> 6950 | CV8: =data!CV154 -> 1750 | CW8: =data!CW154 -> 1821 | CX8: =data!CX154 -> 1734 | CY8: =data!CY154 -> 2080 | CZ8: =SUM(CV8:CY8) -> 7385 | DA8: =data!DA154 -> 1966 | DB8: =data!DB154 -> 2375 | DC8: =data!DC154 -> 2205 | DD8: =data!DD154 -> 2416 | DE8: =SUM(DA8:DD8) -> 8962 | DF8: =data!DF154 -> 2312 | DG8: =data!DG154 -> 2401 | DH8: =data!DH154 -> 2243 | DI8: =data!DI154 -> 2523 | DJ8: =SUM(DF8:DI8) -> 9479 | DK8: =data!DK154 -> 2324 | DL8: =data!DL154 -> 2563 | DM8: =DH8*(1+DM34) -> 2422.44 | DN8: =DI8*(1+DN34) -> 2699.61 | DO8: =SUM(DK8:DN8) -> 10009.05 | DP8: =DK8*(1+DP34) -> 2475.06 | DQ8: =DL8*(1+DQ34) -> 2691.15 | DR8: =DM8*(1+DR34) -> 2519.3376 | DS8: =DN8*(1+DS34) -> 2834.5905 | DT8: =SUM(DP8:DS8) -> 10520.138 | DU8: =DT8*(1+DU34) -> 11046.145 | DV8: =DU8*(1+DV34) -> 11532.175
B9: Insurance | CL9: =data!CL10 -> 699 | CM9: =data!CM10 -> 756 | CN9: =data!CN10 -> 663 | CO9: =data!CO10 -> 747 | CP9: =SUM(CL9:CO9) -> 2865 | CQ9: =data!CQ10 -> 803 | CR9: =data!CR10 -> 810 | CS9: =data!CS10 -> 616 | CT9: =data!CT10 -> 877 | CU9: =SUM(CQ9:CT9) -> 3106 | CV9: =data!CV10 -> 764 | CW9: =data!CW10 -> 766 | CX9: =data!CX10 -> 645 | CY9: =data!CY10 -> 782 | CZ9: =SUM(CV9:CY9) -> 2957 | DA9: =data!DA10 -> 791 | DB9: =data!DB10 -> 847 | DC9: =data!DC10 -> 842 | DD9: =data!DD10 -> 909 | DE9: =SUM(DA9:DD9) -> 3389 | DF9: =data!DF10 -> 879 | DG9: =data!DG10 -> 871 | DH9: =data!DH10 -> 899 | DI9: =data!DI10 -> 933 | DJ9: =SUM(DF9:DI9) -> 3582 | DK9: =data!DK10 -> 934 | DL9: 0 | DM9: 0 | DN9: 0 | DO9: =SUM(DK9:DN9) -> 934 | DP9: 0 | DQ9: 0 | DR9: 0 | DS9: 0 | DT9: =SUM(DP9:DS9) -> 0 | DU9: 0 | DV9: 0
B10: Corporate & Eliminations | DA10: =data!DA156 -> -153 | DB10: =data!DB156 -> -205 | DC10: =data!DC156 -> -201 | DD10: =data!DD156 -> -298 | DE10: =SUM(DA10:DD10) -> -857 | DF10: =data!DF156 -> -332 | DG10: =data!DG156 -> -310 | DH10: =data!DH156 -> -303 | DI10: =data!DI156 -> -294 | DJ10: =SUM(DF10:DI10) -> -1239 | DK10: =data!DK156 -> -300 | DL10: =data!DL156 -> -402 | DM10: -340 | DN10: -350 | DO10: =SUM(DK10:DN10) -> -1392 | DP10: -325 | DQ10: -325 | DR10: -340 | DS10: -360 | DT10: =SUM(DP10:DS10) -> -1350 | DU10: -1380 | DV10: -1400
B11: Total adjusted revenue | C11: =SUM(C7:C9) -> 0 | D11: =SUM(D7:D9) -> 0 | E11: =SUM(E7:E9) -> 0 | F11: =SUM(F7:F9) -> 0 | G11: =SUM(G7:G9) -> 0 | H11: =SUM(H7:H9) -> 0 | I11: =SUM(I7:I9) -> 0 | J11: =SUM(J7:J9) -> 0 | ... BL11: =SUM(BL7:BL9) -> 0 | BM11: =SUM(BM7:BM8) -> 5674 | BN11: =SUM(BN7:BN8) -> 5439.24 | BO11: =SUM(BO7:BO8) -> 5220.87 | BP11: =SUM(BP7:BP8) -> 5858.58 | BQ11: =SUM(BQ7:BQ8) -> 22192.69 | BR11: =SUM(BR7:BR8) -> 6262 | BS11: =SUM(BS7:BS8) -> 5664.57 | BT11: =SUM(BT7:BT8) -> 5481 | ... CZ11: =SUM(CZ7:CZ8) -> 26050 | DA11: =SUM(DA7:DA8,DA10) -> 7045 | DB11: =SUM(DB7:DB8,DB10) -> 7907 | DC11: =SUM(DC7:DC8,DC10) -> 8461 | DD11: =SUM(DD7:DD8,DD10) -> 8547 | DE11: =SUM(DE7:DE8,DE10) -> 31960 | DF11: =SUM(DF7:DF8,DF10) -> 8076 | DG11: =SUM(DG7:DG8,DG10) -> 8223 | DH11: =SUM(DH7:DH8,DH10) -> 8943 | ... DV11: =SUM(DV7:DV8,DV10) -> 52592.722
B12: Acquisitions
B15: Divestitures
B18: Acquired Revenue
B19: Commercial Engines & Services | N19: =SUM(J19:M19) -> 0 | S19: =SUM(O19:R19) -> 0 | X19: =SUM(T19:W19) -> 0 | AC19: =SUM(Y19:AB19) -> 0 | AH19: =SUM(AD19:AG19) -> 0 | AM19: =SUM(AI19:AL19) -> 0 | AR19: =SUM(AN19:AQ19) -> 0 | AW19: =SUM(AS19:AV19) -> 0 | BB19: =SUM(AX19:BA19) -> 0 | BG19: =SUM(BC19:BF19) -> 0 | BL19: =SUM(BH19:BK19) -> 0 | BQ19: =SUM(BM19:BP19) -> 0 | BV19: =SUM(BR19:BU19) -> 0 | CA19: =SUM(BW19:BZ19) -> 0 | CF19: =SUM(CB19:CE19) -> 0 | CK19: =SUM(CG19:CJ19) -> 0 | CP19: =SUM(CL19:CO19) -> 0 | CU19: =SUM(CQ19:CT19) -> 0 | CZ19: =SUM(CV19:CY19) -> 0 | DE19: =SUM(DA19:DD19) -> 0 | DJ19: =SUM(DF19:DI19) -> 0
B20: Defense & Propulsion Technology | N20: =SUM(J20:M20) -> 0 | S20: =SUM(O20:R20) -> 0 | X20: =SUM(T20:W20) -> 0 | AC20: =SUM(Y20:AB20) -> 0 | AH20: =SUM(AD20:AG20) -> 0 | AM20: =SUM(AI20:AL20) -> 0 | AR20: =SUM(AN20:AQ20) -> 0 | AW20: =SUM(AS20:AV20) -> 0 | BB20: =SUM(AX20:BA20) -> 0 | BG20: =SUM(BC20:BF20) -> 0 | BL20: =SUM(BH20:BK20) -> 0 | BQ20: =SUM(BM20:BP20) -> 0 | BV20: =SUM(BR20:BU20) -> 0 | CA20: =SUM(BW20:BZ20) -> 0 | CF20: =SUM(CB20:CE20) -> 0 | CK20: =SUM(CG20:CJ20) -> 0 | CP20: =SUM(CL20:CO20) -> 0 | CU20: =SUM(CQ20:CT20) -> 0 | CZ20: =SUM(CV20:CY20) -> 0 | DE20: =SUM(DA20:DD20) -> 0 | DJ20: =SUM(DF20:DI20) -> 0
B21: Insurance
B22: Corporate & Eliminations | N22: =SUM(J22:M22) -> 0 | S22: =SUM(O22:R22) -> 0 | X22: =SUM(T22:W22) -> 0 | AC22: =SUM(Y22:AB22) -> 0 | AH22: =SUM(AD22:AG22) -> 0 | AM22: =SUM(AI22:AL22) -> 0 | AR22: =SUM(AN22:AQ22) -> 0 | AW22: =SUM(AS22:AV22) -> 0 | BB22: =SUM(AX22:BA22) -> 0 | BG22: =SUM(BC22:BF22) -> 0 | BL22: =SUM(BH22:BK22) -> 0 | BQ22: =SUM(BM22:BP22) -> 0 | BV22: =SUM(BR22:BU22) -> 0 | CA22: =SUM(BW22:BZ22) -> 0 | CF22: =SUM(CB22:CE22) -> 0 | CK22: =SUM(CG22:CJ22) -> 0 | CP22: =SUM(CL22:CO22) -> 0 | CU22: =SUM(CQ22:CT22) -> 0 | CZ22: =SUM(CV22:CY22) -> 0 | DE22: =SUM(DA22:DD22) -> 0 | DJ22: =SUM(DF22:DI22) -> 0
B23: Total acquired revenue | C23: =SUM(C19:C22) -> 0 | D23: =SUM(D19:D22) -> 0 | E23: =SUM(E19:E22) -> 0 | F23: =SUM(F19:F22) -> 0 | G23: =SUM(G19:G22) -> 0 | H23: =SUM(H19:H22) -> 0 | I23: =SUM(I19:I22) -> 0 | J23: =SUM(J19:J22) -> 0 | ... DV23: =SUM(DV19:DV22) -> 0
B25: Divested Revenue
B26: Commercial Engines & Services | N26: =SUM(J26:M26) -> 0 | S26: =SUM(O26:R26) -> 0 | X26: =SUM(T26:W26) -> 0 | AC26: =SUM(Y26:AB26) -> 0 | AH26: =SUM(AD26:AG26) -> 0 | AM26: =SUM(AI26:AL26) -> 0 | AR26: =SUM(AN26:AQ26) -> 0 | AW26: =SUM(AS26:AV26) -> 0 | BB26: =SUM(AX26:BA26) -> 0 | BG26: =SUM(BC26:BF26) -> 0 | BL26: =SUM(BH26:BK26) -> 0 | BQ26: =SUM(BM26:BP26) -> 0 | BV26: =SUM(BR26:BU26) -> 0 | CA26: =SUM(BW26:BZ26) -> 0 | CF26: =SUM(CB26:CE26) -> 0 | CK26: =SUM(CG26:CJ26) -> 0 | CP26: =SUM(CL26:CO26) -> 0 | CU26: =SUM(CQ26:CT26) -> 0 | CZ26: =SUM(CV26:CY26) -> 0 | DE26: =SUM(DA26:DD26) -> 0 | DJ26: =SUM(DF26:DI26) -> 0
B27: Defense & Propulsion Technology | N27: =SUM(J27:M27) -> 0 | S27: =SUM(O27:R27) -> 0 | X27: =SUM(T27:W27) -> 0 | AC27: =SUM(Y27:AB27) -> 0 | AH27: =SUM(AD27:AG27) -> 0 | AM27: =SUM(AI27:AL27) -> 0 | AR27: =SUM(AN27:AQ27) -> 0 | AW27: =SUM(AS27:AV27) -> 0 | BB27: =SUM(AX27:BA27) -> 0 | BG27: =SUM(BC27:BF27) -> 0 | BL27: =SUM(BH27:BK27) -> 0 | BQ27: =SUM(BM27:BP27) -> 0 | BV27: =SUM(BR27:BU27) -> 0 | CA27: =SUM(BW27:BZ27) -> 0 | CF27: =SUM(CB27:CE27) -> 0 | CK27: =SUM(CG27:CJ27) -> 0 | CP27: =SUM(CL27:CO27) -> 0 | CU27: =SUM(CQ27:CT27) -> 0 | CZ27: =SUM(CV27:CY27) -> 0 | DE27: =SUM(DA27:DD27) -> 0 | DJ27: =SUM(DF27:DI27) -> 0
B28: Insurance | N28: =SUM(J28:M28) -> 0 | S28: =SUM(O28:R28) -> 0 | X28: =SUM(T28:W28) -> 0 | AC28: =SUM(Y28:AB28) -> 0 | AH28: =SUM(AD28:AG28) -> 0 | AM28: =SUM(AI28:AL28) -> 0 | AR28: =SUM(AN28:AQ28) -> 0 | AW28: =SUM(AS28:AV28) -> 0 | BB28: =SUM(AX28:BA28) -> 0 | BG28: =SUM(BC28:BF28) -> 0 | BL28: =SUM(BH28:BK28) -> 0 | BQ28: =SUM(BM28:BP28) -> 0 | BV28: =SUM(BR28:BU28) -> 0 | CA28: =SUM(BW28:BZ28) -> 0 | CF28: =SUM(CB28:CE28) -> 0 | CK28: =SUM(CG28:CJ28) -> 0 | CP28: =SUM(CL28:CO28) -> 0 | CU28: =SUM(CQ28:CT28) -> 0 | CZ28: =SUM(CV28:CY28) -> 0 | DE28: =SUM(DA28:DD28) -> 0 | DJ28: =SUM(DF28:DI28) -> 0
B29: Corporate & Eliminations | N29: =SUM(J29:M29) -> 0 | S29: =SUM(O29:R29) -> 0 | X29: =SUM(T29:W29) -> 0 | AC29: =SUM(Y29:AB29) -> 0 | AH29: =SUM(AD29:AG29) -> 0 | AM29: =SUM(AI29:AL29) -> 0 | AR29: =SUM(AN29:AQ29) -> 0 | AW29: =SUM(AS29:AV29) -> 0 | BB29: =SUM(AX29:BA29) -> 0 | BG29: =SUM(BC29:BF29) -> 0 | BL29: =SUM(BH29:BK29) -> 0 | BQ29: =SUM(BM29:BP29) -> 0 | BV29: =SUM(BR29:BU29) -> 0 | CA29: =SUM(BW29:BZ29) -> 0 | CF29: =SUM(CB29:CE29) -> 0 | CK29: =SUM(CG29:CJ29) -> 0 | CP29: =SUM(CL29:CO29) -> 0 | CU29: =SUM(CQ29:CT29) -> 0 | CZ29: =SUM(CV29:CY29) -> 0 | DE29: =SUM(DA29:DD29) -> 0 | DJ29: =SUM(DF29:DI29) -> 0
B30: Total divested revenue | C30: =SUM(C26:C29) -> 0 | D30: =SUM(D26:D29) -> 0 | E30: =SUM(E26:E29) -> 0 | F30: =SUM(F26:F29) -> 0 | G30: =SUM(G26:G29) -> 0 | H30: =SUM(H26:H29) -> 0 | I30: =SUM(I26:I29) -> 0 | J30: =SUM(J26:J29) -> 0 | ... DV30: =SUM(DV26:DV29) -> 0
B32: Organic Revenue Y/Y Growth
B33: Commercial Engines & Services | J33: =(J7-J19-J26)/E7-1 -> #DIV/0! | K33: =(K7-K19-K26)/F7-1 -> #DIV/0! | L33: =(L7-L19-L26)/G7-1 -> #DIV/0! | M33: =(M7-M19-M26)/H7-1 -> #DIV/0! | BR33: =(BR7-BR19-BR26)/BM7-1 -> 0.15092905 | BS33: =(BS7-BS19-BS26)/BN7-1 -> 0.10093684 | BT33: =(BT7-BT19-BT26)/BO7-1 -> 0.10981503 | BU33: =(BU7-BU19-BU26)/BP7-1 -> 0.12825746 | BV33: =(BV7-BV19-BV26)/BQ7-1 -> 0.1220597 | BW33: =(BW7-BW19-BW26)/BR7-1 -> 0.093790334 | BX33: =(BX7-BX19-BX26)/BS7-1 -> 0.016989959 | BY33: =(BY7-BY19-BY26)/BT7-1 -> 0.02960103 | ... DL33: =(DL7-DL19-DL26)/DG7-1 -> 0.30300065 | DM33: 0.14 | DN33: 0.0792 | DO33: =(DO7-DO19-DO26)/DJ7-1 -> 0.16090547 | DP33: 0.16 | DQ33: 0.14 | DR33: 0.15 | DS33: 0.1836 | DT33: =(DT7-DT19-DT26)/DO7-1 -> 0.15856454 | DU33: 0.0935 | DV33: 0.074
B34: Defense & Propulsion Technology | J34: =(J8-J20-J27)/E8-1 -> #DIV/0! | K34: =(K8-K20-K27)/F8-1 -> #DIV/0! | L34: =(L8-L20-L27)/G8-1 -> #DIV/0! | M34: =(M8-M20-M27)/H8-1 -> #DIV/0! | BR34: =(BR8-BR20-BR27)/BM8-1 -> -0.0067324639 | BS34: =(BS8-BS20-BS27)/BN8-1 -> -0.20361484 | BT34: =(BT8-BT20-BT27)/BO8-1 -> -0.19719262 | BU34: =(BU8-BU20-BU27)/BP8-1 -> -0.18385192 | BV34: =(BV8-BV20-BV27)/BQ8-1 -> -0.12971832 | BW34: =(BW8-BW20-BW27)/BR8-1 -> -0.010492447 | BX34: =(BX8-BX20-BX27)/BS8-1 -> 0.063289345 | BY34: =(BY8-BY20-BY27)/BT8-1 -> 0.22100122 | ... DL34: =(DL8-DL20-DL27)/DG8-1 -> 0.067471887 | DM34: 0.08 | DN34: 0.07 | DO34: =(DO8-DO20-DO27)/DJ8-1 -> 0.055918346 | DP34: 0.065 | DQ34: 0.05 | DR34: 0.04 | DS34: 0.05 | DT34: =(DT8-DT20-DT27)/DO8-1 -> 0.051062598 | DU34: 0.05 | DV34: 0.044
B35: Insurance | CQ35: =(CQ9-CQ21-CQ28)/CL9-1 -> 0.14878398 | CR35: =(CR9-CR21-CR28)/CM9-1 -> 0.071428571 | CS35: =(CS9-CS21-CS28)/CN9-1 -> -0.070889894 | CT35: =(CT9-CT21-CT28)/CO9-1 -> 0.17402945 | CU35: =(CU9-CU21-CU28)/CP9-1 -> 0.084118674 | CV35: =(CV9-CV21-CV28)/CQ9-1 -> -0.04856787 | CW35: =(CW9-CW21-CW28)/CR9-1 -> -0.054320988 | CX35: =(CX9-CX21-CX28)/CS9-1 -> 0.047077922 | ... DK35: =(DK9-DK21-DK28)/DF9-1 -> 0.062571104 | DL35: 0 | DM35: 0 | DN35: 0 | DO35: =(DO9-DO21-DO28)/DJ9-1 -> -0.73925181 | DP35: 0 | DQ35: 0 | DR35: 0 | DS35: 0 | DT35: =(DT9-DT21-DT28)/DO9-1 -> -1 | DU35: 0 | DV35: 0
B36: Total | D36: =(D11-D23-D30)/(C11)-1 -> #DIV/0! | E36: =(E11-E23-E30)/(D11)-1 -> #DIV/0! | F36: =(F11-F23-F30)/(E11)-1 -> #DIV/0! | G36: =(G11-G23-G30)/(F11)-1 -> #DIV/0! | H36: =(H11-H23-H30)/(G11)-1 -> #DIV/0! | I36: =(I11-I23-I30)/(H11)-1 -> #DIV/0! | J36: =(J11-J23-J30)/(E11-E30)-1 -> #DIV/0! | K36: =(K11-K23-K30)/(F11-F30)-1 -> #DIV/0! | L36: =(L11-L23-L30)/(G11-G30)-1 -> #DIV/0! | M36: =(M11-M23-M30)/(H11-H30)-1 -> #DIV/0! | BR36: =(BR11-BR23-BR30)/(BM11)-1 -> 0.1036306 | BS36: =(BS11-BS23-BS30)/(BN11)-1 -> 0.041426743 | BT36: =(BT11-BT23-BT30)/(BO11)-1 -> 0.049825029 | BU36: =(BU11-BU23-BU30)/(BP11)-1 -> 0.067270567 | BV36: =(BV11-BV23-BV30)/(BQ11)-1 -> 0.066128532 | BW36: =(BW11-BW23-BW30)/(BR11)-1 -> 0.065633983 | BX36: =(BX11-BX23-BX30)/(BS11)-1 -> 0.023908258 | BY36: =(BY11-BY23-BY30)/(BT11)-1 -> 0.058201058 | ... DT36: =(DT11-DT23-DT30)/(DO11)-1 -> 0.13814259 | DU36: =(DU11-DU23-DU30)/(DT11)-1 -> 0.085526392 | DV36: =(DV11-DV23-DV30)/(DU11)-1 -> 0.068933765
B38: Revenue Y/Y Growth
B39: Commercial Engines & Services | BR39: =BR7/BM7-1 -> 0.15092905 | BS39: =BS7/BN7-1 -> 0.10093684 | BT39: =BT7/BO7-1 -> 0.10981503 | BU39: =BU7/BP7-1 -> 0.12825746 | BV39: =BV7/BQ7-1 -> 0.1220597 | BW39: =BW7/BR7-1 -> 0.093790334 | BX39: =BX7/BS7-1 -> 0.016989959 | BY39: =BY7/BT7-1 -> 0.02960103 | ... DT39: =DT7/DO7-1 -> 0.15856454 | DU39: =DU7/DT7-1 -> 0.0935 | DV39: =DV7/DU7-1 -> 0.074
