Workbook
Name AA.AlternatePriceSourceStartPeriod: "Q1-2019"
Name AA.CIK: "1045810"
Name AA.ColorizerVersion: "2.0.4.0"
Name AA.CompareQuarters.LatestMRQ: "Q2-2025"
Name AA.CSIN: "A7FLSL0150"
Name AA.CurationVersion: "2023.11.1.0"
Name AA.DBMacroVersion: "1.0.13.0"
Name AA.FreeCashFlow: "TRUE"
Name AA.GuidanceAnalysisNonGaapGrossProfitVersion: "1.0.0.0"
Name AA.GuidanceAnalysisRevenueVersion: "1.0.0.0"
Name AA.HardcodeChecker.LatestMRQ: "Q3-2020"
Name AA.ModelChecks.LatestMRQ: "Q3-2022"
Name AA.ModelChecks.LatestVersionNumber: "2.38.25.0"
Name AA.ModelColorScheme: "Classic"
Name AA.ModelVersion: "Q1-2027.23"
Name AA.NonLibraryWideCurationVersion: "4"
Name AA.PartialUpdate.BsAvailable: "TRUE"
Name AA.PartialUpdate.CfsAvailable: "TRUE"
Name AA.PartialUpdate.IsAvailable: "TRUE"
Name AA.PeriodLayout: "QFY"
Name AA.PersonalMacro.VersionNumber: ""
Name AA.RowNameEnforcerVersion: "2023.11.1.0"
Name AA.SessionToUploadId: ""
Name AA.StartWorkModelVersion: "Q1-2027.22"
Name AA.StartWorkType: ""
Name AA.SubyearType: "Q"
Name AA.TemplateUpgradeAttempted: "TRUE"
Name AA.TemplateVersion: "7.5.4.0"
Name AA.UpdateType: "Regular"
Name AA.VerifyUnitsAtModelVersion: "Q2-2019.21"
Name AS_KPI_1_Rpos: Model!$224:$224
Name AS_KPI_2_TotalFutureUnconditionalPurchaseCommitments: Model!$268:$268
Name AS_KPI_3_SalesToLargestCustomerAsAPercentOfTotalSales: Model!$271:$271
Name AS_KPI_4_SalesToSecondLargestCustomerAsAPercentOfTotalSales: Model!$272:$272
Name AS_KPI_5_SalesToThirdLargestCustomerAsAPercentOfTotalSales: Model!$273:$273
Name EC_CEO_BasePay: 'Exec Comp'!$7:$7
Name EC_CEO_EquityComp_Percent: 'Exec Comp'!$12:$12
Name EC_CEO_SharesOwned: 'Exec Comp'!$38:$38
Name EC_CEO_TotalComp: 'Exec Comp'!$11:$11
Name EC_CFO_BasePay: 'Exec Comp'!$40:$40
Name EC_CFO_EquityComp_Percent: 'Exec Comp'!$45:$45
Name EC_CFO_SharesOwned: 'Exec Comp'!$49:$49
Name EC_CFO_TotalComp: 'Exec Comp'!$44:$44
Name EC_Director_Compensation_Cash: 'Exec Comp'!$75:$75
Name EC_Director_Compensation_Total: 'Exec Comp'!$106:$106
Name EC_Directors_Current: 'Exec Comp'!$52:$52
Name EC_Directors_Current_Diverse: 'Exec Comp'!$55:$55
Name EC_Directors_Current_Female: 'Exec Comp'!$54:$54
Name EC_Directors_Current_Independent: 'Exec Comp'!$53:$53
Name EC_Directors_Nominees: 'Exec Comp'!$57:$57
Name EC_Directors_Nominees_Independent: 'Exec Comp'!$58:$58
Name EC_OperatingIncome_Target_NONGAAP: 'Exec Comp'!$121:$121
Name EC_Revenue_Target: 'Exec Comp'!$116:$116
Name FP.DataSource: 'Front Page'!$H$16
Name FP.DataSourceName: 'Front Page'!$H$15
Name FP.DataSourceName: 'Front Page'!$H$15
Name FP.Disclaimer: 'Front Page'!$C$22
Name FP.LastPrice: 'Front Page'!$H$20
Name FP.LastPrice: 'Front Page'!$H$20
Name FP.LastPriceDate: 'Front Page'!$F$20

Sheet Front Page
M6: Please contact this email for any model-specific questions:
M7: person@example.com
C9: Company Model: | H9: =Model!A1 -> Company1915 Company0697
C11: Updated: | H11: =OFFSET('Update Log'!$C$10,1,0,1,1) -> 46162
M12: Comments on Model:
C13: For: | H13: =OFFSET('Update Log'!$E$10,1,0,1,1) -> Quarterly (Earnings Report) | M13: On August 26, 2024, the Board of Directors approved an additional $50.0 billion in share repurchase authorization, without expiration. 'On, May 21, 2021, The company announced a 4-for-1 stock split. The model was adjusted for the split on July 20, 2021' 'Starting with the first quarter of fiscal 2021, the company's reportable segments have changed to “Graphics” and “Compute & Networking.” During the third quarter, Company1915 announced a definitive agreement to acquire Arm Limited from Company2574 Capital Limited and SVF Holdco (UK) Limited in a transaction valued at $40 billion. The transaction -- which is expected to be immediately accretive to Company1915’s non-GAAP gross margin and non-GAAP earnings per share -- is expected to close in the first quarter of calendar 2022.
C15: Consensus Data and Real-Time Stock Price: | H15: Bloomberg
H16: =IF(FP.DataSourceName="Bloomberg",1,IF(FP.DataSourceName="Capital IQ",2,IF(FP.DataSourceName="FactSet",3,IF(FP.DataSourceName="Refinitiv",4)))) -> 1
C18: Real-Time Stock Price: | H18: OFF
C20: Stock Price Override: | F20: 46175 | H20: 222.82
C22: DISCLAIMER Access to and use of this model, including the data contained herein (this "Model") is subject to Company2747, Inc.'s (a successor entity to Source Financial Modeling Company0697) ("Company") Terms of Use that you accepted prior to accessing this Model, the applicable Service Agreement between the Company and you (or a corporate entity that has authorized you to access and use this Model on its behalf in accordance with the terms of such Service Agreement) or other similar agreement between you and the Company. BY CONTINUING TO ACCESS OR USE THIS MODEL, YOU EXPRESSLY AGREE TO THE TERMS AND CONDITIONS OF SUCH AGREEMENTS. The Company and certain of its licensors have exclusive proprietary rights in this Model. This Model is being provided for internal use only. Unless prior written consent by the Company and its licensors has been provided to you, you may not distribute or otherwise furnish this Model to any third party, nor use or permit anyone to use this Model for any unlawful or unauthorized purpose. IF YOU HAVE UNLAWFULLY OBTAINED, OR ARE NOT AUTHORIZED TO USE THIS MODEL, YOU ARE OBLIGATED TO PROMPTLY: (I) RETURN THIS MODEL (AND ANY DERIVATIVE WORKS ARISING FROM OR RELATING THERETO) TO THE AUTHORIZED USER OF THIS MODEL; (II) PROVIDE NOTICE TO THE COMPANY AT person@example.com OF SUCH UNLAWFUL OR UNAUTHORIZED ACCESS AND USE; AND, (III) CERTIFY THAT YOU HAVE DESTROYED THIS MODEL (AND ANY DERIVATIVE WORKS ARISING FROM OR RELATING THERETO) AND ANY COPIES FROM YOUR SYSTEMS SO AS TO ENSURE THEY ARE INCAPABLE OF RETRIEVAL. A portion of the data contained in this Model may be powered by third party contributors and their respective licensors, or derived from data provided by such contributors, including (but not limited to): (i) QuoteMedia Inc.: A portion of the market data is powered by Quotemedia.com. All rights reserved. Data delayed 15 minutes unless otherwise indicated; (ii) S&P Global Market Intelligence LLC: Copyright (c) {{YEAR}} S&P Global Market Intelligence LLC (and its affiliates as applicable). All rights reserved. Reproduction of any information, opinions, views, data or material, including ratings ("Content") in any form is prohibited except with the prior written permission of the relevant party. Such party, its affiliates and suppliers ("Content Providers") do not guarantee the accuracy, adequacy, completeness, timeliness or availability of any Content and are not responsible for any errors or omissions (negligent or otherwise), regardless of the cause, or for the results obtained from the use of such Content. In no event shall Content Providers be liable for any damages, costs, expenses, legal fees, or losses (including lost income or lost profit and opportunity costs) in connection with any use of the Content. A reference to a particular investment or security, a rating or any observation concerning an investment that is part of the Content is not a recommendation to buy, sell or hold such investment or security, does not address the suitability of an investment or security and should not be relied on as investment advice. Credit ratings are statements of opinions and are not statements of fact; and, (iii) Refinitiv Canada Holdings Limited: A portion of the information may be provided by or derived from data provided by Refinitiv. By accessing or using this Model (including any portion of the data contained herein) you expressly represent that such access or use does not constitute a violation of any applicable law or regulation to which you or the securities are subject. This Model does not constitute investment advice by the Company or any of its licensors. Reference to a particular investment or security, credit rating or any observation concerning a security or investment in this Model is not a recommendation or solicitation to buy, sell or hold such investment or security or make any other investment decisions. For greater certainty, any forecasts or forward-looking information expressed herein are for illustrative purposes only and do not purport to express any view on what may transpire. Neither the Company nor any of its licensors have performed company-specific research on any projected information, as such, it is your responsibility to express your own views on projected results. This Model does not guarantee future performance and undue reliance should not be placed on such. You are solely responsible for evaluating the merits and risks of any investment based on your own business and financial expertise, the business and financial expertise of professional advisors with whom you have consulted, your financial situation and risk tolerance. Neither the Company, nor any of its licensors, undertake any liability with respect to your reliance on this Model. This Model is a quantitative tool with no investment views. The Company and its respective directors, officers, employees, agents, contractors, and affiliates may hold long or short positions in the security to which this Model relates, based on their personal views, and may initiate or close out any positions in such security at any time without any notice. THIS MODEL IS PROVIDED "AS IS" AND ON AN "AS AVAILABLE" BASIS ONLY, WITHOUT WARRANTIES OR CONDITIONS OF ANY KIND. NEITHER THE COMPANY NOR ANY OF ITS LICENSORS NOR THEIR RESPECTIVE AFFILIATES OR SUPPLIERS HAVE LIABILITY FOR THE ACCURACY, TIMELINESS OR COMPLETENESS OF THIS MODEL, OR FOR DELAYS, INTERRUPTIONS OR OMISSIONS HEREIN, NOR FOR ANY LOST PROFITS, INDIRECT, SPECIAL OR CONSEQUENTIAL DAMAGES. Access to data in this Model that is sourced from third party contributors is subject to termination in the event that any agreement between the Company and such third party contributors terminates for any reason. Copyright 2023 Company2747. All rights reserved.

Sheet Model
A1: Company1915 Company0697
A2: =CHOOSE(MO.DataSourceIndex,MO.Ticker.Bloomberg,MO.Ticker.CapIQ,MO.Ticker.FactSet,MO.Ticker.Thomson) -> Ticker0027 US | C2: =EOMONTH(C4,-12) -> 39478 | AA2: Restated | AB2: Restated | AC2: Restated | AD2: Restated | AE2: Restated
A3: =HP.TradeCurrency -> USD | B3: =IF(MO.RealTime="OFF",MO.LastPriceHardcoded,MO.LastPriceFormula) -> 222.82 | C3: =C4-C2 -> 360 | D3: =D4-C4 -> 371 | E3: =E4-D4 -> 364 | F3: =F4-E4 -> 364 | G3: =G4-F4 -> 91 | H3: =H4-G4 -> 91 | I3: =I4-H4 -> 91 | J3: =J4-I4 -> 91 | K3: =K4-F4 -> 364 | L3: =L4-K4 -> 91 | M3: =M4-L4 -> 91 | N3: =N4-M4 -> 91 | O3: =O4-N4 -> 91 | P3: =P4-K4 -> 364 | Q3: =Q4-P4 -> 91 | R3: =R4-Q4 -> 91 | S3: =S4-R4 -> 91 | T3: =T4-S4 -> 91 | U3: =U4-P4 -> 364 | V3: =V4-U4 -> 91 | W3: =W4-V4 -> 91 | X3: =X4-W4 -> 91 | Y3: =Y4-X4 -> 98 | Z3: =Z4-U4 -> 371 | AA3: =AA4-Z4 -> 91 | AB3: =AB4-AA4 -> 91 | AC3: =AC4-AB4 -> 91 | AD3: =AD4-AC4 -> 91 | AE3: =AE4-Z4 -> 364 | AF3: =AF4-AE4 -> 91 | AG3: =AG4-AF4 -> 91 | AH3: =AH4-AG4 -> 91 | AI3: =AI4-AH4 -> 91 | AJ3: =AJ4-AE4 -> 364 | AK3: =AK4-AJ4 -> 91 | AL3: =AL4-AK4 -> 91 | AM3: =AM4-AL4 -> 91 | AN3: =AN4-AM4 -> 91 | AO3: =AO4-AJ4 -> 364 | AP3: =AP4-AO4 -> 91 | AQ3: =AQ4-AP4 -> 91 | AR3: =AR4-AQ4 -> 91 | AS3: =AS4-AR4 -> 91 | AT3: =AT4-AO4 -> 364 | AU3: =AU4-AT4 -> 91 | AV3: =AV4-AU4 -> 91 | AW3: =AW4-AV4 -> 91 | AX3: =AX4-AW4 -> 98 | AY3: =AY4-AT4 -> 371 | AZ3: =AZ4-AY4 -> 91 | BA3: =BA4-AZ4 -> 91 | BB3: =BB4-BA4 -> 91 | BC3: =BC4-BB4 -> 91 | BD3: =BD4-AY4 -> 364 | BE3: =BE4-BD4 -> 91 | BF3: =BF4-BE4 -> 91 | BG3: =BG4-BF4 -> 91 | BH3: =BH4-BG4 -> 91 | BI3: =BI4-BD4 -> 364 | BJ3: =BJ4-BI4 -> 91 | BK3: =BK4-BJ4 -> 91 | BL3: =BL4-BK4 -> 91 | BM3: =BM4-BL4 -> 91 | BN3: =BN4-BI4 -> 364 | BO3: =BO4-BN4 -> 91 | BP3: =BP4-BO4 -> 91 | BQ3: =BQ4-BP4 -> 91 | BR3: =BR4-BQ4 -> 91 | BS3: =BS4-BN4 -> 364 | BT3: =BT4-BS4 -> 91 | BU3: =BU4-BT4 -> 91 | BV3: =BV4-BU4 -> 91 | BW3: =BW4-BV4 -> 91 | BX3: =BX4-BS4 -> 364 | BY3: =BY4-BX4 -> 91 | BZ3: =BZ4-BY4 -> 91 | CA3: =CA4-BZ4 -> 92 | CB3: =CB4-CA4 -> 97 | CC3: =CC4-BX4 -> 371 | CD3: =CD4-CC4 -> 89 | CE3: =CE4-CD4 -> 91 | CF3: =CF4-CE4 -> 92 | CG3: =CG4-CF4 -> 93 | CH3: =CH4-CC4 -> 365 | CI3: =CI4-CH4 -> 366 | CJ3: =CJ4-CI4 -> 365 | CK3: =CK4-CJ4 -> 365
A4: =FP.DataSourceName -> Bloomberg | B4: =IF(AND(MO.RealTimeStockPriceToggle,MO.LastPriceFormula<>"N/A"),"ON","OFF") -> OFF | C4: 39838 | D4: 40209 | E4: 40573 | F4: 40937 | G4: 41028 | H4: 41119 | I4: 41210 | J4: =K4 -> 41301 | K4: 41301 | L4: 41392 | M4: 41483 | N4: 41574 | O4: =P4 -> 41665 | P4: 41665 | Q4: 41756 | R4: 41847 | S4: 41938 | T4: =U4 -> 42029 | U4: 42029 | V4: 42120 | W4: 42211 | X4: 42302 | Y4: =Z4 -> 42400 | Z4: 42400 | AA4: 42491 | AB4: 42582 | AC4: 42673 | AD4: =AE4 -> 42764 | AE4: 42764 | AF4: 42855 | AG4: 42946 | AH4: 43037 | AI4: =AJ4 -> 43128 | AJ4: 43128 | AK4: 43219 | AL4: 43310 | AM4: 43401 | AN4: =AO4 -> 43492 | AO4: 43492 | AP4: 43583 | AQ4: 43674 | AR4: 43765 | AS4: =AT4 -> 43856 | AT4: 43856 | AU4: 43947 | AV4: 44038 | AW4: 44129 | AX4: =AY4 -> 44227 | AY4: 44227 | AZ4: 44318 | BA4: 44409 | BB4: 44500 | BC4: =BD4 -> 44591 | BD4: 44591 | BE4: 44682 | BF4: 44773 | BG4: 44864 | BH4: =BI4 -> 44955 | BI4: 44955 | BJ4: 45046 | BK4: 45137 | BL4: 45228 | BM4: =BN4 -> 45319 | BN4: 45319 | BO4: 45410 | BP4: 45501 | BQ4: 45592 | BR4: =BS4 -> 45683 | BS4: 45683 | BT4: 45774 | BU4: 45865 | BV4: 45956 | BW4: =BX4 -> 46047 | BX4: 46047 | BY4: 46138 | BZ4: =+EDATE(BY4,3) -> 46229 | CA4: =+EDATE(BZ4,3) -> 46321 | CB4: =DATE(YEAR(CA4)+1,1,31) -> 46418 | CC4: =CB4 -> 46418 | CD4: =+EDATE(CC4,3) -> 46507 | CE4: =+EDATE(CD4,3) -> 46598 | CF4: =+EDATE(CE4,3) -> 46690 | CG4: =DATE(YEAR(CF4)+1,1,31) -> 46783 | CH4: =CG4 -> 46783 | CI4: =EOMONTH(CH4,12) -> 47149 | CJ4: =EOMONTH(CI4,12) -> 47514 | CK4: =EOMONTH(CJ4,12) -> 47879
A5: =MO.ReportCurrency -> USD | C5: FY2009 | D5: =CONCATENATE("FY",RIGHT(C5,4)+1) -> FY2010 | E5: =CONCATENATE("FY",RIGHT(D5,4)+1) -> FY2011 | F5: =CONCATENATE("FY",RIGHT(E5,4)+1) -> FY2012 | G5: =CONCATENATE("Q1","-",RIGHT(F5,4)+1) -> Q1-2013 | H5: =CONCATENATE("Q2","-",RIGHT(G5,4)) -> Q2-2013 | I5: =CONCATENATE("Q3","-",RIGHT(H5,4)) -> Q3-2013 | J5: =CONCATENATE("Q4","-",RIGHT(I5,4)) -> Q4-2013 | K5: =CONCATENATE("FY",RIGHT(F5,4)+1) -> FY2013 | L5: =CONCATENATE("Q1","-",RIGHT(K5,4)+1) -> Q1-2014 | M5: =CONCATENATE("Q2","-",RIGHT(L5,4)) -> Q2-2014 | N5: =CONCATENATE("Q3","-",RIGHT(M5,4)) -> Q3-2014 | O5: =CONCATENATE("Q4","-",RIGHT(N5,4)) -> Q4-2014 | P5: =CONCATENATE("FY",RIGHT(K5,4)+1) -> FY2014 | Q5: =CONCATENATE("Q1","-",RIGHT(P5,4)+1) -> Q1-2015 | R5: =CONCATENATE("Q2","-",RIGHT(Q5,4)) -> Q2-2015 | S5: =CONCATENATE("Q3","-",RIGHT(R5,4)) -> Q3-2015 | T5: =CONCATENATE("Q4","-",RIGHT(S5,4)) -> Q4-2015 | U5: =CONCATENATE("FY",RIGHT(P5,4)+1) -> FY2015 | V5: =CONCATENATE("Q1","-",RIGHT(U5,4)+1) -> Q1-2016 | W5: =CONCATENATE("Q2","-",RIGHT(V5,4)) -> Q2-2016 | X5: =CONCATENATE("Q3","-",RIGHT(W5,4)) -> Q3-2016 | Y5: =CONCATENATE("Q4","-",RIGHT(X5,4)) -> Q4-2016 | Z5: =CONCATENATE("FY",RIGHT(U5,4)+1) -> FY2016 | AA5: =CONCATENATE("Q1","-",RIGHT(Z5,4)+1) -> Q1-2017 | AB5: =CONCATENATE("Q2","-",RIGHT(AA5,4)) -> Q2-2017 | AC5: =CONCATENATE("Q3","-",RIGHT(AB5,4)) -> Q3-2017 | AD5: =CONCATENATE("Q4","-",RIGHT(AC5,4)) -> Q4-2017 | AE5: =CONCATENATE("FY",RIGHT(Z5,4)+1) -> FY2017 | AF5: =CONCATENATE("Q1","-",RIGHT(AE5,4)+1) -> Q1-2018 | AG5: =CONCATENATE("Q2","-",RIGHT(AF5,4)) -> Q2-2018 | AH5: =CONCATENATE("Q3","-",RIGHT(AG5,4)) -> Q3-2018 | AI5: =CONCATENATE("Q4","-",RIGHT(AH5,4)) -> Q4-2018 | AJ5: =CONCATENATE("FY",RIGHT(AE5,4)+1) -> FY2018 | AK5: =CONCATENATE("Q1","-",RIGHT(AJ5,4)+1) -> Q1-2019 | AL5: =CONCATENATE("Q2","-",RIGHT(AK5,4)) -> Q2-2019 | AM5: =CONCATENATE("Q3","-",RIGHT(AL5,4)) -> Q3-2019 | AN5: =CONCATENATE("Q4","-",RIGHT(AM5,4)) -> Q4-2019 | AO5: =CONCATENATE("FY",RIGHT(AJ5,4)+1) -> FY2019 | AP5: =CONCATENATE("Q1","-",RIGHT(AO5,4)+1) -> Q1-2020 | AQ5: =CONCATENATE("Q2","-",RIGHT(AP5,4)) -> Q2-2020 | AR5: =CONCATENATE("Q3","-",RIGHT(AQ5,4)) -> Q3-2020 | AS5: =CONCATENATE("Q4","-",RIGHT(AR5,4)) -> Q4-2020 | AT5: =CONCATENATE("FY",RIGHT(AO5,4)+1) -> FY2020 | AU5: =CONCATENATE("Q1","-",RIGHT(AT5,4)+1) -> Q1-2021 | AV5: =CONCATENATE("Q2","-",RIGHT(AU5,4)) -> Q2-2021 | AW5: =CONCATENATE("Q3","-",RIGHT(AV5,4)) -> Q3-2021 | AX5: =CONCATENATE("Q4","-",RIGHT(AW5,4)) -> Q4-2021 | AY5: =CONCATENATE("FY",RIGHT(AT5,4)+1) -> FY2021 | AZ5: =CONCATENATE("Q1","-",RIGHT(AY5,4)+1) -> Q1-2022 | BA5: =CONCATENATE("Q2","-",RIGHT(AZ5,4)) -> Q2-2022 | BB5: =CONCATENATE("Q3","-",RIGHT(BA5,4)) -> Q3-2022 | BC5: =CONCATENATE("Q4","-",RIGHT(BB5,4)) -> Q4-2022 | BD5: =CONCATENATE("FY",RIGHT(AY5,4)+1) -> FY2022 | BE5: =CONCATENATE("Q1","-",RIGHT(BD5,4)+1) -> Q1-2023 | BF5: =CONCATENATE("Q2","-",RIGHT(BE5,4)) -> Q2-2023 | BG5: =CONCATENATE("Q3","-",RIGHT(BF5,4)) -> Q3-2023 | BH5: =CONCATENATE("Q4","-",RIGHT(BG5,4)) -> Q4-2023 | BI5: =CONCATENATE("FY",RIGHT(BD5,4)+1) -> FY2023 | BJ5: =CONCATENATE("Q1","-",RIGHT(BI5,4)+1) -> Q1-2024 | BK5: =CONCATENATE("Q2","-",RIGHT(BJ5,4)) -> Q2-2024 | BL5: =CONCATENATE("Q3","-",RIGHT(BK5,4)) -> Q3-2024 | BM5: =CONCATENATE("Q4","-",RIGHT(BL5,4)) -> Q4-2024 | BN5: =CONCATENATE("FY",RIGHT(BI5,4)+1) -> FY2024 | BO5: =CONCATENATE("Q1","-",RIGHT(BN5,4)+1) -> Q1-2025 | BP5: =CONCATENATE("Q2","-",RIGHT(BO5,4)) -> Q2-2025 | BQ5: =CONCATENATE("Q3","-",RIGHT(BP5,4)) -> Q3-2025 | BR5: =CONCATENATE("Q4","-",RIGHT(BQ5,4)) -> Q4-2025 | BS5: =CONCATENATE("FY",RIGHT(BN5,4)+1) -> FY2025 | BT5: =CONCATENATE("Q1","-",RIGHT(BS5,4)+1) -> Q1-2026 | BU5: =CONCATENATE("Q2","-",RIGHT(BT5,4)) -> Q2-2026 | BV5: =CONCATENATE("Q3","-",RIGHT(BU5,4)) -> Q3-2026 | BW5: =CONCATENATE("Q4","-",RIGHT(BV5,4)) -> Q4-2026 | BX5: =CONCATENATE("FY",RIGHT(BS5,4)+1) -> FY2026 | BY5: =CONCATENATE("Q1","-",RIGHT(BX5,4)+1) -> Q1-2027 | BZ5: =CONCATENATE("Q2","-",RIGHT(BY5,4)) -> Q2-2027 | CA5: =CONCATENATE("Q3","-",RIGHT(BZ5,4)) -> Q3-2027 | CB5: =CONCATENATE("Q4","-",RIGHT(CA5,4)) -> Q4-2027 | CC5: =CONCATENATE("FY",RIGHT(BX5,4)+1) -> FY2027 | CD5: =CONCATENATE("Q1","-",RIGHT(CC5,4)+1) -> Q1-2028 | CE5: =CONCATENATE("Q2","-",RIGHT(CD5,4)) -> Q2-2028 | CF5: =CONCATENATE("Q3","-",RIGHT(CE5,4)) -> Q3-2028 | CG5: =CONCATENATE("Q4","-",RIGHT(CF5,4)) -> Q4-2028 | CH5: =CONCATENATE("FY",RIGHT(CC5,4)+1) -> FY2028 | CI5: =CONCATENATE("FY",RIGHT(CH5,4)+1) -> FY2029 | CJ5: =CONCATENATE("FY",RIGHT(CI5,4)+1) -> FY2030 | CK5: =CONCATENATE("FY",RIGHT(CJ5,4)+1) -> FY2031
A6: Revenue Build (FS/PR)
A7: Gaming Revenue, mm | P7: 1511 | Q7: 468 | R7: 417 | S7: 527 | T7: =U7-SUM(Q7,R7,S7) -> 646 | U7: 2058 | V7: 587 | W7: 660 | X7: 761 | Y7: =Z7-SUM(V7,W7,X7) -> 810 | Z7: 2818 | AA7: 687 | AB7: 781 | AC7: 1244 | AD7: =AE7-SUM(AA7,AB7,AC7) -> 1348 | AE7: 4060 | AF7: 1027 | AG7: 1186 | AH7: 1561 | AI7: =AJ7-SUM(AF7,AG7,AH7) -> 1739 | AJ7: 5513 | AK7: 1723 | AL7: 1805 | AM7: 1764 | AN7: 954 | AO7: =SUM(AK7,AL7,AM7,AN7) -> 6246 | AP7: 1055 | AQ7: 1313 | AR7: 1659 | AS7: 1491 | AT7: =SUM(AP7,AQ7,AR7,AS7) -> 5518 | AU7: 1339 | AV7: 1654 | AW7: 2271 | AX7: 2495 | AY7: =SUM(AU7,AV7,AW7,AX7) -> 7759 | AZ7: 2760 | BA7: 3061 | BB7: 3221 | BC7: 3420 | BD7: =SUM(AZ7,BA7,BB7,BC7) -> 12462 | BE7: 3620 | BF7: 2042 | BG7: 1574 | BH7: 1831 | BI7: =SUM(BE7,BF7,BG7,BH7) -> 9067 | BJ7: 2240 | BK7: 2486 | BL7: 2856 | BM7: 2865 | BN7: =SUM(BJ7,BK7,BL7,BM7) -> 10447 | BO7: 2647 | BP7: 2880 | BQ7: 3279 | BR7: 2544 | BS7: =SUM(BO7,BP7,BQ7,BR7) -> 11350 | BT7: 3763 | BU7: 4287 | BV7: 4265 | BW7: 3727 | BX7: =SUM(BT7,BU7,BV7,BW7) -> 16042 | BY7: =BY34-BY30-BY26-BY231-BY11-BY22 -> 4219 | BZ7: =+BU7*(1+BZ9) -> 5573.1 | CA7: =+BV7*(1+CA9) -> 5331.25 | CB7: =+BW7*(1+CB9) -> 4472.4 | CC7: =SUM(BY7,BZ7,CA7,CB7) -> 19595.75 | CD7: =+BY7*(1+CD9) -> 5273.75 | CE7: =+BZ7*(1+CE9) -> 6966.375 | CF7: =+CA7*(1+CF9) -> 6664.0625 | CG7: =+CB7*(1+CG9) -> 5366.88 | CH7: =SUM(CD7,CE7,CF7,CG7) -> 24271.067 | CI7: =+CH7*(1+CI9) -> 26698.174 | CJ7: =+CI7*(1+CJ9) -> 29367.992 | CK7: =+CJ7*(1+CK9) -> 32304.791
A8: Q/Q Gaming Revenue growth, % | R8: =R7/Q7-1 -> -0.10897436 | S8: =S7/R7-1 -> 0.26378897 | T8: =T7/S7-1 -> 0.22580645 | V8: =V7/T7-1 -> -0.091331269 | W8: =W7/V7-1 -> 0.12436116 | X8: =X7/W7-1 -> 0.1530303 | Y8: =Y7/X7-1 -> 0.064388962 | AA8: =AA7/Y7-1 -> -0.15185185 | AB8: =AB7/AA7-1 -> 0.13682678 | AC8: =AC7/AB7-1 -> 0.59282971 | AD8: =AD7/AC7-1 -> 0.083601286 | AF8: =AF7/AD7-1 -> -0.23813056 | AG8: =AG7/AF7-1 -> 0.15481986 | AH8: =AH7/AG7-1 -> 0.31618887 | AI8: =AI7/AH7-1 -> 0.11402947 | AK8: =AK7/AI7-1 -> -0.0092006901 | AL8: =AL7/AK7-1 -> 0.04759141 | AM8: =AM7/AL7-1 -> -0.022714681 | AN8: =AN7/AM7-1 -> -0.45918367 | AP8: =AP7/AN7-1 -> 0.10587002 | AQ8: =AQ7/AP7-1 -> 0.24454976 | AR8: =AR7/AQ7-1 -> 0.26351866 | AS8: =AS7/AR7-1 -> -0.10126582 | AU8: =AU7/AS7-1 -> -0.101945 | AV8: =AV7/AU7-1 -> 0.23525019 | AW8: =AW7/AV7-1 -> 0.37303507 | AX8: =AX7/AW7-1 -> 0.098634963 | AZ8: =AZ7/AX7-1 -> 0.10621242 | BA8: =BA7/AZ7-1 -> 0.10905797 | BB8: =BB7/BA7-1 -> 0.0522705 | BC8: =BC7/BB7-1 -> 0.061782055 | BE8: =BE7/BC7-1 -> 0.058479532 | BF8: =BF7/BE7-1 -> -0.4359116 | BG8: =BG7/BF7-1 -> -0.22918707 | BH8: =BH7/BG7-1 -> 0.16327827 | BJ8: =BJ7/BH7-1 -> 0.2233752 | BK8: =BK7/BJ7-1 -> 0.10982143 | BL8: =BL7/BK7-1 -> 0.14883347 | BM8: =BM7/BL7-1 -> 0.0031512605 | BO8: =BO7/BM7-1 -> -0.07609075 | BP8: =BP7/BO7-1 -> 0.088024178 | BQ8: =BQ7/BP7-1 -> 0.13854167 | BR8: =BR7/BQ7-1 -> -0.22415371 | BT8: =BT7/BR7-1 -> 0.47916667 | BU8: =BU7/BT7-1 -> 0.1392506 | BV8: =BV7/BU7-1 -> -0.0051317938 | BW8: =BW7/BV7-1 -> -0.12614302 | BY8: =BY7/BW7-1 -> 0.13200966 | BZ8: =BZ7/BY7-1 -> 0.32095283 | CA8: =CA7/BZ7-1 -> -0.043395956 | CB8: =CB7/CA7-1 -> -0.1610973 | CD8: =CD7/CB7-1 -> 0.17917673 | CE8: =CE7/CD7-1 -> 0.32095283 | CF8: =CF7/CE7-1 -> -0.043395956 | CG8: =CG7/CF7-1 -> -0.19465341
A9: Y/Y Gaming Revenue Growth, % | U9: =+U7/P7-1 -> 0.36201191 | V9: =+V7/Q7-1 -> 0.2542735 | W9: =+W7/R7-1 -> 0.58273381 | X9: =+X7/S7-1 -> 0.44402277 | Y9: =+Y7/T7-1 -> 0.25386997 | Z9: =+Z7/U7-1 -> 0.36929057 | AA9: =+AA7/V7-1 -> 0.17035775 | AB9: =+AB7/W7-1 -> 0.18333333 | ... BY9: =+BY7/BT7-1 -> 0.12117991 | BZ9: 0.3 | CA9: 0.25 | CB9: 0.2 | CC9: =+CC7/BX7-1 -> 0.22152786 | CD9: 0.25 | CE9: 0.25 | CF9: 0.25 | CG9: 0.2 | CH9: =+CH7/CC7-1 -> 0.23858834 | CI9: 0.1 | CJ9: 0.1 | CK9: 0.1
A11: Professional Visualization Revenue, mm | P11: 789 | Q11: 191 | R11: 208 | S11: 206 | T11: =U11-SUM(Q11,R11,S11) -> 190 | U11: 795 | V11: 181 | W11: 176 | X11: 190 | Y11: =Z11-SUM(V11,W11,X11) -> 203 | Z11: 750 | AA11: 189 | AB11: 214 | AC11: 207 | AD11: =AE11-SUM(AA11,AB11,AC11) -> 225 | AE11: 835 | AF11: 205 | AG11: 235 | AH11: 239 | AI11: =AJ11-SUM(AF11,AG11,AH11) -> 255 | AJ11: 934 | AK11: 251 | AL11: 281 | AM11: 305 | AN11: 293 | AO11: =SUM(AK11,AL11,AM11,AN11) -> 1130 | AP11: 266 | AQ11: 291 | AR11: 324 | AS11: 331 | AT11: =SUM(AP11,AQ11,AR11,AS11) -> 1212 | AU11: 307 | AV11: 203 | AW11: 236 | AX11: 307 | AY11: =SUM(AU11,AV11,AW11,AX11) -> 1053 | AZ11: 372 | BA11: 519 | BB11: 577 | BC11: 643 | BD11: =SUM(AZ11,BA11,BB11,BC11) -> 2111 | BE11: 622 | BF11: 496 | BG11: 200 | BH11: 226 | BI11: =SUM(BE11,BF11,BG11,BH11) -> 1544 | BJ11: 295 | BK11: 379 | BL11: 416 | BM11: 463 | BN11: =SUM(BJ11,BK11,BL11,BM11) -> 1553 | BO11: 427 | BP11: 454 | BQ11: 486 | BR11: 511 | BS11: =SUM(BO11,BP11,BQ11,BR11) -> 1878 | BT11: 509 | BU11: 601 | BV11: 760 | BW11: 1321 | BX11: =SUM(BT11,BU11,BV11,BW11) -> 3191 | BY11: 1300 | BZ11: =+BU11*(1+BZ13) -> 631.05 | CA11: =+BV11*(1+CA13) -> 798 | CB11: =+BW11*(1+CB13) -> 1387.05 | CC11: =SUM(BY11,BZ11,CA11,CB11) -> 4116.1 | CD11: =+BY11*(1+CD13) -> 1365 | CE11: =+BZ11*(1+CE13) -> 662.6025 | CF11: =+CA11*(1+CF13) -> 837.9 | CG11: =+CB11*(1+CG13) -> 1456.4025 | CH11: =SUM(CD11,CE11,CF11,CG11) -> 4321.905 | CI11: =+CH11*(1+CI13) -> 4754.0955 | CJ11: =+CI11*(1+CJ13) -> 5229.5051 | CK11: =+CJ11*(1+CK13) -> 5752.4556
A12: Q/Q Professional Visualization Revenue growth, % | R12: =R11/Q11-1 -> 0.089005236 | S12: =S11/R11-1 -> -0.0096153846 | T12: =T11/S11-1 -> -0.077669903 | V12: =V11/T11-1 -> -0.047368421 | W12: =W11/V11-1 -> -0.027624309 | X12: =X11/W11-1 -> 0.079545455 | Y12: =Y11/X11-1 -> 0.068421053 | AA12: =AA11/Y11-1 -> -0.068965517 | AB12: =AB11/AA11-1 -> 0.13227513 | AC12: =AC11/AB11-1 -> -0.03271028 | AD12: =AD11/AC11-1 -> 0.086956522 | AF12: =AF11/AD11-1 -> -0.088888889 | AG12: =AG11/AF11-1 -> 0.14634146 | AH12: =AH11/AG11-1 -> 0.017021277 | AI12: =AI11/AH11-1 -> 0.066945607 | AK12: =AK11/AI11-1 -> -0.015686275 | AL12: =AL11/AK11-1 -> 0.11952191 | AM12: =AM11/AL11-1 -> 0.085409253 | AN12: =AN11/AM11-1 -> -0.039344262 | AP12: =AP11/AN11-1 -> -0.092150171 | AQ12: =AQ11/AP11-1 -> 0.093984962 | AR12: =AR11/AQ11-1 -> 0.11340206 | AS12: =AS11/AR11-1 -> 0.021604938 | AU12: =AU11/AS11-1 -> -0.072507553 | AV12: =AV11/AU11-1 -> -0.33876221 | AW12: =AW11/AV11-1 -> 0.16256158 | AX12: =AX11/AW11-1 -> 0.30084746 | AZ12: =AZ11/AX11-1 -> 0.21172638 | BA12: =BA11/AZ11-1 -> 0.39516129 | BB12: =BB11/BA11-1 -> 0.11175337 | BC12: =BC11/BB11-1 -> 0.11438475 | BE12: =BE11/BC11-1 -> -0.032659409 | BF12: =BF11/BE11-1 -> -0.20257235 | BG12: =BG11/BF11-1 -> -0.59677419 | BH12: =BH11/BG11-1 -> 0.13 | BJ12: =BJ11/BH11-1 -> 0.30530973 | BK12: =BK11/BJ11-1 -> 0.28474576 | BL12: =BL11/BK11-1 -> 0.09762533 | BM12: =BM11/BL11-1 -> 0.11298077 | BO12: =BO11/BM11-1 -> -0.07775378 | BP12: =BP11/BO11-1 -> 0.06323185 | BQ12: =BQ11/BP11-1 -> 0.070484581 | BR12: =BR11/BQ11-1 -> 0.051440329 | BT12: =BT11/BR11-1 -> -0.0039138943 | BU12: =BU11/BT11-1 -> 0.18074656 | BV12: =BV11/BU11-1 -> 0.26455907 | BW12: =BW11/BV11-1 -> 0.73815789 | BY12: =BY11/BW11-1 -> -0.015897048 | BZ12: =BZ11/BY11-1 -> -0.51457692 | CA12: =CA11/BZ11-1 -> 0.26455907 | CB12: =CB11/CA11-1 -> 0.73815789 | CD12: =CD11/CB11-1 -> -0.015897048 | CE12: =CE11/CD11-1 -> -0.51457692 | CF12: =CF11/CE11-1 -> 0.26455907 | CG12: =CG11/CF11-1 -> 0.73815789
A13: Y/Y Professional Visualization Revenue Growth, % | U13: =+U11/P11-1 -> 0.0076045627 | V13: =+V11/Q11-1 -> -0.052356021 | W13: =+W11/R11-1 -> -0.15384615 | X13: =+X11/S11-1 -> -0.077669903 | Y13: =+Y11/T11-1 -> 0.068421053 | Z13: =+Z11/U11-1 -> -0.056603774 | AA13: =+AA11/V11-1 -> 0.044198895 | AB13: =+AB11/W11-1 -> 0.21590909 | ... BY13: =+BY11/BT11-1 -> 1.5540275 | BZ13: 0.05 | CA13: 0.05 | CB13: 0.05 | CC13: =+CC11/BX11-1 -> 0.28990912 | CD13: 0.05 | CE13: 0.05 | CF13: 0.05 | CG13: 0.05 | CH13: =+CH11/CC11-1 -> 0.05 | CI13: 0.1 | CJ13: 0.1 | CK13: 0.1
A15: Compute revenue, mm | BJ15: 3357 | BK15: 8612 | BL15: 11908 | BM15: 15073 | BN15: 38950 | BO15: 19392 | BP15: 22604 | BQ15: 27644 | BR15: =BS15-SUM(BO15,BP15,BQ15) -> 32556 | BS15: 102196 | BT15: 34155 | BU15: 33844 | BV15: 43028 | BW15: =BX15-SUM(BT15,BU15,BV15) -> 51334 | BX15: 162361 | BY15: =BY22-BY19 -> 60446
A16: Q/Q Compute Revenue growth, % | BK16: =BK15/BJ15-1 -> 1.5653858 | BL16: =BL15/BK15-1 -> 0.38272178 | BM16: =BM15/BL15-1 -> 0.26578771 | BO16: =BO15/BM15-1 -> 0.28653884 | BP16: =BP15/BO15-1 -> 0.16563531 | BQ16: =BQ15/BP15-1 -> 0.22296939 | BR16: =BR15/BQ15-1 -> 0.17768774 | BT16: =BT15/BR15-1 -> 0.04911537 | BU16: =BU15/BT15-1 -> -0.0091055482 | BV16: =BV15/BU15-1 -> 0.27136272 | BW16: =BW15/BV15-1 -> 0.19303709 | BY16: =BY15/BW15-1 -> 0.17750419
A17: Y/Y Compute Revenue Growth, % | BO17: =+BO15/BJ15-1 -> 4.7765862 | BP17: =+BP15/BK15-1 -> 1.6247097 | BQ17: =+BQ15/BL15-1 -> 1.3214646 | BR17: =+BR15/BM15-1 -> 1.1598885 | BS17: =+BS15/BN15-1 -> 1.6237741 | BT17: =+BT15/BO15-1 -> 0.76129332 | BU17: =+BU15/BP15-1 -> 0.49725712 | BV17: =+BV15/BQ15-1 -> 0.55650412 | ... BY17: =+BY15/BT15-1 -> 0.76975553
A19: Networking revenue, mm | BJ19: 927 | BK19: 1711 | BL19: 2606 | BM19: 3331 | BN19: 8575 | BO19: 3171 | BP19: 3668 | BQ19: 3127 | BR19: =BS19-SUM(BO19,BP19,BQ19) -> 3024 | BS19: 12990 | BT19: 4957 | BU19: 7252 | BV19: 8187 | BW19: =BX19-SUM(BT19,BU19,BV19) -> 10980 | BX19: 31376 | BY19: 14800
A20: Q/Q Networking Revenue growth, % | BK20: =BK19/BJ19-1 -> 0.84573894 | BL20: =BL19/BK19-1 -> 0.52308591 | BM20: =BM19/BL19-1 -> 0.27820414 | BO20: =BO19/BM19-1 -> -0.048033624 | BP20: =BP19/BO19-1 -> 0.15673289 | BQ20: =BQ19/BP19-1 -> -0.14749182 | BR20: =BR19/BQ19-1 -> -0.032938919 | BT20: =BT19/BR19-1 -> 0.63921958 | BU20: =BU19/BT19-1 -> 0.46298164 | BV20: =BV19/BU19-1 -> 0.12892995 | BW20: =BW19/BV19-1 -> 0.3411506 | BY20: =BY19/BW19-1 -> 0.34790528
A21: Y/Y Networking Revenue Growth, % | BO21: =+BO19/BJ19-1 -> 2.420712 | BP21: =+BP19/BK19-1 -> 1.1437756 | BQ21: =+BQ19/BL19-1 -> 0.19992325 | BR21: =+BR19/BM19-1 -> -0.092164515 | BS21: =+BS19/BN19-1 -> 0.5148688 | BT21: =+BT19/BO19-1 -> 0.56322927 | BU21: =+BU19/BP19-1 -> 0.97709924 | BV21: =+BV19/BQ19-1 -> 1.6181644 | ... BY21: =+BY19/BT19-1 -> 1.9856768
A22: Datacenter Revenue, mm | P22: 199 | Q22: 57 | R22: 83 | S22: 89 | T22: =U22-SUM(Q22,R22,S22) -> 88 | U22: 317 | V22: 88 | W22: 72 | X22: 82 | Y22: =Z22-SUM(V22,W22,X22) -> 97 | Z22: 339 | AA22: 143 | AB22: 151 | AC22: 240 | AD22: =AE22-SUM(AA22,AB22,AC22) -> 296 | AE22: 830 | AF22: 409 | AG22: 416 | AH22: 501 | AI22: =AJ22-SUM(AF22,AG22,AH22) -> 606 | AJ22: 1932 | AK22: 701 | AL22: 760 | AM22: 792 | AN22: 679 | AO22: =SUM(AK22,AL22,AM22,AN22) -> 2932 | AP22: 634 | AQ22: 655 | AR22: 726 | AS22: 968 | AT22: =SUM(AP22,AQ22,AR22,AS22) -> 2983 | AU22: 1141 | AV22: 1752 | AW22: 1900 | AX22: 1903 | AY22: =SUM(AU22,AV22,AW22,AX22) -> 6696 | AZ22: 2048 | BA22: 2366 | BB22: 2936 | BC22: 3263 | BD22: =SUM(AZ22,BA22,BB22,BC22) -> 10613 | BE22: 3750 | BF22: 3806 | BG22: 3833 | BH22: 3616 | BI22: =SUM(BE22,BF22,BG22,BH22) -> 15005 | BJ22: 4284 | BK22: 10323 | BL22: 14514 | BM22: 18404 | BN22: =SUM(BJ22,BK22,BL22,BM22) -> 47525 | BO22: 22563 | BP22: 26272 | BQ22: 30771 | BR22: 35580 | BS22: =SUM(BO22,BP22,BQ22,BR22) -> 115186 | BT22: 39112 | BU22: 41096 | BV22: 51215 | BW22: 62314 | BX22: =SUM(BT22,BU22,BV22,BW22) -> 193737 | BY22: 75246 | BZ22: =+BU22*(1+BZ24) -> 83835.84 | CA22: =+BV22*(1+CA24) -> 84504.75 | CB22: =+BW22*(1+CB24) -> 87239.6 | CC22: =SUM(BY22,BZ22,CA22,CB22) -> 330826.19 | CD22: =+BY22*(1+CD24) -> 97819.8 | CE22: =+BZ22*(1+CE24) -> 108986.59 | CF22: =+CA22*(1+CF24) -> 105630.94 | CG22: =+CB22*(1+CG24) -> 109049.5 | CH22: =SUM(CD22,CE22,CF22,CG22) -> 421486.83 | CI22: =+CH22*(1+CI24) -> 505784.2 | CJ22: =+CI22*(1+CJ24) -> 596825.35 | CK22: =+CJ22*(1+CK24) -> 704253.91
A23: Q/Q Datacenter Revenue growth, % | R23: =R22/Q22-1 -> 0.45614035 | S23: =S22/R22-1 -> 0.072289157 | T23: =T22/S22-1 -> -0.011235955 | V23: =V22/T22-1 -> 0 | W23: =W22/V22-1 -> -0.18181818 | X23: =X22/W22-1 -> 0.13888889 | Y23: =Y22/X22-1 -> 0.18292683 | AA23: =AA22/Y22-1 -> 0.4742268 | AB23: =AB22/AA22-1 -> 0.055944056 | AC23: =AC22/AB22-1 -> 0.58940397 | AD23: =AD22/AC22-1 -> 0.23333333 | AF23: =AF22/AD22-1 -> 0.38175676 | AG23: =AG22/AF22-1 -> 0.017114914 | AH23: =AH22/AG22-1 -> 0.20432692 | AI23: =AI22/AH22-1 -> 0.20958084 | AK23: =AK22/AI22-1 -> 0.15676568 | AL23: =AL22/AK22-1 -> 0.084165478 | AM23: =AM22/AL22-1 -> 0.042105263 | AN23: =AN22/AM22-1 -> -0.14267677 | AP23: =AP22/AN22-1 -> -0.066273932 | AQ23: =AQ22/AP22-1 -> 0.033123028 | AR23: =AR22/AQ22-1 -> 0.10839695 | AS23: =AS22/AR22-1 -> 0.33333333 | AU23: =AU22/AS22-1 -> 0.17871901 | AV23: =AV22/AU22-1 -> 0.53549518 | AW23: =AW22/AV22-1 -> 0.084474886 | AX23: =AX22/AW22-1 -> 0.0015789474 | AZ23: =AZ22/AX22-1 -> 0.076195481 | BA23: =BA22/AZ22-1 -> 0.15527344 | BB23: =BB22/BA22-1 -> 0.24091293 | BC23: =BC22/BB22-1 -> 0.11137602 | BE23: =BE22/BC22-1 -> 0.14924916 | BF23: =BF22/BE22-1 -> 0.014933333 | BG23: =BG22/BF22-1 -> 0.007094062 | BH23: =BH22/BG22-1 -> -0.056613619 | BJ23: =BJ22/BH22-1 -> 0.18473451 | BK23: =BK22/BJ22-1 -> 1.4096639 | BL23: =BL22/BK22-1 -> 0.40598663 | BM23: =BM22/BL22-1 -> 0.26801709 | BO23: =BO22/BM22-1 -> 0.22598348 | BP23: =BP22/BO22-1 -> 0.16438417 | BQ23: =BQ22/BP22-1 -> 0.17124695 | BR23: =BR22/BQ22-1 -> 0.15628351 | BT23: =BT22/BR22-1 -> 0.099269252 | BU23: =BU22/BT22-1 -> 0.05072612 | BV23: =BV22/BU22-1 -> 0.24622834 | BW23: =BW22/BV22-1 -> 0.21671385 | BY23: =BY22/BW22-1 -> 0.20752961 | BZ23: =BZ22/BY22-1 -> 0.11415677 | CA23: =CA22/BZ22-1 -> 0.0079788072 | CB23: =CB22/CA22-1 -> 0.03236327 | CD23: =CD22/CB22-1 -> 0.12127749 | CE23: =CE22/CD22-1 -> 0.11415677 | CF23: =CF22/CE22-1 -> -0.030789609 | CG23: =CG22/CF22-1 -> 0.03236327
A24: Y/Y Datacenter Revenue Growth, % | U24: =+U22/P22-1 -> 0.59296482 | V24: =+V22/Q22-1 -> 0.54385965 | W24: =+W22/R22-1 -> -0.13253012 | X24: =+X22/S22-1 -> -0.078651685 | Y24: =+Y22/T22-1 -> 0.10227273 | Z24: =+Z22/U22-1 -> 0.069400631 | AA24: =+AA22/V22-1 -> 0.625 | AB24: =+AB22/W22-1 -> 1.0972222 | ... BY24: =+BY22/BT22-1 -> 0.92385969 | BZ24: 1.04 | CA24: 0.65 | CB24: 0.4 | CC24: =+CC22/BX22-1 -> 0.70760459 | CD24: 0.3 | CE24: 0.3 | CF24: 0.25 | CG24: 0.25 | CH24: =+CH22/CC22-1 -> 0.27404311 | CI24: 0.2 | CJ24: 0.18 | CK24: 0.18
A26: Automotive Revenue, mm | P26: 99 | Q26: 35 | R26: 40 | S26: 52 | T26: =U26-SUM(Q26,R26,S26) -> 56 | U26: 183 | V26: 77 | W26: 71 | X26: 79 | Y26: =Z26-SUM(V26,W26,X26) -> 93 | Z26: 320 | AA26: 113 | AB26: 119 | AC26: 127 | AD26: =AE26-SUM(AA26,AB26,AC26) -> 128 | AE26: 487 | AF26: 140 | AG26: 142 | AH26: 144 | AI26: =AJ26-SUM(AF26,AG26,AH26) -> 132 | AJ26: 558 | AK26: 145 | AL26: 161 | AM26: 172 | AN26: 163 | AO26: =SUM(AK26,AL26,AM26,AN26) -> 641 | AP26: 166 | AQ26: 209 | AR26: 162 | AS26: 163 | AT26: =SUM(AP26,AQ26,AR26,AS26) -> 700 | AU26: 155 | AV26: 111 | AW26: 125 | AX26: 145 | AY26: =SUM(AU26,AV26,AW26,AX26) -> 536 | AZ26: 154 | BA26: 152 | BB26: 135 | BC26: 125 | BD26: =SUM(AZ26,BA26,BB26,BC26) -> 566 | BE26: 138 | BF26: 220 | BG26: 251 | BH26: 294 | BI26: =SUM(BE26,BF26,BG26,BH26) -> 903 | BJ26: 296 | BK26: 253 | BL26: 261 | BM26: 281 | BN26: =SUM(BJ26,BK26,BL26,BM26) -> 1091 | BO26: 329 | BP26: 346 | BQ26: 449 | BR26: 570 | BS26: =SUM(BO26,BP26,BQ26,BR26) -> 1694 | BT26: 567 | BU26: 586 | BV26: 592 | BW26: 604 | BX26: =SUM(BT26,BU26,BV26,BW26) -> 2349 | BY26: 650 | BZ26: =+BU26*(1+BZ28) -> 703.2 | CA26: =+BV26*(1+CA28) -> 710.4 | CB26: =+BW26*(1+CB28) -> 724.8 | CC26: =SUM(BY26,BZ26,CA26,CB26) -> 2788.4 | CD26: =+BY26*(1+CD28) -> 845 | CE26: =+BZ26*(1+CE28) -> 843.84 | CF26: =+CA26*(1+CF28) -> 852.48 | CG26: =+CB26*(1+CG28) -> 869.76 | CH26: =SUM(CD26,CE26,CF26,CG26) -> 3411.08 | CI26: =+CH26*(1+CI28) -> 3752.188 | CJ26: =+CI26*(1+CJ28) -> 4127.4068 | CK26: =+CJ26*(1+CK28) -> 4540.1475
A27: Q/Q Automotive Revenue growth, % | R27: =R26/Q26-1 -> 0.14285714 | S27: =S26/R26-1 -> 0.3 | T27: =T26/S26-1 -> 0.076923077 | V27: =V26/T26-1 -> 0.375 | W27: =W26/V26-1 -> -0.077922078 | X27: =X26/W26-1 -> 0.11267606 | Y27: =Y26/X26-1 -> 0.17721519 | AA27: =AA26/Y26-1 -> 0.21505376 | AB27: =AB26/AA26-1 -> 0.053097345 | AC27: =AC26/AB26-1 -> 0.067226891 | AD27: =AD26/AC26-1 -> 0.0078740157 | AF27: =AF26/AD26-1 -> 0.09375 | AG27: =AG26/AF26-1 -> 0.014285714 | AH27: =AH26/AG26-1 -> 0.014084507 | AI27: =AI26/AH26-1 -> -0.083333333 | AK27: =AK26/AI26-1 -> 0.098484848 | AL27: =AL26/AK26-1 -> 0.11034483 | AM27: =AM26/AL26-1 -> 0.068322981 | AN27: =AN26/AM26-1 -> -0.052325581 | AP27: =AP26/AN26-1 -> 0.018404908 | AQ27: =AQ26/AP26-1 -> 0.25903614 | AR27: =AR26/AQ26-1 -> -0.22488038 | AS27: =AS26/AR26-1 -> 0.0061728395 | AU27: =AU26/AS26-1 -> -0.049079755 | AV27: =AV26/AU26-1 -> -0.28387097 | AW27: =AW26/AV26-1 -> 0.12612613 | AX27: =AX26/AW26-1 -> 0.16 | AZ27: =AZ26/AX26-1 -> 0.062068966 | BA27: =BA26/AZ26-1 -> -0.012987013 | BB27: =BB26/BA26-1 -> -0.11184211 | BC27: =BC26/BB26-1 -> -0.074074074 | BE27: =BE26/BC26-1 -> 0.104 | BF27: =BF26/BE26-1 -> 0.5942029 | BG27: =BG26/BF26-1 -> 0.14090909 | BH27: =BH26/BG26-1 -> 0.17131474 | BJ27: =BJ26/BH26-1 -> 0.0068027211 | BK27: =BK26/BJ26-1 -> -0.14527027 | BL27: =BL26/BK26-1 -> 0.031620553 | BM27: =BM26/BL26-1 -> 0.076628352 | BO27: =BO26/BM26-1 -> 0.17081851 | BP27: =BP26/BO26-1 -> 0.051671733 | BQ27: =BQ26/BP26-1 -> 0.29768786 | BR27: =BR26/BQ26-1 -> 0.26948775 | BT27: =BT26/BR26-1 -> -0.0052631579 | BU27: =BU26/BT26-1 -> 0.0335097 | BV27: =BV26/BU26-1 -> 0.010238908 | BW27: =BW26/BV26-1 -> 0.02027027 | BY27: =BY26/BW26-1 -> 0.07615894 | BZ27: =BZ26/BY26-1 -> 0.081846154 | CA27: =CA26/BZ26-1 -> 0.010238908 | CB27: =CB26/CA26-1 -> 0.02027027 | CD27: =CD26/CB26-1 -> 0.16583885 | CE27: =CE26/CD26-1 -> -0.0013727811 | CF27: =CF26/CE26-1 -> 0.010238908 | CG27: =CG26/CF26-1 -> 0.02027027
A28: Y/Y Automotive Revenue Growth, % | U28: =+U26/P26-1 -> 0.84848485 | V28: =+V26/Q26-1 -> 1.2 | W28: =+W26/R26-1 -> 0.775 | X28: =+X26/S26-1 -> 0.51923077 | Y28: =+Y26/T26-1 -> 0.66071429 | Z28: =+Z26/U26-1 -> 0.74863388 | AA28: =+AA26/V26-1 -> 0.46753247 | AB28: =+AB26/W26-1 -> 0.67605634 | ... BY28: =+BY26/BT26-1 -> 0.14638448 | BZ28: 0.2 | CA28: 0.2 | CB28: 0.2 | CC28: =+CC26/BX26-1 -> 0.18705832 | CD28: 0.3 | CE28: 0.2 | CF28: 0.2 | CG28: 0.2 | CH28: =+CH26/CC26-1 -> 0.22331086 | CI28: 0.1 | CJ28: 0.1 | CK28: 0.1
A30: OEM & IP Revenue, mm | P30: 1532 | Q30: 352 | R30: 355 | S30: 351 | T30: =U30-SUM(Q30,R30,S30) -> 271 | U30: 1329 | V30: 218 | W30: 174 | X30: 193 | Y30: =Z30-SUM(V30,W30,X30) -> 198 | Z30: 783 | AA30: 173 | AB30: 163 | AC30: 186 | AD30: =AE30-SUM(AA30,AB30,AC30) -> 176 | AE30: 698 | AF30: 156 | AG30: 251 | AH30: 191 | AI30: =AJ30-SUM(AF30,AG30,AH30) -> 179 | AJ30: 777 | AK30: 387 | AL30: 116 | AM30: 148 | AN30: 116 | AO30: =SUM(AK30,AL30,AM30,AN30) -> 767 | AP30: 99 | AQ30: 111 | AR30: 143 | AS30: 152 | AT30: =SUM(AP30,AQ30,AR30,AS30) -> 505 | AU30: 138 | AV30: 146 | AW30: 194 | AX30: 153 | AY30: =SUM(AU30,AV30,AW30,AX30) -> 631 | AZ30: 327 | BA30: 409 | BB30: 234 | BC30: 192 | BD30: =SUM(AZ30,BA30,BB30,BC30) -> 1162 | BE30: 158 | BF30: 140 | BG30: 73 | BH30: 84 | BI30: =SUM(BE30,BF30,BG30,BH30) -> 455 | BJ30: 77 | BK30: 66 | BL30: 73 | BM30: 90 | BN30: =SUM(BJ30,BK30,BL30,BM30) -> 306 | BO30: 78 | BP30: 88 | BQ30: 97 | BR30: 126 | BS30: =SUM(BO30,BP30,BQ30,BR30) -> 389 | BT30: 111 | BU30: 173 | BV30: 174 | BW30: 161 | BX30: =SUM(BT30,BU30,BV30,BW30) -> 619 | BY30: 200 | BZ30: =+BU30*(1+BZ32) -> 190.3 | CA30: =+BV30*(1+CA32) -> 191.4 | CB30: =+BW30*(1+CB32) -> 177.1 | CC30: =SUM(BY30,BZ30,CA30,CB30) -> 758.8 | CD30: =+BY30*(1+CD32) -> 220 | CE30: =+BZ30*(1+CE32) -> 209.33 | CF30: =+CA30*(1+CF32) -> 210.54 | CG30: =+CB30*(1+CG32) -> 194.81 | CH30: =SUM(CD30,CE30,CF30,CG30) -> 834.68 | CI30: =+CH30*(1+CI32) -> 918.148 | CJ30: =+CI30*(1+CJ32) -> 1009.9628 | CK30: =+CJ30*(1+CK32) -> 1110.9591
A31: Q/Q OEM & IP Revenue growth, % | R31: =R30/Q30-1 -> 0.0085227273 | S31: =S30/R30-1 -> -0.011267606 | T31: =T30/S30-1 -> -0.22792023 | V31: =V30/T30-1 -> -0.19557196 | W31: =W30/V30-1 -> -0.20183486 | X31: =X30/W30-1 -> 0.1091954 | Y31: =Y30/X30-1 -> 0.025906736 | AA31: =AA30/Y30-1 -> -0.12626263 | AB31: =AB30/AA30-1 -> -0.057803468 | AC31: =AC30/AB30-1 -> 0.14110429 | AD31: =AD30/AC30-1 -> -0.053763441 | AF31: =AF30/AD30-1 -> -0.11363636 | AG31: =AG30/AF30-1 -> 0.60897436 | AH31: =AH30/AG30-1 -> -0.23904382 | AI31: =AI30/AH30-1 -> -0.062827225 | AK31: =AK30/AI30-1 -> 1.1620112 | AL31: =AL30/AK30-1 -> -0.7002584 | AM31: =AM30/AL30-1 -> 0.27586207 | AN31: =AN30/AM30-1 -> -0.21621622 | AP31: =AP30/AN30-1 -> -0.14655172 | AQ31: =AQ30/AP30-1 -> 0.12121212 | AR31: =AR30/AQ30-1 -> 0.28828829 | AS31: =AS30/AR30-1 -> 0.062937063 | AU31: =AU30/AS30-1 -> -0.092105263 | AV31: =AV30/AU30-1 -> 0.057971014 | AW31: =AW30/AV30-1 -> 0.32876712 | AX31: =AX30/AW30-1 -> -0.21134021 | AZ31: =AZ30/AX30-1 -> 1.1372549 | BA31: =BA30/AZ30-1 -> 0.25076453 | BB31: =BB30/BA30-1 -> -0.42787286 | BC31: =BC30/BB30-1 -> -0.17948718 | BE31: =BE30/BC30-1 -> -0.17708333 | BF31: =BF30/BE30-1 -> -0.11392405 | BG31: =BG30/BF30-1 -> -0.47857143 | BH31: =BH30/BG30-1 -> 0.15068493 | BJ31: =BJ30/BH30-1 -> -0.083333333 | BK31: =BK30/BJ30-1 -> -0.14285714 | BL31: =BL30/BK30-1 -> 0.10606061 | BM31: =BM30/BL30-1 -> 0.23287671 | BO31: =BO30/BM30-1 -> -0.13333333 | BP31: =BP30/BO30-1 -> 0.12820513 | BQ31: =BQ30/BP30-1 -> 0.10227273 | BR31: =BR30/BQ30-1 -> 0.29896907 | BT31: =BT30/BR30-1 -> -0.11904762 | BU31: =BU30/BT30-1 -> 0.55855856 | BV31: =BV30/BU30-1 -> 0.0057803468 | BW31: =BW30/BV30-1 -> -0.074712644 | BY31: =BY30/BW30-1 -> 0.24223602 | BZ31: =BZ30/BY30-1 -> -0.0485 | CA31: =CA30/BZ30-1 -> 0.0057803468 | CB31: =CB30/CA30-1 -> -0.074712644 | CD31: =CD30/CB30-1 -> 0.24223602 | CE31: =CE30/CD30-1 -> -0.0485 | CF31: =CF30/CE30-1 -> 0.0057803468 | CG31: =CG30/CF30-1 -> -0.074712644
A32: Y/Y OEM & IP Revenue Growth, % | U32: =+U30/P30-1 -> -0.13250653 | V32: =+V30/Q30-1 -> -0.38068182 | W32: =+W30/R30-1 -> -0.50985915 | X32: =+X30/S30-1 -> -0.45014245 | Y32: =+Y30/T30-1 -> -0.26937269 | Z32: =+Z30/U30-1 -> -0.41083521 | AA32: =+AA30/V30-1 -> -0.20642202 | AB32: =+AB30/W30-1 -> -0.063218391 | ... BY32: =+BY30/BT30-1 -> 0.8018018 | BZ32: 0.1 | CA32: 0.1 | CB32: 0.1 | CC32: =+CC30/BX30-1 -> 0.22584814 | CD32: 0.1 | CE32: 0.1 | CF32: 0.1 | CG32: 0.1 | CH32: =+CH30/CC30-1 -> 0.1 | CI32: 0.1 | CJ32: 0.1 | CK32: 0.1
A34: Total Revenue, mm | C34: =C300 -> 3424.859 | D34: =D300 -> 3326.445 | E34: =E300 -> 3543.309 | F34: =F300 -> 3997.93 | G34: =G300 -> 924.877 | H34: =H300 -> 1044.27 | I34: =I300 -> 1204.11 | J34: =J300 -> 1106.902 | ... O34: =O300 -> 1144.218 | P34: =P7+P11+P22+P26+P30 -> 4130 | Q34: =Q7+Q11+Q22+Q26+Q30 -> 1103 | R34: =R7+R11+R22+R26+R30 -> 1103 | S34: =S7+S11+S22+S26+S30 -> 1225 | T34: =T7+T11+T22+T26+T30 -> 1251 | U34: =U7+U11+U22+U26+U30 -> 4682 | V34: =V7+V11+V22+V26+V30 -> 1151 | W34: =W7+W11+W22+W26+W30 -> 1153 | ... BX34: =BX7+BX11+BX22+BX26+BX30 -> 215938 | BY34: =BY370 -> 81615 | BZ34: =BZ7+BZ11+BZ22+BZ26+BZ30 -> 90933.49 | CA34: =CA7+CA11+CA22+CA26+CA30 -> 91535.8 | CB34: =CB7+CB11+CB22+CB26+CB30 -> 94000.95 | CC34: =CC7+CC11+CC22+CC26+CC30 -> 358085.24 | CD34: =CD7+CD11+CD22+CD26+CD30 -> 105523.55 | CE34: =CE7+CE11+CE22+CE26+CE30 -> 117668.74 | CF34: =CF7+CF11+CF22+CF26+CF30 -> 114195.92 | CG34: =CG7+CG11+CG22+CG26+CG30 -> 116937.35 | ... CK34: =CK7+CK11+CK22+CK26+CK30 -> 747962.27
A35: =CONCATENATE("Consensus Estimates - ",IFERROR(LEFT(A34,FIND("(",A34)-1),A34)) -> Consensus Estimates - Total Revenue, mm | BZ35: =BZ371 -> N/A | CA35: =CA371 -> N/A | CB35: =CB371 -> N/A | CC35: =CC371 -> N/A | CD35: =CD371 -> N/A | CE35: =CE371 -> N/A | CF35: =CF371 -> N/A | CG35: =CG371 -> N/A | ... CK35: =CK371 -> N/A
A36: Guidance - Total Revenue, mm | BZ36: =BZ580 -> 91000 | CA36: =CA580 | CB36: =CB580 | CC36: =CC580 | CD36: =CD580 | CE36: =CE580 | CF36: =CF580 | CG36: =CG580 | ... CK36: =CK580 -> 0
A37: Q/Q Total Revenue growth, % | H37: =H34/G34-1 -> 0.12909068 | I37: =I34/H34-1 -> 0.15306386 | J37: =J34/I34-1 -> -0.080730166 | L37: =L34/J34-1 -> -0.13746745 | M37: =M34/L34-1 -> 0.023565603 | N37: =N34/M34-1 -> 0.078516185 | O37: =O34/N34-1 -> 0.085629816 | Q37: =Q34/O34-1 -> -0.036022856 | R37: =R34/Q34-1 -> 0 | S37: =S34/R34-1 -> 0.11060743 | T37: =T34/S34-1 -> 0.02122449 | V37: =V34/T34-1 -> -0.079936051 | W37: =W34/V34-1 -> 0.0017376195 | X37: =X34/W34-1 -> 0.13183001 | Y37: =Y34/X34-1 -> 0.073563218 | AA37: =AA34/Y34-1 -> -0.068522484 | AB37: =AB34/AA34-1 -> 0.094252874 | AC37: =AC34/AB34-1 -> 0.40336134 | AD37: =AD34/AC34-1 -> 0.084331337 | AF37: =AF34/AD34-1 -> -0.10860561 | AG37: =AG34/AF34-1 -> 0.15126484 | AH37: =AH34/AG34-1 -> 0.18206278 | AI37: =AI34/AH34-1 -> 0.10432473 | AK37: =AK34/AI34-1 -> 0.10168327 | AL37: =AL34/AK34-1 -> -0.026192703 | AM37: =AM34/AL34-1 -> 0.018571886 | AN37: =AN34/AM34-1 -> -0.30682175 | AP37: =AP34/AN34-1 -> 0.0068027211 | AQ37: =AQ34/AP34-1 -> 0.16171171 | AR37: =AR34/AQ34-1 -> 0.16867003 | AS37: =AS34/AR34-1 -> 0.030192435 | AU37: =AU34/AS34-1 -> -0.0080515298 | AV37: =AV34/AU34-1 -> 0.25519481 | AW37: =AW34/AV34-1 -> 0.22245215 | AX37: =AX34/AW34-1 -> 0.058611934 | AZ37: =AZ34/AX34-1 -> 0.13152109 | BA37: =BA34/AZ34-1 -> 0.14944356 | BB37: =BB34/BA34-1 -> 0.091593668 | BC37: =BC34/BB34-1 -> 0.076024215 | BE37: =BE34/BC34-1 -> 0.084390946 | BF37: =BF34/BE34-1 -> -0.19111969 | BG37: =BG34/BF34-1 -> -0.1153043 | BH37: =BH34/BG34-1 -> 0.020232676 | BJ37: =BJ34/BH34-1 -> 0.18856387 | BK37: =BK34/BJ34-1 -> 0.87805895 | BL37: =BL34/BK34-1 -> 0.34152662 | BM37: =BM34/BL34-1 -> 0.21981236 | BO37: =BO34/BM34-1 -> 0.17830159 | BP37: =BP34/BO34-1 -> 0.15343265 | BQ37: =BQ34/BP34-1 -> 0.16784288 | BR37: =BR34/BQ34-1 -> 0.12111624 | BT37: =BT34/BR34-1 -> 0.1202868 | BU37: =BU34/BT34-1 -> 0.060846081 | BV37: =BV34/BU34-1 -> 0.21956229 | BW37: =BW34/BV34-1 -> 0.19508473 | BY37: =BY34/BW34-1 -> 0.19798318 | BZ37: =BZ34/BY34-1 -> 0.11417619 | CA37: =CA34/BZ34-1 -> 0.0066236323 | CB37: =CB34/CA34-1 -> 0.026930993 | CD37: =CD34/CB34-1 -> 0.12257961 | CE37: =CE34/CD34-1 -> 0.11509459 | CF37: =CF34/CE34-1 -> -0.029513527 | CG37: =CG34/CF34-1 -> 0.024006396
A38: Y/Y Total Revenue Growth, % | D38: =D34/C34-1 -> -0.028735198 | E38: =E34/D34-1 -> 0.065193923 | F38: =F34/E34-1 -> 0.12830408 | K38: =K34/F34-1 -> 0.070593782 | L38: =L34/G34-1 -> 0.032287537 | M38: =M34/H34-1 -> -0.064190296 | N38: =N34/I34-1 -> -0.1246921 | O38: =O34/J34-1 -> 0.033712108 | P38: =P34/K34-1 -> -0.035082575 | Q38: =Q34/L34-1 -> 0.15528956 | R38: =R34/M34-1 -> 0.12869127 | ... CH38: =CH34/CC34-1 -> 0.26876372 | CI38: =CI34/CH34-1 -> 0.19277198 | CJ38: =CJ34/CI34-1 -> 0.17466733 | CK38: =CK34/CJ34-1 -> 0.1750063
A40: Product0075 Revenue, mm | BR40: 11000
A41: CMP Revenue, mm | AF41: 289 | AK41: 0 | AY41: 0 | AZ41: 155 | BA41: 266 | BB41: 105 | BC41: =BD41-SUM(AZ41,BA41,BB41) -> 24 | BD41: 550 | BE41: 0 | BF41: 0 | BG41: 0 | BH41: =BI41-SUM(BE41,BF41,BG41) -> 0 | BI41: 0 | BM41: =BN41-SUM(BJ41,BK41,BL41) -> 0 | BR41: =BS41-SUM(BO41,BP41,BQ41) -> 0
A43: Operating Expense Forecasting
A44: Revenue, mm | C44: =C300 -> 3424.859 | D44: =D300 -> 3326.445 | E44: =E300 -> 3543.309 | F44: =F300 -> 3997.93 | G44: =G300 -> 924.877 | H44: =H300 -> 1044.27 | I44: =I300 -> 1204.11 | J44: =J300 -> 1106.902 | ... O44: =O300 -> 1144.218 | P44: =P34 -> 4130 | Q44: =Q34 -> 1103 | R44: =R34 -> 1103 | S44: =S34 -> 1225 | T44: =T34 -> 1251 | U44: =U34 -> 4682 | V44: =V34 -> 1151 | W44: =W34 -> 1153 | ... CK44: =CK34 -> 747962.27
A45: Cost of revenue, mm | C45: =C301 -> 2250.59 | D45: =D301 -> 2149.522 | E45: =E301 -> 2134.219 | F45: =F301 -> 1941.413 | G45: =G301 -> 461.513 | H45: =H301 -> 503.551 | I45: =I301 -> 567.452 | J45: =J301 -> 521.3 | ... BY45: =BY301 -> 20458 | BZ45: =BZ44-BZ46 -> 22867.418 | CA45: =CA44-CA46 -> 23324.634 | CB45: =CB44-CB46 -> 22497.278 | CC45: =CC44-CC46 -> 89147.33 | CD45: =CD44-CD46 -> 26459.582 | CE45: =CE44-CE46 -> 29590.641 | CF45: =CF44-CF46 -> 29098.757 | CG45: =CG44-CG46 -> 27986.654 | ... CK45: =CK44-CK46 -> 187004.68
A46: GAAP Gross Profit, mm | C46: =C44-C45 -> 1174.269 | D46: =D44-D45 -> 1176.923 | E46: =E44-E45 -> 1409.09 | F46: =F44-F45 -> 2056.517 | G46: =G44-G45 -> 463.364 | H46: =H44-H45 -> 540.719 | I46: =I44-I45 -> 636.658 | J46: =J44-J45 -> 585.602 | ... BY46: =BY44-BY45 -> 61157 | BZ46: =BZ57-BZ55-BZ53-BZ51 -> 68066.072 | CA46: =CA57-CA55-CA53-CA51 -> 68211.166 | CB46: =CB57-CB55-CB53-CB51 -> 71503.672 | CC46: =SUM(BY46,BZ46,CA46,CB46) -> 268937.91 | CD46: =CD57-CD55-CD53-CD51 -> 79063.968 | CE46: =CE57-CE55-CE53-CE51 -> 88078.099 | CF46: =CF57-CF55-CF53-CF51 -> 85097.163 | CG46: =CG57-CG55-CG53-CG51 -> 88950.698 | CH46: =SUM(CD46,CE46,CF46,CG46) -> 341189.93 | CI46: =CI57-CI55-CI53-CI51 -> 406419.88 | CJ46: =CJ57-CJ55-CJ53-CJ51 -> 477408.15 | CK46: =CK57-CK55-CK53-CK51 -> 560957.59
A47: Y/Y growth in Gross Profit, % | D47: =D46/C46-1 -> 0.0022601295 | E47: =E46/D46-1 -> 0.19726609 | F47: =F46/E46-1 -> 0.45946462 | K47: =K46/F46-1 -> 0.082579429 | L47: =L46/G46-1 -> 0.11913744 | M47: =M46/H46-1 -> 0.0089122076 | N47: =N46/I46-1 -> -0.082058185 | O47: =O46/J46-1 -> 0.057445159 | P47: =P46/K46-1 -> 0.018531736 | Q47: =Q46/L46-1 -> 0.16474599 | R47: =R46/M46-1 -> 0.13465973 | ... CH47: =CH46/CC46-1 -> 0.26865687 | CI47: =CI46/CH46-1 -> 0.1911837 | CJ47: =CJ46/CI46-1 -> 0.17466733 | CK47: =CK46/CJ46-1 -> 0.1750063
A48: GAAP Gross Margin, % | C48: =C46/C44 -> 0.34286638 | D48: =D46/D44 -> 0.35380804 | E48: =E46/E44 -> 0.3976763 | F48: =F46/F44 -> 0.51439545 | G48: =G46/G44 -> 0.50100067 | H48: =H46/H44 -> 0.51779616 | I48: =I46/I44 -> 0.52873741 | J48: =J46/J44 -> 0.52904593 | ... CK48: =CK46/CK44 -> 0.74998114
A49: Y/Y improvement in GAAP Gross Margin, bps | D49: =(D48-C48)*10000 -> 109.41666 | E49: =(E48-D48)*10000 -> 438.68252 | F49: =(F48-E48)*10000 -> 1167.1915 | K49: =(K48-F48)*10000 -> 57.58825 | L49: =(L48-G48)*10000 -> 421.5091 | M49: =(M48-H48)*10000 -> 404.48604 | N49: =(N48-I48)*10000 -> 257.53388 | O49: =(O48-J48)*10000 -> 121.46393 | P49: =(P48-K48)*10000 -> 289.01658 | Q49: =(Q48-L48)*10000 -> 44.458776 | R49: =(R48-M48)*10000 -> 29.519688 | ... CH49: =(CH48-CC48)*10000 -> -0.63252585 | CI49: =(CI48-CH48)*10000 -> -10 | CJ49: =(CJ48-CI48)*10000 -> 0 | CK49: =(CK48-CJ48)*10000 -> 0
A51: SBC COGS, mm | C51: =-C375 -> 11.939 | D51: =-D375 -> 12.05 | E51: =-E375 -> 8.308 | F51: =-F375 -> 11.322 | G51: =-G375 -> 2.526 | H51: =-H375 -> 2.649 | I51: =-I375 -> 2.489 | J51: =-J375 -> 2.826 | ... BY51: =-BY375 -> 0 | BZ51: =BZ44*BZ52 -> 0 | CA51: =CA44*CA52 -> 0 | CB51: =CB44*CB52 -> 0 | CC51: =SUM(BY51,BZ51,CA51,CB51) -> 0 | CD51: =CD44*CD52 -> 0 | CE51: =CE44*CE52 -> 0 | CF51: =CF44*CF52 -> 0 | CG51: =CG44*CG52 -> 0 | CH51: =SUM(CD51,CE51,CF51,CG51) -> 0 | CI51: =CI44*CI52 -> 0 | CJ51: =CJ44*CJ52 -> 0 | CK51: =CK44*CK52 -> 0
A52: SBC COGS as % of revenue, % | C52: =C51/C44 -> 0.0034859829 | D52: =D51/D44 -> 0.0036224859 | E52: =E51/E44 -> 0.002344701 | F52: =F51/F44 -> 0.0028319655 | G52: =G51/G44 -> 0.002731174 | H52: =H51/H44 -> 0.0025367003 | I52: =I51/I44 -> 0.0020670869 | J52: =J51/J44 -> 0.0025530715 | ... BY52: =BY51/BY44 -> 0 | BZ52: 0 | CA52: 0 | CB52: 0 | CC52: =CC51/CC44 -> 0 | CD52: 0 | CE52: 0 | CF52: 0 | CG52: 0 | CH52: =CH51/CH44 -> 0 | CI52: 0 | CJ52: 0 | CK52: 0
A53: Acquisition-related costs COGS, mm | C53: =-C376 -> 0 | D53: =-D376 -> 0 | E53: =-E376 -> 0 | F53: =-F376 -> 0 | G53: =-G376 -> 0 | H53: =-H376 -> 0 | I53: =-I376 -> 0 | J53: =-J376 -> 0 | ... BY53: =-BY376 -> 47 | BZ53: =BZ44*BZ54 -> 90.93349 | CA53: =CA44*CA54 -> 91.5358 | CB53: =CB44*CB54 -> 94.00095 | CC53: =SUM(BY53,BZ53,CA53,CB53) -> 323.47024 | CD53: =CD44*CD54 -> 105.52355 | CE53: =CE44*CE54 -> 117.66874 | CF53: =CF44*CF54 -> 114.19592 | CG53: =CG44*CG54 -> 116.93735 | CH53: =SUM(CD53,CE53,CF53,CG53) -> 454.32556 | CI53: =CI44*CI54 -> 1083.8136 | CJ53: =CJ44*CJ54 -> 1273.1204 | CK53: =CK44*CK54 -> 1495.9245
A54: Acquisition-related costs COGS as % of revenue, % | C54: =C53/C44 -> 0 | D54: =D53/D44 -> 0 | E54: =E53/E44 -> 0 | F54: =F53/F44 -> 0 | G54: =G53/G44 -> 0 | H54: =H53/H44 -> 0 | I54: =I53/I44 -> 0 | J54: =J53/J44 -> 0 | ... BY54: =BY53/BY44 -> 0.00057587453 | BZ54: 0.001 | CA54: 0.001 | CB54: 0.001 | CC54: =CC53/CC44 -> 0.00090333307 | CD54: 0.001 | CE54: 0.001 | CF54: 0.001 | CG54: 0.001 | CH54: =CH53/CH44 -> 0.001 | CI54: 0.002 | CJ54: 0.002 | CK54: 0.002
A55: Other COGS Adjustments, mm | C55: =-C377 -> 181.85 | D55: =-D377 -> 95.24 | E55: =-E377 -> 181.193 | F55: =-F377 -> 7.3 | G55: =-G377 -> 0 | H55: =-H377 -> 0 | I55: =-I377 -> 0 | J55: =-J377 -> 0 | ... BY55: =-BY377 -> 28 | BZ55: 0 | CA55: 0 | CB55: 0 | CC55: =SUM(BY55,BZ55,CA55,CB55) -> 28 | CD55: 0 | CE55: 0 | CF55: 0 | CG55: 0 | CH55: =SUM(CD55,CE55,CF55,CG55) -> 0 | CI55: 0 | CJ55: 0 | CK55: 0
A56: Non-GAAP COGS, mm | C56: =C45-C51-C53-C55 -> 2056.801 | D56: =D45-D51-D53-D55 -> 2042.232 | E56: =E45-E51-E53-E55 -> 1944.718 | F56: =F45-F51-F53-F55 -> 1922.791 | G56: =G45-G51-G53-G55 -> 458.987 | H56: =H45-H51-H53-H55 -> 500.902 | I56: =I45-I51-I53-I55 -> 564.963 | J56: =J45-J51-J53-J55 -> 518.474 | ... BY56: =BY45-BY51-BY53-BY55 -> 20383 | BZ56: =BZ44-BZ57 -> 22776.484 | CA56: =CA44-CA57 -> 23233.098 | CB56: =CB44-CB57 -> 22403.277 | CC56: =SUM(BY56,BZ56,CA56,CB56) -> 88795.859 | CD56: =CD44-CD57 -> 26354.059 | CE56: =CE44-CE57 -> 29472.972 | CF56: =CF44-CF57 -> 28984.562 | CG56: =CG44-CG57 -> 27869.717 | CH56: =SUM(CD56,CE56,CF56,CG56) -> 112681.31 | CI56: =CI44-CI57 -> 134403.11 | CJ56: =CJ44-CJ57 -> 157878.94 | CK56: =CK44-CK57 -> 185508.75
A57: Non-GAAP Gross Profit, mm | C57: =C44-C56 -> 1368.058 | D57: =D44-D56 -> 1284.213 | E57: =E44-E56 -> 1598.591 | F57: =F44-F56 -> 2075.139 | G57: =G44-G56 -> 465.89 | H57: =H44-H56 -> 543.368 | I57: =I44-I56 -> 639.147 | J57: =J44-J56 -> 588.428 | ... BY57: =BY44-BY56 -> 61232 | BZ57: =BZ44*BZ59 -> 68157.006 | CA57: =CA44*CA59 -> 68302.702 | CB57: =CB44*CB59 -> 71597.673 | CC57: =SUM(BY57,BZ57,CA57,CB57) -> 269289.38 | CD57: =CD44*CD59 -> 79169.491 | CE57: =CE44*CE59 -> 88195.768 | CF57: =CF44*CF59 -> 85211.358 | CG57: =CG44*CG59 -> 89067.635 | CH57: =SUM(CD57,CE57,CF57,CG57) -> 341644.25 | CI57: =CI44*CI59 -> 407503.69 | CJ57: =CJ44*CJ59 -> 478681.28 | CK57: =CK44*CK59 -> 562453.52
A58: Y/Y Non-GAAP gross profit growth, % | D58: =D57/C57-1 -> -0.061287606 | E58: =E57/D57-1 -> 0.24480207 | F58: =F57/E57-1 -> 0.29810502 | K58: =K57/F57-1 -> 0.0779196 | L58: =L57/G57-1 -> 0.11876409 | M58: =M57/H57-1 -> 0.012197995 | N58: =N57/I57-1 -> -0.080798314 | O58: =O57/J57-1 -> 0.046325124 | P58: =P57/K57-1 -> 0.016726327 | Q58: =Q57/L57-1 -> 0.16457318 | R58: =R57/M57-1 -> 0.13091732 | ... CH58: =CH57/CC57-1 -> 0.26868817 | CI58: =CI57/CH57-1 -> 0.19277198 | CJ58: =CJ57/CI57-1 -> 0.17466733 | CK58: =CK57/CJ57-1 -> 0.1750063
A59: Non-GAAP Gross Margin, % | C59: =C57/C44 -> 0.39944944 | D59: =D57/D44 -> 0.3860617 | E59: =E57/E44 -> 0.45115766 | F59: =F57/F44 -> 0.51905336 | G59: =G57/G44 -> 0.50373185 | H59: =H57/H44 -> 0.52033286 | I59: =I57/I44 -> 0.53080449 | J59: =J57/J44 -> 0.531599 | ... BY59: =BY57/BY44 -> 0.75025424 | BZ59: =BU59+BZ62/10000 -> 0.7495259 | CA59: =BV59+CA62/10000 -> 0.74618566 | CB59: =BW59+CB62/10000 -> 0.76166968 | CC59: =CC57/CC44 -> 0.75202592 | CD59: =BY59+CD62/10000 -> 0.75025424 | CE59: =BZ59+CE62/10000 -> 0.7495259 | CF59: =CA59+CF62/10000 -> 0.74618566 | CG59: =CB59+CG62/10000 -> 0.76166968 | CH59: =CH57/CH44 -> 0.75198114 | CI59: =CH59+CI62/10000 -> 0.75198114 | CJ59: =CI59+CJ62/10000 -> 0.75198114 | CK59: =CJ59+CK62/10000 -> 0.75198114
A60: Consensus Estimates - Non-GAAP Gross Margin, % | BZ60: =BZ287 -> N/A | CA60: =CA287 -> N/A | CB60: =CB287 -> N/A | CC60: =CC287 -> N/A | CD60: =CD287 -> N/A | CE60: =CE287 -> N/A | CF60: =CF287 -> N/A | CG60: =CG287 -> N/A | ... CK60: =CK287 -> N/A
A61: Guidance - Non-GAAP Gross Margin, % | BZ61: =BZ650 -> 0.75 | CA61: =CA650 | CB61: =CB650 | CC61: =CC650 | CD61: =CD650 | CE61: =CE650 | CF61: =CF650 | CG61: =CG650 | ... CK61: =CK650 -> 0
A62: Y/Y Improvement in non-GAAP gross margin, bps | D62: =(D59-C59)*10000 -> -133.87741 | E62: =(E59-D59)*10000 -> 650.95964 | F62: =(F59-E59)*10000 -> 678.95699 | K62: =(K59-F59)*10000 -> 35.517581 | L62: =(L59-G59)*10000 -> 421.98506 | M62: =(M59-H59)*10000 -> 424.7374 | N62: =(N59-I59)*10000 -> 266.18081 | O62: =(O59-J59)*10000 -> 64.863965 | P62: =(P59-K59)*10000 -> 280.60015 | Q62: =(Q59-L59)*10000 -> 43.869627 | R62: =(R59-M59)*10000 -> 11.099872 | ... BY62: =(BY59-BT59)*10000 -> 1407.0406 | BZ62: 230 | CA62: 100 | CB62: 100 | CC62: =(CC59-BX59)*10000 -> 388.86033 | CD62: 0 | CE62: 0 | CF62: 0 | CG62: 0 | CH62: =(CH59-CC59)*10000 -> -0.4477933 | CI62: 0 | CJ62: 0 | CK62: 0
A64: GAAP R&D Expense, mm | C64: =C381 -> 855.879 | D64: =D381 -> 908.851 | E64: =E381 -> 848.83 | F64: =F381 -> 1002.605 | G64: =G381 -> 283.902 | H64: =H381 -> 281.193 | I64: =I381 -> 284.18 | J64: =J381 -> 298.007 | ... BY64: =BY381 -> 6321 | BZ64: =BZ74+BZ71+BZ69+BZ73 -> 6610.8353 | CA64: =CA74+CA71+CA69+CA73 -> 5653.7575 | CB64: =CB74+CB71+CB69+CB73 -> 5905.6762 | CC64: =SUM(BY64,BZ64,CA64,CB64) -> 24491.269 | CD64: =CD74+CD71+CD69+CD73 -> 8062.2953 | CE64: =CE74+CE71+CE69+CE73 -> 8436.8106 | CF64: =CF74+CF71+CF69+CF73 -> 7053.3719 | CG64: =CG74+CG71+CG69+CG73 -> 7346.6719 | CH64: =SUM(CD64,CE64,CF64,CG64) -> 30899.15 | CI64: =CI74+CI71+CI69+CI73 -> 36855.64 | CJ64: =CJ74+CJ71+CJ69+CJ73 -> 43293.117 | CK64: =CK74+CK71+CK69+CK73 -> 50869.685
A65: Y/Y growth in GAAP R&D, % | D65: =D64/C64-1 -> 0.061891926 | E65: =E64/D64-1 -> -0.066040528 | F65: =F64/E64-1 -> 0.18116113 | K65: =K64/F64-1 -> 0.1443011 | L65: =L64/G64-1 -> 0.152373 | M65: =M64/H64-1 -> 0.17975199 | N65: =N64/I64-1 -> 0.19745936 | O65: =O64/J64-1 -> 0.12964125 | P65: =P64/K64-1 -> 0.16434669 | Q65: =Q64/L64-1 -> 0.020904081 | R65: =R64/M64-1 -> 0.015861915 | ... CH65: =CH64/CC64-1 -> 0.26163939 | CI65: =CI64/CH64-1 -> 0.19277198 | CJ65: =CJ64/CI64-1 -> 0.17466733 | CK65: =CK64/CJ64-1 -> 0.1750063
A66: GAAP R&D Margin, % | C66: =C64/C44 -> 0.24990197 | D66: =D64/D44 -> 0.27321991 | E66: =E64/E44 -> 0.23955856 | F66: =F64/F44 -> 0.25078103 | G66: =G64/G44 -> 0.3069619 | H66: =H64/H44 -> 0.26927231 | I66: =I64/I44 -> 0.23600834 | J66: =J64/J44 -> 0.26922618 | ... CK66: =CK64/CK44 -> 0.068011031
A67: Y/Y Improvement in GAAP R&D Margin, bps | D67: =-(D66-C66)*10000 -> -233.17942 | E67: =-(E66-D66)*10000 -> 336.61349 | F67: =-(F66-E66)*10000 -> -112.2247 | K67: =-(K66-F66)*10000 -> -172.65555 | L67: =-(L66-G66)*10000 -> -357.08716 | M67: =-(M66-H66)*10000 -> -701.92585 | N67: =-(N66-I66)*10000 -> -868.61353 | O67: =-(O66-J66)*10000 -> -249.84361 | P67: =-(P66-K66)*10000 -> -553.99905 | Q67: =-(Q66-L66)*10000 -> 398.60098 | R67: =-(R66-M66)*10000 -> 339.34528 | ... CH67: =-(CH66-CC66)*10000 -> 3.8405049 | CI67: =-(CI66-CH66)*10000 -> 1.3877788e-13 | CJ67: =-(CJ66-CI66)*10000 -> -1.3877788e-13 | CK67: =-(CK66-CJ66)*10000 -> 0
A69: SBC R&D, mm | C69: =C382 -> 98.007 | D69: =D382 -> 61.337 | E69: =E382 -> 57.974 | F69: =F382 -> 80.502 | G69: =G382 -> 21.207 | H69: =H382 -> 18.885 | I69: =I382 -> 20.056 | J69: =J382 -> 22.009 | ... BY69: =BY382 -> 0 | BZ69: =BZ44*BZ70 -> 0 | CA69: =CA44*CA70 -> 0 | CB69: =CB44*CB70 -> 0 | CC69: =SUM(BY69,BZ69,CA69,CB69) -> 0 | CD69: =CD44*CD70 -> 0 | CE69: =CE44*CE70 -> 0 | CF69: =CF44*CF70 -> 0 | CG69: =CG44*CG70 -> 0 | CH69: =SUM(CD69,CE69,CF69,CG69) -> 0 | CI69: =CI44*CI70 -> 0 | CJ69: =CJ44*CJ70 -> 0 | CK69: =CK44*CK70 -> 0
A70: SBC R&D as % of revenue, % | C70: =C69/C44 -> 0.028616361 | D70: =D69/D44 -> 0.018439205 | E70: =E69/E44 -> 0.016361542 | F70: =F69/F44 -> 0.02013592 | G70: =G69/G44 -> 0.022929535 | H70: =H69/H44 -> 0.018084403 | I70: =I69/I44 -> 0.016656286 | J70: =J69/J44 -> 0.019883422 | ... BY70: =BY69/BY44 -> 0 | BZ70: 0 | CA70: 0 | CB70: 0 | CC70: =CC69/CC44 -> 0 | CD70: 0 | CE70: 0 | CF70: 0 | CG70: 0 | CH70: =CH69/CH44 -> 0 | CI70: 0 | CJ70: 0 | CK70: 0
A71: Acquisition-related costs R&D, mm | C71: =C383 -> 0 | D71: =D383 -> 0 | E71: =E383 -> 0 | F71: =F383 -> 10.282 | G71: =G383 -> 3.171 | H71: =H383 -> 2.794 | I71: =I383 -> 2.666 | J71: =J383 -> 3.698 | ... BY71: =BY383 -> 167 | BZ71: =BZ44*BZ72 -> 181.86698 | CA71: =CA44*CA72 -> 91.5358 | CB71: =CB44*CB72 -> 94.00095 | CC71: =SUM(BY71,BZ71,CA71,CB71) -> 534.40373 | CD71: =CD44*CD72 -> 105.52355 | CE71: =CE44*CE72 -> 117.66874 | CF71: =CF44*CF72 -> 114.19592 | CG71: =CG44*CG72 -> 116.93735 | CH71: =SUM(CD71,CE71,CF71,CG71) -> 454.32556 | CI71: =CI44*CI72 -> 541.9068 | CJ71: =CJ44*CJ72 -> 636.56022 | CK71: =CK44*CK72 -> 747.96227
A72: Acquisition-related costs R&D as % of revenue, % | C72: =C71/C44 -> 0 | D72: =D71/D44 -> 0 | E72: =E71/E44 -> 0 | F72: =F71/F44 -> 0.0025718309 | G72: =G71/G44 -> 0.003428564 | H72: =H71/H44 -> 0.0026755533 | I72: =I71/I44 -> 0.0022140834 | J72: =J71/J44 -> 0.0033408558 | ... BY72: =BY71/BY44 -> 0.0020461925 | BZ72: 0.002 | CA72: 0.001 | CB72: 0.001 | CC72: =CC71/CC44 -> 0.0014923925 | CD72: 0.001 | CE72: 0.001 | CF72: 0.001 | CG72: 0.001 | CH72: =CH71/CH44 -> 0.001 | CI72: 0.001 | CJ72: 0.001 | CK72: 0.001
A73: Other R&D, mm | C73: =C384 -> 0 | D73: =D384 -> 0 | E73: =E384 -> 0 | F73: =F384 -> 0 | G73: =G384 -> 0 | H73: =H384 -> 0 | I73: =I384 -> 0 | J73: =J384 -> 0 | ... BY73: =BY384 -> 0 | BZ73: 0 | CA73: 0 | CB73: 0 | CC73: =SUM(BY73,BZ73,CA73,CB73) -> 0 | CD73: 0 | CE73: 0 | CF73: 0 | CG73: 0 | CH73: =SUM(CD73,CE73,CF73,CG73) -> 0 | CI73: 0 | CJ73: 0 | CK73: 0
A74: Non-GAAP R&D Expense, mm | C74: =C64-C69-C71-C73 -> 757.872 | D74: =D64-D69-D71-D73 -> 847.514 | E74: =E64-E69-E71-E73 -> 790.856 | F74: =F64-F69-F71-F73 -> 911.821 | G74: =G64-G69-G71-G73 -> 259.524 | H74: =H64-H69-H71-H73 -> 259.514 | I74: =I64-I69-I71-I73 -> 261.458 | J74: =J64-J69-J71-J73 -> 272.3 | ... BY74: =BY64-BY69-BY71-BY73 -> 6154 | BZ74: =BZ44*BZ76 -> 6428.9684 | CA74: =CA44*CA76 -> 5562.2217 | CB74: =CB44*CB76 -> 5811.6753 | CC74: =SUM(BY74,BZ74,CA74,CB74) -> 23956.865 | CD74: =CD44*CD76 -> 7956.7718 | CE74: =CE44*CE76 -> 8319.1419 | CF74: =CF44*CF76 -> 6939.176 | CG74: =CG44*CG76 -> 7229.7346 | CH74: =SUM(CD74,CE74,CF74,CG74) -> 30444.824 | CI74: =CI44*CI76 -> 36313.733 | CJ74: =CJ44*CJ76 -> 42656.556 | CK74: =CK44*CK76 -> 50121.722
A75: Y/Y Growth in non-GAAP R&D Expense, % | D75: =D74/C74-1 -> 0.11828119 | E75: =E74/D74-1 -> -0.066851993 | F75: =F74/E74-1 -> 0.15295452 | K75: =K74/F74-1 -> 0.14056048 | L75: =L74/G74-1 -> 0.16122208 | M75: =M74/H74-1 -> 0.19153109 | N75: =N74/I74-1 -> 0.21554896 | O75: =O74/J74-1 -> 0.14154609 | P75: =P74/K74-1 -> 0.19159374 | Q75: =Q74/L74-1 -> 0.025480729 | R75: =R74/M74-1 -> 0.0089936259 | ... CH75: =CH74/CC74-1 -> 0.27081835 | CI75: =CI74/CH74-1 -> 0.19277198 | CJ75: =CJ74/CI74-1 -> 0.17466733 | CK75: =CK74/CJ74-1 -> 0.1750063
A76: Non-GAAP R&D Margin, % | C76: =C74/C44 -> 0.22128561 | D76: =D74/D44 -> 0.2547807 | E76: =E74/E44 -> 0.22319702 | F76: =F74/F44 -> 0.22807328 | G76: =G74/G44 -> 0.2806038 | H76: =H74/H44 -> 0.24851236 | I76: =I74/I44 -> 0.21713797 | J76: =J74/J44 -> 0.2460019 | ... BY76: =BY74/BY44 -> 0.075402806 | BZ76: =BU76-BZ77/10000 -> 0.070699677 | CA76: =BV76-CA77/10000 -> 0.060765533 | CB76: =BW76-CB77/10000 -> 0.061825708 | CC76: =CC74/CC44 -> 0.066902689 | CD76: =BY76-CD77/10000 -> 0.075402806 | CE76: =BZ76-CE77/10000 -> 0.070699677 | CF76: =CA76-CF77/10000 -> 0.060765533 | CG76: =CB76-CG77/10000 -> 0.061825708 | CH76: =CH74/CH44 -> 0.067011031 | CI76: =CH76-CI77/10000 -> 0.067011031 | CJ76: =CI76-CJ77/10000 -> 0.067011031 | CK76: =CJ76-CK77/10000 -> 0.067011031
A77: Y/Y Improvement in Non-GAAP R&D Margin, bps | D77: =-(D76-C76)*10000 -> -334.95098 | E77: =-(E76-D76)*10000 -> 315.83687 | F77: =-(F76-E76)*10000 -> -48.762607 | K77: =-(K76-F76)*10000 -> -149.05312 | L77: =-(L76-G76)*10000 -> -350.47913 | M77: =-(M76-H76)*10000 -> -679.09026 | N77: =-(N76-I76)*10000 -> -844.0373 | O77: =-(O76-J76)*10000 -> -256.62237 | P77: =-(P76-K76)*10000 -> -570.80005 | Q77: =-(Q76-L76)*10000 -> 354.66762 | R77: =-(R76-M76)*10000 -> 335.5647 | ... BY77: =-(BY76-BT76)*10000 -> -96.318468 | BZ77: -50 | CA77: 0 | CB77: 0 | CC77: =-(CC76-BX76)*10000 -> -37.132547 | CD77: 0 | CE77: 0 | CF77: 0 | CG77: 0 | CH77: =-(CH76-CC76)*10000 -> -1.0834202 | CI77: 0 | CJ77: 0 | CK77: 0
A79: GAAP SG&A Expense, mm | C79: =C386 -> 362.222 | D79: =D386 -> 367.017 | E79: =E386 -> 361.513 | F79: =F386 -> 405.613 | G79: =G386 -> 106.636 | H79: =H386 -> 119.903 | I79: =I386 -> 100.261 | J79: =J386 -> 104.022 | ... BY79: =BY386 -> 1300 | BZ79: =BZ89+BZ86+BZ84+BZ88 -> 1910.4993 | CA79: =CA89+CA86+CA84+CA88 -> 1224.2045 | CB79: =CB89+CB86+CB84+CB88 -> 1299.2453 | CC79: =SUM(BY79,BZ79,CA79,CB79) -> 5733.9491 | CD79: =CD89+CD86+CD84+CD88 -> 1695.466 | CE79: =CE89+CE86+CE84+CE88 -> 2472.203 | CF79: =CF89+CF86+CF84+CF88 -> 1527.2622 | CG79: =CG89+CG86+CG84+CG88 -> 1616.2635 | CH79: =SUM(CD79,CE79,CF79,CG79) -> 7311.1947 | CI79: =CI89+CI86+CI84+CI88 -> 8449.6347 | CJ79: =CJ89+CJ86+CJ84+CJ88 -> 9607.2298 | CK79: =CK89+CK86+CK84+CK88 -> 10914.574
A80: Y/Y growth in GAAP SG&A, % | D80: =D79/C79-1 -> 0.013237738 | E80: =E79/D79-1 -> -0.014996581 | F80: =F79/E79-1 -> 0.12198731 | K80: =K79/F79-1 -> 0.062150375 | L80: =L79/G79-1 -> 0.018661615 | M80: =M79/H79-1 -> -0.097053452 | N80: =N79/I79-1 -> 0.028645236 | O80: =O79/J79-1 -> 0.11204361 | P80: =P79/K79-1 -> 0.011327184 | Q80: =Q79/L79-1 -> 0.095501998 | R80: =R79/M79-1 -> 0.099144699 | ... CH80: =CH79/CC79-1 -> 0.27507142 | CI80: =CI79/CH79-1 -> 0.15571191 | CJ80: =CJ79/CI79-1 -> 0.13699942 | CK80: =CK79/CJ79-1 -> 0.13607925
A81: GAAP SG&A Margin, % | C81: =C79/C44 -> 0.1057626 | D81: =D79/D44 -> 0.1103331 | E81: =E79/E44 -> 0.10202695 | F81: =F79/F44 -> 0.10145575 | G81: =G79/G44 -> 0.11529749 | H81: =H79/H44 -> 0.11481992 | I81: =I79/I44 -> 0.083265648 | J81: =J79/J44 -> 0.093975799 | ... CK81: =CK79/CK44 -> 0.014592413
A82: Y/Y Improvement in GAAP SG&A Margin, bps | D82: =-(D81-C81)*10000 -> -45.705012 | E82: =-(E81-D81)*10000 -> 83.061562 | F82: =-(F81-E81)*10000 -> 5.7119378 | K82: =-(K81-F81)*10000 -> 8.0014687 | L82: =-(L81-G81)*10000 -> 15.218963 | M82: =-(M81-H81)*10000 -> 40.321713 | N82: =-(N81-I81)*10000 -> -145.86561 | O82: =-(O81-J81)*10000 -> -71.211946 | P82: =-(P81-K81)*10000 -> -48.412458 | Q82: =-(Q81-L81)*10000 -> 58.88018 | R82: =-(R81-M81)*10000 -> 29.001715 | ... CH82: =-(CH81-CC81)*10000 -> -0.79608117 | CI82: =-(CI81-CH81)*10000 -> 5 | CJ82: =-(CJ81-CI81)*10000 -> 5 | CK82: =-(CK81-CJ81)*10000 -> 5
A84: SBC SG&A, mm | C84: =C387 -> 52.76 | D84: =D387 -> 33.704 | E84: =E387 -> 34.071 | F84: =F387 -> 44.53 | G84: =G387 -> 11.836 | H84: =H387 -> 10.721 | I84: =I387 -> 10.524 | J84: =J387 -> 10.934 | ... BY84: =BY387 -> 0 | BZ84: =BZ44*BZ85 -> 0 | CA84: =CA44*CA85 -> 0 | CB84: =CB44*CB85 -> 0 | CC84: =SUM(BY84,BZ84,CA84,CB84) -> 0 | CD84: =CD44*CD85 -> 0 | CE84: =CE44*CE85 -> 0 | CF84: =CF44*CF85 -> 0 | CG84: =CG44*CG85 -> 0 | CH84: =SUM(CD84,CE84,CF84,CG84) -> 0 | CI84: =CI44*CI85 -> 0 | CJ84: =CJ44*CJ85 -> 0 | CK84: =CK44*CK85 -> 0
A85: SBC SG&A as % of revenue, % | C85: =C84/C44 -> 0.015405014 | D85: =D84/D44 -> 0.010132138 | E85: =E84/E44 -> 0.0096155881 | F85: =F84/F44 -> 0.011138264 | G85: =G84/G44 -> 0.012797377 | H85: =H84/H44 -> 0.010266502 | I85: =I84/I44 -> 0.0087400653 | J85: =J84/J44 -> 0.0098780199 | ... BY85: =BY84/BY44 -> 0 | BZ85: 0 | CA85: 0 | CB85: 0 | CC85: =CC84/CC44 -> 0 | CD85: 0 | CE85: 0 | CF85: 0 | CG85: 0 | CH85: =CH84/CH44 -> 0 | CI85: 0 | CJ85: 0 | CK85: 0
A86: Acquisition-related costs SG&A, mm | C86: =C388 -> 0 | D86: =D388 -> 0 | E86: =E388 -> 0 | F86: =F388 -> 10 | G86: =G388 -> 2 | H86: =H388 -> 2 | I86: =I388 -> 2 | J86: =J388 -> 5 | ... BY86: =BY388 -> 5 | BZ86: =BZ44*BZ87 -> 18.186698 | CA86: =CA44*CA87 -> 18.30716 | CB86: =CB44*CB87 -> 18.80019 | CC86: =SUM(BY86,BZ86,CA86,CB86) -> 60.294048 | CD86: =CD44*CD87 -> 21.10471 | CE86: =CE44*CE87 -> 23.533748 | CF86: =CF44*CF87 -> 22.839184 | CG86: =CG44*CG87 -> 23.38747 | CH86: =SUM(CD86,CE86,CF86,CG86) -> 90.865112 | CI86: =CI44*CI87 -> 108.38136 | CJ86: =CJ44*CJ87 -> 127.31204 | CK86: =CK44*CK87 -> 149.59245
A87: Acquisition-related costs SG&A as % of revenue, % | C87: =C86/C44 -> 0 | D87: =D86/D44 -> 0 | E87: =E86/E44 -> 0 | F87: =F86/F44 -> 0.0025012944 | G87: =G86/G44 -> 0.0021624497 | H87: =H86/H44 -> 0.0019152135 | I87: =I86/I44 -> 0.0016609778 | J87: =J86/J44 -> 0.0045171117 | ... BY87: =BY86/BY44 -> 6.1263248e-05 | BZ87: 0.0002 | CA87: 0.0002 | CB87: 0.0002 | CC87: =CC86/CC44 -> 0.00016837904 | CD87: 0.0002 | CE87: 0.0002 | CF87: 0.0002 | CG87: 0.0002 | CH87: =CH86/CH44 -> 0.0002 | CI87: 0.0002 | CJ87: 0.0002 | CK87: 0.0002
A88: Other SG&A, mm | C88: =C389 -> 0 | D88: =D389 -> 0 | E88: =E389 -> 0 | F88: =F389 -> 0 | G88: =G389 -> 0 | H88: =H389 -> 20.127 | I88: =I389 -> 0 | J88: =J389 -> 0 | ... BY88: =BY389 -> 0 | BZ88: 0 | CA88: 0 | CB88: 0 | CC88: =SUM(BY88,BZ88,CA88,CB88) -> 0 | CD88: 0 | CE88: 0 | CF88: 0 | CG88: 0 | CH88: =SUM(CD88,CE88,CF88,CG88) -> 0 | CI88: 0 | CJ88: 0 | CK88: 0
A89: Non-GAAP SG&A Expense, mm | C89: =C79-C84-C86-C88 -> 309.462 | D89: =D79-D84-D86-D88 -> 333.313 | E89: =E79-E84-E86-E88 -> 327.442 | F89: =F79-F84-F86-F88 -> 351.083 | G89: =G79-G84-G86-G88 -> 92.8 | H89: =H79-H84-H86-H88 -> 87.055 | I89: =I79-I84-I86-I88 -> 87.737 | J89: =J79-J84-J86-J88 -> 88.088 | ... BY89: =BY79-BY84-BY86-BY88 -> 1295 | BZ89: =BZ91*BZ44 -> 1892.3126 | CA89: =CA91*CA44 -> 1205.8974 | CB89: =CB91*CB44 -> 1280.4451 | CC89: =SUM(BY89,BZ89,CA89,CB89) -> 5673.6551 | CD89: =CD91*CD44 -> 1674.3613 | CE89: =CE91*CE44 -> 2448.6693 | CF89: =CF91*CF44 -> 1504.423 | CG89: =CG91*CG44 -> 1592.876 | CH89: =SUM(CD89,CE89,CF89,CG89) -> 7220.3295 | CI89: =CI91*CI44 -> 8341.2534 | CJ89: =CJ91*CJ44 -> 9479.9178 | CK89: =CK91*CK44 -> 10764.982
A90: Y/Y Growth in non-GAAP SG&A Expense, % | D90: =D89/C89-1 -> 0.077072468 | E90: =E89/D89-1 -> -0.017614074 | F90: =F89/E89-1 -> 0.072199046 | K90: =K89/F89-1 -> 0.01309377 | L90: =L89/G89-1 -> 0.021734914 | M90: =M89/H89-1 -> 0.052139452 | N90: =N89/I89-1 -> 0.023809795 | O90: =O89/J89-1 -> 0.12158296 | P90: =P89/K89-1 -> 0.054416892 | Q90: =Q89/L89-1 -> 0.071485071 | R90: =R89/M89-1 -> 0.09177457 | ... CH90: =CH89/CC89-1 -> 0.27260636 | CI90: =CI89/CH89-1 -> 0.15524552 | CJ90: =CJ89/CI89-1 -> 0.13650999 | CK90: =CK89/CJ89-1 -> 0.13555647
A91: Non-GAAP SG&A Margin, % | C91: =C89/C44 -> 0.090357588 | D91: =D89/D44 -> 0.10020097 | E91: =E89/E44 -> 0.092411359 | F91: =F89/F44 -> 0.087816195 | G91: =G89/G44 -> 0.10033767 | H91: =H89/H44 -> 0.083364456 | I91: =I89/I44 -> 0.072864605 | J91: =J89/J44 -> 0.079580667 | ... BY91: =BY89/BY44 -> 0.015867181 | BZ91: =BU91-BZ92/10000 -> 0.020809854 | CA91: =BV91-CA92/10000 -> 0.013174052 | CB91: =BW91-CB92/10000 -> 0.013621618 | CC91: =CC89/CC44 -> 0.015844426 | CD91: =BY91-CD92/10000 -> 0.015867181 | CE91: =BZ91-CE92/10000 -> 0.020809854 | CF91: =CA91-CF92/10000 -> 0.013174052 | CG91: =CB91-CG92/10000 -> 0.013621618 | CH91: =CH89/CH44 -> 0.015892413 | CI91: =CH91-CI92/10000 -> 0.015392413 | CJ91: =CI91-CJ92/10000 -> 0.014892413 | CK91: =CJ91-CK92/10000 -> 0.014392413
A92: Y/Y Improvement in Non-GAAP SG&A Margin, bps | D92: =-(D91-C91)*10000 -> -98.433769 | E92: =-(E91-D91)*10000 -> 77.896063 | F92: =-(F91-E91)*10000 -> 45.951641 | K92: =-(K91-F91)*10000 -> 47.164783 | L92: =-(L91-G91)*10000 -> 10.25708 | M92: =-(M91-H91)*10000 -> -103.62968 | N92: =-(N91-I91)*10000 -> -123.61972 | O92: =-(O91-J91)*10000 -> -67.647667 | P92: =-(P91-K91)*10000 -> -77.077894 | Q92: =-(Q91-L91)*10000 -> 72.04071 | R92: =-(R91-M91)*10000 -> 30.655922 | ... BY92: =-(BY91-BT91)*10000 -> -3.2090558 | BZ92: -50 | CA92: 0 | CB92: 0 | CC92: =-(CC91-BX91)*10000 -> -14.791915 | CD92: 0 | CE92: 0 | CF92: 0 | CG92: 0 | CH92: =-(CH91-CC91)*10000 -> -0.47987154 | CI92: 5 | CJ92: 5 | CK92: 5
A94: GAAP OPEX Expense, mm | C94: =SUM(C305:C307) -> 26.868 | D94: =SUM(D305:D307) -> 0 | E94: =SUM(E305:E307) -> -57 | F94: =SUM(F305:F307) -> 0 | G94: =SUM(G305:G307) -> 0 | H94: =SUM(H305:H307) -> 0 | I94: =SUM(I305:I307) -> 0 | J94: =SUM(J305:J307) -> 0 | ... BY94: =SUM(BY305:BY307) -> 0 | BZ94: =BZ100+BZ99 -> 0 | CA94: =CA100+CA99 -> 0 | CB94: =CB100+CB99 -> 0 | CC94: =SUM(BY94,BZ94,CA94,CB94) -> 0 | CD94: =CD100+CD99 -> 0 | CE94: =CE100+CE99 -> 0 | CF94: =CF100+CF99 -> 0 | CG94: =CG100+CG99 -> 0 | CH94: =SUM(CD94,CE94,CF94,CG94) -> 0 | CI94: =CI100+CI99 -> 0 | CJ94: =CJ100+CJ99 -> 0 | CK94: =CK100+CK99 -> 0
A95: Y/Y growth in GAAP OPEX, % | D95: =IFERROR(D94/C94-1,"N/A") -> -1 | E95: =IFERROR(E94/D94-1,"N/A") -> N/A | F95: =IFERROR(F94/E94-1,"N/A") -> -1 | K95: =IFERROR(K94/F94-1,"N/A") -> N/A | L95: =IFERROR(L94/G94-1,"N/A") -> N/A | M95: =IFERROR(M94/H94-1,"N/A") -> N/A | N95: =IFERROR(N94/I94-1,"N/A") -> N/A | O95: =IFERROR(O94/J94-1,"N/A") -> N/A | P95: =IFERROR(P94/K94-1,"N/A") -> N/A | Q95: =IFERROR(Q94/L94-1,"N/A") -> N/A | R95: =IFERROR(R94/M94-1,"N/A") -> N/A | ... CH95: =IFERROR(CH94/CC94-1,"N/A") -> N/A | CI95: =IFERROR(CI94/CH94-1,"N/A") -> N/A | CJ95: =IFERROR(CJ94/CI94-1,"N/A") -> N/A | CK95: =IFERROR(CK94/CJ94-1,"N/A") -> N/A
A96: GAAP OPEX Margin, % | C96: =C94/C44 -> 0.0078449945 | D96: =D94/D44 -> 0 | E96: =E94/E44 -> -0.016086658 | F96: =F94/F44 -> 0 | G96: =G94/G44 -> 0 | H96: =H94/H44 -> 0 | I96: =I94/I44 -> 0 | J96: =J94/J44 -> 0 | ... CK96: =CK94/CK44 -> 0
A97: Y/Y Improvement in GAAP OPEX Margin, bps | D97: =-(D96-C96)*10000 -> 78.449945 | E97: =-(E96-D96)*10000 -> 160.86658 | F97: =-(F96-E96)*10000 -> -160.86658 | K97: =-(K96-F96)*10000 -> 0 | L97: =-(L96-G96)*10000 -> 0 | M97: =-(M96-H96)*10000 -> 0 | N97: =-(N96-I96)*10000 -> 0 | O97: =-(O96-J96)*10000 -> 0 | P97: =-(P96-K96)*10000 -> 0 | Q97: =-(Q96-L96)*10000 -> 0 | R97: =-(R96-M96)*10000 -> 0 | ... CH97: =-(CH96-CC96)*10000 -> 0 | CI97: =-(CI96-CH96)*10000 -> 0 | CJ97: =-(CJ96-CI96)*10000 -> 0 | CK97: =-(CK96-CJ96)*10000 -> 0
A99: Other OPEX Adjustments, mm | C99: =C392 -> 26.868 | D99: =D392 -> 0 | E99: =E392 -> -57 | F99: =F392 -> 0 | G99: =G392 -> 0 | H99: =H392 -> 0 | I99: =I392 -> 0 | J99: =J392 -> 0 | ... BY99: =BY392 -> 0 | BZ99: 0 | CA99: 0 | CB99: 0 | CC99: =SUM(BY99,BZ99,CA99,CB99) -> 0 | CD99: 0 | CE99: 0 | CF99: 0 | CG99: 0 | CH99: =SUM(CD99,CE99,CF99,CG99) -> 0 | CI99: 0 | CJ99: 0 | CK99: 0
A100: Non-GAAP OPEX Expense, mm | C100: =C94-C99 -> 0 | D100: =D94-D99 -> 0 | E100: =E94-E99 -> 0 | F100: =F94-F99 -> 0 | G100: =G94-G99 -> 0 | H100: =H94-H99 -> 0 | I100: =I94-I99 -> 0 | J100: =J94-J99 -> 0 | ... BY100: =BY94-BY99 -> 0 | BZ100: 0 | CA100: 0 | CB100: 0 | CC100: =CC94-CC99 -> 0 | CD100: 0 | CE100: 0 | CF100: 0 | CG100: 0 | CH100: =CH94-CH99 -> 0 | CI100: 0 | CJ100: 0 | CK100: 0
A101: Y/Y Growth in non-GAAP OPEX Expense, % | D101: =IFERROR(D100/C100-1,"N/A") -> N/A | E101: =IFERROR(E100/D100-1,"N/A") -> N/A | F101: =IFERROR(F100/E100-1,"N/A") -> N/A | K101: =IFERROR(K100/F100-1,"N/A") -> N/A | L101: =IFERROR(L100/G100-1,"N/A") -> N/A | M101: =IFERROR(M100/H100-1,"N/A") -> N/A | N101: =IFERROR(N100/I100-1,"N/A") -> N/A | O101: =IFERROR(O100/J100-1,"N/A") -> N/A | P101: =IFERROR(P100/K100-1,"N/A") -> N/A | Q101: =IFERROR(Q100/L100-1,"N/A") -> N/A | R101: =IFERROR(R100/M100-1,"N/A") -> N/A | ... CH101: =IFERROR(CH100/CC100-1,"N/A") -> N/A | CI101: =IFERROR(CI100/CH100-1,"N/A") -> N/A | CJ101: =IFERROR(CJ100/CI100-1,"N/A") -> N/A | CK101: =IFERROR(CK100/CJ100-1,"N/A") -> N/A
A102: Non-GAAP OPEX Margin, % | C102: =C100/C44 -> 0 | D102: =D100/D44 -> 0 | E102: =E100/E44 -> 0 | F102: =F100/F44 -> 0 | G102: =G100/G44 -> 0 | H102: =H100/H44 -> 0 | I102: =I100/I44 -> 0 | J102: =J100/J44 -> 0 | ... CK102: =CK100/CK44 -> 0
A103: Y/Y Improvement in Non-GAAP OPEX Margin, bps | D103: =-(D102-C102)*10000 -> 0 | E103: =-(E102-D102)*10000 -> 0 | F103: =-(F102-E102)*10000 -> 0 | K103: =-(K102-F102)*10000 -> 0 | L103: =-(L102-G102)*10000 -> 0 | M103: =-(M102-H102)*10000 -> 0 | N103: =-(N102-I102)*10000 -> 21.205598 | O103: =-(O102-J102)*10000 -> 16.12455 | P103: =-(P102-K102)*10000 -> 9.8789346 | Q103: =-(Q102-L102)*10000 -> 0 | R103: =-(R102-M102)*10000 -> 0 | ... CH103: =-(CH102-CC102)*10000 -> 0 | CI103: =-(CI102-CH102)*10000 -> 0 | CJ103: =-(CJ102-CI102)*10000 -> 0 | CK103: =-(CK102-CJ102)*10000 -> 0
A105: Other Non-GAAP Operating Items, mm | C105: =C395 -> 152.102 | D105: =D395 -> -31.859 | E105: =E395 -> -21.887 | F105: =F395 -> -17.19 | G105: =G395 -> -4.342 | H105: =H395 -> -4.065 | I105: =I395 -> -4.402 | J105: =J395 -> 0 | ... BY105: =BY395 -> 0 | BZ105: 0 | CA105: 0 | CB105: 0 | CC105: =SUM(BY105,BZ105,CA105,CB105) -> 0 | CD105: 0 | CE105: 0 | CF105: 0 | CG105: 0 | CH105: =SUM(CD105,CE105,CF105,CG105) -> 0 | CI105: 0 | CJ105: 0 | CK105: 0
A106: Non-GAAP Operating Income, mm | C106: =C57-C74-C89-C100-C105 -> 148.622 | D106: =D57-D74-D89-D100-D105 -> 135.245 | E106: =E57-E74-E89-E100-E105 -> 502.18 | F106: =F57-F74-F89-F100-F105 -> 829.425 | G106: =G57-G74-G89-G100-G105 -> 117.908 | H106: =H57-H74-H89-H100-H105 -> 200.864 | I106: =I57-I74-I89-I100-I105 -> 294.354 | J106: =J57-J74-J89-J100-J105 -> 228.04 | ... CK106: =CK57-CK74-CK89-CK100-CK105 -> 501566.81
A107: =CONCATENATE("Consensus Estimates - ",IFERROR(LEFT(A106,FIND("(",A106)-1),A106)) -> Consensus Estimates - Non-GAAP Operating Income, mm | BZ107: =BZ397 -> N/A | CA107: =CA397 -> N/A | CB107: =CB397 -> N/A | CC107: =CC397 -> N/A | CD107: =CD397 -> N/A | CE107: =CE397 -> N/A | CF107: =CF397 -> N/A | CG107: =CG397 -> N/A | ... CK107: =CK397 -> N/A
A108: Y/Y Growth in Non-GAAP Operating Income, % | D108: =D106/C106-1 -> -0.090006863 | E108: =E106/D106-1 -> 2.7131132 | F108: =F106/E106-1 -> 0.65164881 | K108: =K106/F106-1 -> 0.01415559 | L108: =L106/G106-1 -> 0.060479357 | M108: =M106/H106-1 -> -0.25729349 | N108: =N106/I106-1 -> -0.38136054 | O108: =O106/J106-1 -> -0.088357306 | P108: =P106/K106-1 -> -0.2105601 | Q108: =Q106/L106-1 -> 0.56751094 | R108: =R106/M106-1 -> 0.40766709 | ... CH108: =CH106/CC106-1 -> 0.26838248 | CI108: =CI106/CH106-1 -> 0.19366334 | CJ108: =CJ106/CI106-1 -> 0.1755445 | CK108: =CK106/CJ106-1 -> 0.17588307
A109: Non-GAAP Operating Income margin, % | C109: =C106/C44 -> 0.043395071 | D109: =D106/D44 -> 0.040657519 | E109: =E106/E44 -> 0.14172628 | F109: =F106/F44 -> 0.20746361 | G109: =G106/G44 -> 0.12748506 | H109: =H106/H44 -> 0.19234872 | I109: =I106/I44 -> 0.24445773 | J109: =J106/J44 -> 0.20601643 | ... CK109: =CK106/CK44 -> 0.67057769
A110: Consensus Estimates - Non-GAAP Operating Income Margin, % | BZ110: =BZ295 -> 0 | CA110: =CA295 -> 0 | CB110: =CB295 -> 0 | CC110: =CC295 -> 0 | CD110: =CD295 -> 0 | CE110: =CE295 -> 0 | CF110: =CF295 -> 0 | CG110: =CG295 -> 0 | ... CK110: =CK295 -> 0
A111: Y/Y Improvement in Non-GAAP Operating Income margin, bps | D111: =(D109-C109)*10000 -> -27.375524 | E111: =(E109-D109)*10000 -> 1010.6876 | F111: =(F109-E109)*10000 -> 657.37333 | K111: =(K109-F109)*10000 -> -109.36801 | L111: =(L109-G109)*10000 -> 34.816229 | M111: =(M109-H109)*10000 -> -396.90925 | N111: =(N109-I109)*10000 -> -716.82873 | O111: =(O109-J109)*10000 -> -243.28152 | P111: =(P109-K109)*10000 -> -357.39886 | Q111: =(Q109-L109)*10000 -> 467.30506 | R111: =(R109-M109)*10000 -> 377.32049 | ... CH111: =(CH109-CC109)*10000 -> -2.011085 | CI111: =(CI109-CH109)*10000 -> 5 | CJ111: =(CJ109-CI109)*10000 -> 5 | CK111: =(CK109-CJ109)*10000 -> 5
A113: Total Non-GAAP Operating Expenses, mm | C113: =+C100+C89+C74 -> 1067.334 | D113: =+D100+D89+D74 -> 1180.827 | E113: =+E100+E89+E74 -> 1118.298 | F113: =+F100+F89+F74 -> 1262.904 | G113: =+G100+G89+G74 -> 352.324 | H113: =+H100+H89+H74 -> 346.569 | I113: =+I100+I89+I74 -> 349.195 | J113: =+J100+J89+J74 -> 360.388 | ... CK113: =+CK100+CK89+CK74 -> 60886.704
A114: =CONCATENATE("Guidance - ",IFERROR(LEFT(A113,FIND("(",A113)-1),A113)) -> Guidance - Total Non-GAAP Operating Expenses, mm | AH114: =+AH530 | AI114: =+AI530 -> 600 | AJ114: =+AJ530 | AK114: =+AK530 -> 645 | AL114: =+AL530 -> 685 | AM114: =+AM530 -> 730 | AN114: =+AN530 -> 755 | AO114: =+AO530 | ... CK114: =+CK530 -> 0
A116: SBC, D&A, Acquisition-related Costs Breakdown (FS)
A117: Depreciation, mm | C117: =C119-C118 -> 152.423 | D117: =D119-D118 -> 164.764 | E117: =E119-E118 -> 156.989 | F117: =F119-F118 -> 145.205 | G117: =G119-G118 -> 37.891 | H117: =H119-H118 -> 38.995 | I117: =I119-I118 -> 39.848 | J117: =J119-J118 -> 41.101 | ... Y117: =Y119-Y118 -> 29 | Z117: 124 | AA117: =AA119-AA118 -> 28 | AB117: =AB119-AB118 -> 29 | AC117: =AC119-AC118 -> 30 | AD117: =AD119-AD118 -> 32 | AE117: =AE119-AE118 -> 119 | AF117: =AF119-AF118 -> 32 | AG117: =AG119-AG118 -> 35 | AH117: =AH119-AH118 -> 36 | AI117: =AI119-AI118 -> 41 | AJ117: 144 | AK117: =AK119-AK118 -> 46 | AL117: =AL119-AL118 -> 53 | AM117: =AM119-AM118 -> 61 | AN117: =AN119-AN118 -> 73 | AO117: 233 | AP117: =AP119-AP118 -> 84 | AQ117: =AQ119-AQ118 -> 86 | AR117: =AR119-AR118 -> 86 | AS117: =AS119-AS118 -> 100 | AT117: =AT119-AT118 -> 356 | AU117: =AU119-AU118 -> 100 | AV117: =AV119-AV118 -> 120 | AW117: =AW119-AW118 -> 125 | AX117: =AX119-AX118 -> 141 | AY117: 486 | AZ117: =AZ119-AZ118 -> 144 | BA117: =BA119-BA118 -> 148 | BB117: =BB119-BB118 -> 155 | BC117: =BD117-SUM(AZ117,BA117,BB117) -> 164 | BD117: 611 | BE117: =BE119-BE118 -> 179 | BF117: =BF119-BF118 -> 196 | BG117: =BG119-BG118 -> 225 | BH117: =BI117-SUM(BE117,BF117,BG117) -> 244 | BI117: 844 | BJ117: =BJ119-BJ118 -> 203 | BK117: =BK119-BK118 -> 219 | BL117: =BL119-BL118 -> 228 | BM117: =BN117-SUM(BJ117,BK117,BL117) -> 244 | BN117: 894 | BO117: =BO119-BO118 -> 267 | BP117: =BP119-BP118 -> 287 | BQ117: =BQ119-BQ118 -> 329 | BR117: =BS117-SUM(BO117,BP117,BQ117) -> 388 | BS117: =BS119-BS118 -> 1271 | BT117: =BT119-BT118 -> 452 | BU117: =BU119-BU118 -> 583 | BV117: =BV119-BV118 -> 655 | BW117: =BX117-SUM(BT117,BU117,BV117) -> 665 | BX117: =BX119-BX118 -> 2355 | BY117: =BY119-BY118 -> 765 | BZ117: =BZ399 -> 790.98377 | CA117: =CA399 -> 767.53646 | CB117: =CB399 -> 776.95817 | CC117: =SUM(BY117,BZ117,CA117,CB117) -> 3100.4784 | CD117: =CD399 -> 693.88438 | CE117: =CE399 -> 683.45878 | CF117: =CF399 -> 665.34813 | CG117: =CG399 -> 647.88026 | CH117: =SUM(CD117,CE117,CF117,CG117) -> 2690.5716 | CI117: =CI399 -> 2450.357 | CJ117: =CJ399 -> 2117.4642 | CK117: =CK399 -> 1871.1235
A118: Amortization, mm | C118: 32.6 | D118: 31.9 | E118: 30 | F118: 59 | G118: 16.6 | H118: 17.2 | I118: 17.3 | J118: =K118-SUM(G118,H118,I118) -> 17.3 | K118: 68.4 | L118: 17.4 | M118: 18.6 | N118: 19.6 | O118: =P118-SUM(L118,M118,N118) -> 17.1 | P118: 72.7 | Q118: 19 | R118: 19 | S118: 19 | T118: =U118-SUM(Q118,R118,S118) -> 20 | U118: 77 | V118: 19 | W118: 19 | X118: 18 | Y118: =Z118-SUM(V118,W118,X118) -> 17 | Z118: 73 | AA118: 17 | AB118: 18 | AC118: 18 | AD118: =AE118-SUM(AA118,AB118,AC118) -> 15 | AE118: 68 | AF118: 15 | AG118: 14 | AH118: 13 | AI118: =AJ118-SUM(AF118,AG118,AH118) -> 13 | AJ118: 55 | AK118: 11 | AL118: 6 | AM118: 7 | AN118: =AO118-SUM(AK118,AL118,AM118) -> 5 | AO118: 29 | AP118: 7 | AQ118: 6 | AR118: 6 | AS118: =AT118-SUM(AP118,AQ118,AR118) -> 6 | AT118: 25 | AU118: 7 | AV118: 284 | AW118: 174 | AX118: =AY118-SUM(AU118,AV118,AW118) -> 147 | AY118: 612 | AZ118: 137 | BA118: 138 | BB118: 143 | BC118: =BD118-SUM(AZ118,BA118,BB118) -> 145 | BD118: 563 | BE118: 155 | BF118: 182 | BG118: 181 | BH118: =BI118-SUM(BE118,BF118,BG118) -> 181 | BI118: 699 | BJ118: 181 | BK118: 146 | BL118: 144 | BM118: =BN118-SUM(BJ118,BK118,BL118) -> 143 | BN118: 614 | BO118: 143 | BP118: 146 | BQ118: 149 | BR118: =BS118-SUM(BO118,BP118,BQ118) -> 155 | BS118: 593 | BT118: 159 | BU118: 86 | BV118: 96 | BW118: =BX118-SUM(BT118,BU118,BV118) -> 147 | BX118: 488 | BY118: 232 | BZ118: =-BZ931 -> 229.58491 | CA118: =-CA931 -> 217.44597 | CB118: =-CB931 -> 214.75715 | CC118: =SUM(BY118,BZ118,CA118,CB118) -> 893.78803 | CD118: =-CD931 -> 186.95208 | CE118: =-CE931 -> 179.60108 | CF118: =-CF931 -> 170.45146 | CG118: =-CG931 -> 161.75941 | CH118: =SUM(CD118,CE118,CF118,CG118) -> 698.76404 | CI118: =-CI931 -> 596.08438 | CJ118: =-CJ931 -> 456.25907 | CK118: =-CK931 -> 358.38135
...

Sheet Exec Comp
A1: =MO.CompanyName -> Company1915 Company0697
A2: =MO.Ticker -> Ticker0027 US | C2: =Model!C2 -> 39478 | D2: =Model!D2 -> 0 | E2: =Model!E2 -> 0 | F2: =Model!F2 -> 0 | G2: =Model!G2 -> 0 | H2: =Model!H2 -> 0 | I2: =Model!I2 -> 0 | J2: =Model!J2 -> 0 | ... CK2: =Model!CK2 -> 0
A3: =MO.TradingCurrency -> USD | B3: =MO.LastPrice -> 222.82 | C3: =INDEX(MO_Common_FPDays,0,MATCH(C$5,MO_Common_ColumnHeader,0)) -> 360 | D3: =INDEX(MO_Common_FPDays,0,MATCH(D$5,MO_Common_ColumnHeader,0)) -> 371 | E3: =INDEX(MO_Common_FPDays,0,MATCH(E$5,MO_Common_ColumnHeader,0)) -> 364 | F3: =INDEX(MO_Common_FPDays,0,MATCH(F$5,MO_Common_ColumnHeader,0)) -> 364 | G3: =INDEX(MO_Common_FPDays,0,MATCH(G$5,MO_Common_ColumnHeader,0)) -> 91 | H3: =INDEX(MO_Common_FPDays,0,MATCH(H$5,MO_Common_ColumnHeader,0)) -> 91 | I3: =INDEX(MO_Common_FPDays,0,MATCH(I$5,MO_Common_ColumnHeader,0)) -> 91 | J3: =INDEX(MO_Common_FPDays,0,MATCH(J$5,MO_Common_ColumnHeader,0)) -> 91 | ... CK3: =INDEX(MO_Common_FPDays,0,MATCH(CK$5,MO_Common_ColumnHeader,0)) -> 365
A4: =MO.DataSourceName -> Bloomberg | B4: =MO.RealTime -> OFF | C4: =INDEX(MO_Common_QEndDate,0,MATCH(C$5,MO_Common_ColumnHeader,0)) -> 39838 | D4: =INDEX(MO_Common_QEndDate,0,MATCH(D$5,MO_Common_ColumnHeader,0)) -> 40209 | E4: =INDEX(MO_Common_QEndDate,0,MATCH(E$5,MO_Common_ColumnHeader,0)) -> 40573 | F4: =INDEX(MO_Common_QEndDate,0,MATCH(F$5,MO_Common_ColumnHeader,0)) -> 40937 | G4: =INDEX(MO_Common_QEndDate,0,MATCH(G$5,MO_Common_ColumnHeader,0)) -> 41028 | H4: =INDEX(MO_Common_QEndDate,0,MATCH(H$5,MO_Common_ColumnHeader,0)) -> 41119 | I4: =INDEX(MO_Common_QEndDate,0,MATCH(I$5,MO_Common_ColumnHeader,0)) -> 41210 | J4: =INDEX(MO_Common_QEndDate,0,MATCH(J$5,MO_Common_ColumnHeader,0)) -> 41301 | ... CK4: =INDEX(MO_Common_QEndDate,0,MATCH(CK$5,MO_Common_ColumnHeader,0)) -> 47879
A5: =MO.ReportFX -> USD | C5: =Model!C5 -> FY2009 | D5: =Model!D5 -> FY2010 | E5: =Model!E5 -> FY2011 | F5: =Model!F5 -> FY2012 | G5: =Model!G5 -> Q1-2013 | H5: =Model!H5 -> Q2-2013 | I5: =Model!I5 -> Q3-2013 | J5: =Model!J5 -> Q4-2013 | ... CK5: =Model!CK5 -> FY2031
A6: Executive Compensation
A7: CEO - Base Pay, 000s | AT7: 996.514 | AY7: 1017.355 | BD7: 996.216 | BI7: 996.832 | BN7: 996.514 | BS7: 1486.199
A8: CEO - Stock Awards, 000s | AT8: 9676.92 | AY8: 15279.78 | BD8: 18660.407 | BI8: 19666.382 | BN8: 26676.415 | BS8: 38811.306
A9: CEO - Non-equity incentive plans, 000s | AT9: 805.444 | AY9: 3000 | BD9: 4000 | BI9: 0 | BN9: 4000 | BS9: 6000
A10: CEO - All other compensation, 000s | AT10: 13.402 | AY10: 19.266 | BD10: 81.038 | BI10: 693.71 | BN10: 2494.973 | BS10: 3568.746
A11: CEO - Total Comp, 000s | AT11: =SUM(AT7:AT10) -> 11492.28 | AY11: =SUM(AY7:AY10) -> 19316.401 | BD11: =SUM(BD7:BD10) -> 23737.661 | BI11: =SUM(BI7:BI10) -> 21356.924 | BN11: =SUM(BN7:BN10) -> 34167.902 | BS11: =SUM(BS7:BS10) -> 49866.251
A12: CEO - comp tied to equity, % | AT12: =SUM(AT8)/AT11 -> 0.84203657 | AY12: =SUM(AY8)/AY11 -> 0.79102624 | BD12: =SUM(BD8)/BD11 -> 0.78610976 | BI12: =SUM(BI8)/BI11 -> 0.92084338 | BN12: =SUM(BN8)/BN11 -> 0.78074489 | BS12: =SUM(BS8)/BS11 -> 0.77830808
A13: Market Cap - EoP, mm | AT13: =Model!AT754 -> 152648.01 | AU13: =Model!AU754 -> 185940.58 | AV13: =Model!AV754 -> 266199.12 | AW13: =Model!AW754 -> 316358.16 | AX13: =Model!AX754 -> 328380.88 | AY13: =Model!AY754 -> 327861.29 | AZ13: =Model!AZ754 -> 388635.66 | BA13: =Model!BA754 -> 494299.65 | ... BY13: =Model!BY754 -> 5066376
A15: CEO - Options 09/14/2020 # of unexercised exercisable options, 000s | AT15: 250
A16: CEO - Options 09/14/2020 exercise price, $ | AT16: 10.56
A18: CEO - Options 03/17/2021 # of unexercised exercisable options, 000s | AT18: 250 | AY18: 50
A19: CEO - Options 03/17/2021 exercise price, $ | AT19: 17.62 | AY19: 17.62
A21: CEO - Options 09/20/2021 # of unexercised exercisable options, 000s | AT21: 250 | AY21: 250
A22: CEO - Options 09/20/2021 exercise price, $ | AT22: 14.465 | AY22: 14.465
A24: CEO - Options 03/20/2022 # of unexercised exercisable options, 000s | AT24: 300 | AY24: 300 | BD24: 292.34
A25: CEO - Options 03/20/2022 exercise price, $ | AT25: 14.46 | AY25: 14.46 | BD25: 3.615
A27: CEO - Options 09/18/2022 # of unexercised exercisable options, 000s | AT27: 300 | AY27: 300 | BD27: 1200
A28: CEO - Options 09/18/2022 exercise price, $ | AT28: 13.71 | AY28: 13.71 | BD28: 3.4275
A30: CEO - Options 03/19/2023 # of unexercised exercisable options, 000s | AT30: 237.5 | AY30: 237.5 | BD30: 950
A31: CEO - Options 03/19/2023 exercise price, $ | AT31: 12.62 | AY31: 12.62 | BD31: 3.155
A33: CEO - Options 09/17/2023 # of unexercised excercisable options, 000s | AT33: 237.5 | AY33: 237.5 | BD33: 950 | BI33: 475
A34: CEO - Options 09/17/2023 exercise price, $ | AT34: 16 | AY34: 16 | BD34: 4 | BI34: 4
A36: CEO - EoP shares owned, 000s | AT36: =(21462.889*(10))*(4) -> 858515.56 | AY36: =(21375.455*(10))*(4) -> 855018.2 | BD36: =84421.722*(10) -> 844217.22 | BI36: =86403.193*(10) -> 864031.93 | BN36: =93463.791*(10) -> 934637.91 | BS36: 922922.94
A37: CEO - EoP Shares Issuable Within 60 days, 000s | AT37: =(1825*(10))*(4) -> 73000 | AY37: =(1325*(10))*(4) -> 53000 | BD37: =3100*(10) -> 31000 | BI37: =475*(10) -> 4750
A38: CEO - EoP shares beneficially owned, 000s | AT38: =SUM(AT36:AT37) -> 931515.56 | AY38: =SUM(AY36:AY37) -> 908018.2 | BD38: =SUM(BD36:BD37) -> 875217.22 | BI38: =SUM(BI36:BI37) -> 868781.93 | BN38: =SUM(BN36:BN37) -> 934637.91 | BS38: =SUM(BS36:BS37) -> 922922.94
A40: CFO - Base Pay, 000s | AT40: 896.863 | AY40: 915.62 | BD40: 896.595 | BI40: 897.149 | BN40: 896.863 | BS40: 893.739
A41: CFO - Stock Awards, 000s | AT41: 3307.188 | AY41: 6595.691 | BD41: 8269.02 | BI41: 10004.677 | BN41: 11756.027 | BS41: 19849.891
A42: CFO - Non-equity incentive plans, 000s | AT42: 219.667 | AY42: 600 | BD42: 600 | BI42: 0 | BN42: 600 | BS42: 600
A43: CFO - All other compensation, 000s | AT43: 9.122 | AY43: 9.731 | BD43: 10.312 | BI43: 15.402 | BN43: 13.902 | BS43: 18.902
A44: CFO - Total Comp, 000s | AT44: =SUM(AT40:AT43) -> 4432.84 | AY44: =SUM(AY40:AY43) -> 8121.042 | BD44: =SUM(BD40:BD43) -> 9775.927 | BI44: =SUM(BI40:BI43) -> 10917.228 | BN44: =SUM(BN40:BN43) -> 13266.792 | BS44: =SUM(BS40:BS43) -> 21362.532
A45: CFO - comp tied to equity, % | AT45: =SUM(AT41)/AT44 -> 0.74606528 | AY45: =SUM(AY41)/AY44 -> 0.81217299 | BD45: =SUM(BD41)/BD44 -> 0.84585533 | BI45: =SUM(BI41)/BI44 -> 0.91641184 | BN45: =SUM(BN41)/BN44 -> 0.88612432 | BS45: =SUM(BS41)/BS44 -> 0.92919187
A47: CFO - EoP shares owned, 000s | AT47: 81.792 | AY47: 98.873 | BD47: 447.471 | BI47: 478.297 | BN47: 515.421 | BS47: 4872.485
A48: CFO - EoP Shares Issuable Within 60 days, 000s
A49: CFO - EoP shares beneficially owned, 000s | AT49: =SUM(AT47:AT47) -> 81.792 | AY49: =SUM(AY47:AY47) -> 98.873 | BD49: =SUM(BD47:BD47) -> 447.471 | BI49: =SUM(BI47:BI47) -> 478.297 | BN49: =SUM(BN47:BN48) -> 515.421 | BS49: =SUM(BS47:BS48) -> 4872.485
A51: Board Diversity
A52: Total # of current directors | AT52: 11 | AY52: 13 | BD52: 13 | BI52: 13 | BN52: 14 | BS52: 13
A53: Total # of independent current directors | AT53: 10 | AY53: 12 | BD53: 12 | BI53: 12 | BN53: 13 | BS53: 12
A54: Total # of female current directors | AY54: 3 | BD54: 3 | BI54: 3 | BN54: 4 | BS54: 5
A55: Total # of racially/ethnically diverse current directors | AY55: 3 | BD55: 3 | BI55: 3 | BN55: 3 | BS55: 4
A57: Total # of director nominees | AT57: 11 | AY57: 13 | BD57: 13 | BI57: 13 | BN57: 12 | BS57: 13
A58: Total # of independent director nominees | AT58: 10 | AY58: 12 | BD58: 12 | BI58: 12 | BN58: 11 | BS58: 12
A60: Director Compensation
A61: Director 1 cash comp, 000s | AT61: 75 | AY61: 75 | BD61: 82.5 | BI61: 85 | BN61: 85 | BS61: 85
A62: Director 2 cash comp, 000s | AT62: 75 | AY62: 75 | BD62: 82.5 | BI62: 85 | BN62: 85 | BS62: 85
A63: Director 3 cash comp, 000s | AT63: 75 | AY63: 48.03 | BD63: 82.5 | BI63: 85 | BN63: 85 | BS63: 85
A64: Director 4 cash comp, 000s | AT64: 75 | AY64: 75 | BD64: 82.5 | BI64: 85 | BN64: 85 | BS64: 85
A65: Director 5 cash comp, 000s | AT65: 75 | AY65: 37.5 | BD65: 82.5 | BI65: 85 | BN65: 85 | BS65: 85
A66: Director 6 cash comp, 000s | AT66: 75 | AY66: 75 | BD66: 82.5 | BI66: 85 | BN66: 85 | BS66: 85
A67: Director 7 cash comp, 000s | AT67: 75 | AY67: 75 | BD67: 82.5 | BI67: 85 | BN67: 56 | BS67: 85
A68: Director 8 cash comp, 000s | AT68: 67.14 | AY68: 75 | BD68: 82.5 | BI68: 85 | BN68: 85 | BS68: 42.5
A69: Director 9 cash comp, 000s | AT69: 75 | AY69: 75 | BD69: 82.5 | BI69: 85 | BN69: 85 | BS69: 85
A70: Director 10 cash comp, 000s | AT70: 75 | AY70: 75 | BD70: 82.5 | BI70: 85 | BN70: 85 | BS70: 32.55
A71: Director 11 cash comp, 000s | AT71: 75 | AY71: 75 | BD71: 82.5 | BI71: 85 | BN71: 85 | BS71: 42.5
A72: Director 12 cash comp, 000s | AY72: 23.55 | BD72: 82.5 | BI72: 85 | BN72: 85 | BS72: 85
A73: Director 13 cash comp, 000s | AY73: 75 | BN73: 85 | BS73: 85
A74: Director 14 cash comp, 000s | BS74: 85
A75: Total director cash comp, 000s | AT75: =SUM(AT61:AT74) -> 817.14 | AY75: =SUM(AY61:AY74) -> 859.08 | BD75: =SUM(BD61:BD74) -> 990 | BI75: =SUM(BI61:BI74) -> 1020 | BN75: =SUM(BN61:BN74) -> 1076 | BS75: =SUM(BS61:BS74) -> 1052.55
A76: Director 1 stock award comp, 000s | AT76: 184.536 | AY76: 266.338 | BD76: 301.381 | BI76: 268.978 | BN76: 274.268 | BS76: 258.828
A77: Director 2 stock award comp, 000s | AT77: 184.536 | AY77: 266.338 | BD77: 301.381 | BI77: 268.978 | BN77: 274.268 | BS77: 258.828
A78: Director 3 stock award comp, 000s | AT78: 184.536 | AY78: 558.145 | BD78: 301.381 | BI78: 268.978 | BN78: 274.268 | BS78: 258.828
A79: Director 4 stock award comp, 000s | AT79: 184.536 | AY79: 266.338 | BD79: 301.381 | BI79: 268.978 | BN79: 274.268 | BS79: 258.828
A80: Director 5 stock award comp, 000s | AT80: 184.536 | AY80: 0 | BD80: 301.381 | BI80: 268.978 | BN80: 274.268 | BS80: 258.828
A81: Director 6 stock award comp, 000s | AT81: 184.536 | AY81: 266.338 | BD81: 301.381 | BI81: 268.978 | BN81: 274.268 | BS81: 258.828
A82: Director 7 stock award comp, 000s | AT82: 184.536 | AY82: 266.338 | BD82: 301.381 | BI82: 268.978 | BN82: 525.372 | BS82: 258.828
A83: Director 8 stock award comp, 000s | AT83: 480.776 | AY83: 266.338 | BD83: 301.381 | BI83: 268.978 | BN83: 274.268
A84: Director 9 stock award comp, 000s | AT84: 184.536 | AY84: 266.338 | BD84: 301.381 | BI84: 268.978 | BN84: 274.268 | BS84: 258.828
A85: Director 10 stock award comp, 000s | AT85: 184.536 | AY85: 266.338 | BD85: 301.381 | BI85: 268.978 | BN85: 274.268 | BS85: 439.659
A86: Director 11 stock award comp, 000s | AT86: 184.536 | AY86: 266.338 | BD86: 301.381 | BI86: 268.978 | BN86: 274.268
A87: Director 12 stock award comp, 000s | AY87: 440.668 | BD87: 301.381 | BI87: 268.978 | BN87: 274.268 | BS87: 258.828
A88: Director 13 stock award comp, 000s | AY88: 266.338 | BN88: 274.268 | BS88: 258.828
A89: Director 14 stock award comp, 000s | BS89: 258.828
A90: Total director stock award comp, 000s | AT90: =SUM(AT76:AT89) -> 2326.136 | AY90: =SUM(AY76:AY89) -> 3662.193 | BD90: =SUM(BD76:BD89) -> 3616.572 | BI90: =SUM(BI76:BI89) -> 3227.736 | BN90: =SUM(BN76:BN89) -> 3816.588 | BS90: =SUM(BS76:BS89) -> 3286.767
A91: Director 1 all other comp, 000s
A92: Director 2 all other comp, 000s
A93: Director 3 all other comp, 000s
A94: Director 4 all other comp, 000s
A95: Director 5 all other comp, 000s
A96: Director 6 all other comp, 000s
A97: Director 7 all other comp, 000s
A98: Director 8 all other comp, 000s
A99: Director 9 all other comp, 000s
A100: Director 10 all other comp, 000s
A101: Director 11 all other comp, 000s
A102: Director 12 all other comp, 000s
... A104: Director 14 all other comp, 000s
A105: Total director all other comp, 000s | AT105: =SUM(AT91:AT104) -> 0 | AY105: =SUM(AY91:AY104) -> 0 | BD105: =SUM(BD91:BD104) -> 0 | BI105: =SUM(BI91:BI104) -> 0 | BN105: =SUM(BN91:BN104) -> 0 | BS105: =SUM(BS91:BS104) -> 0
A106: Total director compensation, 000s | AT106: =AT75+AT90+AT105 -> 3143.276 | AY106: =AY75+AY90+AY105 -> 4521.273 | BD106: =BD75+BD90+BD105 -> 4606.572 | BI106: =BI75+BI90+BI105 -> 4247.736 | BN106: =BN75+BN90+BN105 -> 4892.588 | BS106: =BS75+BS90+BS105 -> 4339.317
A107: Market Cap - EoP, mm | AT107: =AT13 -> 152648.01 | AU107: =AU13 -> 185940.58 | AV107: =AV13 -> 266199.12 | AW107: =AW13 -> 316358.16 | AX107: =AX13 -> 328380.88 | AY107: =AY13 -> 327861.29 | AZ107: =AZ13 -> 388635.66 | BA107: =BA13 -> 494299.65 | ... BY107: =BY13 -> 5066376
A109: Other Alignment Data Points
A110: CEO - Stock Ownership Guidelines times base salary, x | AT110: 6 | AY110: 6 | BD110: 6 | BI110: 6 | BN110: 6 | BS110: 10
A111: NEO reporting to CEO - Stock Ownership Guidelines base salary, x | AT111: 1 | AY111: 1 | BD111: 1 | BI111: 1 | BN111: 1 | BS111: 3
A112: Directors - Stock Owneshership Guidelines base salary, x | AT112: 6 | AY112: 6 | BD112: 6 | BI112: 6 | BN112: 6 | BS112: 6
A114: Company Financial Goals
A115: Revenue (Base Operating Plan) goal, bn | AT115: 11.4 | AY115: 12.7 | BD115: 20.5 | BI115: 33.5 | BN115: 26 | BS115: 90
A116: Revenue (Base Operating Plan) goal, mm | AT116: =AT115*1000 -> 11400 | AY116: =AY115*1000 -> 12700 | BD116: =BD115*1000 -> 20500 | BI116: =BI115*1000 -> 33500 | BN116: 26000
...

Sheet Guidance
B1: =MO.CompanyName -> Company1915 Company0697
B2: Most Recent Period: | F2: =UL.MRQ -> Q1-2027
I4: Guidance | M4: Model | P4: Difference vs. Mid | S4: Update Log
B5: Type | D5: Item | E5: Item Name | F5: Fiscal Period | G5: Base Period | I5: Low | J5: High | K5: Mid | M5: Type | N5: Output | P5: Absolute | Q5: Relative | S5: Date | T5: Link
A6: 404 | B6: =IF(INDEX(MO_SNA_IsHistoricalPeriod,,MATCH(F6,MO_Common_ColumnHeader,0)),"Historical","Forward") -> Forward | D6: =INDEX(INDIRECT(E6),0,COLUMN(MO_Common_Column_A)) -> Net Revenue | E6: MO_RIS_REV | F6: Q2-2027 | I6: =91000*0.98 -> 89180 | J6: =91000*1.02 -> 92820 | K6: =AVERAGE(I6:J6) -> 91000 | M6: =IF(INDEX(MO_SNA_IsHistoricalPeriod,,MATCH(F6,MO_Common_ColumnHeader,0)),"Actual","Estimate") -> Estimate | N6: =IFERROR(INDEX(INDIRECT(E6),0,MATCH(F6,MO_Common_ColumnHeader,0)),"N/A") -> 90933.49 | P6: =IF(ISNUMBER(N6),N6-K6,"N/A") -> -66.51 | Q6: =IFERROR(IF(ISNUMBER(N6),(N6-K6)/ABS(K6),"N/A"),"N/A") -> -0.00073087912 | S6: 46162 | T6: CFO Commentary
A7: 403 | B7: =IF(INDEX(MO_SNA_IsHistoricalPeriod,,MATCH(F7,MO_Common_ColumnHeader,0)),"Historical","Forward") -> Forward | D7: =INDEX(INDIRECT(E7),0,COLUMN(MO_Common_Column_A)) -> GAAP Gross Margin, % | E7: MO_MA_GM | F7: Q2-2027 | I7: 0.744 | J7: 0.754 | K7: =AVERAGE(I7:J7) -> 0.749 | M7: =IF(INDEX(MO_SNA_IsHistoricalPeriod,,MATCH(F7,MO_Common_ColumnHeader,0)),"Actual","Estimate") -> Estimate | N7: =IFERROR(INDEX(INDIRECT(E7),0,MATCH(F7,MO_Common_ColumnHeader,0)),"N/A") -> 0.7485259 | P7: =IF(ISNUMBER(N7),N7-K7,"N/A") -> -0.00047410307 | Q7: =IFERROR(IF(ISNUMBER(N7),(N7-K7)/ABS(K7),"N/A"),"N/A") -> -0.00063298141 | S7: 46162 | T7: CFO Commentary
A8: 402 | B8: =IF(INDEX(MO_SNA_IsHistoricalPeriod,,MATCH(F8,MO_Common_ColumnHeader,0)),"Historical","Forward") -> Forward | D8: =INDEX(INDIRECT(E8),0,COLUMN(MO_Common_Column_A)) -> Non-GAAP Gross Margin, % | E8: MO_MA_GM_NONGAAP | F8: Q2-2027 | I8: 0.745 | J8: 0.755 | K8: =AVERAGE(I8:J8) -> 0.75 | M8: =IF(INDEX(MO_SNA_IsHistoricalPeriod,,MATCH(F8,MO_Common_ColumnHeader,0)),"Actual","Estimate") -> Estimate | N8: =IFERROR(INDEX(INDIRECT(E8),0,MATCH(F8,MO_Common_ColumnHeader,0)),"N/A") -> 0.7495259 | P8: =IF(ISNUMBER(N8),N8-K8,"N/A") -> -0.00047410307 | Q8: =IFERROR(IF(ISNUMBER(N8),(N8-K8)/ABS(K8),"N/A"),"N/A") -> -0.00063213743 | S8: 46162 | T8: CFO Commentary
A9: 401 | B9: =IF(INDEX(MO_SNA_IsHistoricalPeriod,,MATCH(F9,MO_Common_ColumnHeader,0)),"Historical","Forward") -> Forward | D9: GAAP Operating Expenses | F9: Q2-2027 | I9: 8500 | J9: 8500 | K9: =AVERAGE(I9:J9) -> 8500 | M9: =IF(INDEX(MO_SNA_IsHistoricalPeriod,,MATCH(F9,MO_Common_ColumnHeader,0)),"Actual","Estimate") -> Estimate | N9: =INDEX(MO_RIS_RD,0,MATCH(F9,MO_Common_ColumnHeader,0))+INDEX(MO_RIS_SGA,0,MATCH(F9,MO_Common_ColumnHeader,0)) -> 8521.3347 | P9: =IF(ISNUMBER(N9),N9-K9,"N/A") -> 21.334685 | Q9: =IFERROR(IF(ISNUMBER(N9),(N9-K9)/ABS(K9),"N/A"),"N/A") -> 0.002509963 | S9: 46162 | T9: CFO Commentary
A10: 400 | B10: =IF(INDEX(MO_SNA_IsHistoricalPeriod,,MATCH(F10,MO_Common_ColumnHeader,0)),"Historical","Forward") -> Forward | D10: =INDEX(INDIRECT(E10),0,COLUMN(MO_Common_Column_A)) -> Total Non-GAAP Operating Expenses, mm | E10: MO_OS_OPEX | F10: Q2-2027 | I10: 8300 | J10: 8300 | K10: =AVERAGE(I10:J10) -> 8300 | M10: =IF(INDEX(MO_SNA_IsHistoricalPeriod,,MATCH(F10,MO_Common_ColumnHeader,0)),"Actual","Estimate") -> Estimate | N10: =IFERROR(INDEX(INDIRECT(E10),0,MATCH(F10,MO_Common_ColumnHeader,0)),"N/A") -> 8321.281 | P10: =IF(ISNUMBER(N10),N10-K10,"N/A") -> 21.281007 | Q10: =IFERROR(IF(ISNUMBER(N10),(N10-K10)/ABS(K10),"N/A"),"N/A") -> 0.0025639768 | S10: 46162 | T10: CFO Commentary
A11: 399 | B11: =IF(INDEX(MO_SNA_IsHistoricalPeriod,,MATCH(F11,MO_Common_ColumnHeader,0)),"Historical","Forward") -> Forward | D11: GAAP Tax Rate | E11: MO_RIS_TaxRate | F11: Q2-2027 | I11: 0.16 | J11: 0.18 | K11: =AVERAGE(I11:J11) -> 0.17 | M11: =IF(INDEX(MO_SNA_IsHistoricalPeriod,,MATCH(F11,MO_Common_ColumnHeader,0)),"Actual","Estimate") -> Estimate | N11: =IFERROR(INDEX(INDIRECT(E11),0,MATCH(F11,MO_Common_ColumnHeader,0)),"N/A") -> 0.17009796 | P11: =IF(ISNUMBER(N11),N11-K11,"N/A") -> 9.7956254e-05 | Q11: =IFERROR(IF(ISNUMBER(N11),(N11-K11)/ABS(K11),"N/A"),"N/A") -> 0.00057621326 | S11: 46162 | T11: CFO Commentary
A12: 398 | B12: =IF(INDEX(MO_SNA_IsHistoricalPeriod,,MATCH(F12,MO_Common_ColumnHeader,0)),"Historical","Forward") -> Forward | D12: =INDEX(INDIRECT(E12),0,COLUMN(MO_Common_Column_A)) -> Non-GAAP Tax Rate | E12: MO_RIS_TaxRate_NONGAAP | F12: Q2-2027 | I12: 0.16 | J12: 0.18 | K12: =AVERAGE(I12:J12) -> 0.17 | M12: =IF(INDEX(MO_SNA_IsHistoricalPeriod,,MATCH(F12,MO_Common_ColumnHeader,0)),"Actual","Estimate") -> Estimate | N12: =IFERROR(INDEX(INDIRECT(E12),0,MATCH(F12,MO_Common_ColumnHeader,0)),"N/A") -> 0.17 | P12: =IF(ISNUMBER(N12),N12-K12,"N/A") -> 2.7755576e-17 | Q12: =IFERROR(IF(ISNUMBER(N12),(N12-K12)/ABS(K12),"N/A"),"N/A") -> 1.6326809e-16 | S12: 46162 | T12: CFO Commentary
A13: 397
A14: 396 | B14: =IF(INDEX(MO_SNA_IsHistoricalPeriod,,MATCH(F14,MO_Common_ColumnHeader,0)),"Historical","Forward") -> Historical | D14: =INDEX(INDIRECT(E14),0,COLUMN(MO_Common_Column_A)) -> Net Revenue | E14: MO_RIS_REV | F14: Q1-2027 | I14: =78000*0.98 -> 76440 | J14: =78000*1.02 -> 79560 | K14: =AVERAGE(I14:J14) -> 78000 | M14: =IF(INDEX(MO_SNA_IsHistoricalPeriod,,MATCH(F14,MO_Common_ColumnHeader,0)),"Actual","Estimate") -> Actual | N14: =IFERROR(INDEX(INDIRECT(E14),0,MATCH(F14,MO_Common_ColumnHeader,0)),"N/A") -> 81615 | P14: =IF(ISNUMBER(N14),N14-K14,"N/A") -> 3615 | Q14: =IFERROR(IF(ISNUMBER(N14),(N14-K14)/ABS(K14),"N/A"),"N/A") -> 0.046346154 | S14: 46078 | T14: CFO Commentary
A15: 395 | B15: =IF(INDEX(MO_SNA_IsHistoricalPeriod,,MATCH(F15,MO_Common_ColumnHeader,0)),"Historical","Forward") -> Historical | D15: =INDEX(INDIRECT(E15),0,COLUMN(MO_Common_Column_A)) -> GAAP Gross Margin, % | E15: MO_MA_GM | F15: Q1-2027 | I15: 0.749 | J15: 0.749 | K15: =AVERAGE(I15:J15) -> 0.749 | M15: =IF(INDEX(MO_SNA_IsHistoricalPeriod,,MATCH(F15,MO_Common_ColumnHeader,0)),"Actual","Estimate") -> Actual | N15: =IFERROR(INDEX(INDIRECT(E15),0,MATCH(F15,MO_Common_ColumnHeader,0)),"N/A") -> 0.74933529 | P15: =IF(ISNUMBER(N15),N15-K15,"N/A") -> 0.00033529376 | Q15: =IFERROR(IF(ISNUMBER(N15),(N15-K15)/ABS(K15),"N/A"),"N/A") -> 0.00044765522 | S15: 46078 | T15: CFO Commentary
A16: 394 | B16: =IF(INDEX(MO_SNA_IsHistoricalPeriod,,MATCH(F16,MO_Common_ColumnHeader,0)),"Historical","Forward") -> Historical | D16: =INDEX(INDIRECT(E16),0,COLUMN(MO_Common_Column_A)) -> Non-GAAP Gross Margin, % | E16: MO_MA_GM_NONGAAP | F16: Q1-2027 | I16: 0.75 | J16: 0.75 | K16: =AVERAGE(I16:J16) -> 0.75 | M16: =IF(INDEX(MO_SNA_IsHistoricalPeriod,,MATCH(F16,MO_Common_ColumnHeader,0)),"Actual","Estimate") -> Actual | N16: =IFERROR(INDEX(INDIRECT(E16),0,MATCH(F16,MO_Common_ColumnHeader,0)),"N/A") -> 0.75025424 | P16: =IF(ISNUMBER(N16),N16-K16,"N/A") -> 0.00025424248 | Q16: =IFERROR(IF(ISNUMBER(N16),(N16-K16)/ABS(K16),"N/A"),"N/A") -> 0.00033898997 | S16: 46078 | T16: CFO Commentary
A17: 393 | B17: =IF(INDEX(MO_SNA_IsHistoricalPeriod,,MATCH(F17,MO_Common_ColumnHeader,0)),"Historical","Forward") -> Historical | D17: GAAP Operating Expenses | F17: Q1-2027 | I17: 7700 | J17: 7700 | K17: =AVERAGE(I17:J17) -> 7700 | M17: =IF(INDEX(MO_SNA_IsHistoricalPeriod,,MATCH(F17,MO_Common_ColumnHeader,0)),"Actual","Estimate") -> Actual | N17: =INDEX(MO_RIS_RD,0,MATCH(F17,MO_Common_ColumnHeader,0))+INDEX(MO_RIS_SGA,0,MATCH(F17,MO_Common_ColumnHeader,0)) -> 7621 | P17: =IF(ISNUMBER(N17),N17-K17,"N/A") -> -79 | Q17: =IFERROR(IF(ISNUMBER(N17),(N17-K17)/ABS(K17),"N/A"),"N/A") -> -0.01025974 | S17: 46078 | T17: CFO Commentary
A18: 392 | B18: =IF(INDEX(MO_SNA_IsHistoricalPeriod,,MATCH(F18,MO_Common_ColumnHeader,0)),"Historical","Forward") -> Historical | D18: =INDEX(INDIRECT(E18),0,COLUMN(MO_Common_Column_A)) -> Total Non-GAAP Operating Expenses, mm | E18: MO_OS_OPEX | F18: Q1-2027 | I18: 7500 | J18: 7500 | K18: =AVERAGE(I18:J18) -> 7500 | M18: =IF(INDEX(MO_SNA_IsHistoricalPeriod,,MATCH(F18,MO_Common_ColumnHeader,0)),"Actual","Estimate") -> Actual | N18: =IFERROR(INDEX(INDIRECT(E18),0,MATCH(F18,MO_Common_ColumnHeader,0)),"N/A") -> 7449 | P18: =IF(ISNUMBER(N18),N18-K18,"N/A") -> -51 | Q18: =IFERROR(IF(ISNUMBER(N18),(N18-K18)/ABS(K18),"N/A"),"N/A") -> -0.0068 | S18: 46078 | T18: CFO Commentary
A19: 391 | B19: =IF(INDEX(MO_SNA_IsHistoricalPeriod,,MATCH(F19,MO_Common_ColumnHeader,0)),"Historical","Forward") -> Historical | D19: GAAP Tax Rate | E19: MO_RIS_TaxRate | F19: Q1-2027 | I19: 0.17 | J19: 0.19 | K19: =AVERAGE(I19:J19) -> 0.18 | M19: =IF(INDEX(MO_SNA_IsHistoricalPeriod,,MATCH(F19,MO_Common_ColumnHeader,0)),"Actual","Estimate") -> Actual | N19: =IFERROR(INDEX(INDIRECT(E19),0,MATCH(F19,MO_Common_ColumnHeader,0)),"N/A") -> 0.16568674 | P19: =IF(ISNUMBER(N19),N19-K19,"N/A") -> -0.014313263 | Q19: =IFERROR(IF(ISNUMBER(N19),(N19-K19)/ABS(K19),"N/A"),"N/A") -> -0.079518126 | S19: 46078 | T19: CFO Commentary
A20: 390 | B20: =IF(INDEX(MO_SNA_IsHistoricalPeriod,,MATCH(F20,MO_Common_ColumnHeader,0)),"Historical","Forward") -> Historical | D20: =INDEX(INDIRECT(E20),0,COLUMN(MO_Common_Column_A)) -> Non-GAAP Tax Rate | E20: MO_RIS_TaxRate_NONGAAP | F20: Q1-2027 | I20: 0.17 | J20: 0.19 | K20: =AVERAGE(I20:J20) -> 0.18 | M20: =IF(INDEX(MO_SNA_IsHistoricalPeriod,,MATCH(F20,MO_Common_ColumnHeader,0)),"Actual","Estimate") -> Actual | N20: =IFERROR(INDEX(INDIRECT(E20),0,MATCH(F20,MO_Common_ColumnHeader,0)),"N/A") -> 0.16025074 | P20: =IF(ISNUMBER(N20),N20-K20,"N/A") -> -0.019749263 | Q20: =IFERROR(IF(ISNUMBER(N20),(N20-K20)/ABS(K20),"N/A"),"N/A") -> -0.10971813 | S20: 46078 | T20: CFO Commentary
A21: 389
A22: 388 | B22: =IF(INDEX(MO_SNA_IsHistoricalPeriod,,MATCH(F22,MO_Common_ColumnHeader,0)),"Historical","Forward") -> Historical | D22: =INDEX(INDIRECT(E22),0,COLUMN(MO_Common_Column_A)) -> Net Revenue | E22: MO_RIS_REV | F22: Q4-2026 | I22: =65000*0.98 -> 63700 | J22: =65000*1.02 -> 66300 | K22: =AVERAGE(I22:J22) -> 65000 | M22: =IF(INDEX(MO_SNA_IsHistoricalPeriod,,MATCH(F22,MO_Common_ColumnHeader,0)),"Actual","Estimate") -> Actual | N22: =IFERROR(INDEX(INDIRECT(E22),0,MATCH(F22,MO_Common_ColumnHeader,0)),"N/A") -> 68127 | P22: =IF(ISNUMBER(N22),N22-K22,"N/A") -> 3127 | Q22: =IFERROR(IF(ISNUMBER(N22),(N22-K22)/ABS(K22),"N/A"),"N/A") -> 0.048107692 | S22: 45980 | T22: CFO Commentary
A23: 387 | B23: =IF(INDEX(MO_SNA_IsHistoricalPeriod,,MATCH(F23,MO_Common_ColumnHeader,0)),"Historical","Forward") -> Historical | D23: =INDEX(INDIRECT(E23),0,COLUMN(MO_Common_Column_A)) -> GAAP Gross Margin, % | E23: MO_MA_GM | F23: Q4-2026 | I23: =74.8%-0.5% -> 0.743 | J23: =74.8%+0.5% -> 0.753 | K23: =AVERAGE(I23:J23) -> 0.748 | M23: =IF(INDEX(MO_SNA_IsHistoricalPeriod,,MATCH(F23,MO_Common_ColumnHeader,0)),"Actual","Estimate") -> Actual | N23: =IFERROR(INDEX(INDIRECT(E23),0,MATCH(F23,MO_Common_ColumnHeader,0)),"N/A") -> 0.74996697 | P23: =IF(ISNUMBER(N23),N23-K23,"N/A") -> 0.0019669734 | Q23: =IFERROR(IF(ISNUMBER(N23),(N23-K23)/ABS(K23),"N/A"),"N/A") -> 0.0026296436 | S23: 45980 | T23: CFO Commentary
A24: 386 | B24: =IF(INDEX(MO_SNA_IsHistoricalPeriod,,MATCH(F24,MO_Common_ColumnHeader,0)),"Historical","Forward") -> Historical | D24: =INDEX(INDIRECT(E24),0,COLUMN(MO_Common_Column_A)) -> Non-GAAP Gross Margin, % | E24: MO_MA_GM_NONGAAP | F24: Q4-2026 | I24: =75%-0.5% -> 0.745 | J24: =75%+0.5% -> 0.755 | K24: =AVERAGE(I24:J24) -> 0.75 | M24: =IF(INDEX(MO_SNA_IsHistoricalPeriod,,MATCH(F24,MO_Common_ColumnHeader,0)),"Actual","Estimate") -> Actual | N24: =IFERROR(INDEX(INDIRECT(E24),0,MATCH(F24,MO_Common_ColumnHeader,0)),"N/A") -> 0.75166968 | P24: =IF(ISNUMBER(N24),N24-K24,"N/A") -> 0.0016696758 | Q24: =IFERROR(IF(ISNUMBER(N24),(N24-K24)/ABS(K24),"N/A"),"N/A") -> 0.0022262343 | S24: 45980 | T24: CFO Commentary
A25: 385 | B25: =IF(INDEX(MO_SNA_IsHistoricalPeriod,,MATCH(F25,MO_Common_ColumnHeader,0)),"Historical","Forward") -> Historical | D25: GAAP Operating Expenses | F25: Q4-2026 | I25: 6700 | J25: 6700 | K25: =AVERAGE(I25:J25) -> 6700 | M25: =IF(INDEX(MO_SNA_IsHistoricalPeriod,,MATCH(F25,MO_Common_ColumnHeader,0)),"Actual","Estimate") -> Actual | N25: =INDEX(MO_RIS_RD,0,MATCH(F25,MO_Common_ColumnHeader,0))+INDEX(MO_RIS_SGA,0,MATCH(F25,MO_Common_ColumnHeader,0)) -> 6794 | P25: =IF(ISNUMBER(N25),N25-K25,"N/A") -> 94 | Q25: =IFERROR(IF(ISNUMBER(N25),(N25-K25)/ABS(K25),"N/A"),"N/A") -> 0.014029851 | S25: 45980 | T25: CFO Commentary
A26: 384 | B26: =IF(INDEX(MO_SNA_IsHistoricalPeriod,,MATCH(F26,MO_Common_ColumnHeader,0)),"Historical","Forward") -> Historical | D26: =INDEX(INDIRECT(E26),0,COLUMN(MO_Common_Column_A)) -> Total Non-GAAP Operating Expenses, mm | E26: MO_OS_OPEX | F26: Q4-2026 | I26: 5000 | J26: 5000 | K26: =AVERAGE(I26:J26) -> 5000 | M26: =IF(INDEX(MO_SNA_IsHistoricalPeriod,,MATCH(F26,MO_Common_ColumnHeader,0)),"Actual","Estimate") -> Actual | N26: =IFERROR(INDEX(INDIRECT(E26),0,MATCH(F26,MO_Common_ColumnHeader,0)),"N/A") -> 5102 | P26: =IF(ISNUMBER(N26),N26-K26,"N/A") -> 102 | Q26: =IFERROR(IF(ISNUMBER(N26),(N26-K26)/ABS(K26),"N/A"),"N/A") -> 0.0204 | S26: 45980 | T26: CFO Commentary
A27: 383 | B27: =IF(INDEX(MO_SNA_IsHistoricalPeriod,,MATCH(F27,MO_Common_ColumnHeader,0)),"Historical","Forward") -> Historical | D27: GAAP Other Income | F27: Q4-2026 | I27: -500 | J27: -500 | K27: =AVERAGE(I27:J27) -> -500 | M27: =IF(INDEX(MO_SNA_IsHistoricalPeriod,,MATCH(F27,MO_Common_ColumnHeader,0)),"Actual","Estimate") -> Actual | N27: =IFERROR(INDEX(INDIRECT(E27),0,MATCH(F27,MO_Common_ColumnHeader,0)),"N/A") -> N/A | P27: =IF(ISNUMBER(N27),N27-K27,"N/A") -> N/A | Q27: =IFERROR(IF(ISNUMBER(N27),(N27-K27)/ABS(K27),"N/A"),"N/A") -> N/A | S27: 45980 | T27: CFO Commentary
A28: 382 | B28: =IF(INDEX(MO_SNA_IsHistoricalPeriod,,MATCH(F28,MO_Common_ColumnHeader,0)),"Historical","Forward") -> Historical | D28: Non-GAAP Other Income | F28: Q4-2026 | I28: -500 | J28: -500 | K28: =AVERAGE(I28:J28) -> -500 | M28: =IF(INDEX(MO_SNA_IsHistoricalPeriod,,MATCH(F28,MO_Common_ColumnHeader,0)),"Actual","Estimate") -> Actual | N28: =INDEX(MO_RIS_IE_Net_NONGAAP,0,MATCH(F28,MO_Common_ColumnHeader,0))+INDEX(MO_RIS_OI_NONGAAP,0,MATCH(F28,MO_Common_ColumnHeader,0)) -> -620 | P28: =IF(ISNUMBER(N28),N28-K28,"N/A") -> -120 | Q28: =IFERROR(IF(ISNUMBER(N28),(N28-K28)/ABS(K28),"N/A"),"N/A") -> -0.24 | S28: 45980 | T28: CFO Commentary
A29: 381 | B29: =IF(INDEX(MO_SNA_IsHistoricalPeriod,,MATCH(F29,MO_Common_ColumnHeader,0)),"Historical","Forward") -> Historical | D29: GAAP Tax Rate | E29: MO_RIS_TaxRate | F29: Q4-2026 | I29: 0.16 | J29: 0.18 | K29: =AVERAGE(I29:J29) -> 0.17 | M29: =IF(INDEX(MO_SNA_IsHistoricalPeriod,,MATCH(F29,MO_Common_ColumnHeader,0)),"Actual","Estimate") -> Actual | N29: =IFERROR(INDEX(INDIRECT(E29),0,MATCH(F29,MO_Common_ColumnHeader,0)),"N/A") -> 0.14756831 | P29: =IF(ISNUMBER(N29),N29-K29,"N/A") -> -0.022431692 | Q29: =IFERROR(IF(ISNUMBER(N29),(N29-K29)/ABS(K29),"N/A"),"N/A") -> -0.13195113 | S29: 45980 | T29: CFO Commentary
A30: 380 | B30: =IF(INDEX(MO_SNA_IsHistoricalPeriod,,MATCH(F30,MO_Common_ColumnHeader,0)),"Historical","Forward") -> Historical | D30: =INDEX(INDIRECT(E30),0,COLUMN(MO_Common_Column_A)) -> Non-GAAP Tax Rate | E30: MO_RIS_TaxRate_NONGAAP | F30: Q4-2026 | I30: 0.16 | J30: 0.18 | K30: =AVERAGE(I30:J30) -> 0.17 | M30: =IF(INDEX(MO_SNA_IsHistoricalPeriod,,MATCH(F30,MO_Common_ColumnHeader,0)),"Actual","Estimate") -> Actual | N30: =IFERROR(INDEX(INDIRECT(E30),0,MATCH(F30,MO_Common_ColumnHeader,0)),"N/A") -> 0.15355148 | P30: =IF(ISNUMBER(N30),N30-K30,"N/A") -> -0.01644852 | Q30: =IFERROR(IF(ISNUMBER(N30),(N30-K30)/ABS(K30),"N/A"),"N/A") -> -0.096756001 | S30: 45980 | T30: CFO Commentary
A31: 379
A32: 378 | B32: =IF(INDEX(MO_SNA_IsHistoricalPeriod,,MATCH(F32,MO_Common_ColumnHeader,0)),"Historical","Forward") -> Historical | D32: =INDEX(INDIRECT(E32),0,COLUMN(MO_Common_Column_A)) -> Net Revenue | E32: MO_RIS_REV | F32: Q3-2026 | I32: =54000*0.98 -> 52920 | J32: =54000*1.02 -> 55080 | K32: =AVERAGE(I32:J32) -> 54000 | M32: =IF(INDEX(MO_SNA_IsHistoricalPeriod,,MATCH(F32,MO_Common_ColumnHeader,0)),"Actual","Estimate") -> Actual | N32: =IFERROR(INDEX(INDIRECT(E32),0,MATCH(F32,MO_Common_ColumnHeader,0)),"N/A") -> 57006 | P32: =IF(ISNUMBER(N32),N32-K32,"N/A") -> 3006 | Q32: =IFERROR(IF(ISNUMBER(N32),(N32-K32)/ABS(K32),"N/A"),"N/A") -> 0.055666667 | S32: 45896 | T32: CFO Commentary
A33: 377 | B33: =IF(INDEX(MO_SNA_IsHistoricalPeriod,,MATCH(F33,MO_Common_ColumnHeader,0)),"Historical","Forward") -> Historical | D33: =INDEX(INDIRECT(E33),0,COLUMN(MO_Common_Column_A)) -> GAAP Gross Margin, % | E33: MO_MA_GM | F33: Q3-2026 | I33: =73.3%-0.5% -> 0.728 | J33: =73.3%+0.5% -> 0.738 | K33: =AVERAGE(I33:J33) -> 0.733 | M33: =IF(INDEX(MO_SNA_IsHistoricalPeriod,,MATCH(F33,MO_Common_ColumnHeader,0)),"Actual","Estimate") -> Actual | N33: =IFERROR(INDEX(INDIRECT(E33),0,MATCH(F33,MO_Common_ColumnHeader,0)),"N/A") -> 0.73411571 | P33: =IF(ISNUMBER(N33),N33-K33,"N/A") -> 0.0011157071 | Q33: =IFERROR(IF(ISNUMBER(N33),(N33-K33)/ABS(K33),"N/A"),"N/A") -> 0.0015221107 | S33: 45896 | T33: CFO Commentary
A34: 376 | B34: =IF(INDEX(MO_SNA_IsHistoricalPeriod,,MATCH(F34,MO_Common_ColumnHeader,0)),"Historical","Forward") -> Historical | D34: =INDEX(INDIRECT(E34),0,COLUMN(MO_Common_Column_A)) -> Non-GAAP Gross Margin, % | E34: MO_MA_GM_NONGAAP | F34: Q3-2026 | I34: =73.5%-0.5% -> 0.73 | J34: =73.5%+0.5% -> 0.74 | K34: =AVERAGE(I34:J34) -> 0.735 | M34: =IF(INDEX(MO_SNA_IsHistoricalPeriod,,MATCH(F34,MO_Common_ColumnHeader,0)),"Actual","Estimate") -> Actual | N34: =IFERROR(INDEX(INDIRECT(E34),0,MATCH(F34,MO_Common_ColumnHeader,0)),"N/A") -> 0.73618566 | P34: =IF(ISNUMBER(N34),N34-K34,"N/A") -> 0.0011856647 | Q34: =IFERROR(IF(ISNUMBER(N34),(N34-K34)/ABS(K34),"N/A"),"N/A") -> 0.0016131492 | S34: 45896 | T34: CFO Commentary
A35: 375 | B35: =IF(INDEX(MO_SNA_IsHistoricalPeriod,,MATCH(F35,MO_Common_ColumnHeader,0)),"Historical","Forward") -> Historical | D35: GAAP Operating Expenses | F35: Q3-2026 | I35: 5900 | J35: 5900 | K35: =AVERAGE(I35:J35) -> 5900 | M35: =IF(INDEX(MO_SNA_IsHistoricalPeriod,,MATCH(F35,MO_Common_ColumnHeader,0)),"Actual","Estimate") -> Actual | N35: =INDEX(MO_RIS_RD,0,MATCH(F35,MO_Common_ColumnHeader,0))+INDEX(MO_RIS_SGA,0,MATCH(F35,MO_Common_ColumnHeader,0)) -> 5839 | P35: =IF(ISNUMBER(N35),N35-K35,"N/A") -> -61 | Q35: =IFERROR(IF(ISNUMBER(N35),(N35-K35)/ABS(K35),"N/A"),"N/A") -> -0.010338983 | S35: 45896 | T35: CFO Commentary
A36: 374 | B36: =IF(INDEX(MO_SNA_IsHistoricalPeriod,,MATCH(F36,MO_Common_ColumnHeader,0)),"Historical","Forward") -> Historical | D36: =INDEX(INDIRECT(E36),0,COLUMN(MO_Common_Column_A)) -> Total Non-GAAP Operating Expenses, mm | E36: MO_OS_OPEX | F36: Q3-2026 | I36: 4200 | J36: 4200 | K36: =AVERAGE(I36:J36) -> 4200 | M36: =IF(INDEX(MO_SNA_IsHistoricalPeriod,,MATCH(F36,MO_Common_ColumnHeader,0)),"Actual","Estimate") -> Actual | N36: =IFERROR(INDEX(INDIRECT(E36),0,MATCH(F36,MO_Common_ColumnHeader,0)),"N/A") -> 4215 | P36: =IF(ISNUMBER(N36),N36-K36,"N/A") -> 15 | Q36: =IFERROR(IF(ISNUMBER(N36),(N36-K36)/ABS(K36),"N/A"),"N/A") -> 0.0035714286 | S36: 45896 | T36: CFO Commentary
A37: 373 | B37: =IF(INDEX(MO_SNA_IsHistoricalPeriod,,MATCH(F37,MO_Common_ColumnHeader,0)),"Historical","Forward") -> Historical | D37: GAAP Other Income | F37: Q3-2026 | I37: -500 | J37: -500 | K37: =AVERAGE(I37:J37) -> -500 | M37: =IF(INDEX(MO_SNA_IsHistoricalPeriod,,MATCH(F37,MO_Common_ColumnHeader,0)),"Actual","Estimate") -> Actual | N37: =IFERROR(INDEX(INDIRECT(E37),0,MATCH(F37,MO_Common_ColumnHeader,0)),"N/A") -> N/A | P37: =IF(ISNUMBER(N37),N37-K37,"N/A") -> N/A | Q37: =IFERROR(IF(ISNUMBER(N37),(N37-K37)/ABS(K37),"N/A"),"N/A") -> N/A | S37: 45896 | T37: CFO Commentary
A38: 372 | B38: =IF(INDEX(MO_SNA_IsHistoricalPeriod,,MATCH(F38,MO_Common_ColumnHeader,0)),"Historical","Forward") -> Historical | D38: Non-GAAP Other Income | F38: Q3-2026 | I38: -500 | J38: -500 | K38: =AVERAGE(I38:J38) -> -500 | M38: =IF(INDEX(MO_SNA_IsHistoricalPeriod,,MATCH(F38,MO_Common_ColumnHeader,0)),"Actual","Estimate") -> Actual | N38: =INDEX(MO_RIS_IE_Net_NONGAAP,0,MATCH(F38,MO_Common_ColumnHeader,0))+INDEX(MO_RIS_OI_NONGAAP,0,MATCH(F38,MO_Common_ColumnHeader,0)) -> -573 | P38: =IF(ISNUMBER(N38),N38-K38,"N/A") -> -73 | Q38: =IFERROR(IF(ISNUMBER(N38),(N38-K38)/ABS(K38),"N/A"),"N/A") -> -0.146 | S38: 45896 | T38: CFO Commentary
A39: 371 | B39: =IF(INDEX(MO_SNA_IsHistoricalPeriod,,MATCH(F39,MO_Common_ColumnHeader,0)),"Historical","Forward") -> Historical | D39: GAAP Tax Rate | E39: MO_RIS_TaxRate | F39: Q3-2026 | I39: 0.155 | J39: 0.175 | K39: =AVERAGE(I39:J39) -> 0.165 | M39: =IF(INDEX(MO_SNA_IsHistoricalPeriod,,MATCH(F39,MO_Common_ColumnHeader,0)),"Actual","Estimate") -> Actual | N39: =IFERROR(INDEX(INDIRECT(E39),0,MATCH(F39,MO_Common_ColumnHeader,0)),"N/A") -> 0.15884648 | P39: =IF(ISNUMBER(N39),N39-K39,"N/A") -> -0.0061535217 | Q39: =IFERROR(IF(ISNUMBER(N39),(N39-K39)/ABS(K39),"N/A"),"N/A") -> -0.037294071 | S39: 45896 | T39: CFO Commentary
A40: 370 | B40: =IF(INDEX(MO_SNA_IsHistoricalPeriod,,MATCH(F40,MO_Common_ColumnHeader,0)),"Historical","Forward") -> Historical | D40: =INDEX(INDIRECT(E40),0,COLUMN(MO_Common_Column_A)) -> Non-GAAP Tax Rate | E40: MO_RIS_TaxRate_NONGAAP | F40: Q3-2026 | I40: 0.155 | J40: 0.175 | K40: =AVERAGE(I40:J40) -> 0.165 | M40: =IF(INDEX(MO_SNA_IsHistoricalPeriod,,MATCH(F40,MO_Common_ColumnHeader,0)),"Actual","Estimate") -> Actual | N40: =IFERROR(INDEX(INDIRECT(E40),0,MATCH(F40,MO_Common_ColumnHeader,0)),"N/A") -> 0.17111546 | P40: =IF(ISNUMBER(N40),N40-K40,"N/A") -> 0.0061154599 | Q40: =IFERROR(IF(ISNUMBER(N40),(N40-K40)/ABS(K40),"N/A"),"N/A") -> 0.037063393 | S40: 45896 | T40: CFO Commentary
A41: 369
A42: 368 | B42: =IF(INDEX(MO_SNA_IsHistoricalPeriod,,MATCH(F42,MO_Common_ColumnHeader,0)),"Historical","Forward") -> Historical | D42: =INDEX(INDIRECT(E42),0,COLUMN(MO_Common_Column_A)) -> Net Revenue | E42: MO_RIS_REV | F42: Q2-2026 | I42: =45000*0.98 -> 44100 | J42: =45000*1.02 -> 45900 | K42: =AVERAGE(I42:J42) -> 45000 | M42: =IF(INDEX(MO_SNA_IsHistoricalPeriod,,MATCH(F42,MO_Common_ColumnHeader,0)),"Actual","Estimate") -> Actual | N42: =IFERROR(INDEX(INDIRECT(E42),0,MATCH(F42,MO_Common_ColumnHeader,0)),"N/A") -> 46743 | P42: =IF(ISNUMBER(N42),N42-K42,"N/A") -> 1743 | Q42: =IFERROR(IF(ISNUMBER(N42),(N42-K42)/ABS(K42),"N/A"),"N/A") -> 0.038733333 | S42: 45805 | T42: CFO Commentary
A43: 367 | B43: =IF(INDEX(MO_SNA_IsHistoricalPeriod,,MATCH(F43,MO_Common_ColumnHeader,0)),"Historical","Forward") -> Historical | D43: =INDEX(INDIRECT(E43),0,COLUMN(MO_Common_Column_A)) -> GAAP Gross Margin, % | E43: MO_MA_GM | F43: Q2-2026 | I43: 0.713 | J43: 0.723 | K43: =AVERAGE(I43:J43) -> 0.718 | M43: =IF(INDEX(MO_SNA_IsHistoricalPeriod,,MATCH(F43,MO_Common_ColumnHeader,0)),"Actual","Estimate") -> Actual | N43: =IFERROR(INDEX(INDIRECT(E43),0,MATCH(F43,MO_Common_ColumnHeader,0)),"N/A") -> 0.72423678 | P43: =IF(ISNUMBER(N43),N43-K43,"N/A") -> 0.0062367841 | Q43: =IFERROR(IF(ISNUMBER(N43),(N43-K43)/ABS(K43),"N/A"),"N/A") -> 0.0086863289 | S43: 45805 | T43: CFO Commentary
A44: 366 | B44: =IF(INDEX(MO_SNA_IsHistoricalPeriod,,MATCH(F44,MO_Common_ColumnHeader,0)),"Historical","Forward") -> Historical | D44: =INDEX(INDIRECT(E44),0,COLUMN(MO_Common_Column_A)) -> Non-GAAP Gross Margin, % | E44: MO_MA_GM_NONGAAP | F44: Q2-2026 | I44: 0.715 | J44: 0.725 | K44: =AVERAGE(I44:J44) -> 0.72 | M44: =IF(INDEX(MO_SNA_IsHistoricalPeriod,,MATCH(F44,MO_Common_ColumnHeader,0)),"Actual","Estimate") -> Actual | N44: =IFERROR(INDEX(INDIRECT(E44),0,MATCH(F44,MO_Common_ColumnHeader,0)),"N/A") -> 0.7265259 | P44: =IF(ISNUMBER(N44),N44-K44,"N/A") -> 0.0065258969 | Q44: =IFERROR(IF(ISNUMBER(N44),(N44-K44)/ABS(K44),"N/A"),"N/A") -> 0.0090637457 | S44: 45805 | T44: CFO Commentary
A45: 365 | B45: =IF(INDEX(MO_SNA_IsHistoricalPeriod,,MATCH(F45,MO_Common_ColumnHeader,0)),"Historical","Forward") -> Historical | D45: GAAP Operating Expenses | F45: Q2-2026 | I45: 5700 | J45: 5700 | K45: =AVERAGE(I45:J45) -> 5700 | M45: =IF(INDEX(MO_SNA_IsHistoricalPeriod,,MATCH(F45,MO_Common_ColumnHeader,0)),"Actual","Estimate") -> Actual | N45: =INDEX(MO_RIS_RD,0,MATCH(F45,MO_Common_ColumnHeader,0))+INDEX(MO_RIS_SGA,0,MATCH(F45,MO_Common_ColumnHeader,0)) -> 5413 | P45: =IF(ISNUMBER(N45),N45-K45,"N/A") -> -287 | Q45: =IFERROR(IF(ISNUMBER(N45),(N45-K45)/ABS(K45),"N/A"),"N/A") -> -0.050350877 | S45: 45805 | T45: CFO Commentary
A46: 364 | B46: =IF(INDEX(MO_SNA_IsHistoricalPeriod,,MATCH(F46,MO_Common_ColumnHeader,0)),"Historical","Forward") -> Historical | D46: =INDEX(INDIRECT(E46),0,COLUMN(MO_Common_Column_A)) -> Total Non-GAAP Operating Expenses, mm | E46: MO_OS_OPEX | F46: Q2-2026 | I46: 4000 | J46: 4000 | K46: =AVERAGE(I46:J46) -> 4000 | M46: =IF(INDEX(MO_SNA_IsHistoricalPeriod,,MATCH(F46,MO_Common_ColumnHeader,0)),"Actual","Estimate") -> Actual | N46: =IFERROR(INDEX(INDIRECT(E46),0,MATCH(F46,MO_Common_ColumnHeader,0)),"N/A") -> 3795 | P46: =IF(ISNUMBER(N46),N46-K46,"N/A") -> -205 | Q46: =IFERROR(IF(ISNUMBER(N46),(N46-K46)/ABS(K46),"N/A"),"N/A") -> -0.05125 | S46: 45805 | T46: CFO Commentary
A47: 363 | B47: =IF(INDEX(MO_SNA_IsHistoricalPeriod,,MATCH(F47,MO_Common_ColumnHeader,0)),"Historical","Forward") -> Historical | D47: GAAP Other Income | F47: Q2-2026 | I47: -450 | J47: -450 | K47: =AVERAGE(I47:J47) -> -450 | M47: =IF(INDEX(MO_SNA_IsHistoricalPeriod,,MATCH(F47,MO_Common_ColumnHeader,0)),"Actual","Estimate") -> Actual | N47: =IFERROR(INDEX(INDIRECT(E47),0,MATCH(F47,MO_Common_ColumnHeader,0)),"N/A") -> N/A | P47: =IF(ISNUMBER(N47),N47-K47,"N/A") -> N/A | Q47: =IFERROR(IF(ISNUMBER(N47),(N47-K47)/ABS(K47),"N/A"),"N/A") -> N/A | S47: 45805 | T47: CFO Commentary
A48: 362 | B48: =IF(INDEX(MO_SNA_IsHistoricalPeriod,,MATCH(F48,MO_Common_ColumnHeader,0)),"Historical","Forward") -> Historical | D48: Non-GAAP Other Income | F48: Q2-2026 | I48: -450 | J48: -450 | K48: =AVERAGE(I48:J48) -> -450 | M48: =IF(INDEX(MO_SNA_IsHistoricalPeriod,,MATCH(F48,MO_Common_ColumnHeader,0)),"Actual","Estimate") -> Actual | N48: =INDEX(MO_RIS_IE_Net_NONGAAP,0,MATCH(F48,MO_Common_ColumnHeader,0))+INDEX(MO_RIS_OI_NONGAAP,0,MATCH(F48,MO_Common_ColumnHeader,0)) -> -520 | P48: =IF(ISNUMBER(N48),N48-K48,"N/A") -> -70 | Q48: =IFERROR(IF(ISNUMBER(N48),(N48-K48)/ABS(K48),"N/A"),"N/A") -> -0.15555556 | S48: 45805 | T48: CFO Commentary
A49: 361 | B49: =IF(INDEX(MO_SNA_IsHistoricalPeriod,,MATCH(F49,MO_Common_ColumnHeader,0)),"Historical","Forward") -> Historical | D49: GAAP Tax Rate | E49: MO_RIS_TaxRate | F49: Q2-2026 | I49: 0.155 | J49: 0.175 | K49: =AVERAGE(I49:J49) -> 0.165 | M49: =IF(INDEX(MO_SNA_IsHistoricalPeriod,,MATCH(F49,MO_Common_ColumnHeader,0)),"Actual","Estimate") -> Actual | N49: =IFERROR(INDEX(INDIRECT(E49),0,MATCH(F49,MO_Common_ColumnHeader,0)),"N/A") -> 0.15330385 | P49: =IF(ISNUMBER(N49),N49-K49,"N/A") -> -0.011696148 | Q49: =IFERROR(IF(ISNUMBER(N49),(N49-K49)/ABS(K49),"N/A"),"N/A") -> -0.070885747 | S49: 45805 | T49: CFO Commentary
A50: 360 | B50: =IF(INDEX(MO_SNA_IsHistoricalPeriod,,MATCH(F50,MO_Common_ColumnHeader,0)),"Historical","Forward") -> Historical | D50: =INDEX(INDIRECT(E50),0,COLUMN(MO_Common_Column_A)) -> Non-GAAP Tax Rate | E50: MO_RIS_TaxRate_NONGAAP | F50: Q2-2026 | I50: 0.155 | J50: 0.175 | K50: =AVERAGE(I50:J50) -> 0.165 | M50: =IF(INDEX(MO_SNA_IsHistoricalPeriod,,MATCH(F50,MO_Common_ColumnHeader,0)),"Actual","Estimate") -> Actual | N50: =IFERROR(INDEX(INDIRECT(E50),0,MATCH(F50,MO_Common_ColumnHeader,0)),"N/A") -> 0.15975232 | P50: =IF(ISNUMBER(N50),N50-K50,"N/A") -> -0.005247678 | Q50: =IFERROR(IF(ISNUMBER(N50),(N50-K50)/ABS(K50),"N/A"),"N/A") -> -0.031804109 | S50: 45805 | T50: CFO Commentary
A51: 359
A52: 358 | B52: =IF(INDEX(MO_SNA_IsHistoricalPeriod,,MATCH(F52,MO_Common_ColumnHeader,0)),"Historical","Forward") -> Historical | D52: =INDEX(INDIRECT(E52),0,COLUMN(MO_Common_Column_A)) -> Net Revenue | E52: MO_RIS_REV | F52: Q1-2026 | I52: =43000*0.98 -> 42140 | J52: =43000*1.02 -> 43860 | K52: =AVERAGE(I52:J52) -> 43000 | M52: =IF(INDEX(MO_SNA_IsHistoricalPeriod,,MATCH(F52,MO_Common_ColumnHeader,0)),"Actual","Estimate") -> Actual | N52: =IFERROR(INDEX(INDIRECT(E52),0,MATCH(F52,MO_Common_ColumnHeader,0)),"N/A") -> 44062 | P52: =IF(ISNUMBER(N52),N52-K52,"N/A") -> 1062 | Q52: =IFERROR(IF(ISNUMBER(N52),(N52-K52)/ABS(K52),"N/A"),"N/A") -> 0.024697674 | S52: 45714 | T52: CFO Commentary
A53: 357 | B53: =IF(INDEX(MO_SNA_IsHistoricalPeriod,,MATCH(F53,MO_Common_ColumnHeader,0)),"Historical","Forward") -> Historical | D53: =INDEX(INDIRECT(E53),0,COLUMN(MO_Common_Column_A)) -> GAAP Gross Margin, % | E53: MO_MA_GM | F53: Q1-2026 | I53: =70.6%-0.5% -> 0.701 | J53: =70.6%+0.5% -> 0.711 | K53: =AVERAGE(I53:J53) -> 0.706 | M53: =IF(INDEX(MO_SNA_IsHistoricalPeriod,,MATCH(F53,MO_Common_ColumnHeader,0)),"Actual","Estimate") -> Actual | N53: =IFERROR(INDEX(INDIRECT(E53),0,MATCH(F53,MO_Common_ColumnHeader,0)),"N/A") -> 0.60523807 | P53: =IF(ISNUMBER(N53),N53-K53,"N/A") -> -0.10076193 | Q53: =IFERROR(IF(ISNUMBER(N53),(N53-K53)/ABS(K53),"N/A"),"N/A") -> -0.14272228 | S53: 45714 | T53: CFO Commentary
A54: 356 | B54: =IF(INDEX(MO_SNA_IsHistoricalPeriod,,MATCH(F54,MO_Common_ColumnHeader,0)),"Historical","Forward") -> Historical | D54: =INDEX(INDIRECT(E54),0,COLUMN(MO_Common_Column_A)) -> Non-GAAP Gross Margin, % | E54: MO_MA_GM_NONGAAP | F54: Q1-2026 | I54: =71%-0.5% -> 0.705 | J54: =71%+0.5% -> 0.715 | K54: =AVERAGE(I54:J54) -> 0.71 | M54: =IF(INDEX(MO_SNA_IsHistoricalPeriod,,MATCH(F54,MO_Common_ColumnHeader,0)),"Actual","Estimate") -> Actual | N54: =IFERROR(INDEX(INDIRECT(E54),0,MATCH(F54,MO_Common_ColumnHeader,0)),"N/A") -> 0.60955018 | P54: =IF(ISNUMBER(N54),N54-K54,"N/A") -> -0.10044982 | Q54: =IFERROR(IF(ISNUMBER(N54),(N54-K54)/ABS(K54),"N/A"),"N/A") -> -0.14147862 | S54: 45714 | T54: CFO Commentary
A55: 355 | B55: =IF(INDEX(MO_SNA_IsHistoricalPeriod,,MATCH(F55,MO_Common_ColumnHeader,0)),"Historical","Forward") -> Historical | D55: GAAP Operating Expenses | F55: Q1-2026 | I55: 5200 | J55: 5200 | K55: =AVERAGE(I55:J55) -> 5200 | M55: =IF(INDEX(MO_SNA_IsHistoricalPeriod,,MATCH(F55,MO_Common_ColumnHeader,0)),"Actual","Estimate") -> Actual | N55: =INDEX(MO_RIS_RD,0,MATCH(F55,MO_Common_ColumnHeader,0))+INDEX(MO_RIS_SGA,0,MATCH(F55,MO_Common_ColumnHeader,0)) -> 5030 | P55: =IF(ISNUMBER(N55),N55-K55,"N/A") -> -170 | Q55: =IFERROR(IF(ISNUMBER(N55),(N55-K55)/ABS(K55),"N/A"),"N/A") -> -0.032692308 | S55: 45714 | T55: CFO Commentary
A56: 354 | B56: =IF(INDEX(MO_SNA_IsHistoricalPeriod,,MATCH(F56,MO_Common_ColumnHeader,0)),"Historical","Forward") -> Historical | D56: =INDEX(INDIRECT(E56),0,COLUMN(MO_Common_Column_A)) -> Total Non-GAAP Operating Expenses, mm | E56: MO_OS_OPEX | F56: Q1-2026 | I56: 3600 | J56: 3600 | K56: =AVERAGE(I56:J56) -> 3600 | M56: =IF(INDEX(MO_SNA_IsHistoricalPeriod,,MATCH(F56,MO_Common_ColumnHeader,0)),"Actual","Estimate") -> Actual | N56: =IFERROR(INDEX(INDIRECT(E56),0,MATCH(F56,MO_Common_ColumnHeader,0)),"N/A") -> 3583 | P56: =IF(ISNUMBER(N56),N56-K56,"N/A") -> -17 | Q56: =IFERROR(IF(ISNUMBER(N56),(N56-K56)/ABS(K56),"N/A"),"N/A") -> -0.0047222222 | S56: 45714 | T56: CFO Commentary
A57: 353 | B57: =IF(INDEX(MO_SNA_IsHistoricalPeriod,,MATCH(F57,MO_Common_ColumnHeader,0)),"Historical","Forward") -> Historical | D57: GAAP Other Income | F57: Q1-2026 | I57: -400 | J57: -400 | K57: =AVERAGE(I57:J57) -> -400 | M57: =IF(INDEX(MO_SNA_IsHistoricalPeriod,,MATCH(F57,MO_Common_ColumnHeader,0)),"Actual","Estimate") -> Actual | N57: =IFERROR(INDEX(INDIRECT(E57),0,MATCH(F57,MO_Common_ColumnHeader,0)),"N/A") -> N/A | P57: =IF(ISNUMBER(N57),N57-K57,"N/A") -> N/A | Q57: =IFERROR(IF(ISNUMBER(N57),(N57-K57)/ABS(K57),"N/A"),"N/A") -> N/A | S57: 45714 | T57: CFO Commentary
A58: 352 | B58: =IF(INDEX(MO_SNA_IsHistoricalPeriod,,MATCH(F58,MO_Common_ColumnHeader,0)),"Historical","Forward") -> Historical | D58: Non-GAAP Other Income | F58: Q1-2026 | I58: -400 | J58: -400 | K58: =AVERAGE(I58:J58) -> -400 | M58: =IF(INDEX(MO_SNA_IsHistoricalPeriod,,MATCH(F58,MO_Common_ColumnHeader,0)),"Actual","Estimate") -> Actual | N58: =INDEX(MO_RIS_IE_Net_NONGAAP,0,MATCH(F58,MO_Common_ColumnHeader,0))+INDEX(MO_RIS_OI_NONGAAP,0,MATCH(F58,MO_Common_ColumnHeader,0)) -> -448 | P58: =IF(ISNUMBER(N58),N58-K58,"N/A") -> -48 | Q58: =IFERROR(IF(ISNUMBER(N58),(N58-K58)/ABS(K58),"N/A"),"N/A") -> -0.12 | S58: 45714 | T58: CFO Commentary
A59: 351 | B59: =IF(INDEX(MO_SNA_IsHistoricalPeriod,,MATCH(F59,MO_Common_ColumnHeader,0)),"Historical","Forward") -> Historical | D59: GAAP Tax Rate | E59: MO_RIS_TaxRate | F59: Q1-2026 | I59: 0.16 | J59: 0.18 | K59: =AVERAGE(I59:J59) -> 0.17 | M59: =IF(INDEX(MO_SNA_IsHistoricalPeriod,,MATCH(F59,MO_Common_ColumnHeader,0)),"Actual","Estimate") -> Actual | N59: =IFERROR(INDEX(INDIRECT(E59),0,MATCH(F59,MO_Common_ColumnHeader,0)),"N/A") -> 0.14308535 | P59: =IF(ISNUMBER(N59),N59-K59,"N/A") -> -0.026914651 | Q59: =IFERROR(IF(ISNUMBER(N59),(N59-K59)/ABS(K59),"N/A"),"N/A") -> -0.15832148 | S59: 45714 | T59: CFO Commentary
A60: 350 | B60: =IF(INDEX(MO_SNA_IsHistoricalPeriod,,MATCH(F60,MO_Common_ColumnHeader,0)),"Historical","Forward") -> Historical | D60: =INDEX(INDIRECT(E60),0,COLUMN(MO_Common_Column_A)) -> Non-GAAP Tax Rate | E60: MO_RIS_TaxRate_NONGAAP | F60: Q1-2026 | I60: 0.16 | J60: 0.18 | K60: =AVERAGE(I60:J60) -> 0.17 | M60: =IF(INDEX(MO_SNA_IsHistoricalPeriod,,MATCH(F60,MO_Common_ColumnHeader,0)),"Actual","Estimate") -> Actual | N60: =IFERROR(INDEX(INDIRECT(E60),0,MATCH(F60,MO_Common_ColumnHeader,0)),"N/A") -> 0.16140454 | P60: =IF(ISNUMBER(N60),N60-K60,"N/A") -> -0.0085954559 | Q60: =IFERROR(IF(ISNUMBER(N60),(N60-K60)/ABS(K60),"N/A"),"N/A") -> -0.050561505 | S60: 45714 | T60: CFO Commentary
A61: 349
A62: 348 | B62: =IF(INDEX(MO_SNA_IsHistoricalPeriod,,MATCH(F62,MO_Common_ColumnHeader,0)),"Historical","Forward") -> Historical | D62: =INDEX(INDIRECT(E62),0,COLUMN(MO_Common_Column_A)) -> Net Revenue | E62: MO_RIS_REV | F62: Q4-2025 | I62: =37500*(1-2%) -> 36750 | J62: =37500*(1+2%) -> 38250 | K62: =AVERAGE(I62:J62) -> 37500 | M62: =IF(INDEX(MO_SNA_IsHistoricalPeriod,,MATCH(F62,MO_Common_ColumnHeader,0)),"Actual","Estimate") -> Actual | N62: =IFERROR(INDEX(INDIRECT(E62),0,MATCH(F62,MO_Common_ColumnHeader,0)),"N/A") -> 39331 | P62: =IF(ISNUMBER(N62),N62-K62,"N/A") -> 1831 | Q62: =IFERROR(IF(ISNUMBER(N62),(N62-K62)/ABS(K62),"N/A"),"N/A") -> 0.048826667 | S62: 45616 | T62: CFO Commentary
A63: 347 | B63: =IF(INDEX(MO_SNA_IsHistoricalPeriod,,MATCH(F63,MO_Common_ColumnHeader,0)),"Historical","Forward") -> Historical | D63: =INDEX(INDIRECT(E63),0,COLUMN(MO_Common_Column_A)) -> GAAP Gross Margin, % | E63: MO_MA_GM | F63: Q4-2025 | I63: 0.725 | J63: 0.735 | K63: =AVERAGE(I63:J63) -> 0.73 | M63: =IF(INDEX(MO_SNA_IsHistoricalPeriod,,MATCH(F63,MO_Common_ColumnHeader,0)),"Actual","Estimate") -> Actual | N63: =IFERROR(INDEX(INDIRECT(E63),0,MATCH(F63,MO_Common_ColumnHeader,0)),"N/A") -> 0.73028908 | P63: =IF(ISNUMBER(N63),N63-K63,"N/A") -> 0.00028908495 | Q63: =IFERROR(IF(ISNUMBER(N63),(N63-K63)/ABS(K63),"N/A"),"N/A") -> 0.00039600677 | S63: 45616 | T63: CFO Commentary
A64: 346 | B64: =IF(INDEX(MO_SNA_IsHistoricalPeriod,,MATCH(F64,MO_Common_ColumnHeader,0)),"Historical","Forward") -> Historical | D64: =INDEX(INDIRECT(E64),0,COLUMN(MO_Common_Column_A)) -> Non-GAAP Gross Margin, % | E64: MO_MA_GM_NONGAAP | F64: Q4-2025 | I64: 0.73 | J64: 0.74 | K64: =AVERAGE(I64:J64) -> 0.735 | M64: =IF(INDEX(MO_SNA_IsHistoricalPeriod,,MATCH(F64,MO_Common_ColumnHeader,0)),"Actual","Estimate") -> Actual | N64: =IFERROR(INDEX(INDIRECT(E64),0,MATCH(F64,MO_Common_ColumnHeader,0)),"N/A") -> 0.7346368 | P64: =IF(ISNUMBER(N64),N64-K64,"N/A") -> -0.00036319951 | Q64: =IFERROR(IF(ISNUMBER(N64),(N64-K64)/ABS(K64),"N/A"),"N/A") -> -0.000494149 | S64: 45616 | T64: CFO Commentary
A65: 345 | B65: =IF(INDEX(MO_SNA_IsHistoricalPeriod,,MATCH(F65,MO_Common_ColumnHeader,0)),"Historical","Forward") -> Historical | D65: GAAP Operating Expenses | F65: Q4-2025 | I65: 4750 | J65: 4750 | K65: =AVERAGE(I65:J65) -> 4750 | M65: =IF(INDEX(MO_SNA_IsHistoricalPeriod,,MATCH(F65,MO_Common_ColumnHeader,0)),"Actual","Estimate") -> Actual | N65: =INDEX(MO_RIS_RD,0,MATCH(F65,MO_Common_ColumnHeader,0))+INDEX(MO_RIS_SGA,0,MATCH(F65,MO_Common_ColumnHeader,0)) -> 4689 | P65: =IF(ISNUMBER(N65),N65-K65,"N/A") -> -61 | Q65: =IFERROR(IF(ISNUMBER(N65),(N65-K65)/ABS(K65),"N/A"),"N/A") -> -0.012842105 | S65: 45616 | T65: CFO Commentary
A66: 344 | B66: =IF(INDEX(MO_SNA_IsHistoricalPeriod,,MATCH(F66,MO_Common_ColumnHeader,0)),"Historical","Forward") -> Historical | D66: =INDEX(INDIRECT(E66),0,COLUMN(MO_Common_Column_A)) -> Total Non-GAAP Operating Expenses, mm | E66: MO_OS_OPEX | F66: Q4-2025 | I66: 3400 | J66: 3400 | K66: =AVERAGE(I66:J66) -> 3400 | M66: =IF(INDEX(MO_SNA_IsHistoricalPeriod,,MATCH(F66,MO_Common_ColumnHeader,0)),"Actual","Estimate") -> Actual | N66: =IFERROR(INDEX(INDIRECT(E66),0,MATCH(F66,MO_Common_ColumnHeader,0)),"N/A") -> 3378 | P66: =IF(ISNUMBER(N66),N66-K66,"N/A") -> -22 | Q66: =IFERROR(IF(ISNUMBER(N66),(N66-K66)/ABS(K66),"N/A"),"N/A") -> -0.0064705882 | S66: 45616 | T66: CFO Commentary
A67: 343 | B67: =IF(INDEX(MO_SNA_IsHistoricalPeriod,,MATCH(F67,MO_Common_ColumnHeader,0)),"Historical","Forward") -> Historical | D67: GAAP Other Income | F67: Q4-2025 | I67: -400 | J67: -400 | K67: =AVERAGE(I67:J67) -> -400 | M67: =IF(INDEX(MO_SNA_IsHistoricalPeriod,,MATCH(F67,MO_Common_ColumnHeader,0)),"Actual","Estimate") -> Actual | N67: =IFERROR(INDEX(INDIRECT(E67),0,MATCH(F67,MO_Common_ColumnHeader,0)),"N/A") -> N/A | P67: =IF(ISNUMBER(N67),N67-K67,"N/A") -> N/A | Q67: =IFERROR(IF(ISNUMBER(N67),(N67-K67)/ABS(K67),"N/A"),"N/A") -> N/A | S67: 45616 | T67: CFO Commentary
A68: 342 | B68: =IF(INDEX(MO_SNA_IsHistoricalPeriod,,MATCH(F68,MO_Common_ColumnHeader,0)),"Historical","Forward") -> Historical | D68: Non-GAAP Other Income | F68: Q4-2025 | I68: -400 | J68: -400 | K68: =AVERAGE(I68:J68) -> -400 | M68: =IF(INDEX(MO_SNA_IsHistoricalPeriod,,MATCH(F68,MO_Common_ColumnHeader,0)),"Actual","Estimate") -> Actual | N68: =INDEX(MO_RIS_IE_Net_NONGAAP,0,MATCH(F68,MO_Common_ColumnHeader,0))+INDEX(MO_RIS_OI_NONGAAP,0,MATCH(F68,MO_Common_ColumnHeader,0)) -> -457 | P68: =IF(ISNUMBER(N68),N68-K68,"N/A") -> -57 | Q68: =IFERROR(IF(ISNUMBER(N68),(N68-K68)/ABS(K68),"N/A"),"N/A") -> -0.1425 | S68: 45616 | T68: CFO Commentary
A69: 341 | B69: =IF(INDEX(MO_SNA_IsHistoricalPeriod,,MATCH(F69,MO_Common_ColumnHeader,0)),"Historical","Forward") -> Historical | D69: GAAP Tax Rate | E69: MO_RIS_TaxRate | F69: Q4-2025 | I69: 0.155 | J69: 0.175 | K69: =AVERAGE(I69:J69) -> 0.165 | M69: =IF(INDEX(MO_SNA_IsHistoricalPeriod,,MATCH(F69,MO_Common_ColumnHeader,0)),"Actual","Estimate") -> Actual | N69: =IFERROR(INDEX(INDIRECT(E69),0,MATCH(F69,MO_Common_ColumnHeader,0)),"N/A") -> 0.12396399 | P69: =IF(ISNUMBER(N69),N69-K69,"N/A") -> -0.041036007 | Q69: =IFERROR(IF(ISNUMBER(N69),(N69-K69)/ABS(K69),"N/A"),"N/A") -> -0.24870308 | S69: 45616 | T69: CFO Commentary
A70: 340 | B70: =IF(INDEX(MO_SNA_IsHistoricalPeriod,,MATCH(F70,MO_Common_ColumnHeader,0)),"Historical","Forward") -> Historical | D70: =INDEX(INDIRECT(E70),0,COLUMN(MO_Common_Column_A)) -> Non-GAAP Tax Rate | E70: MO_RIS_TaxRate_NONGAAP | F70: Q4-2025 | I70: 0.155 | J70: 0.175 | K70: =AVERAGE(I70:J70) -> 0.165 | M70: =IF(INDEX(MO_SNA_IsHistoricalPeriod,,MATCH(F70,MO_Common_ColumnHeader,0)),"Actual","Estimate") -> Actual | N70: =IFERROR(INDEX(INDIRECT(E70),0,MATCH(F70,MO_Common_ColumnHeader,0)),"N/A") -> 0.15042544 | P70: =IF(ISNUMBER(N70),N70-K70,"N/A") -> -0.014574558 | Q70: =IFERROR(IF(ISNUMBER(N70),(N70-K70)/ABS(K70),"N/A"),"N/A") -> -0.088330656 | S70: 45616 | T70: CFO Commentary
A71: 339
A72: 338 | B72: =IF(INDEX(MO_SNA_IsHistoricalPeriod,,MATCH(F72,MO_Common_ColumnHeader,0)),"Historical","Forward") -> Historical | D72: =INDEX(INDIRECT(E72),0,COLUMN(MO_Common_Column_A)) -> GAAP Gross Margin, % | E72: MO_MA_GM | F72: FY2025 | I72: 0.74 | J72: 0.76 | K72: =AVERAGE(I72:J72) -> 0.75 | M72: =IF(INDEX(MO_SNA_IsHistoricalPeriod,,MATCH(F72,MO_Common_ColumnHeader,0)),"Actual","Estimate") -> Actual | N72: =IFERROR(INDEX(INDIRECT(E72),0,MATCH(F72,MO_Common_ColumnHeader,0)),"N/A") -> 0.74988697 | P72: =IF(ISNUMBER(N72),N72-K72,"N/A") -> -0.00011302942 | Q72: =IFERROR(IF(ISNUMBER(N72),(N72-K72)/ABS(K72),"N/A"),"N/A") -> -0.00015070589 | S72: 45532 | T72: CFO Commentary
A73: 337 | B73: =IF(INDEX(MO_SNA_IsHistoricalPeriod,,MATCH(F73,MO_Common_ColumnHeader,0)),"Historical","Forward") -> Historical | D73: =INDEX(INDIRECT(E73),0,COLUMN(MO_Common_Column_A)) -> Non-GAAP Gross Margin, % | E73: MO_MA_GM_NONGAAP | F73: FY2025 | I73: 0.74 | J73: 0.76 | K73: =AVERAGE(I73:J73) -> 0.75 | M73: =IF(INDEX(MO_SNA_IsHistoricalPeriod,,MATCH(F73,MO_Common_ColumnHeader,0)),"Actual","Estimate") -> Actual | N73: =IFERROR(INDEX(INDIRECT(E73),0,MATCH(F73,MO_Common_ColumnHeader,0)),"N/A") -> 0.75484494 | P73: =IF(ISNUMBER(N73),N73-K73,"N/A") -> 0.004844939 | Q73: =IFERROR(IF(ISNUMBER(N73),(N73-K73)/ABS(K73),"N/A"),"N/A") -> 0.0064599186 | S73: 45532 | T73: CFO Commentary
A74: 336 | B74: =IF(INDEX(MO_SNA_IsHistoricalPeriod,,MATCH(F74,MO_Common_ColumnHeader,0)),"Historical","Forward") -> Historical | D74: GAAP Operating Expenses | F74: FY2025 | G74: FY2024 | I74: 0.44 | J74: 0.49 | K74: =AVERAGE(I74:J74) -> 0.465 | M74: =IF(INDEX(MO_SNA_IsHistoricalPeriod,,MATCH(F74,MO_Common_ColumnHeader,0)),"Actual","Estimate") -> Actual | N74: =(INDEX(MO_RIS_RD,0,MATCH(F74,MO_Common_ColumnHeader,0))+INDEX(MO_RIS_SGA,0,MATCH(F74,MO_Common_ColumnHeader,0)))/(INDEX(MO_RIS_RD,0,MATCH(G74,MO_Common_ColumnHeader,0))+INDEX(MO_RIS_SGA,0,MATCH(G74,MO_Common_ColumnHeader,0)))-1 -> 0.44805367 | P74: =IF(ISNUMBER(N74),N74-K74,"N/A") -> -0.016946332 | Q74: =IFERROR(IF(ISNUMBER(N74),(N74-K74)/ABS(K74),"N/A"),"N/A") -> -0.036443726 | S74: 45532 | T74: CFO Commentary
A75: 335 | B75: =IF(INDEX(MO_SNA_IsHistoricalPeriod,,MATCH(F75,MO_Common_ColumnHeader,0)),"Historical","Forward") -> Historical | D75: =INDEX(INDIRECT(E75),0,COLUMN(MO_Common_Column_A)) -> Total Non-GAAP Operating Expenses, mm | E75: MO_OS_OPEX | F75: FY2025 | G75: FY2024 | I75: 0.44 | J75: 0.49 | K75: =AVERAGE(I75:J75) -> 0.465 | M75: =IF(INDEX(MO_SNA_IsHistoricalPeriod,,MATCH(F75,MO_Common_ColumnHeader,0)),"Actual","Estimate") -> Actual | N75: =(INDEX(MO_RIS_RD,0,MATCH(F75,MO_Common_ColumnHeader,0))+INDEX(MO_RIS_SGA,0,MATCH(F75,MO_Common_ColumnHeader,0)))/(INDEX(MO_RIS_RD,0,MATCH(G75,MO_Common_ColumnHeader,0))+INDEX(MO_RIS_SGA,0,MATCH(G75,MO_Common_ColumnHeader,0)))-1 -> 0.44805367 | P75: =IF(ISNUMBER(N75),N75-K75,"N/A") -> -0.016946332 | Q75: =IFERROR(IF(ISNUMBER(N75),(N75-K75)/ABS(K75),"N/A"),"N/A") -> -0.036443726 | S75: 45532 | T75: CFO Commentary
A76: 334
A77: 333 | B77: =IF(INDEX(MO_SNA_IsHistoricalPeriod,,MATCH(F77,MO_Common_ColumnHeader,0)),"Historical","Forward") -> Historical | D77: =INDEX(INDIRECT(E77),0,COLUMN(MO_Common_Column_A)) -> Net Revenue | E77: MO_RIS_REV | F77: Q3-2025 | I77: 31850 | J77: 33150 | K77: =AVERAGE(I77:J77) -> 32500 | M77: =IF(INDEX(MO_SNA_IsHistoricalPeriod,,MATCH(F77,MO_Common_ColumnHeader,0)),"Actual","Estimate") -> Actual | N77: =IFERROR(INDEX(INDIRECT(E77),0,MATCH(F77,MO_Common_ColumnHeader,0)),"N/A") -> 35082 | P77: =IF(ISNUMBER(N77),N77-K77,"N/A") -> 2582 | Q77: =IFERROR(IF(ISNUMBER(N77),(N77-K77)/ABS(K77),"N/A"),"N/A") -> 0.079446154 | S77: 45532 | T77: CFO Commentary
A78: 332 | B78: =IF(INDEX(MO_SNA_IsHistoricalPeriod,,MATCH(F78,MO_Common_ColumnHeader,0)),"Historical","Forward") -> Historical | D78: =INDEX(INDIRECT(E78),0,COLUMN(MO_Common_Column_A)) -> GAAP Gross Margin, % | E78: MO_MA_GM | F78: Q3-2025 | I78: 0.739 | J78: 0.749 | K78: =AVERAGE(I78:J78) -> 0.744 | M78: =IF(INDEX(MO_SNA_IsHistoricalPeriod,,MATCH(F78,MO_Common_ColumnHeader,0)),"Actual","Estimate") -> Actual | N78: =IFERROR(INDEX(INDIRECT(E78),0,MATCH(F78,MO_Common_ColumnHeader,0)),"N/A") -> 0.74556753 | P78: =IF(ISNUMBER(N78),N78-K78,"N/A") -> 0.0015675275 | Q78: =IFERROR(IF(ISNUMBER(N78),(N78-K78)/ABS(K78),"N/A"),"N/A") -> 0.0021068918 | S78: 45532 | T78: CFO Commentary
A79: 331 | B79: =IF(INDEX(MO_SNA_IsHistoricalPeriod,,MATCH(F79,MO_Common_ColumnHeader,0)),"Historical","Forward") -> Historical | D79: =INDEX(INDIRECT(E79),0,COLUMN(MO_Common_Column_A)) -> Non-GAAP Gross Margin, % | E79: MO_MA_GM_NONGAAP | F79: Q3-2025 | I79: 0.745 | J79: 0.755 | K79: =AVERAGE(I79:J79) -> 0.75 | M79: =IF(INDEX(MO_SNA_IsHistoricalPeriod,,MATCH(F79,MO_Common_ColumnHeader,0)),"Actual","Estimate") -> Actual | N79: =IFERROR(INDEX(INDIRECT(E79),0,MATCH(F79,MO_Common_ColumnHeader,0)),"N/A") -> 0.7502993 | P79: =IF(ISNUMBER(N79),N79-K79,"N/A") -> 0.00029929879 | Q79: =IFERROR(IF(ISNUMBER(N79),(N79-K79)/ABS(K79),"N/A"),"N/A") -> 0.00039906505 | S79: 45532 | T79: CFO Commentary
A80: 330 | B80: =IF(INDEX(MO_SNA_IsHistoricalPeriod,,MATCH(F80,MO_Common_ColumnHeader,0)),"Historical","Forward") -> Historical | D80: GAAP Operating Expenses | F80: Q3-2025 | I80: 4300 | J80: 4300 | K80: =AVERAGE(I80:J80) -> 4300 | M80: =IF(INDEX(MO_SNA_IsHistoricalPeriod,,MATCH(F80,MO_Common_ColumnHeader,0)),"Actual","Estimate") -> Actual | N80: =INDEX(MO_RIS_RD,0,MATCH(F80,MO_Common_ColumnHeader,0))+INDEX(MO_RIS_SGA,0,MATCH(F80,MO_Common_ColumnHeader,0)) -> 4287 | P80: =IF(ISNUMBER(N80),N80-K80,"N/A") -> -13 | Q80: =IFERROR(IF(ISNUMBER(N80),(N80-K80)/ABS(K80),"N/A"),"N/A") -> -0.0030232558 | S80: 45532 | T80: CFO Commentary
A81: 329 | B81: =IF(INDEX(MO_SNA_IsHistoricalPeriod,,MATCH(F81,MO_Common_ColumnHeader,0)),"Historical","Forward") -> Historical | D81: =INDEX(INDIRECT(E81),0,COLUMN(MO_Common_Column_A)) -> Total Non-GAAP Operating Expenses, mm | E81: MO_OS_OPEX | F81: Q3-2025 | I81: 3000 | J81: 3000 | K81: =AVERAGE(I81:J81) -> 3000 | M81: =IF(INDEX(MO_SNA_IsHistoricalPeriod,,MATCH(F81,MO_Common_ColumnHeader,0)),"Actual","Estimate") -> Actual | N81: =IFERROR(INDEX(INDIRECT(E81),0,MATCH(F81,MO_Common_ColumnHeader,0)),"N/A") -> 3046 | P81: =IF(ISNUMBER(N81),N81-K81,"N/A") -> 46 | Q81: =IFERROR(IF(ISNUMBER(N81),(N81-K81)/ABS(K81),"N/A"),"N/A") -> 0.015333333 | S81: 45532 | T81: CFO Commentary
A82: 328 | B82: =IF(INDEX(MO_SNA_IsHistoricalPeriod,,MATCH(F82,MO_Common_ColumnHeader,0)),"Historical","Forward") -> Historical | D82: GAAP Other Income | F82: Q3-2025 | I82: -350 | J82: -350 | K82: =AVERAGE(I82:J82) -> -350 | M82: =IF(INDEX(MO_SNA_IsHistoricalPeriod,,MATCH(F82,MO_Common_ColumnHeader,0)),"Actual","Estimate") -> Actual | N82: =IFERROR(INDEX(INDIRECT(E82),0,MATCH(F82,MO_Common_ColumnHeader,0)),"N/A") -> N/A | P82: =IF(ISNUMBER(N82),N82-K82,"N/A") -> N/A | Q82: =IFERROR(IF(ISNUMBER(N82),(N82-K82)/ABS(K82),"N/A"),"N/A") -> N/A | S82: 45532 | T82: CFO Commentary
A83: 327 | B83: =IF(INDEX(MO_SNA_IsHistoricalPeriod,,MATCH(F83,MO_Common_ColumnHeader,0)),"Historical","Forward") -> Historical | D83: Non-GAAP Other Income | F83: Q3-2025 | I83: -350 | J83: -350 | K83: =AVERAGE(I83:J83) -> -350 | M83: =IF(INDEX(MO_SNA_IsHistoricalPeriod,,MATCH(F83,MO_Common_ColumnHeader,0)),"Actual","Estimate") -> Actual | N83: =INDEX(MO_RIS_IE_Net_NONGAAP,0,MATCH(F83,MO_Common_ColumnHeader,0))+INDEX(MO_RIS_OI_NONGAAP,0,MATCH(F83,MO_Common_ColumnHeader,0)) -> -411 | P83: =IF(ISNUMBER(N83),N83-K83,"N/A") -> -61 | Q83: =IFERROR(IF(ISNUMBER(N83),(N83-K83)/ABS(K83),"N/A"),"N/A") -> -0.17428571 | S83: 45532 | T83: CFO Commentary
A84: 326 | B84: =IF(INDEX(MO_SNA_IsHistoricalPeriod,,MATCH(F84,MO_Common_ColumnHeader,0)),"Historical","Forward") -> Historical | D84: GAAP Tax Rate | E84: MO_RIS_TaxRate | F84: Q3-2025 | I84: 0.16 | J84: 0.18 | K84: =AVERAGE(I84:J84) -> 0.17 | M84: =IF(INDEX(MO_SNA_IsHistoricalPeriod,,MATCH(F84,MO_Common_ColumnHeader,0)),"Actual","Estimate") -> Actual | N84: =IFERROR(INDEX(INDIRECT(E84),0,MATCH(F84,MO_Common_ColumnHeader,0)),"N/A") -> 0.13474637 | P84: =IF(ISNUMBER(N84),N84-K84,"N/A") -> -0.03525363 | Q84: =IFERROR(IF(ISNUMBER(N84),(N84-K84)/ABS(K84),"N/A"),"N/A") -> -0.20737429 | S84: 45532 | T84: CFO Commentary
A85: 325 | B85: =IF(INDEX(MO_SNA_IsHistoricalPeriod,,MATCH(F85,MO_Common_ColumnHeader,0)),"Historical","Forward") -> Historical | D85: =INDEX(INDIRECT(E85),0,COLUMN(MO_Common_Column_A)) -> Non-GAAP Tax Rate | E85: MO_RIS_TaxRate_NONGAAP | F85: Q3-2025 | I85: 0.16 | J85: 0.18 | K85: =AVERAGE(I85:J85) -> 0.17 | M85: =IF(INDEX(MO_SNA_IsHistoricalPeriod,,MATCH(F85,MO_Common_ColumnHeader,0)),"Actual","Estimate") -> Actual | N85: =IFERROR(INDEX(INDIRECT(E85),0,MATCH(F85,MO_Common_ColumnHeader,0)),"N/A") -> 0.15523283 | P85: =IF(ISNUMBER(N85),N85-K85,"N/A") -> -0.014767172 | Q85: =IFERROR(IF(ISNUMBER(N85),(N85-K85)/ABS(K85),"N/A"),"N/A") -> -0.086865717 | S85: 45532 | T85: CFO Commentary
A86: 324
A87: 323 | B87: =IF(INDEX(MO_SNA_IsHistoricalPeriod,,MATCH(F87,MO_Common_ColumnHeader,0)),"Historical","Forward") -> Historical | D87: =INDEX(INDIRECT(E87),0,COLUMN(MO_Common_Column_A)) -> GAAP Gross Margin, % | E87: MO_MA_GM | F87: FY2025 | I87: 0.74 | J87: 0.76 | K87: =AVERAGE(I87:J87) -> 0.75 | M87: =IF(INDEX(MO_SNA_IsHistoricalPeriod,,MATCH(F87,MO_Common_ColumnHeader,0)),"Actual","Estimate") -> Actual | N87: =IFERROR(INDEX(INDIRECT(E87),0,MATCH(F87,MO_Common_ColumnHeader,0)),"N/A") -> 0.74988697 | P87: =IF(ISNUMBER(N87),N87-K87,"N/A") -> -0.00011302942 | Q87: =IFERROR(IF(ISNUMBER(N87),(N87-K87)/ABS(K87),"N/A"),"N/A") -> -0.00015070589 | S87: 45434 | T87: CFO Commentary
A88: 322 | B88: =IF(INDEX(MO_SNA_IsHistoricalPeriod,,MATCH(F88,MO_Common_ColumnHeader,0)),"Historical","Forward") -> Historical | D88: =INDEX(INDIRECT(E88),0,COLUMN(MO_Common_Column_A)) -> Non-GAAP Gross Margin, % | E88: MO_MA_GM_NONGAAP | F88: FY2025 | I88: 0.74 | J88: 0.76 | K88: =AVERAGE(I88:J88) -> 0.75 | M88: =IF(INDEX(MO_SNA_IsHistoricalPeriod,,MATCH(F88,MO_Common_ColumnHeader,0)),"Actual","Estimate") -> Actual | N88: =IFERROR(INDEX(INDIRECT(E88),0,MATCH(F88,MO_Common_ColumnHeader,0)),"N/A") -> 0.75484494 | P88: =IF(ISNUMBER(N88),N88-K88,"N/A") -> 0.004844939 | Q88: =IFERROR(IF(ISNUMBER(N88),(N88-K88)/ABS(K88),"N/A"),"N/A") -> 0.0064599186 | S88: 45434 | T88: CFO Commentary
A89: 321 | B89: =IF(INDEX(MO_SNA_IsHistoricalPeriod,,MATCH(F89,MO_Common_ColumnHeader,0)),"Historical","Forward") -> Historical | D89: GAAP Operating Expenses | F89: FY2025 | G89: FY2024 | I89: 0.41 | J89: 0.43 | K89: =AVERAGE(I89:J89) -> 0.42 | M89: =IF(INDEX(MO_SNA_IsHistoricalPeriod,,MATCH(F89,MO_Common_ColumnHeader,0)),"Actual","Estimate") -> Actual | N89: =(INDEX(MO_RIS_RD,0,MATCH(F89,MO_Common_ColumnHeader,0))+INDEX(MO_RIS_SGA,0,MATCH(F89,MO_Common_ColumnHeader,0)))/(INDEX(MO_RIS_RD,0,MATCH(G89,MO_Common_ColumnHeader,0))+INDEX(MO_RIS_SGA,0,MATCH(G89,MO_Common_ColumnHeader,0)))-1 -> 0.44805367 | P89: =IF(ISNUMBER(N89),N89-K89,"N/A") -> 0.028053668 | Q89: =IFERROR(IF(ISNUMBER(N89),(N89-K89)/ABS(K89),"N/A"),"N/A") -> 0.066794447 | S89: 45434 | T89: CFO Commentary
A90: 320 | B90: =IF(INDEX(MO_SNA_IsHistoricalPeriod,,MATCH(F90,MO_Common_ColumnHeader,0)),"Historical","Forward") -> Historical | D90: =INDEX(INDIRECT(E90),0,COLUMN(MO_Common_Column_A)) -> Total Non-GAAP Operating Expenses, mm | E90: MO_OS_OPEX | F90: FY2025 | G90: FY2024 | I90: 0.41 | J90: 0.43 | K90: =AVERAGE(I90:J90) -> 0.42 | M90: =IF(INDEX(MO_SNA_IsHistoricalPeriod,,MATCH(F90,MO_Common_ColumnHeader,0)),"Actual","Estimate") -> Actual | N90: =(INDEX(MO_RIS_RD,0,MATCH(F90,MO_Common_ColumnHeader,0))+INDEX(MO_RIS_SGA,0,MATCH(F90,MO_Common_ColumnHeader,0)))/(INDEX(MO_RIS_RD,0,MATCH(G90,MO_Common_ColumnHeader,0))+INDEX(MO_RIS_SGA,0,MATCH(G90,MO_Common_ColumnHeader,0)))-1 -> 0.44805367 | P90: =IF(ISNUMBER(N90),N90-K90,"N/A") -> 0.028053668 | Q90: =IFERROR(IF(ISNUMBER(N90),(N90-K90)/ABS(K90),"N/A"),"N/A") -> 0.066794447 | S90: 45434 | T90: CFO Commentary
A91: 319
A92: 318 | B92: =IF(INDEX(MO_SNA_IsHistoricalPeriod,,MATCH(F92,MO_Common_ColumnHeader,0)),"Historical","Forward") -> Historical | D92: =INDEX(INDIRECT(E92),0,COLUMN(MO_Common_Column_A)) -> Net Revenue | E92: MO_RIS_REV | F92: Q2-2025 | I92: =28000*0.98 -> 27440 | J92: =28000*1.02 -> 28560 | K92: =AVERAGE(I92:J92) -> 28000 | M92: =IF(INDEX(MO_SNA_IsHistoricalPeriod,,MATCH(F92,MO_Common_ColumnHeader,0)),"Actual","Estimate") -> Actual | N92: =IFERROR(INDEX(INDIRECT(E92),0,MATCH(F92,MO_Common_ColumnHeader,0)),"N/A") -> 30040 | P92: =IF(ISNUMBER(N92),N92-K92,"N/A") -> 2040 | Q92: =IFERROR(IF(ISNUMBER(N92),(N92-K92)/ABS(K92),"N/A"),"N/A") -> 0.072857143 | S92: 45434 | T92: CFO Commentary
A93: 317 | B93: =IF(INDEX(MO_SNA_IsHistoricalPeriod,,MATCH(F93,MO_Common_ColumnHeader,0)),"Historical","Forward") -> Historical | D93: =INDEX(INDIRECT(E93),0,COLUMN(MO_Common_Column_A)) -> GAAP Gross Margin, % | E93: MO_MA_GM | F93: Q2-2025 | I93: 0.743 | J93: 0.753 | K93: =AVERAGE(I93:J93) -> 0.748 | M93: =IF(INDEX(MO_SNA_IsHistoricalPeriod,,MATCH(F93,MO_Common_ColumnHeader,0)),"Actual","Estimate") -> Actual | N93: =IFERROR(INDEX(INDIRECT(E93),0,MATCH(F93,MO_Common_ColumnHeader,0)),"N/A") -> 0.75146471 | P93: =IF(ISNUMBER(N93),N93-K93,"N/A") -> 0.0034647137 | Q93: =IFERROR(IF(ISNUMBER(N93),(N93-K93)/ABS(K93),"N/A"),"N/A") -> 0.0046319702 | S93: 45434 | T93: CFO Commentary
A94: 316 | B94: =IF(INDEX(MO_SNA_IsHistoricalPeriod,,MATCH(F94,MO_Common_ColumnHeader,0)),"Historical","Forward") -> Historical | D94: =INDEX(INDIRECT(E94),0,COLUMN(MO_Common_Column_A)) -> Non-GAAP Gross Margin, % | E94: MO_MA_GM_NONGAAP | F94: Q2-2025 | I94: 0.75 | J94: 0.76 | K94: =AVERAGE(I94:J94) -> 0.755 | M94: =IF(INDEX(MO_SNA_IsHistoricalPeriod,,MATCH(F94,MO_Common_ColumnHeader,0)),"Actual","Estimate") -> Actual | N94: =IFERROR(INDEX(INDIRECT(E94),0,MATCH(F94,MO_Common_ColumnHeader,0)),"N/A") -> 0.7566245 | P94: =IF(ISNUMBER(N94),N94-K94,"N/A") -> 0.0016245007 | Q94: =IFERROR(IF(ISNUMBER(N94),(N94-K94)/ABS(K94),"N/A"),"N/A") -> 0.0021516565 | S94: 45434 | T94: CFO Commentary
A95: 315 | B95: =IF(INDEX(MO_SNA_IsHistoricalPeriod,,MATCH(F95,MO_Common_ColumnHeader,0)),"Historical","Forward") -> Historical | D95: GAAP Operating Expenses | F95: Q2-2025 | I95: 4000 | J95: 4000 | K95: =AVERAGE(I95:J95) -> 4000 | M95: =IF(INDEX(MO_SNA_IsHistoricalPeriod,,MATCH(F95,MO_Common_ColumnHeader,0)),"Actual","Estimate") -> Actual | N95: =INDEX(MO_RIS_RD,0,MATCH(F95,MO_Common_ColumnHeader,0))+INDEX(MO_RIS_SGA,0,MATCH(F95,MO_Common_ColumnHeader,0)) -> 3932 | P95: =IF(ISNUMBER(N95),N95-K95,"N/A") -> -68 | Q95: =IFERROR(IF(ISNUMBER(N95),(N95-K95)/ABS(K95),"N/A"),"N/A") -> -0.017 | S95: 45434 | T95: CFO Commentary
A96: 314 | B96: =IF(INDEX(MO_SNA_IsHistoricalPeriod,,MATCH(F96,MO_Common_ColumnHeader,0)),"Historical","Forward") -> Historical | D96: =INDEX(INDIRECT(E96),0,COLUMN(MO_Common_Column_A)) -> Total Non-GAAP Operating Expenses, mm | E96: MO_OS_OPEX | F96: Q2-2025 | I96: 2800 | J96: 2800 | K96: =AVERAGE(I96:J96) -> 2800 | M96: =IF(INDEX(MO_SNA_IsHistoricalPeriod,,MATCH(F96,MO_Common_ColumnHeader,0)),"Actual","Estimate") -> Actual | N96: =IFERROR(INDEX(INDIRECT(E96),0,MATCH(F96,MO_Common_ColumnHeader,0)),"N/A") -> 2792 | P96: =IF(ISNUMBER(N96),N96-K96,"N/A") -> -8 | Q96: =IFERROR(IF(ISNUMBER(N96),(N96-K96)/ABS(K96),"N/A"),"N/A") -> -0.0028571429 | S96: 45434 | T96: CFO Commentary
A97: 313 | B97: =IF(INDEX(MO_SNA_IsHistoricalPeriod,,MATCH(F97,MO_Common_ColumnHeader,0)),"Historical","Forward") -> Historical | D97: GAAP Other Income | F97: Q2-2025 | I97: -300 | J97: -300 | K97: =AVERAGE(I97:J97) -> -300 | M97: =IF(INDEX(MO_SNA_IsHistoricalPeriod,,MATCH(F97,MO_Common_ColumnHeader,0)),"Actual","Estimate") -> Actual | N97: =IFERROR(INDEX(INDIRECT(E97),0,MATCH(F97,MO_Common_ColumnHeader,0)),"N/A") -> N/A | P97: =IF(ISNUMBER(N97),N97-K97,"N/A") -> N/A | Q97: =IFERROR(IF(ISNUMBER(N97),(N97-K97)/ABS(K97),"N/A"),"N/A") -> N/A | S97: 45434 | T97: CFO Commentary
A98: 312 | B98: =IF(INDEX(MO_SNA_IsHistoricalPeriod,,MATCH(F98,MO_Common_ColumnHeader,0)),"Historical","Forward") -> Historical | D98: Non-GAAP Other Income | F98: Q2-2025 | I98: -300 | J98: -300 | K98: =AVERAGE(I98:J98) -> -300 | M98: =IF(INDEX(MO_SNA_IsHistoricalPeriod,,MATCH(F98,MO_Common_ColumnHeader,0)),"Actual","Estimate") -> Actual | N98: =INDEX(MO_RIS_IE_Net_NONGAAP,0,MATCH(F98,MO_Common_ColumnHeader,0))+INDEX(MO_RIS_OI_NONGAAP,0,MATCH(F98,MO_Common_ColumnHeader,0)) -> -380 | P98: =IF(ISNUMBER(N98),N98-K98,"N/A") -> -80 | Q98: =IFERROR(IF(ISNUMBER(N98),(N98-K98)/ABS(K98),"N/A"),"N/A") -> -0.26666667 | S98: 45434 | T98: CFO Commentary
A99: 311 | B99: =IF(INDEX(MO_SNA_IsHistoricalPeriod,,MATCH(F99,MO_Common_ColumnHeader,0)),"Historical","Forward") -> Historical | D99: GAAP Tax Rate | E99: MO_RIS_TaxRate | F99: Q2-2025 | I99: 0.16 | J99: 0.18 | K99: =AVERAGE(I99:J99) -> 0.17 | M99: =IF(INDEX(MO_SNA_IsHistoricalPeriod,,MATCH(F99,MO_Common_ColumnHeader,0)),"Actual","Estimate") -> Actual | N99: =IFERROR(INDEX(INDIRECT(E99),0,MATCH(F99,MO_Common_ColumnHeader,0)),"N/A") -> 0.13609868 | P99: =IF(ISNUMBER(N99),N99-K99,"N/A") -> -0.033901322 | Q99: =IFERROR(IF(ISNUMBER(N99),(N99-K99)/ABS(K99),"N/A"),"N/A") -> -0.19941954 | S99: 45434 | T99: CFO Commentary
A100: 310 | B100: =IF(INDEX(MO_SNA_IsHistoricalPeriod,,MATCH(F100,MO_Common_ColumnHeader,0)),"Historical","Forward") -> Historical | D100: =INDEX(INDIRECT(E100),0,COLUMN(MO_Common_Column_A)) -> Non-GAAP Tax Rate | E100: MO_RIS_TaxRate_NONGAAP | F100: Q2-2025 | I100: 0.16 | J100: 0.18 | K100: =AVERAGE(I100:J100) -> 0.17 | M100: =IF(INDEX(MO_SNA_IsHistoricalPeriod,,MATCH(F100,MO_Common_ColumnHeader,0)),"Actual","Estimate") -> Actual | N100: =IFERROR(INDEX(INDIRECT(E100),0,MATCH(F100,MO_Common_ColumnHeader,0)),"N/A") -> 0.16562485 | P100: =IF(ISNUMBER(N100),N100-K100,"N/A") -> -0.0043751538 | Q100: =IFERROR(IF(ISNUMBER(N100),(N100-K100)/ABS(K100),"N/A"),"N/A") -> -0.025736199 | S100: 45434 | T100: CFO Commentary
A101: 309
...

Sheet Summary Page
A1: =MO.CompanyName -> Company1915 Company0697 | C1: =INDEX(MO_Common_QEndDate,0,COLUMN()) -> 39838 | D1: =INDEX(MO_Common_QEndDate,0,COLUMN()) -> 40209 | E1: =INDEX(MO_Common_QEndDate,0,COLUMN()) -> 40573 | F1: =INDEX(MO_Common_QEndDate,0,COLUMN()) -> 40937 | G1: =INDEX(MO_Common_QEndDate,0,COLUMN()) -> 41028 | H1: =INDEX(MO_Common_QEndDate,0,COLUMN()) -> 41119 | I1: =INDEX(MO_Common_QEndDate,0,COLUMN()) -> 41210 | J1: =INDEX(MO_Common_QEndDate,0,COLUMN()) -> 41301 | ... CK1: =INDEX(MO_Common_QEndDate,0,COLUMN()) -> 47879
A2: Reports | B2: =MO.ReportFX -> USD | C2: =INDEX(MO_Common_ColumnHeader,0,COLUMN()) -> FY2009 | D2: =INDEX(MO_Common_ColumnHeader,0,COLUMN()) -> FY2010 | E2: =INDEX(MO_Common_ColumnHeader,0,COLUMN()) -> FY2011 | F2: =INDEX(MO_Common_ColumnHeader,0,COLUMN()) -> FY2012 | G2: =INDEX(MO_Common_ColumnHeader,0,COLUMN()) -> Q1-2013 | H2: =INDEX(MO_Common_ColumnHeader,0,COLUMN()) -> Q2-2013 | I2: =INDEX(MO_Common_ColumnHeader,0,COLUMN()) -> Q3-2013 | J2: =INDEX(MO_Common_ColumnHeader,0,COLUMN()) -> Q4-2013 | ... CK2: =INDEX(MO_Common_ColumnHeader,0,COLUMN()) -> FY2031
A3: Capitalization Summary
A4: ="Stock Price - "&SP.ValuationToggle -> Stock Price - EoP | B4: EoP | C4: =IF(INDEX(MO_SNA_IsHistoricalPeriod,1,COLUMN())=FALSE,MO.LastPrice/HP.MRFX,CHOOSE(VLOOKUP(SP.ValuationToggle,tb_ValuationToggle,COLUMNS(tb_ValuationToggle),FALSE),INDEX(MO_SPT_StockHigh,1,COLUMN()),INDEX(MO_SPT_StockLow,1,COLUMN()),INDEX(MO_SPT_StockAverage,1,COLUMN()),INDEX(MO_SPT_StockEoP,1,COLUMN()))/IF(SP.ValuationToggle="EoP",IF(INDEX(MO_SPT_FXEoP,1,COLUMN())=0,1,INDEX(MO_SPT_FXEoP,1,COLUMN())),IF(INDEX(MO_SPT_FXAverage,1,COLUMN())=0,1,INDEX(MO_SPT_FXAverage,1,COLUMN())))) -> 0.19875 | D4: =IF(INDEX(MO_SNA_IsHistoricalPeriod,1,COLUMN())=FALSE,MO.LastPrice/HP.MRFX,CHOOSE(VLOOKUP(SP.ValuationToggle,tb_ValuationToggle,COLUMNS(tb_ValuationToggle),FALSE),INDEX(MO_SPT_StockHigh,1,COLUMN()),INDEX(MO_SPT_StockLow,1,COLUMN()),INDEX(MO_SPT_StockAverage,1,COLUMN()),INDEX(MO_SPT_StockEoP,1,COLUMN()))/IF(SP.ValuationToggle="EoP",IF(INDEX(MO_SPT_FXEoP,1,COLUMN())=0,1,INDEX(MO_SPT_FXEoP,1,COLUMN())),IF(INDEX(MO_SPT_FXAverage,1,COLUMN())=0,1,INDEX(MO_SPT_FXAverage,1,COLUMN())))) -> 0.38475 | E4: =IF(INDEX(MO_SNA_IsHistoricalPeriod,1,COLUMN())=FALSE,MO.LastPrice/HP.MRFX,CHOOSE(VLOOKUP(SP.ValuationToggle,tb_ValuationToggle,COLUMNS(tb_ValuationToggle),FALSE),INDEX(MO_SPT_StockHigh,1,COLUMN()),INDEX(MO_SPT_StockLow,1,COLUMN()),INDEX(MO_SPT_StockAverage,1,COLUMN()),INDEX(MO_SPT_StockEoP,1,COLUMN()))/IF(SP.ValuationToggle="EoP",IF(INDEX(MO_SPT_FXEoP,1,COLUMN())=0,1,INDEX(MO_SPT_FXEoP,1,COLUMN())),IF(INDEX(MO_SPT_FXAverage,1,COLUMN())=0,1,INDEX(MO_SPT_FXAverage,1,COLUMN())))) -> 0.594 | F4: =IF(INDEX(MO_SNA_IsHistoricalPeriod,1,COLUMN())=FALSE,MO.LastPrice/HP.MRFX,CHOOSE(VLOOKUP(SP.ValuationToggle,tb_ValuationToggle,COLUMNS(tb_ValuationToggle),FALSE),INDEX(MO_SPT_StockHigh,1,COLUMN()),INDEX(MO_SPT_StockLow,1,COLUMN()),INDEX(MO_SPT_StockAverage,1,COLUMN()),INDEX(MO_SPT_StockEoP,1,COLUMN()))/IF(SP.ValuationToggle="EoP",IF(INDEX(MO_SPT_FXEoP,1,COLUMN())=0,1,INDEX(MO_SPT_FXEoP,1,COLUMN())),IF(INDEX(MO_SPT_FXAverage,1,COLUMN())=0,1,INDEX(MO_SPT_FXAverage,1,COLUMN())))) -> 0.37 | G4: =IF(INDEX(MO_SNA_IsHistoricalPeriod,1,COLUMN())=FALSE,MO.LastPrice/HP.MRFX,CHOOSE(VLOOKUP(SP.ValuationToggle,tb_ValuationToggle,COLUMNS(tb_ValuationToggle),FALSE),INDEX(MO_SPT_StockHigh,1,COLUMN()),INDEX(MO_SPT_StockLow,1,COLUMN()),INDEX(MO_SPT_StockAverage,1,COLUMN()),INDEX(MO_SPT_StockEoP,1,COLUMN()))/IF(SP.ValuationToggle="EoP",IF(INDEX(MO_SPT_FXEoP,1,COLUMN())=0,1,INDEX(MO_SPT_FXEoP,1,COLUMN())),IF(INDEX(MO_SPT_FXAverage,1,COLUMN())=0,1,INDEX(MO_SPT_FXAverage,1,COLUMN())))) -> 0.3245 | H4: =IF(INDEX(MO_SNA_IsHistoricalPeriod,1,COLUMN())=FALSE,MO.LastPrice/HP.MRFX,CHOOSE(VLOOKUP(SP.ValuationToggle,tb_ValuationToggle,COLUMNS(tb_ValuationToggle),FALSE),INDEX(MO_SPT_StockHigh,1,COLUMN()),INDEX(MO_SPT_StockLow,1,COLUMN()),INDEX(MO_SPT_StockAverage,1,COLUMN()),INDEX(MO_SPT_StockEoP,1,COLUMN()))/IF(SP.ValuationToggle="EoP",IF(INDEX(MO_SPT_FXEoP,1,COLUMN())=0,1,INDEX(MO_SPT_FXEoP,1,COLUMN())),IF(INDEX(MO_SPT_FXAverage,1,COLUMN())=0,1,INDEX(MO_SPT_FXAverage,1,COLUMN())))) -> 0.33325 | I4: =IF(INDEX(MO_SNA_IsHistoricalPeriod,1,COLUMN())=FALSE,MO.LastPrice/HP.MRFX,CHOOSE(VLOOKUP(SP.ValuationToggle,tb_ValuationToggle,COLUMNS(tb_ValuationToggle),FALSE),INDEX(MO_SPT_StockHigh,1,COLUMN()),INDEX(MO_SPT_StockLow,1,COLUMN()),INDEX(MO_SPT_StockAverage,1,COLUMN()),INDEX(MO_SPT_StockEoP,1,COLUMN()))/IF(SP.ValuationToggle="EoP",IF(INDEX(MO_SPT_FXEoP,1,COLUMN())=0,1,INDEX(MO_SPT_FXEoP,1,COLUMN())),IF(INDEX(MO_SPT_FXAverage,1,COLUMN())=0,1,INDEX(MO_SPT_FXAverage,1,COLUMN())))) -> 0.30125 | J4: =IF(INDEX(MO_SNA_IsHistoricalPeriod,1,COLUMN())=FALSE,MO.LastPrice/HP.MRFX,CHOOSE(VLOOKUP(SP.ValuationToggle,tb_ValuationToggle,COLUMNS(tb_ValuationToggle),FALSE),INDEX(MO_SPT_StockHigh,1,COLUMN()),INDEX(MO_SPT_StockLow,1,COLUMN()),INDEX(MO_SPT_StockAverage,1,COLUMN()),INDEX(MO_SPT_StockEoP,1,COLUMN()))/IF(SP.ValuationToggle="EoP",IF(INDEX(MO_SPT_FXEoP,1,COLUMN())=0,1,INDEX(MO_SPT_FXEoP,1,COLUMN())),IF(INDEX(MO_SPT_FXAverage,1,COLUMN())=0,1,INDEX(MO_SPT_FXAverage,1,COLUMN())))) -> 0.308 | ... CK4: =IF(INDEX(MO_SNA_IsHistoricalPeriod,1,COLUMN())=FALSE,MO.LastPrice/HP.MRFX,CHOOSE(VLOOKUP(SP.ValuationToggle,tb_ValuationToggle,COLUMNS(tb_ValuationToggle),FALSE),INDEX(MO_SPT_StockHigh,1,COLUMN()),INDEX(MO_SPT_StockLow,1,COLUMN()),INDEX(MO_SPT_StockAverage,1,COLUMN()),INDEX(MO_SPT_StockEoP,1,COLUMN()))/IF(SP.ValuationToggle="EoP",IF(INDEX(MO_SPT_FXEoP,1,COLUMN())=0,1,INDEX(MO_SPT_FXEoP,1,COLUMN())),IF(INDEX(MO_SPT_FXAverage,1,COLUMN())=0,1,INDEX(MO_SPT_FXAverage,1,COLUMN())))) -> 222.82
A5: =INDEX(MO_SCA_ShareCount_EoP_Diluted,0,COLUMN()) -> EoP Total Diluted Common Stock Outstanding, mm shares | C5: =INDEX(MO_SCA_ShareCount_EoP_Diluted,0,COLUMN()) -> 21538.431 | D5: =INDEX(MO_SCA_ShareCount_EoP_Diluted,0,COLUMN()) -> 22458.634 | E5: =INDEX(MO_SCA_ShareCount_EoP_Diluted,0,COLUMN()) -> 24082.508 | F5: =INDEX(MO_SCA_ShareCount_EoP_Diluted,0,COLUMN()) -> 24996.656 | G5: =INDEX(MO_SCA_ShareCount_EoP_Diluted,0,COLUMN()) -> 25094.984 | H5: =INDEX(MO_SCA_ShareCount_EoP_Diluted,0,COLUMN()) -> 24910.816 | I5: =INDEX(MO_SCA_ShareCount_EoP_Diluted,0,COLUMN()) -> 25302.944 | J5: =INDEX(MO_SCA_ShareCount_EoP_Diluted,0,COLUMN()) -> 24744.205 | ... CK5: =INDEX(MO_SCA_ShareCount_EoP_Diluted,0,COLUMN()) -> 24459.178
A6: ="Market Cap - "&SP.ValuationToggle -> Market Cap - EoP | C6: =INDEX(SP_CS_StockPrice,0,COLUMN())*INDEX(SP_CS_ShareCount_EoP_Diluted,0,COLUMN()) -> 4280.7631 | D6: =INDEX(SP_CS_StockPrice,0,COLUMN())*INDEX(SP_CS_ShareCount_EoP_Diluted,0,COLUMN()) -> 8640.9594 | E6: =INDEX(SP_CS_StockPrice,0,COLUMN())*INDEX(SP_CS_ShareCount_EoP_Diluted,0,COLUMN()) -> 14305.01 | F6: =INDEX(SP_CS_StockPrice,0,COLUMN())*INDEX(SP_CS_ShareCount_EoP_Diluted,0,COLUMN()) -> 9248.7629 | G6: =INDEX(SP_CS_StockPrice,0,COLUMN())*INDEX(SP_CS_ShareCount_EoP_Diluted,0,COLUMN()) -> 8143.3222 | H6: =INDEX(SP_CS_StockPrice,0,COLUMN())*INDEX(SP_CS_ShareCount_EoP_Diluted,0,COLUMN()) -> 8301.5296 | I6: =INDEX(SP_CS_StockPrice,0,COLUMN())*INDEX(SP_CS_ShareCount_EoP_Diluted,0,COLUMN()) -> 7622.5117 | J6: =INDEX(SP_CS_StockPrice,0,COLUMN())*INDEX(SP_CS_ShareCount_EoP_Diluted,0,COLUMN()) -> 7621.2153 | ... CK6: =INDEX(SP_CS_StockPrice,0,COLUMN())*INDEX(SP_CS_ShareCount_EoP_Diluted,0,COLUMN()) -> 5449994
A7: =INDEX(MO_BSS_Cash,0,COLUMN()) -> Cash | C7: =INDEX(MO_BSS_Cash,0,COLUMN()) -> 1255.39 | D7: =INDEX(MO_BSS_Cash,0,COLUMN()) -> 1728.227 | E7: =INDEX(MO_BSS_Cash,0,COLUMN()) -> 2490.563 | F7: =INDEX(MO_BSS_Cash,0,COLUMN()) -> 3129.576 | G7: =INDEX(MO_BSS_Cash,0,COLUMN()) -> 3130.812 | H7: =INDEX(MO_BSS_Cash,0,COLUMN()) -> 3278.1 | I7: =INDEX(MO_BSS_Cash,0,COLUMN()) -> 3434.772 | J7: =INDEX(MO_BSS_Cash,0,COLUMN()) -> 3727.883 | ... CK7: =INDEX(MO_BSS_Cash,0,COLUMN()) -> 1487894.1
A8: =INDEX(MO_BSS_Debt,0,COLUMN()) -> Debt | C8: =INDEX(MO_BSS_Debt,0,COLUMN()) -> 25.634 | D8: =INDEX(MO_BSS_Debt,0,COLUMN()) -> 24.45 | E8: =INDEX(MO_BSS_Debt,0,COLUMN()) -> 23.389 | F8: =INDEX(MO_BSS_Debt,0,COLUMN()) -> 21.439 | G8: =INDEX(MO_BSS_Debt,0,COLUMN()) -> 20.83 | H8: =INDEX(MO_BSS_Debt,0,COLUMN()) -> 20.237 | I8: =INDEX(MO_BSS_Debt,0,COLUMN()) -> 19.627 | J8: =INDEX(MO_BSS_Debt,0,COLUMN()) -> 18.998 | ... CK8: =INDEX(MO_BSS_Debt,0,COLUMN()) -> 8470
A9: Operating Lease Liabilities | C9: =INDEX(MO_BSS_OL,0,COLUMN()) -> 0 | D9: =INDEX(MO_BSS_OL,0,COLUMN()) -> 0 | E9: =INDEX(MO_BSS_OL,0,COLUMN()) -> 0 | F9: =INDEX(MO_BSS_OL,0,COLUMN()) -> 0 | G9: =INDEX(MO_BSS_OL,0,COLUMN()) -> 0 | H9: =INDEX(MO_BSS_OL,0,COLUMN()) -> 0 | I9: =INDEX(MO_BSS_OL,0,COLUMN()) -> 0 | J9: =INDEX(MO_BSS_OL,0,COLUMN()) -> 0 | ... CK9: =INDEX(MO_BSS_OL,0,COLUMN()) -> 4344
A10: Other EV Components | C10: =INDEX(MO_VA_EVCalc_NCI,0,COLUMN())+INDEX(MO_VA_EVCalc_Prefs,0,COLUMN())+INDEX(MO_VA_EVCalc_Other,0,COLUMN()) -> 0 | D10: =INDEX(MO_VA_EVCalc_NCI,0,COLUMN())+INDEX(MO_VA_EVCalc_Prefs,0,COLUMN())+INDEX(MO_VA_EVCalc_Other,0,COLUMN()) -> 0 | E10: =INDEX(MO_VA_EVCalc_NCI,0,COLUMN())+INDEX(MO_VA_EVCalc_Prefs,0,COLUMN())+INDEX(MO_VA_EVCalc_Other,0,COLUMN()) -> 0 | F10: =INDEX(MO_VA_EVCalc_NCI,0,COLUMN())+INDEX(MO_VA_EVCalc_Prefs,0,COLUMN())+INDEX(MO_VA_EVCalc_Other,0,COLUMN()) -> 0 | G10: =INDEX(MO_VA_EVCalc_NCI,0,COLUMN())+INDEX(MO_VA_EVCalc_Prefs,0,COLUMN())+INDEX(MO_VA_EVCalc_Other,0,COLUMN()) -> 0 | H10: =INDEX(MO_VA_EVCalc_NCI,0,COLUMN())+INDEX(MO_VA_EVCalc_Prefs,0,COLUMN())+INDEX(MO_VA_EVCalc_Other,0,COLUMN()) -> 0 | I10: =INDEX(MO_VA_EVCalc_NCI,0,COLUMN())+INDEX(MO_VA_EVCalc_Prefs,0,COLUMN())+INDEX(MO_VA_EVCalc_Other,0,COLUMN()) -> 0 | J10: =INDEX(MO_VA_EVCalc_NCI,0,COLUMN())+INDEX(MO_VA_EVCalc_Prefs,0,COLUMN())+INDEX(MO_VA_EVCalc_Other,0,COLUMN()) -> 0 | ... CK10: =INDEX(MO_VA_EVCalc_NCI,0,COLUMN())+INDEX(MO_VA_EVCalc_Prefs,0,COLUMN())+INDEX(MO_VA_EVCalc_Other,0,COLUMN()) -> 0
A11: ="Enterprise Value - "&SP.ValuationToggle -> Enterprise Value - EoP | C11: =INDEX(SP_CS_MarketCap,0,COLUMN())-INDEX(SP_CS_Cash,0,COLUMN())+INDEX(SP_CS_Debt,0,COLUMN())+INDEX(SP_CS_OL,0,COLUMN())+INDEX(SP_CS_EVCalc_Other,0,COLUMN()) -> 3051.0071 | D11: =INDEX(SP_CS_MarketCap,0,COLUMN())-INDEX(SP_CS_Cash,0,COLUMN())+INDEX(SP_CS_Debt,0,COLUMN())+INDEX(SP_CS_OL,0,COLUMN())+INDEX(SP_CS_EVCalc_Other,0,COLUMN()) -> 6937.1824 | E11: =INDEX(SP_CS_MarketCap,0,COLUMN())-INDEX(SP_CS_Cash,0,COLUMN())+INDEX(SP_CS_Debt,0,COLUMN())+INDEX(SP_CS_OL,0,COLUMN())+INDEX(SP_CS_EVCalc_Other,0,COLUMN()) -> 11837.836 | F11: =INDEX(SP_CS_MarketCap,0,COLUMN())-INDEX(SP_CS_Cash,0,COLUMN())+INDEX(SP_CS_Debt,0,COLUMN())+INDEX(SP_CS_OL,0,COLUMN())+INDEX(SP_CS_EVCalc_Other,0,COLUMN()) -> 6140.6259 | G11: =INDEX(SP_CS_MarketCap,0,COLUMN())-INDEX(SP_CS_Cash,0,COLUMN())+INDEX(SP_CS_Debt,0,COLUMN())+INDEX(SP_CS_OL,0,COLUMN())+INDEX(SP_CS_EVCalc_Other,0,COLUMN()) -> 5033.3402 | H11: =INDEX(SP_CS_MarketCap,0,COLUMN())-INDEX(SP_CS_Cash,0,COLUMN())+INDEX(SP_CS_Debt,0,COLUMN())+INDEX(SP_CS_OL,0,COLUMN())+INDEX(SP_CS_EVCalc_Other,0,COLUMN()) -> 5043.6666 | I11: =INDEX(SP_CS_MarketCap,0,COLUMN())-INDEX(SP_CS_Cash,0,COLUMN())+INDEX(SP_CS_Debt,0,COLUMN())+INDEX(SP_CS_OL,0,COLUMN())+INDEX(SP_CS_EVCalc_Other,0,COLUMN()) -> 4207.3667 | J11: =INDEX(SP_CS_MarketCap,0,COLUMN())-INDEX(SP_CS_Cash,0,COLUMN())+INDEX(SP_CS_Debt,0,COLUMN())+INDEX(SP_CS_OL,0,COLUMN())+INDEX(SP_CS_EVCalc_Other,0,COLUMN()) -> 3912.3303 | ... CK11: =INDEX(SP_CS_MarketCap,0,COLUMN())-INDEX(SP_CS_Cash,0,COLUMN())+INDEX(SP_CS_Debt,0,COLUMN())+INDEX(SP_CS_OL,0,COLUMN())+INDEX(SP_CS_EVCalc_Other,0,COLUMN()) -> 3974913.9
A13: Company-Specific Operational Data
A14: =+Model!A9 -> Y/Y Gaming Revenue Growth, % | U14: =+Model!U9 -> 0.36201191 | V14: =+Model!V9 -> 0.2542735 | W14: =+Model!W9 -> 0.58273381 | X14: =+Model!X9 -> 0.44402277 | Y14: =+Model!Y9 -> 0.25386997 | Z14: =+Model!Z9 -> 0.36929057 | AA14: =+Model!AA9 -> 0.17035775 | AB14: =+Model!AB9 -> 0.18333333 | ... CK14: =+Model!CK9 -> 0.1
A15: =+Model!A13 -> Y/Y Professional Visualization Revenue Growth, % | U15: =+Model!U13 -> 0.0076045627 | V15: =+Model!V13 -> -0.052356021 | W15: =+Model!W13 -> -0.15384615 | X15: =+Model!X13 -> -0.077669903 | Y15: =+Model!Y13 -> 0.068421053 | Z15: =+Model!Z13 -> -0.056603774 | AA15: =+Model!AA13 -> 0.044198895 | AB15: =+Model!AB13 -> 0.21590909 | ... CK15: =+Model!CK13 -> 0.1
A16: =+Model!A24 -> Y/Y Datacenter Revenue Growth, % | U16: =+Model!U24 -> 0.59296482 | V16: =+Model!V24 -> 0.54385965 | W16: =+Model!W24 -> -0.13253012 | X16: =+Model!X24 -> -0.078651685 | Y16: =+Model!Y24 -> 0.10227273 | Z16: =+Model!Z24 -> 0.069400631 | AA16: =+Model!AA24 -> 0.625 | AB16: =+Model!AB24 -> 1.0972222 | ... CK16: =+Model!CK24 -> 0.18
A17: =+Model!A28 -> Y/Y Automotive Revenue Growth, % | U17: =+Model!U28 -> 0.84848485 | V17: =+Model!V28 -> 1.2 | W17: =+Model!W28 -> 0.775 | X17: =+Model!X28 -> 0.51923077 | Y17: =+Model!Y28 -> 0.66071429 | Z17: =+Model!Z28 -> 0.74863388 | AA17: =+Model!AA28 -> 0.46753247 | AB17: =+Model!AB28 -> 0.67605634 | ... CK17: =+Model!CK28 -> 0.1
A18: =+Model!A32 -> Y/Y OEM & IP Revenue Growth, % | U18: =+Model!U32 -> -0.13250653 | V18: =+Model!V32 -> -0.38068182 | W18: =+Model!W32 -> -0.50985915 | X18: =+Model!X32 -> -0.45014245 | Y18: =+Model!Y32 -> -0.26937269 | Z18: =+Model!Z32 -> -0.41083521 | AA18: =+Model!AA32 -> -0.20642202 | AB18: =+Model!AB32 -> -0.063218391 | ... CK18: =+Model!CK32 -> 0.1
A19: =+Model!A38 -> Y/Y Total Revenue Growth, % | D19: =+Model!D38 -> -0.028735198 | E19: =+Model!E38 -> 0.065193923 | F19: =+Model!F38 -> 0.12830408 | K19: =+Model!K38 -> 0.070593782 | L19: =+Model!L38 -> 0.032287537 | M19: =+Model!M38 -> -0.064190296 | N19: =+Model!N38 -> -0.1246921 | O19: =+Model!O38 -> 0.033712108 | P19: =+Model!P38 -> -0.035082575 | Q19: =+Model!Q38 -> 0.15528956 | R19: =+Model!R38 -> 0.12869127 | ... CK19: =+Model!CK38 -> 0.1750063
A21: =+Model!A7 -> Gaming Revenue, mm | P21: =+Model!P7 -> 1511 | Q21: =+Model!Q7 -> 468 | R21: =+Model!R7 -> 417 | S21: =+Model!S7 -> 527 | T21: =+Model!T7 -> 646 | U21: =+Model!U7 -> 2058 | V21: =+Model!V7 -> 587 | W21: =+Model!W7 -> 660 | ... CK21: =+Model!CK7 -> 32304.791
A22: =+Model!A11 -> Professional Visualization Revenue, mm | P22: =+Model!P11 -> 789 | Q22: =+Model!Q11 -> 191 | R22: =+Model!R11 -> 208 | S22: =+Model!S11 -> 206 | T22: =+Model!T11 -> 190 | U22: =+Model!U11 -> 795 | V22: =+Model!V11 -> 181 | W22: =+Model!W11 -> 176 | ... CK22: =+Model!CK11 -> 5752.4556
A23: =+Model!A22 -> Datacenter Revenue, mm | P23: =+Model!P22 -> 199 | Q23: =+Model!Q22 -> 57 | R23: =+Model!R22 -> 83 | S23: =+Model!S22 -> 89 | T23: =+Model!T22 -> 88 | U23: =+Model!U22 -> 317 | V23: =+Model!V22 -> 88 | W23: =+Model!W22 -> 72 | ... CK23: =+Model!CK22 -> 704253.91
A24: =+Model!A26 -> Automotive Revenue, mm | P24: =+Model!P26 -> 99 | Q24: =+Model!Q26 -> 35 | R24: =+Model!R26 -> 40 | S24: =+Model!S26 -> 52 | T24: =+Model!T26 -> 56 | U24: =+Model!U26 -> 183 | V24: =+Model!V26 -> 77 | W24: =+Model!W26 -> 71 | ... CK24: =+Model!CK26 -> 4540.1475
A25: =+Model!A30 -> OEM & IP Revenue, mm | P25: =+Model!P30 -> 1532 | Q25: =+Model!Q30 -> 352 | R25: =+Model!R30 -> 355 | S25: =+Model!S30 -> 351 | T25: =+Model!T30 -> 271 | U25: =+Model!U30 -> 1329 | V25: =+Model!V30 -> 218 | W25: =+Model!W30 -> 174 | ... CK25: =+Model!CK30 -> 1110.9591
A26: =+Model!A34 -> Total Revenue, mm | P26: =+Model!P34 -> 4130 | Q26: =+Model!Q34 -> 1103 | R26: =+Model!R34 -> 1103 | S26: =+Model!S34 -> 1225 | T26: =+Model!T34 -> 1251 | U26: =+Model!U34 -> 4682 | V26: =+Model!V34 -> 1151 | W26: =+Model!W34 -> 1153 | ... CK26: =+Model!CK34 -> 747962.27
A28: GAAP and Non-GAAP Financials
A29: =INDEX(MO_RIS_REV,0,COLUMN()) -> Net Revenue | C29: =INDEX(MO_RIS_REV,0,COLUMN()) -> 3424.859 | D29: =INDEX(MO_RIS_REV,0,COLUMN()) -> 3326.445 | E29: =INDEX(MO_RIS_REV,0,COLUMN()) -> 3543.309 | F29: =INDEX(MO_RIS_REV,0,COLUMN()) -> 3997.93 | G29: =INDEX(MO_RIS_REV,0,COLUMN()) -> 924.877 | H29: =INDEX(MO_RIS_REV,0,COLUMN()) -> 1044.27 | I29: =INDEX(MO_RIS_REV,0,COLUMN()) -> 1204.11 | J29: =INDEX(MO_RIS_REV,0,COLUMN()) -> 1106.902 | ... CK29: =INDEX(MO_RIS_REV,0,COLUMN()) -> 747962.27
A30: =INDEX(MO_RIS_COGS,0,COLUMN()) -> GAAP COGS | C30: =INDEX(MO_RIS_COGS,0,COLUMN()) -> 2250.59 | D30: =INDEX(MO_RIS_COGS,0,COLUMN()) -> 2149.522 | E30: =INDEX(MO_RIS_COGS,0,COLUMN()) -> 2134.219 | F30: =INDEX(MO_RIS_COGS,0,COLUMN()) -> 1941.413 | G30: =INDEX(MO_RIS_COGS,0,COLUMN()) -> 461.513 | H30: =INDEX(MO_RIS_COGS,0,COLUMN()) -> 503.551 | I30: =INDEX(MO_RIS_COGS,0,COLUMN()) -> 567.452 | J30: =INDEX(MO_RIS_COGS,0,COLUMN()) -> 521.3 | ... CK30: =INDEX(MO_RIS_COGS,0,COLUMN()) -> 187004.68
A31: =INDEX(MO_RIS_SBC_COGS,0,COLUMN()) -> SBC in COGS | C31: =INDEX(MO_RIS_SBC_COGS,0,COLUMN()) -> -11.939 | D31: =INDEX(MO_RIS_SBC_COGS,0,COLUMN()) -> -12.05 | E31: =INDEX(MO_RIS_SBC_COGS,0,COLUMN()) -> -8.308 | F31: =INDEX(MO_RIS_SBC_COGS,0,COLUMN()) -> -11.322 | G31: =INDEX(MO_RIS_SBC_COGS,0,COLUMN()) -> -2.526 | H31: =INDEX(MO_RIS_SBC_COGS,0,COLUMN()) -> -2.649 | I31: =INDEX(MO_RIS_SBC_COGS,0,COLUMN()) -> -2.489 | J31: =INDEX(MO_RIS_SBC_COGS,0,COLUMN()) -> -2.826 | ... CK31: =INDEX(MO_RIS_SBC_COGS,0,COLUMN()) -> 0
A32: =INDEX(z_A7FLSL0150_MO_RIS_AcquisitionrelatedcostsCOGS,0,COLUMN()) -> Acquisition-related costs COGS | C32: =INDEX(z_A7FLSL0150_MO_RIS_AcquisitionrelatedcostsCOGS,0,COLUMN()) -> 0 | D32: =INDEX(z_A7FLSL0150_MO_RIS_AcquisitionrelatedcostsCOGS,0,COLUMN()) -> 0 | E32: =INDEX(z_A7FLSL0150_MO_RIS_AcquisitionrelatedcostsCOGS,0,COLUMN()) -> 0 | F32: =INDEX(z_A7FLSL0150_MO_RIS_AcquisitionrelatedcostsCOGS,0,COLUMN()) -> 0 | G32: =INDEX(z_A7FLSL0150_MO_RIS_AcquisitionrelatedcostsCOGS,0,COLUMN()) -> 0 | H32: =INDEX(z_A7FLSL0150_MO_RIS_AcquisitionrelatedcostsCOGS,0,COLUMN()) -> 0 | I32: =INDEX(z_A7FLSL0150_MO_RIS_AcquisitionrelatedcostsCOGS,0,COLUMN()) -> 0 | J32: =INDEX(z_A7FLSL0150_MO_RIS_AcquisitionrelatedcostsCOGS,0,COLUMN()) -> 0 | ... CK32: =INDEX(z_A7FLSL0150_MO_RIS_AcquisitionrelatedcostsCOGS,0,COLUMN()) -> -1495.9245
A33: =INDEX(MO_RIS_COGS_Adjustments,0,COLUMN()) -> Other COGS adjustments | C33: =INDEX(MO_RIS_COGS_Adjustments,0,COLUMN()) -> -181.85 | D33: =INDEX(MO_RIS_COGS_Adjustments,0,COLUMN()) -> -95.24 | E33: =INDEX(MO_RIS_COGS_Adjustments,0,COLUMN()) -> -181.193 | F33: =INDEX(MO_RIS_COGS_Adjustments,0,COLUMN()) -> -7.3 | G33: =INDEX(MO_RIS_COGS_Adjustments,0,COLUMN()) -> 0 | H33: =INDEX(MO_RIS_COGS_Adjustments,0,COLUMN()) -> 0 | I33: =INDEX(MO_RIS_COGS_Adjustments,0,COLUMN()) -> 0 | J33: =INDEX(MO_RIS_COGS_Adjustments,0,COLUMN()) -> 0 | ... CK33: =INDEX(MO_RIS_COGS_Adjustments,0,COLUMN()) -> 0
A34: =INDEX(MO_RIS_RD_NONGAAP,0,COLUMN()) -> Non-GAAP R&D | C34: =INDEX(MO_RIS_RD_NONGAAP,0,COLUMN()) -> 757.872 | D34: =INDEX(MO_RIS_RD_NONGAAP,0,COLUMN()) -> 847.514 | E34: =INDEX(MO_RIS_RD_NONGAAP,0,COLUMN()) -> 790.856 | F34: =INDEX(MO_RIS_RD_NONGAAP,0,COLUMN()) -> 911.821 | G34: =INDEX(MO_RIS_RD_NONGAAP,0,COLUMN()) -> 259.524 | H34: =INDEX(MO_RIS_RD_NONGAAP,0,COLUMN()) -> 259.514 | I34: =INDEX(MO_RIS_RD_NONGAAP,0,COLUMN()) -> 261.458 | J34: =INDEX(MO_RIS_RD_NONGAAP,0,COLUMN()) -> 272.3 | ... CK34: =INDEX(MO_RIS_RD_NONGAAP,0,COLUMN()) -> 50121.722
A35: =INDEX(MO_RIS_SGA_NONGAAP,0,COLUMN()) -> Non-GAAP SG&A | C35: =INDEX(MO_RIS_SGA_NONGAAP,0,COLUMN()) -> 309.462 | D35: =INDEX(MO_RIS_SGA_NONGAAP,0,COLUMN()) -> 333.313 | E35: =INDEX(MO_RIS_SGA_NONGAAP,0,COLUMN()) -> 327.442 | F35: =INDEX(MO_RIS_SGA_NONGAAP,0,COLUMN()) -> 351.083 | G35: =INDEX(MO_RIS_SGA_NONGAAP,0,COLUMN()) -> 92.8 | H35: =INDEX(MO_RIS_SGA_NONGAAP,0,COLUMN()) -> 87.055 | I35: =INDEX(MO_RIS_SGA_NONGAAP,0,COLUMN()) -> 87.737 | J35: =INDEX(MO_RIS_SGA_NONGAAP,0,COLUMN()) -> 88.088 | ... CK35: =INDEX(MO_RIS_SGA_NONGAAP,0,COLUMN()) -> 10764.982
A36: =INDEX(MO_RIS_OPEX_NONGAAP,0,COLUMN()) -> Non-GAAP OPEX | C36: =INDEX(MO_RIS_OPEX_NONGAAP,0,COLUMN()) -> 0 | D36: =INDEX(MO_RIS_OPEX_NONGAAP,0,COLUMN()) -> 0 | E36: =INDEX(MO_RIS_OPEX_NONGAAP,0,COLUMN()) -> 0 | F36: =INDEX(MO_RIS_OPEX_NONGAAP,0,COLUMN()) -> 0 | G36: =INDEX(MO_RIS_OPEX_NONGAAP,0,COLUMN()) -> 0 | H36: =INDEX(MO_RIS_OPEX_NONGAAP,0,COLUMN()) -> 0 | I36: =INDEX(MO_RIS_OPEX_NONGAAP,0,COLUMN()) -> 0 | J36: =INDEX(MO_RIS_OPEX_NONGAAP,0,COLUMN()) -> 0 | ... CK36: =INDEX(MO_RIS_OPEX_NONGAAP,0,COLUMN()) -> 0
A37: =INDEX(MO_RIS_OtherOperating_NONGAAP,0,COLUMN()) -> Other Non-GAAP Operating Items | C37: =INDEX(MO_RIS_OtherOperating_NONGAAP,0,COLUMN()) -> 152.102 | D37: =INDEX(MO_RIS_OtherOperating_NONGAAP,0,COLUMN()) -> -31.859 | E37: =INDEX(MO_RIS_OtherOperating_NONGAAP,0,COLUMN()) -> -21.887 | F37: =INDEX(MO_RIS_OtherOperating_NONGAAP,0,COLUMN()) -> -17.19 | G37: =INDEX(MO_RIS_OtherOperating_NONGAAP,0,COLUMN()) -> -4.342 | H37: =INDEX(MO_RIS_OtherOperating_NONGAAP,0,COLUMN()) -> -4.065 | I37: =INDEX(MO_RIS_OtherOperating_NONGAAP,0,COLUMN()) -> -4.402 | J37: =INDEX(MO_RIS_OtherOperating_NONGAAP,0,COLUMN()) -> 0 | ... CK37: =INDEX(MO_RIS_OtherOperating_NONGAAP,0,COLUMN()) -> 0
A38: =INDEX(MO_RIS_Reported_OperatingIncome_NONGAAP,0,COLUMN()) -> Company Reported Non-GAAP Operating Income | C38: =INDEX(MO_RIS_Reported_OperatingIncome_NONGAAP,0,COLUMN()) -> 148.622 | D38: =INDEX(MO_RIS_Reported_OperatingIncome_NONGAAP,0,COLUMN()) -> 135.245 | E38: =INDEX(MO_RIS_Reported_OperatingIncome_NONGAAP,0,COLUMN()) -> 502.18 | F38: =INDEX(MO_RIS_Reported_OperatingIncome_NONGAAP,0,COLUMN()) -> 829.425 | G38: =INDEX(MO_RIS_Reported_OperatingIncome_NONGAAP,0,COLUMN()) -> 117.908 | H38: =INDEX(MO_RIS_Reported_OperatingIncome_NONGAAP,0,COLUMN()) -> 200.864 | I38: =INDEX(MO_RIS_Reported_OperatingIncome_NONGAAP,0,COLUMN()) -> 294.354 | J38: =INDEX(MO_RIS_Reported_OperatingIncome_NONGAAP,0,COLUMN()) -> 228.04 | ... CK38: =INDEX(MO_RIS_Reported_OperatingIncome_NONGAAP,0,COLUMN()) -> 501566.81
A39: =INDEX(MO_RIS_IE_Net_NONGAAP,0,COLUMN()) -> Non-GAAP Net Interest Expense | C39: =INDEX(MO_RIS_IE_Net_NONGAAP,0,COLUMN()) -> -42.453 | D39: =INDEX(MO_RIS_IE_Net_NONGAAP,0,COLUMN()) -> -19.795 | E39: =INDEX(MO_RIS_IE_Net_NONGAAP,0,COLUMN()) -> -15.93 | F39: =INDEX(MO_RIS_IE_Net_NONGAAP,0,COLUMN()) -> -16.06 | G39: =INDEX(MO_RIS_IE_Net_NONGAAP,0,COLUMN()) -> -4.269 | H39: =INDEX(MO_RIS_IE_Net_NONGAAP,0,COLUMN()) -> -5.585 | I39: =INDEX(MO_RIS_IE_Net_NONGAAP,0,COLUMN()) -> -1.411 | J39: =INDEX(MO_RIS_IE_Net_NONGAAP,0,COLUMN()) -> -5.349 | ... CK39: =INDEX(MO_RIS_IE_Net_NONGAAP,0,COLUMN()) -> -42431.41
A40: =INDEX(MO_RIS_OI_NONGAAP,0,COLUMN()) -> Non-GAAP Other Items | C40: =INDEX(MO_RIS_OI_NONGAAP,0,COLUMN()) -> 14.707 | D40: =INDEX(MO_RIS_OI_NONGAAP,0,COLUMN()) -> 3.144 | E40: =INDEX(MO_RIS_OI_NONGAAP,0,COLUMN()) -> 0.508 | F40: =INDEX(MO_RIS_OI_NONGAAP,0,COLUMN()) -> 0.963 | G40: =INDEX(MO_RIS_OI_NONGAAP,0,COLUMN()) -> -1.9539925e-14 | H40: =INDEX(MO_RIS_OI_NONGAAP,0,COLUMN()) -> -7.9936058e-15 | I40: =INDEX(MO_RIS_OI_NONGAAP,0,COLUMN()) -> -1.7763568e-15 | J40: =INDEX(MO_RIS_OI_NONGAAP,0,COLUMN()) -> 2.814 | ... CK40: =INDEX(MO_RIS_OI_NONGAAP,0,COLUMN()) -> 12
A41: =INDEX(MO_MA_RIS_EBIT_NONGAAP,0,COLUMN()) -> Non-GAAP Earnings before Taxes | C41: =INDEX(MO_MA_RIS_EBIT_NONGAAP,0,COLUMN()) -> 176.368 | D41: =INDEX(MO_MA_RIS_EBIT_NONGAAP,0,COLUMN()) -> 151.896 | E41: =INDEX(MO_MA_RIS_EBIT_NONGAAP,0,COLUMN()) -> 517.602 | F41: =INDEX(MO_MA_RIS_EBIT_NONGAAP,0,COLUMN()) -> 844.522 | G41: =INDEX(MO_MA_RIS_EBIT_NONGAAP,0,COLUMN()) -> 122.177 | H41: =INDEX(MO_MA_RIS_EBIT_NONGAAP,0,COLUMN()) -> 206.449 | I41: =INDEX(MO_MA_RIS_EBIT_NONGAAP,0,COLUMN()) -> 295.765 | J41: =INDEX(MO_MA_RIS_EBIT_NONGAAP,0,COLUMN()) -> 230.575 | ... CK41: =INDEX(MO_MA_RIS_EBIT_NONGAAP,0,COLUMN()) -> 543986.22
A42: =INDEX(MO_RIS_Tax_NONGAAP,0,COLUMN()) -> Non-GAAP Provision for taxes | C42: =INDEX(MO_RIS_Tax_NONGAAP,0,COLUMN()) -> 16.084 | D42: =INDEX(MO_RIS_Tax_NONGAAP,0,COLUMN()) -> 10.513 | E42: =INDEX(MO_RIS_Tax_NONGAAP,0,COLUMN()) -> 41.188 | F42: =INDEX(MO_RIS_Tax_NONGAAP,0,COLUMN()) -> 110.116 | G42: =INDEX(MO_RIS_Tax_NONGAAP,0,COLUMN()) -> 24.647 | H42: =INDEX(MO_RIS_Tax_NONGAAP,0,COLUMN()) -> 36.001 | I42: =INDEX(MO_RIS_Tax_NONGAAP,0,COLUMN()) -> 50.303 | J42: =INDEX(MO_RIS_Tax_NONGAAP,0,COLUMN()) -> 15.642 | ... CK42: =INDEX(MO_RIS_Tax_NONGAAP,0,COLUMN()) -> 81597.933
A43: =INDEX(MO_RIS_NI_NONGAAP_Diluted,0,COLUMN()) -> Non-GAAP Net Income Attributable to Common Shareholders | C43: =INDEX(MO_RIS_NI_NONGAAP_Diluted,0,COLUMN()) -> 160.284 | D43: =INDEX(MO_RIS_NI_NONGAAP_Diluted,0,COLUMN()) -> 141.383 | E43: =INDEX(MO_RIS_NI_NONGAAP_Diluted,0,COLUMN()) -> 476.414 | F43: =INDEX(MO_RIS_NI_NONGAAP_Diluted,0,COLUMN()) -> 734.406 | G43: =INDEX(MO_RIS_NI_NONGAAP_Diluted,0,COLUMN()) -> 97.53 | H43: =INDEX(MO_RIS_NI_NONGAAP_Diluted,0,COLUMN()) -> 170.448 | I43: =INDEX(MO_RIS_NI_NONGAAP_Diluted,0,COLUMN()) -> 245.462 | J43: =INDEX(MO_RIS_NI_NONGAAP_Diluted,0,COLUMN()) -> 214.933 | ... CK43: =INDEX(MO_RIS_NI_NONGAAP_Diluted,0,COLUMN()) -> 462388.29
A44: GAAP Adjustments | C44: =+Model!C416+Model!C417+Model!C418+Model!C419+Model!C420+Model!C421 -> 190.325 | D44: =+Model!D416+Model!D417+Model!D418+Model!D419+Model!D420+Model!D421 -> 209.37 | E44: =+Model!E416+Model!E417+Model!E418+Model!E419+Model!E420+Model!E421 -> 223.268 | F44: =+Model!F416+Model!F417+Model!F418+Model!F419+Model!F420+Model!F421 -> 153.316 | G44: =+Model!G416+Model!G417+Model!G418+Model!G419+Model!G420+Model!G421 -> 37.093 | H44: =+Model!H416+Model!H417+Model!H418+Model!H419+Model!H420+Model!H421 -> 51.402 | I44: =+Model!I416+Model!I417+Model!I418+Model!I419+Model!I420+Model!I421 -> 36.382 | J44: =+Model!J416+Model!J417+Model!J418+Model!J419+Model!J420+Model!J421 -> 40.96 | ... CK44: =+Model!CK416+Model!CK417+Model!CK418+Model!CK419+Model!CK420+Model!CK421 -> 2034.4574
A45: =INDEX(MO_RIS_NI_GAAP_Diluted,0,COLUMN()) -> GAAP Net Income - Diluted | C45: =INDEX(MO_RIS_NI_GAAP_Diluted,0,COLUMN()) -> -30.041 | D45: =INDEX(MO_RIS_NI_GAAP_Diluted,0,COLUMN()) -> -67.987 | E45: =INDEX(MO_RIS_NI_GAAP_Diluted,0,COLUMN()) -> 253.146 | F45: =INDEX(MO_RIS_NI_GAAP_Diluted,0,COLUMN()) -> 581.09 | G45: =INDEX(MO_RIS_NI_GAAP_Diluted,0,COLUMN()) -> 60.437 | H45: =INDEX(MO_RIS_NI_GAAP_Diluted,0,COLUMN()) -> 119.046 | I45: =INDEX(MO_RIS_NI_GAAP_Diluted,0,COLUMN()) -> 209.08 | J45: =INDEX(MO_RIS_NI_GAAP_Diluted,0,COLUMN()) -> 173.973 | ... CK45: =INDEX(MO_RIS_NI_GAAP_Diluted,0,COLUMN()) -> 460353.83
A47: =INDEX(MO_RIS_EPS_WAD,0,COLUMN()) -> GAAP Earnings Per Share - WAD | C47: =INDEX(MO_RIS_EPS_WAD,0,COLUMN()) -> -0.0013701685 | D47: =INDEX(MO_RIS_EPS_WAD,0,COLUMN()) -> -0.0030927136 | E47: =INDEX(MO_RIS_EPS_WAD,0,COLUMN()) -> 0.010750505 | F47: =INDEX(MO_RIS_EPS_WAD,0,COLUMN()) -> 0.023569003 | G47: =INDEX(MO_RIS_EPS_WAD,0,COLUMN()) -> 0.0024221849 | H47: =INDEX(MO_RIS_EPS_WAD,0,COLUMN()) -> 0.0047760305 | I47: =INDEX(MO_RIS_EPS_WAD,0,COLUMN()) -> 0.0083120642 | J47: =INDEX(MO_RIS_EPS_WAD,0,COLUMN()) -> 0.0069922816 | ... CK47: =INDEX(MO_RIS_EPS_WAD,0,COLUMN()) -> 18.821313
A48: =INDEX(MO_RIS_ShareCount_WAD_Adj,0,COLUMN()) -> Adjusted Shares Outstanding - WAD | C48: =INDEX(MO_RIS_ShareCount_WAD_Adj,0,COLUMN()) -> 21925.04 | D48: =INDEX(MO_RIS_ShareCount_WAD_Adj,0,COLUMN()) -> 21982.96 | E48: =INDEX(MO_RIS_ShareCount_WAD_Adj,0,COLUMN()) -> 23547.36 | F48: =INDEX(MO_RIS_ShareCount_WAD_Adj,0,COLUMN()) -> 24654.84 | G48: =INDEX(MO_RIS_ShareCount_WAD_Adj,0,COLUMN()) -> 24951.44 | H48: =INDEX(MO_RIS_ShareCount_WAD_Adj,0,COLUMN()) -> 24925.72 | I48: =INDEX(MO_RIS_ShareCount_WAD_Adj,0,COLUMN()) -> 25153.8 | J48: =INDEX(MO_RIS_ShareCount_WAD_Adj,0,COLUMN()) -> 24880.72 | ... CK48: =INDEX(MO_RIS_ShareCount_WAD_Adj,0,COLUMN()) -> 24459.178
A50: Non-GAAP Financials
A51: =INDEX(MO_RIS_EBITDA_Adj,0,COLUMN()) -> Non-GAAP EBITDA | C51: =INDEX(MO_RIS_EBITDA_Adj,0,COLUMN()) -> 301.045 | D51: =INDEX(MO_RIS_EBITDA_Adj,0,COLUMN()) -> 300.009 | E51: =INDEX(MO_RIS_EBITDA_Adj,0,COLUMN()) -> 659.169 | F51: =INDEX(MO_RIS_EBITDA_Adj,0,COLUMN()) -> 974.63 | G51: =INDEX(MO_RIS_EBITDA_Adj,0,COLUMN()) -> 155.799 | H51: =INDEX(MO_RIS_EBITDA_Adj,0,COLUMN()) -> 239.859 | I51: =INDEX(MO_RIS_EBITDA_Adj,0,COLUMN()) -> 334.202 | J51: =INDEX(MO_RIS_EBITDA_Adj,0,COLUMN()) -> 269.141 | ... CK51: =INDEX(MO_RIS_EBITDA_Adj,0,COLUMN()) -> 503437.93
A52: =INDEX(MO_RIS_NI_NONGAAP_Diluted,0,COLUMN()) -> Non-GAAP Net Income Attributable to Common Shareholders | C52: =INDEX(MO_RIS_NI_NONGAAP_Diluted,0,COLUMN()) -> 160.284 | D52: =INDEX(MO_RIS_NI_NONGAAP_Diluted,0,COLUMN()) -> 141.383 | E52: =INDEX(MO_RIS_NI_NONGAAP_Diluted,0,COLUMN()) -> 476.414 | F52: =INDEX(MO_RIS_NI_NONGAAP_Diluted,0,COLUMN()) -> 734.406 | G52: =INDEX(MO_RIS_NI_NONGAAP_Diluted,0,COLUMN()) -> 97.53 | H52: =INDEX(MO_RIS_NI_NONGAAP_Diluted,0,COLUMN()) -> 170.448 | I52: =INDEX(MO_RIS_NI_NONGAAP_Diluted,0,COLUMN()) -> 245.462 | J52: =INDEX(MO_RIS_NI_NONGAAP_Diluted,0,COLUMN()) -> 214.933 | ... CK52: =INDEX(MO_RIS_NI_NONGAAP_Diluted,0,COLUMN()) -> 462388.29
A53: =+Model!A433 -> Non-GAAP Adjusted Earnings Per Share - WAD | C53: =+Model!C433 -> 0.0073105454 | D53: =+Model!D433 -> 0.0064314815 | E53: =+Model!E433 -> 0.020232162 | F53: =+Model!F433 -> 0.029787498 | G53: =+Model!G433 -> 0.0039087924 | H53: =+Model!H433 -> 0.0068382378 | I53: =+Model!I433 -> 0.009758446 | J53: =+Model!J433 -> 0.0086385362 | ... CK53: =+Model!CK433 -> 18.90449
A55: Margin Analysis
A56: =INDEX(MO_MA_COGS_NONGAAP,0,COLUMN()) -> Non-GAAP COGS Margin, % | C56: =INDEX(MO_MA_COGS_NONGAAP,0,COLUMN()) -> 0.60055056 | D56: =INDEX(MO_MA_COGS_NONGAAP,0,COLUMN()) -> 0.6139383 | E56: =INDEX(MO_MA_COGS_NONGAAP,0,COLUMN()) -> 0.54884234 | F56: =INDEX(MO_MA_COGS_NONGAAP,0,COLUMN()) -> 0.48094664 | G56: =INDEX(MO_MA_COGS_NONGAAP,0,COLUMN()) -> 0.49626815 | H56: =INDEX(MO_MA_COGS_NONGAAP,0,COLUMN()) -> 0.47966714 | I56: =INDEX(MO_MA_COGS_NONGAAP,0,COLUMN()) -> 0.46919551 | J56: =INDEX(MO_MA_COGS_NONGAAP,0,COLUMN()) -> 0.468401 | ... CK56: =INDEX(MO_MA_COGS_NONGAAP,0,COLUMN()) -> 0.24801886
A57: =INDEX(MO_MA_RD_NONGAAP,0,COLUMN()) -> Non-GAAP R&D Margin, % | C57: =INDEX(MO_MA_RD_NONGAAP,0,COLUMN()) -> 0.22128561 | D57: =INDEX(MO_MA_RD_NONGAAP,0,COLUMN()) -> 0.2547807 | E57: =INDEX(MO_MA_RD_NONGAAP,0,COLUMN()) -> 0.22319702 | F57: =INDEX(MO_MA_RD_NONGAAP,0,COLUMN()) -> 0.22807328 | G57: =INDEX(MO_MA_RD_NONGAAP,0,COLUMN()) -> 0.2806038 | H57: =INDEX(MO_MA_RD_NONGAAP,0,COLUMN()) -> 0.24851236 | I57: =INDEX(MO_MA_RD_NONGAAP,0,COLUMN()) -> 0.21713797 | J57: =INDEX(MO_MA_RD_NONGAAP,0,COLUMN()) -> 0.2460019 | ... CK57: =INDEX(MO_MA_RD_NONGAAP,0,COLUMN()) -> 0.067011031
A58: =INDEX(MO_MA_SGA_NONGAAP,0,COLUMN()) -> Non-GAAP SG&A Margin, % | C58: =INDEX(MO_MA_SGA_NONGAAP,0,COLUMN()) -> 0.090357588 | D58: =INDEX(MO_MA_SGA_NONGAAP,0,COLUMN()) -> 0.10020097 | E58: =INDEX(MO_MA_SGA_NONGAAP,0,COLUMN()) -> 0.092411359 | F58: =INDEX(MO_MA_SGA_NONGAAP,0,COLUMN()) -> 0.087816195 | G58: =INDEX(MO_MA_SGA_NONGAAP,0,COLUMN()) -> 0.10033767 | H58: =INDEX(MO_MA_SGA_NONGAAP,0,COLUMN()) -> 0.083364456 | I58: =INDEX(MO_MA_SGA_NONGAAP,0,COLUMN()) -> 0.072864605 | J58: =INDEX(MO_MA_SGA_NONGAAP,0,COLUMN()) -> 0.079580667 | ... CK58: =INDEX(MO_MA_SGA_NONGAAP,0,COLUMN()) -> 0.014392413
A59: =INDEX(MO_MA_OPEX_NONGAAP,0,COLUMN()) -> Non-GAAP OPEX Margin, % | C59: =INDEX(MO_MA_OPEX_NONGAAP,0,COLUMN()) -> 0 | D59: =INDEX(MO_MA_OPEX_NONGAAP,0,COLUMN()) -> 0 | E59: =INDEX(MO_MA_OPEX_NONGAAP,0,COLUMN()) -> 0 | F59: =INDEX(MO_MA_OPEX_NONGAAP,0,COLUMN()) -> 0 | G59: =INDEX(MO_MA_OPEX_NONGAAP,0,COLUMN()) -> 0 | H59: =INDEX(MO_MA_OPEX_NONGAAP,0,COLUMN()) -> 0 | I59: =INDEX(MO_MA_OPEX_NONGAAP,0,COLUMN()) -> 0 | J59: =INDEX(MO_MA_OPEX_NONGAAP,0,COLUMN()) -> 0 | ... CK59: =INDEX(MO_MA_OPEX_NONGAAP,0,COLUMN()) -> 0
A60: =INDEX(MO_MA_OperatingIncome_NONGAAP,0,COLUMN()) -> Non-GAAP Operating Income Margin, % | C60: =INDEX(MO_MA_OperatingIncome_NONGAAP,0,COLUMN()) -> 0.087806243 | D60: =INDEX(MO_MA_OperatingIncome_NONGAAP,0,COLUMN()) -> 0.031080027 | E60: =INDEX(MO_MA_OperatingIncome_NONGAAP,0,COLUMN()) -> 0.13554928 | F60: =INDEX(MO_MA_OperatingIncome_NONGAAP,0,COLUMN()) -> 0.20316389 | G60: =INDEX(MO_MA_OperatingIncome_NONGAAP,0,COLUMN()) -> 0.12279038 | H60: =INDEX(MO_MA_OperatingIncome_NONGAAP,0,COLUMN()) -> 0.18845605 | I60: =INDEX(MO_MA_OperatingIncome_NONGAAP,0,COLUMN()) -> 0.24080192 | J60: =INDEX(MO_MA_OperatingIncome_NONGAAP,0,COLUMN()) -> 0.20601643 | ... CK60: =INDEX(MO_MA_OperatingIncome_NONGAAP,0,COLUMN()) -> 0.67057769
A61: =INDEX(MO_MA_OperatingIncome,0,COLUMN()) -> Company Reported Non-GAAP Operating Income Margin, % | C61: =INDEX(MO_MA_OperatingIncome,0,COLUMN()) -> 0.043395071 | D61: =INDEX(MO_MA_OperatingIncome,0,COLUMN()) -> 0.040657519 | E61: =INDEX(MO_MA_OperatingIncome,0,COLUMN()) -> 0.14172628 | F61: =INDEX(MO_MA_OperatingIncome,0,COLUMN()) -> 0.20746361 | G61: =INDEX(MO_MA_OperatingIncome,0,COLUMN()) -> 0.12748506 | H61: =INDEX(MO_MA_OperatingIncome,0,COLUMN()) -> 0.19234872 | I61: =INDEX(MO_MA_OperatingIncome,0,COLUMN()) -> 0.24445773 | J61: =INDEX(MO_MA_OperatingIncome,0,COLUMN()) -> 0.20601643 | ... CK61: =INDEX(MO_MA_OperatingIncome,0,COLUMN()) -> 0.67057769
A63: Cash Flow Analysis
A64: =INDEX(MO_CFSum_CFO_BeforeWC,0,COLUMN()) -> Operating Cash Flow before WC | C64: =INDEX(MO_CFSum_CFO_BeforeWC,0,COLUMN()) -> 282.693 | D64: =INDEX(MO_CFSum_CFO_BeforeWC,0,COLUMN()) -> 351.392 | E64: =INDEX(MO_CFSum_CFO_BeforeWC,0,COLUMN()) -> 524.098 | F64: =INDEX(MO_CFSum_CFO_BeforeWC,0,COLUMN()) -> 907.007 | G64: =INDEX(MO_CFSum_CFO_BeforeWC,0,COLUMN()) -> 150.903 | H64: =INDEX(MO_CFSum_CFO_BeforeWC,0,COLUMN()) -> 235.223 | I64: =INDEX(MO_CFSum_CFO_BeforeWC,0,COLUMN()) -> 328.18 | J64: =INDEX(MO_CFSum_CFO_BeforeWC,0,COLUMN()) -> 222.188 | ... CK64: =INDEX(MO_CFSum_CFO_BeforeWC,0,COLUMN()) -> 462583.33
A65: Change in WC | C65: =SUM(OFFSET(INDEX(MO_CFS_CFO_BeforeWC,0,COLUMN()),1,0,ROW(INDEX(MO_CFS_CFO,0,COLUMN()))-ROW(INDEX(MO_CFS_CFO_BeforeWC,0,COLUMN()))-1,1)) -> -33.333 | D65: =SUM(OFFSET(INDEX(MO_CFS_CFO_BeforeWC,0,COLUMN()),1,0,ROW(INDEX(MO_CFS_CFO,0,COLUMN()))-ROW(INDEX(MO_CFS_CFO_BeforeWC,0,COLUMN()))-1,1)) -> 136.415 | E65: =SUM(OFFSET(INDEX(MO_CFS_CFO_BeforeWC,0,COLUMN()),1,0,ROW(INDEX(MO_CFS_CFO,0,COLUMN()))-ROW(INDEX(MO_CFS_CFO_BeforeWC,0,COLUMN()))-1,1)) -> 151.699 | F65: =SUM(OFFSET(INDEX(MO_CFS_CFO_BeforeWC,0,COLUMN()),1,0,ROW(INDEX(MO_CFS_CFO,0,COLUMN()))-ROW(INDEX(MO_CFS_CFO_BeforeWC,0,COLUMN()))-1,1)) -> 2.149 | G65: =SUM(OFFSET(INDEX(MO_CFS_CFO_BeforeWC,0,COLUMN()),1,0,ROW(INDEX(MO_CFS_CFO,0,COLUMN()))-ROW(INDEX(MO_CFS_CFO_BeforeWC,0,COLUMN()))-1,1)) -> -160.111 | H65: =SUM(OFFSET(INDEX(MO_CFS_CFO_BeforeWC,0,COLUMN()),1,0,ROW(INDEX(MO_CFS_CFO,0,COLUMN()))-ROW(INDEX(MO_CFS_CFO_BeforeWC,0,COLUMN()))-1,1)) -> -34.337 | I65: =SUM(OFFSET(INDEX(MO_CFS_CFO_BeforeWC,0,COLUMN()),1,0,ROW(INDEX(MO_CFS_CFO,0,COLUMN()))-ROW(INDEX(MO_CFS_CFO_BeforeWC,0,COLUMN()))-1,1)) -> -146.695 | J65: =SUM(OFFSET(INDEX(MO_CFS_CFO_BeforeWC,0,COLUMN()),1,0,ROW(INDEX(MO_CFS_CFO,0,COLUMN()))-ROW(INDEX(MO_CFS_CFO_BeforeWC,0,COLUMN()))-1,1)) -> 228.821 | ... CK65: =SUM(OFFSET(INDEX(MO_CFS_CFO_BeforeWC,0,COLUMN()),1,0,ROW(INDEX(MO_CFS_CFO,0,COLUMN()))-ROW(INDEX(MO_CFS_CFO_BeforeWC,0,COLUMN()))-1,1)) -> -14188.499
A66: Operating Cash Flow after WC | C66: =SUM(C64:C65) -> 249.36 | D66: =SUM(D64:D65) -> 487.807 | E66: =SUM(E64:E65) -> 675.797 | F66: =SUM(F64:F65) -> 909.156 | G66: =SUM(G64:G65) -> -9.208 | H66: =SUM(H64:H65) -> 200.886 | I66: =SUM(I64:I65) -> 181.485 | J66: =SUM(J64:J65) -> 451.009 | ... CK66: =SUM(CK64:CK65) -> 448394.84
A67: =INDEX(MO_CFSum_Capex,0,COLUMN()) -> Capex | C67: =INDEX(MO_CFSum_Capex,0,COLUMN()) -> -407.67 | D67: =INDEX(MO_CFSum_Capex,0,COLUMN()) -> -77.601 | E67: =INDEX(MO_CFSum_Capex,0,COLUMN()) -> -97.89 | F67: =INDEX(MO_CFSum_Capex,0,COLUMN()) -> -138.735 | G67: =INDEX(MO_CFSum_Capex,0,COLUMN()) -> -28.923 | H67: =INDEX(MO_CFSum_Capex,0,COLUMN()) -> -61.944 | I67: =INDEX(MO_CFSum_Capex,0,COLUMN()) -> -44.684 | J67: =INDEX(MO_CFSum_Capex,0,COLUMN()) -> -47.758 | ... CK67: =INDEX(MO_CFSum_Capex,0,COLUMN()) -> -1300
A68: Core FCF, Pre Div | C68: =SUM(C66:C67) -> -158.31 | D68: =SUM(D66:D67) -> 410.206 | E68: =SUM(E66:E67) -> 577.907 | F68: =SUM(F66:F67) -> 770.421 | G68: =SUM(G66:G67) -> -38.131 | H68: =SUM(H66:H67) -> 138.942 | I68: =SUM(I66:I67) -> 136.801 | J68: =SUM(J66:J67) -> 403.251 | ... CK68: =SUM(CK66:CK67) -> 447094.84
A69: =INDEX(MO_CFSum_Dividend,0,COLUMN()) -> Dividend Paid | C69: =INDEX(MO_CFSum_Dividend,0,COLUMN()) -> 0 | D69: =INDEX(MO_CFSum_Dividend,0,COLUMN()) -> 0 | E69: =INDEX(MO_CFSum_Dividend,0,COLUMN()) -> 0 | F69: =INDEX(MO_CFSum_Dividend,0,COLUMN()) -> 0 | G69: =INDEX(MO_CFSum_Dividend,0,COLUMN()) -> 0 | H69: =INDEX(MO_CFSum_Dividend,0,COLUMN()) -> 0 | I69: =INDEX(MO_CFSum_Dividend,0,COLUMN()) -> 0 | J69: =INDEX(MO_CFSum_Dividend,0,COLUMN()) -> -46.866 | ... CK69: =INDEX(MO_CFSum_Dividend,0,COLUMN()) -> -24221
A70: Core FCF, Post Div | C70: =SUM(C68:C69) -> -158.31 | D70: =SUM(D68:D69) -> 410.206 | E70: =SUM(E68:E69) -> 577.907 | F70: =SUM(F68:F69) -> 770.421 | G70: =SUM(G68:G69) -> -38.131 | H70: =SUM(H68:H69) -> 138.942 | I70: =SUM(I68:I69) -> 136.801 | J70: =SUM(J68:J69) -> 356.385 | ... CK70: =SUM(CK68:CK69) -> 422873.84
A71: =INDEX(MO_CFSum_Acquisition,0,COLUMN()) -> Acquisitions | C71: =INDEX(MO_CFSum_Acquisition,0,COLUMN()) -> -27.948 | D71: =INDEX(MO_CFSum_Acquisition,0,COLUMN()) -> 0 | E71: =INDEX(MO_CFSum_Acquisition,0,COLUMN()) -> 0 | F71: =INDEX(MO_CFSum_Acquisition,0,COLUMN()) -> -348.884 | G71: =INDEX(MO_CFSum_Acquisition,0,COLUMN()) -> 0 | H71: =INDEX(MO_CFSum_Acquisition,0,COLUMN()) -> 0 | I71: =INDEX(MO_CFSum_Acquisition,0,COLUMN()) -> 0 | J71: =INDEX(MO_CFSum_Acquisition,0,COLUMN()) -> 0 | ... CK71: =INDEX(MO_CFSum_Acquisition,0,COLUMN()) -> 0
A72: =INDEX(MO_CFSum_Divestiture,0,COLUMN()) -> Divestiture | C72: =INDEX(MO_CFSum_Divestiture,0,COLUMN()) -> 0 | D72: =INDEX(MO_CFSum_Divestiture,0,COLUMN()) -> 0 | E72: =INDEX(MO_CFSum_Divestiture,0,COLUMN()) -> 0 | F72: =INDEX(MO_CFSum_Divestiture,0,COLUMN()) -> 0 | G72: =INDEX(MO_CFSum_Divestiture,0,COLUMN()) -> 0 | H72: =INDEX(MO_CFSum_Divestiture,0,COLUMN()) -> 0 | I72: =INDEX(MO_CFSum_Divestiture,0,COLUMN()) -> 0 | J72: =INDEX(MO_CFSum_Divestiture,0,COLUMN()) -> 0 | ... CK72: =INDEX(MO_CFSum_Divestiture,0,COLUMN()) -> 0
A73: New Equity Issuance | C73: =INDEX(MO_CFSum_NetShares,0,COLUMN()) -> -350.089 | D73: =INDEX(MO_CFSum_NetShares,0,COLUMN()) -> 59.954 | E73: =INDEX(MO_CFSum_NetShares,0,COLUMN()) -> 192.592 | F73: =INDEX(MO_CFSum_NetShares,0,COLUMN()) -> 248.65 | G73: =INDEX(MO_CFSum_NetShares,0,COLUMN()) -> 46.036 | H73: =INDEX(MO_CFSum_NetShares,0,COLUMN()) -> 14.796 | I73: =INDEX(MO_CFSum_NetShares,0,COLUMN()) -> 27.595 | J73: =INDEX(MO_CFSum_NetShares,0,COLUMN()) -> -54.782 | ... CK73: =INDEX(MO_CFSum_NetShares,0,COLUMN()) -> 0
A74: New Debt Issuance | C74: =INDEX(MO_CFSum_NetDebtIssuance,0,COLUMN()) -> 0 | D74: =INDEX(MO_CFSum_NetDebtIssuance,0,COLUMN()) -> 0 | E74: =INDEX(MO_CFSum_NetDebtIssuance,0,COLUMN()) -> -0.571 | F74: =INDEX(MO_CFSum_NetDebtIssuance,0,COLUMN()) -> -11.927 | G74: =INDEX(MO_CFSum_NetDebtIssuance,0,COLUMN()) -> -0.515 | H74: =INDEX(MO_CFSum_NetDebtIssuance,0,COLUMN()) -> -0.496 | I74: =INDEX(MO_CFSum_NetDebtIssuance,0,COLUMN()) -> 1.011 | J74: =INDEX(MO_CFSum_NetDebtIssuance,0,COLUMN()) -> -2.049 | ... CK74: =INDEX(MO_CFSum_NetDebtIssuance,0,COLUMN()) -> 0
A75: Other Items | C75: =+Model!C889+Model!C909+Model!C912+Model!C888+Model!C880+Model!C881+Model!C882+Model!C887+Model!C908+Model!C883 -> 227.066 | D75: =+Model!D889+Model!D909+Model!D912+Model!D888+Model!D880+Model!D881+Model!D882+Model!D887+Model!D908+Model!D883 -> -440.627 | E75: =+Model!E889+Model!E909+Model!E912+Model!E888+Model!E880+Model!E881+Model!E882+Model!E887+Model!E908+Model!E883 -> -551.788 | F75: =+Model!F889+Model!F909+Model!F912+Model!F888+Model!F880+Model!F881+Model!F882+Model!F887+Model!F908+Model!F883 -> -655.745 | G75: =+Model!G889+Model!G909+Model!G912+Model!G888+Model!G880+Model!G881+Model!G882+Model!G887+Model!G908+Model!G883 -> -306.131 | H75: =+Model!H889+Model!H909+Model!H912+Model!H888+Model!H880+Model!H881+Model!H882+Model!H887+Model!H908+Model!H883 -> -22.759 | I75: =+Model!I889+Model!I909+Model!I912+Model!I888+Model!I880+Model!I881+Model!I882+Model!I887+Model!I908+Model!I883 -> -139.637 | J75: =+Model!J889+Model!J909+Model!J912+Model!J888+Model!J880+Model!J881+Model!J882+Model!J887+Model!J908+Model!J883 -> -92.156 | ... CK75: =+Model!CK889+Model!CK909+Model!CK912+Model!CK888+Model!CK880+Model!CK881+Model!CK882+Model!CK887+Model!CK908+Model!CK883 -> 0
A76: Change in Cash Position | C76: =SUM(C70:C75) -> -309.281 | D76: =SUM(D70:D75) -> 29.533 | E76: =SUM(E70:E75) -> 218.14 | F76: =SUM(F70:F75) -> 2.515 | G76: =SUM(G70:G75) -> -298.741 | H76: =SUM(H70:H75) -> 130.483 | I76: =SUM(I70:I75) -> 25.77 | J76: =SUM(J70:J75) -> 207.398 | ... CK76: =SUM(CK70:CK75) -> 422873.84
A78: Operating Cash Flow Per Share | C78: =INDEX(SP_CFA_CFO,0,COLUMN())/INDEX(SP_CS_ShareCount,0,COLUMN()) -> 0.011577445 | D78: =INDEX(SP_CFA_CFO,0,COLUMN())/INDEX(SP_CS_ShareCount,0,COLUMN()) -> 0.021720243 | E78: =INDEX(SP_CFA_CFO,0,COLUMN())/INDEX(SP_CS_ShareCount,0,COLUMN()) -> 0.028061737 | F78: =INDEX(SP_CFA_CFO,0,COLUMN())/INDEX(SP_CS_ShareCount,0,COLUMN()) -> 0.036371104 | G78: =INDEX(SP_CFA_CFO,0,COLUMN())/INDEX(SP_CS_ShareCount,0,COLUMN()) -> -0.00036692592 | H78: =INDEX(SP_CFA_CFO,0,COLUMN())/INDEX(SP_CS_ShareCount,0,COLUMN()) -> 0.0080642078 | I78: =INDEX(SP_CFA_CFO,0,COLUMN())/INDEX(SP_CS_ShareCount,0,COLUMN()) -> 0.0071724857 | J78: =INDEX(SP_CFA_CFO,0,COLUMN())/INDEX(SP_CS_ShareCount,0,COLUMN()) -> 0.018226853 | ... CK78: =INDEX(SP_CFA_CFO,0,COLUMN())/INDEX(SP_CS_ShareCount,0,COLUMN()) -> 18.332376
A79: Core Free Cash Flow Per Share, Pre Div | C79: =INDEX(SP_CFA_FCF_PreDiv,0,COLUMN())/INDEX(SP_CS_ShareCount,0,COLUMN()) -> -0.0073501177 | D79: =INDEX(SP_CFA_FCF_PreDiv,0,COLUMN())/INDEX(SP_CS_ShareCount,0,COLUMN()) -> 0.018264958 | E79: =INDEX(SP_CFA_FCF_PreDiv,0,COLUMN())/INDEX(SP_CS_ShareCount,0,COLUMN()) -> 0.023996961 | F79: =INDEX(SP_CFA_FCF_PreDiv,0,COLUMN())/INDEX(SP_CS_ShareCount,0,COLUMN()) -> 0.030820962 | G79: =INDEX(SP_CFA_FCF_PreDiv,0,COLUMN())/INDEX(SP_CS_ShareCount,0,COLUMN()) -> -0.001519467 | H79: =INDEX(SP_CFA_FCF_PreDiv,0,COLUMN())/INDEX(SP_CS_ShareCount,0,COLUMN()) -> 0.0055775771 | I79: =INDEX(SP_CFA_FCF_PreDiv,0,COLUMN())/INDEX(SP_CS_ShareCount,0,COLUMN()) -> 0.0054065251 | J79: =INDEX(SP_CFA_FCF_PreDiv,0,COLUMN())/INDEX(SP_CS_ShareCount,0,COLUMN()) -> 0.016296785 | ... CK79: =INDEX(SP_CFA_FCF_PreDiv,0,COLUMN())/INDEX(SP_CS_ShareCount,0,COLUMN()) -> 18.279226
A80: Dividend Per Share | C80: =INDEX(MO_CFSum_DPS,0,COLUMN()) -> 0 | D80: =INDEX(MO_CFSum_DPS,0,COLUMN()) -> 0 | E80: =INDEX(MO_CFSum_DPS,0,COLUMN()) -> 0 | F80: =INDEX(MO_CFSum_DPS,0,COLUMN()) -> 0 | G80: =INDEX(MO_CFSum_DPS,0,COLUMN()) -> 0 | H80: =INDEX(MO_CFSum_DPS,0,COLUMN()) -> 0 | I80: =INDEX(MO_CFSum_DPS,0,COLUMN()) -> 0 | J80: =INDEX(MO_CFSum_DPS,0,COLUMN()) -> 0.001875 | ... CK80: =INDEX(MO_CFSum_DPS,0,COLUMN()) -> 1
A81: Dividend Payout Ratio vs Core FCF, Pre Div | C81: =C80/C79 -> 0 | D81: =D80/D79 -> 0 | E81: =E80/E79 -> 0 | F81: =F80/F79 -> 0 | G81: =G80/G79 -> 0 | H81: =H80/H79 -> 0 | I81: =I80/I79 -> 0 | J81: =J80/J79 -> 0.11505337 | ... CK81: =CK80/CK79 -> 0.054706912
A82: Dividend Payout Ratio vs Earnings Per Share | C82: =C80/C53 -> 0 | D82: =D80/D53 -> 0 | E82: =E80/E53 -> 0 | F82: =F80/F53 -> 0 | G82: =G80/G53 -> 0 | H82: =H80/H53 -> 0 | I82: =I80/I53 -> 0 | J82: =J80/J53 -> 0.21705066 | ... CK82: =CK80/CK53 -> 0.052897486
A84: Balance Sheet Ratios
A85: Net Debt / EBITDA | D85: =INDEX(MO_BSS_Debt_Net,0,COLUMN())/INDEX(SP_BSR_EBITDA_LTM,0,COLUMN()) -> -5.6790863 | E85: =INDEX(MO_BSS_Debt_Net,0,COLUMN())/INDEX(SP_BSR_EBITDA_LTM,0,COLUMN()) -> -3.742855 | F85: =INDEX(MO_BSS_Debt_Net,0,COLUMN())/INDEX(SP_BSR_EBITDA_LTM,0,COLUMN()) -> -3.189043 | J85: =INDEX(MO_BSS_Debt_Net,0,COLUMN())/INDEX(SP_BSR_EBITDA_LTM,0,COLUMN()) -> -3.7125939 | K85: =INDEX(MO_BSS_Debt_Net,0,COLUMN())/INDEX(SP_BSR_EBITDA_LTM,0,COLUMN()) -> -3.7125939 | L85: =INDEX(MO_BSS_Debt_Net,0,COLUMN())/INDEX(SP_BSR_EBITDA_LTM,0,COLUMN()) -> -3.6563159 | M85: =INDEX(MO_BSS_Debt_Net,0,COLUMN())/INDEX(SP_BSR_EBITDA_LTM,0,COLUMN()) -> -3.0298614 | N85: =INDEX(MO_BSS_Debt_Net,0,COLUMN())/INDEX(SP_BSR_EBITDA_LTM,0,COLUMN()) -> -3.5308334 | O85: =INDEX(MO_BSS_Debt_Net,0,COLUMN())/INDEX(SP_BSR_EBITDA_LTM,0,COLUMN()) -> -3.9702586 | P85: =INDEX(MO_BSS_Debt_Net,0,COLUMN())/INDEX(SP_BSR_EBITDA_LTM,0,COLUMN()) -> -3.9702586 | Q85: =INDEX(MO_BSS_Debt_Net,0,COLUMN())/INDEX(SP_BSR_EBITDA_LTM,0,COLUMN()) -> -3.3150165 | ... CK85: =INDEX(MO_BSS_Debt_Net,0,COLUMN())/INDEX(SP_BSR_EBITDA_LTM,0,COLUMN()) -> -2.9300138
A86: Net Debt / Cash Flow | C86: =INDEX(MO_BSS_Debt_Net,0,COLUMN())/INDEX(SP_BSR_CashFlow_LTM,0,COLUMN()) -> -4.931649 | D86: =INDEX(MO_BSS_Debt_Net,0,COLUMN())/INDEX(SP_BSR_CashFlow_LTM,0,COLUMN()) -> -3.4927277 | E86: =INDEX(MO_BSS_Debt_Net,0,COLUMN())/INDEX(SP_BSR_CashFlow_LTM,0,COLUMN()) -> -3.650762 | F86: =INDEX(MO_BSS_Debt_Net,0,COLUMN())/INDEX(SP_BSR_CashFlow_LTM,0,COLUMN()) -> -3.4187059 | J86: =INDEX(MO_BSS_Debt_Net,0,COLUMN())/INDEX(SP_BSR_CashFlow_LTM,0,COLUMN()) -> -4.5001347 | K86: =INDEX(MO_BSS_Debt_Net,0,COLUMN())/INDEX(SP_BSR_CashFlow_LTM,0,COLUMN()) -> -4.5001347 | L86: =INDEX(MO_BSS_Debt_Net,0,COLUMN())/INDEX(SP_BSR_CashFlow_LTM,0,COLUMN()) -> -3.6619506 | M86: =INDEX(MO_BSS_Debt_Net,0,COLUMN())/INDEX(SP_BSR_CashFlow_LTM,0,COLUMN()) -> -3.2259187 | N86: =INDEX(MO_BSS_Debt_Net,0,COLUMN())/INDEX(SP_BSR_CashFlow_LTM,0,COLUMN()) -> -3.4061357 | O86: =INDEX(MO_BSS_Debt_Net,0,COLUMN())/INDEX(SP_BSR_CashFlow_LTM,0,COLUMN()) -> -3.9489323 | P86: =INDEX(MO_BSS_Debt_Net,0,COLUMN())/INDEX(SP_BSR_CashFlow_LTM,0,COLUMN()) -> -3.9489323 | Q86: =INDEX(MO_BSS_Debt_Net,0,COLUMN())/INDEX(SP_BSR_CashFlow_LTM,0,COLUMN()) -> -3.6617799 | ... CK86: =INDEX(MO_BSS_Debt_Net,0,COLUMN())/INDEX(SP_BSR_CashFlow_LTM,0,COLUMN()) -> -3.2896902
