Workbook

Sheet ANNUAL_FINANCIALS
B2: $ in millions | C2: Historical (Annual) | F2: Projections (Annual)
B3: Company2167 (FYE 12/31) | C3: FY2022A | D3: FY2023A | E3: FY2024A | F3: FY2025E | G3: FY2026E | H3: FY2027E
B5: Total Revenue | C5: 2802.574 | D5: =SUM(QUARTERLY_KPIs!$D$10:$G$10) -> 3055 | E5: =SUM(QUARTERLY_KPIs!$H$10:$K$10) -> 3646 | F5: =SUM(QUARTERLY_KPIs!$L$10:$O$10) -> 4356.1836 | G5: =SUM(QUARTERLY_KPIs!$P$10:$S$10) -> 5212.8229 | H5: =SUM(QUARTERLY_KPIs!$T$10:$W$10) -> 6248.4709
B6: % Y/Y Change | D6: =D5/C5-1 -> 0.090069343 | E6: =E5/D5-1 -> 0.19345336 | F6: =F5/E5-1 -> 0.1947843 | G6: =G5/F5-1 -> 0.19664904 | H6: =H5/G5-1 -> 0.19867316
B8: Cost of revenue | C8: -678.597 | D8: -688.76 | E8: -750.355 | F8: =F10*F$5 -> -871.23671 | G8: =G10*G$5 -> -990.43635 | H8: =H10*H$5 -> -1124.7248
B9: % Y/Y Change | D9: =D8/C8-1 -> 0.014976488 | E9: =E8/D8-1 -> 0.089428829 | F9: =F8/E8-1 -> 0.16109936 | G9: =G8/F8-1 -> 0.13681659 | H9: =H8/G8-1 -> 0.1355851
B10: % of Total Revenue | C10: =C8/C$5 -> -0.24213348 | D10: =D8/D$5 -> -0.22545336 | E10: =E8/E$5 -> -0.20580225 | F10: -0.2 | G10: -0.19 | H10: -0.18
B12: Research and development | C12: -948.98 | D12: -1068.416 | E12: -1240.564 | F12: =F14*F$5 -> -1524.6642 | G12: =G14*G$5 -> -1824.488 | H12: =H14*H$5 -> -2186.9648
B13: % Y/Y Change | D13: =D12/C12-1 -> 0.12585724 | E13: =E12/D12-1 -> 0.16112451 | F13: =F12/E12-1 -> 0.22900894 | G13: =G12/F12-1 -> 0.19664904 | H13: =H12/G12-1 -> 0.19867316
B14: % of Total Revenue | C14: =C12/C$5 -> -0.33861015 | D14: =D12/D$5 -> -0.349727 | E14: =E12/E$5 -> -0.34025343 | F14: -0.35 | G14: -0.35 | H14: -0.35
B16: Sales and marketing | C16: -933.133 | D16: -911.166 | E16: -1011.772 | F16: =F18*F$5 -> -1263.2932 | G16: =G18*G$5 -> -1459.5904 | H16: =H18*H$5 -> -1687.0871
B17: % Y/Y Change | D17: =D16/C16-1 -> -0.023541124 | E17: =E16/D16-1 -> 0.11041457 | F17: =F16/E16-1 -> 0.24859477 | G17: =G16/F16-1 -> 0.15538528 | H17: =H16/G16-1 -> 0.15586341
B18: % of Total Revenue | C18: =C16/C$5 -> -0.3329557 | D18: =D16/D$5 -> -0.29825401 | E18: =E16/E$5 -> -0.27750192 | F18: -0.29 | G18: -0.28 | H18: -0.27
B20: General and administrative | C20: -343.541 | D20: -512.407 | E20: -463.658 | F20: =E20*(1+F21) -> -472.93116 | G20: =F20*(1+G21) -> -482.38978 | H20: =G20*(1+H21) -> -492.03758
B21: % Y/Y Change | D21: =D20/C20-1 -> 0.49154541 | E21: =E20/D20-1 -> -0.095137264 | F21: 0.02 | G21: 0.02 | H21: 0.02
B22: % of Total Revenue | C22: =C20/C$5 -> -0.12258053 | D22: =D20/D$5 -> -0.16772733 | E22: =E20/E$5 -> -0.12716895 | F22: =F20/F$5 -> -0.10856548 | G22: =G20/G$5 -> -0.092539071 | H22: =H20/H$5 -> -0.078745278
B24: Income (loss) from operations ("EBIT") | C24: =SUM(C5,C8,C12,C16,C20) -> -101.677 | D24: =SUM(D5,D8,D12,D16,D20) -> -125.749 | E24: =SUM(E5,E8,E12,E16,E20) -> 179.651 | F24: =SUM(F5,F8,F12,F16,F20) -> 224.05821 | G24: =SUM(G5,G8,G12,G16,G20) -> 455.91833 | H24: =SUM(H5,H8,H12,H16,H20) -> 757.6566
B25: % Y/Y Change | D25: =D24/C24-1 -> 0.23674971 | E25: =E24/D24-1 -> -2.4286475 | F25: =F24/E24-1 -> 0.24718598 | G25: =G24/F24-1 -> 1.0348209 | H25: =H24/G24-1 -> 0.66182524
B26: % Margin | C26: =C24/C$5 -> -0.036279863 | D26: =D24/D$5 -> -0.041161702 | E26: =E24/E$5 -> 0.04927345 | F26: =F24/F$5 -> 0.05143452 | G26: =G24/G$5 -> 0.087460929 | H26: =H24/H$5 -> 0.12125472
B29: Addbacks to EBIT to derive Adjusted EBITDA
B30: Depreciation | C30: 46.489 | D30: 21.509 | E30: 21.266 | F30: =AVERAGE($C$30/$C$5,$D$30/$D$5,$E$30/$E$5)*F5 -> 42.779534 | G30: =AVERAGE($C$30/$C$5,$D$30/$D$5,$E$30/$E$5)*G5 -> 51.192089 | H30: =AVERAGE($C$30/$C$5,$D$30/$D$5,$E$30/$E$5)*H5 -> 61.362583
B31: Share-based compensation | C31: 497.123 | D31: 647.86 | E31: 765.795 | F31: =-F40 -> 870.48652 | G31: =-G40 -> 1041.6669 | H31: =-H40 -> 1248.6181
B32: Payroll tax expense related to share-based compensation | C32: 19.488 | D32: 24.131 | E32: 30.787 | F32: =SUM($C$32:$E$32)/SUM($C$31:$E$31)*F31 -> 33.896884 | G32: =SUM($C$32:$E$32)/SUM($C$31:$E$31)*G31 -> 40.562673 | H32: =SUM($C$32:$E$32)/SUM($C$31:$E$31)*H31 -> 48.621388
B33: Legal settlement | C33: 0 | D33: 0 | E33: 34.65 | F33: 0 | G33: 0 | H33: 0
B34: Restructuring charges | C34: 0 | D34: 126.883 | E34: 0 | F34: 0 | G34: 0 | H34: 0
B35: Non-cash charitable contributions | C35: 0 | D35: 12.89 | E35: 0 | F35: 0 | G35: 0 | H35: 0
B36: Adjusted EBITDA | C36: =SUM(C24,C30:C35) -> 461.423 | D36: =SUM(D24,D30:D35) -> 707.524 | E36: =SUM(E24,E30:E35) -> 1032.149 | F36: =SUM(F24,F30:F35) -> 1171.2211 | G36: =SUM(G24,G30:G35) -> 1589.3399 | H36: =SUM(H24,H30:H35) -> 2116.2587
B37: % Y/Y Change | D37: =D36/C36-1 -> 0.53335226 | E37: =E36/D36-1 -> 0.45881836 | F37: =F36/E36-1 -> 0.13474037 | G37: =G36/F36-1 -> 0.3569939 | H37: =H36/G36-1 -> 0.33153305
B38: % Margin | C38: =C36/C$5 -> 0.16464258 | D38: =D36/D$5 -> 0.23159542 | E38: =E36/E$5 -> 0.28309078 | F38: =F36/F$5 -> 0.26886405 | G38: =G36/G$5 -> 0.30489046 | H38: =H36/H$5 -> 0.33868425
B40: Share-based compensation | C40: =-C31 -> -497.123 | D40: =-D31 -> -647.86 | E40: =-E31 -> -765.795 | F40: =F42*F5 -> -870.48652 | G40: =G42*G5 -> -1041.6669 | H40: =H42*H5 -> -1248.6181
B41: % Y/Y Change | D41: =D40/C40-1 -> 0.30321872 | E41: =E40/D40-1 -> 0.18203779 | F41: =F40/E40-1 -> 0.13670958 | G41: =G40/F40-1 -> 0.19664904 | H41: =H40/G40-1 -> 0.19867316
B42: % of Total Revenue | C42: =C40/C$5 -> -0.17738086 | D42: =D40/D$5 -> -0.21206547 | E42: =E40/E$5 -> -0.21003703 | F42: =AVERAGE($C$42:$E$42) -> -0.19982779 | G42: =AVERAGE($C$42:$E$42) -> -0.19982779 | H42: =AVERAGE($C$42:$E$42) -> -0.19982779
B44: Adjusted EBITDA (Burdened by SBC) | C44: =SUM(C36,C40) -> -35.7 | D44: =SUM(D36,D40) -> 59.664 | E44: =SUM(E36,E40) -> 266.354 | F44: =SUM(F36,F40) -> 300.73463 | G44: =SUM(G36,G40) -> 547.6731 | H44: =SUM(H36,H40) -> 867.64057
B45: % Y/Y Change | D45: =D44/C44-1 -> -2.6712605 | E45: =E44/D44-1 -> 3.464233 | F45: =F44/E44-1 -> 0.1290787 | G45: =G44/F44-1 -> 0.82111751 | H45: =H44/G44-1 -> 0.58423076
B46: % Margin | C46: =C44/C$5 -> -0.01273829 | D46: =D44/D$5 -> 0.019529951 | E46: =E44/E$5 -> 0.073053758 | F46: =F44/F$5 -> 0.069036261 | G46: =G44/G$5 -> 0.10506267 | H46: =H44/H$5 -> 0.13885646

Sheet QUARTERLY_KPIs
B2: $ in millions, except ARPU | C2: Historical (Quarterly) | L2: Projections (Quarterly)
C3: FY2022A | D3: FY2023A | H3: FY2024A | L3: FY2025E | P3: FY2026E | T3: FY2027E
B4: Company2167 (FYE 12/31) | C4: Q4'22 | D4: Q1'23 | E4: Q2'23 | F4: Q3'23 | G4: Q4'23 | H4: Q1'24 | I4: Q2'24 | J4: Q3'24 | K4: Q4'24 | L4: Q1'23 | M4: Q2'23 | N4: Q3'23 | O4: Q4'23 | P4: Q1'24 | Q4: Q2'24 | R4: Q3'24 | S4: Q4'24 | T4: Q1'24 | U4: Q2'24 | V4: Q3'24 | W4: Q4'24
B6: Revenue
B7: US and Canada | C7: 722 | D7: 486 | E7: 565 | F7: 618 | G7: 779 | H7: 592 | I7: 673 | J7: 719 | K7: 900 | L7: =L13*L19 -> 721.11934 | M7: =M13*M19 -> 801.64425 | N7: =N13*N19 -> 836.50647 | O7: =O13*O19 -> 1039.7946 | P7: =P13*P19 -> 878.40051 | Q7: =Q13*Q19 -> 954.8789 | R7: =R13*R19 -> 973.21708 | S7: =S13*S19 -> 1201.3031 | ... W7: =W13*W19 -> 1387.8984
B8: Europe | C8: 123 | D8: 93 | E8: 114 | F8: 114 | G8: 162 | H8: 118 | I8: 143 | J8: 137 | K8: 196 | L8: =L14*L20 -> 149.72043 | M8: =M14*M20 -> 179.37719 | N8: =N14*N20 -> 164.64035 | O8: =O14*O20 -> 237.1358 | P8: =P14*P20 -> 189.96786 | Q8: =Q14*Q20 -> 225.00823 | R8: =R14*R20 -> 197.85726 | S8: =S14*S20 -> 286.90504 | ... W8: =W14*W20 -> 347.11968
B9: Rest of World | C9: 32 | D9: 24 | E9: 29 | F9: 31 | G9: 41 | H9: 30 | I9: 38 | J9: 42 | K9: 58 | L9: =L15*L21 -> 37.5 | M9: =M15*M21 -> 49.793103 | N9: =N15*N21 -> 56.903226 | O9: =O15*O21 -> 82.04878 | P9: =P15*P21 -> 46.875 | Q9: =Q15*Q21 -> 65.246136 | R9: =R15*R21 -> 77.094693 | S9: =S15*S21 -> 116.06901 | ... W9: =W15*W21 -> 164.19518
B10: Total Revenue | C10: 877 | D10: 603 | E10: 708 | F10: 763 | G10: 981 | H10: 740 | I10: 854 | J10: 898 | K10: 1154 | L10: =SUM(L7:L9) -> 908.33977 | M10: =SUM(M7:M9) -> 1030.8145 | N10: =SUM(N7:N9) -> 1058.05 | O10: =SUM(O7:O9) -> 1358.9792 | P10: =SUM(P7:P9) -> 1115.2434 | Q10: =SUM(Q7:Q9) -> 1245.1333 | R10: =SUM(R7:R9) -> 1248.169 | S10: =SUM(S7:S9) -> 1604.2772 | ... W10: =SUM(W7:W9) -> 1899.2132
B12: Monthly Active Users (MAUs)
B13: US and Canada | C13: 95 | D13: 95 | E13: 95 | F13: 96 | G13: 97 | H13: 98 | I13: 98 | J13: 99 | K13: 101 | L13: =H13*(1+L31) -> 101.09474 | M13: =I13*(1+M31) -> 101.09474 | N13: =J13*(1+N31) -> 102.09375 | O13: =K13*(1+O31) -> 105.16495 | P13: =L13*(1+P31) -> 104.2872 | Q13: =M13*(1+Q31) -> 104.2872 | R13: =N13*(1+R31) -> 105.28418 | S13: =O13*(1+S31) -> 109.50165 | ... W13: =S13*(1+W31) -> 114.01718
B14: Europe | C14: 124 | D14: 128 | E14: 124 | F14: 128 | G14: 135 | H14: 140 | I14: 136 | J14: 139 | K14: 145 | L14: =H14*(1+L32) -> 153.125 | M14: =I14*(1+M32) -> 149.16129 | N14: =J14*(1+N32) -> 150.94531 | O14: =K14*(1+O32) -> 155.74074 | P14: =L14*(1+P32) -> 167.48047 | Q14: =M14*(1+Q32) -> 163.59625 | R14: =N14*(1+R32) -> 163.91718 | S14: =O14*(1+S32) -> 167.27709 | ... W14: =S14*(1+W32) -> 179.66799
B15: Rest of World | C15: 231 | D15: 240 | E15: 246 | F15: 258 | G15: 266 | H15: 279 | I15: 288 | J15: 300 | K15: 307 | L15: =H15*(1+L33) -> 324.3375 | M15: =I15*(1+M33) -> 337.17073 | N15: =J15*(1+N33) -> 348.83721 | O15: =K15*(1+O33) -> 354.31955 | P15: =L15*(1+P33) -> 377.04234 | Q15: =M15*(1+Q33) -> 394.73647 | R15: =N15*(1+R33) -> 405.62466 | S15: =O15*(1+S33) -> 408.93271 | ... W15: =S15*(1+W33) -> 471.96369
B16: Total MAUs (millions) | C16: 450 | D16: 463 | E16: 465 | F16: 482 | G16: 498 | H16: 518 | I16: 522 | J16: 537 | K16: 553 | L16: =SUM(L13:L15) -> 578.55724 | M16: =SUM(M13:M15) -> 587.42676 | N16: =SUM(N13:N15) -> 601.87627 | O16: =SUM(O13:O15) -> 615.22524 | P16: =SUM(P13:P15) -> 648.81001 | Q16: =SUM(Q13:Q15) -> 662.61992 | R16: =SUM(R13:R15) -> 674.82602 | S16: =SUM(S13:S15) -> 685.71145 | ... W16: =SUM(W13:W15) -> 765.64886
B18: Average Revenue per User (ARPU)
B19: US and Canada | C19: =C7/C13 -> 7.6 | D19: =D7/D13 -> 5.1157895 | E19: =E7/E13 -> 5.9473684 | F19: =F7/F13 -> 6.4375 | G19: =G7/G13 -> 8.0309278 | H19: =H7/H13 -> 6.0408163 | I19: =I7/I13 -> 6.8673469 | J19: =J7/J13 -> 7.2626263 | K19: =K7/K13 -> 8.9108911 | L19: =H19*(1+L37) -> 7.1331047 | M19: =I19*(1+M37) -> 7.9296339 | N19: =J19*(1+N37) -> 8.193513 | O19: =K19*(1+O37) -> 9.8872735 | P19: =L19*(1+P37) -> 8.4228985 | Q19: =M19*(1+Q37) -> 9.1562424 | R19: =N19*(1+R37) -> 9.2437162 | S19: =O19*(1+S37) -> 10.97064 | ... W19: =S19*(1+W37) -> 12.172713
B20: Europe | C20: =C8/C14 -> 0.99193548 | D20: =D8/D14 -> 0.7265625 | E20: =E8/E14 -> 0.91935484 | F20: =F8/F14 -> 0.890625 | G20: =G8/G14 -> 1.2 | H20: =H8/H14 -> 0.84285714 | I20: =I8/I14 -> 1.0514706 | J20: =J8/J14 -> 0.98561151 | K20: =K8/K14 -> 1.3517241 | L20: =H20*(1+L38) -> 0.97776607 | M20: =I20*(1+M38) -> 1.202572 | N20: =J20*(1+N38) -> 1.0907285 | O20: =K20*(1+O38) -> 1.5226318 | P20: =L20*(1+P38) -> 1.1342687 | Q20: =M20*(1+Q38) -> 1.3753874 | R20: =N20*(1+R38) -> 1.2070563 | S20: =O20*(1+S38) -> 1.7151485 | ... W20: =S20*(1+W38) -> 1.9320063
B21: Rest of World | C21: =C9/C15 -> 0.13852814 | D21: =D9/D15 -> 0.1 | E21: =E9/E15 -> 0.11788618 | F21: =F9/F15 -> 0.12015504 | G21: =G9/G15 -> 0.15413534 | H21: =H9/H15 -> 0.10752688 | I21: =I9/I15 -> 0.13194444 | J21: =J9/J15 -> 0.14 | K21: =K9/K15 -> 0.18892508 | L21: =H21*(1+L39) -> 0.1156203 | M21: =I21*(1+M39) -> 0.1476792 | N21: =J21*(1+N39) -> 0.16312258 | O21: =K21*(1+O39) -> 0.23156718 | P21: =L21*(1+P39) -> 0.12432291 | Q21: =M21*(1+Q39) -> 0.16529037 | R21: =N21*(1+R39) -> 0.19006412 | S21: =O21*(1+S39) -> 0.283834 | ... W21: =S21*(1+W39) -> 0.3478979
B22: Total ARPU | C22: =C10/C16 -> 1.9488889 | D22: =D10/D16 -> 1.3023758 | E22: =E10/E16 -> 1.5225806 | F22: =F10/F16 -> 1.5829876 | G22: =G10/G16 -> 1.9698795 | H22: =H10/H16 -> 1.4285714 | I22: =I10/I16 -> 1.6360153 | J22: =J10/J16 -> 1.6722533 | ... W22: =W10/W16 -> 2.4805277
B24: Y/Y Revenue Growth Rate (%)
B25: US and Canada | C25: N/A | D25: N/A | E25: N/A | F25: N/A | G25: =G7/C7-1 -> 0.078947368 | H25: =H7/D7-1 -> 0.218107 | I25: =I7/E7-1 -> 0.19115044 | J25: =J7/F7-1 -> 0.16343042 | K25: =K7/G7-1 -> 0.15532734 | L25: =L7/H7-1 -> 0.218107 | M25: =M7/I7-1 -> 0.19115044 | N25: =N7/J7-1 -> 0.16343042 | ... W25: =W7/S7-1 -> 0.15532734
B26: Europe | C26: N/A | D26: N/A | E26: N/A | F26: N/A | G26: =G8/C8-1 -> 0.31707317 | H26: =H8/D8-1 -> 0.2688172 | I26: =I8/E8-1 -> 0.25438596 | J26: =J8/F8-1 -> 0.20175439 | K26: =K8/G8-1 -> 0.20987654 | L26: =L8/H8-1 -> 0.2688172 | M26: =M8/I8-1 -> 0.25438596 | N26: =N8/J8-1 -> 0.20175439 | ... W26: =W8/S8-1 -> 0.20987654
B27: Rest of World | C27: N/A | D27: N/A | E27: N/A | F27: N/A | G27: =G9/C9-1 -> 0.28125 | H27: =H9/D9-1 -> 0.25 | I27: =I9/E9-1 -> 0.31034483 | J27: =J9/F9-1 -> 0.35483871 | K27: =K9/G9-1 -> 0.41463415 | L27: =L9/H9-1 -> 0.25 | M27: =M9/I9-1 -> 0.31034483 | N27: =N9/J9-1 -> 0.35483871 | ... W27: =W9/S9-1 -> 0.41463415
B28: Total Revenue Growth Rate | C28: N/A | D28: N/A | E28: N/A | F28: N/A | G28: =G10/C10-1 -> 0.11858609 | H28: =H10/D10-1 -> 0.22719735 | I28: =I10/E10-1 -> 0.20621469 | J28: =J10/F10-1 -> 0.17693316 | K28: =K10/G10-1 -> 0.17635066 | L28: =L10/H10-1 -> 0.22748618 | M28: =M10/I10-1 -> 0.20704279 | N28: =N10/J10-1 -> 0.17822945 | ... W28: =W10/S10-1 -> 0.18384356
B30: Y/Y MAUs Growth Rate (%)
B31: US and Canada | C31: N/A | D31: N/A | E31: N/A | F31: N/A | G31: =G13/C13-1 -> 0.021052632 | H31: =H13/D13-1 -> 0.031578947 | I31: =I13/E13-1 -> 0.031578947 | J31: =J13/F13-1 -> 0.03125 | K31: =K13/G13-1 -> 0.041237113 | L31: =H31 -> 0.031578947 | M31: =I31 -> 0.031578947 | N31: =J31 -> 0.03125 | O31: =K31 -> 0.041237113 | P31: =L31 -> 0.031578947 | Q31: =M31 -> 0.031578947 | R31: =N31 -> 0.03125 | S31: =O31 -> 0.041237113 | ... W31: =S31 -> 0.041237113
B32: Europe | C32: N/A | D32: N/A | E32: N/A | F32: N/A | G32: =G14/C14-1 -> 0.088709677 | H32: =H14/D14-1 -> 0.09375 | I32: =I14/E14-1 -> 0.096774194 | J32: =J14/F14-1 -> 0.0859375 | K32: =K14/G14-1 -> 0.074074074 | L32: =H32 -> 0.09375 | M32: =I32 -> 0.096774194 | N32: =J32 -> 0.0859375 | O32: =K32 -> 0.074074074 | P32: =L32 -> 0.09375 | Q32: =M32 -> 0.096774194 | R32: =N32 -> 0.0859375 | S32: =O32 -> 0.074074074 | ... W32: =S32 -> 0.074074074
B33: Rest of World | C33: N/A | D33: N/A | E33: N/A | F33: N/A | G33: =G15/C15-1 -> 0.15151515 | H33: =H15/D15-1 -> 0.1625 | I33: =I15/E15-1 -> 0.17073171 | J33: =J15/F15-1 -> 0.1627907 | K33: =K15/G15-1 -> 0.15413534 | L33: =H33 -> 0.1625 | M33: =I33 -> 0.17073171 | N33: =J33 -> 0.1627907 | O33: =K33 -> 0.15413534 | P33: =L33 -> 0.1625 | Q33: =M33 -> 0.17073171 | R33: =N33 -> 0.1627907 | S33: =O33 -> 0.15413534 | ... W33: =S33 -> 0.15413534
B34: Total MAUs Growth Rate | C34: N/A | D34: N/A | E34: N/A | F34: N/A | G34: =G16/C16-1 -> 0.10666667 | H34: =H16/D16-1 -> 0.1187905 | I34: =I16/E16-1 -> 0.12258065 | J34: =J16/F16-1 -> 0.11410788 | K34: =K16/G16-1 -> 0.11044177 | L34: =L16/H16-1 -> 0.11690586 | M34: =M16/I16-1 -> 0.12533862 | N34: =N16/J16-1 -> 0.12081242 | ... W34: =W16/S16-1 -> 0.11657587
B36: Y/Y ARPU Growth Rate (%)
B37: US and Canada | C37: N/A | D37: N/A | E37: N/A | F37: N/A | G37: =G19/C19-1 -> 0.056701031 | H37: =H19/D19-1 -> 0.18081801 | I37: =I19/E19-1 -> 0.15468665 | J37: =J19/F19-1 -> 0.12817495 | K37: =K19/G19-1 -> 0.1095718 | L37: =H37 -> 0.18081801 | M37: =I37 -> 0.15468665 | N37: =J37 -> 0.12817495 | O37: =K37 -> 0.1095718 | P37: =L37 -> 0.18081801 | Q37: =M37 -> 0.15468665 | R37: =N37 -> 0.12817495 | S37: =O37 -> 0.1095718 | ... W37: =S37 -> 0.1095718
B38: Europe | C38: N/A | D38: N/A | E38: N/A | F38: N/A | G38: =G20/C20-1 -> 0.2097561 | H38: =H20/D20-1 -> 0.16006144 | I38: =I20/E20-1 -> 0.14370485 | J38: =J20/F20-1 -> 0.10665152 | K38: =K20/G20-1 -> 0.12643678 | L38: =H38 -> 0.16006144 | M38: =I38 -> 0.14370485 | N38: =J38 -> 0.10665152 | O38: =K38 -> 0.12643678 | P38: =L38 -> 0.16006144 | Q38: =M38 -> 0.14370485 | R38: =N38 -> 0.10665152 | S38: =O38 -> 0.12643678 | ... W38: =S38 -> 0.12643678
B39: Rest of World | C39: N/A | D39: N/A | E39: N/A | F39: N/A | G39: =G21/C21-1 -> 0.11266447 | H39: =H21/D21-1 -> 0.075268817 | I39: =I21/E21-1 -> 0.11925287 | J39: =J21/F21-1 -> 0.16516129 | K39: =K21/G21-1 -> 0.22570906 | L39: =H39 -> 0.075268817 | M39: =I39 -> 0.11925287 | N39: =J39 -> 0.16516129 | O39: =K39 -> 0.22570906 | P39: =L39 -> 0.075268817 | Q39: =M39 -> 0.11925287 | R39: =N39 -> 0.16516129 | S39: =O39 -> 0.22570906 | ... W39: =S39 -> 0.22570906
B40: Total ARPU Growth Rate | C40: N/A | D40: N/A | E40: N/A | F40: N/A | G40: =G22/C22-1 -> 0.010770562 | H40: =H22/D22-1 -> 0.09689647 | I40: =I22/E22-1 -> 0.074501591 | J40: =J22/F22-1 -> 0.056390656 | K40: =K22/G22-1 -> 0.059353761 | L40: =L22/H22-1 -> 0.09900594 | M40: =M22/I22-1 -> 0.072604078 | N40: =N22/J22-1 -> 0.051228045 | ... W40: =W22/S22-1 -> 0.060244624
