Workbook
Name EC_CCMO_BasePay: 'Exec Comp'!$1503:$1503
Name EC_CCMO_EquityComp_Percent: 'Exec Comp'!$1507:$1507
Name EC_CCMO_SharesOwned: 'Exec Comp'!$1692:$1692
Name EC_CCMO_TotalComp: 'Exec Comp'!$1506:$1506
Name EC_CEO_BasePay: 'Exec Comp'!$7:$7
Name EC_CEO_EquityComp_Percent: 'Exec Comp'!$13:$13
Name EC_CEO_SharesOwned: 'Exec Comp'!$456:$456
Name EC_CEO_TotalComp: 'Exec Comp'!$12:$12
Name EC_CFO_BasePay: 'Exec Comp'!$976:$976
Name EC_CFO_EquityComp_Percent: 'Exec Comp'!$982:$982
Name EC_CFO_SharesOwned: 'Exec Comp'!$1164:$1164
Name EC_CFO_TotalComp: 'Exec Comp'!$981:$981
Name EC_CLO_BasePay: 'Exec Comp'!$1166:$1166
Name EC_CLO_EquityComp_Percent: 'Exec Comp'!$1172:$1172
Name EC_CLO_SharesOwned: 'Exec Comp'!$1501:$1501
Name EC_CLO_TotalComp: 'Exec Comp'!$1171:$1171
Name EC_CoCEOCCO_BasePay: 'Exec Comp'!$458:$458
Name EC_CoCEOCCO_EquityComp_Percent: 'Exec Comp'!$464:$464
Name EC_CoCEOCCO_SharesOwned: 'Exec Comp'!$720:$720
Name EC_CoCEOCCO_TotalComp: 'Exec Comp'!$463:$463
Name EC_Person0187_BasePay: 'Exec Comp'!$722:$722
Name EC_Person0187_EquityComp_Percent: 'Exec Comp'!$726:$726
Name EC_Person0187_SharesOwned: 'Exec Comp'!$974:$974
Name EC_Person0187_TotalComp: 'Exec Comp'!$725:$725
Name EC_CTO_BasePay: 'Exec Comp'!$1694:$1694
Name EC_CTO_EquityComp_Percent: 'Exec Comp'!$1698:$1698
Name EC_CTO_OptionsAwards: 'Exec Comp'!$1695:$1695
Name EC_CTO_SharesOwned: 'Exec Comp'!$A$1733
Name EC_CTO_TotalComp: 'Exec Comp'!$1697:$1697
Name EC_Director_Compensation_Cash: 'Exec Comp'!$1755:$1755
Name EC_Director_Compensation_Total: 'Exec Comp'!$1780:$1780
Name EC_Directors_Current: 'Exec Comp'!$1736:$1736
Name EC_Directors_Current_Diverse: 'Exec Comp'!$1739:$1739
Name EC_Directors_Current_Female: 'Exec Comp'!$1738:$1738
Name EC_Directors_Current_Independent: 'Exec Comp'!$1737:$1737
Name EC_Directors_Nominees: 'Exec Comp'!$1741:$1741
Name GD.CompanyName: Guidance!$B$1
Name GD.MRQ: Guidance!$F$2
Name GD_Difference_Mid_Absolute: Guidance!$P:$P
Name GD_Difference_Mid_Relative: Guidance!$Q:$Q
Name GD_Guidance_High: Guidance!$J:$J
Name GD_Guidance_Low: Guidance!$I:$I
Name GD_Guidance_Mid: Guidance!$K:$K
Name GD_Header_Column: Guidance!$5:$5
Name GD_Header_Section: Guidance!$4:$4
Name GD_Index: Guidance!$A:$A
Name GD_Item: Guidance!$D:$D
Name GD_Item_BasePeriod: Guidance!$G:$G
Name GD_Item_FiscalPeriod: Guidance!$F:$F
Name GD_Item_Name: Guidance!$E:$E
Name GD_Model_Output: Guidance!$N:$N
Name GD_Model_Type: Guidance!$M:$M
Name GD_Type: Guidance!$B:$B
Name GD_Update_Date: Guidance!$S:$S
Name GD_Update_Link: Guidance!$T:$T
Name HP.MRFX: Model!$B$1411
Name HP.ReportCurrency: Model!$B$1410
Name HP.Ticker: Model!$A$2
Name HP.TradeCurrency: Model!$B$1408
Name HP.TradeCurrency.HardCoded: Model!$B$1409

Sheet Model
A1: Company1933, Inc.
A2: =CHOOSE(MO.DataSourceIndex,MO.Ticker.Bloomberg,MO.Ticker.CapIQ,MO.Ticker.FactSet,MO.Ticker.Thomson) | C2: =EOMONTH(C4,-12)
A3: =HP.TradeCurrency | B3: =IF(MO.RealTime="OFF",MO.LastPriceHardcoded,MO.LastPriceFormula) | C3: =C4-C2 | D3: =D4-C4 | E3: =E4-D4 | F3: =F4-E4 | G3: =G4-F4 | H3: =H4-G4 | I3: =I4-H4 | J3: =J4-I4 | K3: =K4-F4 | L3: =L4-K4 | M3: =M4-L4 | N3: =N4-M4 | O3: =O4-N4 | P3: =P4-K4 | Q3: =Q4-P4 | R3: =R4-Q4 | S3: =S4-R4 | T3: =T4-S4 | U3: =U4-P4 | V3: =V4-U4 | W3: =W4-V4 | X3: =X4-W4 | Y3: =Y4-X4 | Z3: =Z4-U4 | AA3: =AA4-Z4 | AB3: =AB4-AA4 | AC3: =AC4-AB4 | AD3: =AD4-AC4 | AE3: =AE4-Z4 | AF3: =AF4-AE4 | AG3: =AG4-AF4 | AH3: =AH4-AG4 | AI3: =AI4-AH4 | AJ3: =AJ4-AE4 | AK3: =AK4-AJ4 | AL3: =AL4-AK4 | AM3: =AM4-AL4 | AN3: =AN4-AM4 | AO3: =AO4-AJ4 | AP3: =AP4-AO4 | AQ3: =AQ4-AP4 | AR3: =AR4-AQ4 | AS3: =AS4-AR4 | AT3: =AT4-AO4 | AU3: =AU4-AT4 | AV3: =AV4-AU4 | AW3: =AW4-AV4 | AX3: =AX4-AW4 | AY3: =AY4-AT4 | AZ3: =AZ4-AY4 | BA3: =BA4-AZ4 | BB3: =BB4-BA4 | BC3: =BC4-BB4 | BD3: =BD4-AY4 | BE3: =BE4-BD4 | BF3: =BF4-BE4 | BG3: =BG4-BF4 | BH3: =BH4-BG4 | BI3: =BI4-BD4 | BJ3: =BJ4-BI4 | BK3: =BK4-BJ4 | BL3: =BL4-BK4 | BM3: =BM4-BL4 | BN3: =BN4-BI4 | BO3: =BO4-BN4 | BP3: =BP4-BO4 | BQ3: =BQ4-BP4 | BR3: =BR4-BQ4 | BS3: =BS4-BN4 | BT3: =BT4-BS4 | BU3: =BU4-BT4 | BV3: =BV4-BU4 | BW3: =BW4-BV4 | BX3: =BX4-BS4 | BY3: =BY4-BX4 | BZ3: =BZ4-BY4 | CA3: =CA4-BZ4 | CB3: =CB4-CA4 | CC3: =CC4-BX4 | CD3: =CD4-CC4 | CE3: =CE4-CD4 | CF3: =CF4-CE4
A4: Bloomberg | B4: =IF(AND(MO.RealTimeStockPriceToggle,MO.LastPriceFormula<>"N/A"),"ON","OFF") | C4: 40178 | D4: =EOMONTH(C4,12) | E4: =EOMONTH(D4,12) | F4: =EOMONTH(E4,12) | G4: =EOMONTH(F4,3) | H4: =EOMONTH(G4,3) | I4: =EOMONTH(H4,3) | J4: =EOMONTH(I4,3) | K4: =J4 | L4: =EOMONTH(K4,3) | M4: =EOMONTH(L4,3) | N4: =EOMONTH(M4,3) | O4: =EOMONTH(N4,3) | P4: =O4 | Q4: =EOMONTH(P4,3) | R4: =EOMONTH(Q4,3) | S4: =EOMONTH(R4,3) | T4: =EOMONTH(S4,3) | U4: =T4 | V4: =EOMONTH(U4,3) | W4: =EOMONTH(V4,3) | X4: =EOMONTH(W4,3) | Y4: =EOMONTH(X4,3) | Z4: =Y4 | AA4: =EOMONTH(Z4,3) | AB4: =EOMONTH(AA4,3) | AC4: =EOMONTH(AB4,3) | AD4: =EOMONTH(AC4,3) | AE4: =AD4 | AF4: =EOMONTH(AE4,3) | AG4: =EOMONTH(AF4,3) | AH4: =EOMONTH(AG4,3) | AI4: =EOMONTH(AH4,3) | AJ4: =AI4 | AK4: =EOMONTH(AJ4,3) | AL4: =EOMONTH(AK4,3) | AM4: =EOMONTH(AL4,3) | AN4: =EOMONTH(AM4,3) | AO4: =AN4 | AP4: =EOMONTH(AO4,3) | AQ4: =EOMONTH(AP4,3) | AR4: =EOMONTH(AQ4,3) | AS4: =EOMONTH(AR4,3) | AT4: =AS4 | AU4: =EOMONTH(AT4,3) | AV4: =EOMONTH(AU4,3) | AW4: =EOMONTH(AV4,3) | AX4: =EOMONTH(AW4,3) | AY4: =AX4 | AZ4: =EOMONTH(AY4,3) | BA4: =EOMONTH(AZ4,3) | BB4: =EOMONTH(BA4,3) | BC4: =EOMONTH(BB4,3) | BD4: =BC4 | BE4: =EOMONTH(BD4,3) | BF4: =EOMONTH(BE4,3) | BG4: =EOMONTH(BF4,3) | BH4: =EOMONTH(BG4,3) | BI4: =BH4 | BJ4: =EOMONTH(BI4,3) | BK4: =EOMONTH(BJ4,3) | BL4: =EOMONTH(BK4,3) | BM4: =EOMONTH(BL4,3) | BN4: =BM4 | BO4: =EOMONTH(BN4,3) | BP4: =EOMONTH(BO4,3) | BQ4: =EOMONTH(BP4,3) | BR4: =EOMONTH(BQ4,3) | BS4: =BR4 | BT4: =EOMONTH(BS4,3) | BU4: =EOMONTH(BT4,3) | BV4: =EOMONTH(BU4,3) | BW4: =EOMONTH(BV4,3) | BX4: =BW4 | BY4: =EOMONTH(BX4,3) | BZ4: =EOMONTH(BY4,3) | CA4: =EOMONTH(BZ4,3) | CB4: =EOMONTH(CA4,3) | CC4: =CB4 | CD4: =EOMONTH(CC4,12) | CE4: =EOMONTH(CD4,12) | CF4: =EOMONTH(CE4,12)
A5: =MO.ReportCurrency | C5: FY2009 | D5: =CONCATENATE("FY",RIGHT(C5,4)+1) | E5: =CONCATENATE("FY",RIGHT(D5,4)+1) | F5: =CONCATENATE("FY",RIGHT(E5,4)+1) | G5: =CONCATENATE("Q1","-",RIGHT(F5,4)+1) | H5: =CONCATENATE("Q2","-",RIGHT(G5,4)) | I5: =CONCATENATE("Q3","-",RIGHT(H5,4)) | J5: =CONCATENATE("Q4","-",RIGHT(I5,4)) | K5: =CONCATENATE("FY",RIGHT(F5,4)+1) | L5: =CONCATENATE("Q1","-",RIGHT(K5,4)+1) | M5: =CONCATENATE("Q2","-",RIGHT(L5,4)) | N5: =CONCATENATE("Q3","-",RIGHT(M5,4)) | O5: =CONCATENATE("Q4","-",RIGHT(N5,4)) | P5: =CONCATENATE("FY",RIGHT(K5,4)+1) | Q5: =CONCATENATE("Q1","-",RIGHT(P5,4)+1) | R5: =CONCATENATE("Q2","-",RIGHT(Q5,4)) | S5: =CONCATENATE("Q3","-",RIGHT(R5,4)) | T5: =CONCATENATE("Q4","-",RIGHT(S5,4)) | U5: =CONCATENATE("FY",RIGHT(P5,4)+1) | V5: =CONCATENATE("Q1","-",RIGHT(U5,4)+1) | W5: =CONCATENATE("Q2","-",RIGHT(V5,4)) | X5: =CONCATENATE("Q3","-",RIGHT(W5,4)) | Y5: =CONCATENATE("Q4","-",RIGHT(X5,4)) | Z5: =CONCATENATE("FY",RIGHT(U5,4)+1) | AA5: =CONCATENATE("Q1","-",RIGHT(Z5,4)+1) | AB5: =CONCATENATE("Q2","-",RIGHT(AA5,4)) | AC5: =CONCATENATE("Q3","-",RIGHT(AB5,4)) | AD5: =CONCATENATE("Q4","-",RIGHT(AC5,4)) | AE5: =CONCATENATE("FY",RIGHT(Z5,4)+1) | AF5: =CONCATENATE("Q1","-",RIGHT(AE5,4)+1) | AG5: =CONCATENATE("Q2","-",RIGHT(AF5,4)) | AH5: =CONCATENATE("Q3","-",RIGHT(AG5,4)) | AI5: =CONCATENATE("Q4","-",RIGHT(AH5,4)) | AJ5: =CONCATENATE("FY",RIGHT(AE5,4)+1) | AK5: =CONCATENATE("Q1","-",RIGHT(AJ5,4)+1) | AL5: =CONCATENATE("Q2","-",RIGHT(AK5,4)) | AM5: =CONCATENATE("Q3","-",RIGHT(AL5,4)) | AN5: =CONCATENATE("Q4","-",RIGHT(AM5,4)) | AO5: =CONCATENATE("FY",RIGHT(AJ5,4)+1) | AP5: =CONCATENATE("Q1","-",RIGHT(AO5,4)+1) | AQ5: =CONCATENATE("Q2","-",RIGHT(AP5,4)) | AR5: =CONCATENATE("Q3","-",RIGHT(AQ5,4)) | AS5: =CONCATENATE("Q4","-",RIGHT(AR5,4)) | AT5: =CONCATENATE("FY",RIGHT(AO5,4)+1) | AU5: =CONCATENATE("Q1","-",RIGHT(AT5,4)+1) | AV5: =CONCATENATE("Q2","-",RIGHT(AU5,4)) | AW5: =CONCATENATE("Q3","-",RIGHT(AV5,4)) | AX5: =CONCATENATE("Q4","-",RIGHT(AW5,4)) | AY5: =CONCATENATE("FY",RIGHT(AT5,4)+1) | AZ5: =CONCATENATE("Q1","-",RIGHT(AY5,4)+1) | BA5: =CONCATENATE("Q2","-",RIGHT(AZ5,4)) | BB5: =CONCATENATE("Q3","-",RIGHT(BA5,4)) | BC5: =CONCATENATE("Q4","-",RIGHT(BB5,4)) | BD5: =CONCATENATE("FY",RIGHT(AY5,4)+1) | BE5: =CONCATENATE("Q1","-",RIGHT(BD5,4)+1) | BF5: =CONCATENATE("Q2","-",RIGHT(BE5,4)) | BG5: =CONCATENATE("Q3","-",RIGHT(BF5,4)) | BH5: =CONCATENATE("Q4","-",RIGHT(BG5,4)) | BI5: =CONCATENATE("FY",RIGHT(BD5,4)+1) | BJ5: =CONCATENATE("Q1","-",RIGHT(BI5,4)+1) | BK5: =CONCATENATE("Q2","-",RIGHT(BJ5,4)) | BL5: =CONCATENATE("Q3","-",RIGHT(BK5,4)) | BM5: =CONCATENATE("Q4","-",RIGHT(BL5,4)) | BN5: =CONCATENATE("FY",RIGHT(BI5,4)+1) | BO5: =CONCATENATE("Q1","-",RIGHT(BN5,4)+1) | BP5: =CONCATENATE("Q2","-",RIGHT(BO5,4)) | BQ5: =CONCATENATE("Q3","-",RIGHT(BP5,4)) | BR5: =CONCATENATE("Q4","-",RIGHT(BQ5,4)) | BS5: =CONCATENATE("FY",RIGHT(BN5,4)+1) | BT5: =CONCATENATE("Q1","-",RIGHT(BS5,4)+1) | BU5: =CONCATENATE("Q2","-",RIGHT(BT5,4)) | BV5: =CONCATENATE("Q3","-",RIGHT(BU5,4)) | BW5: =CONCATENATE("Q4","-",RIGHT(BV5,4)) | BX5: =CONCATENATE("FY",RIGHT(BS5,4)+1) | BY5: =CONCATENATE("Q1","-",RIGHT(BX5,4)+1) | BZ5: =CONCATENATE("Q2","-",RIGHT(BY5,4)) | CA5: =CONCATENATE("Q3","-",RIGHT(BZ5,4)) | CB5: =CONCATENATE("Q4","-",RIGHT(CA5,4)) | CC5: =CONCATENATE("FY",RIGHT(BX5,4)+1) | CD5: =CONCATENATE("FY",RIGHT(CC5,4)+1) | CE5: =CONCATENATE("FY",RIGHT(CD5,4)+1) | CF5: =CONCATENATE("FY",RIGHT(CE5,4)+1)
A6: Consolidated Summary
A7: BoP Total Global Paid Streaming Memberships, 000s | G7: =F9 | H7: =G9 | I7: =H9 | J7: =I9 | K7: =F9 | L7: =K9 | M7: =L9 | N7: =M9 | O7: =N9 | P7: =K9 | Q7: =P9 | R7: =Q9 | S7: =R9 | T7: =S9 | U7: =P9 | V7: =U9 | W7: =V9 | X7: =W9 | Y7: =X9 | Z7: =U9 | AA7: =Z9 | AB7: =AA9 | AC7: =AB9 | AD7: =AC9 | AE7: =Z9 | AF7: =AE9 | AG7: =AF9 | AH7: =AG9 | AI7: =AH9 | AJ7: =AE9 | AK7: =AJ9 | AL7: =AK9 | AM7: =AL9 | AN7: =AM9 | AO7: =AJ9 | AP7: =AO9 | AQ7: =AP9 | AR7: =AQ9 | AS7: =AR9 | AT7: =AO9 | AU7: =AT9 | AV7: =AU9 | AW7: =AV9 | AX7: =AW9 | AY7: =AT9 | AZ7: =AY9 | BA7: =AZ9 | BB7: =BA9 | BC7: =BB9 | BD7: =AY9 | BE7: =BD9 | BF7: =BE9 | BG7: =BF9 | BH7: =BG9 | BI7: =BD9 | BJ7: =BI9 | BK7: =BJ9 | BL7: =BK9 | BM7: =BL9 | BN7: =BI9 | BO7: =BN9 | BP7: =BO9 | BQ7: =BP9 | BR7: =BQ9 | BS7: =BN9 | BT7: =BS9 | BU7: =BT9 | BV7: =BU9 | BW7: =BV9 | BX7: =BS9 | BY7: =BX9 | BZ7: =BY9 | CA7: =BZ9 | CB7: =CA9 | CC7: =BX9 | CD7: =CC9 | CE7: =CD9 | CF7: =CE9
A8: Total paid streaming memberships net additions, 000s | G8: =G9-G7 | H8: =H9-H7 | I8: =I9-I7 | J8: =J9-J7 | K8: =K9-K7 | L8: =L9-L7 | M8: =M9-M7 | N8: =N9-N7 | ... CF8: =CF9-CF7
A9: EoP Total Global Paid Streaming Memberships, 000s | F9: =F150 | G9: =G150 | H9: =H150 | I9: =I150 | J9: =J150 | K9: =K150 | L9: =L150 | M9: =M150 | ... BQ9: =BQ150 | BR9: 325000 | BS9: =BR9 | BT9: =BT150 | BU9: =BU150 | BV9: =BV150 | BW9: =BW150 | BX9: =BX150 | BY9: =BY150 | BZ9: =BZ150 | CA9: =CA150 | ... CF9: =CF150
A10: Q/Q Global EOP paid streaming memberships growth, % | H10: =H9/G9-1 | I10: =I9/H9-1 | J10: =J9/I9-1 | L10: =L9/J9-1 | M10: =M9/L9-1 | N10: =N9/M9-1 | O10: =O9/N9-1 | Q10: =Q9/O9-1 | R10: =R9/Q9-1 | S10: =S9/R9-1 | T10: =T9/S9-1 | V10: =V9/T9-1 | W10: =W9/V9-1 | X10: =X9/W9-1 | Y10: =Y9/X9-1 | AA10: =AA9/Y9-1 | AB10: =AB9/AA9-1 | AC10: =AC9/AB9-1 | AD10: =AD9/AC9-1 | AF10: =AF9/AD9-1 | AG10: =AG9/AF9-1 | AH10: =AH9/AG9-1 | AI10: =AI9/AH9-1 | AK10: =AK9/AI9-1 | AL10: =AL9/AK9-1 | AM10: =AM9/AL9-1 | AN10: =AN9/AM9-1 | AP10: =AP9/AN9-1 | AQ10: =AQ9/AP9-1 | AR10: =AR9/AQ9-1 | AS10: =AS9/AR9-1 | AU10: =AU9/AS9-1 | AV10: =AV9/AU9-1 | AW10: =AW9/AV9-1 | AX10: =AX9/AW9-1 | AZ10: =AZ9/AX9-1 | BA10: =BA9/AZ9-1 | BB10: =BB9/BA9-1 | BC10: =BC9/BB9-1 | BE10: =BE9/BC9-1 | BF10: =BF9/BE9-1 | BG10: =BG9/BF9-1 | BH10: =BH9/BG9-1 | BJ10: =BJ9/BH9-1 | BK10: =BK9/BJ9-1 | BL10: =BL9/BK9-1 | BM10: =BM9/BL9-1 | BO10: =BO9/BM9-1 | BP10: =BP9/BO9-1 | BQ10: =BQ9/BP9-1 | BR10: =BR9/BQ9-1 | BT10: =BT9/BR9-1 | BU10: =BU9/BT9-1 | BV10: =BV9/BU9-1 | BW10: =BW9/BV9-1 | BY10: =BY9/BW9-1 | BZ10: =BZ9/BY9-1 | CA10: =CA9/BZ9-1 | CB10: =CB9/CA9-1
A11: Y/Y Global EOP paid streaming memberships growth, % | K11: =K9/F9-1 | L11: =L9/G9-1 | M11: =M9/H9-1 | N11: =N9/I9-1 | O11: =O9/J9-1 | P11: =P9/K9-1 | Q11: =Q9/L9-1 | R11: =R9/M9-1 | ... CC11: =CC9/BX9-1 | CD11: =CD9/CC9-1 | CE11: =CE9/CD9-1 | CF11: =CF9/CE9-1
A12: Total Average Paying Memberships, 000s | G12: =AVERAGE(G9,G7) | H12: =AVERAGE(H9,H7) | I12: =AVERAGE(I9,I7) | J12: =AVERAGE(J9,J7) | K12: =AVERAGE(G12,H12,I12,J12) | L12: =AVERAGE(L9,L7) | M12: =AVERAGE(M9,M7) | N12: =AVERAGE(N9,N7) | O12: =AVERAGE(O9,O7) | P12: =AVERAGE(L12,M12,N12,O12) | Q12: =AVERAGE(Q9,Q7) | R12: =AVERAGE(R9,R7) | S12: =AVERAGE(S9,S7) | T12: =AVERAGE(T9,T7) | U12: =AVERAGE(Q12,R12,S12,T12) | V12: =AVERAGE(V9,V7) | W12: =AVERAGE(W9,W7) | X12: =AVERAGE(X9,X7) | Y12: =AVERAGE(Y9,Y7) | Z12: =AVERAGE(V12,W12,X12,Y12) | AA12: =AVERAGE(AA9,AA7) | AB12: =AVERAGE(AB9,AB7) | AC12: =AVERAGE(AC9,AC7) | AD12: =AVERAGE(AD9,AD7) | AE12: =AVERAGE(AA12,AB12,AC12,AD12) | AF12: =AVERAGE(AF9,AF7) | AG12: =AVERAGE(AG9,AG7) | AH12: =AVERAGE(AH9,AH7) | AI12: =AVERAGE(AI9,AI7) | AJ12: =AVERAGE(AF12,AG12,AH12,AI12) | AK12: =AVERAGE(AK9,AK7) | AL12: =AVERAGE(AL9,AL7) | AM12: =AVERAGE(AM9,AM7) | AN12: =AVERAGE(AN9,AN7) | AO12: =AVERAGE(AK12,AL12,AM12,AN12) | AP12: =AVERAGE(AP9,AP7) | AQ12: =AVERAGE(AQ9,AQ7) | AR12: =AVERAGE(AR9,AR7) | AS12: =AVERAGE(AS9,AS7) | AT12: =AVERAGE(AP12,AQ12,AR12,AS12) | AU12: =AVERAGE(AU9,AU7) | AV12: =AVERAGE(AV9,AV7) | AW12: =AVERAGE(AW9,AW7) | AX12: =AVERAGE(AX9,AX7) | AY12: =AVERAGE(AU12,AV12,AW12,AX12) | AZ12: =AVERAGE(AZ9,AZ7) | BA12: =AVERAGE(BA9,BA7) | BB12: =AVERAGE(BB9,BB7) | BC12: =AVERAGE(BC9,BC7) | BD12: =AVERAGE(AZ12,BA12,BB12,BC12) | BE12: =AVERAGE(BE9,BE7) | BF12: =AVERAGE(BF9,BF7) | BG12: =AVERAGE(BG9,BG7) | BH12: =AVERAGE(BH9,BH7) | BI12: =AVERAGE(BE12,BF12,BG12,BH12) | BJ12: =AVERAGE(BJ9,BJ7) | BK12: =AVERAGE(BK9,BK7) | BL12: =AVERAGE(BL9,BL7) | BM12: =AVERAGE(BM9,BM7) | BN12: =AVERAGE(BJ12,BK12,BL12,BM12) | BO12: =AVERAGE(BO9,BO7) | BP12: =AVERAGE(BP9,BP7) | BQ12: =AVERAGE(BQ9,BQ7) | BR12: =AVERAGE(BR9,BR7) | BS12: =AVERAGE(BO12,BP12,BQ12,BR12) | BT12: =AVERAGE(BT9,BT7) | BU12: =AVERAGE(BU9,BU7) | BV12: =AVERAGE(BV9,BV7) | BW12: =AVERAGE(BW9,BW7) | BX12: =AVERAGE(BT12,BU12,BV12,BW12) | BY12: =AVERAGE(BY9,BY7) | BZ12: =AVERAGE(BZ9,BZ7) | CA12: =AVERAGE(CA9,CA7) | CB12: =AVERAGE(CB9,CB7) | CC12: =AVERAGE(BY12,BZ12,CA12,CB12) | CD12: =AVERAGE(CD9,CD7) | CE12: =AVERAGE(CE9,CE7) | CF12: =AVERAGE(CF9,CF7)
A13: Q/Q Total average paying memberships growth, % | H13: =H12/G12-1 | I13: =I12/H12-1 | J13: =J12/I12-1 | L13: =L12/J12-1 | M13: =M12/L12-1 | N13: =N12/M12-1 | O13: =O12/N12-1 | Q13: =Q12/O12-1 | R13: =R12/Q12-1 | S13: =S12/R12-1 | T13: =T12/S12-1 | V13: =V12/T12-1 | W13: =W12/V12-1 | X13: =X12/W12-1 | Y13: =Y12/X12-1 | AA13: =AA12/Y12-1 | AB13: =AB12/AA12-1 | AC13: =AC12/AB12-1 | AD13: =AD12/AC12-1 | AF13: =AF12/AD12-1 | AG13: =AG12/AF12-1 | AH13: =AH12/AG12-1 | AI13: =AI12/AH12-1 | AK13: =AK12/AI12-1 | AL13: =AL12/AK12-1 | AM13: =AM12/AL12-1 | AN13: =AN12/AM12-1 | AP13: =AP12/AN12-1 | AQ13: =AQ12/AP12-1 | AR13: =AR12/AQ12-1 | AS13: =AS12/AR12-1 | AU13: =AU12/AS12-1 | AV13: =AV12/AU12-1 | AW13: =AW12/AV12-1 | AX13: =AX12/AW12-1 | AZ13: =AZ12/AX12-1 | BA13: =BA12/AZ12-1 | BB13: =BB12/BA12-1 | BC13: =BC12/BB12-1 | BE13: =BE12/BC12-1 | BF13: =BF12/BE12-1 | BG13: =BG12/BF12-1 | BH13: =BH12/BG12-1 | BJ13: =BJ12/BH12-1 | BK13: =BK12/BJ12-1 | BL13: =BL12/BK12-1 | BM13: =BM12/BL12-1 | BO13: =BO12/BM12-1 | BP13: =BP12/BO12-1 | BQ13: =BQ12/BP12-1 | BR13: =BR12/BQ12-1 | BT13: =BT12/BR12-1 | BU13: =BU12/BT12-1 | BV13: =BV12/BU12-1 | BW13: =BW12/BV12-1 | BY13: =BY12/BW12-1 | BZ13: =BZ12/BY12-1 | CA13: =CA12/BZ12-1 | CB13: =CB12/CA12-1
A14: Y/Y Total average paying memberships growth, % | L14: =L12/G12-1 | M14: =M12/H12-1 | N14: =N12/I12-1 | O14: =O12/J12-1 | P14: =P12/K12-1 | Q14: =Q12/L12-1 | R14: =R12/M12-1 | S14: =S12/N12-1 | ... CC14: =CC12/BX12-1 | CD14: =CD12/CC12-1 | CE14: =CE12/CD12-1 | CF14: =CF12/CE12-1
A16: Total Global Streaming ARPU, $/Member | AA16: =AA183 | AB16: =AB183 | AC16: =AC183 | AD16: =AD183 | AE16: =AE183 | AF16: =AF183 | AG16: =AG183 | AH16: =AH183 | ... CF16: =CF183
A17: Q/Q Global streaming ARPU growth, % | AB17: =AB16/AA16-1 | AC17: =AC16/AB16-1 | AD17: =AD16/AC16-1 | AF17: =AF16/AD16-1 | AG17: =AG16/AF16-1 | AH17: =AH16/AG16-1 | AI17: =AI16/AH16-1 | AK17: =AK16/AI16-1 | AL17: =AL16/AK16-1 | AM17: =AM16/AL16-1 | AN17: =AN16/AM16-1 | AP17: =AP16/AN16-1 | AQ17: =AQ16/AP16-1 | AR17: =AR16/AQ16-1 | AS17: =AS16/AR16-1 | AU17: =AU16/AS16-1 | AV17: =AV16/AU16-1 | AW17: =AW16/AV16-1 | AX17: =AX16/AW16-1 | AZ17: =AZ16/AX16-1 | BA17: =BA16/AZ16-1 | BB17: =BB16/BA16-1 | BC17: =BC16/BB16-1 | BE17: =BE16/BC16-1 | BF17: =BF16/BE16-1 | BG17: =BG16/BF16-1 | BH17: =BH16/BG16-1 | BJ17: =BJ16/BH16-1 | BK17: =BK16/BJ16-1 | BL17: =BL16/BK16-1 | BM17: =BM16/BL16-1 | BO17: =BO16/BM16-1 | BP17: =BP16/BO16-1 | BQ17: =BQ16/BP16-1 | BR17: =BR16/BQ16-1 | BT17: =BT16/BR16-1 | BU17: =BU16/BT16-1 | BV17: =BV16/BU16-1 | BW17: =BW16/BV16-1 | BY17: =BY16/BW16-1 | BZ17: =BZ16/BY16-1 | CA17: =CA16/BZ16-1 | CB17: =CB16/CA16-1
A18: Y/Y Global streaming constant currency ARPU growth, % | AK18: 0.03 | AL18: 0.09 | AM18: 0.12 | AN18: 0.12 | AP18: 0.08 | AQ18: 0.05 | AR18: 0.01 | AS18: 0 | AU18: 0.05 | AV18: 0.04 | AW18: 0.05 | AX18: 0.07 | AZ18: 0.06 | BA18: 0.07 | BB18: 0.08 | BC18: 0.05 | BE18: 0.04 | BF18: -0.01 | BG18: -0.01 | BH18: 0.01 | BJ18: 0.04 | BK18: 0.05 | BL18: 0.05 | BM18: 0.03
A19: Y/Y Global streaming ARPU growth, % | AF19: =AF16/AA16-1 | AG19: =AG16/AB16-1 | AH19: =AH16/AC16-1 | AI19: =AI16/AD16-1 | AJ19: =AJ16/AE16-1 | AK19: =AK16/AF16-1 | AL19: =AL16/AG16-1 | AM19: =AM16/AH16-1 | ... CC19: =CC16/BX16-1 | CD19: =CD16/CC16-1 | CE19: =CE16/CD16-1 | CF19: =CF16/CE16-1
A21: Total Streaming Revenue, mm | F21: =F192 | G21: =G192 | H21: =H192 | I21: =I192 | J21: =J192 | K21: =K192 | L21: =L192 | M21: =M192 | ... CF21: =CF192
A22: Q/Q Streaming revenue growth, % | H22: =H21/G21-1 | I22: =I21/H21-1 | J22: =J21/I21-1 | L22: =L21/J21-1 | M22: =M21/L21-1 | N22: =N21/M21-1 | O22: =O21/N21-1 | Q22: =Q21/O21-1 | R22: =R21/Q21-1 | S22: =S21/R21-1 | T22: =T21/S21-1 | V22: =V21/T21-1 | W22: =W21/V21-1 | X22: =X21/W21-1 | Y22: =Y21/X21-1 | AA22: =AA21/Y21-1 | AB22: =AB21/AA21-1 | AC22: =AC21/AB21-1 | AD22: =AD21/AC21-1 | AF22: =AF21/AD21-1 | AG22: =AG21/AF21-1 | AH22: =AH21/AG21-1 | AI22: =AI21/AH21-1 | AK22: =AK21/AI21-1 | AL22: =AL21/AK21-1 | AM22: =AM21/AL21-1 | AN22: =AN21/AM21-1 | AP22: =AP21/AN21-1 | AQ22: =AQ21/AP21-1 | AR22: =AR21/AQ21-1 | AS22: =AS21/AR21-1 | AU22: =AU21/AS21-1 | AV22: =AV21/AU21-1 | AW22: =AW21/AV21-1 | AX22: =AX21/AW21-1 | AZ22: =AZ21/AX21-1 | BA22: =BA21/AZ21-1 | BB22: =BB21/BA21-1 | BC22: =BC21/BB21-1 | BE22: =BE21/BC21-1 | BF22: =BF21/BE21-1 | BG22: =BG21/BF21-1 | BH22: =BH21/BG21-1 | BJ22: =BJ21/BH21-1 | BK22: =BK21/BJ21-1 | BL22: =BL21/BK21-1 | BM22: =BM21/BL21-1 | BO22: =BO21/BM21-1 | BP22: =BP21/BO21-1 | BQ22: =BQ21/BP21-1 | BR22: =BR21/BQ21-1 | BT22: =BT21/BR21-1 | BU22: =BU21/BT21-1 | BV22: =BV21/BU21-1 | BW22: =BW21/BV21-1 | BY22: =BY21/BW21-1 | BZ22: =BZ21/BY21-1 | CA22: =CA21/BZ21-1 | CB22: =CB21/CA21-1
A23: Y/Y Streaming revenue growth, % | K23: =K21/F21-1 | L23: =L21/G21-1 | M23: =M21/H21-1 | N23: =N21/I21-1 | O23: =O21/J21-1 | P23: =P21/K21-1 | Q23: =Q21/L21-1 | R23: =R21/M21-1 | ... CC23: =CC21/BX21-1 | CD23: =CD21/CC21-1 | CE23: =CE21/CD21-1 | CF23: =CF21/CE21-1
A24: United States DVD Revenue, mm | F24: =F193 | G24: =G193 | H24: =H193 | I24: =I193 | J24: =J193 | K24: =K193 | L24: =L193 | M24: =M193 | ... BI24: =BI193
A25: Q/Q United States DVD revenue growth, % | H25: =H24/G24-1 | I25: =I24/H24-1 | J25: =J24/I24-1 | L25: =L24/J24-1 | M25: =M24/L24-1 | N25: =N24/M24-1 | O25: =O24/N24-1 | Q25: =Q24/O24-1 | R25: =R24/Q24-1 | S25: =S24/R24-1 | T25: =T24/S24-1 | V25: =V24/T24-1 | W25: =W24/V24-1 | X25: =X24/W24-1 | Y25: =Y24/X24-1 | AA25: =AA24/Y24-1 | AB25: =AB24/AA24-1 | AC25: =AC24/AB24-1 | AD25: =AD24/AC24-1 | AF25: =AF24/AD24-1 | AG25: =AG24/AF24-1 | AH25: =AH24/AG24-1 | AI25: =AI24/AH24-1 | AK25: =AK24/AI24-1 | AL25: =AL24/AK24-1 | AM25: =AM24/AL24-1 | AN25: =AN24/AM24-1 | AP25: =AP24/AN24-1 | AQ25: =AQ24/AP24-1 | AR25: =AR24/AQ24-1 | AS25: =AS24/AR24-1 | AU25: =AU24/AS24-1 | AV25: =AV24/AU24-1 | AW25: =AW24/AV24-1 | AX25: =AX24/AW24-1 | AZ25: =AZ24/AX24-1 | BA25: =BA24/AZ24-1 | BB25: =BB24/BA24-1 | BC25: =BC24/BB24-1 | BE25: =BE24/BC24-1 | BF25: =BF24/BE24-1 | BG25: =BG24/BF24-1
A26: Y/Y United States DVD revenue growth, % | K26: =K24/F24-1 | L26: =L24/G24-1 | M26: =M24/H24-1 | N26: =N24/I24-1 | O26: =O24/J24-1 | P26: =P24/K24-1 | Q26: =Q24/L24-1 | R26: =R24/M24-1 | ... BG26: =BG24/BB24-1 | BI26: =BI24/BD24-1
A28: Total Revenue, mm | C28: =C462 | D28: =D462 | E28: =E462 | F28: =F21+F24 | G28: =G21+G24 | H28: =H21+H24 | I28: =I21+I24 | J28: =J21+J24 | K28: =K21+K24 | L28: =L21+L24 | M28: =M21+M24 | ... CF28: =CF21+CF24
A29: =A463 | BU29: =BU463 | BV29: =BV463 | BW29: =BW463 | BX29: =BX463 | BY29: =BY463 | BZ29: =BZ463 | CA29: =CA463 | CB29: =CB463 | ... CF29: =CF463
A30: =A464 | AD30: =AD464 | AE30: =AE464 | AF30: =AF464 | AG30: =AG464 | AH30: =AH464 | AI30: =AI464 | AJ30: =AJ464 | AK30: =AK464 | ... CF30: =CF464
A31: Q/Q Total revenue growth, % | H31: =H28/G28-1 | I31: =I28/H28-1 | J31: =J28/I28-1 | L31: =L28/J28-1 | M31: =M28/L28-1 | N31: =N28/M28-1 | O31: =O28/N28-1 | Q31: =Q28/O28-1 | R31: =R28/Q28-1 | S31: =S28/R28-1 | T31: =T28/S28-1 | V31: =V28/T28-1 | W31: =W28/V28-1 | X31: =X28/W28-1 | Y31: =Y28/X28-1 | AA31: =AA28/Y28-1 | AB31: =AB28/AA28-1 | AC31: =AC28/AB28-1 | AD31: =AD28/AC28-1 | AF31: =AF28/AD28-1 | AG31: =AG28/AF28-1 | AH31: =AH28/AG28-1 | AI31: =AI28/AH28-1 | AK31: =AK28/AI28-1 | AL31: =AL28/AK28-1 | AM31: =AM28/AL28-1 | AN31: =AN28/AM28-1 | AP31: =AP28/AN28-1 | AQ31: =AQ28/AP28-1 | AR31: =AR28/AQ28-1 | AS31: =AS28/AR28-1 | AU31: =AU28/AS28-1 | AV31: =AV28/AU28-1 | AW31: =AW28/AV28-1 | AX31: =AX28/AW28-1 | AZ31: =AZ28/AX28-1 | BA31: =BA28/AZ28-1 | BB31: =BB28/BA28-1 | BC31: =BC28/BB28-1 | BE31: =BE28/BC28-1 | BF31: =BF28/BE28-1 | BG31: =BG28/BF28-1 | BH31: =BH28/BG28-1 | BJ31: =BJ28/BH28-1 | BK31: =BK28/BJ28-1 | BL31: =BL28/BK28-1 | BM31: =BM28/BL28-1 | BO31: =BO28/BM28-1 | BP31: =BP28/BO28-1 | BQ31: =BQ28/BP28-1 | BR31: =BR28/BQ28-1 | BT31: =BT28/BR28-1 | BU31: =BU28/BT28-1 | BV31: =BV28/BU28-1 | BW31: =BW28/BV28-1 | BY31: =BY28/BW28-1 | BZ31: =BZ28/BY28-1 | CA31: =CA28/BZ28-1 | CB31: =CB28/CA28-1
A32: Y/Y Total constant currency revenue growth (calculated), % | AK32: =AK35/AF28-1 | AL32: =AL35/AG28-1 | AM32: =AM35/AH28-1 | AN32: =AN35/AI28-1 | AO32: =AO35/AJ28-1 | AP32: =AP35/AK28-1 | AQ32: =AQ35/AL28-1 | AR32: =AR35/AM28-1 | ... BI32: =BI35/BD28-1 | BJ32: =BJ312 | BK32: =BK312 | BL32: =BL312 | BM32: =BM312 | BN32: =BN312 | BO32: =BO312 | BP32: =BP312 | BQ32: =BQ312 | ... BT32: =BT312
A33: Y/Y Total revenue growth, % | D33: =D28/C28-1 | E33: =E28/D28-1 | F33: =F28/E28-1 | K33: =K28/F28-1 | L33: =L28/G28-1 | M33: =M28/H28-1 | N33: =N28/I28-1 | O33: =O28/J28-1 | P33: =P28/K28-1 | Q33: =Q28/L28-1 | R33: =R28/M28-1 | ... CC33: =CC28/BX28-1 | CD33: =CD28/CC28-1 | CE33: =CE28/CD28-1 | CF33: =CF28/CE28-1
A35: Constant currency revenue, mm | AK35: =AK38-AK36 | AL35: =AL38-AL36 | AM35: =AM38-AM36 | AN35: =AN38-AN36 | AO35: =AO38-AO36 | AP35: =AP38-AP36 | AQ35: =AQ38-AQ36 | AR35: =AR38-AR36 | ... BI35: =BI38-BI36 | BJ35: =BJ38-SUM(BJ36:BJ37) | BK35: =BK38-SUM(BK36:BK37) | BL35: =BL38-SUM(BL36:BL37) | BM35: =BM38-SUM(BM36:BM37) | BN35: =BN38-SUM(BN36:BN37) | BO35: =BO38-SUM(BO36:BO37) | BP35: =BP38-SUM(BP36:BP37) | BQ35: =BQ38-SUM(BQ36:BQ37) | ... BT35: =BT38-SUM(BT36:BT37)
A36: FX impact, mm | AK36: -228 | AL36: -265 | AM36: -137 | AN36: -133 | AO36: -762 | AP36: -115 | AQ36: -289 | AR36: -158 | AS36: =AT36-SUM(AP36,AQ36,AR36) | AT36: -596 | AU36: 80 | AV36: 277 | AW36: 128 | AX36: =AY36-SUM(AU36,AV36,AW36) | AY36: 443 | AZ36: -280 | BA36: -339 | BB36: -548 | BC36: =BD36-SUM(AZ36,BA36,BB36) | BD36: -1773 | BE36: -345.859 | BF36: -231.144 | BG36: 8.548 | BH36: -28.294 | BI36: =SUM(BE36,BF36,BG36,BH36) | BJ36: =-BJ308 | BK36: =-BK308 | BL36: =-BL308 | BM36: =-BM308 | BN36: =-BN308 | BO36: =-BO308 | BP36: =-BP308 | BQ36: =-BQ308 | ... BT36: =-BT308
A37: Hedging (gains) losses included in revenue, mm | BJ37: =-BJ309 | BK37: =-BK309 | BL37: =-BL309 | BM37: =-BM309 | BN37: =-BN309 | BO37: =-BO309 | BP37: =-BP309 | BQ37: =-BQ309 | ... BT37: =-BT309
A38: Total Revenue, mm | AK38: =AK28 | AL38: =AL28 | AM38: =AM28 | AN38: =AN28 | AO38: =AO28 | AP38: =AP28 | AQ38: =AQ28 | AR38: =AR28 | ... BT38: =BT28
A40: Segmented Results - US and Canada Streaming (FS)
A41: United States EOP paid streaming memberships, 000s | F41: 25471 | G41: 27913 | H41: 28624 | I41: 29925 | J41: 31712 | K41: 31712 | L41: 34377 | M41: 35085 | N41: 36265 | O41: 37698 | P41: 37698 | Q41: 40315 | R41: 41057 | S41: 42068 | T41: 43401 | U41: 43401 | V41: 45714 | W41: 46004 | X41: 46479 | Y41: 47905 | Z41: 47905 | AA41: 49375 | AB41: 50323 | AC41: 51345 | AD41: 52810 | AE41: 52810 | AF41: 55087 | AG41: 55959 | AH41: 56957 | AI41: 58486 | AJ41: 58486 | AK41: 60229 | AL41: 60103 | AM41: 60620 | AN41: 61043 | AO41: 61043
A42: Q/Q United States EOP paid streaming membership growth, % | H42: =H41/G41-1 | I42: =I41/H41-1 | J42: =J41/I41-1 | L42: =L41/J41-1 | M42: =M41/L41-1 | N42: =N41/M41-1 | O42: =O41/N41-1 | Q42: =Q41/O41-1 | R42: =R41/Q41-1 | S42: =S41/R41-1 | T42: =T41/S41-1 | V42: =V41/T41-1 | W42: =W41/V41-1 | X42: =X41/W41-1 | Y42: =Y41/X41-1 | AA42: =AA41/Y41-1 | AB42: =AB41/AA41-1 | AC42: =AC41/AB41-1 | AD42: =AD41/AC41-1 | AF42: =AF41/AD41-1 | AG42: =AG41/AF41-1 | AH42: =AH41/AG41-1 | AI42: =AI41/AH41-1 | AK42: =AK41/AI41-1 | AL42: =AL41/AK41-1 | AM42: =AM41/AL41-1 | AN42: =AN41/AM41-1
A43: Y/Y United States EOP paid streaming membership growth, % | K43: =+K41/F41-1 | L43: =+L41/G41-1 | M43: =+M41/H41-1 | N43: =+N41/I41-1 | O43: =+O41/J41-1 | P43: =+P41/K41-1 | Q43: =+Q41/L41-1 | R43: =+R41/M41-1 | ... AO43: =+AO41/AJ41-1
A44: United States paid streaming memberships net additions, 000s | G44: =+G41-F41 | H44: =+H41-G41 | I44: =+I41-H41 | J44: =+J41-I41 | K44: =SUM(G44,H44,I44,J44) | L44: =+L41-K41 | M44: =+M41-L41 | N44: =+N41-M41 | O44: =+O41-N41 | P44: =SUM(L44,M44,N44,O44) | Q44: =+Q41-P41 | R44: =+R41-Q41 | S44: =+S41-R41 | T44: =+T41-S41 | U44: =SUM(Q44,R44,S44,T44) | V44: =+V41-U41 | W44: =+W41-V41 | X44: =+X41-W41 | Y44: =+Y41-X41 | Z44: =SUM(V44,W44,X44,Y44) | AA44: =+AA41-Z41 | AB44: =+AB41-AA41 | AC44: =+AC41-AB41 | AD44: =+AD41-AC41 | AE44: =SUM(AA44,AB44,AC44,AD44) | AF44: =+AF41-AE41 | AG44: =+AG41-AF41 | AH44: =+AH41-AG41 | AI44: =+AI41-AH41 | AJ44: =SUM(AF44,AG44,AH44,AI44) | AK44: =+AK41-AJ41 | AL44: =+AL41-AK41 | AM44: =+AM41-AL41 | AN44: =+AN41-AM41 | AO44: =SUM(AK44,AL44,AM44,AN44)
A45: Calculated Canada EOP paid streaming memberships, 000s | AA45: =+AA52-AA41 | AB45: =+AB52-AB41 | AC45: =+AC52-AC41 | AD45: =+AD52-AD41 | AE45: =+AE52-AE41 | AF45: =+AF52-AF41 | AG45: =+AG52-AG41 | AH45: =+AH52-AH41 | ... AO45: =+AO52-AO41
A46: Q/Q Calculated Canada EOP paid streaming membership growth, % | AB46: =AB45/AA45-1 | AC46: =AC45/AB45-1 | AD46: =AD45/AC45-1 | AF46: =AF45/AD45-1 | AG46: =AG45/AF45-1 | AH46: =AH45/AG45-1 | AI46: =AI45/AH45-1 | AK46: =AK45/AI45-1 | AL46: =AL45/AK45-1 | AM46: =AM45/AL45-1 | AN46: =AN45/AM45-1
A47: Y/Y Calculated Canada EOP paid streaming membership growth, % | AF47: =+AF45/AA45-1 | AG47: =+AG45/AB45-1 | AH47: =+AH45/AC45-1 | AI47: =+AI45/AD45-1 | AJ47: =+AJ45/AE45-1 | AK47: =+AK45/AF45-1 | AL47: =+AL45/AG45-1 | AM47: =+AM45/AH45-1 | ... AO47: =+AO45/AJ45-1
A48: Canada paid streaming memberships net additions, 000s | AA48: =AA51-AA44 | AB48: =+AB45-AA45 | AC48: =+AC45-AB45 | AD48: =+AD45-AC45 | AE48: =SUM(AA48,AB48,AC48,AD48) | AF48: =+AF45-AE45 | AG48: =+AG45-AF45 | AH48: =+AH45-AG45 | AI48: =+AI45-AH45 | AJ48: =SUM(AF48,AG48,AH48,AI48) | AK48: =+AK45-AJ45 | AL48: =+AL45-AK45 | AM48: =+AM45-AL45 | AN48: =+AN45-AM45 | AO48: =SUM(AK48,AL48,AM48,AN48)
A50: BoP United States & Canada Paid Streaming Memberships, 000s | AA50: =AA56*2-AA52 | AB50: =AA52 | AC50: =AB52 | AD50: =AC52 | AE50: =AA50 | AF50: =AE52 | AG50: =AF52 | AH50: =AG52 | AI50: =AH52 | AJ50: =AE52 | AK50: =AJ52 | AL50: =AK52 | AM50: =AL52 | AN50: =AM52 | AO50: =AJ52 | AP50: =AO52 | AQ50: =AP52 | AR50: =AQ52 | AS50: =AR52 | AT50: =AO52 | AU50: =AT52 | AV50: =AU52 | AW50: =AV52 | AX50: =AW52 | AY50: =AT52 | AZ50: =AY52 | BA50: =AZ52 | BB50: =BA52 | BC50: =BB52 | BD50: =AY52 | BE50: =BD52 | BF50: =BE52 | BG50: =BF52 | BH50: =BG52 | BI50: =BD52 | BJ50: =BI52 | BK50: =BJ52 | BL50: =BK52 | BM50: =BL52 | BN50: =BI52 | BO50: =BN52 | BP50: =BO52 | BQ50: =BP52 | BR50: =BQ52 | BS50: =BN52 | BT50: =BS52 | BU50: =BT52 | BV50: =BU52 | BW50: =BV52 | BX50: =BS52 | BY50: =BX52 | BZ50: =BY52 | CA50: =BZ52 | CB50: =CA52 | CC50: =BX52 | CD50: =CC52 | CE50: =CD52 | CF50: =CE52
A51: United States and Canada Paid Streaming Memberships Net Additions, 000s | AA51: =AA52-AA50 | AB51: =AB52-AB50 | AC51: =AC52-AC50 | AD51: =AD52-AD50 | AE51: =SUM(AA51,AB51,AC51,AD51) | AF51: =AF52-AF50 | AG51: =AG52-AG50 | AH51: =AH52-AH50 | AI51: =AI52-AI50 | AJ51: =SUM(AF51,AG51,AH51,AI51) | AK51: =AK52-AK50 | AL51: =AL52-AL50 | AM51: =AM52-AM50 | AN51: =AN52-AN50 | AO51: =SUM(AK51,AL51,AM51,AN51) | AP51: =AP52-AP50 | AQ51: =AQ52-AQ50 | AR51: =AR52-AR50 | AS51: =AS52-AS50 | AT51: =SUM(AP51,AQ51,AR51,AS51) | AU51: =AU52-AU50 | AV51: =AV52-AV50 | AW51: =AW52-AW50 | AX51: =AX52-AX50 | AY51: =SUM(AU51,AV51,AW51,AX51) | AZ51: =AZ52-AZ50 | BA51: =BA52-BA50 | BB51: =BB52-BB50 | BC51: =BC52-BC50 | BD51: =SUM(AZ51,BA51,BB51,BC51) | BE51: =BE52-BE50 | BF51: =BF52-BF50 | BG51: =BG52-BG50 | BH51: =BH52-BH50 | BI51: =SUM(BE51,BF51,BG51,BH51) | BJ51: =BJ52-BJ50 | BK51: =BK52-BK50 | BL51: =BL52-BL50 | BM51: =BM52-BM50 | BN51: =SUM(BJ51,BK51,BL51,BM51) | BO51: =BO52-BO50 | BP51: =BP52-BP50 | BQ51: =BQ52-BQ50 | BR51: =BR52-BR50 | BS51: =SUM(BO51,BP51,BQ51,BR51) | BT51: =BT52-BT50 | BU51: =BU53*BU50 | BV51: =BV53*BV50 | BW51: =BW53*BW50 | BX51: =SUM(BT51,BU51,BV51,BW51) | BY51: =BY53*BY50 | BZ51: =BZ53*BZ50 | CA51: =CA53*CA50 | CB51: =CB53*CB50 | CC51: =SUM(BY51,BZ51,CA51,CB51) | CD51: =CD54*CD50 | CE51: =CE54*CE50 | CF51: =CF54*CF50
A52: EoP United States & Canada Paid Streaming Memberships, 000s | AA52: 54575 | AB52: 55617 | AC52: 56779 | AD52: 58422 | AE52: =SUM(AE50:AE51) | AF52: 60909 | AG52: 61870 | AH52: 63010 | AI52: 64757 | AJ52: =SUM(AJ50:AJ51) | AK52: 66633 | AL52: 66501 | AM52: 67114 | AN52: 67662 | AO52: =SUM(AO50:AO51) | AP52: 69969 | AQ52: 72904 | AR52: 73081 | AS52: 73936 | AT52: =SUM(AT50:AT51) | AU52: 74384 | AV52: 73951 | AW52: 74024 | AX52: 75215 | AY52: =SUM(AY50:AY51) | AZ52: 74579 | BA52: 73283 | BB52: 73387 | BC52: 74296 | BD52: =SUM(BD50:BD51) | BE52: 74398 | BF52: 75571 | BG52: 77321 | BH52: 80128 | BI52: =SUM(BI50:BI51) | BJ52: 82658 | BK52: 84109 | BL52: 84803 | BM52: 89625 | BN52: =SUM(BN50:BN51) | BO52: 88000 | BP52: 91000 | BQ52: 92000 | BR52: 93000 | BS52: =SUM(BS50:BS51) | BT52: 94000 | BU52: =SUM(BU50:BU51) | BV52: =SUM(BV50:BV51) | BW52: =SUM(BW50:BW51) | BX52: =SUM(BX50:BX51) | BY52: =SUM(BY50:BY51) | BZ52: =SUM(BZ50:BZ51) | CA52: =SUM(CA50:CA51) | CB52: =SUM(CB50:CB51) | ... CF52: =SUM(CF50:CF51)
A53: Q/Q United States & Canada EOP paid streaming memberships growth, % | AB53: =AB52/AA52-1 | AC53: =AC52/AB52-1 | AD53: =AD52/AC52-1 | AF53: =AF52/AD52-1 | AG53: =AG52/AF52-1 | AH53: =AH52/AG52-1 | AI53: =AI52/AH52-1 | AK53: =AK52/AI52-1 | AL53: =AL52/AK52-1 | AM53: =AM52/AL52-1 | AN53: =AN52/AM52-1 | AP53: =AP52/AN52-1 | AQ53: =AQ52/AP52-1 | AR53: =AR52/AQ52-1 | AS53: =AS52/AR52-1 | AU53: =AU52/AS52-1 | AV53: =AV52/AU52-1 | AW53: =AW52/AV52-1 | AX53: =AX52/AW52-1 | AZ53: =AZ52/AX52-1 | BA53: =BA52/AZ52-1 | BB53: =BB52/BA52-1 | BC53: =BC52/BB52-1 | BE53: =BE52/BC52-1 | BF53: =BF52/BE52-1 | BG53: =BG52/BF52-1 | BH53: =BH52/BG52-1 | BJ53: =BJ52/BH52-1 | BK53: =BK52/BJ52-1 | BL53: =BL52/BK52-1 | BM53: =BM52/BL52-1 | BO53: =BO52/BM52-1 | BP53: =BP52/BO52-1 | BQ53: =BQ52/BP52-1 | BR53: =BR52/BQ52-1 | BT53: =BT52/BR52-1 | BU53: 0.01 | BV53: 0.02 | BW53: 0.01 | BY53: 0.005 | BZ53: 0.005 | CA53: 0.005 | CB53: 0.005
A54: Y/Y United States & Canada EOP paid streaming memberships growth, % | AF54: =+AF52/AA52-1 | AG54: =+AG52/AB52-1 | AH54: =+AH52/AC52-1 | AI54: =+AI52/AD52-1 | AJ54: =+AJ52/AE52-1 | AK54: =+AK52/AF52-1 | AL54: =+AL52/AG52-1 | AM54: =+AM52/AH52-1 | ... CC54: =+CC52/BX52-1 | CD54: 0.05 | CE54: 0.05 | CF54: 0.05
A56: United States & Canada Average Paying Memberships, 000s | AA56: 53743 | AB56: =AVERAGE(AB52,AB50) | AC56: =AVERAGE(AC52,AC50) | AD56: =AVERAGE(AD52,AD50) | AE56: =AVERAGE(AA56,AB56,AC56,AD56) | AF56: =AVERAGE(AF52,AF50) | AG56: =AVERAGE(AG52,AG50) | AH56: =AVERAGE(AH52,AH50) | AI56: =AVERAGE(AI52,AI50) | AJ56: =AVERAGE(AF56,AG56,AH56,AI56) | AK56: =AVERAGE(AK52,AK50) | AL56: =AVERAGE(AL52,AL50) | AM56: =AVERAGE(AM52,AM50) | AN56: =AVERAGE(AN52,AN50) | AO56: =AVERAGE(AK56,AL56,AM56,AN56) | AP56: =AVERAGE(AP52,AP50) | AQ56: =AVERAGE(AQ52,AQ50) | AR56: =AVERAGE(AR52,AR50) | AS56: =AVERAGE(AS52,AS50) | AT56: =AVERAGE(AP56,AQ56,AR56,AS56) | AU56: =AVERAGE(AU52,AU50) | AV56: =AVERAGE(AV52,AV50) | AW56: =AVERAGE(AW52,AW50) | AX56: =AVERAGE(AX52,AX50) | AY56: =AVERAGE(AU56,AV56,AW56,AX56) | AZ56: =AVERAGE(AZ52,AZ50) | BA56: =AVERAGE(BA52,BA50) | BB56: =AVERAGE(BB52,BB50) | BC56: =AVERAGE(BC52,BC50) | BD56: =AVERAGE(AZ56,BA56,BB56,BC56) | BE56: =AVERAGE(BE52,BE50) | BF56: =AVERAGE(BF52,BF50) | BG56: =AVERAGE(BG52,BG50) | BH56: =AVERAGE(BH52,BH50) | BI56: =AVERAGE(BE56,BF56,BG56,BH56) | BJ56: =AVERAGE(BJ52,BJ50) | BK56: =AVERAGE(BK52,BK50) | BL56: =AVERAGE(BL52,BL50) | BM56: =AVERAGE(BM52,BM50) | BN56: =AVERAGE(BJ56,BK56,BL56,BM56) | BO56: =AVERAGE(BO52,BO50) | BP56: =AVERAGE(BP52,BP50) | BQ56: =AVERAGE(BQ52,BQ50) | BR56: =AVERAGE(BR52,BR50) | BS56: =AVERAGE(BO56,BP56,BQ56,BR56) | BT56: =AVERAGE(BT52,BT50) | BU56: =AVERAGE(BU52,BU50) | BV56: =AVERAGE(BV52,BV50) | BW56: =AVERAGE(BW52,BW50) | BX56: =AVERAGE(BT56,BU56,BV56,BW56) | BY56: =AVERAGE(BY52,BY50) | BZ56: =AVERAGE(BZ52,BZ50) | CA56: =AVERAGE(CA52,CA50) | CB56: =AVERAGE(CB52,CB50) | CC56: =AVERAGE(BY56,BZ56,CA56,CB56) | CD56: =AVERAGE(CD52,CD50) | CE56: =AVERAGE(CE52,CE50) | CF56: =AVERAGE(CF52,CF50)
A57: Q/Q United States & Canada average paying memberships growth, % | AB57: =AB56/AA56-1 | AC57: =AC56/AB56-1 | AD57: =AD56/AC56-1 | AF57: =AF56/AD56-1 | AG57: =AG56/AF56-1 | AH57: =AH56/AG56-1 | AI57: =AI56/AH56-1 | AK57: =AK56/AI56-1 | AL57: =AL56/AK56-1 | AM57: =AM56/AL56-1 | AN57: =AN56/AM56-1 | AP57: =AP56/AN56-1 | AQ57: =AQ56/AP56-1 | AR57: =AR56/AQ56-1 | AS57: =AS56/AR56-1 | AU57: =AU56/AS56-1 | AV57: =AV56/AU56-1 | AW57: =AW56/AV56-1 | AX57: =AX56/AW56-1 | AZ57: =AZ56/AX56-1 | BA57: =BA56/AZ56-1 | BB57: =BB56/BA56-1 | BC57: =BC56/BB56-1 | BE57: =BE56/BC56-1 | BF57: =BF56/BE56-1 | BG57: =BG56/BF56-1 | BH57: =BH56/BG56-1 | BJ57: =BJ56/BH56-1 | BK57: =BK56/BJ56-1 | BL57: =BL56/BK56-1 | BM57: =BM56/BL56-1 | BO57: =BO56/BM56-1 | BP57: =BP56/BO56-1 | BQ57: =BQ56/BP56-1 | BR57: =BR56/BQ56-1 | BT57: =BT56/BR56-1 | BU57: =BU56/BT56-1 | BV57: =BV56/BU56-1 | BW57: =BW56/BV56-1 | BY57: =BY56/BW56-1 | BZ57: =BZ56/BY56-1 | CA57: =CA56/BZ56-1 | CB57: =CB56/CA56-1
A58: Y/Y United States & Canada average paying memberships growth, % | AF58: =AF56/AA56-1 | AG58: =AG56/AB56-1 | AH58: =AH56/AC56-1 | AI58: =AI56/AD56-1 | AJ58: =AJ56/AE56-1 | AK58: =AK56/AF56-1 | AL58: =AL56/AG56-1 | AM58: =AM56/AH56-1 | ... CC58: =CC56/BX56-1 | CD58: =CD56/CC56-1 | CE58: =CE56/CD56-1 | CF58: =CF56/CE56-1
A60: United States Streaming ARPU, $/member | G60: =+G69*1000/(AVERAGE(G41,F41))/3 | H60: =+H69*1000/(AVERAGE(H41,G41))/3 | I60: =+I69*1000/(AVERAGE(I41,H41))/3 | J60: =+J69*1000/(AVERAGE(J41,I41))/3 | K60: =AVERAGE(G60,H60,I60,J60) | L60: =+L69*1000/(AVERAGE(L41,K41))/3 | M60: =+M69*1000/(AVERAGE(M41,L41))/3 | N60: =+N69*1000/(AVERAGE(N41,M41))/3 | O60: =+O69*1000/(AVERAGE(O41,N41))/3 | P60: =AVERAGE(L60,M60,N60,O60) | Q60: =+Q69*1000/(AVERAGE(Q41,P41))/3 | R60: =+R69*1000/(AVERAGE(R41,Q41))/3 | S60: =+S69*1000/(AVERAGE(S41,R41))/3 | T60: =+T69*1000/(AVERAGE(T41,S41))/3 | U60: =AVERAGE(Q60,R60,S60,T60) | V60: =+V69*1000/(AVERAGE(V41,U41))/3 | W60: =+W69*1000/(AVERAGE(W41,V41))/3 | X60: =+X69*1000/(AVERAGE(X41,W41))/3 | Y60: =+Y69*1000/(AVERAGE(Y41,X41))/3 | Z60: =AVERAGE(V60,W60,X60,Y60) | AA60: =+AA69*1000/(AVERAGE(AA41,Z41))/3 | AB60: =+AB69*1000/(AVERAGE(AB41,AA41))/3 | AC60: =+AC69*1000/(AVERAGE(AC41,AB41))/3 | AD60: =+AD69*1000/(AVERAGE(AD41,AC41))/3 | AE60: =AVERAGE(AA60,AB60,AC60,AD60) | AF60: =+AF69*1000/(AVERAGE(AF41,AE41))/3 | AG60: =+AG69*1000/(AVERAGE(AG41,AF41))/3 | AH60: =+AH69*1000/(AVERAGE(AH41,AG41))/3 | AI60: =+AI69*1000/(AVERAGE(AI41,AH41))/3 | AJ60: =AVERAGE(AF60,AG60,AH60,AI60) | AK60: =+AK69*1000/(AVERAGE(AK41,AJ41))/3 | AL60: =+AL69*1000/(AVERAGE(AL41,AK41))/3 | AM60: =+AM69*1000/(AVERAGE(AM41,AL41))/3 | AN60: =+AN69*1000/(AVERAGE(AN41,AM41))/3 | AO60: =AVERAGE(AK60,AL60,AM60,AN60)
A61: Y/Y United States streaming ARPU growth, % | L61: =+L60/G60-1 | M61: =+M60/H60-1 | N61: =+N60/I60-1 | O61: =+O60/J60-1 | P61: =+P60/K60-1 | Q61: =+Q60/L60-1 | R61: =+R60/M60-1 | S61: =+S60/N60-1 | ... AO61: =+AO60/AJ60-1
A62: Calculated Canada Streaming ARPU, $/member | AA62: =+AA71*1000/AVERAGE(AA45,Z45)/3 | AB62: =+AB71*1000/AVERAGE(AB45,AA45)/3 | AC62: =+AC71*1000/AVERAGE(AC45,AB45)/3 | AD62: =+AD71*1000/AVERAGE(AD45,AC45)/3 | AE62: =AVERAGE(AA62,AB62,AC62,AD62) | AF62: =+AF71*1000/AVERAGE(AF45,AE45)/3 | AG62: =+AG71*1000/AVERAGE(AG45,AF45)/3 | AH62: =+AH71*1000/AVERAGE(AH45,AG45)/3 | AI62: =+AI71*1000/AVERAGE(AI45,AH45)/3 | AJ62: =AVERAGE(AF62,AG62,AH62,AI62) | AK62: =+AK71*1000/AVERAGE(AK45,AJ45)/3 | AL62: =+AL71*1000/AVERAGE(AL45,AK45)/3 | AM62: =+AM71*1000/AVERAGE(AM45,AL45)/3 | AN62: =+AN71*1000/AVERAGE(AN45,AM45)/3 | AO62: =AVERAGE(AK62,AL62,AM62,AN62)
A63: Y/Y Calculated Canada streaming ARPU growth, % | AF63: =+AF62/AA62-1 | AG63: =+AG62/AB62-1 | AH63: =+AH62/AC62-1 | AI63: =+AI62/AD62-1 | AJ63: =+AJ62/AE62-1 | AK63: =+AK62/AF62-1 | AL63: =+AL62/AG62-1 | AM63: =+AM62/AH62-1 | ... AO63: =+AO62/AJ62-1
A64: United States & Canada Streaming ARPU, $/member | AA64: 9.84 | AB64: 9.83 | AC64: 9.93 | AD64: 10.28 | AE64: 9.97 | AF64: 11.04 | AG64: 11.13 | AH64: 11.18 | AI64: 11.28 | AJ64: 11.16 | AK64: 11.45 | AL64: 12.52 | AM64: 13.08 | AN64: 13.22 | AO64: 12.57 | AP64: 13.09 | AQ64: 13.25 | AR64: 13.4 | AS64: 13.51 | AT64: 13.32 | AU64: 14.25 | AV64: 14.54 | AW64: 14.68 | AX64: 14.78 | AY64: 14.56 | AZ64: 14.91 | BA64: 15.95 | BB64: 16.37 | BC64: 16.23 | BD64: 15.86 | BE64: 16.18 | BF64: 16 | BG64: 16.29 | BH64: 16.64 | BI64: 16.28 | BJ64: 17.3 | BK64: 17.17 | BL64: 17.06 | BM64: 17.26 | BN64: 17.2 | BO64: =BO73/BO56*1000/3 | BP64: =BP73/BP56*1000/3 | BQ64: =BQ73/BQ56*1000/3 | BR64: =BR73/BR56*1000/3 | BS64: =BS73/BS56*1000/12 | BT64: =BT73/BT52*1000/3 | BU64: =BT64*(1+BU65) | BV64: =BU64*(1+BV65) | BW64: =BV64*(1+BW65) | BX64: =AVERAGE(BT64,BU64,BV64,BW64) | BY64: =BW64*(1+BY65) | BZ64: =BY64*(1+BZ65) | CA64: =BZ64*(1+CA65) | CB64: =CA64*(1+CB65) | CC64: =AVERAGE(BY64,BZ64,CA64,CB64) | CD64: =+CC64*(1+CD67) | CE64: =+CD64*(1+CE67) | CF64: =+CE64*(1+CF67)
A65: Q/Q United States & Canada streaming ARPU growth, % | AB65: =AB64/AA64-1 | AC65: =AC64/AB64-1 | AD65: =AD64/AC64-1 | AF65: =AF64/AD64-1 | AG65: =AG64/AF64-1 | AH65: =AH64/AG64-1 | AI65: =AI64/AH64-1 | AK65: =AK64/AI64-1 | AL65: =AL64/AK64-1 | AM65: =AM64/AL64-1 | AN65: =AN64/AM64-1 | AP65: =AP64/AN64-1 | AQ65: =AQ64/AP64-1 | AR65: =AR64/AQ64-1 | AS65: =AS64/AR64-1 | AU65: =AU64/AS64-1 | AV65: =AV64/AU64-1 | AW65: =AW64/AV64-1 | AX65: =AX64/AW64-1 | AZ65: =AZ64/AX64-1 | BA65: =BA64/AZ64-1 | BB65: =BB64/BA64-1 | BC65: =BC64/BB64-1 | BE65: =BE64/BC64-1 | BF65: =BF64/BE64-1 | BG65: =BG64/BF64-1 | BH65: =BH64/BG64-1 | BJ65: =BJ64/BH64-1 | BK65: =BK64/BJ64-1 | BL65: =BL64/BK64-1 | BM65: =BM64/BL64-1 | BO65: =BO64/BM64-1 | BP65: =BP64/BO64-1 | BQ65: =BQ64/BP64-1 | BR65: =BR64/BQ64-1 | BT65: =BT64/BR64-1 | BU65: 0.02 | BV65: 0.02 | BW65: 0.01 | BY65: 0.01 | BZ65: 0.005 | CA65: 0.005 | CB65: 0.005
A66: Y/Y US and Canada streaming constant currency ARPU growth, % | AA66: 0.16 | AB66: 0.15 | AC66: 0.08 | AD66: 0.06 | AE66: 0.11 | AF66: 0.12 | AG66: 0.13 | AH66: 0.13 | AI66: 0.1 | AJ66: 0.12 | AK66: 0.04 | AL66: 0.13 | AM66: 0.17 | AN66: 0.17 | AO66: 0.13 | AP66: 0.14 | AQ66: 0.06 | AR66: 0.03 | AS66: 0.02 | AT66: 0.06 | AU66: 0.09 | AV66: 0.09 | AW66: 0.09 | AX66: 0.09 | AY66: 0.09 | AZ66: 0.05 | BA66: 0.1 | BB66: 0.12 | BC66: 0.1 | BD66: 0.09 | BE66: 0.09 | BF66: 0.01 | BG66: 0 | BH66: 0.03 | BI66: 0.03 | BJ66: 0.07 | BK66: 0.07 | BL66: 0.05 | BM66: 0.04 | BN66: 0.06
A67: Y/Y United States & Canada streaming ARPU growth, % | AF67: =+AF64/AA64-1 | AG67: =+AG64/AB64-1 | AH67: =+AH64/AC64-1 | AI67: =+AI64/AD64-1 | AJ67: =+AJ64/AE64-1 | AK67: =+AK64/AF64-1 | AL67: =+AL64/AG64-1 | AM67: =+AM64/AH64-1 | ... CC67: =+CC64/BX64-1 | CD67: 0.062 | CE67: 0.062 | CF67: 0.062
A69: United States streaming revenue, mm | F69: 2184.868 | G69: 638.649 | H69: 671.089 | I69: 701.083 | J69: 740.554 | K69: 2751.375 | L69: 798.617 | M69: 838.225 | N69: 877.15 | O69: 917.442 | P69: 3431.434 | Q69: 984.532 | R69: 1025.913 | S69: 1063.961 | T69: 1105.933 | U69: 4180.339 | V69: 1161.241 | W69: 1208.271 | X69: 1304.333 | Y69: 1403.462 | Z69: 5077.307 | AA69: 1470.042 | AB69: 1505.499 | AC69: 1547.21 | AD69: 1630.274 | AE69: 6153.025 | AF69: 1820.019 | AG69: 1893.222 | AH69: 1937.314 | AI69: 1996.092 | AJ69: 7646.647 | AK69: 2073.555 | AL69: 2299.189 | AM69: 2412.598 | AN69: 2457.663 | AO69: 9243.005
A70: Y/Y United States streaming revenue growth, % | K70: =+K69/F69-1 | L70: =+L69/G69-1 | M70: =+M69/H69-1 | N70: =+N69/I69-1 | O70: =+O69/J69-1 | P70: =+P69/K69-1 | Q70: =+Q69/L69-1 | R70: =+R69/M69-1 | ... AO70: =+AO69/AJ69-1
A71: Calculated Canada streaming revenue, mm | AA71: =+AA73-AA69 | AB71: =+AB73-AB69 | AC71: =+AC73-AC69 | AD71: =+AD73-AD69 | AE71: =+AE73-AE69 | AF71: =+AF73-AF69 | AG71: =+AG73-AG69 | AH71: =+AH73-AH69 | ... AO71: =+AO73-AO69
A72: Y/Y Calculated Canada streaming revenue growth, % | AF72: =+AF71/AA71-1 | AG72: =+AG71/AB71-1 | AH72: =+AH71/AC71-1 | AI72: =+AI71/AD71-1 | AJ72: =+AJ71/AE71-1 | AK72: =+AK71/AF71-1 | AL72: =+AL71/AG71-1 | AM72: =+AM71/AH71-1 | ... AO72: =+AO71/AJ71-1
A73: United States & Canada Streaming Revenue, mm | AA73: 1586.167 | AB73: 1624.397 | AC73: 1674.308 | AD73: 1775.987 | AE73: 6660.859 | AF73: 1976.157 | AG73: 2049.546 | AH73: 2094.85 | AI73: 2160.979 | AJ73: 8281.532 | AK73: 2256.851 | AL73: 2501.199 | AM73: 2621.25 | AN73: 2671.908 | AO73: 10051.208 | AP73: 2702.776 | AQ73: 2839.67 | AR73: 2933.445 | AS73: =AT73-SUM(AP73,AQ73,AR73) | AT73: 11455.396 | AU73: 3170.972 | AV73: 3234.643 | AW73: 3257.697 | AX73: =AY73-SUM(AU73,AV73,AW73) | AY73: 12972.1 | AZ73: 3350.424 | BA73: 3537.863 | BB73: 3601.565 | BC73: =BD73-SUM(AZ73,BA73,BB73) | BD73: 14084.643 | BE73: 3608.645 | BF73: 3599.448 | BG73: 3735.133 | BH73: =BI73-SUM(BE73,BF73,BG73) | BI73: 14873.783 | BJ73: 4224.315 | BK73: 4295.56 | BL73: 4322.476 | BM73: =BN73-SUM(BJ73,BK73,BL73) | BN73: 17359.369 | BO73: 4617.098 | BP73: 4929.003 | BQ73: 5071.781 | BR73: =BS73-SUM(BO73,BP73,BQ73) | BS73: 19957.152 | BT73: 5245.298 | BU73: =BU56*BU64*3/1000 | BV73: =BV56*BV64*3/1000 | BW73: =BW56*BW64*3/1000 | BX73: =SUM(BT73,BU73,BV73,BW73) | BY73: =BY56*BY64*3/1000 | BZ73: =BZ56*BZ64*3/1000 | CA73: =CA56*CA64*3/1000 | CB73: =CB56*CB64*3/1000 | CC73: =SUM(BY73,BZ73,CA73,CB73) | CD73: =CD56*CD64*12/1000 | CE73: =CE56*CE64*12/1000 | CF73: =CF56*CF64*12/1000
A74: Q/Q United States & Canada streaming revenue growth, % | AB74: =AB73/AA73-1 | AC74: =AC73/AB73-1 | AD74: =AD73/AC73-1 | AF74: =AF73/AD73-1 | AG74: =AG73/AF73-1 | AH74: =AH73/AG73-1 | AI74: =AI73/AH73-1 | AK74: =AK73/AI73-1 | AL74: =AL73/AK73-1 | AM74: =AM73/AL73-1 | AN74: =AN73/AM73-1 | AP74: =AP73/AN73-1 | AQ74: =AQ73/AP73-1 | AR74: =AR73/AQ73-1 | AS74: =AS73/AR73-1 | AU74: =AU73/AS73-1 | AV74: =AV73/AU73-1 | AW74: =AW73/AV73-1 | AX74: =AX73/AW73-1 | AZ74: =AZ73/AX73-1 | BA74: =BA73/AZ73-1 | BB74: =BB73/BA73-1 | BC74: =BC73/BB73-1 | BE74: =BE73/BC73-1 | BF74: =BF73/BE73-1 | BG74: =BG73/BF73-1 | BH74: =BH73/BG73-1 | BJ74: =BJ73/BH73-1 | BK74: =BK73/BJ73-1 | BL74: =BL73/BK73-1 | BM74: =BM73/BL73-1 | BO74: =BO73/BM73-1 | BP74: =BP73/BO73-1 | BQ74: =BQ73/BP73-1 | BR74: =BR73/BQ73-1 | BT74: =BT73/BR73-1 | BU74: =BU73/BT73-1 | BV74: =BV73/BU73-1 | BW74: =BW73/BV73-1 | BY74: =BY73/BW73-1 | BZ74: =BZ73/BY73-1 | CA74: =CA73/BZ73-1 | CB74: =CB73/CA73-1
A75: Y/Y United States & Canada streaming revenue growth, % | AF75: =+AF73/AA73-1 | AG75: =+AG73/AB73-1 | AH75: =+AH73/AC73-1 | AI75: =+AI73/AD73-1 | AJ75: =+AJ73/AE73-1 | AK75: =+AK73/AF73-1 | AL75: =+AL73/AG73-1 | AM75: =+AM73/AH73-1 | ... CC75: =+CC73/BX73-1 | CD75: =+CD73/CC73-1 | CE75: =+CE73/CD73-1 | CF75: =+CF73/CE73-1
A77: Segmented Results - EMEA Streaming (FS)
A78: BoP EMEA Paid Streaming Memberships, 000s | AA78: =AA84*2-AA80 | AB78: =AA80 | AC78: =AB80 | AD78: =AC80 | AE78: =AA78 | AF78: =AE80 | AG78: =AF80 | AH78: =AG80 | AI78: =AH80 | AJ78: =AE80 | AK78: =AJ80 | AL78: =AK80 | AM78: =AL80 | AN78: =AM80 | AO78: =AJ80 | AP78: =AO80 | AQ78: =AP80 | AR78: =AQ80 | AS78: =AR80 | AT78: =AO80 | AU78: =AT80 | AV78: =AU80 | AW78: =AV80 | AX78: =AW80 | AY78: =AT80 | AZ78: =AY80 | BA78: =AZ80 | BB78: =BA80 | BC78: =BB80 | BD78: =AY80 | BE78: =BD80 | BF78: =BE80 | BG78: =BF80 | BH78: =BG80 | BI78: =BD80 | BJ78: =BI80 | BK78: =BJ80 | BL78: =BK80 | BM78: =BL80 | BN78: =BI80 | BO78: =BN80 | BP78: =BO80 | BQ78: =BP80 | BR78: =BQ80 | BS78: =BN80 | BT78: =BS80 | BU78: =BT80 | BV78: =BU80 | BW78: =BV80 | BX78: =BS80 | BY78: =BX80 | BZ78: =BY80 | CA78: =BZ80 | CB78: =CA80 | CC78: =BX80 | CD78: =CC80 | CE78: =CD80 | CF78: =CE80
A79: EMEA Paid Streaming Memberships Net Additions, 000s | AA79: =AA80-AA78 | AB79: =AB80-AB78 | AC79: =AC80-AC78 | AD79: =AD80-AD78 | AE79: =SUM(AA79,AB79,AC79,AD79) | AF79: =AF80-AF78 | AG79: =AG80-AG78 | AH79: =AH80-AH78 | AI79: =AI80-AI78 | AJ79: =SUM(AF79,AG79,AH79,AI79) | AK79: =AK80-AK78 | AL79: =AL80-AL78 | AM79: =AM80-AM78 | AN79: =AN80-AN78 | AO79: =SUM(AK79,AL79,AM79,AN79) | AP79: =AP80-AP78 | AQ79: =AQ80-AQ78 | AR79: =AR80-AR78 | AS79: =AS80-AS78 | AT79: =SUM(AP79,AQ79,AR79,AS79) | AU79: =AU80-AU78 | AV79: =AV80-AV78 | AW79: =AW80-AW78 | AX79: =AX80-AX78 | AY79: =SUM(AU79,AV79,AW79,AX79) | AZ79: =AZ80-AZ78 | BA79: =BA80-BA78 | BB79: =BB80-BB78 | BC79: =BC80-BC78 | BD79: =SUM(AZ79,BA79,BB79,BC79) | BE79: =BE80-BE78 | BF79: =BF80-BF78 | BG79: =BG80-BG78 | BH79: =BH80-BH78 | BI79: =SUM(BE79,BF79,BG79,BH79) | BJ79: =BJ80-BJ78 | BK79: =BK80-BK78 | BL79: =BL80-BL78 | BM79: =BM80-BM78 | BN79: =SUM(BJ79,BK79,BL79,BM79) | BO79: =BO80-BO78 | BP79: =BP80-BP78 | BQ79: =BQ80-BQ78 | BR79: =BR80-BR78 | BS79: =SUM(BO79,BP79,BQ79,BR79) | BT79: =BT80-BT78 | BU79: =BU81*BU78 | BV79: =BV81*BV78 | BW79: =BW81*BW78 | BX79: =SUM(BT79,BU79,BV79,BW79) | BY79: =BY81*BY78 | BZ79: =BZ81*BZ78 | CA79: =CA81*CA78 | CB79: =CB81*CB78 | CC79: =SUM(BY79,BZ79,CA79,CB79) | CD79: =CD82*CD78 | CE79: =CE82*CE78 | CF79: =CF82*CF78
A80: EoP EMEA Paid Streaming Memberships, 000s | AA80: 19699 | AB80: 21152 | AC80: 23135 | AD80: 26004 | AE80: =SUM(AE78:AE79) | AF80: 29339 | AG80: 31317 | AH80: 33836 | AI80: 37818 | AJ80: =SUM(AJ78:AJ79) | AK80: 42542 | AL80: 44229 | AM80: 47355 | AN80: 51778 | AO80: =SUM(AO78:AO79) | AP80: 58734 | AQ80: 61483 | AR80: 62242 | AS80: 66698 | AT80: =SUM(AT78:AT79) | AU80: 68508 | AV80: 68696 | AW80: 70500 | AX80: 74036 | AY80: =SUM(AY78:AY79) | AZ80: 73733 | BA80: 72966 | BB80: 73534 | BC80: 76729 | BD80: =SUM(BD78:BD79) | BE80: 77373 | BF80: 79807 | BG80: 83760 | BH80: 88813 | BI80: =SUM(BI78:BI79) | BJ80: 91729 | BK80: 93964 | BL80: 96131 | BM80: 101133 | BN80: =SUM(BN78:BN79) | BO80: 100000 | BP80: 102000 | BQ80: 105000 | BR80: 108000 | BS80: =SUM(BS78:BS79) | BT80: 109000 | BU80: =SUM(BU78:BU79) | BV80: =SUM(BV78:BV79) | BW80: =SUM(BW78:BW79) | BX80: =SUM(BX78:BX79) | BY80: =SUM(BY78:BY79) | BZ80: =SUM(BZ78:BZ79) | CA80: =SUM(CA78:CA79) | CB80: =SUM(CB78:CB79) | ... CF80: =SUM(CF78:CF79)
A81: Q/Q EMEA EOP paid streaming memberships growth, % | AB81: =AB80/AA80-1 | AC81: =AC80/AB80-1 | AD81: =AD80/AC80-1 | AF81: =AF80/AD80-1 | AG81: =AG80/AF80-1 | AH81: =AH80/AG80-1 | AI81: =AI80/AH80-1 | AK81: =AK80/AI80-1 | AL81: =AL80/AK80-1 | AM81: =AM80/AL80-1 | AN81: =AN80/AM80-1 | AP81: =AP80/AN80-1 | AQ81: =AQ80/AP80-1 | AR81: =AR80/AQ80-1 | AS81: =AS80/AR80-1 | AU81: =AU80/AS80-1 | AV81: =AV80/AU80-1 | AW81: =AW80/AV80-1 | AX81: =AX80/AW80-1 | AZ81: =AZ80/AX80-1 | BA81: =BA80/AZ80-1 | BB81: =BB80/BA80-1 | BC81: =BC80/BB80-1 | BE81: =BE80/BC80-1 | BF81: =BF80/BE80-1 | BG81: =BG80/BF80-1 | BH81: =BH80/BG80-1 | BJ81: =BJ80/BH80-1 | BK81: =BK80/BJ80-1 | BL81: =BL80/BK80-1 | BM81: =BM80/BL80-1 | BO81: =BO80/BM80-1 | BP81: =BP80/BO80-1 | BQ81: =BQ80/BP80-1 | BR81: =BR80/BQ80-1 | BT81: =BT80/BR80-1 | BU81: 0.02 | BV81: 0.03 | BW81: 0.02 | BY81: 0.02 | BZ81: 0.01 | CA81: 0.02 | CB81: 0.005
A82: Y/Y EMEA EOP paid streaming membership growth, % | AF82: =+AF80/AA80-1 | AG82: =+AG80/AB80-1 | AH82: =+AH80/AC80-1 | AI82: =+AI80/AD80-1 | AJ82: =+AJ80/AE80-1 | AK82: =+AK80/AF80-1 | AL82: =+AL80/AG80-1 | AM82: =+AM80/AH80-1 | ... CC82: =+CC80/BX80-1 | CD82: 0.035 | CE82: 0.02 | CF82: 0.035
A84: EMEA Average Paying Memberships, 000s | AA84: 18765 | AB84: =AVERAGE(AB80,AB78) | AC84: =AVERAGE(AC80,AC78) | AD84: =AVERAGE(AD80,AD78) | AE84: =AVERAGE(AA84,AB84,AC84,AD84) | AF84: =AVERAGE(AF80,AF78) | AG84: =AVERAGE(AG80,AG78) | AH84: =AVERAGE(AH80,AH78) | AI84: =AVERAGE(AI80,AI78) | AJ84: =AVERAGE(AF84,AG84,AH84,AI84) | AK84: =AVERAGE(AK80,AK78) | AL84: =AVERAGE(AL80,AL78) | AM84: =AVERAGE(AM80,AM78) | AN84: =AVERAGE(AN80,AN78) | AO84: =AVERAGE(AK84,AL84,AM84,AN84) | AP84: =AVERAGE(AP80,AP78) | AQ84: =AVERAGE(AQ80,AQ78) | AR84: =AVERAGE(AR80,AR78) | AS84: =AVERAGE(AS80,AS78) | AT84: =AVERAGE(AP84,AQ84,AR84,AS84) | AU84: =AVERAGE(AU80,AU78) | AV84: =AVERAGE(AV80,AV78) | AW84: =AVERAGE(AW80,AW78) | AX84: =AVERAGE(AX80,AX78) | AY84: =AVERAGE(AU84,AV84,AW84,AX84) | AZ84: =AVERAGE(AZ80,AZ78) | BA84: =AVERAGE(BA80,BA78) | BB84: =AVERAGE(BB80,BB78) | BC84: =AVERAGE(BC80,BC78) | BD84: =AVERAGE(AZ84,BA84,BB84,BC84) | BE84: =AVERAGE(BE80,BE78) | BF84: =AVERAGE(BF80,BF78) | BG84: =AVERAGE(BG80,BG78) | BH84: =AVERAGE(BH80,BH78) | BI84: =AVERAGE(BE84,BF84,BG84,BH84) | BJ84: =AVERAGE(BJ80,BJ78) | BK84: =AVERAGE(BK80,BK78) | BL84: =AVERAGE(BL80,BL78) | BM84: =AVERAGE(BM80,BM78) | BN84: =AVERAGE(BJ84,BK84,BL84,BM84) | BO84: =AVERAGE(BO80,BO78) | BP84: =AVERAGE(BP80,BP78) | BQ84: =AVERAGE(BQ80,BQ78) | BR84: =AVERAGE(BR80,BR78) | BS84: =AVERAGE(BO84,BP84,BQ84,BR84) | BT84: =AVERAGE(BT80,BT78) | BU84: =AVERAGE(BU80,BU78) | BV84: =AVERAGE(BV80,BV78) | BW84: =AVERAGE(BW80,BW78) | BX84: =AVERAGE(BT84,BU84,BV84,BW84) | BY84: =AVERAGE(BY80,BY78) | BZ84: =AVERAGE(BZ80,BZ78) | CA84: =AVERAGE(CA80,CA78) | CB84: =AVERAGE(CB80,CB78) | CC84: =AVERAGE(BY84,BZ84,CA84,CB84) | CD84: =AVERAGE(CD80,CD78) | CE84: =AVERAGE(CE80,CE78) | CF84: =AVERAGE(CF80,CF78)
A85: Q/Q EMEA average paying memberships growth, % | AB85: =AB84/AA84-1 | AC85: =AC84/AB84-1 | AD85: =AD84/AC84-1 | AF85: =AF84/AD84-1 | AG85: =AG84/AF84-1 | AH85: =AH84/AG84-1 | AI85: =AI84/AH84-1 | AK85: =AK84/AI84-1 | AL85: =AL84/AK84-1 | AM85: =AM84/AL84-1 | AN85: =AN84/AM84-1 | AP85: =AP84/AN84-1 | AQ85: =AQ84/AP84-1 | AR85: =AR84/AQ84-1 | AS85: =AS84/AR84-1 | AU85: =AU84/AS84-1 | AV85: =AV84/AU84-1 | AW85: =AW84/AV84-1 | AX85: =AX84/AW84-1 | AZ85: =AZ84/AX84-1 | BA85: =BA84/AZ84-1 | BB85: =BB84/BA84-1 | BC85: =BC84/BB84-1 | BE85: =BE84/BC84-1 | BF85: =BF84/BE84-1 | BG85: =BG84/BF84-1 | BH85: =BH84/BG84-1 | BJ85: =BJ84/BH84-1 | BK85: =BK84/BJ84-1 | BL85: =BL84/BK84-1 | BM85: =BM84/BL84-1 | BO85: =BO84/BM84-1 | BP85: =BP84/BO84-1 | BQ85: =BQ84/BP84-1 | BR85: =BR84/BQ84-1 | BT85: =BT84/BR84-1 | BU85: =BU84/BT84-1 | BV85: =BV84/BU84-1 | BW85: =BW84/BV84-1 | BY85: =BY84/BW84-1 | BZ85: =BZ84/BY84-1 | CA85: =CA84/BZ84-1 | CB85: =CB84/CA84-1
A86: Y/Y EMEA average paying memberships growth, % | AF86: =AF84/AA84-1 | AG86: =AG84/AB84-1 | AH86: =AH84/AC84-1 | AI86: =AI84/AD84-1 | AJ86: =AJ84/AE84-1 | AK86: =AK84/AF84-1 | AL86: =AL84/AG84-1 | AM86: =AM84/AH84-1 | ... CC86: =CC84/BX84-1 | CD86: =CD84/CC84-1 | CE86: =CE84/CD84-1 | CF86: =CF84/CE84-1
A88: EMEA Streaming ARPU, $/member | AA88: 8.57 | AB88: 8.7 | AC88: 9.25 | AD88: 9.94 | AE88: 9.17 | AF88: 10.68 | AG88: 10.72 | AH88: 10.28 | AI88: 10.2 | AJ88: 10.45 | AK88: 10.23 | AL88: 10.13 | AM88: 10.4 | AN88: 10.51 | AO88: 10.33 | AP88: 10.4 | AQ88: 10.5 | AR88: 10.88 | AS88: 11.05 | AT88: 10.72 | AU88: 11.56 | AV88: 11.66 | AW88: 11.65 | AX88: 11.64 | AY88: 11.63 | AZ88: 11.56 | BA88: 11.17 | BB88: 10.81 | BC88: 10.43 | BD88: 10.99 | BE88: 10.89 | BF88: 10.87 | BG88: 10.98 | BH88: 10.75 | BI88: 10.87 | BJ88: 10.92 | BK88: 10.8 | BL88: 10.99 | BM88: 11.11 | BN88: 10.96 | BO88: =BO93/BO84*1000/3 | BP88: =BP93/BP84*1000/3 | BQ88: =BQ93/BQ84*1000/3 | BR88: =BR93/BR84*1000/3 | BS88: =BS93/BS84*1000/12 | BT88: =BT93/BT80*1000/3 | BU88: =BT88*(1+BU89) | BV88: =BU88*(1+BV89) | BW88: =BV88*(1+BW89) | BX88: =AVERAGE(BT88,BU88,BV88,BW88) | BY88: =BW88*(1+BY89) | BZ88: =BY88*(1+BZ89) | CA88: =BZ88*(1+CA89) | CB88: =CA88*(1+CB89) | CC88: =AVERAGE(BY88,BZ88,CA88,CB88) | CD88: =+CC88*(1+CD91) | CE88: =+CD88*(1+CE91) | CF88: =+CE88*(1+CF91)
A89: Q/Q EMEA streaming ARPU growth, % | AB89: =AB88/AA88-1 | AC89: =AC88/AB88-1 | AD89: =AD88/AC88-1 | AF89: =AF88/AD88-1 | AG89: =AG88/AF88-1 | AH89: =AH88/AG88-1 | AI89: =AI88/AH88-1 | AK89: =AK88/AI88-1 | AL89: =AL88/AK88-1 | AM89: =AM88/AL88-1 | AN89: =AN88/AM88-1 | AP89: =AP88/AN88-1 | AQ89: =AQ88/AP88-1 | AR89: =AR88/AQ88-1 | AS89: =AS88/AR88-1 | AU89: =AU88/AS88-1 | AV89: =AV88/AU88-1 | AW89: =AW88/AV88-1 | AX89: =AX88/AW88-1 | AZ89: =AZ88/AX88-1 | BA89: =BA88/AZ88-1 | BB89: =BB88/BA88-1 | BC89: =BC88/BB88-1 | BE89: =BE88/BC88-1 | BF89: =BF88/BE88-1 | BG89: =BG88/BF88-1 | BH89: =BH88/BG88-1 | BJ89: =BJ88/BH88-1 | BK89: =BK88/BJ88-1 | BL89: =BL88/BK88-1 | BM89: =BM88/BL88-1 | BO89: =BO88/BM88-1 | BP89: =BP88/BO88-1 | BQ89: =BQ88/BP88-1 | BR89: =BR88/BQ88-1 | BT89: =BT88/BR88-1 | BU89: 0.01 | BV89: 0.0175 | BW89: 0.015 | BY89: 0.036 | BZ89: -0.006 | CA89: 0.0175 | CB89: -0.02
A90: Y/Y EMEA streaming constant currency ARPU growth, % | AA90: 0.11 | AB90: 0.08 | AC90: 0.05 | AD90: 0.09 | AE90: 0.08 | AF90: 0.11 | AG90: 0.11 | AH90: 0.1 | AI90: 0.06 | AJ90: 0.09 | AK90: 0.02 | AL90: 0.03 | AM90: 0.06 | AN90: 0.07 | AO90: 0.04 | AP90: 0.04 | AQ90: 0.08 | AR90: 0.03 | AS90: 0 | AT90: 0.03 | AU90: 0.04 | AV90: 0.02 | AW90: 0.03 | AX90: 0.06 | AY90: 0.04 | AZ90: 0.06 | BA90: 0.06 | BB90: 0.07 | BC90: 0.05 | BD90: 0.06 | BE90: 0.01 | BF90: -0.01 | BG90: -0.02 | BH90: -0.01 | BI90: -0.01 | BJ90: 0 | BK90: 0.01 | BL90: 0.01 | BM90: 0.01 | BN90: 0.01
A91: Y/Y EMEA streaming ARPU growth, % | AF91: =+AF88/AA88-1 | AG91: =+AG88/AB88-1 | AH91: =+AH88/AC88-1 | AI91: =+AI88/AD88-1 | AJ91: =+AJ88/AE88-1 | AK91: =+AK88/AF88-1 | AL91: =+AL88/AG88-1 | AM91: =+AM88/AH88-1 | ... CC91: =+CC88/BX88-1 | CD91: 0.055 | CE91: 0.02 | CF91: 0.055
A93: EMEA Streaming Revenue, mm | AA93: 482.282 | AB93: 533.098 | AC93: 614.707 | AD93: 732.726 | AE93: 2362.813 | AF93: 886.649 | AG93: 975.497 | AH93: 1004.749 | AI93: 1096.812 | AJ93: 3963.707 | AK93: 1233.379 | AL93: 1319.087 | AM93: 1428.04 | AN93: 1562.561 | AO93: 5543.067 | AP93: 1723.474 | AQ93: 1892.537 | AR93: 2019.083 | AS93: =AT93-SUM(AP93,AQ93,AR93) | AT93: 7772.252 | AU93: 2343.674 | AV93: 2400.48 | AW93: 2432.239 | AX93: =AY93-SUM(AU93,AV93,AW93) | AY93: 9699.819 | AZ93: 2561.831 | BA93: 2457.235 | BB93: 2375.814 | BC93: =BD93-SUM(AZ93,BA93,BB93) | BD93: 9745.015 | BE93: 2517.641 | BF93: 2562.17 | BG93: 2693.146 | BH93: =BI93-SUM(BE93,BF93,BG93) | BI93: 10556.487 | BJ93: 2958.193 | BK93: 3007.772 | BL93: 3133.466 | BM93: =BN93-SUM(BJ93,BK93,BL93) | BN93: 12387.035 | BO93: 3404.676 | BP93: 3538.175 | BQ93: 3699.052 | BR93: =BS93-SUM(BO93,BP93,BQ93) | BS93: 14514.646 | BT93: 3998.419 | BU93: =BU84*BU88*3/1000 | BV93: =BV84*BV88*3/1000 | BW93: =BW84*BW88*3/1000 | BX93: =SUM(BT93,BU93,BV93,BW93) | BY93: =BY84*BY88*3/1000 | BZ93: =BZ84*BZ88*3/1000 | CA93: =CA84*CA88*3/1000 | CB93: =CB84*CB88*3/1000 | CC93: =SUM(BY93,BZ93,CA93,CB93) | CD93: =CD84*CD88*12/1000 | CE93: =CE84*CE88*12/1000 | CF93: =CF84*CF88*12/1000
A94: Q/Q EMEA streaming revenue growth, % | AB94: =AB93/AA93-1 | AC94: =AC93/AB93-1 | AD94: =AD93/AC93-1 | AF94: =AF93/AD93-1 | AG94: =AG93/AF93-1 | AH94: =AH93/AG93-1 | AI94: =AI93/AH93-1 | AK94: =AK93/AI93-1 | AL94: =AL93/AK93-1 | AM94: =AM93/AL93-1 | AN94: =AN93/AM93-1 | AP94: =AP93/AN93-1 | AQ94: =AQ93/AP93-1 | AR94: =AR93/AQ93-1 | AS94: =AS93/AR93-1 | AU94: =AU93/AS93-1 | AV94: =AV93/AU93-1 | AW94: =AW93/AV93-1 | AX94: =AX93/AW93-1 | AZ94: =AZ93/AX93-1 | BA94: =BA93/AZ93-1 | BB94: =BB93/BA93-1 | BC94: =BC93/BB93-1 | BE94: =BE93/BC93-1 | BF94: =BF93/BE93-1 | BG94: =BG93/BF93-1 | BH94: =BH93/BG93-1 | BJ94: =BJ93/BH93-1 | BK94: =BK93/BJ93-1 | BL94: =BL93/BK93-1 | BM94: =BM93/BL93-1 | BO94: =BO93/BM93-1 | BP94: =BP93/BO93-1 | BQ94: =BQ93/BP93-1 | BR94: =BR93/BQ93-1 | BT94: =BT93/BR93-1 | BU94: =BU93/BT93-1 | BV94: =BV93/BU93-1 | BW94: =BW93/BV93-1 | BY94: =BY93/BW93-1 | BZ94: =BZ93/BY93-1 | CA94: =CA93/BZ93-1 | CB94: =CB93/CA93-1
A95: Y/Y EMEA streaming revenue growth, % | AF95: =+AF93/AA93-1 | AG95: =+AG93/AB93-1 | AH95: =+AH93/AC93-1 | AI95: =+AI93/AD93-1 | AJ95: =+AJ93/AE93-1 | AK95: =+AK93/AF93-1 | AL95: =+AL93/AG93-1 | AM95: =+AM93/AH93-1 | ... CC95: =+CC93/BX93-1 | CD95: =+CD93/CC93-1 | CE95: =+CE93/CD93-1 | CF95: =+CF93/CE93-1
A97: Segmented Results - Latin America Streaming (FS)
A98: BoP Latin America Paid Streaming Memberships, 000s | AA98: =AA104*2-AA100 | AB98: =AA100 | AC98: =AB100 | AD98: =AC100 | AE98: =AA98 | AF98: =AE100 | AG98: =AF100 | AH98: =AG100 | AI98: =AH100 | AJ98: =AE100 | AK98: =AJ100 | AL98: =AK100 | AM98: =AL100 | AN98: =AM100 | AO98: =AJ100 | AP98: =AO100 | AQ98: =AP100 | AR98: =AQ100 | AS98: =AR100 | AT98: =AO100 | AU98: =AT100 | AV98: =AU100 | AW98: =AV100 | AX98: =AW100 | AY98: =AT100 | AZ98: =AY100 | BA98: =AZ100 | BB98: =BA100 | BC98: =BB100 | BD98: =AY100 | BE98: =BD100 | BF98: =BE100 | BG98: =BF100 | BH98: =BG100 | BI98: =BD100 | BJ98: =BI100 | BK98: =BJ100 | BL98: =BK100 | BM98: =BL100 | BN98: =BI100 | BO98: =BN100 | BP98: =BO100 | BQ98: =BP100 | BR98: =BQ100 | BS98: =BN100 | BT98: =BS100 | BU98: =BT100 | BV98: =BU100 | BW98: =BV100 | BX98: =BS100 | BY98: =BX100 | BZ98: =BY100 | CA98: =BZ100 | CB98: =CA100 | CC98: =BX100 | CD98: =CC100 | CE98: =CD100 | CF98: =CE100
A99: Latin America Paid Streaming Memberships Net Additions, 000s | AA99: =AA100-AA98 | AB99: =AB100-AB98 | AC99: =AC100-AC98 | AD99: =AD100-AD98 | AE99: =SUM(AA99,AB99,AC99,AD99) | AF99: =AF100-AF98 | AG99: =AG100-AG98 | AH99: =AH100-AH98 | AI99: =AI100-AI98 | AJ99: =SUM(AF99,AG99,AH99,AI99) | AK99: =AK100-AK98 | AL99: =AL100-AL98 | AM99: =AM100-AM98 | AN99: =AN100-AN98 | AO99: =SUM(AK99,AL99,AM99,AN99) | AP99: =AP100-AP98 | AQ99: =AQ100-AQ98 | AR99: =AR100-AR98 | AS99: =AS100-AS98 | AT99: =SUM(AP99,AQ99,AR99,AS99) | AU99: =AU100-AU98 | AV99: =AV100-AV98 | AW99: =AW100-AW98 | AX99: =AX100-AX98 | AY99: =SUM(AU99,AV99,AW99,AX99) | AZ99: =AZ100-AZ98 | BA99: =BA100-BA98 | BB99: =BB100-BB98 | BC99: =BC100-BC98 | BD99: =SUM(AZ99,BA99,BB99,BC99) | BE99: =BE100-BE98 | BF99: =BF100-BF98 | BG99: =BG100-BG98 | BH99: =BH100-BH98 | BI99: =SUM(BE99,BF99,BG99,BH99) | BJ99: =BJ100-BJ98 | BK99: =BK100-BK98 | BL99: =BL100-BL98 | BM99: =BM100-BM98 | BN99: =SUM(BJ99,BK99,BL99,BM99) | BO99: =BO100-BO98 | BP99: =BP100-BP98 | BQ99: =BQ100-BQ98 | BR99: =BR100-BR98 | BS99: =SUM(BO99,BP99,BQ99,BR99) | BT99: =BT100-BT98 | BU99: =BU101*BU98 | BV99: =BV101*BV98 | BW99: =BW101*BW98 | BX99: =SUM(BT99,BU99,BV99,BW99) | BY99: =BY101*BY98 | BZ99: =BZ101*BZ98 | CA99: =CA101*CA98 | CB99: =CB101*CB98 | CC99: =SUM(BY99,BZ99,CA99,CB99) | CD99: =CD102*CD98 | CE99: =CE102*CE98 | CF99: =CF102*CF98
A100: EoP Latin America Paid Streaming Memberships, 000s | AA100: 15425 | AB100: 17013 | AC100: 18267 | AD100: 19717 | AE100: =SUM(AE98:AE99) | AF100: 21260 | AG100: 22795 | AH100: 24115 | AI100: 26077 | AJ100: =SUM(AJ98:AJ99) | AK100: 27547 | AL100: 27890 | AM100: 29380 | AN100: 31417 | AO100: =SUM(AO98:AO99) | AP100: 34318 | AQ100: 36068 | AR100: 36324 | AS100: 37537 | AT100: =SUM(AT98:AT99) | AU100: 37894 | AV100: 38658 | AW100: 38988 | AX100: 39961 | AY100: =SUM(AY98:AY99) | AZ100: 39610 | BA100: 39624 | BB100: 39936 | BC100: 41699 | BD100: =SUM(BD98:BD99) | BE100: 41249 | BF100: 42466 | BG100: 43645 | BH100: 45997 | BI100: =SUM(BI98:BI99) | BJ100: 47720 | BK100: 49250 | BL100: 49182 | BM100: 53327 | BN100: =SUM(BN98:BN99) | BO100: 52000 | BP100: 53000 | BQ100: 55000 | BR100: 57000 | BS100: =SUM(BS98:BS99) | BT100: 58000 | BU100: =SUM(BU98:BU99) | BV100: =SUM(BV98:BV99) | BW100: =SUM(BW98:BW99) | BX100: =SUM(BX98:BX99) | BY100: =SUM(BY98:BY99) | BZ100: =SUM(BZ98:BZ99) | CA100: =SUM(CA98:CA99) | CB100: =SUM(CB98:CB99) | ... CF100: =SUM(CF98:CF99)
A101: Q/Q Latin America EOP paid streaming memberships growth, % | AB101: =AB100/AA100-1 | AC101: =AC100/AB100-1 | AD101: =AD100/AC100-1 | AF101: =AF100/AD100-1 | AG101: =AG100/AF100-1 | AH101: =AH100/AG100-1 | AI101: =AI100/AH100-1 | AK101: =AK100/AI100-1 | AL101: =AL100/AK100-1 | AM101: =AM100/AL100-1 | AN101: =AN100/AM100-1 | AP101: =AP100/AN100-1 | AQ101: =AQ100/AP100-1 | AR101: =AR100/AQ100-1 | AS101: =AS100/AR100-1 | AU101: =AU100/AS100-1 | AV101: =AV100/AU100-1 | AW101: =AW100/AV100-1 | AX101: =AX100/AW100-1 | AZ101: =AZ100/AX100-1 | BA101: =BA100/AZ100-1 | BB101: =BB100/BA100-1 | BC101: =BC100/BB100-1 | BE101: =BE100/BC100-1 | BF101: =BF100/BE100-1 | BG101: =BG100/BF100-1 | BH101: =BH100/BG100-1 | BJ101: =BJ100/BH100-1 | BK101: =BK100/BJ100-1 | BL101: =BL100/BK100-1 | BM101: =BM100/BL100-1 | BO101: =BO100/BM100-1 | BP101: =BP100/BO100-1 | BQ101: =BQ100/BP100-1 | BR101: =BR100/BQ100-1 | BT101: =BT100/BR100-1 | BU101: 0.01 | BV101: 0.004 | BW101: 0.01 | BY101: 0.05 | BZ101: 0.004 | CA101: 0.004 | CB101: -0.02
A102: Y/Y Latin America EOP paid streaming membership growth, % | AF102: =+AF100/AA100-1 | AG102: =+AG100/AB100-1 | AH102: =+AH100/AC100-1 | AI102: =+AI100/AD100-1 | AJ102: =+AJ100/AE100-1 | AK102: =+AK100/AF100-1 | AL102: =+AL100/AG100-1 | AM102: =+AM100/AH100-1 | ... CC102: =+CC100/BX100-1 | CD102: 0.04 | CE102: 0.04 | CF102: 0.04
A104: Latin America Average Paying Memberships, 000s | AA104: 14817 | AB104: =AVERAGE(AB100,AB98) | AC104: =AVERAGE(AC100,AC98) | AD104: =AVERAGE(AD100,AD98) | AE104: =AVERAGE(AA104,AB104,AC104,AD104) | AF104: =AVERAGE(AF100,AF98) | AG104: =AVERAGE(AG100,AG98) | AH104: =AVERAGE(AH100,AH98) | AI104: =AVERAGE(AI100,AI98) | AJ104: =AVERAGE(AF104,AG104,AH104,AI104) | AK104: =AVERAGE(AK100,AK98) | AL104: =AVERAGE(AL100,AL98) | AM104: =AVERAGE(AM100,AM98) | AN104: =AVERAGE(AN100,AN98) | AO104: =AVERAGE(AK104,AL104,AM104,AN104) | AP104: =AVERAGE(AP100,AP98) | AQ104: =AVERAGE(AQ100,AQ98) | AR104: =AVERAGE(AR100,AR98) | AS104: =AVERAGE(AS100,AS98) | AT104: =AVERAGE(AP104,AQ104,AR104,AS104) | AU104: =AVERAGE(AU100,AU98) | AV104: =AVERAGE(AV100,AV98) | AW104: =AVERAGE(AW100,AW98) | AX104: =AVERAGE(AX100,AX98) | AY104: =AVERAGE(AU104,AV104,AW104,AX104) | AZ104: =AVERAGE(AZ100,AZ98) | BA104: =AVERAGE(BA100,BA98) | BB104: =AVERAGE(BB100,BB98) | BC104: =AVERAGE(BC100,BC98) | BD104: =AVERAGE(AZ104,BA104,BB104,BC104) | BE104: =AVERAGE(BE100,BE98) | BF104: =AVERAGE(BF100,BF98) | BG104: =AVERAGE(BG100,BG98) | BH104: =AVERAGE(BH100,BH98) | BI104: =AVERAGE(BE104,BF104,BG104,BH104) | BJ104: =AVERAGE(BJ100,BJ98) | BK104: =AVERAGE(BK100,BK98) | BL104: =AVERAGE(BL100,BL98) | BM104: =AVERAGE(BM100,BM98) | BN104: =AVERAGE(BJ104,BK104,BL104,BM104) | BO104: =AVERAGE(BO100,BO98) | BP104: =AVERAGE(BP100,BP98) | BQ104: =AVERAGE(BQ100,BQ98) | BR104: =AVERAGE(BR100,BR98) | BS104: =AVERAGE(BO104,BP104,BQ104,BR104) | BT104: =AVERAGE(BT100,BT98) | BU104: =AVERAGE(BU100,BU98) | BV104: =AVERAGE(BV100,BV98) | BW104: =AVERAGE(BW100,BW98) | BX104: =AVERAGE(BT104,BU104,BV104,BW104) | BY104: =AVERAGE(BY100,BY98) | BZ104: =AVERAGE(BZ100,BZ98) | CA104: =AVERAGE(CA100,CA98) | CB104: =AVERAGE(CB100,CB98) | CC104: =AVERAGE(BY104,BZ104,CA104,CB104) | CD104: =AVERAGE(CD100,CD98) | CE104: =AVERAGE(CE100,CE98) | CF104: =AVERAGE(CF100,CF98)
A105: Q/Q Latin America average paying memberships growth, % | AB105: =AB104/AA104-1 | AC105: =AC104/AB104-1 | AD105: =AD104/AC104-1 | AF105: =AF104/AD104-1 | AG105: =AG104/AF104-1 | AH105: =AH104/AG104-1 | AI105: =AI104/AH104-1 | AK105: =AK104/AI104-1 | AL105: =AL104/AK104-1 | AM105: =AM104/AL104-1 | AN105: =AN104/AM104-1 | AP105: =AP104/AN104-1 | AQ105: =AQ104/AP104-1 | AR105: =AR104/AQ104-1 | AS105: =AS104/AR104-1 | AU105: =AU104/AS104-1 | AV105: =AV104/AU104-1 | AW105: =AW104/AV104-1 | AX105: =AX104/AW104-1 | AZ105: =AZ104/AX104-1 | BA105: =BA104/AZ104-1 | BB105: =BB104/BA104-1 | BC105: =BC104/BB104-1 | BE105: =BE104/BC104-1 | BF105: =BF104/BE104-1 | BG105: =BG104/BF104-1 | BH105: =BH104/BG104-1 | BJ105: =BJ104/BH104-1 | BK105: =BK104/BJ104-1 | BL105: =BL104/BK104-1 | BM105: =BM104/BL104-1 | BO105: =BO104/BM104-1 | BP105: =BP104/BO104-1 | BQ105: =BQ104/BP104-1 | BR105: =BR104/BQ104-1 | BT105: =BT104/BR104-1 | BU105: =BU104/BT104-1 | BV105: =BV104/BU104-1 | BW105: =BW104/BV104-1 | BY105: =BY104/BW104-1 | BZ105: =BZ104/BY104-1 | CA105: =CA104/BZ104-1 | CB105: =CB104/CA104-1
A106: Y/Y Latin America average paying memberships growth, % | AF106: =AF104/AA104-1 | AG106: =AG104/AB104-1 | AH106: =AH104/AC104-1 | AI106: =AI104/AD104-1 | AJ106: =AJ104/AE104-1 | AK106: =AK104/AF104-1 | AL106: =AL104/AG104-1 | AM106: =AM104/AH104-1 | ... CC106: =CC104/BX104-1 | CD106: =CD104/CC104-1 | CE106: =CE104/CD104-1 | CF106: =CF104/CE104-1
A108: Latin America Streaming ARPU, $/member | AA108: 7.46 | AB108: 7.84 | AC108: 8.21 | AD108: 8.69 | AE108: 8.09 | AF108: 8.79 | AG108: 8.6 | AH108: 7.99 | AI108: 7.53 | AJ108: 8.19 | AK108: 7.84 | AL108: 8.14 | AM108: 8.63 | AN108: 8.18 | AO108: 8.21 | AP108: 8.05 | AQ108: 7.44 | AR108: 7.27 | AS108: 7.12 | AT108: 7.45 | AU108: 7.39 | AV108: 7.5 | AW108: 7.86 | AX108: 8.14 | AY108: 7.73 | AZ108: 8.37 | BA108: 8.67 | BB108: 8.58 | BC108: 8.3 | BD108: 8.48 | BE108: 8.6 | BF108: 8.58 | BG108: 8.85 | BH108: 8.6 | BI108: 8.66 | BJ108: 8.29 | BK108: 8.28 | BL108: 8.4 | BM108: 8 | BN108: 8.24 | BO108: =BO113/BO104*1000/3 | BP108: =BP113/BP104*1000/3 | BQ108: =BQ113/BQ104*1000/3 | BR108: =BR113/BR104*1000/3 | BS108: =BS113/BS104*1000/12 | BT108: =BT113/BT100*1000/3 | BU108: =BT108*(1+BU109) | BV108: =BU108*(1+BV109) | BW108: =BV108*(1+BW109) | BX108: =AVERAGE(BT108,BU108,BV108,BW108) | BY108: =BW108*(1+BY109) | BZ108: =BY108*(1+BZ109) | CA108: =BZ108*(1+CA109) | CB108: =CA108*(1+CB109) | CC108: =AVERAGE(BY108,BZ108,CA108,CB108) | CD108: =+CC108*(1+CD111) | CE108: =+CD108*(1+CE111) | CF108: =+CE108*(1+CF111)
A109: Q/Q Latin America streaming ARPU growth, % | AB109: =AB108/AA108-1 | AC109: =AC108/AB108-1 | AD109: =AD108/AC108-1 | AF109: =AF108/AD108-1 | AG109: =AG108/AF108-1 | AH109: =AH108/AG108-1 | AI109: =AI108/AH108-1 | AK109: =AK108/AI108-1 | AL109: =AL108/AK108-1 | AM109: =AM108/AL108-1 | AN109: =AN108/AM108-1 | AP109: =AP108/AN108-1 | AQ109: =AQ108/AP108-1 | AR109: =AR108/AQ108-1 | AS109: =AS108/AR108-1 | AU109: =AU108/AS108-1 | AV109: =AV108/AU108-1 | AW109: =AW108/AV108-1 | AX109: =AX108/AW108-1 | AZ109: =AZ108/AX108-1 | BA109: =BA108/AZ108-1 | BB109: =BB108/BA108-1 | BC109: =BC108/BB108-1 | BE109: =BE108/BC108-1 | BF109: =BF108/BE108-1 | BG109: =BG108/BF108-1 | BH109: =BH108/BG108-1 | BJ109: =BJ108/BH108-1 | BK109: =BK108/BJ108-1 | BL109: =BL108/BK108-1 | BM109: =BM108/BL108-1 | BO109: =BO108/BM108-1 | BP109: =BP108/BO108-1 | BQ109: =BQ108/BP108-1 | BR109: =BR108/BQ108-1 | BT109: =BT108/BR108-1 | BU109: 0.01 | BV109: 0.01 | BW109: 0.01 | BY109: 0.05 | BZ109: 0 | CA109: 0.01 | CB109: -0.02
A110: Y/Y Latin America streaming constant currency ARPU growth, % | AA110: 0.15 | AB110: 0.15 | AC110: 0.13 | AD110: 0.17 | AE110: 0.15 | AF110: 0.18 | AG110: 0.18 | AH110: 0.14 | AI110: 0.06 | AJ110: 0.13 | AK110: 0.07 | AL110: 0.12 | AM110: 0.17 | AN110: 0.18 | AO110: 0.13 | AP110: 0.12 | AQ110: 0.13 | AR110: 0.05 | AS110: 0.04 | AT110: 0.08 | AU110: 0.05 | AV110: 0.02 | AW110: 0.08 | AX110: 0.17 | AY110: 0.08 | AZ110: 0.2 | BA110: 0.15 | BB110: 0.16 | BC110: 0.07 | BD110: 0.14 | BE110: 0.08 | BF110: 0.08 | BG110: 0.08 | BH110: 0.16 | BI110: 0.1 | BJ110: 0.16 | BK110: 0.24 | BL110: 0.27 | BM110: 0.18 | BN110: 0.21
A111: Y/Y Latin America streaming ARPU growth, % | AF111: =+AF108/AA108-1 | AG111: =+AG108/AB108-1 | AH111: =+AH108/AC108-1 | AI111: =+AI108/AD108-1 | AJ111: =+AJ108/AE108-1 | AK111: =+AK108/AF108-1 | AL111: =+AL108/AG108-1 | AM111: =+AM108/AH108-1 | ... CC111: =+CC108/BX108-1 | CD111: 0.05 | CE111: 0.05 | CF111: 0.05
A113: Latin America Streaming Revenue, mm | AA113: 331.453 | AB113: 381.459 | AC113: 434.637 | AD113: 495.067 | AE113: 1642.616 | AF113: 540.182 | AG113: 568.071 | AH113: 562.307 | AI113: 567.137 | AJ113: 2237.697 | AK113: 630.472 | AL113: 677.136 | AM113: 741.434 | AN113: 746.392 | AO113: 2795.434 | AP113: 793.453 | AQ113: 785.368 | AR113: 789.384 | AS113: =AT113-SUM(AP113,AQ113,AR113) | AT113: 3156.727 | AU113: 836.647 | AV113: 860.882 | AW113: 915.297 | AX113: =AY113-SUM(AU113,AV113,AW113) | AY113: 3576.976 | AZ113: 998.948 | BA113: 1030.234 | BB113: 1023.945 | BC113: =BD113-SUM(AZ113,BA113,BB113) | BD113: 4069.973 | BE113: 1070.192 | BF113: 1077.435 | BG113: 1142.811 | BH113: =BI113-SUM(BE113,BF113,BG113) | BI113: 4446.461 | BJ113: 1165.008 | BK113: 1204.145 | BL113: 1240.892 | BM113: =BN113-SUM(BJ113,BK113,BL113) | BN113: 4839.816 | BO113: 1261.934 | BP113: 1306.735 | BQ113: 1370.913 | BR113: =BS113-SUM(BO113,BP113,BQ113) | BS113: 5357.521 | BT113: 1497.058 | BU113: =BU104*BU108*3/1000 | BV113: =BV104*BV108*3/1000 | BW113: =BW104*BW108*3/1000 | BX113: =SUM(BT113,BU113,BV113,BW113) | BY113: =BY104*BY108*3/1000 | BZ113: =BZ104*BZ108*3/1000 | CA113: =CA104*CA108*3/1000 | CB113: =CB104*CB108*3/1000 | CC113: =SUM(BY113,BZ113,CA113,CB113) | CD113: =CD104*CD108*12/1000 | CE113: =CE104*CE108*12/1000 | CF113: =CF104*CF108*12/1000
A114: Q/Q Latin America streaming revenue growth, % | AB114: =AB113/AA113-1 | AC114: =AC113/AB113-1 | AD114: =AD113/AC113-1 | AF114: =AF113/AD113-1 | AG114: =AG113/AF113-1 | AH114: =AH113/AG113-1 | AI114: =AI113/AH113-1 | AK114: =AK113/AI113-1 | AL114: =AL113/AK113-1 | AM114: =AM113/AL113-1 | AN114: =AN113/AM113-1 | AP114: =AP113/AN113-1 | AQ114: =AQ113/AP113-1 | AR114: =AR113/AQ113-1 | AS114: =AS113/AR113-1 | AU114: =AU113/AS113-1 | AV114: =AV113/AU113-1 | AW114: =AW113/AV113-1 | AX114: =AX113/AW113-1 | AZ114: =AZ113/AX113-1 | BA114: =BA113/AZ113-1 | BB114: =BB113/BA113-1 | BC114: =BC113/BB113-1 | BE114: =BE113/BC113-1 | BF114: =BF113/BE113-1 | BG114: =BG113/BF113-1 | BH114: =BH113/BG113-1 | BJ114: =BJ113/BH113-1 | BK114: =BK113/BJ113-1 | BL114: =BL113/BK113-1 | BM114: =BM113/BL113-1 | BO114: =BO113/BM113-1 | BP114: =BP113/BO113-1 | BQ114: =BQ113/BP113-1 | BR114: =BR113/BQ113-1 | BT114: =BT113/BR113-1 | BU114: =BU113/BT113-1 | BV114: =BV113/BU113-1 | BW114: =BW113/BV113-1 | BY114: =BY113/BW113-1 | BZ114: =BZ113/BY113-1 | CA114: =CA113/BZ113-1 | CB114: =CB113/CA113-1
A115: Y/Y Latin America streaming revenue growth, % | AF115: =+AF113/AA113-1 | AG115: =+AG113/AB113-1 | AH115: =+AH113/AC113-1 | AI115: =+AI113/AD113-1 | AJ115: =+AJ113/AE113-1 | AK115: =+AK113/AF113-1 | AL115: =+AL113/AG113-1 | AM115: =+AM113/AH113-1 | ... CC115: =+CC113/BX113-1 | CD115: =+CD113/CC113-1 | CE115: =+CE113/CD113-1 | CF115: =+CF113/CE113-1
A117: Segmented Results - Asia Pacific Streaming (FS)
A118: BoP Asia Pacific Paid Streaming Memberships, 000s | AA118: =AA124*2-AA120 | AB118: =AA120 | AC118: =AB120 | AD118: =AC120 | AE118: =AA118 | AF118: =AE120 | AG118: =AF120 | AH118: =AG120 | AI118: =AH120 | AJ118: =AE120 | AK118: =AJ120 | AL118: =AK120 | AM118: =AL120 | AN118: =AM120 | AO118: =AJ120 | AP118: =AO120 | AQ118: =AP120 | AR118: =AQ120 | AS118: =AR120 | AT118: =AO120 | AU118: =AT120 | AV118: =AU120 | AW118: =AV120 | AX118: =AW120 | AY118: =AT120 | AZ118: =AY120 | BA118: =AZ120 | BB118: =BA120 | BC118: =BB120 | BD118: =AY120 | BE118: =BD120 | BF118: =BE120 | BG118: =BF120 | BH118: =BG120 | BI118: =BD120 | BJ118: =BI120 | BK118: =BJ120 | BL118: =BK120 | BM118: =BL120 | BN118: =BI120 | BO118: =BN120 | BP118: =BO120 | BQ118: =BP120 | BR118: =BQ120 | BS118: =BN120 | BT118: =BS120 | BU118: =BT120 | BV118: =BU120 | BW118: =BV120 | BX118: =BS120 | BY118: =BX120 | BZ118: =BY120 | CA118: =BZ120 | CB118: =CA120 | CC118: =BX120 | CD118: =CC120 | CE118: =CD120 | CF118: =CE120
...

Sheet Exec Comp
A1: =MO.CompanyName
A2: =MO.Ticker | C2: =Model!C2 | D2: =Model!D2 | E2: =Model!E2 | F2: =Model!F2 | G2: =Model!G2 | H2: =Model!H2 | I2: =Model!I2 | J2: =Model!J2 | ... CF2: =Model!CF2
A3: =MO.TradingCurrency | B3: =MO.LastPrice | C3: =INDEX(MO_Common_FPDays,0,MATCH(C$5,MO_Common_ColumnHeader,0)) | D3: =INDEX(MO_Common_FPDays,0,MATCH(D$5,MO_Common_ColumnHeader,0)) | E3: =INDEX(MO_Common_FPDays,0,MATCH(E$5,MO_Common_ColumnHeader,0)) | F3: =INDEX(MO_Common_FPDays,0,MATCH(F$5,MO_Common_ColumnHeader,0)) | G3: =INDEX(MO_Common_FPDays,0,MATCH(G$5,MO_Common_ColumnHeader,0)) | H3: =INDEX(MO_Common_FPDays,0,MATCH(H$5,MO_Common_ColumnHeader,0)) | I3: =INDEX(MO_Common_FPDays,0,MATCH(I$5,MO_Common_ColumnHeader,0)) | J3: =INDEX(MO_Common_FPDays,0,MATCH(J$5,MO_Common_ColumnHeader,0)) | ... CF3: =INDEX(MO_Common_FPDays,0,MATCH(CF$5,MO_Common_ColumnHeader,0))
A4: =MO.DataSourceName | B4: =MO.RealTime | C4: =INDEX(MO_Common_QEndDate,0,MATCH(C$5,MO_Common_ColumnHeader,0)) | D4: =INDEX(MO_Common_QEndDate,0,MATCH(D$5,MO_Common_ColumnHeader,0)) | E4: =INDEX(MO_Common_QEndDate,0,MATCH(E$5,MO_Common_ColumnHeader,0)) | F4: =INDEX(MO_Common_QEndDate,0,MATCH(F$5,MO_Common_ColumnHeader,0)) | G4: =INDEX(MO_Common_QEndDate,0,MATCH(G$5,MO_Common_ColumnHeader,0)) | H4: =INDEX(MO_Common_QEndDate,0,MATCH(H$5,MO_Common_ColumnHeader,0)) | I4: =INDEX(MO_Common_QEndDate,0,MATCH(I$5,MO_Common_ColumnHeader,0)) | J4: =INDEX(MO_Common_QEndDate,0,MATCH(J$5,MO_Common_ColumnHeader,0)) | ... CF4: =INDEX(MO_Common_QEndDate,0,MATCH(CF$5,MO_Common_ColumnHeader,0))
A5: =MO.ReportFX | C5: =Model!C5 | D5: =Model!D5 | E5: =Model!E5 | F5: =Model!F5 | G5: =Model!G5 | H5: =Model!H5 | I5: =Model!I5 | J5: =Model!J5 | ... CF5: =Model!CF5
A6: Executive Compensation
A7: Co-CEO - Base Pay, 000s | AT7: 650 | AY7: 650 | BD7: 650 | BI7: 2890.385 | BN7: 3000
A8: Co-CEO - Stock Awards, 000s | BN8: 42707.872
A9: Co-CEO - Option Awards, 000s | AT9: 42428.878 | AY9: 39731.118 | BD9: 49408.182 | BI9: 22667.588 | BN9: 1951.611
A10: Co-CEO - Non-Equity Incentive Plan, 000s | BI10: 13938.549 | BN10: 12000
A11: Co-CEO - All other compensation, 000s | AT11: 147.146 | AY11: 442.607 | BD11: 1015.055 | BI11: 620.602 | BN11: 613.091
A12: Co-CEO - Total Comp, 000s | AT12: =SUM(AT7:AT11) | AY12: =SUM(AY7:AY11) | BD12: =SUM(BD7:BD11) | BI12: =SUM(BI7:BI11) | BN12: =SUM(BN7:BN11)
A13: Co-CEO - comp tied to equity, % | AT13: =SUM(AT9)/AT12 | AY13: =SUM(AY9)/AY12 | BD13: =SUM(BD9)/BD12 | BI13: =SUM(BI9)/BI12 | BN13: =SUM(BN9)/BN12
A14: Market Cap - EoP, mm | AT14: =Model!AT1008 | AU14: =Model!AU1008 | AV14: =Model!AV1008 | AW14: =Model!AW1008 | AX14: =Model!AX1008 | AY14: =Model!AY1008 | AZ14: =Model!AZ1008 | BA14: =Model!BA1008 | ... BT14: =Model!BT1008
A16: Co-CEO - Options 03/01/2022 # of unexercised exercisable options, 000s | AT16: 38.801
A17: Co-CEO - Options 03/01/2022 exercise price, $ | AT17: 16.11
A19: Co-CEO - Options 04/02/2022 # of unexercised exercisable options, 000s | AT19: 38.388
A20: Co-CEO - Options 04/02/2022 exercise price, $ | AT20: 16.28
A22: Co-CEO - Options 05/01/2022 # of unexercised exercisable options, 000s | AT22: 53.774
A23: Co-CEO - Options 05/01/2022 exercise price, $ | AT23: 11.62
A25: Co-CEO - Options 06/01/2022 # of unexercised exercisable options, 000s | AT25: 69.503
A26: Co-CEO - Options 06/01/2022 exercise price, $ | AT26: 8.99
A28: Co-CEO - Options 07/02/2022 # of unexercised exercisable options, 000s | AT28: 64.477
A29: Co-CEO - Options 07/02/2022 exercise price, $ | AT29: 9.69
A31: Co-CEO - Options 08/01/2022 # of unexercised exercisable options, 000s | AT31: 80.276
A32: Co-CEO - Options 08/01/2022 exercise price, $ | AT32: 7.79
... A59: Co-CEO - Options 05/01/2023 exercise price, $ | AT59: 30.42
A61: Co-CEO - Options 06/03/2023 # of unexercised exercisable options, 000s | AT61: 26.278 | AY61: 26.278 | BD61: 26.278
A62: Co-CEO - Options 06/03/2023 exercise price, $ | AT62: 31.71 | AY62: 31.71 | BD62: 31.71
A64: Co-CEO - Options 07/01/2023 # of unexercised exercisable options, 000s | AT64: 26.012 | AY64: 26.012 | BD64: 26.012
A65: Co-CEO - Options 07/01/2023 exercise price, $ | AT65: 32.04 | AY65: 32.04 | BD65: 32.04
A67: Co-CEO - Options 08/01/2023 # of unexercised exercisable options, 000s | AT67: 23.415 | AY67: 23.415 | BD67: 23.415
A68: Co-CEO - Options 08/01/2023 exercise price, $ | AT68: 35.59 | AY68: 35.59 | BD68: 35.59
A70: Co-CEO - Options 09/03/2023 # of unexercised exercisable options, 000s | AT70: 20.188 | AY70: 20.188 | BD70: 20.188
A71: Co-CEO - Options 09/03/2023 exercise price, $ | AT71: 41.29 | AY71: 41.29 | BD71: 41.29
A73: Co-CEO - Options 10/01/2023 # of unexercised exercisable options, 000s | AT73: 17.969 | AY73: 17.969 | BD73: 17.969
A74: Co-CEO - Options 10/01/2023 exercise price, $ | AT74: 46.37 | AY74: 46.37 | BD74: 46.37
A76: Co-CEO - Options 11/01/2023 # of unexercised exercisable options, 000s | AT76: 17.717 | AY76: 17.717 | BD76: 17.717
A77: Co-CEO - Options 11/01/2023 exercise price, $ | AT77: 47.04 | AY77: 47.04 | BD77: 47.04
... A176: Co-CEO - Options 08/01/2026 exercise price, $ | AT176: 94.37 | AY176: 94.37 | BD176: 94.37
A178: Co-CEO - Options 09/01/2026 # of unexercised exercisable options, 000s | AT178: 40.755 | AY178: 40.755 | BD178: 40.755 | BI178: 7.007
A179: Co-CEO - Options 09/01/2026 exercise price, $ | AT179: 97.38 | AY179: 97.38 | BD179: 97.38 | BI179: 97.38
A181: Co-CEO - Options 10/03/2026 # of unexercised exercisable options, 000s | AT181: 38.67 | AY181: 38.67 | BD181: 38.67 | BI181: 6.648
A182: Co-CEO - Options 10/03/2026 exercise price, $ | AT182: 102.63 | AY182: 102.63 | BD182: 102.63 | BI182: 102.63
A184: Co-CEO - Options 11/01/2026 # of unexercised exercisable options, 000s | AT184: 32.188 | AY184: 32.188 | BD184: 32.188 | BI184: 5.533
A185: Co-CEO - Options 11/01/2026 exercise price, $ | AT185: 123.3 | AY185: 123.3 | BD185: 123.3 | BI185: 123.3
A187: Co-CEO - Options 12/01/2026 # of unexercised exercisable options, 000s | AT187: 33.857 | AY187: 33.857 | BD187: 33.857 | BI187: 5.821
A188: Co-CEO - Options 12/01/2026 exercise price, $ | AT188: 117.22 | AY188: 117.22 | BD188: 117.22 | BI188: 117.22
A190: Co-CEO - Options 01/03/2027 # of unexercised exercisable options, 000s | AT190: 31.13 | AY190: 31.13 | BD190: 31.13 | BI190: 5.352
A191: Co-CEO - Options 01/03/2027 exercise price, $ | AT191: 127.49 | AY191: 127.49 | BD191: 127.49 | BI191: 127.49
A193: Co-CEO - Options 02/01/2027 # of unexercised exercisable options, 000s | AT193: 31.373 | AY193: 31.373 | BD193: 31.373 | BI193: 4.846
A194: Co-CEO - Options 02/01/2027 exercise price, $ | AT194: 140.78 | AY194: 140.78 | BD194: 140.78 | BI194: 140.78
... A206: Co-CEO - Options 06/01/2027 exercise price, $ | AT206: 162.99 | AY206: 162.99 | BD206: 162.99 | BI206: 162.99
A208: Co-CEO - Options 07/03/2027 # of unexercised exercisable options, 000s | AT208: 30.216 | AY208: 30.216 | BD208: 30.216 | BI208: 4.668 | BN208: 4.668
A209: Co-CEO - Options 07/03/2027 exercise price, $ | AT209: 146.17 | AY209: 146.17 | BD209: 146.17 | BI209: 146.17 | BN209: 146.17
A211: Co-CEO - Options 08/01/2027 # of unexercised exercisable options, 000s | AT211: 24.264 | AY211: 24.264 | BD211: 24.264 | BI211: 3.891 | BN211: 3.891
A212: Co-CEO - Options 08/01/2027 exercise price, $ | AT212: 182.03 | AY212: 182.03 | BD212: 182.03 | BI212: 182.03 | BN212: 182.03
A214: Co-CEO - Options 09/01/2027 # of unexercised exercisable options, 000s | AT214: 25.275 | AY214: 25.275 | BD214: 25.275 | BI214: 4.054 | BN214: 4.054
A215: Co-CEO - Options 09/01/2027 exercise price, $ | AT215: 174.74 | AY215: 174.74 | BD215: 174.74 | BI215: 174.74 | BN215: 174.74
A217: Co-CEO - Options 10/02/2027 # of unexercised exercisable options, 000s | AT217: 24.952 | AY217: 24.952 | BD217: 24.952 | BI217: 4.001 | BN217: 4.001
A218: Co-CEO - Options 10/02/2027 exercise price, $ | AT218: 177.01 | AY218: 177.01 | BD218: 177.01 | BI218: 177.01 | BN218: 177.01
A220: Co-CEO - Options 11/01/2027 # of unexercised exercisable options, 000s | AT220: 22.306 | AY220: 22.306 | BD220: 22.306 | BI220: 3.578 | BN220: 3.578
A221: Co-CEO - Options 11/01/2027 exercise price, $ | AT221: 198 | AY221: 198 | BD221: 198 | BI221: 198 | BN221: 198
A223: Co-CEO - Options 12/01/2027 # of unexercised exercisable options, 000s | AT223: 23.641 | AY223: 23.641 | BD223: 23.641 | BI223: 3.791 | BN223: 3.791
A224: Co-CEO - Options 12/01/2027 exercise price, $ | AT224: 186.82 | AY224: 186.82 | BD224: 186.82 | BI224: 186.82 | BN224: 186.82
... A332: Co-CEO - Options 12/01/2030 exercise price, $ | AT332: 504.58 | AY332: 504.58 | BD332: 504.58 | BI332: 504.58 | BN332: 504.58
A334: Co-CEO - Options 01/04/2031 # of unexercised exercisable options, 000s | AY334: 13.547 | BD334: 13.547 | BI334: 2.75 | BN334: 2.75
A335: Co-CEO - Options 01/04/2031 exercise price, $ | AY335: 522.86 | BD335: 522.86 | BI335: 522.86 | BN335: 522.86
A337: Co-CEO - Options 02/01/2031 # of unexercised exercisable options, 000s | AY337: 13.141 | BD337: 13.141 | BI337: 2.666 | BN337: 2.666
A338: Co-CEO - Options 02/01/2031 exercise price, $ | AY338: 539.04 | BD338: 539.04 | BI338: 539.04 | BN338: 539.04
A340: Co-CEO - Options 03/01/2031 # of unexercised exercisable options, 000s | AY340: 12.864 | BD340: 12.864 | BI340: 2.611 | BN340: 2.611
A341: Co-CEO - Options 03/01/2031 exercise price, $ | AY341: 550.64 | BD341: 550.64 | BI341: 550.64 | BN341: 550.64
A343: Co-CEO - Options 04/01/2031 # of unexercised exercisable options, 000s | AY343: 13.131 | BD343: 13.131 | BI343: 2.665 | BN343: 2.665
A344: Co-CEO - Options 04/01/2031 exercise price, $ | AY344: 539.42 | BD344: 539.42 | BI344: 539.42 | BN344: 539.42
A346: Co-CEO - Options 05/03/2031 # of unexercised exercisable options, 000s | AY346: 13.913 | BD346: 13.913 | BI346: 2.823 | BN346: 2.823
A347: Co-CEO - Options 05/03/2031 exercise price, $ | AY347: 509.11 | BD347: 509.11 | BI347: 509.11 | BN347: 509.11
A349: Co-CEO - Options 06/01/2031 # of unexercised exercisable options, 000s | AY349: 14.193 | BD349: 14.193 | BI349: 2.881 | BN349: 2.881
A350: Co-CEO - Options 06/01/2031 exercise price, $ | AY350: 499.08 | BD350: 499.08 | BI350: 499.08 | BN350: 499.08
... A368: Co-CEO - Options 12/01/2031 exercise price, $ | AY368: 617.77 | BD368: 617.77 | BI368: 617.77 | BN368: 617.77
A370: Co-CEO - Options 01/03/2032 # of unexercised exercisable options, 000s | BD370: 11.858 | BI370: 2.406 | BN370: 2.406
A371: Co-CEO - Options 01/03/2032 exercise price, $ | BD371: 597.37 | BI371: 597.37 | BN371: 597.37
A373: Co-CEO - Options 02/01/2032 # of unexercised exercisable options, 000s | BD373: 15.495 | BI373: 3.646 | BN373: 3.646
A374: Co-CEO - Options 02/01/2032 exercise price, $ | BD374: 457.13 | BI374: 457.13 | BN374: 457.13
A376: Co-CEO - Options 03/01/2032 # of unexercised exercisable options, 000s | BD376: 18.34 | BI376: 4.315 | BN376: 4.315
A377: Co-CEO - Options 03/01/2032 exercise price, $ | BD377: 386.24 | BI377: 386.24 | BN377: 386.24
A379: Co-CEO - Options 04/01/2032 # of unexercised exercisable options, 000s | BD379: 18.966 | BI379: 4.463 | BN379: 4.463
A380: Co-CEO - Options 04/01/2032 exercise price, $ | BD380: 373.47 | BI380: 373.47 | BN380: 373.47
A382: Co-CEO - Options 05/02/2032 # of unexercised exercisable options, 000s | BD382: 35.513 | BI382: 8.356 | BN382: 8.356
A383: Co-CEO - Options 05/02/2032 exercise price, $ | BD383: 199.46 | BI383: 199.46 | BN383: 199.46
A385: Co-CEO - Options 06/01/2032 # of unexercised exercisable options, 000s | BD385: 36.718 | BI385: 8.64 | BN385: 8.64
A386: Co-CEO - Options 06/01/2032 exercise price, $ | BD386: 192.91 | BI386: 192.91 | BN386: 192.91
... A404: Co-CEO - Options 12/01/2032 exercise price, $ | BD404: 316.95 | BI404: 316.95 | BN404: 316.95
A406: Co-CEO - Options 01/03/2033 # of unexercised exercisable options, 000s | BI406: 5.651 | BN406: 5.651
A407: Co-CEO - Options 01/03/2033 exercise price, $ | BI407: 294.95 | BN407: 294.95
A409: Co-CEO - Options 02/01/2033 # of unexercised exercisable options, 000s | BN409: 6.577
A410: Co-CEO - Options 02/01/2033 # of unexercised unexercisable options, 000s | BI410: 6.577
A411: Co-CEO - Options 02/01/2033 exercise price, $ | BI411: 361.99 | BN411: 361.99
A413: Co-CEO - Options 03/01/2033 # of unexercised exercisable options, 000s | BN413: 11.514
A414: Co-CEO - Options 03/01/2033 # of unexercised unexercisable options, 000s | BI414: 11.514
A415: Co-CEO - Options 03/01/2033 exercise price, $ | BI415: 313.48 | BN415: 313.48
...

Sheet Supplemental Data
A1: =MO.CompanyName
A2: =MO.Ticker | C2: =Model!C2 | D2: =Model!D2 | E2: =Model!E2 | F2: =Model!F2 | G2: =Model!G2 | H2: =Model!H2 | I2: =Model!I2 | J2: =Model!J2 | ... CF2: =Model!CF2
A3: =MO.TradingCurrency | B3: =MO.LastPrice | C3: =INDEX(MO_Common_FPDays,0,MATCH(C$5,MO_Common_ColumnHeader,0)) | D3: =INDEX(MO_Common_FPDays,0,MATCH(D$5,MO_Common_ColumnHeader,0)) | E3: =INDEX(MO_Common_FPDays,0,MATCH(E$5,MO_Common_ColumnHeader,0)) | F3: =INDEX(MO_Common_FPDays,0,MATCH(F$5,MO_Common_ColumnHeader,0)) | G3: =INDEX(MO_Common_FPDays,0,MATCH(G$5,MO_Common_ColumnHeader,0)) | H3: =INDEX(MO_Common_FPDays,0,MATCH(H$5,MO_Common_ColumnHeader,0)) | I3: =INDEX(MO_Common_FPDays,0,MATCH(I$5,MO_Common_ColumnHeader,0)) | J3: =INDEX(MO_Common_FPDays,0,MATCH(J$5,MO_Common_ColumnHeader,0)) | ... CF3: =INDEX(MO_Common_FPDays,0,MATCH(CF$5,MO_Common_ColumnHeader,0))
A4: =MO.DataSourceName | B4: =MO.RealTime | C4: =INDEX(MO_Common_QEndDate,0,MATCH(C$5,MO_Common_ColumnHeader,0)) | D4: =INDEX(MO_Common_QEndDate,0,MATCH(D$5,MO_Common_ColumnHeader,0)) | E4: =INDEX(MO_Common_QEndDate,0,MATCH(E$5,MO_Common_ColumnHeader,0)) | F4: =INDEX(MO_Common_QEndDate,0,MATCH(F$5,MO_Common_ColumnHeader,0)) | G4: =INDEX(MO_Common_QEndDate,0,MATCH(G$5,MO_Common_ColumnHeader,0)) | H4: =INDEX(MO_Common_QEndDate,0,MATCH(H$5,MO_Common_ColumnHeader,0)) | I4: =INDEX(MO_Common_QEndDate,0,MATCH(I$5,MO_Common_ColumnHeader,0)) | J4: =INDEX(MO_Common_QEndDate,0,MATCH(J$5,MO_Common_ColumnHeader,0)) | ... CF4: =INDEX(MO_Common_QEndDate,0,MATCH(CF$5,MO_Common_ColumnHeader,0))
A5: =MO.ReportFX | C5: =Model!C5 | D5: =Model!D5 | E5: =Model!E5 | F5: =Model!F5 | G5: =Model!G5 | H5: =Model!H5 | I5: =Model!I5 | J5: =Model!J5 | ... CF5: =Model!CF5
A6: Key Metrics - Content Obligations (FS)
A7: Current content liabilities, mm | D7: =Model!D1226 | E7: =Model!E1226 | F7: =Model!F1226 | G7: =Model!G1226 | H7: =Model!H1226 | I7: =Model!I1226 | J7: =K7 | K7: =Model!K1226 | L7: =Model!L1226 | M7: =Model!M1226 | N7: =Model!N1226 | O7: =P7 | P7: =Model!P1226 | Q7: =Model!Q1226 | R7: =Model!R1226 | S7: =Model!S1226 | T7: =U7 | U7: =Model!U1226 | V7: =Model!V1226 | W7: =Model!W1226 | X7: =Model!X1226 | Y7: =Z7 | Z7: =Model!Z1226 | AA7: =Model!AA1226 | AB7: =Model!AB1226 | AC7: =Model!AC1226 | AD7: =AE7 | AE7: =Model!AE1226 | AF7: =Model!AF1226 | AG7: =Model!AG1226 | AH7: =Model!AH1226 | AI7: =AJ7 | AJ7: =Model!AJ1226 | AK7: =Model!AK1226 | AL7: =Model!AL1226 | AM7: =Model!AM1226 | AN7: =AO7 | AO7: =Model!AO1226 | AP7: =Model!AP1226 | AQ7: =Model!AQ1226 | AR7: =Model!AR1226 | AS7: =AT7 | AT7: =Model!AT1226 | AU7: =Model!AU1226 | AV7: =Model!AV1226 | AW7: 4110.962 | AX7: =AY7 | AY7: =Model!AY1226 | AZ7: =Model!AZ1226 | BA7: =Model!BA1226 | BB7: =Model!BB1226 | BC7: =BD7 | BD7: =Model!BD1226 | BE7: =Model!BE1226 | BF7: =Model!BF1226 | BG7: =Model!BG1226 | BH7: =BI7 | BI7: =Model!BI1226 | BJ7: =Model!BJ1226 | BK7: =Model!BK1226 | BL7: =Model!BL1226 | BM7: =BN7 | BN7: =Model!BN1226 | BO7: =Model!BO1226 | BP7: =Model!BP1226 | BQ7: =Model!BQ1226 | BR7: =BS7 | BS7: =Model!BS1226 | BT7: =Model!BT1226
A8: Non-current content liabilities, mm | D8: =Model!D1237 | E8: =Model!E1237 | F8: =Model!F1237 | G8: =Model!G1237 | H8: =Model!H1237 | I8: =Model!I1237 | J8: =K8 | K8: =Model!K1237 | L8: =Model!L1237 | M8: =Model!M1237 | N8: =Model!N1237 | O8: =P8 | P8: =Model!P1237 | Q8: =Model!Q1237 | R8: =Model!R1237 | S8: =Model!S1237 | T8: =U8 | U8: =Model!U1237 | V8: =Model!V1237 | W8: =Model!W1237 | X8: =Model!X1237 | Y8: =Z8 | Z8: =Model!Z1237 | AA8: =Model!AA1237 | AB8: =Model!AB1237 | AC8: =Model!AC1237 | AD8: =AE8 | AE8: =Model!AE1237 | AF8: =Model!AF1237 | AG8: =Model!AG1237 | AH8: =Model!AH1237 | AI8: =AJ8 | AJ8: =Model!AJ1237 | AK8: =Model!AK1237 | AL8: =Model!AL1237 | AM8: =Model!AM1237 | AN8: =AO8 | AO8: =Model!AO1237 | AP8: =Model!AP1237 | AQ8: =Model!AQ1237 | AR8: =Model!AR1237 | AS8: =AT8 | AT8: =Model!AT1237 | AU8: =Model!AU1237 | AV8: =Model!AV1237 | AW8: 2301.026 | AX8: =AY8 | AY8: =Model!AY1237 | AZ8: =Model!AZ1237 | BA8: =Model!BA1237 | BB8: =Model!BB1237 | BC8: =BD8 | BD8: =Model!BD1237 | BE8: =Model!BE1237 | BF8: =Model!BF1237 | BG8: =Model!BG1237 | BH8: =BI8 | BI8: =Model!BI1237 | BJ8: =Model!BJ1237 | BK8: =Model!BK1237 | BL8: =Model!BL1237 | BM8: =BN8 | BN8: =Model!BN1237 | BO8: =Model!BO1237 | BP8: =Model!BP1237 | BQ8: =Model!BQ1237 | BR8: =BS8 | BS8: =Model!BS1237 | BT8: =Model!BT1237
A9: Other obligations not reflected in Balance sheet, mm | D9: =D10-D7-D8 | E9: =E10-E7-E8 | F9: =F10-F7-F8 | G9: =G10-G7-G8 | H9: =H10-H7-H8 | I9: =I10-I7-I8 | J9: =K9 | K9: =K10-K7-K8 | L9: =L10-L7-L8 | M9: =M10-M7-M8 | N9: =N10-N7-N8 | O9: =P9 | P9: =P10-P7-P8 | Q9: =Q10-Q7-Q8 | R9: =R10-R7-R8 | S9: =S10-S7-S8 | T9: =U9 | U9: =U10-U7-U8 | V9: =V10-V7-V8 | W9: =W10-W7-W8 | X9: =X10-X7-X8 | Y9: =Z9 | Z9: =Z10-Z7-Z8 | AA9: =AA10-AA7-AA8 | AB9: =AB10-AB7-AB8 | AC9: =AC10-AC7-AC8 | AD9: =AE9 | AE9: =AE10-AE7-AE8 | AF9: =AF10-AF7-AF8 | AG9: =AG10-AG7-AG8 | AH9: =AH10-AH7-AH8 | AI9: =AJ9 | AJ9: =AJ10-AJ7-AJ8 | AK9: =AK10-AK7-AK8 | AL9: =AL10-AL7-AL8 | AM9: =AM10-AM7-AM8 | AN9: =AO9 | AO9: =AO10-AO7-AO8 | AP9: =AP10-AP7-AP8 | AQ9: =AQ10-AQ7-AQ8 | AR9: =AR10-AR7-AR8 | AS9: =AT9 | AT9: =AT10-AT7-AT8 | AU9: =AU10-AU7-AU8 | AV9: =AV10-AV7-AV8 | AW9: =AW10-AW7-AW8 | AX9: =AY9 | AY9: =AY10-AY7-AY8 | AZ9: =AZ10-AZ7-AZ8 | BA9: =BA10-BA7-BA8 | BB9: =BB10-BB7-BB8 | BC9: =BD9 | BD9: =BD10-BD7-BD8 | BE9: =BE10-BE7-BE8 | BF9: =BF10-BF7-BF8 | BG9: =BG10-BG7-BG8 | BH9: =BI9 | BI9: =BI10-BI7-BI8 | BJ9: =BJ10-BJ7-BJ8 | BK9: =BK10-BK7-BK8 | BL9: =BL10-BL7-BL8 | BM9: =BN9 | BN9: =BN10-BN7-BN8 | BO9: =BO10-BO7-BO8 | BP9: =BP10-BP7-BP8 | BQ9: =BQ10-BQ7-BQ8 | BR9: =BS9 | BS9: =BS10-BS7-BS8 | BT9: =BT10-BT7-BT8
A10: Total Content Obligations, mm | D10: 1299.176 | E10: 3907.198 | F10: 5633.685 | G10: 5672.486 | H10: 6368.105 | I10: 6505.351 | J10: =K10 | K10: 7252.161 | L10: 7123.209 | M10: 7728.05 | N10: 8857.227 | O10: =P10 | P10: 9451.112 | Q10: 9780.262 | R10: 10073.409 | S10: 10378.218 | T10: =U10 | U10: 10902.231 | V10: 12318.233 | W10: 13194.009 | X10: 14353.045 | Y10: =Z10 | Z10: 14479.487 | AA10: 15290.134 | AB10: 15699.387 | AC10: 16991.93 | AD10: =AE10 | AE10: 17694.642 | AF10: 17937.682 | AG10: 18398.766 | AH10: 18645.758 | AI10: =AJ10 | AJ10: 19285.875 | AK10: 18922.789 | AL10: 18502.817 | AM10: 19141.543 | AN10: =AO10 | AO10: 19490.082 | AP10: 19174.038 | AQ10: 19133.34 | AR10: 19072.254 | AS10: =AT10 | AT10: 19218.83 | AU10: 20725.165 | AV10: 21863.144 | AW10: 22465.54 | AX10: =AY10 | AY10: 23161.36 | AZ10: 22365.56 | BA10: 22769.606 | BB10: 21572.745 | BC10: =BD10 | BD10: 21831.947 | BE10: 21525.871 | BF10: =BF16 | BG10: =BG16 | BH10: =BI10 | BI10: 21713.349 | BJ10: 24195 | BK10: =BK16 | BL10: 22698.295 | BM10: =BN10 | BN10: 23248.931 | BO10: 21790.643 | BP10: 20967.27 | BQ10: 20940.9 | BR10: =BS10 | BS10: 24039.228 | BT10: 24139.431
A12: Content obligations due in less than one year, mm | D12: 530.878 | E12: 797.649 | F12: 2299.562 | G12: 2376.26 | H12: 2533.061 | I12: 2766.597 | J12: =K12 | K12: 2972.325 | L12: 3055.127 | M12: 3304.367 | N12: 3574.129 | O12: =P12 | P12: 3747.648 | Q12: 4016.95 | R12: 4271.285 | S12: 4535.209 | T12: =U12 | U12: 4703.172 | V12: 5161.279 | W12: 5544.875 | X12: 5895.205 | Y12: =Z12 | Z12: 6200.611 | AA12: 6599.754 | AB12: 6592.517 | AC12: 6984.36 | AD12: =AE12 | AE12: 7446.947 | AF12: 7949.544 | AG12: 8212.614 | AH12: 8407.156 | AI12: =AJ12 | AJ12: 8611.398 | AK12: 8888.491 | AL12: 8741.623 | AM12: 8993.612 | AN12: =AO12 | AO12: 8477.367 | AP12: 8618.185 | AQ12: 8415.792 | AR12: 8668.296 | AS12: =AT12 | AT12: 8980.868 | AU12: 9456.342 | AV12: 9885.589 | AW12: 10017.405 | AX12: =AY12 | AY12: 10019.306 | AZ12: 9861.979 | BA12: 10208.609 | BB12: 9667.326 | BC12: =BD12 | BD12: 10038.483 | BE12: 9771.665 | BF12: 9818.37 | BG12: 9512.081 | BH12: =BI12 | BI12: 10328.923 | BJ12: 11066.048 | BK12: 11456.834 | BL12: 11810.836 | BM12: =BN12 | BN12: 11424.696 | BO12: 10977.295 | BP12: 10842.959 | BQ12: 11267.688 | BR12: =BS12 | BS12: 11528.03 | BT12: 11779.222
A13: Content obligations due after one year and through three years, mm | D13: 531.698 | E13: 2384.373 | F13: 2715.294 | G13: 2696.896 | H13: 2864.331 | I13: 2829.201 | J13: =K13 | K13: 3266.907 | L13: 3393.761 | M13: 3732.38 | N13: 4176.621 | O13: =P13 | P13: 4495.103 | Q13: 4634.792 | R13: 4791.033 | S13: 4888.13 | T13: =U13 | U13: 5249.147 | V13: 5745.041 | W13: 6305.936 | X13: 6770.007 | Y13: =Z13 | Z13: 6731.336 | AA13: 6939.847 | AB13: 7461.47 | AC13: 7918.009 | AD13: =AE13 | AE13: 8210.159 | AF13: 8015.837 | AG13: 8374.64 | AH13: 8557.396 | AI13: =AJ13 | AJ13: 8841.561 | AK13: 8416.736 | AL13: 8282.265 | AM13: 8082.44 | AN13: =AO13 | AO13: 8352.731 | AP13: 8064.206 | AQ13: 8315.449 | AR13: 8004.624 | AS13: =AT13 | AT13: 7819.563 | AU13: 8241.022 | AV13: 8548.463 | AW13: 8991.781 | AX13: =AY13 | AY13: 9238.315 | AZ13: 9089.537 | BA13: 9286.478 | BB13: 8961.147 | BC13: =BD13 | BD13: 9425.551 | BE13: 9536.111 | BF13: 9131.131 | BG13: 8470.469 | BH13: =BI13 | BI13: 8784.302 | BJ13: 9378.186 | BK13: 8592.237 | BL13: 8062.166 | BM13: =BN13 | BN13: 8113.91 | BO13: 7552.902 | BP13: 7179.966 | BQ13: 6981.849 | BR13: =BS13 | BS13: 8376.16 | BT13: 8611.852
A14: Content obligations due after three years and through five years, mm | D14: 236.6 | E14: 650.48 | F14: 540.346 | G14: 535.617 | H14: 830.536 | I14: 803.942 | J14: =K14 | K14: 929.645 | L14: 630.518 | M14: 653.408 | N14: 1071.238 | O14: =P14 | P14: 1164.308 | Q14: 1071.291 | R14: 961.784 | S14: 908.111 | T14: =U14 | U14: 891.864 | V14: 1256.041 | W14: 1220.827 | X14: 1489.933 | Y14: =Z14 | Z14: 1386.934 | AA14: 1562.941 | AB14: 1488.76 | AC14: 1918.123 | AD14: =AE14 | AE14: 1894.001 | AF14: 1849.029 | AG14: 1718.511 | AH14: 1590.976 | AI14: =AJ14 | AJ14: 1684.582 | AK14: 1480.67 | AL14: 1341.448 | AM14: 1586.731 | AN14: =AO14 | AO14: 2041.34 | AP14: 1974.855 | AQ14: 1941.731 | AR14: 1956.565 | AS14: =AT14 | AT14: 1973.091 | AU14: 2259.821 | AV14: 2688.616 | AW14: 2860.871 | AX14: =AY14 | AY14: 3238.977 | AZ14: 3072.216 | BA14: 2904.226 | BB14: 2639.608 | BC14: =BD14 | BD14: 2124.307 | BE14: 1964.812 | BF14: 1662.733 | BG14: 1449.676 | BH14: =BI14 | BI14: 2016.358 | BJ14: 2820.168 | BK14: 2528.545 | BL14: 2277.918 | BM14: =BN14 | BN14: 2809.834 | BO14: 2520.879 | BP14: 2273.025 | BQ14: 2110.536 | BR14: =BS14 | BS14: 3041.538 | BT14: 2825.509
A15: Content obligations due after five years, mm | D15: 0 | E15: 74.696 | F15: 78.483 | G15: 63.713 | H15: 140.177 | I15: 105.611 | J15: =K15 | K15: 83.284 | L15: 43.803 | M15: 37.895 | N15: 35.239 | O15: =P15 | P15: 44.053 | Q15: 57.229 | R15: 49.307 | S15: 46.768 | T15: =U15 | U15: 58.048 | V15: 155.872 | W15: 122.371 | X15: 197.9 | Y15: =Z15 | Z15: 160.606 | AA15: 187.592 | AB15: 156.64 | AC15: 171.438 | AD15: =AE15 | AE15: 143.535 | AF15: 123.272 | AG15: 93.001 | AH15: 90.23 | AI15: =AJ15 | AJ15: 148.334 | AK15: 136.892 | AL15: 137.481 | AM15: 478.76 | AN15: =AO15 | AO15: 618.644 | AP15: 516.792 | AQ15: 460.368 | AR15: 442.769 | AS15: =AT15 | AT15: 445.308 | AU15: 767.98 | AV15: 740.476 | AW15: 595.483 | AX15: =AY15 | AY15: 664.762 | AZ15: 341.828 | BA15: 370.293 | BB15: 304.664 | BC15: =BD15 | BD15: 243.606 | BE15: 253.283 | BF15: 288.054 | BG15: 217.823 | BH15: =BI15 | BI15: 583.766 | BJ15: 930.598 | BK15: 731.986 | BL15: 547.375 | BM15: =BN15 | BN15: 900.491 | BO15: 739.567 | BP15: 671.32 | BQ15: 580.827 | BR15: =BS15 | BS15: 1093.5 | BT15: 922.848
A16: Total Content Obligations, mm | D16: =SUM(D12:D15) | E16: =SUM(E12:E15) | F16: =SUM(F12:F15) | G16: =SUM(G12:G15) | H16: =SUM(H12:H15) | I16: =SUM(I12:I15) | J16: =SUM(J12:J15) | K16: =SUM(K12:K15) | ... BT16: =SUM(BT12:BT15)
A18: Key Metrics - Headcount (FS)
A19: United States & Canada employees, # of employees | AT19: 7600 | AY19: 8600 | BD19: 9000 | BI19: 9000 | BN19: 9600 | BS19: 10900
A20: EMEA employees, # of employees | AT20: 1000 | AY20: 1400 | BD20: 2000 | BI20: 2000 | BN20: 2200 | BS20: 2500
A21: Latin America employees, # of employees | AT21: 200 | AY21: 400 | BD21: 400 | BI21: 500 | BN21: 600 | BS21: 700
A22: Asia Pacific employees, # of employees | AT22: 600 | AY22: 900 | BD22: 1400 | BI22: 1500 | BN22: 1600 | BS22: 1900
A23: Total Full-time Employees, # of employees | C23: 1883 | D23: 2180 | E23: 2348 | F23: 2045 | K23: 2022 | P23: 2189 | U23: 3500 | Z23: 4500 | AE23: 5400 | AJ23: 7100 | AO23: 8600 | AT23: =SUM(AT19:AT22) | AY23: =SUM(AY19:AY22) | BD23: =SUM(BD19:BD22) | BI23: =SUM(BI19:BI22) | BN23: =SUM(BN19:BN22) | BS23: =SUM(BS19:BS22)
A25: Segmented Results - Revenue Breakdown Based On Old Segmentation (FS) (Historical)
A26: Domestic Streaming Revenue, mm | F26: 2184.868 | G26: 638.649 | H26: 671.089 | I26: 701.083 | J26: =K26-I26-H26-G26 | K26: 2751.375 | L26: 798.617 | M26: 838.225 | N26: 877.15 | O26: =P26-N26-M26-L26 | P26: 3431.434 | Q26: 984.532 | R26: 1025.913 | S26: 1063.961 | T26: =U26-Q26-R26-S26 | U26: 4180.339 | V26: 1161.241 | W26: 1208.271 | X26: 1304.333 | Y26: =Z26-V26-W26-X26 | Z26: 5077.307 | AA26: 1470.042 | AB26: 1505.499 | AC26: 1547.21 | AD26: =AE26-AA26-AB26-AC26 | AE26: 6153.025 | AF26: 1820.019 | AG26: 1893.222 | AH26: 1937.314 | AI26: =AJ26-AF26-AG26-AH26 | AJ26: 7646.647 | AK26: 2073.555 | AL26: 2299.189 | AM26: 2412.598 | AN26: =AO26-AK26-AL26-AM26 | AO26: 9243.005
A27: Y/Y Domestic streaming revenue growth, % | K27: ='Supplemental Data'!K26/'Supplemental Data'!F26-1 | L27: ='Supplemental Data'!L26/'Supplemental Data'!G26-1 | M27: ='Supplemental Data'!M26/'Supplemental Data'!H26-1 | N27: ='Supplemental Data'!N26/'Supplemental Data'!I26-1 | O27: ='Supplemental Data'!O26/'Supplemental Data'!J26-1 | P27: ='Supplemental Data'!P26/'Supplemental Data'!K26-1 | Q27: ='Supplemental Data'!Q26/'Supplemental Data'!L26-1 | R27: ='Supplemental Data'!R26/'Supplemental Data'!M26-1 | ... AO27: ='Supplemental Data'!AO26/'Supplemental Data'!AJ26-1
A28: International Streaming Revenue, mm | F28: 287.542 | G28: 142.019 | H28: 165.902 | I28: 183.051 | J28: =K28-I28-H28-G28 | K28: 712.39 | L28: 267.118 | M28: 307.461 | N28: 345.685 | O28: =P28-N28-M28-L28 | P28: 1308.061 | Q28: 415.397 | R28: 454.763 | S28: 516.87 | T28: =U28-Q28-R28-S28 | U28: 1953.435 | V28: 651.748 | W28: 758.201 | X28: 853.48 | Y28: =Z28-V28-W28-X28 | Z28: 3211.095 | AA28: 1046.199 | AB28: 1165.228 | AC28: 1327.435 | AD28: =AE28-AA28-AB28-AC28 | AE28: 5089.191 | AF28: 1782.086 | AG28: 1921.144 | AH28: 1973.283 | AI28: =AJ28-AF28-AG28-AH28 | AJ28: 7782.105 | AK28: 2366.749 | AL28: 2547.727 | AM28: 2760.43 | AN28: =AO28-AK28-AL28-AM28 | AO28: 10616.225
A29: Y/Y International streaming revenue growth, % | K29: ='Supplemental Data'!K28/'Supplemental Data'!F28-1 | L29: ='Supplemental Data'!L28/'Supplemental Data'!G28-1 | M29: ='Supplemental Data'!M28/'Supplemental Data'!H28-1 | N29: ='Supplemental Data'!N28/'Supplemental Data'!I28-1 | O29: ='Supplemental Data'!O28/'Supplemental Data'!J28-1 | P29: ='Supplemental Data'!P28/'Supplemental Data'!K28-1 | Q29: ='Supplemental Data'!Q28/'Supplemental Data'!L28-1 | R29: ='Supplemental Data'!R28/'Supplemental Data'!M28-1 | ... AO29: ='Supplemental Data'!AO28/'Supplemental Data'!AJ28-1
A30: Domestic DVD Revenue, mm | F30: 1136.872 | G30: 243.293 | H30: 232.381 | I30: 221.865 | J30: =K30-I30-H30-G30 | K30: 910.797 | L30: 204.354 | M30: 194.721 | N30: 186.597 | O30: =P30-N30-M30-L30 | P30: 765.161 | Q30: 173.2 | R30: 164.018 | S30: 157.524 | T30: =U30-Q30-R30-S30 | U30: 645.737 | V30: 144.747 | W30: 138.732 | X30: 132.375 | Y30: =Z30-V30-W30-X30 | Z30: 542.267 | AA30: 120.394 | AB30: 114.737 | AC30: 110.214 | AD30: =AE30-AA30-AB30-AC30 | AE30: 450.497 | AF30: 98.751 | AG30: 92.904 | AH30: 88.777 | AI30: =AJ30-AF30-AG30-AH30 | AJ30: 365.589 | AK30: 80.688 | AL30: 76.2 | AM30: 71.877 | AN30: =AO30-AK30-AL30-AM30 | AO30: 297.217
A31: Y/Y Domestic DVD Revenue Growth, % | K31: ='Supplemental Data'!K30/'Supplemental Data'!F30-1 | L31: ='Supplemental Data'!L30/'Supplemental Data'!G30-1 | M31: ='Supplemental Data'!M30/'Supplemental Data'!H30-1 | N31: ='Supplemental Data'!N30/'Supplemental Data'!I30-1 | O31: ='Supplemental Data'!O30/'Supplemental Data'!J30-1 | P31: ='Supplemental Data'!P30/'Supplemental Data'!K30-1 | Q31: ='Supplemental Data'!Q30/'Supplemental Data'!L30-1 | R31: ='Supplemental Data'!R30/'Supplemental Data'!M30-1 | ... AO31: ='Supplemental Data'!AO30/'Supplemental Data'!AJ30-1
A32: Total Revenue, mm | F32: =F26+F28+F30 | G32: =G26+G28+G30 | H32: =H26+H28+H30 | I32: =I26+I28+I30 | J32: =J26+J28+J30 | K32: =K26+K28+K30 | L32: =L26+L28+L30 | M32: =M26+M28+M30 | ... AO32: =AO26+AO28+AO30
A34: Segmented Results - Costs Breakdown Based On Old Segmentation (FS) (Historical)
A35: Domestic Streaming COGS, mm | F35: 1570.6 | G35: 440.334 | H35: 452.598 | I35: 473.965 | J35: =K35-I35-H35-G35 | K35: 1863.376 | L35: 517.094 | M35: 546.223 | N35: 565.251 | O35: =P35-N35-M35-L35 | P35: 2201.761 | Q35: 582.529 | R35: 612.691 | S35: 644.914 | T35: =U35-Q35-R35-S35 | U35: 2487.193 | V35: 687.756 | W35: 729.399 | X35: 746.22 | Y35: 788.598 | Z35: 2951.973 | AA35: 783.954 | AB35: 868.53 | AC35: 902.275 | AD35: 916.1 | AE35: 3470.859 | AF35: 936.48 | AG35: 969.995 | AH35: 1038.473 | AI35: 1093.446 | AJ35: =SUM(AF35,AG35,AH35,AI35) | AK35: 1139.535 | AL35: 1196.42 | AM35: 1210.105 | AN35: 1321.283 | AO35: =SUM(AK35,AL35,AM35,AN35)
A36: International Streaming COGS, mm | F36: 483.295 | G36: 166.892 | H36: 184.4 | I36: 209.811 | J36: =K36-I36-H36-G36 | K36: 782.304 | L36: 245.267 | M36: 266.697 | N36: 291.942 | O36: =P36-N36-M36-L36 | P36: 1154.117 | Q36: 375.278 | R36: 422.966 | S36: 451.251 | T36: =U36-Q36-R36-S36 | U36: 1780.375 | V36: 657.73 | W36: 728.168 | X36: 783.877 | Y36: 872.972 | Z36: 3042.747 | AA36: 896.558 | AB36: 1070.432 | AC36: 1136.877 | AD36: 1255.749 | AE36: 4359.616 | AF36: 1321.706 | AG36: 1392.512 | AH36: 1455.554 | AI36: 1606.275 | AJ36: =SUM(AF36,AG36,AH36,AI36) | AK36: 1697.121 | AL36: 1778.89 | AM36: 1860.021 | AN36: 2113.631 | AO36: =SUM(AK36,AL36,AM36,AN36)
A37: Domestic DVD COGS, mm | F37: 598.163 | G37: 129.726 | H37: 123.676 | I37: 115.124 | J37: =K37-I37-H37-G37 | K37: 471.523 | L37: 106.825 | M37: 101.928 | N37: 97.201 | O37: =P37-N37-M37-L37 | P37: 396.882 | Q37: 88.594 | R37: 86.095 | S37: 77.793 | T37: =U37-Q37-R37-S37 | U37: 323.908 | V37: 73.095 | W37: 67.83 | X37: 63.671 | Y37: =Z37-V37-W37-X37 | Z37: 262.742 | AA37: 60.219 | AB37: 52.734 | AC37: 47.087 | AD37: =AE37-AA37-AB37-AC37 | AE37: 202.525 | AF37: 42.393 | AG37: 39.924 | AH37: 37.101 | AI37: 33.679 | AJ37: 153.097 | AK37: 33.958 | AL37: 30.347 | AM37: 27.793 | AN37: 31.109 | AO37: =SUM(AK37,AL37,AM37,AN37)
A38: Total COGS, mm | F38: =SUM(F35:F37) | G38: =SUM(G35:G37) | H38: =SUM(H35:H37) | I38: =SUM(I35:I37) | J38: =SUM(J35:J37) | K38: =SUM(K35:K37) | L38: =SUM(L35:L37) | M38: =SUM(M35:M37) | ... AO38: =SUM(AO35:AO37)
A40: Domestic Streaming Marketing Expense, mm | F40: 245.259 | G40: 66.965 | H40: 67.177 | I40: 60.637 | J40: =K40-I40-H40-G40 | K40: 265.232 | L40: 80.258 | M40: 64.727 | N40: 61.045 | O40: =P40-N40-M40-L40 | P40: 293.453 | Q40: 89.551 | R40: 73.427 | S40: 74.835 | T40: =U40-Q40-R40-S40 | U40: 317.646 | V40: 88.574 | W40: 93.751 | X40: 116.687 | Y40: 113.916 | Z40: 412.928 | AA40: 126.253 | AB40: 124.903 | AC40: 141.533 | AD40: 211.057 | AE40: 603.746 | AF40: 250.719 | AG40: 251.298 | AH40: 210.595 | AI40: 312.739 | AJ40: 1025.351 | AK40: 221.046 | AL40: 250.606 | AM40: 211.793 | AN40: 379.597 | AO40: =SUM(AK40,AL40,AM40,AN40)
A41: International Streaming Marketing Expense, mm | F41: 193.39 | G41: 52.047 | H41: 47.335 | I41: 47.537 | J41: =K41-I41-H41-G41 | K41: 204.418 | L41: 56.84 | M41: 56.036 | N41: 84.609 | O41: =P41-N41-M41-L41 | P41: 313.733 | Q41: 105.126 | R41: 123.713 | S41: 133.267 | T41: =U41-Q41-R41-S41 | U41: 506.446 | V41: 142.891 | W41: 146.839 | X41: 194.33 | Y41: 200.531 | Z41: 684.591 | AA41: 179.895 | AB41: 186.257 | AC41: 210.913 | AD41: 255.47 | AE41: 832.535 | AF41: 286.058 | AG41: 340.709 | AH41: 299.735 | AI41: 417.616 | AJ41: 1344.118 | AK41: 395.532 | AL41: 352.544 | AM41: 342.004 | AN41: 499.34 | AO41: =SUM(AK41,AL41,AM41,AN41)
A42: Domestic DVD Marketing Expense, mm | F42: 0.559 | G42: 0.074 | H42: 0.099 | I42: 0.054 | J42: =K42-I42-H42-G42 | K42: 0.292 | L42: 0 | M42: 0 | N42: 0 | O42: =P42-N42-M42-L42 | P42: 0 | Q42: 0 | R42: 0 | S42: 0 | T42: =U42-Q42-R42-S42 | U42: 0 | V42: 0 | W42: 0 | X42: 0 | Y42: =Z42-V42-W42-X42 | Z42: 0 | AA42: 0 | AB42: 0 | AC42: 0 | AD42: =AE42-AA42-AB42-AC42 | AE42: 0 | AF42: 0 | AG42: 0 | AH42: 0 | AI42: 0 | AJ42: 0 | AK42: 0 | AL42: 0 | AM42: 0 | AN42: 0
A43: Total Marketing Expense, mm | F43: =SUM(F40:F42) | G43: =SUM(G40:G42) | H43: =SUM(H40:H42) | I43: =SUM(I40:I42) | J43: =SUM(J40:J42) | K43: =SUM(K40:K42) | L43: =SUM(L40:L42) | M43: =SUM(M40:M42) | ... AO43: =SUM(AO40:AO42)
A45: Domestic Streaming Net Contribution, mm | F45: ='Supplemental Data'!F26-F35-F40 | G45: ='Supplemental Data'!G26-G35-G40 | H45: ='Supplemental Data'!H26-H35-H40 | I45: ='Supplemental Data'!I26-I35-I40 | J45: ='Supplemental Data'!J26-J35-J40 | K45: ='Supplemental Data'!K26-K35-K40 | L45: ='Supplemental Data'!L26-L35-L40 | M45: ='Supplemental Data'!M26-M35-M40 | ... AO45: ='Supplemental Data'!AO26-AO35-AO40
A46: International Streaming Net Contribution, mm | F46: ='Supplemental Data'!F28-F36-F41 | G46: ='Supplemental Data'!G28-G36-G41 | H46: ='Supplemental Data'!H28-H36-H41 | I46: ='Supplemental Data'!I28-I36-I41 | J46: ='Supplemental Data'!J28-J36-J41 | K46: ='Supplemental Data'!K28-K36-K41 | L46: ='Supplemental Data'!L28-L36-L41 | M46: ='Supplemental Data'!M28-M36-M41 | ... AO46: ='Supplemental Data'!AO28-AO36-AO41
A47: Domestic DVD Net Contribution, mm | F47: ='Supplemental Data'!F30-F37-F42 | G47: ='Supplemental Data'!G30-G37-G42 | H47: ='Supplemental Data'!H30-H37-H42 | I47: ='Supplemental Data'!I30-I37-I42 | J47: ='Supplemental Data'!J30-J37-J42 | K47: ='Supplemental Data'!K30-K37-K42 | L47: ='Supplemental Data'!L30-L37-L42 | M47: ='Supplemental Data'!M30-M37-M42 | ... AO47: ='Supplemental Data'!AO30-AO37-AO42
A48: Total Net Contribution, mm | F48: =SUM(F45:F47) | G48: =SUM(G45:G47) | H48: =SUM(H45:H47) | I48: =SUM(I45:I47) | J48: =SUM(J45:J47) | K48: =SUM(K45:K47) | L48: =SUM(L45:L47) | M48: =SUM(M45:M47) | ... AO48: =SUM(AO45:AO47)
A50: Domestic Streaming Net Contribution margin, % | F50: =F45/'Supplemental Data'!F26 | G50: =G45/'Supplemental Data'!G26 | H50: =H45/'Supplemental Data'!H26 | I50: =I45/'Supplemental Data'!I26 | J50: =J45/'Supplemental Data'!J26 | K50: =K45/'Supplemental Data'!K26 | L50: =L45/'Supplemental Data'!L26 | M50: =M45/'Supplemental Data'!M26 | ... AO50: =AO45/'Supplemental Data'!AO26
A51: International Streaming Net Contribution margin, % | F51: =F46/'Supplemental Data'!F28 | G51: =G46/'Supplemental Data'!G28 | H51: =H46/'Supplemental Data'!H28 | I51: =I46/'Supplemental Data'!I28 | J51: =J46/'Supplemental Data'!J28 | K51: =K46/'Supplemental Data'!K28 | L51: =L46/'Supplemental Data'!L28 | M51: =M46/'Supplemental Data'!M28 | ... AO51: =AO46/'Supplemental Data'!AO28
A52: Domestic DVD Net Contribution margin, % | F52: =F47/'Supplemental Data'!F30 | G52: =G47/'Supplemental Data'!G30 | H52: =H47/'Supplemental Data'!H30 | I52: =I47/'Supplemental Data'!I30 | J52: =J47/'Supplemental Data'!J30 | K52: =K47/'Supplemental Data'!K30 | L52: =L47/'Supplemental Data'!L30 | M52: =M47/'Supplemental Data'!M30 | ... AO52: =AO47/'Supplemental Data'!AO30
A53: Total Net Contribution margin, % | F53: =F48/'Supplemental Data'!F32 | G53: =G48/'Supplemental Data'!G32 | H53: =H48/'Supplemental Data'!H32 | I53: =I48/'Supplemental Data'!I32 | J53: =J48/'Supplemental Data'!J32 | K53: =K48/'Supplemental Data'!K32 | L53: =L48/'Supplemental Data'!L32 | M53: =M48/'Supplemental Data'!M32 | ... AO53: =AO48/'Supplemental Data'!AO32
A55: Key Metrics- Membership Breakdown Based On Old Segmentation (MD&A) (Historical)
A56: Domestic Paid BOP Streaming Memberships, 000s | G56: =F58 | H56: =G58 | I56: =H58 | J56: =I58 | K56: =F58 | L56: =K58 | M56: =L58 | N56: =M58 | O56: =N58 | P56: =K58 | Q56: =P58 | R56: =Q58 | S56: =R58 | T56: =S58 | U56: =P58 | V56: =U58 | W56: =V58 | X56: =W58 | Y56: =X58 | Z56: =U58 | AA56: =Z58 | AB56: =AA58 | AC56: =AB58 | AD56: =AC58 | AE56: =Z58 | AF56: =AE58 | AG56: =AF58 | AH56: =AG58 | AI56: =AH58 | AJ56: =AE58 | AK56: =AJ58 | AL56: =AK58 | AM56: =AL58 | AN56: =AM58 | AO56: =AJ58
A57: Net Domestic Paid Streaming Memberships Change, 000s | G57: =G58-G56 | H57: =H58-H56 | I57: =I58-I56 | J57: =J58-J56 | K57: =K58-K56 | L57: =L58-L56 | M57: =M58-M56 | N57: =N58-N56 | ... AO57: =AO58-AO56
A58: Domestic Paid EOP Streaming Memberships, 000s | F58: 25471 | G58: 27913 | H58: 28624 | I58: 29925 | J58: =K58 | K58: 31712 | L58: 34377 | M58: 35085 | N58: 36265 | O58: =P58 | P58: 37698 | Q58: 40315 | R58: 41057 | S58: 42068 | T58: 43401 | U58: 43401 | V58: 45714 | W58: 46004 | X58: 46479 | Y58: =Z58 | Z58: 47905 | AA58: 49375 | AB58: 50323 | AC58: 51345 | AD58: =AE58 | AE58: 52810 | AF58: 55087 | AG58: 55959 | AH58: 56957 | AI58: =AJ58 | AJ58: 58486 | AK58: 60229 | AL58: 60103 | AM58: 60620 | AN58: =AO58 | AO58: 61043
A59: Average Domestic Paid Streaming Memberships in period, 000s | G59: =AVERAGE(G56,G58) | H59: =AVERAGE(H56,H58) | I59: =AVERAGE(I56,I58) | J59: =AVERAGE(J56,J58) | K59: =AVERAGE(K56,K58) | L59: =AVERAGE(L56,L58) | M59: =AVERAGE(M56,M58) | N59: =AVERAGE(N56,N58) | ... AO59: =AVERAGE(AO56,AO58)
A61: International Paid BOP Streaming Memberships, 000s | G61: =F63 | H61: =G63 | I61: =H63 | J61: =I63 | K61: =F63 | L61: =K63 | M61: =L63 | N61: =M63 | O61: =N63 | P61: =K63 | Q61: =P63 | R61: =Q63 | S61: =R63 | T61: =S63 | U61: =P63 | V61: =U63 | W61: =V63 | X61: =W63 | Y61: =X63 | Z61: =U63 | AA61: =Z63 | AB61: =AA63 | AC61: =AB63 | AD61: =AC63 | AE61: =Z63 | AF61: =AE63 | AG61: =AF63 | AH61: =AG63 | AI61: =AH63 | AJ61: =AE63 | AK61: =AJ63 | AL61: =AK63 | AM61: =AL63 | AN61: =AM63 | AO61: =AJ63
A62: Net International Paid Streaming Memberships Change, 000s | G62: =G63-G61 | H62: =H63-H61 | I62: =I63-I61 | J62: =J63-J61 | K62: =K63-K61 | L62: =L63-L61 | M62: =M63-M61 | N62: =N63-N61 | ... AO62: =AO63-AO61
A63: International Paid EOP Streaming Memberships, 000s | F63: 4892 | G63: 6331 | H63: 7014 | I63: 8084 | J63: =K63 | K63: 9722 | L63: 11755 | M63: 12907 | N63: 14389 | O63: =P63 | P63: 16778 | Q63: 19304 | R63: 21649 | S63: 23951 | T63: 27438 | U63: 27438 | V63: 31993 | W63: 33892 | X63: 36799 | Y63: =Z63 | Z63: 41185 | AA63: 44988 | AB63: 48713 | AC63: 52678 | AD63: =AE63 | AE63: 57834 | AF63: 63815 | AG63: 68395 | AH63: 73465 | AI63: =AJ63 | AJ63: 80773 | AK63: 88634 | AL63: 91459 | AM63: 97714 | AN63: =AO63 | AO63: 106047
A64: Average International Paid Streaming Memberships in period, 000s | G64: =AVERAGE(G61,G63) | H64: =AVERAGE(H61,H63) | I64: =AVERAGE(I61,I63) | J64: =AVERAGE(J61,J63) | K64: =AVERAGE(K61,K63) | L64: =AVERAGE(L61,L63) | M64: =AVERAGE(M61,M63) | N64: =AVERAGE(N61,N63) | ... AO64: =AVERAGE(AO61,AO63)
A66: International Streaming Monthly ARPU, $/Member | F66: ='Supplemental Data'!F28*1000/F63/12 | G66: ='Supplemental Data'!G28*1000/G64/3 | H66: ='Supplemental Data'!H28*1000/H64/3 | I66: ='Supplemental Data'!I28*1000/I64/3 | J66: ='Supplemental Data'!J28*1000/J64/3 | K66: ='Supplemental Data'!K28*1000/K64/12 | L66: ='Supplemental Data'!L28*1000/L64/3 | M66: ='Supplemental Data'!M28*1000/M64/3 | N66: ='Supplemental Data'!N28*1000/N64/3 | O66: ='Supplemental Data'!O28*1000/O64/3 | P66: ='Supplemental Data'!P28*1000/P64/12 | Q66: ='Supplemental Data'!Q28*1000/Q64/3 | R66: ='Supplemental Data'!R28*1000/R64/3 | S66: ='Supplemental Data'!S28*1000/S64/3 | T66: ='Supplemental Data'!T28*1000/T64/3 | U66: ='Supplemental Data'!U28*1000/U64/12 | V66: ='Supplemental Data'!V28*1000/V64/3 | W66: ='Supplemental Data'!W28*1000/W64/3 | X66: ='Supplemental Data'!X28*1000/X64/3 | Y66: ='Supplemental Data'!Y28*1000/Y64/3 | Z66: ='Supplemental Data'!Z28*1000/Z64/12 | AA66: ='Supplemental Data'!AA28*1000/AA64/3 | AB66: ='Supplemental Data'!AB28*1000/AB64/3 | AC66: ='Supplemental Data'!AC28*1000/AC64/3 | AD66: ='Supplemental Data'!AD28*1000/AD64/3 | AE66: ='Supplemental Data'!AE28*1000/AE64/12 | AF66: ='Supplemental Data'!AF28*1000/AF64/3 | AG66: ='Supplemental Data'!AG28*1000/AG64/3 | AH66: ='Supplemental Data'!AH28*1000/AH64/3 | AI66: ='Supplemental Data'!AI28*1000/AI64/3 | AJ66: ='Supplemental Data'!AJ28*1000/AJ64/12 | AK66: ='Supplemental Data'!AK28*1000/AK64/3 | AL66: ='Supplemental Data'!AL28*1000/AL64/3 | AM66: ='Supplemental Data'!AM28*1000/AM64/3 | AN66: ='Supplemental Data'!AN28*1000/AN64/3 | AO66: ='Supplemental Data'!AO28*1000/AO64/12
A67: International Streaming monthly ARPU growth, % | K67: =K66/F66-1 | L67: =L66/G66-1 | M67: =M66/H66-1 | N67: =N66/I66-1 | O67: =O66/J66-1 | P67: =P66/K66-1 | Q67: =Q66/L66-1 | R67: =R66/M66-1 | ... AO67: =AO66/AJ66-1
A69: Domestic Paid BOP DVD Memberships, 000s | G69: =F71 | H69: =G71 | I69: =H71 | J69: =I71 | K69: =F71 | L69: =K71 | M69: =L71 | N69: =M71 | O69: =N71 | P69: =K71 | Q69: =P71 | R69: =Q71 | S69: =R71 | T69: =S71 | U69: =P71 | V69: =U71 | W69: =V71 | X69: =W71 | Y69: =X71 | Z69: =U71 | AA69: =Z71 | AB69: =AA71 | AC69: =AB71 | AD69: =AC71 | AE69: =Z71 | AF69: =AE71 | AG69: =AF71 | AH69: =AG71 | AI69: =AH71 | AJ69: =AE71 | AK69: =AJ71 | AL69: =AK71 | AM69: =AL71 | AN69: =AM71 | AO69: =AJ71
A70: Net Domestic Paid DVD Memberships Change, 000s | G70: =G71-G69 | H70: =H71-H69 | I70: =I71-I69 | J70: =J71-J69 | K70: =K71-K69 | L70: =L71-L69 | M70: =M71-M69 | N70: =N71-N69 | ... AO70: =AO71-AO69
A71: Domestic Paid EOP DVD Memberships, 000s | F71: 8049 | G71: 7827 | H71: 7369 | I71: 7148 | J71: =K71 | K71: 6765 | L71: 6509 | M71: 6167 | N71: 5899 | O71: =P71 | P71: 5668 | Q71: 5470 | R71: 5219 | S71: 4971 | T71: 4787 | U71: 4787 | V71: 4647 | W71: 4435 | X71: 4194 | Y71: =Z71 | Z71: 4029 | AA71: 3867 | AB71: 3692 | AC71: 3520 | AD71: =AE71 | AE71: 3330 | AF71: 3138 | AG71: 2971 | AH71: 2828 | AI71: =AJ71 | AJ71: 2706 | AK71: 2565 | AL71: 2411 | AM71: 2276 | AN71: =AO71 | AO71: 2153
A72: Average Domestic Paid DVD Memberships in period, 000s | G72: =AVERAGE(G69,G71) | H72: =AVERAGE(H69,H71) | I72: =AVERAGE(I69,I71) | J72: =AVERAGE(J69,J71) | K72: =AVERAGE(K69,K71) | L72: =AVERAGE(L69,L71) | M72: =AVERAGE(M69,M71) | N72: =AVERAGE(N69,N71) | ... AO72: =AVERAGE(AO69,AO71)
A74: Domestic DVD ARPU, $/Member | G74: =G30*1000/G72/3 | H74: =H30*1000/H72/3 | I74: =I30*1000/I72/3 | J74: =J30*1000/J72/3 | K74: =AVERAGE(G74,H74,I74,J74) | L74: =L30*1000/L72/3 | M74: =M30*1000/M72/3 | N74: =N30*1000/N72/3 | O74: =O30*1000/O72/3 | P74: =AVERAGE(L74,M74,N74,O74) | Q74: =Q30*1000/Q72/3 | R74: =R30*1000/R72/3 | S74: =S30*1000/S72/3 | T74: =T30*1000/T72/3 | U74: =AVERAGE(Q74,R74,S74,T74) | V74: =V30*1000/V72/3 | W74: =W30*1000/W72/3 | X74: =X30*1000/X72/3 | Y74: =Y30*1000/Y72/3 | Z74: =AVERAGE(V74,W74,X74,Y74) | AA74: =AA30*1000/AA72/3 | AB74: =AB30*1000/AB72/3 | AC74: =AC30*1000/AC72/3 | AD74: =AD30*1000/AD72/3 | AE74: =AVERAGE(AA74,AB74,AC74,AD74) | AF74: =AF30*1000/AF72/3 | AG74: =AG30*1000/AG72/3 | AH74: =AH30*1000/AH72/3 | AI74: =AI30*1000/AI72/3 | AJ74: =AVERAGE(AF74,AG74,AH74,AI74) | AK74: =AK30*1000/AK72/3 | AL74: =AL30*1000/AL72/3 | AM74: =AM30*1000/AM72/3 | AN74: =AN30*1000/AN72/3 | AO74: =AVERAGE(AK74,AL74,AM74,AN74)
A75: Domestic DVD ARPU growth, % | L75: =+L74/G74-1 | M75: =+M74/H74-1 | N75: =+N74/I74-1 | O75: =+O74/J74-1 | P75: =+P74/K74-1 | Q75: =+Q74/L74-1 | R75: =+R74/M74-1 | S75: =+S74/N74-1 | ... AO75: =+AO74/AJ74-1
A77: Domestic free trials, 000s | AE77: 1940 | AF77: 1618 | AG77: 1420 | AH77: 1507 | AI77: 2065 | AJ77: =+AI77 | AK77: 1563 | AL77: 1575 | AM77: 1375 | AN77: 1405 | AO77: =AN77
A78: International free trials, 000s | AE78: 4998 | AF78: 4475 | AG78: 4367 | AH78: 5170 | AI78: 7131 | AJ78: =+AI78 | AK78: 5003 | AL78: 4481 | AM78: 4215 | AN78: 3274 | AO78: =AN78
A79: Domestic DVD free trials, 000s | AE79: 53 | AF79: 29 | AG79: 28 | AH79: 24 | AI79: 25 | AJ79: =+AI79 | AK79: 22 | AL79: 17 | AM79: 16 | AN79: 15 | AO79: =AN79
A80: Total free trials, 000s | AE80: =SUM(AE77:AE79) | AF80: =SUM(AF77:AF79) | AG80: =SUM(AG77:AG79) | AH80: =SUM(AH77:AH79) | AI80: =SUM(AI77:AI79) | AJ80: =SUM(AJ77:AJ79) | AK80: =SUM(AK77:AK79) | AL80: =SUM(AL77:AL79) | ... AO80: =SUM(AO77:AO79)
A82: Key Metrics - Content Assets Breakdown (FS) - (Historical)
A83: Licensed content net, mm | U83: 6827.119 | W83: 8349.966 | X83: 9248.12 | Y83: =Z83 | Z83: 9595.315 | AA83: 10330.305 | AB83: 11195.034 | AC83: 11462.217 | AD83: =AE83 | AE83: 11771.778 | AF83: 12508.344 | AG83: 13032.4 | AH83: 13458.275 | AI83: =AJ83 | AJ83: 14081.463
A84: Released less amortization, mm | U84: 61.515 | W84: 165.006 | X84: 194.621 | Y84: =Z84 | Z84: 335.4 | AA84: 473.054 | AB84: 861.967 | AC84: 984.945 | AD84: =AE84 | AE84: 1427.256 | AF84: 1643.252 | AG84: 1786.221 | AH84: 1946.994 | AI84: =AJ84 | AJ84: 2403.896
A85: In production, mm | U85: 279.013 | W85: 529.077 | X85: 802.552 | Y85: =Z85 | Z85: 1010.463 | AA85: 1146.982 | AB85: 1057.283 | AC85: 1338.208 | AD85: =AE85 | AE85: 1311.137 | AF85: 1613.898 | AG85: 2085.501 | AH85: 2757.434 | AI85: =AJ85 | AJ85: 3305.126
A86: In development and production, mm | U86: 24.651 | W86: 21.411 | X86: 40.154 | Y86: =Z86 | Z86: 34.215 | AA86: 82.98 | AB86: 95.24 | AC86: 163.393 | AD86: =AE86 | AE86: 158.517 | AF86: 161.497 | AG86: 179.06 | AH86: 222.885 | AI86: =AJ86 | AJ86: 311.842
A87: Produced content net, mm | U87: =SUM(U84:U86) | V87: =SUM(V84:V86) | W87: =SUM(W84:W86) | X87: =SUM(X84:X86) | Y87: =SUM(Y84:Y86) | Z87: =SUM(Z84:Z86) | AA87: =SUM(AA84:AA86) | AB87: =SUM(AB84:AB86) | ... AJ87: =SUM(AJ84:AJ86)
A88: DVD net, mm | U88: 26.517 | W88: 26.74 | X88: 24.626 | Y88: =Z88 | Z88: 25.415 | AA88: 22.406 | AB88: 18.061 | AC88: 14.328 | AD88: =AE88 | AE88: 13.301 | AF88: 14.334 | AG88: 12.551 | AH88: 10.771 | AI88: =AJ88 | AJ88: 9.813
A89: Total Content Assets, mm | U89: =U87+U88+U83 | V89: =V87+V88+V83 | W89: =W87+W88+W83 | X89: =X87+X88+X83 | Y89: =Y87+Y88+Y83 | Z89: =Z87+Z88+Z83 | AA89: =AA87+AA88+AA83 | AB89: =AB87+AB88+AB83 | ... AJ89: =AJ87+AJ88+AJ83

Sheet Guidance
B1: =MO.CompanyName
B2: Most Recent Period: | F2: =MO.MRFP
I4: Guidance | M4: Model | P4: Difference vs. Mid | S4: Update Log
B5: Type | D5: Item | E5: Item Name | F5: Fiscal Period | G5: Base Period | I5: Low | J5: High | K5: Mid | M5: Type | N5: Output | P5: Absolute | Q5: Relative | S5: Date | T5: Link
A6: 427 | B6: =IF(INDEX(MO_SNA_IsHistoricalPeriod,,MATCH(F6,MO_Common_ColumnHeader,0)),"Historical","Forward") | D6: =INDEX(INDIRECT(E6),0,COLUMN(MO_Common_Column_A)) | E6: MO_RIS_REV | F6: FY2026 | I6: 50700 | J6: 51700 | K6: =AVERAGE(I6:J6) | M6: =IF(INDEX(MO_SNA_IsHistoricalPeriod,,MATCH(F6,MO_Common_ColumnHeader,0)),"Actual","Estimate") | N6: =IFERROR(INDEX(INDIRECT(E6),0,MATCH(F6,MO_Common_ColumnHeader,0)),"N/A") | P6: =IF(ISNUMBER(N6),N6-K6,"N/A") | Q6: =IFERROR(IF(ISNUMBER(N6),(N6-K6)/ABS(K6),"N/A"),"N/A") | S6: 46128 | T6: Letter to Shareholders
A7: 426 | B7: =IF(INDEX(MO_SNA_IsHistoricalPeriod,,MATCH(F7,MO_Common_ColumnHeader,0)),"Historical","Forward") | D7: =INDEX(INDIRECT(E7),0,COLUMN(MO_Common_Column_A)) | E7: MO_GA_TotalRevenue | F7: FY2026 | I7: 0.12 | J7: 0.14 | K7: =AVERAGE(I7:J7) | M7: =IF(INDEX(MO_SNA_IsHistoricalPeriod,,MATCH(F7,MO_Common_ColumnHeader,0)),"Actual","Estimate") | N7: =IFERROR(INDEX(INDIRECT(E7),0,MATCH(F7,MO_Common_ColumnHeader,0)),"N/A") | P7: =IF(ISNUMBER(N7),N7-K7,"N/A") | Q7: =IFERROR(IF(ISNUMBER(N7),(N7-K7)/ABS(K7),"N/A"),"N/A") | S7: 46128 | T7: Letter to Shareholders
A8: 425 | B8: =IF(INDEX(MO_SNA_IsHistoricalPeriod,,MATCH(F8,MO_Common_ColumnHeader,0)),"Historical","Forward") | D8: =INDEX(INDIRECT(E8),0,COLUMN(MO_Common_Column_A)) | E8: MO_GA_REV_ConstantCurrency | F8: FY2026 | I8: 0.11 | J8: 0.13 | K8: =AVERAGE(I8:J8) | M8: =IF(INDEX(MO_SNA_IsHistoricalPeriod,,MATCH(F8,MO_Common_ColumnHeader,0)),"Actual","Estimate") | N8: =IF(B8="Historical",IFERROR(INDEX(INDIRECT(E8),0,MATCH(F8,MO_Common_ColumnHeader,0)),"N/A"),"N/A") | P8: =IF(ISNUMBER(N8),N8-K8,"N/A") | Q8: =IFERROR(IF(ISNUMBER(N8),(N8-K8)/ABS(K8),"N/A"),"N/A") | S8: 46128 | T8: Letter to Shareholders
A9: 424 | B9: =IF(INDEX(MO_SNA_IsHistoricalPeriod,,MATCH(F9,MO_Common_ColumnHeader,0)),"Historical","Forward") | D9: Operating Margin | E9: MO_MA_EBIT | F9: FY2026 | I9: 0.315 | J9: 0.315 | K9: =AVERAGE(I9:J9) | M9: =IF(INDEX(MO_SNA_IsHistoricalPeriod,,MATCH(F9,MO_Common_ColumnHeader,0)),"Actual","Estimate") | N9: =IFERROR(INDEX(INDIRECT(E9),0,MATCH(F9,MO_Common_ColumnHeader,0)),"N/A") | P9: =IF(ISNUMBER(N9),N9-K9,"N/A") | Q9: =IFERROR(IF(ISNUMBER(N9),(N9-K9)/ABS(K9),"N/A"),"N/A") | S9: 46128 | T9: Letter to Shareholders
A10: 423
A11: 422 | B11: =IF(INDEX(MO_SNA_IsHistoricalPeriod,,MATCH(F11,MO_Common_ColumnHeader,0)),"Historical","Forward") | D11: =INDEX(INDIRECT(E11),0,COLUMN(MO_Common_Column_A)) | E11: MO_RIS_REV | F11: Q2-2026 | I11: 12574 | J11: 12574 | K11: =AVERAGE(I11:J11) | M11: =IF(INDEX(MO_SNA_IsHistoricalPeriod,,MATCH(F11,MO_Common_ColumnHeader,0)),"Actual","Estimate") | N11: =IFERROR(INDEX(INDIRECT(E11),0,MATCH(F11,MO_Common_ColumnHeader,0)),"N/A") | P11: =IF(ISNUMBER(N11),N11-K11,"N/A") | Q11: =IFERROR(IF(ISNUMBER(N11),(N11-K11)/ABS(K11),"N/A"),"N/A") | S11: 46128 | T11: Letter to Shareholders
A12: 421 | B12: =IF(INDEX(MO_SNA_IsHistoricalPeriod,,MATCH(F12,MO_Common_ColumnHeader,0)),"Historical","Forward") | D12: =INDEX(INDIRECT(E12),0,COLUMN(MO_Common_Column_A)) | E12: MO_GA_TotalRevenue | F12: Q2-2026 | I12: 0.135 | J12: 0.135 | K12: =AVERAGE(I12:J12) | M12: =IF(INDEX(MO_SNA_IsHistoricalPeriod,,MATCH(F12,MO_Common_ColumnHeader,0)),"Actual","Estimate") | N12: =IFERROR(INDEX(INDIRECT(E12),0,MATCH(F12,MO_Common_ColumnHeader,0)),"N/A") | P12: =IF(ISNUMBER(N12),N12-K12,"N/A") | Q12: =IFERROR(IF(ISNUMBER(N12),(N12-K12)/ABS(K12),"N/A"),"N/A") | S12: 46128 | T12: Letter to Shareholders
A13: 420 | B13: =IF(INDEX(MO_SNA_IsHistoricalPeriod,,MATCH(F13,MO_Common_ColumnHeader,0)),"Historical","Forward") | D13: =INDEX(INDIRECT(E13),0,COLUMN(MO_Common_Column_A)) | E13: MO_GA_REV_ConstantCurrency | F13: Q2-2026 | I13: 0.12 | J13: 0.12 | K13: =AVERAGE(I13:J13) | M13: =IF(INDEX(MO_SNA_IsHistoricalPeriod,,MATCH(F13,MO_Common_ColumnHeader,0)),"Actual","Estimate") | N13: =IF(B13="Historical",IFERROR(INDEX(INDIRECT(E13),0,MATCH(F13,MO_Common_ColumnHeader,0)),"N/A"),"N/A") | P13: =IF(ISNUMBER(N13),N13-K13,"N/A") | Q13: =IFERROR(IF(ISNUMBER(N13),(N13-K13)/ABS(K13),"N/A"),"N/A") | S13: 46128 | T13: Letter to Shareholders
A14: 419 | B14: =IF(INDEX(MO_SNA_IsHistoricalPeriod,,MATCH(F14,MO_Common_ColumnHeader,0)),"Historical","Forward") | D14: =INDEX(INDIRECT(E14),0,COLUMN(MO_Common_Column_A)) | E14: MO_RIS_EBIT | F14: Q2-2026 | I14: 4105 | J14: 4105 | K14: =AVERAGE(I14:J14) | M14: =IF(INDEX(MO_SNA_IsHistoricalPeriod,,MATCH(F14,MO_Common_ColumnHeader,0)),"Actual","Estimate") | N14: =IFERROR(INDEX(INDIRECT(E14),0,MATCH(F14,MO_Common_ColumnHeader,0)),"N/A") | P14: =IF(ISNUMBER(N14),N14-K14,"N/A") | Q14: =IFERROR(IF(ISNUMBER(N14),(N14-K14)/ABS(K14),"N/A"),"N/A") | S14: 46128 | T14: Letter to Shareholders
A15: 418 | B15: =IF(INDEX(MO_SNA_IsHistoricalPeriod,,MATCH(F15,MO_Common_ColumnHeader,0)),"Historical","Forward") | D15: Operating Margin | E15: MO_MA_EBIT | F15: Q2-2026 | I15: 0.326 | J15: 0.326 | K15: =AVERAGE(I15:J15) | M15: =IF(INDEX(MO_SNA_IsHistoricalPeriod,,MATCH(F15,MO_Common_ColumnHeader,0)),"Actual","Estimate") | N15: =IFERROR(INDEX(INDIRECT(E15),0,MATCH(F15,MO_Common_ColumnHeader,0)),"N/A") | P15: =IF(ISNUMBER(N15),N15-K15,"N/A") | Q15: =IFERROR(IF(ISNUMBER(N15),(N15-K15)/ABS(K15),"N/A"),"N/A") | S15: 46128 | T15: Letter to Shareholders
A16: 417 | B16: =IF(INDEX(MO_SNA_IsHistoricalPeriod,,MATCH(F16,MO_Common_ColumnHeader,0)),"Historical","Forward") | D16: =INDEX(INDIRECT(E16),0,COLUMN(MO_Common_Column_A)) | E16: MO_RIS_NI_GAAP_Basic | F16: Q2-2026 | I16: 3327 | J16: 3327 | K16: =AVERAGE(I16:J16) | M16: =IF(INDEX(MO_SNA_IsHistoricalPeriod,,MATCH(F16,MO_Common_ColumnHeader,0)),"Actual","Estimate") | N16: =IFERROR(INDEX(INDIRECT(E16),0,MATCH(F16,MO_Common_ColumnHeader,0)),"N/A") | P16: =IF(ISNUMBER(N16),N16-K16,"N/A") | Q16: =IFERROR(IF(ISNUMBER(N16),(N16-K16)/ABS(K16),"N/A"),"N/A") | S16: 46128 | T16: Letter to Shareholders
A17: 416 | B17: =IF(INDEX(MO_SNA_IsHistoricalPeriod,,MATCH(F17,MO_Common_ColumnHeader,0)),"Historical","Forward") | D17: =INDEX(INDIRECT(E17),0,COLUMN(MO_Common_Column_A)) | E17: MO_RIS_EPS_WAD | F17: Q2-2026 | I17: 0.78 | J17: 0.78 | K17: =AVERAGE(I17:J17) | M17: =IF(INDEX(MO_SNA_IsHistoricalPeriod,,MATCH(F17,MO_Common_ColumnHeader,0)),"Actual","Estimate") | N17: =IFERROR(INDEX(INDIRECT(E17),0,MATCH(F17,MO_Common_ColumnHeader,0)),"N/A") | P17: =IF(ISNUMBER(N17),N17-K17,"N/A") | Q17: =IFERROR(IF(ISNUMBER(N17),(N17-K17)/ABS(K17),"N/A"),"N/A") | S17: 46128 | T17: Letter to Shareholders
A18: 415
A19: 414 | B19: =IF(INDEX(MO_SNA_IsHistoricalPeriod,,MATCH(F19,MO_Common_ColumnHeader,0)),"Historical","Forward") | D19: =INDEX(INDIRECT(E19),0,COLUMN(MO_Common_Column_A)) | E19: MO_RIS_REV | F19: FY2026 | I19: 50700 | J19: 51700 | K19: =AVERAGE(I19:J19) | M19: =IF(INDEX(MO_SNA_IsHistoricalPeriod,,MATCH(F19,MO_Common_ColumnHeader,0)),"Actual","Estimate") | N19: =IFERROR(INDEX(INDIRECT(E19),0,MATCH(F19,MO_Common_ColumnHeader,0)),"N/A") | P19: =IF(ISNUMBER(N19),N19-K19,"N/A") | Q19: =IFERROR(IF(ISNUMBER(N19),(N19-K19)/ABS(K19),"N/A"),"N/A") | S19: 46042 | T19: Letter to Shareholders
A20: 413 | B20: =IF(INDEX(MO_SNA_IsHistoricalPeriod,,MATCH(F20,MO_Common_ColumnHeader,0)),"Historical","Forward") | D20: =INDEX(INDIRECT(E20),0,COLUMN(MO_Common_Column_A)) | E20: MO_GA_TotalRevenue | F20: FY2026 | I20: 0.12 | J20: 0.14 | K20: =AVERAGE(I20:J20) | M20: =IF(INDEX(MO_SNA_IsHistoricalPeriod,,MATCH(F20,MO_Common_ColumnHeader,0)),"Actual","Estimate") | N20: =IFERROR(INDEX(INDIRECT(E20),0,MATCH(F20,MO_Common_ColumnHeader,0)),"N/A") | P20: =IF(ISNUMBER(N20),N20-K20,"N/A") | Q20: =IFERROR(IF(ISNUMBER(N20),(N20-K20)/ABS(K20),"N/A"),"N/A") | S20: 46042 | T20: Letter to Shareholders
A21: 412 | B21: =IF(INDEX(MO_SNA_IsHistoricalPeriod,,MATCH(F21,MO_Common_ColumnHeader,0)),"Historical","Forward") | D21: =INDEX(INDIRECT(E21),0,COLUMN(MO_Common_Column_A)) | E21: MO_GA_REV_ConstantCurrency | F21: FY2026 | I21: 0.11 | J21: 0.13 | K21: =AVERAGE(I21:J21) | M21: =IF(INDEX(MO_SNA_IsHistoricalPeriod,,MATCH(F21,MO_Common_ColumnHeader,0)),"Actual","Estimate") | N21: =IF(B21="Historical",IFERROR(INDEX(INDIRECT(E21),0,MATCH(F21,MO_Common_ColumnHeader,0)),"N/A"),"N/A") | P21: =IF(ISNUMBER(N21),N21-K21,"N/A") | Q21: =IFERROR(IF(ISNUMBER(N21),(N21-K21)/ABS(K21),"N/A"),"N/A") | S21: 46042 | T21: Letter to Shareholders
A22: 411 | B22: =IF(INDEX(MO_SNA_IsHistoricalPeriod,,MATCH(F22,MO_Common_ColumnHeader,0)),"Historical","Forward") | D22: Operating Margin | E22: MO_MA_EBIT | F22: FY2026 | I22: 0.315 | J22: 0.315 | K22: =AVERAGE(I22:J22) | M22: =IF(INDEX(MO_SNA_IsHistoricalPeriod,,MATCH(F22,MO_Common_ColumnHeader,0)),"Actual","Estimate") | N22: =IFERROR(INDEX(INDIRECT(E22),0,MATCH(F22,MO_Common_ColumnHeader,0)),"N/A") | P22: =IF(ISNUMBER(N22),N22-K22,"N/A") | Q22: =IFERROR(IF(ISNUMBER(N22),(N22-K22)/ABS(K22),"N/A"),"N/A") | S22: 46042 | T22: Letter to Shareholders
A23: 410
A24: 409 | B24: =IF(INDEX(MO_SNA_IsHistoricalPeriod,,MATCH(F24,MO_Common_ColumnHeader,0)),"Historical","Forward") | D24: =INDEX(INDIRECT(E24),0,COLUMN(MO_Common_Column_A)) | E24: MO_RIS_REV | F24: Q1-2026 | I24: 12157 | J24: 12157 | K24: =AVERAGE(I24:J24) | M24: =IF(INDEX(MO_SNA_IsHistoricalPeriod,,MATCH(F24,MO_Common_ColumnHeader,0)),"Actual","Estimate") | N24: =IFERROR(INDEX(INDIRECT(E24),0,MATCH(F24,MO_Common_ColumnHeader,0)),"N/A") | P24: =IF(ISNUMBER(N24),N24-K24,"N/A") | Q24: =IFERROR(IF(ISNUMBER(N24),(N24-K24)/ABS(K24),"N/A"),"N/A") | S24: 46042 | T24: Letter to Shareholders
A25: 408 | B25: =IF(INDEX(MO_SNA_IsHistoricalPeriod,,MATCH(F25,MO_Common_ColumnHeader,0)),"Historical","Forward") | D25: =INDEX(INDIRECT(E25),0,COLUMN(MO_Common_Column_A)) | E25: MO_GA_TotalRevenue | F25: Q1-2026 | I25: 0.153 | J25: 0.153 | K25: =AVERAGE(I25:J25) | M25: =IF(INDEX(MO_SNA_IsHistoricalPeriod,,MATCH(F25,MO_Common_ColumnHeader,0)),"Actual","Estimate") | N25: =IFERROR(INDEX(INDIRECT(E25),0,MATCH(F25,MO_Common_ColumnHeader,0)),"N/A") | P25: =IF(ISNUMBER(N25),N25-K25,"N/A") | Q25: =IFERROR(IF(ISNUMBER(N25),(N25-K25)/ABS(K25),"N/A"),"N/A") | S25: 46042 | T25: Letter to Shareholders
A26: 407 | B26: =IF(INDEX(MO_SNA_IsHistoricalPeriod,,MATCH(F26,MO_Common_ColumnHeader,0)),"Historical","Forward") | D26: =INDEX(INDIRECT(E26),0,COLUMN(MO_Common_Column_A)) | E26: MO_RIS_EBIT | F26: Q1-2026 | I26: 3906 | J26: 3906 | K26: =AVERAGE(I26:J26) | M26: =IF(INDEX(MO_SNA_IsHistoricalPeriod,,MATCH(F26,MO_Common_ColumnHeader,0)),"Actual","Estimate") | N26: =IFERROR(INDEX(INDIRECT(E26),0,MATCH(F26,MO_Common_ColumnHeader,0)),"N/A") | P26: =IF(ISNUMBER(N26),N26-K26,"N/A") | Q26: =IFERROR(IF(ISNUMBER(N26),(N26-K26)/ABS(K26),"N/A"),"N/A") | S26: 46042 | T26: Letter to Shareholders
A27: 406 | B27: =IF(INDEX(MO_SNA_IsHistoricalPeriod,,MATCH(F27,MO_Common_ColumnHeader,0)),"Historical","Forward") | D27: Operating Margin | E27: MO_MA_EBIT | F27: Q1-2026 | I27: 0.321 | J27: 0.321 | K27: =AVERAGE(I27:J27) | M27: =IF(INDEX(MO_SNA_IsHistoricalPeriod,,MATCH(F27,MO_Common_ColumnHeader,0)),"Actual","Estimate") | N27: =IFERROR(INDEX(INDIRECT(E27),0,MATCH(F27,MO_Common_ColumnHeader,0)),"N/A") | P27: =IF(ISNUMBER(N27),N27-K27,"N/A") | Q27: =IFERROR(IF(ISNUMBER(N27),(N27-K27)/ABS(K27),"N/A"),"N/A") | S27: 46042 | T27: Letter to Shareholders
A28: 405 | B28: =IF(INDEX(MO_SNA_IsHistoricalPeriod,,MATCH(F28,MO_Common_ColumnHeader,0)),"Historical","Forward") | D28: =INDEX(INDIRECT(E28),0,COLUMN(MO_Common_Column_A)) | E28: MO_RIS_NI_GAAP_Basic | F28: Q1-2026 | I28: 3264 | J28: 3264 | K28: =AVERAGE(I28:J28) | M28: =IF(INDEX(MO_SNA_IsHistoricalPeriod,,MATCH(F28,MO_Common_ColumnHeader,0)),"Actual","Estimate") | N28: =IFERROR(INDEX(INDIRECT(E28),0,MATCH(F28,MO_Common_ColumnHeader,0)),"N/A") | P28: =IF(ISNUMBER(N28),N28-K28,"N/A") | Q28: =IFERROR(IF(ISNUMBER(N28),(N28-K28)/ABS(K28),"N/A"),"N/A") | S28: 46042 | T28: Letter to Shareholders
A29: 404 | B29: =IF(INDEX(MO_SNA_IsHistoricalPeriod,,MATCH(F29,MO_Common_ColumnHeader,0)),"Historical","Forward") | D29: =INDEX(INDIRECT(E29),0,COLUMN(MO_Common_Column_A)) | E29: MO_RIS_EPS_WAD | F29: Q1-2026 | I29: 0.76 | J29: 0.76 | K29: =AVERAGE(I29:J29) | M29: =IF(INDEX(MO_SNA_IsHistoricalPeriod,,MATCH(F29,MO_Common_ColumnHeader,0)),"Actual","Estimate") | N29: =IFERROR(INDEX(INDIRECT(E29),0,MATCH(F29,MO_Common_ColumnHeader,0)),"N/A") | P29: =IF(ISNUMBER(N29),N29-K29,"N/A") | Q29: =IFERROR(IF(ISNUMBER(N29),(N29-K29)/ABS(K29),"N/A"),"N/A") | S29: 46042 | T29: Letter to Shareholders
A30: 403
A31: 402 | B31: =IF(INDEX(MO_SNA_IsHistoricalPeriod,,MATCH(F31,MO_Common_ColumnHeader,0)),"Historical","Forward") | D31: =INDEX(INDIRECT(E31),0,COLUMN(MO_Common_Column_A)) | E31: MO_RIS_REV | F31: FY2025 | I31: 45100 | J31: 45100 | K31: =AVERAGE(I31:J31) | M31: =IF(INDEX(MO_SNA_IsHistoricalPeriod,,MATCH(F31,MO_Common_ColumnHeader,0)),"Actual","Estimate") | N31: =IFERROR(INDEX(INDIRECT(E31),0,MATCH(F31,MO_Common_ColumnHeader,0)),"N/A") | P31: =IF(ISNUMBER(N31),N31-K31,"N/A") | Q31: =IFERROR(IF(ISNUMBER(N31),(N31-K31)/ABS(K31),"N/A"),"N/A") | S31: 45951 | T31: Letter to Shareholders
A32: 401 | B32: =IF(INDEX(MO_SNA_IsHistoricalPeriod,,MATCH(F32,MO_Common_ColumnHeader,0)),"Historical","Forward") | D32: =INDEX(INDIRECT(E32),0,COLUMN(MO_Common_Column_A)) | E32: MO_GA_TotalRevenue | F32: FY2025 | I32: 0.16 | J32: 0.16 | K32: =AVERAGE(I32:J32) | M32: =IF(INDEX(MO_SNA_IsHistoricalPeriod,,MATCH(F32,MO_Common_ColumnHeader,0)),"Actual","Estimate") | N32: =IFERROR(INDEX(INDIRECT(E32),0,MATCH(F32,MO_Common_ColumnHeader,0)),"N/A") | P32: =IF(ISNUMBER(N32),N32-K32,"N/A") | Q32: =IFERROR(IF(ISNUMBER(N32),(N32-K32)/ABS(K32),"N/A"),"N/A") | S32: 45951 | T32: Letter to Shareholders
A33: 400 | B33: =IF(INDEX(MO_SNA_IsHistoricalPeriod,,MATCH(F33,MO_Common_ColumnHeader,0)),"Historical","Forward") | D33: =INDEX(INDIRECT(E33),0,COLUMN(MO_Common_Column_A)) | E33: MO_GA_REV_ConstantCurrency | F33: FY2025 | I33: 0.17 | J33: 0.17 | K33: =AVERAGE(I33:J33) | M33: =IF(INDEX(MO_SNA_IsHistoricalPeriod,,MATCH(F33,MO_Common_ColumnHeader,0)),"Actual","Estimate") | N33: =IF(B33="Historical",IFERROR(INDEX(INDIRECT(E33),0,MATCH(F33,MO_Common_ColumnHeader,0)),"N/A"),"N/A") | P33: =IF(ISNUMBER(N33),N33-K33,"N/A") | Q33: =IFERROR(IF(ISNUMBER(N33),(N33-K33)/ABS(K33),"N/A"),"N/A") | S33: 45951 | T33: Letter to Shareholders
A34: 399 | B34: =IF(INDEX(MO_SNA_IsHistoricalPeriod,,MATCH(F34,MO_Common_ColumnHeader,0)),"Historical","Forward") | D34: Operating Margin | E34: MO_MA_EBIT | F34: FY2025 | I34: 0.29 | J34: 0.29 | K34: =AVERAGE(I34:J34) | M34: =IF(INDEX(MO_SNA_IsHistoricalPeriod,,MATCH(F34,MO_Common_ColumnHeader,0)),"Actual","Estimate") | N34: =IFERROR(INDEX(INDIRECT(E34),0,MATCH(F34,MO_Common_ColumnHeader,0)),"N/A") | P34: =IF(ISNUMBER(N34),N34-K34,"N/A") | Q34: =IFERROR(IF(ISNUMBER(N34),(N34-K34)/ABS(K34),"N/A"),"N/A") | S34: 45951 | T34: Letter to Shareholders
A35: 398
A36: 397 | B36: =IF(INDEX(MO_SNA_IsHistoricalPeriod,,MATCH(F36,MO_Common_ColumnHeader,0)),"Historical","Forward") | D36: =INDEX(INDIRECT(E36),0,COLUMN(MO_Common_Column_A)) | E36: MO_RIS_REV | F36: Q4-2025 | I36: 11960 | J36: 11960 | K36: =AVERAGE(I36:J36) | M36: =IF(INDEX(MO_SNA_IsHistoricalPeriod,,MATCH(F36,MO_Common_ColumnHeader,0)),"Actual","Estimate") | N36: =IFERROR(INDEX(INDIRECT(E36),0,MATCH(F36,MO_Common_ColumnHeader,0)),"N/A") | P36: =IF(ISNUMBER(N36),N36-K36,"N/A") | Q36: =IFERROR(IF(ISNUMBER(N36),(N36-K36)/ABS(K36),"N/A"),"N/A") | S36: 45951 | T36: Letter to Shareholders
A37: 396 | B37: =IF(INDEX(MO_SNA_IsHistoricalPeriod,,MATCH(F37,MO_Common_ColumnHeader,0)),"Historical","Forward") | D37: =INDEX(INDIRECT(E37),0,COLUMN(MO_Common_Column_A)) | E37: MO_GA_TotalRevenue | F37: Q4-2025 | I37: 0.167 | J37: 0.167 | K37: =AVERAGE(I37:J37) | M37: =IF(INDEX(MO_SNA_IsHistoricalPeriod,,MATCH(F37,MO_Common_ColumnHeader,0)),"Actual","Estimate") | N37: =IFERROR(INDEX(INDIRECT(E37),0,MATCH(F37,MO_Common_ColumnHeader,0)),"N/A") | P37: =IF(ISNUMBER(N37),N37-K37,"N/A") | Q37: =IFERROR(IF(ISNUMBER(N37),(N37-K37)/ABS(K37),"N/A"),"N/A") | S37: 45951 | T37: Letter to Shareholders
A38: 395 | B38: =IF(INDEX(MO_SNA_IsHistoricalPeriod,,MATCH(F38,MO_Common_ColumnHeader,0)),"Historical","Forward") | D38: =INDEX(INDIRECT(E38),0,COLUMN(MO_Common_Column_A)) | E38: MO_GA_REV_ConstantCurrency | F38: Q4-2025 | I38: 0.16 | J38: 0.16 | K38: =AVERAGE(I38:J38) | M38: =IF(INDEX(MO_SNA_IsHistoricalPeriod,,MATCH(F38,MO_Common_ColumnHeader,0)),"Actual","Estimate") | N38: =IF(B38="Historical",IFERROR(INDEX(INDIRECT(E38),0,MATCH(F38,MO_Common_ColumnHeader,0)),"N/A"),"N/A") | P38: =IF(ISNUMBER(N38),N38-K38,"N/A") | Q38: =IFERROR(IF(ISNUMBER(N38),(N38-K38)/ABS(K38),"N/A"),"N/A") | S38: 45951 | T38: Letter to Shareholders
A39: 394 | B39: =IF(INDEX(MO_SNA_IsHistoricalPeriod,,MATCH(F39,MO_Common_ColumnHeader,0)),"Historical","Forward") | D39: =INDEX(INDIRECT(E39),0,COLUMN(MO_Common_Column_A)) | E39: MO_RIS_EBIT | F39: Q4-2025 | I39: 2860 | J39: 2860 | K39: =AVERAGE(I39:J39) | M39: =IF(INDEX(MO_SNA_IsHistoricalPeriod,,MATCH(F39,MO_Common_ColumnHeader,0)),"Actual","Estimate") | N39: =IFERROR(INDEX(INDIRECT(E39),0,MATCH(F39,MO_Common_ColumnHeader,0)),"N/A") | P39: =IF(ISNUMBER(N39),N39-K39,"N/A") | Q39: =IFERROR(IF(ISNUMBER(N39),(N39-K39)/ABS(K39),"N/A"),"N/A") | S39: 45951 | T39: Letter to Shareholders
A40: 393 | B40: =IF(INDEX(MO_SNA_IsHistoricalPeriod,,MATCH(F40,MO_Common_ColumnHeader,0)),"Historical","Forward") | D40: Operating Margin | E40: MO_MA_EBIT | F40: Q4-2025 | I40: 0.239 | J40: 0.239 | K40: =AVERAGE(I40:J40) | M40: =IF(INDEX(MO_SNA_IsHistoricalPeriod,,MATCH(F40,MO_Common_ColumnHeader,0)),"Actual","Estimate") | N40: =IFERROR(INDEX(INDIRECT(E40),0,MATCH(F40,MO_Common_ColumnHeader,0)),"N/A") | P40: =IF(ISNUMBER(N40),N40-K40,"N/A") | Q40: =IFERROR(IF(ISNUMBER(N40),(N40-K40)/ABS(K40),"N/A"),"N/A") | S40: 45951 | T40: Letter to Shareholders
A41: 392 | B41: =IF(INDEX(MO_SNA_IsHistoricalPeriod,,MATCH(F41,MO_Common_ColumnHeader,0)),"Historical","Forward") | D41: =INDEX(INDIRECT(E41),0,COLUMN(MO_Common_Column_A)) | E41: MO_RIS_NI_GAAP_Basic | F41: Q4-2025 | I41: 2355 | J41: 2355 | K41: =AVERAGE(I41:J41) | M41: =IF(INDEX(MO_SNA_IsHistoricalPeriod,,MATCH(F41,MO_Common_ColumnHeader,0)),"Actual","Estimate") | N41: =IFERROR(INDEX(INDIRECT(E41),0,MATCH(F41,MO_Common_ColumnHeader,0)),"N/A") | P41: =IF(ISNUMBER(N41),N41-K41,"N/A") | Q41: =IFERROR(IF(ISNUMBER(N41),(N41-K41)/ABS(K41),"N/A"),"N/A") | S41: 45951 | T41: Letter to Shareholders
A42: 391 | B42: =IF(INDEX(MO_SNA_IsHistoricalPeriod,,MATCH(F42,MO_Common_ColumnHeader,0)),"Historical","Forward") | D42: =INDEX(INDIRECT(E42),0,COLUMN(MO_Common_Column_A)) | E42: MO_RIS_EPS_WAD | F42: Q4-2025 | I42: 0.545 | J42: 0.545 | K42: =AVERAGE(I42:J42) | M42: =IF(INDEX(MO_SNA_IsHistoricalPeriod,,MATCH(F42,MO_Common_ColumnHeader,0)),"Actual","Estimate") | N42: =IFERROR(INDEX(INDIRECT(E42),0,MATCH(F42,MO_Common_ColumnHeader,0)),"N/A") | P42: =IF(ISNUMBER(N42),N42-K42,"N/A") | Q42: =IFERROR(IF(ISNUMBER(N42),(N42-K42)/ABS(K42),"N/A"),"N/A") | S42: 45951 | T42: Letter to Shareholders
A43: 390
A44: 389 | B44: =IF(INDEX(MO_SNA_IsHistoricalPeriod,,MATCH(F44,MO_Common_ColumnHeader,0)),"Historical","Forward") | D44: =INDEX(INDIRECT(E44),0,COLUMN(MO_Common_Column_A)) | E44: MO_RIS_REV | F44: FY2025 | I44: 44800 | J44: 45200 | K44: =AVERAGE(I44:J44) | M44: =IF(INDEX(MO_SNA_IsHistoricalPeriod,,MATCH(F44,MO_Common_ColumnHeader,0)),"Actual","Estimate") | N44: =IFERROR(INDEX(INDIRECT(E44),0,MATCH(F44,MO_Common_ColumnHeader,0)),"N/A") | P44: =IF(ISNUMBER(N44),N44-K44,"N/A") | Q44: =IFERROR(IF(ISNUMBER(N44),(N44-K44)/ABS(K44),"N/A"),"N/A") | S44: 45855 | T44: Letter to Shareholders
A45: 388 | B45: =IF(INDEX(MO_SNA_IsHistoricalPeriod,,MATCH(F45,MO_Common_ColumnHeader,0)),"Historical","Forward") | D45: =INDEX(INDIRECT(E45),0,COLUMN(MO_Common_Column_A)) | E45: MO_GA_TotalRevenue | F45: FY2025 | I45: 0.15 | J45: 0.16 | K45: =AVERAGE(I45:J45) | M45: =IF(INDEX(MO_SNA_IsHistoricalPeriod,,MATCH(F45,MO_Common_ColumnHeader,0)),"Actual","Estimate") | N45: =IFERROR(INDEX(INDIRECT(E45),0,MATCH(F45,MO_Common_ColumnHeader,0)),"N/A") | P45: =IF(ISNUMBER(N45),N45-K45,"N/A") | Q45: =IFERROR(IF(ISNUMBER(N45),(N45-K45)/ABS(K45),"N/A"),"N/A") | S45: 45855 | T45: Letter to Shareholders
A46: 387 | B46: =IF(INDEX(MO_SNA_IsHistoricalPeriod,,MATCH(F46,MO_Common_ColumnHeader,0)),"Historical","Forward") | D46: =INDEX(INDIRECT(E46),0,COLUMN(MO_Common_Column_A)) | E46: MO_GA_REV_ConstantCurrency | F46: FY2025 | I46: 0.16 | J46: 0.17 | K46: =AVERAGE(I46:J46) | M46: =IF(INDEX(MO_SNA_IsHistoricalPeriod,,MATCH(F46,MO_Common_ColumnHeader,0)),"Actual","Estimate") | N46: =IF(B46="Historical",IFERROR(INDEX(INDIRECT(E46),0,MATCH(F46,MO_Common_ColumnHeader,0)),"N/A"),"N/A") | P46: =IF(ISNUMBER(N46),N46-K46,"N/A") | Q46: =IFERROR(IF(ISNUMBER(N46),(N46-K46)/ABS(K46),"N/A"),"N/A") | S46: 45855 | T46: Letter to Shareholders
A47: 386 | B47: =IF(INDEX(MO_SNA_IsHistoricalPeriod,,MATCH(F47,MO_Common_ColumnHeader,0)),"Historical","Forward") | D47: Operating Margin | E47: MO_MA_EBIT | F47: FY2025 | I47: 0.295 | J47: 0.295 | K47: =AVERAGE(I47:J47) | M47: =IF(INDEX(MO_SNA_IsHistoricalPeriod,,MATCH(F47,MO_Common_ColumnHeader,0)),"Actual","Estimate") | N47: =IFERROR(INDEX(INDIRECT(E47),0,MATCH(F47,MO_Common_ColumnHeader,0)),"N/A") | P47: =IF(ISNUMBER(N47),N47-K47,"N/A") | Q47: =IFERROR(IF(ISNUMBER(N47),(N47-K47)/ABS(K47),"N/A"),"N/A") | S47: 45855 | T47: Letter to Shareholders
A48: 385
A49: 384 | B49: =IF(INDEX(MO_SNA_IsHistoricalPeriod,,MATCH(F49,MO_Common_ColumnHeader,0)),"Historical","Forward") | D49: =INDEX(INDIRECT(E49),0,COLUMN(MO_Common_Column_A)) | E49: MO_RIS_REV | F49: Q3-2025 | I49: 11526 | J49: 11526 | K49: =AVERAGE(I49:J49) | M49: =IF(INDEX(MO_SNA_IsHistoricalPeriod,,MATCH(F49,MO_Common_ColumnHeader,0)),"Actual","Estimate") | N49: =IFERROR(INDEX(INDIRECT(E49),0,MATCH(F49,MO_Common_ColumnHeader,0)),"N/A") | P49: =IF(ISNUMBER(N49),N49-K49,"N/A") | Q49: =IFERROR(IF(ISNUMBER(N49),(N49-K49)/ABS(K49),"N/A"),"N/A") | S49: 45855 | T49: Letter to Shareholders
A50: 383 | B50: =IF(INDEX(MO_SNA_IsHistoricalPeriod,,MATCH(F50,MO_Common_ColumnHeader,0)),"Historical","Forward") | D50: =INDEX(INDIRECT(E50),0,COLUMN(MO_Common_Column_A)) | E50: MO_GA_TotalRevenue | F50: Q3-2025 | I50: 0.173 | J50: 0.173 | K50: =AVERAGE(I50:J50) | M50: =IF(INDEX(MO_SNA_IsHistoricalPeriod,,MATCH(F50,MO_Common_ColumnHeader,0)),"Actual","Estimate") | N50: =IFERROR(INDEX(INDIRECT(E50),0,MATCH(F50,MO_Common_ColumnHeader,0)),"N/A") | P50: =IF(ISNUMBER(N50),N50-K50,"N/A") | Q50: =IFERROR(IF(ISNUMBER(N50),(N50-K50)/ABS(K50),"N/A"),"N/A") | S50: 45855 | T50: Letter to Shareholders
A51: 382 | B51: =IF(INDEX(MO_SNA_IsHistoricalPeriod,,MATCH(F51,MO_Common_ColumnHeader,0)),"Historical","Forward") | D51: =INDEX(INDIRECT(E51),0,COLUMN(MO_Common_Column_A)) | E51: MO_GA_REV_ConstantCurrency | F51: Q3-2025 | I51: 0.17 | J51: 0.17 | K51: =AVERAGE(I51:J51) | M51: =IF(INDEX(MO_SNA_IsHistoricalPeriod,,MATCH(F51,MO_Common_ColumnHeader,0)),"Actual","Estimate") | N51: =IF(B51="Historical",IFERROR(INDEX(INDIRECT(E51),0,MATCH(F51,MO_Common_ColumnHeader,0)),"N/A"),"N/A") | P51: =IF(ISNUMBER(N51),N51-K51,"N/A") | Q51: =IFERROR(IF(ISNUMBER(N51),(N51-K51)/ABS(K51),"N/A"),"N/A") | S51: 45855 | T51: Letter to Shareholders
A52: 381 | B52: =IF(INDEX(MO_SNA_IsHistoricalPeriod,,MATCH(F52,MO_Common_ColumnHeader,0)),"Historical","Forward") | D52: =INDEX(INDIRECT(E52),0,COLUMN(MO_Common_Column_A)) | E52: MO_RIS_EBIT | F52: Q3-2025 | I52: 3625 | J52: 3625 | K52: =AVERAGE(I52:J52) | M52: =IF(INDEX(MO_SNA_IsHistoricalPeriod,,MATCH(F52,MO_Common_ColumnHeader,0)),"Actual","Estimate") | N52: =IFERROR(INDEX(INDIRECT(E52),0,MATCH(F52,MO_Common_ColumnHeader,0)),"N/A") | P52: =IF(ISNUMBER(N52),N52-K52,"N/A") | Q52: =IFERROR(IF(ISNUMBER(N52),(N52-K52)/ABS(K52),"N/A"),"N/A") | S52: 45855 | T52: Letter to Shareholders
A53: 380 | B53: =IF(INDEX(MO_SNA_IsHistoricalPeriod,,MATCH(F53,MO_Common_ColumnHeader,0)),"Historical","Forward") | D53: Operating Margin | E53: MO_MA_EBIT | F53: Q3-2025 | I53: 0.315 | J53: 0.315 | K53: =AVERAGE(I53:J53) | M53: =IF(INDEX(MO_SNA_IsHistoricalPeriod,,MATCH(F53,MO_Common_ColumnHeader,0)),"Actual","Estimate") | N53: =IFERROR(INDEX(INDIRECT(E53),0,MATCH(F53,MO_Common_ColumnHeader,0)),"N/A") | P53: =IF(ISNUMBER(N53),N53-K53,"N/A") | Q53: =IFERROR(IF(ISNUMBER(N53),(N53-K53)/ABS(K53),"N/A"),"N/A") | S53: 45855 | T53: Letter to Shareholders
A54: 379 | B54: =IF(INDEX(MO_SNA_IsHistoricalPeriod,,MATCH(F54,MO_Common_ColumnHeader,0)),"Historical","Forward") | D54: =INDEX(INDIRECT(E54),0,COLUMN(MO_Common_Column_A)) | E54: MO_RIS_NI_GAAP_Basic | F54: Q3-2025 | I54: 2979 | J54: 2979 | K54: =AVERAGE(I54:J54) | M54: =IF(INDEX(MO_SNA_IsHistoricalPeriod,,MATCH(F54,MO_Common_ColumnHeader,0)),"Actual","Estimate") | N54: =IFERROR(INDEX(INDIRECT(E54),0,MATCH(F54,MO_Common_ColumnHeader,0)),"N/A") | P54: =IF(ISNUMBER(N54),N54-K54,"N/A") | Q54: =IFERROR(IF(ISNUMBER(N54),(N54-K54)/ABS(K54),"N/A"),"N/A") | S54: 45855 | T54: Letter to Shareholders
A55: 378 | B55: =IF(INDEX(MO_SNA_IsHistoricalPeriod,,MATCH(F55,MO_Common_ColumnHeader,0)),"Historical","Forward") | D55: =INDEX(INDIRECT(E55),0,COLUMN(MO_Common_Column_A)) | E55: MO_RIS_EPS_WAD | F55: Q3-2025 | I55: 0.687 | J55: 0.687 | K55: =AVERAGE(I55:J55) | M55: =IF(INDEX(MO_SNA_IsHistoricalPeriod,,MATCH(F55,MO_Common_ColumnHeader,0)),"Actual","Estimate") | N55: =IFERROR(INDEX(INDIRECT(E55),0,MATCH(F55,MO_Common_ColumnHeader,0)),"N/A") | P55: =IF(ISNUMBER(N55),N55-K55,"N/A") | Q55: =IFERROR(IF(ISNUMBER(N55),(N55-K55)/ABS(K55),"N/A"),"N/A") | S55: 45855 | T55: Letter to Shareholders
A56: 377
A57: 376 | B57: =IF(INDEX(MO_SNA_IsHistoricalPeriod,,MATCH(F57,MO_Common_ColumnHeader,0)),"Historical","Forward") | D57: =INDEX(INDIRECT(E57),0,COLUMN(MO_Common_Column_A)) | E57: MO_RIS_REV | F57: FY2025 | I57: 43500 | J57: 44500 | K57: =AVERAGE(I57:J57) | M57: =IF(INDEX(MO_SNA_IsHistoricalPeriod,,MATCH(F57,MO_Common_ColumnHeader,0)),"Actual","Estimate") | N57: =IFERROR(INDEX(INDIRECT(E57),0,MATCH(F57,MO_Common_ColumnHeader,0)),"N/A") | P57: =IF(ISNUMBER(N57),N57-K57,"N/A") | Q57: =IFERROR(IF(ISNUMBER(N57),(N57-K57)/ABS(K57),"N/A"),"N/A") | S57: 45764 | T57: Letter to Shareholders
A58: 375 | B58: =IF(INDEX(MO_SNA_IsHistoricalPeriod,,MATCH(F58,MO_Common_ColumnHeader,0)),"Historical","Forward") | D58: =INDEX(INDIRECT(E58),0,COLUMN(MO_Common_Column_A)) | E58: MO_GA_TotalRevenue | F58: FY2025 | I58: 0.12 | J58: 0.14 | K58: =AVERAGE(I58:J58) | M58: =IF(INDEX(MO_SNA_IsHistoricalPeriod,,MATCH(F58,MO_Common_ColumnHeader,0)),"Actual","Estimate") | N58: =IFERROR(INDEX(INDIRECT(E58),0,MATCH(F58,MO_Common_ColumnHeader,0)),"N/A") | P58: =IF(ISNUMBER(N58),N58-K58,"N/A") | Q58: =IFERROR(IF(ISNUMBER(N58),(N58-K58)/ABS(K58),"N/A"),"N/A") | S58: 45764 | T58: Letter to Shareholders
A59: 374 | B59: =IF(INDEX(MO_SNA_IsHistoricalPeriod,,MATCH(F59,MO_Common_ColumnHeader,0)),"Historical","Forward") | D59: =INDEX(INDIRECT(E59),0,COLUMN(MO_Common_Column_A)) | E59: MO_GA_REV_ConstantCurrency | F59: FY2025 | I59: 0.14 | J59: 0.17 | K59: =AVERAGE(I59:J59) | M59: =IF(INDEX(MO_SNA_IsHistoricalPeriod,,MATCH(F59,MO_Common_ColumnHeader,0)),"Actual","Estimate") | N59: =IF(B59="Historical",IFERROR(INDEX(INDIRECT(E59),0,MATCH(F59,MO_Common_ColumnHeader,0)),"N/A"),"N/A") | P59: =IF(ISNUMBER(N59),N59-K59,"N/A") | Q59: =IFERROR(IF(ISNUMBER(N59),(N59-K59)/ABS(K59),"N/A"),"N/A") | S59: 45764 | T59: Letter to Shareholders
A60: 373 | B60: =IF(INDEX(MO_SNA_IsHistoricalPeriod,,MATCH(F60,MO_Common_ColumnHeader,0)),"Historical","Forward") | D60: Operating Margin | E60: MO_MA_EBIT | F60: FY2025 | I60: 0.29 | J60: 0.29 | K60: =AVERAGE(I60:J60) | M60: =IF(INDEX(MO_SNA_IsHistoricalPeriod,,MATCH(F60,MO_Common_ColumnHeader,0)),"Actual","Estimate") | N60: =IFERROR(INDEX(INDIRECT(E60),0,MATCH(F60,MO_Common_ColumnHeader,0)),"N/A") | P60: =IF(ISNUMBER(N60),N60-K60,"N/A") | Q60: =IFERROR(IF(ISNUMBER(N60),(N60-K60)/ABS(K60),"N/A"),"N/A") | S60: 45764 | T60: Letter to Shareholders
A61: 372
A62: 371 | B62: =IF(INDEX(MO_SNA_IsHistoricalPeriod,,MATCH(F62,MO_Common_ColumnHeader,0)),"Historical","Forward") | D62: =INDEX(INDIRECT(E62),0,COLUMN(MO_Common_Column_A)) | E62: MO_RIS_REV | F62: Q2-2025 | I62: 11035 | J62: 11035 | K62: =AVERAGE(I62:J62) | M62: =IF(INDEX(MO_SNA_IsHistoricalPeriod,,MATCH(F62,MO_Common_ColumnHeader,0)),"Actual","Estimate") | N62: =IFERROR(INDEX(INDIRECT(E62),0,MATCH(F62,MO_Common_ColumnHeader,0)),"N/A") | P62: =IF(ISNUMBER(N62),N62-K62,"N/A") | Q62: =IFERROR(IF(ISNUMBER(N62),(N62-K62)/ABS(K62),"N/A"),"N/A") | S62: 45764 | T62: Letter to Shareholders
A63: 370 | B63: =IF(INDEX(MO_SNA_IsHistoricalPeriod,,MATCH(F63,MO_Common_ColumnHeader,0)),"Historical","Forward") | D63: =INDEX(INDIRECT(E63),0,COLUMN(MO_Common_Column_A)) | E63: MO_GA_TotalRevenue | F63: Q2-2025 | I63: 0.154 | J63: 0.154 | K63: =AVERAGE(I63:J63) | M63: =IF(INDEX(MO_SNA_IsHistoricalPeriod,,MATCH(F63,MO_Common_ColumnHeader,0)),"Actual","Estimate") | N63: =IFERROR(INDEX(INDIRECT(E63),0,MATCH(F63,MO_Common_ColumnHeader,0)),"N/A") | P63: =IF(ISNUMBER(N63),N63-K63,"N/A") | Q63: =IFERROR(IF(ISNUMBER(N63),(N63-K63)/ABS(K63),"N/A"),"N/A") | S63: 45764 | T63: Letter to Shareholders
A64: 369 | B64: =IF(INDEX(MO_SNA_IsHistoricalPeriod,,MATCH(F64,MO_Common_ColumnHeader,0)),"Historical","Forward") | D64: =INDEX(INDIRECT(E64),0,COLUMN(MO_Common_Column_A)) | E64: MO_GA_REV_ConstantCurrency | F64: Q2-2025 | I64: 0.17 | J64: 0.17 | K64: =AVERAGE(I64:J64) | M64: =IF(INDEX(MO_SNA_IsHistoricalPeriod,,MATCH(F64,MO_Common_ColumnHeader,0)),"Actual","Estimate") | N64: =IF(B64="Historical",IFERROR(INDEX(INDIRECT(E64),0,MATCH(F64,MO_Common_ColumnHeader,0)),"N/A"),"N/A") | P64: =IF(ISNUMBER(N64),N64-K64,"N/A") | Q64: =IFERROR(IF(ISNUMBER(N64),(N64-K64)/ABS(K64),"N/A"),"N/A") | S64: 45764 | T64: Letter to Shareholders
A65: 368 | B65: =IF(INDEX(MO_SNA_IsHistoricalPeriod,,MATCH(F65,MO_Common_ColumnHeader,0)),"Historical","Forward") | D65: =INDEX(INDIRECT(E65),0,COLUMN(MO_Common_Column_A)) | E65: MO_RIS_EBIT | F65: Q2-2025 | I65: 3675 | J65: 3675 | K65: =AVERAGE(I65:J65) | M65: =IF(INDEX(MO_SNA_IsHistoricalPeriod,,MATCH(F65,MO_Common_ColumnHeader,0)),"Actual","Estimate") | N65: =IFERROR(INDEX(INDIRECT(E65),0,MATCH(F65,MO_Common_ColumnHeader,0)),"N/A") | P65: =IF(ISNUMBER(N65),N65-K65,"N/A") | Q65: =IFERROR(IF(ISNUMBER(N65),(N65-K65)/ABS(K65),"N/A"),"N/A") | S65: 45764 | T65: Letter to Shareholders
A66: 367 | B66: =IF(INDEX(MO_SNA_IsHistoricalPeriod,,MATCH(F66,MO_Common_ColumnHeader,0)),"Historical","Forward") | D66: Operating Margin | E66: MO_MA_EBIT | F66: Q2-2025 | I66: 0.33 | J66: 0.33 | K66: =AVERAGE(I66:J66) | M66: =IF(INDEX(MO_SNA_IsHistoricalPeriod,,MATCH(F66,MO_Common_ColumnHeader,0)),"Actual","Estimate") | N66: =IFERROR(INDEX(INDIRECT(E66),0,MATCH(F66,MO_Common_ColumnHeader,0)),"N/A") | P66: =IF(ISNUMBER(N66),N66-K66,"N/A") | Q66: =IFERROR(IF(ISNUMBER(N66),(N66-K66)/ABS(K66),"N/A"),"N/A") | S66: 45764 | T66: Letter to Shareholders
A67: 366 | B67: =IF(INDEX(MO_SNA_IsHistoricalPeriod,,MATCH(F67,MO_Common_ColumnHeader,0)),"Historical","Forward") | D67: =INDEX(INDIRECT(E67),0,COLUMN(MO_Common_Column_A)) | E67: MO_RIS_NI_GAAP_Basic | F67: Q2-2025 | I67: 3055 | J67: 3055 | K67: =AVERAGE(I67:J67) | M67: =IF(INDEX(MO_SNA_IsHistoricalPeriod,,MATCH(F67,MO_Common_ColumnHeader,0)),"Actual","Estimate") | N67: =IFERROR(INDEX(INDIRECT(E67),0,MATCH(F67,MO_Common_ColumnHeader,0)),"N/A") | P67: =IF(ISNUMBER(N67),N67-K67,"N/A") | Q67: =IFERROR(IF(ISNUMBER(N67),(N67-K67)/ABS(K67),"N/A"),"N/A") | S67: 45764 | T67: Letter to Shareholders
A68: 365 | B68: =IF(INDEX(MO_SNA_IsHistoricalPeriod,,MATCH(F68,MO_Common_ColumnHeader,0)),"Historical","Forward") | D68: =INDEX(INDIRECT(E68),0,COLUMN(MO_Common_Column_A)) | E68: MO_RIS_EPS_WAD | F68: Q2-2025 | I68: 0.703 | J68: 0.703 | K68: =AVERAGE(I68:J68) | M68: =IF(INDEX(MO_SNA_IsHistoricalPeriod,,MATCH(F68,MO_Common_ColumnHeader,0)),"Actual","Estimate") | N68: =IFERROR(INDEX(INDIRECT(E68),0,MATCH(F68,MO_Common_ColumnHeader,0)),"N/A") | P68: =IF(ISNUMBER(N68),N68-K68,"N/A") | Q68: =IFERROR(IF(ISNUMBER(N68),(N68-K68)/ABS(K68),"N/A"),"N/A") | S68: 45764 | T68: Letter to Shareholders
A69: 364
A70: 363 | B70: =IF(INDEX(MO_SNA_IsHistoricalPeriod,,MATCH(F70,MO_Common_ColumnHeader,0)),"Historical","Forward") | D70: =INDEX(INDIRECT(E70),0,COLUMN(MO_Common_Column_A)) | E70: MO_RIS_REV | F70: FY2025 | I70: 43500 | J70: 44500 | K70: =AVERAGE(I70:J70) | M70: =IF(INDEX(MO_SNA_IsHistoricalPeriod,,MATCH(F70,MO_Common_ColumnHeader,0)),"Actual","Estimate") | N70: =IFERROR(INDEX(INDIRECT(E70),0,MATCH(F70,MO_Common_ColumnHeader,0)),"N/A") | P70: =IF(ISNUMBER(N70),N70-K70,"N/A") | Q70: =IFERROR(IF(ISNUMBER(N70),(N70-K70)/ABS(K70),"N/A"),"N/A") | S70: 45678 | T70: Letter to Shareholders
A71: 362 | B71: =IF(INDEX(MO_SNA_IsHistoricalPeriod,,MATCH(F71,MO_Common_ColumnHeader,0)),"Historical","Forward") | D71: =INDEX(INDIRECT(E71),0,COLUMN(MO_Common_Column_A)) | E71: MO_GA_TotalRevenue | F71: FY2025 | I71: 0.12 | J71: 0.14 | K71: =AVERAGE(I71:J71) | M71: =IF(INDEX(MO_SNA_IsHistoricalPeriod,,MATCH(F71,MO_Common_ColumnHeader,0)),"Actual","Estimate") | N71: =IFERROR(INDEX(INDIRECT(E71),0,MATCH(F71,MO_Common_ColumnHeader,0)),"N/A") | P71: =IF(ISNUMBER(N71),N71-K71,"N/A") | Q71: =IFERROR(IF(ISNUMBER(N71),(N71-K71)/ABS(K71),"N/A"),"N/A") | S71: 45678 | T71: Letter to Shareholders
A72: 361 | B72: =IF(INDEX(MO_SNA_IsHistoricalPeriod,,MATCH(F72,MO_Common_ColumnHeader,0)),"Historical","Forward") | D72: =INDEX(INDIRECT(E72),0,COLUMN(MO_Common_Column_A)) | E72: MO_GA_REV_ConstantCurrency | F72: FY2025 | I72: 0.14 | J72: 0.17 | K72: =AVERAGE(I72:J72) | M72: =IF(INDEX(MO_SNA_IsHistoricalPeriod,,MATCH(F72,MO_Common_ColumnHeader,0)),"Actual","Estimate") | N72: =IF(B72="Historical",IFERROR(INDEX(INDIRECT(E72),0,MATCH(F72,MO_Common_ColumnHeader,0)),"N/A"),"N/A") | P72: =IF(ISNUMBER(N72),N72-K72,"N/A") | Q72: =IFERROR(IF(ISNUMBER(N72),(N72-K72)/ABS(K72),"N/A"),"N/A") | S72: 45678 | T72: Letter to Shareholders
A73: 360 | B73: =IF(INDEX(MO_SNA_IsHistoricalPeriod,,MATCH(F73,MO_Common_ColumnHeader,0)),"Historical","Forward") | D73: Operating Margin | E73: MO_MA_EBIT | F73: FY2025 | I73: 0.29 | J73: 0.29 | K73: =AVERAGE(I73:J73) | M73: =IF(INDEX(MO_SNA_IsHistoricalPeriod,,MATCH(F73,MO_Common_ColumnHeader,0)),"Actual","Estimate") | N73: =IFERROR(INDEX(INDIRECT(E73),0,MATCH(F73,MO_Common_ColumnHeader,0)),"N/A") | P73: =IF(ISNUMBER(N73),N73-K73,"N/A") | Q73: =IFERROR(IF(ISNUMBER(N73),(N73-K73)/ABS(K73),"N/A"),"N/A") | S73: 45678 | T73: Letter to Shareholders
A74: 359
A75: 358 | B75: =IF(INDEX(MO_SNA_IsHistoricalPeriod,,MATCH(F75,MO_Common_ColumnHeader,0)),"Historical","Forward") | D75: =INDEX(INDIRECT(E75),0,COLUMN(MO_Common_Column_A)) | E75: MO_RIS_REV | F75: Q1-2025 | I75: 10416 | J75: 10416 | K75: =AVERAGE(I75:J75) | M75: =IF(INDEX(MO_SNA_IsHistoricalPeriod,,MATCH(F75,MO_Common_ColumnHeader,0)),"Actual","Estimate") | N75: =IFERROR(INDEX(INDIRECT(E75),0,MATCH(F75,MO_Common_ColumnHeader,0)),"N/A") | P75: =IF(ISNUMBER(N75),N75-K75,"N/A") | Q75: =IFERROR(IF(ISNUMBER(N75),(N75-K75)/ABS(K75),"N/A"),"N/A") | S75: 45678 | T75: Letter to Shareholders
A76: 357 | B76: =IF(INDEX(MO_SNA_IsHistoricalPeriod,,MATCH(F76,MO_Common_ColumnHeader,0)),"Historical","Forward") | D76: =INDEX(INDIRECT(E76),0,COLUMN(MO_Common_Column_A)) | E76: MO_GA_TotalRevenue | F76: Q1-2025 | I76: 0.112 | J76: 0.112 | K76: =AVERAGE(I76:J76) | M76: =IF(INDEX(MO_SNA_IsHistoricalPeriod,,MATCH(F76,MO_Common_ColumnHeader,0)),"Actual","Estimate") | N76: =IFERROR(INDEX(INDIRECT(E76),0,MATCH(F76,MO_Common_ColumnHeader,0)),"N/A") | P76: =IF(ISNUMBER(N76),N76-K76,"N/A") | Q76: =IFERROR(IF(ISNUMBER(N76),(N76-K76)/ABS(K76),"N/A"),"N/A") | S76: 45678 | T76: Letter to Shareholders
A77: 356 | B77: =IF(INDEX(MO_SNA_IsHistoricalPeriod,,MATCH(F77,MO_Common_ColumnHeader,0)),"Historical","Forward") | D77: =INDEX(INDIRECT(E77),0,COLUMN(MO_Common_Column_A)) | E77: MO_GA_REV_ConstantCurrency | F77: Q1-2025 | I77: 0.14 | J77: 0.14 | K77: =AVERAGE(I77:J77) | M77: =IF(INDEX(MO_SNA_IsHistoricalPeriod,,MATCH(F77,MO_Common_ColumnHeader,0)),"Actual","Estimate") | N77: =IF(B77="Historical",IFERROR(INDEX(INDIRECT(E77),0,MATCH(F77,MO_Common_ColumnHeader,0)),"N/A"),"N/A") | P77: =IF(ISNUMBER(N77),N77-K77,"N/A") | Q77: =IFERROR(IF(ISNUMBER(N77),(N77-K77)/ABS(K77),"N/A"),"N/A") | S77: 45678 | T77: Letter to Shareholders
A78: 355 | B78: =IF(INDEX(MO_SNA_IsHistoricalPeriod,,MATCH(F78,MO_Common_ColumnHeader,0)),"Historical","Forward") | D78: =INDEX(INDIRECT(E78),0,COLUMN(MO_Common_Column_A)) | E78: MO_RIS_EBIT | F78: Q1-2025 | I78: 2940 | J78: 2940 | K78: =AVERAGE(I78:J78) | M78: =IF(INDEX(MO_SNA_IsHistoricalPeriod,,MATCH(F78,MO_Common_ColumnHeader,0)),"Actual","Estimate") | N78: =IFERROR(INDEX(INDIRECT(E78),0,MATCH(F78,MO_Common_ColumnHeader,0)),"N/A") | P78: =IF(ISNUMBER(N78),N78-K78,"N/A") | Q78: =IFERROR(IF(ISNUMBER(N78),(N78-K78)/ABS(K78),"N/A"),"N/A") | S78: 45678 | T78: Letter to Shareholders
A79: 354 | B79: =IF(INDEX(MO_SNA_IsHistoricalPeriod,,MATCH(F79,MO_Common_ColumnHeader,0)),"Historical","Forward") | D79: Operating Margin | E79: MO_MA_EBIT | F79: Q1-2025 | I79: 0.282 | J79: 0.282 | K79: =AVERAGE(I79:J79) | M79: =IF(INDEX(MO_SNA_IsHistoricalPeriod,,MATCH(F79,MO_Common_ColumnHeader,0)),"Actual","Estimate") | N79: =IFERROR(INDEX(INDIRECT(E79),0,MATCH(F79,MO_Common_ColumnHeader,0)),"N/A") | P79: =IF(ISNUMBER(N79),N79-K79,"N/A") | Q79: =IFERROR(IF(ISNUMBER(N79),(N79-K79)/ABS(K79),"N/A"),"N/A") | S79: 45678 | T79: Letter to Shareholders
A80: 353 | B80: =IF(INDEX(MO_SNA_IsHistoricalPeriod,,MATCH(F80,MO_Common_ColumnHeader,0)),"Historical","Forward") | D80: =INDEX(INDIRECT(E80),0,COLUMN(MO_Common_Column_A)) | E80: MO_RIS_NI_GAAP_Basic | F80: Q1-2025 | I80: 2440 | J80: 2440 | K80: =AVERAGE(I80:J80) | M80: =IF(INDEX(MO_SNA_IsHistoricalPeriod,,MATCH(F80,MO_Common_ColumnHeader,0)),"Actual","Estimate") | N80: =IFERROR(INDEX(INDIRECT(E80),0,MATCH(F80,MO_Common_ColumnHeader,0)),"N/A") | P80: =IF(ISNUMBER(N80),N80-K80,"N/A") | Q80: =IFERROR(IF(ISNUMBER(N80),(N80-K80)/ABS(K80),"N/A"),"N/A") | S80: 45678 | T80: Letter to Shareholders
A81: 352 | B81: =IF(INDEX(MO_SNA_IsHistoricalPeriod,,MATCH(F81,MO_Common_ColumnHeader,0)),"Historical","Forward") | D81: =INDEX(INDIRECT(E81),0,COLUMN(MO_Common_Column_A)) | E81: MO_RIS_EPS_WAD | F81: Q1-2025 | I81: 0.558 | J81: 0.558 | K81: =AVERAGE(I81:J81) | M81: =IF(INDEX(MO_SNA_IsHistoricalPeriod,,MATCH(F81,MO_Common_ColumnHeader,0)),"Actual","Estimate") | N81: =IFERROR(INDEX(INDIRECT(E81),0,MATCH(F81,MO_Common_ColumnHeader,0)),"N/A") | P81: =IF(ISNUMBER(N81),N81-K81,"N/A") | Q81: =IFERROR(IF(ISNUMBER(N81),(N81-K81)/ABS(K81),"N/A"),"N/A") | S81: 45678 | T81: Letter to Shareholders
A82: 351
A83: 350 | B83: =IF(INDEX(MO_SNA_IsHistoricalPeriod,,MATCH(F83,MO_Common_ColumnHeader,0)),"Historical","Forward") | D83: =INDEX(INDIRECT(E83),0,COLUMN(MO_Common_Column_A)) | E83: MO_RIS_REV | F83: FY2025 | I83: 43000 | J83: 44000 | K83: =AVERAGE(I83:J83) | M83: =IF(INDEX(MO_SNA_IsHistoricalPeriod,,MATCH(F83,MO_Common_ColumnHeader,0)),"Actual","Estimate") | N83: =IFERROR(INDEX(INDIRECT(E83),0,MATCH(F83,MO_Common_ColumnHeader,0)),"N/A") | P83: =IF(ISNUMBER(N83),N83-K83,"N/A") | Q83: =IFERROR(IF(ISNUMBER(N83),(N83-K83)/ABS(K83),"N/A"),"N/A") | S83: 45582 | T83: Letter to Shareholders
A84: 349 | B84: =IF(INDEX(MO_SNA_IsHistoricalPeriod,,MATCH(F84,MO_Common_ColumnHeader,0)),"Historical","Forward") | D84: =INDEX(INDIRECT(E84),0,COLUMN(MO_Common_Column_A)) | E84: MO_GA_TotalRevenue | F84: FY2025 | I84: 0.11 | J84: 0.13 | K84: =AVERAGE(I84:J84) | M84: =IF(INDEX(MO_SNA_IsHistoricalPeriod,,MATCH(F84,MO_Common_ColumnHeader,0)),"Actual","Estimate") | N84: =IFERROR(INDEX(INDIRECT(E84),0,MATCH(F84,MO_Common_ColumnHeader,0)),"N/A") | P84: =IF(ISNUMBER(N84),N84-K84,"N/A") | Q84: =IFERROR(IF(ISNUMBER(N84),(N84-K84)/ABS(K84),"N/A"),"N/A") | S84: 45582 | T84: Letter to Shareholders
A85: 348 | B85: =IF(INDEX(MO_SNA_IsHistoricalPeriod,,MATCH(F85,MO_Common_ColumnHeader,0)),"Historical","Forward") | D85: Operating Margin | E85: MO_MA_EBIT | F85: FY2025 | I85: 0.28 | J85: 0.28 | K85: =AVERAGE(I85:J85) | M85: =IF(INDEX(MO_SNA_IsHistoricalPeriod,,MATCH(F85,MO_Common_ColumnHeader,0)),"Actual","Estimate") | N85: =IFERROR(INDEX(INDIRECT(E85),0,MATCH(F85,MO_Common_ColumnHeader,0)),"N/A") | P85: =IF(ISNUMBER(N85),N85-K85,"N/A") | Q85: =IFERROR(IF(ISNUMBER(N85),(N85-K85)/ABS(K85),"N/A"),"N/A") | S85: 45582 | T85: Letter to Shareholders
A86: 347
A87: 346 | B87: =IF(INDEX(MO_SNA_IsHistoricalPeriod,,MATCH(F87,MO_Common_ColumnHeader,0)),"Historical","Forward") | D87: =INDEX(INDIRECT(E87),0,COLUMN(MO_Common_Column_A)) | E87: MO_GA_TotalRevenue | F87: FY2024 | I87: 0.15 | J87: 0.15 | K87: =AVERAGE(I87:J87) | M87: =IF(INDEX(MO_SNA_IsHistoricalPeriod,,MATCH(F87,MO_Common_ColumnHeader,0)),"Actual","Estimate") | N87: =IFERROR(INDEX(INDIRECT(E87),0,MATCH(F87,MO_Common_ColumnHeader,0)),"N/A") | P87: =IF(ISNUMBER(N87),N87-K87,"N/A") | Q87: =IFERROR(IF(ISNUMBER(N87),(N87-K87)/ABS(K87),"N/A"),"N/A") | S87: 45582 | T87: Letter to Shareholders
A88: 345 | B88: =IF(INDEX(MO_SNA_IsHistoricalPeriod,,MATCH(F88,MO_Common_ColumnHeader,0)),"Historical","Forward") | D88: Operating Margin | E88: MO_MA_EBIT | F88: FY2024 | I88: 0.27 | J88: 0.27 | K88: =AVERAGE(I88:J88) | M88: =IF(INDEX(MO_SNA_IsHistoricalPeriod,,MATCH(F88,MO_Common_ColumnHeader,0)),"Actual","Estimate") | N88: =IFERROR(INDEX(INDIRECT(E88),0,MATCH(F88,MO_Common_ColumnHeader,0)),"N/A") | P88: =IF(ISNUMBER(N88),N88-K88,"N/A") | Q88: =IFERROR(IF(ISNUMBER(N88),(N88-K88)/ABS(K88),"N/A"),"N/A") | S88: 45582 | T88: Letter to Shareholders
A89: 344
A90: 343 | B90: =IF(INDEX(MO_SNA_IsHistoricalPeriod,,MATCH(F90,MO_Common_ColumnHeader,0)),"Historical","Forward") | D90: =INDEX(INDIRECT(E90),0,COLUMN(MO_Common_Column_A)) | E90: MO_RIS_REV | F90: Q4-2024 | I90: 10128 | J90: 10128 | K90: =AVERAGE(I90:J90) | M90: =IF(INDEX(MO_SNA_IsHistoricalPeriod,,MATCH(F90,MO_Common_ColumnHeader,0)),"Actual","Estimate") | N90: =IFERROR(INDEX(INDIRECT(E90),0,MATCH(F90,MO_Common_ColumnHeader,0)),"N/A") | P90: =IF(ISNUMBER(N90),N90-K90,"N/A") | Q90: =IFERROR(IF(ISNUMBER(N90),(N90-K90)/ABS(K90),"N/A"),"N/A") | S90: 45582 | T90: Letter to Shareholders
A91: 342 | B91: =IF(INDEX(MO_SNA_IsHistoricalPeriod,,MATCH(F91,MO_Common_ColumnHeader,0)),"Historical","Forward") | D91: =INDEX(INDIRECT(E91),0,COLUMN(MO_Common_Column_A)) | E91: MO_GA_TotalRevenue | F91: Q4-2024 | I91: 0.147 | J91: 0.147 | K91: =AVERAGE(I91:J91) | M91: =IF(INDEX(MO_SNA_IsHistoricalPeriod,,MATCH(F91,MO_Common_ColumnHeader,0)),"Actual","Estimate") | N91: =IFERROR(INDEX(INDIRECT(E91),0,MATCH(F91,MO_Common_ColumnHeader,0)),"N/A") | P91: =IF(ISNUMBER(N91),N91-K91,"N/A") | Q91: =IFERROR(IF(ISNUMBER(N91),(N91-K91)/ABS(K91),"N/A"),"N/A") | S91: 45582 | T91: Letter to Shareholders
A92: 341 | B92: =IF(INDEX(MO_SNA_IsHistoricalPeriod,,MATCH(F92,MO_Common_ColumnHeader,0)),"Historical","Forward") | D92: =INDEX(INDIRECT(E92),0,COLUMN(MO_Common_Column_A)) | E92: MO_GA_REV_ConstantCurrency | F92: Q4-2024 | I92: 0.17 | J92: 0.17 | K92: =AVERAGE(I92:J92) | M92: =IF(INDEX(MO_SNA_IsHistoricalPeriod,,MATCH(F92,MO_Common_ColumnHeader,0)),"Actual","Estimate") | N92: =IF(B92="Historical",IFERROR(INDEX(INDIRECT(E92),0,MATCH(F92,MO_Common_ColumnHeader,0)),"N/A"),"N/A") | P92: =IF(ISNUMBER(N92),N92-K92,"N/A") | Q92: =IFERROR(IF(ISNUMBER(N92),(N92-K92)/ABS(K92),"N/A"),"N/A") | S92: 45582 | T92: Letter to Shareholders
A93: 340 | B93: =IF(INDEX(MO_SNA_IsHistoricalPeriod,,MATCH(F93,MO_Common_ColumnHeader,0)),"Historical","Forward") | D93: =INDEX(INDIRECT(E93),0,COLUMN(MO_Common_Column_A)) | E93: MO_RIS_EBIT | F93: Q4-2024 | I93: 2190 | J93: 2190 | K93: =AVERAGE(I93:J93) | M93: =IF(INDEX(MO_SNA_IsHistoricalPeriod,,MATCH(F93,MO_Common_ColumnHeader,0)),"Actual","Estimate") | N93: =IFERROR(INDEX(INDIRECT(E93),0,MATCH(F93,MO_Common_ColumnHeader,0)),"N/A") | P93: =IF(ISNUMBER(N93),N93-K93,"N/A") | Q93: =IFERROR(IF(ISNUMBER(N93),(N93-K93)/ABS(K93),"N/A"),"N/A") | S93: 45582 | T93: Letter to Shareholders
A94: 339 | B94: =IF(INDEX(MO_SNA_IsHistoricalPeriod,,MATCH(F94,MO_Common_ColumnHeader,0)),"Historical","Forward") | D94: Operating Margin | E94: MO_MA_EBIT | F94: Q4-2024 | I94: 0.216 | J94: 0.216 | K94: =AVERAGE(I94:J94) | M94: =IF(INDEX(MO_SNA_IsHistoricalPeriod,,MATCH(F94,MO_Common_ColumnHeader,0)),"Actual","Estimate") | N94: =IFERROR(INDEX(INDIRECT(E94),0,MATCH(F94,MO_Common_ColumnHeader,0)),"N/A") | P94: =IF(ISNUMBER(N94),N94-K94,"N/A") | Q94: =IFERROR(IF(ISNUMBER(N94),(N94-K94)/ABS(K94),"N/A"),"N/A") | S94: 45582 | T94: Letter to Shareholders
A95: 338 | B95: =IF(INDEX(MO_SNA_IsHistoricalPeriod,,MATCH(F95,MO_Common_ColumnHeader,0)),"Historical","Forward") | D95: =INDEX(INDIRECT(E95),0,COLUMN(MO_Common_Column_A)) | E95: MO_RIS_NI_GAAP_Basic | F95: Q4-2024 | I95: 1847 | J95: 1847 | K95: =AVERAGE(I95:J95) | M95: =IF(INDEX(MO_SNA_IsHistoricalPeriod,,MATCH(F95,MO_Common_ColumnHeader,0)),"Actual","Estimate") | N95: =IFERROR(INDEX(INDIRECT(E95),0,MATCH(F95,MO_Common_ColumnHeader,0)),"N/A") | P95: =IF(ISNUMBER(N95),N95-K95,"N/A") | Q95: =IFERROR(IF(ISNUMBER(N95),(N95-K95)/ABS(K95),"N/A"),"N/A") | S95: 45582 | T95: Letter to Shareholders
A96: 337 | B96: =IF(INDEX(MO_SNA_IsHistoricalPeriod,,MATCH(F96,MO_Common_ColumnHeader,0)),"Historical","Forward") | D96: =INDEX(INDIRECT(E96),0,COLUMN(MO_Common_Column_A)) | E96: MO_RIS_EPS_WAD | F96: Q4-2024 | I96: 0.423 | J96: 0.423 | K96: =AVERAGE(I96:J96) | M96: =IF(INDEX(MO_SNA_IsHistoricalPeriod,,MATCH(F96,MO_Common_ColumnHeader,0)),"Actual","Estimate") | N96: =IFERROR(INDEX(INDIRECT(E96),0,MATCH(F96,MO_Common_ColumnHeader,0)),"N/A") | P96: =IF(ISNUMBER(N96),N96-K96,"N/A") | Q96: =IFERROR(IF(ISNUMBER(N96),(N96-K96)/ABS(K96),"N/A"),"N/A") | S96: 45582 | T96: Letter to Shareholders
A97: 336 | B97: =IF(INDEX(MO_SNA_IsHistoricalPeriod,,MATCH(F97,MO_Common_ColumnHeader,0)),"Historical","Forward") | D97: =INDEX(INDIRECT(E97),0,COLUMN(MO_Common_Column_A)) | E97: MX_MO_OS_TotalPaidStreamingMembershipsNetAdditions_1 | F97: Q4-2024 | M97: =IF(INDEX(MO_SNA_IsHistoricalPeriod,,MATCH(F97,MO_Common_ColumnHeader,0)),"Actual","Estimate") | N97: =IFERROR(INDEX(INDIRECT(E97),0,MATCH(F97,MO_Common_ColumnHeader,0)),"N/A") | P97: =IF(ISNUMBER(N97),N97-K97,"N/A") | Q97: =IFERROR(IF(ISNUMBER(N97),(N97-K97)/ABS(K97),"N/A"),"N/A") | S97: 45582 | T97: Letter to Shareholders
A98: 335
A99: 334 | B99: =IF(INDEX(MO_SNA_IsHistoricalPeriod,,MATCH(F99,MO_Common_ColumnHeader,0)),"Historical","Forward") | D99: =INDEX(INDIRECT(E99),0,COLUMN(MO_Common_Column_A)) | E99: MO_GA_TotalRevenue | F99: FY2024 | I99: 0.14 | J99: 0.15 | K99: =AVERAGE(I99:J99) | M99: =IF(INDEX(MO_SNA_IsHistoricalPeriod,,MATCH(F99,MO_Common_ColumnHeader,0)),"Actual","Estimate") | N99: =IFERROR(INDEX(INDIRECT(E99),0,MATCH(F99,MO_Common_ColumnHeader,0)),"N/A") | P99: =IF(ISNUMBER(N99),N99-K99,"N/A") | Q99: =IFERROR(IF(ISNUMBER(N99),(N99-K99)/ABS(K99),"N/A"),"N/A") | S99: 45491 | T99: Letter to Shareholders
A100: 333 | B100: =IF(INDEX(MO_SNA_IsHistoricalPeriod,,MATCH(F100,MO_Common_ColumnHeader,0)),"Historical","Forward") | D100: Operating Margin | E100: MO_MA_EBIT | F100: FY2024 | I100: 0.26 | J100: 0.26 | K100: =AVERAGE(I100:J100) | M100: =IF(INDEX(MO_SNA_IsHistoricalPeriod,,MATCH(F100,MO_Common_ColumnHeader,0)),"Actual","Estimate") | N100: =IFERROR(INDEX(INDIRECT(E100),0,MATCH(F100,MO_Common_ColumnHeader,0)),"N/A") | P100: =IF(ISNUMBER(N100),N100-K100,"N/A") | Q100: =IFERROR(IF(ISNUMBER(N100),(N100-K100)/ABS(K100),"N/A"),"N/A") | S100: 45491 | T100: Letter to Shareholders
A101: 332
...

Sheet Summary Page
A1: =MO.CompanyName | C1: =INDEX(MO_Common_QEndDate,0,COLUMN()) | D1: =INDEX(MO_Common_QEndDate,0,COLUMN()) | E1: =INDEX(MO_Common_QEndDate,0,COLUMN()) | F1: =INDEX(MO_Common_QEndDate,0,COLUMN()) | G1: =INDEX(MO_Common_QEndDate,0,COLUMN()) | H1: =INDEX(MO_Common_QEndDate,0,COLUMN()) | I1: =INDEX(MO_Common_QEndDate,0,COLUMN()) | J1: =INDEX(MO_Common_QEndDate,0,COLUMN()) | ... CF1: =INDEX(MO_Common_QEndDate,0,COLUMN())
A2: Reports | B2: =MO.ReportFX | C2: =INDEX(MO_Common_ColumnHeader,0,COLUMN()) | D2: =INDEX(MO_Common_ColumnHeader,0,COLUMN()) | E2: =INDEX(MO_Common_ColumnHeader,0,COLUMN()) | F2: =INDEX(MO_Common_ColumnHeader,0,COLUMN()) | G2: =INDEX(MO_Common_ColumnHeader,0,COLUMN()) | H2: =INDEX(MO_Common_ColumnHeader,0,COLUMN()) | I2: =INDEX(MO_Common_ColumnHeader,0,COLUMN()) | J2: =INDEX(MO_Common_ColumnHeader,0,COLUMN()) | ... CF2: =INDEX(MO_Common_ColumnHeader,0,COLUMN())
A3: Capitalization Summary
A4: ="Stock Price - "&SP.ValuationToggle | B4: EoP | C4: =IF(INDEX(MO_SNA_IsHistoricalPeriod,1,COLUMN())=FALSE,MO.LastPrice/HP.MRFX,CHOOSE(VLOOKUP(SP.ValuationToggle,tb_ValuationToggle,COLUMNS(tb_ValuationToggle),FALSE),INDEX(MO_SPT_StockHigh,1,COLUMN()),INDEX(MO_SPT_StockLow,1,COLUMN()),INDEX(MO_SPT_StockAverage,1,COLUMN()),INDEX(MO_SPT_StockEoP,1,COLUMN()))/IF(SP.ValuationToggle="EoP",IF(INDEX(MO_SPT_FXEoP,1,COLUMN())=0,1,INDEX(MO_SPT_FXEoP,1,COLUMN())),IF(INDEX(MO_SPT_FXAverage,1,COLUMN())=0,1,INDEX(MO_SPT_FXAverage,1,COLUMN())))) | D4: =IF(INDEX(MO_SNA_IsHistoricalPeriod,1,COLUMN())=FALSE,MO.LastPrice/HP.MRFX,CHOOSE(VLOOKUP(SP.ValuationToggle,tb_ValuationToggle,COLUMNS(tb_ValuationToggle),FALSE),INDEX(MO_SPT_StockHigh,1,COLUMN()),INDEX(MO_SPT_StockLow,1,COLUMN()),INDEX(MO_SPT_StockAverage,1,COLUMN()),INDEX(MO_SPT_StockEoP,1,COLUMN()))/IF(SP.ValuationToggle="EoP",IF(INDEX(MO_SPT_FXEoP,1,COLUMN())=0,1,INDEX(MO_SPT_FXEoP,1,COLUMN())),IF(INDEX(MO_SPT_FXAverage,1,COLUMN())=0,1,INDEX(MO_SPT_FXAverage,1,COLUMN())))) | E4: =IF(INDEX(MO_SNA_IsHistoricalPeriod,1,COLUMN())=FALSE,MO.LastPrice/HP.MRFX,CHOOSE(VLOOKUP(SP.ValuationToggle,tb_ValuationToggle,COLUMNS(tb_ValuationToggle),FALSE),INDEX(MO_SPT_StockHigh,1,COLUMN()),INDEX(MO_SPT_StockLow,1,COLUMN()),INDEX(MO_SPT_StockAverage,1,COLUMN()),INDEX(MO_SPT_StockEoP,1,COLUMN()))/IF(SP.ValuationToggle="EoP",IF(INDEX(MO_SPT_FXEoP,1,COLUMN())=0,1,INDEX(MO_SPT_FXEoP,1,COLUMN())),IF(INDEX(MO_SPT_FXAverage,1,COLUMN())=0,1,INDEX(MO_SPT_FXAverage,1,COLUMN())))) | F4: =IF(INDEX(MO_SNA_IsHistoricalPeriod,1,COLUMN())=FALSE,MO.LastPrice/HP.MRFX,CHOOSE(VLOOKUP(SP.ValuationToggle,tb_ValuationToggle,COLUMNS(tb_ValuationToggle),FALSE),INDEX(MO_SPT_StockHigh,1,COLUMN()),INDEX(MO_SPT_StockLow,1,COLUMN()),INDEX(MO_SPT_StockAverage,1,COLUMN()),INDEX(MO_SPT_StockEoP,1,COLUMN()))/IF(SP.ValuationToggle="EoP",IF(INDEX(MO_SPT_FXEoP,1,COLUMN())=0,1,INDEX(MO_SPT_FXEoP,1,COLUMN())),IF(INDEX(MO_SPT_FXAverage,1,COLUMN())=0,1,INDEX(MO_SPT_FXAverage,1,COLUMN())))) | G4: =IF(INDEX(MO_SNA_IsHistoricalPeriod,1,COLUMN())=FALSE,MO.LastPrice/HP.MRFX,CHOOSE(VLOOKUP(SP.ValuationToggle,tb_ValuationToggle,COLUMNS(tb_ValuationToggle),FALSE),INDEX(MO_SPT_StockHigh,1,COLUMN()),INDEX(MO_SPT_StockLow,1,COLUMN()),INDEX(MO_SPT_StockAverage,1,COLUMN()),INDEX(MO_SPT_StockEoP,1,COLUMN()))/IF(SP.ValuationToggle="EoP",IF(INDEX(MO_SPT_FXEoP,1,COLUMN())=0,1,INDEX(MO_SPT_FXEoP,1,COLUMN())),IF(INDEX(MO_SPT_FXAverage,1,COLUMN())=0,1,INDEX(MO_SPT_FXAverage,1,COLUMN())))) | H4: =IF(INDEX(MO_SNA_IsHistoricalPeriod,1,COLUMN())=FALSE,MO.LastPrice/HP.MRFX,CHOOSE(VLOOKUP(SP.ValuationToggle,tb_ValuationToggle,COLUMNS(tb_ValuationToggle),FALSE),INDEX(MO_SPT_StockHigh,1,COLUMN()),INDEX(MO_SPT_StockLow,1,COLUMN()),INDEX(MO_SPT_StockAverage,1,COLUMN()),INDEX(MO_SPT_StockEoP,1,COLUMN()))/IF(SP.ValuationToggle="EoP",IF(INDEX(MO_SPT_FXEoP,1,COLUMN())=0,1,INDEX(MO_SPT_FXEoP,1,COLUMN())),IF(INDEX(MO_SPT_FXAverage,1,COLUMN())=0,1,INDEX(MO_SPT_FXAverage,1,COLUMN())))) | I4: =IF(INDEX(MO_SNA_IsHistoricalPeriod,1,COLUMN())=FALSE,MO.LastPrice/HP.MRFX,CHOOSE(VLOOKUP(SP.ValuationToggle,tb_ValuationToggle,COLUMNS(tb_ValuationToggle),FALSE),INDEX(MO_SPT_StockHigh,1,COLUMN()),INDEX(MO_SPT_StockLow,1,COLUMN()),INDEX(MO_SPT_StockAverage,1,COLUMN()),INDEX(MO_SPT_StockEoP,1,COLUMN()))/IF(SP.ValuationToggle="EoP",IF(INDEX(MO_SPT_FXEoP,1,COLUMN())=0,1,INDEX(MO_SPT_FXEoP,1,COLUMN())),IF(INDEX(MO_SPT_FXAverage,1,COLUMN())=0,1,INDEX(MO_SPT_FXAverage,1,COLUMN())))) | J4: =IF(INDEX(MO_SNA_IsHistoricalPeriod,1,COLUMN())=FALSE,MO.LastPrice/HP.MRFX,CHOOSE(VLOOKUP(SP.ValuationToggle,tb_ValuationToggle,COLUMNS(tb_ValuationToggle),FALSE),INDEX(MO_SPT_StockHigh,1,COLUMN()),INDEX(MO_SPT_StockLow,1,COLUMN()),INDEX(MO_SPT_StockAverage,1,COLUMN()),INDEX(MO_SPT_StockEoP,1,COLUMN()))/IF(SP.ValuationToggle="EoP",IF(INDEX(MO_SPT_FXEoP,1,COLUMN())=0,1,INDEX(MO_SPT_FXEoP,1,COLUMN())),IF(INDEX(MO_SPT_FXAverage,1,COLUMN())=0,1,INDEX(MO_SPT_FXAverage,1,COLUMN())))) | ... CF4: =IF(INDEX(MO_SNA_IsHistoricalPeriod,1,COLUMN())=FALSE,MO.LastPrice/HP.MRFX,CHOOSE(VLOOKUP(SP.ValuationToggle,tb_ValuationToggle,COLUMNS(tb_ValuationToggle),FALSE),INDEX(MO_SPT_StockHigh,1,COLUMN()),INDEX(MO_SPT_StockLow,1,COLUMN()),INDEX(MO_SPT_StockAverage,1,COLUMN()),INDEX(MO_SPT_StockEoP,1,COLUMN()))/IF(SP.ValuationToggle="EoP",IF(INDEX(MO_SPT_FXEoP,1,COLUMN())=0,1,INDEX(MO_SPT_FXEoP,1,COLUMN())),IF(INDEX(MO_SPT_FXAverage,1,COLUMN())=0,1,INDEX(MO_SPT_FXAverage,1,COLUMN()))))
A5: =INDEX(MO_SCA_ShareCount_EoP_Diluted,0,COLUMN()) | C5: =INDEX(MO_SCA_ShareCount_EoP_Diluted,0,COLUMN()) | D5: =INDEX(MO_SCA_ShareCount_EoP_Diluted,0,COLUMN()) | E5: =INDEX(MO_SCA_ShareCount_EoP_Diluted,0,COLUMN()) | F5: =INDEX(MO_SCA_ShareCount_EoP_Diluted,0,COLUMN()) | G5: =INDEX(MO_SCA_ShareCount_EoP_Diluted,0,COLUMN()) | H5: =INDEX(MO_SCA_ShareCount_EoP_Diluted,0,COLUMN()) | I5: =INDEX(MO_SCA_ShareCount_EoP_Diluted,0,COLUMN()) | J5: =INDEX(MO_SCA_ShareCount_EoP_Diluted,0,COLUMN()) | ... CF5: =INDEX(MO_SCA_ShareCount_EoP_Diluted,0,COLUMN())
A6: ="Market Cap - "&SP.ValuationToggle | C6: =INDEX(SP_CS_StockPrice,0,COLUMN())*INDEX(SP_CS_ShareCount_EoP_Diluted,0,COLUMN()) | D6: =INDEX(SP_CS_StockPrice,0,COLUMN())*INDEX(SP_CS_ShareCount_EoP_Diluted,0,COLUMN()) | E6: =INDEX(SP_CS_StockPrice,0,COLUMN())*INDEX(SP_CS_ShareCount_EoP_Diluted,0,COLUMN()) | F6: =INDEX(SP_CS_StockPrice,0,COLUMN())*INDEX(SP_CS_ShareCount_EoP_Diluted,0,COLUMN()) | G6: =INDEX(SP_CS_StockPrice,0,COLUMN())*INDEX(SP_CS_ShareCount_EoP_Diluted,0,COLUMN()) | H6: =INDEX(SP_CS_StockPrice,0,COLUMN())*INDEX(SP_CS_ShareCount_EoP_Diluted,0,COLUMN()) | I6: =INDEX(SP_CS_StockPrice,0,COLUMN())*INDEX(SP_CS_ShareCount_EoP_Diluted,0,COLUMN()) | J6: =INDEX(SP_CS_StockPrice,0,COLUMN())*INDEX(SP_CS_ShareCount_EoP_Diluted,0,COLUMN()) | ... CF6: =INDEX(SP_CS_StockPrice,0,COLUMN())*INDEX(SP_CS_ShareCount_EoP_Diluted,0,COLUMN())
A7: =INDEX(MO_BSS_Cash,0,COLUMN()) | C7: =INDEX(MO_BSS_Cash,0,COLUMN()) | D7: =INDEX(MO_BSS_Cash,0,COLUMN()) | E7: =INDEX(MO_BSS_Cash,0,COLUMN()) | F7: =INDEX(MO_BSS_Cash,0,COLUMN()) | G7: =INDEX(MO_BSS_Cash,0,COLUMN()) | H7: =INDEX(MO_BSS_Cash,0,COLUMN()) | I7: =INDEX(MO_BSS_Cash,0,COLUMN()) | J7: =INDEX(MO_BSS_Cash,0,COLUMN()) | ... CF7: =INDEX(MO_BSS_Cash,0,COLUMN())
A8: =INDEX(MO_BSS_Debt,0,COLUMN()) | C8: =INDEX(MO_BSS_Debt,0,COLUMN()) | D8: =INDEX(MO_BSS_Debt,0,COLUMN()) | E8: =INDEX(MO_BSS_Debt,0,COLUMN()) | F8: =INDEX(MO_BSS_Debt,0,COLUMN()) | G8: =INDEX(MO_BSS_Debt,0,COLUMN()) | H8: =INDEX(MO_BSS_Debt,0,COLUMN()) | I8: =INDEX(MO_BSS_Debt,0,COLUMN()) | J8: =INDEX(MO_BSS_Debt,0,COLUMN()) | ... CF8: =INDEX(MO_BSS_Debt,0,COLUMN())
A9: Operating Lease Liabilities | C9: =INDEX(MO_BSS_OL,0,COLUMN()) | D9: =INDEX(MO_BSS_OL,0,COLUMN()) | E9: =INDEX(MO_BSS_OL,0,COLUMN()) | F9: =INDEX(MO_BSS_OL,0,COLUMN()) | G9: =INDEX(MO_BSS_OL,0,COLUMN()) | H9: =INDEX(MO_BSS_OL,0,COLUMN()) | I9: =INDEX(MO_BSS_OL,0,COLUMN()) | J9: =INDEX(MO_BSS_OL,0,COLUMN()) | ... CF9: =INDEX(MO_BSS_OL,0,COLUMN())
A10: Other EV Components | C10: =INDEX(MO_VA_EVCalc_NCI,0,COLUMN())+INDEX(MO_VA_EVCalc_Prefs,0,COLUMN())+INDEX(MO_VA_EVCalc_Other,0,COLUMN()) | D10: =INDEX(MO_VA_EVCalc_NCI,0,COLUMN())+INDEX(MO_VA_EVCalc_Prefs,0,COLUMN())+INDEX(MO_VA_EVCalc_Other,0,COLUMN()) | E10: =INDEX(MO_VA_EVCalc_NCI,0,COLUMN())+INDEX(MO_VA_EVCalc_Prefs,0,COLUMN())+INDEX(MO_VA_EVCalc_Other,0,COLUMN()) | F10: =INDEX(MO_VA_EVCalc_NCI,0,COLUMN())+INDEX(MO_VA_EVCalc_Prefs,0,COLUMN())+INDEX(MO_VA_EVCalc_Other,0,COLUMN()) | G10: =INDEX(MO_VA_EVCalc_NCI,0,COLUMN())+INDEX(MO_VA_EVCalc_Prefs,0,COLUMN())+INDEX(MO_VA_EVCalc_Other,0,COLUMN()) | H10: =INDEX(MO_VA_EVCalc_NCI,0,COLUMN())+INDEX(MO_VA_EVCalc_Prefs,0,COLUMN())+INDEX(MO_VA_EVCalc_Other,0,COLUMN()) | I10: =INDEX(MO_VA_EVCalc_NCI,0,COLUMN())+INDEX(MO_VA_EVCalc_Prefs,0,COLUMN())+INDEX(MO_VA_EVCalc_Other,0,COLUMN()) | J10: =INDEX(MO_VA_EVCalc_NCI,0,COLUMN())+INDEX(MO_VA_EVCalc_Prefs,0,COLUMN())+INDEX(MO_VA_EVCalc_Other,0,COLUMN()) | ... CF10: =INDEX(MO_VA_EVCalc_NCI,0,COLUMN())+INDEX(MO_VA_EVCalc_Prefs,0,COLUMN())+INDEX(MO_VA_EVCalc_Other,0,COLUMN())
A11: ="Enterprise Value - "&SP.ValuationToggle | C11: =INDEX(SP_CS_MarketCap,0,COLUMN())-INDEX(SP_CS_Cash,0,COLUMN())+INDEX(SP_CS_Debt,0,COLUMN())+INDEX(SP_CS_OL,0,COLUMN())+INDEX(SP_CS_EVCalc_Other,0,COLUMN()) | D11: =INDEX(SP_CS_MarketCap,0,COLUMN())-INDEX(SP_CS_Cash,0,COLUMN())+INDEX(SP_CS_Debt,0,COLUMN())+INDEX(SP_CS_OL,0,COLUMN())+INDEX(SP_CS_EVCalc_Other,0,COLUMN()) | E11: =INDEX(SP_CS_MarketCap,0,COLUMN())-INDEX(SP_CS_Cash,0,COLUMN())+INDEX(SP_CS_Debt,0,COLUMN())+INDEX(SP_CS_OL,0,COLUMN())+INDEX(SP_CS_EVCalc_Other,0,COLUMN()) | F11: =INDEX(SP_CS_MarketCap,0,COLUMN())-INDEX(SP_CS_Cash,0,COLUMN())+INDEX(SP_CS_Debt,0,COLUMN())+INDEX(SP_CS_OL,0,COLUMN())+INDEX(SP_CS_EVCalc_Other,0,COLUMN()) | G11: =INDEX(SP_CS_MarketCap,0,COLUMN())-INDEX(SP_CS_Cash,0,COLUMN())+INDEX(SP_CS_Debt,0,COLUMN())+INDEX(SP_CS_OL,0,COLUMN())+INDEX(SP_CS_EVCalc_Other,0,COLUMN()) | H11: =INDEX(SP_CS_MarketCap,0,COLUMN())-INDEX(SP_CS_Cash,0,COLUMN())+INDEX(SP_CS_Debt,0,COLUMN())+INDEX(SP_CS_OL,0,COLUMN())+INDEX(SP_CS_EVCalc_Other,0,COLUMN()) | I11: =INDEX(SP_CS_MarketCap,0,COLUMN())-INDEX(SP_CS_Cash,0,COLUMN())+INDEX(SP_CS_Debt,0,COLUMN())+INDEX(SP_CS_OL,0,COLUMN())+INDEX(SP_CS_EVCalc_Other,0,COLUMN()) | J11: =INDEX(SP_CS_MarketCap,0,COLUMN())-INDEX(SP_CS_Cash,0,COLUMN())+INDEX(SP_CS_Debt,0,COLUMN())+INDEX(SP_CS_OL,0,COLUMN())+INDEX(SP_CS_EVCalc_Other,0,COLUMN()) | ... CF11: =INDEX(SP_CS_MarketCap,0,COLUMN())-INDEX(SP_CS_Cash,0,COLUMN())+INDEX(SP_CS_Debt,0,COLUMN())+INDEX(SP_CS_OL,0,COLUMN())+INDEX(SP_CS_EVCalc_Other,0,COLUMN())
A13: Company-Specific Operational Data
A14: =Model!A75 | C14: =Model!C75 | D14: =Model!D75 | E14: =Model!E75 | F14: =Model!F75 | G14: =Model!G75 | H14: =Model!H75 | I14: =Model!I75 | J14: =Model!J75 | ... CF14: =Model!CF75
A15: =Model!A95 | C15: =Model!C95 | D15: =Model!D95 | E15: =Model!E95 | F15: =Model!F95 | G15: =Model!G95 | H15: =Model!H95 | I15: =Model!I95 | J15: =Model!J95 | ... CF15: =Model!CF95
A16: =Model!A115 | C16: =Model!C115 | D16: =Model!D115 | E16: =Model!E115 | F16: =Model!F115 | G16: =Model!G115 | H16: =Model!H115 | I16: =Model!I115 | J16: =Model!J115 | ... CF16: =Model!CF115
A17: =Model!A135 | C17: =Model!C135 | D17: =Model!D135 | E17: =Model!E135 | F17: =Model!F135 | G17: =Model!G135 | H17: =Model!H135 | I17: =Model!I135 | J17: =Model!J135 | ... CF17: =Model!CF135
A18: =Model!A23 | C18: =Model!C23 | D18: =Model!D23 | E18: =Model!E23 | F18: =Model!F23 | G18: =Model!G23 | H18: =Model!H23 | I18: =Model!I23 | J18: =Model!J23 | ... CF18: =Model!CF23
A19: =Model!A26 | C19: =Model!C26 | D19: =Model!D26 | E19: =Model!E26 | F19: =Model!F26 | G19: =Model!G26 | H19: =Model!H26 | I19: =Model!I26 | J19: =Model!J26 | ... CF19: =Model!CF26
A20: =Model!A33 | C20: =Model!C33 | D20: =Model!D33 | E20: =Model!E33 | F20: =Model!F33 | G20: =Model!G33 | H20: =Model!H33 | I20: =Model!I33 | J20: =Model!J33 | ... CF20: =Model!CF33
A21: =Model!A32 | C21: =Model!C32 | D21: =Model!D32 | E21: =Model!E32 | F21: =Model!F32 | G21: =Model!G32 | H21: =Model!H32 | I21: =Model!I32 | J21: =Model!J32 | ... CF21: =Model!CF32
A23: =Model!A54 | C23: =Model!C54 | D23: =Model!D54 | E23: =Model!E54 | F23: =Model!F54 | G23: =Model!G54 | H23: =Model!H54 | I23: =Model!I54 | J23: =Model!J54 | ... CF23: =Model!CF54
A24: =Model!A82 | C24: =Model!C82 | D24: =Model!D82 | E24: =Model!E82 | F24: =Model!F82 | G24: =Model!G82 | H24: =Model!H82 | I24: =Model!I82 | J24: =Model!J82 | ... CF24: =Model!CF82
A25: =Model!A102 | C25: =Model!C102 | D25: =Model!D102 | E25: =Model!E102 | F25: =Model!F102 | G25: =Model!G102 | H25: =Model!H102 | I25: =Model!I102 | J25: =Model!J102 | ... CF25: =Model!CF102
A26: =Model!A122 | C26: =Model!C122 | D26: =Model!D122 | E26: =Model!E122 | F26: =Model!F122 | G26: =Model!G122 | H26: =Model!H122 | I26: =Model!I122 | J26: =Model!J122 | ... CF26: =Model!CF122
A27: =Model!A11 | C27: =Model!C11 | D27: =Model!D11 | E27: =Model!E11 | F27: =Model!F11 | G27: =Model!G11 | H27: =Model!H11 | I27: =Model!I11 | J27: =Model!J11 | ... CF27: =Model!CF11
A29: =Model!A17 | C29: =Model!C17 | D29: =Model!D17 | E29: =Model!E17 | F29: =Model!F17 | G29: =Model!G17 | H29: =Model!H17 | I29: =Model!I17 | J29: =Model!J17 | ... CF29: =Model!CF17
A30: =Model!A18 | C30: =Model!C18 | D30: =Model!D18 | E30: =Model!E18 | F30: =Model!F18 | G30: =Model!G18 | H30: =Model!H18 | I30: =Model!I18 | J30: =Model!J18 | ... CF30: =Model!CF18
A31: =Model!A19 | C31: =Model!C19 | D31: =Model!D19 | E31: =Model!E19 | F31: =Model!F19 | G31: =Model!G19 | H31: =Model!H19 | I31: =Model!I19 | J31: =Model!J19 | ... CF31: =Model!CF19
A33: GAAP Financials
A34: =INDEX(MO_RIS_REV,0,COLUMN()) | C34: =INDEX(MO_RIS_REV,0,COLUMN()) | D34: =INDEX(MO_RIS_REV,0,COLUMN()) | E34: =INDEX(MO_RIS_REV,0,COLUMN()) | F34: =INDEX(MO_RIS_REV,0,COLUMN()) | G34: =INDEX(MO_RIS_REV,0,COLUMN()) | H34: =INDEX(MO_RIS_REV,0,COLUMN()) | I34: =INDEX(MO_RIS_REV,0,COLUMN()) | J34: =INDEX(MO_RIS_REV,0,COLUMN()) | ... CF34: =INDEX(MO_RIS_REV,0,COLUMN())
A35: =INDEX(MO_RIS_COGS,0,COLUMN()) | C35: =INDEX(MO_RIS_COGS,0,COLUMN()) | D35: =INDEX(MO_RIS_COGS,0,COLUMN()) | E35: =INDEX(MO_RIS_COGS,0,COLUMN()) | F35: =INDEX(MO_RIS_COGS,0,COLUMN()) | G35: =INDEX(MO_RIS_COGS,0,COLUMN()) | H35: =INDEX(MO_RIS_COGS,0,COLUMN()) | I35: =INDEX(MO_RIS_COGS,0,COLUMN()) | J35: =INDEX(MO_RIS_COGS,0,COLUMN()) | ... CF35: =INDEX(MO_RIS_COGS,0,COLUMN())
A36: =INDEX(MO_RIS_SM,0,COLUMN()) | C36: =INDEX(MO_RIS_SM,0,COLUMN()) | D36: =INDEX(MO_RIS_SM,0,COLUMN()) | E36: =INDEX(MO_RIS_SM,0,COLUMN()) | F36: =INDEX(MO_RIS_SM,0,COLUMN()) | G36: =INDEX(MO_RIS_SM,0,COLUMN()) | H36: =INDEX(MO_RIS_SM,0,COLUMN()) | I36: =INDEX(MO_RIS_SM,0,COLUMN()) | J36: =INDEX(MO_RIS_SM,0,COLUMN()) | ... CF36: =INDEX(MO_RIS_SM,0,COLUMN())
A37: =INDEX(MO_RIS_GA,0,COLUMN()) | C37: =INDEX(MO_RIS_GA,0,COLUMN()) | D37: =INDEX(MO_RIS_GA,0,COLUMN()) | E37: =INDEX(MO_RIS_GA,0,COLUMN()) | F37: =INDEX(MO_RIS_GA,0,COLUMN()) | G37: =INDEX(MO_RIS_GA,0,COLUMN()) | H37: =INDEX(MO_RIS_GA,0,COLUMN()) | I37: =INDEX(MO_RIS_GA,0,COLUMN()) | J37: =INDEX(MO_RIS_GA,0,COLUMN()) | ... CF37: =INDEX(MO_RIS_GA,0,COLUMN())
A38: =INDEX(MO_RIS_RD,0,COLUMN()) | C38: =INDEX(MO_RIS_RD,0,COLUMN()) | D38: =INDEX(MO_RIS_RD,0,COLUMN()) | E38: =INDEX(MO_RIS_RD,0,COLUMN()) | F38: =INDEX(MO_RIS_RD,0,COLUMN()) | G38: =INDEX(MO_RIS_RD,0,COLUMN()) | H38: =INDEX(MO_RIS_RD,0,COLUMN()) | I38: =INDEX(MO_RIS_RD,0,COLUMN()) | J38: =INDEX(MO_RIS_RD,0,COLUMN()) | ... CF38: =INDEX(MO_RIS_RD,0,COLUMN())
A39: =INDEX(MO_RIS_EBIT,0,COLUMN()) | C39: =IFERROR(INDEX(SP_GF_Rev,0,COLUMN()),0)-IFERROR(INDEX(SP_GF_COGS,0,COLUMN()),0)-IFERROR(INDEX(SP_GF_SGA,0,COLUMN()),0)-IFERROR(INDEX(SP_GF_OI_Operating,0,COLUMN()),0)-IFERROR(INDEX(SP_GF_DA_Operating,0,COLUMN()),0)-IFERROR(INDEX(SP_GF_OPEX,0,COLUMN()),0)-IFERROR(INDEX(SP_GF_RD,0,COLUMN()),0)-IFERROR(INDEX(SP_GF_SM,0,COLUMN()),0)-IFERROR(INDEX(SP_GF_GA,0,COLUMN()),0) | D39: =IFERROR(INDEX(SP_GF_Rev,0,COLUMN()),0)-IFERROR(INDEX(SP_GF_COGS,0,COLUMN()),0)-IFERROR(INDEX(SP_GF_SGA,0,COLUMN()),0)-IFERROR(INDEX(SP_GF_OI_Operating,0,COLUMN()),0)-IFERROR(INDEX(SP_GF_DA_Operating,0,COLUMN()),0)-IFERROR(INDEX(SP_GF_OPEX,0,COLUMN()),0)-IFERROR(INDEX(SP_GF_RD,0,COLUMN()),0)-IFERROR(INDEX(SP_GF_SM,0,COLUMN()),0)-IFERROR(INDEX(SP_GF_GA,0,COLUMN()),0) | E39: =IFERROR(INDEX(SP_GF_Rev,0,COLUMN()),0)-IFERROR(INDEX(SP_GF_COGS,0,COLUMN()),0)-IFERROR(INDEX(SP_GF_SGA,0,COLUMN()),0)-IFERROR(INDEX(SP_GF_OI_Operating,0,COLUMN()),0)-IFERROR(INDEX(SP_GF_DA_Operating,0,COLUMN()),0)-IFERROR(INDEX(SP_GF_OPEX,0,COLUMN()),0)-IFERROR(INDEX(SP_GF_RD,0,COLUMN()),0)-IFERROR(INDEX(SP_GF_SM,0,COLUMN()),0)-IFERROR(INDEX(SP_GF_GA,0,COLUMN()),0) | F39: =IFERROR(INDEX(SP_GF_Rev,0,COLUMN()),0)-IFERROR(INDEX(SP_GF_COGS,0,COLUMN()),0)-IFERROR(INDEX(SP_GF_SGA,0,COLUMN()),0)-IFERROR(INDEX(SP_GF_OI_Operating,0,COLUMN()),0)-IFERROR(INDEX(SP_GF_DA_Operating,0,COLUMN()),0)-IFERROR(INDEX(SP_GF_OPEX,0,COLUMN()),0)-IFERROR(INDEX(SP_GF_RD,0,COLUMN()),0)-IFERROR(INDEX(SP_GF_SM,0,COLUMN()),0)-IFERROR(INDEX(SP_GF_GA,0,COLUMN()),0) | G39: =IFERROR(INDEX(SP_GF_Rev,0,COLUMN()),0)-IFERROR(INDEX(SP_GF_COGS,0,COLUMN()),0)-IFERROR(INDEX(SP_GF_SGA,0,COLUMN()),0)-IFERROR(INDEX(SP_GF_OI_Operating,0,COLUMN()),0)-IFERROR(INDEX(SP_GF_DA_Operating,0,COLUMN()),0)-IFERROR(INDEX(SP_GF_OPEX,0,COLUMN()),0)-IFERROR(INDEX(SP_GF_RD,0,COLUMN()),0)-IFERROR(INDEX(SP_GF_SM,0,COLUMN()),0)-IFERROR(INDEX(SP_GF_GA,0,COLUMN()),0) | H39: =IFERROR(INDEX(SP_GF_Rev,0,COLUMN()),0)-IFERROR(INDEX(SP_GF_COGS,0,COLUMN()),0)-IFERROR(INDEX(SP_GF_SGA,0,COLUMN()),0)-IFERROR(INDEX(SP_GF_OI_Operating,0,COLUMN()),0)-IFERROR(INDEX(SP_GF_DA_Operating,0,COLUMN()),0)-IFERROR(INDEX(SP_GF_OPEX,0,COLUMN()),0)-IFERROR(INDEX(SP_GF_RD,0,COLUMN()),0)-IFERROR(INDEX(SP_GF_SM,0,COLUMN()),0)-IFERROR(INDEX(SP_GF_GA,0,COLUMN()),0) | I39: =IFERROR(INDEX(SP_GF_Rev,0,COLUMN()),0)-IFERROR(INDEX(SP_GF_COGS,0,COLUMN()),0)-IFERROR(INDEX(SP_GF_SGA,0,COLUMN()),0)-IFERROR(INDEX(SP_GF_OI_Operating,0,COLUMN()),0)-IFERROR(INDEX(SP_GF_DA_Operating,0,COLUMN()),0)-IFERROR(INDEX(SP_GF_OPEX,0,COLUMN()),0)-IFERROR(INDEX(SP_GF_RD,0,COLUMN()),0)-IFERROR(INDEX(SP_GF_SM,0,COLUMN()),0)-IFERROR(INDEX(SP_GF_GA,0,COLUMN()),0) | J39: =IFERROR(INDEX(SP_GF_Rev,0,COLUMN()),0)-IFERROR(INDEX(SP_GF_COGS,0,COLUMN()),0)-IFERROR(INDEX(SP_GF_SGA,0,COLUMN()),0)-IFERROR(INDEX(SP_GF_OI_Operating,0,COLUMN()),0)-IFERROR(INDEX(SP_GF_DA_Operating,0,COLUMN()),0)-IFERROR(INDEX(SP_GF_OPEX,0,COLUMN()),0)-IFERROR(INDEX(SP_GF_RD,0,COLUMN()),0)-IFERROR(INDEX(SP_GF_SM,0,COLUMN()),0)-IFERROR(INDEX(SP_GF_GA,0,COLUMN()),0) | ... CF39: =IFERROR(INDEX(SP_GF_Rev,0,COLUMN()),0)-IFERROR(INDEX(SP_GF_COGS,0,COLUMN()),0)-IFERROR(INDEX(SP_GF_SGA,0,COLUMN()),0)-IFERROR(INDEX(SP_GF_OI_Operating,0,COLUMN()),0)-IFERROR(INDEX(SP_GF_DA_Operating,0,COLUMN()),0)-IFERROR(INDEX(SP_GF_OPEX,0,COLUMN()),0)-IFERROR(INDEX(SP_GF_RD,0,COLUMN()),0)-IFERROR(INDEX(SP_GF_SM,0,COLUMN()),0)-IFERROR(INDEX(SP_GF_GA,0,COLUMN()),0)
A40: =INDEX(MO_RIS_IE,0,COLUMN()) | C40: =IFERROR(INDEX(MO_RIS_IE_Net,0,COLUMN()),INDEX(MO_RIS_IE,0,COLUMN())+INDEX(MO_RIS_II,0,COLUMN())) | D40: =IFERROR(INDEX(MO_RIS_IE_Net,0,COLUMN()),INDEX(MO_RIS_IE,0,COLUMN())+INDEX(MO_RIS_II,0,COLUMN())) | E40: =IFERROR(INDEX(MO_RIS_IE_Net,0,COLUMN()),INDEX(MO_RIS_IE,0,COLUMN())+INDEX(MO_RIS_II,0,COLUMN())) | F40: =IFERROR(INDEX(MO_RIS_IE_Net,0,COLUMN()),INDEX(MO_RIS_IE,0,COLUMN())+INDEX(MO_RIS_II,0,COLUMN())) | G40: =IFERROR(INDEX(MO_RIS_IE_Net,0,COLUMN()),INDEX(MO_RIS_IE,0,COLUMN())+INDEX(MO_RIS_II,0,COLUMN())) | H40: =IFERROR(INDEX(MO_RIS_IE_Net,0,COLUMN()),INDEX(MO_RIS_IE,0,COLUMN())+INDEX(MO_RIS_II,0,COLUMN())) | I40: =IFERROR(INDEX(MO_RIS_IE_Net,0,COLUMN()),INDEX(MO_RIS_IE,0,COLUMN())+INDEX(MO_RIS_II,0,COLUMN())) | J40: =IFERROR(INDEX(MO_RIS_IE_Net,0,COLUMN()),INDEX(MO_RIS_IE,0,COLUMN())+INDEX(MO_RIS_II,0,COLUMN())) | ... CF40: =IFERROR(INDEX(MO_RIS_IE_Net,0,COLUMN()),INDEX(MO_RIS_IE,0,COLUMN())+INDEX(MO_RIS_II,0,COLUMN()))
A41: Other Items | C41: =INDEX(MO_RIS_OI,0,COLUMN())+INDEX(MO_RIS_OTI,0,COLUMN()) | D41: =INDEX(MO_RIS_OI,0,COLUMN())+INDEX(MO_RIS_OTI,0,COLUMN()) | E41: =INDEX(MO_RIS_OI,0,COLUMN())+INDEX(MO_RIS_OTI,0,COLUMN()) | F41: =INDEX(MO_RIS_OI,0,COLUMN())+INDEX(MO_RIS_OTI,0,COLUMN()) | G41: =INDEX(MO_RIS_OI,0,COLUMN())+INDEX(MO_RIS_OTI,0,COLUMN()) | H41: =INDEX(MO_RIS_OI,0,COLUMN())+INDEX(MO_RIS_OTI,0,COLUMN()) | I41: =INDEX(MO_RIS_OI,0,COLUMN())+INDEX(MO_RIS_OTI,0,COLUMN()) | J41: =INDEX(MO_RIS_OI,0,COLUMN())+INDEX(MO_RIS_OTI,0,COLUMN()) | ... CF41: =INDEX(MO_RIS_OI,0,COLUMN())+INDEX(MO_RIS_OTI,0,COLUMN())
A42: =INDEX(MO_RIS_EBT,0,COLUMN()) | C42: =INDEX(SP_GF_EBIT,0,COLUMN())-INDEX(SP_GF_IE,0,COLUMN())-INDEX(SP_GF_OI,0,COLUMN()) | D42: =INDEX(SP_GF_EBIT,0,COLUMN())-INDEX(SP_GF_IE,0,COLUMN())-INDEX(SP_GF_OI,0,COLUMN()) | E42: =INDEX(SP_GF_EBIT,0,COLUMN())-INDEX(SP_GF_IE,0,COLUMN())-INDEX(SP_GF_OI,0,COLUMN()) | F42: =INDEX(SP_GF_EBIT,0,COLUMN())-INDEX(SP_GF_IE,0,COLUMN())-INDEX(SP_GF_OI,0,COLUMN()) | G42: =INDEX(SP_GF_EBIT,0,COLUMN())-INDEX(SP_GF_IE,0,COLUMN())-INDEX(SP_GF_OI,0,COLUMN()) | H42: =INDEX(SP_GF_EBIT,0,COLUMN())-INDEX(SP_GF_IE,0,COLUMN())-INDEX(SP_GF_OI,0,COLUMN()) | I42: =INDEX(SP_GF_EBIT,0,COLUMN())-INDEX(SP_GF_IE,0,COLUMN())-INDEX(SP_GF_OI,0,COLUMN()) | J42: =INDEX(SP_GF_EBIT,0,COLUMN())-INDEX(SP_GF_IE,0,COLUMN())-INDEX(SP_GF_OI,0,COLUMN()) | ... CF42: =INDEX(SP_GF_EBIT,0,COLUMN())-INDEX(SP_GF_IE,0,COLUMN())-INDEX(SP_GF_OI,0,COLUMN())
A43: Tax | C43: =INDEX(MO_RIS_Tax_Current,0,COLUMN())+INDEX(MO_RIS_Tax_Deferred,0,COLUMN()) | D43: =INDEX(MO_RIS_Tax_Current,0,COLUMN())+INDEX(MO_RIS_Tax_Deferred,0,COLUMN()) | E43: =INDEX(MO_RIS_Tax_Current,0,COLUMN())+INDEX(MO_RIS_Tax_Deferred,0,COLUMN()) | F43: =INDEX(MO_RIS_Tax_Current,0,COLUMN())+INDEX(MO_RIS_Tax_Deferred,0,COLUMN()) | G43: =INDEX(MO_RIS_Tax_Current,0,COLUMN())+INDEX(MO_RIS_Tax_Deferred,0,COLUMN()) | H43: =INDEX(MO_RIS_Tax_Current,0,COLUMN())+INDEX(MO_RIS_Tax_Deferred,0,COLUMN()) | I43: =INDEX(MO_RIS_Tax_Current,0,COLUMN())+INDEX(MO_RIS_Tax_Deferred,0,COLUMN()) | J43: =INDEX(MO_RIS_Tax_Current,0,COLUMN())+INDEX(MO_RIS_Tax_Deferred,0,COLUMN()) | ... CF43: =INDEX(MO_RIS_Tax_Current,0,COLUMN())+INDEX(MO_RIS_Tax_Deferred,0,COLUMN())
A44: =INDEX(MO_RIS_DisCont,0,COLUMN()) | C44: =INDEX(MO_RIS_DisCont,0,COLUMN()) | D44: =INDEX(MO_RIS_DisCont,0,COLUMN()) | E44: =INDEX(MO_RIS_DisCont,0,COLUMN()) | F44: =INDEX(MO_RIS_DisCont,0,COLUMN()) | G44: =INDEX(MO_RIS_DisCont,0,COLUMN()) | H44: =INDEX(MO_RIS_DisCont,0,COLUMN()) | I44: =INDEX(MO_RIS_DisCont,0,COLUMN()) | J44: =INDEX(MO_RIS_DisCont,0,COLUMN()) | ... CF44: =INDEX(MO_RIS_DisCont,0,COLUMN())
A45: =INDEX(MO_RIS_NCI,0,COLUMN()) | C45: =INDEX(MO_RIS_NCI,0,COLUMN()) | D45: =INDEX(MO_RIS_NCI,0,COLUMN()) | E45: =INDEX(MO_RIS_NCI,0,COLUMN()) | F45: =INDEX(MO_RIS_NCI,0,COLUMN()) | G45: =INDEX(MO_RIS_NCI,0,COLUMN()) | H45: =INDEX(MO_RIS_NCI,0,COLUMN()) | I45: =INDEX(MO_RIS_NCI,0,COLUMN()) | J45: =INDEX(MO_RIS_NCI,0,COLUMN()) | ... CF45: =INDEX(MO_RIS_NCI,0,COLUMN())
A46: =INDEX(MO_RIS_Dividend_Prefs,0,COLUMN()) | C46: =INDEX(MO_RIS_Dividend_Prefs,0,COLUMN()) | D46: =INDEX(MO_RIS_Dividend_Prefs,0,COLUMN()) | E46: =INDEX(MO_RIS_Dividend_Prefs,0,COLUMN()) | F46: =INDEX(MO_RIS_Dividend_Prefs,0,COLUMN()) | G46: =INDEX(MO_RIS_Dividend_Prefs,0,COLUMN()) | H46: =INDEX(MO_RIS_Dividend_Prefs,0,COLUMN()) | I46: =INDEX(MO_RIS_Dividend_Prefs,0,COLUMN()) | J46: =INDEX(MO_RIS_Dividend_Prefs,0,COLUMN()) | ... CF46: =INDEX(MO_RIS_Dividend_Prefs,0,COLUMN())
A47: =INDEX(MO_RIS_NI_GAAP_Basic,0,COLUMN()) | C47: =INDEX(MO_RIS_NI_GAAP_Basic,0,COLUMN()) | D47: =INDEX(MO_RIS_NI_GAAP_Basic,0,COLUMN()) | E47: =INDEX(MO_RIS_NI_GAAP_Basic,0,COLUMN()) | F47: =INDEX(MO_RIS_NI_GAAP_Basic,0,COLUMN()) | G47: =INDEX(MO_RIS_NI_GAAP_Basic,0,COLUMN()) | H47: =INDEX(MO_RIS_NI_GAAP_Basic,0,COLUMN()) | I47: =INDEX(MO_RIS_NI_GAAP_Basic,0,COLUMN()) | J47: =INDEX(MO_RIS_NI_GAAP_Basic,0,COLUMN()) | ... CF47: =INDEX(MO_RIS_NI_GAAP_Basic,0,COLUMN())
A48: =INDEX(MO_RIS_Adjustments_Dilution_GAAP,0,COLUMN()) | C48: =INDEX(MO_RIS_Adjustments_Dilution_GAAP,0,COLUMN()) | D48: =INDEX(MO_RIS_Adjustments_Dilution_GAAP,0,COLUMN()) | E48: =INDEX(MO_RIS_Adjustments_Dilution_GAAP,0,COLUMN()) | F48: =INDEX(MO_RIS_Adjustments_Dilution_GAAP,0,COLUMN()) | G48: =INDEX(MO_RIS_Adjustments_Dilution_GAAP,0,COLUMN()) | H48: =INDEX(MO_RIS_Adjustments_Dilution_GAAP,0,COLUMN()) | I48: =INDEX(MO_RIS_Adjustments_Dilution_GAAP,0,COLUMN()) | J48: =INDEX(MO_RIS_Adjustments_Dilution_GAAP,0,COLUMN()) | ... CF48: =INDEX(MO_RIS_Adjustments_Dilution_GAAP,0,COLUMN())
A49: =INDEX(MO_RIS_NI_GAAP_Diluted,0,COLUMN()) | C49: =INDEX(MO_RIS_NI_GAAP_Diluted,0,COLUMN()) | D49: =INDEX(MO_RIS_NI_GAAP_Diluted,0,COLUMN()) | E49: =INDEX(MO_RIS_NI_GAAP_Diluted,0,COLUMN()) | F49: =INDEX(MO_RIS_NI_GAAP_Diluted,0,COLUMN()) | G49: =INDEX(MO_RIS_NI_GAAP_Diluted,0,COLUMN()) | H49: =INDEX(MO_RIS_NI_GAAP_Diluted,0,COLUMN()) | I49: =INDEX(MO_RIS_NI_GAAP_Diluted,0,COLUMN()) | J49: =INDEX(MO_RIS_NI_GAAP_Diluted,0,COLUMN()) | ... CF49: =INDEX(MO_RIS_NI_GAAP_Diluted,0,COLUMN())
A50: =INDEX(MO_RIS_EPS_WAD,0,COLUMN()) | C50: =INDEX(MO_RIS_EPS_WAD,0,COLUMN()) | D50: =INDEX(MO_RIS_EPS_WAD,0,COLUMN()) | E50: =INDEX(MO_RIS_EPS_WAD,0,COLUMN()) | F50: =INDEX(MO_RIS_EPS_WAD,0,COLUMN()) | G50: =INDEX(MO_RIS_EPS_WAD,0,COLUMN()) | H50: =INDEX(MO_RIS_EPS_WAD,0,COLUMN()) | I50: =INDEX(MO_RIS_EPS_WAD,0,COLUMN()) | J50: =INDEX(MO_RIS_EPS_WAD,0,COLUMN()) | ... CF50: =INDEX(MO_RIS_EPS_WAD,0,COLUMN())
A51: =INDEX(MO_RIS_ShareCount_WAD_Adj,0,COLUMN()) | C51: =INDEX(MO_RIS_ShareCount_WAD_Adj,0,COLUMN()) | D51: =INDEX(MO_RIS_ShareCount_WAD_Adj,0,COLUMN()) | E51: =INDEX(MO_RIS_ShareCount_WAD_Adj,0,COLUMN()) | F51: =INDEX(MO_RIS_ShareCount_WAD_Adj,0,COLUMN()) | G51: =INDEX(MO_RIS_ShareCount_WAD_Adj,0,COLUMN()) | H51: =INDEX(MO_RIS_ShareCount_WAD_Adj,0,COLUMN()) | I51: =INDEX(MO_RIS_ShareCount_WAD_Adj,0,COLUMN()) | J51: =INDEX(MO_RIS_ShareCount_WAD_Adj,0,COLUMN()) | ... CF51: =INDEX(MO_RIS_ShareCount_WAD_Adj,0,COLUMN())
A53: Non-GAAP Financials
A54: =INDEX(MO_RIS_EBITDA_Adj,0,COLUMN()) | C54: =INDEX(MO_RIS_EBITDA_Adj,0,COLUMN()) | D54: =INDEX(MO_RIS_EBITDA_Adj,0,COLUMN()) | E54: =INDEX(MO_RIS_EBITDA_Adj,0,COLUMN()) | F54: =INDEX(MO_RIS_EBITDA_Adj,0,COLUMN()) | G54: =INDEX(MO_RIS_EBITDA_Adj,0,COLUMN()) | H54: =INDEX(MO_RIS_EBITDA_Adj,0,COLUMN()) | I54: =INDEX(MO_RIS_EBITDA_Adj,0,COLUMN()) | J54: =INDEX(MO_RIS_EBITDA_Adj,0,COLUMN()) | ... CF54: =INDEX(MO_RIS_EBITDA_Adj,0,COLUMN())
A55: =INDEX(MO_RIS_EBIT_Adj,0,COLUMN()) | C55: =INDEX(MO_RIS_EBIT_Adj,0,COLUMN()) | D55: =INDEX(MO_RIS_EBIT_Adj,0,COLUMN()) | E55: =INDEX(MO_RIS_EBIT_Adj,0,COLUMN()) | F55: =INDEX(MO_RIS_EBIT_Adj,0,COLUMN()) | G55: =INDEX(MO_RIS_EBIT_Adj,0,COLUMN()) | H55: =INDEX(MO_RIS_EBIT_Adj,0,COLUMN()) | I55: =INDEX(MO_RIS_EBIT_Adj,0,COLUMN()) | J55: =INDEX(MO_RIS_EBIT_Adj,0,COLUMN()) | ... CF55: =INDEX(MO_RIS_EBIT_Adj,0,COLUMN())
A56: =INDEX(MO_RIS_NI_NONGAAP_Diluted,0,COLUMN()) | C56: =INDEX(MO_RIS_NI_NONGAAP_Diluted,0,COLUMN()) | D56: =INDEX(MO_RIS_NI_NONGAAP_Diluted,0,COLUMN()) | E56: =INDEX(MO_RIS_NI_NONGAAP_Diluted,0,COLUMN()) | F56: =INDEX(MO_RIS_NI_NONGAAP_Diluted,0,COLUMN()) | G56: =INDEX(MO_RIS_NI_NONGAAP_Diluted,0,COLUMN()) | H56: =INDEX(MO_RIS_NI_NONGAAP_Diluted,0,COLUMN()) | I56: =INDEX(MO_RIS_NI_NONGAAP_Diluted,0,COLUMN()) | J56: =INDEX(MO_RIS_NI_NONGAAP_Diluted,0,COLUMN()) | ... CF56: =INDEX(MO_RIS_NI_NONGAAP_Diluted,0,COLUMN())
A57: =INDEX(MO_RIS_EPS_WAD_Adj,0,COLUMN()) | C57: =INDEX(MO_RIS_EPS_WAD_Adj,0,COLUMN()) | D57: =INDEX(MO_RIS_EPS_WAD_Adj,0,COLUMN()) | E57: =INDEX(MO_RIS_EPS_WAD_Adj,0,COLUMN()) | F57: =INDEX(MO_RIS_EPS_WAD_Adj,0,COLUMN()) | G57: =INDEX(MO_RIS_EPS_WAD_Adj,0,COLUMN()) | H57: =INDEX(MO_RIS_EPS_WAD_Adj,0,COLUMN()) | I57: =INDEX(MO_RIS_EPS_WAD_Adj,0,COLUMN()) | J57: =INDEX(MO_RIS_EPS_WAD_Adj,0,COLUMN()) | ... CF57: =INDEX(MO_RIS_EPS_WAD_Adj,0,COLUMN())
A59: Margin Analysis
A60: =INDEX(MO_MA_COGS,0,COLUMN()) | C60: =INDEX(MO_MA_COGS,0,COLUMN()) | D60: =INDEX(MO_MA_COGS,0,COLUMN()) | E60: =INDEX(MO_MA_COGS,0,COLUMN()) | F60: =INDEX(MO_MA_COGS,0,COLUMN()) | G60: =INDEX(MO_MA_COGS,0,COLUMN()) | H60: =INDEX(MO_MA_COGS,0,COLUMN()) | I60: =INDEX(MO_MA_COGS,0,COLUMN()) | J60: =INDEX(MO_MA_COGS,0,COLUMN()) | ... CF60: =INDEX(MO_MA_COGS,0,COLUMN())
A61: =INDEX(MO_MA_SM,0,COLUMN()) | C61: =INDEX(MO_MA_SM,0,COLUMN()) | D61: =INDEX(MO_MA_SM,0,COLUMN()) | E61: =INDEX(MO_MA_SM,0,COLUMN()) | F61: =INDEX(MO_MA_SM,0,COLUMN()) | G61: =INDEX(MO_MA_SM,0,COLUMN()) | H61: =INDEX(MO_MA_SM,0,COLUMN()) | I61: =INDEX(MO_MA_SM,0,COLUMN()) | J61: =INDEX(MO_MA_SM,0,COLUMN()) | ... CF61: =INDEX(MO_MA_SM,0,COLUMN())
A62: =INDEX(MO_MA_GA,0,COLUMN()) | C62: =INDEX(MO_MA_GA,0,COLUMN()) | D62: =INDEX(MO_MA_GA,0,COLUMN()) | E62: =INDEX(MO_MA_GA,0,COLUMN()) | F62: =INDEX(MO_MA_GA,0,COLUMN()) | G62: =INDEX(MO_MA_GA,0,COLUMN()) | H62: =INDEX(MO_MA_GA,0,COLUMN()) | I62: =INDEX(MO_MA_GA,0,COLUMN()) | J62: =INDEX(MO_MA_GA,0,COLUMN()) | ... CF62: =INDEX(MO_MA_GA,0,COLUMN())
A63: =INDEX(MO_MA_RD,0,COLUMN()) | C63: =INDEX(SP_GF_RD,0,COLUMN())/INDEX(SP_GF_Rev,0,COLUMN()) | D63: =INDEX(SP_GF_RD,0,COLUMN())/INDEX(SP_GF_Rev,0,COLUMN()) | E63: =INDEX(SP_GF_RD,0,COLUMN())/INDEX(SP_GF_Rev,0,COLUMN()) | F63: =INDEX(SP_GF_RD,0,COLUMN())/INDEX(SP_GF_Rev,0,COLUMN()) | G63: =INDEX(SP_GF_RD,0,COLUMN())/INDEX(SP_GF_Rev,0,COLUMN()) | H63: =INDEX(SP_GF_RD,0,COLUMN())/INDEX(SP_GF_Rev,0,COLUMN()) | I63: =INDEX(SP_GF_RD,0,COLUMN())/INDEX(SP_GF_Rev,0,COLUMN()) | J63: =INDEX(SP_GF_RD,0,COLUMN())/INDEX(SP_GF_Rev,0,COLUMN()) | ... CF63: =INDEX(SP_GF_RD,0,COLUMN())/INDEX(SP_GF_Rev,0,COLUMN())
A64: =INDEX(MO_MA_EBIT,0,COLUMN()) | C64: =INDEX(MO_MA_EBIT,0,COLUMN()) | D64: =INDEX(MO_MA_EBIT,0,COLUMN()) | E64: =INDEX(MO_MA_EBIT,0,COLUMN()) | F64: =INDEX(MO_MA_EBIT,0,COLUMN()) | G64: =INDEX(MO_MA_EBIT,0,COLUMN()) | H64: =INDEX(MO_MA_EBIT,0,COLUMN()) | I64: =INDEX(MO_MA_EBIT,0,COLUMN()) | J64: =INDEX(MO_MA_EBIT,0,COLUMN()) | ... CF64: =INDEX(MO_MA_EBIT,0,COLUMN())
A65: =INDEX(MO_MA_EBIT_Adj,0,COLUMN()) | C65: =INDEX(MO_MA_EBIT_Adj,0,COLUMN()) | D65: =INDEX(MO_MA_EBIT_Adj,0,COLUMN()) | E65: =INDEX(MO_MA_EBIT_Adj,0,COLUMN()) | F65: =INDEX(MO_MA_EBIT_Adj,0,COLUMN()) | G65: =INDEX(MO_MA_EBIT_Adj,0,COLUMN()) | H65: =INDEX(MO_MA_EBIT_Adj,0,COLUMN()) | I65: =INDEX(MO_MA_EBIT_Adj,0,COLUMN()) | J65: =INDEX(MO_MA_EBIT_Adj,0,COLUMN()) | ... CF65: =INDEX(MO_MA_EBIT_Adj,0,COLUMN())
A66: =INDEX(MO_MA_EBITDA,0,COLUMN()) | C66: =INDEX(MO_MA_EBITDA,0,COLUMN()) | D66: =INDEX(MO_MA_EBITDA,0,COLUMN()) | E66: =INDEX(MO_MA_EBITDA,0,COLUMN()) | F66: =INDEX(MO_MA_EBITDA,0,COLUMN()) | G66: =INDEX(MO_MA_EBITDA,0,COLUMN()) | H66: =INDEX(MO_MA_EBITDA,0,COLUMN()) | I66: =INDEX(MO_MA_EBITDA,0,COLUMN()) | J66: =INDEX(MO_MA_EBITDA,0,COLUMN()) | ... CF66: =INDEX(MO_MA_EBITDA,0,COLUMN())
A67: =INDEX(MO_MA_EBITDA_Adj,0,COLUMN()) | C67: =INDEX(SP_Company1876_EBITDA,0,COLUMN())/INDEX(SP_GF_Rev,0,COLUMN()) | D67: =INDEX(SP_Company1876_EBITDA,0,COLUMN())/INDEX(SP_GF_Rev,0,COLUMN()) | E67: =INDEX(SP_Company1876_EBITDA,0,COLUMN())/INDEX(SP_GF_Rev,0,COLUMN()) | F67: =INDEX(SP_Company1876_EBITDA,0,COLUMN())/INDEX(SP_GF_Rev,0,COLUMN()) | G67: =INDEX(SP_Company1876_EBITDA,0,COLUMN())/INDEX(SP_GF_Rev,0,COLUMN()) | H67: =INDEX(SP_Company1876_EBITDA,0,COLUMN())/INDEX(SP_GF_Rev,0,COLUMN()) | I67: =INDEX(SP_Company1876_EBITDA,0,COLUMN())/INDEX(SP_GF_Rev,0,COLUMN()) | J67: =INDEX(SP_Company1876_EBITDA,0,COLUMN())/INDEX(SP_GF_Rev,0,COLUMN()) | ... CF67: =INDEX(SP_Company1876_EBITDA,0,COLUMN())/INDEX(SP_GF_Rev,0,COLUMN())
A69: Cash Flow Analysis
A70: =INDEX(MO_CFSum_CFO_BeforeWC,0,COLUMN()) | C70: =INDEX(MO_CFSum_CFO_BeforeWC,0,COLUMN()) | D70: =INDEX(MO_CFSum_CFO_BeforeWC,0,COLUMN()) | E70: =INDEX(MO_CFSum_CFO_BeforeWC,0,COLUMN()) | F70: =INDEX(MO_CFSum_CFO_BeforeWC,0,COLUMN()) | G70: =INDEX(MO_CFSum_CFO_BeforeWC,0,COLUMN()) | H70: =INDEX(MO_CFSum_CFO_BeforeWC,0,COLUMN()) | I70: =INDEX(MO_CFSum_CFO_BeforeWC,0,COLUMN()) | J70: =INDEX(MO_CFSum_CFO_BeforeWC,0,COLUMN()) | ... CF70: =INDEX(MO_CFSum_CFO_BeforeWC,0,COLUMN())
A71: Change in WC | C71: =SUM(OFFSET(INDEX(MO_CFS_CFO_BeforeWC,0,COLUMN()),1,0,ROW(INDEX(MO_CFS_CFO,0,COLUMN()))-ROW(INDEX(MO_CFS_CFO_BeforeWC,0,COLUMN()))-1,1)) | D71: =SUM(OFFSET(INDEX(MO_CFS_CFO_BeforeWC,0,COLUMN()),1,0,ROW(INDEX(MO_CFS_CFO,0,COLUMN()))-ROW(INDEX(MO_CFS_CFO_BeforeWC,0,COLUMN()))-1,1)) | E71: =SUM(OFFSET(INDEX(MO_CFS_CFO_BeforeWC,0,COLUMN()),1,0,ROW(INDEX(MO_CFS_CFO,0,COLUMN()))-ROW(INDEX(MO_CFS_CFO_BeforeWC,0,COLUMN()))-1,1)) | F71: =SUM(OFFSET(INDEX(MO_CFS_CFO_BeforeWC,0,COLUMN()),1,0,ROW(INDEX(MO_CFS_CFO,0,COLUMN()))-ROW(INDEX(MO_CFS_CFO_BeforeWC,0,COLUMN()))-1,1)) | G71: =SUM(OFFSET(INDEX(MO_CFS_CFO_BeforeWC,0,COLUMN()),1,0,ROW(INDEX(MO_CFS_CFO,0,COLUMN()))-ROW(INDEX(MO_CFS_CFO_BeforeWC,0,COLUMN()))-1,1)) | H71: =SUM(OFFSET(INDEX(MO_CFS_CFO_BeforeWC,0,COLUMN()),1,0,ROW(INDEX(MO_CFS_CFO,0,COLUMN()))-ROW(INDEX(MO_CFS_CFO_BeforeWC,0,COLUMN()))-1,1)) | I71: =SUM(OFFSET(INDEX(MO_CFS_CFO_BeforeWC,0,COLUMN()),1,0,ROW(INDEX(MO_CFS_CFO,0,COLUMN()))-ROW(INDEX(MO_CFS_CFO_BeforeWC,0,COLUMN()))-1,1)) | J71: =SUM(OFFSET(INDEX(MO_CFS_CFO_BeforeWC,0,COLUMN()),1,0,ROW(INDEX(MO_CFS_CFO,0,COLUMN()))-ROW(INDEX(MO_CFS_CFO_BeforeWC,0,COLUMN()))-1,1)) | ... CF71: =SUM(OFFSET(INDEX(MO_CFS_CFO_BeforeWC,0,COLUMN()),1,0,ROW(INDEX(MO_CFS_CFO,0,COLUMN()))-ROW(INDEX(MO_CFS_CFO_BeforeWC,0,COLUMN()))-1,1))
