Workbook
Name CIRCULARITY: 'Model Summary'!$D$11
Name CRT: 'Model Summary'!$D$6
Name GrowthCase: 'Model Summary'!$D$7
Name Mergers: 'Model Summary'!$D$4
Name MultipleExpansion: 'Model Summary'!$D$8
Name SOFR: 'Model Summary'!$D$9
Name XSell: 'Model Summary'!$D$5

Sheet Model Summary
C3: Toggles:
C4: M&A | D4: No
C5: Cross-Sell | D5: Base
C6: Cost Reduction | D6: Base
C7: Growth Case | D7: Base
C8: Multiple Expansion | D8: Yes
C9: SOFR Curve | D9: Forward Curve
C11: CIRC | D11: 1
C12: INPUT: EBITDA and Annual Debt Paydown | M12: INPUT: Purchase Price / Capitalization | U12: Returns by Year
E13: Est. Dec | F13: Projected | Q13: PF
E14: 2024 | F14: =E14+1 -> 2025 | G14: =F14+1 -> 2026 | H14: =G14+1 -> 2027 | I14: =H14+1 -> 2028 | J14: =I14+1 -> 2029 | K14: CAGR | P14: pre fee | Q14: w/ fee | V14: Exit Year | W14: IRR | X14: MOIC
A15: A | C15: Organic Revenue | E15: ='Operating Build'!Q23 -> 1288.3681 | F15: =E15*(1+F16) -> 1349.2524 | G15: =F15*(1+G16) -> 1420.6578 | H15: =G15*(1+H16) -> 1512.1049 | I15: =H15*(1+I16) -> 1621.2493 | J15: =I15*(1+J16) -> 1742.3495 | K15: =(J15/E15)^(1/5)-1 -> 0.062231217 | M15: TEV / Price Paid | P15: =H100 -> 715 | Q15: =H102 -> 715 | V15: 1 | W15: =INDEX($F$216:$J$216, MATCH($V15, $F$215:$J$215, 0)) -> 0.56661787 | X15: =INDEX($F$214:$J$214, MATCH($V15, $F$215:$J$215, 0)) -> 1.5666179
C16: % growth | F16: =F52 -> 0.047256875 | G16: =G52 -> 0.052922166 | H16: =H52 -> 0.064369549 | I16: =I52 -> 0.072180494 | J16: =J52 -> 0.074695598 | M16: FY EBITDA | N16: =E29 -> 81.607343 | P16: =P$15/N16 -> 8.7614665 | Q16: =Q$15/N16 -> 8.7614665 | S16: H | V16: 2 | W16: =INDEX($F$216:$J$216, MATCH($V16, $F$215:$J$215, 0)) -> 0.44556915 | X16: =INDEX($F$214:$J$214, MATCH($V16, $F$215:$J$215, 0)) -> 2.0896702
V17: 3 | W17: =INDEX($F$216:$J$216, MATCH($V17, $F$215:$J$215, 0)) -> 0.35886934 | X17: =INDEX($F$214:$J$214, MATCH($V17, $F$215:$J$215, 0)) -> 2.5091874
A18: B | C18: Gross Profit | E18: ='Operating Build'!Q45 -> 256.991 | F18: =F19*F15 -> 270.18162 | G18: =G19*G15 -> 284.70873 | H18: =H19*H15 -> 302.8315 | I18: =I19*I15 -> 324.2819 | J18: =J19*J15 -> 348.06719 | K18: =(J18/E18)^(1/5)-1 -> 0.06254917 | M18: Revolver / (Cash) | Q18: =SUM(O$17:O18)/N16 -> 0 | V18: 4 | W18: =INDEX($F$216:$J$216, MATCH($V18, $F$215:$J$215, 0)) -> 0.31571157 | X18: =INDEX($F$214:$J$214, MATCH($V18, $F$215:$J$215, 0)) -> 2.9966966
C19: % margin | E19: =E18/E15 -> 0.19947016 | F19: =F53 -> 0.20024543 | G19: =G53 -> 0.20040628 | H19: =H53 -> 0.2002715 | I19: =I53 -> 0.20001976 | J19: =J53 -> 0.19976887 | M19: 1st Lien / Senior Debt | O19: =G105 -> 118.6 | Q19: =SUM(O$17:O19)/N16 -> 1.4533006 | V19: 5 | W19: =INDEX($F$216:$J$216, MATCH($V19, $F$215:$J$215, 0)) -> 0.28839736 | X19: =INDEX($F$214:$J$214, MATCH($V19, $F$215:$J$215, 0)) -> 3.5501699
M20: 2nd Lien / Sub Debt | O20: =G106 -> 200 | Q20: =SUM(O$17:O20)/N16 -> 3.9040604
A21: C | C21: SG&A | E21: =-('Operating Build'!Q49+'Operating Build'!Q52) -> 179.21915 | F21: =F22*F15 -> 175.2079 | G21: =G22*G15 -> 171.3392 | H21: =H22*H15 -> 176.57182 | I21: =I22*I15 -> 183.10207 | J21: =J22*J15 -> 190.09999 | K21: =(J21/E21)^(1/5)-1 -> 0.011857921 | M21: Total Debt | N21: =O21/O26 -> 0.44559441 | O21: =SUM(O17:O20) -> 318.6 | Q21: =Q20 -> 3.9040604
C22: % margin | E22: =E21/E15 -> 0.13910554 | F22: =F54 -> 0.12985554 | G22: =G54 -> 0.12060554 | H22: =H54 -> 0.11677221 | I22: =I54 -> 0.11293887 | J22: =J54 -> 0.10910554 | M22: Rollover Equity | O22: 0 | S22: I
C24: Adjustments | E24: 3.8354945 | F24: 0 | G24: 0 | H24: 0 | I24: 0 | J24: 0 | M24: PE Sponsor | O24: =H108-O22 -> 396.4
C25: Organic EBITDA | E25: =E18-E21+E24 -> 81.607343 | F25: =F18-F21+F24 -> 94.973724 | G25: =G18-G21+G24 -> 113.36954 | H25: =H18-H21+H24 -> 126.25968 | I25: =I18-I21+I24 -> 141.17982 | J25: =J18-J21+J24 -> 157.96721 | K25: =(J25/E25)^(1/5)-1 -> 0.14121518 | M25: Total Equity | N25: =O25/O26 -> 0.55440559 | O25: =O22+O24 -> 396.4 | Q25: =(O25+O21)/N16 -> 8.7614665
C26: % margin | E26: =E25/E15 -> 0.063341634 | F26: =F25/F15 -> 0.070389887 | G26: =G25/G15 -> 0.079800738 | H26: =H25/H15 -> 0.083499289 | I26: =I25/I15 -> 0.087080882 | J26: =J25/J15 -> 0.090663328 | M26: Total Sources | O26: =O25+O21 -> 715 | Q26: =Q25 -> 8.7614665
A28: Acq | C28: Add-on Acq EBITDA | E28: 0 | F28: =F153 -> 0 | G28: =G153 -> 0 | H28: =H153 -> 0 | I28: =I153 -> 0 | J28: =J153 -> 0
C29: Total EBITDA | E29: =E25+E28 -> 81.607343 | F29: =F25+F28 -> 94.973724 | G29: =G25+G28 -> 113.36954 | H29: =H25+H28 -> 126.25968 | I29: =I25+I28 -> 141.17982 | J29: =J25+J28 -> 157.96721 | K29: =(J29/E29)^(1/5)-1 -> 0.14121518
C30: % margin | E30: =E29/E15 -> 0.063341634 | F30: =F29/F15 -> 0.070389887 | G30: =G29/G15 -> 0.079800738 | H30: =H29/H15 -> 0.083499289 | I30: =I29/I15 -> 0.087080882 | J30: =J29/J15 -> 0.090663328 | M30: Downside Return | P30: =J214 -> 3.5501699 | Q30: =J216 -> 0.28839736 | S30: J
O31: Exit Multiple
A32: D | C32: Capex | E32: ='Operating Build'!L112 -> -25.391958 | F32: =F60+F61 -> -22.114506 | G32: =G60+G61 -> -23.284853 | H32: =H60+H61 -> -24.783689 | I32: =I60+I61 -> -26.572588 | J32: =J60+J61 -> -28.557443 | N32: =J216 -> 0.28839736 | O32: =P32-0.5 -> 9.2614665 | P32: =H116 -> 9.7614665 | Q32: =P32+0.5 -> 10.261466
A33: Acq | C33: Add-on Acq Price (if debt) | F33: =-F145 -> 0 | G33: =-G145 -> 0 | H33: =-H145 -> 0 | I33: =-I145 -> 0 | J33: =-J145 -> 0 | N33: =N34*0.9 -> 142.17048 | O33: 0.24752186 | P33: 0.26099854 | Q33: 0.27392258
A34: E | C34: Change in NWC | F34: =F66+F67 -> -6.3843508 | G34: =G66+G67 -> -7.0861113 | H34: =H66+H67 -> -8.1493559 | I34: =I66+I67 -> -9.6407084 | J34: =J66+J67 -> -10.709711 | M34: Exit EBITDA | N34: =J29 -> 157.96721 | O34: 0.27465759 | P34: 0.28839736 | Q34: 0.30157487
A35: F | C35: Interest | F35: =IF(CIRCULARITY=1,-F83,-0.69) -> -30.833899 | G35: =IF(CIRCULARITY=1,-G83,-0.69) -> -25.801878 | H35: =IF(CIRCULARITY=1,-H83,-0.69) -> -22.738482 | I35: =IF(CIRCULARITY=1,-I83,-0.69) -> -21.515024 | J35: =IF(CIRCULARITY=1,-J83,-0.69) -> -21.592168 | N35: =N34*1.1 -> 173.76393 | O35: 0.29966186 | P35: 0.31364619 | Q35: 0.32705921
A36: G | C36: Cash taxes | F36: =-F91 -> -8.456303 | G36: =-G91 -> -13.822785 | H36: =-H91 -> -17.60127 | I36: =-I91 -> -21.299727 | J36: =-J91 -> -25.066828 | K36: cum
C37: Annual Debt Paydown | F37: =SUM(F32:F36)+F29 -> 27.184665 | G37: =SUM(G32:G36)+G29 -> 43.373909 | H37: =SUM(H32:H36)+H29 -> 52.986885 | I37: =SUM(I32:I36)+I29 -> 62.151775 | J37: =SUM(J32:J36)+J29 -> 72.041055 | K37: =SUM(F37:J37) -> 257.73829 | M37: Value Creation: | O37: At Acq. | P37: Exit | Q37: Change
C38: Ending Net Debt | E38: =H107 -> 318.6 | F38: =E38-F37 -> 291.41533 | G38: =F38-G37 -> 248.04143 | H38: =G38-H37 -> 195.05454 | I38: =H38-I37 -> 132.90277 | J38: =I38-J37 -> 60.861711 | K38: =SUM(E38-J38) -> 257.73829 | M38: EBITDA | O38: =E29 -> 81.607343 | P38: =J29 -> 157.96721 | Q38: =(P38-O38)*O39 -> 669.02437
C39: Debt / EBITDA | E39: =E38/E29 -> 3.9040604 | F39: =F38/F29 -> 3.0683785 | G39: =G38/G29 -> 2.1879019 | H39: =H38/H29 -> 1.544868 | I39: =I38/I29 -> 0.94137224 | J39: =J38/J29 -> 0.38528067 | M39: TEV mult | O39: =P16 -> 8.7614665 | P39: =H116 -> 9.7614665 | Q39: =(P39-O39)*P38 -> 157.96721
C40: EBITDA-Capex / Interest | E40: =(E29+E32)/-F35 -> 1.8231682 | F40: =(F29+F32)/-F35 -> 2.3629583 | G40: =(G29+G32)/-G35 -> 3.4914003 | H40: =(H29+H32)/-H35 -> 4.4627426 | I40: =(I29+I32)/-I35 -> 5.3268467 | J40: =(J29+J32)/-J35 -> 5.9933658 | M40: TEV | O40: =O38*O39 -> 715 | P40: =P38*P39 -> 1541.9916 | Q40: =Q38+Q39 -> 826.99158
M41: less: Debt | O41: =O21 -> 318.6 | P41: =J38 -> 60.861711 | Q41: =O41-P41 -> 257.73829
C42: Debt- 1st Lien / (cash) | E42: =E185 -> 118.6 | F42: =F185 -> 93.415335 | G42: =G185 -> 52.041426 | H42: =H185 -> 1.0545413 | I42: =I185 -> -59.097234 | J42: =J185 -> -129.13829 | M42: less: options | P42: =J208 -> 73.842531 | Q42: =-P42 -> -73.842531
C43: Debt - 2nd Lien/Sub | E43: =E191 -> 200 | F43: =F191 -> 198 | G43: =G191 -> 196 | H43: =H191 -> 194 | I43: =I191 -> 192 | J43: =J191 -> 190 | M43: Equity value | O43: =O40-O41-O42 -> 396.4 | P43: =P40-P41-P42 -> 1407.2873 | Q43: =Q40+Q41+Q42 -> 1010.8873
C44: Total Debt (Net) | E44: =E42+E43 -> 318.6 | F44: =F42+F43 -> 291.41533 | G44: =G42+G43 -> 248.04143 | H44: =H42+H43 -> 195.05454 | I44: =I42+I43 -> 132.90277 | J44: =J42+J43 -> 60.861711 | K44: =E44-J44 -> 257.73829 | M44: MOIC | P44: =P43/O43 -> 3.5501699
B49: INPUT: EBITDA and DEBT PAYDOWN
B50: Income Statement Assumptions | E50: Base | F50: =F14 -> 2025 | G50: =G14 -> 2026 | H50: =H14 -> 2027 | I50: =I14 -> 2028 | J50: =J14 -> 2029 | K50: CAGR | L50: notes:
C51: LTM and est. at closing | F51: input above in output page
A52: A | C52: Revenue growth | F52: ='Operating Build'!R24 -> 0.047256875 | G52: ='Operating Build'!S24 -> 0.052922166 | H52: ='Operating Build'!T24 -> 0.064369549 | I52: ='Operating Build'!U24 -> 0.072180494 | J52: ='Operating Build'!V24 -> 0.074695598 | K52: =K15 -> 0.062231217
A53: B | C53: Gross margin | E53: =E19 -> 0.19947016 | F53: ='Operating Build'!R46 -> 0.20024543 | G53: ='Operating Build'!S46 -> 0.20040628 | H53: ='Operating Build'!T46 -> 0.2002715 | I53: ='Operating Build'!U46 -> 0.20001976 | J53: ='Operating Build'!V46 -> 0.19976887 | K53: =K18 -> 0.06254917
A54: C | C54: SG&A | E54: =E22 -> 0.13910554 | F54: ='Operating Build'!R50+'Operating Build'!R53 -> 0.12985554 | G54: ='Operating Build'!S50+'Operating Build'!S53 -> 0.12060554 | H54: ='Operating Build'!T50+'Operating Build'!T53 -> 0.11677221 | I54: ='Operating Build'!U50+'Operating Build'!U53 -> 0.11293887 | J54: ='Operating Build'!V50+'Operating Build'!V53 -> 0.10910554 | K54: =K21 -> 0.011857921
C55: Adjustments | F55: input above in output page
C56: EBITDA margin output | E56: =E30 -> 0.063341634 | F56: =E30 -> 0.063341634 | G56: =F30 -> 0.070389887 | H56: =G30 -> 0.079800738 | I56: =H30 -> 0.083499289 | J56: =I30 -> 0.087080882 | K56: =K29 -> 0.14121518
B58: Capex
A59: D | C59: Capex % Base -% of sales input | E59: =-E32/E15 -> 0.01970862 | F59: ='Operating Build'!Q115 -> 0.016390192 | G59: ='Operating Build'!R115 -> 0.016390192 | H59: ='Operating Build'!S115 -> 0.016390192 | I59: ='Operating Build'!T115 -> 0.016390192 | J59: ='Operating Build'!U115 -> 0.016390192
C60: Capex - Base | F60: =-F59*F15 -> -22.114506 | G60: =-G59*G15 -> -23.284853 | H60: =-H59*H15 -> -24.783689 | I60: =-I59*I15 -> -26.572588 | J60: =-J59*J15 -> -28.557443
C61: Capex - Add on Acq | F61: =F161 -> 0 | G61: =G161 -> 0 | H61: =H161 -> 0 | I61: =I161 -> 0 | J61: =J161 -> 0
B63: Net Working Capital
A64: E | C64: % of sales input - Base | E64: =E65/E15 -> 0.083536251 | F64: ='Operating Build'!R93 -> 0.084498494 | G64: ='Operating Build'!S93 -> 0.085239324 | H64: ='Operating Build'!T93 -> 0.085473744 | I64: ='Operating Build'!U93 -> 0.085666016 | J64: ='Operating Build'!V93 -> 0.085858595
C65: Net assets (liabilities) | E65: ='Operating Build'!Q92 -> 107.62545 | F65: =F64*F15 -> 114.0098 | G65: =G64*G15 -> 121.09591 | H65: =H64*H15 -> 129.24526 | I65: =I64*I15 -> 138.88597 | J65: =J64*J15 -> 149.59568 | K65: =(J65/E65)^(1/5)-1 -> 0.068072713
C66: (Inc) / Dec vs PY - Base | F66: =E65-F65 -> -6.3843508 | G66: =F65-G65 -> -7.0861113 | H66: =G65-H65 -> -8.1493559 | I66: =H65-I65 -> -9.6407084 | J66: =I65-J65 -> -10.709711
C67: (Inc) / Dec vs PY - Add on Acq | F67: =F169 -> 0 | G67: =G169 -> 0 | H67: =H169 -> 0 | I67: =I169 -> 0 | J67: =J169 -> 0
A69: F | B69: Interest
C70: A/R Facility | E70: =E182 -> 118.6 | F70: =F185 -> 93.415335 | G70: =G185 -> 52.041426 | H70: =H185 -> 1.0545413 | I70: =I185 -> -59.097234 | J70: =J185 -> -129.13829
C71: Cash Interest | D71: 0 | F71: =MAX(AVERAGE(E70:F70)*F$74,0) -> 6.4802593 | G71: =MAX(AVERAGE(F70:G70)*G$74,0) -> 3.7036146 | H71: =MAX(AVERAGE(G70:H70)*H$74,0) -> 1.2935273 | I71: =MAX(AVERAGE(H70:I70)*I$74,0) -> 0 | J71: =MAX(AVERAGE(I70:J70)*J$74,0) -> 0
C72: Forward SOFR | F72: =IF(SOFR="Flat",SOFR!$S$20,SOFR!S20) -> 0.0423801 | G72: =IF(SOFR="Flat",SOFR!$S$20,SOFR!T20) -> 0.032173925 | H72: =IF(SOFR="Flat",SOFR!$S$20,SOFR!U20) -> 0.029974125 | I72: =IF(SOFR="Flat",SOFR!$S$20,SOFR!V20) -> 0.031476808 | J72: =IF(SOFR="Flat",SOFR!$S$20,SOFR!W20) -> 0.033048
C73: Spread | F73: 187.5 | G73: 187.5 | H73: 187.5 | I73: 187.5 | J73: 187.5
C74: Interest Rate | F74: =F73/10000+F72 -> 0.0611301 | G74: =G73/10000+G72 -> 0.050923925 | H74: =H73/10000+H72 -> 0.048724125 | I74: =I73/10000+I72 -> 0.050226808 | J74: =J73/10000+J72 -> 0.051798
C76: Term Loan | E76: =E188 -> 200 | F76: =F191 -> 198 | G76: =G191 -> 196 | H76: =H191 -> 194 | I76: =I191 -> 192 | J76: =J191 -> 190
C77: Cash Interest | D77: 0 | F77: =AVERAGE(E76:F76)*F$81 -> 24.35364 | G77: =AVERAGE(F76:G76)*G$81 -> 22.098263 | H77: =AVERAGE(G76:H76)*H$81 -> 21.444954 | I77: =AVERAGE(H76:I76)*I$81 -> 21.515024 | J77: =AVERAGE(I76:J76)*J$81 -> 21.592168
C78: Pay-in-kind (non cash) | D78: 0 | F78: =AVERAGE(E76:F76)*$D78 -> 0 | G78: =AVERAGE(F76:G76)*$D78 -> 0 | H78: =AVERAGE(G76:H76)*$D78 -> 0 | I78: =AVERAGE(H76:I76)*$D78 -> 0 | J78: =AVERAGE(I76:J76)*$D78 -> 0
C79: Forward SOFR | F79: =F72 -> 0.0423801 | G79: =G72 -> 0.032173925 | H79: =H72 -> 0.029974125 | I79: =I72 -> 0.031476808 | J79: =J72 -> 0.033048
C80: Spread | F80: 800 | G80: 800 | H80: 800 | I80: 800 | J80: 800
C81: Interest Rate | F81: =F80/10000+F79 -> 0.1223801 | G81: =G80/10000+G79 -> 0.11217393 | H81: =H80/10000+H79 -> 0.10997413 | I81: =I80/10000+I79 -> 0.11147681 | J81: =J80/10000+J79 -> 0.113048
C83: Total Interest | F83: =F71+F77+F78 -> 30.833899 | G83: =G71+G77+G78 -> 25.801878 | H83: =H71+H77+H78 -> 22.738482 | I83: =I71+I77+I78 -> 21.515024 | J83: =J71+J77+J78 -> 21.592168
A85: G | B85: Tax
C86: EBITDA | E86: =E29 -> 81.607343 | F86: =F29 -> 94.973724 | G86: =G29 -> 113.36954 | H86: =H29 -> 126.25968 | I86: =I29 -> 141.17982 | J86: =J29 -> 157.96721
C87: Less: D&A | E87: ='Operating Build'!Q67 -> -34.643387 | F87: =-F93*F15 -> -36.280525 | G87: =-G93*G15 -> -38.200569 | H87: =-H93*H15 -> -40.659522 | I87: =-I93*I15 -> -43.594346 | J87: =-J93*J15 -> -46.850652
C88: Less: Max Interest or 30% EBITDA | F88: =-MIN(F83,0.3*F86) -> -28.492117 | G88: =-MIN(G83,0.3*G86) -> -25.801878 | H88: =-MIN(H83,0.3*H86) -> -22.738482 | I88: =-MIN(I83,0.3*I86) -> -21.515024 | J88: =-MIN(J83,0.3*J86) -> -21.592168
C89: EBT | F89: =SUM(F86:F88) -> 30.201082 | G89: =SUM(G86:G88) -> 49.36709 | H89: =SUM(H86:H88) -> 62.861677 | I89: =SUM(I86:I88) -> 76.070452 | J89: =SUM(J86:J88) -> 89.524385
C90: Tax Rate % | F90: 0.28 | G90: =F90 -> 0.28 | H90: =G90 -> 0.28 | I90: =H90 -> 0.28 | J90: =I90 -> 0.28
C91: Taxes | F91: =MAX(F89*F90,0) -> 8.456303 | G91: =MAX(G89*G90,0) -> 13.822785 | H91: =MAX(H89*H90,0) -> 17.60127 | I91: =MAX(I89*I90,0) -> 21.299727 | J91: =MAX(J89*J90,0) -> 25.066828
C93: Note: D&A (for tax purposes) | E93: =-E87/E15 -> 0.026889353 | F93: =-'Operating Build'!R68 -> 0.026889353 | G93: =-'Operating Build'!S68 -> 0.026889353 | H93: =-'Operating Build'!T68 -> 0.026889353 | I93: =-'Operating Build'!U68 -> 0.026889353 | J93: =-'Operating Build'!V68 -> 0.026889353
B96: INPUT: PURCHASE PRICE AND CAPITALIZATION
B97: Entry Purchase Price Assumption
C98: EBITDA at Acquisition | H98: =E29 -> 81.607343
A99: H | C99: Purchase Multipe (pre fees) | H99: =H100/H98 -> 8.7614665
C100: TEV to seller | H100: 715
C101: Closing cost / fees | H101: 0 | I101: Costs included above
C102: TEV w/ fees - capital needed at closing | H102: =H101+H100 -> 715
B104: Capitalization: Opeing Debt and Equity
A105: I | C105: ABL Facility | E105: multiple: | F105: 1.4533006 | G105: =F105*E29 -> 118.6
C106: Term Loan | F106: 2.4507598 | G106: =F106*E29 -> 200
C107: Debt at closing | H107: =G106+G105 -> 318.6
C108: Equity (plug to fund remining capital) | H108: =H102-H107 -> 396.4
C109: Total Capitalization at closing | H109: =H107+H108 -> 715
C110: Equity % of Total Capital | H110: =H108/H109 -> 0.55440559
C111: Test: equal to need at closing? | H111: =IF(H109=H102,"Yes","NO") -> Yes
A113: J | B113: Exit Multiple
C114: Acquisition Multiple | H114: =P16 -> 8.7614665
C115: Acquisition Multiple w fees | H115: =Q16 -> 8.7614665
C116: Sale / Exit Multiple | H116: =IF(MultipleExpansion="Yes",H115+1,H115) -> 9.7614665
A118: J | B118: Management Incentive Options Assumptions | F118: % of Shares | I118: Hurdle to Earn $
F119: Per Tranche | G119: Cum | I119: Mult of Equity | J119: $
C120: Time | F120: 0.07 | G120: =F120 -> 0.07 | I120: 0 | J120: =$H$108*I120/(1-G120) -> 0
C121: Performance 1 | F121: 0 | G121: =F121+G120 -> 0.07 | I121: 0 | J121: =$H$108*I121/(1-G121) -> 0
...

Sheet Operating Build
B4: LBO-audit
H6: Q1 | I6: Q2 | J6: Q3 | K6: Q4 | L6: FY | M6: Q1 | N6: Q2 | O6: Q3 | P6: Q4 | Q6: FY | R6: FY | S6: FY | T6: FY | U6: FY | V6: FY
B7: ($ in millions) | D7: 43830 | E7: =EOMONTH(D7,12) -> 44196 | F7: =EOMONTH(E7,12) -> 44561 | G7: =EOMONTH(F7,12) -> 44926 | H7: =EOMONTH(G7,3) -> 45016 | I7: =EOMONTH(H7,3) -> 45107 | J7: =EOMONTH(I7,3) -> 45199 | K7: =EOMONTH(J7,3) -> 45291 | L7: =EOMONTH(G7,12) -> 45291 | M7: 45382 | N7: =EOMONTH(M7,3) -> 45473 | O7: =EOMONTH(N7,3) -> 45565 | P7: =EOMONTH(O7,3) -> 45657 | Q7: =P7 -> 45657 | R7: =EOMONTH(Q7,12) -> 46022 | S7: =EOMONTH(R7,12) -> 46387 | T7: =EOMONTH(S7,12) -> 46752 | U7: =EOMONTH(T7,12) -> 47118 | V7: =EOMONTH(U7,12) -> 47483
A9: x | B9: P&L Summary
B11: Infrastructure | D11: 557.20315 | E11: 519.12937 | F11: 619.67696 | G11: 651.93614 | H11: 140.03735 | I11: 177.34492 | J11: 137.62342 | K11: 200.15326 | L11: 655.15895 | M11: =Q11*$D$74 -> 154.04097 | N11: =Q11*$E$74 -> 158.88755 | O11: =Q11*$F$74 -> 163.82991 | P11: =Q11*$G$74 -> 193.90228 | Q11: =L11*(1+Q12) -> 670.66071 | R11: =Q11*(1+R12) -> 694.82258 | S11: =R11*(1+S12) -> 719.92129 | T11: =S11*(1+T12) -> 745.99523 | U11: =T11*(1+U12) -> 773.08443 | V11: =U11*(1+V12) -> 801.23063
B12: % Growth | D12: -- | E12: =IFERROR(+E11/D11-1,0) -> -0.068330156 | F12: =IFERROR(+F11/E11-1,0) -> 0.19368504 | G12: =IFERROR(+G11/F11-1,0) -> 0.052058055 | L12: =IFERROR(+L11/G11-1,0) -> 0.0049434423 | M12: =M11/H11-1 -> 0.09999913 | N12: =N11/I11-1 -> -0.10407607 | O12: =O11/J11-1 -> 0.19042178 | P12: =P11/K11-1 -> -0.031230977 | Q12: ='Top Customer Data'!I31 -> 0.023661077 | R12: =IF(GrowthCase="Recession",0.5%,'Revenue Build'!J43) -> 0.036026963 | S12: =IF(GrowthCase="Recession",0.5%,'Revenue Build'!K43) -> 0.036122467 | T12: =IF(GrowthCase="Recession",0.5%,'Revenue Build'!L43) -> 0.036217765 | U12: =IF(GrowthCase="Recession",0.5%,'Revenue Build'!M43) -> 0.036312839 | V12: =IF(GrowthCase="Recession",0.5%,'Revenue Build'!N43) -> 0.036407671
B14: Cloud | D14: 81.869709 | E14: 75.624607 | F14: 85.547617 | G14: 89.989896 | H14: 23.256295 | I14: 25.626924 | J14: 26.64538 | K14: 27.020934 | L14: 102.54953 | M14: =Q14*$D$74 -> 26.20416 | N14: =Q14*$E$74 -> 27.028621 | O14: =Q14*$F$74 -> 27.869373 | P14: =Q14*$G$74 -> 32.985032 | Q14: =L14*(1+Q15) -> 114.08719 | R14: =Q14*(1+R15) -> 125.86906 | S14: =R14*(1+S15) -> 137.82897 | T14: =S14*(1+T15) -> 149.77183 | U14: =T14*(1+U15) -> 162.98588 | V14: =U14*(1+V15) -> 177.58612
B15: % Growth | D15: -- | E15: =IFERROR(+E14/D14-1,0) -> -0.076280987 | F15: =IFERROR(+F14/E14-1,0) -> 0.13121404 | G15: =IFERROR(+G14/F14-1,0) -> 0.051927569 | L15: =IFERROR(+L14/G14-1,0) -> 0.13956719 | M15: =M14/H14-1 -> 0.12675557 | N15: =N14/I14-1 -> 0.054696232 | O15: =O14/J14-1 -> 0.045936413 | P15: =P14/K14-1 -> 0.22072137 | Q15: ='Top Customer Data'!I56 -> 0.11250809 | R15: =IF(GrowthCase="Recession",0.5%,'Revenue Build'!J77) -> 0.10327083 | S15: =IF(GrowthCase="Recession",0.5%,'Revenue Build'!K77) -> 0.095018616 | T15: =IF(GrowthCase="Recession",0.5%,'Revenue Build'!L77) -> 0.086649882 | U15: =IF(GrowthCase="Recession",0.5%,'Revenue Build'!M77) -> 0.088227865 | V15: =IF(GrowthCase="Recession",0.5%,'Revenue Build'!N77) -> 0.089579756
B17: Consulting | D17: 152.63324 | E17: 196.02662 | F17: 299.11454 | G17: 339.4398 | H17: 84.723232 | I17: 88.954097 | J17: 85.144657 | K17: 81.836048 | L17: 340.65803 | M17: =Q17*$D$74 -> 80.341593 | N17: =Q17*$E$74 -> 82.869379 | O17: =Q17*$F$74 -> 85.447115 | P17: =Q17*$G$74 -> 101.13165 | Q17: =L17*(1+Q18) -> 349.78974 | R17: =Q17*(1+R18) -> 369.723 | S17: =R17*(1+S18) -> 398.53211 | T17: =S17*(1+T18) -> 445.85529 | U17: =T17*(1+U18) -> 507.97847 | V17: =U17*(1+V18) -> 578.95925
B18: % Growth | D18: -- | E18: =IFERROR(+E17/D17-1,0) -> 0.28429837 | F18: =IFERROR(+F17/E17-1,0) -> 0.52588734 | G18: =IFERROR(+G17/F17-1,0) -> 0.13481544 | L18: =IFERROR(+L17/G17-1,0) -> 0.0035889671 | M18: =M17/H17-1 -> -0.05171709 | N18: =N17/I17-1 -> -0.068402892 | O18: =O17/J17-1 -> 0.0035522844 | P18: =P17/K17-1 -> 0.23578369 | Q18: ='Top Customer Data'!I81 -> 0.026806083 | R18: =IF(GrowthCase="Recession",0.5%,'Revenue Build'!J92) -> 0.056986401 | S18: =IF(GrowthCase="Recession",0.5%,'Revenue Build'!K92) -> 0.077920786 | T18: =IF(GrowthCase="Recession",0.5%,'Revenue Build'!L92) -> 0.11874371 | U18: =IF(GrowthCase="Recession",0.5%,'Revenue Build'!M92) -> 0.13933484 | V18: =IF(GrowthCase="Recession",0.5%,'Revenue Build'!N92) -> 0.13973188
B20: Comms | D20: 100.79152 | E20: 114.68729 | F20: 121.81334 | G20: 133.65576 | H20: 35.557871 | I20: 34.269577 | J20: 36.824528 | K20: 38.681066 | L20: 145.33304 | M20: =Q20*$D$74 -> 35.33262 | N20: =Q20*$E$74 -> 36.44429 | O20: =Q20*$F$74 -> 37.577926 | P20: =Q20*$G$74 -> 44.475672 | Q20: =L20*(1+Q21) -> 153.83051 | R20: =Q20*(1+R21) -> 158.83775 | S20: =R20*(1+S21) -> 164.3754 | T20: =S20*(1+T21) -> 170.48251 | U20: =T20*(1+U21) -> 177.20056 | V20: =U20*(1+V21) -> 184.57352
B21: % Growth | D21: -- | E21: =IFERROR(+E20/D20-1,0) -> 0.1378664 | F21: =IFERROR(+F20/E20-1,0) -> 0.062134672 | G21: =IFERROR(+G20/F20-1,0) -> 0.097217754 | L21: =IFERROR(+L20/G20-1,0) -> 0.087368314 | M21: =M20/H20-1 -> -0.0063347802 | N21: =N20/I20-1 -> 0.063458978 | O21: =O20/J20-1 -> 0.020459143 | P21: =P20/K20-1 -> 0.14980471 | Q21: ='Top Customer Data'!I106 -> 0.058468914 | R21: =IF(GrowthCase="Recession",0.5%,'Revenue Build'!J113) -> 0.032550418 | S21: =IF(GrowthCase="Recession",0.5%,'Revenue Build'!K113) -> 0.034863511 | T21: =IF(GrowthCase="Recession",0.5%,'Revenue Build'!L113) -> 0.037153452 | U21: =IF(GrowthCase="Recession",0.5%,'Revenue Build'!M113) -> 0.039406081 | V21: =IF(GrowthCase="Recession",0.5%,'Revenue Build'!N113) -> 0.041608017
B23: Total Organic Revenue | D23: =SUM(D20,D17,D14,D11) -> 892.49762 | E23: =SUM(E20,E17,E14,E11) -> 905.46788 | F23: =SUM(F20,F17,F14,F11) -> 1126.1525 | G23: =SUM(G20,G17,G14,G11) -> 1215.0216 | H23: =SUM(H20,H17,H14,H11) -> 283.57475 | I23: =SUM(I20,I17,I14,I11) -> 326.19551 | J23: =SUM(J20,J17,J14,J11) -> 286.23798 | K23: =SUM(K20,K17,K14,K11) -> 347.69131 | ... V23: =SUM(V20,V17,V14,V11) -> 1742.3495
B24: % Growth | D24: -- | E24: =+E23/D23-1 -> 0.01453255 | F24: =+F23/E23-1 -> 0.24372436 | G24: =+G23/F23-1 -> 0.078913945 | L24: =+L23/G23-1 -> 0.023602842 | M24: =M23/H23-1 -> 0.043532042 | N24: =N23/I23-1 -> -0.064273327 | O24: =O23/J23-1 -> 0.099519796 | P24: =P23/K23-1 -> 0.07133721 | Q24: =+Q23/L23-1 -> 0.035915901 | R24: =R23/Q23-1 -> 0.047256875 | S24: =S23/R23-1 -> 0.052922166 | T24: =T23/S23-1 -> 0.064369549 | U24: =U23/T23-1 -> 0.072180494 | V24: =V23/U23-1 -> 0.074695598
B26: Acquired Revenue | C26: 1
B28: Total Revenue | D28: =SUM(D20,D17,D14,D11,D26) -> 892.49762 | E28: =SUM(E20,E17,E14,E11,E26) -> 905.46788 | F28: =SUM(F20,F17,F14,F11,F26) -> 1126.1525 | G28: =SUM(G20,G17,G14,G11,G26) -> 1215.0216 | H28: =SUM(H20,H17,H14,H11,H26) -> 283.57475 | I28: =SUM(I20,I17,I14,I11,I26) -> 326.19551 | J28: =SUM(J20,J17,J14,J11,J26) -> 286.23798 | K28: =SUM(K20,K17,K14,K11,K26) -> 347.69131 | ... V28: =SUM(V20,V17,V14,V11,V26) -> 1742.3495
B29: % Growth | D29: -- | E29: =+E28/D28-1 -> 0.01453255 | F29: =+F28/E28-1 -> 0.24372436 | G29: =+G28/F28-1 -> 0.078913945 | L29: =+L28/G28-1 -> 0.023602842 | M29: =M28/H28-1 -> 0.043532042 | N29: =N28/I28-1 -> -0.064273327 | O29: =O28/J28-1 -> 0.099519796 | P29: =P28/K28-1 -> 0.07133721 | Q29: =+Q28/L28-1 -> 0.035915901 | R29: =+R28/Q28-1 -> 0.047256875 | S29: =+S28/R28-1 -> 0.052922166 | T29: =+T28/S28-1 -> 0.064369549 | U29: =+U28/T28-1 -> 0.072180494 | V29: =+V28/U28-1 -> 0.074695598
B31: Memo: Organic COGS | D31: =D23-D45 -> 720.80984 | E31: =E23-E45 -> 726.01931 | F31: =F23-F45 -> 915.37287 | G31: =G23-G45 -> 982.01218 | H31: =H23-H45 -> 228.26864 | I31: =I23-I45 -> 261.7457 | J31: =J23-J45 -> 230.92556 | K31: =K23-K45 -> 280.48725 | ... V31: =V23-V45 -> 1394.2823
B33: =B11&" Gross Profit" -> Infrastructure Gross Profit | D33: 99.677349 | E33: 93.404027 | F33: 108.73486 | G33: 117.02704 | H33: 25.775385 | I33: 30.989439 | J33: 22.664984 | K33: 33.734926 | L33: 113.1648 | M33: =M34*M11 -> 26.819423 | N33: =N34*N11 -> 27.663242 | O33: =O34*O11 -> 28.523735 | P33: =P34*P11 -> 33.759508 | Q33: =Q34*Q11 -> 116.76591 | R33: =R34*R11 -> 121.59395 | S33: =S34*S11 -> 125.98623 | T33: =T34*T11 -> 130.54916 | ... V33: =V34*V11 -> 140.21536
B34: % Margin | D34: =D33/D11 -> 0.1788887 | E34: =E33/E11 -> 0.17992437 | F34: =F33/F11 -> 0.17547023 | G34: =G33/G11 -> 0.1795069 | H34: =H33/H11 -> 0.18406078 | I34: =I33/I11 -> 0.17474106 | J34: =J33/J11 -> 0.16468842 | K34: =K33/K11 -> 0.16854548 | L34: =L33/L11 -> 0.17272878 | M34: =Q34 -> 0.17410578 | N34: =Q34 -> 0.17410578 | O34: =Q34 -> 0.17410578 | P34: =Q34 -> 0.17410578 | Q34: ='Top Customer Data'!W30 -> 0.17410578 | R34: 0.175 | S34: =R34 -> 0.175 | T34: =S34 -> 0.175 | U34: =T34 -> 0.175 | V34: =U34 -> 0.175
B36: =B14&" Gross Profit" -> Cloud Gross Profit | D36: 20.758924 | E36: 21.237845 | F36: 27.480422 | G36: 26.24656 | H36: 6.4647798 | I36: 7.5819124 | J36: 7.0411578 | K36: 7.2790346 | L36: 28.367191 | M36: =M37*M14 -> 7.4495808 | N36: =N37*N14 -> 7.6839668 | O36: =O37*O14 -> 7.9229844 | P36: =P37*P14 -> 9.377315 | Q36: =Q37*Q14 -> 32.433847 | R36: =R37*R14 -> 35.783317 | S36: =S37*S14 -> 39.183399 | T36: =T37*T14 -> 42.578635 | ... V36: =V37*V14 -> 50.485959
B37: % Margin | D37: =D36/D14 -> 0.25356049 | E37: =E36/E14 -> 0.28083247 | F37: =F36/F14 -> 0.32122955 | G37: =G36/G14 -> 0.29166118 | H37: =H36/H14 -> 0.27797978 | I37: =I36/I14 -> 0.29585729 | J37: =J36/J14 -> 0.26425436 | K37: =K36/K14 -> 0.26938501 | L37: =L36/L14 -> 0.27661941 | M37: =Q37 -> 0.28429001 | N37: =Q37 -> 0.28429001 | O37: =Q37 -> 0.28429001 | P37: =Q37 -> 0.28429001 | Q37: ='Top Customer Data'!W55 -> 0.28429001 | R37: =Q37 -> 0.28429001 | S37: =R37 -> 0.28429001 | T37: =S37 -> 0.28429001 | U37: =T37 -> 0.28429001 | V37: =U37 -> 0.28429001
B39: =B17&" Gross Profit" -> Consulting Gross Profit | D39: 24.828103 | E39: 31.566227 | F39: 42.440442 | G39: 52.600549 | H39: 13.343253 | I39: 16.048453 | J39: 14.36389 | K39: 14.182058 | L39: 57.937289 | M39: =M40*M17 -> 14.141173 | N39: =N40*N17 -> 14.586097 | O39: =O40*O17 -> 15.039812 | P39: =P40*P17 -> 17.800496 | Q39: =Q40*Q17 -> 61.567578 | R39: =R40*R17 -> 65.076093 | S39: =S40*S17 -> 70.146873 | T39: =T40*T17 -> 78.476373 | ... V39: =V40*V17 -> 101.90441
B40: % Margin | D40: =D39/D17 -> 0.16266511 | E40: =E39/E17 -> 0.16103031 | F40: =F39/F17 -> 0.14188692 | G40: =G39/G17 -> 0.15496282 | H40: =H39/H17 -> 0.15749225 | I40: =I39/I17 -> 0.18041275 | J40: =J39/J17 -> 0.16869984 | K40: =K39/K17 -> 0.17329842 | L40: =L39/L17 -> 0.17007463 | M40: =Q40 -> 0.1760131 | N40: =Q40 -> 0.1760131 | O40: =Q40 -> 0.1760131 | P40: =Q40 -> 0.1760131 | Q40: ='Top Customer Data'!W80 -> 0.1760131 | R40: =Q40 -> 0.1760131 | S40: =R40 -> 0.1760131 | T40: =S40 -> 0.1760131 | U40: =T40 -> 0.1760131 | V40: =U40 -> 0.1760131
B42: =B20&" Gross Profit" -> Comms Gross Profit | D42: 26.4234 | E42: 33.240477 | F42: 32.12387 | G42: 37.135265 | H42: 9.7226968 | I42: 9.8300064 | J42: 11.242391 | K42: 12.00804 | L42: 42.803597 | M42: =M43*M20 -> 10.6169 | N42: =N43*N20 -> 10.950939 | O42: =O43*O20 -> 11.29158 | P42: =P43*P20 -> 13.364244 | Q42: =Q43*Q20 -> 46.223663 | R42: =R43*R20 -> 47.728263 | S42: =S43*S20 -> 49.392238 | T42: =T43*T20 -> 51.22733 | ... V42: =V43*V20 -> 55.461458
B43: % Margin | D43: =D42/D20 -> 0.26215895 | E43: =E42/E20 -> 0.28983576 | F43: =F42/F20 -> 0.26371388 | G43: =G42/G20 -> 0.2778426 | H43: =H42/H20 -> 0.27343304 | I43: =I42/I20 -> 0.28684353 | J43: =J42/J20 -> 0.30529628 | K43: =K42/K20 -> 0.31043716 | L43: =L42/L20 -> 0.29452075 | M43: =Q43 -> 0.30048437 | N43: =Q43 -> 0.30048437 | O43: =Q43 -> 0.30048437 | P43: =Q43 -> 0.30048437 | Q43: ='Top Customer Data'!W105 -> 0.30048437 | R43: =Q43 -> 0.30048437 | S43: =R43 -> 0.30048437 | T43: =S43 -> 0.30048437 | U43: =T43 -> 0.30048437 | V43: =U43 -> 0.30048437
B45: Total Organic Gross Profit | D45: =SUM(D42,D39,D36,D33) -> 171.68778 | E45: =SUM(E42,E39,E36,E33) -> 179.44858 | F45: =SUM(F42,F39,F36,F33) -> 210.77959 | G45: =SUM(G42,G39,G36,G33) -> 233.00941 | H45: =SUM(H42,H39,H36,H33) -> 55.306114 | I45: =SUM(I42,I39,I36,I33) -> 64.449811 | J45: =SUM(J42,J39,J36,J33) -> 55.312423 | K45: =SUM(K42,K39,K36,K33) -> 67.204059 | ... V45: =SUM(V42,V39,V36,V33) -> 348.06719
B46: % Margin | D46: =+D45/D$23 -> 0.19236777 | E46: =+E45/E$23 -> 0.19818326 | F46: =+F45/F$23 -> 0.1871679 | G46: =+G45/G$23 -> 0.19177388 | H46: =+H45/H$23 -> 0.19503187 | I46: =+I45/I$23 -> 0.19758031 | J46: =+J45/J$23 -> 0.19323928 | K46: =+K45/K$23 -> 0.19328657 | ... V46: =+V45/V$23 -> 0.19976887
B47: Memo: Organic OPEX | D47: =-D49-D52 -> 142.23412 | E47: =-E49-E52 -> 137.28448 | F47: =-F49-F52 -> 144.33604 | G47: =-G49-G52 -> 155.50079 | H47: =H45-H64 -> 41.045456 | I47: =I45-I64 -> 41.290687 | J47: =J45-J64 -> 41.572599 | K47: =K45-K64 -> 40.688888 | L47: =-L49-L52 -> 163.48517 | M47: =-M49-M52-M57 -> 41.16402 | N47: =-N49-N52-N57 -> 42.459163 | O47: =-O49-O52-O57 -> 43.779898 | P47: =-P49-P52-P57 -> 51.816068 | Q47: =-Q49-Q52-Q57 -> 179.21915 | R47: =-R49-R52-R57 -> 175.2079 | S47: =-S49-S52-S57 -> 171.3392 | T47: =-T49-T52-T57 -> 176.57182 | ... V47: =-V49-V52-V57 -> 190.09999
B49: Selling Expense | D49: -102.00389 | E49: -102.91753 | F49: -105.6066 | G49: -109.65123 | H49: -28.312927 | I49: -28.017868 | J49: -27.35567 | K49: -30.650395 | L49: -114.33686 | M49: =-M$23*M50 -> -26.23302 | N49: =-N$23*N50 -> -27.058389 | O49: =-O$23*O50 -> -27.900068 | P49: =-P$23*P50 -> -33.021361 | Q49: =-Q$23*Q50 -> -114.21284 | R49: =-R$23*R50 -> -119.61018 | S49: =-S$23*S50 -> -125.94021 | T49: =-T$23*T50 -> -134.04692 | ... V49: =-V$23*V50 -> -154.45793
B50: % Margin | D50: =-D49/D$23 -> 0.11429038 | E50: =-E49/E$23 -> 0.11366226 | F50: =-F49/F$23 -> 0.093776471 | G50: =-G49/G$23 -> 0.090246322 | H50: =-H49/H$23 -> 0.099842907 | I50: =-I49/I$23 -> 0.085892866 | J50: =-J49/J$23 -> 0.095569672 | K50: =-K49/K$23 -> 0.088154043 | L50: =-L49/L$23 -> 0.091932862 | M50: =Q50 -> 0.088649225 | N50: =Q50 -> 0.088649225 | O50: =Q50 -> 0.088649225 | P50: =Q50 -> 0.088649225 | Q50: 0.088649225 | R50: =Q50 -> 0.088649225 | S50: =R50 -> 0.088649225 | T50: =S50 -> 0.088649225 | U50: =T50 -> 0.088649225 | V50: =U50 -> 0.088649225
B52: Operating Expenses | D52: -40.230226 | E52: -34.366957 | F52: -38.729434 | G52: -45.849561 | H52: -12.454294 | I52: -12.994585 | J52: -13.938694 | K52: -9.7602589 | L52: -49.148305 | M52: =-M$23*M53 -> -14.931 | N52: =-N$23*N53 -> -15.400774 | O52: =-O$23*O53 -> -15.87983 | P52: =-P$23*P53 -> -18.794707 | Q52: =-Q$23*Q53 -> -65.006311 | R52: =-R$23*R53 -> -55.597721 | S52: =-S$23*S53 -> -45.398989 | T52: =-T$23*T53 -> -42.524899 | ... V52: =-V$23*V53 -> -35.642053
B53: % Margin | D53: =-D52/D$23 -> 0.045076004 | E53: =-E52/E$23 -> 0.037954915 | F53: =-F52/F$23 -> 0.034390933 | G53: =-G52/G$23 -> 0.037735593 | H53: =-H52/H$23 -> 0.043918911 | I53: =-I52/I$23 -> 0.039836799 | J53: =-J52/J$23 -> 0.048696173 | K53: =-K52/K$23 -> 0.028071622 | L53: =-L52/L$23 -> 0.039517828 | M53: =Q53 -> 0.050456316 | N53: =Q53 -> 0.050456316 | O53: =Q53 -> 0.050456316 | P53: =Q53 -> 0.050456316 | Q53: 0.050456316 | R53: =Q53-'Margin Build vF'!J19/10000 -> 0.041206316 | S53: =R53-'Margin Build vF'!K19/10000 -> 0.031956316 | T53: =S53-'Margin Build vF'!L19/10000 -> 0.028122983 | U53: =T53-'Margin Build vF'!M19/10000 -> 0.02428965 | V53: =U53-'Margin Build vF'!N19/10000 -> 0.020456316
B55: Adjustments | D55: -12.816102 | E55: -12.816102 | F55: -21.650103 | G55: -17.626647 | H55: =$L55/4 -> -0.27823445 | I55: =$L55/4 -> -0.27823445 | J55: =$L55/4 -> -0.27823445 | K55: =$L55/4 -> -0.27823445 | L55: -1.1129378 | M55: =Q55*$D$74 -> 0.88095704 | N55: =Q55*$E$74 -> 0.90867458 | O55: =Q55*$F$74 -> 0.93693982 | P55: =Q55*$G$74 -> 1.108923 | Q55: 3.8354945 | R55: 0 | S55: 0 | T55: 0 | U55: 0 | V55: 0
B57: Run-Rate Impact of Cost Initiatives | M57: =Q57*25% -> 0 | N57: =Q57*25% -> 0 | O57: =Q57*25% -> 0 | P57: =Q57*25% -> 0 | Q57: 0 | R57: 0 | S57: 0 | T57: 0 | U57: 0 | V57: 0
B59: Organic PF Adj. EBITDA | D59: =D45+D49+D52+D55+D57 -> 16.637554 | E59: =E45+E49+E52+E55+E57 -> 29.347991 | F59: =F45+F49+F52+F55+F57 -> 44.79345 | G59: =G45+G49+G52+G55+G57 -> 59.881973 | H59: =H45+H49+H52+H55+H57 -> 14.260658 | I59: =I45+I49+I52+I55+I57 -> 23.159124 | J59: =J45+J49+J52+J55+J57 -> 13.739824 | K59: =K45+K49+K52+K55+K57 -> 26.515171 | ... V59: =V45+V49+V52+V55+V57 -> 157.96721
B60: % Margin | D60: =+D59/D$23 -> 0.018641567 | E60: =+E59/E$23 -> 0.032411962 | F60: =+F59/F$23 -> 0.039775653 | G60: =+G59/G$23 -> 0.049284698 | H60: =+H59/H$23 -> 0.050288883 | I60: =+I59/I$23 -> 0.070997676 | J60: =+J59/J$23 -> 0.048001401 | K60: =+K59/K$23 -> 0.076260667 | ... V60: =+V59/V$23 -> 0.090663328
B62: Acquired EBITDA | C62: =C26 -> 1
B64: Total PF Adj. EBITDA | D64: =D59+D62 -> 16.637554 | E64: =E59+E62 -> 29.347991 | F64: =F59+F62 -> 44.79345 | G64: =G59+G62 -> 59.881973 | H64: =H59+H62 -> 14.260658 | I64: =I59+I62 -> 23.159124 | J64: =J59+J62 -> 13.739824 | K64: =K59+K62 -> 26.515171 | ... V64: =V59+V62 -> 157.96721
B65: % Margin | D65: =+D64/D$28 -> 0.018641567 | E65: =+E64/E$28 -> 0.032411962 | F65: =+F64/F$28 -> 0.039775653 | G65: =+G64/G$28 -> 0.049284698 | H65: =+H64/H$28 -> 0.050288883 | I65: =+I64/I$28 -> 0.070997676 | J65: =+J64/J$28 -> 0.048001401 | K65: =+K64/K$28 -> 0.076260667 | ... V65: =+V64/V$28 -> 0.090663328
B67: Normalized D&A | D67: -44.914875 | E67: -36.324867 | F67: -40.619871 | G67: -40.619871 | L67: -28.927587 | M67: =M$28*M68 -> -7.9570797 | N67: =N$28*N68 -> -8.2074332 | O67: =O$28*O68 -> -8.4627337 | P67: =P$28*P68 -> -10.01614 | Q67: =Q$23*Q68 -> -34.643387 | R67: =R$23*R68 -> -36.280525 | S67: =S$23*S68 -> -38.200569 | T67: =T$23*T68 -> -40.659522 | U67: =U$23*U68 -> -43.594346 | V67: =V$23*V68 -> -46.850652
B68: % of Revenue | D68: =D67/D$23 -> -0.050324925 | E68: =E67/E$23 -> -0.040117234 | F68: =F67/F$23 -> -0.036069602 | G68: =G67/G$23 -> -0.033431399 | H68: =H67/H$23 -> 0 | I68: =I67/I$23 -> 0 | J68: =J67/J$23 -> 0 | K68: =K67/K$23 -> 0 | L68: =L67/L$23 -> -0.023259304 | M68: =Q68 -> -0.026889353 | N68: =Q68 -> -0.026889353 | O68: =Q68 -> -0.026889353 | P68: =Q68 -> -0.026889353 | Q68: =IF($C$62=1,-2.6889353476805%,-2.6889353476805%) -> -0.026889353 | R68: =IF($C$62=1,-2.6889353476805%,-2.6889353476805%) -> -0.026889353 | S68: =IF($C$62=1,-2.6889353476805%,-2.6889353476805%) -> -0.026889353 | T68: =IF($C$62=1,-2.6889353476805%,-2.6889353476805%) -> -0.026889353 | U68: =IF($C$62=1,-2.6889353476805%,-2.6889353476805%) -> -0.026889353 | V68: =IF($C$62=1,-2.6889353476805%,-2.6889353476805%) -> -0.026889353
B70: Quarterly Revenue Distribution | D70: Q1 | E70: Q2 | F70: Q3 | G70: Q4
C71: 2021A | D71: 0.23415238 | E71: 0.20871898 | F71: 0.23313693 | G71: 0.32399171
C72: 2022A | D72: 0.22689474 | E72: 0.23973856 | F72: 0.26955674 | G72: 0.26380996
C73: 2023E | D73: 0.22800905 | E73: 0.26227839 | F73: 0.23015043 | G73: 0.27956214
C74: Average | D74: =AVERAGE(D71:D73) -> 0.22968539 | E74: =AVERAGE(E71:E73) -> 0.23691198 | F74: =AVERAGE(F71:F73) -> 0.24428136 | G74: =AVERAGE(G71:G73) -> 0.28912127
A76: x | B76: NWC and Capex Build | R76: x
B78: Net Working Capital Build
B80: Organic NWC | F80: PwC Adj. | G80: PwC Adj. | H80: PwC Adj. | I80: PwC Adj. | J80: PwC Adj. | K80: Projection | L80: Projection
B81: Receivables | F81: 372.64389 | G81: 407.98786 | H81: 303.90878 | I81: 332.64677 | J81: 309.26415 | K81: =L81 -> 414.57888 | L81: =(L23)*L99/365 -> 414.57888 | M81: =(SUM(M23,K23,J23,I23))*M99/365 -> 418.69387 | N81: =(SUM(N23,M23,K23,J23))*N99/365 -> 411.7051 | O81: =(SUM(O23,N23,M23,K23))*O99/365 -> 421.20084 | P81: =(SUM(P23,O23,N23,M23))*P99/365 -> 429.46886 | Q81: =(Q23)*Q99/365 -> 429.46886 | R81: =(R23)*R99/365 -> 449.76421 | S81: =(S23)*S99/365 -> 473.56671 | T81: =(T23)*T99/365 -> 504.04999 | U81: =(U23)*U99/365 -> 540.43256 | V81: =(V23)*V99/365 -> 580.8005
B82: Inventory | F82: 23.147299 | G82: 22.85749 | H82: 9.1901558 | I82: 7.388537 | J82: 20.764425 | K82: =L82 -> 24.480196 | L82: =L100*L$23 -> 24.480196 | M82: =M100*SUM(M$23,K23,J23,I23) -> 24.723179 | N82: =N100*SUM(N$23,M23,K23,J23) -> 24.310504 | O82: =O100*SUM(O$23,N23,M23,K23) -> 24.871211 | P82: =P100*SUM(P$23,O23,N23,M23) -> 25.359424 | Q82: =Q100*Q$23 -> 25.359424 | R82: =R100*R$23 -> 26.557831 | S82: =S100*S$23 -> 27.963329 | T82: =T100*T$23 -> 29.763316 | U82: =U100*U$23 -> 31.911647 | V82: =V100*V$23 -> 34.295307
B83: Prepaid and Other Current Assets | F83: 36.881669 | G83: 31.306143 | H83: 35.486523 | I83: 34.955378 | J83: 36.366904 | K83: =L83 -> 36.388206 | L83: =L101*L$23 -> 36.388206 | M83: =M101*SUM(M$23,K23,J23,I23) -> 36.749385 | N83: =N101*SUM(N$23,M23,K23,J23) -> 36.13597 | O83: =O101*SUM(O$23,N23,M23,K23) -> 36.969425 | P83: =P101*SUM(P$23,O23,N23,M23) -> 37.695121 | Q83: =Q101*Q$23 -> 37.695121 | R83: =R101*R$23 -> 39.476475 | S83: =S101*S$23 -> 41.565656 | T83: =T101*T$23 -> 44.241218 | U83: =U101*U$23 -> 47.434571 | V83: =V101*V$23 -> 50.977725
B84: Current Assets | F84: =SUM(F81:F83) -> 432.67286 | G84: =SUM(G81:G83) -> 462.1515 | H84: =SUM(H81:H83) -> 348.58546 | I84: =SUM(I81:I83) -> 374.99068 | J84: =SUM(J81:J83) -> 366.39548 | K84: =L84 -> 475.44729 | L84: =SUM(L81:L83) -> 475.44729 | M84: =SUM(M81:M83) -> 480.16643 | N84: =SUM(N81:N83) -> 472.15158 | O84: =SUM(O81:O83) -> 483.04147 | P84: =SUM(P81:P83) -> 492.5234 | Q84: =SUM(Q81:Q83) -> 492.5234 | R84: =SUM(R81:R83) -> 515.79852 | S84: =SUM(S81:S83) -> 543.09569 | ... V84: =SUM(V81:V83) -> 666.07353
B86: Accounts Payable and Accrued Liabilities | F86: -254.36805 | G86: -289.87949 | H86: -226.29699 | I86: -224.93203 | J86: -207.04567 | K86: =L86 -> -286.94576 | L86: =-L31*L103/365 -> -286.94576 | M86: =-SUM(M31,K31,J31,I31)*M103/365 -> -289.41688 | N86: =-SUM(N31,M31,K31,J31)*N103/365 -> -284.43111 | O86: =-SUM(O31,N31,M31,K31)*O103/365 -> -290.45431 | P86: =-SUM(P31,O31,N31,M31)*P103/365 -> -295.52768 | Q86: =-Q31*Q103/365 -> -295.52768 | R86: =-R31*R103/365 -> -309.19367 | S86: =-S31*S103/365 -> -325.49139 | T86: =-T31*T103/365 -> -346.50152 | U86: =-U31*U103/365 -> -371.62911 | V86: =-V31*V103/365 -> -399.51343
B87: Accrued Expenses | F87: -24.859267 | G87: -21.935498 | H87: -9.9176591 | I87: -14.717968 | J87: -10.259185 | K87: =L87 -> -24.895515 | L87: =(L$31+L$47)*L104 -> -24.895515 | M87: =M104*SUM(M$31,K$31,J$31,I$31,M$47,K$47,J$47,I$47) -> -25.10613 | N87: =N104*SUM(N$31,M$31,K$31,J$31,N$47,M$47,K$47,J$47) -> -24.759242 | O87: =O104*SUM(O$31,N$31,M$31,K$31,O$47,N$47,M$47,K$47) -> -25.25565 | P87: =P104*SUM(P$31,O$31,N$31,M$31,P$47,O$47,N$47,M$47) -> -25.871845 | Q87: =(Q$31+Q$47)*Q104 -> -25.871845 | R87: =(R$31+R$47)*R104 -> -26.805388 | S87: =(S$31+S$47)*S104 -> -27.938263 | T87: =(T$31+T$47)*T104 -> -29.617116 | U87: =(U$31+U$47)*U104 -> -31.630799 | V87: =(V$31+V$47)*V104 -> -33.860085
B88: Advanced Billings and Customer Deposits | F88: -47.958314 | G88: -38.245028 | H88: -31.624071 | I88: -19.192558 | J88: -21.898954 | K88: =L88 -> -45.942807 | L88: =(L$31+L$47)*L105 -> -45.942807 | M88: =M105*SUM(M$31,K$31,J$31,I$31,M$47,K$47,J$47,I$47) -> -46.331482 | N88: =N105*SUM(N$31,M$31,K$31,J$31,N$47,M$47,K$47,J$47) -> -45.691325 | O88: =O105*SUM(O$31,N$31,M$31,K$31,O$47,N$47,M$47,K$47) -> -46.607409 | P88: =P105*SUM(P$31,O$31,N$31,M$31,P$47,O$47,N$47,M$47) -> -47.74455 | Q88: =(Q$31+Q$47)*Q105 -> -47.74455 | R88: =(R$31+R$47)*R105 -> -49.467334 | S88: =(S$31+S$47)*S105 -> -51.55797 | T88: =(T$31+T$47)*T105 -> -54.656168 | U88: =(U$31+U$47)*U105 -> -58.372269 | V88: =(V$31+V$47)*V105 -> -62.486248
B89: Total Other Current Liabilities | F89: -13.756071 | G89: -14.839608 | H89: -13.230046 | I89: -15.458662 | J89: -15.019888 | K89: =L89 -> -15.159377 | L89: =(L$31+L$47)*L106 -> -15.159377 | M89: =M106*SUM(M$31,K$31,J$31,I$31,M$47,K$47,J$47,I$47) -> -15.287625 | N89: =N106*SUM(N$31,M$31,K$31,J$31,N$47,M$47,K$47,J$47) -> -15.076398 | O89: =O106*SUM(O$31,N$31,M$31,K$31,O$47,N$47,M$47,K$47) -> -15.378671 | P89: =P106*SUM(P$31,O$31,N$31,M$31,P$47,O$47,N$47,M$47) -> -15.753884 | Q89: =(Q$31+Q$47)*Q106 -> -15.753884 | R89: =(R$31+R$47)*R106 -> -16.322337 | S89: =(S$31+S$47)*S106 -> -17.012167 | T89: =(T$31+T$47)*T106 -> -18.034455 | U89: =(U$31+U$47)*U106 -> -19.260627 | V89: =(V$31+V$47)*V106 -> -20.618083
B90: Current Liabilities | F90: =SUM(F86:F89) -> -340.94171 | G90: =SUM(G86:G89) -> -364.89962 | H90: =SUM(H86:H89) -> -281.06877 | I90: =SUM(I86:I89) -> -274.30122 | J90: =SUM(J86:J89) -> -254.22369 | K90: =L90 -> -372.94346 | L90: =SUM(L86:L89) -> -372.94346 | M90: =SUM(M86:M89) -> -376.14212 | N90: =SUM(N86:N89) -> -369.95808 | O90: =SUM(O86:O89) -> -377.69604 | P90: =SUM(P86:P89) -> -384.89796 | Q90: =SUM(Q86:Q89) -> -384.89796 | R90: =SUM(R86:R89) -> -401.78872 | S90: =SUM(S86:S89) -> -421.99979 | ... V90: =SUM(V86:V89) -> -516.47784
B92: Total Transaction Perimeter Adj. NWC | F92: =F84+F90 -> 91.731151 | G92: =G84+G90 -> 97.251876 | H92: =H84+H90 -> 67.516691 | I92: =I84+I90 -> 100.68946 | J92: =J84+J90 -> 112.17179 | K92: =K84+K90 -> 102.50383 | L92: =L84+L90 -> 102.50383 | M92: =M84+M90 -> 104.02431 | ... V92: =V84+V90 -> 149.59568
B93: Organic NWC as % of Revenue | F93: =F92/F$23 -> 0.081455357 | G93: =G92/G$23 -> 0.080041273 | L93: =(L92)/SUM(K$23,J$23,I$23,H$23) -> 0.082418479 | M93: =(M92)/SUM(M$23,K$23,J$23,I$23) -> 0.082818992 | N93: =(N92)/SUM(N$23,M$23,K$23,J$23) -> 0.082742518 | O93: =(O92)/SUM(O$23,N$23,M$23,K$23) -> 0.083371611 | P93: =(P92)/SUM(P$23,O$23,N$23,M$23) -> 0.083536251 | Q93: =(Q92)/Q23 -> 0.083536251 | R93: =(R92)/R23 -> 0.084498494 | S93: =(S92)/S23 -> 0.085239324 | T93: =(T92)/T23 -> 0.085473744 | U93: =(U92)/U23 -> 0.085666016 | V93: =(V92)/V23 -> 0.085858595
B95: Organic Change in NWC | G95: =F92-G92 -> -5.5207245 | L95: =G92-L92 -> -5.2519495 | M95: =L92-M92 -> -1.5204852 | N95: =M92-N92 -> 1.8308081 | O95: =N92-O92 -> -3.1519324 | P95: =O92-P92 -> -2.2800103 | Q95: =L92-Q92 -> -5.1216199 | R95: =Q92-R92 -> -6.3843508 | S95: =R92-S92 -> -7.0861113 | T95: =S92-T92 -> -8.1493559 | U95: =T92-U92 -> -9.6407084 | V95: =U92-V92 -> -10.709711
B96: Acquired Change in NWC
B97: Total Change in NWC | G97: =SUM(G95:G96) -> -5.5207245 | H97: =SUM(H95:H96) -> 0 | I97: =SUM(I95:I96) -> 0 | J97: =SUM(J95:J96) -> 0 | K97: =SUM(K95:K96) -> 0 | L97: =SUM(L95:L96) -> -5.2519495 | M97: =SUM(M95:M96) -> -1.5204852 | N97: =SUM(N95:N96) -> 1.8308081 | ... V97: =SUM(V95:V96) -> -10.709711
B99: DSO | F99: =365*(F81/F$23) -> 120.77851 | G99: =365*(G81/G$23) -> 122.56208 | H99: =90*(H81/H$23) -> 96.453545 | I99: =90*(I81/I$23) -> 91.779953 | J99: =90*(J81/J$23) -> 97.239973 | K99: =L99 -> 121.6703 | L99: =AVERAGE(F99,G99) -> 121.6703 | M99: =Q99 -> 121.6703 | N99: =Q99 -> 121.6703 | O99: =Q99 -> 121.6703 | P99: =Q99 -> 121.6703 | Q99: =$L99 -> 121.6703 | R99: =$L99 -> 121.6703 | S99: =$L99 -> 121.6703 | T99: =$L99 -> 121.6703 | U99: =$L99 -> 121.6703 | V99: =$L99 -> 121.6703
B100: Inventory % of Revenue | F100: =F82/F$23 -> 0.020554321 | G100: =G82/G$23 -> 0.018812415 | H100: =H82/H$23/4 -> 0.0081020576 | I100: =I82/I$23/4 -> 0.0056626599 | J100: =J82/J$23/4 -> 0.01813563 | K100: =L100 -> 0.019683368 | L100: =AVERAGE(F100,G100) -> 0.019683368 | M100: =Q100 -> 0.019683368 | N100: =Q100 -> 0.019683368 | O100: =Q100 -> 0.019683368 | P100: =Q100 -> 0.019683368 | Q100: =$L100 -> 0.019683368 | R100: =$L100 -> 0.019683368 | S100: =$L100 -> 0.019683368 | T100: =$L100 -> 0.019683368 | U100: =$L100 -> 0.019683368 | V100: =$L100 -> 0.019683368
B101: Prepaid and Other CA % of Revenue | F101: =F83/F$23 -> 0.032750157 | G101: =G83/G$23 -> 0.025765915 | H101: =H83/H$23/4 -> 0.031284982 | I101: =I83/I$23/4 -> 0.026790204 | J101: =J83/J$23/4 -> 0.031762822 | K101: =L101 -> 0.029258036 | L101: =AVERAGE(F101,G101) -> 0.029258036 | M101: =Q101 -> 0.029258036 | N101: =Q101 -> 0.029258036 | O101: =Q101 -> 0.029258036 | P101: =Q101 -> 0.029258036 | Q101: =$L101 -> 0.029258036 | R101: =$L101 -> 0.029258036 | S101: =$L101 -> 0.029258036 | T101: =$L101 -> 0.029258036 | U101: =$L101 -> 0.029258036 | V101: =$L101 -> 0.029258036
B103: DPO | F103: =365*(-F86/F31) -> 101.42789 | G103: =365*(-G86/G31) -> 107.74409 | H103: =90*(-H86/H31) -> 89.222634 | I103: =90*(-I86/I31) -> 77.341797 | J103: =90*(-J86/J31) -> 80.693146 | K103: =L103 -> 104.58599 | L103: =AVERAGE(F103,G103) -> 104.58599 | M103: =Q103 -> 104.58599 | N103: =Q103 -> 104.58599 | O103: =Q103 -> 104.58599 | P103: =Q103 -> 104.58599 | Q103: =$L103 -> 104.58599 | R103: =$L103 -> 104.58599 | S103: =$L103 -> 104.58599 | T103: =$L103 -> 104.58599 | U103: =$L103 -> 104.58599 | V103: =$L103 -> 104.58599
B104: Accrued Expenses % of COGS + Opex | F104: =F87/(F$31+F$47) -> -0.023458581 | G104: =G87/(G$31+G$47) -> -0.019283735 | H104: =H87/(H$31+H$47)/4 -> -0.0092064056 | I104: =I87/(I$31+I$47)/4 -> -0.01214208 | J104: =J87/(J$31+J$47)/4 -> -0.0094121598 | K104: =L104 -> -0.021371158 | L104: =AVERAGE(F104,G104) -> -0.021371158 | M104: =Q104 -> -0.021371158 | N104: =Q104 -> -0.021371158 | O104: =Q104 -> -0.021371158 | P104: =Q104 -> -0.021371158 | Q104: =$L104 -> -0.021371158 | R104: =$L104 -> -0.021371158 | S104: =$L104 -> -0.021371158 | T104: =$L104 -> -0.021371158 | U104: =$L104 -> -0.021371158 | V104: =$L104 -> -0.021371158
B105: Advanced Billings and Customer Deposits % of COGS + Opex | F105: =F88/(F$31+F$47) -> -0.045256121 | G105: =G88/(G$31+G$47) -> -0.033621619 | H105: =H88/(H$31+H$47)/4 -> -0.029356123 | I105: =I88/(I$31+I$47)/4 -> -0.015833542 | J105: =J88/(J$31+J$47)/4 -> -0.02009092 | K105: =L105 -> -0.03943887 | L105: =AVERAGE(F105,G105) -> -0.03943887 | M105: =Q105 -> -0.03943887 | N105: =Q105 -> -0.03943887 | O105: =Q105 -> -0.03943887 | P105: =Q105 -> -0.03943887 | Q105: =$L105 -> -0.03943887 | R105: =$L105 -> -0.03943887 | S105: =$L105 -> -0.03943887 | T105: =$L105 -> -0.03943887 | U105: =$L105 -> -0.03943887 | V105: =$L105 -> -0.03943887
B106: Total Other Current Liabilities % of COGS + Opex | F106: =F89/(F$31+F$47) -> -0.012980991 | G106: =G89/(G$31+G$47) -> -0.013045661 | H106: =H89/(H$31+H$47)/4 -> -0.012281241 | I106: =I89/(I$31+I$47)/4 -> -0.01275314 | J106: =J89/(J$31+J$47)/4 -> -0.013779807 | K106: =L106 -> -0.013013326 | L106: =AVERAGE(F106,G106) -> -0.013013326 | M106: =Q106 -> -0.013013326 | N106: =Q106 -> -0.013013326 | O106: =Q106 -> -0.013013326 | P106: =Q106 -> -0.013013326 | Q106: =$L106 -> -0.013013326 | R106: =$L106 -> -0.013013326 | S106: =$L106 -> -0.013013326 | T106: =$L106 -> -0.013013326 | U106: =$L106 -> -0.013013326 | V106: =$L106 -> -0.013013326
B108: Capex Build
B110: Maintenance | D110: -11.794052 | E110: -10.066015 | F110: -6.1722099 | G110: -10.431784 | L110: -19.703431 | M110: =-M113*M$28 -> -3.1139775 | N110: =-N113*N$28 -> -3.2119525 | O110: =-O113*O$28 -> -3.3118636 | P110: =-P113*P$28 -> -3.9197841 | Q110: =-Q$28*Q113 -> -13.557578 | R110: =-R$28*R113 -> -14.198266 | S110: =-S$28*S113 -> -14.949669 | T110: =-T$28*T113 -> -15.911973 | U110: =-U$28*U113 -> -17.060507 | V110: =-V$28*V113 -> -18.334852
B111: Growth | D111: -2.3803012 | E111: -3.8048435 | F111: -7.9705634 | G111: -13.140452 | L111: -5.688527 | M111: =-M114*M$28 -> -1.7361973 | N111: =-N114*N$28 -> -1.7908232 | O111: =-O114*O$28 -> -1.8465286 | P111: =-P114*P$28 -> -2.1854745 | Q111: =-Q$28*Q114 -> -7.5590237 | R111: =-R$28*R114 -> -7.9162395 | S111: =-S$28*S114 -> -8.335184 | T111: =-T$28*T114 -> -8.8717161 | U111: =-U$28*U114 -> -9.5120809 | V111: =-V$28*V114 -> -10.222591
B112: Total Capex | D112: -14.174353 | E112: -13.870859 | F112: -14.142773 | G112: -23.572237 | L112: -25.391958 | M112: =SUM(M110:M111) -> -4.8501748 | N112: =SUM(N110:N111) -> -5.0027758 | O112: =SUM(O110:O111) -> -5.1583922 | P112: =SUM(P110:P111) -> -6.1052586 | Q112: =SUM(Q110:Q111) -> -21.116601 | R112: =SUM(R110:R111) -> -22.114506 | S112: =SUM(S110:S111) -> -23.284853 | T112: =SUM(T110:T111) -> -24.783689 | ... V112: =SUM(V110:V111) -> -28.557443
B113: Maintenance % of Revenue | D113: =-D110/D$28 -> 0.013214659 | E113: =-E110/E$28 -> 0.011116922 | F113: =-F110/F$28 -> 0.0054807942 | G113: =-G110/G$28 -> 0.0085856782 | L113: =-L110/L$28 -> 0.015842597 | M113: =Q113 -> 0.010523062 | N113: =Q113 -> 0.010523062 | O113: =Q113 -> 0.010523062 | P113: =Q113 -> 0.010523062 | Q113: =IF($C$62=0,1.05230618437647%,1.05230618437647%-0%) -> 0.010523062 | R113: =IF($C$62=0,1.05230618437647%,1.05230618437647%-0%) -> 0.010523062 | S113: =IF($C$62=0,1.05230618437647%,1.05230618437647%-0%) -> 0.010523062 | T113: =IF($C$62=0,1.05230618437647%,1.05230618437647%-0%) -> 0.010523062 | U113: =IF($C$62=0,1.05230618437647%,1.05230618437647%-0%) -> 0.010523062 | V113: =IF($C$62=0,1.05230618437647%,1.05230618437647%-0%) -> 0.010523062
B114: Growth% of Revenue | D114: =-D111/D$28 -> 0.0026670113 | E114: =-E111/E$28 -> 0.0042020745 | F114: =-F111/F$28 -> 0.0070776948 | G114: =-G111/G$28 -> 0.010814995 | L114: =-L111/L$28 -> 0.0045738755 | M114: =Q114 -> 0.0058671302 | N114: =Q114 -> 0.0058671302 | O114: =Q114 -> 0.0058671302 | P114: =Q114 -> 0.0058671302 | Q114: 0.0058671302 | R114: 0.0058671302 | S114: 0.0058671302 | T114: 0.0058671302 | U114: 0.0058671302 | V114: 0.0058671302
B115: Total % of Revenue | D115: =-D112/D$28 -> 0.015881671 | E115: =-E112/E$28 -> 0.015318996 | F115: =-F112/F$28 -> 0.012558489 | G115: =-G112/G$28 -> 0.019400673 | L115: =-L112/L$28 -> 0.020416473 | M115: =Q115 -> 0.016390192 | N115: =Q115 -> 0.016390192 | O115: =Q115 -> 0.016390192 | P115: =Q115 -> 0.016390192 | Q115: =-Q112/Q$28 -> 0.016390192 | R115: =-R112/R$28 -> 0.016390192 | S115: =-S112/S$28 -> 0.016390192 | T115: =-T112/T$28 -> 0.016390192 | U115: =-U112/U$28 -> 0.016390192 | V115: =-V112/V$28 -> 0.016390192
A117: x

Sheet Revenue Build
B2: Cross-Sell | C2: =XSell -> Base
D5: 43830 | E5: =EOMONTH(D5,12) -> 44196 | F5: =EOMONTH(E5,12) -> 44561 | G5: =EOMONTH(F5,12) -> 44926 | H5: =EOMONTH(G5,12) -> 45291 | I5: =EOMONTH(H5,12) -> 45657 | J5: =EOMONTH(I5,12) -> 46022 | K5: =EOMONTH(J5,12) -> 46387 | L5: =EOMONTH(K5,12) -> 46752 | ... N5: =EOMONTH(M5,12) -> 47483
D6: 2019 | E6: =D6+1 -> 2020 | F6: =E6+1 -> 2021 | G6: =F6+1 -> 2022 | H6: =G6+1 -> 2023 | I6: =H6+1 -> 2024 | J6: =I6+1 -> 2025 | K6: =J6+1 -> 2026 | L6: =K6+1 -> 2027 | ... N6: =M6+1 -> 2029
A7: x | B7: Industry Data
B9: Forecasted Industry Growth
B10: Communications | J10: 0.014 | K10: 0.014 | L10: 0.014 | M10: 0.014 | N10: 0.014
B11: Consulting | J11: 0.135 | K11: 0.135 | L11: 0.135 | M11: 0.135 | N11: 0.135
B12: Cloud | J12: 0.145 | K12: 0.145 | L12: 0.145 | M12: 0.145 | N12: 0.145
B13: Infrastructure | J13: 0.045 | K13: 0.045 | L13: 0.045 | M13: 0.045 | N13: 0.045
A15: x | B15: Infrastructure
B17: Customer A | D17: 133.87019 | E17: 119.36184 | F17: 216.554 | G17: 184.38929 | H17: 161.06997 | I17: 162.68067
B18: Customer B | D18: 0 | E18: 0 | F18: 0 | G18: 0 | H18: 0 | I18: 0
B19: Customer C | D19: 0 | E19: 1.211 | F19: 0.737 | G19: 0.852 | H19: 1.0747681 | I19: 1.1257698
B20: Customer D | D20: 35.109 | E20: 29.821 | F20: 34.501 | G20: 34.163 | H20: 37.897286 | I20: 40.171123
B21: Customer E | D21: 6.209 | E21: 5.610572 | F21: 2.475 | G21: 5.859 | H21: 21.205057 | I21: 19.296602
B22: Customer F | D22: 7.1745 | E22: 11.310568 | F22: 20.824025 | G22: 22.216846 | H22: 14.45348 | I22: 14.887084
B23: Customer G | D23: 16.3534 | E23: 5.359 | F23: 2.671 | G23: 4.548 | H23: 1.1347891 | I23: 1.3730948
B24: Customer H | D24: 1.2815 | E24: 0.843 | F24: 1.636 | G24: 1.524 | H24: 2.888449 | I24: 3.0617559
B25: Customer I | D25: 1.83786 | E25: 5.971 | F25: 8.911 | G25: 11.724 | H25: 10.591103 | I25: 11.014747
B26: Customer J | D26: 9.20245 | E26: 10.149942 | F26: 15.27686 | G26: 13.014011 | H26: 13.950893 | I26: 12.695313
B27: Customer K | D27: 1.593 | E27: 0.661 | F27: 0.266 | G27: 0.502 | H27: 2.069129 | I27: 7.9868379
B28: Customer L | D28: 7.267305 | E28: 2.052507 | F28: 2.779591 | G28: 3.606554 | H28: 5.20156 | I28: 5.5136536
... B31: Customer O | D31: 0 | E31: 0 | F31: 0.035 | G31: 0.202 | H31: 0.620261 | I31: 0.620261
B32: Top 15 Customers | D32: =SUM(D17:D31) -> 227.5977 | E32: =SUM(E17:E31) -> 202.94023 | F32: =SUM(F17:F31) -> 314.58472 | G32: =SUM(G17:G31) -> 295.44871 | H32: =SUM(H17:H31) -> 291.33648 | I32: =SUM(I17:I31) -> 300.89318 | J32: =I32*(1+J33) -> 308.41551 | K32: =J32*(1+K33) -> 316.1259 | L32: =K32*(1+L33) -> 324.02905 | M32: =L32*(1+M33) -> 332.12978 | N32: =M32*(1+N33) -> 340.43302
B33: % growth | E33: =E32/D32-1 -> -0.10833796 | F33: =F32/E32-1 -> 0.55013483 | G33: =G32/F32-1 -> -0.060829435 | H33: =H32/G32-1 -> -0.013918584 | I33: =I32/H32-1 -> 0.032802967 | J33: =SUM(J34,J35) -> 0.025 | K33: =SUM(K34,K35) -> 0.025 | L33: =SUM(L34,L35) -> 0.025 | M33: =SUM(M34,M35) -> 0.025 | N33: =SUM(N34,N35) -> 0.025
B34: industry growth | J34: =J13 -> 0.045 | K34: =K13 -> 0.045 | L34: =L13 -> 0.045 | M34: =M13 -> 0.045 | N34: =N13 -> 0.045
B35: size impact | J35: -0.02 | K35: -0.02 | L35: -0.02 | M35: -0.02 | N35: -0.02
B37: Remaining Customers | D37: ='Top Customer Data'!D27 -> 329.60544 | E37: ='Top Customer Data'!E27 -> 316.18914 | F37: ='Top Customer Data'!F27 -> 305.09224 | G37: ='Top Customer Data'!G27 -> 356.48743 | H37: ='Top Customer Data'!H27 -> 363.82246 | I37: ='Top Customer Data'!I27 -> 369.76753 | J37: =I37*(1+J38) -> 386.40707 | K37: =J37*(1+K38) -> 403.79538 | L37: =K37*(1+L38) -> 421.96618 | M37: =L37*(1+M38) -> 440.95465 | N37: =M37*(1+N38) -> 460.79761
B38: % growth | E38: =E37/D37-1 -> -0.040704144 | F38: =F37/E37-1 -> -0.035095762 | G38: =G37/F37-1 -> 0.16845787 | H38: =H37/G37-1 -> 0.020575863 | I38: =I37/H37-1 -> 0.016340566 | J38: =SUM(J39,J40) -> 0.045 | K38: =SUM(K39,K40) -> 0.045 | L38: =SUM(L39,L40) -> 0.045 | M38: =SUM(M39,M40) -> 0.045 | N38: =SUM(N39,N40) -> 0.045
B39: industry growth | J39: =J13 -> 0.045 | K39: =K13 -> 0.045 | L39: =L13 -> 0.045 | M39: =M13 -> 0.045 | N39: =N13 -> 0.045
B40: share taking | J40: 0 | K40: 0 | L40: 0 | M40: 0 | N40: 0
B42: Total Revenue | D42: =D37+D32 -> 557.20315 | E42: =E37+E32 -> 519.12937 | F42: =F37+F32 -> 619.67696 | G42: =G37+G32 -> 651.93614 | H42: =H37+H32 -> 655.15895 | I42: =I37+I32 -> 670.66071 | J42: =J37+J32 -> 694.82258 | K42: =K37+K32 -> 719.92129 | ... N42: =N37+N32 -> 801.23063
B43: % growth | E43: =E42/D42-1 -> -0.068330156 | F43: =F42/E42-1 -> 0.19368504 | G43: =G42/F42-1 -> 0.052058055 | H43: =H42/G42-1 -> 0.0049434423 | I43: =I42/H42-1 -> 0.023661077 | J43: =J42/I42-1 -> 0.036026963 | K43: =K42/J42-1 -> 0.036122467 | L43: =L42/K42-1 -> 0.036217765 | ... N43: =N42/M42-1 -> 0.036407671
B45: Top 15 Customer Outgrowth | E45: =E33-E38 -> -0.067633814 | F45: =F33-F38 -> 0.58523059 | G45: =G33-G38 -> -0.2292873 | H45: =H33-H38 -> -0.034494447 | I45: =I33-I38 -> 0.016462401 | J45: =J33-J38 -> -0.02 | K45: =K33-K38 -> -0.02 | L45: =L33-L38 -> -0.02 | ... N45: =N33-N38 -> -0.02
B47: Mix:
B48: Top 15 | D48: =D32/D$42 -> 0.4084645 | E48: =E32/E$42 -> 0.3909242 | F48: =F32/F$42 -> 0.50765922 | G48: =G32/G$42 -> 0.45318658 | H48: =H32/H$42 -> 0.44468062 | I48: =I32/I$42 -> 0.44865187 | J48: =J32/J$42 -> 0.44387664 | K48: =K32/K$42 -> 0.43911176 | ... N48: =N32/N$42 -> 0.42488767
B49: Other | D49: =D37/D42 -> 0.5915355 | E49: =E37/E42 -> 0.6090758 | F49: =F37/F42 -> 0.49234078 | G49: =G37/G42 -> 0.54681342 | H49: =H37/H42 -> 0.55531938 | I49: =I37/I42 -> 0.55134813 | J49: =J37/J42 -> 0.55612336 | K49: =K37/K42 -> 0.56088824 | ... N49: =N37/N42 -> 0.57511233
A52: x | B52: Cloud
B54: Customer A | D54: ='Top Customer Data'!D34 -> 0 | E54: ='Top Customer Data'!E34 -> 0 | F54: ='Top Customer Data'!F34 -> 0 | G54: ='Top Customer Data'!G34 -> 0 | H54: ='Top Customer Data'!H34 -> 0 | I54: ='Top Customer Data'!I34 -> 0
B55: Customer B | D55: ='Top Customer Data'!D35 -> 0 | E55: ='Top Customer Data'!E35 -> 0 | F55: ='Top Customer Data'!F35 -> 0 | G55: ='Top Customer Data'!G35 -> 0 | H55: ='Top Customer Data'!H35 -> 0 | I55: ='Top Customer Data'!I35 -> 0
B56: Customer C | D56: ='Top Customer Data'!D36 -> 0 | E56: ='Top Customer Data'!E36 -> 0 | F56: ='Top Customer Data'!F36 -> 0 | G56: ='Top Customer Data'!G36 -> 0 | H56: ='Top Customer Data'!H36 -> 0 | I56: ='Top Customer Data'!I36 -> 0
B57: Customer D | D57: ='Top Customer Data'!D37 -> 0.575 | E57: ='Top Customer Data'!E37 -> 0.566 | F57: ='Top Customer Data'!F37 -> 0.167 | G57: ='Top Customer Data'!G37 -> 0.021 | H57: ='Top Customer Data'!H37 -> 0.091266 | I57: ='Top Customer Data'!I37 -> 0.09217866
B58: Customer E | D58: ='Top Customer Data'!D38 -> 12.8567 | E58: ='Top Customer Data'!E38 -> 5.684 | F58: ='Top Customer Data'!F38 -> 5.391 | G58: ='Top Customer Data'!G38 -> 6.813 | H58: ='Top Customer Data'!H38 -> 9.146 | I58: ='Top Customer Data'!I38 -> 10.15206
B59: Customer F | D59: ='Top Customer Data'!D39 -> 0 | E59: ='Top Customer Data'!E39 -> 0 | F59: ='Top Customer Data'!F39 -> 0 | G59: ='Top Customer Data'!G39 -> 0 | H59: ='Top Customer Data'!H39 -> 0 | I59: ='Top Customer Data'!I39 -> 0
B60: Customer G | D60: ='Top Customer Data'!D40 -> 10.8393 | E60: ='Top Customer Data'!E40 -> 10.647 | F60: ='Top Customer Data'!F40 -> 10.125 | G60: ='Top Customer Data'!G40 -> 10.425 | H60: ='Top Customer Data'!H40 -> 10.2854 | I60: ='Top Customer Data'!I40 -> 10.593962
B61: Customer H | D61: ='Top Customer Data'!D41 -> 0 | E61: ='Top Customer Data'!E41 -> 0 | F61: ='Top Customer Data'!F41 -> 0 | G61: ='Top Customer Data'!G41 -> 0 | H61: ='Top Customer Data'!H41 -> 0 | I61: ='Top Customer Data'!I41 -> 0
B62: Customer I | D62: ='Top Customer Data'!D42 -> 0 | E62: ='Top Customer Data'!E42 -> 0 | F62: ='Top Customer Data'!F42 -> 0 | G62: ='Top Customer Data'!G42 -> 0 | H62: ='Top Customer Data'!H42 -> 0 | I62: ='Top Customer Data'!I42 -> 0
B63: Customer J | D63: ='Top Customer Data'!D43 -> 0.0144 | E63: ='Top Customer Data'!E43 -> 0.10215 | F63: ='Top Customer Data'!F43 -> 0.0939 | G63: ='Top Customer Data'!G43 -> 0.0144 | H63: ='Top Customer Data'!H43 -> 0.0144 | I63: ='Top Customer Data'!I43 -> 0.014544
B64: Customer K | D64: ='Top Customer Data'!D44 -> 0 | E64: ='Top Customer Data'!E44 -> 0.876954 | F64: ='Top Customer Data'!F44 -> 3.954 | G64: ='Top Customer Data'!G44 -> 5.143 | H64: ='Top Customer Data'!H44 -> 9.031 | I64: ='Top Customer Data'!I44 -> 10.47596
B65: Customer L | D65: ='Top Customer Data'!D45 -> 0.04687275 | E65: ='Top Customer Data'!E45 -> 1.852743 | F65: ='Top Customer Data'!F45 -> 5.311784 | G65: ='Top Customer Data'!G45 -> 6.165946 | H65: ='Top Customer Data'!H45 -> 6.08 | I65: ='Top Customer Data'!I45 -> 6.1408
... B68: Customer O | D68: ='Top Customer Data'!D48 -> 0 | E68: ='Top Customer Data'!E48 -> 0 | F68: ='Top Customer Data'!F48 -> 0 | G68: ='Top Customer Data'!G48 -> 0 | H68: ='Top Customer Data'!H48 -> 0.188 | I68: ='Top Customer Data'!I48 -> 0.42488
B69: Top 15 Customers | D69: =SUM(D54:D68) -> 24.332273 | E69: =SUM(E54:E68) -> 19.728847 | F69: =SUM(F54:F68) -> 25.39438 | G69: =SUM(G54:G68) -> 30.23941 | H69: =SUM(H54:H68) -> 38.134066 | I69: =SUM(I54:I68) -> 42.893965
B70: % growth | E70: =E69/D69-1 -> -0.18919013 | F70: =F69/E69-1 -> 0.28717 | G70: =G69/F69-1 -> 0.19079143 | H70: =H69/G69-1 -> 0.26107176 | I70: =I69/H69-1 -> 0.12482012
B72: Remaining Customers | D72: ='Top Customer Data'!D52 -> 57.537436 | E72: ='Top Customer Data'!E52 -> 55.89576 | F72: ='Top Customer Data'!F52 -> 60.153237 | G72: ='Top Customer Data'!G52 -> 59.750486 | H72: ='Top Customer Data'!H52 -> 64.415468 | I72: ='Top Customer Data'!I52 -> 71.193221
B73: % growth | E73: =E72/D72-1 -> -0.028532318 | F73: =F72/E72-1 -> 0.076168158 | G73: =G72/F72-1 -> -0.0066954038 | H73: =H72/G72-1 -> 0.078074366 | I73: =I72/H72-1 -> 0.10521934
B74: Cloud Revenues | I74: =I6 -> 2024 | J74: =J6 -> 2025 | K74: =K6 -> 2026 | L74: =L6 -> 2027 | M74: =M6 -> 2028 | N74: =N6 -> 2029
B76: Total Cloud Revenues | D76: =D69+D72 -> 81.869709 | E76: =E69+E72 -> 75.624607 | F76: =F69+F72 -> 85.547617 | G76: =G69+G72 -> 89.989896 | H76: =H69+H72 -> 102.54953 | I76: =I69+I72 -> 114.08719 | J76: =I76*(1+J77) -> 125.86906 | K76: =J76*(1+K77) -> 137.82897 | L76: =K76*(1+L77) -> 149.77183 | M76: =L76*(1+M77) -> 162.98588 | N76: =M76*(1+N77) -> 177.58612
B77: % growth | E77: =E76/D76-1 -> -0.076280987 | F77: =F76/E76-1 -> 0.13121404 | G77: =G76/F76-1 -> 0.051927569 | H77: =H76/G76-1 -> 0.13956719 | I77: =I76/H76-1 -> 0.11250809 | J77: =SUM(J78:J81) -> 0.10327083 | K77: =SUM(K78:K81) -> 0.095018616 | L77: =SUM(L78:L81) -> 0.086649882 | M77: =SUM(M78:M81) -> 0.088227865 | N77: =SUM(N78:N81) -> 0.089579756
B78: industry growth | J78: =J12 -> 0.145 | K78: =K12 -> 0.145 | L78: =L12 -> 0.145 | M78: =M12 -> 0.145 | N78: =N12 -> 0.145
B79: Private Cloud Headwind | J79: -0.07 | K79: -0.07 | L79: -0.07 | M79: -0.07 | N79: -0.07
B80: cross-sell benefit | J80: =J87 -> 0.018270831 | K80: =K87 -> 0.020018616 | L80: =L87 -> 0.021649882 | M80: =M87 -> 0.023227865 | N80: =N87 -> 0.024579756
B81: share taking | J81: 0.01 | K81: 0 | L81: -0.01 | M81: -0.01 | N81: -0.01
B83: Cross Sell Benefit:
B84: Infrastructure Sales | J84: =J42 -> 694.82258 | K84: =K42 -> 719.92129 | L84: =L42 -> 745.99523 | M84: =M42 -> 773.08443 | N84: =N42 -> 801.23063
B85: Cloud Attach (bps) | J85: =J137 -> 30 | K85: =K137 -> 35 | L85: =L137 -> 40 | M85: =M137 -> 45 | N85: =N137 -> 50
B86: Cloud Revenues | J86: =J84*J85/10000 -> 2.0844677 | K86: =K84*K85/10000 -> 2.5197245 | L86: =L84*L85/10000 -> 2.9839809 | M86: =M84*M85/10000 -> 3.4788799 | N86: =N84*N85/10000 -> 4.0061532
B87: impact to growth (%) | J87: =J86/I76 -> 0.018270831 | K87: =K86/J76 -> 0.020018616 | L87: =L86/K76 -> 0.021649882 | M87: =M86/L76 -> 0.023227865 | N87: =N86/M76 -> 0.024579756
A89: x | B89: Consulting Revenue
B91: Total Consulting Revenues | D91: =+'Top Customer Data'!D80 -> 152.63324 | E91: =+'Top Customer Data'!E80 -> 196.02662 | F91: =+'Top Customer Data'!F80 -> 299.11454 | G91: =+'Top Customer Data'!G80 -> 339.4398 | H91: =+'Top Customer Data'!H80 -> 340.65803 | I91: =+'Top Customer Data'!I80 -> 349.78974 | J91: =(1+J92)*I91 -> 369.723 | K91: =(1+K92)*J91 -> 398.53211 | L91: =(1+L92)*K91 -> 445.85529 | M91: =(1+M92)*L91 -> 507.97847 | N91: =(1+N92)*M91 -> 578.95925
B92: % growth | E92: =E91/D91-1 -> 0.28429837 | F92: =F91/E91-1 -> 0.52588734 | G92: =G91/F91-1 -> 0.13481544 | H92: =H91/G91-1 -> 0.0035889671 | I92: =I91/H91-1 -> 0.026806083 | J92: =SUM(J93:J96) -> 0.056986401 | K92: =SUM(K93:K96) -> 0.077920786 | L92: =SUM(L93:L96) -> 0.11874371 | M92: =SUM(M93:M96) -> 0.13933484 | N92: =SUM(N93:N96) -> 0.13973188
B93: industry growth | J93: =J11 -> 0.135 | K93: =K11 -> 0.135 | L93: =L11 -> 0.135 | M93: =M11 -> 0.135 | N93: =N11 -> 0.135
B94: share taking | J94: 0 | K94: 0 | L94: 0 | M94: 0 | N94: 0
B95: NT restructuring headwind | J95: -0.08 | K95: -0.06 | L95: -0.02 | M95: 0 | N95: 0
B96: cross-sell | J96: =J102 -> 0.0019864007 | K96: =K102 -> 0.0029207864 | L96: =L102 -> 0.0037437146 | M96: =M102 -> 0.0043348394 | N96: =N102 -> 0.0047318776
B98: Cross Sell Benefit
B99: Infrastructure Sales | J99: =J84 -> 694.82258 | K99: =K84 -> 719.92129 | L99: =L84 -> 745.99523 | M99: =M84 -> 773.08443 | N99: =N84 -> 801.23063
B100: Consulting Attach (bps) | J100: =J132 -> 10 | K100: =K132 -> 15 | L100: =L132 -> 20 | M100: =M132 -> 25 | N100: =N132 -> 30
B101: Consulting Revenues | J101: =J99*J100/10000 -> 0.69482258 | K101: =K99*K100/10000 -> 1.0798819 | L101: =L99*L100/10000 -> 1.4919905 | M101: =M99*M100/10000 -> 1.9327111 | N101: =N99*N100/10000 -> 2.4036919
B102: impact to growth (%) | J102: =J101/I91 -> 0.0019864007 | K102: =K101/J91 -> 0.0029207864 | L102: =L101/K91 -> 0.0037437146 | M102: =M101/L91 -> 0.0043348394 | N102: =N101/M91 -> 0.0047318776
B104: T15 Customers Revenue | D104: ='Top Customer Data'!D74 -> 102.0444 | E104: ='Top Customer Data'!E74 -> 135.56815 | F104: ='Top Customer Data'!F74 -> 224.51887 | G104: ='Top Customer Data'!G74 -> 255.26094 | H104: ='Top Customer Data'!H74 -> 255.09192 | I104: ='Top Customer Data'!I74 -> 254.81135
E105: =E104/D104-1 -> 0.32852124 | F105: =F104/E104-1 -> 0.65613289 | G105: =G104/F104-1 -> 0.13692421 | H105: =H104/G104-1 -> -0.00066216554 | I105: =I104/H104-1 -> -0.0010998605
B107: Other Customers Revenue | D107: ='Top Customer Data'!D77 -> 50.588842 | E107: ='Top Customer Data'!E77 -> 60.458471 | F107: ='Top Customer Data'!F77 -> 74.595667 | G107: ='Top Customer Data'!G77 -> 84.178854 | H107: ='Top Customer Data'!H77 -> 85.566117 | I107: ='Top Customer Data'!I77 -> 94.97839
E108: =E107/D107-1 -> 0.19509499 | F108: =F107/E107-1 -> 0.23383316 | G108: =G107/F107-1 -> 0.12846842 | H108: =H107/G107-1 -> 0.01647995 | I108: =I107/H107-1 -> 0.11
A110: x | B110: Communications Revenue
B112: Total Communications Revenue | D112: ='Top Customer Data'!D105 -> 100.79152 | E112: ='Top Customer Data'!E105 -> 114.68729 | F112: ='Top Customer Data'!F105 -> 121.81334 | G112: ='Top Customer Data'!G105 -> 133.65576 | H112: ='Top Customer Data'!H105 -> 145.33304 | I112: ='Top Customer Data'!I105 -> 153.83051 | J112: =I112*(1+J113) -> 158.83775 | K112: =J112*(1+K113) -> 164.3754 | L112: =K112*(1+L113) -> 170.48251 | M112: =L112*(1+M113) -> 177.20056 | N112: =M112*(1+N113) -> 184.57352
B113: % growth | E113: =E112/D112-1 -> 0.1378664 | F113: =F112/E112-1 -> 0.062134672 | G113: =G112/F112-1 -> 0.097217754 | H113: =H112/G112-1 -> 0.087368314 | I113: =I112/H112-1 -> 0.058468914 | J113: =SUM(J114:J116) -> 0.032550418 | K113: =SUM(K114:K116) -> 0.034863511 | L113: =SUM(L114:L116) -> 0.037153452 | M113: =SUM(M114:M116) -> 0.039406081 | N113: =SUM(N114:N116) -> 0.041608017
B114: industry growth | J114: =J10 -> 0.014 | K114: =K10 -> 0.014 | L114: =L10 -> 0.014 | M114: =M10 -> 0.014 | N114: =N10 -> 0.014
B115: share taking | J115: 0.005 | K115: 0.005 | L115: 0.005 | M115: 0.005 | N115: 0.005
B116: cross-sell | J116: =J122 -> 0.013550418 | K116: =K122 -> 0.015863511 | L116: =L122 -> 0.018153452 | M116: =M122 -> 0.020406081 | N116: =N122 -> 0.022608017
B118: Cross Sell Benefit
B119: Infrastructure Sales | J119: =J99 -> 694.82258 | K119: =K99 -> 719.92129 | L119: =L99 -> 745.99523 | M119: =M99 -> 773.08443 | N119: =N99 -> 801.23063
B120: Comms Attach (bps) | J120: =J137 -> 30 | K120: =K137 -> 35 | L120: =L137 -> 40 | M120: =M137 -> 45 | N120: =N137 -> 50
B121: Comms Revenues | J121: =J119*J120/10000 -> 2.0844677 | K121: =K119*K120/10000 -> 2.5197245 | L121: =L119*L120/10000 -> 2.9839809 | M121: =M119*M120/10000 -> 3.4788799 | N121: =N119*N120/10000 -> 4.0061532
B122: impact to growth (%) | J122: =J121/I112 -> 0.013550418 | K122: =K121/J112 -> 0.015863511 | L122: =L121/K112 -> 0.018153452 | M122: =M121/L112 -> 0.020406081 | N122: =N121/M112 -> 0.022608017
B130: Cross Sell Toggles
B132: Consulting | J132: =IF(XSell="None",J133,IF(XSell="Base",J134,IF(XSell="High",J135))) -> 10 | K132: =IF(XSell="None",K133,IF(XSell="Base",K134,IF(XSell="High",K135))) -> 15 | L132: =IF(XSell="None",L133,IF(XSell="Base",L134,IF(XSell="High",L135))) -> 20 | M132: =IF(XSell="None",M133,IF(XSell="Base",M134,IF(XSell="High",M135))) -> 25 | N132: =IF(XSell="None",N133,IF(XSell="Base",N134,IF(XSell="High",N135))) -> 30
B133: None | J133: 0 | K133: 0 | L133: 0 | M133: 0 | N133: 0
B134: Base | J134: 10 | K134: =J134+5 -> 15 | L134: =K134+5 -> 20 | M134: =L134+5 -> 25 | N134: =M134+5 -> 30
B135: High | J135: 30 | K135: =J135+5 -> 35 | L135: =K135+5 -> 40 | M135: =L135+5 -> 45 | N135: =M135+5 -> 50
B137: Other | J137: =IF(XSell="None",J138,IF(XSell="Base",J139,IF(XSell="High",J140))) -> 30 | K137: =IF(XSell="None",K138,IF(XSell="Base",K139,IF(XSell="High",K140))) -> 35 | L137: =IF(XSell="None",L138,IF(XSell="Base",L139,IF(XSell="High",L140))) -> 40 | M137: =IF(XSell="None",M138,IF(XSell="Base",M139,IF(XSell="High",M140))) -> 45 | N137: =IF(XSell="None",N138,IF(XSell="Base",N139,IF(XSell="High",N140))) -> 50
...

Sheet Margin Build vF
B2: Cost Reduction Toggle | C2: =CRT -> Base | J2: 1 | K2: 2 | L2: 3 | M2: 4 | N2: 5
A4: x | B4: EBITDA Margin Build (Cost Savings)
D5: 43830 | E5: =EOMONTH(D5,12) -> 44196 | F5: =EOMONTH(E5,12) -> 44561 | G5: =EOMONTH(F5,12) -> 44926 | H5: =EOMONTH(G5,12) -> 45291 | I5: =EOMONTH(H5,12) -> 45657 | J5: 2025E | K5: 2026E | L5: 2027E | M5: 2028E | N5: 2029E | R5: Cost Savings By Year Summary
B6: EBITDA Margins BoP | E6: 0.018641567 | F6: 0.032411962 | G6: 0.039775653 | H6: 0.049284698 | I6: 0.062454615 | J6: =I20 -> 0.062454615 | K6: =J20 -> 0.071704615 | L6: =K20 -> 0.080954615 | M6: =L20 -> 0.084787949 | N6: =M20 -> 0.088621282
B7: (+) Near-term Offshoring (bps impact) | J7: {=_xlfn.IFS($E$35=0,0,$E$35=1,$D$35,$E$35=2,$D$36)} -> 40 | K7: {=_xlfn.IFS($E$35=0,0,$E$35=1,$D$35,$E$35=2,$D$36)} -> 40 | Q7: Year | R7: Bps | S7: EoP EBITDA Margin
B8: (+) Managed Services Utilization Improvement (bps impact) | J8: {=_xlfn.IFS($E$39=0,0,$E$39=1,$D$39,$E$39=2,$D$40)} -> 17.5 | K8: {=_xlfn.IFS($E$39=0,0,$E$39=1,$D$39,$E$39=2,$D$40)} -> 17.5 | Q8: 1 | R8: =INDEX($J$19:$N$19,MATCH($Q8,$J$2:$N$2,0)) -> 92.5 | S8: =INDEX($J$20:$N$20,MATCH($Q8,$J$2:$N$2,0)) -> 0.071704615
B9: (+) Sales Commission Change (bps impact) | J9: {=_xlfn.IFS($E$43=0,0,$E$43=1,$D$43,$E$43=2,$D$44)} -> 15 | K9: {=_xlfn.IFS($E$43=0,0,$E$43=1,$D$43,$E$43=2,$D$44)} -> 15 | Q9: 2 | R9: =INDEX($J$19:$N$19,MATCH($Q9,$J$2:$N$2,0)) -> 92.5 | S9: =INDEX($J$20:$N$20,MATCH($Q9,$J$2:$N$2,0)) -> 0.080954615
B10: (+) In-Process SG&A Reduction (bps impact) | J10: {=_xlfn.IFS($E$47=0,0,$E$47=1,$D$47,$E$47=2,$D$48)} -> 10 | K10: {=_xlfn.IFS($E$47=0,0,$E$47=1,$D$47,$E$47=2,$D$48)} -> 10 | Q10: 3 | R10: =INDEX($J$19:$N$19,MATCH($Q10,$J$2:$N$2,0)) -> 38.333333 | S10: =INDEX($J$20:$N$20,MATCH($Q10,$J$2:$N$2,0)) -> 0.084787949
B11: (+) Back Office IT Spend Reduction (bps impact) | J11: {=_xlfn.IFS($E$51=0,0,$E$51=1,$D$51,$E$51=2,$D$52)} -> 10 | K11: {=_xlfn.IFS($E$51=0,0,$E$51=1,$D$51,$E$51=2,$D$52)} -> 10 | Q11: 4 | R11: =INDEX($J$19:$N$19,MATCH($Q11,$J$2:$N$2,0)) -> 38.333333 | S11: =INDEX($J$20:$N$20,MATCH($Q11,$J$2:$N$2,0)) -> 0.088621282
B12: (+) Pricing Increase (bps impact) | L12: {=_xlfn.IFS($E$23=0,0,$E$23=1,$D$23,$E$23=2,$D$24)} -> 25 | M12: {=_xlfn.IFS($E$23=0,0,$E$23=1,$D$23,$E$23=2,$D$24)} -> 25 | N12: {=_xlfn.IFS($E$23=0,0,$E$23=1,$D$23,$E$23=2,$D$24)} -> 25 | Q12: 5 | R12: =INDEX($J$19:$N$19,MATCH($Q12,$J$2:$N$2,0)) -> 38.333333 | S12: =INDEX($J$20:$N$20,MATCH($Q12,$J$2:$N$2,0)) -> 0.092454615
B13: (+) Span and Layer Reduction (bps impact) | L13: {=_xlfn.IFS($E$31=0,0,$E$31=1,$D$31,$E$31=2,$D$32)} -> 0 | M13: {=_xlfn.IFS($E$31=0,0,$E$31=1,$D$31,$E$31=2,$D$32)} -> 0 | N13: {=_xlfn.IFS($E$31=0,0,$E$31=1,$D$31,$E$31=2,$D$32)} -> 0
B14: (+) Offshoring / Nearshoring / Outsourcing (bps impact) | L14: {=_xlfn.IFS($E$27=0,0,$E$27=1,$D$27,$E$27=2,$D$28)} -> 13.333333 | M14: {=_xlfn.IFS($E$27=0,0,$E$27=1,$D$27,$E$27=2,$D$28)} -> 13.333333 | N14: {=_xlfn.IFS($E$27=0,0,$E$27=1,$D$27,$E$27=2,$D$28)} -> 13.333333
B15: (+) Resale Margin Expansion | J15: 0 | K15: 0 | L15: 0 | M15: 0 | N15: 0
B16: (+) Time/Materials Margin Expansion | J16: 0 | K16: 0 | L16: 0 | M16: 0 | N16: 0
B17: (+) Consulting Margin Expansion | J17: 0 | K17: 0 | L17: 0 | M17: 0 | N17: 0
B18: (+) Cloud Margin Expansion | J18: 0 | K18: 0 | L18: 0 | M18: 0 | N18: 0
B19: Total bps impact | I19: =SUM(I7:I18) -> 0 | J19: =SUM(J7:J18) -> 92.5 | K19: =SUM(K7:K18) -> 92.5 | L19: =SUM(L7:L18) -> 38.333333 | M19: =SUM(M7:M18) -> 38.333333 | N19: =SUM(N7:N18) -> 38.333333
B20: EoP EBITDA Margin | D20: 0.018641567 | E20: 0.032411962 | F20: 0.039775653 | G20: 0.049284698 | H20: 0.062454615 | I20: =H20 -> 0.062454615 | J20: =J6+J19/10000 -> 0.071704615 | K20: =K6+K19/10000 -> 0.080954615 | L20: =L6+L19/10000 -> 0.084787949 | M20: =M6+M19/10000 -> 0.088621282 | N20: =N6+N19/10000 -> 0.092454615
B22: Pricing Increase (bps impact) cases | C22: Total Cost Savings | D22: Per Year Savings | E22: Case Manager
B23: Low Cost Savings | C23: 75 | D23: =C23/3 -> 25 | E23: =IF(CRT="Base",1,IF(CRT="None",0,IF(CRT="High",2))) -> 1 | G23: Case Manager
B24: High Cost Savings | C24: 110 | D24: =C24/3 -> 36.666667 | G24: No Cost Savings: 0
G25: Low Cost Savings: 1
B26: Offshoring / Nearshoring / Outsourcing (bps impact) cases | E26: Case Manager | G26: High Cost Savings: 2
B27: Low Cost Savings | C27: 40 | D27: =C27/3 -> 13.333333 | E27: =IF(CRT="Base",1,IF(CRT="None",0,IF(CRT="High",2))) -> 1
B28: High Cost Savings | C28: 255 | D28: =C28/3 -> 85
B30: Span and Layer Reduction (bps impact) cases | E30: Case Manager
B31: Low Cost Savings | C31: 5 | D31: =C31/3 -> 1.6666667 | E31: =IF(CRT="Base",0,IF(CRT="None",0,IF(CRT="High",2))) -> 0
B32: High Cost Savings | C32: 10 | D32: =C32/3 -> 3.3333333
B34: Near-term Offshoring (bps impact) cases | E34: Case Manager
B35: Low Cost Savings | C35: 50 | D35: =C35/2 -> 25 | E35: =IF(CRT="Base",2,IF(CRT="None",0,IF(CRT="High",2))) -> 2
B36: High Cost Savings | C36: 80 | D36: =C36/2 -> 40
B38: Near-term Managed Services Utilization Improvement (bps impact) cases | E38: Case Manager
B39: Low Cost Savings | C39: 15 | D39: =C39/2 -> 7.5 | E39: =IF(CRT="Base",2,IF(CRT="None",0,IF(CRT="High",2))) -> 2
B40: High Cost Savings | C40: 35 | D40: =C40/2 -> 17.5
B42: Near-term Sales Commission Change (bps impact) cases | E42: Case Manager
B43: Low Cost Savings | C43: 10 | D43: =C43/2 -> 5 | E43: =IF(CRT="Base",2,IF(CRT="None",0,IF(CRT="High",2))) -> 2
B44: High Cost Savings | C44: 30 | D44: =C44/2 -> 15
B46: Near-term In-Process SG&A Reduction (bps impact) cases | E46: Case Manager
B47: Low Cost Savings | C47: 10 | D47: =C47/2 -> 5 | E47: =IF(CRT="Base",2,IF(CRT="None",0,IF(CRT="High",2))) -> 2
B48: High Cost Savings | C48: 20 | D48: =C48/2 -> 10
B50: Near-term Back Office IT Spend Reduction (bps impact) cases | E50: Case Manager
B51: Low Cost Savings | C51: 10 | D51: =C51/2 -> 5 | E51: =IF(CRT="Base",2,IF(CRT="None",0,IF(CRT="High",2))) -> 2
B52: High Cost Savings | C52: 20 | D52: =C52/2 -> 10

Sheet Top Customer Data
A1: Strictly private & confidential
A2: There can be no assurance this investment will achieve its objectives or avoid losses.
B4: Top Customer Financials
B6: $m | D6: 2019A | E6: 2020A | F6: 2021A | G6: 2022A | H6: 2023E | I6: 2024E | K6: 2019A | L6: 2020A | M6: 2021A | N6: 2022A | O6: 2023E | P6: 2024E | R6: 2019A | S6: 2020A | T6: 2021A | U6: 2022A | V6: 2023E | W6: 2024E | Y6: 2019A | Z6: 2020A | AA6: 2021A | AB6: 2022A | AC6: 2023E | AD6: 2024E
A8: x | B8: Rank | C8: Infrastructure Revenue | D8: Revenue | K8: Gross Profit | R8: Gross Margin | Y8: Revenue Growth
B9: 1 | C9: Customer A | D9: 133.87019 | E9: 119.36184 | F9: 216.554 | G9: 184.38929 | H9: 161.06997 | I9: =IFERROR(H9*(1+AD9),0) -> 162.68067 | K9: 18.454073 | L9: 15.035522 | M9: 24.717 | N9: 22.248266 | O9: 16.782791 | P9: =IFERROR(I9*W9,0) -> 19.613077 | R9: =IFERROR(K9/D9,0) -> 0.1378505 | S9: =IFERROR(L9/E9,0) -> 0.1259659 | T9: =IFERROR(M9/F9,0) -> 0.11413781 | U9: =IFERROR(N9/G9,0) -> 0.12065921 | V9: =IFERROR(O9/H9,0) -> 0.10419566 | W9: =AVERAGE(R9:V9) -> 0.12056182 | Z9: =IFERROR(E9/D9-1,0) -> -0.10837626 | AA9: =IFERROR(F9/E9-1,0) -> 0.81426488 | AB9: =IFERROR(G9/F9-1,0) -> -0.14852975 | AC9: =IFERROR(H9/G9-1,0) -> -0.12646787 | AD9: 0.01
B10: =B9+1 -> 2 | C10: Customer B | D10: 0 | E10: 0 | F10: 0 | G10: 0 | H10: 0 | I10: =IFERROR(H10*(1+AD10),0) -> 0 | K10: 0 | L10: 0 | M10: 0 | N10: 0 | O10: 0 | P10: =IFERROR(I10*W10,0) -> 0 | R10: =IFERROR(K10/D10,0) -> 0 | S10: =IFERROR(L10/E10,0) -> 0 | T10: =IFERROR(M10/F10,0) -> 0 | U10: =IFERROR(N10/G10,0) -> 0 | V10: =IFERROR(O10/H10,0) -> 0 | W10: =IFERROR(P10/I10,0) -> 0 | Z10: =IFERROR(E10/D10-1,0) -> 0 | AA10: =IFERROR(F10/E10-1,0) -> 0 | AB10: =IFERROR(G10/F10-1,0) -> 0 | AC10: =IFERROR(H10/G10-1,0) -> 0 | AD10: 0.01
B11: =B10+1 -> 3 | C11: Customer C | D11: 0 | E11: 1.211 | F11: 0.737 | G11: 0.852 | H11: 1.0747681 | I11: =IFERROR(H11*(1+AD11),0) -> 1.1257698 | K11: 0 | L11: 0.268 | M11: 0.186 | N11: 0.283 | O11: 0.22094828 | P11: =IFERROR(I11*W11,0) -> 0.33019731 | R11: =IFERROR(K11/D11,0) -> 0 | S11: =IFERROR(L11/E11,0) -> 0.22130471 | T11: =IFERROR(M11/F11,0) -> 0.25237449 | U11: =IFERROR(N11/G11,0) -> 0.33215962 | V11: =IFERROR(O11/H11,0) -> 0.20557763 | W11: 0.29330801 | Z11: =IFERROR(E11/D11-1,0) -> 0 | AA11: =IFERROR(F11/E11-1,0) -> -0.39141206 | AB11: =IFERROR(G11/F11-1,0) -> 0.15603799 | AC11: =IFERROR(H11/G11-1,0) -> 0.26146492 | AD11: 0.047453709
B12: =B11+1 -> 4 | C12: Customer D | D12: 35.109 | E12: 29.821 | F12: 34.501 | G12: 34.163 | H12: 37.897286 | I12: =IFERROR(H12*(1+AD12),0) -> 40.171123 | K12: 4.91526 | L12: 3.955 | M12: 3.459 | N12: 3.395 | O12: 2.5137979 | P12: =IFERROR(I12*W12,0) -> 4.1777968 | R12: =IFERROR(K12/D12,0) -> 0.14 | S12: =IFERROR(L12/E12,0) -> 0.13262466 | T12: =IFERROR(M12/F12,0) -> 0.10025796 | U12: =IFERROR(N12/G12,0) -> 0.099376518 | V12: =IFERROR(O12/H12,0) -> 0.066331871 | W12: 0.104 | Z12: =IFERROR(E12/D12-1,0) -> -0.15061665 | AA12: =IFERROR(F12/E12-1,0) -> 0.15693639 | AB12: =IFERROR(G12/F12-1,0) -> -0.0097968175 | AC12: =IFERROR(H12/G12-1,0) -> 0.1093079 | AD12: 0.06
B13: =B12+1 -> 5 | C13: Customer E | D13: 6.209 | E13: 5.610572 | F13: 2.475 | G13: 5.859 | H13: 21.205057 | I13: =IFERROR(H13*(1+AD13),0) -> 19.296602 | K13: 0.707 | L13: 0.776753 | M13: 0.428 | N13: 1.386773 | O13: 2.788593 | P13: =IFERROR(I13*W13,0) -> 1.3507621 | R13: =IFERROR(K13/D13,0) -> 0.11386697 | S13: =IFERROR(L13/E13,0) -> 0.13844453 | T13: =IFERROR(M13/F13,0) -> 0.17292929 | U13: =IFERROR(N13/G13,0) -> 0.23669107 | V13: =IFERROR(O13/H13,0) -> 0.13150603 | W13: 0.07 | Z13: =IFERROR(E13/D13-1,0) -> -0.096380738 | AA13: =IFERROR(F13/E13-1,0) -> -0.55886851 | AB13: =IFERROR(G13/F13-1,0) -> 1.3672727 | AC13: =IFERROR(H13/G13-1,0) -> 2.6192281 | AD13: -0.09
B14: =B13+1 -> 6 | C14: Customer F | D14: 7.1745 | E14: 11.310568 | F14: 20.824025 | G14: 22.216846 | H14: 14.45348 | I14: =IFERROR(H14*(1+AD14),0) -> 14.887084 | K14: 1.00443 | L14: 1.6283201 | M14: 3.9251758 | N14: 5.9095803 | O14: 3.3876 | P14: =IFERROR(I14*W14,0) -> 3.5729003 | R14: =IFERROR(K14/D14,0) -> 0.14 | S14: =IFERROR(L14/E14,0) -> 0.14396448 | T14: =IFERROR(M14/F14,0) -> 0.18849266 | U14: =IFERROR(N14/G14,0) -> 0.26599546 | V14: =IFERROR(O14/H14,0) -> 0.23437954 | W14: 0.24 | Z14: =IFERROR(E14/D14-1,0) -> 0.57649568 | AA14: =IFERROR(F14/E14-1,0) -> 0.84111219 | AB14: =IFERROR(G14/F14-1,0) -> 0.066885293 | AC14: =IFERROR(H14/G14-1,0) -> -0.34943601 | AD14: 0.03
B15: =B14+1 -> 7 | C15: Customer G | D15: 16.3534 | E15: 5.359 | F15: 2.671 | G15: 4.548 | H15: 1.1347891 | I15: =IFERROR(H15*(1+AD15),0) -> 1.3730948 | K15: 2.0318 | L15: 0.475 | M15: 0.504 | N15: 0.77593 | O15: 0.46706554 | P15: =IFERROR(I15*W15,0) -> 0.37542846 | R15: =IFERROR(K15/D15,0) -> 0.12424328 | S15: =IFERROR(L15/E15,0) -> 0.08863594 | T15: =IFERROR(M15/F15,0) -> 0.18869337 | U15: =IFERROR(N15/G15,0) -> 0.17060906 | V15: =IFERROR(O15/H15,0) -> 0.41158796 | W15: 0.27341772 | Z15: =IFERROR(E15/D15-1,0) -> -0.67230056 | AA15: =IFERROR(F15/E15-1,0) -> -0.50158612 | AB15: =IFERROR(G15/F15-1,0) -> 0.70273306 | AC15: =IFERROR(H15/G15-1,0) -> -0.75048612 | AD15: 0.21
B16: =B15+1 -> 8 | C16: Customer H | D16: 1.2815 | E16: 0.843 | F16: 1.636 | G16: 1.524 | H16: 2.888449 | I16: =IFERROR(H16*(1+AD16),0) -> 3.0617559 | K16: 0.138 | L16: 0.09 | M16: 0.201 | N16: 0.133 | O16: 0.208296 | P16: =IFERROR(I16*W16,0) -> 0.28321242 | R16: =IFERROR(K16/D16,0) -> 0.10768631 | S16: =IFERROR(L16/E16,0) -> 0.10676157 | T16: =IFERROR(M16/F16,0) -> 0.12286064 | U16: =IFERROR(N16/G16,0) -> 0.087270341 | V16: =IFERROR(O16/H16,0) -> 0.072113442 | W16: 0.0925 | Z16: =IFERROR(E16/D16-1,0) -> -0.34217714 | AA16: =IFERROR(F16/E16-1,0) -> 0.94068802 | AB16: =IFERROR(G16/F16-1,0) -> -0.068459658 | AC16: =IFERROR(H16/G16-1,0) -> 0.89530774 | AD16: 0.06
B17: =B16+1 -> 9 | C17: Customer I | D17: 1.83786 | E17: 5.971 | F17: 8.911 | G17: 11.724 | H17: 10.591103 | I17: =IFERROR(H17*(1+AD17),0) -> 11.014747 | K17: 0.1654074 | L17: 0.708 | M17: 1.19 | N17: 1.435 | O17: 1.2218628 | P17: =IFERROR(I17*W17,0) -> 1.2362688 | R17: =IFERROR(K17/D17,0) -> 0.09 | S17: =IFERROR(L17/E17,0) -> 0.1185731 | T17: =IFERROR(M17/F17,0) -> 0.13354281 | U17: =IFERROR(N17/G17,0) -> 0.1223985 | V17: =IFERROR(O17/H17,0) -> 0.11536691 | W17: 0.11223761 | Z17: =IFERROR(E17/D17-1,0) -> 2.2488873 | AA17: =IFERROR(F17/E17-1,0) -> 0.49237984 | AB17: =IFERROR(G17/F17-1,0) -> 0.31567725 | AC17: =IFERROR(H17/G17-1,0) -> -0.096630618 | AD17: 0.04
B18: =B17+1 -> 10 | C18: Customer J | D18: 9.20245 | E18: 10.149942 | F18: 15.27686 | G18: 13.014011 | H18: 13.950893 | I18: =IFERROR(H18*(1+AD18),0) -> 12.695313 | K18: 2.618 | L18: 1.4717416 | M18: 2.2151447 | N18: 1.8870316 | O18: 2.7839651 | P18: =IFERROR(I18*W18,0) -> 1.8408203 | R18: =IFERROR(K18/D18,0) -> 0.28448946 | S18: =IFERROR(L18/E18,0) -> 0.145 | T18: =IFERROR(M18/F18,0) -> 0.145 | U18: =IFERROR(N18/G18,0) -> 0.145 | V18: =IFERROR(O18/H18,0) -> 0.19955461 | W18: 0.145 | Z18: =IFERROR(E18/D18-1,0) -> 0.10296081 | AA18: =IFERROR(F18/E18-1,0) -> 0.50511798 | AB18: =IFERROR(G18/F18-1,0) -> -0.14812262 | AC18: =IFERROR(H18/G18-1,0) -> 0.071990235 | AD18: -0.09
B19: =B18+1 -> 11 | C19: Customer K | D19: 1.593 | E19: 0.661 | F19: 0.266 | G19: 0.502 | H19: 2.069129 | I19: =IFERROR(H19*(1+AD19),0) -> 7.9868379 | K19: 0.307562 | L19: 0.155 | M19: 0.056 | N19: 0.109 | O19: 0.1755247 | P19: =IFERROR(I19*W19,0) -> 1.2778941 | R19: =IFERROR(K19/D19,0) -> 0.19307094 | S19: =IFERROR(L19/E19,0) -> 0.23449319 | T19: =IFERROR(M19/F19,0) -> 0.21052632 | U19: =IFERROR(N19/G19,0) -> 0.21713147 | V19: =IFERROR(O19/H19,0) -> 0.084830235 | W19: 0.16 | Z19: =IFERROR(E19/D19-1,0) -> -0.58505964 | AA19: =IFERROR(F19/E19-1,0) -> -0.59757943 | AB19: =IFERROR(G19/F19-1,0) -> 0.88721805 | AC19: =IFERROR(H19/G19-1,0) -> 3.1217709 | AD19: 2.86
B20: =B19+1 -> 12 | C20: Customer L | D20: 7.267305 | E20: 2.052507 | F20: 2.779591 | G20: 3.606554 | H20: 5.20156 | I20: =IFERROR(H20*(1+AD20),0) -> 5.5136536 | K20: 1.0667982 | L20: -0.22941456 | M20: 0.67538628 | N20: 0.83532836 | O20: 0.68344 | P20: =IFERROR(I20*W20,0) -> 0.99245765 | R20: =IFERROR(K20/D20,0) -> 0.14679419 | S20: =IFERROR(L20/E20,0) -> -0.11177285 | T20: =IFERROR(M20/F20,0) -> 0.24298045 | U20: =IFERROR(N20/G20,0) -> 0.23161399 | V20: =IFERROR(O20/H20,0) -> 0.13139135 | W20: 0.18 | Z20: =IFERROR(E20/D20-1,0) -> -0.71756972 | AA20: =IFERROR(F20/E20-1,0) -> 0.35424191 | AB20: =IFERROR(G20/F20-1,0) -> 0.29751248 | AC20: =IFERROR(H20/G20-1,0) -> 0.44225208 | AD20: 0.06
B21: =B20+1 -> 13 | C21: Customer M | D21: 0.2706165 | E21: 0.55575 | F21: 1.438634 | G21: 6.652186 | H21: 2.715 | I21: =IFERROR(H21*(1+AD21),0) -> 3.01365 | K21: 0.040592475 | L21: 0.0833625 | M21: 0.248625 | N21: 1.2463875 | O21: 0.5973 | P21: =IFERROR(I21*W21,0) -> 0.663003 | R21: =IFERROR(K21/D21,0) -> 0.15 | S21: =IFERROR(L21/E21,0) -> 0.15 | T21: =IFERROR(M21/F21,0) -> 0.17282019 | U21: =IFERROR(N21/G21,0) -> 0.1873651 | V21: =IFERROR(O21/H21,0) -> 0.22 | W21: 0.22 | Z21: =IFERROR(E21/D21-1,0) -> 1.0536442 | AA21: =IFERROR(F21/E21-1,0) -> 1.5886352 | AB21: =IFERROR(G21/F21-1,0) -> 3.62396 | AC21: =IFERROR(H21/G21-1,0) -> -0.59186349 | AD21: 0.11
B22: =B21+1 -> 14 | C22: Customer N | D22: 7.4288768 | E22: 10.03305 | F22: 6.4796125 | G22: 6.195825 | H22: 16.46474 | I22: =IFERROR(H22*(1+AD22),0) -> 17.452624 | K22: 1.154883 | L22: 1.169358 | M22: 0.88124215 | N22: 0.90957975 | O22: 3.292948 | P22: =IFERROR(I22*W22,0) -> 3.4905249 | R22: =IFERROR(K22/D22,0) -> 0.15545862 | S22: =IFERROR(L22/E22,0) -> 0.1165506 | T22: =IFERROR(M22/F22,0) -> 0.13600229 | U22: =IFERROR(N22/G22,0) -> 0.14680527 | V22: =IFERROR(O22/H22,0) -> 0.2 | W22: 0.2 | Z22: =IFERROR(E22/D22-1,0) -> 0.35054738 | AA22: =IFERROR(F22/E22-1,0) -> -0.35417321 | AB22: =IFERROR(G22/F22-1,0) -> -0.043796986 | AC22: =IFERROR(H22/G22-1,0) -> 1.6573927 | AD22: 0.06
B23: =B22+1 -> 15 | C23: Customer O | D23: 0 | E23: 0 | F23: 0.035 | G23: 0.202 | H23: 0.620261 | I23: =IFERROR(H23*(1+AD23),0) -> 0.620261 | K23: 0 | L23: 0 | M23: 0.496 | N23: 0.028 | O23: 0.10905051 | P23: =IFERROR(I23*W23,0) -> 0.09924176 | R23: =IFERROR(K23/D23,0) -> 0 | S23: =IFERROR(L23/E23,0) -> 0 | T23: =IFERROR(M23/F23,0) -> 14.171429 | U23: =IFERROR(N23/G23,0) -> 0.13861386 | V23: =IFERROR(O23/H23,0) -> 0.17581391 | W23: 0.16 | Z23: =IFERROR(E23/D23-1,0) -> 0 | AA23: =IFERROR(F23/E23-1,0) -> 0 | AB23: =IFERROR(G23/F23-1,0) -> 4.7714286 | AC23: =IFERROR(H23/G23-1,0) -> 2.070599
C24: Top 15 Total | D24: =SUM(D9:D23) -> 227.5977 | E24: =SUM(E9:E23) -> 202.94023 | F24: =SUM(F9:F23) -> 314.58472 | G24: =SUM(G9:G23) -> 295.44871 | H24: =SUM(H9:H23) -> 291.33648 | I24: =SUM(I9:I23) -> 300.89318 | K24: =SUM(K9:K23) -> 32.603806 | L24: =SUM(L9:L23) -> 25.586643 | M24: =SUM(M9:M23) -> 39.182574 | N24: =SUM(N9:N23) -> 40.581877 | O24: =SUM(O9:O23) -> 35.233183 | P24: =SUM(P9:P23) -> 39.303585 | R24: =IFERROR(K24/D24,0) -> 0.14325191 | S24: =IFERROR(L24/E24,0) -> 0.1260797 | T24: =IFERROR(M24/F24,0) -> 0.12455333 | U24: =IFERROR(N24/G24,0) -> 0.13735676 | V24: =IFERROR(O24/H24,0) -> 0.12093639 | W24: =IFERROR(P24/I24,0) -> 0.13062305 | Z24: =IFERROR(E24/D24-1,"--") -> -0.10833796 | AA24: =IFERROR(F24/E24-1,"--") -> 0.55013483 | AB24: =IFERROR(G24/F24-1,"--") -> -0.060829435 | AC24: =IFERROR(H24/G24-1,"--") -> -0.013918584 | AD24: =IFERROR(I24/H24-1,"--") -> 0.032802967
C25: Growth | E25: =E24/D24-1 -> -0.10833796 | F25: =F24/E24-1 -> 0.55013483 | G25: =G24/F24-1 -> -0.060829435 | H25: =H24/G24-1 -> -0.013918584 | I25: =I24/H24-1 -> 0.032802967 | L25: =L24/K24-1 -> -0.21522528 | M25: =M24/L24-1 -> 0.53136832 | N25: =N24/M24-1 -> 0.035712371 | O25: =O24/N24-1 -> -0.13180006 | P25: =P24/O24-1 -> 0.11552751
C27: Rest of Customers | D27: =D30-D24 -> 329.60544 | E27: =E30-E24 -> 316.18914 | F27: =F30-F24 -> 305.09224 | G27: =G30-G24 -> 356.48743 | H27: =H30-H24 -> 363.82246 | I27: =I30-I24 -> 369.76753 | K27: =K30-K24 -> 67.073543 | L27: =L30-L24 -> 67.817384 | M27: =M30-M24 -> 69.552282 | N27: =N30-N24 -> 76.44516 | O27: =O30-O24 -> 77.93162 | P27: =P30-P24 -> 77.462324 | R27: =IFERROR(K27/D27,"--") -> 0.20349647 | S27: =IFERROR(L27/E27,"--") -> 0.2144836 | T27: =IFERROR(M27/F27,"--") -> 0.22797133 | U27: =IFERROR(N27/G27,"--") -> 0.21443999 | V27: =IFERROR(O27/H27,"--") -> 0.21420233 | W27: =IFERROR(P27/I27,"--") -> 0.20948926 | Z27: =IFERROR(E27/D27-1,"--") -> -0.040704144 | AA27: =IFERROR(F27/E27-1,"--") -> -0.035095762 | AB27: =IFERROR(G27/F27-1,"--") -> 0.16845787 | AC27: =IFERROR(H27/G27-1,"--") -> 0.020575863 | AD27: =IFERROR(I27/H27-1,"--") -> 0.016340566
C28: Growth | E28: =E27/D27-1 -> -0.040704144 | F28: =F27/E27-1 -> -0.035095762 | G28: =G27/F27-1 -> 0.16845787 | H28: =H27/G27-1 -> 0.020575863 | I28: =I27/H27-1 -> 0.016340566 | L28: =L27/K27-1 -> 0.011089931 | M28: =M27/L27-1 -> 0.025581903 | N28: =N27/M27-1 -> 0.099103559 | O28: =O27/N27-1 -> 0.019444788 | P28: =P27/O27-1 -> -0.0060219017
C30: Total infrastructure | D30: 557.20315 | E30: 519.12937 | F30: 619.67696 | G30: 651.93614 | H30: 655.15895 | I30: 670.66071 | K30: 99.677349 | L30: 93.404027 | M30: 108.73486 | N30: 117.02704 | O30: 113.1648 | P30: 116.76591 | R30: =IFERROR(K30/D30,"--") -> 0.1788887 | S30: =IFERROR(L30/E30,"--") -> 0.17992437 | T30: =IFERROR(M30/F30,"--") -> 0.17547023 | U30: =IFERROR(N30/G30,"--") -> 0.1795069 | V30: =IFERROR(O30/H30,"--") -> 0.17272878 | W30: =IFERROR(P30/I30,"--") -> 0.17410578 | Z30: =IFERROR(E30/D30-1,"--") -> -0.068330156 | AA30: =IFERROR(F30/E30-1,"--") -> 0.19368504 | AB30: =IFERROR(G30/F30-1,"--") -> 0.052058055 | AC30: =IFERROR(H30/G30-1,"--") -> 0.0049434423 | AD30: =IFERROR(I30/H30-1,"--") -> 0.023661077
C31: Growth | E31: =E30/D30-1 -> -0.068330156 | F31: =F30/E30-1 -> 0.19368504 | G31: =G30/F30-1 -> 0.052058055 | H31: =H30/G30-1 -> 0.0049434423 | I31: =I30/H30-1 -> 0.023661077 | L31: =L30/K30-1 -> -0.062936289 | M31: =M30/L30-1 -> 0.16413456 | N31: =N30/M30-1 -> 0.076260562 | O31: =O30/N30-1 -> -0.033002918 | P31: =P30/O30-1 -> 0.031821777
A33: x | B33: Rank | C33: Cloud Revenue | D33: Revenue | K33: Gross Profit | R33: Gross Margin | Y33: Revenue Growth
B34: 1 | C34: Customer A | D34: 0 | E34: 0 | F34: 0 | G34: 0 | H34: 0 | I34: =IFERROR(H34*(1+AD34),0) -> 0 | K34: 0 | L34: 0 | M34: 0 | N34: 0 | O34: 0 | P34: =IFERROR(I34*W34,0) -> 0 | R34: =IFERROR(K34/D34,"--") -> -- | S34: =IFERROR(L34/E34,"--") -> -- | T34: =IFERROR(M34/F34,"--") -> -- | U34: =IFERROR(N34/G34,"--") -> -- | V34: =IFERROR(O34/H34,"--") -> -- | Z34: =IFERROR(E34/D34-1,"--") -> -- | AA34: =IFERROR(F34/E34-1,"--") -> -- | AB34: =IFERROR(G34/F34-1,"--") -> -- | AC34: =IFERROR(H34/G34-1,"--") -> -- | AD34: 0.01 | AM34: =IFERROR(AL34/AK34-1,"")
B35: =B34+1 -> 2 | C35: Customer B | D35: 0 | E35: 0 | F35: 0 | G35: 0 | H35: 0 | I35: =IFERROR(H35*(1+AD35),0) -> 0 | K35: 0 | L35: 0 | M35: 0 | N35: 0 | O35: 0 | P35: =IFERROR(I35*W35,0) -> 0 | R35: =IFERROR(K35/D35,"--") -> -- | S35: =IFERROR(L35/E35,"--") -> -- | T35: =IFERROR(M35/F35,"--") -> -- | U35: =IFERROR(N35/G35,"--") -> -- | V35: =IFERROR(O35/H35,"--") -> -- | Z35: =IFERROR(E35/D35-1,"--") -> -- | AA35: =IFERROR(F35/E35-1,"--") -> -- | AB35: =IFERROR(G35/F35-1,"--") -> -- | AC35: =IFERROR(H35/G35-1,"--") -> -- | AD35: 0.01 | AM35: =IFERROR(AL35/AK35-1,"")
B36: =B35+1 -> 3 | C36: Customer C | D36: 0 | E36: 0 | F36: 0 | G36: 0 | H36: 0 | I36: =IFERROR(H36*(1+AD36),0) -> 0 | K36: 0 | L36: 0 | M36: 0 | N36: 0 | O36: 0 | P36: =IFERROR(I36*W36,0) -> 0 | R36: =IFERROR(K36/D36,"--") -> -- | S36: =IFERROR(L36/E36,"--") -> -- | T36: =IFERROR(M36/F36,"--") -> -- | U36: =IFERROR(N36/G36,"--") -> -- | V36: =IFERROR(O36/H36,"--") -> -- | Z36: =IFERROR(E36/D36-1,"--") -> -- | AA36: =IFERROR(F36/E36-1,"--") -> -- | AB36: =IFERROR(G36/F36-1,"--") -> -- | AC36: =IFERROR(H36/G36-1,"--") -> -- | AD36: 0.01 | AM36: =IFERROR(AL36/AK36-1,"")
B37: =B36+1 -> 4 | C37: Customer D | D37: 0.575 | E37: 0.566 | F37: 0.167 | G37: 0.021 | H37: 0.091266 | I37: =IFERROR(H37*(1+AD37),0) -> 0.09217866 | K37: 0.253 | L37: 0.255 | M37: 0.075 | N37: 0.01 | O37: 0.0273798 | P37: =IFERROR(I37*W37,0) -> 0.044245757 | R37: =IFERROR(K37/D37,"--") -> 0.44 | S37: =IFERROR(L37/E37,"--") -> 0.45053004 | T37: =IFERROR(M37/F37,"--") -> 0.4491018 | U37: =IFERROR(N37/G37,"--") -> 0.47619048 | V37: =IFERROR(O37/H37,"--") -> 0.3 | W37: 0.48 | Z37: =IFERROR(E37/D37-1,"--") -> -0.015652174 | AA37: =IFERROR(F37/E37-1,"--") -> -0.704947 | AB37: =IFERROR(G37/F37-1,"--") -> -0.8742515 | AC37: =IFERROR(H37/G37-1,"--") -> 3.346 | AD37: 0.01
B38: =B37+1 -> 5 | C38: Customer E | D38: 12.8567 | E38: 5.684 | F38: 5.391 | G38: 6.813 | H38: 9.146 | I38: =IFERROR(H38*(1+AD38),0) -> 10.15206 | K38: 5.8278 | L38: 3.305 | M38: 3.261 | N38: 4.131 | O38: 5.62 | P38: =IFERROR(I38*W38,0) -> 5.8223308 | R38: =IFERROR(K38/D38,"--") -> 0.45328895 | S38: =IFERROR(L38/E38,"--") -> 0.58145672 | T38: =IFERROR(M38/F38,"--") -> 0.60489705 | U38: =IFERROR(N38/G38,"--") -> 0.60634082 | V38: =IFERROR(O38/H38,"--") -> 0.61447627 | W38: 0.57351225 | Z38: =IFERROR(E38/D38-1,"--") -> -0.55789588 | AA38: =IFERROR(F38/E38-1,"--") -> -0.051548205 | AB38: =IFERROR(G38/F38-1,"--") -> 0.26377295 | AC38: =IFERROR(H38/G38-1,"--") -> 0.34243358 | AD38: 0.11
B39: =B38+1 -> 6 | C39: Customer F | D39: 0 | E39: 0 | F39: 0 | G39: 0 | H39: 0 | I39: =IFERROR(H39*(1+AD39),0) -> 0 | K39: 0 | L39: 0 | M39: 0 | N39: 0 | O39: 0 | P39: =IFERROR(I39*W39,0) -> 0 | R39: =IFERROR(K39/D39,"--") -> -- | S39: =IFERROR(L39/E39,"--") -> -- | T39: =IFERROR(M39/F39,"--") -> -- | U39: =IFERROR(N39/G39,"--") -> -- | V39: =IFERROR(O39/H39,"--") -> -- | W39: -- | Z39: =IFERROR(E39/D39-1,"--") -> -- | AA39: =IFERROR(F39/E39-1,"--") -> -- | AB39: =IFERROR(G39/F39-1,"--") -> -- | AC39: =IFERROR(H39/G39-1,"--") -> -- | AD39: 0.01
B40: =B39+1 -> 7 | C40: Customer G | D40: 10.8393 | E40: 10.647 | F40: 10.125 | G40: 10.425 | H40: 10.2854 | I40: =IFERROR(H40*(1+AD40),0) -> 10.593962 | K40: 2.3178 | L40: 2.479 | M40: 2.593 | N40: 2.341 | O40: 2.316 | P40: =IFERROR(I40*W40,0) -> 2.4969271 | R40: =IFERROR(K40/D40,"--") -> 0.213833 | S40: =IFERROR(L40/E40,"--") -> 0.23283554 | T40: =IFERROR(M40/F40,"--") -> 0.25609877 | U40: =IFERROR(N40/G40,"--") -> 0.22455635 | V40: =IFERROR(O40/H40,"--") -> 0.22517355 | W40: 0.23569342 | Z40: =IFERROR(E40/D40-1,"--") -> -0.017740998 | AA40: =IFERROR(F40/E40-1,"--") -> -0.049027895 | AB40: =IFERROR(G40/F40-1,"--") -> 0.02962963 | AC40: =IFERROR(H40/G40-1,"--") -> -0.013390887 | AD40: 0.03
B41: =B40+1 -> 8 | C41: Customer H | D41: 0 | E41: 0 | F41: 0 | G41: 0 | H41: 0 | I41: =IFERROR(H41*(1+AD41),0) -> 0 | K41: 0 | L41: 0 | M41: 0 | N41: 0 | O41: 0 | P41: =IFERROR(I41*W41,0) -> 0 | R41: =IFERROR(K41/D41,"--") -> -- | S41: =IFERROR(L41/E41,"--") -> -- | T41: =IFERROR(M41/F41,"--") -> -- | U41: =IFERROR(N41/G41,"--") -> -- | V41: =IFERROR(O41/H41,"--") -> -- | W41: -- | Z41: =IFERROR(E41/D41-1,"--") -> -- | AA41: =IFERROR(F41/E41-1,"--") -> -- | AB41: =IFERROR(G41/F41-1,"--") -> -- | AC41: =IFERROR(H41/G41-1,"--") -> -- | AD41: 0.01
B42: =B41+1 -> 9 | C42: Customer I | D42: 0 | E42: 0 | F42: 0 | G42: 0 | H42: 0 | I42: =IFERROR(H42*(1+AD42),0) -> 0 | K42: 0 | L42: 0 | M42: 0 | N42: 0 | O42: 0 | P42: =IFERROR(I42*W42,0) -> 0 | R42: =IFERROR(K42/D42,"--") -> -- | S42: =IFERROR(L42/E42,"--") -> -- | T42: =IFERROR(M42/F42,"--") -> -- | U42: =IFERROR(N42/G42,"--") -> -- | V42: =IFERROR(O42/H42,"--") -> -- | W42: -- | Z42: =IFERROR(E42/D42-1,"--") -> -- | AA42: =IFERROR(F42/E42-1,"--") -> -- | AB42: =IFERROR(G42/F42-1,"--") -> -- | AC42: =IFERROR(H42/G42-1,"--") -> -- | AD42: 0.01
B43: =B42+1 -> 10 | C43: Customer J | D43: 0.0144 | E43: 0.10215 | F43: 0.0939 | G43: 0.0144 | H43: 0.0144 | I43: =IFERROR(H43*(1+AD43),0) -> 0.014544 | K43: 0.006048 | L43: 0.042903 | M43: 0.039438 | N43: 0.00432 | O43: 0.00432 | P43: =IFERROR(I43*W43,0) -> 0.0043632 | R43: =IFERROR(K43/D43,"--") -> 0.42 | S43: =IFERROR(L43/E43,"--") -> 0.42 | T43: =IFERROR(M43/F43,"--") -> 0.42 | U43: =IFERROR(N43/G43,"--") -> 0.3 | V43: =IFERROR(O43/H43,"--") -> 0.3 | W43: 0.3 | Z43: =IFERROR(E43/D43-1,"--") -> 6.09375 | AA43: =IFERROR(F43/E43-1,"--") -> -0.080763583 | AB43: =IFERROR(G43/F43-1,"--") -> -0.84664537 | AC43: =IFERROR(H43/G43-1,"--") -> 0 | AD43: 0.01
B44: =B43+1 -> 11 | C44: Customer K | D44: 0 | E44: 0.876954 | F44: 3.954 | G44: 5.143 | H44: 9.031 | I44: =IFERROR(H44*(1+AD44),0) -> 10.47596 | K44: 0 | L44: 0.297 | M44: 1.347 | N44: 1.677 | O44: 2.7093 | P44: =IFERROR(I44*W44,0) -> 3.4570668 | R44: =IFERROR(K44/D44,"--") -> -- | S44: =IFERROR(L44/E44,"--") -> 0.33867227 | T44: =IFERROR(M44/F44,"--") -> 0.34066768 | U44: =IFERROR(N44/G44,"--") -> 0.32607428 | V44: =IFERROR(O44/H44,"--") -> 0.3 | W44: 0.33 | Z44: =IFERROR(E44/D44-1,"--") -> -- | AA44: =IFERROR(F44/E44-1,"--") -> 3.5087884 | AB44: =IFERROR(G44/F44-1,"--") -> 0.30070814 | AC44: =IFERROR(H44/G44-1,"--") -> 0.755979 | AD44: 0.16
B45: =B44+1 -> 12 | C45: Customer L | D45: 0.04687275 | E45: 1.852743 | F45: 5.311784 | G45: 6.165946 | H45: 6.08 | I45: =IFERROR(H45*(1+AD45),0) -> 6.1408 | K45: 0.0187491 | L45: 0.77815206 | M45: 1.7528887 | N45: 2.0964216 | O45: 2.303535 | P45: =IFERROR(I45*W45,0) -> 2.087872 | R45: =IFERROR(K45/D45,"--") -> 0.4 | S45: =IFERROR(L45/E45,"--") -> 0.42 | T45: =IFERROR(M45/F45,"--") -> 0.33 | U45: =IFERROR(N45/G45,"--") -> 0.34 | V45: =IFERROR(O45/H45,"--") -> 0.37887089 | W45: 0.34 | Z45: =IFERROR(E45/D45-1,"--") -> 38.527081 | AA45: =IFERROR(F45/E45-1,"--") -> 1.8669837 | AB45: =IFERROR(G45/F45-1,"--") -> 0.16080511 | AC45: =IFERROR(H45/G45-1,"--") -> -0.013938818 | AD45: 0.01
B46: =B45+1 -> 13 | C46: Customer M | D46: 0 | E46: 0 | F46: 0.218866 | G46: 1.657064 | H46: 3.2 | I46: =IFERROR(H46*(1+AD46),0) -> 4.832 | K46: 0 | L46: 0 | M46: 0 | N46: 0 | O46: 0.096 | P46: =IFERROR(I46*W46,0) -> 0.14496 | R46: =IFERROR(K46/D46,"--") -> -- | S46: =IFERROR(L46/E46,"--") -> -- | T46: =IFERROR(M46/F46,"--") -> 0 | U46: =IFERROR(N46/G46,"--") -> 0 | V46: =IFERROR(O46/H46,"--") -> 0.03 | W46: 0.03 | Z46: =IFERROR(E46/D46-1,"--") -> -- | AA46: =IFERROR(F46/E46-1,"--") -> -- | AB46: =IFERROR(G46/F46-1,"--") -> 6.5711348 | AC46: =IFERROR(H46/G46-1,"--") -> 0.93112638 | AD46: 0.51
B47: =B46+1 -> 14 | C47: Customer N | D47: 0 | E47: 0 | F47: 0.13283 | G47: 0 | H47: 0.098 | I47: =IFERROR(H47*(1+AD47),0) -> 0.16758 | K47: 0 | L47: 0 | M47: 0.0332075 | N47: 0 | O47: 0.01862 | P47: =IFERROR(I47*W47,0) -> 0.0318402 | R47: =IFERROR(K47/D47,"--") -> -- | S47: =IFERROR(L47/E47,"--") -> -- | T47: =IFERROR(M47/F47,"--") -> 0.25 | U47: =IFERROR(N47/G47,"--") -> -- | V47: =IFERROR(O47/H47,"--") -> 0.19 | W47: 0.19 | Z47: =IFERROR(E47/D47-1,"--") -> -- | AA47: =IFERROR(F47/E47-1,"--") -> -- | AB47: =IFERROR(G47/F47-1,"--") -> -1 | AC47: =IFERROR(H47/G47-1,"--") -> -- | AD47: 0.71
B48: =B47+1 -> 15 | C48: Customer O | D48: 0 | E48: 0 | F48: 0 | G48: 0 | H48: 0.188 | I48: =IFERROR(H48*(1+AD48),0) -> 0.42488 | K48: 0 | L48: 0 | M48: 0 | N48: 0 | O48: 0.0658 | P48: =IFERROR(I48*W48,0) -> 0.148708 | R48: =IFERROR(K48/D48,"--") -> -- | S48: =IFERROR(L48/E48,"--") -> -- | T48: =IFERROR(M48/F48,"--") -> -- | U48: =IFERROR(N48/G48,"--") -> -- | V48: =IFERROR(O48/H48,"--") -> 0.35 | W48: 0.35 | Z48: =IFERROR(E48/D48-1,"--") -> -- | AA48: =IFERROR(F48/E48-1,"--") -> -- | AB48: =IFERROR(G48/F48-1,"--") -> -- | AC48: =IFERROR(H48/G48-1,"--") -> -- | AD48: 1.26
C49: Top 15 Total | D49: =SUM(D34:D48) -> 24.332273 | E49: =SUM(E34:E48) -> 19.728847 | F49: =SUM(F34:F48) -> 25.39438 | G49: =SUM(G34:G48) -> 30.23941 | H49: =SUM(H34:H48) -> 38.134066 | I49: =SUM(I34:I48) -> 42.893965 | K49: =SUM(K34:K48) -> 8.4233971 | L49: =SUM(L34:L48) -> 7.1570551 | M49: =SUM(M34:M48) -> 9.1015342 | N49: =SUM(N34:N48) -> 10.259742 | O49: =SUM(O34:O48) -> 13.160955 | P49: =SUM(P34:P48) -> 14.238314 | R49: =IFERROR(K49/D49,"--") -> 0.34618209 | S49: =IFERROR(L49/E49,"--") -> 0.36277108 | T49: =IFERROR(M49/F49,"--") -> 0.35840742 | U49: =IFERROR(N49/G49,"--") -> 0.33928379 | V49: =IFERROR(O49/H49,"--") -> 0.3451233 | W49: =IFERROR(P49/I49,"--") -> 0.33194213 | Z49: =IFERROR(E49/D49-1,"--") -> -0.18919013 | AA49: =IFERROR(F49/E49-1,"--") -> 0.28717 | AB49: =IFERROR(G49/F49-1,"--") -> 0.19079143 | AC49: =IFERROR(H49/G49-1,"--") -> 0.26107176 | AD49: =IFERROR(I49/H49-1,"--") -> 0.12482012
C50: Growth | E50: =E49/D49-1 -> -0.18919013 | F50: =F49/E49-1 -> 0.28717 | G50: =G49/F49-1 -> 0.19079143 | H50: =H49/G49-1 -> 0.26107176 | I50: =I49/H49-1 -> 0.12482012 | L50: =L49/K49-1 -> -0.15033626 | M50: =M49/L49-1 -> 0.27168705 | N50: =N49/M49-1 -> 0.12725409 | O50: =O49/N49-1 -> 0.28277643 | P50: =P49/O49-1 -> 0.081860251 | AD50: 0.11482012
C52: Rest of Customers | D52: =D55-D49 -> 57.537436 | E52: =E55-E49 -> 55.89576 | F52: =F55-F49 -> 60.153237 | G52: =G55-G49 -> 59.750486 | H52: =H55-H49 -> 64.415468 | I52: =I55-I49 -> 71.193221 | K52: =K55-K49 -> 12.335527 | L52: =L55-L49 -> 14.08079 | M52: =M55-M49 -> 18.378888 | N52: =N55-N49 -> 15.986818 | O52: =O55-O49 -> 15.206236 | P52: =P55-P49 -> 18.195533 | R52: =IFERROR(K52/D52,"--") -> 0.21439132 | S52: =IFERROR(L52/E52,"--") -> 0.2519116 | T52: =IFERROR(M52/F52,"--") -> 0.30553448 | U52: =IFERROR(N52/G52,"--") -> 0.26755963 | V52: =IFERROR(O52/H52,"--") -> 0.23606498 | W52: =IFERROR(P52/I52,"--") -> 0.25557957 | Z52: =IFERROR(E52/D52-1,"--") -> -0.028532318 | AA52: =IFERROR(F52/E52-1,"--") -> 0.076168158 | AB52: =IFERROR(G52/F52-1,"--") -> -0.0066954038 | AC52: =IFERROR(H52/G52-1,"--") -> 0.078074366 | AD52: =IFERROR(I52/H52-1,"--") -> 0.10521934
C53: Growth | E53: =E52/D52-1 -> -0.028532318 | F53: =F52/E52-1 -> 0.076168158 | G53: =G52/F52-1 -> -0.0066954038 | H53: =H52/G52-1 -> 0.078074366 | I53: =I52/H52-1 -> 0.10521934 | L53: =L52/K52-1 -> 0.1414827 | M53: =M52/L52-1 -> 0.30524549 | N53: =N52/M52-1 -> -0.13015313 | O53: =O52/N52-1 -> -0.048826595 | P53: =P52/O52-1 -> 0.19658361
C55: Total Cloud | D55: 81.869709 | E55: 75.624607 | F55: 85.547617 | G55: 89.989896 | H55: 102.54953 | I55: 114.08719 | K55: 20.758924 | L55: 21.237845 | M55: 27.480422 | N55: 26.24656 | O55: 28.367191 | P55: 32.433847 | R55: =IFERROR(K55/D55,"--") -> 0.25356049 | S55: =IFERROR(L55/E55,"--") -> 0.28083247 | T55: =IFERROR(M55/F55,"--") -> 0.32122955 | U55: =IFERROR(N55/G55,"--") -> 0.29166118 | V55: =IFERROR(O55/H55,"--") -> 0.27661941 | W55: =IFERROR(P55/I55,"--") -> 0.28429001 | Z55: =IFERROR(E55/D55-1,"--") -> -0.076280987 | AA55: =IFERROR(F55/E55-1,"--") -> 0.13121404 | AB55: =IFERROR(G55/F55-1,"--") -> 0.051927569 | AC55: =IFERROR(H55/G55-1,"--") -> 0.13956719 | AD55: =IFERROR(I55/H55-1,"--") -> 0.11250809
C56: Growth | E56: =E55/D55-1 -> -0.076280987 | F56: =F55/E55-1 -> 0.13121404 | G56: =G55/F55-1 -> 0.051927569 | H56: =H55/G55-1 -> 0.13956719 | I56: =I55/H55-1 -> 0.11250809 | L56: =L55/K55-1 -> 0.023070635 | M56: =M55/L55-1 -> 0.29393645 | N56: =N55/M55-1 -> -0.044899691 | O56: =O55/N55-1 -> 0.080796542 | P56: =P55/O55-1 -> 0.14335772
A58: x | B58: Rank | C58: Consulting Revenue | D58: Revenue | K58: Gross Profit | R58: Gross Margin | Y58: Revenue Growth
B59: 1 | C59: Customer A | D59: 2.198386 | E59: 4.482 | F59: 5.446 | G59: 7.123367 | H59: 7.825 | I59: =IFERROR(H59*(1+AD59),0) -> 9.46825 | K59: 0.64115 | L59: 1.418 | M59: 1.356 | N59: 1.5363 | O59: 2.027 | P59: =IFERROR(I59*(W59),0) -> 2.1862537 | R59: =IFERROR(K59/D59,"--") -> 0.29164578 | S59: =IFERROR(L59/E59,"--") -> 0.31637662 | T59: =IFERROR(M59/F59,"--") -> 0.24899008 | U59: =IFERROR(N59/G59,"--") -> 0.21567048 | V59: =IFERROR(O59/H59,"--") -> 0.25904153 | W59: 0.23090367 | Z59: =IFERROR(E59/D59-1,"--") -> 1.0387684 | AA59: =IFERROR(F59/E59-1,"--") -> 0.21508255 | AB59: =IFERROR(G59/F59-1,"--") -> 0.30799982 | AC59: =IFERROR(H59/G59-1,"--") -> 0.098497382 | AD59: 0.21
B60: =B59+1 -> 2 | C60: Customer B | D60: 9.811 | E60: 39.447 | F60: 110.076 | G60: 121.399 | H60: 115.474 | I60: =IFERROR(H60*(1+AD60),0) -> 113.74189 | K60: 1.604 | L60: 3.731 | M60: 7.614 | N60: 10.184 | O60: 10.455 | P60: =IFERROR(I60*(W60),0) -> 10.78212 | R60: =IFERROR(K60/D60,"--") -> 0.16348996 | S60: =IFERROR(L60/E60,"--") -> 0.094582605 | T60: =IFERROR(M60/F60,"--") -> 0.069170391 | U60: =IFERROR(N60/G60,"--") -> 0.083888665 | V60: =IFERROR(O60/H60,"--") -> 0.090539862 | W60: 0.094794622 | Z60: =IFERROR(E60/D60-1,"--") -> 3.0206911 | AA60: =IFERROR(F60/E60-1,"--") -> 1.7904784 | AB60: =IFERROR(G60/F60-1,"--") -> 0.10286529 | AC60: =IFERROR(H60/G60-1,"--") -> -0.048806003 | AD60: -0.015
B61: =B60+1 -> 3 | C61: Customer C | D61: 45.635 | E61: 42.802 | F61: 49.742 | G61: 50.344 | H61: 43.583 | I61: =IFERROR(H61*(1+AD61),0) -> 45.32632 | K61: 7.346 | L61: 5.95 | M61: 7.512 | N61: 8.591 | O61: 7.348 | P61: =IFERROR(I61*(W61),0) -> 7.8433724 | R61: =IFERROR(K61/D61,"--") -> 0.16097294 | S61: =IFERROR(L61/E61,"--") -> 0.1390122 | T61: =IFERROR(M61/F61,"--") -> 0.15101926 | U61: =IFERROR(N61/G61,"--") -> 0.17064596 | V61: =IFERROR(O61/H61,"--") -> 0.16859785 | W61: 0.17304234 | Z61: =IFERROR(E61/D61-1,"--") -> -0.062079544 | AA61: =IFERROR(F61/E61-1,"--") -> 0.16214196 | AB61: =IFERROR(G61/F61-1,"--") -> 0.012102449 | AC61: =IFERROR(H61/G61-1,"--") -> -0.13429604 | AD61: 0.04
B62: =B61+1 -> 4 | C62: Customer D | D62: 6.888321 | E62: 10.321 | F62: 12.381 | G62: 14.017 | H62: 17.566 | I62: =IFERROR(H62*(1+AD62),0) -> 19.14694 | K62: 2.1353795 | L62: 3.406 | M62: 3.962 | N62: 4.485 | O62: 5.482 | P62: =IFERROR(I62*(W62),0) -> 6.246579 | R62: =IFERROR(K62/D62,"--") -> 0.31 | S62: =IFERROR(L62/E62,"--") -> 0.33000678 | T62: =IFERROR(M62/F62,"--") -> 0.32000646 | U62: =IFERROR(N62/G62,"--") -> 0.31996861 | V62: =IFERROR(O62/H62,"--") -> 0.31208015 | W62: 0.32624424 | Z62: =IFERROR(E62/D62-1,"--") -> 0.49833319 | AA62: =IFERROR(F62/E62-1,"--") -> 0.19959306 | AB62: =IFERROR(G62/F62-1,"--") -> 0.13213795 | AC62: =IFERROR(H62/G62-1,"--") -> 0.25319255 | AD62: 0.09
B63: =B62+1 -> 5 | C63: Customer E | D63: 10.0579 | E63: 9.662 | F63: 9.114 | G63: 14.217 | H63: 20.284 | I63: =IFERROR(H63*(1+AD63),0) -> 18.45844 | K63: 0.18 | L63: 0.642873 | M63: 1.058 | N63: 3.828 | O63: 4.781 | P63: =IFERROR(I63*(W63),0) -> 4.3301638 | R63: =IFERROR(K63/D63,"--") -> 0.01789638 | S63: =IFERROR(L63/E63,"--") -> 0.066536224 | T63: =IFERROR(M63/F63,"--") -> 0.11608514 | U63: =IFERROR(N63/G63,"--") -> 0.26925512 | V63: =IFERROR(O63/H63,"--") -> 0.23570302 | W63: 0.23458991 | Z63: =IFERROR(E63/D63-1,"--") -> -0.039362093 | AA63: =IFERROR(F63/E63-1,"--") -> -0.056717036 | AB63: =IFERROR(G63/F63-1,"--") -> 0.55990783 | AC63: =IFERROR(H63/G63-1,"--") -> 0.42674263 | AD63: -0.09
B64: =B63+1 -> 6 | C64: Customer F | D64: 15.40125 | E64: 7.938 | F64: 10.75875 | G64: 16.65 | H64: 16.14438 | I64: =IFERROR(H64*(1+AD64),0) -> 13.884167 | K64: 1.0195627 | L64: 0.55566 | M64: 0.8607 | N64: 1.8315 | O64: 1.78126 | P64: =IFERROR(I64*(W64),0) -> 1.5966832 | R64: =IFERROR(K64/D64,"--") -> 0.0662 | S64: =IFERROR(L64/E64,"--") -> 0.07 | T64: =IFERROR(M64/F64,"--") -> 0.08 | U64: =IFERROR(N64/G64,"--") -> 0.11 | V64: =IFERROR(O64/H64,"--") -> 0.11033313 | W64: 0.11500029 | Z64: =IFERROR(E64/D64-1,"--") -> -0.48458729 | AA64: =IFERROR(F64/E64-1,"--") -> 0.35534769 | AB64: =IFERROR(G64/F64-1,"--") -> 0.54757755 | AC64: =IFERROR(H64/G64-1,"--") -> -0.030367568 | AD64: -0.14
B65: =B64+1 -> 7 | C65: Customer G | D65: 9.1218 | E65: 13.227 | F65: 14.179 | G65: 15.726 | H65: 17.907 | I65: =IFERROR(H65*(1+AD65),0) -> 18.62328 | K65: 2.0806 | L65: 2.881 | M65: 3.476 | N65: 4.196078 | O65: 4.648 | P65: =IFERROR(I65*(W65),0) -> 4.7693289 | R65: =IFERROR(K65/D65,"--") -> 0.22809095 | S65: =IFERROR(L65/E65,"--") -> 0.21781205 | T65: =IFERROR(M65/F65,"--") -> 0.24515128 | U65: =IFERROR(N65/G65,"--") -> 0.26682424 | V65: =IFERROR(O65/H65,"--") -> 0.2595633 | W65: 0.256095 | Z65: =IFERROR(E65/D65-1,"--") -> 0.45004275 | AA65: =IFERROR(F65/E65-1,"--") -> 0.071973993 | AB65: =IFERROR(G65/F65-1,"--") -> 0.10910501 | AC65: =IFERROR(H65/G65-1,"--") -> 0.13868752 | AD65: 0.04
B66: =B65+1 -> 8 | C66: Customer H | D66: 0.124 | E66: 0.242 | F66: 0.262 | G66: 0.145 | H66: 0.154 | I66: =IFERROR(H66*(1+AD66),0) -> 0.15554 | K66: 0.065 | L66: 0.073 | M66: 0.084 | N66: 0.036 | O66: 0.046 | P66: =IFERROR(I66*(W66),0) -> 0.05151 | R66: =IFERROR(K66/D66,"--") -> 0.52419355 | S66: =IFERROR(L66/E66,"--") -> 0.30165289 | T66: =IFERROR(M66/F66,"--") -> 0.32061069 | U66: =IFERROR(N66/G66,"--") -> 0.24827586 | V66: =IFERROR(O66/H66,"--") -> 0.2987013 | W66: 0.33116883 | Z66: =IFERROR(E66/D66-1,"--") -> 0.9516129 | AA66: =IFERROR(F66/E66-1,"--") -> 0.082644628 | AB66: =IFERROR(G66/F66-1,"--") -> -0.44656489 | AC66: =IFERROR(H66/G66-1,"--") -> 0.062068966 | AD66: 0.01
B67: =B66+1 -> 9 | C67: Customer I | D67: 1.1219 | E67: 5.404 | F67: 8.137 | G67: 9.342 | H67: 9.253617 | I67: =IFERROR(H67*(1+AD67),0) -> 8.4207915 | K67: 0.280475 | L67: 1.214 | M67: 1.029 | N67: 0.004 | O67: 1.224 | P67: =IFERROR(I67*(W67),0) -> 1.3057341 | R67: =IFERROR(K67/D67,"--") -> 0.25 | S67: =IFERROR(L67/E67,"--") -> 0.22464841 | T67: =IFERROR(M67/F67,"--") -> 0.12645938 | U67: =IFERROR(N67/G67,"--") -> 0.00042817384 | V67: =IFERROR(O67/H67,"--") -> 0.1322726 | W67: 0.15506073 | Z67: =IFERROR(E67/D67-1,"--") -> 3.8168286 | AA67: =IFERROR(F67/E67-1,"--") -> 0.50573649 | AB67: =IFERROR(G67/F67-1,"--") -> 0.14808898 | AC67: =IFERROR(H67/G67-1,"--") -> -0.0094608221 | AD67: -0.09
B68: =B67+1 -> 10 | C68: Customer J | D68: 0.7517 | E68: 0.77195 | F68: 1.73969 | G68: 1.60315 | H68: 0.63305 | I68: =IFERROR(H68*(1+AD68),0) -> 0.5760755 | K68: 0.195 | L68: 0.18912775 | M68: 0.42622405 | N68: 0.39277175 | O68: 0.16036 | P68: =IFERROR(I68*(W68),0) -> 0.22260957 | R68: =IFERROR(K68/D68,"--") -> 0.259412 | S68: =IFERROR(L68/E68,"--") -> 0.245 | T68: =IFERROR(M68/F68,"--") -> 0.245 | U68: =IFERROR(N68/G68,"--") -> 0.245 | V68: =IFERROR(O68/H68,"--") -> 0.25331332 | W68: 0.3864243 | Z68: =IFERROR(E68/D68-1,"--") -> 0.026938938 | AA68: =IFERROR(F68/E68-1,"--") -> 1.2536304 | AB68: =IFERROR(G68/F68-1,"--") -> -0.078485247 | AC68: =IFERROR(H68/G68-1,"--") -> -0.60512117 | AD68: -0.09
B69: =B68+1 -> 11 | C69: Customer K | D69: 0.500562 | E69: 0.739 | F69: 2.304 | G69: 4.148 | H69: 5.084 | I69: =IFERROR(H69*(1+AD69),0) -> 5.64324 | K69: 0.13264893 | L69: 0.193 | M69: 0.562 | N69: 1.108 | O69: 1.351 | P69: =IFERROR(I69*(W69),0) -> 1.513022 | R69: =IFERROR(K69/D69,"--") -> 0.265 | S69: =IFERROR(L69/E69,"--") -> 0.26116373 | T69: =IFERROR(M69/F69,"--") -> 0.24392361 | U69: =IFERROR(N69/G69,"--") -> 0.26711668 | V69: =IFERROR(O69/H69,"--") -> 0.26573564 | W69: 0.26811229 | Z69: =IFERROR(E69/D69-1,"--") -> 0.47634059 | AA69: =IFERROR(F69/E69-1,"--") -> 2.1177267 | AB69: =IFERROR(G69/F69-1,"--") -> 0.80034722 | AC69: =IFERROR(H69/G69-1,"--") -> 0.22565092 | AD69: 0.11
B70: =B69+1 -> 12 | C70: Customer L | D70: 0.08907225 | E70: 0.285 | F70: 0.043125 | G70: 0 | H70: 0.15061 | I70: =IFERROR(H70*(1+AD70),0) -> 0.1972991 | K70: 0.02494023 | L70: 0.0798 | M70: 0.012075 | N70: 0 | O70: 0.04572 | P70: =IFERROR(I70*(W70),0) -> 0.031239516 | R70: =IFERROR(K70/D70,"--") -> 0.28 | S70: =IFERROR(L70/E70,"--") -> 0.28 | T70: =IFERROR(M70/F70,"--") -> 0.28 | U70: =IFERROR(N70/G70,"--") -> -- | V70: =IFERROR(O70/H70,"--") -> 0.3035655 | W70: 0.15833583 | Z70: =IFERROR(E70/D70-1,"--") -> 2.1996497 | AA70: =IFERROR(F70/E70-1,"--") -> -0.84868421 | AB70: =IFERROR(G70/F70-1,"--") -> -1 | AC70: =IFERROR(H70/G70-1,"--") -> -- | AD70: 0.31
B71: =B70+1 -> 13 | C71: Customer M | D71: 0.0061335 | E71: 0 | F71: 0 | G71: 0 | H71: 0 | I71: =IFERROR(H71*(1+AD71),0) -> 0 | K71: 0.000920025 | L71: 0 | M71: 0 | N71: 0 | O71: 0 | R71: =IFERROR(K71/D71,"--") -> 0.15 | S71: =IFERROR(L71/E71,"--") -> -- | T71: =IFERROR(M71/F71,"--") -> -- | U71: =IFERROR(N71/G71,"--") -> -- | V71: =IFERROR(O71/H71,"--") -> -- | W71: -- | Z71: =IFERROR(E71/D71-1,"--") -> -1 | AA71: =IFERROR(F71/E71-1,"--") -> -- | AB71: =IFERROR(G71/F71-1,"--") -> -- | AC71: =IFERROR(H71/G71-1,"--") -> -- | AD71: --
B72: =B71+1 -> 14 | C72: Customer N | D72: 0.33737325 | E72: 0.2472 | F72: 0.2823075 | G72: 0.247425 | H72: 0.58926 | I72: =IFERROR(H72*(1+AD72),0) -> 0.6540786 | K72: 0.087717045 | L72: 0.064272 | M72: 0.05081535 | N72: 0.05690775 | O72: 0.17758 | P72: =IFERROR(I72*(W72),0) -> 0.19109747 | R72: =IFERROR(K72/D72,"--") -> 0.26 | S72: =IFERROR(L72/E72,"--") -> 0.26 | T72: =IFERROR(M72/F72,"--") -> 0.18 | U72: =IFERROR(N72/G72,"--") -> 0.23 | V72: =IFERROR(O72/H72,"--") -> 0.30136103 | W72: 0.29216285 | Z72: =IFERROR(E72/D72-1,"--") -> -0.26728038 | AA72: =IFERROR(F72/E72-1,"--") -> 0.14202063 | AB72: =IFERROR(G72/F72-1,"--") -> -0.12356207 | AC72: =IFERROR(H72/G72-1,"--") -> 1.3815702 | AD72: 0.11
B73: =B72+1 -> 15 | C73: Customer O | D73: 0 | E73: 0 | F73: 0.054 | G73: 0.299 | H73: 0.444 | I73: =IFERROR(H73*(1+AD73),0) -> 0.51504 | K73: 0 | L73: 0 | M73: 0.014 | N73: 0.075 | O73: 0.16 | P73: =IFERROR(I73*(W73),0) -> 0.18419833 | R73: =IFERROR(K73/D73,"--") -> -- | S73: =IFERROR(L73/E73,"--") -> -- | T73: =IFERROR(M73/F73,"--") -> 0.25925926 | U73: =IFERROR(N73/G73,"--") -> 0.25083612 | V73: =IFERROR(O73/H73,"--") -> 0.36036036 | W73: 0.35763889 | Z73: =IFERROR(E73/D73-1,"--") -> -- | AA73: =IFERROR(F73/E73-1,"--") -> -- | AB73: =IFERROR(G73/F73-1,"--") -> 4.537037 | AC73: =IFERROR(H73/G73-1,"--") -> 0.48494983 | AD73: 0.16
C74: Top 15 Total | D74: =SUM(D59:D73) -> 102.0444 | E74: =SUM(E59:E73) -> 135.56815 | F74: =SUM(F59:F73) -> 224.51887 | G74: =SUM(G59:G73) -> 255.26094 | H74: =SUM(H59:H73) -> 255.09192 | I74: =SUM(I59:I73) -> 254.81135 | K74: =SUM(K59:K73) -> 15.793393 | L74: =SUM(L59:L73) -> 20.397733 | M74: =SUM(M59:M73) -> 28.016814 | N74: =SUM(N59:N73) -> 36.324557 | O74: =SUM(O59:O73) -> 39.68692 | P74: =SUM(P59:P73) -> 41.253911 | R74: =IFERROR(K74/D74,"--") -> 0.15476982 | S74: =IFERROR(L74/E74,"--") -> 0.1504611 | T74: =IFERROR(M74/F74,"--") -> 0.12478601 | U74: =IFERROR(N74/G74,"--") -> 0.14230363 | V74: =IFERROR(O74/H74,"--") -> 0.1555789 | W74: =IFERROR(P74/I74,"--") -> 0.16189982 | Z74: =IFERROR(E74/D74-1,"--") -> 0.32852124 | AA74: =IFERROR(F74/E74-1,"--") -> 0.65613289 | AB74: =IFERROR(G74/F74-1,"--") -> 0.13692421 | AC74: =IFERROR(H74/G74-1,"--") -> -0.00066216554 | AD74: =IFERROR(I74/H74-1,"--") -> -0.0010998605
C75: Growth | E75: =E74/D74-1 -> 0.32852124 | F75: =F74/E74-1 -> 0.65613289 | G75: =G74/F74-1 -> 0.13692421 | H75: =H74/G74-1 -> -0.00066216554 | I75: =I74/H74-1 -> -0.0010998605 | L75: =L74/K74-1 -> 0.29153578 | M75: =M74/L74-1 -> 0.37352591 | N75: =N74/M74-1 -> 0.29652704 | O75: =O74/N74-1 -> 0.092564445 | P75: =P74/O74-1 -> 0.039483825
C77: Rest of Customers | D77: =D80-D74 -> 50.588842 | E77: =E80-E74 -> 60.458471 | F77: =F80-F74 -> 74.595667 | G77: =G80-G74 -> 84.178854 | H77: =H80-H74 -> 85.566117 | I77: =I80-I74 -> 94.97839 | K77: =K80-K74 -> 9.0347093 | L77: =L80-L74 -> 11.168495 | M77: =M80-M74 -> 14.423627 | N77: =N80-N74 -> 16.275991 | O77: =O80-O74 -> 18.250369 | P77: =P80-P74 -> 20.313667 | R77: =IFERROR(K77/D77,"--") -> 0.17859095 | S77: =IFERROR(L77/E77,"--") -> 0.18473002 | T77: =IFERROR(M77/F77,"--") -> 0.19335744 | U77: =IFERROR(N77/G77,"--") -> 0.19335011 | V77: =IFERROR(O77/H77,"--") -> 0.21328967 | W77: =IFERROR(P77/I77,"--") -> 0.21387672 | Z77: =IFERROR(E77/D77-1,"--") -> 0.19509499 | AA77: =IFERROR(F77/E77-1,"--") -> 0.23383316 | AB77: =IFERROR(G77/F77-1,"--") -> 0.12846842 | AC77: =IFERROR(H77/G77-1,"--") -> 0.01647995 | AD77: =IFERROR(I77/H77-1,"--") -> 0.11
C78: Growth | E78: =E77/D77-1 -> 0.19509499 | F78: =F77/E77-1 -> 0.23383316 | G78: =G77/F77-1 -> 0.12846842 | H78: =H77/G77-1 -> 0.01647995 | I78: =I77/H77-1 -> 0.11 | L78: =L77/K77-1 -> 0.23617643 | M78: =M77/L77-1 -> 0.29145671 | N78: =N77/M77-1 -> 0.12842564 | O78: =O77/N77-1 -> 0.12130617 | P78: =P77/O77-1 -> 0.11305512
C80: Total Consulting | D80: 152.63324 | E80: 196.02662 | F80: 299.11454 | G80: 339.4398 | H80: 340.65803 | I80: 349.78974 | K80: 24.828103 | L80: 31.566227 | M80: 42.440442 | N80: 52.600549 | O80: 57.937289 | P80: 61.567578 | R80: =IFERROR(K80/D80,"--") -> 0.16266511 | S80: =IFERROR(L80/E80,"--") -> 0.16103031 | T80: =IFERROR(M80/F80,"--") -> 0.14188692 | U80: =IFERROR(N80/G80,"--") -> 0.15496282 | V80: =IFERROR(O80/H80,"--") -> 0.17007463 | W80: =IFERROR(P80/I80,"--") -> 0.1760131 | Z80: =IFERROR(E80/D80-1,"--") -> 0.28429837 | AA80: =IFERROR(F80/E80-1,"--") -> 0.52588734 | AB80: =IFERROR(G80/F80-1,"--") -> 0.13481544 | AC80: =IFERROR(H80/G80-1,"--") -> 0.0035889671 | AD80: =IFERROR(I80/H80-1,"--") -> 0.026806083
C81: Growth | E81: =E80/D80-1 -> 0.28429837 | F81: =F80/E80-1 -> 0.52588734 | G81: =G80/F80-1 -> 0.13481544 | H81: =H80/G80-1 -> 0.0035889671 | I81: =I80/H80-1 -> 0.026806083 | L81: =L80/K80-1 -> 0.27139104 | M81: =M80/L80-1 -> 0.34448888 | N81: =N80/M80-1 -> 0.23939682 | O81: =O80/N80-1 -> 0.10145789 | P81: =P80/O80-1 -> 0.062658939
A83: x | B83: Rank | C83: Comms Revenue | D83: Revenue | K83: Gross Profit | R83: Gross Margin | Y83: Revenue Growth
B84: 1 | C84: Customer A | D84: 0 | E84: 0 | F84: 0 | G84: 0 | H84: 0.00666 | I84: =IFERROR(H84*(1+AD84),0) -> 0 | K84: 0 | L84: 0 | M84: 0 | N84: 0 | O84: 0 | P84: =IFERROR(I84*W84,0) -> 0 | R84: =IFERROR(K84/D84,"--") -> -- | S84: =IFERROR(L84/E84,"--") -> -- | T84: =IFERROR(M84/F84,"--") -> -- | U84: =IFERROR(N84/G84,"--") -> -- | V84: =IFERROR(O84/H84,"--") -> 0 | W84: -- | Z84: =IFERROR(E84/D84-1,"--") -> -- | AA84: =IFERROR(F84/E84-1,"--") -> -- | AB84: =IFERROR(G84/F84-1,"--") -> -- | AC84: =IFERROR(H84/G84-1,"--") -> -- | AD84: --
B85: =B84+1 -> 2 | C85: Customer B | D85: 0 | E85: 0 | F85: 0 | G85: 0 | H85: 0 | I85: =IFERROR(H85*(1+AD85),0) -> 0 | K85: 0 | L85: 0 | M85: 0 | N85: 0 | O85: 0 | P85: =IFERROR(I85*W85,0) -> 0 | R85: =IFERROR(K85/D85,"--") -> -- | S85: =IFERROR(L85/E85,"--") -> -- | T85: =IFERROR(M85/F85,"--") -> -- | U85: =IFERROR(N85/G85,"--") -> -- | V85: =IFERROR(O85/H85,"--") -> -- | W85: -- | Z85: =IFERROR(E85/D85-1,"--") -> -- | AA85: =IFERROR(F85/E85-1,"--") -> -- | AB85: =IFERROR(G85/F85-1,"--") -> -- | AC85: =IFERROR(H85/G85-1,"--") -> -- | AD85: --
B86: =B85+1 -> 3 | C86: Customer C | D86: 0 | E86: 0 | F86: 0 | G86: 0 | H86: 0 | I86: =IFERROR(H86*(1+AD86),0) -> 0 | K86: 0 | L86: 0 | M86: 0 | N86: 0 | O86: 0 | P86: =IFERROR(I86*W86,0) -> 0 | R86: =IFERROR(K86/D86,"--") -> -- | S86: =IFERROR(L86/E86,"--") -> -- | T86: =IFERROR(M86/F86,"--") -> -- | U86: =IFERROR(N86/G86,"--") -> -- | V86: =IFERROR(O86/H86,"--") -> -- | W86: -- | Z86: =IFERROR(E86/D86-1,"--") -> -- | AA86: =IFERROR(F86/E86-1,"--") -> -- | AB86: =IFERROR(G86/F86-1,"--") -> -- | AC86: =IFERROR(H86/G86-1,"--") -> -- | AD86: --
B87: =B86+1 -> 4 | C87: Customer D | D87: 1.625 | E87: 1.566 | F87: 1.349 | G87: 1.169 | H87: 0.861871 | I87: =IFERROR(H87*(1+AD87),0) -> 0.82739616 | K87: 0.82875 | L87: 0.783 | M87: 0.675 | N87: 0.584 | O87: 0.30165485 | P87: =IFERROR(I87*W87,0) -> 0.28958866 | R87: =IFERROR(K87/D87,"--") -> 0.51 | S87: =IFERROR(L87/E87,"--") -> 0.5 | T87: =IFERROR(M87/F87,"--") -> 0.50037064 | U87: =IFERROR(N87/G87,"--") -> 0.49957228 | V87: =IFERROR(O87/H87,"--") -> 0.35 | W87: 0.35 | Z87: =IFERROR(E87/D87-1,"--") -> -0.036307692 | AA87: =IFERROR(F87/E87-1,"--") -> -0.1385696 | AB87: =IFERROR(G87/F87-1,"--") -> -0.13343217 | AC87: =IFERROR(H87/G87-1,"--") -> -0.26272797 | AD87: -0.04
B88: =B87+1 -> 5 | C88: Customer E | D88: 21.435354 | E88: 20.104 | F88: 16.502 | G88: 18.791 | H88: 22.516 | I88: =IFERROR(H88*(1+AD88),0) -> 22.74116 | K88: 12.041 | L88: 8.878 | M88: 7.758 | N88: 9.412 | O88: 12.582 | P88: =IFERROR(I88*W88,0) -> 12.507638 | R88: =IFERROR(K88/D88,"--") -> 0.56173553 | S88: =IFERROR(L88/E88,"--") -> 0.44160366 | T88: =IFERROR(M88/F88,"--") -> 0.47012483 | U88: =IFERROR(N88/G88,"--") -> 0.50087808 | V88: =IFERROR(O88/H88,"--") -> 0.55880263 | W88: 0.55 | Z88: =IFERROR(E88/D88-1,"--") -> -0.062110194 | AA88: =IFERROR(F88/E88-1,"--") -> -0.17916832 | AB88: =IFERROR(G88/F88-1,"--") -> 0.13871046 | AC88: =IFERROR(H88/G88-1,"--") -> 0.1982332 | AD88: 0.01
B89: =B88+1 -> 6 | C89: Customer F | D89: 0 | E89: 0 | F89: 0 | G89: 0 | H89: 0 | I89: =IFERROR(H89*(1+AD89),0) -> 0 | K89: 0 | L89: 0 | M89: 0 | N89: 0 | O89: 0 | P89: =IFERROR(I89*W89,0) -> 0 | R89: =IFERROR(K89/D89,"--") -> -- | S89: =IFERROR(L89/E89,"--") -> -- | T89: =IFERROR(M89/F89,"--") -> -- | U89: =IFERROR(N89/G89,"--") -> -- | V89: =IFERROR(O89/H89,"--") -> -- | W89: -- | Z89: =IFERROR(E89/D89-1,"--") -> -- | AA89: =IFERROR(F89/E89-1,"--") -> -- | AB89: =IFERROR(G89/F89-1,"--") -> -- | AC89: =IFERROR(H89/G89-1,"--") -> -- | AD89: --
B90: =B89+1 -> 7 | C90: Customer G | D90: 0.5005 | E90: 0.48 | F90: 0.48 | G90: 0.48 | H90: 0.48 | I90: =IFERROR(H90*(1+AD90),0) -> 0.4848 | K90: 0.2863 | L90: 0.316 | M90: 0.381 | N90: 0.379 | O90: 0.379 | P90: =IFERROR(I90*W90,0) -> 0.382992 | R90: =IFERROR(K90/D90,"--") -> 0.57202797 | S90: =IFERROR(L90/E90,"--") -> 0.65833333 | T90: =IFERROR(M90/F90,"--") -> 0.79375 | U90: =IFERROR(N90/G90,"--") -> 0.78958333 | V90: =IFERROR(O90/H90,"--") -> 0.78958333 | W90: 0.79 | Z90: =IFERROR(E90/D90-1,"--") -> -0.040959041 | AA90: =IFERROR(F90/E90-1,"--") -> 0 | AB90: =IFERROR(G90/F90-1,"--") -> 0 | AC90: =IFERROR(H90/G90-1,"--") -> 0 | AD90: 0.01
B91: =B90+1 -> 8 | C91: Customer H | D91: 12.51 | E91: 20.615 | F91: 21.215 | G91: 21.579 | H91: 24.613767 | I91: =IFERROR(H91*(1+AD91),0) -> 25.598318 | K91: 5.66 | L91: 10.311 | M91: 9.006 | N91: 8.698 | O91: 9.0332525 | P91: =IFERROR(I91*W91,0) -> 8.9594112 | R91: =IFERROR(K91/D91,"--") -> 0.45243805 | S91: =IFERROR(L91/E91,"--") -> 0.50016978 | T91: =IFERROR(M91/F91,"--") -> 0.42451096 | U91: =IFERROR(N91/G91,"--") -> 0.40307707 | V91: =IFERROR(O91/H91,"--") -> 0.367 | W91: 0.35 | Z91: =IFERROR(E91/D91-1,"--") -> 0.64788169 | AA91: =IFERROR(F91/E91-1,"--") -> 0.029105021 | AB91: =IFERROR(G91/F91-1,"--") -> 0.017157671 | AC91: =IFERROR(H91/G91-1,"--") -> 0.14063521 | AD91: 0.04
B92: =B91+1 -> 9 | C92: Customer I | D92: 3.22594 | E92: 2.701 | F92: 1.768 | G92: 1.527 | H92: 1.434 | I92: =IFERROR(H92*(1+AD92),0) -> 1.37664 | K92: 1.290376 | L92: 0.877 | M92: 0.561 | N92: 0.473 | O92: 0.434 | P92: =IFERROR(I92*W92,0) -> 0.412992 | R92: =IFERROR(K92/D92,"--") -> 0.4 | S92: =IFERROR(L92/E92,"--") -> 0.32469456 | T92: =IFERROR(M92/F92,"--") -> 0.31730769 | U92: =IFERROR(N92/G92,"--") -> 0.30975769 | V92: =IFERROR(O92/H92,"--") -> 0.30264993 | W92: 0.3 | Z92: =IFERROR(E92/D92-1,"--") -> -0.16272466 | AA92: =IFERROR(F92/E92-1,"--") -> -0.34542762 | AB92: =IFERROR(G92/F92-1,"--") -> -0.13631222 | AC92: =IFERROR(H92/G92-1,"--") -> -0.060903733 | AD92: -0.04
B93: =B92+1 -> 10 | C93: Customer J | D93: 1.0831 | E93: 1.52146 | F93: 1.99231 | G93: 2.01027 | H93: 2.009135 | I93: =IFERROR(H93*(1+AD93),0) -> 2.0292264 | K93: 0.779832 | L93: 0.995 | M93: 1.0659 | N93: 1.0791 | O93: 1.0849329 | P93: =IFERROR(I93*W93,0) -> 1.1160745 | R93: =IFERROR(K93/D93,"--") -> 0.72 | S93: =IFERROR(L93/E93,"--") -> 0.6539771 | T93: =IFERROR(M93/F93,"--") -> 0.5350071 | U93: =IFERROR(N93/G93,"--") -> 0.53679357 | V93: =IFERROR(O93/H93,"--") -> 0.54 | W93: 0.55 | Z93: =IFERROR(E93/D93-1,"--") -> 0.40472717 | AA93: =IFERROR(F93/E93-1,"--") -> 0.30947248 | AB93: =IFERROR(G93/F93-1,"--") -> 0.0090146614 | AC93: =IFERROR(H93/G93-1,"--") -> -0.00056460078 | AD93: 0.01
B94: =B93+1 -> 11 | C94: Customer K | D94: 1.552 | E94: 0.69 | F94: 0.537 | G94: 0.571 | H94: 0.488065 | I94: =IFERROR(H94*(1+AD94),0) -> 0.5173489 | K94: 0.617 | L94: 0.215 | M94: 0.083 | N94: 0.112 | O94: 0.115 | P94: =IFERROR(I94*W94,0) -> 0.12933722 | R94: =IFERROR(K94/D94,"--") -> 0.39755155 | S94: =IFERROR(L94/E94,"--") -> 0.3115942 | T94: =IFERROR(M94/F94,"--") -> 0.15456238 | U94: =IFERROR(N94/G94,"--") -> 0.19614711 | V94: =IFERROR(O94/H94,"--") -> 0.23562435 | W94: 0.25 | Z94: =IFERROR(E94/D94-1,"--") -> -0.55541237 | AA94: =IFERROR(F94/E94-1,"--") -> -0.22173913 | AB94: =IFERROR(G94/F94-1,"--") -> 0.063314711 | AC94: =IFERROR(H94/G94-1,"--") -> -0.14524518 | AD94: 0.06
B95: =B94+1 -> 12 | C95: Customer L | D95: 0 | E95: 0 | F95: 0 | G95: 0 | H95: 0 | I95: =IFERROR(H95*(1+AD95),0) -> 0 | K95: 0 | L95: 0 | M95: 0 | N95: 0 | O95: 0 | P95: =IFERROR(I95*W95,0) -> 0 | R95: =IFERROR(K95/D95,"--") -> -- | S95: =IFERROR(L95/E95,"--") -> -- | T95: =IFERROR(M95/F95,"--") -> -- | U95: =IFERROR(N95/G95,"--") -> -- | V95: =IFERROR(O95/H95,"--") -> -- | W95: -- | Z95: =IFERROR(E95/D95-1,"--") -> -- | AA95: =IFERROR(F95/E95-1,"--") -> -- | AB95: =IFERROR(G95/F95-1,"--") -> -- | AC95: =IFERROR(H95/G95-1,"--") -> -- | AD95: --
B96: =B95+1 -> 13 | C96: Customer M | D96: 0 | E96: 0 | F96: 0 | G96: 0 | H96: 0 | I96: =IFERROR(H96*(1+AD96),0) -> 0 | K96: 0 | L96: 0 | M96: 0 | N96: 0 | O96: 0 | P96: =IFERROR(I96*W96,0) -> 0 | R96: =IFERROR(K96/D96,"--") -> -- | S96: =IFERROR(L96/E96,"--") -> -- | T96: =IFERROR(M96/F96,"--") -> -- | U96: =IFERROR(N96/G96,"--") -> -- | V96: =IFERROR(O96/H96,"--") -> -- | W96: -- | Z96: =IFERROR(E96/D96-1,"--") -> -- | AA96: =IFERROR(F96/E96-1,"--") -> -- | AB96: =IFERROR(G96/F96-1,"--") -> -- | AC96: =IFERROR(H96/G96-1,"--") -> -- | AD96: --
B97: =B96+1 -> 14 | C97: Customer N | D97: 0 | E97: 0 | F97: 0 | G97: 0 | H97: 0 | I97: =IFERROR(H97*(1+AD97),0) -> 0 | K97: 0 | L97: 0 | M97: 0 | N97: 0 | O97: 0 | P97: =IFERROR(I97*W97,0) -> 0 | R97: =IFERROR(K97/D97,"--") -> -- | S97: =IFERROR(L97/E97,"--") -> -- | T97: =IFERROR(M97/F97,"--") -> -- | U97: =IFERROR(N97/G97,"--") -> -- | V97: =IFERROR(O97/H97,"--") -> -- | W97: -- | Z97: =IFERROR(E97/D97-1,"--") -> -- | AA97: =IFERROR(F97/E97-1,"--") -> -- | AB97: =IFERROR(G97/F97-1,"--") -> -- | AC97: =IFERROR(H97/G97-1,"--") -> -- | AD97: --
B98: =B97+1 -> 15 | C98: Customer O | D98: 1.708 | E98: 3.239 | F98: 4.165 | G98: 4.756 | H98: 5.52696 | I98: =IFERROR(H98*(1+AD98),0) -> 6.2730996 | K98: 1.013 | L98: 1.98 | M98: 1.678 | N98: 2.24 | O98: 2.210784 | P98: =IFERROR(I98*W98,0) -> 2.8228948 | R98: =IFERROR(K98/D98,"--") -> 0.59309133 | S98: =IFERROR(L98/E98,"--") -> 0.61129978 | T98: =IFERROR(M98/F98,"--") -> 0.40288115 | U98: =IFERROR(N98/G98,"--") -> 0.47098402 | V98: =IFERROR(O98/H98,"--") -> 0.4 | W98: 0.45 | Z98: =IFERROR(E98/D98-1,"--") -> 0.89637002 | AA98: =IFERROR(F98/E98-1,"--") -> 0.28589071 | AB98: =IFERROR(G98/F98-1,"--") -> 0.14189676 | AC98: =IFERROR(H98/G98-1,"--") -> 0.16210261 | AD98: 0.135
C99: Top 15 Total | D99: =SUM(D84:D98) -> 43.639894 | E99: =SUM(E84:E98) -> 50.91646 | F99: =SUM(F84:F98) -> 48.00831 | G99: =SUM(G84:G98) -> 50.88327 | H99: =SUM(H84:H98) -> 57.936458 | I99: =SUM(I84:I98) -> 59.847989 | K99: =SUM(K84:K98) -> 22.516258 | L99: =SUM(L84:L98) -> 24.355 | M99: =SUM(M84:M98) -> 21.2079 | N99: =SUM(N84:N98) -> 22.9771 | O99: =SUM(O84:O98) -> 26.140624 | P99: =SUM(P84:P98) -> 26.620928 | R99: =IFERROR(K99/D99,"--") -> 0.51595584 | S99: =IFERROR(L99/E99,"--") -> 0.47833255 | T99: =IFERROR(M99/F99,"--") -> 0.44175477 | U99: =IFERROR(N99/G99,"--") -> 0.45156492 | V99: =IFERROR(O99/H99,"--") -> 0.45119472 | W99: =IFERROR(P99/I99,"--") -> 0.44480907 | Z99: =IFERROR(E99/D99-1,"--") -> 0.16674115 | AA99: =IFERROR(F99/E99-1,"--") -> -0.057116107 | AB99: =IFERROR(G99/F99-1,"--") -> 0.059884632 | AC99: =IFERROR(H99/G99-1,"--") -> 0.13861507 | AD99: =IFERROR(I99/H99-1,"--") -> 0.032993572
C100: Growth | E100: =E99/D99-1 -> 0.16674115 | F100: =F99/E99-1 -> -0.057116107 | G100: =G99/F99-1 -> 0.059884632 | H100: =H99/G99-1 -> 0.13861507 | I100: =I99/H99-1 -> 0.032993572 | L100: =L99/K99-1 -> 0.081662859 | M100: =M99/L99-1 -> -0.12921782 | N100: =N99/M99-1 -> 0.083421744 | O100: =O99/N99-1 -> 0.13768162 | P100: =P99/O99-1 -> 0.018373859
C102: Rest of Customers | D102: =D105-D99 -> 57.151628 | E102: =E105-E99 -> 63.770827 | F102: =F105-F99 -> 73.805034 | G102: =G105-G99 -> 82.772494 | H102: =H105-H99 -> 87.396584 | I102: =I105-I99 -> 93.982519 | K102: =K105-K99 -> 3.9071421 | L102: =L105-L99 -> 8.8854767 | M102: =M105-M99 -> 10.91597 | N102: =N105-N99 -> 14.158165 | O102: =O105-O99 -> 16.662973 | P102: =P105-P99 -> 19.602735 | R102: =IFERROR(K102/D102,"--") -> 0.068364493 | S102: =IFERROR(L102/E102,"--") -> 0.13933451 | T102: =IFERROR(M102/F102,"--") -> 0.14790279 | U102: =IFERROR(N102/G102,"--") -> 0.17104915 | V102: =IFERROR(O102/H102,"--") -> 0.19065932 | W102: =IFERROR(P102/I102,"--") -> 0.20857852 | Z102: =IFERROR(E102/D102-1,"--") -> 0.1158182 | AA102: =IFERROR(F102/E102-1,"--") -> 0.15734792 | AB102: =IFERROR(G102/F102-1,"--") -> 0.12150201 | AC102: =IFERROR(H102/G102-1,"--") -> 0.055865063 | AD102: =IFERROR(I102/H102-1,"--") -> 0.075356887
C103: Growth | E103: =E102/D102-1 -> 0.1158182 | F103: =F102/E102-1 -> 0.15734792 | G103: =G102/F102-1 -> 0.12150201 | H103: =H102/G102-1 -> 0.055865063 | I103: =I102/H102-1 -> 0.075356887 | L103: =L102/K102-1 -> 1.2741627 | M103: =M102/L102-1 -> 0.22851824 | N103: =N102/M102-1 -> 0.2970139 | O103: =O102/N102-1 -> 0.17691614 | P103: =P102/O102-1 -> 0.17642481
C105: Total Comms | D105: 100.79152 | E105: 114.68729 | F105: 121.81334 | G105: 133.65576 | H105: 145.33304 | I105: 153.83051 | K105: 26.4234 | L105: 33.240477 | M105: 32.12387 | N105: 37.135265 | O105: 42.803597 | P105: 46.223663 | R105: =IFERROR(K105/D105,"--") -> 0.26215895 | S105: =IFERROR(L105/E105,"--") -> 0.28983576 | T105: =IFERROR(M105/F105,"--") -> 0.26371388 | U105: =IFERROR(N105/G105,"--") -> 0.2778426 | V105: =IFERROR(O105/H105,"--") -> 0.29452075 | W105: =IFERROR(P105/I105,"--") -> 0.30048437 | Z105: =IFERROR(E105/D105-1,"--") -> 0.1378664 | AA105: =IFERROR(F105/E105-1,"--") -> 0.062134672 | AB105: =IFERROR(G105/F105-1,"--") -> 0.097217754 | AC105: =IFERROR(H105/G105-1,"--") -> 0.087368314 | AD105: =IFERROR(I105/H105-1,"--") -> 0.058468914
C106: Growth | E106: =E105/D105-1 -> 0.1378664 | F106: =F105/E105-1 -> 0.062134672 | G106: =G105/F105-1 -> 0.097217754 | H106: =H105/G105-1 -> 0.087368314 | I106: =I105/H105-1 -> 0.058468914 | L106: =L105/K105-1 -> 0.25799392 | M106: =M105/L105-1 -> -0.033591773 | N106: =N105/M105-1 -> 0.15600222 | O106: =O105/N105-1 -> 0.15264014 | P106: =P105/O105-1 -> 0.07990137
A108: x | B108: Rank | C108: Total | D108: Revenue | K108: Gross Profit | R108: Gross Margin | Y108: Revenue Growth
B109: 1 | C109: Customer A | D109: =SUM(D9,D34,D84,D59) -> 136.06858 | E109: =SUM(E9,E34,E84,E59) -> 123.84384 | F109: =SUM(F9,F34,F84,F59) -> 222 | G109: =SUM(G9,G34,G84,G59) -> 191.51266 | H109: =SUM(H9,H34,H84,H59) -> 168.90163 | I109: =SUM(I9,I34,I84,I59) -> 172.14892 | K109: =SUM(K9,K34,K84,K59) -> 19.095223 | L109: =SUM(L9,L34,L84,L59) -> 16.453522 | M109: =SUM(M9,M34,M84,M59) -> 26.073 | N109: =SUM(N9,N34,N84,N59) -> 23.784566 | O109: =SUM(O9,O34,O84,O59) -> 18.809791 | P109: =SUM(P9,P34,P84,P59) -> 21.79933 | R109: =IFERROR(K109/D109,"--") -> 0.14033529 | S109: =IFERROR(L109/E109,"--") -> 0.132857 | T109: =IFERROR(M109/F109,"--") -> 0.11744595 | U109: =IFERROR(N109/G109,"--") -> 0.12419318 | V109: =IFERROR(O109/H109,"--") -> 0.11136536 | W109: =IFERROR(P109/I109,"--") -> 0.12663066 | Z109: =IFERROR(E109/D109-1,"--") -> -0.089842468 | AA109: =IFERROR(F109/E109-1,"--") -> 0.79258003 | AB109: =IFERROR(G109/F109-1,"--") -> -0.13733038 | AC109: =IFERROR(H109/G109-1,"--") -> -0.11806545 | AD109: =IFERROR(I109/H109-1,"--") -> 0.019225923
B110: =B109+1 -> 2 | C110: Customer B | D110: =SUM(D10,D35,D85,D60) -> 9.811 | E110: =SUM(E10,E35,E85,E60) -> 39.447 | F110: =SUM(F10,F35,F85,F60) -> 110.076 | G110: =SUM(G10,G35,G85,G60) -> 121.399 | H110: =SUM(H10,H35,H85,H60) -> 115.474 | I110: =SUM(I10,I35,I85,I60) -> 113.74189 | K110: =SUM(K10,K35,K85,K60) -> 1.604 | L110: =SUM(L10,L35,L85,L60) -> 3.731 | M110: =SUM(M10,M35,M85,M60) -> 7.614 | N110: =SUM(N10,N35,N85,N60) -> 10.184 | O110: =SUM(O10,O35,O85,O60) -> 10.455 | P110: =SUM(P10,P35,P85,P60) -> 10.78212 | R110: =IFERROR(K110/D110,"--") -> 0.16348996 | S110: =IFERROR(L110/E110,"--") -> 0.094582605 | T110: =IFERROR(M110/F110,"--") -> 0.069170391 | U110: =IFERROR(N110/G110,"--") -> 0.083888665 | V110: =IFERROR(O110/H110,"--") -> 0.090539862 | W110: =IFERROR(P110/I110,"--") -> 0.094794622 | Z110: =IFERROR(E110/D110-1,"--") -> 3.0206911 | AA110: =IFERROR(F110/E110-1,"--") -> 1.7904784 | AB110: =IFERROR(G110/F110-1,"--") -> 0.10286529 | AC110: =IFERROR(H110/G110-1,"--") -> -0.048806003 | AD110: =IFERROR(I110/H110-1,"--") -> -0.015
B111: =B110+1 -> 3 | C111: Customer C | D111: =SUM(D11,D36,D86,D61) -> 45.635 | E111: =SUM(E11,E36,E86,E61) -> 44.013 | F111: =SUM(F11,F36,F86,F61) -> 50.479 | G111: =SUM(G11,G36,G86,G61) -> 51.196 | H111: =SUM(H11,H36,H86,H61) -> 44.657768 | I111: =SUM(I11,I36,I86,I61) -> 46.45209 | K111: =SUM(K11,K36,K86,K61) -> 7.346 | L111: =SUM(L11,L36,L86,L61) -> 6.218 | M111: =SUM(M11,M36,M86,M61) -> 7.698 | N111: =SUM(N11,N36,N86,N61) -> 8.874 | O111: =SUM(O11,O36,O86,O61) -> 7.5689483 | P111: =SUM(P11,P36,P86,P61) -> 8.1735698 | R111: =IFERROR(K111/D111,"--") -> 0.16097294 | S111: =IFERROR(L111/E111,"--") -> 0.14127644 | T111: =IFERROR(M111/F111,"--") -> 0.15249906 | U111: =IFERROR(N111/G111,"--") -> 0.17333385 | V111: =IFERROR(O111/H111,"--") -> 0.16948783 | W111: =IFERROR(P111/I111,"--") -> 0.17595699 | Z111: =IFERROR(E111/D111-1,"--") -> -0.035542895 | AA111: =IFERROR(F111/E111-1,"--") -> 0.14691114 | AB111: =IFERROR(G111/F111-1,"--") -> 0.014203926 | AC111: =IFERROR(H111/G111-1,"--") -> -0.12770982 | AD111: =IFERROR(I111/H111-1,"--") -> 0.040179387
B112: =B111+1 -> 4 | C112: Customer D | D112: =SUM(D12,D37,D87,D62) -> 44.197321 | E112: =SUM(E12,E37,E87,E62) -> 42.274 | F112: =SUM(F12,F37,F87,F62) -> 48.398 | G112: =SUM(G12,G37,G87,G62) -> 49.37 | H112: =SUM(H12,H37,H87,H62) -> 56.416423 | I112: =SUM(I12,I37,I87,I62) -> 60.237638 | K112: =SUM(K12,K37,K87,K62) -> 8.1323895 | L112: =SUM(L12,L37,L87,L62) -> 8.399 | M112: =SUM(M12,M37,M87,M62) -> 8.171 | N112: =SUM(N12,N37,N87,N62) -> 8.474 | O112: =SUM(O12,O37,O87,O62) -> 8.3248325 | P112: =SUM(P12,P37,P87,P62) -> 10.75821 | R112: =IFERROR(K112/D112,"--") -> 0.18400187 | S112: =IFERROR(L112/E112,"--") -> 0.19868004 | T112: =IFERROR(M112/F112,"--") -> 0.16882929 | U112: =IFERROR(N112/G112,"--") -> 0.1716427 | V112: =IFERROR(O112/H112,"--") -> 0.14756045 | W112: =IFERROR(P112/I112,"--") -> 0.17859615 | Z112: =IFERROR(E112/D112-1,"--") -> -0.043516687 | AA112: =IFERROR(F112/E112-1,"--") -> 0.14486446 | AB112: =IFERROR(G112/F112-1,"--") -> 0.020083475 | AC112: =IFERROR(H112/G112-1,"--") -> 0.14272682 | AD112: =IFERROR(I112/H112-1,"--") -> 0.067732316
B113: =B112+1 -> 5 | C113: Customer E | D113: =SUM(D13,D38,D88,D63) -> 50.558954 | E113: =SUM(E13,E38,E88,E63) -> 41.060572 | F113: =SUM(F13,F38,F88,F63) -> 33.482 | G113: =SUM(G13,G38,G88,G63) -> 45.68 | H113: =SUM(H13,H38,H88,H63) -> 73.151057 | I113: =SUM(I13,I38,I88,I63) -> 70.648262 | K113: =SUM(K13,K38,K88,K63) -> 18.7558 | L113: =SUM(L13,L38,L88,L63) -> 13.602626 | M113: =SUM(M13,M38,M88,M63) -> 12.505 | N113: =SUM(N13,N38,N88,N63) -> 18.757773 | O113: =SUM(O13,O38,O88,O63) -> 25.771593 | P113: =SUM(P13,P38,P88,P63) -> 24.010895 | R113: =IFERROR(K113/D113,"--") -> 0.37096891 | S113: =IFERROR(L113/E113,"--") -> 0.33128194 | T113: =IFERROR(M113/F113,"--") -> 0.37348426 | U113: =IFERROR(N113/G113,"--") -> 0.41063426 | V113: =IFERROR(O113/H113,"--") -> 0.3523065 | W113: =IFERROR(P113/I113,"--") -> 0.33986533 | Z113: =IFERROR(E113/D113-1,"--") -> -0.18786745 | AA113: =IFERROR(F113/E113-1,"--") -> -0.18457054 | AB113: =IFERROR(G113/F113-1,"--") -> 0.36431515 | AC113: =IFERROR(H113/G113-1,"--") -> 0.60138041 | AD113: =IFERROR(I113/H113-1,"--") -> -0.034214067
B114: =B113+1 -> 6 | C114: Customer F | D114: =SUM(D14,D39,D89,D64) -> 22.57575 | E114: =SUM(E14,E39,E89,E64) -> 19.248568 | F114: =SUM(F14,F39,F89,F64) -> 31.582775 | G114: =SUM(G14,G39,G89,G64) -> 38.866846 | H114: =SUM(H14,H39,H89,H64) -> 30.59786 | I114: =SUM(I14,I39,I89,I64) -> 28.771251 | K114: =SUM(K14,K39,K89,K64) -> 2.0239927 | L114: =SUM(L14,L39,L89,L64) -> 2.1839801 | M114: =SUM(M14,M39,M89,M64) -> 4.7858758 | N114: =SUM(N14,N39,N89,N64) -> 7.7410803 | O114: =SUM(O14,O39,O89,O64) -> 5.16886 | P114: =SUM(P14,P39,P89,P64) -> 5.1695834 | R114: =IFERROR(K114/D114,"--") -> 0.0896534 | S114: =IFERROR(L114/E114,"--") -> 0.11346195 | T114: =IFERROR(M114/F114,"--") -> 0.15153437 | U114: =IFERROR(N114/G114,"--") -> 0.19916924 | V114: =IFERROR(O114/H114,"--") -> 0.16892881 | W114: =IFERROR(P114/I114,"--") -> 0.17967878 | Z114: =IFERROR(E114/D114-1,"--") -> -0.14737857 | AA114: =IFERROR(F114/E114-1,"--") -> 0.64078568 | AB114: =IFERROR(G114/F114-1,"--") -> 0.23063429 | AC114: =IFERROR(H114/G114-1,"--") -> -0.21275166 | AD114: =IFERROR(I114/H114-1,"--") -> -0.059697273
B115: =B114+1 -> 7 | C115: Customer G | D115: =SUM(D15,D40,D90,D65) -> 36.815 | E115: =SUM(E15,E40,E90,E65) -> 29.713 | F115: =SUM(F15,F40,F90,F65) -> 27.455 | G115: =SUM(G15,G40,G90,G65) -> 31.179 | H115: =SUM(H15,H40,H90,H65) -> 29.807189 | I115: =SUM(I15,I40,I90,I65) -> 31.075137 | K115: =SUM(K15,K40,K90,K65) -> 6.7165 | L115: =SUM(L15,L40,L90,L65) -> 6.151 | M115: =SUM(M15,M40,M90,M65) -> 6.954 | N115: =SUM(N15,N40,N90,N65) -> 7.692008 | O115: =SUM(O15,O40,O90,O65) -> 7.8100655 | P115: =SUM(P15,P40,P90,P65) -> 8.0246764 | R115: =IFERROR(K115/D115,"--") -> 0.18243922 | S115: =IFERROR(L115/E115,"--") -> 0.20701377 | T115: =IFERROR(M115/F115,"--") -> 0.2532872 | U115: =IFERROR(N115/G115,"--") -> 0.24670477 | V115: =IFERROR(O115/H115,"--") -> 0.26201953 | W115: =IFERROR(P115/I115,"--") -> 0.25823463 | Z115: =IFERROR(E115/D115-1,"--") -> -0.1929105 | AA115: =IFERROR(F115/E115-1,"--") -> -0.075993673 | AB115: =IFERROR(G115/F115-1,"--") -> 0.13564014 | AC115: =IFERROR(H115/G115-1,"--") -> -0.043997911 | AD115: =IFERROR(I115/H115-1,"--") -> 0.042538319
...

Sheet SOFR
O2: Date | P2: 1-month Term SOFR | Q2: 3-month Term SOFR
N3: =YEAR(O3) -> 2025 | O3: 45952 | P3: 0.0421
N4: =YEAR(O4) -> 2025 | O4: 45930 | P4: 0.0424
N5: =YEAR(O5) -> 2025 | O5: 45898 | P5: 0.0434
N6: =YEAR(O6) -> 2025 | O6: 45869 | P6: 0.0439
N7: =YEAR(O7) -> 2025 | O7: 45838 | P7: 0.0445
N8: =YEAR(O8) -> 2025 | O8: 45807 | P8: 0.0435
N9: =YEAR(O9) -> 2025 | O9: 45777 | P9: 0.0441
B10: Secured Overnight Financing Rate (SOFR) Forward Curves | N10: =YEAR(O10) -> 2025 | O10: 45747 | P10: 0.0441
N11: =YEAR(O11) -> 2025 | O11: 45716 | P11: 0.0439 | T11: SOFR
N12: =YEAR(O12) -> 2025 | O12: 45688 | P12: 0.0438 | S12: 2025 | T12: =AVERAGEIFS(P$3:P$133,$N$3:$N$133,S12) -> 0.0423801
N13: =YEAR(O13) -> 2025 | O13: 45957 | P13: 0.0399119 | Q13: 0.038586 | S13: 2026 | T13: =AVERAGEIFS(P$13:P$133,$N$13:$N$133,S13) -> 0.032173925
N14: =YEAR(O14) -> 2025 | O14: 45989 | P14: 0.0382989 | Q14: 0.0371039 | S14: 2027 | T14: =AVERAGEIFS(P$13:P$133,$N$13:$N$133,S14) -> 0.029974125
N15: =YEAR(O15) -> 2025 | O15: 46020 | P15: 0.0370305 | Q15: 0.0359936 | S15: 2028 | T15: =AVERAGEIFS(P$13:P$133,$N$13:$N$133,S15) -> 0.031476808
N16: =YEAR(O16) -> 2026 | O16: 46049 | P16: 0.035639 | Q16: 0.0349637 | S16: 2029 | T16: =AVERAGEIFS(P$13:P$133,$N$13:$N$133,S16) -> 0.033048
N17: =YEAR(O17) -> 2026 | O17: 46080 | P17: 0.0350707 | Q17: 0.0342973
N18: =YEAR(O18) -> 2026 | O18: 46108 | P18: 0.0338977 | Q18: 0.0336159
N19: =YEAR(O19) -> 2026 | O19: 46139 | P19: 0.0337021 | Q19: 0.0329322 | S19: 2025 | T19: =S19+1 -> 2026 | U19: =T19+1 -> 2027 | V19: =U19+1 -> 2028 | W19: =V19+1 -> 2029
N20: =YEAR(O20) -> 2026 | O20: 46169 | P20: 0.0329941 | Q20: 0.0322792 | S20: {=TRANSPOSE(T12:T16)} -> 0.0423801 | T20: 0.032173925 | U20: 0.029974125 | V20: 0.031476808 | W20: 0.033048
N21: =YEAR(O21) -> 2026 | O21: 46202 | P21: 0.0317427 | Q21: 0.031616
N22: =YEAR(O22) -> 2026 | O22: 46230 | P22: 0.0317441 | Q22: 0.0311561
N23: =YEAR(O23) -> 2026 | O23: 46261 | P23: 0.0311817 | Q23: 0.0306469
N24: =YEAR(O24) -> 2026 | O24: 46293 | P24: 0.0302397 | Q24: 0.0302363
N25: =YEAR(O25) -> 2026 | O25: 46322 | P25: 0.030241 | Q25: 0.0300381
N26: =YEAR(O26) -> 2026 | O26: 46353 | P26: 0.0300044 | Q26: 0.0298313
N27: =YEAR(O27) -> 2026 | O27: 46384 | P27: 0.0296299 | Q27: 0.0296979
N28: =YEAR(O28) -> 2027 | O28: 46414 | P28: 0.0296287 | Q28: 0.0296946
N29: =YEAR(O29) -> 2027 | O29: 46444 | P29: 0.0296146 | Q29: 0.02971
N30: =YEAR(O30) -> 2027 | O30: 46475 | P30: 0.0296257 | Q30: 0.0297656
N31: =YEAR(O31) -> 2027 | O31: 46504 | P31: 0.0296808 | Q31: 0.029833
N32: =YEAR(O32) -> 2027 | O32: 46534 | P32: 0.0297575 | Q32: 0.0299207
... N34: =YEAR(O34) -> 2027 | O34: 46595 | P34: 0.0299396 | Q34: 0.0301324
B35: Latest curve as of 23 Oct 2025 | 16:00 EDT | N35: =YEAR(O35) -> 2027 | O35: 46626 | P35: 0.0300534 | Q35: 0.0302662
N36: =YEAR(O36) -> 2027 | O36: 46657 | P36: 0.0301771 | Q36: 0.0303913
B37: For the latest rates, please visit: | N37: =YEAR(O37) -> 2027 | O37: 46687 | P37: 0.0303211 | Q37: 0.0305303
B38: https://example.com/ | N38: =YEAR(O38) -> 2027 | O38: 46720 | P38: 0.0304594 | Q38: 0.0306797
N39: =YEAR(O39) -> 2027 | O39: 46748 | P39: 0.0305891 | Q39: 0.0308026
N40: =YEAR(O40) -> 2028 | O40: 46779 | P40: 0.030732 | Q40: 0.0309425
N41: =YEAR(O41) -> 2028 | O41: 46811 | P41: 0.030865 | Q41: 0.0310902
N42: =YEAR(O42) -> 2028 | O42: 46839 | P42: 0.0309975 | Q42: 0.031216
N43: =YEAR(O43) -> 2028 | O43: 46870 | P43: 0.0311433 | Q43: 0.0313515
N44: =YEAR(O44) -> 2028 | O44: 46903 | P44: 0.0312834 | Q44: 0.0315029
N45: =YEAR(O45) -> 2028 | O45: 46931 | P45: 0.0314046 | Q45: 0.0316281
N46: =YEAR(O46) -> 2028 | O46: 46961 | P46: 0.0315452 | Q46: 0.031762
N47: =YEAR(O47) -> 2028 | O47: 46993 | P47: 0.0316837 | Q47: 0.0319045
N48: =YEAR(O48) -> 2028 | O48: 47023 | P48: 0.031813 | Q48: 0.032034
N49: =YEAR(O49) -> 2028 | O49: 47053 | P49: 0.0319492 | Q49: 0.0321772
N50: =YEAR(O50) -> 2028 | O50: 47084 | P50: 0.0320816 | Q50: 0.0323058
... N133: =YEAR(O133) -> 2035 | O133: 49611 | P133: 0.0415298 | Q133: 0.0417693
