Workbook
Name Buyer_Diversification: WACC!$F$11
Name CapEx_Pct_Revenue: DCF!$J$16
Name Company_Name: 'Company0462-GAAP'!$F$8
Name Cost_of_Debt: WACC!$F$8
Name Cost_of_Preferred: WACC!$F$9
Name DA_Pct_Revenue: DCF!$J$15
Name Equity_Risk_Premium: WACC!$F$7
Name FCF_Decline_Rate: DCF!$T$21
Name Market_Correlation: WACC!$F$10
Name Min_Op_Margin: DCF!$J$13
Name Min_Rev_Growth: DCF!$J$10
Name Op_Margin_Change: DCF!$J$12
Name PrivCo_Discount: 'Company0462-GAAP'!$F$10
Name Rev_Growth_Decline: DCF!$J$9
Name Risk_Free_Rate: WACC!$F$6
Name Tax_Rate: 'Company0462-GAAP'!$F$7
Name Terminal_Growth_Rate: DCF!$J$21
Name Terminal_Multiple: DCF!$E$21
Name TV_Discount: DCF!$E$11
Name TV_Liquidation_Discount: DCF!$E$13
Name WACC: WACC!$L$35
Name WC_Pct_Change_in_Rev: DCF!$J$17

Sheet Company0462-Internal
B2: ="Sample Private Company Financial Statements - "&Company_Name
B3: ($ USD as Stated)
G5: Historical | L5: Projected
B6: Revenue and Expense Drivers: | F6: Units: | G6: Year 1 | H6: Year 2 | I6: Year 3 | J6: Year 4 | K6: Year 5 | L6: Year 6 | M6: Year 7 | N6: Year 8 | O6: Year 9 | P6: Year 10
C8: Course Sign-Ups: | F8: # Customers | G8: 1011 | H8: 2051 | I8: 2978 | J8: 4000 | K8: 4500 | L8: 4800 | M8: 5200 | N8: 5600 | O8: 6000 | P8: 6500
C9: Average Customer Value: | F9: $ / Customer | G9: =+G79/G8 | H9: =+H79/H8 | I9: =+I79/I8 | J9: =+J79/J8 | K9: =+K79/K8 | L9: 175 | M9: 190 | N9: 210 | O9: 225 | P9: 240
C11: Revenue Growth Rates:
C12: Product Sales Referred by Affiliates: | F12: % | G12: =IFERROR(+G80/F80-1,"N/A") | H12: =IFERROR(+H80/G80-1,"N/A") | I12: =IFERROR(+I80/H80-1,"N/A") | J12: =IFERROR(+J80/I80-1,"N/A") | K12: =IFERROR(+K80/J80-1,"N/A") | L12: 0.25 | M12: 0.2 | N12: 0.15 | O12: 0.1 | P12: 0.1
C13: Coaching & Resume Editing Services: | F13: % | G13: =IFERROR(+G81/F81-1,"N/A") | H13: =IFERROR(+H81/G81-1,"N/A") | I13: =IFERROR(+I81/H81-1,"N/A") | J13: =IFERROR(+J81/I81-1,"N/A") | K13: =IFERROR(+K81/J81-1,"N/A") | L13: 0.1 | M13: 0.1 | N13: 0.08 | O13: 0.08 | P13: 0.06
C14: Sales to Institutions: | F14: % | G14: =IFERROR(+G82/F82-1,"N/A") | H14: =IFERROR(+H82/G82-1,"N/A") | I14: =IFERROR(+I82/H82-1,"N/A") | J14: =IFERROR(+J82/I82-1,"N/A") | K14: =IFERROR(+K82/J82-1,"N/A") | L14: 0.4 | M14: 0.35 | N14: 0.3 | O14: 0.3 | P14: 0.25
C15: Commissions from Other Products: | F15: % | G15: =IFERROR(+G83/F83-1,"N/A") | H15: =IFERROR(+H83/G83-1,"N/A") | I15: =IFERROR(+I83/H83-1,"N/A") | J15: =IFERROR(+J83/I83-1,"N/A") | K15: =IFERROR(+K83/J83-1,"N/A") | L15: 0.15 | M15: 0.1 | N15: 0.1 | O15: 0.08 | P15: 0.08
C17: Expense Percentages:
C18: Commission Rate - Affiliates: | F18: % | G18: =IFERROR(-G87/G80,"N/A") | H18: =IFERROR(-H87/H80,"N/A") | I18: =IFERROR(-I87/I80,"N/A") | J18: =IFERROR(-J87/J80,"N/A") | K18: =IFERROR(-K87/K80,"N/A") | L18: 0.5 | M18: 0.5 | N18: 0.5 | O18: 0.5 | P18: 0.5
C19: Commission Rate - Coaches: | F19: % | G19: =IFERROR(-G88/G81,"N/A") | H19: =IFERROR(-H88/H81,"N/A") | I19: =IFERROR(-I88/I81,"N/A") | J19: =IFERROR(-J88/J81,"N/A") | K19: =IFERROR(-K88/K81,"N/A") | L19: 0.5 | M19: 0.5 | N19: 0.5 | O19: 0.5 | P19: 0.5
C20: Commission Rate - Sales Reps: | F20: % | G20: =IFERROR(-G89/G82,"N/A") | H20: =IFERROR(-H89/H82,"N/A") | I20: =IFERROR(-I89/I82,"N/A") | J20: =IFERROR(-J89/J82,"N/A") | K20: =IFERROR(-K89/K82,"N/A") | L20: 0.4 | M20: 0.4 | N20: 0.4 | O20: 0.4 | P20: 0.4
C22: Payment Fees % Gross Sales: | F22: % | G22: =IFERROR(-G95/G$84,"N/A") | H22: =IFERROR(-H95/H$84,"N/A") | I22: =IFERROR(-I95/I$84,"N/A") | J22: =IFERROR(-J95/J$84,"N/A") | K22: =IFERROR(-K95/K$84,"N/A") | L22: 0.028 | M22: 0.028 | N22: 0.029 | O22: 0.029 | P22: 0.03
C23: Refunds % Gross Sales: | F23: % | G23: =IFERROR(-G96/G$84,"N/A") | H23: =IFERROR(-H96/H$84,"N/A") | I23: =IFERROR(-I96/I$84,"N/A") | J23: =IFERROR(-J96/J$84,"N/A") | K23: =IFERROR(-K96/K$84,"N/A") | L23: 0.045 | M23: 0.045 | N23: 0.05 | O23: 0.05 | P23: 0.06
C25: Tax & Legal Fees % Gross Sales: | F25: % | G25: =IFERROR(-G102/G$84,"N/A") | H25: =IFERROR(-H102/H$84,"N/A") | I25: =IFERROR(-I102/I$84,"N/A") | J25: =IFERROR(-J102/J$84,"N/A") | K25: =IFERROR(-K102/K$84,"N/A") | L25: 0.002 | M25: 0.002 | N25: 0.003 | O25: 0.003 | P25: 0.003
C26: Online Advertising % Gross Sales: | F26: % | G26: =IFERROR(-G104/G$84,"N/A") | H26: =IFERROR(-H104/H$84,"N/A") | I26: =IFERROR(-I104/I$84,"N/A") | J26: =IFERROR(-J104/J$84,"N/A") | K26: =IFERROR(-K104/K$84,"N/A") | L26: 0.031 | M26: 0.033 | N26: 0.035 | O26: 0.035 | P26: 0.037
C27: IT Infrastructure % Gross Sales: | F27: % | G27: =IFERROR(-G108/G$84,"N/A") | H27: =IFERROR(-H108/H$84,"N/A") | I27: =IFERROR(-I108/I$84,"N/A") | J27: =IFERROR(-J108/J$84,"N/A") | K27: =IFERROR(-K108/K$84,"N/A") | L27: 0.022 | M27: 0.024 | N27: 0.024 | O27: 0.026 | P27: 0.026
C28: Travel & Moving % Gross Sales: | F28: % | G28: =IFERROR(-G109/G$84,"N/A") | H28: =IFERROR(-H109/H$84,"N/A") | I28: =IFERROR(-I109/I$84,"N/A") | J28: =IFERROR(-J109/J$84,"N/A") | K28: =IFERROR(-K109/K$84,"N/A") | L28: 0.007 | M28: 0.006 | N28: 0.005 | O28: 0.004 | P28: 0.004
C29: Depr. & Amort. % Gross Sales: | F29: % | G29: =IFERROR(-G110/G$84,"N/A") | H29: =IFERROR(-H110/H$84,"N/A") | I29: =IFERROR(-I110/I$84,"N/A") | J29: =IFERROR(-J110/J$84,"N/A") | K29: =IFERROR(-K110/K$84,"N/A") | L29: 0.002 | M29: 0.002 | N29: 0.003 | O29: 0.004 | P29: 0.004
C31: Effective Tax Rate: | F31: % | G31: =IFERROR(-G117/G115,"N/A") | H31: =IFERROR(-H117/H115,"N/A") | I31: =IFERROR(-I117/I115,"N/A") | J31: =IFERROR(-J117/J115,"N/A") | K31: =IFERROR(-K117/K115,"N/A") | L31: 0.3 | M31: 0.3 | N31: 0.3 | O31: 0.3 | P31: 0.3
C33: Full-Time Equivalents (FTEs):
C34: Customer Support: | F34: # FTEs | G34: 0 | H34: 0 | I34: 0.5 | J34: 0.75 | K34: 1 | L34: 1 | M34: 1.5 | N34: 1.5 | O34: 2 | P34: 2
C35: Web Design & Development: | F35: # FTEs | G35: 0 | H35: 0.5 | I35: 1 | J35: 1 | K35: 1 | L35: 1.5 | M35: 1.5 | N35: 2 | O35: 2 | P35: 2
C36: Sales Reps: | F36: # FTEs | G36: 0 | H36: 0.5 | I36: 0.5 | J36: 0.5 | K36: 0.5 | L36: 0.5 | M36: 1 | N36: 1 | O36: 1 | P36: 1
C37: Marketing Staff: | F37: # FTEs | G37: 0 | H37: 0 | I37: 0.5 | J37: 0.75 | K37: 1 | L37: 1 | M37: 1 | N37: 1 | O37: 1.25 | P37: 1.5
C38: Product Creation: | F38: # FTEs | G38: 0 | H38: 0 | I38: 0.5 | J38: 0.5 | K38: 1 | L38: 1 | M38: 1 | N38: 2 | O38: 2 | P38: 2
C39: Content Creation: | F39: # FTEs | G39: 0 | H39: 0 | I39: 0.5 | J39: 0.5 | K39: 0.5 | L39: 0.5 | M39: 0.75 | N39: 0.75 | O39: 1 | P39: 1
C40: Total FTEs: | G40: =SUM(G34:G39) | H40: =SUM(H34:H39) | I40: =SUM(I34:I39) | J40: =SUM(J34:J39) | K40: =SUM(K34:K39) | L40: =SUM(L34:L39) | M40: =SUM(M34:M39) | N40: =SUM(N34:N39) | ... P40: =SUM(P34:P39)
C42: Average Expense per FTE:
C43: =+C34 | F43: $ / FTE | G43: =IFERROR(-G103/G34,"N/A") | H43: =IFERROR(-H103/H34,"N/A") | I43: =IFERROR(-I103/I34,"N/A") | J43: =IFERROR(-J103/J34,"N/A") | K43: =IFERROR(-K103/K34,"N/A") | L43: =+K43*(1+L$50) | M43: =+L43*(1+M$50) | N43: =+M43*(1+N$50) | O43: =+N43*(1+O$50) | P43: =+O43*(1+P$50)
C44: =+C35 | F44: $ / FTE | G44: =IFERROR(-G105/G35,"N/A") | H44: =IFERROR(-H105/H35,"N/A") | I44: =IFERROR(-I105/I35,"N/A") | J44: =IFERROR(-J105/J35,"N/A") | K44: =IFERROR(-K105/K35,"N/A") | L44: =+K44*(1+L$50) | M44: =+L44*(1+M$50) | N44: =+M44*(1+N$50) | O44: =+N44*(1+O$50) | P44: =+O44*(1+P$50)
C45: =+C36 | F45: $ / FTE | G45: =IFERROR(-G106/G36,"N/A") | H45: =IFERROR(-H106/H36,"N/A") | I45: =IFERROR(-I106/I36,"N/A") | J45: =IFERROR(-J106/J36,"N/A") | K45: =IFERROR(-K106/K36,"N/A") | L45: =+K45*(1+L$50) | M45: =+L45*(1+M$50) | N45: =+M45*(1+N$50) | O45: =+N45*(1+O$50) | P45: =+O45*(1+P$50)
C46: =+C37 | F46: $ / FTE | G46: =IFERROR(-G107/G37,"N/A") | H46: =IFERROR(-H107/H37,"N/A") | I46: =IFERROR(-I107/I37,"N/A") | J46: =IFERROR(-J107/J37,"N/A") | K46: =IFERROR(-K107/K37,"N/A") | L46: =+K46*(1+L$50) | M46: =+L46*(1+M$50) | N46: =+M46*(1+N$50) | O46: =+N46*(1+O$50) | P46: =+O46*(1+P$50)
C47: =+C38 | F47: $ / FTE | G47: =IFERROR(-G111/G38,"N/A") | H47: =IFERROR(-H111/H38,"N/A") | I47: =IFERROR(-I111/I38,"N/A") | J47: =IFERROR(-J111/J38,"N/A") | K47: =IFERROR(-K111/K38,"N/A") | L47: =+K47*(1+L$50) | M47: =+L47*(1+M$50) | N47: =+M47*(1+N$50) | O47: =+N47*(1+O$50) | P47: =+O47*(1+P$50)
C48: =+C39 | F48: $ / FTE | G48: =IFERROR(-G112/G39,"N/A") | H48: =IFERROR(-H112/H39,"N/A") | I48: =IFERROR(-I112/I39,"N/A") | J48: =IFERROR(-J112/J39,"N/A") | K48: =IFERROR(-K112/K39,"N/A") | L48: =+K48*(1+L$50) | M48: =+L48*(1+M$50) | N48: =+M48*(1+N$50) | O48: =+N48*(1+O$50) | P48: =+O48*(1+P$50)
C50: Salary Growth Rate: | F50: % | L50: 0.04 | M50: 0.04 | N50: 0.04 | O50: 0.04 | P50: 0.04
G52: =+$G$5 | L52: =+$L$5
B53: BS and CFS Drivers: | F53: =+$F$6 | G53: =+$G$6 | H53: =+$H$6 | I53: =+$I$6 | J53: =+$J$6 | K53: =+$K$6 | L53: =+$L$6 | M53: =+$M$6 | N53: =+$N$6 | O53: =+$O$6 | P53: =+$P$6
C55: Accounts Receivable % Gross Sales: | F55: % | G55: =IFERROR(+G140/G84,"N/A") | H55: =IFERROR(+H140/H84,"N/A") | I55: =IFERROR(+I140/I84,"N/A") | J55: =IFERROR(+J140/J84,"N/A") | K55: =IFERROR(+K140/K84,"N/A") | L55: 0.012 | M55: 0.013 | N55: 0.014 | O55: 0.015 | P55: 0.016
C56: Accounts Payable % OpEx: | F56: % | G56: =IFERROR(-G152/G$113,"N/A") | H56: =IFERROR(-H152/H$113,"N/A") | I56: =IFERROR(-I152/I$113,"N/A") | J56: =IFERROR(-J152/J$113,"N/A") | K56: =IFERROR(-K152/K$113,"N/A") | L56: 0.022 | M56: 0.024 | N56: 0.024 | O56: 0.026 | P56: 0.026
C57: Accrued Expenses % OpEx: | F57: % | G57: =IFERROR(-G153/G$113,"N/A") | H57: =IFERROR(-H153/H$113,"N/A") | I57: =IFERROR(-I153/I$113,"N/A") | J57: =IFERROR(-J153/J$113,"N/A") | K57: =IFERROR(-K153/K$113,"N/A") | L57: 0.017 | M57: 0.017 | N57: 0.019 | O57: 0.019 | P57: 0.02
C58: Deferred Revenue % Gross Sales: | F58: % | G58: =IFERROR(+G157/G84,"N/A") | H58: =IFERROR(+H157/H84,"N/A") | I58: =IFERROR(+I157/I84,"N/A") | J58: =IFERROR(+J157/J84,"N/A") | K58: =IFERROR(+K157/K84,"N/A") | L58: 0.012 | M58: 0.014 | N58: 0.015 | O58: 0.017 | P58: 0.019
C60: CapEx % Revenue: | F60: % | G60: =IFERROR(-G181/G84,"N/A") | H60: =IFERROR(-H181/H84,"N/A") | I60: =IFERROR(-I181/I84,"N/A") | J60: =IFERROR(-J181/J84,"N/A") | K60: =IFERROR(-K181/K84,"N/A") | L60: 0.006 | M60: 0.007 | N60: 0.007 | O60: 0.008 | P60: 0.008
C61: Sales / (Purchases) of Other Assets: | F61: $ | G61: =+G182 | H61: =+H182 | I61: =+I182 | J61: =+J182 | K61: =+K182 | L61: -500 | M61: -600 | N61: -750 | O61: -900 | P61: -1100
C63: Change in Other Non-Current Liabilities: | F63: $ | G63: =+G186 | H63: =+H186 | I63: =+I186 | J63: =+J186 | K63: =+K186 | L63: 3500 | M63: 3800 | N63: 4100 | O63: 4400 | P63: 4700
C64: Owner Draw % Gross Sales: | F64: $ | G64: =-G187/G84 | H64: =-H187/H84 | I64: =-I187/I84 | J64: =-J187/J84 | K64: =-K187/K84 | L64: 0.2 | M64: =+L64 | N64: =+M64 | O64: =+N64 | P64: =+O64
C66: Dividends or Owner Draw: | F66: $ | G66: =-G187 | H66: =-H187 | I66: =-I187 | J66: =-J187 | K66: =-K187 | L66: =-L187 | M66: =-M187 | N66: =-N187 | ... P66: =-P187
C68: Owner Draw - G&A Allocation: | F68: % | G68: 0.25 | H68: 0.2 | I68: 0.15 | J68: 0.1 | K68: 0.1 | L68: 0.05 | M68: 0.05 | N68: 0.05 | O68: 0.05 | P68: 0.05
C69: Owner Draw - S&M Allocation: | F69: % | G69: 0.5 | H69: 0.5 | I69: 0.5 | J69: 0.55 | K69: 0.55 | L69: 0.6 | M69: 0.65 | N69: 0.65 | O69: 0.65 | P69: 0.65
C70: Owner Draw - R&D Allocation: | F70: % | G70: 0.25 | H70: 0.3 | I70: 0.35 | J70: 0.35 | K70: 0.35 | L70: 0.35 | M70: 0.3 | N70: 0.3 | O70: 0.3 | P70: 0.3
C72: Owner Draw - G&A Allocation: | F72: $ | G72: =+G$66*G68 | H72: =+H$66*H68 | I72: =+I$66*I68 | J72: =+J$66*J68 | K72: =+K$66*K68 | L72: =+L$66*L68 | M72: =+M$66*M68 | N72: =+N$66*N68 | ... P72: =+P$66*P68
C73: Owner Draw - S&M Allocation: | F73: $ | G73: =+G$66*G69 | H73: =+H$66*H69 | I73: =+I$66*I69 | J73: =+J$66*J69 | K73: =+K$66*K69 | L73: =+L$66*L69 | M73: =+M$66*M69 | N73: =+N$66*N69 | ... P73: =+P$66*P69
C74: Owner Draw - R&D Allocation: | F74: $ | G74: =+G$66*G70 | H74: =+H$66*H70 | I74: =+I$66*I70 | J74: =+J$66*J70 | K74: =+K$66*K70 | L74: =+L$66*L70 | M74: =+M$66*M70 | N74: =+N$66*N70 | ... P74: =+P$66*P70
G76: =+$G$5 | L76: =+$L$5
B77: Income Statement: | F77: =+$F$6 | G77: =+$G$6 | H77: =+$H$6 | I77: =+$I$6 | J77: =+$J$6 | K77: =+$K$6 | L77: =+$L$6 | M77: =+$M$6 | N77: =+$N$6 | O77: =+$O$6 | P77: =+$P$6
C78: Gross Sales by Category:
C79: (+) Online Courses: | F79: $ | G79: 108419.37 | H79: 263157.05 | I79: 433718.41 | J79: 583030.14 | K79: 734674.71 | L79: =+L8*L9 | M79: =+M8*M9 | N79: =+N8*N9 | O79: =+O8*O9 | P79: =+P8*P9
C80: (+) Product Sales Referred by Affiliates: | F80: $ | G80: 40391.53 | H80: 52631.41 | I80: 61087.1 | J80: 37859.1 | K80: 47706.15 | L80: =+K80*(1+L12) | M80: =+L80*(1+M12) | N80: =+M80*(1+N12) | O80: =+N80*(1+O12) | P80: =+O80*(1+P12)
C81: (+) Coaching & Resume Editing Services: | F81: $ | G81: 36139.79 | H81: 44534.27 | I81: 54978.39 | J81: 60574.56 | K81: 66788.61 | L81: =+K81*(1+L13) | M81: =+L81*(1+M13) | N81: =+M81*(1+N13) | O81: =+N81*(1+O13) | P81: =+O81*(1+P13)
C82: (+) Sales to Institutions: | F82: $ | G82: 8503.48 | H82: 20242.85 | I82: 30543.55 | J82: 53002.74 | K82: 76329.84 | L82: =+K82*(1+L14) | M82: =+L82*(1+M14) | N82: =+M82*(1+N14) | O82: =+N82*(1+O14) | P82: =+O82*(1+P14)
C83: (+) Commissions from Other Products: | F83: $ | G83: 19132.83 | H83: 24291.42 | I83: 30543.55 | J83: 22715.46 | K83: 28623.69 | L83: =+K83*(1+L15) | M83: =+L83*(1+M15) | N83: =+M83*(1+N15) | O83: =+N83*(1+O15) | P83: =+O83*(1+P15)
C84: Total Gross Sales: | F84: $ | G84: =SUM(G79:G83) | H84: =SUM(H79:H83) | I84: =SUM(I79:I83) | J84: =SUM(J79:J83) | K84: =SUM(K79:K83) | L84: =SUM(L79:L83) | M84: =SUM(M79:M83) | N84: =SUM(N79:N83) | ... P84: =SUM(P79:P83)
C86: Commissions by Category:
C87: (-) Commissions Paid to Affiliates: | F87: $ | G87: -20195.765 | H87: -26315.705 | I87: -30543.55 | J87: -18929.55 | K87: -23853.075 | L87: =-L80*L18 | M87: =-M80*M18 | N87: =-N80*N18 | O87: =-O80*O18 | P87: =-P80*P18
C88: (-) Commissions Paid to Coaches: | F88: $ | G88: -18069.895 | H88: -22267.135 | I88: -27489.195 | J88: -30287.28 | K88: -33394.305 | L88: =-L81*L19 | M88: =-M81*M19 | N88: =-N81*N19 | O88: =-O81*O19 | P88: =-P81*P19
C89: (-) Commissions Paid to Sales Reps: | F89: $ | G89: 0 | H89: -8097.14 | I89: -12217.42 | J89: -21201.096 | K89: -30531.936 | L89: =-L82*L20 | M89: =-M82*M20 | N89: =-N82*N20 | O89: =-O82*O20 | P89: =-P82*P20
C90: Total Commissions: | F90: $ | G90: =SUM(G87:G89) | H90: =SUM(H87:H89) | I90: =SUM(I87:I89) | J90: =SUM(J87:J89) | K90: =SUM(K87:K89) | L90: =SUM(L87:L89) | M90: =SUM(M87:M89) | N90: =SUM(N87:N89) | ... P90: =SUM(P87:P89)
C92: Gross Sales Less Commissions: | F92: $ | G92: =+G84+G90 | H92: =+H84+H90 | I92: =+I84+I90 | J92: =+J84+J90 | K92: =+K84+K90 | L92: =+L84+L90 | M92: =+M84+M90 | N92: =+N84+N90 | ... P92: =+P84+P90
C94: Fees & Refunds:
C95: (-) Payment Fees: | F95: $ | G95: -6165.023 | H95: -11335.996 | I95: -17104.388 | J95: -21201.096 | K95: -26715.444 | L95: =-L$84*L22 | M95: =-M$84*M22 | N95: =-N$84*N22 | O95: =-O$84*O22 | P95: =-P$84*P22
C96: (-) Refunds: | F96: $ | G96: -6377.61 | H96: -12550.567 | I96: -21380.485 | J96: -30287.28 | K96: -39119.043 | L96: =-L$84*L23 | M96: =-M$84*M23 | N96: =-N$84*N23 | O96: =-O$84*O23 | P96: =-P$84*P23
C97: Total Fees & Refunds: | F97: $ | G97: =SUM(G95:G96) | H97: =SUM(H95:H96) | I97: =SUM(I95:I96) | J97: =SUM(J95:J96) | K97: =SUM(K95:K96) | L97: =SUM(L95:L96) | M97: =SUM(M95:M96) | N97: =SUM(N95:N96) | ... P97: =SUM(P95:P96)
C99: Net Sales After Fees and Refunds: | F99: $ | G99: =+G92+G97 | H99: =+H92+H97 | I99: =+I92+I97 | J99: =+J92+J97 | K99: =+K92+K97 | L99: =+L92+L97 | M99: =+M92+M97 | N99: =+N92+N97 | ... P99: =+P92+P97
C101: Operating Expenses:
C102: (-) Tax, Bookkeeping & Legal Fees: | F102: $ | G102: -1250 | H102: -1500 | I102: -1500 | J102: -2000 | K102: -2250 | L102: =-L$84*L25 | M102: =-M$84*M25 | N102: =-N$84*N25 | O102: =-O$84*O25 | P102: =-P$84*P25
C103: (-) Customer Support: | F103: $ | G103: 0 | H103: -30000 | I103: -30000 | J103: -45000 | K103: -60000 | L103: =-L34*L43 | M103: =-M34*M43 | N103: =-N34*N43 | O103: =-O34*O43 | P103: =-P34*P43
C104: (-) Online Advertising: | F104: $ | G104: 0 | H104: -10000 | I104: -20000 | J104: -20000 | K104: -30000 | L104: =-L$84*L26 | M104: =-M$84*M26 | N104: =-N$84*N26 | O104: =-O$84*O26 | P104: =-P$84*P26
C105: (-) Web Design & Development: | F105: $ | G105: -10000 | H105: -30000 | I105: -60000 | J105: -60000 | K105: -60000 | L105: =-L35*L44 | M105: =-M35*M44 | N105: =-N35*N44 | O105: =-O35*O44 | P105: =-P35*P44
C106: (-) Sales Reps - Base Salaries: | F106: $ | G106: 0 | H106: -10000 | I106: -12000 | J106: -12000 | K106: -12000 | L106: =-L36*L45 | M106: =-M36*M45 | N106: =-N36*N45 | O106: =-O36*O45 | P106: =-P36*P45
C107: (-) Marketing Staff: | F107: $ | G107: 0 | H107: 0 | I107: -40000 | J107: -60000 | K107: -80000 | L107: =-L37*L46 | M107: =-M37*M46 | N107: =-N37*N46 | O107: =-O37*O46 | P107: =-P37*P46
C108: (-) IT Infrastructure: | F108: $ | G108: -2000 | H108: -5000 | I108: -10000 | J108: -15000 | K108: -20000 | L108: =-L$84*L27 | M108: =-M$84*M27 | N108: =-N$84*N27 | O108: =-O$84*O27 | P108: =-P$84*P27
C109: (-) Travel & Moving Expenses: | F109: $ | G109: -5768 | H109: -8798 | I109: -6012 | J109: -5123 | K109: -6763 | L109: =-L$84*L28 | M109: =-M$84*M28 | N109: =-N$84*N28 | O109: =-O$84*O28 | P109: =-P$84*P28
C110: (-) Depreciation & Amortization: | F110: $ | G110: -568 | H110: -792 | I110: -1011 | J110: -1523 | K110: -2024 | L110: =-L$84*L29 | M110: =-M$84*M29 | N110: =-N$84*N29 | O110: =-O$84*O29 | P110: =-P$84*P29
C111: (-) Product Creation: | F111: $ | G111: 0 | H111: 0 | I111: -40000 | J111: -40000 | K111: -80000 | L111: =-L38*L47 | M111: =-M38*M47 | N111: =-N38*N47 | O111: =-O38*O47 | P111: =-P38*P47
C112: (-) Content Creation: | F112: $ | G112: 0 | H112: 0 | I112: -30000 | J112: -30000 | K112: -30000 | L112: =-L39*L48 | M112: =-M39*M48 | N112: =-N39*N48 | O112: =-O39*O48 | P112: =-P39*P48
C113: Total Operating Expenses: | F113: $ | G113: =SUM(G102:G112) | H113: =SUM(H102:H112) | I113: =SUM(I102:I112) | J113: =SUM(J102:J112) | K113: =SUM(K102:K112) | L113: =SUM(L102:L112) | M113: =SUM(M102:M112) | N113: =SUM(N102:N112) | ... P113: =SUM(P102:P112)
C115: Operating Income: | F115: $ | G115: =+G99+G113 | H115: =+H99+H113 | I115: =+I99+I113 | J115: =+J99+J113 | K115: =+K99+K113 | L115: =+L99+L113 | M115: =+M99+M113 | N115: =+N99+N113 | ... P115: =+P99+P113
C117: (-) Income Taxes: | F117: $ | G117: -35548.177 | H117: -61614.123 | I117: -70451.629 | J117: -99942.612 | K117: -125241.66 | L117: =-L115*L31 | M117: =-M115*M31 | N117: =-N115*N31 | O117: =-O115*O31 | P117: =-P115*P31
C119: Net Income: | F119: $ | G119: =+G115+G117 | H119: =+H115+H117 | I119: =+I115+I117 | J119: =+J115+J117 | K119: =+K115+K117 | L119: =+L115+L117 | M119: =+M115+M117 | N119: =+N115+N117 | ... P119: =+P115+P117
G121: =+$G$5 | L121: =+$L$5
B122: Key Metrics and Ratios: | F122: =+$F$6 | G122: =+$G$6 | H122: =+$H$6 | I122: =+$I$6 | J122: =+$J$6 | K122: =+$K$6 | L122: =+$L$6 | M122: =+$M$6 | N122: =+$N$6 | O122: =+$O$6 | P122: =+$P$6
C124: (+) Operating Income: | F124: $ | G124: =+G115 | H124: =+H115 | I124: =+I115 | J124: =+J115 | K124: =+K115 | L124: =+L115 | M124: =+M115 | N124: =+N115 | ... P124: =+P115
C125: (+) Depreciation & Amortization: | F125: $ | G125: =-G110 | H125: =-H110 | I125: =-I110 | J125: =-J110 | K125: =-K110 | L125: =-L110 | M125: =-M110 | N125: =-N110 | ... P125: =-P110
C126: EBITDA: | F126: $ | G126: =SUM(G124:G125) | H126: =SUM(H124:H125) | I126: =SUM(I124:I125) | J126: =SUM(J124:J125) | K126: =SUM(K124:K125) | L126: =SUM(L124:L125) | M126: =SUM(M124:M125) | N126: =SUM(N124:N125) | ... P126: =SUM(P124:P125)
C128: Revenue Growth: | F128: % | G128: =IFERROR(+G84/F84-1,"N/A") | H128: =IFERROR(+H84/G84-1,"N/A") | I128: =IFERROR(+I84/H84-1,"N/A") | J128: =IFERROR(+J84/I84-1,"N/A") | K128: =IFERROR(+K84/J84-1,"N/A") | L128: =IFERROR(+L84/K84-1,"N/A") | M128: =IFERROR(+M84/L84-1,"N/A") | N128: =IFERROR(+N84/M84-1,"N/A") | ... P128: =IFERROR(+P84/O84-1,"N/A")
C129: Operating Margin: | F129: % | G129: =IFERROR(+G115/G84,"N/A") | H129: =IFERROR(+H115/H84,"N/A") | I129: =IFERROR(+I115/I84,"N/A") | J129: =IFERROR(+J115/J84,"N/A") | K129: =IFERROR(+K115/K84,"N/A") | L129: =IFERROR(+L115/L84,"N/A") | M129: =IFERROR(+M115/M84,"N/A") | N129: =IFERROR(+N115/N84,"N/A") | ... P129: =IFERROR(+P115/P84,"N/A")
C130: EBITDA Margin: | F130: % | G130: =IFERROR(+G126/G84,"N/A") | H130: =IFERROR(+H126/H84,"N/A") | I130: =IFERROR(+I126/I84,"N/A") | J130: =IFERROR(+J126/J84,"N/A") | K130: =IFERROR(+K126/K84,"N/A") | L130: =IFERROR(+L126/L84,"N/A") | M130: =IFERROR(+M126/M84,"N/A") | N130: =IFERROR(+N126/N84,"N/A") | ... P130: =IFERROR(+P126/P84,"N/A")
...

Sheet Company0462-GAAP
B2: ="Sample Private Company Financial Statements - "&Company_Name&" - U.S. GAAP / IFRS-Compliant"
B3: ($ USD as Stated)
B5: Assumptions:
C7: Potential Buyer's Tax Rate: | F7: 0.35
C8: Company Name: | F8: Capital Capable Media LLC
C10: Private Company Discount: | F10: 0.3
G12: Historical | L12: Projected
B13: Income Statement: | F13: Units: | G13: Year 1 | H13: Year 2 | I13: Year 3 | J13: Year 4 | K13: Year 5 | L13: Year 6 | M13: Year 7 | N13: Year 8 | O13: Year 9 | P13: Year 10
C15: Gross Sales: | F15: $
C16: (-) Allowances & Refunds: | F16: $
C17: Net Sales: | F17: $
C19: Operating Expenses:
C20: (+) General & Administrative: | F20: $
C21: (+) Sales & Marketing: | F21: $
C22: (+) Research & Development: | F22: $
C23: (+) Depreciation & Amortization: | F23: $
C24: Total Operating Expenses: | F24: $
C26: Operating Income: | F26: $
C27: (+) Net Interest Income / (-) Expense: | F27: $
C28: Pre-Tax Income: | F28: $
C30: Income Taxes: | F30: $
C32: Net Income: | F32: $
G34: =+$G$12 | L34: =+$L$12
B35: Key Metrics and Ratios: | F35: =+$F$13 | G35: =+$G$13 | H35: =+$H$13 | I35: =+$I$13 | J35: =+$J$13 | K35: =+$K$13 | L35: =+$L$13 | M35: =+$M$13 | N35: =+$N$13 | O35: =+$O$13 | P35: =+$P$13
C37: (+) Operating Income: | F37: $
C38: (+) Depreciation & Amortization: | F38: $
C39: EBITDA: | F39: $
C41: Revenue Growth: | F41: %
C42: Operating Margin: | F42: %
C43: EBITDA Margin: | F43: %
C44: Net Margin: | F44: %
C46: Effective Tax Rate: | F46: %
G48: =+$G$12 | L48: =+$L$12
B49: Balance Sheet: | F49: =+$F$13 | G49: =+$G$13 | H49: =+$H$13 | I49: =+$I$13 | J49: =+$J$13 | K49: =+$K$13 | L49: =+$L$13 | M49: =+$M$13 | N49: =+$N$13 | O49: =+$O$13 | P49: =+$P$13
B50: ASSETS:
C51: Current Assets:
C52: Cash & Cash Equivalents: | F52: $
C53: Accounts Receivable: | F53: $
C54: Total Current Assets: | F54: $
C56: Long-Term Assets:
C57: Plants, Property & Equipment: | F57: $
C58: Other Assets: | F58: $
C59: Total Long-Term Assets: | F59: $
C61: Total Assets: | F61: $
B63: LIABILITIES & EQUITY:
C64: Current Liabilities:
C65: Accounts Payable: | F65: $
C66: Accrued Expenses: | F66: $
C67: Total Current Liabilities: | F67: $
C69: Long-Term Liabilities:
C70: Deferred Revenue: | F70: $
C71: Other Non-Current Liabilities: | F71: $
C72: Total Long-Term Liabilities: | F72: $
C74: Total Liabilities: | F74: $
C76: Equity: | F76: $
C78: TOTAL LIABILITIES & EQUITY: | F78: $
C80: Balance Sheet Check:
G82: =+$G$12 | L82: =+$L$12
B83: Cash Flow Statement: | F83: =+$F$13 | G83: =+$G$13 | H83: =+$H$13 | I83: =+$I$13 | J83: =+$J$13 | K83: =+$K$13 | L83: =+$L$13 | M83: =+$M$13 | N83: =+$N$13 | O83: =+$O$13 | P83: =+$P$13
C84: CASH FLOWS FROM OPERATING ACTIVITIES:
C85: Net Income: | F85: $
C86: (+) Depreciation & Amortization: | F86: $
C87: (+/-) Change in Accounts Receivable: | F87: $
C88: (+/-) Change in Accounts Payable: | F88: $
C89: (+/-) Change in Accrued Expenses: | F89: $
C90: (+/-) Change in Deferred Revenue: | F90: $
C91: Cash Flow from Operations: | F91: $
C93: CASH FLOWS FROM INVESTING ACTIVITIES:
C94: (-) Capital Expenditures (CapEx): | F94: $
C95: (+) Sales / (-) Purchases of Other Assets: | F95: $
C96: Cash Flow from Investing: | F96: $
C98: CASH FLOW FROM FINANCING ACTIVITIES:
C99: (+/-) Change in Other Non-Current Liab.: | F99: $
C100: Cash Flow from Financing: | F100: $
C102: Net Change in Cash: | F102: $
C103: Beginning Cash Balance: | F103: $
C104: Ending Cash Balance: | F104: $

Sheet DCF
B2: ="Private Company DCF Analysis - "&Company_Name
B3: ($ USD as Stated)
B5: ="DCF Assumptions - "&Company_Name&":"
B7: Financial Assumptions for DCF: | G7: Operating Assumptions for Extended Projection Period:
B9: Discount Rate: | E9: =+WACC | G9: Annual Change in Revenue Growth: | J9: -0.02
G10: Minimum Revenue Growth: | J10: 0.04
B11: "Going Concern" Discount to Terminal Value: | E11: 0.25
G12: Annual Change in EBIT Margin: | J12: -0.005
B13: Discount to Liquidation Value Terminal Value: | E13: 0 | G13: Minimum EBIT Margin: | J13: 0.15
G15: Depreciation & Amortization % Revenue: | J15: 0.005
G16: CapEx % Revenue: | J16: 0.01
G17: Change in WC % Change in Revenue: | J17: 0.03
B19: Terminal Value - Multiples Method: | G19: Terminal Value - Perpetuity Growth Method: | L19: Terminal Value - Liquidation Value Method: | Q19: Terminal Value - "Cease Operations" Method:
B21: Baseline Terminal EBITDA Multiple: | E21: 5.6970458 | G21: Baseline Terminal FCF Growth Rate: | J21: 0.03 | L21: Final Projection Year Liquidation Value: | Q21: FCF Growth / (Decline) Rate: | T21: -0.1
B22: Baseline Terminal Value: | G22: Baseline Terminal Value: | L22: Cumulative FCF Beyond Final Year:
B23: Terminal Value After "Going Concern" Discount: | G23: Terminal Value After "Going Concern" Discount: | L23: Terminal Value Based on Asset Liquidation:
B24: Implied Terminal FCF Growth Rate: | G24: Implied Terminal EBITDA Multiple: | L24: Terminal Value After Discount:
B26: (+) PV of Terminal Value: | G26: =+$B$26 | L26: =+$B$26 | Q26: =+$B$26
B27: (+) Sum of PV of Free Cash Flows: | G27: =+$B$27 | L27: =+$B$27 | Q27: =+$B$27
B28: Implied Enterprise Value: | E28: =SUM(E26:E27) | G28: =+$B$28 | L28: =+$B$28 | Q28: =+$B$28
B30: % of Implied EV from Terminal Value: | G30: =+$B$30 | L30: =+$B$30 | Q30: =+$B$30
B32: (+) Cash & Cash-Equivalents: | G32: =+$B$32 | L32: =+$B$32 | Q32: =+$B$32
B33: (+) Equity Investments: | G33: =+$B$33 | L33: =+$B$33 | Q33: =+$B$33
B34: (+) Other Non-Core Assets, Net: | G34: =+$B$34 | L34: =+$B$34 | Q34: =+$B$34
B35: (-) Total Debt: | G35: =+$B$35 | L35: =+$B$35 | Q35: =+$B$35
B36: (-) Noncontrolling Interests: | G36: =+$B$36 | L36: =+$B$36 | Q36: =+$B$36
B37: Implied Equity Value: | G37: =+$B$37 | L37: =+$B$37 | Q37: =+$B$37
C39: Unlevered Free Cash Flow Projections:
B40: FCF Projections: | C40: =+'Company0462-GAAP'!L13 | D40: =+'Company0462-GAAP'!M13 | E40: =+'Company0462-GAAP'!N13 | F40: =+'Company0462-GAAP'!O13 | G40: =+'Company0462-GAAP'!P13 | H40: Year 11 | I40: Year 12 | J40: Year 13 | K40: Year 14 | L40: Year 15 | M40: Year 16 | N40: Year 17 | O40: Year 18 | P40: Year 19 | Q40: Year 20 | R40: Year 21 | S40: Year 22 | T40: Year 23 | U40: Year 24 | V40: Year 25
B42: Revenue:
B43: Growth Rate:
B45: Operating Income (EBIT):
B46: Operating Margin:
B48: (-) Taxes:
B50: NOPAT:
B52: (+) Depreciation & Amortization:
B53: (+/-) Change in WC:
B54: (-) CapEx:
B56: Unlevered FCF:
B57: Growth Rate:
B58: PV of FCF:
B60: Discount Period: | C60: 1
B61: Mid-Year:
B63: Sensitivity - Terminal FCF Growth Rate vs. Discount Rate and Implied Equity Value from DCF Analysis:
D65: Terminal FCF Growth Rate:
C66: =+$J$37 | D66: 0 | E66: =+D66+0.5% | F66: =+E66+0.5% | G66: =+F66+0.5% | H66: =+G66+0.5% | I66: =+H66+0.5% | J66: =+I66+0.5% | K66: =+J66+0.5% | L66: =+K66+0.5%
B67: Discount Rate (WACC): | C67: 0.13
C68: =+C67+0.5%
C69: =+C68+0.5%
C70: =+C69+0.5%
C71: 0.14844063
C72: 0.15
C73: =+C72+0.5%
C74: =+C73+0.5%
C75: =+C74+0.5%
B77: Sensitivity - Terminal EBITDA Multiple vs. Discount Rate and Implied Equity Value from DCF Analysis:
D79: Terminal EBITDA Multiple:
C80: =+$E$37 | D80: 4 | E80: =+D80+0.5 | F80: =+E80+0.5 | G80: =+F80+0.5 | H80: 5.6970458 | I80: 6 | J80: =+I80+0.5 | K80: =+J80+0.5 | L80: =+K80+0.5
B81: Discount Rate (WACC): | C81: =+C67
C82: =+C68
C83: =+C69
C84: =+C70
C85: =+C71
C86: =+C72
C87: =+C73
C88: =+C74
C89: =+C75
B91: Sensitivity - Discount to Liquidation Value vs. Discount Rate and Implied Equity Value from DCF Analysis:
D93: Discount to Liquidation Value Terminal Value:
C94: =+$O$37 | D94: 0 | E94: =+D94+5% | F94: =+E94+5% | G94: =+F94+5% | H94: =+G94+5% | I94: =+H94+5% | J94: =+I94+5% | K94: =+J94+5% | L94: =+K94+5%
B95: Discount Rate (WACC): | C95: =+C81
C96: =+C82
C97: =+C83
C98: =+C84
C99: =+C85
C100: =+C86
C101: =+C87
C102: =+C88
C103: =+C89
B105: Sensitivity - Annual FCF Growth Rate Past Year 15 vs. Discount Rate and Implied Equity Value from DCF Analysis:
D107: Annual FCF Growth Rate Past Year 15:
C108: =+$T$37 | D108: -0.4 | E108: =+D108+5% | F108: =+E108+5% | G108: =+F108+5% | H108: =+G108+5% | I108: =+H108+5% | J108: =+I108+5% | K108: =+J108+5% | L108: =+K108+5%
B109: Discount Rate (WACC): | C109: =+C95
C110: =+C96
C111: =+C97
C112: =+C98
C113: =+C99
C114: =+C100
C115: =+C101
C116: =+C102
C117: =+C103

Sheet WACC
B2: ="Private Company WACC Analysis - "&Company_Name
B3: =+'Company0462-GAAP'!$B$3
B5: Discount Rate Calculations - Assumptions
B6: Risk-Free Rate: | F6: 0.0205
B7: Equity Risk Premium: | F7: 0.07
B8: Pre-Tax Cost of Debt: | F8: =+Risk_Free_Rate+0.4%
B9: Cost of Preferred Stock: | F9: 0
B10: Market Correlation (R^2) for Education Companies: | F10: 0.1988
B11: Adjustment for Portfolio Diversification of Potential Buyer: | F11: 0.25
B13: Comparable Companies - Unlevered Beta Calculation
D14: Levered | G14: Preferred | I14: Equity | L14: Unlevered
B15: Name | C15: Ticker | D15: Beta | E15: Debt | F15: % Debt | G15: Stock | H15: % Preferred | I15: Value | J15: % Equity | K15: Tax Rate | L15: Beta
B16: =+'Public Comps'!B8 | C16: =+'Public Comps'!C8 | K16: 0.4
B17: =+'Public Comps'!B9 | C17: =+'Public Comps'!C9 | K17: 0.4
B18: =+'Public Comps'!B10 | C18: =+'Public Comps'!C10 | K18: 0.4
B19: =+'Public Comps'!B11 | C19: =+'Public Comps'!C11 | K19: 0.4
B20: =+'Public Comps'!B12 | C20: =+'Public Comps'!C12 | K20: 0.4
B21: =+'Public Comps'!B13 | C21: =+'Public Comps'!C13 | K21: 0.4
B23: Median:
B24: Median "Total" Unlevered Beta:
B26: =TEXT(Company_Name,"")&" - Levered Beta & WACC Calculation"
D27: Unlevered | G27: Preferred | I27: Equity | L27: Levered
C28: Ticker | D28: Beta | E28: Debt | F28: % Debt | G28: Stock | H28: % Preferred | I28: Value | J28: % Equity | K28: Tax Rate | L28: Beta
B29: "Optimal" Capital Structure: | C29: N/A
B31: Cost of Equity Based on Comparables and "Optimal" Capital Structure:
B35: WACC, "Optimal" Capital Structure:

Sheet Public Comps
B2: Comparable Public Companies - U.S.-Based, For-Profit Education Companies with Less Than $500 Million USD in LTM Revenue
B3: ($ USD in Millions Except Per Share Amounts in USD as Stated)
B5: Operating Statistics | E5: Capitalization
D6: Share | E6: Equity | G6: Preferred | H6: Enterprise | I6: Revenue | L6: EBITDA | O6: EBITDA Margin | R6: Net Income
B7: Company Name | C7: Ticker | D7: Price | E7: Value | F7: Debt | G7: Stock | H7: Value | I7: LTM | J7: Forward Year 1 | K7: Forward Year 2 | L7: =+$I$7 | M7: =+$J$7 | N7: =+$K$7 | O7: =+$I$7 | P7: =+$J$7 | Q7: =+$K$7 | R7: =+$I$7 | S7: =+$J$7 | T7: =+$K$7 | U7: Beta
B8: Nord Anglia Education Inc | C8: NYSE:Company1891 | D8: 19.69 | E8: 1924.6975 | F8: 522.4 | G8: 0 | H8: 2280.3975 | I8: 474.6 | J8: 542.5 | K8: 616.1 | L8: 127.4 | M8: 143.6 | N8: 169.6 | R8: 26.3925 | S8: 61.5825 | T8: 78.2 | U8: 0.32
B9: Company2600 Education Inc | C9: NASDAQ:Company2494 | D9: 62.14 | E9: 671.112 | F9: 118.75 | G9: 0 | H9: 627.582 | I9: 446.041 | J9: 431.62 | K9: 443.6 | L9: 102.377 | M9: 95.6 | N9: 104.3 | R9: 46.36 | S9: 36.828 | T9: 41.472 | U9: 1.55
B10: Capella Education Company | C10: NASDAQ:Company0593 | D10: 65.4 | E10: 800.496 | F10: 0 | G10: 0 | H10: 633.444 | I10: 421.967 | J10: 440.8 | K10: 463.93 | L10: 90.583 | M10: 95 | N10: 99.1 | R10: 37.943 | S10: 42.228 | T10: 46.512 | U10: 1.11
B11: American Public Education, Inc. | C11: NASDAQ:Company0117 | D11: 34.48 | E11: 595.1248 | F11: 0 | G11: 0 | H11: 474.2958 | I11: 348.72 | J11: 368.86 | K11: 385.2 | L11: 74.1 | M11: 75.3 | N11: 80.1 | R11: 37.7994 | S11: 40.9062 | T11: 43.4952 | U11: 1.15
B12: Lincoln Educational Services Corp | C12: NASDAQ:Company1557 | D12: 2.2 | E12: 52.91 | F12: 43.904 | G12: 0 | H12: 77.802 | I12: 330.249 | J12: 320 | K12: 339.06 | L12: -34.301 | M12: -45 | N12: -15.6 | R12: -75.39 | S12: -18.759 | T12: -3.367 | U12: 2.11
B13: National American University Holdings Inc | C13: NASDAQ:Company1849 | D13: 3.26 | E13: 82.0868 | F13: 12.303 | G13: 0 | H13: 74.6548 | I13: 127.753 | J13: 119.63 | K13: 124.21 | L13: 12.723 | M13: 11.1 | N13: 15.2 | R13: 3.468 | S13: 6.0432 | T13: 6.7986 | U13: 1.25
B15: Maximum
B16: 75th Percentile
B17: Median
B18: 25th Percentile
B19: Minimum
B21: Valuation Statistics | E21: Capitalization | I21: Enterprise Value / | L21: Enterprise Value /
D22: =+$D$6 | E22: =+$E$6 | G22: =+$G$6 | H22: =+$H$6 | I22: Revenue | L22: EBITDA | O22: Price / Earnings Multiple
B23: =+$B$7 | C23: =+$C$7 | D23: =+$D$7 | E23: =+$E$7 | F23: =+$F$7 | G23: =+$G$7 | H23: =+$H$7 | I23: =+$I$7 | J23: =+$J$7 | K23: =+$K$7 | L23: =+$I$7 | M23: =+$J$7 | N23: =+$K$7 | O23: =+$I$7 | P23: =+$J$7 | Q23: =+$K$7
B24: =+B8 | C24: =+C8
B25: =+B9 | C25: =+C9
B26: =+B10 | C26: =+C10
B27: =+B11 | C27: =+C11
B28: =+B12 | C28: =+C12
B29: =+B13 | C29: =+C13
B31: Maximum
B32: 75th Percentile
B33: Median
B34: 25th Percentile
B35: Minimum

Sheet ValSum
B2: ="Valuation Summary - "&Company_Name
B3: =+'Company0462-GAAP'!$B$3
B5: ="Valuation Statistics - "&TEXT(Company_Name,"") | C5: =TEXT(Company_Name,"")&" - Range of Valuation Multiples" | J5: =TEXT(Company_Name,"")&" - Range of Implied Equity Values"
D7: 75th | F7: 25th | H7: Applicable | I7: Private | K7: 25th | M7: 75th
C8: Maximum | D8: Percentile | E8: Median | F8: Percentile | G8: Minimum | H8: Company | I8: Company | J8: Minimum | K8: Percentile | L8: Median | M8: Percentile | N8: Maximum
B9: Methodology Name | C9: Multiple | D9: Multiple | E9: Multiple | F9: Multiple | G9: Multiple | H9: Figure | I9: Discount | J9: Multiple | K9: Multiple | L9: Multiple | M9: Multiple | N9: Multiple
B11: Public Company Comparables:
B12: LTM EV / Revenue:
B13: =TEXT('Public Comps'!$J$7,"yyyy-mm-dd")&" EV / Revenue:"
B14: =TEXT('Public Comps'!$K$7,"yyyy-mm-dd")&" EV / Revenue:"
B15: LTM EV / EBITDA:
B16: =TEXT('Public Comps'!$J$7,"yyyy-mm-dd")&" EV / EBITDA:"
B17: =TEXT('Public Comps'!$K$7,"yyyy-mm-dd")&" EV / EBITDA:"
B18: LTM Price / Earnings:
B19: =TEXT('Public Comps'!$J$7,"yyyy-mm-dd")&" Price / Earnings:"
B20: =TEXT('Public Comps'!$K$7,"yyyy-mm-dd")&" Price / Earnings:"
B22: Precedent Transactions:
B23: LTM EV / Revenue: | C23: 2.5 | D23: 1.7 | E23: 1.5 | F23: 1.4 | G23: 0.9
B24: LTM EV / EBITDA: | C24: 13.5 | D24: 12.1 | E24: 11.1 | F24: 10.1 | G24: 8
B26: Discounted Cash Flow Analysis:
B27: 13.5% - 15.5% Discount Rate, 2.0% - 4.0% Terminal FCF Growth Rate:
H29: Implied Enterprise Value or Equity Value at a Range of Multiples:
G31: Enterprise Value -->
G32: Enterprise Value -->
G33: Enterprise Value -->
G34: Enterprise Value -->
G35: Enterprise Value -->
G36: Enterprise Value -->
G38: Equity Value -->
G39: Equity Value -->
G40: Equity Value -->
G41: Equity Value -->
G42: Equity Value -->
G43: Equity Value -->
... G52: Equity Value -->

Sheet ValGraph
I25: Min | J25: 25th | K25: Median | L25: 75th | M25: Max | N25: Min Point | O25: 25th Point | P25: Median Point | Q25: 75th Point | R25: Max Point
B27: =+ValSum!B27
B29: =+ValSum!B24
B30: =+ValSum!B23
B32: =+ValSum!B20
B33: =+ValSum!B19
B34: =+ValSum!B18
B35: =+ValSum!B17
B36: =+ValSum!B16
B37: =+ValSum!B15
B38: =+ValSum!B14
B39: =+ValSum!B13
B40: =+ValSum!B12
