Workbook
Name AP: WORKCAP!$C$31:$G$31
Name AP_CHANGE: WORKCAP!$C$32:$G$32
Name AR: WORKCAP!$C$12:$G$12
Name AR_CHANGE: WORKCAP!$C$13:$G$13
Name ARdata: WORKCAP!$A$67:$G$78
Name ARMonths: WORKCAP!$A$67:$A$78
Name CAP_EXPEND: 'PROP & EQUIP'!$C$13:$G$13
Name Cash_Begin: #REF!
Name Cash_Begin: 'CASHFLOW-MOS'!#REF!
Name DEPRECIATION: 'PROP & EQUIP'!$C$34:$G$34
Name EARNINGS_BEFORE_INTEREST___TAXES: 'CASHFLOW-MOS'!#REF!
Name EARNINGS_BEFORE_INTEREST___TAXES: 'INCOME-MOS'!$B$27
Name EXTR_INC_EXCL_INT_INCOME: EXTRA!$C$21:$G$21
Name FUNDINGf14: #REF!
Name INC_TAX_CHANGE: WORKCAP!$C$38:$G$38
Name INC_TAX_LIAB: WORKCAP!$C$37:$G$37
Name INC_TAX_RATE: TAXES!$C$9:$G$9
Name INV: WORKCAP!$C$19:$G$19
Name INV_CHANGE: WORKCAP!$C$20:$G$20
Name investment: 'VAL-2'!$B$8
Name Name: REVENUE!$A$1
Name Name: REVENUE!$A$1
Name NET_EARNINGS: 'INCOME-MOS'!$B$35
Name NET_PL_EQUIP: 'PROP & EQUIP'!$C$53:$G$53
Name OTHER_CA: WORKCAP!$C$25:$G$25
Name OTHER_CA_CHANGE: WORKCAP!$C$26:$G$26
Name PE: 'VAL-2'!$B$7
Name Rate: 'VAL-2'!$B$6
Name TAXES: 'INCOME-MOS'!$B$33
Name TOT_EXTR_INC_EXP: EXTRA!$C$16:$G$16
Name TOTAL_COG: WORKCAP!$C$28:$G$28
Name WORK_CAP_CHANGE: WORKCAP!$C$40:$G$40

Sheet COMPS
A1: XYZ Company
A2: Peer Company Comparisons
E5: Select Best
B6: Company A | C6: Company B | D6: Company C | E6: Comparison | F6: Projections
A7: Ratios | F7: Year 1 | G7: Year 2 | H7: Year 3 | I7: Year 4 | J7: Year 5
A8: Accounts Receivable % of Rev | B8: 0.098 | C8: 0.074 | D8: 0.116 | E8: 0.1 | F8: =WORKCAP!C10 -> 0.083 | G8: =WORKCAP!D10 -> 0.083 | H8: =WORKCAP!E10 -> 0.083 | I8: =WORKCAP!F10 -> 0.083 | J8: =WORKCAP!G10 -> 0.083
A9: Inventory % of Rev | B9: 0.135 | C9: 0.112 | D9: 0.169 | E9: 0.15 | F9: =WORKCAP!C16 -> 0.083 | G9: =WORKCAP!D16 -> 0.083 | H9: =WORKCAP!E16 -> 0.067 | I9: =WORKCAP!F16 -> 0.067 | J9: =WORKCAP!G16 -> 0.067
A10: Accounts Payable % of Rev | B10: 0.079 | C10: 0.086 | D10: 0.094 | E10: 0.08 | F10: =WORKCAP!C29 -> 0.087 | G10: =WORKCAP!D29 -> 0.087 | H10: =WORKCAP!E29 -> 0.087 | I10: =WORKCAP!F29 -> 0.087 | J10: =WORKCAP!G29 -> 0.087
A11: Working Capital % of Rev | B11: 0.154 | C11: 0.123 | D11: 0.187 | E11: 0.16 | F11: =WORKCAP!C10+WORKCAP!C16+WORKCAP!C23-WORKCAP!C29-WORKCAP!C35 -> 0.079 | G11: =WORKCAP!D10+WORKCAP!D16+WORKCAP!D23-WORKCAP!D29-WORKCAP!D35 -> 0.079 | H11: =WORKCAP!E10+WORKCAP!E16+WORKCAP!E23-WORKCAP!E29-WORKCAP!E35 -> 0.063 | I11: =WORKCAP!F10+WORKCAP!F16+WORKCAP!F23-WORKCAP!F29-WORKCAP!F35 -> 0.063 | J11: =WORKCAP!G10+WORKCAP!G16+WORKCAP!G23-WORKCAP!G29-WORKCAP!G35 -> 0.063
A12: Net Fixed Assets % of Rev | B12: 0.087 | C12: 0.095 | D12: 0.108 | E12: 0.09 | F12: ='PROP & EQUIP'!C54 -> 0.088862338 | G12: ='PROP & EQUIP'!D54 -> 0.15725818 | H12: ='PROP & EQUIP'!E54 -> 0.15396402 | I12: ='PROP & EQUIP'!F54 -> 0.14838025 | J12: ='PROP & EQUIP'!G54 -> 0.11863822
A13: Current Ratio | B13: 2.1 | C13: 3.2 | D13: 1.9 | E13: 2.3 | F13: =BALANCE!C13/BALANCE!C23 -> 3.8692769 | G13: =BALANCE!D13/BALANCE!D23 -> 4.0806633 | H13: =BALANCE!E13/BALANCE!E23 -> 2.6366848 | I13: =BALANCE!F13/BALANCE!F23 -> 3.8422343 | J13: =BALANCE!G13/BALANCE!G23 -> 4.0882108
A14: Debt to Capital (LT Debt + Equity) | B14: 1.25 | C14: 1.08 | D14: 1.36 | E14: 1.2 | F14: =(BALANCE!C22+BALANCE!C25)/(BALANCE!C22+BALANCE!C25+BALANCE!C31) -> 0.67143449 | G14: =(BALANCE!D22+BALANCE!D25)/(BALANCE!D22+BALANCE!D25+BALANCE!D31) -> 0.57204498 | H14: =(BALANCE!E22+BALANCE!E25)/(BALANCE!E22+BALANCE!E25+BALANCE!E31) -> 0.50297904 | I14: =(BALANCE!F22+BALANCE!F25)/(BALANCE!F22+BALANCE!F25+BALANCE!F31) -> 0.33323967 | J14: =(BALANCE!G22+BALANCE!G25)/(BALANCE!G22+BALANCE!G25+BALANCE!G31) -> 0.20151079
A16: Profitability
A17: Gross Profit % of Rev | B17: 0.317 | C17: 0.462 | D17: 0.541 | E17: 0.3 | F17: =INCOME!C13 -> 0.51798961 | G17: =INCOME!D13 -> 0.50104167 | H17: =INCOME!E13 -> 0.58064101 | I17: =INCOME!F13 -> 0.61641626 | J17: =INCOME!G13 -> 0.66470002
A18: Sales & Marketing % of Rev | B18: 0.294 | C18: 0.246 | D18: 0.213 | E18: 0.294 | F18: ='OPER EXP'!C17 -> 0.23981818 | G18: ='OPER EXP'!D17 -> 0.21598958 | H18: ='OPER EXP'!E17 -> 0.18700417 | I18: ='OPER EXP'!F17 -> 0.17463054 | J18: ='OPER EXP'!G17 -> 0.15778878
A19: Research & Development % of Rev | B19: 0.281 | C19: 0.148 | D19: 0.112 | E19: 0.281 | F19: ='OPER EXP'!C26 -> 0.10454545 | G19: ='OPER EXP'!D26 -> 0.14621094 | H19: ='OPER EXP'!E26 -> 0.12905922 | I19: ='OPER EXP'!F26 -> 0.11933498 | J19: ='OPER EXP'!G26 -> 0.10023102
A20: General & Administration % of Rev | B20: 0.307 | C20: 0.195 | D20: 0.146 | E20: 0.3 | F20: ='OPER EXP'!C39 -> 0.22545455 | G20: ='OPER EXP'!D39 -> 0.22641927 | H20: ='OPER EXP'!E39 -> 0.17651209 | I20: ='OPER EXP'!F39 -> 0.16178161 | J20: ='OPER EXP'!G39 -> 0.13134213
A21: Operating Expenses % of Rev | B21: 0.405 | C21: 0.342 | D21: 0.316 | E21: 0.17 | F21: ='OPER EXP'!C42 -> 0.56981818 | G21: ='OPER EXP'!D42 -> 0.58861979 | H21: ='OPER EXP'!E42 -> 0.49257548 | I21: ='OPER EXP'!F42 -> 0.45574713 | J21: ='OPER EXP'!G42 -> 0.38936194
A22: Earnings from Operations % of Rev | B22: 0.112 | C22: 0.161 | D22: 0.225 | E22: 0.12 | F22: =INCOME!C22/INCOME!C7 -> -0.051828571 | G22: =INCOME!D22/INCOME!D7 -> -0.087578125 | H22: =INCOME!E22/INCOME!E7 -> 0.088065531 | I22: =INCOME!F22/INCOME!F7 -> 0.16066913 | J22: =INCOME!G22/INCOME!G7 -> 0.27533809
A23: EBIT % of Rev | B23: 0.112 | C23: 0.161 | D23: 0.225 | E23: 0.12 | F23: =INCOME!C26/INCOME!C7 -> -0.095464935 | G23: =INCOME!D26/INCOME!D7 -> -0.057630208 | H23: =INCOME!E26/INCOME!E7 -> 0.11809055 | I23: =INCOME!F26/INCOME!F7 -> 0.19268883 | J23: =INCOME!G26/INCOME!G7 -> 0.30256581
A24: Depreciation % of Rev | B24: 0.028 | C24: 0.037 | D24: 0.049 | E24: 0.03 | F24: ='PROP & EQUIP'!C48 -> 0.01641039 | G24: ='PROP & EQUIP'!D48 -> 0.034765625 | H24: ='PROP & EQUIP'!E48 -> 0.041844394 | I24: ='PROP & EQUIP'!F48 -> 0.047188013 | J24: ='PROP & EQUIP'!G48 -> 0.042652837
A25: EBITDA % of Rev | B25: 0.14 | C25: 0.198 | D25: 0.274 | E25: 0.14 | F25: =(INCOME!C26+'PROP & EQUIP'!C47)/INCOME!C7 -> -0.079054545 | G25: =(INCOME!D26+'PROP & EQUIP'!D47)/INCOME!D7 -> -0.022864583 | H25: =(INCOME!E26+'PROP & EQUIP'!E47)/INCOME!E7 -> 0.15993495 | I25: =(INCOME!F26+'PROP & EQUIP'!F47)/INCOME!F7 -> 0.23987685 | J25: =(INCOME!G26+'PROP & EQUIP'!G47)/INCOME!G7 -> 0.34521865
A26: Net Earnings % of Rev | B26: 0.051 | C26: 0.096 | D26: 0.143 | E26: 0.05 | F26: =INCOME!C35 -> -0.17331948 | G26: =INCOME!D35 -> -0.10848958 | H26: =INCOME!E35 -> 0.081460026 | I26: =INCOME!F35 -> 0.12639536 | J26: =INCOME!G35 -> 0.17722265
A28: Returns
A29: Return on Assets | B29: 0.115 | C29: 0.158 | D29: 0.179 | E29: 0.12 | F29: =INCOME!C34/BALANCE!C15 -> -0.11010034 | G29: =INCOME!D34/BALANCE!D15 -> -0.089126571 | H29: =INCOME!E34/BALANCE!E15 -> 0.09116777 | I29: =INCOME!F34/BALANCE!F15 -> 0.1750194 | J29: =INCOME!G34/BALANCE!G15 -> 0.27986049
A30: Return on Equity | B30: 0.144 | C30: 0.196 | D30: 0.247 | E30: 0.15 | F30: =INCOME!C34/BALANCE!C31 -> -0.3896025 | G30: =INCOME!D34/BALANCE!D31 -> -0.23447023 | H30: =INCOME!E34/BALANCE!E31 -> 0.23533668 | I30: =INCOME!F34/BALANCE!F31 -> 0.29736167 | J30: =INCOME!G34/BALANCE!G31 -> 0.40152939
A31: Return on Capital (LT Debt + Equity) | B31: 0.148 | C31: 0.183 | D31: 0.219 | E31: 0.15 | F31: =INCOME!C34/(BALANCE!C22+BALANCE!C25+BALANCE!C31) -> -0.12800994 | G31: =INCOME!D34/(BALANCE!D22+BALANCE!D25+BALANCE!D31) -> -0.10034271 | H31: =INCOME!E34/(BALANCE!E22+BALANCE!E25+BALANCE!E31) -> 0.11696726 | I31: =INCOME!F34/(BALANCE!F22+BALANCE!F25+BALANCE!F31) -> 0.19826896 | J31: =INCOME!G34/(BALANCE!G22+BALANCE!G25+BALANCE!G31) -> 0.32061689
A33: Growth
A34: Revenue Growth Rate - CAGR: | B34: 0.142 | C34: 0.195 | D34: 0.248 | E34: 0.15 | G34: =INCOME!D7/INCOME!C7-1 -> 0.39636364 | H34: =INCOME!E7/INCOME!D7-1 -> 0.56119792 | I34: =INCOME!F7/INCOME!E7-1 -> 0.35446205 | J34: =(INCOME!G7/INCOME!F7-1) -> 0.49261084
A35: Net Earnings Growth Rate - CAGR: | B35: 0.116 | C35: 0.179 | D35: 0.215 | E35: 0.12 | G35: =IF((INCOME!D34/INCOME!C34-1)>0,(INCOME!D34/INCOME!C34-1),"Negative") -> Negative | H35: =IF((INCOME!E34/INCOME!D34-1)>0,(INCOME!E34/INCOME!D34-1),"Negative") -> Negative | I35: =IF((INCOME!F34/INCOME!E34-1)>0,(INCOME!F34/INCOME!E34-1),"Negative") -> 1.1016162 | J35: =IF((INCOME!G34/INCOME!F34-1)>0,(INCOME!G34/INCOME!F34-1),"Negative") -> 1.0928337

Sheet REVENUE
A1: XYZ Company | M1: checksum | N1: =SUM(C16:G16,C38:G38,C41:G42,'COST OF REV'!C32:G33,'COST OF REV'!C38:G38,'COST OF REV'!C59:G59,'OPER EXP'!C16:G17,'OPER EXP'!C25:G26,'OPER EXP'!C38:G39,'OPER EXP'!C41:G42,'OPER EXP'!C47:G47,'OPER EXP'!C69:G69,'OPER EXP'!C91:G91,'OPER EXP'!C113:G113) -> 1.7619413e+08
A2: Revenue Projections
A3: Years 1 to 5
A4: ($)
C5: Year 1 | D5: Year 2 | E5: Year 3 | F5: Year 4 | G5: Year 5
A6: Product A
A7: Number of Units | C7: 9000 | D7: 12000 | E7: 17000 | F7: 22000 | G7: 30000
A8: Price per unit | C8: 250 | D8: 250 | E8: 275 | F8: 275 | G8: 300
A9: Total | C9: =C7*C8 -> 2250000 | D9: =D7*D8 -> 3000000 | E9: =E7*E8 -> 4675000 | F9: =F7*F8 -> 6050000 | G9: =G7*G8 -> 9000000
A10: Service B
A11: Number of Customers | C11: 500 | D11: 800 | E11: 1200 | F11: 1800 | G11: 2600
A12: Fee per Customer | C12: 1000 | D12: 1050 | E12: 1100 | F12: 1150 | G12: 1200
A13: Total | C13: =C11*C12 -> 500000 | D13: =D11*D12 -> 840000 | E13: =E11*E12 -> 1320000 | F13: =F11*F12 -> 2070000 | G13: =G11*G12 -> 3120000
A16: Net Revenue | C16: =C9+C13 -> 2750000 | D16: =D9+D13 -> 3840000 | E16: =E9+E13 -> 5995000 | F16: =F9+F13 -> 8120000 | G16: =G9+G13 -> 12120000
D19: Revenues by Months & Quarters
D20: ($)
A21: Months | C21: Year 1 | D21: Year 2 | E21: Year 3 | F21: Year 4 | G21: Year 5
A22: Month 1 | C22: 0 | D22: =D$16/12 -> 320000 | E22: =E$16/12 -> 499583.33 | F22: =F$16/12 -> 676666.67 | G22: =G$16/12 -> 1010000
A23: Month 2 | C23: 0 | D23: =D$16/12 -> 320000 | E23: =E$16/12 -> 499583.33 | F23: =F$16/12 -> 676666.67 | G23: =G$16/12 -> 1010000
A24: Month 3 | C24: 0 | D24: =D$16/12 -> 320000 | E24: =E$16/12 -> 499583.33 | F24: =F$16/12 -> 676666.67 | G24: =G$16/12 -> 1010000
A25: Total 1st Quarter | C25: =SUM(C22:C24) -> 0 | D25: =SUM(D22:D24) -> 960000 | E25: =SUM(E22:E24) -> 1498750 | F25: =SUM(F22:F24) -> 2030000 | G25: =SUM(G22:G24) -> 3030000
A26: Month 4 | C26: =C$16/9 -> 305555.56 | D26: =D$16/12 -> 320000 | E26: =E$16/12 -> 499583.33 | F26: =F$16/12 -> 676666.67 | G26: =G$16/12 -> 1010000
A27: Month 5 | C27: =C$16/9 -> 305555.56 | D27: =D$16/12 -> 320000 | E27: =E$16/12 -> 499583.33 | F27: =F$16/12 -> 676666.67 | G27: =G$16/12 -> 1010000
A28: Month 6 | C28: =C$16/9 -> 305555.56 | D28: =D$16/12 -> 320000 | E28: =E$16/12 -> 499583.33 | F28: =F$16/12 -> 676666.67 | G28: =G$16/12 -> 1010000
A29: Total 2nd Quarter | C29: =SUM(C26:C28) -> 916666.67 | D29: =SUM(D26:D28) -> 960000 | E29: =SUM(E26:E28) -> 1498750 | F29: =SUM(F26:F28) -> 2030000 | G29: =SUM(G26:G28) -> 3030000
A30: Month 7 | C30: =C$16/9 -> 305555.56 | D30: =D$16/12 -> 320000 | E30: =E$16/12 -> 499583.33 | F30: =F$16/12 -> 676666.67 | G30: =G$16/12 -> 1010000
A31: Month 8 | C31: =C$16/9 -> 305555.56 | D31: =D$16/12 -> 320000 | E31: =E$16/12 -> 499583.33 | F31: =F$16/12 -> 676666.67 | G31: =G$16/12 -> 1010000
A32: Month 9 | C32: =C$16/9 -> 305555.56 | D32: =D$16/12 -> 320000 | E32: =E$16/12 -> 499583.33 | F32: =F$16/12 -> 676666.67 | G32: =G$16/12 -> 1010000
A33: Total 3rd Quarter | C33: =SUM(C30:C32) -> 916666.67 | D33: =SUM(D30:D32) -> 960000 | E33: =SUM(E30:E32) -> 1498750 | F33: =SUM(F30:F32) -> 2030000 | G33: =SUM(G30:G32) -> 3030000
A34: Month 10 | C34: =C$16/9 -> 305555.56 | D34: =D$16/12 -> 320000 | E34: =E$16/12 -> 499583.33 | F34: =F$16/12 -> 676666.67 | G34: =G$16/12 -> 1010000
A35: Month 11 | C35: =C$16/9 -> 305555.56 | D35: =D$16/12 -> 320000 | E35: =E$16/12 -> 499583.33 | F35: =F$16/12 -> 676666.67 | G35: =G$16/12 -> 1010000
A36: Month 12 | C36: =C$16/9 -> 305555.56 | D36: =D$16/12 -> 320000 | E36: =E$16/12 -> 499583.33 | F36: =F$16/12 -> 676666.67 | G36: =G$16/12 -> 1010000
A37: Total 4th Quarter | C37: =SUM(C34:C36) -> 916666.67 | D37: =SUM(D34:D36) -> 960000 | E37: =SUM(E34:E36) -> 1498750 | F37: =SUM(F34:F36) -> 2030000 | G37: =SUM(G34:G36) -> 3030000
A38: Total for year | C38: =C25+C29+C33+C37 -> 2750000 | D38: =D25+D29+D33+D37 -> 3840000 | E38: =E25+E29+E33+E37 -> 5995000 | F38: =F25+F29+F33+F37 -> 8120000 | G38: =G25+G29+G33+G37 -> 12120000
A40: Average Revenue
A41: by Month | C41: =C16/12 -> 229166.67 | D41: =D16/12 -> 320000 | E41: =E16/12 -> 499583.33 | F41: =F16/12 -> 676666.67 | G41: =G16/12 -> 1010000
A42: by Quarter | C42: =C16/4 -> 687500 | D42: =D16/4 -> 960000 | E42: =E16/4 -> 1498750 | F42: =F16/4 -> 2030000 | G42: =G16/4 -> 3030000

Sheet COST OF REV
A1: XYZ Company
A2: Cost of Revenues
A3: Years 1 to 5
A4: ($)
C5: Year 1 | D5: Year 2 | E5: Year 3 | F5: Year 4 | G5: Year 5
A7: Revenue | C7: =REVENUE!C16 -> 2750000 | D7: =REVENUE!D16 -> 3840000 | E7: =REVENUE!E16 -> 5995000 | F7: =REVENUE!F16 -> 8120000 | G7: =REVENUE!G16 -> 12120000
A9: Cost of Revenue
A11: Product A
A12: Material Costs per Unit | C12: 18.7 | D12: 18.2 | E12: 17.5 | F12: 16.8 | G12: 16.2
A13: Subcontract Costs per Unit | C13: 12.4 | D13: 11.8 | E13: 11.2 | F13: 10.7 | G13: 10.2
A14: Total Direct Costs per Unit | C14: =SUM(C12:C13) -> 31.1 | D14: =SUM(D12:D13) -> 30 | E14: =SUM(E12:E13) -> 28.7 | F14: =SUM(F12:F13) -> 27.5 | G14: =SUM(G12:G13) -> 26.4
A15: Unit Sales | C15: =REVENUE!C7 -> 9000 | D15: =REVENUE!D7 -> 12000 | E15: =REVENUE!E7 -> 17000 | F15: =REVENUE!F7 -> 22000 | G15: =REVENUE!G7 -> 30000
A16: Total Direct Costs | C16: =C14*C15 -> 279900 | D16: =D14*D15 -> 360000 | E16: =E14*E15 -> 487900 | F16: =F14*F15 -> 605000 | G16: =G14*G15 -> 792000
A17: Labor Costs | C17: =PERSONNEL!C65 -> 66000 | D17: =PERSONNEL!D65 -> 227700 | E17: =PERSONNEL!E65 -> 358800 | F17: =PERSONNEL!F65 -> 489600 | G17: =PERSONNEL!G65 -> 600000
A18: Total Direct Costs | C18: =C16+C17 -> 345900 | D18: =D16+D17 -> 587700 | E18: =E16+E17 -> 846700 | F18: =F16+F17 -> 1094600 | G18: =G16+G17 -> 1392000
A20: Service B
A21: Service Personnel Costs | C21: =PERSONNEL!C73 -> 115500 | D21: =PERSONNEL!D73 -> 212750 | E21: =PERSONNEL!E73 -> 336000 | F21: =PERSONNEL!F73 -> 480000 | G21: =PERSONNEL!G73 -> 825000
A23: Other Expenses
A24: Salary Expenses | C24: =PERSONNEL!C57 -> 181500 | D24: =PERSONNEL!D57 -> 290950 | E24: =PERSONNEL!E57 -> 325200 | F24: =PERSONNEL!F57 -> 346800 | G24: =PERSONNEL!G57 -> 383750
A25: Depreciation | C25: ='PROP & EQUIP'!C34+'PROP & EQUIP'!C44 -> 37628.571 | D25: ='PROP & EQUIP'!D34+'PROP & EQUIP'!D44 -> 91000 | E25: ='PROP & EQUIP'!E34+'PROP & EQUIP'!E44 -> 138357.14 | F25: ='PROP & EQUIP'!F34+'PROP & EQUIP'!F44 -> 191500 | G25: ='PROP & EQUIP'!G34+'PROP & EQUIP'!G44 -> 245285.71
A26: Facility costs (rent, energy) | C26: 325000 | D26: 345000 | E26: 368000 | F26: 392000 | G26: 418000
A27: System Costs | C27: 210000 | D27: 235000 | E27: 260000 | F27: 285000 | G27: 315000
A31: All other costs % of Revenue | B31: 0.04 | C31: =$B31*C7 -> 110000 | D31: =$B31*D7 -> 153600 | E31: =$B31*E7 -> 239800 | F31: =$B31*F7 -> 324800 | G31: =$B31*G7 -> 484800
A32: Total Cost of Revenues | C32: =C18+C21+C24+C25+C26+C27+C31 -> 1325528.6 | D32: =D18+D21+D24+D25+D26+D27+D31 -> 1916000 | E32: =E18+E21+E24+E25+E26+E27+E31 -> 2514057.1 | F32: =F18+F21+F24+F25+F26+F27+F31 -> 3114700 | G32: =G18+G21+G24+G25+G26+G27+G31 -> 4063835.7
A33: % of Revenue | C33: =C32/C7 -> 0.48201039 | D33: =D32/D7 -> 0.49895833 | E33: =E32/E7 -> 0.41935899 | F33: =F32/F7 -> 0.38358374 | G33: =G32/G7 -> 0.33529998
A35: Allocation of Cost of Revenue between:
A36: Variable | C36: =C18+C21+C31 -> 571400 | D36: =D18+D21+D31 -> 954050 | E36: =E18+E21+E31 -> 1422500 | F36: =F18+F21+F31 -> 1899400 | G36: =G18+G21+G31 -> 2701800
A37: Fixed | C37: =C24+C25+C26+C27 -> 754128.57 | D37: =D24+D25+D26+D27 -> 961950 | E37: =E24+E25+E26+E27 -> 1091557.1 | F37: =F24+F25+F26+F27 -> 1215300 | G37: =G24+G25+G26+G27 -> 1362035.7
A38: Total | C38: =SUM(C36:C37) -> 1325528.6 | D38: =SUM(D36:D37) -> 1916000 | E38: =SUM(E36:E37) -> 2514057.1 | F38: =SUM(F36:F37) -> 3114700 | G38: =SUM(G36:G37) -> 4063835.7
D40: Cost of Revenues by Months & Quarters
D41: ($)
C42: Year 1 | D42: Year 2 | E42: Year 3 | F42: Year 4 | G42: Year 5
A43: Month 1 | C43: =REVENUE!C22*'COST OF REV'!C$33 -> 0 | D43: =REVENUE!D22*'COST OF REV'!D$33 -> 159666.67 | E43: =REVENUE!E22*'COST OF REV'!E$33 -> 209504.76 | F43: =REVENUE!F22*'COST OF REV'!F$33 -> 259558.33 | G43: =REVENUE!G22*'COST OF REV'!G$33 -> 338652.98
A44: Month 2 | C44: =REVENUE!C23*'COST OF REV'!C$33 -> 0 | D44: =REVENUE!D23*'COST OF REV'!D$33 -> 159666.67 | E44: =REVENUE!E23*'COST OF REV'!E$33 -> 209504.76 | F44: =REVENUE!F23*'COST OF REV'!F$33 -> 259558.33 | G44: =REVENUE!G23*'COST OF REV'!G$33 -> 338652.98
A45: Month 3 | C45: =REVENUE!C24*'COST OF REV'!C$33 -> 0 | D45: =REVENUE!D24*'COST OF REV'!D$33 -> 159666.67 | E45: =REVENUE!E24*'COST OF REV'!E$33 -> 209504.76 | F45: =REVENUE!F24*'COST OF REV'!F$33 -> 259558.33 | G45: =REVENUE!G24*'COST OF REV'!G$33 -> 338652.98
A46: Total 1st Quarter | C46: =REVENUE!C25*'COST OF REV'!C$33 -> 0 | D46: =REVENUE!D25*'COST OF REV'!D$33 -> 479000 | E46: =REVENUE!E25*'COST OF REV'!E$33 -> 628514.29 | F46: =REVENUE!F25*'COST OF REV'!F$33 -> 778675 | G46: =REVENUE!G25*'COST OF REV'!G$33 -> 1015958.9
A47: Month 4 | C47: =REVENUE!C26*'COST OF REV'!C$33 -> 147280.95 | D47: =REVENUE!D26*'COST OF REV'!D$33 -> 159666.67 | E47: =REVENUE!E26*'COST OF REV'!E$33 -> 209504.76 | F47: =REVENUE!F26*'COST OF REV'!F$33 -> 259558.33 | G47: =REVENUE!G26*'COST OF REV'!G$33 -> 338652.98
A48: Month 5 | C48: =REVENUE!C27*'COST OF REV'!C$33 -> 147280.95 | D48: =REVENUE!D27*'COST OF REV'!D$33 -> 159666.67 | E48: =REVENUE!E27*'COST OF REV'!E$33 -> 209504.76 | F48: =REVENUE!F27*'COST OF REV'!F$33 -> 259558.33 | G48: =REVENUE!G27*'COST OF REV'!G$33 -> 338652.98
A49: Month 6 | C49: =REVENUE!C28*'COST OF REV'!C$33 -> 147280.95 | D49: =REVENUE!D28*'COST OF REV'!D$33 -> 159666.67 | E49: =REVENUE!E28*'COST OF REV'!E$33 -> 209504.76 | F49: =REVENUE!F28*'COST OF REV'!F$33 -> 259558.33 | G49: =REVENUE!G28*'COST OF REV'!G$33 -> 338652.98
A50: Total 2nd Quarter | C50: =REVENUE!C29*'COST OF REV'!C$33 -> 441842.86 | D50: =REVENUE!D29*'COST OF REV'!D$33 -> 479000 | E50: =REVENUE!E29*'COST OF REV'!E$33 -> 628514.29 | F50: =REVENUE!F29*'COST OF REV'!F$33 -> 778675 | G50: =REVENUE!G29*'COST OF REV'!G$33 -> 1015958.9
A51: Month 7 | C51: =REVENUE!C30*'COST OF REV'!C$33 -> 147280.95 | D51: =REVENUE!D30*'COST OF REV'!D$33 -> 159666.67 | E51: =REVENUE!E30*'COST OF REV'!E$33 -> 209504.76 | F51: =REVENUE!F30*'COST OF REV'!F$33 -> 259558.33 | G51: =REVENUE!G30*'COST OF REV'!G$33 -> 338652.98
A52: Month 8 | C52: =REVENUE!C31*'COST OF REV'!C$33 -> 147280.95 | D52: =REVENUE!D31*'COST OF REV'!D$33 -> 159666.67 | E52: =REVENUE!E31*'COST OF REV'!E$33 -> 209504.76 | F52: =REVENUE!F31*'COST OF REV'!F$33 -> 259558.33 | G52: =REVENUE!G31*'COST OF REV'!G$33 -> 338652.98
A53: Month 9 | C53: =REVENUE!C32*'COST OF REV'!C$33 -> 147280.95 | D53: =REVENUE!D32*'COST OF REV'!D$33 -> 159666.67 | E53: =REVENUE!E32*'COST OF REV'!E$33 -> 209504.76 | F53: =REVENUE!F32*'COST OF REV'!F$33 -> 259558.33 | G53: =REVENUE!G32*'COST OF REV'!G$33 -> 338652.98
A54: Total 3rd Quarter | C54: =REVENUE!C33*'COST OF REV'!C$33 -> 441842.86 | D54: =REVENUE!D33*'COST OF REV'!D$33 -> 479000 | E54: =REVENUE!E33*'COST OF REV'!E$33 -> 628514.29 | F54: =REVENUE!F33*'COST OF REV'!F$33 -> 778675 | G54: =REVENUE!G33*'COST OF REV'!G$33 -> 1015958.9
... A59: Total for year | C59: =REVENUE!C38*'COST OF REV'!C$33 -> 1325528.6 | D59: =REVENUE!D38*'COST OF REV'!D$33 -> 1916000 | E59: =REVENUE!E38*'COST OF REV'!E$33 -> 2514057.1 | F59: =REVENUE!F38*'COST OF REV'!F$33 -> 3114700 | G59: =REVENUE!G38*'COST OF REV'!G$33 -> 4063835.7

Sheet OPER EXP
A1: XYZ Company
A2: Operating Expenses
A3: Years 1 to 5
A4: ($)
C5: Year 1 | D5: Year 2 | E5: Year 3 | F5: Year 4 | G5: Year 5
A7: Net Revenues | C7: =REVENUE!C16 -> 2750000 | D7: =REVENUE!D16 -> 3840000 | E7: =REVENUE!E16 -> 5995000 | F7: =REVENUE!F16 -> 8120000 | G7: =REVENUE!G16 -> 12120000
A9: Sales & Marketing
A10: Drivers
A11: Salaries and Benefits | C11: =PERSONNEL!C18 -> 297000 | D11: =PERSONNEL!D18 -> 322000 | E11: =PERSONNEL!E18 -> 341640 | F11: =PERSONNEL!F18 -> 364800 | G11: =PERSONNEL!G18 -> 379200
A12: Commissions % of Revenue | B12: 0.05 | C12: =$B12*C7 -> 137500 | D12: =$B12*D7 -> 192000 | E12: =$B12*E7 -> 299750 | F12: =$B12*F7 -> 406000 | G12: =$B12*G7 -> 606000
A13: Direct Mail Campaign | C13: 60000 | D13: 85000 | E13: 120000 | F13: 160000 | G13: 200000
A15: All other expenses % of Revenue | B15: 0.06 | C15: =$B15*C7 -> 165000 | D15: =$B15*D7 -> 230400 | E15: =$B15*E7 -> 359700 | F15: =$B15*F7 -> 487200 | G15: =$B15*G7 -> 727200
A16: Total Sales and Marketing | C16: =SUM(C11:C15) -> 659500 | D16: =SUM(D11:D15) -> 829400 | E16: =SUM(E11:E15) -> 1121090 | F16: =SUM(F11:F15) -> 1418000 | G16: =SUM(G11:G15) -> 1912400
A17: % of Revenue | C17: =C16/C7 -> 0.23981818 | D17: =D16/D7 -> 0.21598958 | E17: =E16/E7 -> 0.18700417 | F17: =F16/F7 -> 0.17463054 | G17: =G16/G7 -> 0.15778878
A19: Research & Development
A20: Drivers
A21: Salaries and Benefits | C21: =PERSONNEL!C31 -> 110000 | D21: =PERSONNEL!D31 -> 316250 | E21: =PERSONNEL!E31 -> 418860 | F21: =PERSONNEL!F31 -> 500400 | G21: =PERSONNEL!G31 -> 571200
A22: Testing | C22: 95000 | D22: 130000 | E22: 175000 | F22: 225000 | G22: 280000
A24: All other expenses % of Revenue | B24: 0.03 | C24: =$B24*C7 -> 82500 | D24: =$B24*D7 -> 115200 | E24: =$B24*E7 -> 179850 | F24: =$B24*F7 -> 243600 | G24: =$B24*G7 -> 363600
A25: Total Research & Development | C25: =SUM(C21:C24) -> 287500 | D25: =SUM(D21:D24) -> 561450 | E25: =SUM(E21:E24) -> 773710 | F25: =SUM(F21:F24) -> 969000 | G25: =SUM(G21:G24) -> 1214800
A26: % of Revenue | C26: =C25/C7 -> 0.10454545 | D26: =D25/D7 -> 0.14621094 | E26: =E25/E7 -> 0.12905922 | F26: =F25/F7 -> 0.11933498 | G26: =G25/G7 -> 0.10023102
A28: General & Administration
A29: Drivers
A30: Salaries and Benefits | C30: =PERSONNEL!C44 -> 137500 | D30: =PERSONNEL!D44 -> 300150 | E30: =PERSONNEL!E44 -> 335790 | F30: =PERSONNEL!F44 -> 429600 | G30: =PERSONNEL!G44 -> 502800
A31: Depreciation | C31: ='PROP & EQUIP'!C24 -> 7500 | D31: ='PROP & EQUIP'!D24 -> 42500 | E31: ='PROP & EQUIP'!E24 -> 112500 | F31: ='PROP & EQUIP'!F24 -> 191666.67 | G31: ='PROP & EQUIP'!G24 -> 271666.67
A32: Rent and Utilities | C32: 420000 | D32: 450000 | E32: 490000 | F32: 530000 | G32: 575000
A36: All other expenses % of Revenue | B36: 0.02 | C36: =$B36*C7 -> 55000 | D36: =$B36*D7 -> 76800 | E36: =$B36*E7 -> 119900 | F36: =$B36*F7 -> 162400 | G36: =$B36*G7 -> 242400
A38: Total General & Administration | C38: =SUM(C30:C36) -> 620000 | D38: =SUM(D30:D36) -> 869450 | E38: =SUM(E30:E36) -> 1058190 | F38: =SUM(F30:F36) -> 1313666.7 | G38: =SUM(G30:G36) -> 1591866.7
A39: % of Revenue | C39: =C38/C7 -> 0.22545455 | D39: =D38/D7 -> 0.22641927 | E39: =E38/E7 -> 0.17651209 | F39: =F38/F7 -> 0.16178161 | G39: =G38/G7 -> 0.13134213
A41: Total Operating Expenses | C41: =C16+C25+C38 -> 1567000 | D41: =D16+D25+D38 -> 2260300 | E41: =E16+E25+E38 -> 2952990 | F41: =F16+F25+F38 -> 3700666.7 | G41: =G16+G25+G38 -> 4719066.7
A42: % of Revenue | C42: =C41/C7 -> 0.56981818 | D42: =D41/D7 -> 0.58861979 | E42: =E41/E7 -> 0.49257548 | F42: =F41/F7 -> 0.45574713 | G42: =G41/G7 -> 0.38936194
A44: Allocation of Operating Expenses between:
A45: Variable | C45: =C12+C15+C24+C36 -> 440000 | D45: =D12+D15+D24+D36 -> 614400 | E45: =E12+E15+E24+E36 -> 959200 | F45: =F12+F15+F24+F36 -> 1299200 | G45: =G12+G15+G24+G36 -> 1939200
A46: Fixed | C46: =C11+C13+C21+C22+C30+C31+C32 -> 1127000 | D46: =D11+D13+D21+D22+D30+D31+D32 -> 1645900 | E46: =E11+E13+E21+E22+E30+E31+E32 -> 1993790 | F46: =F11+F13+F21+F22+F30+F31+F32 -> 2401466.7 | G46: =G11+G13+G21+G22+G30+G31+G32 -> 2779866.7
A47: Total | C47: =C45+C46 -> 1567000 | D47: =D45+D46 -> 2260300 | E47: =E45+E46 -> 2952990 | F47: =F45+F46 -> 3700666.7 | G47: =G45+G46 -> 4719066.7
D50: Sales & Marketing by Months & Quarters
D51: ($)
C52: Year 1 | D52: Year 2 | E52: Year 3 | F52: Year 4 | G52: Year 5
A53: Month 1 | C53: =REVENUE!C22*'OPER EXP'!C$17 -> 0 | D53: =REVENUE!D22*'OPER EXP'!D$17 -> 69116.667 | E53: =REVENUE!E22*'OPER EXP'!E$42 -> 246082.5 | F53: =REVENUE!F22*'OPER EXP'!F$42 -> 308388.89 | G53: =REVENUE!G22*'OPER EXP'!G$42 -> 393255.56
A54: Month 2 | C54: =REVENUE!C23*'OPER EXP'!C$17 -> 0 | D54: =REVENUE!D23*'OPER EXP'!D$17 -> 69116.667 | E54: =REVENUE!E23*'OPER EXP'!E$42 -> 246082.5 | F54: =REVENUE!F23*'OPER EXP'!F$42 -> 308388.89 | G54: =REVENUE!G23*'OPER EXP'!G$42 -> 393255.56
A55: Month 3 | C55: =REVENUE!C24*'OPER EXP'!C$17 -> 0 | D55: =REVENUE!D24*'OPER EXP'!D$17 -> 69116.667 | E55: =REVENUE!E24*'OPER EXP'!E$42 -> 246082.5 | F55: =REVENUE!F24*'OPER EXP'!F$42 -> 308388.89 | G55: =REVENUE!G24*'OPER EXP'!G$42 -> 393255.56
A56: Total 1st Quarter | C56: =REVENUE!C25*'OPER EXP'!C$17 -> 0 | D56: =REVENUE!D25*'OPER EXP'!D$17 -> 207350 | E56: =REVENUE!E25*'OPER EXP'!E$17 -> 280272.5 | F56: =REVENUE!F25*'OPER EXP'!F$17 -> 354500 | G56: =REVENUE!G25*'OPER EXP'!G$17 -> 478100
A57: Month 4 | C57: =REVENUE!C26*'OPER EXP'!C$17 -> 73277.778 | D57: =REVENUE!D26*'OPER EXP'!D$17 -> 69116.667 | E57: =REVENUE!E26*'OPER EXP'!E$42 -> 246082.5 | F57: =REVENUE!F26*'OPER EXP'!F$42 -> 308388.89 | G57: =REVENUE!G26*'OPER EXP'!G$42 -> 393255.56
A58: Month 5 | C58: =REVENUE!C27*'OPER EXP'!C$17 -> 73277.778 | D58: =REVENUE!D27*'OPER EXP'!D$17 -> 69116.667 | E58: =REVENUE!E27*'OPER EXP'!E$42 -> 246082.5 | F58: =REVENUE!F27*'OPER EXP'!F$42 -> 308388.89 | G58: =REVENUE!G27*'OPER EXP'!G$42 -> 393255.56
A59: Month 6 | C59: =REVENUE!C28*'OPER EXP'!C$17 -> 73277.778 | D59: =REVENUE!D28*'OPER EXP'!D$17 -> 69116.667 | E59: =REVENUE!E28*'OPER EXP'!E$42 -> 246082.5 | F59: =REVENUE!F28*'OPER EXP'!F$42 -> 308388.89 | G59: =REVENUE!G28*'OPER EXP'!G$42 -> 393255.56
A60: Total 2nd Quarter | C60: =REVENUE!C29*'OPER EXP'!C$17 -> 219833.33 | D60: =REVENUE!D29*'OPER EXP'!D$17 -> 207350 | E60: =REVENUE!E29*'OPER EXP'!E$17 -> 280272.5 | F60: =REVENUE!F29*'OPER EXP'!F$17 -> 354500 | G60: =REVENUE!G29*'OPER EXP'!G$17 -> 478100
A61: Month 7 | C61: =REVENUE!C30*'OPER EXP'!C$17 -> 73277.778 | D61: =REVENUE!D30*'OPER EXP'!D$17 -> 69116.667 | E61: =REVENUE!E30*'OPER EXP'!E$42 -> 246082.5 | F61: =REVENUE!F30*'OPER EXP'!F$42 -> 308388.89 | G61: =REVENUE!G30*'OPER EXP'!G$42 -> 393255.56
A62: Month 8 | C62: =REVENUE!C31*'OPER EXP'!C$17 -> 73277.778 | D62: =REVENUE!D31*'OPER EXP'!D$17 -> 69116.667 | E62: =REVENUE!E31*'OPER EXP'!E$42 -> 246082.5 | F62: =REVENUE!F31*'OPER EXP'!F$42 -> 308388.89 | G62: =REVENUE!G31*'OPER EXP'!G$42 -> 393255.56
A63: Month 9 | C63: =REVENUE!C32*'OPER EXP'!C$17 -> 73277.778 | D63: =REVENUE!D32*'OPER EXP'!D$17 -> 69116.667 | E63: =REVENUE!E32*'OPER EXP'!E$42 -> 246082.5 | F63: =REVENUE!F32*'OPER EXP'!F$42 -> 308388.89 | G63: =REVENUE!G32*'OPER EXP'!G$42 -> 393255.56
A64: Total 3rd Quarter | C64: =REVENUE!C33*'OPER EXP'!C$17 -> 219833.33 | D64: =REVENUE!D33*'OPER EXP'!D$17 -> 207350 | E64: =REVENUE!E33*'OPER EXP'!E$17 -> 280272.5 | F64: =REVENUE!F33*'OPER EXP'!F$17 -> 354500 | G64: =REVENUE!G33*'OPER EXP'!G$17 -> 478100
A65: Month 10 | C65: =REVENUE!C34*'OPER EXP'!C$17 -> 73277.778 | D65: =REVENUE!D34*'OPER EXP'!D$17 -> 69116.667 | E65: =REVENUE!E34*'OPER EXP'!E$42 -> 246082.5 | F65: =REVENUE!F34*'OPER EXP'!F$42 -> 308388.89 | G65: =REVENUE!G34*'OPER EXP'!G$42 -> 393255.56
A66: Month 11 | C66: =REVENUE!C35*'OPER EXP'!C$17 -> 73277.778 | D66: =REVENUE!D35*'OPER EXP'!D$17 -> 69116.667 | E66: =REVENUE!E35*'OPER EXP'!E$42 -> 246082.5 | F66: =REVENUE!F35*'OPER EXP'!F$42 -> 308388.89 | G66: =REVENUE!G35*'OPER EXP'!G$42 -> 393255.56
A67: Month 12 | C67: =REVENUE!C36*'OPER EXP'!C$17 -> 73277.778 | D67: =REVENUE!D36*'OPER EXP'!D$17 -> 69116.667 | E67: =REVENUE!E36*'OPER EXP'!E$42 -> 246082.5 | F67: =REVENUE!F36*'OPER EXP'!F$42 -> 308388.89 | G67: =REVENUE!G36*'OPER EXP'!G$42 -> 393255.56
A68: Total 4th Quarter | C68: =REVENUE!C37*'OPER EXP'!C$17 -> 219833.33 | D68: =REVENUE!D37*'OPER EXP'!D$17 -> 207350 | E68: =REVENUE!E37*'OPER EXP'!E$17 -> 280272.5 | F68: =REVENUE!F37*'OPER EXP'!F$17 -> 354500 | G68: =REVENUE!G37*'OPER EXP'!G$17 -> 478100
A69: Total for year | C69: =REVENUE!C38*'OPER EXP'!C$17 -> 659500 | D69: =REVENUE!D38*'OPER EXP'!D$17 -> 829400 | E69: =REVENUE!E38*'OPER EXP'!E$17 -> 1121090 | F69: =REVENUE!F38*'OPER EXP'!F$17 -> 1418000 | G69: =REVENUE!G38*'OPER EXP'!G$17 -> 1912400
D72: Research & Development by Months & Quarters
D73: ($)
C74: Year 1 | D74: Year 2 | E74: Year 3 | F74: Year 4 | G74: Year 5
A75: Month 1 | C75: =REVENUE!C22*'OPER EXP'!C$26 -> 0 | D75: =REVENUE!D22*'OPER EXP'!D$26 -> 46787.5 | E75: =REVENUE!E44*'OPER EXP'!E$42 -> 0 | F75: =REVENUE!F44*'OPER EXP'!F$42 -> 0 | G75: =REVENUE!G44*'OPER EXP'!G$42 -> 0
A76: Month 2 | C76: =REVENUE!C23*'OPER EXP'!C$26 -> 0 | D76: =REVENUE!D23*'OPER EXP'!D$26 -> 46787.5 | E76: =REVENUE!E45*'OPER EXP'!E$42 -> 0 | F76: =REVENUE!F45*'OPER EXP'!F$42 -> 0 | G76: =REVENUE!G45*'OPER EXP'!G$42 -> 0
A77: Month 3 | C77: =REVENUE!C24*'OPER EXP'!C$26 -> 0 | D77: =REVENUE!D24*'OPER EXP'!D$26 -> 46787.5 | E77: =REVENUE!E46*'OPER EXP'!E$42 -> 0 | F77: =REVENUE!F46*'OPER EXP'!F$42 -> 0 | G77: =REVENUE!G46*'OPER EXP'!G$42 -> 0
A78: Total 1st Quarter | C78: =REVENUE!C25*'OPER EXP'!C$26 -> 0 | D78: =REVENUE!D25*'OPER EXP'!D$26 -> 140362.5 | E78: =REVENUE!E25*'OPER EXP'!E$26 -> 193427.5 | F78: =REVENUE!F25*'OPER EXP'!F$26 -> 242250 | G78: =REVENUE!G25*'OPER EXP'!G$26 -> 303700
A79: Month 4 | C79: =REVENUE!C26*'OPER EXP'!C$26 -> 31944.444 | D79: =REVENUE!D26*'OPER EXP'!D$26 -> 46787.5 | E79: =REVENUE!E48*'OPER EXP'!E$42 -> 0 | F79: =REVENUE!F48*'OPER EXP'!F$42 -> 0 | G79: =REVENUE!G48*'OPER EXP'!G$42 -> 0
A80: Month 5 | C80: =REVENUE!C27*'OPER EXP'!C$26 -> 31944.444 | D80: =REVENUE!D27*'OPER EXP'!D$26 -> 46787.5 | E80: =REVENUE!E49*'OPER EXP'!E$42 -> 0 | F80: =REVENUE!F49*'OPER EXP'!F$42 -> 0 | G80: =REVENUE!G49*'OPER EXP'!G$42 -> 0
A81: Month 6 | C81: =REVENUE!C28*'OPER EXP'!C$26 -> 31944.444 | D81: =REVENUE!D28*'OPER EXP'!D$26 -> 46787.5 | E81: =REVENUE!E50*'OPER EXP'!E$42 -> 0 | F81: =REVENUE!F50*'OPER EXP'!F$42 -> 0 | G81: =REVENUE!G50*'OPER EXP'!G$42 -> 0
A82: Total 2nd Quarter | C82: =REVENUE!C29*'OPER EXP'!C$26 -> 95833.333 | D82: =REVENUE!D29*'OPER EXP'!D$26 -> 140362.5 | E82: =REVENUE!E29*'OPER EXP'!E$26 -> 193427.5 | F82: =REVENUE!F29*'OPER EXP'!F$26 -> 242250 | G82: =REVENUE!G29*'OPER EXP'!G$26 -> 303700
A83: Month 7 | C83: =REVENUE!C30*'OPER EXP'!C$26 -> 31944.444 | D83: =REVENUE!D30*'OPER EXP'!D$26 -> 46787.5 | E83: =REVENUE!E52*'OPER EXP'!E$42 -> 0 | F83: =REVENUE!F52*'OPER EXP'!F$42 -> 0 | G83: =REVENUE!G52*'OPER EXP'!G$42 -> 0
A84: Month 8 | C84: =REVENUE!C31*'OPER EXP'!C$26 -> 31944.444 | D84: =REVENUE!D31*'OPER EXP'!D$26 -> 46787.5 | E84: =REVENUE!E53*'OPER EXP'!E$42 -> 0 | F84: =REVENUE!F53*'OPER EXP'!F$42 -> 0 | G84: =REVENUE!G53*'OPER EXP'!G$42 -> 0
A85: Month 9 | C85: =REVENUE!C32*'OPER EXP'!C$26 -> 31944.444 | D85: =REVENUE!D32*'OPER EXP'!D$26 -> 46787.5 | E85: =REVENUE!E54*'OPER EXP'!E$42 -> 0 | F85: =REVENUE!F54*'OPER EXP'!F$42 -> 0 | G85: =REVENUE!G54*'OPER EXP'!G$42 -> 0
A86: Total 3rd Quarter | C86: =REVENUE!C33*'OPER EXP'!C$26 -> 95833.333 | D86: =REVENUE!D33*'OPER EXP'!D$26 -> 140362.5 | E86: =REVENUE!E33*'OPER EXP'!E$26 -> 193427.5 | F86: =REVENUE!F33*'OPER EXP'!F$26 -> 242250 | G86: =REVENUE!G33*'OPER EXP'!G$26 -> 303700
A87: Month 10 | C87: =REVENUE!C34*'OPER EXP'!C$26 -> 31944.444 | D87: =REVENUE!D34*'OPER EXP'!D$26 -> 46787.5 | E87: =REVENUE!E56*'OPER EXP'!E$42 -> 0 | F87: =REVENUE!F56*'OPER EXP'!F$42 -> 0 | G87: =REVENUE!G56*'OPER EXP'!G$42 -> 0
A88: Month 11 | C88: =REVENUE!C35*'OPER EXP'!C$26 -> 31944.444 | D88: =REVENUE!D35*'OPER EXP'!D$26 -> 46787.5 | E88: =REVENUE!E57*'OPER EXP'!E$42 -> 0 | F88: =REVENUE!F57*'OPER EXP'!F$42 -> 0 | G88: =REVENUE!G57*'OPER EXP'!G$42 -> 0
A89: Month 12 | C89: =REVENUE!C36*'OPER EXP'!C$26 -> 31944.444 | D89: =REVENUE!D36*'OPER EXP'!D$26 -> 46787.5 | E89: =REVENUE!E58*'OPER EXP'!E$42 -> 0 | F89: =REVENUE!F58*'OPER EXP'!F$42 -> 0 | G89: =REVENUE!G58*'OPER EXP'!G$42 -> 0
A90: Total 4th Quarter | C90: =REVENUE!C37*'OPER EXP'!C$26 -> 95833.333 | D90: =REVENUE!D37*'OPER EXP'!D$26 -> 140362.5 | E90: =REVENUE!E37*'OPER EXP'!E$26 -> 193427.5 | F90: =REVENUE!F37*'OPER EXP'!F$26 -> 242250 | G90: =REVENUE!G37*'OPER EXP'!G$26 -> 303700
A91: Total for year | C91: =REVENUE!C38*'OPER EXP'!C$26 -> 287500 | D91: =REVENUE!D38*'OPER EXP'!D$26 -> 561450 | E91: =REVENUE!E38*'OPER EXP'!E$26 -> 773710 | F91: =REVENUE!F38*'OPER EXP'!F$26 -> 969000 | G91: =REVENUE!G38*'OPER EXP'!G$26 -> 1214800
D94: General & Administrative by Months & Quarters
D95: ($)
C96: Year 1 | D96: Year 2 | E96: Year 3 | F96: Year 4 | G96: Year 5
A97: Month 1 | C97: =REVENUE!C22*'OPER EXP'!C$39 -> 0 | D97: =REVENUE!D22*'OPER EXP'!D$39 -> 72454.167 | E97: =REVENUE!E66*'OPER EXP'!E$42 -> 0 | F97: =REVENUE!F66*'OPER EXP'!F$42 -> 0 | G97: =REVENUE!G66*'OPER EXP'!G$42 -> 0
A98: Month 2 | C98: =REVENUE!C23*'OPER EXP'!C$39 -> 0 | D98: =REVENUE!D23*'OPER EXP'!D$39 -> 72454.167 | E98: =REVENUE!E67*'OPER EXP'!E$42 -> 0 | F98: =REVENUE!F67*'OPER EXP'!F$42 -> 0 | G98: =REVENUE!G67*'OPER EXP'!G$42 -> 0
A99: Month 3 | C99: =REVENUE!C24*'OPER EXP'!C$39 -> 0 | D99: =REVENUE!D24*'OPER EXP'!D$39 -> 72454.167 | E99: =REVENUE!E68*'OPER EXP'!E$42 -> 0 | F99: =REVENUE!F68*'OPER EXP'!F$42 -> 0 | G99: =REVENUE!G68*'OPER EXP'!G$42 -> 0
A100: Total 1st Quarter | C100: =REVENUE!C25*'OPER EXP'!C$39 -> 0 | D100: =REVENUE!D25*'OPER EXP'!D$39 -> 217362.5 | E100: =REVENUE!E25*'OPER EXP'!E$39 -> 264547.5 | F100: =REVENUE!F25*'OPER EXP'!F$39 -> 328416.67 | G100: =REVENUE!G25*'OPER EXP'!G$39 -> 397966.67
A101: Month 4 | C101: =REVENUE!C26*'OPER EXP'!C$39 -> 68888.889 | D101: =REVENUE!D26*'OPER EXP'!D$39 -> 72454.167 | E101: =REVENUE!E70*'OPER EXP'!E$42 -> 0 | F101: =REVENUE!F70*'OPER EXP'!F$42 -> 0 | G101: =REVENUE!G70*'OPER EXP'!G$42 -> 0
A102: Month 5 | C102: =REVENUE!C27*'OPER EXP'!C$39 -> 68888.889 | D102: =REVENUE!D27*'OPER EXP'!D$39 -> 72454.167 | E102: =REVENUE!E71*'OPER EXP'!E$42 -> 0 | F102: =REVENUE!F71*'OPER EXP'!F$42 -> 0 | G102: =REVENUE!G71*'OPER EXP'!G$42 -> 0
A103: Month 6 | C103: =REVENUE!C28*'OPER EXP'!C$39 -> 68888.889 | D103: =REVENUE!D28*'OPER EXP'!D$39 -> 72454.167 | E103: =REVENUE!E72*'OPER EXP'!E$42 -> 0 | F103: =REVENUE!F72*'OPER EXP'!F$42 -> 0 | G103: =REVENUE!G72*'OPER EXP'!G$42 -> 0
A104: Total 2nd Quarter | C104: =REVENUE!C29*'OPER EXP'!C$39 -> 206666.67 | D104: =REVENUE!D29*'OPER EXP'!D$39 -> 217362.5 | E104: =REVENUE!E29*'OPER EXP'!E$39 -> 264547.5 | F104: =REVENUE!F29*'OPER EXP'!F$39 -> 328416.67 | G104: =REVENUE!G29*'OPER EXP'!G$39 -> 397966.67
A105: Month 7 | C105: =REVENUE!C30*'OPER EXP'!C$39 -> 68888.889 | D105: =REVENUE!D30*'OPER EXP'!D$39 -> 72454.167 | E105: =REVENUE!E74*'OPER EXP'!E$42 -> 0 | F105: =REVENUE!F74*'OPER EXP'!F$42 -> 0 | G105: =REVENUE!G74*'OPER EXP'!G$42 -> 0
A106: Month 8 | C106: =REVENUE!C31*'OPER EXP'!C$39 -> 68888.889 | D106: =REVENUE!D31*'OPER EXP'!D$39 -> 72454.167 | E106: =REVENUE!E75*'OPER EXP'!E$42 -> 0 | F106: =REVENUE!F75*'OPER EXP'!F$42 -> 0 | G106: =REVENUE!G75*'OPER EXP'!G$42 -> 0
A107: Month 9 | C107: =REVENUE!C32*'OPER EXP'!C$39 -> 68888.889 | D107: =REVENUE!D32*'OPER EXP'!D$39 -> 72454.167 | E107: =REVENUE!E76*'OPER EXP'!E$42 -> 0 | F107: =REVENUE!F76*'OPER EXP'!F$42 -> 0 | G107: =REVENUE!G76*'OPER EXP'!G$42 -> 0
A108: Total 3rd Quarter | C108: =REVENUE!C33*'OPER EXP'!C$39 -> 206666.67 | D108: =REVENUE!D33*'OPER EXP'!D$39 -> 217362.5 | E108: =REVENUE!E33*'OPER EXP'!E$39 -> 264547.5 | F108: =REVENUE!F33*'OPER EXP'!F$39 -> 328416.67 | G108: =REVENUE!G33*'OPER EXP'!G$39 -> 397966.67
A109: Month 10 | C109: =REVENUE!C34*'OPER EXP'!C$39 -> 68888.889 | D109: =REVENUE!D34*'OPER EXP'!D$39 -> 72454.167 | E109: =REVENUE!E78*'OPER EXP'!E$42 -> 0 | F109: =REVENUE!F78*'OPER EXP'!F$42 -> 0 | G109: =REVENUE!G78*'OPER EXP'!G$42 -> 0
A110: Month 11 | C110: =REVENUE!C35*'OPER EXP'!C$39 -> 68888.889 | D110: =REVENUE!D35*'OPER EXP'!D$39 -> 72454.167 | E110: =REVENUE!E79*'OPER EXP'!E$42 -> 0 | F110: =REVENUE!F79*'OPER EXP'!F$42 -> 0 | G110: =REVENUE!G79*'OPER EXP'!G$42 -> 0
A111: Month 12 | C111: =REVENUE!C36*'OPER EXP'!C$39 -> 68888.889 | D111: =REVENUE!D36*'OPER EXP'!D$39 -> 72454.167 | E111: =REVENUE!E80*'OPER EXP'!E$42 -> 0 | F111: =REVENUE!F80*'OPER EXP'!F$42 -> 0 | G111: =REVENUE!G80*'OPER EXP'!G$42 -> 0
A112: Total 4th Quarter | C112: =REVENUE!C37*'OPER EXP'!C$39 -> 206666.67 | D112: =REVENUE!D37*'OPER EXP'!D$39 -> 217362.5 | E112: =REVENUE!E37*'OPER EXP'!E$39 -> 264547.5 | F112: =REVENUE!F37*'OPER EXP'!F$39 -> 328416.67 | G112: =REVENUE!G37*'OPER EXP'!G$39 -> 397966.67
A113: Total for year | C113: =REVENUE!C38*'OPER EXP'!C$39 -> 620000 | D113: =REVENUE!D38*'OPER EXP'!D$39 -> 869450 | E113: =REVENUE!E38*'OPER EXP'!E$39 -> 1058190 | F113: =REVENUE!F38*'OPER EXP'!F$39 -> 1313666.7 | G113: =REVENUE!G38*'OPER EXP'!G$39 -> 1591866.7

Sheet PERSONNEL
A1: XYZ Company | M1: checksum | N1: =SUM(C18:G19,C31:G32,C44:G45,C75:G81,EXTRA!C15:G16,EXTRA!C39:G39,TAXES!C14:G15,'PROP & EQUIP'!B13:G14,'PROP & EQUIP'!C47:G48,'PROP & EQUIP'!B53:G54,'PROP & EQUIP'!C77:G77,WORKCAP!C61:G61,WORKCAP!C6:G6,FUNDING!C9:G9,FUNDING!C14:G14,FUNDING!B15:G15,FUNDING!C19:G19,FUNDING!C24:G24,FUNDING!C27:G29,FUNDING!C41:G41,FUNDING!C50:G52) -> 1.3795575e+08
A2: Personnel
A3: Years 1 to 5
A4: ($)
C5: Year 1 | D5: Year 2 | E5: Year 3 | F5: Year 4 | G5: Year 5
A7: Net Revenues | C7: =REVENUE!C16 -> 2750000 | D7: =REVENUE!D16 -> 3840000 | E7: =REVENUE!E16 -> 5995000 | F7: =REVENUE!F16 -> 8120000 | G7: =REVENUE!G16 -> 12120000
A9: Sales & Marketing
A10: Sales Manager | C10: 85000 | D10: 88000 | E10: 92000 | F10: 96000 | G10: 100000
A11: Marketing Manager | C11: 80000 | D11: 83000 | E11: 87000 | F11: 91000 | G11: 95000
A12: Customer Service Rep 1 | C12: 45000 | D12: 47000 | E12: 49000 | F12: 51000 | G12: 53000
A13: Operations Coordinator | C13: 60000 | D13: 62000 | E13: 64000 | F13: 66000 | G13: 68000
A14: Total Salary | C14: =SUM(C10:C13) -> 270000 | D14: =SUM(D10:D13) -> 280000 | E14: =SUM(E10:E13) -> 292000 | F14: =SUM(F10:F13) -> 304000 | G14: =SUM(G10:G13) -> 316000
A15: Benefits
A16: Percent (%) | C16: 0.1 | D16: 0.15 | E16: 0.17 | F16: 0.2 | G16: 0.2
A17: Total benefit costs | C17: =C16*C14 -> 27000 | D17: =D16*D14 -> 42000 | E17: =E16*E14 -> 49640 | F17: =F16*F14 -> 60800 | G17: =G16*G14 -> 63200
A18: Total S & M Compensation | C18: =C14+C17 -> 297000 | D18: =D14+D17 -> 322000 | E18: =E14+E17 -> 341640 | F18: =F14+F17 -> 364800 | G18: =G14+G17 -> 379200
A19: % of Revenue | C19: =C18/C$7 -> 0.108 | D19: =D18/D$7 -> 0.083854167 | E19: =E18/E$7 -> 0.05698749 | F19: =F18/F$7 -> 0.044926108 | G19: =G18/G$7 -> 0.031287129
A21: Research and Development
A22: R&D Manager | D22: 80000 | E22: 100000 | F22: 125000 | G22: 130000
A23: Engineer | C23: 60000 | D23: 60000 | E23: 90000 | F23: 95000 | G23: 110000
A24: Technician | D24: 50000 | E24: 55000 | F24: 65000 | G24: 70000
A25: Subcontract (Contract R&D) | C25: 40000 | D25: 50000 | E25: 75000 | F25: 90000 | G25: 120000
A26: Other 1: Lab Assistant | D26: 35000 | E26: 38000 | F26: 42000 | G26: 46000
A27: Total Salary | C27: =SUM(C22:C26) -> 100000 | D27: =SUM(D22:D26) -> 275000 | E27: =SUM(E22:E26) -> 358000 | F27: =SUM(F22:F26) -> 417000 | G27: =SUM(G22:G26) -> 476000
A28: Benefits
A29: Percent (%) | C29: 0.1 | D29: 0.15 | E29: 0.17 | F29: 0.2 | G29: 0.2
A30: Total benefit costs | C30: =C29*C27 -> 10000 | D30: =D29*D27 -> 41250 | E30: =E29*E27 -> 60860 | F30: =F29*F27 -> 83400 | G30: =G29*G27 -> 95200
A31: Total R & D Compensation | C31: =C27+C30 -> 110000 | D31: =D27+D30 -> 316250 | E31: =E27+E30 -> 418860 | F31: =F27+F30 -> 500400 | G31: =G27+G30 -> 571200
A32: % of Revenue | C32: =C31/C$7 -> 0.04 | D32: =D31/D$7 -> 0.082356771 | E32: =E31/E$7 -> 0.069868224 | F32: =F31/F$7 -> 0.061625616 | G32: =G31/G$7 -> 0.047128713
A34: General & Administration
A35: CEO | C35: 60000 | D35: 80000 | E35: 100000 | F35: 125000 | G35: 130000
A36: CFO | D36: 50000 | E36: 60000 | F36: 75000 | G36: 100000
A37: Accounting | C37: 40000 | D37: 45000 | E37: 25000 | F37: 50000 | G37: 75000
A38: Secretarial | C38: 25000 | D38: 26000 | E38: 27000 | F38: 28000 | G38: 29000
A39: Clerks/Admin Personnel | D39: 60000 | E39: 75000 | F39: 80000 | G39: 85000
A40: Total Salary | C40: =SUM(C35:C39) -> 125000 | D40: =SUM(D35:D39) -> 261000 | E40: =SUM(E35:E39) -> 287000 | F40: =SUM(F35:F39) -> 358000 | G40: =SUM(G35:G39) -> 419000
A41: Benefits
A42: Percent (%) | C42: 0.1 | D42: 0.15 | E42: 0.17 | F42: 0.2 | G42: 0.2
A43: Total benefit costs | C43: =C42*C40 -> 12500 | D43: =D42*D40 -> 39150 | E43: =E42*E40 -> 48790 | F43: =F42*F40 -> 71600 | G43: =G42*G40 -> 83800
A44: Total G & A Compensation | C44: =C40+C43 -> 137500 | D44: =D40+D43 -> 300150 | E44: =E40+E43 -> 335790 | F44: =F40+F43 -> 429600 | G44: =G40+G43 -> 502800
A45: % of Revenue | C45: =C44/C$7 -> 0.05 | D45: =D44/D$7 -> 0.078164063 | E45: =E44/E$7 -> 0.056011676 | F45: =F44/F$7 -> 0.052906404 | G45: =G44/G$7 -> 0.041485149
A47: Cost of Revenue
A48: Manufacturing Personnel
A49: Operations Manager | C49: 75000 | D49: 78000 | E49: 81000 | F49: 84000 | G49: 87000
A50: Quality Assurance | C50: 50000 | D50: 55000 | E50: 60000 | F50: 65000 | G50: 70000
A51: Materials & Logistics | C51: 40000 | D51: 45000 | E51: 50000 | F51: 55000 | G51: 60000
A52: Engineering | D52: 75000 | E52: 80000 | F52: 85000 | G52: 90000
A53: Total Salary | C53: =SUM(C49:C52) -> 165000 | D53: =SUM(D49:D52) -> 253000 | E53: =SUM(E49:E52) -> 271000 | F53: =SUM(F49:F52) -> 289000 | G53: =SUM(G49:G52) -> 307000
A54: Benefits
A55: Percent (%) | C55: 0.1 | D55: 0.15 | E55: 0.2 | F55: 0.2 | G55: 0.25
A56: Total benefit costs | C56: =C55*C53 -> 16500 | D56: =D55*D53 -> 37950 | E56: =E55*E53 -> 54200 | F56: =F55*F53 -> 57800 | G56: =G55*G53 -> 76750
A57: Total Salary Costs | C57: =C53+C56 -> 181500 | D57: =D53+D56 -> 290950 | E57: =E53+E56 -> 325200 | F57: =F53+F56 -> 346800 | G57: =G53+G56 -> 383750
A58: Hourly Personnel
A59: Number of employees | C59: 3 | D59: 9 | E59: 13 | F59: 17 | G59: 20
A60: Average wages per employee | C60: 20000 | D60: 22000 | E60: 23000 | F60: 24000 | G60: 24000
A61: Total wages | C61: =C59*C60 -> 60000 | D61: =D59*D60 -> 198000 | E61: =E59*E60 -> 299000 | F61: =F59*F60 -> 408000 | G61: =G59*G60 -> 480000
A62: Benefits
A63: Percent (%) | C63: 0.1 | D63: 0.15 | E63: 0.2 | F63: 0.2 | G63: 0.25
A64: Total benefit costs | C64: =C61*C63 -> 6000 | D64: =D61*D63 -> 29700 | E64: =E61*E63 -> 59800 | F64: =F61*F63 -> 81600 | G64: =G61*G63 -> 120000
A65: Total Wage Costs | C65: =C61+C64 -> 66000 | D65: =D61+D64 -> 227700 | E65: =E61+E64 -> 358800 | F65: =F61+F64 -> 489600 | G65: =G61+G64 -> 600000
A66: Service Personnel
A67: Number of employees | C67: 3 | D67: 5 | E67: 7 | F67: 8 | G67: 12
A68: Salary per employee | C68: 35000 | D68: 37000 | E68: 40000 | F68: 50000 | G68: 55000
A69: Total salaries | C69: =C67*C68 -> 105000 | D69: =D67*D68 -> 185000 | E69: =E67*E68 -> 280000 | F69: =F67*F68 -> 400000 | G69: =G67*G68 -> 660000
A70: Benefits
A71: Percent (%) | C71: 0.1 | D71: 0.15 | E71: 0.2 | F71: 0.2 | G71: 0.25
A72: Total benefit costs | C72: =C69*C71 -> 10500 | D72: =D69*D71 -> 27750 | E72: =E69*E71 -> 56000 | F72: =F69*F71 -> 80000 | G72: =G69*G71 -> 165000
A73: Total Salary Costs | C73: =C69+C72 -> 115500 | D73: =D69+D72 -> 212750 | E73: =E69+E72 -> 336000 | F73: =F69+F72 -> 480000 | G73: =G69+G72 -> 825000
A75: Total COR's Compensation | C75: =C57+C65+C73 -> 363000 | D75: =D57+D65+D73 -> 731400 | E75: =E57+E65+E73 -> 1020000 | F75: =F57+F65+F73 -> 1316400 | G75: =G57+G65+G73 -> 1808750
A76: % of Revenue | C76: =C75/C$7 -> 0.132 | D76: =D75/D$7 -> 0.19046875 | E76: =E75/E$7 -> 0.17014178 | F76: =F75/F$7 -> 0.16211823 | G76: =G75/G$7 -> 0.1492368
A78: Total Salary & Wages | C78: =C14+C27+C40+C53+C61 -> 720000 | D78: =D14+D27+D40+D53+D61 -> 1267000 | E78: =E14+E27+E40+E53+E61 -> 1507000 | F78: =F14+F27+F40+F53+F61 -> 1776000 | G78: =G14+G27+G40+G53+G61 -> 1998000
A79: Total Benefits | C79: =C17+C30+C43+C56+C64 -> 72000 | D79: =D17+D30+D43+D56+D64 -> 190050 | E79: =E17+E30+E43+E56+E64 -> 273290 | F79: =F17+F30+F43+F56+F64 -> 355200 | G79: =G17+G30+G43+G56+G64 -> 438950
A80: Total Compensation | C80: =C18+C31+C44+C75 -> 907500 | D80: =D18+D31+D44+D75 -> 1669800 | E80: =E18+E31+E44+E75 -> 2116290 | F80: =F18+F31+F44+F75 -> 2611200 | G80: =G18+G31+G44+G75 -> 3261950
A81: % of Revenue | C81: =C80/C$7 -> 0.33 | D81: =D80/D$7 -> 0.43484375 | E81: =E80/E$7 -> 0.35300917 | F81: =F80/F$7 -> 0.32157635 | G81: =G80/G$7 -> 0.26913779

Sheet EXTRA
A1: XYZ Company
A2: Extraordinary Income & Expense
A3: Years 1 to 5
A4: ($)
C5: Year 1 | D5: Year 2 | E5: Year 3 | F5: Year 4 | G5: Year 5
A7: Income
A8: Training Services (B2B workshops) | C8: 0 | D8: 50000 | E8: 80000 | F8: 120000 | G8: 150000
A9: Equipment Leasing (spare capacity) | C9: 0 | D9: 40000 | E9: 60000 | F9: 80000 | G9: 100000
A10: Consulting Add-ons | C10: 0 | D10: 25000 | E10: 40000 | F10: 60000 | G10: 80000
A11: Total | C11: =SUM(C8:C10) -> 0 | D11: =SUM(D8:D10) -> 115000 | E11: =SUM(E8:E10) -> 180000 | F11: =SUM(F8:F10) -> 260000 | G11: =SUM(G8:G10) -> 330000
A12: Start-up expenses
A13: Legal | C13: 50000 | D13: 0 | E13: 0 | F13: 0 | G13: 0
A14: Relocation | C14: 70000 | D14: 0 | E14: 0 | F14: 0 | G14: 0
A15: Total | C15: =SUM(C13:C14) -> 120000 | D15: =SUM(D13:D14) -> 0 | E15: =SUM(E13:E14) -> 0 | F15: =SUM(F13:F14) -> 0 | G15: =SUM(G13:G14) -> 0
A16: Total Extraordinary Income/(Expense) | C16: =C11-C15 -> -120000 | D16: =D11-D15 -> 115000 | E16: =E11-E15 -> 180000 | F16: =F11-F15 -> 260000 | G16: =G11-G15 -> 330000
D20: Extraordinary Income and Expense by Months & Quarters
D21: ($)
C22: Year 1 | D22: Year 2 | E22: Year 3 | F22: Year 4 | G22: Year 5
A23: Month 1 | C23: -50000 | D23: =D8 -> 50000 | E23: 0 | F23: 0 | G23: 0
A24: Month 2 | C24: -70000 | D24: 0 | E24: 80000 | F24: 120000 | G24: 150000
A25: Month 3 | C25: 0 | D25: 0 | E25: 0 | F25: 0 | G25: 0
A26: Total 1st Quarter | C26: =SUM(C23:C25) -> -120000 | D26: =SUM(D23:D25) -> 50000 | E26: =SUM(E23:E25) -> 80000 | F26: =SUM(F23:F25) -> 120000 | G26: =SUM(G23:G25) -> 150000
A27: Month 4 | C27: 0 | D27: 0 | E27: 0 | F27: 0 | G27: 100000
A28: Month 5 | C28: 0 | D28: 40000 | E28: 0 | F28: 80000 | G28: 0
A29: Month 6 | C29: 0 | D29: 0 | E29: 0 | F29: 0 | G29: 0
A30: Total 2nd Quarter | C30: =SUM(C27:C29) -> 0 | D30: =SUM(D27:D29) -> 40000 | E30: =SUM(E27:E29) -> 0 | F30: =SUM(F27:F29) -> 80000 | G30: =SUM(G27:G29) -> 100000
A31: Month 7 | C31: 0 | D31: 0 | E31: 0 | F31: 0 | G31: 80000
A32: Month 8 | C32: 0 | D32: 0 | E32: 60000 | F32: 0 | G32: 0
A33: Month 9 | C33: 0 | D33: 0 | E33: 0 | F33: 0 | G33: 0
A34: Total 3rd Quarter | C34: =SUM(C31:C33) -> 0 | D34: =SUM(D31:D33) -> 0 | E34: =SUM(E31:E33) -> 60000 | F34: =SUM(F31:F33) -> 0 | G34: =SUM(G31:G33) -> 80000
A35: Month 10 | C35: 0 | D35: 25000 | E35: 0 | F35: 60000 | G35: 0
A36: Month 11 | C36: 0 | D36: 0 | E36: 40000 | F36: 0 | G36: 0
A37: Month 12 | C37: 0 | D37: 0 | E37: 0 | F37: 0 | G37: 0
A38: Total 4th Quarter | C38: =SUM(C35:C37) -> 0 | D38: =SUM(D35:D37) -> 25000 | E38: =SUM(E35:E37) -> 40000 | F38: =SUM(F35:F37) -> 60000 | G38: =SUM(G35:G37) -> 0
A39: Total for year | C39: =SUM(C38,C34,C30,C26) -> -120000 | D39: =SUM(D38,D34,D30,D26) -> 115000 | E39: =SUM(E38,E34,E30,E26) -> 180000 | F39: =SUM(F38,F34,F30,F26) -> 260000 | G39: =SUM(G38,G34,G30,G26) -> 330000

Sheet TAXES
A1: XYZ Company
A2: Taxes
A3: Years 1 to 5
A4: ($)
C5: Year 1 | D5: Year 2 | E5: Year 3 | F5: Year 4 | G5: Year 5
A7: Net Revenues | C7: =REVENUE!C16 -> 2750000 | D7: =REVENUE!D16 -> 3840000 | E7: =REVENUE!E16 -> 5995000 | F7: =REVENUE!F16 -> 8120000 | G7: =REVENUE!G16 -> 12120000
A9: Income Tax (Rate Federal & State) | C9: 0.4 | D9: 0.4 | E9: 0.4 | F9: 0.4 | G9: 0.4
A11: Net Earnings Before Taxes | C11: =INCOME!C30 -> -476628.57 | D11: =INCOME!D30 -> -416600 | E11: =INCOME!E30 -> 488352.86 | F11: =INCOME!F30 -> 1440633.3 | G11: =INCOME!G30 -> 3579897.6
A12: Cumulative | C12: =C11 -> -476628.57 | D12: =D11+C12 -> -893228.57 | E12: =E11+D12 -> -404875.71 | F12: =F11+E12 -> 1035757.6 | G12: =G11+F12 -> 4615655.2
A14: Taxes | C14: =-IF(C12>=0,TAXES!$C$9*MIN(C11,C12),0) -> 0 | D14: =-IF(D12>=0,TAXES!$D$9*MIN(D11,D12),0) -> 0 | E14: =-IF(E12>=0,TAXES!$E$9*MIN(E11,E12),0) -> 0 | F14: =-IF(F12>=0,TAXES!$F$9*MIN(F11,F12),0) -> -414303.05 | G14: =-IF(G12>=0,TAXES!$G$9*MIN(G11,G12),0) -> -1431959
A15: Percent of Revenues | C15: =C14/C7 -> 0 | D15: =D14/D7 -> 0 | E15: =E14/E7 -> 0 | F15: =F14/F7 -> -0.051022543 | G15: =G14/G7 -> -0.11814844

Sheet PROP & EQUIP
A1: XYZ Company
A2: Property and Equipment
A3: Years 1 to 5
A4: ($)
B5: Year 0 | C5: Year 1 | D5: Year 2 | E5: Year 3 | F5: Year 4 | G5: Year 5
B6: Purchased
A7: Net Revenues | B7: Assets | C7: =REVENUE!C16 -> 2750000 | D7: =REVENUE!D16 -> 3840000 | E7: =REVENUE!E16 -> 5995000 | F7: =REVENUE!F16 -> 8120000 | G7: =REVENUE!G16 -> 12120000
A9: Capital Expenditures
A10: Computers, Software & Office Equipment | C10: 22500 | D10: 105000 | E10: 210000 | F10: 260000 | G10: 345000
A11: Plant & Equipment | C11: 255000 | D11: 340000 | E11: 265000 | F11: 295000 | G11: 310000
A12: Other | C12: 12000 | D12: 48000 | E12: 95000 | F12: 110000 | G12: 95000
A13: Total Capital Expenditures | B13: =SUM(B10:B12) -> 0 | C13: =SUM(C10:C12) -> 289500 | D13: =SUM(D10:D12) -> 493000 | E13: =SUM(E10:E12) -> 570000 | F13: =SUM(F10:F12) -> 665000 | G13: =SUM(G10:G12) -> 750000
A14: % of Revenue | C14: =C13/C7 -> 0.10527273 | D14: =D13/D7 -> 0.12838542 | E14: =E13/E7 -> 0.095079233 | F14: =F13/F7 -> 0.081896552 | G14: =G13/G7 -> 0.061881188
A16: Depreciation Computers, Sofware & Office Equipment (allocated to General & Administrative Expenses)
A17: Depreciation Rate: Years | B17: 1 | C17: 3 | D17: 3 | E17: 3 | F17: 3 | G17: 3
A18: Year 0 | C18: =$B10*1/$B17 -> 0 | D18: =IF(C18<$B10,($B10*1/$B$17),0) -> 0 | E18: =IF(SUM(C18:D18)<$B10,($B10*1/$B$17),0) -> 0 | F18: =IF(SUM(C18:E18)<$B10,($B10*1/$B$17),0) -> 0 | G18: =IF(SUM(C18:F18)<$B10,($B10*1/$B$17),0) -> 0
A19: Year 1 | C19: =$C10*1/$C17 -> 7500 | D19: =IF(C19<$C10,($C10*1/$C$17),0) -> 7500 | E19: =IF(SUM(C19:D19)<$C10,($C10*1/$C$17),0) -> 7500 | F19: =IF(SUM(C19:E19)<$C10,($C10*1/$C$17),0) -> 0 | G19: =IF(SUM(C19:F19)<$C10,($C10*1/$C$17),0) -> 0
A20: Year 2 | D20: =$D10*1/$D$17 -> 35000 | E20: =IF(D20<$D10,($D10*1/$D$17),0) -> 35000 | F20: =IF(SUM(D20:E20)<$D10,($D10*1/$D$17),0) -> 35000 | G20: =IF(SUM(D20:F20)<$D10,($D10*1/$D$17),0) -> 0
A21: Year 3 | E21: =$E10*1/$E$17 -> 70000 | F21: =IF(E21<$E10,($E10*1/$E$17),0) -> 70000 | G21: =IF(SUM(E21:F21)<$E10,($E10*1/$E$17),0) -> 70000
A22: Year 4 | F22: =$F10*1/$F$17 -> 86666.667 | G22: =IF(F22<$F10,($F10*1/$F$17),0) -> 86666.667
A23: Year 5 | G23: =$G10*1/G$17 -> 115000
A24: Total Depreciation | C24: =SUM(C18:C23) -> 7500 | D24: =SUM(D18:D23) -> 42500 | E24: =SUM(E18:E23) -> 112500 | F24: =SUM(F18:F23) -> 191666.67 | G24: =SUM(G18:G23) -> 271666.67
A26: Depreciation on Plant and Equipment (allocated to Cost of Revenue)
A27: Depreciation Rate: Years | B27: 1 | C27: 7 | D27: 7 | E27: 7 | F27: 7 | G27: 7
A28: Year 0 | C28: =$B11*1/$B27 -> 0 | D28: =IF(C28<$B11,($B11*1/$B$27),0) -> 0 | E28: =IF(SUM(C28:D28)<$B11,($B11*1/$B$27),0) -> 0 | F28: =IF(SUM(C28:E28)<$B11,($B11*1/$B$27),0) -> 0 | G28: =IF(SUM(C28:F28)<$B11,($B11*1/$B$27),0) -> 0
A29: Year 1 | C29: =$C11*1/$C27 -> 36428.571 | D29: =IF(C29<$C11,($C11*1/$C$27),0) -> 36428.571 | E29: =IF(SUM(C29:D29)<$C11,($C11*1/$C$27),0) -> 36428.571 | F29: =IF(SUM(C29:E29)<$C11,($C11*1/$C$27),0) -> 36428.571 | G29: =IF(SUM(C29:F29)<$C11,($C11*1/$C$27),0) -> 36428.571
A30: Year 2 | D30: =$D11*1/$D$27 -> 48571.429 | E30: =IF(D30<$D11,($D11*1/$D$27),0) -> 48571.429 | F30: =IF(SUM(D30:E30)<$D11,($D11*1/$D$27),0) -> 48571.429 | G30: =IF(SUM(D30:F30)<$D11,($D11*1/$D$27),0) -> 48571.429
A31: Year 3 | E31: =$E11*1/$E$27 -> 37857.143 | F31: =IF(E31<$E11,($E11*1/$E$27),0) -> 37857.143 | G31: =IF(SUM(E31:F31)<$E11,($E11*1/$E$27),0) -> 37857.143
A32: Year 4 | F32: =$F11*1/$F$27 -> 42142.857 | G32: =IF(F32<$F11,($F11*1/$F$27),0) -> 42142.857
A33: Year 5 | G33: =$G11*1/G$27 -> 44285.714
A34: Total Depreciation | C34: =SUM(C28:C33) -> 36428.571 | D34: =SUM(D28:D33) -> 85000 | E34: =SUM(E28:E33) -> 122857.14 | F34: =SUM(F28:F33) -> 165000 | G34: =SUM(G28:G33) -> 209285.71
A36: Depreciation Other (allocated to Cost of Revenue)
A37: Depreciation Rate: Years | B37: 1 | C37: 10 | D37: 10 | E37: 10 | F37: 10 | G37: 10
A38: Year 0 | C38: =$B12*1/$B37 -> 0 | D38: =IF(C38<$B12,($B12*1/$B$37),0) -> 0 | E38: =IF(SUM(C38:D38)<$B12,($B12*1/$B$37),0) -> 0 | F38: =IF(SUM(C38:E38)<$B12,($B12*1/$B$37),0) -> 0 | G38: =IF(SUM(C38:F38)<$B12,($B12*1/$B$37),0) -> 0
A39: Year 1 | C39: =$C12*1/$C37 -> 1200 | D39: =IF(C39<$C12,($C12*1/$C$37),0) -> 1200 | E39: =IF(SUM(C39:D39)<$C12,($C12*1/$C$37),0) -> 1200 | F39: =IF(SUM(C39:E39)<$C12,($C12*1/$C$37),0) -> 1200 | G39: =IF(SUM(C39:F39)<$C12,($C12*1/$C$37),0) -> 1200
A40: Year 2 | D40: =$D12*1/$D$37 -> 4800 | E40: =IF(D40<D12,($D12*1/$D$37),0) -> 4800 | F40: =IF(SUM(D40:E40)<$D12,($D12*1/$D$37),0) -> 4800 | G40: =IF(SUM(D40:F40)<$D12,($D12*1/$D$37),0) -> 4800
A41: Year 3 | E41: =$E12*1/$E$37 -> 9500 | F41: =IF(E41<$E12,($E12*1/$E$37),0) -> 9500 | G41: =IF(SUM(E41:F41)<$E12,($E12*1/$E$37),0) -> 9500
A42: Year 4 | F42: =$F12*1/$F$37 -> 11000 | G42: =IF(F42<$F12,($F12*1/$F$37),0) -> 11000
A43: Year 5 | G43: =$G12*1/G$37 -> 9500
A44: Total Depreciation | C44: =SUM(C38:C43) -> 1200 | D44: =SUM(D38:D43) -> 6000 | E44: =SUM(E38:E43) -> 15500 | F44: =SUM(F38:F43) -> 26500 | G44: =SUM(G38:G43) -> 36000
A47: Total Depreciation | C47: =C24+C34+C44 -> 45128.571 | D47: =D24+D34+D44 -> 133500 | E47: =E24+E34+E44 -> 250857.14 | F47: =F24+F34+F44 -> 383166.67 | G47: =G24+G34+G44 -> 516952.38
A48: % of Revenue | C48: =C47/C7 -> 0.01641039 | D48: =D47/D7 -> 0.034765625 | E48: =E47/E7 -> 0.041844394 | F48: =F47/F7 -> 0.047188013 | G48: =G47/G7 -> 0.042652837
A50: Property & Equipment
A51: Gross Asset Value | B51: =B13 -> 0 | C51: =C13+B12 -> 289500 | D51: =C51+D13 -> 782500 | E51: =D51+E13 -> 1352500 | F51: =E51+F13 -> 2017500 | G51: =F51+G13 -> 2767500
A52: Accumulated Depreciation | C52: =C47 -> 45128.571 | D52: =C52+D47 -> 178628.57 | E52: =D52+E47 -> 429485.71 | F52: =E52+F47 -> 812652.38 | G52: =F52+G47 -> 1329604.8
A53: Net Property and Equipment | B53: =B51-B52 -> 0 | C53: =C51-C52 -> 244371.43 | D53: =D51-D52 -> 603871.43 | E53: =E51-E52 -> 923014.29 | F53: =F51-F52 -> 1204847.6 | G53: =G51-G52 -> 1437895.2
A54: % of Revenue | C54: =C53/C7 -> 0.088862338 | D54: =D53/D7 -> 0.15725818 | E54: =E53/E7 -> 0.15396402 | F54: =F53/F7 -> 0.14838025 | G54: =G53/G7 -> 0.11863822
D58: Capital Expenditures by Months & Quarters
D59: ($)
C60: Year 1 | D60: Year 2 | E60: Year 3 | F60: Year 4 | G60: Year 5
A61: Month 1 | C61: 50000 | D61: 100000 | E61: 100000 | F61: 100000 | G61: 100000
A62: Month 2 | C62: 100000 | D62: 100000 | E62: 100000 | F62: 100000 | G62: 100000
A63: Month 3 | C63: 50000 | D63: 0 | E63: 0 | F63: 0 | G63: 0
A64: Total 1st Quarter | C64: =SUM(C61:C63) -> 200000 | D64: =SUM(D61:D63) -> 200000 | E64: =SUM(E61:E63) -> 200000 | F64: =SUM(F61:F63) -> 200000 | G64: =SUM(G61:G63) -> 200000
A65: Month 4 | C65: 40000 | D65: 0 | E65: 0 | F65: 0 | G65: 0
A66: Month 5 | C66: 0 | D66: 0 | E66: 0 | F66: 165000 | G66: 250000
A67: Month 6 | C67: 0 | D67: 100000 | E67: 0 | F67: 0 | G67: 0
A68: Total 2nd Quarter | C68: =SUM(C65:C67) -> 40000 | D68: =SUM(D65:D67) -> 100000 | E68: =SUM(E65:E67) -> 0 | F68: =SUM(F65:F67) -> 165000 | G68: =SUM(G65:G67) -> 250000
A69: Month 7 | C69: 40000 | D69: 0 | E69: 100000 | F69: 0 | G69: 0
A70: Month 8 | C70: 0 | D70: 93000 | E70: 0 | F70: 100000 | G70: 150000
A71: Month 9 | C71: 0 | D71: 0 | E71: 0 | F71: 0 | G71: 0
A72: Total 3rd Quarter | C72: =SUM(C69:C71) -> 40000 | D72: =SUM(D69:D71) -> 93000 | E72: =SUM(E69:E71) -> 100000 | F72: =SUM(F69:F71) -> 100000 | G72: =SUM(G69:G71) -> 150000
A73: Month 10 | C73: 9500 | D73: 0 | E73: 0 | F73: 0 | G73: 0
A74: Month 11 | C74: 0 | D74: 0 | E74: 270000 | F74: 200000 | G74: 150000
A75: Month 12 | C75: 0 | D75: 100000 | E75: 0 | F75: 0 | G75: 0
A76: Total 4th Quarter | C76: =SUM(C73:C75) -> 9500 | D76: =SUM(D73:D75) -> 100000 | E76: =SUM(E73:E75) -> 270000 | F76: =SUM(F73:F75) -> 200000 | G76: =SUM(G73:G75) -> 150000
A77: Total for year | C77: =C64+C68+C72+C76 -> 289500 | D77: =D64+D68+D72+D76 -> 493000 | E77: =E64+E68+E72+E76 -> 570000 | F77: =F64+F68+F72+F76 -> 665000 | G77: =G64+G68+G72+G76 -> 750000

Sheet WORKCAP
A1: XYZ Company
A2: Working Capital
A3: Years 1 to 5
A4: ($)
C5: Year 1 | D5: Year 2 | E5: Year 3 | F5: Year 4 | G5: Year 5
A6: Net Revenues | C6: =REVENUE!C16 -> 2750000 | D6: =REVENUE!D16 -> 3840000 | E6: =REVENUE!E16 -> 5995000 | F6: =REVENUE!F16 -> 8120000 | G6: =REVENUE!G16 -> 12120000
A9: Accounts Receivable
A10: % of Revenue | C10: 0.083 | D10: 0.083 | E10: 0.083 | F10: 0.083 | G10: 0.083
A11: Days Outstanding | C11: =C10*360 -> 29.88 | D11: =D10*360 -> 29.88 | E11: =E10*360 -> 29.88 | F11: =F10*360 -> 29.88 | G11: =G10*360 -> 29.88
A12: Accounts Receivable | C12: =C78 -> 304333.33 | D12: =D78 -> 318720 | E12: =E78 -> 497585 | F12: =F78 -> 673960 | G12: =G78 -> 1005960
A13: (Increase)/Decrease from Prev. Period | C13: =-C12 -> -304333.33 | D13: =-(D12-C12) -> -14386.667 | E13: =-(E12-D12) -> -178865 | F13: =-(F12-E12) -> -176375 | G13: =-(G12-F12) -> -332000
A15: Inventory
A16: % of Revenue | C16: 0.083 | D16: 0.083 | E16: 0.067 | F16: 0.067 | G16: 0.067
A17: Inventory Turns | C17: =IF(C18<=0,0,ROUND(360/C18,0)) -> 12 | D17: =IF(D18<=0,0,ROUND(360/D18,0)) -> 12 | E17: =IF(E18<=0,0,ROUND(360/E18,0)) -> 15 | F17: =IF(F18<=0,0,ROUND(360/F18,0)) -> 15 | G17: =IF(G18<=0,0,ROUND(360/G18,0)) -> 15
A18: Inventory Days | C18: =C16*360 -> 29.88 | D18: =D16*360 -> 29.88 | E18: =E16*360 -> 24.12 | F18: =F16*360 -> 24.12 | G18: =G16*360 -> 24.12
A19: Inventory | C19: =C95 -> 304333.33 | D19: =D95 -> 318720 | E19: =E95 -> 401665 | F19: =F95 -> 544040 | G19: =G95 -> 812040
A20: (Increase)/Decrease from Prev. Period | C20: =-C19 -> -304333.33 | D20: =-(D19-C19) -> -14386.667 | E20: =-(E19-D19) -> -82945 | F20: =-(F19-E19) -> -142375 | G20: =-(G19-F19) -> -268000
A22: Other Current Assets
A23: % of Revenue | C23: 0.01 | D23: 0.01 | E23: 0.01 | F23: 0.01 | G23: 0.01
A24: Days | C24: =C23*360 -> 3.6 | D24: =D23*360 -> 3.6 | E24: =E23*360 -> 3.6 | F24: =F23*360 -> 3.6 | G24: =G23*360 -> 3.6
A25: Other CA Value | C25: =C112 -> 36666.667 | D25: =D112 -> 38400 | E25: =E112 -> 59950 | F25: =F112 -> 81200 | G25: =G112 -> 121200
A26: (Increase)/Decrease from Prev. Period | C26: =-C25 -> -36666.667 | D26: =-(D25-C25) -> -1733.3333 | E26: =-(E25-D25) -> -21550 | F26: =-(F25-E25) -> -21250 | G26: =-(G25-F25) -> -40000
A28: Accounts Payable & Accrued Expenses
A29: % of Revenue | C29: 0.087 | D29: 0.087 | E29: 0.087 | F29: 0.087 | G29: 0.087
A30: Days | C30: =C29*360 -> 31.32 | D30: =D29*360 -> 31.32 | E30: =E29*360 -> 31.32 | F30: =F29*360 -> 31.32 | G30: =G29*360 -> 31.32
A31: AP & Accrued Value | C31: =C129 -> 319000 | D31: =D129 -> 334080 | E31: =E129 -> 521565 | F31: =F129 -> 706440 | G31: =G129 -> 1054440
A32: Increase/(Decrease) from Prev. Period | C32: =C31 -> 319000 | D32: =(D31-C31) -> 15080 | E32: =(E31-D31) -> 187485 | F32: =(F31-E31) -> 184875 | G32: =(G31-F31) -> 348000
A34: Other Current Liabilites
A35: % of Revenue | C35: 0.01 | D35: 0.01 | E35: 0.01 | F35: 0.01 | G35: 0.01
A36: Days | C36: =C35*360 -> 3.6 | D36: =D35*360 -> 3.6 | E36: =E35*360 -> 3.6 | F36: =F35*360 -> 3.6 | G36: =G35*360 -> 3.6
A37: Other Current Liabilities | C37: =C146 -> 36666.667 | D37: =D146 -> 38400 | E37: =E146 -> 59950 | F37: =F146 -> 81200 | G37: =G146 -> 121200
A38: Increase/(Decrease) from Prev. Period | C38: =C37 -> 36666.667 | D38: =D37-C37 -> 1733.3333 | E38: =E37-D37 -> 21550 | F38: =F37-E37 -> 21250 | G38: =G37-F37 -> 40000
A42: Revenues by Months & Quarters
D43: ($)
C44: Year 1 | D44: Year 2 | E44: Year 3 | F44: Year 4 | G44: Year 5
A45: Month 1 | C45: =REVENUE!C22 -> 0 | D45: =REVENUE!D22 -> 320000 | E45: =REVENUE!E22 -> 499583.33 | F45: =REVENUE!F22 -> 676666.67 | G45: =REVENUE!G22 -> 1010000
A46: Month 2 | C46: =REVENUE!C23 -> 0 | D46: =REVENUE!D23 -> 320000 | E46: =REVENUE!E23 -> 499583.33 | F46: =REVENUE!F23 -> 676666.67 | G46: =REVENUE!G23 -> 1010000
A47: Month 3 | C47: =REVENUE!C24 -> 0 | D47: =REVENUE!D24 -> 320000 | E47: =REVENUE!E24 -> 499583.33 | F47: =REVENUE!F24 -> 676666.67 | G47: =REVENUE!G24 -> 1010000
A48: Total 1st Quarter | C48: =REVENUE!C25 -> 0 | D48: =REVENUE!D25 -> 960000 | E48: =REVENUE!E25 -> 1498750 | F48: =REVENUE!F25 -> 2030000 | G48: =REVENUE!G25 -> 3030000
A49: Month 4 | C49: =REVENUE!C26 -> 305555.56 | D49: =REVENUE!D26 -> 320000 | E49: =REVENUE!E26 -> 499583.33 | F49: =REVENUE!F26 -> 676666.67 | G49: =REVENUE!G26 -> 1010000
A50: Month 5 | C50: =REVENUE!C27 -> 305555.56 | D50: =REVENUE!D27 -> 320000 | E50: =REVENUE!E27 -> 499583.33 | F50: =REVENUE!F27 -> 676666.67 | G50: =REVENUE!G27 -> 1010000
A51: Month 6 | C51: =REVENUE!C28 -> 305555.56 | D51: =REVENUE!D28 -> 320000 | E51: =REVENUE!E28 -> 499583.33 | F51: =REVENUE!F28 -> 676666.67 | G51: =REVENUE!G28 -> 1010000
A52: Total 2nd Quarter | C52: =REVENUE!C29 -> 916666.67 | D52: =REVENUE!D29 -> 960000 | E52: =REVENUE!E29 -> 1498750 | F52: =REVENUE!F29 -> 2030000 | G52: =REVENUE!G29 -> 3030000
A53: Month 7 | C53: =REVENUE!C30 -> 305555.56 | D53: =REVENUE!D30 -> 320000 | E53: =REVENUE!E30 -> 499583.33 | F53: =REVENUE!F30 -> 676666.67 | G53: =REVENUE!G30 -> 1010000
A54: Month 8 | C54: =REVENUE!C31 -> 305555.56 | D54: =REVENUE!D31 -> 320000 | E54: =REVENUE!E31 -> 499583.33 | F54: =REVENUE!F31 -> 676666.67 | G54: =REVENUE!G31 -> 1010000
A55: Month 9 | C55: =REVENUE!C32 -> 305555.56 | D55: =REVENUE!D32 -> 320000 | E55: =REVENUE!E32 -> 499583.33 | F55: =REVENUE!F32 -> 676666.67 | G55: =REVENUE!G32 -> 1010000
A56: Total 3rd Quarter | C56: =REVENUE!C33 -> 916666.67 | D56: =REVENUE!D33 -> 960000 | E56: =REVENUE!E33 -> 1498750 | F56: =REVENUE!F33 -> 2030000 | G56: =REVENUE!G33 -> 3030000
... A61: Total for year | C61: =REVENUE!C38 -> 2750000 | D61: =REVENUE!D38 -> 3840000 | E61: =REVENUE!E38 -> 5995000 | F61: =REVENUE!F38 -> 8120000 | G61: =REVENUE!G38 -> 12120000
A64: Accounts Receivable by Months & Quarters
D65: ($)
C66: Year 1 | D66: Year 2 | E66: Year 3 | F66: Year 4 | G66: Year 5
A67: Month 1 | C67: =IF(C$11<=30,C$11/30*C45,0)+IF(AND(30<C$11,C$11<=60),C45,0)+IF(AND(60<C$11,C$11<=90),C45,0)+IF(AND(90<C$11,C$11<=120),C45,0) -> 0 | D67: =IF(D$11<=30,D$11/30*D45,0)+IF(AND(30<D$11,D$11<=60),D45+(D$11-30)/30*C59,0)+IF(AND(60<D$11,D$11<=90),D45+C59+(D$11-60)/30*C58,0)+IF(AND(90<D$11,D$11<=120),D45+C59+C58+(D$11-90)/30*C57,0) -> 318720
A68: Month 2 | C68: =IF(C$11<=30,C$11/30*C46,0)+IF(AND(30<C$11,C$11<=60),C46+(C$11-30)/30*C45,0)+IF(AND(60<C$11,C$11<=90),C46+C45,0)+IF(AND(90<C$11,C$11<=120),C46+C45,0) -> 0 | D68: =IF(D$11<=30,D$11/30*D46,0)+IF(AND(30<D$11,D$11<=60),D46+(D$11-30)/30*D45,0)+IF(AND(60<D$11,D$11<=90),D46+D45+(D$11-60)/30*C59,0)+IF(AND(90<D$11,D$11<=120),D46+D45+C59+(D$11-90)/30*C58,0) -> 318720
A69: Month 3 | C69: =IF(C$11<=30,C11/30*C47,0)+IF(AND(30<C$11,C$11<=60),C47+(C$11-30)/30*C46,0)+IF(AND(60<C$11,C$11<=90),C47+C46+(C$11-60)/30*C45,0)+IF(AND(90<C$11,C$11<=120),C47+C46+C45,0) -> 0 | D69: =IF(D$11<=30,D$11/30*D47,0)+IF(AND(30<D$11,D$11<=60),D47+(D$11-30)/30*D46,0)+IF(AND(60<D$11,D$11<=90),D47+D46+(D$11-60)/30*D45,0)+IF(AND(90<D$11,D$11<=120),D47+D46+D45+(D$11-90)/30*C59,0) -> 318720 | E69: =IF((E$11<=90),E48*(E$11)/90,0)+IF(AND(90<E$11,E$11<=120),E48+(E$11-90)/90*D60,0) -> 497585 | F69: =IF((F$11<=90),F48*(F$11)/90,0)+IF(AND(90<F$11,F$11<=120),F48+(F$11-90)/90*E60,0) -> 673960 | G69: =IF((G$11<=90),G48*(G$11)/90,0)+IF(AND(90<G$11,G$11<=120),G48+(G$11-90)/90*F60,0) -> 1005960
A70: Month 4 | C70: =IF(C$11<=30,C$11/30*C49,0)+IF(AND(30<C$11,C$11<=60),C49+(C$11-30)/30*C47,0)+IF(AND(60<C$11,C$11<=90),C49+C47+(C$11-60)/30*C46,0)+IF(AND(90<C$11,C$11<=120),C49+C47+C46+(C$11-90)/30*C45,0) -> 304333.33 | D70: =IF(D$11<=30,D$11/30*D49,0)+IF(AND(30<D$11,D$11<=60),D49+(D$11-30)/30*D47,0)+IF(AND(60<D$11,D$11<=90),D49+D47+(D$11-60)/30*D46,0)+IF(AND(90<D$11,D$11<=120),D49+D47+D46+(D$11-90)/30*D45,0) -> 318720
A71: Month 5 | C71: =IF(C$11<=30,C$11/30*C50,0)+IF(AND(30<C$11,C$11<=60),C50+(C$11-30)/30*C49,0)+IF(AND(60<C$11,C$11<=90),C50+C49+(C$11-60)/30*C47,0)+IF(AND(90<C$11,C$11<=120),C50+C49+C47+(C$11-90)/30*C46,0) -> 304333.33 | D71: =IF(D$11<=30,D$11/30*D50,0)+IF(AND(30<D$11,D$11<=60),D50+(D$11-30)/30*D49,0)+IF(AND(60<D$11,D$11<=90),D50+D49+(D$11-60)/30*D47,0)+IF(AND(90<D$11,D$11<=120),D50+D49+D47+(D$11-90)/30*D46,0) -> 318720
A72: Month 6 | C72: =IF(C$11<=30,C$11/30*C51,0)+IF(AND(30<C$11,C$11<=60),C51+(C$11-30)/30*C50,0)+IF(AND(60<C$11,C$11<=90),C51+C50+(C$11-60)/30*C49,0)+IF(AND(90<C$11,C$11<=120),C51+C50+C49+(C$11-90)/30*C47,0) -> 304333.33 | D72: =IF(D$11<=30,D$11/30*D51,0)+IF(AND(30<D$11,D$11<=60),D51+(D$11-30)/30*D50,0)+IF(AND(60<D$11,D$11<=90),D51+D50+(D$11-60)/30*D49,0)+IF(AND(90<D$11,D$11<=120),D51+D50+D49+(D$11-90)/30*D47,0) -> 318720 | E72: =IF((E$11<=90),E52*(E$11)/90,0)+IF(AND(90<E$11,E$11<=120),E52+(E$11-90)/90*E48,0) -> 497585 | F72: =IF((F$11<=90),F52*(F$11)/90,0)+IF(AND(90<F$11,F$11<=120),F52+(F$11-90)/90*F48,0) -> 673960 | G72: =IF((G$11<=90),G52*(G$11)/90,0)+IF(AND(90<G$11,G$11<=120),G52+(G$11-90)/90*G48,0) -> 1005960
A73: Month 7 | C73: =IF(C$11<=30,C$11/30*C53,0)+IF(AND(30<C$11,C$11<=60),C53+(C$11-30)/30*C51,0)+IF(AND(60<C$11,C$11<=90),C53+C51+(C$11-60)/30*C50,0)+IF(AND(90<C$11,C$11<=120),C53+C51+C50+(C$11-90)/30*C49,0) -> 304333.33 | D73: =IF(D$11<=30,D$11/30*D53,0)+IF(AND(30<D$11,D$11<=60),D53+(D$11-30)/30*D51,0)+IF(AND(60<D$11,D$11<=90),D53+D51+(D$11-60)/30*D50,0)+IF(AND(90<D$11,D$11<=120),D53+D51+D50+(D$11-90)/30*D49,0) -> 318720
A74: Month 8 | C74: =IF(C$11<=30,C$11/30*C54,0)+IF(AND(30<C$11,C$11<=60),C54+(C$11-30)/30*C53,0)+IF(AND(60<C$11,C$11<=90),C54+C53+(C$11-60)/30*C51,0)+IF(AND(90<C$11,C$11<=120),C54+C53+C51+(C$11-90)/30*C50,0) -> 304333.33 | D74: =IF(D$11<=30,D$11/30*D54,0)+IF(AND(30<D$11,D$11<=60),D54+(D$11-30)/30*D53,0)+IF(AND(60<D$11,D$11<=90),D54+D53+(D$11-60)/30*D51,0)+IF(AND(90<D$11,D$11<=120),D54+D53+D51+(D$11-90)/30*D50,0) -> 318720
A75: Month 9 | C75: =IF(C$11<=30,C$11/30*C55,0)+IF(AND(30<C$11,C$11<=60),C55+(C$11-30)/30*C54,0)+IF(AND(60<C$11,C$11<=90),C55+C54+(C$11-60)/30*C53,0)+IF(AND(90<C$11,C$11<=120),C55+C54+C53+(C$11-90)/30*C51,0) -> 304333.33 | D75: =IF(D$11<=30,D$11/30*D55,0)+IF(AND(30<D$11,D$11<=60),D55+(D$11-30)/30*D54,0)+IF(AND(60<D$11,D$11<=90),D55+D54+(D$11-60)/30*D53,0)+IF(AND(90<D$11,D$11<=120),D55+D54+D53+(D$11-90)/30*D51,0) -> 318720 | E75: =IF((E$11<=90),E56*(E$11)/90,0)+IF(AND(90<E$11,E$11<=120),E56+(E$11-90)/90*E52,0) -> 497585 | F75: =IF((F$11<=90),F56*(F$11)/90,0)+IF(AND(90<F$11,F$11<=120),F56+(F$11-90)/90*F52,0) -> 673960 | G75: =IF((G$11<=90),G56*(G$11)/90,0)+IF(AND(90<G$11,G$11<=120),G56+(G$11-90)/90*G52,0) -> 1005960
A76: Month 10 | C76: =IF(C$11<=30,C$11/30*C57,0)+IF(AND(30<C$11,C$11<=60),C57+(C$11-30)/30*C55,0)+IF(AND(60<C$11,C$11<=90),C57+C55+(C$11-60)/30*C54,0)+IF(AND(90<C$11,C$11<=120),C57+C55+C54+(C$11-90)/30*C53,0) -> 304333.33 | D76: =IF(D$11<=30,D$11/30*D57,0)+IF(AND(30<D$11,D$11<=60),D57+(D$11-30)/30*D55,0)+IF(AND(60<D$11,D$11<=90),D57+D55+(D$11-60)/30*D54,0)+IF(AND(90<D$11,D$11<=120),D57+D55+D54+(D$11-90)/30*D53,0) -> 318720
A77: Month 11 | C77: =IF(C$11<=30,C$11/30*C58,0)+IF(AND(30<C$11,C$11<=60),C58+(C$11-30)/30*C57,0)+IF(AND(60<C$11,C$11<=90),C58+C57+(C$11-60)/30*C55,0)+IF(AND(90<C$11,C$11<=120),C58+C57+C55+(C$11-90)/30*C54,0) -> 304333.33 | D77: =IF(D$11<=30,D$11/30*D58,0)+IF(AND(30<D$11,D$11<=60),D58+(D$11-30)/30*D57,0)+IF(AND(60<D$11,D$11<=90),D58+D57+(D$11-60)/30*D55,0)+IF(AND(90<D$11,D$11<=120),D58+D57+D55+(D$11-90)/30*D54,0) -> 318720
A78: Month 12 | C78: =IF(C$11<=30,C$11/30*C59,0)+IF(AND(30<C$11,C$11<=60),C59+(C$11-30)/30*C58,0)+IF(AND(60<C$11,C$11<=90),C59+C58+(C$11-60)/30*C57,0)+IF(AND(90<C$11,C$11<=120),C59+C58+C57+(C$11-90)/30*C55,0) -> 304333.33 | D78: =IF(D$11<=30,D$11/30*D59,0)+IF(AND(30<D$11,D$11<=60),D59+(D$11-30)/30*D58,0)+IF(AND(60<D$11,D$11<=90),D59+D58+(D$11-60)/30*D57,0)+IF(AND(90<D$11,D$11<=120),D59+D58+D57+(D$11-90)/30*D55,0) -> 318720 | E78: =IF((E$11<=90),E60*(E$11)/90,0)+IF(AND(90<E$11,E$11<=120),E60+(E$11-90)/90*E56,0) -> 497585 | F78: =IF((F$11<=90),F60*(F$11)/90,0)+IF(AND(90<F$11,F$11<=120),F60+(F$11-90)/90*F56,0) -> 673960 | G78: =IF((G$11<=90),G60*(G$11)/90,0)+IF(AND(90<G$11,G$11<=120),G60+(G$11-90)/90*G56,0) -> 1005960
A81: Inventory by Months & Quarters
D82: ($)
C83: Year 1 | D83: Year 2 | E83: Year 3 | F83: Year 4 | G83: Year 5
A84: Month 1 | C84: =IF(C$18<=30,C$18/30*C45,0)+IF(AND(30<C$18,C$18<=60),C45,0)+IF(AND(60<C$18,C$18<=90),C45,0)+IF(AND(90<C$18,C$18<=120),C45,0) -> 0 | D84: =IF(D$18<=30,D$18/30*D45,0)+IF(AND(30<D$18,D$18<=60),D45+(D$18-30)/30*C59,0)+IF(AND(60<D$18,D$18<=90),D45+C59+(D$18-60)/30*C58,0)+IF(AND(90<D$18,D$18<=120),D45+C59+C58+(D$18-90)/30*C57,0) -> 318720
A85: Month 2 | C85: =IF(C$18<=30,C$18/30*C46,0)+IF(AND(30<C$18,C$18<=60),C46+(C$18-30)/30*C45,0)+IF(AND(60<C$18,C$18<=90),C46+C45,0)+IF(AND(90<C$18,C$18<=120),C46+C45,0) -> 0 | D85: =IF(D$18<=30,D$18/30*D46,0)+IF(AND(30<D$18,D$18<=60),D46+(D$18-30)/30*D45,0)+IF(AND(60<D$18,D$18<=90),D46+D45+(D$18-60)/30*C59,0)+IF(AND(90<D$18,D$18<=120),D46+D45+C59+(D$18-90)/30*C58,0) -> 318720
A86: Month 3 | C86: =IF(C$18<=30,C$18/30*C47,0)+IF(AND(30<C$18,C$18<=60),C47+(C$18-30)/30*C46,0)+IF(AND(60<C$18,C$18<=90),C47+C46+(C$18-60)/30*C45,0)+IF(AND(90<C$18,C$18<=120),C47+C46+C45,0) -> 0 | D86: =IF(D$18<=30,D$18/30*D47,0)+IF(AND(30<D$18,D$18<=60),D47+(D$18-30)/30*D46,0)+IF(AND(60<D$18,D$18<=90),D47+D46+(D$18-60)/30*D45,0)+IF(AND(90<D$18,D$18<=120),D47+D46+D45+(D$18-90)/30*C59,0) -> 318720 | E86: =IF((E$18<=90),E48*(E$18)/90,0)+IF(AND(90<E$18,E$18<=120),E48+(E$18-90)/90*D60,0) -> 401665 | F86: =IF((F$18<=90),F48*(F$18)/90,0)+IF(AND(90<F$18,F$18<=120),F48+(F$18-90)/90*E60,0) -> 544040 | G86: =IF((G$18<=90),G48*(G$18)/90,0)+IF(AND(90<G$18,G$18<=120),G48+(G$18-90)/90*F60,0) -> 812040
A87: Month 4 | C87: =IF(C$18<=30,C$18/30*C49,0)+IF(AND(30<C$18,C$18<=60),C49+(C$18-30)/30*C47,0)+IF(AND(60<C$18,C$18<=90),C49+C47+(C$18-60)/30*C46,0)+IF(AND(90<C$18,C$18<=120),C49+C47+C46+(C$18-90)/30*C45,0) -> 304333.33 | D87: =IF(D$18<=30,D$18/30*D49,0)+IF(AND(30<D$18,D$18<=60),D49+(D$18-30)/30*D47,0)+IF(AND(60<D$18,D$18<=90),D49+D47+(D$18-60)/30*D46,0)+IF(AND(90<D$18,D$18<=120),D49+D47+D46+(D$18-90)/30*D45,0) -> 318720
A88: Month 5 | C88: =IF(C$18<=30,C$18/30*C50,0)+IF(AND(30<C$18,C$18<=60),C50+(C$18-30)/30*C49,0)+IF(AND(60<C$18,C$18<=90),C50+C49+(C$18-60)/30*C47,0)+IF(AND(90<C$18,C$18<=120),C50+C49+C47+(C$18-90)/30*C46,0) -> 304333.33 | D88: =IF(D$18<=30,D$18/30*D50,0)+IF(AND(30<D$18,D$18<=60),D50+(D$18-30)/30*D49,0)+IF(AND(60<D$18,D$18<=90),D50+D49+(D$18-60)/30*D47,0)+IF(AND(90<D$18,D$18<=120),D50+D49+D47+(D$18-90)/30*D46,0) -> 318720
A89: Month 6 | C89: =IF(C$18<=30,C$18/30*C51,0)+IF(AND(30<C$18,C$18<=60),C51+(C$18-30)/30*C50,0)+IF(AND(60<C$18,C$18<=90),C51+C50+(C$18-60)/30*C49,0)+IF(AND(90<C$18,C$18<=120),C51+C50+C49+(C$18-90)/30*C47,0) -> 304333.33 | D89: =IF(D$18<=30,D$18/30*D51,0)+IF(AND(30<D$18,D$18<=60),D51+(D$18-30)/30*D50,0)+IF(AND(60<D$18,D$18<=90),D51+D50+(D$18-60)/30*D49,0)+IF(AND(90<D$18,D$18<=120),D51+D50+D49+(D$18-90)/30*D47,0) -> 318720 | E89: =IF((E$18<=90),E52*(E$18)/90,0)+IF(AND(90<E$18,E$18<=120),E52+(E$18-90)/90*E48,0) -> 401665 | F89: =IF((F$18<=90),F52*(F$18)/90,0)+IF(AND(90<F$18,F$18<=120),F48+(F$18-90)/90*E80,0) -> 544040 | G89: =IF((G$18<=90),G52*(G$18)/90,0)+IF(AND(90<G$18,G$18<=120),G48+(G$18-90)/90*F80,0) -> 812040
A90: Month 7 | C90: =IF(C$18<=30,C$18/30*C53,0)+IF(AND(30<C$18,C$18<=60),C53+(C$18-30)/30*C51,0)+IF(AND(60<C$18,C$18<=90),C53+C51+(C$18-60)/30*C50,0)+IF(AND(90<C$18,C$18<=120),C53+C51+C50+(C$18-90)/30*C49,0) -> 304333.33 | D90: =IF(D$18<=30,D$18/30*D53,0)+IF(AND(30<D$18,D$18<=60),D53+(D$18-30)/30*D51,0)+IF(AND(60<D$18,D$18<=90),D53+D51+(D$18-60)/30*D50,0)+IF(AND(90<D$18,D$18<=120),D53+D51+D50+(D$18-90)/30*D49,0) -> 318720
A91: Month 8 | C91: =IF(C$18<=30,C$18/30*C54,0)+IF(AND(30<C$18,C$18<=60),C54+(C$18-30)/30*C53,0)+IF(AND(60<C$18,C$18<=90),C54+C53+(C$18-60)/30*C51,0)+IF(AND(90<C$18,C$18<=120),C54+C53+C51+(C$18-90)/30*C50,0) -> 304333.33 | D91: =IF(D$18<=30,D$18/30*D54,0)+IF(AND(30<D$18,D$18<=60),D54+(D$18-30)/30*D53,0)+IF(AND(60<D$18,D$18<=90),D54+D53+(D$18-60)/30*D51,0)+IF(AND(90<D$18,D$18<=120),D54+D53+D51+(D$18-90)/30*D50,0) -> 318720
A92: Month 9 | C92: =IF(C$18<=30,C$18/30*C55,0)+IF(AND(30<C$18,C$18<=60),C55+(C$18-30)/30*C54,0)+IF(AND(60<C$18,C$18<=90),C55+C54+(C$18-60)/30*C53,0)+IF(AND(90<C$18,C$18<=120),C55+C54+C53+(C$18-90)/30*C51,0) -> 304333.33 | D92: =IF(D$18<=30,D$18/30*D55,0)+IF(AND(30<D$18,D$18<=60),D55+(D$18-30)/30*D54,0)+IF(AND(60<D$18,D$18<=90),D55+D54+(D$18-60)/30*D53,0)+IF(AND(90<D$18,D$18<=120),D55+D54+D53+(D$18-90)/30*D51,0) -> 318720 | E92: =IF((E$18<=90),E56*(E$18)/90,0)+IF(AND(90<E$18,E$18<=120),E56+(E$18-90)/90*E52,0) -> 401665 | F92: =IF((F$18<=90),F56*(F$18)/90,0)+IF(AND(90<F$18,F$18<=120),#REF!+(F$18-90)/90*F52,0) -> 544040 | G92: =IF((G$18<=90),G56*(G$18)/90,0)+IF(AND(90<G$18,G$18<=120),#REF!+(G$18-90)/90*G52,0) -> 812040
A93: Month 10 | C93: =IF(C$18<=30,C$18/30*C57,0)+IF(AND(30<C$18,C$18<=60),C57+(C$18-30)/30*C55,0)+IF(AND(60<C$18,C$18<=90),C57+C55+(C$18-60)/30*C54,0)+IF(AND(90<C$18,C$18<=120),C57+C55+C54+(C$18-90)/30*C53,0) -> 304333.33 | D93: =IF(D$18<=30,D$18/30*D57,0)+IF(AND(30<D$18,D$18<=60),D57+(D$18-30)/30*D55,0)+IF(AND(60<D$18,D$18<=90),D57+D55+(D$18-60)/30*D54,0)+IF(AND(90<D$18,D$18<=120),D57+D55+D54+(D$18-90)/30*D53,0) -> 318720
A94: Month 11 | C94: =IF(C$18<=30,C$18/30*C58,0)+IF(AND(30<C$18,C$18<=60),C58+(C$18-30)/30*C57,0)+IF(AND(60<C$18,C$18<=90),C58+C57+(C$18-60)/30*C55,0)+IF(AND(90<C$18,C$18<=120),C58+C57+C55+(C$18-90)/30*C54,0) -> 304333.33 | D94: =IF(D$18<=30,D$18/30*D58,0)+IF(AND(30<D$18,D$18<=60),D58+(D$18-30)/30*D57,0)+IF(AND(60<D$18,D$18<=90),D58+D57+(D$18-60)/30*D55,0)+IF(AND(90<D$18,D$18<=120),D58+D57+D55+(D$18-90)/30*D54,0) -> 318720
A95: Month 12 | C95: =IF(C$18<=30,C$18/30*C59,0)+IF(AND(30<C$18,C$18<=60),C59+(C$18-30)/30*C58,0)+IF(AND(60<C$18,C$18<=90),C59+C58+(C$18-60)/30*C57,0)+IF(AND(90<C$18,C$18<=120),C59+C58+C57+(C$18-90)/30*C55,0) -> 304333.33 | D95: =IF(D$18<=30,D$18/30*D59,0)+IF(AND(30<D$18,D$18<=60),D59+(D$18-30)/30*D58,0)+IF(AND(60<D$18,D$18<=90),D59+D58+(D$18-60)/30*D57,0)+IF(AND(90<D$18,D$18<=120),D59+D58+D57+(D$18-90)/30*D55,0) -> 318720 | E95: =IF((E$18<=90),E60*(E$18)/90,0)+IF(AND(90<E$18,E$18<=120),E60+(E$18-90)/90*E56,0) -> 401665 | F95: =IF((F$18<=90),F60*(F$18)/90,0)+IF(AND(90<F$18,F$18<=120),F60+(F$18-90)/90*F56,0) -> 544040 | G95: =IF((G$18<=90),G60*(G$18)/90,0)+IF(AND(90<G$18,G$18<=120),G60+(G$18-90)/90*G56,0) -> 812040
A98: Other Current Assets by Months & Quarters
D99: ($)
C100: Year 1 | D100: Year 2 | E100: Year 3 | F100: Year 4 | G100: Year 5
A101: Month 1 | C101: =IF(C$18<=30,C$18/30*C45,0)+IF(AND(30<C$18,C$18<=60),C45,0)+IF(AND(60<C$18,C$18<=90),C45,0)+IF(AND(90<C$18,C$18<=120),C45,0) -> 0 | D101: =IF(D$24<=30,D$24/30*D45,0)+IF(AND(30<D$24,D$24<=60),D45+(D$24-30)/30*C59,0)+IF(AND(60<D$24,D$24<=90),D45+C59+(D$24-60)/30*C58,0)+IF(AND(90<D$24,D$24<=120),D45+C59+C58+(D$24-90)/30*C57,0) -> 38400
A102: Month 2 | C102: =IF(C$18<=30,C$18/30*C46,0)+IF(AND(30<C$18,C$18<=60),C46+(C$18-30)/30*C45,0)+IF(AND(60<C$18,C$18<=90),C46+C45,0)+IF(AND(90<C$18,C$18<=120),C46+C45,0) -> 0 | D102: =IF(D$24<=30,D$24/30*D46,0)+IF(AND(30<D$24,D$24<=60),D46+(D$24-30)/30*D45,0)+IF(AND(60<D$24,D$24<=90),D46+D45+(D$24-60)/30*C59,0)+IF(AND(90<D$24,D$24<=120),D46+D45+C59+(D$24-90)/30*C58,0) -> 38400
A103: Month 3 | C103: =IF(C$18<=30,C$18/30*C47,0)+IF(AND(30<C$18,C$18<=60),C47+(C$18-30)/30*C46,0)+IF(AND(60<C$18,C$18<=90),C47+C46+(C$18-60)/30*C45,0)+IF(AND(90<C$18,C$18<=120),C47+C46+C45,0) -> 0 | D103: =IF(D$24<=30,D$24/30*D47,0)+IF(AND(30<D$24,D$24<=60),D47+(D$24-30)/30*D46,0)+IF(AND(60<D$24,D$24<=90),D47+D47+(D$24-60)/30*D45,0)+IF(AND(90<D$24,D$24<=120),D47+D46+D45+(D$24-90)/30*C59,0) -> 38400 | E103: =IF((E$24<=90),E48*(E$24)/90,0)+IF(AND(90<E$24,E$24<=120),E48+(E$24-90)/90*D60,0) -> 59950 | F103: =IF((F$24<=90),F48*(F$24)/90,0)+IF(AND(90<F$24,F$24<=120),F48+(F$24-90)/90*E60,0) -> 81200 | G103: =IF((G$24<=90),G48*(G$24)/90,0)+IF(AND(90<G$24,G$24<=120),G48+(G$24-90)/90*F60,0) -> 121200
A104: Month 4 | C104: =IF(C$24<=30,C$24/30*C49,0)+IF(AND(30<C$24,C$24<=60),C49+(C$24-30)/30*C47,0)+IF(AND(60<C$24,C$24<=90),C49+C47+(C$24-60)/30*C46,0)+IF(AND(90<C$24,C$24<=120),C49+C47+C46+(C$24-90)/30*C45,0) -> 36666.667 | D104: =IF(D$24<=30,D$24/30*D49,0)+IF(AND(30<D$24,D$24<=60),D49+(D$24-30)/30*D47,0)+IF(AND(60<D$24,D$24<=90),D49+D47+(D$24-60)/30*D46,0)+IF(AND(90<D$24,D$24<=120),D49+D47+D46+(D$24-90)/30*D45,0) -> 38400
A105: Month 5 | C105: =IF(C$24<=30,C$24/30*C50,0)+IF(AND(30<C$24,C$24<=60),C50+(C$24-30)/30*C49,0)+IF(AND(60<C$24,C$24<=90),C50+C49+(C$24-60)/30*C47,0)+IF(AND(90<C$24,C$24<=120),C50+C49+C47+(C$24-90)/30*C46,0) -> 36666.667 | D105: =IF(D$24<=30,D$24/30*D50,0)+IF(AND(30<D$24,D$24<=60),D50+(D$24-30)/30*D49,0)+IF(AND(60<D$24,D$24<=90),D50+D49+(D$24-60)/30*D47,0)+IF(AND(90<D$24,D$24<=120),D50+D49+D47+(D$24-90)/30*D46,0) -> 38400
A106: Month 6 | C106: =IF(C$24<=30,C$24/30*C51,0)+IF(AND(30<C$24,C$24<=60),C51+(C$24-30)/30*C50,0)+IF(AND(60<C$24,C$24<=90),C51+C50+(C$24-60)/30*C49,0)+IF(AND(90<C$24,C$24<=120),C51+C50+C49+(C$24-90)/30*C47,0) -> 36666.667 | D106: =IF(D$24<=30,D$24/30*D51,0)+IF(AND(30<D$24,D$24<=60),D51+(D$24-30)/30*D50,0)+IF(AND(60<D$24,D$24<=90),D51+D50+(D$24-60)/30*D49,0)+IF(AND(90<D$24,D$24<=120),D51+D50+D49+(D$24-90)/30*D47,0) -> 38400 | E106: =IF((E$24<=90),E52*(E$24)/90,0)+IF(AND(90<E$24,E$24<=120),E52+(E$24-90)/90*E48,0) -> 59950 | F106: =IF((F$24<=90),F52*(F$24)/90,0)+IF(AND(90<F$24,F$24<=120),F52+(F$24-90)/90*F48,0) -> 81200 | G106: =IF((G$24<=90),G52*(G$24)/90,0)+IF(AND(90<G$24,G$24<=120),G52+(G$24-90)/90*G48,0) -> 121200
A107: Month 7 | C107: =IF(C$24<=30,C$24/30*C53,0)+IF(AND(30<C$24,C$24<=60),C53+(C$24-30)/30*C51,0)+IF(AND(60<C$24,C$24<=90),C53+C51+(C$24-60)/30*C50,0)+IF(AND(90<C$24,C$24<=120),C53+C51+C50+(C$24-90)/30*C49,0) -> 36666.667 | D107: =IF(D$24<=30,D$24/30*D53,0)+IF(AND(30<D$24,D$24<=60),D53+(D$24-30)/30*D51,0)+IF(AND(60<D$24,D$24<=90),D53+D51+(D$24-60)/30*D50,0)+IF(AND(90<D$24,D$24<=120),D53+D51+D50+(D$24-90)/30*D49,0) -> 38400
A108: Month 8 | C108: =IF(C$24<=30,C$24/30*C54,0)+IF(AND(30<C$24,C$24<=60),C54+(C$24-30)/30*C53,0)+IF(AND(60<C$24,C$24<=90),C54+C53+(C$24-60)/30*C51,0)+IF(AND(90<C$24,C$24<=120),C54+C53+C51+(C$24-90)/30*C50,0) -> 36666.667 | D108: =IF(D$24<=30,D$24/30*D54,0)+IF(AND(30<D$24,D$24<=60),D54+(D$24-30)/30*D53,0)+IF(AND(60<D$24,D$24<=90),D54+D53+(D$24-60)/30*D51,0)+IF(AND(90<D$24,D$24<=120),D54+D53+D51+(D$24-90)/30*D50,0) -> 38400
A109: Month 9 | C109: =IF(C$24<=30,C$24/30*C55,0)+IF(AND(30<C$24,C$24<=60),C55+(C$24-30)/30*C54,0)+IF(AND(60<C$24,C$24<=90),C55+C54+(C$24-60)/30*C53,0)+IF(AND(90<C$24,C$24<=120),C55+C54+C53+(C$24-90)/30*C51,0) -> 36666.667 | D109: =IF(D$24<=30,D$24/30*D55,0)+IF(AND(30<D$24,D$24<=60),D55+(D$24-30)/30*D54,0)+IF(AND(60<D$24,D$24<=90),D55+D54+(D$24-60)/30*D53,0)+IF(AND(90<D$24,D$24<=120),D55+D54+D53+(D$24-90)/30*D51,0) -> 38400 | E109: =IF((E$24<=90),E56*(E$24)/90,0)+IF(AND(90<E$24,E$24<=120),E56+(E$24-90)/90*E52,0) -> 59950 | F109: =IF((F$24<=90),F56*(F$24)/90,0)+IF(AND(90<F$24,F$24<=120),F56+(F$24-90)/90*F52,0) -> 81200 | G109: =IF((G$24<=90),G56*(G$24)/90,0)+IF(AND(90<G$24,G$24<=120),G56+(G$24-90)/90*G52,0) -> 121200
A110: Month 10 | C110: =IF(C$24<=30,C$24/30*C57,0)+IF(AND(30<C$24,C$24<=60),C57+(C$24-30)/30*C55,0)+IF(AND(60<C$24,C$24<=90),C57+C55+(C$24-60)/30*C54,0)+IF(AND(90<C$24,C$24<=120),C57+C55+C54+(C$24-90)/30*C53,0) -> 36666.667 | D110: =IF(D$24<=30,D$24/30*D57,0)+IF(AND(30<D$24,D$24<=60),D57+(D$24-30)/30*D55,0)+IF(AND(60<D$24,D$24<=90),D57+D55+(D$24-60)/30*D54,0)+IF(AND(90<D$24,D$24<=120),D57+D55+D54+(D$24-90)/30*D53,0) -> 38400
A111: Month 11 | C111: =IF(C$24<=30,C$24/30*C58,0)+IF(AND(30<C$24,C$24<=60),C58+(C$24-30)/30*C57,0)+IF(AND(60<C$24,C$24<=90),C58+C57+(C$24-60)/30*C55,0)+IF(AND(90<C$24,C$24<=120),C58+C57+C55+(C$24-90)/30*C54,0) -> 36666.667 | D111: =IF(D$24<=30,D$24/30*D58,0)+IF(AND(30<D$24,D$24<=60),D58+(D$24-30)/30*D57,0)+IF(AND(60<D$24,D$24<=90),D58+D57+(D$24-60)/30*D55,0)+IF(AND(90<D$24,D$24<=120),D58+D57+D55+(D$24-90)/30*D54,0) -> 38400
A112: Month 12 | C112: =IF(C$24<=30,C$24/30*C59,0)+IF(AND(30<C$24,C$24<=60),C59+(C$24-30)/30*C58,0)+IF(AND(60<C$24,C$24<=90),C59+C58+(C$24-60)/30*C57,0)+IF(AND(90<C$24,C$24<=120),C59+C58+C57+(C$24-90)/30*C55,0) -> 36666.667 | D112: =IF(D$24<=30,D$24/30*D59,0)+IF(AND(30<D$24,D$24<=60),D59+(D$24-30)/30*D58,0)+IF(AND(60<D$24,D$24<=90),D59+D58+(D$24-60)/30*D57,0)+IF(AND(90<D$24,D$24<=120),D59+D58+D57+(D$24-90)/30*D55,0) -> 38400 | E112: =IF((E$24<=90),E60*(E$24)/90,0)+IF(AND(90<E$24,E$24<=120),E60+(E$24-90)/90*E56,0) -> 59950 | F112: =IF((F$24<=90),F60*(F$24)/90,0)+IF(AND(90<F$24,F$24<=120),F60+(F$24-90)/90*F56,0) -> 81200 | G112: =IF((G$24<=90),G60*(G$24)/90,0)+IF(AND(90<G$24,G$24<=120),G60+(G$24-90)/90*G56,0) -> 121200
A115: Accounts Payble & Accrued Expenses by Months & Quarters
D116: ($)
C117: Year 1 | D117: Year 2 | E117: Year 3 | F117: Year 4 | G117: Year 5
A118: Month 1 | C118: =IF(C$30<=30,C$30/30*C28,0)+IF(AND(30<C$30,C$30<=60),C28,0)+IF(AND(60<C$30,C$30<=90),C28,0)+IF(AND(90<C$30,C$30<=120),C28,0) -> 0 | D118: =IF(D$30<=30,D$30/30*D28,0)+IF(AND(30<D$30,D$30<=60),D28+(D$30-30)/30*C59,0)+IF(AND(60<D$30,D$30<=90),D28+C42+(D$30-60)/30*C58,0)+IF(AND(90<D$30,D$30<=120),D28+C42+C41+(D$30-90)/30*C57,0) -> 13444.444
A119: Month 2 | C119: =IF(C$30<=30,C$30/30*C29,0)+IF(AND(30<C$30,C$30<=60),C29+(C$30-30)/30*C28,0)+IF(AND(60<C$30,C$30<=90),C29+C28,0)+IF(AND(90<C$30,C$30<=120),C29+C28,0) -> 0.087 | D119: =IF(D$30<=30,D$30/30*D29,0)+IF(AND(30<D$30,D$30<=60),D29+(D$30-30)/30*D28,0)+IF(AND(60<D$30,D$30<=90),D29+D28+(D$30-60)/30*C42,0)+IF(AND(90<D$30,D$30<=120),D29+D28+C42+(D$30-90)/30*C41,0) -> 0.087
A120: Month 3 | C120: =IF(C$30<=30,C$30/30*C30,0)+IF(AND(30<C$30,C$30<=60),C30+(C$30-30)/30*C29,0)+IF(AND(60<C$30,C$30<=90),C30+C29+(C$30-60)/30*C28,0)+IF(AND(90<C$30,C$30<=120),C30+C29+C28,0) -> 31.323828 | D120: =IF(D$30<=30,D$30/30*D30,0)+IF(AND(30<D$30,D$30<=60),D30+(D$30-30)/30*D29,0)+IF(AND(60<D$30,D$30<=90),D30+D29+(D$30-60)/30*D28,0)+IF(AND(90<D$30,D$30<=120),D30+D29+D28+(D$30-90)/30*C42,0) -> 31.323828 | E120: =IF((E$30<=90),E48*(E$30)/90,0)+IF(AND(90<E$30,E$30<=120),E48+(E$30-90)/90*D60,0) -> 521565 | F120: =IF((F$30<=90),F48*(F$30)/90,0)+IF(AND(90<F$30,F$30<=120),F48+(F$30-90)/90*E60,0) -> 706440 | G120: =IF((G$30<=90),G48*(G$30)/90,0)+IF(AND(90<G$30,G$30<=120),G48+(G$30-90)/90*F60,0) -> 1054440
A121: Month 4 | C121: =IF(C$30<=30,C$30/30*C49,0)+IF(AND(30<C$30,C$30<=60),C49+(C$30-30)/30*C47,0)+IF(AND(60<C$30,C$30<=90),C49+C47+(C$30-60)/30*C46,0)+IF(AND(90<C$30,C$30<=120),C49+C47+C46+(C$30-90)/30*C45,0) -> 305555.56 | D121: =IF(D$30<=30,D$30/30*D49,0)+IF(AND(30<D$30,D$30<=60),D49+(D$30-30)/30*D47,0)+IF(AND(60<D$30,D$30<=90),D49+D47+(D$30-60)/30*D46,0)+IF(AND(90<D$30,D$30<=120),D49+D47+D46+(D$30-90)/30*D45,0) -> 334080
...

Sheet FUNDING
A1: XYZ Company
A2: Funding Projections
A3: Years 1 to 5
A4: ($)
B5: Begin | C5: Year 1 | D5: Year 2 | E5: Year 3 | F5: Year 4 | G5: Year 5
A6: Beginning Cash | B6: 2500000
A7: Equity
A8: Common | B8: 1500000 | C8: 500000 | D8: 750000 | E8: 600000 | F8: 1000000 | G8: 800000
A9: Increase / (Decrease) Previous Period | C9: =C8-B8 -> -1000000 | D9: =D8-C8 -> 250000 | E9: =E8-D8 -> -150000 | F9: =F8-E8 -> 400000 | G9: =G8-F8 -> -200000
A10: Preferred
A11: A Round | B11: 1200000 | C11: 1200000 | D11: 1200000 | E11: 1200000 | F11: 1200000 | G11: 1200000
A12: B Round | D12: 750000 | E12: 750000 | F12: 750000 | G12: 750000
A13: Total Preferred | B13: =SUM(B11:B12) -> 1200000 | C13: =SUM(C11:C12) -> 1200000 | D13: =SUM(D11:D12) -> 1950000 | E13: =SUM(E11:E12) -> 1950000 | F13: =SUM(F11:F12) -> 1950000 | G13: =SUM(G11:G12) -> 1950000
A14: Increase / (Decrease) Previous Period | C14: =C13-B13 -> 0 | D14: =D13-C13 -> 750000 | E14: =E13-D13 -> 0 | F14: =F13-E13 -> 0 | G14: =G13-F13 -> 0
A15: Total Equity | B15: =B8+B13 -> 2700000 | C15: =C8+C13 -> 1700000 | D15: =D8+D13 -> 2700000 | E15: =E8+E13 -> 2550000 | F15: =F8+F13 -> 2950000 | G15: =G8+G13 -> 2750000
A17: Debt
A18: Short Term Debt | C18: 450000 | D18: 350000 | E18: 800000 | F18: 100000
A19: Increase / (Decrease) Previous Period | C19: =C18-B18 -> 450000 | D19: =D18-C18 -> -100000 | E19: =E18-D18 -> 450000 | F19: =F18-E18 -> -700000 | G19: =G18-F18 -> -100000
A21: Long Term Debt
A22: Current Portion | C22: 250000 | D22: 275000 | E22: 300000 | F22: 325000 | G22: 350000
A23: Long Term Portion | C23: 2250000 | D23: 2100000 | E23: 1800000 | F23: 1400000 | G23: 1000000
A24: Total Long Term Debt | C24: =C22+C23 -> 2500000 | D24: =D22+D23 -> 2375000 | E24: =E22+E23 -> 2100000 | F24: =F22+F23 -> 1725000 | G24: =G22+G23 -> 1350000
A26: Increase / (Decrease) Previous Period
A27: Current Portion | C27: =C22-B22 -> 250000 | D27: =D22-C22 -> 25000 | E27: =E22-D22 -> 25000 | F27: =F22-E22 -> 25000 | G27: =G22-F22 -> 25000
A28: Long Term Protion | C28: =C23-B23 -> 2250000 | D28: =D23-C23 -> -150000 | E28: =E23-D23 -> -300000 | F28: =F23-E23 -> -400000 | G28: =G23-F23 -> -400000
A29: Total Long Term Debt | C29: =SUM(C27:C28) -> 2500000 | D29: =SUM(D27:D28) -> -125000 | E29: =SUM(E27:E28) -> -275000 | F29: =SUM(F27:F28) -> -375000 | G29: =SUM(G27:G28) -> -375000
A31: Total Equity & Debt | B31: =B15+B18+B24 -> 2700000 | C31: =C15+C18+C24 -> 4650000 | D31: =D15+D18+D24 -> 5425000 | E31: =E15+E18+E24 -> 5450000 | F31: =F15+F18+F24 -> 4775000 | G31: =G15+G18+G24 -> 4100000
A33: Interest
A34: Interest Rate
A35: Short Term Debt | C35: 0.098 | D35: 0.098 | E35: 0.098 | F35: 0.098 | G35: 0.098
A36: Long Term Debt | C36: 0.072 | D36: 0.072 | E36: 0.072 | F36: 0.072 | G36: 0.072
A38: Interest Expense
A39: Short Term Debt | C39: =C35*C18 -> 44100 | D39: =D35*D18 -> 34300 | E39: =E35*E18 -> 78400 | F39: =F35*F18 -> 9800 | G39: =G35*G18 -> 0
A40: Long Term Debt | C40: =C36*C24 -> 180000 | D40: =D36*D24 -> 171000 | E40: =E36*E24 -> 151200 | F40: =F36*F24 -> 124200 | G40: =G36*G24 -> 97200
A41: Total Interest | C41: =SUM(C39:C40) -> 224100 | D41: =SUM(D39:D40) -> 205300 | E41: =SUM(E39:E40) -> 229600 | F41: =SUM(F39:F40) -> 134000 | G41: =SUM(G39:G40) -> 97200
A43: Interest Income
A44: Interest Rate | C44: 0.032 | D44: 0.032 | E44: 0.032 | F44: 0.032 | G44: 0.032
A45: Interest Income | C45: 10000 | D45: 10000 | E45: 10000 | F45: 10000 | G45: 10000
A47: Retained Earnings
A48: Net Income | C48: =INCOME!C34 -> -476628.57 | D48: =INCOME!D34 -> -416600 | E48: =INCOME!E34 -> 488352.86 | F48: =INCOME!F34 -> 1026330.3 | G48: =INCOME!G34 -> 2147938.6
A49: Dividends | D49: 30000 | E49: 40000 | F49: 50000 | G49: 50000
A50: Increase / (Decrease) Retained Earnings | C50: =C48-C49 -> -476628.57 | D50: =D48-D49 -> -446600 | E50: =E48-E49 -> 448352.86 | F50: =F48-F49 -> 976330.29 | G50: =G48-G49 -> 2097938.6
A51: Beginning Retained Earnings | C51: 0 | D51: =C52 -> -476628.57 | E51: =D52 -> -923228.57 | F51: =E52 -> -474875.71 | G51: =F52 -> 501454.57
A52: Ending Retained Earnings | C52: =C50+C51 -> -476628.57 | D52: =D50+D51 -> -923228.57 | E52: =E50+E51 -> -474875.71 | F52: =F50+F51 -> 501454.57 | G52: =G50+G51 -> 2599393.1

Sheet INCOME
A1: XYZ Company | M1: Checksum | N1: =SUM(C19:G20,C34:G35,BALANCE!B15:G15,BALANCE!B23:G23,BALANCE!B31:G32,CASHFLOW!C15:G15,CASHFLOW!C20:G20,CASHFLOW!C29:G29,CASHFLOW!C31:G31,CASHFLOW!C33:G34,BREAKEVEN!C21:G21,BREAKEVEN!C19:G20,BREAKEVEN!C23:G23,BREAKEVEN!C25:G25,'INCOME-MOS'!C35:P35,'INCOME-MOS'!C68:P68,'INCOME-MOS'!C102:T102,'CASHFLOW-MOS'!B20:O20,'CASHFLOW-MOS'!B25:O25,'CASHFLOW-MOS'!B34:O34,'CASHFLOW-MOS'!B36:O36,'CASHFLOW-MOS'!B38:O39,'CASHFLOW-MOS'!B56:O56,'CASHFLOW-MOS'!B61:O61,'CASHFLOW-MOS'!B70:O70,'CASHFLOW-MOS'!B72:O72,'CASHFLOW-MOS'!B74:O75,'CASHFLOW-MOS'!B92:S92,'CASHFLOW-MOS'!B97:S97,'CASHFLOW-MOS'!B106:S106,'CASHFLOW-MOS'!B108:S108,'CASHFLOW-MOS'!B110:S111,SUMMARY!C18:G18,SUMMARY!C34:G36) -> 5.8459393e+08
A2: Income Statement
A3: Years 1 to 5
A4: ($)
C5: Year 1 | D5: Year 2 | E5: Year 3 | F5: Year 4 | G5: Year 5
A7: NET REVENUES | C7: =REVENUE!C16 -> 2750000 | D7: =REVENUE!D16 -> 3840000 | E7: =REVENUE!E16 -> 5995000 | F7: =REVENUE!F16 -> 8120000 | G7: =REVENUE!G16 -> 12120000
A9: COST OF REVENUE | C9: ='COST OF REV'!C32 -> 1325528.6 | D9: ='COST OF REV'!D32 -> 1916000 | E9: ='COST OF REV'!E32 -> 2514057.1 | F9: ='COST OF REV'!F32 -> 3114700 | G9: ='COST OF REV'!G32 -> 4063835.7
A10: % of Revenues | C10: =C9/C7 -> 0.48201039 | D10: =D9/D7 -> 0.49895833 | E10: =E9/E7 -> 0.41935899 | F10: =F9/F7 -> 0.38358374 | G10: =G9/G7 -> 0.33529998
A12: GROSS PROFIT | C12: =C7-C9 -> 1424471.4 | D12: =D7-D9 -> 1924000 | E12: =E7-E9 -> 3480942.9 | F12: =F7-F9 -> 5005300 | G12: =G7-G9 -> 8056164.3
A13: % of Revenues | C13: =C12/C7 -> 0.51798961 | D13: =D12/D7 -> 0.50104167 | E13: =E12/E7 -> 0.58064101 | F13: =F12/F7 -> 0.61641626 | G13: =G12/G7 -> 0.66470002
A15: OPERATING EXPENSES
A16: Sales & Marketing | C16: ='OPER EXP'!C16 -> 659500 | D16: ='OPER EXP'!D16 -> 829400 | E16: ='OPER EXP'!E16 -> 1121090 | F16: ='OPER EXP'!F16 -> 1418000 | G16: ='OPER EXP'!G16 -> 1912400
A17: Research & Development | C17: ='OPER EXP'!C25 -> 287500 | D17: ='OPER EXP'!D25 -> 561450 | E17: ='OPER EXP'!E25 -> 773710 | F17: ='OPER EXP'!F25 -> 969000 | G17: ='OPER EXP'!G25 -> 1214800
A18: General and Administration | C18: ='OPER EXP'!C38 -> 620000 | D18: ='OPER EXP'!D38 -> 869450 | E18: ='OPER EXP'!E38 -> 1058190 | F18: ='OPER EXP'!F38 -> 1313666.7 | G18: ='OPER EXP'!G38 -> 1591866.7
A19: Total Operating Expenses | C19: ='OPER EXP'!C41 -> 1567000 | D19: ='OPER EXP'!D41 -> 2260300 | E19: ='OPER EXP'!E41 -> 2952990 | F19: ='OPER EXP'!F41 -> 3700666.7 | G19: ='OPER EXP'!G41 -> 4719066.7
A20: % of Revenues | C20: ='OPER EXP'!C42 -> 0.56981818 | D20: ='OPER EXP'!D42 -> 0.58861979 | E20: ='OPER EXP'!E42 -> 0.49257548 | F20: ='OPER EXP'!F42 -> 0.45574713 | G20: ='OPER EXP'!G42 -> 0.38936194
A22: EARNINGS FROM OPERATIONS | C22: =C12-C19 -> -142528.57 | D22: =D12-D19 -> -336300 | E22: =E12-E19 -> 527952.86 | F22: =F12-F19 -> 1304633.3 | G22: =G12-G19 -> 3337097.6
A24: EXTRAORDINARY INCOME / (EXPENSE) | C24: =EXTRA!C16 -> -120000 | D24: =EXTRA!D16 -> 115000 | E24: =EXTRA!E16 -> 180000 | F24: =EXTRA!F16 -> 260000 | G24: =EXTRA!G16 -> 330000
A26: EARNINGS BEFORE INTEREST & TAXES | C26: =C22+C24 -> -262528.57 | D26: =D22+D24 -> -221300 | E26: =E22+E24 -> 707952.86 | F26: =F22+F24 -> 1564633.3 | G26: =G22+G24 -> 3667097.6
A28: INTEREST INCOME / (EXPENSE) | C28: =-FUNDING!C41+FUNDING!C45 -> -214100 | D28: =-FUNDING!D41+FUNDING!D45 -> -195300 | E28: =-FUNDING!E41+FUNDING!E45 -> -219600 | F28: =-FUNDING!F41+FUNDING!F45 -> -124000 | G28: =-FUNDING!G41+FUNDING!G45 -> -87200
A30: NET EARNINGS BEFORE TAXES | C30: =C26+C28 -> -476628.57 | D30: =D26+D28 -> -416600 | E30: =E26+E28 -> 488352.86 | F30: =F26+F28 -> 1440633.3 | G30: =G26+G28 -> 3579897.6
A32: TAXES | C32: =TAXES!C14 -> 0 | D32: =TAXES!D14 -> 0 | E32: =TAXES!E14 -> 0 | F32: =TAXES!F14 -> -414303.05 | G32: =TAXES!G14 -> -1431959
A34: NET EARNINGS | C34: =C30+C32 -> -476628.57 | D34: =D30+D32 -> -416600 | E34: =E30+E32 -> 488352.86 | F34: =F30+F32 -> 1026330.3 | G34: =G30+G32 -> 2147938.6
A35: % of Revenues | C35: =C34/C7 -> -0.17331948 | D35: =D34/D7 -> -0.10848958 | E35: =E34/E7 -> 0.081460026 | F35: =F34/F7 -> 0.12639536 | G35: =G34/G7 -> 0.17722265

Sheet BALANCE
A1: XYZ Company | M1: Checksum | N1: =SUM(B9:G9,C10:G14,B13:B14,B15:G15,C19:G23,B22:B23,B19,B25:G25,C28:G32,B31:B32,B28:B29) -> 1.7303034e+08
A2: Balance Sheet
A3: Years 1 to 5
A4: ($)
B5: Begin | C5: Year 1 | D5: Year 2 | E5: Year 3 | F5: Year 4 | G5: Year 5
A7: ASSETS
A8: CURRENT ASSETS
A9: Cash | B9: =FUNDING!B6 -> 2500000 | C9: =CASHFLOW!C34 -> 3439333.3 | D9: =CASHFLOW!D34 -> 3394540 | E9: =CASHFLOW!E34 -> 3474425 | F9: =CASHFLOW!F34 -> 3360047 | G9: =CASHFLOW!G34 -> 4297937.9
A10: Accounts Receivable | C10: =WORKCAP!C12 -> 304333.33 | D10: =WORKCAP!D12 -> 318720 | E10: =WORKCAP!E12 -> 497585 | F10: =WORKCAP!F12 -> 673960 | G10: =WORKCAP!G12 -> 1005960
A11: Inventories | C11: =WORKCAP!C19 -> 304333.33 | D11: =WORKCAP!D19 -> 318720 | E11: =WORKCAP!E19 -> 401665 | F11: =WORKCAP!F19 -> 544040 | G11: =WORKCAP!G19 -> 812040
A12: Other Current Assets | C12: =WORKCAP!C25 -> 36666.667 | D12: =WORKCAP!D25 -> 38400 | E12: =WORKCAP!E25 -> 59950 | F12: =WORKCAP!F25 -> 81200 | G12: =WORKCAP!G25 -> 121200
A13: Total Current Assets | B13: =SUM(B9:B12) -> 2500000 | C13: =SUM(C9:C12) -> 4084666.7 | D13: =SUM(D9:D12) -> 4070380 | E13: =SUM(E9:E12) -> 4433625 | F13: =SUM(F9:F12) -> 4659247 | G13: =SUM(G9:G12) -> 6237137.9
A14: PROPERTY & EQUIPMENT | B14: ='PROP & EQUIP'!B53 -> 0 | C14: ='PROP & EQUIP'!C53 -> 244371.43 | D14: ='PROP & EQUIP'!D53 -> 603871.43 | E14: ='PROP & EQUIP'!E53 -> 923014.29 | F14: ='PROP & EQUIP'!F53 -> 1204847.6 | G14: ='PROP & EQUIP'!G53 -> 1437895.2
A15: TOTAL ASSETS | B15: =B13+B14 -> 2500000 | C15: =C13+C14 -> 4329038.1 | D15: =D13+D14 -> 4674251.4 | E15: =E13+E14 -> 5356639.3 | F15: =F13+F14 -> 5864094.6 | G15: =G13+G14 -> 7675033.1
A17: LIABILITIES & SHAREHOLDERS' EQUITY
A18: CURRENT LIABILITIES
A19: Short Term Debt | B19: =FUNDING!B18 -> 0 | C19: =FUNDING!C18 -> 450000 | D19: =FUNDING!D18 -> 350000 | E19: =FUNDING!E18 -> 800000 | F19: =FUNDING!F18 -> 100000 | G19: =FUNDING!G18 -> 0
A20: Accounts Payable & Accrued Expen | C20: =WORKCAP!C31 -> 319000 | D20: =WORKCAP!D31 -> 334080 | E20: =WORKCAP!E31 -> 521565 | F20: =WORKCAP!F31 -> 706440 | G20: =WORKCAP!G31 -> 1054440
A21: Other Current Liab | C21: =WORKCAP!C37 -> 36666.667 | D21: =WORKCAP!D37 -> 38400 | E21: =WORKCAP!E37 -> 59950 | F21: =WORKCAP!F37 -> 81200 | G21: =WORKCAP!G37 -> 121200
A22: Current portion of long term debt | B22: =FUNDING!B22 -> 0 | C22: =FUNDING!C22 -> 250000 | D22: =FUNDING!D22 -> 275000 | E22: =FUNDING!E22 -> 300000 | F22: =FUNDING!F22 -> 325000 | G22: =FUNDING!G22 -> 350000
A23: Total Current Liabilities | B23: =SUM(B19:B22) -> 0 | C23: =SUM(C19:C22) -> 1055666.7 | D23: =SUM(D19:D22) -> 997480 | E23: =SUM(E19:E22) -> 1681515 | F23: =SUM(F19:F22) -> 1212640 | G23: =SUM(G19:G22) -> 1525640
A25: LONG TERM DEBT (less current portion) | B25: =FUNDING!B23 -> 0 | C25: =FUNDING!C23 -> 2250000 | D25: =FUNDING!D23 -> 2100000 | E25: =FUNDING!E23 -> 1800000 | F25: =FUNDING!F23 -> 1400000 | G25: =FUNDING!G23 -> 1000000
A27: STOCKHOLDERS' EQUITY
A28: CommonStock | B28: =FUNDING!B8 -> 1500000 | C28: =FUNDING!C8 -> 500000 | D28: =FUNDING!D8 -> 750000 | E28: =FUNDING!E8 -> 600000 | F28: =FUNDING!F8 -> 1000000 | G28: =FUNDING!G8 -> 800000
A29: Preferred Stock | B29: =FUNDING!B13 -> 1200000 | C29: =FUNDING!C13 -> 1200000 | D29: =FUNDING!D13 -> 1950000 | E29: =FUNDING!E13 -> 1950000 | F29: =FUNDING!F13 -> 1950000 | G29: =FUNDING!G13 -> 1950000
A30: Retained Earnings | C30: =FUNDING!C52 -> -476628.57 | D30: =FUNDING!D52 -> -923228.57 | E30: =FUNDING!E52 -> -474875.71 | F30: =FUNDING!F52 -> 501454.57 | G30: =FUNDING!G52 -> 2599393.1
A31: Total Equity | B31: =SUM(B28:B30) -> 2700000 | C31: =SUM(C28:C30) -> 1223371.4 | D31: =SUM(D28:D30) -> 1776771.4 | E31: =SUM(E28:E30) -> 2075124.3 | F31: =SUM(F28:F30) -> 3451454.6 | G31: =SUM(G28:G30) -> 5349393.1
A32: TOTAL LIABILITIES & EQUITY | B32: =B23+B25+B31 -> 2700000 | C32: =C23+C25+C31 -> 4529038.1 | D32: =D23+D25+D31 -> 4874251.4 | E32: =E23+E25+E31 -> 5556639.3 | F32: =F23+F25+F31 -> 6064094.6 | G32: =G23+G25+G31 -> 7875033.1

Sheet CASHFLOW
A1: XYZ Company
A2: Cash Flow Statememt
A3: Years 1 to 5
A4: ($)
C5: Year 1 | D5: Year 2 | E5: Year 3 | F5: Year 4 | G5: Year 5
A6: OPERATING ACTIVITIES
A7: Net Earnings | C7: =INCOME!C34 -> -476628.57 | D7: =INCOME!D34 -> -416600 | E7: =INCOME!E34 -> 488352.86 | F7: =INCOME!F34 -> 1026330.3 | G7: =INCOME!G34 -> 2147938.6
A8: Depreciation | C8: ='PROP & EQUIP'!C47 -> 45128.571 | D8: ='PROP & EQUIP'!D47 -> 133500 | E8: ='PROP & EQUIP'!E47 -> 250857.14 | F8: ='PROP & EQUIP'!F47 -> 383166.67 | G8: ='PROP & EQUIP'!G47 -> 516952.38
A9: Working Capital Changes
A10: (Increase)/Decrease Accounts Receivable | C10: =WORKCAP!C13 -> -304333.33 | D10: =WORKCAP!D13 -> -14386.667 | E10: =WORKCAP!E13 -> -178865 | F10: =WORKCAP!F13 -> -176375 | G10: =WORKCAP!G13 -> -332000
A11: (Increase)/Decrease Inventories | C11: =WORKCAP!C20 -> -304333.33 | D11: =WORKCAP!D20 -> -14386.667 | E11: =WORKCAP!E20 -> -82945 | F11: =WORKCAP!F20 -> -142375 | G11: =WORKCAP!G20 -> -268000
A12: (Increase)/Decrease Other Current Assets | C12: =WORKCAP!C26 -> -36666.667 | D12: =WORKCAP!D26 -> -1733.3333 | E12: =WORKCAP!E26 -> -21550 | F12: =WORKCAP!F26 -> -21250 | G12: =WORKCAP!G26 -> -40000
A13: Increase/(Decrease) Accts Pay & Accrd Expenses | C13: =WORKCAP!C32 -> 319000 | D13: =WORKCAP!D32 -> 15080 | E13: =WORKCAP!E32 -> 187485 | F13: =WORKCAP!F32 -> 184875 | G13: =WORKCAP!G32 -> 348000
A14: Increase/(Decrease) Other Current Liab | C14: =WORKCAP!C38 -> 36666.667 | D14: =WORKCAP!D38 -> 1733.3333 | E14: =WORKCAP!E38 -> 21550 | F14: =WORKCAP!F38 -> 21250 | G14: =WORKCAP!G38 -> 40000
A15: Net Cash Provided/(Used) by Operating Activities | C15: =SUM(C7:C14) -> -721166.67 | D15: =SUM(D7:D14) -> -296793.33 | E15: =SUM(E7:E14) -> 664885 | F15: =SUM(F7:F14) -> 1275622 | G15: =SUM(G7:G14) -> 2412891
A17: INVESTING ACTIVITIES
A18: Property & Equipment | C18: =-'PROP & EQUIP'!C13 -> -289500 | D18: =-'PROP & EQUIP'!D13 -> -493000 | E18: =-'PROP & EQUIP'!E13 -> -570000 | F18: =-'PROP & EQUIP'!F13 -> -665000 | G18: =-'PROP & EQUIP'!G13 -> -750000
A19: Other
A20: Net Cash Used in Investing Activities | C20: =SUM(C18:C19) -> -289500 | D20: =SUM(D18:D19) -> -493000 | E20: =SUM(E18:E19) -> -570000 | F20: =SUM(F18:F19) -> -665000 | G20: =SUM(G18:G19) -> -750000
A22: FINANCING ACTIVITIES
A23: Increase/(Decrease) Short Term Debt | C23: =FUNDING!C19 -> 450000 | D23: =FUNDING!D19 -> -100000 | E23: =FUNDING!E19 -> 450000 | F23: =FUNDING!F19 -> -700000 | G23: =FUNDING!G19 -> -100000
A24: Increase/(Decrease) Curr. Portion LTD | C24: =FUNDING!C27 -> 250000 | D24: =FUNDING!D27 -> 25000 | E24: =FUNDING!E27 -> 25000 | F24: =FUNDING!F27 -> 25000 | G24: =FUNDING!G27 -> 25000
A25: Increase/(Decrease) Long Term Debt | C25: =FUNDING!C28 -> 2250000 | D25: =FUNDING!D28 -> -150000 | E25: =FUNDING!E28 -> -300000 | F25: =FUNDING!F28 -> -400000 | G25: =FUNDING!G28 -> -400000
A26: Increase/(Decrease) Common Stock | C26: =FUNDING!C9 -> -1000000 | D26: =FUNDING!D9 -> 250000 | E26: =FUNDING!E9 -> -150000 | F26: =FUNDING!F9 -> 400000 | G26: =FUNDING!G9 -> -200000
A27: Increase/(Decrease) Preferred Stock | C27: =FUNDING!C14 -> 0 | D27: =FUNDING!D14 -> 750000 | E27: =FUNDING!E14 -> 0 | F27: =FUNDING!F14 -> 0 | G27: =FUNDING!G14 -> 0
A28: Dividends Declared | C28: =-FUNDING!C49 -> 0 | D28: =-FUNDING!D49 -> -30000 | E28: =-FUNDING!E49 -> -40000 | F28: =-FUNDING!F49 -> -50000 | G28: =-FUNDING!G49 -> -50000
A29: Net Cash Provided / (Used) by Financing | C29: =SUM(C23:C28) -> 1950000 | D29: =SUM(D23:D28) -> 745000 | E29: =SUM(E23:E28) -> -15000 | F29: =SUM(F23:F28) -> -725000 | G29: =SUM(G23:G28) -> -725000
A31: INCREASE/(DECREASE) IN CASH | C31: =C15+C20+C29 -> 939333.33 | D31: =D15+D20+D29 -> -44793.333 | E31: =E15+E20+E29 -> 79885 | F31: =F15+F20+F29 -> -114378.05 | G31: =G15+G20+G29 -> 937890.95
A33: CASH AT BEGINNING OF YEAR | C33: =B34 -> 2500000 | D33: =C34 -> 3439333.3 | E33: =D34 -> 3394540 | F33: =E34 -> 3474425 | G33: =F34 -> 3360047
A34: CASH AT END OF YEAR | B34: =BALANCE!B9 -> 2500000 | C34: =C33+C31 -> 3439333.3 | D34: =D33+D31 -> 3394540 | E34: =E33+E31 -> 3474425 | F34: =F33+F31 -> 3360047 | G34: =G33+G31 -> 4297937.9

Sheet BREAKEVEN
A1: XYZ Company
A2: Break-Even Analysis
A3: Years 1 to 5
A4: ($)
C5: Year 1 | D5: Year 2 | E5: Year 3 | F5: Year 4 | G5: Year 5
A6: Revenue | C6: =REVENUE!C16 -> 2750000 | D6: =REVENUE!D16 -> 3840000 | E6: =REVENUE!E16 -> 5995000 | F6: =REVENUE!F16 -> 8120000 | G6: =REVENUE!G16 -> 12120000
A8: ='COST OF REV'!A9 -> Cost of Revenue | B8: ='COST OF REV'!B9 -> 0
A9: Variable | C9: ='COST OF REV'!C36 -> 571400 | D9: ='COST OF REV'!D36 -> 954050 | E9: ='COST OF REV'!E36 -> 1422500 | F9: ='COST OF REV'!F36 -> 1899400 | G9: ='COST OF REV'!G36 -> 2701800
A10: Fixed | C10: ='COST OF REV'!C37 -> 754128.57 | D10: ='COST OF REV'!D37 -> 961950 | E10: ='COST OF REV'!E37 -> 1091557.1 | F10: ='COST OF REV'!F37 -> 1215300 | G10: ='COST OF REV'!G37 -> 1362035.7
A11: Total | C11: ='COST OF REV'!C38 -> 1325528.6 | D11: ='COST OF REV'!D38 -> 1916000 | E11: ='COST OF REV'!E38 -> 2514057.1 | F11: ='COST OF REV'!F38 -> 3114700 | G11: ='COST OF REV'!G38 -> 4063835.7
A13: Operating Expenses
A14: Variable | C14: ='OPER EXP'!C45 -> 440000 | D14: ='OPER EXP'!D45 -> 614400 | E14: ='OPER EXP'!E45 -> 959200 | F14: ='OPER EXP'!F45 -> 1299200 | G14: ='OPER EXP'!G45 -> 1939200
A15: Fixed | C15: ='OPER EXP'!C46 -> 1127000 | D15: ='OPER EXP'!D46 -> 1645900 | E15: ='OPER EXP'!E46 -> 1993790 | F15: ='OPER EXP'!F46 -> 2401466.7 | G15: ='OPER EXP'!G46 -> 2779866.7
A16: Total | C16: ='OPER EXP'!C47 -> 1567000 | D16: ='OPER EXP'!D47 -> 2260300 | E16: ='OPER EXP'!E47 -> 2952990 | F16: ='OPER EXP'!F47 -> 3700666.7 | G16: ='OPER EXP'!G47 -> 4719066.7
A18: Total Costs & Expenses
A19: Variable | C19: =C9+C14 -> 1011400 | D19: =D9+D14 -> 1568450 | E19: =E9+E14 -> 2381700 | F19: =F9+F14 -> 3198600 | G19: =G9+G14 -> 4641000
A20: Fixed | C20: =C10+C15 -> 1881128.6 | D20: =D10+D15 -> 2607850 | E20: =E10+E15 -> 3085347.1 | F20: =F10+F15 -> 3616766.7 | G20: =G10+G15 -> 4141902.4
A21: Total | C21: =C19+C20 -> 2892528.6 | D21: =D19+D20 -> 4176300 | E21: =E19+E20 -> 5467047.1 | F21: =F19+F20 -> 6815366.7 | G21: =G19+G20 -> 8782902.4
A23: Variable Costs/Revenue Ratio | C23: =C19/C6 -> 0.36778182 | D23: =D19/D6 -> 0.40845052 | E23: =E19/E6 -> 0.39728107 | F23: =F19/F6 -> 0.39391626 | G23: =G19/G6 -> 0.38292079
A25: Break-Even Point Revenues | C25: =C20/(1-C19/C6) -> 2975442.1 | D25: =D20/(1-D19/D6) -> 4408507 | E25: =E20/(1-E19/E6) -> 5119048 | F25: =F20/(1-F19/F6) -> 5967437.2 | G25: =G20/(1-G19/G6) -> 6712108.2

Sheet INCOME-MOS
A1: XYZ Company
A2: Income Statements
A3: 5 Years by Months & Quarters
A4: ($)
A6: =A1 -> XYZ Company
A7: Income Statement | P7: Year 1
A8: Year 1 by Months | O8: Total | P8: Annual
C9: Month 1 | D9: Month 2 | E9: Month 3 | F9: Month 4 | G9: Month 5 | H9: Month 6 | I9: Month 7 | J9: Month 8 | K9: Month 9 | L9: Month 10 | M9: Month 11 | N9: Month 12 | O9: 12 Months | P9: Projection
A11: NET REVENUES | C11: =REVENUE!C22 -> 0 | D11: =REVENUE!C23 -> 0 | E11: =REVENUE!C24 -> 0 | F11: =REVENUE!C26 -> 305555.56 | G11: =REVENUE!C27 -> 305555.56 | H11: =REVENUE!C28 -> 305555.56 | I11: =REVENUE!C30 -> 305555.56 | J11: =REVENUE!C31 -> 305555.56 | K11: =REVENUE!C32 -> 305555.56 | L11: =REVENUE!C34 -> 305555.56 | M11: =REVENUE!C35 -> 305555.56 | N11: =REVENUE!C36 -> 305555.56 | O11: =SUM(C11:N11) -> 2750000 | P11: =INCOME!C7 -> 2750000
A13: COST OF REVENUE | C13: ='COST OF REV'!$C$33*'INCOME-MOS'!C11 -> 0 | D13: ='COST OF REV'!$C$33*'INCOME-MOS'!D11 -> 0 | E13: ='COST OF REV'!$C$33*'INCOME-MOS'!E11 -> 0 | F13: ='COST OF REV'!$C$33*'INCOME-MOS'!F11 -> 147280.95 | G13: ='COST OF REV'!$C$33*'INCOME-MOS'!G11 -> 147280.95 | H13: ='COST OF REV'!$C$33*'INCOME-MOS'!H11 -> 147280.95 | I13: ='COST OF REV'!$C$33*'INCOME-MOS'!I11 -> 147280.95 | J13: ='COST OF REV'!$C$33*'INCOME-MOS'!J11 -> 147280.95 | ... N13: ='COST OF REV'!$C$33*'INCOME-MOS'!N11 -> 147280.95 | O13: =SUM(C13:N13) -> 1325528.6 | P13: =INCOME!C9 -> 1325528.6
A15: GROSS PROFIT | C15: =C11-C13 -> 0 | D15: =D11-D13 -> 0 | E15: =E11-E13 -> 0 | F15: =F11-F13 -> 158274.6 | G15: =G11-G13 -> 158274.6 | H15: =H11-H13 -> 158274.6 | I15: =I11-I13 -> 158274.6 | J15: =J11-J13 -> 158274.6 | ... N15: =N11-N13 -> 158274.6 | O15: =SUM(C15:N15) -> 1424471.4 | P15: =INCOME!C12 -> 1424471.4
A17: OPERATING EXPENSES
A18: Sales & Marketing | C18: ='OPER EXP'!C53 -> 0 | D18: ='OPER EXP'!C54 -> 0 | E18: ='OPER EXP'!C55 -> 0 | F18: ='OPER EXP'!C57 -> 73277.778 | G18: ='OPER EXP'!C58 -> 73277.778 | H18: ='OPER EXP'!C59 -> 73277.778 | I18: ='OPER EXP'!C61 -> 73277.778 | J18: ='OPER EXP'!C62 -> 73277.778 | K18: ='OPER EXP'!C63 -> 73277.778 | L18: ='OPER EXP'!C65 -> 73277.778 | M18: ='OPER EXP'!C66 -> 73277.778 | N18: ='OPER EXP'!C67 -> 73277.778 | O18: =SUM(C18:N18) -> 659500 | P18: =INCOME!C16 -> 659500
A19: Research & Development | C19: ='OPER EXP'!C75 -> 0 | D19: ='OPER EXP'!C76 -> 0 | E19: ='OPER EXP'!C77 -> 0 | F19: ='OPER EXP'!C79 -> 31944.444 | G19: ='OPER EXP'!C80 -> 31944.444 | H19: ='OPER EXP'!C81 -> 31944.444 | I19: ='OPER EXP'!C83 -> 31944.444 | J19: ='OPER EXP'!C84 -> 31944.444 | K19: ='OPER EXP'!C85 -> 31944.444 | L19: ='OPER EXP'!C87 -> 31944.444 | M19: ='OPER EXP'!C88 -> 31944.444 | N19: ='OPER EXP'!C89 -> 31944.444 | O19: =SUM(C19:N19) -> 287500 | P19: =INCOME!C17 -> 287500
A20: General and Administration | C20: ='OPER EXP'!C97 -> 0 | D20: ='OPER EXP'!C98 -> 0 | E20: ='OPER EXP'!C99 -> 0 | F20: ='OPER EXP'!C101 -> 68888.889 | G20: ='OPER EXP'!C102 -> 68888.889 | H20: ='OPER EXP'!C103 -> 68888.889 | I20: ='OPER EXP'!C105 -> 68888.889 | J20: ='OPER EXP'!C106 -> 68888.889 | K20: ='OPER EXP'!C107 -> 68888.889 | L20: ='OPER EXP'!C109 -> 68888.889 | M20: ='OPER EXP'!C110 -> 68888.889 | N20: ='OPER EXP'!C111 -> 68888.889 | O20: =SUM(C20:N20) -> 620000 | P20: =INCOME!C18 -> 620000
A21: Total Operating Expenses | C21: =SUM(C18:C20) -> 0 | D21: =SUM(D18:D20) -> 0 | E21: =SUM(E18:E20) -> 0 | F21: =SUM(F18:F20) -> 174111.11 | G21: =SUM(G18:G20) -> 174111.11 | H21: =SUM(H18:H20) -> 174111.11 | I21: =SUM(I18:I20) -> 174111.11 | J21: =SUM(J18:J20) -> 174111.11 | ... N21: =SUM(N18:N20) -> 174111.11 | O21: =SUM(C21:N21) -> 1567000 | P21: =INCOME!C19 -> 1567000
A23: EARNINGS FROM OPERATIONS | C23: =C15-C21 -> 0 | D23: =D15-D21 -> 0 | E23: =E15-E21 -> 0 | F23: =F15-F21 -> -15836.508 | G23: =G15-G21 -> -15836.508 | H23: =H15-H21 -> -15836.508 | I23: =I15-I21 -> -15836.508 | J23: =J15-J21 -> -15836.508 | ... N23: =N15-N21 -> -15836.508 | O23: =SUM(C23:N23) -> -142528.57 | P23: =INCOME!C22 -> -142528.57
A25: EXTRAORDINARY INCOME / (EXPENSE) | C25: =EXTRA!C23 -> -50000 | D25: =EXTRA!C24 -> -70000 | E25: =EXTRA!C25 -> 0 | F25: =EXTRA!C27 -> 0 | G25: =EXTRA!C28 -> 0 | H25: =EXTRA!C29 -> 0 | I25: =EXTRA!C31 -> 0 | J25: =EXTRA!C32 -> 0 | K25: =EXTRA!C33 -> 0 | L25: =EXTRA!C35 -> 0 | M25: =EXTRA!C36 -> 0 | N25: =EXTRA!C37 -> 0 | O25: =SUM(C25:N25) -> -120000 | P25: =INCOME!C24 -> -120000
A27: EARNINGS BEFORE INTEREST & TAXES | C27: =C23+C25 -> -50000 | D27: =D23+D25 -> -70000 | E27: =E23+E25 -> 0 | F27: =F23+F25 -> -15836.508 | G27: =G23+G25 -> -15836.508 | H27: =H23+H25 -> -15836.508 | I27: =I23+I25 -> -15836.508 | J27: =J23+J25 -> -15836.508 | ... N27: =N23+N25 -> -15836.508 | O27: =SUM(C27:N27) -> -262528.57 | P27: =INCOME!C26 -> -262528.57
A29: INTEREST INCOME / (EXPENSE) | C29: =$D$120 -> -17841.667 | D29: =$D$120 -> -17841.667 | E29: =$D$120 -> -17841.667 | F29: =$D$120 -> -17841.667 | G29: =$D$120 -> -17841.667 | H29: =$D$120 -> -17841.667 | I29: =$D$120 -> -17841.667 | J29: =$D$120 -> -17841.667 | ... N29: =$D$120 -> -17841.667 | O29: =SUM(C29:N29) -> -214100 | P29: =INCOME!C28 -> -214100
A31: NET EARNINGS BEFORE TAXES | C31: =C27+C29 -> -67841.667 | D31: =D27+D29 -> -87841.667 | E31: =E27+E29 -> -17841.667 | F31: =F27+F29 -> -33678.175 | G31: =G27+G29 -> -33678.175 | H31: =H27+H29 -> -33678.175 | I31: =I27+I29 -> -33678.175 | J31: =J27+J29 -> -33678.175 | ... N31: =N27+N29 -> -33678.175 | O31: =SUM(C31:N31) -> -476628.57 | P31: =INCOME!C30 -> -476628.57
A33: TAXES | C33: =-IF(TAXES!$C11>=0,IF(TAXES!$C12<=TAXES!$C11,(TAXES!$C9*'INCOME-MOS'!C31)*TAXES!$C12/TAXES!$C11,TAXES!$C9*'INCOME-MOS'!C31),0) -> 0 | D33: =-IF(TAXES!$C11>=0,IF(TAXES!$C12<=TAXES!$C11,(TAXES!$C9*'INCOME-MOS'!D31)*TAXES!$C12/TAXES!$C11,TAXES!$C9*'INCOME-MOS'!D31),0) -> 0 | E33: =-IF(TAXES!$C11>=0,IF(TAXES!$C12<=TAXES!$C11,(TAXES!$C9*'INCOME-MOS'!E31)*TAXES!$C12/TAXES!$C11,TAXES!$C9*'INCOME-MOS'!E31),0) -> 0 | F33: =-IF(TAXES!$C11>=0,IF(TAXES!$C12<=TAXES!$C11,(TAXES!$C9*'INCOME-MOS'!F31)*TAXES!$C12/TAXES!$C11,TAXES!$C9*'INCOME-MOS'!F31),0) -> 0 | G33: =-IF(TAXES!$C11>=0,IF(TAXES!$C12<=TAXES!$C11,(TAXES!$C9*'INCOME-MOS'!G31)*TAXES!$C12/TAXES!$C11,TAXES!$C9*'INCOME-MOS'!G31),0) -> 0 | H33: =-IF(TAXES!$C11>=0,IF(TAXES!$C12<=TAXES!$C11,(TAXES!$C9*'INCOME-MOS'!H31)*TAXES!$C12/TAXES!$C11,TAXES!$C9*'INCOME-MOS'!H31),0) -> 0 | I33: =-IF(TAXES!$C11>=0,IF(TAXES!$C12<=TAXES!$C11,(TAXES!$C9*'INCOME-MOS'!I31)*TAXES!$C12/TAXES!$C11,TAXES!$C9*'INCOME-MOS'!I31),0) -> 0 | J33: =-IF(TAXES!$C11>=0,IF(TAXES!$C12<=TAXES!$C11,(TAXES!$C9*'INCOME-MOS'!J31)*TAXES!$C12/TAXES!$C11,TAXES!$C9*'INCOME-MOS'!J31),0) -> 0 | ... N33: =-IF(TAXES!$C11>=0,IF(TAXES!$C12<=TAXES!$C11,(TAXES!$C9*'INCOME-MOS'!N31)*TAXES!$C12/TAXES!$C11,TAXES!$C9*'INCOME-MOS'!N31),0) -> 0 | O33: =SUM(C33:N33) -> 0 | P33: =INCOME!C32 -> 0
A35: NET EARNINGS | C35: =C31+C33 -> -67841.667 | D35: =D31+D33 -> -87841.667 | E35: =E31+E33 -> -17841.667 | F35: =F31+F33 -> -33678.175 | G35: =G31+G33 -> -33678.175 | H35: =H31+H33 -> -33678.175 | I35: =I31+I33 -> -33678.175 | J35: =J31+J33 -> -33678.175 | ... N35: =N31+N33 -> -33678.175 | O35: =SUM(C35:N35) -> -476628.57 | P35: =INCOME!C34 -> -476628.57
A39: =A1 -> XYZ Company
A40: Income Statement | P40: Year 2
A41: Year 2 by Months | O41: Total | P41: Annual
C42: Month 1 | D42: Month 2 | E42: Month 3 | F42: Month 4 | G42: Month 5 | H42: Month 6 | I42: Month 7 | J42: Month 8 | K42: Month 9 | L42: Month 10 | M42: Month 11 | N42: Month 12 | O42: 12 Months | P42: Projection
A44: NET REVENUES | C44: =REVENUE!D22 -> 320000 | D44: =REVENUE!D23 -> 320000 | E44: =REVENUE!D24 -> 320000 | F44: =REVENUE!D26 -> 320000 | G44: =REVENUE!D27 -> 320000 | H44: =REVENUE!D28 -> 320000 | I44: =REVENUE!D30 -> 320000 | J44: =REVENUE!D31 -> 320000 | K44: =REVENUE!D32 -> 320000 | L44: =REVENUE!D34 -> 320000 | M44: =REVENUE!D35 -> 320000 | N44: =REVENUE!D36 -> 320000 | O44: =SUM(C44:N44) -> 3840000 | P44: =INCOME!D7 -> 3840000
A46: COST OF REVENUE | C46: ='COST OF REV'!$D$33*'INCOME-MOS'!C44 -> 159666.67 | D46: ='COST OF REV'!$D$33*'INCOME-MOS'!D44 -> 159666.67 | E46: ='COST OF REV'!$D$33*'INCOME-MOS'!E44 -> 159666.67 | F46: ='COST OF REV'!$D$33*'INCOME-MOS'!F44 -> 159666.67 | G46: ='COST OF REV'!$D$33*'INCOME-MOS'!G44 -> 159666.67 | H46: ='COST OF REV'!$D$33*'INCOME-MOS'!H44 -> 159666.67 | I46: ='COST OF REV'!$D$33*'INCOME-MOS'!I44 -> 159666.67 | J46: ='COST OF REV'!$D$33*'INCOME-MOS'!J44 -> 159666.67 | ... N46: ='COST OF REV'!$D$33*'INCOME-MOS'!N44 -> 159666.67 | O46: =SUM(C46:N46) -> 1916000 | P46: =INCOME!D9 -> 1916000
A48: GROSS PROFIT | C48: =C44-C46 -> 160333.33 | D48: =D44-D46 -> 160333.33 | E48: =E44-E46 -> 160333.33 | F48: =F44-F46 -> 160333.33 | G48: =G44-G46 -> 160333.33 | H48: =H44-H46 -> 160333.33 | I48: =I44-I46 -> 160333.33 | J48: =J44-J46 -> 160333.33 | ... N48: =N44-N46 -> 160333.33 | O48: =SUM(C48:N48) -> 1924000 | P48: =INCOME!D12 -> 1924000
A50: OPERATING EXPENSES
A51: Sales & Marketing | C51: ='OPER EXP'!D53 -> 69116.667 | D51: ='OPER EXP'!D54 -> 69116.667 | E51: ='OPER EXP'!D55 -> 69116.667 | F51: ='OPER EXP'!D57 -> 69116.667 | G51: ='OPER EXP'!D58 -> 69116.667 | H51: ='OPER EXP'!D59 -> 69116.667 | I51: ='OPER EXP'!D61 -> 69116.667 | J51: ='OPER EXP'!D62 -> 69116.667 | K51: ='OPER EXP'!D63 -> 69116.667 | L51: ='OPER EXP'!D65 -> 69116.667 | M51: ='OPER EXP'!D66 -> 69116.667 | N51: ='OPER EXP'!D67 -> 69116.667 | O51: =SUM(C51:N51) -> 829400 | P51: =INCOME!D16 -> 829400
A52: Research & Development | C52: ='OPER EXP'!D75 -> 46787.5 | D52: ='OPER EXP'!D76 -> 46787.5 | E52: ='OPER EXP'!D77 -> 46787.5 | F52: ='OPER EXP'!D79 -> 46787.5 | G52: ='OPER EXP'!D80 -> 46787.5 | H52: ='OPER EXP'!D81 -> 46787.5 | I52: ='OPER EXP'!D83 -> 46787.5 | J52: ='OPER EXP'!D84 -> 46787.5 | K52: ='OPER EXP'!D85 -> 46787.5 | L52: ='OPER EXP'!D87 -> 46787.5 | M52: ='OPER EXP'!D88 -> 46787.5 | N52: ='OPER EXP'!D89 -> 46787.5 | O52: =SUM(C52:N52) -> 561450 | P52: =INCOME!D17 -> 561450
A53: General and Administration | C53: ='OPER EXP'!D97 -> 72454.167 | D53: ='OPER EXP'!D98 -> 72454.167 | E53: ='OPER EXP'!D99 -> 72454.167 | F53: ='OPER EXP'!D101 -> 72454.167 | G53: ='OPER EXP'!D102 -> 72454.167 | H53: ='OPER EXP'!D103 -> 72454.167 | I53: ='OPER EXP'!D105 -> 72454.167 | J53: ='OPER EXP'!D106 -> 72454.167 | K53: ='OPER EXP'!D107 -> 72454.167 | L53: ='OPER EXP'!D109 -> 72454.167 | M53: ='OPER EXP'!D110 -> 72454.167 | N53: ='OPER EXP'!D111 -> 72454.167 | O53: =SUM(C53:N53) -> 869450 | P53: =INCOME!D18 -> 869450
A54: Total Operating Expenses | C54: =SUM(C51:C53) -> 188358.33 | D54: =SUM(D51:D53) -> 188358.33 | E54: =SUM(E51:E53) -> 188358.33 | F54: =SUM(F51:F53) -> 188358.33 | G54: =SUM(G51:G53) -> 188358.33 | H54: =SUM(H51:H53) -> 188358.33 | I54: =SUM(I51:I53) -> 188358.33 | J54: =SUM(J51:J53) -> 188358.33 | ... N54: =SUM(N51:N53) -> 188358.33 | O54: =SUM(C54:N54) -> 2260300 | P54: =INCOME!D19 -> 2260300
A56: EARNINGS FROM OPERATIONS | C56: =C48-C54 -> -28025 | D56: =D48-D54 -> -28025 | E56: =E48-E54 -> -28025 | F56: =F48-F54 -> -28025 | G56: =G48-G54 -> -28025 | H56: =H48-H54 -> -28025 | I56: =I48-I54 -> -28025 | J56: =J48-J54 -> -28025 | ... N56: =N48-N54 -> -28025 | O56: =SUM(C56:N56) -> -336300 | P56: =INCOME!D22 -> -336300
A58: EXTRAORDINARY INCOME / (EXPENSE) | C58: =EXTRA!D23 -> 50000 | D58: =EXTRA!D24 -> 0 | E58: =EXTRA!D25 -> 0 | F58: =EXTRA!D27 -> 0 | G58: =EXTRA!D28 -> 40000 | H58: =EXTRA!D29 -> 0 | I58: =EXTRA!D31 -> 0 | J58: =EXTRA!D32 -> 0 | K58: =EXTRA!D33 -> 0 | L58: =EXTRA!D35 -> 25000 | M58: =EXTRA!D36 -> 0 | N58: =EXTRA!D37 -> 0 | O58: =SUM(C58:N58) -> 115000 | P58: =INCOME!D24 -> 115000
A60: EARNINGS BEFORE INTEREST & TAXES | C60: =C56+C58 -> 21975 | D60: =D56+D58 -> -28025 | E60: =E56+E58 -> -28025 | F60: =F56+F58 -> -28025 | G60: =G56+G58 -> 11975 | H60: =H56+H58 -> -28025 | I60: =I56+I58 -> -28025 | J60: =J56+J58 -> -28025 | ... N60: =N56+N58 -> -28025 | O60: =SUM(C60:N60) -> -221300 | P60: =INCOME!D26 -> -221300
A62: INTEREST INCOME / (EXPENSE) | C62: =$D$121 -> -16275 | D62: =$D$121 -> -16275 | E62: =$D$121 -> -16275 | F62: =$D$121 -> -16275 | G62: =$D$121 -> -16275 | H62: =$D$121 -> -16275 | I62: =$D$121 -> -16275 | J62: =$D$121 -> -16275 | ... N62: =$D$121 -> -16275 | O62: =SUM(C62:N62) -> -195300 | P62: =INCOME!D28 -> -195300
A64: NET EARNINGS BEFORE TAXES | C64: =C60+C62 -> 5700 | D64: =D60+D62 -> -44300 | E64: =E60+E62 -> -44300 | F64: =F60+F62 -> -44300 | G64: =G60+G62 -> -4300 | H64: =H60+H62 -> -44300 | I64: =I60+I62 -> -44300 | J64: =J60+J62 -> -44300 | ... N64: =N60+N62 -> -44300 | O64: =SUM(C64:N64) -> -416600 | P64: =INCOME!D30 -> -416600
A66: TAXES | C66: =-IF(TAXES!$D12>=0,IF(TAXES!$D12<=TAXES!$D11,(TAXES!$D9*'INCOME-MOS'!C64)*TAXES!$D12/TAXES!$D11,TAXES!$D9*'INCOME-MOS'!C64),0) -> 0 | D66: =-IF(TAXES!$D12>=0,IF(TAXES!$D12<=TAXES!$D11,(TAXES!$D9*'INCOME-MOS'!D64)*TAXES!$D12/TAXES!$D11,TAXES!$D9*'INCOME-MOS'!D64),0) -> 0 | E66: =-IF(TAXES!$D12>=0,IF(TAXES!$D12<=TAXES!$D11,(TAXES!$D9*'INCOME-MOS'!E64)*TAXES!$D12/TAXES!$D11,TAXES!$D9*'INCOME-MOS'!E64),0) -> 0 | F66: =-IF(TAXES!$D12>=0,IF(TAXES!$D12<=TAXES!$D11,(TAXES!$D9*'INCOME-MOS'!F64)*TAXES!$D12/TAXES!$D11,TAXES!$D9*'INCOME-MOS'!F64),0) -> 0 | G66: =-IF(TAXES!$D12>=0,IF(TAXES!$D12<=TAXES!$D11,(TAXES!$D9*'INCOME-MOS'!G64)*TAXES!$D12/TAXES!$D11,TAXES!$D9*'INCOME-MOS'!G64),0) -> 0 | H66: =-IF(TAXES!$D12>=0,IF(TAXES!$D12<=TAXES!$D11,(TAXES!$D9*'INCOME-MOS'!H64)*TAXES!$D12/TAXES!$D11,TAXES!$D9*'INCOME-MOS'!H64),0) -> 0 | I66: =-IF(TAXES!$D12>=0,IF(TAXES!$D12<=TAXES!$D11,(TAXES!$D9*'INCOME-MOS'!I64)*TAXES!$D12/TAXES!$D11,TAXES!$D9*'INCOME-MOS'!I64),0) -> 0 | J66: =-IF(TAXES!$D12>=0,IF(TAXES!$D12<=TAXES!$D11,(TAXES!$D9*'INCOME-MOS'!J64)*TAXES!$D12/TAXES!$D11,TAXES!$D9*'INCOME-MOS'!J64),0) -> 0 | ... N66: =-IF(TAXES!$D12>=0,IF(TAXES!$D12<=TAXES!$D11,(TAXES!$D9*'INCOME-MOS'!N64)*TAXES!$D12/TAXES!$D11,TAXES!$D9*'INCOME-MOS'!N64),0) -> 0 | O66: =SUM(C66:N66) -> 0 | P66: =INCOME!D32 -> 0
A68: NET EARNINGS | C68: =C64+C66 -> 5700 | D68: =D64+D66 -> -44300 | E68: =E64+E66 -> -44300 | F68: =F64+F66 -> -44300 | G68: =G64+G66 -> -4300 | H68: =H64+H66 -> -44300 | I68: =I64+I66 -> -44300 | J68: =J64+J66 -> -44300 | ... N68: =N64+N66 -> -44300 | O68: =SUM(C68:N68) -> -416600 | P68: =INCOME!D34 -> -416600
A72: =A1 -> XYZ Company
A73: Income Statement | R73: Year 3 | S73: Year 4 | T73: Year 5
A74: Years 3, 4 & 5 by Quarters | R74: Annual | S74: Annual | T74: Annual
C75: Year 3 | H75: Year 4 | M75: Year 5 | R75: Projection | S75: Projection | T75: Projection
C76: 1st Qtr | D76: 2nd Qrtr | E76: 3rd Qrtr | F76: 4th Qrtr | G76: Total | H76: 1st Qtr | I76: 2nd Qtr | J76: 3rd Qtr | K76: 4th Qtr | L76: Total | M76: 1st Qtr | N76: 2nd Qtr | O76: 3rd Qtr | P76: 4th Qtr | Q76: Total
A78: NET REVENUES | C78: =REVENUE!E25 -> 1498750 | D78: =REVENUE!E29 -> 1498750 | E78: =REVENUE!E33 -> 1498750 | F78: =REVENUE!E37 -> 1498750 | G78: =SUM(C78:F78) -> 5995000 | H78: =REVENUE!F25 -> 2030000 | I78: =REVENUE!F29 -> 2030000 | J78: =REVENUE!F33 -> 2030000 | K78: =REVENUE!F37 -> 2030000 | L78: =SUM(H78:K78) -> 8120000 | M78: =REVENUE!G25 -> 3030000 | N78: =REVENUE!G29 -> 3030000 | O78: =REVENUE!G33 -> 3030000 | P78: =REVENUE!G37 -> 3030000 | Q78: =SUM(M78:P78) -> 12120000 | R78: =INCOME!E7 -> 5995000 | S78: =INCOME!F7 -> 8120000 | T78: =INCOME!G7 -> 12120000
R79: =INCOME!E8 -> 0 | S79: =INCOME!F8 -> 0 | T79: =INCOME!G8 -> 0
A80: COST OF REVENUE | C80: ='COST OF REV'!$E$33*C78 -> 628514.29 | D80: ='COST OF REV'!$E$33*D78 -> 628514.29 | E80: ='COST OF REV'!$E$33*E78 -> 628514.29 | F80: ='COST OF REV'!$E$33*F78 -> 628514.29 | G80: =SUM(C80:F80) -> 2514057.1 | H80: ='COST OF REV'!$F$33*H78 -> 778675 | I80: ='COST OF REV'!$F$33*I78 -> 778675 | J80: ='COST OF REV'!$F$33*J78 -> 778675 | K80: ='COST OF REV'!$F$33*K78 -> 778675 | L80: =SUM(H80:K80) -> 3114700 | M80: ='COST OF REV'!$G$33*M78 -> 1015958.9 | N80: ='COST OF REV'!$G$33*N78 -> 1015958.9 | O80: ='COST OF REV'!$G$33*O78 -> 1015958.9 | P80: ='COST OF REV'!$G$33*P78 -> 1015958.9 | Q80: =SUM(M80:P80) -> 4063835.7 | R80: =INCOME!E9 -> 2514057.1 | S80: =INCOME!F9 -> 3114700 | T80: =INCOME!G9 -> 4063835.7
A82: GROSS PROFIT | C82: =C78-C80 -> 870235.71 | D82: =D78-D80 -> 870235.71 | E82: =E78-E80 -> 870235.71 | F82: =F78-F80 -> 870235.71 | G82: =G78-G80 -> 3480942.9 | H82: =H78-H80 -> 1251325 | I82: =I78-I80 -> 1251325 | J82: =J78-J80 -> 1251325 | ... Q82: =Q78-Q80 -> 8056164.3 | R82: =INCOME!E12 -> 3480942.9 | S82: =INCOME!F12 -> 5005300 | T82: =INCOME!G12 -> 8056164.3
A84: OPERATING EXPENSES
A85: Sales & Marketing | C85: ='OPER EXP'!E56 -> 280272.5 | D85: ='OPER EXP'!E60 -> 280272.5 | E85: ='OPER EXP'!E64 -> 280272.5 | F85: ='OPER EXP'!E68 -> 280272.5 | G85: ='OPER EXP'!E69 -> 1121090 | H85: ='OPER EXP'!F56 -> 354500 | I85: ='OPER EXP'!F60 -> 354500 | J85: ='OPER EXP'!F64 -> 354500 | K85: ='OPER EXP'!F68 -> 354500 | L85: ='OPER EXP'!F69 -> 1418000 | M85: ='OPER EXP'!G56 -> 478100 | N85: ='OPER EXP'!G60 -> 478100 | O85: ='OPER EXP'!G64 -> 478100 | P85: ='OPER EXP'!G68 -> 478100 | Q85: ='OPER EXP'!G69 -> 1912400 | R85: =INCOME!E16 -> 1121090 | S85: =INCOME!F16 -> 1418000 | T85: =INCOME!G16 -> 1912400
A86: Research & Development | C86: ='OPER EXP'!E78 -> 193427.5 | D86: ='OPER EXP'!E82 -> 193427.5 | E86: ='OPER EXP'!E86 -> 193427.5 | F86: ='OPER EXP'!E90 -> 193427.5 | G86: ='OPER EXP'!E91 -> 773710 | H86: ='OPER EXP'!F78 -> 242250 | I86: ='OPER EXP'!F82 -> 242250 | J86: ='OPER EXP'!F86 -> 242250 | K86: ='OPER EXP'!F90 -> 242250 | L86: ='OPER EXP'!F91 -> 969000 | M86: ='OPER EXP'!G78 -> 303700 | N86: ='OPER EXP'!G82 -> 303700 | O86: ='OPER EXP'!G86 -> 303700 | P86: ='OPER EXP'!G90 -> 303700 | Q86: ='OPER EXP'!G91 -> 1214800 | R86: =INCOME!E17 -> 773710 | S86: =INCOME!F17 -> 969000 | T86: =INCOME!G17 -> 1214800
A87: General and Administration | C87: ='OPER EXP'!E100 -> 264547.5 | D87: ='OPER EXP'!E104 -> 264547.5 | E87: ='OPER EXP'!E108 -> 264547.5 | F87: ='OPER EXP'!E112 -> 264547.5 | G87: ='OPER EXP'!E113 -> 1058190 | H87: ='OPER EXP'!F100 -> 328416.67 | I87: ='OPER EXP'!F104 -> 328416.67 | J87: ='OPER EXP'!F108 -> 328416.67 | K87: ='OPER EXP'!F112 -> 328416.67 | L87: ='OPER EXP'!F113 -> 1313666.7 | M87: ='OPER EXP'!G100 -> 397966.67 | N87: ='OPER EXP'!G104 -> 397966.67 | O87: ='OPER EXP'!G108 -> 397966.67 | P87: ='OPER EXP'!G112 -> 397966.67 | Q87: ='OPER EXP'!G113 -> 1591866.7 | R87: =INCOME!E18 -> 1058190 | S87: =INCOME!F18 -> 1313666.7 | T87: =INCOME!G18 -> 1591866.7
A88: Total Operating Expenses | C88: =SUM(C85:C87) -> 738247.5 | D88: =SUM(D85:D87) -> 738247.5 | E88: =SUM(E85:E87) -> 738247.5 | F88: =SUM(F85:F87) -> 738247.5 | G88: =SUM(C88:F88) -> 2952990 | H88: =SUM(H85:H87) -> 925166.67 | I88: =SUM(I85:I87) -> 925166.67 | J88: =SUM(J85:J87) -> 925166.67 | K88: =SUM(K85:K87) -> 925166.67 | L88: =SUM(H88:K88) -> 3700666.7 | M88: =SUM(M85:M87) -> 1179766.7 | N88: =SUM(N85:N87) -> 1179766.7 | O88: =SUM(O85:O87) -> 1179766.7 | P88: =SUM(P85:P87) -> 1179766.7 | Q88: =SUM(M88:P88) -> 4719066.7 | R88: =INCOME!E19 -> 2952990 | S88: =INCOME!F19 -> 3700666.7 | T88: =INCOME!G19 -> 4719066.7
A90: EARNINGS FROM OPERATIONS | C90: =C82-C88 -> 131988.21 | D90: =D82-D88 -> 131988.21 | E90: =E82-E88 -> 131988.21 | F90: =F82-F88 -> 131988.21 | G90: =SUM(C90:F90) -> 527952.86 | H90: =H82-H88 -> 326158.33 | I90: =I82-I88 -> 326158.33 | J90: =J82-J88 -> 326158.33 | K90: =K82-K88 -> 326158.33 | L90: =SUM(H90:K90) -> 1304633.3 | M90: =M82-M88 -> 834274.4 | N90: =N82-N88 -> 834274.4 | O90: =O82-O88 -> 834274.4 | P90: =P82-P88 -> 834274.4 | Q90: =SUM(M90:P90) -> 3337097.6 | R90: =INCOME!E22 -> 527952.86 | S90: =INCOME!F22 -> 1304633.3 | T90: =INCOME!G22 -> 3337097.6
A92: EXTRAORDINARY INCOME / (EXPENSE) | C92: =EXTRA!E26 -> 80000 | D92: =EXTRA!E30 -> 0 | E92: =EXTRA!E34 -> 60000 | F92: =EXTRA!E38 -> 40000 | G92: =EXTRA!E39 -> 180000 | H92: =EXTRA!F26 -> 120000 | I92: =EXTRA!F30 -> 80000 | J92: =EXTRA!F34 -> 0 | K92: =EXTRA!F38 -> 60000 | L92: =EXTRA!F39 -> 260000 | M92: =EXTRA!G26 -> 150000 | N92: =EXTRA!G30 -> 100000 | O92: =EXTRA!G34 -> 80000 | P92: =EXTRA!G38 -> 0 | Q92: =EXTRA!G39 -> 330000 | R92: =INCOME!E24 -> 180000 | S92: =INCOME!F24 -> 260000 | T92: =INCOME!G24 -> 330000
A94: EARNINGS BEFORE INTEREST & TAXES | C94: =C90+C92 -> 211988.21 | D94: =D90+D92 -> 131988.21 | E94: =E90+E92 -> 191988.21 | F94: =F90+F92 -> 171988.21 | G94: =SUM(C94:F94) -> 707952.86 | H94: =H90+H92 -> 446158.33 | I94: =I90+I92 -> 406158.33 | J94: =J90+J92 -> 326158.33 | K94: =K90+K92 -> 386158.33 | L94: =SUM(H94:K94) -> 1564633.3 | M94: =M90+M92 -> 984274.4 | N94: =N90+N92 -> 934274.4 | O94: =O90+O92 -> 914274.4 | P94: =P90+P92 -> 834274.4 | Q94: =SUM(M94:P94) -> 3667097.6 | R94: =INCOME!E26 -> 707952.86 | S94: =INCOME!F26 -> 1564633.3 | T94: =INCOME!G26 -> 3667097.6
A96: INTEREST INCOME / (EXPENSE) | C96: =$D$122 -> -54900 | D96: =$D$122 -> -54900 | E96: =$D$122 -> -54900 | F96: =$D$122 -> -54900 | G96: =SUM(C96:F96) -> -219600 | H96: =$D$123 -> -31000 | I96: =$D$123 -> -31000 | J96: =$D$123 -> -31000 | K96: =$D$123 -> -31000 | L96: =SUM(H96:K96) -> -124000 | M96: =$D$124 -> -21800 | N96: =$D$124 -> -21800 | O96: =$D$124 -> -21800 | P96: =$D$124 -> -21800 | Q96: =SUM(M96:P96) -> -87200 | R96: =INCOME!E28 -> -219600 | S96: =INCOME!F28 -> -124000 | T96: =INCOME!G28 -> -87200
A98: NET EARNINGS BEFORE TAXES | C98: =C94+C96 -> 157088.21 | D98: =D94+D96 -> 77088.214 | E98: =E94+E96 -> 137088.21 | F98: =F94+F96 -> 117088.21 | G98: =SUM(C98:F98) -> 488352.86 | H98: =H94+H96 -> 415158.33 | I98: =I94+I96 -> 375158.33 | J98: =J94+J96 -> 295158.33 | K98: =K94+K96 -> 355158.33 | L98: =SUM(H98:K98) -> 1440633.3 | M98: =M94+M96 -> 962474.4 | N98: =N94+N96 -> 912474.4 | O98: =O94+O96 -> 892474.4 | P98: =P94+P96 -> 812474.4 | Q98: =SUM(M98:P98) -> 3579897.6 | R98: =INCOME!E30 -> 488352.86 | S98: =INCOME!F30 -> 1440633.3 | T98: =INCOME!G30 -> 3579897.6
A100: TAXES | C100: =-IF(TAXES!$E12>=0,IF(TAXES!$E12<=TAXES!$E11,(TAXES!$E9*'INCOME-MOS'!C98)*TAXES!$E12/TAXES!$E11,TAXES!$E9*'INCOME-MOS'!C98),0) -> 0 | D100: =-IF(TAXES!$E12>=0,IF(TAXES!$E12<=TAXES!$E11,(TAXES!$E9*'INCOME-MOS'!D98)*TAXES!$E12/TAXES!$E11,TAXES!$E9*'INCOME-MOS'!D98),0) -> 0 | E100: =-IF(TAXES!$E12>=0,IF(TAXES!$E12<=TAXES!$E11,(TAXES!$E9*'INCOME-MOS'!E98)*TAXES!$E12/TAXES!$E11,TAXES!$E9*'INCOME-MOS'!E98),0) -> 0 | F100: =-IF(TAXES!$E12>=0,IF(TAXES!$E12<=TAXES!$E11,(TAXES!$E9*'INCOME-MOS'!F98)*TAXES!$E12/TAXES!$E11,TAXES!$E9*'INCOME-MOS'!F98),0) -> 0 | G100: =SUM(C100:F100) -> 0 | H100: =-IF(TAXES!$F12>=0,IF(TAXES!$F12<=TAXES!$F11,(TAXES!$F9*'INCOME-MOS'!H98)*TAXES!$F12/TAXES!$F11,TAXES!$F9*'INCOME-MOS'!H98),0) -> -119392.88 | I100: =-IF(TAXES!$F12>=0,IF(TAXES!$F12<=TAXES!$F11,(TAXES!$F9*'INCOME-MOS'!I98)*TAXES!$F12/TAXES!$F11,TAXES!$F9*'INCOME-MOS'!I98),0) -> -107889.52 | J100: =-IF(TAXES!$F12>=0,IF(TAXES!$F12<=TAXES!$F11,(TAXES!$F9*'INCOME-MOS'!J98)*TAXES!$F12/TAXES!$F11,TAXES!$F9*'INCOME-MOS'!J98),0) -> -84882.804 | K100: =-IF(TAXES!$F12>=0,IF(TAXES!$F12<=TAXES!$F11,(TAXES!$F9*'INCOME-MOS'!K98)*TAXES!$F12/TAXES!$F11,TAXES!$F9*'INCOME-MOS'!K98),0) -> -102137.84 | L100: =SUM(H100:K100) -> -414303.05 | M100: =-IF(TAXES!$G12>=0,IF(TAXES!$G12<=TAXES!$G11,(TAXES!$G9*'INCOME-MOS'!M98)*TAXES!$G12/TAXES!$G11,TAXES!$G9*'INCOME-MOS'!M98),0) -> -384989.76 | N100: =-IF(TAXES!$G12>=0,IF(TAXES!$G12<=TAXES!$G11,(TAXES!$G9*'INCOME-MOS'!N98)*TAXES!$G12/TAXES!$G11,TAXES!$G9*'INCOME-MOS'!N98),0) -> -364989.76 | O100: =-IF(TAXES!$G12>=0,IF(TAXES!$G12<=TAXES!$G11,(TAXES!$G9*'INCOME-MOS'!O98)*TAXES!$G12/TAXES!$G11,TAXES!$G9*'INCOME-MOS'!O98),0) -> -356989.76 | P100: =-IF(TAXES!$G12>=0,IF(TAXES!$G12<=TAXES!$G11,(TAXES!$G9*'INCOME-MOS'!P98)*TAXES!$G12/TAXES!$G11,TAXES!$G9*'INCOME-MOS'!P98),0) -> -324989.76 | Q100: =SUM(M100:P100) -> -1431959 | R100: =INCOME!E32 -> 0 | S100: =INCOME!F32 -> -414303.05 | T100: =INCOME!G32 -> -1431959
A102: NET EARNINGS | C102: =C98+C100 -> 157088.21 | D102: =D98+D100 -> 77088.214 | E102: =E98+E100 -> 137088.21 | F102: =F98+F100 -> 117088.21 | G102: =SUM(C102:F102) -> 488352.86 | H102: =H98+H100 -> 295765.45 | I102: =I98+I100 -> 267268.81 | J102: =J98+J100 -> 210275.53 | K102: =K98+K100 -> 253020.49 | L102: =SUM(H102:K102) -> 1026330.3 | M102: =M98+M100 -> 577484.64 | N102: =N98+N100 -> 547484.64 | O102: =O98+O100 -> 535484.64 | P102: =P98+P100 -> 487484.64 | Q102: =SUM(M102:P102) -> 2147938.6 | R102: =INCOME!E34 -> 488352.86 | S102: =INCOME!F34 -> 1026330.3 | T102: =INCOME!G34 -> 2147938.6
H106: Do Not Delete
H107: Calculation Area
G108: Tax Loss Carry Forward
G109: Interest Income/(Expense)
A110: Tax Loss Carry Forward
A111: Cumulative Net Earning Before Taxes | C111: Month 1 | D111: Month 2 | E111: Month 3 | F111: Month 4 | G111: Month 5 | H111: Month 6 | I111: Month 7 | J111: Month 8 | K111: Month 9 | L111: Month 10 | M111: Month 11 | N111: Month 12
A112: Year 1 | C112: =C31 -> -67841.667 | D112: =C112+D31 -> -155683.33 | E112: =D112+E31 -> -173525 | F112: =E112+F31 -> -207203.17 | G112: =F112+G31 -> -240881.35 | H112: =G112+H31 -> -274559.52 | I112: =H112+I31 -> -308237.7 | J112: =I112+J31 -> -341915.87 | K112: =J112+K31 -> -375594.05 | ... N112: =M112+N31 -> -476628.57
A113: Year 2 | C113: =N112+C64 -> -470928.57 | D113: =C113+D64 -> -515228.57 | E113: =D113+E64 -> -559528.57 | F113: =E113+F64 -> -603828.57 | G113: =F113+G64 -> -608128.57 | H113: =G113+H64 -> -652428.57 | I113: =H113+I64 -> -696728.57 | J113: =I113+J64 -> -741028.57 | K113: =J113+K64 -> -785328.57 | ... N113: =M113+N64 -> -893228.57
A115: Cumulative Net Earning Before Taxes | C115: Year 3 | H115: Year 4 | M115: Year 5
C116: Quarter 1 | D116: Quarter 2 | E116: Quarter 3 | F116: Quarter 4 | H116: Quarter 1 | I116: Quarter 2 | J116: Quarter 3 | K116: Quarter 4 | M116: Quarter 1 | N116: Quarter 2 | O116: Quarter 3 | P116: Quarter 4
C117: =N113+C98 -> -736140.36 | D117: =C117+D98 -> -659052.14 | E117: =D117+E98 -> -521963.93 | F117: =E117+F98 -> -404875.71 | H117: =F117+H98 -> 10282.619 | I117: =H117+I98 -> 385440.95 | J117: =I117+J98 -> 680599.29 | K117: =J117+K98 -> 1035757.6 | M117: =K117+M98 -> 1998232 | N117: =M117+N98 -> 2910706.4 | O117: =N117+O98 -> 3803180.8 | P117: =O117+P98 -> 4615655.2
A119: Interest Income/(Expense) | C119: Total Year | D119: Per Month/Qtr
A120: Year 1 | C120: =FUNDING!C45-FUNDING!C41 -> -214100 | D120: =C120/12 -> -17841.667
A121: Year 2 | C121: =FUNDING!D45-FUNDING!D41 -> -195300 | D121: =C121/12 -> -16275
A122: Year 3 | C122: =FUNDING!E45-FUNDING!E41 -> -219600 | D122: =C122/4 -> -54900
A123: Year 4 | C123: =FUNDING!F45-FUNDING!F41 -> -124000 | D123: =C123/4 -> -31000
A124: Year 5 | C124: =FUNDING!G45-FUNDING!G41 -> -87200 | D124: =C124/4 -> -21800

Sheet CASHFLOW-MOS
A1: XYZ Company
A2: Cash Flow Statememt
A3: Year 1 by Months
A4: ($)
A7: =A1 -> XYZ Company
A8: Cash Flow Statement | O8: Year 1
A9: Year 1 by Months | N9: Estimated | O9: Annual
B10: Month 1 | C10: Month 2 | D10: Month 3 | E10: Month 4 | F10: Month 5 | G10: Month 6 | H10: Month 7 | I10: Month 8 | J10: Month 9 | K10: Month 10 | L10: Month 11 | M10: Month 12 | N10: Year 1 | O10: Projection
A11: OPERATING ACTIVITIES
A12: Net Earnings | B12: ='INCOME-MOS'!C35 -> -67841.667 | C12: ='INCOME-MOS'!D35 -> -87841.667 | D12: ='INCOME-MOS'!E35 -> -17841.667 | E12: ='INCOME-MOS'!F35 -> -33678.175 | F12: ='INCOME-MOS'!G35 -> -33678.175 | G12: ='INCOME-MOS'!H35 -> -33678.175 | H12: ='INCOME-MOS'!I35 -> -33678.175 | I12: ='INCOME-MOS'!J35 -> -33678.175 | ... M12: ='INCOME-MOS'!N35 -> -33678.175 | N12: =SUM(B12:M12) -> -476628.57 | O12: =CASHFLOW!C7 -> -476628.57
A13: Depreciation | B13: ='PROP & EQUIP'!$C$47/12 -> 3760.7143 | C13: ='PROP & EQUIP'!$C$47/12 -> 3760.7143 | D13: ='PROP & EQUIP'!$C$47/12 -> 3760.7143 | E13: ='PROP & EQUIP'!$C$47/12 -> 3760.7143 | F13: ='PROP & EQUIP'!$C$47/12 -> 3760.7143 | G13: ='PROP & EQUIP'!$C$47/12 -> 3760.7143 | H13: ='PROP & EQUIP'!$C$47/12 -> 3760.7143 | I13: ='PROP & EQUIP'!$C$47/12 -> 3760.7143 | ... M13: ='PROP & EQUIP'!$C$47/12 -> 3760.7143 | N13: =SUM(B13:M13) -> 45128.571 | O13: =CASHFLOW!C8 -> 45128.571
A14: Working Capital Changes
A15: (Increase)/Decrease Accounts Receivable | B15: =-WORKCAP!C67 -> 0 | C15: =-(WORKCAP!$C68-WORKCAP!$C67) -> 0 | D15: =-(WORKCAP!$C69-WORKCAP!$C68) -> 0 | E15: =-(WORKCAP!$C70-WORKCAP!$C69) -> -304333.33 | F15: =-(WORKCAP!$C71-WORKCAP!$C70) -> 0 | G15: =-(WORKCAP!$C72-WORKCAP!$C71) -> 0 | H15: =-(WORKCAP!$C73-WORKCAP!$C72) -> 0 | I15: =-(WORKCAP!$C74-WORKCAP!$C73) -> 0 | J15: =-(WORKCAP!$C75-WORKCAP!$C74) -> 0 | K15: =-(WORKCAP!$C76-WORKCAP!$C75) -> 0 | L15: =-(WORKCAP!$C77-WORKCAP!$C76) -> 0 | M15: =-(WORKCAP!$C78-WORKCAP!$C77) -> 0 | N15: =SUM(B15:M15) -> -304333.33 | O15: =CASHFLOW!C10 -> -304333.33
A16: (Increase)/Decrease Inventories | B16: =-WORKCAP!C84 -> 0 | C16: =-(WORKCAP!$C85-WORKCAP!$C84) -> 0 | D16: =-(WORKCAP!$C86-WORKCAP!$C85) -> 0 | E16: =-(WORKCAP!$C87-WORKCAP!$C86) -> -304333.33 | F16: =-(WORKCAP!$C88-WORKCAP!$C87) -> 0 | G16: =-(WORKCAP!$C89-WORKCAP!$C88) -> 0 | H16: =-(WORKCAP!$C90-WORKCAP!$C89) -> 0 | I16: =-(WORKCAP!$C91-WORKCAP!$C90) -> 0 | J16: =-(WORKCAP!$C92-WORKCAP!$C91) -> 0 | K16: =-(WORKCAP!$C93-WORKCAP!$C92) -> 0 | L16: =-(WORKCAP!$C94-WORKCAP!$C93) -> 0 | M16: =-(WORKCAP!$C95-WORKCAP!$C94) -> 0 | N16: =SUM(B16:M16) -> -304333.33 | O16: =CASHFLOW!C11 -> -304333.33
A17: (Increase)/Decrease Other Current Assets | B17: =-WORKCAP!$C101 -> 0 | C17: =-(WORKCAP!$C102-WORKCAP!$C101) -> 0 | D17: =-(WORKCAP!$C103-WORKCAP!$C102) -> 0 | E17: =-(WORKCAP!$C104-WORKCAP!$C103) -> -36666.667 | F17: =-(WORKCAP!$C105-WORKCAP!$C104) -> 0 | G17: =-(WORKCAP!$C106-WORKCAP!$C105) -> 0 | H17: =-(WORKCAP!$C107-WORKCAP!$C106) -> 0 | I17: =-(WORKCAP!$C108-WORKCAP!$C107) -> 0 | J17: =-(WORKCAP!$C109-WORKCAP!$C108) -> 0 | K17: =-(WORKCAP!$C110-WORKCAP!$C109) -> 0 | L17: =-(WORKCAP!$C111-WORKCAP!$C110) -> 0 | M17: =-(WORKCAP!$C112-WORKCAP!$C111) -> 0 | N17: =SUM(B17:M17) -> -36666.667 | O17: =CASHFLOW!C12 -> -36666.667
A18: Increase/(Decrease) Accts Pay & Accrd Expenses | B18: =WORKCAP!$C118 -> 0 | C18: =(WORKCAP!$C119-WORKCAP!$C118) -> 0.087 | D18: =(WORKCAP!$C120-WORKCAP!$C119) -> 31.236828 | E18: =(WORKCAP!$C121-WORKCAP!$C120) -> 305524.23 | F18: =(WORKCAP!$C122-WORKCAP!$C121) -> 13444.444 | G18: =(WORKCAP!$C123-WORKCAP!$C122) -> 0 | H18: =(WORKCAP!$C124-WORKCAP!$C123) -> 0 | I18: =(WORKCAP!$C125-WORKCAP!$C124) -> 0 | J18: =(WORKCAP!$C126-WORKCAP!$C125) -> 0 | K18: =(WORKCAP!$C127-WORKCAP!$C126) -> 0 | L18: =(WORKCAP!$C128-WORKCAP!$C127) -> 0 | M18: =(WORKCAP!$C129-WORKCAP!$C128) -> 0 | N18: =SUM(B18:M18) -> 319000 | O18: =CASHFLOW!C13 -> 319000
A19: Increase/(Decrease) Other Current Liab | B19: =WORKCAP!C135 -> 0 | C19: =(WORKCAP!$C136-WORKCAP!$C135) -> 0 | D19: =(WORKCAP!$C137-WORKCAP!$C136) -> 0 | E19: =(WORKCAP!$C138-WORKCAP!$C137) -> 36666.667 | F19: =(WORKCAP!$C139-WORKCAP!$C138) -> 0 | G19: =(WORKCAP!$C140-WORKCAP!$C139) -> 0 | H19: =(WORKCAP!$C141-WORKCAP!$C140) -> 0 | I19: =(WORKCAP!$C142-WORKCAP!$C141) -> 0 | J19: =(WORKCAP!$C143-WORKCAP!$C142) -> 0 | K19: =(WORKCAP!$C144-WORKCAP!$C143) -> 0 | L19: =(WORKCAP!$C145-WORKCAP!$C144) -> 0 | M19: =(WORKCAP!$C146-WORKCAP!$C145) -> 0 | N19: =SUM(B19:M19) -> 36666.667 | O19: =CASHFLOW!C14 -> 36666.667
A20: Net Cash Provided/(Used) by Operating Activities | B20: =SUM(B12:B19) -> -64080.952 | C20: =SUM(C12:C19) -> -84080.865 | D20: =SUM(D12:D19) -> -14049.716 | E20: =SUM(E12:E19) -> -333059.9 | F20: =SUM(F12:F19) -> -16473.016 | G20: =SUM(G12:G19) -> -29917.46 | H20: =SUM(H12:H19) -> -29917.46 | I20: =SUM(I12:I19) -> -29917.46 | ... N20: =SUM(N12:N19) -> -721166.67 | O20: =CASHFLOW!C15 -> -721166.67
A22: INVESTING ACTIVITIES
A23: Property & Equipment | B23: =-'PROP & EQUIP'!$C61 -> -50000 | C23: =-'PROP & EQUIP'!$C62 -> -100000 | D23: =-'PROP & EQUIP'!$C63 -> -50000 | E23: =-'PROP & EQUIP'!$C65 -> -40000 | F23: =-'PROP & EQUIP'!$C66 -> 0 | G23: =-'PROP & EQUIP'!$C67 -> 0 | H23: =-'PROP & EQUIP'!$C69 -> -40000 | I23: =-'PROP & EQUIP'!$C70 -> 0 | J23: =-'PROP & EQUIP'!$C71 -> 0 | K23: =-'PROP & EQUIP'!$C73 -> -9500 | L23: =-'PROP & EQUIP'!$C74 -> 0 | M23: =-'PROP & EQUIP'!$C75 -> 0 | N23: =SUM(B23:M23) -> -289500 | O23: =CASHFLOW!C18 -> -289500
A24: Other | N24: =SUM(B24:M24) -> 0 | O24: =CASHFLOW!C19 -> 0
A25: Net Cash Used in Investing Activities | B25: =SUM(B23:B24) -> -50000 | C25: =SUM(C23:C24) -> -100000 | D25: =SUM(D23:D24) -> -50000 | E25: =SUM(E23:E24) -> -40000 | F25: =SUM(F23:F24) -> 0 | G25: =SUM(G23:G24) -> 0 | H25: =SUM(H23:H24) -> -40000 | I25: =SUM(I23:I24) -> 0 | ... N25: =SUM(N23:N24) -> -289500 | O25: =CASHFLOW!C20 -> -289500
A27: FINANCING ACTIVITIES
A28: Increase/(Decrease) Short Term Debt | B28: =IF(FUNDING!C19>=0,FUNDING!C19,0) -> 450000 | M28: =IF(FUNDING!C19<0,FUNDING!C19,0) -> 0 | N28: =SUM(B28:M28) -> 450000 | O28: =CASHFLOW!C23 -> 450000
A29: Increase/(Decrease) Curr. Portion LTD | B29: =IF(FUNDING!C27>=0,FUNDING!C27,0) -> 250000 | M29: =IF(FUNDING!C27<0,FUNDING!C27,0) -> 0 | N29: =SUM(B29:M29) -> 250000 | O29: =CASHFLOW!C24 -> 250000
A30: Increase/(Decrease) Long Term Debt | B30: =IF(FUNDING!C28>=0,FUNDING!C28,0) -> 2250000 | M30: =IF(FUNDING!C28<0,FUNDING!C28,0) -> 0 | N30: =SUM(B30:M30) -> 2250000 | O30: =CASHFLOW!C25 -> 2250000
A31: Increase/(Decrease) Common Stock | B31: =IF(FUNDING!C9>=0,FUNDING!C9,0) -> 0 | M31: =IF(FUNDING!C9<0,FUNDING!C9,0) -> -1000000 | N31: =SUM(B31:M31) -> -1000000 | O31: =CASHFLOW!C26 -> -1000000
A32: Increase/(Decrease) Preferred Stock | B32: =IF(FUNDING!C14>=0,FUNDING!C14,0) -> 0 | M32: =IF(FUNDING!C14<0,FUNDING!C14,0) -> 0 | N32: =SUM(B32:M32) -> 0 | O32: =CASHFLOW!C27 -> 0
A33: Dividends Declared | M33: =-FUNDING!C49 -> 0 | N33: =SUM(B33:M33) -> 0 | O33: =CASHFLOW!C28 -> 0
A34: Net Cash Provided / (Used) by Financing | B34: =SUM(B28:B33) -> 2950000 | C34: =SUM(C28:C33) -> 0 | D34: =SUM(D28:D33) -> 0 | E34: =SUM(E28:E33) -> 0 | F34: =SUM(F28:F33) -> 0 | G34: =SUM(G28:G33) -> 0 | H34: =SUM(H28:H33) -> 0 | I34: =SUM(I28:I33) -> 0 | ... M34: =SUM(M28:M33) -> -1000000 | N34: =SUM(B34:M34) -> 1950000 | O34: =CASHFLOW!C29 -> 1950000
A36: INCREASE/(DECREASE) IN CASH | B36: =B20+B25+B34 -> 2835919 | C36: =C20+C25+C34 -> -184080.87 | D36: =D20+D25+D34 -> -64049.716 | E36: =E20+E25+E34 -> -373059.9 | F36: =F20+F25+F34 -> -16473.016 | G36: =G20+G25+G34 -> -29917.46 | H36: =H20+H25+H34 -> -69917.46 | I36: =I20+I25+I34 -> -29917.46 | ... M36: =M20+M25+M34 -> -1029917.5 | N36: =SUM(B36:M36) -> 939333.33 | O36: =CASHFLOW!C31 -> 939333.33
A38: CASH AT BEGINNING OF PERIOD | B38: =BALANCE!B9 -> 2500000 | C38: =B39 -> 5335919 | D38: =C39 -> 5151838.2 | E38: =D39 -> 5087788.5 | F38: =E39 -> 4714728.6 | G38: =F39 -> 4698255.6 | H38: =G39 -> 4668338.1 | I38: =H39 -> 4598420.6 | J38: =I39 -> 4568503.2 | ... M38: =L39 -> 4469250.8 | O38: =CASHFLOW!C33 -> 2500000
A39: CASH AT END OF PERIOD | B39: =B38+B36 -> 5335919 | C39: =C38+C36 -> 5151838.2 | D39: =D38+D36 -> 5087788.5 | E39: =E38+E36 -> 4714728.6 | F39: =F38+F36 -> 4698255.6 | G39: =G38+G36 -> 4668338.1 | H39: =H38+H36 -> 4598420.6 | I39: =I38+I36 -> 4568503.2 | ... M39: =M38+M36 -> 3439333.3 | O39: =CASHFLOW!C34 -> 3439333.3
A43: =A1 -> XYZ Company
A44: Cash Flow Statement | O44: Year 2
A45: Year 2 by Months | N45: Estimated | O45: Annual
B46: Month 1 | C46: Month 2 | D46: Month 3 | E46: Month 4 | F46: Month 5 | G46: Month 6 | H46: Month 7 | I46: Month 8 | J46: Month 9 | K46: Month 10 | L46: Month 11 | M46: Month 12 | N46: Year 2 | O46: Projection
A47: OPERATING ACTIVITIES
A48: Net Earnings | B48: ='INCOME-MOS'!C68 -> 5700 | C48: ='INCOME-MOS'!D68 -> -44300 | D48: ='INCOME-MOS'!E68 -> -44300 | E48: ='INCOME-MOS'!F68 -> -44300 | F48: ='INCOME-MOS'!G68 -> -4300 | G48: ='INCOME-MOS'!H68 -> -44300 | H48: ='INCOME-MOS'!I68 -> -44300 | I48: ='INCOME-MOS'!J68 -> -44300 | ... M48: ='INCOME-MOS'!N68 -> -44300 | N48: =SUM(B48:M48) -> -416600 | O48: =CASHFLOW!D7 -> -416600
A49: Depreciation | B49: ='PROP & EQUIP'!$D$47/12 -> 11125 | C49: ='PROP & EQUIP'!$D$47/12 -> 11125 | D49: ='PROP & EQUIP'!$D$47/12 -> 11125 | E49: ='PROP & EQUIP'!$D$47/12 -> 11125 | F49: ='PROP & EQUIP'!$D$47/12 -> 11125 | G49: ='PROP & EQUIP'!$D$47/12 -> 11125 | H49: ='PROP & EQUIP'!$D$47/12 -> 11125 | I49: ='PROP & EQUIP'!$D$47/12 -> 11125 | ... M49: ='PROP & EQUIP'!$D$47/12 -> 11125 | N49: =SUM(B49:M49) -> 133500 | O49: =CASHFLOW!D8 -> 133500
A50: Working Capital Changes | O50: =CASHFLOW!D9 -> 0
A51: (Increase)/Decrease Accounts Receivable | B51: =-(WORKCAP!$D67-WORKCAP!$C78) -> -14386.667 | C51: =-(WORKCAP!$D68-WORKCAP!$D67) -> 0 | D51: =-(WORKCAP!$D69-WORKCAP!$D68) -> 0 | E51: =-(WORKCAP!$D70-WORKCAP!$D69) -> 0 | F51: =-(WORKCAP!$D71-WORKCAP!$D70) -> 0 | G51: =-(WORKCAP!$D72-WORKCAP!$D71) -> 0 | H51: =-(WORKCAP!$D73-WORKCAP!$D72) -> 0 | I51: =-(WORKCAP!$D74-WORKCAP!$D73) -> 0 | J51: =-(WORKCAP!$D75-WORKCAP!$D74) -> 0 | K51: =-(WORKCAP!$D76-WORKCAP!$D75) -> 0 | L51: =-(WORKCAP!$D77-WORKCAP!$D76) -> 0 | M51: =-(WORKCAP!$D78-WORKCAP!$D77) -> 0 | N51: =SUM(B51:M51) -> -14386.667 | O51: =CASHFLOW!D10 -> -14386.667
A52: (Increase)/Decrease Inventories | B52: =-(WORKCAP!$D84-WORKCAP!$C95) -> -14386.667 | C52: =-(WORKCAP!$D85-WORKCAP!$D84) -> 0 | D52: =-(WORKCAP!$D86-WORKCAP!$D85) -> 0 | E52: =-(WORKCAP!$D87-WORKCAP!$D86) -> 0 | F52: =-(WORKCAP!$D88-WORKCAP!$D87) -> 0 | G52: =-(WORKCAP!$D89-WORKCAP!$D88) -> 0 | H52: =-(WORKCAP!$D90-WORKCAP!$D89) -> 0 | I52: =-(WORKCAP!$D91-WORKCAP!$D90) -> 0 | J52: =-(WORKCAP!$D92-WORKCAP!$D91) -> 0 | K52: =-(WORKCAP!$D93-WORKCAP!$D92) -> 0 | L52: =-(WORKCAP!$D94-WORKCAP!$D93) -> 0 | M52: =-(WORKCAP!$D95-WORKCAP!$D94) -> 0 | N52: =SUM(B52:M52) -> -14386.667 | O52: =CASHFLOW!D11 -> -14386.667
A53: (Increase)/Decrease Other Current Assets | B53: =-(WORKCAP!$D101-WORKCAP!$C112) -> -1733.3333 | C53: =-(WORKCAP!$D102-WORKCAP!$D101) -> 0 | D53: =-(WORKCAP!$D103-WORKCAP!$D102) -> 0 | E53: =-(WORKCAP!$D104-WORKCAP!$D103) -> 0 | F53: =-(WORKCAP!$D105-WORKCAP!$D104) -> 0 | G53: =-(WORKCAP!$D106-WORKCAP!$D105) -> 0 | H53: =-(WORKCAP!$D107-WORKCAP!$D106) -> 0 | I53: =-(WORKCAP!$D108-WORKCAP!$D107) -> 0 | J53: =-(WORKCAP!$D109-WORKCAP!$D108) -> 0 | K53: =-(WORKCAP!$D110-WORKCAP!$D109) -> 0 | L53: =-(WORKCAP!$D111-WORKCAP!$D110) -> 0 | M53: =-(WORKCAP!$D112-WORKCAP!$D111) -> 0 | N53: =SUM(B53:M53) -> -1733.3333 | O53: =CASHFLOW!D12 -> -1733.3333
A54: Increase/(Decrease) Accts Pay & Accrd Expenses | B54: =(WORKCAP!$D118-WORKCAP!$C129) -> -305555.56 | C54: =(WORKCAP!$D119-WORKCAP!$D118) -> -13444.357 | D54: =(WORKCAP!$D120-WORKCAP!$D119) -> 31.236828 | E54: =(WORKCAP!$D121-WORKCAP!$D120) -> 334048.68 | F54: =(WORKCAP!$D122-WORKCAP!$D121) -> 0 | G54: =(WORKCAP!$D123-WORKCAP!$D122) -> 0 | H54: =(WORKCAP!$D124-WORKCAP!$D123) -> 0 | I54: =(WORKCAP!$D125-WORKCAP!$D124) -> 0 | J54: =(WORKCAP!$D126-WORKCAP!$D125) -> 0 | K54: =(WORKCAP!$D127-WORKCAP!$D126) -> 0 | L54: =(WORKCAP!$D128-WORKCAP!$D127) -> 0 | M54: =(WORKCAP!$D129-WORKCAP!$D128) -> 0 | N54: =SUM(B54:M54) -> 15080 | O54: =CASHFLOW!D13 -> 15080
A55: Increase/(Decrease) Other Current Liab | B55: =(WORKCAP!$D135-WORKCAP!$C146) -> 1733.3333 | C55: =(WORKCAP!$D136-WORKCAP!$D135) -> 0 | D55: =(WORKCAP!$D137-WORKCAP!$D136) -> 0 | E55: =(WORKCAP!$D138-WORKCAP!$D137) -> 0 | F55: =(WORKCAP!$D139-WORKCAP!$D138) -> 0 | G55: =(WORKCAP!$D140-WORKCAP!$D139) -> 0 | H55: =(WORKCAP!$D141-WORKCAP!$D140) -> 0 | I55: =(WORKCAP!$D142-WORKCAP!$D141) -> 0 | J55: =(WORKCAP!$D143-WORKCAP!$D142) -> 0 | K55: =(WORKCAP!$D144-WORKCAP!$D143) -> 0 | L55: =(WORKCAP!$D145-WORKCAP!$D144) -> 0 | M55: =(WORKCAP!$D146-WORKCAP!$D145) -> 0 | N55: =SUM(B55:M55) -> 1733.3333 | O55: =CASHFLOW!D14 -> 1733.3333
A56: Net Cash Provided/(Used) by Operating Activities | B56: =SUM(B48:B55) -> -317503.89 | C56: =SUM(C48:C55) -> -46619.357 | D56: =SUM(D48:D55) -> -33143.763 | E56: =SUM(E48:E55) -> 300873.68 | F56: =SUM(F48:F55) -> 6825 | G56: =SUM(G48:G55) -> -33175 | H56: =SUM(H48:H55) -> -33175 | I56: =SUM(I48:I55) -> -33175 | ... M56: =SUM(M48:M55) -> -33175 | N56: =SUM(B56:M56) -> -296793.33 | O56: =CASHFLOW!D15 -> -296793.33
O57: =CASHFLOW!D16 -> 0
A58: INVESTING ACTIVITIES | O58: =CASHFLOW!D17 -> 0
A59: Property & Equipment | B59: =-'PROP & EQUIP'!$D61 -> -100000 | C59: =-'PROP & EQUIP'!$D62 -> -100000 | D59: =-'PROP & EQUIP'!$D63 -> 0 | E59: =-'PROP & EQUIP'!$D65 -> 0 | F59: =-'PROP & EQUIP'!$D66 -> 0 | G59: =-'PROP & EQUIP'!$D67 -> -100000 | H59: =-'PROP & EQUIP'!$D69 -> 0 | I59: =-'PROP & EQUIP'!$D70 -> -93000 | J59: =-'PROP & EQUIP'!$D71 -> 0 | K59: =-'PROP & EQUIP'!$D73 -> 0 | L59: =-'PROP & EQUIP'!$D74 -> 0 | M59: =-'PROP & EQUIP'!$D75 -> -100000 | N59: =SUM(B59:M59) -> -493000 | O59: =CASHFLOW!D18 -> -493000
A60: Other | N60: =SUM(B60:M60) -> 0 | O60: =CASHFLOW!D19 -> 0
A61: Net Cash Used in Investing Activities | B61: =SUM(B59:B60) -> -100000 | C61: =SUM(C59:C60) -> -100000 | D61: =SUM(D59:D60) -> 0 | E61: =SUM(E59:E60) -> 0 | F61: =SUM(F59:F60) -> 0 | G61: =SUM(G59:G60) -> -100000 | H61: =SUM(H59:H60) -> 0 | I61: =SUM(I59:I60) -> -93000 | ... M61: =SUM(M59:M60) -> -100000 | N61: =SUM(B61:M61) -> -493000 | O61: =CASHFLOW!D20 -> -493000
O62: =CASHFLOW!D21 -> 0
A63: FINANCING ACTIVITIES | O63: =CASHFLOW!D22 -> 0
A64: Increase/(Decrease) Short Term Debt | B64: =IF(FUNDING!D19>=0,FUNDING!D19,0) -> 0 | M64: =IF(FUNDING!D19<0,FUNDING!D19,0) -> -100000 | N64: =SUM(B64:M64) -> -100000 | O64: =CASHFLOW!D23 -> -100000
A65: Increase/(Decrease) Curr. Portion LTD | B65: =IF(FUNDING!D27>=0,FUNDING!D27,0) -> 25000 | M65: =IF(FUNDING!D27<0,FUNDING!D27,0) -> 0 | N65: =SUM(B65:M65) -> 25000 | O65: =CASHFLOW!D24 -> 25000
A66: Increase/(Decrease) Long Term Debt | B66: =IF(FUNDING!D28>=0,FUNDING!D28,0) -> 0 | M66: =IF(FUNDING!D28<0,FUNDING!D28,0) -> -150000 | N66: =SUM(B66:M66) -> -150000 | O66: =CASHFLOW!D25 -> -150000
A67: Increase/(Decrease) Common Stock | B67: =IF(FUNDING!D9>=0,FUNDING!D9,0) -> 250000 | M67: =IF(FUNDING!D9<0,FUNDING!CC9,0) -> 0 | N67: =SUM(B67:M67) -> 250000 | O67: =CASHFLOW!D26 -> 250000
A68: Increase/(Decrease) Preferred Stock | B68: =IF(FUNDING!D14>=0,FUNDING!D14,0) -> 750000 | M68: =IF(FUNDING!D14<0,FUNDING!D14,0) -> 0 | N68: =SUM(B68:M68) -> 750000 | O68: =CASHFLOW!D27 -> 750000
A69: Dividends Declared | M69: =-FUNDING!D49 -> -30000 | N69: =SUM(B69:M69) -> -30000 | O69: =CASHFLOW!D28 -> -30000
A70: Net Cash Provided / (Used) by Financing | B70: =SUM(B64:B69) -> 1025000 | C70: =SUM(C64:C69) -> 0 | D70: =SUM(D64:D69) -> 0 | E70: =SUM(E64:E69) -> 0 | F70: =SUM(F64:F69) -> 0 | G70: =SUM(G64:G69) -> 0 | H70: =SUM(H64:H69) -> 0 | I70: =SUM(I64:I69) -> 0 | ... M70: =SUM(M64:M69) -> -280000 | N70: =SUM(B70:M70) -> 745000 | O70: =CASHFLOW!D29 -> 745000
O71: =CASHFLOW!D30 -> 0
A72: INCREASE/(DECREASE) IN CASH | B72: =B56+B61+B70 -> 607496.11 | C72: =C56+C61+C70 -> -146619.36 | D72: =D56+D61+D70 -> -33143.763 | E72: =E56+E61+E70 -> 300873.68 | F72: =F56+F61+F70 -> 6825 | G72: =G56+G61+G70 -> -133175 | H72: =H56+H61+H70 -> -33175 | I72: =I56+I61+I70 -> -126175 | ... M72: =M56+M61+M70 -> -413175 | N72: =SUM(B72:M72) -> -44793.333 | O72: =CASHFLOW!D31 -> -44793.333
A74: CASH AT BEGINNING OF PERIOD | B74: =M39 -> 3439333.3 | C74: =B75 -> 4046829.4 | D74: =C75 -> 3900210.1 | E74: =D75 -> 3867066.3 | F74: =E75 -> 4167940 | G74: =F75 -> 4174765 | H74: =G75 -> 4041590 | I74: =H75 -> 4008415 | J74: =I75 -> 3882240 | ... M74: =L75 -> 3807715 | O74: =CASHFLOW!D33 -> 3439333.3
A75: CASH AT END OF PERIOD | B75: =B74+B72 -> 4046829.4 | C75: =C74+C72 -> 3900210.1 | D75: =D74+D72 -> 3867066.3 | E75: =E74+E72 -> 4167940 | F75: =F74+F72 -> 4174765 | G75: =G74+G72 -> 4041590 | H75: =H74+H72 -> 4008415 | I75: =I74+I72 -> 3882240 | ... M75: =M74+M72 -> 3394540 | O75: =CASHFLOW!D34 -> 3394540
A78: =A1 -> XYZ Company
A79: Cash Flow Statement | Q79: Year 3 | R79: Year 4 | S79: Year 5
A80: Years 3, 4 & 5 by Quarters | Q80: Annual | R80: Annual | S80: Annual
B81: Year 3 | G81: Year 4 | L81: Year 5 | Q81: Projection | R81: Projection | S81: Projection
B82: 1st Qtr | C82: 2nd Qrtr | D82: 3rd Qrtr | E82: 4th Qrtr | F82: Total | G82: 1st Qtr | H82: 2nd Qtr | I82: 3rd Qtr | J82: 4th Qtr | K82: Total | L82: 1st Qtr | M82: 2nd Qtr | N82: 3rd Qtr | O82: 4th Qtr | P82: Total
A83: OPERATING ACTIVITIES
A84: Net Earnings | B84: ='INCOME-MOS'!C102 -> 157088.21 | C84: ='INCOME-MOS'!D102 -> 77088.214 | D84: ='INCOME-MOS'!E102 -> 137088.21 | E84: ='INCOME-MOS'!F102 -> 117088.21 | F84: =SUM(B84:E84) -> 488352.86 | G84: ='INCOME-MOS'!H102 -> 295765.45 | H84: ='INCOME-MOS'!I102 -> 267268.81 | I84: ='INCOME-MOS'!J102 -> 210275.53 | J84: ='INCOME-MOS'!K102 -> 253020.49 | K84: =SUM(G84:J84) -> 1026330.3 | L84: ='INCOME-MOS'!M102 -> 577484.64 | M84: ='INCOME-MOS'!N102 -> 547484.64 | N84: ='INCOME-MOS'!O102 -> 535484.64 | O84: ='INCOME-MOS'!P102 -> 487484.64 | P84: =SUM(L84:O84) -> 2147938.6 | Q84: =CASHFLOW!E7 -> 488352.86 | R84: =CASHFLOW!F7 -> 1026330.3 | S84: =CASHFLOW!G7 -> 2147938.6
A85: Depreciation | B85: ='PROP & EQUIP'!$E$47/4 -> 62714.286 | C85: ='PROP & EQUIP'!$E$47/4 -> 62714.286 | D85: ='PROP & EQUIP'!$E$47/4 -> 62714.286 | E85: ='PROP & EQUIP'!$E$47/4 -> 62714.286 | F85: =SUM(B85:E85) -> 250857.14 | G85: ='PROP & EQUIP'!$F$47/4 -> 95791.667 | H85: ='PROP & EQUIP'!$F$47/4 -> 95791.667 | I85: ='PROP & EQUIP'!$F$47/4 -> 95791.667 | J85: ='PROP & EQUIP'!$F$47/4 -> 95791.667 | K85: =SUM(G85:J85) -> 383166.67 | L85: ='PROP & EQUIP'!$G$47/4 -> 129238.1 | M85: ='PROP & EQUIP'!$G$47/4 -> 129238.1 | N85: ='PROP & EQUIP'!$G$47/4 -> 129238.1 | O85: ='PROP & EQUIP'!$G$47/4 -> 129238.1 | P85: =SUM(L85:O85) -> 516952.38 | Q85: =CASHFLOW!E8 -> 250857.14 | R85: =CASHFLOW!F8 -> 383166.67 | S85: =CASHFLOW!G8 -> 516952.38
A86: Working Capital Changes
A87: (Increase)/Decrease Accounts Receivable | B87: =-(WORKCAP!$E69-WORKCAP!$D78) -> -178865 | C87: =-(WORKCAP!$E72-WORKCAP!$E69) -> 0 | D87: =-(WORKCAP!$E75-WORKCAP!$E72) -> 0 | E87: =-(WORKCAP!$E78-WORKCAP!$E75) -> 0 | F87: =SUM(B87:E87) -> -178865 | G87: =-(WORKCAP!$F69-WORKCAP!$E78) -> -176375 | H87: =-(WORKCAP!$F72-WORKCAP!$F69) -> 0 | I87: =-(WORKCAP!$F75-WORKCAP!$F72) -> 0 | J87: =-(WORKCAP!$F78-WORKCAP!$F75) -> 0 | K87: =SUM(G87:J87) -> -176375 | L87: =-(WORKCAP!$G69-WORKCAP!$F78) -> -332000 | M87: =-(WORKCAP!$G72-WORKCAP!$G69) -> 0 | N87: =-(WORKCAP!$G75-WORKCAP!$G72) -> 0 | O87: =-(WORKCAP!$G78-WORKCAP!$G75) -> 0 | P87: =SUM(L87:O87) -> -332000 | Q87: =CASHFLOW!E10 -> -178865 | R87: =CASHFLOW!F10 -> -176375 | S87: =CASHFLOW!G10 -> -332000
A88: (Increase)/Decrease Inventories | B88: =-(WORKCAP!E86-WORKCAP!D95) -> -82945 | C88: =-(WORKCAP!E89-WORKCAP!E86) -> 0 | D88: =-(WORKCAP!E92-WORKCAP!E89) -> 0 | E88: =-(WORKCAP!E95-WORKCAP!E92) -> 0 | F88: =SUM(B88:E88) -> -82945 | G88: =-(WORKCAP!F86-WORKCAP!E95) -> -142375 | H88: =-(WORKCAP!F89-WORKCAP!F86) -> 0 | I88: =-(WORKCAP!F92-WORKCAP!F89) -> 0 | J88: =-(WORKCAP!F95-WORKCAP!F92) -> 0 | K88: =SUM(G88:J88) -> -142375 | L88: =-(WORKCAP!G86-WORKCAP!F95) -> -268000 | M88: =-(WORKCAP!G89-WORKCAP!G86) -> 0 | N88: =-(WORKCAP!G92-WORKCAP!G89) -> 0 | O88: =-(WORKCAP!G95-WORKCAP!G92) -> 0 | P88: =SUM(L88:O88) -> -268000 | Q88: =CASHFLOW!E11 -> -82945 | R88: =CASHFLOW!F11 -> -142375 | S88: =CASHFLOW!G11 -> -268000
A89: (Increase)/Decrease Other Current Assets | B89: =-(WORKCAP!E103-WORKCAP!D112) -> -21550 | C89: =-(WORKCAP!E106-WORKCAP!E103) -> 0 | D89: =-(WORKCAP!E109-WORKCAP!E106) -> 0 | E89: =-(WORKCAP!E112-WORKCAP!E109) -> 0 | F89: =SUM(B89:E89) -> -21550 | G89: =-(WORKCAP!F103-WORKCAP!E112) -> -21250 | H89: =-(WORKCAP!F106-WORKCAP!F103) -> 0 | I89: =-(WORKCAP!F109-WORKCAP!F106) -> 0 | J89: =-(WORKCAP!F112-WORKCAP!F109) -> 0 | K89: =SUM(G89:J89) -> -21250 | L89: =-(WORKCAP!G103-WORKCAP!F112) -> -40000 | M89: =-(WORKCAP!G106-WORKCAP!G103) -> 0 | N89: =-(WORKCAP!G109-WORKCAP!G106) -> 0 | O89: =-(WORKCAP!G112-WORKCAP!G109) -> 0 | P89: =SUM(L89:O89) -> -40000 | Q89: =CASHFLOW!E12 -> -21550 | R89: =CASHFLOW!F12 -> -21250 | S89: =CASHFLOW!G12 -> -40000
A90: Increase/(Decrease) Accts Pay & Accrd Expenses | B90: =(WORKCAP!E120-WORKCAP!D129) -> 187485 | C90: =(WORKCAP!E123-WORKCAP!E120) -> 0 | D90: =(WORKCAP!E126-WORKCAP!E123) -> 0 | E90: =(WORKCAP!E129-WORKCAP!E126) -> 0 | F90: =SUM(B90:E90) -> 187485 | G90: =(WORKCAP!F120-WORKCAP!E129) -> 184875 | H90: =(WORKCAP!F123-WORKCAP!F120) -> 0 | I90: =(WORKCAP!F126-WORKCAP!F123) -> 0 | J90: =(WORKCAP!F129-WORKCAP!F126) -> 0 | K90: =SUM(G90:J90) -> 184875 | L90: =(WORKCAP!G120-WORKCAP!F129) -> 348000 | M90: =(WORKCAP!G123-WORKCAP!G120) -> 0 | N90: =(WORKCAP!G126-WORKCAP!G123) -> 0 | O90: =(WORKCAP!G129-WORKCAP!G126) -> 0 | P90: =SUM(L90:O90) -> 348000 | Q90: =CASHFLOW!E13 -> 187485 | R90: =CASHFLOW!F13 -> 184875 | S90: =CASHFLOW!G13 -> 348000
A91: Increase/(Decrease) Other Current Liab | B91: =(WORKCAP!E137-WORKCAP!D146) -> 21550 | C91: =(WORKCAP!E140-WORKCAP!E137) -> 0 | D91: =(WORKCAP!E143-WORKCAP!E140) -> 0 | E91: =(WORKCAP!E146-WORKCAP!E143) -> 0 | F91: =SUM(B91:E91) -> 21550 | G91: =(WORKCAP!F137-WORKCAP!E146) -> 21250 | H91: =(WORKCAP!F140-WORKCAP!F137) -> 0 | I91: =(WORKCAP!F143-WORKCAP!F140) -> 0 | J91: =(WORKCAP!F146-WORKCAP!F143) -> 0 | K91: =SUM(G91:J91) -> 21250 | L91: =(WORKCAP!G137-WORKCAP!F146) -> 40000 | M91: =(WORKCAP!G140-WORKCAP!G137) -> 0 | N91: =(WORKCAP!G143-WORKCAP!G140) -> 0 | O91: =(WORKCAP!G146-WORKCAP!G143) -> 0 | P91: =SUM(L91:O91) -> 40000 | Q91: =CASHFLOW!E14 -> 21550 | R91: =CASHFLOW!F14 -> 21250 | S91: =CASHFLOW!G14 -> 40000
A92: Net Cash Provided/(Used) by Operating Activities | B92: =SUM(B84:B91) -> 145477.5 | C92: =SUM(C84:C91) -> 139802.5 | D92: =SUM(D84:D91) -> 199802.5 | E92: =SUM(E84:E91) -> 179802.5 | F92: =SUM(B92:E92) -> 664885 | G92: =SUM(G84:G91) -> 257682.12 | H92: =SUM(H84:H91) -> 363060.48 | I92: =SUM(I84:I91) -> 306067.2 | J92: =SUM(J84:J91) -> 348812.16 | K92: =SUM(G92:J92) -> 1275622 | L92: =SUM(L84:L91) -> 454722.74 | M92: =SUM(M84:M91) -> 676722.74 | N92: =SUM(N84:N91) -> 664722.74 | O92: =SUM(O84:O91) -> 616722.74 | P92: =SUM(L92:O92) -> 2412891 | Q92: =CASHFLOW!E15 -> 664885 | R92: =CASHFLOW!F15 -> 1275622 | S92: =CASHFLOW!G15 -> 2412891
A94: INVESTING ACTIVITIES
A95: Property & Equipment | B95: =-'PROP & EQUIP'!E64 -> -200000 | C95: =-'PROP & EQUIP'!E68 -> 0 | D95: =-'PROP & EQUIP'!E72 -> -100000 | E95: =-'PROP & EQUIP'!E76 -> -270000 | F95: =SUM(B95:E95) -> -570000 | G95: =-'PROP & EQUIP'!F64 -> -200000 | H95: =-'PROP & EQUIP'!F68 -> -165000 | I95: =-'PROP & EQUIP'!F72 -> -100000 | J95: =-'PROP & EQUIP'!F76 -> -200000 | K95: =SUM(G95:J95) -> -665000 | L95: =-'PROP & EQUIP'!G64 -> -200000 | M95: =-'PROP & EQUIP'!G68 -> -250000 | N95: =-'PROP & EQUIP'!G72 -> -150000 | O95: =-'PROP & EQUIP'!G76 -> -150000 | P95: =SUM(L95:O95) -> -750000 | Q95: =CASHFLOW!E18 -> -570000 | R95: =CASHFLOW!F18 -> -665000 | S95: =CASHFLOW!G18 -> -750000
A96: Other | F96: =SUM(B96:E96) -> 0 | K96: =SUM(G96:J96) -> 0 | Q96: =CASHFLOW!E19 -> 0 | R96: =CASHFLOW!F19 -> 0 | S96: =CASHFLOW!G19 -> 0
A97: Net Cash Used in Investing Activities | B97: =SUM(B95:B96) -> -200000 | C97: =SUM(C95:C96) -> 0 | D97: =SUM(D95:D96) -> -100000 | E97: =SUM(E95:E96) -> -270000 | F97: =SUM(B97:E97) -> -570000 | G97: =SUM(G95:G96) -> -200000 | H97: =SUM(H95:H96) -> -165000 | I97: =SUM(I95:I96) -> -100000 | J97: =SUM(J95:J96) -> -200000 | K97: =SUM(G97:J97) -> -665000 | L97: =SUM(L95:L96) -> -200000 | M97: =SUM(M95:M96) -> -250000 | N97: =SUM(N95:N96) -> -150000 | O97: =SUM(O95:O96) -> -150000 | P97: =SUM(L97:O97) -> -750000 | Q97: =CASHFLOW!E20 -> -570000 | R97: =CASHFLOW!F20 -> -665000 | S97: =CASHFLOW!G20 -> -750000
A99: FINANCING ACTIVITIES
A100: Increase/(Decrease) Short Term Debt | B100: =IF(FUNDING!E19>=0,FUNDING!E19,0) -> 450000 | E100: =IF(FUNDING!E19<0,FUNDING!E19,0) -> 0 | F100: =SUM(B100:E100) -> 450000 | G100: =IF(FUNDING!F19>=0,FUNDING!F19,0) -> 0 | J100: =IF(FUNDING!F19<0,FUNDING!F19,0) -> -700000 | K100: =SUM(G100:J100) -> -700000 | L100: =IF(FUNDING!G19>=0,FUNDING!G19,0) -> 0 | O100: =IF(FUNDING!G19<0,FUNDING!G19,0) -> -100000 | P100: =SUM(L100:O100) -> -100000 | Q100: =CASHFLOW!E23 -> 450000 | R100: =CASHFLOW!F23 -> -700000 | S100: =CASHFLOW!G23 -> -100000
A101: Increase/(Decrease) Curr. Portion LTD | B101: =IF(FUNDING!E27>=0,FUNDING!E27,0) -> 25000 | E101: =IF(FUNDING!E27<0,FUNDING!E27,0) -> 0 | F101: =SUM(B101:E101) -> 25000 | G101: =IF(FUNDING!F27>=0,FUNDING!F27,0) -> 25000 | J101: =IF(FUNDING!F27<0,FUNDING!F27,0) -> 0 | K101: =SUM(G101:J101) -> 25000 | L101: =IF(FUNDING!G27>=0,FUNDING!G27,0) -> 25000 | O101: =IF(FUNDING!G27<0,FUNDING!G27,0) -> 0 | P101: =SUM(L101:O101) -> 25000 | Q101: =CASHFLOW!E24 -> 25000 | R101: =CASHFLOW!F24 -> 25000 | S101: =CASHFLOW!G24 -> 25000
A102: Increase/(Decrease) Long Term Debt | B102: =IF(FUNDING!E28>=0,FUNDING!E28,0) -> 0 | E102: =IF(FUNDING!E28<0,FUNDING!E28,0) -> -300000 | F102: =SUM(B102:E102) -> -300000 | G102: =IF(FUNDING!F28>=0,FUNDING!F28,0) -> 0 | J102: =IF(FUNDING!F28<0,FUNDING!F28,0) -> -400000 | K102: =SUM(G102:J102) -> -400000 | L102: =IF(FUNDING!G28>=0,FUNDING!G28,0) -> 0 | O102: =IF(FUNDING!G28<0,FUNDING!G28,0) -> -400000 | P102: =SUM(L102:O102) -> -400000 | Q102: =CASHFLOW!E25 -> -300000 | R102: =CASHFLOW!F25 -> -400000 | S102: =CASHFLOW!G25 -> -400000
A103: Increase/(Decrease) Common Stock | B103: =IF(FUNDING!E9>=0,FUNDING!E9,0) -> 0 | E103: =IF(FUNDING!E9<0,FUNDING!E9,0) -> -150000 | F103: =SUM(B103:E103) -> -150000 | G103: =IF(FUNDING!F9>=0,FUNDING!F9,0) -> 400000 | J103: =IF(FUNDING!F9<0,FUNDING!F9,0) -> 0 | K103: =SUM(G103:J103) -> 400000 | L103: =IF(FUNDING!G9>=0,FUNDING!G9,0) -> 0 | O103: =IF(FUNDING!G9<0,FUNDING!G9,0) -> -200000 | P103: =SUM(L103:O103) -> -200000 | Q103: =CASHFLOW!E26 -> -150000 | R103: =CASHFLOW!F26 -> 400000 | S103: =CASHFLOW!G26 -> -200000
A104: Increase/(Decrease) Preferred Stock | B104: =IF(FUNDING!E14>=0,FUNDING!E14,0) -> 0 | E104: =IF(FUNDING!E14<0,FUNDING!E14,0) -> 0 | F104: =SUM(B104:E104) -> 0 | G104: =IF(FUNDING!F14>=0,FUNDING!F14,0) -> 0 | J104: =IF(FUNDING!F14<0,FUNDINGf14,0) -> 0 | K104: =SUM(G104:J104) -> 0 | L104: =IF(FUNDING!G14>=0,FUNDING!G14,0) -> 0 | O104: =IF(FUNDING!G14<0,FUNDING!G14,0) -> 0 | P104: =SUM(L104:O104) -> 0 | Q104: =CASHFLOW!E27 -> 0 | R104: =CASHFLOW!F27 -> 0 | S104: =CASHFLOW!G27 -> 0
A105: Dividends Declared | E105: =-FUNDING!E49 -> -40000 | F105: =SUM(B105:E105) -> -40000 | J105: =-FUNDING!F49 -> -50000 | K105: =SUM(G105:J105) -> -50000 | O105: =-FUNDING!G49 -> -50000 | P105: =SUM(L105:O105) -> -50000 | Q105: =CASHFLOW!E28 -> -40000 | R105: =CASHFLOW!F28 -> -50000 | S105: =CASHFLOW!G28 -> -50000
A106: Net Cash Provided / (Used) by Financing | B106: =SUM(B100:B105) -> 475000 | C106: =SUM(C100:C105) -> 0 | D106: =SUM(D100:D105) -> 0 | E106: =SUM(E100:E105) -> -490000 | F106: =SUM(B106:E106) -> -15000 | G106: =SUM(G100:G105) -> 425000 | H106: =SUM(H100:H105) -> 0 | I106: =SUM(I100:I105) -> 0 | J106: =SUM(J100:J105) -> -1150000 | K106: =SUM(G106:J106) -> -725000 | L106: =SUM(L100:L105) -> 25000 | M106: =SUM(M100:M105) -> 0 | N106: =SUM(N100:N105) -> 0 | O106: =SUM(O100:O105) -> -750000 | P106: =SUM(O106) -> -750000 | Q106: =CASHFLOW!E29 -> -15000 | R106: =CASHFLOW!F29 -> -725000 | S106: =CASHFLOW!G29 -> -725000
A108: INCREASE/(DECREASE) IN CASH | B108: =B92+B97+B106 -> 420477.5 | C108: =C92+C97+C106 -> 139802.5 | D108: =D92+D97+D106 -> 99802.5 | E108: =E92+E97+E106 -> -580197.5 | F108: =SUM(B108:E108) -> 79885 | G108: =G92+G97+G106 -> 482682.12 | H108: =H92+H97+H106 -> 198060.48 | I108: =I92+I97+I106 -> 206067.2 | J108: =J92+J97+J106 -> -1001187.8 | K108: =SUM(G108:J108) -> -114378.05 | L108: =L92+L97+L106 -> 279722.74 | M108: =M92+M97+M106 -> 426722.74 | N108: =N92+N97+N106 -> 514722.74 | O108: =O92+O97+O106 -> -283277.26 | P108: =SUM(L108:O108) -> 937890.95 | Q108: =CASHFLOW!E31 -> 79885 | R108: =CASHFLOW!F31 -> -114378.05 | S108: =CASHFLOW!G31 -> 937890.95
A110: CASH AT BEGINNING OF PERIOD | B110: =M75 -> 3394540 | C110: =B111 -> 3815017.5 | D110: =C111 -> 3954820 | E110: =D111 -> 4054622.5 | G110: =E111 -> 3474425 | H110: =G111 -> 3957107.1 | I110: =H111 -> 4155167.6 | J110: =I111 -> 4361234.8 | L110: =J111 -> 3360047 | M110: =L111 -> 3639769.7 | N110: =M111 -> 4066492.4 | O110: =N111 -> 4581215.2 | Q110: =CASHFLOW!E33 -> 3394540 | R110: =CASHFLOW!F33 -> 3474425 | S110: =CASHFLOW!G33 -> 3360047
A111: CASH AT END OF PERIOD | B111: =B108+B110 -> 3815017.5 | C111: =C108+C110 -> 3954820 | D111: =D108+D110 -> 4054622.5 | E111: =E108+E110 -> 3474425 | G111: =G108+G110 -> 3957107.1 | H111: =H108+H110 -> 4155167.6 | I111: =I108+I110 -> 4361234.8 | J111: =J108+J110 -> 3360047 | L111: =L108+L110 -> 3639769.7 | M111: =M108+M110 -> 4066492.4 | N111: =N108+N110 -> 4581215.2 | O111: =O108+O110 -> 4297937.9 | Q111: =CASHFLOW!E34 -> 3474425 | R111: =CASHFLOW!F34 -> 3360047 | S111: =CASHFLOW!G34 -> 4297937.9

Sheet Sheet1

Sheet SUMMARY
A1: XYZ Company
A2: Summary
A3: Years 1 to 5
C5: Year 1 | D5: Year 2 | E5: Year 3 | F5: Year 4 | G5: Year 5
A6: Summary Financials ($)
A7: Revenue | C7: =INCOME!C7 -> 2750000 | D7: =INCOME!D7 -> 3840000 | E7: =INCOME!E7 -> 5995000 | F7: =INCOME!F7 -> 8120000 | G7: =INCOME!G7 -> 12120000
A8: Gross Profit | C8: =INCOME!C12 -> 1424471.4 | D8: =INCOME!D12 -> 1924000 | E8: =INCOME!E12 -> 3480942.9 | F8: =INCOME!F12 -> 5005300 | G8: =INCOME!G12 -> 8056164.3
A9: EBIT | C9: =INCOME!C26 -> -262528.57 | D9: =INCOME!D26 -> -221300 | E9: =INCOME!E26 -> 707952.86 | F9: =INCOME!F26 -> 1564633.3 | G9: =INCOME!G26 -> 3667097.6
A10: EBITDA | C10: =INCOME!C26+'PROP & EQUIP'!C47 -> -217400 | D10: =INCOME!D26+'PROP & EQUIP'!D47 -> -87800 | E10: =INCOME!E26+'PROP & EQUIP'!E47 -> 958810 | F10: =INCOME!F26+'PROP & EQUIP'!F47 -> 1947800 | G10: =INCOME!G26+'PROP & EQUIP'!G47 -> 4184050
A11: Net Earnings | C11: =INCOME!C34 -> -476628.57 | D11: =INCOME!D34 -> -416600 | E11: =INCOME!E34 -> 488352.86 | F11: =INCOME!F34 -> 1026330.3 | G11: =INCOME!G34 -> 2147938.6
A12: Net Cash from Operating Activities | C12: =CASHFLOW!C15 -> -721166.67 | D12: =CASHFLOW!D15 -> -296793.33 | E12: =CASHFLOW!E15 -> 664885 | F12: =CASHFLOW!F15 -> 1275622 | G12: =CASHFLOW!G15 -> 2412891
A13: Capital Expenditures | C13: ='PROP & EQUIP'!C13 -> 289500 | D13: ='PROP & EQUIP'!D13 -> 493000 | E13: ='PROP & EQUIP'!E13 -> 570000 | F13: ='PROP & EQUIP'!F13 -> 665000 | G13: ='PROP & EQUIP'!G13 -> 750000
A14: Interest Income/(Expense) | C14: =FUNDING!C45-FUNDING!C41 -> -214100 | D14: =FUNDING!D45-FUNDING!D41 -> -195300 | E14: =FUNDING!E45-FUNDING!E41 -> -219600 | F14: =FUNDING!F45-FUNDING!F41 -> -124000 | G14: =FUNDING!G45-FUNDING!G41 -> -87200
A15: Dividends | C15: =FUNDING!C49 -> 0 | D15: =FUNDING!D49 -> 30000 | E15: =FUNDING!E49 -> 40000 | F15: =FUNDING!F49 -> 50000 | G15: =FUNDING!G49 -> 50000
A16: Cash | C16: =BALANCE!C9 -> 3439333.3 | D16: =BALANCE!D9 -> 3394540 | E16: =BALANCE!E9 -> 3474425 | F16: =BALANCE!F9 -> 3360047 | G16: =BALANCE!G9 -> 4297937.9
A17: Total Equity | C17: =FUNDING!C52+FUNDING!C8+FUNDING!C10 -> 23371.429 | D17: =FUNDING!D52+FUNDING!D8+FUNDING!D10 -> -173228.57 | E17: =FUNDING!E52+FUNDING!E8+FUNDING!E10 -> 125124.29 | F17: =FUNDING!F52+FUNDING!F8+FUNDING!F10 -> 1501454.6 | G17: =FUNDING!G52+FUNDING!G8+FUNDING!G10 -> 3399393.1
A18: Total Debt | C18: =FUNDING!C24 -> 2500000 | D18: =FUNDING!D24 -> 2375000 | E18: =FUNDING!E24 -> 2100000 | F18: =FUNDING!F24 -> 1725000 | G18: =FUNDING!G24 -> 1350000
A20: Growth
A21: Revenue Growth Rate - CAGR: | D21: =D7/C7-1 -> 0.39636364 | E21: =E7/D7-1 -> 0.56119792 | F21: =F7/E7-1 -> 0.35446205 | G21: =G7/F7-1 -> 0.49261084
A22: Net Earnings Growth Rate - CAGR: | D22: =IF((INCOME!D34/INCOME!C34-1)>0,(INCOME!D34/INCOME!C34-1),"Nil") -> Nil | E22: =IF((INCOME!E34/INCOME!D34-1)>0,(INCOME!E34/INCOME!D34-1),"Nil") -> Nil | F22: =IF((INCOME!F34/INCOME!E34-1)>0,(INCOME!F34/INCOME!E34-1),"Nil") -> 1.1016162 | G22: =IF((INCOME!G34/INCOME!F34-1)>0,(INCOME!G34/INCOME!F34-1),"Nil") -> 1.0928337
A24: Ratios
A25: Current Ratio | C25: =BALANCE!C13/BALANCE!C23 -> 3.8692769 | D25: =BALANCE!D13/BALANCE!D23 -> 4.0806633 | E25: =BALANCE!E13/BALANCE!E23 -> 2.6366848 | F25: =BALANCE!F13/BALANCE!F23 -> 3.8422343 | G25: =BALANCE!G13/BALANCE!G23 -> 4.0882108
A26: Debt to Capital (LT Debt + Equity) | C26: =(BALANCE!C25+BALANCE!C22)/(BALANCE!C25+BALANCE!C22+BALANCE!C31) -> 0.67143449 | D26: =(BALANCE!D25+BALANCE!D22)/(BALANCE!D25+BALANCE!D22+BALANCE!D31) -> 0.57204498 | E26: =(BALANCE!E25+BALANCE!E22)/(BALANCE!E25+BALANCE!E22+BALANCE!E31) -> 0.50297904 | F26: =(BALANCE!F25+BALANCE!F22)/(BALANCE!F25+BALANCE!F22+BALANCE!F31) -> 0.33323967 | G26: =(BALANCE!G25+BALANCE!G22)/(BALANCE!G25+BALANCE!G22+BALANCE!G31) -> 0.20151079
A28: Profitability
A29: Gross Profit % | C29: =INCOME!C13 -> 0.51798961 | D29: =INCOME!D13 -> 0.50104167 | E29: =INCOME!E13 -> 0.58064101 | F29: =INCOME!F13 -> 0.61641626 | G29: =INCOME!G13 -> 0.66470002
A30: Operating Expenses % | C30: =INCOME!C20 -> 0.56981818 | D30: =INCOME!D20 -> 0.58861979 | E30: =INCOME!E20 -> 0.49257548 | F30: =INCOME!F20 -> 0.45574713 | G30: =INCOME!G20 -> 0.38936194
A31: Net Earnings % | C31: =C11/C7 -> -0.17331948 | D31: =D11/D7 -> -0.10848958 | E31: =E11/E7 -> 0.081460026 | F31: =F11/F7 -> 0.12639536 | G31: =G11/G7 -> 0.17722265
A33: Returns
A34: Return on Assets | C34: =INCOME!C34/BALANCE!C15 -> -0.11010034 | D34: =INCOME!D34/BALANCE!D15 -> -0.089126571 | E34: =INCOME!E34/BALANCE!E15 -> 0.09116777 | F34: =INCOME!F34/BALANCE!F15 -> 0.1750194 | G34: =INCOME!G34/BALANCE!G15 -> 0.27986049
A35: Return on Equity | C35: =INCOME!C34/BALANCE!C31 -> -0.3896025 | D35: =INCOME!D34/BALANCE!D31 -> -0.23447023 | E35: =INCOME!E34/BALANCE!E31 -> 0.23533668 | F35: =INCOME!F34/BALANCE!F31 -> 0.29736167 | G35: =INCOME!G34/BALANCE!G31 -> 0.40152939
A36: Return on Capital (LT Debt + Equity) | C36: =INCOME!C34/(BALANCE!C22+BALANCE!C25+BALANCE!C31) -> -0.12800994 | D36: =INCOME!D34/(BALANCE!D22+BALANCE!D25+BALANCE!D31) -> -0.10034271 | E36: =INCOME!E34/(BALANCE!E22+BALANCE!E25+BALANCE!E31) -> 0.11696726 | F36: =INCOME!F34/(BALANCE!F22+BALANCE!F25+BALANCE!F31) -> 0.19826896 | G36: =INCOME!G34/(BALANCE!G22+BALANCE!G25+BALANCE!G31) -> 0.32061689

Sheet VAL-1
A1: XYZ Company
A2: Valuation
A3: Venture Capital Method
A4: Years 1 to 5
A6: Assumptions:
A7: Investor required IRR | B7: 0.6
A8: P/E ratio at IPO or acquisition | B8: 15
A9: Initial investment | B9: 1500000
A12: Valuation Calculation | B12: Year | C12: Net Income | D12: Market Capitalization | E12: Required Future Value (Investor) | F12: Investor's Share | G12: Investor's Return | H12: Investor's ROI | I12: Investor's IRR | J12: IRR Calculation Workspace
A13: Calculation | C13: Income Stmt | D13: B * E | E13: FV(F,D) | F13: C / G | G13: F * H | H13: I / C | I13: IRR(I,C,D) | J13: Start | K13: Year 1 | L13: Year 2 | M13: Year 3 | N13: Year 4 | O13: Year 5
A14: Liquidity Event in Year 1 | B14: 1 | C14: =INCOME!C34 -> -476628.57 | D14: =C14*B$8 -> -7149428.6 | E14: =B$9*(1+B$7)^B14 -> 2400000 | F14: =IF(C14<=0,1,E14/D14) -> 1 | G14: =IF(D14<0,0,IF(E14>D14,D14,E14)) -> 0 | H14: =G14/B$9 -> 0 | I14: =IF(D14<=0,NA(),IRR(J14:O14)) -> #N/A | J14: =-B$9 -> -1500000 | K14: =G14 -> 0
A15: Liquidity Event in Year 2 | B15: 2 | C15: =INCOME!D34 -> -416600 | D15: =C15*B$8 -> -6249000 | E15: =B$9*(1+B$7)^B15 -> 3840000 | F15: =IF(C15<=0,1,E15/D15) -> 1 | G15: =IF(D15<0,0,IF(E15>D15,D15,E15)) -> 0 | H15: =G15/B$9 -> 0 | I15: =IF(D15<=0,NA(),IRR(J15:O15)) -> #N/A | J15: =-B$9 -> -1500000 | K15: 0 | L15: =G15 -> 0
A16: Liquidity Event in Year 3 | B16: 3 | C16: =INCOME!E34 -> 488352.86 | D16: =C16*B$8 -> 7325292.9 | E16: =B$9*(1+B$7)^B16 -> 6144000 | F16: =IF(C16<=0,1,E16/D16) -> 0.8387378 | G16: =IF(D16<0,0,IF(E16>D16,D16,E16)) -> 6144000 | H16: =G16/B$9 -> 4.096 | I16: =IF(D16<=0,NA(),IRR(J16:O16)) -> 0.6 | J16: =-B$9 -> -1500000 | K16: 0 | L16: 0 | M16: =G16 -> 6144000
A17: Liquidity Event in Year 4 | B17: 4 | C17: =INCOME!F34 -> 1026330.3 | D17: =C17*B$8 -> 15394954 | E17: =B$9*(1+B$7)^B17 -> 9830400 | F17: =IF(C17<=0,1,E17/D17) -> 0.63854688 | G17: =IF(D17<0,0,IF(E17>D17,D17,E17)) -> 9830400 | H17: =G17/B$9 -> 6.5536 | I17: =IF(D17<=0,NA(),IRR(J17:O17)) -> 0.6 | J17: =-B$9 -> -1500000 | K17: 0 | L17: 0 | M17: 0 | N17: =G17 -> 9830400
A18: Liquidity Event in Year 5 | B18: 5 | C18: =INCOME!G34 -> 2147938.6 | D18: =C18*B$8 -> 32219079 | E18: =B$9*(1+B$7)^B18 -> 15728640 | F18: =IF(C18<=0,1,E18/D18) -> 0.48817783 | G18: =IF(D18<0,0,IF(E18>D18,D18,E18)) -> 15728640 | H18: =G18/B$9 -> 10.48576 | I18: =IF(D18<=0,NA(),IRR(J18:O18)) -> 0.6 | J18: =-B$9 -> -1500000 | K18: 0 | L18: 0 | M18: 0 | N18: 0 | O18: =G18 -> 15728640
F21: Negotiation Workspace
E22: Year | F22: Investor's Share | G22: Investor's Return | H22: Investor's ROI | I22: Investor's IRR
E23: 1 | F23: 0.25 | G23: =IF(D14<0,0,F23*D14) -> 0 | H23: =G23/B$9 -> 0 | I23: =IF(G23=0,NA(),IRR(J23:O23)) -> #N/A | J23: =-B$9 -> -1500000 | K23: =G23 -> 0
E24: 2 | F24: 0.25 | G24: =IF(D15<0,0,F24*D15) -> 0 | H24: =G24/B$9 -> 0 | I24: =IF(G24=0,NA(),IRR(J24:O24)) -> #N/A | J24: =-B$9 -> -1500000 | K24: 0 | L24: =G24 -> 0
E25: 3 | F25: 0.25 | G25: =IF(D16<0,0,F25*D16) -> 1831323.2 | H25: =G25/B$9 -> 1.2208821 | I25: =IF(G25=0,NA(),IRR(J25:O25)) -> 0.068787208 | J25: =-B$9 -> -1500000 | K25: 0 | L25: 0 | M25: =G25 -> 1831323.2
E26: 4 | F26: 0.25 | G26: =IF(D17<0,0,F26*D17) -> 3848738.6 | H26: =G26/B$9 -> 2.5658257 | I26: =IF(G26=0,NA(),IRR(J26:O26)) -> 0.26563008 | J26: =-B$9 -> -1500000 | K26: 0 | L26: 0 | M26: 0 | N26: =G26 -> 3848738.6
E27: 5 | F27: 0.4 | G27: =IF(D18<0,0,F27*D18) -> 12887631 | H27: =G27/B$9 -> 8.5917543 | I27: =IF(G27=0,NA(),IRR(J27:O27)) -> 0.53750441 | J27: =-B$9 -> -1500000 | K27: 0 | L27: 0 | M27: 0 | N27: 0 | O27: =G27 -> 12887631

Sheet VAL-2
A1: XYZ Company
A2: Valuation
A3: Venture Capital Method
A4: Years 1 to 5
A5: Multiple Rounds
A8: Assumptions
A9: Month of IPO | B9: 60
A10: Forecast annualized earnings at IPO | B10: =INCOME!G34 -> 2147938.6
A11: P/E ratio at IPO | B11: 15
A13: Investment Round | B13: First | C13: Second | D13: Third
A14: Month of Investment | B14: 0 | C14: 24 | D14: 18
A15: Investor required IRR | B15: 0.6 | C15: 0.5 | D15: 0.3
A16: Amount of Investment | B16: 1500000 | C16: 500000 | D16: 750000
A17: Required Monthly IRR | B17: =B15/12 -> 0.05 | C17: =C15/12 -> 0.041666667 | D17: =D15/12 -> 0.025
A18: Duration of Investment | B18: =$B$9-B14 -> 60 | C18: =$B$9-C14 -> 36 | D18: =$B$9-D14 -> 42
A20: Calculations
A21: Market Capitalization at IPO | B21: =B11*B10 -> 32219079
B23: First | C23: Second | D23: Third
A24: Required FV for Investor at IPO | B24: =B16*(1+B15)^(B18/12) -> 15728640 | C24: =C16*(1+C15)^(C18/12) -> 1687500 | D24: =D16*(1+D15)^(D18/12) -> 1878724.1
A25: Individual Investor's Share | B25: =B24/$B$21 -> 0.48817783 | C25: =C24/$B$21 -> 0.0523758 | D25: =D24/$B$21 -> 0.058310918
A26: Individual Investor's ROI | B26: =B24/B16 -> 10.48576 | C26: =C24/C16 -> 3.375 | D26: =D24/D16 -> 2.5049654
A27: Individual Investor's IRR | B27: =(B24/B16)^(12/B18)-1 -> 0.6 | C27: =(C24/C16)^(12/C18)-1 -> 0.5 | D27: =(D24/D16)^(12/D18)-1 -> 0.3
A29: Cumulative Investors' Share | B29: =B25 -> 0.48817783 | C29: =SUM(B25:C25) -> 0.54055363 | D29: =SUM(B25:D25) -> 0.59886455
A30: Cumulative Founders' Share | B30: =1-B29 -> 0.51182217 | C30: =1-C29 -> 0.45944637 | D30: =1-D29 -> 0.40113545
A33: Negotiations Round | B33: First | C33: Second | D33: Third
A34: Individual Investor's Share | B34: 0.15 | C34: 0.05 | D34: 0.03
A35: FV for Investor at IPO | B35: =B34*$B$21 -> 4832861.8 | C35: =C34*$B$21 -> 1610953.9 | D35: =D34*$B$21 -> 966572.36
A36: Individual Investor's ROI | B36: =B35/B16 -> 3.2219079 | C36: =C35/C16 -> 3.2219079 | D36: =D35/D16 -> 1.2887631
A37: Individual Investor's IRR | B37: =(B35/B16)^(12/B18)-1 -> 0.26363784 | C37: =(C35/C16)^(12/C18)-1 -> 0.47696784 | D37: =(D35/D16)^(12/D18)-1 -> 0.07517221
