Workbook

Sheet Valuation & Returns
D3: Key Assumptions | I3: Valuations & Returns
D4: Purchase Price: | E4: 1650000
D5: Maintenance CapEx % of revenue: | E5: 0.02
I7: ($ in 000'S)
E8: FY2024 | F8: FY2025 | G8: FY2026 | J8: FY2024 | K8: FY2025 | L8: FY2026 | N8: EV/EBITDA Multiple | O8: Valuation | P8: IRR
D9: Purchase Price | E9: -1650000 | F9: =E9 -> -1650000 | G9: =F9 -> -1650000 | I9: Purchase Price | J9: =E9/$D$39 -> -1650 | K9: =F9/$D$39 -> -1650 | L9: =G9/$D$39 -> -1650 | N9: 10 | O9: =N9*$L$12 -> 4806.1127 | P9: =N35 -> 0.5915053
D10: Revenue | E10: ='220k EBITDA'!AI12 -> 1842485.3 | F10: ='220k EBITDA'!AL12 -> 2053503.1 | G10: ='220k EBITDA'!AO12 -> 2115108.2 | I10: Practice Revenue | J10: =E10/$D$39 -> 1842.4853 | K10: =F10/$D$39 -> 2053.5031 | L10: =G10/$D$39 -> 2115.1082 | N10: 11 | O10: =N10*$L$12 -> 5286.724 | P10: =N36 -> 0.63328291
I11: Revenue Multiple | J11: =-J$9/J10 -> 0.89552951 | K11: =-K$9/K10 -> 0.80350499 | L11: =-L$9/L10 -> 0.78010194
D12: EBITDA | E12: ='220k EBITDA'!AI39 -> 341810.93 | F12: ='220k EBITDA'!AL39 -> 455646 | G12: ='220k EBITDA'!AO39 -> 480611.27 | I12: Practice EBITDA | J12: =E12/$D$39 -> 341.81093 | K12: =F12/$D$39 -> 455.646 | L12: =G12/$D$39 -> 480.61127
I13: EBITDA Multiple | J13: =-J$9/J12 -> 4.82723 | K13: =-K$9/K12 -> 3.6212323 | L13: =-L$9/L12 -> 3.433128
J15: Initial | K15: FY2024 | L15: FY2025 | M15: FY2026
I16: Purchase Price | J16: =J9 -> -1650
I17: Annual Practice EBITDA | K17: =J12 -> 341.81093 | L17: =K12 -> 455.646 | M17: =L12 -> 480.61127
I18: Transition CapEx | K18: =-(10000/$D$39) -> -10
I19: Maintenance CapEx | K19: =-(0.02*J10) -> -36.849707 | L19: =-(0.02*K10) -> -41.070062 | M19: =-(0.02*L10) -> -42.302164
I20: Practice Net Cash Flows | J20: =SUM(J16:J19) -> -1650 | K20: =SUM(K16:K19) -> 294.96123 | L20: =SUM(L16:L19) -> 414.57593 | M20: =SUM(M16:M19) -> 438.30911
I21: Cumulative Cash Flows | J21: =J20 -> -1650 | K21: =J21+K20 -> -1355.0388 | L21: =K21+L20 -> -940.46284 | M21: =L21+M20 -> -502.15373
I22: Fraction Row | J22: =IF(J21<0,"-",ABS(I21/J20)) -> - | K22: =IF(K21<0,"-",ABS(J21/K20)) -> - | L22: =IF(L21<0,"-",ABS(K21/L20)) -> - | M22: =IF(M21<0,"-",ABS(L21/M20)) -> -
I24: Key Figures
I25: Payback Period (Years) | J25: >3 years
I26: 2026 ROIC | J26: =SUM($K$17:$M$17)/-SUM($J$16,$J$18:$M$18,$J$19:$M$19) -> 0.71792633
I27: Cumulative EBITDA | J27: =SUM(K17:M17) -> 1278.0682
I28: Invested Capital | J28: =-SUM(J16,J18:M18,J19:M19) -> 1780.2219
I32: =N8 -> EV/EBITDA Multiple | J32: =J15 -> Initial | K32: =K15 -> FY2024 | L32: =L15 -> FY2025 | M32: =M15 -> FY2026 | N32: IRR
I33: 8 | J33: =J20 -> -1650 | K33: =K20 -> 294.96123 | L33: =L20 -> 414.57593 | M33: =M20+(I33*L12) -> 4283.1993 | N33: =IRR(J33:M33) -> 0.49999755
I34: 9 | J34: =J20 -> -1650 | K34: =K20 -> 294.96123 | L34: =L20 -> 414.57593 | M34: =M20+(I34*L12) -> 4763.8106 | N34: =IRR(J34:M34) -> 0.5472165
I35: 10 | J35: =J20 -> -1650 | K35: =K20 -> 294.96123 | L35: =L20 -> 414.57593 | M35: =M20+O9 -> 5244.4218 | N35: =IRR(J35:M35) -> 0.5915053
I36: 11 | J36: =J20 -> -1650 | K36: =K20 -> 294.96123 | L36: =L20 -> 414.57593 | M36: =M20+O10 -> 5725.0331 | N36: =IRR(J36:M36) -> 0.63328291
D39: 1000

Sheet 220k EBITDA
K2: Person0161 (MD)
K3: Pro Forma Model
AC4: QofE Revenue
AC5: MINUS DR Product0014
W6: *Sept 2023 TTM* | Z6: FY 2023 | AC6: *Sept 2023 TTM* | AF6: Combines 2023 with Doctor leaving
E7: Actuals | H7: Actuals | K7: Actuals | N7: Actuals | Q7: Company1574 EBITDA Calculation | T7: Company1574 EBITDA Calculation | W7: Company1574 EBITDA Calculation | Z7: Company1574 EBITDA Calculation | AC7: Company1574 EBITDA Calculation | AF7: Company1574 EBITDA Calculation | AI7: Proforma | AL7: Proforma | AO7: Proforma
E8: 2020 | F8: % Revenue | H8: 2021 | I8: % Revenue | K8: 2022 | L8: % Revenue | N8: 2023 TTM | O8: % Revenue | Q8: 2021 | R8: % Revenue | T8: 2022 | U8: % Revenue | W8: 2023 TTM | X8: % Revenue | Z8: 2023 FY | AA8: % Revenue | AC8: 2023 TTM | AD8: % Revenue | AF8: 2023 FY | AG8: % Revenue | AI8: 2024 | AJ8: % Revenue | AL8: 2025 | AM8: % Revenue | AO8: 2026 | AP8: % Revenue
C10: Clinical Revenue | D10: Revenue | E10: 1132420 | F10: 1 | H10: 1152650 | I10: 1 | K10: 1626511 | L10: 1 | N10: 1745051.1 | O10: 1 | R10: 0 | T10: 1626511 | U10: 1 | W10: 1745051.1 | X10: 1 | Z10: 1725748.9 | AA10: 1 | AC10: 1652239.5 | AD10: 1 | AF10: 1632937.2 | AG10: 1 | AI10: 1681925.3 | AJ10: 0.91285684 | AL10: 1732383.1 | AM10: 0.84362332 | AO10: 1784354.6 | AP10: 0.84362332
D11: New Doctor Revenue | R11: 0 | U11: 0 | Z11: 0 | AA11: 0 | AF11: 0 | AG11: 0 | AI11: 160560 | AJ11: 0.087143163 | AL11: 321120 | AM11: 0.15637668 | AO11: 330753.6 | AP11: 0.15637668
D12: Revenue | E12: 1132420 | F12: 1 | H12: 1152650 | I12: 1 | K12: 1626511 | L12: 1 | N12: 1745051.1 | O12: 1 | R12: 0 | T12: 1626511 | U12: 1 | W12: 1745051.1 | X12: 1 | Z12: 1725748.9 | AA12: 1 | AC12: 1652239.5 | AD12: 1 | AF12: 1632937.2 | AG12: 1 | AI12: 1842485.3 | AJ12: 1 | AL12: 2053503.1 | AM12: 1 | AO12: 2115108.2 | AP12: 1
D14: Labor
C15: Doctor Labor | D15: Doctor Labor | E15: 0 | F15: 0 | H15: 0 | I15: 0 | K15: 0 | L15: 0 | N15: 0 | O15: 0 | R15: 0 | T15: 518200 | U15: 0.31859606 | W15: 460600 | X15: 0.26394642 | Z15: 452674.83 | AA15: 0.26230631 | AC15: 408600 | AD15: 0.24730071 | AF15: 400674.83 | AG15: 0.24537062 | AI15: 482963.07 | AJ15: 0.26212587 | AL15: 543511.93 | AM15: 0.26467548 | AO15: 559154.28 | AP15: 0.26436202
C16: Staff Labor | D16: Staff Labor | E16: 529364 | F16: 0.4674626 | H16: 490292 | I16: 0.42536069 | K16: 648810 | L16: 0.39889678 | N16: 796610.35 | O16: 0.45649685 | R16: 0 | T16: 464210 | U16: 0.28540231 | W16: 549900 | X16: 0.3151197 | Z16: 549900 | AA16: 0.31864427 | AC16: 549900 | AD16: 0.332821 | AF16: 549900 | AG16: 0.33675514 | AI16: 524943 | AJ16: 0.28491027 | AL16: 535441.86 | AM16: 0.26074558 | AO16: 546150.7 | AP16: 0.25821407
C17: Benefits | D17: Benefits | E17: 13842 | F17: 0.01222338 | H17: 2536 | I17: 0.0022001475 | K17: 0 | L17: 0 | N17: 0 | O17: 0 | R17: 0 | T17: 32530.22 | U17: 0.02 | W17: 34901.023 | X17: 0.02 | Z17: 33898.861 | AA17: 0.019642986 | AC17: 33044.79 | AD17: 0.02 | AF17: 32658.745 | AG17: 0.02 | AI17: 36849.707 | AJ17: 0.02 | AL17: 41070.062 | AM17: 0.02 | AO17: 42302.164 | AP17: 0.02
C18: Payroll Taxes | D18: Payroll Taxes | E18: 1702 | F18: 0.0015029759 | H18: 38869 | I18: 0.033721425 | K18: 51055 | L18: 0.031389274 | N18: 0 | O18: 0 | R18: 0 | T18: 75645.57 | U18: 0.046507875 | W18: 77808.5 | X18: 0.044588092 | Z18: 77198.262 | AA18: 0.044733195 | AC18: 77808.5 | AD18: 0.047092749 | AF18: 77198.262 | AG18: 0.047275707 | AI18: 77608.768 | AJ18: 0.042121783 | AL18: 83079.441 | AM18: 0.040457422 | AO18: 85108.483 | AP18: 0.040238359
D19: Labor Expense Total | E19: 544908 | F19: 0.48118896 | H19: 531697 | I19: 0.46128226 | K19: 699865 | L19: 0.43028605 | N19: 796610.35 | O19: 0.45649685 | R19: 0 | T19: 1090585.8 | U19: 0.67050625 | W19: 1123209.5 | X19: 0.64365422 | Z19: 1113672 | AA19: 0.64532677 | AC19: 1069353.3 | AD19: 0.64721446 | AF19: 1060431.8 | AG19: 0.64940147 | AI19: 1122364.5 | AJ19: 0.60915792 | AL19: 1203103.3 | AM19: 0.58587848 | AO19: 1232715.6 | AP19: 0.58281445
D21: Non-Labor Expense
C22: Supplies | D22: Supplies | E22: 73389 | F22: 0.064807227 | H22: 143679 | I22: 0.12465102 | K22: 86543 | L22: 0.053207756 | N22: 115402.62 | O22: 0.066131369 | R22: 0 | T22: 86543 | U22: 0.053207756 | W22: 115402.62 | X22: 0.066131369 | Z22: 109468.89 | AA22: 0.063432688 | AC22: 109264.9 | AD22: 0.066131395 | AF22: 103581.6 | AG22: 0.063432688 | AI22: 116873.8 | AJ22: 0.063432688 | AL22: 130259.22 | AM22: 0.063432688 | AO22: 134167 | AP22: 0.063432688
C23: Rent | D23: Rent | E23: 87600 | F23: 0.077356458 | H23: 79354 | I23: 0.068844836 | K23: 84218 | L23: 0.051778316 | N23: 90578.68 | O23: 0.051906032 | R23: 0 | T23: 84218 | U23: 0.051778316 | W23: 90578.68 | X23: 0.051906032 | Z23: 95722.47 | AA23: 0.055467207 | AC23: 90578.68 | AD23: 0.054821762 | AF23: 95722.47 | AG23: 0.05861981 | AI23: 95722.47 | AJ23: 0.051952907 | AL23: 97636.919 | AM23: 0.047546517 | AO23: 99589.658 | AP23: 0.0470849
C24: Occupancy Other | D24: Occupancy Other | E24: 0 | F24: 0 | H24: 0 | I24: 0 | K24: 0 | L24: 0 | N24: 0 | O24: 0 | R24: 0 | T24: 0 | U24: 0 | W24: 0 | X24: 0 | Z24: 0 | AA24: 0 | AC24: 0 | AD24: 0 | AF24: 0 | AG24: 0 | AI24: 0 | AJ24: 0 | AL24: 0 | AM24: 0 | AO24: 0 | AP24: 0
C25: Equipment | D25: Equipment | E25: 16011 | F25: 0.014138747 | H25: 27144 | I25: 0.023549213 | K25: 26685 | L25: 0.016406283 | N25: 11744.6 | O25: 0.0067302326 | R25: 0 | T25: 26685 | U25: 0.016406283 | W25: 11744.6 | X25: 0.0067302326 | Z25: 21930.7 | AA25: 0.012707932 | AC25: 11744.6 | AD25: 0.0071082915 | AF25: 21930.7 | AG25: 0.013430216 | AI25: 21930.7 | AJ25: 0.011902781 | AL25: 21930.7 | AM25: 0.010679653 | AO25: 21930.7 | AP25: 0.010368595
C26: Marketing | D26: Marketing | E26: 6217 | F26: 0.0054900125 | H26: 9433 | I26: 0.0081837505 | K26: 6916 | L26: 0.0042520463 | N26: 7878 | O26: 0.0045144809 | R26: 0 | T26: 6916 | U26: 0.0042520463 | W26: 7878 | X26: 0.0045144809 | Z26: 9099.51 | AA26: 0.0052727892 | AC26: 7878 | AD26: 0.0047680739 | AF26: 9099.51 | AG26: 0.00557248 | AI26: 15015 | AJ26: 0.0081493185 | AL26: 15015 | AM26: 0.0073118954 | AO26: 15015 | AP26: 0.0070989276
C27: Licenses | D27: Licenses | E27: 1754 | F27: 0.0015488953 | H27: 482 | I27: 0.00041816683 | K27: 6600 | L27: 0.0040577654 | N27: 1310 | O27: 0.00075069433 | R27: 0 | T27: 6600 | U27: 0.0040577654 | W27: 1310 | X27: 0.00075069433 | Z27: 1089 | AA27: 0.0006310304 | AC27: 1310 | AD27: 0.00079286327 | AF27: 1089 | AG27: 0.00066689642 | AI27: 1089 | AJ27: 0.00059104948 | AL27: 1089 | AM27: 0.0005303133 | AO27: 1089 | AP27: 0.00051486728
C28: Office Expense | D28: Office Expense | E28: 2100 | F28: 0.0018544356 | H28: 958 | I28: 0.00083112827 | K28: 208 | L28: 0.00012788109 | N28: 8276.97 | O28: 0.0047431103 | R28: 0 | T28: 208 | U28: 0.00012788109 | W28: 8276.97 | X28: 0.0047431103 | Z28: 6800.25 | AA28: 0.0039404632 | AC28: 8276.97 | AD28: 0.0050095462 | AF28: 6800.25 | AG28: 0.0041644283 | AI28: 6800.25 | AJ28: 0.0036908028 | AL28: 6800.25 | AM28: 0.0033115363 | AO28: 6800.25 | AP28: 0.0032150837
C29: Professional Fees | D29: Professional Fees | E29: 13521 | F29: 0.011939916 | H29: 15752 | I29: 0.0136659 | K29: 7320 | L29: 0.0045004307 | N29: 1920 | O29: 0.0011002543 | R29: 0 | T29: 7320 | U29: 0.0045004307 | W29: 1920 | X29: 0.0011002543 | Z29: 5053.75 | AA29: 0.0029284388 | AC29: 1920 | AD29: 0.0011620591 | AF29: 5053.75 | AG29: 0.0030948832 | AI29: 0 | AJ29: 0 | AL29: 0 | AM29: 0 | AO29: 0 | AP29: 0
C30: Accounting | D30: Accounting | E30: 0 | F30: 0 | H30: 0 | I30: 0 | K30: 0 | L30: 0 | N30: 0 | O30: 0 | R30: 0 | T30: 0 | U30: 0 | W30: 0 | X30: 0 | Z30: 0 | AA30: 0 | AC30: 0 | AD30: 0 | AF30: 0 | AG30: 0 | AI30: 24000 | AJ30: 0.013025884 | AL30: 24000 | AM30: 0.011687345 | AO30: 24000 | AP30: 0.011346937
C31: IT / Phone / Internet | D31: IT / Phone / Internet | E31: 39404 | F31: 0.034796277 | H31: 49024 | I31: 0.042531558 | K31: 28809 | L31: 0.017712146 | N31: 43578.27 | O31: 0.024972489 | R31: 0 | T31: 28809 | U31: 0.017712146 | W31: 43578.27 | X31: 0.024972489 | Z31: 39674.55 | AA31: 0.022989759 | AC31: 43578.27 | AD31: 0.026375274 | AF31: 39674.55 | AG31: 0.024296433 | AI31: 39674.55 | AJ31: 0.02153317 | AL31: 39674.55 | AM31: 0.019320424 | AO31: 39674.55 | AP31: 0.018757693
C32: Travel | D32: Travel | E32: 8077 | F32: 0.0071325127 | H32: 946 | I32: 0.00082071748 | K32: 4113 | L32: 0.0025287256 | N32: 12310.44 | O32: 0.0070544867 | R32: 0 | T32: 4113 | U32: 0.0025287256 | W32: 12310.44 | X32: 0.0070544867 | Z32: 11186.26 | AA32: 0.0064819744 | AC32: 12310.44 | AD32: 0.0074507601 | AF32: 11186.26 | AG32: 0.0068503919 | AI32: 0 | AJ32: 0 | AL32: 0 | AM32: 0 | AO32: 0 | AP32: 0
C33: Admin - Other | D33: Admin - Other | E33: 57971 | F33: 0.051192137 | H33: 53098 | I33: 0.046066022 | K33: 36402 | L33: 0.02238042 | N33: 90781.78 | O33: 0.052022418 | R33: 0 | T33: 36402 | U33: 0.02238042 | W33: 63874.93 | X33: 0.036603472 | Z33: 57528.45 | AA33: 0.033335354 | AC33: 63874.93 | AD33: 0.038659607 | AF33: 57528.45 | AG33: 0.035230044 | AI33: 57204.099 | AJ33: 0.031047248 | AL33: 58348.181 | AM33: 0.028413973 | AO33: 59515.145 | AP33: 0.028138109
D35: Non-Labor Expense Total | E35: 306044 | F35: 0.27025662 | H35: 379870 | I35: 0.32956231 | K35: 287814 | L35: 0.17695177 | N35: 383781.36 | O35: 0.21992557 | Q35: 0 | R35: 0 | T35: 287814 | U35: 0.17695177 | W35: 356874.51 | X35: 0.20450662 | Z35: 357553.83 | AA35: 0.20718764 | AC35: 350736.79 | AD35: 0.21227963 | AF35: 351666.54 | AG35: 0.21535827 | AI35: 378309.87 | AJ35: 0.20532585 | AL35: 394753.82 | AM35: 0.19223434 | AO35: 401781.3 | AP35: 0.1899578
D37: Total Practice Expenses | E37: 850952 | F37: 0.75144558 | H37: 911567 | I37: 0.79084458 | K37: 987679 | L37: 0.60723782 | N37: 1180391.7 | O37: 0.67642242 | Q37: 0 | R37: 0 | T37: 1378399.8 | U37: 0.84745802 | W37: 1480084 | X37: 0.84816084 | Z37: 1471225.8 | AA37: 0.85251441 | AC37: 1420090.1 | AD37: 0.85949409 | AF37: 1412098.4 | AG37: 0.86475974 | AI37: 1500674.4 | AJ37: 0.81448377 | AL37: 1597857.1 | AM37: 0.77811283 | AO37: 1634496.9 | AP37: 0.77277225
D39: Clinical EBITDA | E39: 281468 | F39: 0.24855442 | H39: 241083 | I39: 0.20915542 | K39: 638832 | L39: 0.39276218 | N39: 564659.43 | O39: 0.32357758 | Q39: 0 | R39: 0 | T39: 248111.21 | U39: 0.15254198 | W39: 264967.11 | X39: 0.15183916 | Z39: 254523.1 | AA39: 0.14748559 | AC39: 232149.41 | AD39: 0.14050591 | AF39: 220838.86 | AG39: 0.13524026 | AI39: 341810.93 | AJ39: 0.18551623 | AL39: 455646 | AM39: 0.22188717 | AO39: 480611.27 | AP39: 0.22722775
AC41: 0.053185261
AC42: 0.94681474
