Workbook
Name AA.AlternatePriceSourceStartPeriod: "Q1-2018"
Name AA.CIK: "93410"
Name AA.ColorizerVersion: "2.0.4.0"
Name AA.CompareQuarters.LatestMRQ: "Q2-2018"
Name AA.CSIN: "Z99BO00122"
Name AA.CurationVersion: "2023.11.1.0"
Name AA.DBMacroVersion: "1.0.13.0"
Name AA.FreeCashFlow: "TRUE"
Name AA.HardcodeChecker.LatestMRQ: "Q3-2019"
Name AA.ModelChecks.LatestMRQ: "Q3-2021"
Name AA.ModelChecks.LatestVersionNumber: "2.38.12.0"
Name AA.ModelColorScheme: "Classic"
Name AA.ModelVersion: "Q1-2026.23"
Name AA.NonLibraryWideCurationVersion: "D"
Name AA.PartialUpdate.BsAvailable: "FALSE"
Name AA.PartialUpdate.CfsAvailable: "FALSE"
Name AA.PartialUpdate.IsAvailable: "TRUE"
Name AA.PeriodLayout: "QFY"
Name AA.PersonalMacro.VersionNumber: "1.6.1.0"
Name AA.RowNameEnforcerVersion: "2023.11.1.0"
Name AA.SessionToUploadId: ""
Name AA.StartWorkModelVersion: "Q1-2026.21"
Name AA.StartWorkType: ""
Name AA.SubyearType: "Q"
Name AA.TemplateUpgradeAttempted: "TRUE"
Name AA.TemplateVersion: "7.5.4.0"
Name AA.UpdateType: "Regular"
Name AA.VerifyUnitsAtModelVersion: "Q1-2018.22"
Name CR.42.Gal.Per.Boe: 42
Name CR.6Mcf.Per.Boe: 6
Name FP.DataSource: 'Front Page'!$H$16
Name FP.DataSourceName: 'Front Page'!$H$15
Name FP.Disclaimer: 'Front Page'!$C$22
Name FP.LastPrice: 'Front Page'!$H$20
Name FP.LastPriceDate: 'Front Page'!$F$20
Name FP.RealTimeToggle: 'Front Page'!$H$18
Name FP.UpdateDate: 'Front Page'!$H$11
Name FP.UpdateEvent: 'Front Page'!$H$13
Name FP_Comment: 'Front Page'!$M$13:$P$20
Name FP_StockPriceOverride: 'Front Page'!$C$20:$H$20
Name GD.CompanyName: Guidance!$B$1
Name GD.MRQ: Guidance!$F$2
Name GD_Difference_Mid_Absolute: Guidance!$P:$P
Name GD_Difference_Mid_Relative: Guidance!$Q:$Q
Name GD_Guidance_High: Guidance!$J:$J
Name GD_Guidance_Low: Guidance!$I:$I
Name GD_Guidance_Mid: Guidance!$K:$K
Name GD_Header_Column: Guidance!$5:$5
Name GD_Header_Section: Guidance!$4:$4
Name GD_Index: Guidance!$A:$A
Name GD_Item: Guidance!$D:$D
Name GD_Item_BasePeriod: Guidance!$G:$G
Name GD_Item_FiscalPeriod: Guidance!$F:$F
Name GD_Item_Name: Guidance!$E:$E
Name GD_Model_Output: Guidance!$N:$N
Name GD_Model_Type: Guidance!$M:$M
Name GD_Type: Guidance!$B:$B
Name GD_Update_Date: Guidance!$S:$S
Name GD_Update_Link: Guidance!$T:$T
Name HP.MRFX: Model!$B$914

Sheet Front Page
M6: Please contact this email for any model-specific questions:
M7: person@example.com
C9: Company Model: | H9: =Model!A1 -> Company0670 Company0697
C11: Updated: | H11: =OFFSET('Update Log'!$C$10,1,0,1,1) -> 46149
M12: Comments on Model:
C13: For: | H13: =OFFSET('Update Log'!$E$10,1,0,1,1) -> Quarterly (Earnings Report) | M13: On October 23, 2023, the company announced the definitive agreement to acquire all outstanding shares of Company1245 Company0697 in an all-stock transaction valued at $53 billion. Company1245 shareholders will receive 1.025 shares of Company0670 for each Company1245 share. The acquisition is expected to close in the first half of 2024. The acquisition is subject to Company1245 shareholder approval and has not been modelled.
C15: Consensus Data and Real-Time Stock Price: | H15: Bloomberg
H16: =IF(FP.DataSourceName="Bloomberg",1,IF(FP.DataSourceName="Capital IQ",2,IF(FP.DataSourceName="FactSet",3,IF(FP.DataSourceName="Refinitiv",4)))) -> 1
C18: Real-Time Stock Price: | H18: OFF
C20: Stock Price Override: | F20: 46148 | H20: 185.16
C22: DISCLAIMER Access to and use of this model, including the data contained herein (this "Model") is subject to Company2747, Inc.'s (a successor entity to Source Financial Modeling Company0697) ("Company") Terms of Use that you accepted prior to accessing this Model, the applicable Service Agreement between the Company and you (or a corporate entity that has authorized you to access and use this Model on its behalf in accordance with the terms of such Service Agreement) or other similar agreement between you and the Company. BY CONTINUING TO ACCESS OR USE THIS MODEL, YOU EXPRESSLY AGREE TO THE TERMS AND CONDITIONS OF SUCH AGREEMENTS. The Company and certain of its licensors have exclusive proprietary rights in this Model. This Model is being provided for internal use only. Unless prior written consent by the Company and its licensors has been provided to you, you may not distribute or otherwise furnish this Model to any third party, nor use or permit anyone to use this Model for any unlawful or unauthorized purpose. IF YOU HAVE UNLAWFULLY OBTAINED, OR ARE NOT AUTHORIZED TO USE THIS MODEL, YOU ARE OBLIGATED TO PROMPTLY: (I) RETURN THIS MODEL (AND ANY DERIVATIVE WORKS ARISING FROM OR RELATING THERETO) TO THE AUTHORIZED USER OF THIS MODEL; (II) PROVIDE NOTICE TO THE COMPANY AT person@example.com OF SUCH UNLAWFUL OR UNAUTHORIZED ACCESS AND USE; AND, (III) CERTIFY THAT YOU HAVE DESTROYED THIS MODEL (AND ANY DERIVATIVE WORKS ARISING FROM OR RELATING THERETO) AND ANY COPIES FROM YOUR SYSTEMS SO AS TO ENSURE THEY ARE INCAPABLE OF RETRIEVAL. A portion of the data contained in this Model may be powered by third party contributors and their respective licensors, or derived from data provided by such contributors, including (but not limited to): (i) QuoteMedia Inc.: A portion of the market data is powered by Quotemedia.com. All rights reserved. Data delayed 15 minutes unless otherwise indicated; (ii) S&P Global Market Intelligence LLC: Copyright (c) {{YEAR}} S&P Global Market Intelligence LLC (and its affiliates as applicable). All rights reserved. Reproduction of any information, opinions, views, data or material, including ratings ("Content") in any form is prohibited except with the prior written permission of the relevant party. Such party, its affiliates and suppliers ("Content Providers") do not guarantee the accuracy, adequacy, completeness, timeliness or availability of any Content and are not responsible for any errors or omissions (negligent or otherwise), regardless of the cause, or for the results obtained from the use of such Content. In no event shall Content Providers be liable for any damages, costs, expenses, legal fees, or losses (including lost income or lost profit and opportunity costs) in connection with any use of the Content. A reference to a particular investment or security, a rating or any observation concerning an investment that is part of the Content is not a recommendation to buy, sell or hold such investment or security, does not address the suitability of an investment or security and should not be relied on as investment advice. Credit ratings are statements of opinions and are not statements of fact; and, (iii) Refinitiv Canada Holdings Limited: A portion of the information may be provided by or derived from data provided by Refinitiv. By accessing or using this Model (including any portion of the data contained herein) you expressly represent that such access or use does not constitute a violation of any applicable law or regulation to which you or the securities are subject. This Model does not constitute investment advice by the Company or any of its licensors. Reference to a particular investment or security, credit rating or any observation concerning a security or investment in this Model is not a recommendation or solicitation to buy, sell or hold such investment or security or make any other investment decisions. For greater certainty, any forecasts or forward-looking information expressed herein are for illustrative purposes only and do not purport to express any view on what may transpire. Neither the Company nor any of its licensors have performed company-specific research on any projected information, as such, it is your responsibility to express your own views on projected results. This Model does not guarantee future performance and undue reliance should not be placed on such. You are solely responsible for evaluating the merits and risks of any investment based on your own business and financial expertise, the business and financial expertise of professional advisors with whom you have consulted, your financial situation and risk tolerance. Neither the Company, nor any of its licensors, undertake any liability with respect to your reliance on this Model. This Model is a quantitative tool with no investment views. The Company and its respective directors, officers, employees, agents, contractors, and affiliates may hold long or short positions in the security to which this Model relates, based on their personal views, and may initiate or close out any positions in such security at any time without any notice. THIS MODEL IS PROVIDED "AS IS" AND ON AN "AS AVAILABLE" BASIS ONLY, WITHOUT WARRANTIES OR CONDITIONS OF ANY KIND. NEITHER THE COMPANY NOR ANY OF ITS LICENSORS NOR THEIR RESPECTIVE AFFILIATES OR SUPPLIERS HAVE LIABILITY FOR THE ACCURACY, TIMELINESS OR COMPLETENESS OF THIS MODEL, OR FOR DELAYS, INTERRUPTIONS OR OMISSIONS HEREIN, NOR FOR ANY LOST PROFITS, INDIRECT, SPECIAL OR CONSEQUENTIAL DAMAGES. Access to data in this Model that is sourced from third party contributors is subject to termination in the event that any agreement between the Company and such third party contributors terminates for any reason. Copyright 2023 Company2747. All rights reserved.

Sheet Model
A1: Company0670 Company0697
A2: =CHOOSE(MO.DataSourceIndex,MO.Ticker.Bloomberg,MO.Ticker.CapIQ,MO.Ticker.FactSet,MO.Ticker.Thomson) -> Ticker0006 US | C2: =EOMONTH(C4,-12) -> 39813
A3: =HP.TradeCurrency -> USD | B3: =IF(MO.RealTime="OFF",MO.LastPriceHardcoded,MO.LastPriceFormula) -> 185.16 | C3: =C4-C2 -> 365 | D3: =D4-C4 -> 365 | E3: =E4-D4 -> 365 | F3: =F4-E4 -> 366 | G3: =G4-F4 -> 90 | H3: =H4-G4 -> 91 | I3: =I4-H4 -> 92 | J3: =J4-I4 -> 92 | K3: =K4-F4 -> 365 | L3: =L4-K4 -> 90 | M3: =M4-L4 -> 91 | N3: =N4-M4 -> 92 | O3: =O4-N4 -> 92 | P3: =P4-K4 -> 365 | Q3: =Q4-P4 -> 90 | R3: =R4-Q4 -> 91 | S3: =S4-R4 -> 92 | T3: =T4-S4 -> 92 | U3: =U4-P4 -> 365 | V3: =V4-U4 -> 91 | W3: =W4-V4 -> 91 | X3: =X4-W4 -> 92 | Y3: =Y4-X4 -> 92 | Z3: =Z4-U4 -> 366 | AA3: =AA4-Z4 -> 90 | AB3: =AB4-AA4 -> 91 | AC3: =AC4-AB4 -> 92 | AD3: =AD4-AC4 -> 92 | AE3: =AE4-Z4 -> 365 | AF3: =AF4-AE4 -> 90 | AG3: =AG4-AF4 -> 91 | AH3: =AH4-AG4 -> 92 | AI3: =AI4-AH4 -> 92 | AJ3: =AJ4-AE4 -> 365 | AK3: =AK4-AJ4 -> 90 | AL3: =AL4-AK4 -> 91 | AM3: =AM4-AL4 -> 92 | AN3: =AN4-AM4 -> 92 | AO3: =AO4-AJ4 -> 365 | AP3: =AP4-AO4 -> 91 | AQ3: =AQ4-AP4 -> 91 | AR3: =AR4-AQ4 -> 92 | AS3: =AS4-AR4 -> 92 | AT3: =AT4-AO4 -> 366 | AU3: =AU4-AT4 -> 90 | AV3: =AV4-AU4 -> 91 | AW3: =AW4-AV4 -> 92 | AX3: =AX4-AW4 -> 92 | AY3: =AY4-AT4 -> 365 | AZ3: =AZ4-AY4 -> 90 | BA3: =BA4-AZ4 -> 91 | BB3: =BB4-BA4 -> 92 | BC3: =BC4-BB4 -> 92 | BD3: =BD4-AY4 -> 365 | BE3: =BE4-BD4 -> 90 | BF3: =BF4-BE4 -> 91 | BG3: =BG4-BF4 -> 92 | BH3: =BH4-BG4 -> 92 | BI3: =BI4-BD4 -> 365 | BJ3: =BJ4-BI4 -> 91 | BK3: =BK4-BJ4 -> 91 | BL3: =BL4-BK4 -> 92 | BM3: =BM4-BL4 -> 92 | BN3: =BN4-BI4 -> 366 | BO3: =BO4-BN4 -> 90 | BP3: =BP4-BO4 -> 91 | BQ3: =BQ4-BP4 -> 92 | BR3: =BR4-BQ4 -> 92 | BS3: =BS4-BN4 -> 365 | BT3: =BT4-BS4 -> 90 | BU3: =BU4-BT4 -> 91 | BV3: =BV4-BU4 -> 92 | BW3: =BW4-BV4 -> 92 | BX3: =BX4-BS4 -> 365 | BY3: =BY4-BX4 -> 90 | BZ3: =BZ4-BY4 -> 91 | CA3: =CA4-BZ4 -> 92 | CB3: =CB4-CA4 -> 92 | CC3: =CC4-BX4 -> 365 | CD3: =CD4-CC4 -> 366 | CE3: =CE4-CD4 -> 365 | CF3: =CF4-CE4 -> 365
A4: =FP.DataSourceName -> Bloomberg | B4: =IF(AND(MO.RealTimeStockPriceToggle,MO.LastPriceFormula<>"N/A"),"ON","OFF") -> OFF | C4: 40178 | D4: =EOMONTH(C4,12) -> 40543 | E4: =EOMONTH(D4,12) -> 40908 | F4: =EOMONTH(E4,12) -> 41274 | G4: =EOMONTH(F4,3) -> 41364 | H4: =EOMONTH(G4,3) -> 41455 | I4: =EOMONTH(H4,3) -> 41547 | J4: =EOMONTH(I4,3) -> 41639 | K4: =J4 -> 41639 | L4: =EOMONTH(K4,3) -> 41729 | M4: =EOMONTH(L4,3) -> 41820 | N4: =EOMONTH(M4,3) -> 41912 | O4: =EOMONTH(N4,3) -> 42004 | P4: =O4 -> 42004 | Q4: =EOMONTH(P4,3) -> 42094 | R4: =EOMONTH(Q4,3) -> 42185 | S4: =EOMONTH(R4,3) -> 42277 | T4: =EOMONTH(S4,3) -> 42369 | U4: =T4 -> 42369 | V4: =EOMONTH(U4,3) -> 42460 | W4: =EOMONTH(V4,3) -> 42551 | X4: =EOMONTH(W4,3) -> 42643 | Y4: =EOMONTH(X4,3) -> 42735 | Z4: =Y4 -> 42735 | AA4: =EOMONTH(Z4,3) -> 42825 | AB4: =EOMONTH(AA4,3) -> 42916 | AC4: =EOMONTH(AB4,3) -> 43008 | AD4: =EOMONTH(AC4,3) -> 43100 | AE4: =AD4 -> 43100 | AF4: =EOMONTH(AE4,3) -> 43190 | AG4: =EOMONTH(AF4,3) -> 43281 | AH4: =EOMONTH(AG4,3) -> 43373 | AI4: =EOMONTH(AH4,3) -> 43465 | AJ4: =AI4 -> 43465 | AK4: =EOMONTH(AJ4,3) -> 43555 | AL4: =EOMONTH(AK4,3) -> 43646 | AM4: =EOMONTH(AL4,3) -> 43738 | AN4: =EOMONTH(AM4,3) -> 43830 | AO4: =AN4 -> 43830 | AP4: =EOMONTH(AO4,3) -> 43921 | AQ4: =EOMONTH(AP4,3) -> 44012 | AR4: =EOMONTH(AQ4,3) -> 44104 | AS4: =EOMONTH(AR4,3) -> 44196 | AT4: =AS4 -> 44196 | AU4: =EOMONTH(AT4,3) -> 44286 | AV4: =EOMONTH(AU4,3) -> 44377 | AW4: =EOMONTH(AV4,3) -> 44469 | AX4: =EOMONTH(AW4,3) -> 44561 | AY4: =AX4 -> 44561 | AZ4: =EOMONTH(AY4,3) -> 44651 | BA4: =EOMONTH(AZ4,3) -> 44742 | BB4: =EOMONTH(BA4,3) -> 44834 | BC4: =EOMONTH(BB4,3) -> 44926 | BD4: =BC4 -> 44926 | BE4: =EOMONTH(BD4,3) -> 45016 | BF4: =EOMONTH(BE4,3) -> 45107 | BG4: =EOMONTH(BF4,3) -> 45199 | BH4: =EOMONTH(BG4,3) -> 45291 | BI4: =BH4 -> 45291 | BJ4: =EOMONTH(BI4,3) -> 45382 | BK4: =EOMONTH(BJ4,3) -> 45473 | BL4: =EOMONTH(BK4,3) -> 45565 | BM4: =EOMONTH(BL4,3) -> 45657 | BN4: =BM4 -> 45657 | BO4: =EOMONTH(BN4,3) -> 45747 | BP4: =EOMONTH(BO4,3) -> 45838 | BQ4: =EOMONTH(BP4,3) -> 45930 | BR4: =EOMONTH(BQ4,3) -> 46022 | BS4: =BR4 -> 46022 | BT4: =EOMONTH(BS4,3) -> 46112 | BU4: =EOMONTH(BT4,3) -> 46203 | BV4: =EOMONTH(BU4,3) -> 46295 | BW4: =EOMONTH(BV4,3) -> 46387 | BX4: =BW4 -> 46387 | BY4: =EOMONTH(BX4,3) -> 46477 | BZ4: =EOMONTH(BY4,3) -> 46568 | CA4: =EOMONTH(BZ4,3) -> 46660 | CB4: =EOMONTH(CA4,3) -> 46752 | CC4: =CB4 -> 46752 | CD4: =EOMONTH(CC4,12) -> 47118 | CE4: =EOMONTH(CD4,12) -> 47483 | CF4: =EOMONTH(CE4,12) -> 47848
A5: =MO.ReportCurrency -> USD | C5: FY2009 | D5: =CONCATENATE("FY",RIGHT(C5,4)+1) -> FY2010 | E5: =CONCATENATE("FY",RIGHT(D5,4)+1) -> FY2011 | F5: =CONCATENATE("FY",RIGHT(E5,4)+1) -> FY2012 | G5: =CONCATENATE("Q1","-",RIGHT(F5,4)+1) -> Q1-2013 | H5: =CONCATENATE("Q2","-",RIGHT(G5,4)) -> Q2-2013 | I5: =CONCATENATE("Q3","-",RIGHT(H5,4)) -> Q3-2013 | J5: =CONCATENATE("Q4","-",RIGHT(I5,4)) -> Q4-2013 | K5: =CONCATENATE("FY",RIGHT(F5,4)+1) -> FY2013 | L5: =CONCATENATE("Q1","-",RIGHT(K5,4)+1) -> Q1-2014 | M5: =CONCATENATE("Q2","-",RIGHT(L5,4)) -> Q2-2014 | N5: =CONCATENATE("Q3","-",RIGHT(M5,4)) -> Q3-2014 | O5: =CONCATENATE("Q4","-",RIGHT(N5,4)) -> Q4-2014 | P5: =CONCATENATE("FY",RIGHT(K5,4)+1) -> FY2014 | Q5: =CONCATENATE("Q1","-",RIGHT(P5,4)+1) -> Q1-2015 | R5: =CONCATENATE("Q2","-",RIGHT(Q5,4)) -> Q2-2015 | S5: =CONCATENATE("Q3","-",RIGHT(R5,4)) -> Q3-2015 | T5: =CONCATENATE("Q4","-",RIGHT(S5,4)) -> Q4-2015 | U5: =CONCATENATE("FY",RIGHT(P5,4)+1) -> FY2015 | V5: =CONCATENATE("Q1","-",RIGHT(U5,4)+1) -> Q1-2016 | W5: =CONCATENATE("Q2","-",RIGHT(V5,4)) -> Q2-2016 | X5: =CONCATENATE("Q3","-",RIGHT(W5,4)) -> Q3-2016 | Y5: =CONCATENATE("Q4","-",RIGHT(X5,4)) -> Q4-2016 | Z5: =CONCATENATE("FY",RIGHT(U5,4)+1) -> FY2016 | AA5: =CONCATENATE("Q1","-",RIGHT(Z5,4)+1) -> Q1-2017 | AB5: =CONCATENATE("Q2","-",RIGHT(AA5,4)) -> Q2-2017 | AC5: =CONCATENATE("Q3","-",RIGHT(AB5,4)) -> Q3-2017 | AD5: =CONCATENATE("Q4","-",RIGHT(AC5,4)) -> Q4-2017 | AE5: =CONCATENATE("FY",RIGHT(Z5,4)+1) -> FY2017 | AF5: =CONCATENATE("Q1","-",RIGHT(AE5,4)+1) -> Q1-2018 | AG5: =CONCATENATE("Q2","-",RIGHT(AF5,4)) -> Q2-2018 | AH5: =CONCATENATE("Q3","-",RIGHT(AG5,4)) -> Q3-2018 | AI5: =CONCATENATE("Q4","-",RIGHT(AH5,4)) -> Q4-2018 | AJ5: =CONCATENATE("FY",RIGHT(AE5,4)+1) -> FY2018 | AK5: =CONCATENATE("Q1","-",RIGHT(AJ5,4)+1) -> Q1-2019 | AL5: =CONCATENATE("Q2","-",RIGHT(AK5,4)) -> Q2-2019 | AM5: =CONCATENATE("Q3","-",RIGHT(AL5,4)) -> Q3-2019 | AN5: =CONCATENATE("Q4","-",RIGHT(AM5,4)) -> Q4-2019 | AO5: =CONCATENATE("FY",RIGHT(AJ5,4)+1) -> FY2019 | AP5: =CONCATENATE("Q1","-",RIGHT(AO5,4)+1) -> Q1-2020 | AQ5: =CONCATENATE("Q2","-",RIGHT(AP5,4)) -> Q2-2020 | AR5: =CONCATENATE("Q3","-",RIGHT(AQ5,4)) -> Q3-2020 | AS5: =CONCATENATE("Q4","-",RIGHT(AR5,4)) -> Q4-2020 | AT5: =CONCATENATE("FY",RIGHT(AO5,4)+1) -> FY2020 | AU5: =CONCATENATE("Q1","-",RIGHT(AT5,4)+1) -> Q1-2021 | AV5: =CONCATENATE("Q2","-",RIGHT(AU5,4)) -> Q2-2021 | AW5: =CONCATENATE("Q3","-",RIGHT(AV5,4)) -> Q3-2021 | AX5: =CONCATENATE("Q4","-",RIGHT(AW5,4)) -> Q4-2021 | AY5: =CONCATENATE("FY",RIGHT(AT5,4)+1) -> FY2021 | AZ5: =CONCATENATE("Q1","-",RIGHT(AY5,4)+1) -> Q1-2022 | BA5: =CONCATENATE("Q2","-",RIGHT(AZ5,4)) -> Q2-2022 | BB5: =CONCATENATE("Q3","-",RIGHT(BA5,4)) -> Q3-2022 | BC5: =CONCATENATE("Q4","-",RIGHT(BB5,4)) -> Q4-2022 | BD5: =CONCATENATE("FY",RIGHT(AY5,4)+1) -> FY2022 | BE5: =CONCATENATE("Q1","-",RIGHT(BD5,4)+1) -> Q1-2023 | BF5: =CONCATENATE("Q2","-",RIGHT(BE5,4)) -> Q2-2023 | BG5: =CONCATENATE("Q3","-",RIGHT(BF5,4)) -> Q3-2023 | BH5: =CONCATENATE("Q4","-",RIGHT(BG5,4)) -> Q4-2023 | BI5: =CONCATENATE("FY",RIGHT(BD5,4)+1) -> FY2023 | BJ5: =CONCATENATE("Q1","-",RIGHT(BI5,4)+1) -> Q1-2024 | BK5: =CONCATENATE("Q2","-",RIGHT(BJ5,4)) -> Q2-2024 | BL5: =CONCATENATE("Q3","-",RIGHT(BK5,4)) -> Q3-2024 | BM5: =CONCATENATE("Q4","-",RIGHT(BL5,4)) -> Q4-2024 | BN5: =CONCATENATE("FY",RIGHT(BI5,4)+1) -> FY2024 | BO5: =CONCATENATE("Q1","-",RIGHT(BN5,4)+1) -> Q1-2025 | BP5: =CONCATENATE("Q2","-",RIGHT(BO5,4)) -> Q2-2025 | BQ5: =CONCATENATE("Q3","-",RIGHT(BP5,4)) -> Q3-2025 | BR5: =CONCATENATE("Q4","-",RIGHT(BQ5,4)) -> Q4-2025 | BS5: =CONCATENATE("FY",RIGHT(BN5,4)+1) -> FY2025 | BT5: =CONCATENATE("Q1","-",RIGHT(BS5,4)+1) -> Q1-2026 | BU5: =CONCATENATE("Q2","-",RIGHT(BT5,4)) -> Q2-2026 | BV5: =CONCATENATE("Q3","-",RIGHT(BU5,4)) -> Q3-2026 | BW5: =CONCATENATE("Q4","-",RIGHT(BV5,4)) -> Q4-2026 | BX5: =CONCATENATE("FY",RIGHT(BS5,4)+1) -> FY2026 | BY5: =CONCATENATE("Q1","-",RIGHT(BX5,4)+1) -> Q1-2027 | BZ5: =CONCATENATE("Q2","-",RIGHT(BY5,4)) -> Q2-2027 | CA5: =CONCATENATE("Q3","-",RIGHT(BZ5,4)) -> Q3-2027 | CB5: =CONCATENATE("Q4","-",RIGHT(CA5,4)) -> Q4-2027 | CC5: =CONCATENATE("FY",RIGHT(BX5,4)+1) -> FY2027 | CD5: =CONCATENATE("FY",RIGHT(CC5,4)+1) -> FY2028 | CE5: =CONCATENATE("FY",RIGHT(CD5,4)+1) -> FY2029 | CF5: =CONCATENATE("FY",RIGHT(CE5,4)+1) -> FY2030
A6: Revenue and Volume Summary
A7: Upstream revenues, mm | C7: =C95 -> 22688 | D7: =D95 -> 27616 | E7: =E95 -> 29709 | F7: =F95 -> 25875 | G7: =G95 -> 6628 | H7: =H95 -> 6493 | I7: =I95 -> 6275 | J7: =J95 -> 6263 | ... CF7: =CF95 -> 47954.92
A8: Downstream revenues, mm | C8: =C236 -> 144010 | D8: =D236 -> 169949 | E8: =E236 -> 214132 | F8: =F236 -> 204333 | G8: =G236 -> 47581 | H8: =H236 -> 48740 | I8: =I236 -> 50233 | J8: =J236 -> 47582 | ... CF8: =CF236 -> 140985.56
A9: Other revenues, mm | C9: =C255 -> 704 | D9: =D255 -> 633 | E9: =E255 -> 530 | F9: =F255 -> 382 | G9: =G255 -> 87 | H9: =H255 -> 74 | I9: =I255 -> 95 | J9: =J255 -> 105 | ... AO9: =AO255 -> 246 | AP9: =AP10-SUM(AP7:AP8) -> 65 | AQ9: =AQ10-SUM(AQ7:AQ8) -> 33 | AR9: =AR10-SUM(AR7:AR8) -> 37 | AS9: =AS10-SUM(AS7:AS8) -> -58 | AT9: =SUM(AP9,AQ9,AR9,AS9) -> 77 | AU9: =AU10-SUM(AU7:AU8) -> 24 | AV9: =AV10-SUM(AV7:AV8) -> 25 | AW9: =AW10-SUM(AW7:AW8) -> 39 | AX9: =AX10-SUM(AX7:AX8) -> 36 | AY9: =AY10-SUM(AY7:AY8) -> 124 | AZ9: =AZ10-SUM(AZ7:AZ8) -> 16 | BA9: =BA10-SUM(BA7:BA8) -> 38 | BB9: =BB10-SUM(BB7:BB8) -> 32 | ... BT9: =BT10-SUM(BT7:BT8) -> 14 | BU9: =BU255 -> 130 | BV9: =BV255 -> 130 | BW9: =BW255 -> 130 | BX9: =BX255 -> 404 | BY9: =BY255 -> 130 | BZ9: =BZ255 -> 130 | CA9: =CA255 -> 130 | CB9: =CB255 -> 130 | ... CF9: =CF255 -> 520
A10: Total Sales and other operating revenue, mm | C10: =SUM(C7:C9) -> 167402 | D10: =SUM(D7:D9) -> 198198 | E10: =SUM(E7:E9) -> 244371 | F10: =SUM(F7:F9) -> 230590 | G10: =SUM(G7:G9) -> 54296 | H10: =SUM(H7:H9) -> 55307 | I10: =SUM(I7:I9) -> 56603 | J10: =SUM(J7:J9) -> 53950 | ... AH10: =SUM(AH7:AH9) -> 42105 | AI10: =AI495 -> 40338 | AJ10: =AJ495 -> 158902 | AK10: =SUM(AK7:AK9) -> 34189 | AL10: =SUM(AL7:AL9) -> 36323 | AM10: =SUM(AM7:AM9) -> 34779 | AN10: =AN495 -> 34574 | AO10: =AO495 -> 139865 | AP10: =AP495 -> 29705 | AQ10: =AQ495 -> 15926 | AR10: =AR495 -> 23997 | AS10: =AS495 -> 24843 | AT10: =AT495 -> 94471 | AU10: =AU495 -> 31076 | ... BT10: =BT495 -> 47556 | BU10: =SUM(BU7:BU9) -> 58939.442 | BV10: =SUM(BV7:BV9) -> 54894.09 | BW10: =SUM(BW7:BW9) -> 54052.44 | BX10: =SUM(BX7:BX9) -> 215441.97 | BY10: =SUM(BY7:BY9) -> 51942.325 | BZ10: =SUM(BZ7:BZ9) -> 51909.601 | CA10: =SUM(CA7:CA9) -> 52751.602 | CB10: =SUM(CB7:CB9) -> 52295.674 | ... CF10: =SUM(CF7:CF9) -> 189460.48
A12: Upstream earnings, mm | C12: =C99 -> 10932 | D12: =D99 -> 17677 | E12: =E99 -> 24786 | F12: =F99 -> 23788 | G12: =G99 -> 5916 | H12: =H99 -> 4949 | I12: =I99 -> 5092 | J12: =J99 -> 4852 | ... BT12: =BT99 -> 3909
A13: Downstream earnings, mm | C13: =C243 -> 473 | D13: =D243 -> 2478 | E13: =E243 -> 3591 | F13: =F243 -> 4299 | G13: =G243 -> 701 | H13: =H243 -> 766 | I13: =I243 -> 380 | J13: =J243 -> 390 | ... BT13: =BT243 -> -817
A14: Other earnings, mm | C14: =C260 -> -922 | D14: =D260 -> -1131 | E14: =E260 -> -1482 | F14: =F260 -> -1908 | G14: =G260 -> -439 | H14: =H260 -> -350 | I14: =I260 -> -522 | J14: =J260 -> -312 | ... BT14: =BT260 -> -882
A15: Total earnings, mm | C15: =SUM(C12:C14) -> 10483 | D15: =SUM(D12:D14) -> 19024 | E15: =SUM(E12:E14) -> 26895 | F15: =SUM(F12:F14) -> 26179 | G15: =SUM(G12:G14) -> 6178 | H15: =SUM(H12:H14) -> 5365 | I15: =SUM(I12:I14) -> 4950 | J15: =SUM(J12:J14) -> 4930 | ... BT15: =SUM(BT12:BT14) -> 2210 | BU15: =MO_RIS_NI_GAAP_Basic -> 9898.3571 | BV15: =MO_RIS_NI_GAAP_Basic -> 7375.6397 | BW15: =MO_RIS_NI_GAAP_Basic -> 6589.1303 | BX15: =MO_RIS_NI_GAAP_Basic -> 26073.127 | BY15: =MO_RIS_NI_GAAP_Basic -> 5996.1876 | BZ15: =MO_RIS_NI_GAAP_Basic -> 6012.9055 | CA15: =MO_RIS_NI_GAAP_Basic -> 6177.51 | CB15: =MO_RIS_NI_GAAP_Basic -> 6087.3183 | ... CF15: =MO_RIS_NI_GAAP_Basic -> 16219.818
A17: Upstream total production volumes, kBOE/d | C17: =C53 -> 2348.5 | D17: =D53 -> 2396.5 | E17: =E53 -> 2312 | F17: =F53 -> 2255 | G17: =G53 -> 2644.8333 | H17: =H53 -> 2582 | I17: =I53 -> 2585.6667 | J17: =J53 -> 2575.5 | ... CF17: =CF53 -> 3650
A18: Downstream total refinery input, kbbl/d | C18: =C169+C185 -> 1878 | D18: =D169+D185 -> 1894 | E18: =E169+E185 -> 1787 | F18: =F169+F185 -> 1702 | G18: =G169+G185 -> 1394 | H18: =H169+H185 -> 1686 | I18: =I169+I185 -> 1716 | J18: =J169+J185 -> 1749 | ... CF18: =CF169+CF185 -> 1675
A19: Downstream total refined products sold, kbbl/d | C19: =C190+C173 -> 3254 | D19: =D190+D173 -> 3113 | E19: =E190+E173 -> 2949 | F19: =F190+F173 -> 2765 | G19: =G190+G173 -> 2547 | H19: =H190+H173 -> 2761 | I19: =I190+I173 -> 2756 | J19: =J190+J173 -> 1220.5109 | ... CF19: =CF190+CF173 -> 3007.5
A21: Upstream Operating Stats - Production Volumes (Company1282)
A22: Angola, k bbl/d | C22: 141 | D22: 152 | E22: 139 | F22: 128 | G22: 120 | H22: 122 | I22: 120 | J22: 116 | K22: =SUM(G22*G$3,H22*H$3,I22*I$3,J22*J$3)/K$3 -> 119.49041 | L22: 118 | M22: 113 | N22: 110 | O22: 114 | P22: =SUM(L22*L$3,M22*M$3,N22*N$3,O22*O$3)/P$3 -> 113.72877 | Q22: 113 | R22: 111 | S22: 106 | T22: 110 | U22: =SUM(Q22*Q$3,R22*R$3,S22*S$3,T22*T$3)/U$3 -> 109.98082 | V22: 111 | W22: 107 | X22: 105 | Y22: 107 | Z22: 108 | AA22: 105 | AB22: 116 | AC22: 117 | AD22: 113 | AE22: 113 | AF22: 111 | AG22: 108 | AH22: 105 | AI22: 104 | AJ22: 107 | AK22: 105 | AL22: 102 | AM22: 94 | AN22: 88 | AO22: 97 | AP22: 97 | AQ22: 89 | AR22: 88 | AS22: 81 | AT22: 89 | AU22: 83 | AV22: 77 | AW22: 76 | AX22: 78 | AY22: 79 | AZ22: 75 | BA22: 71 | BB22: 71 | BC22: 62 | BD22: 70 | BE22: 67 | BF22: 70 | BG22: 66 | BH22: 69 | BI22: 68 | BJ22: 67 | BK22: 66 | BL22: 63 | BM22: 64 | BN22: 64 | BO22: 59 | BP22: 55 | BQ22: 59 | BR22: 59 | BS22: 58 | BT22: 57
A23: Canada, k bbl/d | AP23: 141 | AQ23: 152 | AR23: 117 | AS23: 141 | AT23: 138 | AU23: 143 | AV23: 138 | AW23: 131 | AX23: 131 | AY23: 136 | AZ23: 113 | BA23: 112 | BB23: 118 | BC23: 120 | BD23: 116 | BE23: 118 | BF23: 106 | BG23: 107 | BH23: 122 | BI23: 114 | BJ23: 110 | BK23: 117 | BL23: 115 | BM23: 98 | BN23: 110 | BO23: 43 | BP23: 47 | BQ23: 48 | BR23: 47 | BS23: 46 | BT23: 55
A24: Guyana, k bbl/d | BQ24: 210 | BR24: 261 | BS24: 119 | BT24: 284
A25: Europe, k bbl/d | C25: 115 | D25: 101 | E25: 93 | F25: 75 | G25: 71 | H25: 66 | I25: 56 | J25: 57 | K25: =SUM(G25*G$3,H25*H$3,I25*I$3,J25*J$3)/K$3 -> 62.443836 | L25: 59 | M25: 52 | N25: 43 | O25: 53 | P25: =SUM(L25*L$3,M25*M$3,N25*N$3,O25*O$3)/P$3 -> 51.709589 | Q25: 47 | R25: 55 | S25: 58 | T25: 62 | U25: =SUM(Q25*Q$3,R25*R$3,S25*S$3,T25*T$3)/U$3 -> 55.547945 | V25: 58 | W25: 49 | X25: 56 | Y25: 65 | Z25: 57 | AA25: 69 | AB25: 68 | AC25: 59 | AD25: 59 | AE25: 64 | AF25: 57 | AG25: 46 | AH25: 50 | AI25: 66 | AJ25: 55 | AK25: 65 | AL25: 49 | AM25: 44 | AN25: 29 | AO25: 47 | AP25: 13 | AQ25: 13 | AR25: 12 | AS25: 12 | AT25: 13 | AU25: 13 | AV25: 11 | AW25: 13 | AX25: 16 | AY25: 13
A26: Indonesia, k bbl/d | C26: 199 | D26: 187 | E26: 166 | F26: 158 | G26: 150 | H26: 154 | I26: 159 | J26: 160 | K26: =SUM(G26*G$3,H26*H$3,I26*I$3,J26*J$3)/K$3 -> 155.7863 | L26: 149 | M26: 145 | N26: 149 | O26: 156 | P26: =SUM(L26*L$3,M26*M$3,N26*N$3,O26*O$3)/P$3 -> 149.76712 | Q26: 173 | R26: 161 | S26: 176 | T26: 196 | U26: =SUM(Q26*Q$3,R26*R$3,S26*S$3,T26*T$3)/U$3 -> 176.56164 | V26: 198 | W26: 158 | X26: 147 | Y26: 189 | Z26: 173 | AA26: 135 | AB26: 137 | AC26: 140 | AD26: 135 | AE26: 137 | AF26: 114 | AG26: 112 | AH26: 114 | AI26: 114 | AJ26: 113 | AK26: 98 | AL26: 99 | AM26: 102 | AN26: 103 | AO26: 101 | AP26: 106 | AQ26: 122 | AR26: 109 | AS26: 186 | AT26: 131 | AU26: 84 | AV26: 76 | AW26: 86 | AX26: 2 | AY26: 62
A27: Kazakhstan/Eurasia, k bbl/d | C27: 70 | D27: 67 | E27: 64 | F27: 63 | G27: 335 | H27: 315 | I27: 313 | J27: 333 | K27: =SUM(G27*G$3,H27*H$3,I27*I$3,J27*J$3)/K$3 -> 323.96438 | L27: 326 | M27: 294 | N27: 310 | O27: 333 | P27: =SUM(L27*L$3,M27*M$3,N27*N$3,O27*O$3)/P$3 -> 315.75342 | Q27: 361 | R27: 350 | S27: 308 | T27: 354 | U27: =SUM(Q27*Q$3,R27*R$3,S27*S$3,T27*T$3)/U$3 -> 343.13425 | V27: 381 | W27: 357 | X27: 298 | Y27: 373 | Z27: 352 | AA27: 363 | AB27: 352 | AC27: 334 | AD27: 347 | AE27: 349 | AF27: 342 | AG27: 337 | AH27: 312 | AI27: 343 | AJ27: 333 | AK27: 361 | AL27: 348 | AM27: 344 | AN27: 377 | AO27: 357 | AP27: 388 | AQ27: 351 | AR27: 309 | AS27: 327 | AT27: 344 | AU27: 309 | AV27: 314 | AW27: 246 | AX27: 329 | AY27: 299 | AZ27: 310 | BA27: 291 | BB27: 297 | BC27: 342 | BD27: 310 | BE27: 324 | BF27: 333 | BG27: 302 | BH27: 334 | BI27: 323 | BJ27: 343 | BK27: 326 | BL27: 330 | BM27: 317 | BN27: 329 | BO27: 431 | BP27: 458 | BQ27: 483 | BR27: 408 | BS27: 445 | BT27: 285
A28: Partitioned zone, k bbl/d | C28: 101 | D28: 94 | E28: 88 | F28: 86 | G28: 86 | H28: 84 | I28: 84 | J28: 83 | K28: =SUM(G28*G$3,H28*H$3,I28*I$3,J28*J$3)/K$3 -> 84.241096 | L28: 80 | M28: 80 | N28: 77 | O28: 76 | P28: =SUM(L28*L$3,M28*M$3,N28*N$3,O28*O$3)/P$3 -> 78.235616 | Q28: 74 | R28: 35 | S28: 0 | T28: 0 | U28: =SUM(Q28*Q$3,R28*R$3,S28*S$3,T28*T$3)/U$3 -> 26.972603 | V28: 0 | W28: 1 | X28: 0 | Y28: 0 | Z28: 0 | AA28: 0 | AB28: 0 | AC28: 0 | AD28: 0 | AE28: 0 | AF28: 0 | AG28: 0 | AH28: 0 | AK28: 0 | AL28: 0 | AM28: 0 | AN28: 0 | AO28: 0 | AR28: 29 | AS28: 39 | AT28: 17 | AU28: 57 | AV28: 57 | AW28: 55 | AX28: 56 | AY28: 56 | AZ28: 57 | BA28: 58 | BB28: 59 | BC28: 59 | BD28: 58 | BE28: 59 | BF28: 61 | BG28: 60 | BH28: 60 | BI28: 60 | BJ28: 60 | BK28: 60 | BL28: 60 | BM28: 60 | BN28: 60 | BO28: 62 | BP28: 63 | BQ28: 66 | BR28: 69 | BS28: 65 | BT28: 59
A29: Nigeria, k bbl/d | C29: 225 | D29: 239 | E29: 236 | F29: 242 | G29: 239 | H29: 223 | I29: 247 | J29: 242 | K29: =SUM(G29*G$3,H29*H$3,I29*I$3,J29*J$3)/K$3 -> 237.78356 | L29: 248 | M29: 245 | N29: 248 | O29: 247 | P29: =SUM(L29*L$3,M29*M$3,N29*N$3,O29*O$3)/P$3 -> 247 | Q29: 235 | R29: 231 | S29: 228 | T29: 225 | U29: =SUM(Q29*Q$3,R29*R$3,S29*S$3,T29*T$3)/U$3 -> 229.71781 | V29: 226 | W29: 214 | X29: 209 | Y29: 186 | Z29: 208 | AA29: 214 | AB29: 220 | AC29: 209 | AD29: 210 | AE29: 213 | AF29: 210 | AG29: 203 | AH29: 198 | AI29: 189 | AJ29: 200 | AK29: 188 | AL29: 184 | AM29: 170 | AN29: 150 | AO29: 173 | AP29: 176 | AQ29: 140 | AR29: 126 | AS29: 119 | AT29: 140 | AU29: 136 | AV29: 120 | AW29: 124 | AX29: 117 | AY29: 124 | AZ29: 115 | BA29: 107 | BB29: 104 | BC29: 104 | BD29: 107 | BE29: 110 | BF29: 98 | BG29: 119 | BH29: 110 | BI29: 109 | BJ29: 96 | BK29: 95 | BL29: 106 | BM29: 98 | BN29: 99 | BO29: 101 | BP29: 103 | BQ29: 102 | BR29: 83 | BS29: 97 | BT29: 94
A30: South America, k bbl/d | C30: 36 | D30: 55 | E30: 59 | F30: 27 | G30: 80 | H30: 84 | I30: 85 | J30: 88 | K30: =SUM(G30*G$3,H30*H$3,I30*I$3,J30*J$3)/K$3 -> 84.273973 | L30: 92 | M30: 101 | N30: 103 | O30: 102 | P30: =SUM(L30*L$3,M30*M$3,N30*N$3,O30*O$3)/P$3 -> 99.536986 | Q30: 101 | R30: 96 | S30: 96 | T30: 95 | U30: =SUM(Q30*Q$3,R30*R$3,S30*S$3,T30*T$3)/U$3 -> 96.980822 | V30: 94 | W30: 90 | X30: 91 | Y30: 92 | Z30: 92 | AA30: 91 | AB30: 88 | AC30: 82 | AD30: 72 | AE30: 83 | AF30: 69 | AG30: 68 | AH30: 74 | AI30: 79 | AJ30: 72 | AK30: 74 | AL30: 61 | AM30: 61 | AN30: 63 | AO30: 65 | AP30: 68 | AQ30: 48 | AR30: 31 | AS30: 27 | AT30: 42 | AU30: 32 | AV30: 34 | AW30: 28 | AX30: 30 | AY30: 31 | AZ30: 32 | BA30: 32 | BB30: 35 | BC30: 39 | BD30: 35 | BE30: 37 | BF30: 37 | BG30: 36 | BH30: 39 | BI30: 37 | BJ30: 41 | BK30: 40 | BL30: 44 | BM30: 48 | BN30: 43 | BO30: 48 | BP30: 48 | BQ30: 53 | BR30: 61 | BS30: 52 | BT30: 61
A31: Other, k bbl/d | C31: 198 | D31: 233 | E31: 235 | F31: 230 | G31: 224 | H31: 210 | I31: 215 | J31: 207 | K31: =SUM(G31*G$3,H31*H$3,I31*I$3,J31*J$3)/K$3 -> 213.95616 | L31: 203 | M31: 204 | N31: 195 | O31: 189 | P31: =SUM(L31*L$3,M31*M$3,N31*N$3,O31*O$3)/P$3 -> 197.70411 | Q31: 208 | R31: 172 | S31: 201 | T31: 234 | U31: =SUM(Q31*Q$3,R31*R$3,S31*S$3,T31*T$3)/U$3 -> 203.8137 | V31: 223 | W31: 212 | X31: 236 | Y31: 225 | Z31: 225 | AA31: 227 | AB31: 240 | AC31: 253 | AD31: 259 | AE31: 245 | AF31: 283 | AG31: 274 | AH31: 280 | AI31: 293 | AJ31: 284 | AK31: 294 | AL31: 310 | AM31: 289 | AN31: 312 | AO31: 301 | AP31: 174 | AQ31: 162 | AR31: 155 | AS31: 166 | AT31: 164 | AU31: 167 | AV31: 163 | AW31: 156 | AX31: 140 | AY31: 156 | AZ31: 154 | BA31: 128 | BB31: 132 | BC31: 126 | BD31: 136 | BE31: 134 | BF31: 122 | BG31: 113 | BH31: 117 | BI31: 122 | BJ31: 121 | BK31: 119 | BL31: 116 | BM31: 112 | BN31: 118 | BO31: 78 | BP31: 76 | BQ31: 78 | BR31: 83 | BS31: 80 | BT31: 79
A32: International net liquids production, k bbl/d | C32: =SUM(C22:C31) -> 1085 | D32: =SUM(D22:D31) -> 1128 | E32: =SUM(E22:E31) -> 1080 | F32: =SUM(F22:F31) -> 1009 | G32: =SUM(G22:G31) -> 1305 | H32: =SUM(H22:H31) -> 1258 | I32: =SUM(I22:I31) -> 1279 | J32: =SUM(J22:J31) -> 1286 | ... BT32: =SUM(BT22:BT31) -> 974 | BU32: 1000 | BV32: 1250 | BW32: 1000 | BX32: =SUM(BT32*BT$3,BU32*BU$3,BV32*BV$3,BW32*BW$3)/BX$3 -> 1056.6027 | BY32: 1000 | BZ32: 1000 | CA32: 1000 | CB32: 1000 | CC32: =SUM(BY32*BY$3,BZ32*BZ$3,CA32*CA$3,CB32*CB$3)/CC$3 -> 1000 | CD32: 925 | CE32: 925 | CF32: 925
A33: US net liquids production, k bbl/d | C33: 484 | D33: 489 | E33: 465 | F33: 455 | G33: 455 | H33: 455 | I33: 448 | J33: 440 | K33: =SUM(G33*G$3,H33*H$3,I33*I$3,J33*J$3)/K$3 -> 449.45479 | L33: 438 | M33: 460 | N33: 464 | O33: 462 | P33: =SUM(L33*L$3,M33*M$3,N33*N$3,O33*O$3)/P$3 -> 456.08767 | Q33: 489 | R33: 511 | S33: 505 | T33: 499 | U33: =SUM(Q33*Q$3,R33*R$3,S33*S$3,T33*T$3)/U$3 -> 501.03836 | V33: 490 | W33: 501 | X33: 519 | Y33: 508 | Z33: 504 | AA33: 504 | AB33: 530 | AC33: 525 | AD33: 518 | AE33: 519 | AF33: 567 | AG33: 575 | AH33: 654 | AI33: 674 | AJ33: 618 | AK33: 690 | AL33: 710 | AM33: 726 | AN33: 771 | AO33: 724 | AP33: 803 | AQ33: 747 | AR33: 731 | AS33: 880 | AT33: 790 | AU33: 802 | AV33: 857 | AW33: 842 | AX33: 929 | AY33: 858 | AZ33: 880 | BA33: 888 | BB33: 891 | BC33: 895 | BD33: 888 | BE33: 877 | BF33: 916 | BG33: 1028 | BH33: 1164 | BI33: 997 | BJ33: 1130 | BK33: 1132 | BL33: 1156 | BM33: 1189 | BN33: 1152 | BO33: 1159 | BP33: 1218 | BQ33: 1496 | BR33: 1488 | BS33: 1341 | BT33: 1461 | BU33: 1500 | BV33: 1500 | BW33: 1500 | BX33: =SUM(BT33*BT$3,BU33*BU$3,BV33*BV$3,BW33*BW$3)/BX$3 -> 1490.3836 | BY33: 1500 | BZ33: 1500 | CA33: 1500 | CB33: 1500 | CC33: =SUM(BY33*BY$3,BZ33*BZ$3,CA33*CA$3,CB33*CB$3)/CC$3 -> 1500 | CD33: 1325 | CE33: 1325 | CF33: 1325
A34: Liquids, k bbl/d | C34: =SUM(C32:C33) -> 1569 | D34: =SUM(D32:D33) -> 1617 | E34: =SUM(E32:E33) -> 1545 | F34: =SUM(F32:F33) -> 1464 | G34: =SUM(G32:G33) -> 1760 | H34: =SUM(H32:H33) -> 1713 | I34: =SUM(I32:I33) -> 1727 | J34: =SUM(J32:J33) -> 1726 | ... CF34: =SUM(CF32:CF33) -> 2250
A35: Angola, MMcf/d | AZ35: 281 | BA35: 224 | BB35: 271 | BC35: 260 | BD35: 259 | BE35: 300 | BF35: 290 | BG35: 284 | BH35: 261 | BI35: 284 | BJ35: 247 | BK35: 293 | BL35: 310 | BM35: 296 | BN35: 287 | BO35: 315 | BP35: 315 | BQ35: 397 | BR35: 377 | BS35: 351 | BT35: 362
A36: Australia, MMcf/d | C36: 434 | D36: 458 | E36: 448 | F36: 428 | G36: 433 | H36: 391 | I36: 450 | J36: 410 | K36: =SUM(G36*G$3,H36*H$3,I36*I$3,J36*J$3)/K$3 -> 421.01644 | L36: 434 | M36: 423 | N36: 479 | O36: 430 | P36: =SUM(L36*L$3,M36*M$3,N36*N$3,O36*O$3)/P$3 -> 441.59178 | Q36: 457 | R36: 396 | S36: 446 | T36: 457 | U36: =SUM(Q36*Q$3,R36*R$3,S36*S$3,T36*T$3)/U$3 -> 439.01918 | V36: 474 | W36: 409 | X36: 721 | Y36: 854 | Z36: 615 | AA36: 1061 | AB36: 1316 | AC36: 1551 | AD36: 1552 | AE36: 1372 | AF36: 1973 | AG36: 2012 | AH36: 2578 | AI36: 2643 | AJ36: 2304 | AK36: 2202 | AL36: 2661 | AM36: 2644 | AN36: 2331 | AO36: 2460 | AP36: 2588 | AQ36: 2470 | AR36: 2239 | AS36: 2276 | AT36: 2392 | AU36: 2344 | AV36: 2240 | AW36: 2614 | AX36: 2534 | AY36: 2434 | AZ36: 2560 | BA36: 2411 | BB36: 2849 | BC36: 2748 | BD36: 2643 | BE36: 2697 | BF36: 2632 | BG36: 2676 | BH36: 2709 | BI36: 2678 | BJ36: 2715 | BK36: 2542 | BL36: 2607 | BM36: 2635 | BN36: 2625 | BO36: 2562 | BP36: 2510 | BQ36: 2650 | BR36: 2697 | BS36: 2605 | BT36: 2523
A37: Bangladesh, MMcf/d | C37: 387 | D37: 404 | E37: 434 | F37: 550 | G37: 658 | H37: 684 | I37: 675 | J37: 634 | K37: =SUM(G37*G$3,H37*H$3,I37*I$3,J37*J$3)/K$3 -> 662.71781 | L37: 649 | M37: 593 | N37: 651 | O37: 679 | P37: =SUM(L37*L$3,M37*M$3,N37*N$3,O37*O$3)/P$3 -> 643.10411 | Q37: 742 | R37: 738 | S37: 660 | T37: 742 | U37: =SUM(Q37*Q$3,R37*R$3,S37*S$3,T37*T$3)/U$3 -> 720.33425 | V37: 694 | W37: 647 | X37: 620 | Y37: 673 | Z37: 658 | AA37: 660 | AB37: 623 | AC37: 639 | AD37: 644 | AE37: 642 | AF37: 646 | AG37: 641 | AH37: 649 | AI37: 657 | AJ37: 648 | AK37: 637 | AL37: 634 | AM37: 636 | AN37: 646 | AO37: 638 | AP37: 644 | AQ37: 543 | AR37: 631 | AS37: 670 | AT37: 622 | AU37: 678 | AV37: 667 | AW37: 583 | AX37: 691 | AY37: 655 | AZ37: 675 | BA37: 635 | BB37: 841 | BC37: 633 | BD37: 696 | BE37: 598 | BF37: 580 | BG37: 624 | BH37: 640 | BI37: 610 | BJ37: 612 | BK37: 575 | BL37: 592 | BM37: 529 | BN37: 577 | BO37: 510 | BP37: 476 | BQ37: 519 | BR37: 471 | BS37: 494 | BT37: 424
A38: Canada, MMcf/d | AP38: 115 | AQ38: 127 | AR38: 126 | AS38: 135 | AT38: 126 | AU38: 149 | AV38: 149 | AW38: 149 | AX38: 152 | AY38: 150 | AZ38: 141 | BA38: 135 | BB38: 137 | BC38: 126 | BD38: 135 | BE38: 125 | BF38: 72 | BG38: 109 | BH38: 132 | BI38: 110 | BJ38: 127 | BK38: 134 | BL38: 147 | BM38: 115 | BN38: 131 | BO38: 10 | BP38: 10 | BQ38: 10 | BR38: 9 | BS38: 10 | BT38: 10
A39: Guyana, MMcf/d | BQ39: 18 | BR39: 21 | BS39: 10 | BT39: 24
A40: Europe, MMcf/d | C40: 383 | D40: 346 | E40: 278 | F40: 239 | G40: 218 | H40: 207 | I40: 157 | J40: 185 | K40: =SUM(G40*G$3,H40*H$3,I40*I$3,J40*J$3)/K$3 -> 191.56438 | L40: 199 | M40: 168 | N40: 157 | O40: 170 | P40: =SUM(L40*L$3,M40*M$3,N40*N$3,O40*O$3)/P$3 -> 173.37534 | Q40: 146 | R40: 166 | S40: 163 | T40: 184 | U40: =SUM(Q40*Q$3,R40*R$3,S40*S$3,T40*T$3)/U$3 -> 164.84932 | V40: 161 | W40: 152 | X40: 140 | Y40: 229 | Z40: 170 | AA40: 247 | AB40: 234 | AC40: 157 | AD40: 193 | AE40: 208 | AF40: 190 | AG40: 176 | AH40: 157 | AI40: 188 | AJ40: 178 | AK40: 184 | AL40: 126 | AM40: 107 | AN40: 56 | AO40: 119 | AP40: 5 | AQ40: 5 | AR40: 5 | AS40: 5 | AT40: 5 | AU40: 5 | AV40: 5 | AW40: 7 | AX40: 9 | AY40: 6
A41: Indonesia, MMcf/d | C41: 268 | D41: 236 | E41: 253 | F41: 236 | G41: 225 | H41: 225 | I41: 226 | J41: 227 | K41: =SUM(G41*G$3,H41*H$3,I41*I$3,J41*J$3)/K$3 -> 225.75616 | L41: 219 | M41: 216 | N41: 213 | O41: 207 | P41: =SUM(L41*L$3,M41*M$3,N41*N$3,O41*O$3)/P$3 -> 213.71507 | Q41: 193 | R41: 188 | S41: 169 | T41: 191 | U41: =SUM(Q41*Q$3,R41*R$3,S41*S$3,T41*T$3)/U$3 -> 185.2 | V41: 174 | W41: 196 | X41: 168 | Y41: 188 | Z41: 182 | AA41: 197 | AB41: 188 | AC41: 128 | AD41: 139 | AE41: 163 | AF41: 136 | AG41: 111 | AH41: 120 | AI41: 85 | AJ41: 113 | AK41: 46 | AL41: 60 | AM41: 34 | AN41: 69 | AO41: 52 | AP41: 36 | AQ41: 46 | AR41: 56 | AS41: 35 | AT41: 43 | AU41: 39 | AV41: 33 | AW41: 23 | AX41: 23 | AY41: 29
A42: Israel, MMcf/d | AS42: 462 | AT42: 116 | AU42: 515 | AV42: 520 | AW42: 597 | AX42: 530 | AY42: 541 | AZ42: 600 | BA42: 597 | BB42: 635 | BC42: 575 | BD42: 602 | BE42: 598 | BF42: 549 | BG42: 615 | BH42: 502 | BI42: 566 | BJ42: 578 | BK42: 574 | BL42: 640 | BM42: 577 | BN42: 592 | BO42: 630 | BP42: 496 | BQ42: 642 | BR42: 557 | BS42: 581 | BT42: 492
A43: Kazakhstan/Eurasia, MMcf/d | C43: 171 | D43: 160 | E43: 154 | F43: 149 | G43: 499 | H43: 469 | I43: 486 | J43: 513 | K43: =SUM(G43*G$3,H43*H$3,I43*I$3,J43*J$3)/K$3 -> 491.7726 | L43: 488 | M43: 437 | N43: 461 | O43: 501 | P43: =SUM(L43*L$3,M43*M$3,N43*N$3,O43*O$3)/P$3 -> 471.75616 | Q43: 527 | R43: 516 | S43: 439 | T43: 512 | U43: =SUM(Q43*Q$3,R43*R$3,S43*S$3,T43*T$3)/U$3 -> 498.29589 | V43: 552 | W43: 543 | X43: 479 | Y43: 594 | Z43: 542 | AA43: 595 | AB43: 535 | AC43: 497 | AD43: 552 | AE43: 544 | AF43: 543 | AG43: 537 | AH43: 482 | AI43: 506 | AJ43: 517 | AK43: 565 | AL43: 544 | AM43: 530 | AN43: 591 | AO43: 558 | AP43: 595 | AQ43: 562 | AR43: 484 | AS43: 534 | AT43: 544 | AU43: 515 | AV43: 508 | AW43: 349 | AX43: 550 | AY43: 480 | AZ43: 557 | BA43: 510 | BB43: 513 | BC43: 483 | BD43: 516 | BE43: 512 | BF43: 487 | BG43: 422 | BH43: 501 | BI43: 480 | BJ43: 515 | BK43: 478 | BL43: 483 | BM43: 465 | BN43: 485 | BO43: 500 | BP43: 458 | BQ43: 465 | BR43: 485 | BS43: 477 | BT43: 392
A44: Myanmar, MMcf/d | C44: 76 | D44: 81 | E44: 86 | F44: 94 | G44: 0 | H44: 0 | I44: 0 | J44: 0 | K44: =SUM(G44*G$3,H44*H$3,I44*I$3,J44*J$3)/K$3 -> 0 | L44: 0 | M44: 0 | N44: 0 | O44: 0 | P44: =SUM(L44*L$3,M44*M$3,N44*N$3,O44*O$3)/P$3 -> 0 | Q44: 135 | R44: 105 | S44: 116 | T44: 114 | U44: =SUM(Q44*Q$3,R44*R$3,S44*S$3,T44*T$3)/U$3 -> 117.43836 | V44: 120 | W44: 135 | X44: 120 | Y44: 136 | Z44: 128 | AA44: 127 | AB44: 137 | AC44: 108 | AD44: 92 | AE44: 116 | AF44: 97 | AG44: 109 | AH44: 94 | AI44: 94 | AJ44: 98 | AK44: 101 | AL44: 93 | AM44: 86 | AN44: 90 | AO44: 93 | AP44: 96 | AQ44: 93 | AR44: 90 | AS44: 87 | AT44: 92 | AU44: 95 | AV44: 100 | AW44: 86 | AX44: 86 | AY44: 92
A45: Nigeria, MMcf/d | C45: 48 | D45: 86 | E45: 142 | F45: 165 | G45: 0 | H45: 0 | I45: 0 | J45: 0 | K45: =SUM(G45*G$3,H45*H$3,I45*I$3,J45*J$3)/K$3 -> 0 | L45: 0 | M45: 0 | N45: 0 | O45: 0 | P45: =SUM(L45*L$3,M45*M$3,N45*N$3,O45*O$3)/P$3 -> 0 | Q45: 236 | R45: 222 | S45: 249 | T45: 276 | U45: =SUM(Q45*Q$3,R45*R$3,S45*S$3,T45*T$3)/U$3 -> 245.86849 | V45: 245 | W45: 172 | X45: 92 | Y45: 125 | Z45: 159 | AA45: 174 | AB45: 256 | AC45: 220 | AD45: 240 | AE45: 223 | AF45: 201 | AG45: 262 | AH45: 228 | AI45: 241 | AJ45: 233 | AK45: 266 | AL45: 253 | AM45: 182 | AN45: 162 | AO45: 215 | AP45: 279 | AQ45: 265 | AR45: 269 | AS45: 226 | AT45: 260 | AU45: 272 | AV45: 236 | AW45: 258 | AX45: 218 | AY45: 246 | AZ45: 274 | BA45: 247 | BB45: 279 | BC45: 265 | BD45: 266 | BE45: 241 | BF45: 208 | BG45: 238 | BH45: 220 | BI45: 227 | BJ45: 110 | BK45: 196 | BL45: 219 | BM45: 207 | BN45: 183 | BO45: 247 | BP45: 251 | BQ45: 229 | BR45: 155 | BS45: 220 | BT45: 157
A46: Philippines, MMcf/d | C46: 137 | D46: 124 | E46: 126 | F46: 120 | G46: 123 | H46: 133 | I46: 123 | J46: 96 | K46: =SUM(G46*G$3,H46*H$3,I46*I$3,J46*J$3)/K$3 -> 118.68767 | L46: 112 | M46: 118 | N46: 119 | O46: 124 | P46: =SUM(L46*L$3,M46*M$3,N46*N$3,O46*O$3)/P$3 -> 118.28493 | Q46: 99 | R46: 115 | S46: 134 | T46: 139 | U46: =SUM(Q46*Q$3,R46*R$3,S46*S$3,T46*T$3)/U$3 -> 121.89315 | V46: 140 | W46: 146 | X46: 133 | Y46: 131 | Z46: 138 | AA46: 104 | AB46: 140 | AC46: 135 | AD46: 137 | AE46: 129 | AF46: 138 | AG46: 142 | AH46: 137 | AI46: 133 | AJ46: 138 | AK46: 137 | AL46: 152 | AM46: 127 | AN46: 127 | AO46: 136 | AP46: 100 | AQ46: 0 | AR46: 0 | AS46: 0 | AT46: 25 | AU46: 0 | AV46: 0 | AX46: 0 | AY46: 0
A47: South America, MMcf/d | C47: 471 | D47: 484 | E47: 434 | F47: 395 | G47: 441 | H47: 426 | I47: 403 | J47: 421 | K47: =SUM(G47*G$3,H47*H$3,I47*I$3,J47*J$3)/K$3 -> 422.6411 | L47: 412 | M47: 370 | N47: 372 | O47: 263 | P47: =SUM(L47*L$3,M47*M$3,N47*N$3,O47*O$3)/P$3 -> 353.89041 | Q47: 375 | R47: 354 | S47: 334 | T47: 327 | U47: =SUM(Q47*Q$3,R47*R$3,S47*S$3,T47*T$3)/U$3 -> 347.33151 | V47: 306 | W47: 265 | X47: 252 | Y47: 205 | Z47: 257 | AA47: 194 | AB47: 195 | AC47: 159 | AD47: 140 | AE47: 171 | AF47: 122 | AG47: 122 | AH47: 117 | AI47: 118 | AJ47: 119 | AK47: 109 | AL47: 96 | AM47: 97 | AN47: 93 | AO47: 98 | AP47: 84 | AQ47: 38 | AR47: 25 | AS47: 24 | AT47: 42 | AU47: 28 | AV47: 31 | AW47: 33 | AX47: 35 | AY47: 32 | AZ47: 38 | BA47: 37 | BB47: 24 | BC47: 35 | BD47: 34 | BE47: 36 | BF47: 37 | BG47: 33 | BH47: 38 | BI47: 36 | BJ47: 39 | BK47: 41 | BL47: 49 | BM47: 59 | BN47: 47 | BO47: 61 | BP47: 61 | BQ47: 74 | BR47: 99 | BS47: 74 | BT47: 94
A48: Thailand, MMcf/d | C48: 794 | D48: 875 | E48: 867 | F48: 1060 | G48: 1073 | H48: 1025 | I48: 964 | J48: 955 | K48: =SUM(G48*G$3,H48*H$3,I48*I$3,J48*J$3)/K$3 -> 1003.8164 | L48: 1045 | M48: 1102 | N48: 1040 | O48: 1002 | P48: =SUM(L48*L$3,M48*M$3,N48*N$3,O48*O$3)/P$3 -> 1047.1123 | Q48: 1024 | R48: 1050 | S48: 1029 | T48: 1027 | U48: =SUM(Q48*Q$3,R48*R$3,S48*S$3,T48*T$3)/U$3 -> 1032.4986 | V48: 1039 | W48: 1030 | X48: 1085 | Y48: 1049 | Z48: 1051 | AA48: 1011 | AB48: 1058 | AC48: 1005 | AD48: 1052 | AE48: 1031 | AF48: 1037 | AG48: 1005 | AH48: 997 | AI48: 1049 | AJ48: 1022 | AK48: 1019 | AL48: 1045 | AM48: 1058 | AN48: 1031 | AO48: 1038 | AP48: 1017 | AQ48: 867 | AR48: 904 | AS48: 886 | AT48: 918 | AU48: 860 | AV48: 833 | AW48: 675 | AX48: 580 | AY48: 736 | AZ48: 509 | BA48: 270 | BB48: 206 | BC48: 210 | BD48: 298 | BE48: 197 | BF48: 177 | BG48: 187 | BH48: 205 | BI48: 192 | BJ48: 212 | BK48: 198 | BL48: 188 | BM48: 203 | BN48: 200 | BO48: 204 | BP48: 197 | BQ48: 179 | BR48: 217 | BS48: 199 | BT48: 233
A49: Other, MMcf/d | C49: 109 | D49: 109 | E49: 101 | F49: 107 | G49: 384 | H49: 427 | I49: 426 | J49: 395 | K49: =SUM(G49*G$3,H49*H$3,I49*I$3,J49*J$3)/K$3 -> 408.07945 | L49: 483 | M49: 434 | N49: 443 | O49: 458 | P49: =SUM(L49*L$3,M49*M$3,N49*N$3,O49*O$3)/P$3 -> 454.4 | Q49: 92 | R49: 81 | S49: 75 | T49: 96 | U49: =SUM(Q49*Q$3,R49*R$3,S49*S$3,T49*T$3)/U$3 -> 85.980822 | V49: 139 | W49: 248 | X49: 226 | Y49: 319 | Z49: 232 | AA49: 431 | AB49: 462 | AC49: 454 | AD49: 501 | AE49: 463 | AF49: 517 | AG49: 519 | AH49: 392 | AI49: 513 | AJ49: 485 | AK49: 547 | AL49: 533 | AM49: 471 | AN49: 551 | AO49: 525 | AP49: 490 | AQ49: 508 | AR49: 428 | AS49: 564 | AT49: 498 | AU49: 627 | AV49: 671 | AW49: 579 | AX49: 602 | AY49: 619 | AZ49: 484 | BA49: 481 | BB49: 456 | BC49: 463 | BD49: 471 | BE49: 471 | BF49: 446 | BG49: 428 | BH49: 453 | BI49: 449 | BJ49: 455 | BK49: 347 | BL49: 315 | BM49: 351 | BN49: 367 | BO49: 332 | BP49: 325 | BQ49: 491 | BR49: 426 | BS49: 395 | BT49: 450
A50: International net natural gas production, MMcf/d | C50: =SUM(C35:C49) -> 3278 | D50: =SUM(D35:D49) -> 3363 | E50: =SUM(E35:E49) -> 3323 | F50: =SUM(F35:F49) -> 3543 | G50: =SUM(G35:G49) -> 4054 | H50: =SUM(H35:H49) -> 3987 | I50: =SUM(I35:I49) -> 3910 | J50: =SUM(J35:J49) -> 3836 | ... BT50: =SUM(BT35:BT49) -> 5161 | BU50: 5600 | BV50: 5600 | BW50: 5600 | BX50: =SUM(BT50*BT$3,BU50*BU$3,BV50*BV$3,BW50*BW$3)/BX$3 -> 5491.7534 | BY50: 5500 | BZ50: 5400 | CA50: 5400 | CB50: 5400 | CC50: =SUM(BY50*BY$3,BZ50*BZ$3,CA50*CA$3,CB50*CB$3)/CC$3 -> 5424.6575 | CD50: 5400 | CE50: 5400 | CF50: 5300
A51: US net natural gas production, MMcf/d | C51: 1399 | D51: 1314 | E51: 1279 | F51: 1203 | G51: 1255 | H51: 1227 | I51: 1242 | J51: 1261 | K51: =SUM(G51*G$3,H51*H$3,I51*I$3,J51*J$3)/K$3 -> 1246.2548 | L51: 1212 | M51: 1244 | N51: 1278 | O51: 1266 | P51: =SUM(L51*L$3,M51*M$3,N51*N$3,O51*O$3)/P$3 -> 1250.2247 | Q51: 1257 | R51: 1312 | S51: 1351 | T51: 1320 | U51: =SUM(Q51*Q$3,R51*R$3,S51*S$3,T51*T$3)/U$3 -> 1310.2849 | V51: 1266 | W51: 1088 | X51: 1077 | Y51: 1044 | Z51: 1120 | AA51: 1006 | AB51: 1027 | AC51: 932 | AD51: 920 | AE51: 970 | AF51: 993 | AG51: 980 | AH51: 1061 | AI51: 1101 | AJ51: 1034 | AK51: 1162 | AL51: 1130 | AM51: 1243 | AN51: 1363 | AO51: 1225 | AP51: 1564 | AQ51: 1462 | AR51: 1507 | AS51: 1892 | AT51: 1607 | AU51: 1643 | AV51: 1678 | AW51: 1708 | AX51: 1726 | AY51: 1689 | AZ51: 1828 | BA51: 1705 | BB51: 1708 | BC51: 1789 | BD51: 1758 | BE51: 1742 | BF51: 1817 | BG51: 2275 | BH51: 2604 | BI51: 2112 | BJ51: 2657 | BK51: 2643 | BL51: 2694 | BM51: 2743 | BN51: 2684 | BO51: 2859 | BP51: 2864 | BQ51: 3265 | BR51: 3402 | BS51: 3099 | BT51: 3380 | BU51: 3500 | BV51: 3500 | BW51: 3500 | BX51: =SUM(BT51*BT$3,BU51*BU$3,BV51*BV$3,BW51*BW$3)/BX$3 -> 3470.411 | BY51: 3500 | BZ51: 3000 | CA51: 3000 | CB51: 3000 | CC51: =SUM(BY51*BY$3,BZ51*BZ$3,CA51*CA$3,CB51*CB$3)/CC$3 -> 3123.2877 | CD51: 3100 | CE51: 3100 | CF51: 3100
A52: Natural gas, MMcf/d | C52: =SUM(C50:C51) -> 4677 | D52: =SUM(D50:D51) -> 4677 | E52: =SUM(E50:E51) -> 4602 | F52: =SUM(F50:F51) -> 4746 | G52: =SUM(G50:G51) -> 5309 | H52: =SUM(H50:H51) -> 5214 | I52: =SUM(I50:I51) -> 5152 | J52: =SUM(J50:J51) -> 5097 | ... CF52: =SUM(CF50:CF51) -> 8400
A53: Total average daily production volumes, kBOE/d | C53: =C34+C52/CR.6Mcf.Per.Boe -> 2348.5 | D53: =D34+D52/CR.6Mcf.Per.Boe -> 2396.5 | E53: =E34+E52/CR.6Mcf.Per.Boe -> 2312 | F53: =F34+F52/CR.6Mcf.Per.Boe -> 2255 | G53: =G34+G52/CR.6Mcf.Per.Boe -> 2644.8333 | H53: =H34+H52/CR.6Mcf.Per.Boe -> 2582 | I53: =I34+I52/CR.6Mcf.Per.Boe -> 2585.6667 | J53: =J34+J52/CR.6Mcf.Per.Boe -> 2575.5 | ... CF53: =CF34+CF52/CR.6Mcf.Per.Boe -> 3650
A54: =CONCATENATE("Consensus Estimates - ",IFERROR(LEFT(A53,FIND("(",A53)-1),A53)) -> Consensus Estimates - Total average daily production volumes, kBOE/d | BU54: =IFERROR(VLOOKUP($A54,tb_ConsensusEstimate,MATCH(BU$5,OFFSET(tb_ConsensusEstimate,0,0,1,COLUMNS(tb_ConsensusEstimate)),0),FALSE),"-") -> n/a | BV54: =IFERROR(VLOOKUP($A54,tb_ConsensusEstimate,MATCH(BV$5,OFFSET(tb_ConsensusEstimate,0,0,1,COLUMNS(tb_ConsensusEstimate)),0),FALSE),"-") -> n/a | BW54: =IFERROR(VLOOKUP($A54,tb_ConsensusEstimate,MATCH(BW$5,OFFSET(tb_ConsensusEstimate,0,0,1,COLUMNS(tb_ConsensusEstimate)),0),FALSE),"-") -> n/a | BX54: =IFERROR(VLOOKUP($A54,tb_ConsensusEstimate,MATCH(BX$5,OFFSET(tb_ConsensusEstimate,0,0,1,COLUMNS(tb_ConsensusEstimate)),0),FALSE),"-") -> n/a | BY54: =IFERROR(VLOOKUP($A54,tb_ConsensusEstimate,MATCH(BY$5,OFFSET(tb_ConsensusEstimate,0,0,1,COLUMNS(tb_ConsensusEstimate)),0),FALSE),"-") -> n/a | BZ54: =IFERROR(VLOOKUP($A54,tb_ConsensusEstimate,MATCH(BZ$5,OFFSET(tb_ConsensusEstimate,0,0,1,COLUMNS(tb_ConsensusEstimate)),0),FALSE),"-") -> n/a | CA54: =IFERROR(VLOOKUP($A54,tb_ConsensusEstimate,MATCH(CA$5,OFFSET(tb_ConsensusEstimate,0,0,1,COLUMNS(tb_ConsensusEstimate)),0),FALSE),"-") -> n/a | CB54: =IFERROR(VLOOKUP($A54,tb_ConsensusEstimate,MATCH(CB$5,OFFSET(tb_ConsensusEstimate,0,0,1,COLUMNS(tb_ConsensusEstimate)),0),FALSE),"-") -> n/a | CC54: =IFERROR(VLOOKUP($A54,tb_ConsensusEstimate,MATCH(CC$5,OFFSET(tb_ConsensusEstimate,0,0,1,COLUMNS(tb_ConsensusEstimate)),0),FALSE),"-") -> n/a | CD54: =IFERROR(VLOOKUP($A54,tb_ConsensusEstimate,MATCH(CD5,OFFSET(tb_ConsensusEstimate,0,0,1,COLUMNS(tb_ConsensusEstimate)),0),FALSE),"-") -> n/a | CE54: =IFERROR(VLOOKUP($A54,tb_ConsensusEstimate,MATCH(CE5,OFFSET(tb_ConsensusEstimate,0,0,1,COLUMNS(tb_ConsensusEstimate)),0),FALSE),"-") -> n/a | CF54: =IFERROR(VLOOKUP($A54,tb_ConsensusEstimate,MATCH(CF5,OFFSET(tb_ConsensusEstimate,0,0,1,COLUMNS(tb_ConsensusEstimate)),0),FALSE),"-") -> n/a
A56: US liquids, MMbbl | C56: =C33*C$3/1000 -> 176.66 | D56: =D33*D$3/1000 -> 178.485 | E56: =E33*E$3/1000 -> 169.725 | F56: =F33*F$3/1000 -> 166.53 | G56: =G33*G$3/1000 -> 40.95 | H56: =H33*H$3/1000 -> 41.405 | I56: =I33*I$3/1000 -> 41.216 | J56: =J33*J$3/1000 -> 40.48 | ... BW56: =BW33*BW$3/1000 -> 138 | BX56: =SUM(BT56,BU56,BV56,BW56) -> 543.99 | BY56: =BY33*BY$3/1000 -> 135 | BZ56: =BZ33*BZ$3/1000 -> 136.5 | CA56: =CA33*CA$3/1000 -> 138 | CB56: =CB33*CB$3/1000 -> 138 | CC56: =SUM(BY56,BZ56,CA56,CB56) -> 547.5 | CD56: =CD33*CD3/1000 -> 484.95 | CE56: =CE33*CE3/1000 -> 483.625 | CF56: =CF33*CF3/1000 -> 483.625
A57: International liquids, MMbbl | C57: =C32*C$3/1000 -> 396.025 | D57: =D32*D$3/1000 -> 411.72 | E57: =E32*E$3/1000 -> 394.2 | F57: =F32*F$3/1000 -> 369.294 | G57: =G32*G$3/1000 -> 117.45 | H57: =H32*H$3/1000 -> 114.478 | I57: =I32*I$3/1000 -> 117.668 | J57: =J32*J$3/1000 -> 118.312 | ... BW57: =BW32*BW$3/1000 -> 92 | BX57: =SUM(BT57,BU57,BV57,BW57) -> 385.66 | BY57: =BY32*BY$3/1000 -> 90 | BZ57: =BZ32*BZ$3/1000 -> 91 | CA57: =CA32*CA$3/1000 -> 92 | CB57: =CB32*CB$3/1000 -> 92 | CC57: =SUM(BY57,BZ57,CA57,CB57) -> 365 | CD57: =CD32*CD3/1000 -> 338.55 | CE57: =CE32*CE3/1000 -> 337.625 | CF57: =CF32*CF3/1000 -> 337.625
A58: Liquids, MMbbl | C58: =SUM(C56:C57) -> 572.685 | D58: =SUM(D56:D57) -> 590.205 | E58: =SUM(E56:E57) -> 563.925 | F58: =SUM(F56:F57) -> 535.824 | G58: =SUM(G56:G57) -> 158.4 | H58: =SUM(H56:H57) -> 155.883 | I58: =SUM(I56:I57) -> 158.884 | J58: =SUM(J56:J57) -> 158.792 | ... CF58: =SUM(CF56:CF57) -> 821.25
A59: US natural gas, BNcf | C59: =C51*C$3/1000 -> 510.635 | D59: =D51*D$3/1000 -> 479.61 | E59: =E51*E$3/1000 -> 466.835 | F59: =F51*F$3/1000 -> 440.298 | G59: =G51*G$3/1000 -> 112.95 | H59: =H51*H$3/1000 -> 111.657 | I59: =I51*I$3/1000 -> 114.264 | J59: =J51*J$3/1000 -> 116.012 | ... BW59: =BW51*BW$3/1000 -> 322 | BX59: =SUM(BT59,BU59,BV59,BW59) -> 1266.7 | BY59: =BY51*BY$3/1000 -> 315 | BZ59: =BZ51*BZ$3/1000 -> 273 | CA59: =CA51*CA$3/1000 -> 276 | CB59: =CB51*CB$3/1000 -> 276 | CC59: =SUM(BY59,BZ59,CA59,CB59) -> 1140 | CD59: =CD51*CD3/1000 -> 1134.6 | CE59: =CE51*CE3/1000 -> 1131.5 | CF59: =CF51*CF3/1000 -> 1131.5
A60: International natural gas, BNcf | C60: =C50*C$3/1000 -> 1196.47 | D60: =D50*D$3/1000 -> 1227.495 | E60: =E50*E$3/1000 -> 1212.895 | F60: =F50*F$3/1000 -> 1296.738 | G60: =G50*G$3/1000 -> 364.86 | H60: =H50*H$3/1000 -> 362.817 | I60: =I50*I$3/1000 -> 359.72 | J60: =J50*J$3/1000 -> 352.912 | ... BW60: =BW50*BW$3/1000 -> 515.2 | BX60: =SUM(BT60,BU60,BV60,BW60) -> 2004.49 | BY60: =BY50*BY$3/1000 -> 495 | BZ60: =BZ50*BZ$3/1000 -> 491.4 | CA60: =CA50*CA$3/1000 -> 496.8 | CB60: =CB50*CB$3/1000 -> 496.8 | CC60: =SUM(BY60,BZ60,CA60,CB60) -> 1980 | CD60: =CD50*CD3/1000 -> 1976.4 | CE60: =CE50*CE3/1000 -> 1971 | CF60: =CF50*CF3/1000 -> 1934.5
A61: Natural gas, BNcf | C61: =SUM(C59:C60) -> 1707.105 | D61: =SUM(D59:D60) -> 1707.105 | E61: =SUM(E59:E60) -> 1679.73 | F61: =SUM(F59:F60) -> 1737.036 | G61: =SUM(G59:G60) -> 477.81 | H61: =SUM(H59:H60) -> 474.474 | I61: =SUM(I59:I60) -> 473.984 | J61: =SUM(J59:J60) -> 468.924 | ... CF61: =SUM(CF59:CF60) -> 3066
A62: Total production volumes, mmBOE | C62: =C58+C61/CR.6Mcf.Per.Boe -> 857.2025 | D62: =D58+D61/CR.6Mcf.Per.Boe -> 874.7225 | E62: =E58+E61/CR.6Mcf.Per.Boe -> 843.88 | F62: =F58+F61/CR.6Mcf.Per.Boe -> 825.33 | G62: =G58+G61/CR.6Mcf.Per.Boe -> 238.035 | H62: =H58+H61/CR.6Mcf.Per.Boe -> 234.962 | I62: =I58+I61/CR.6Mcf.Per.Boe -> 237.88133 | J62: =J58+J61/CR.6Mcf.Per.Boe -> 236.946 | ... CF62: =CF58+CF61/CR.6Mcf.Per.Boe -> 1332.25
A63: Liquids, % | C63: =(C58/C62) -> 0.66808601 | D63: =(D58/D62) -> 0.67473399 | E63: =(E58/E62) -> 0.6682526 | F63: =(F58/F62) -> 0.64922395 | G63: =(G58/G62) -> 0.66544836 | H63: =(H58/H62) -> 0.66343919 | I63: =(I58/I62) -> 0.66791285 | J63: =(J58/J62) -> 0.67016113 | ... CF63: =(CF58/CF62) -> 0.61643836
A64: Total Production Volume Growth, % | D64: =D62/C62-1 -> 0.020438578 | E64: =E62/D62-1 -> -0.035259754 | F64: =F62/E62-1 -> -0.021981798 | K64: =K62/F62-1 -> 0.14841861 | L64: =L62/G62-1 -> -0.021299389 | M64: =M62/H62-1 -> -0.014394526 | N64: =N62/I62-1 -> -0.0068969963 | O64: =O62/J62-1 -> 0.0025237818 | P64: =P62/K62-1 -> -0.010017503 | Q64: =Q62/L62-1 -> 0.035928144 | R64: =R62/M62-1 -> 0.020040605 | ... CC64: =CC62/BX62-1 -> -0.028713687 | CD64: =CD62/CC62-1 -> -0.063176265 | CE64: =CE62/CD62-1 -> -0.0027322404 | CF64: =CF62/CE62-1 -> -0.0045454545
A65: Production Growth Per Share, % | D65: =(D62/D537)/(C62/C537)-1 -> 0.017620669 | E65: =(E62/E537)/(D62/D537)-1 -> -0.032484321 | F65: =(F62/F537)/(E62/E537)-1 -> -0.0040467399 | K65: =(K62/K537)/(F62/F537)-1 -> 0.16765131 | L65: =(L62/L537)/(G62/G537)-1 -> -0.003612368 | M65: =(M62/M537)/(H62/H537)-1 -> 0.0034604708 | N65: =(N62/N537)/(I62/I537)-1 -> 0.010561058 | O65: =(O62/O537)/(J62/J537)-1 -> 0.021510342 | P65: =(P62/P537)/(K62/K537)-1 -> 0.0079763269 | Q65: =(Q62/Q537)/(L62/L537)-1 -> 0.054105072 | R65: =(R62/R537)/(M62/M537)-1 -> 0.033963603 | ... CC65: =(CC62/CC537)/(BX62/BX537)-1 -> -0.026101521 | CD65: =(CD62/CD537)/(CC62/CC537)-1 -> -0.063176265 | CE65: =(CE62/CE537)/(CD62/CD537)-1 -> -0.0027322404 | CF65: =(CF62/CF537)/(CE62/CE537)-1 -> -0.0045454545
A67: Total Crude Oil Production, k bbl/d | AT67: 1635 | AY67: 1553 | BD67: 1440 | BI67: 1497 | BN67: 1560 | BS67: 1827
A68: Total NGL production, k bbl/d | AT68: 233 | AY68: 261 | BD68: 279 | BI68: 333 | BN68: 415 | BS68: 477
A70: Upstream Operating Stats - Natural Gas Sales Volumes (MD&A)
A71: International sales of natural gas, MMcf/d | C71: 4062 | D71: 4493 | E71: 4361 | F71: 4315 | G71: 4498 | H71: 4272 | I71: 4072 | J71: =J78*1000/J$3 -> 4167.5978 | K71: 4251 | L71: 4041 | M71: 4132 | N71: 4290 | O71: =O78*1000/O$3 -> 4745.413 | P71: 4304 | Q71: 4026 | R71: 3931 | S71: 4105 | T71: =T78*1000/T$3 -> 5124.0652 | U71: 4299 | V71: 4044 | W71: 4503 | X71: 4306 | Y71: 4598 | Z71: 4491 | AA71: 4801 | AB71: 5142 | AC71: 4978 | AD71: 5270 | AE71: 5081 | AF71: 5475 | AG71: 4979 | AH71: 5681 | AI71: 6271 | AJ71: 5604 | AK71: 5836 | AL71: 6007 | AM71: 5923 | AN71: 5713 | AO71: 5869 | AP71: 6226 | AQ71: 5430 | AR71: 5513 | AS71: 5369 | AT71: 5634 | AU71: 5430 | AV71: 4756 | AW71: 5450 | AX71: 5077 | AY71: 5178 | AZ71: 4875 | BA71: 4537 | BB71: 7990 | BC71: 5734 | BD71: 5789 | BE71: 5785 | BF71: 5676 | BG71: 5600 | BH71: 5549 | BI71: 6025 | BJ71: 5770 | BK71: 5389 | BL71: 5576 | BM71: 5973 | BN71: 5678 | BO71: 5377 | BP71: 5507 | BQ71: 5682 | BR71: 5567 | BS71: 5535 | BT71: 5405
A72: US sales of natural gas, MMcf/d | C72: 5901 | D72: 5932 | E72: 5836 | F72: 5470 | G72: 6095 | H72: 5651 | I72: 5643 | J72: =J79*1000/J$3 -> 4558.1304 | K72: 5483 | L72: 4936 | M72: 3676 | N72: 3697 | O72: =O79*1000/O$3 -> 3687.9891 | P72: 3995 | Q72: 4139 | R72: 3777 | S72: 3896 | T72: =T79*1000/T$3 -> 3843.4348 | U72: 3913 | V72: 3808 | W72: 3154 | X72: 3263 | Y72: 3045 | Z72: 3317 | AA72: 3142 | AB72: 3265 | AC72: 3455 | AD72: 3456 | AE72: 3331 | AF72: 3408 | AG72: 3289 | AH72: 3334 | AI72: 3891 | AJ72: 3481 | AK72: 4255 | AL72: 3744 | AM72: 3945 | AN72: 4121 | AO72: 4016 | AP72: 4363 | AQ72: 3863 | AR72: 3776 | AS72: 3581 | AT72: 3894 | AU72: 3911 | AV72: 3776 | AW72: 4076 | AX72: 4260 | AY72: 4007 | AZ72: 4461 | BA72: 4364 | BB72: 4464 | BC72: 4224 | BD72: 4378 | BE72: 4096 | BF72: 4529 | BG72: 4942 | BH72: 4969 | BI72: 4637 | BJ72: 5138 | BK72: 5242 | BL72: 5378 | BM72: 4933 | BN72: 5172 | BO72: 5416 | BP72: 5594 | BQ72: 6031 | BR72: 5819 | BS72: 5717 | BT72: 6078
A73: Natural gas sales, MMcf/d | C73: =SUM(C71:C72) -> 9963 | D73: =SUM(D71:D72) -> 10425 | E73: =SUM(E71:E72) -> 10197 | F73: =SUM(F71:F72) -> 9785 | G73: =SUM(G71:G72) -> 10593 | H73: =SUM(H71:H72) -> 9923 | I73: =SUM(I71:I72) -> 9715 | J73: =SUM(J71:J72) -> 8725.7283 | ... BT73: =SUM(BT71:BT72) -> 11483
A75: US natural gas sold but not produced, BNcf | C75: =C78-C59 -> 971.995 | D75: =D78-D59 -> 1160.335 | E75: =E78-E59 -> 1124.93 | F75: =F78-F59 -> 1138.992 | G75: =G78-G59 -> 291.87 | H75: =H78-H59 -> 277.095 | I75: =I78-I59 -> 260.36 | J75: =J78-J59 -> 267.407 | ... BT75: =BT78-BT59 -> 182.25 | BU75: 320 | BV75: 283 | BW75: 320 | BX75: =SUM(BT75,BU75,BV75,BW75) -> 1105.25 | BY75: 283 | BZ75: 283 | CA75: 283 | CB75: 283 | CC75: =SUM(BY75,BZ75,CA75,CB75) -> 1132 | CD75: 1150 | CE75: 1150 | CF75: 1150
A76: International natural gas sold but not produced, BNcf | C76: =C79-C60 -> 957.395 | D76: =D79-D60 -> 937.685 | E76: =E79-E60 -> 917.245 | F76: =F79-F60 -> 705.282 | G76: =G79-G60 -> 183.69 | H76: =H79-H60 -> 151.424 | I76: =I79-I60 -> 159.436 | J76: =J79-J60 -> 66.436 | ... BT76: =BT79-BT60 -> 82.53 | BU76: 45 | BV76: -43 | BW76: 45 | BX76: =SUM(BT76,BU76,BV76,BW76) -> 129.53 | BY76: -43 | BZ76: -43 | CA76: -43 | CB76: -43 | CC76: =SUM(BY76,BZ76,CA76,CB76) -> -172 | CD76: -172 | CE76: -172 | CF76: -172
A78: International sales of natural gas, BNcf | C78: =C71*C$3/1000 -> 1482.63 | D78: =D71*D$3/1000 -> 1639.945 | E78: =E71*E$3/1000 -> 1591.765 | F78: =F71*F$3/1000 -> 1579.29 | G78: =G71*G$3/1000 -> 404.82 | H78: =H71*H$3/1000 -> 388.752 | I78: =I71*I$3/1000 -> 374.624 | J78: =K78-SUM(G78,H78,I78) -> 383.419 | K78: =K71*K$3/1000 -> 1551.615 | L78: =L71*L$3/1000 -> 363.69 | M78: =M71*M$3/1000 -> 376.012 | N78: =N71*N$3/1000 -> 394.68 | O78: =P78-SUM(L78,M78,N78) -> 436.578 | P78: =P71*P$3/1000 -> 1570.96 | Q78: =Q71*Q$3/1000 -> 362.34 | R78: =R71*R$3/1000 -> 357.721 | S78: =S71*S$3/1000 -> 377.66 | T78: =U78-SUM(Q78,R78,S78) -> 471.414 | U78: =U71*U$3/1000 -> 1569.135 | V78: =V71*V$3/1000 -> 368.004 | W78: =W71*W$3/1000 -> 409.773 | X78: =X71*X$3/1000 -> 396.152 | Y78: =Y71*Y$3/1000 -> 423.016 | Z78: =Z71*Z$3/1000 -> 1643.706 | AA78: =AA71*AA$3/1000 -> 432.09 | AB78: =AB71*AB$3/1000 -> 467.922 | ... BT78: =BT71*BT$3/1000 -> 486.45 | BU78: =BU59+BU75 -> 638.5 | BV78: =BV59+BV75 -> 605 | BW78: =BW59+BW75 -> 642 | BX78: =SUM(BT78,BU78,BV78,BW78) -> 2371.95 | BY78: =BY59+BY75 -> 598 | BZ78: =BZ59+BZ75 -> 556 | CA78: =CA59+CA75 -> 559 | CB78: =CB59+CB75 -> 559 | CC78: =SUM(BY78,BZ78,CA78,CB78) -> 2272 | CD78: =CD59+CD75 -> 2284.6 | CE78: =CE59+CE75 -> 2281.5 | CF78: =CF59+CF75 -> 2281.5
A79: US sales of natural gas, BNcf | C79: =C72*C$3/1000 -> 2153.865 | D79: =D72*D$3/1000 -> 2165.18 | E79: =E72*E$3/1000 -> 2130.14 | F79: =F72*F$3/1000 -> 2002.02 | G79: =G72*G$3/1000 -> 548.55 | H79: =H72*H$3/1000 -> 514.241 | I79: =I72*I$3/1000 -> 519.156 | J79: =K79-SUM(G79,H79,I79) -> 419.348 | K79: =K72*K$3/1000 -> 2001.295 | L79: =L72*L$3/1000 -> 444.24 | M79: =M72*M$3/1000 -> 334.516 | N79: =N72*N$3/1000 -> 340.124 | O79: =P79-SUM(L79,M79,N79) -> 339.295 | P79: =P72*P$3/1000 -> 1458.175 | Q79: =Q72*Q$3/1000 -> 372.51 | R79: =R72*R$3/1000 -> 343.707 | S79: =S72*S$3/1000 -> 358.432 | T79: =U79-SUM(Q79,R79,S79) -> 353.596 | U79: =U72*U$3/1000 -> 1428.245 | V79: =V72*V$3/1000 -> 346.528 | W79: =W72*W$3/1000 -> 287.014 | X79: =X72*X$3/1000 -> 300.196 | Y79: =Y72*Y$3/1000 -> 280.14 | Z79: =Z72*Z$3/1000 -> 1214.022 | AA79: =AA72*AA$3/1000 -> 282.78 | AB79: =AB72*AB$3/1000 -> 297.115 | ... BT79: =BT72*BT$3/1000 -> 547.02 | BU79: =BU60+BU76 -> 554.6 | BV79: =BV60+BV76 -> 472.2 | BW79: =BW60+BW76 -> 560.2 | BX79: =SUM(BT79,BU79,BV79,BW79) -> 2134.02 | BY79: =BY60+BY76 -> 452 | BZ79: =BZ60+BZ76 -> 448.4 | CA79: =CA60+CA76 -> 453.8 | CB79: =CB60+CB76 -> 453.8 | CC79: =SUM(BY79,BZ79,CA79,CB79) -> 1808 | CD79: =CD60+CD76 -> 1804.4 | CE79: =CE60+CE76 -> 1799 | CF79: =CF60+CF76 -> 1762.5
A80: Total natural gas sales, BNcf | C80: =SUM(C78:C79) -> 3636.495 | D80: =SUM(D78:D79) -> 3805.125 | E80: =SUM(E78:E79) -> 3721.905 | F80: =SUM(F78:F79) -> 3581.31 | G80: =SUM(G78:G79) -> 953.37 | H80: =SUM(H78:H79) -> 902.993 | I80: =SUM(I78:I79) -> 893.78 | J80: =SUM(J78:J79) -> 802.767 | ... CF80: =SUM(CF78:CF79) -> 4044
A82: Segmented Results - Upstream Financials (FS)
A83: Implied US revenues from sales of liquids and gas, mm | C83: =(C56*C114)+(C79*C116) -> 17637.154 | D83: =(D56*D114)+(D79*D116) -> 22001.408 | E83: =(E56*E114)+(E79*E116) -> 25155.65 | F83: =(F56*F114)+(F79*F116) -> 21140.654 | G83: =(G56*G114)+(G79*G116) -> 5575.356 | H83: =(H56*H114)+(H79*H116) -> 5763.4422 | I83: =(I56*I114)+(I79*I116) -> 5682.2448 | J83: =(J56*J114)+(J79*J116) -> 5043.1582 | ... BW83: =(BW56*BW114)+(BW79*BW116) -> 8624.69 | BX83: =SUM(BT83,BU83,BV83,BW83) -> 35789.62 | BY83: =(BY56*BY114)+(BY79*BY116) -> 8059.61 | BZ83: =(BZ56*BZ114)+(BZ79*BZ116) -> 7535.813 | CA83: =(CA56*CA114)+(CA79*CA116) -> 7630.722 | CB83: =(CB56*CB114)+(CB79*CB116) -> 7766.144 | CC83: =SUM(BY83,BZ83,CA83,CB83) -> 30992.289 | CD83: =(CD56*CD114)+(CD79*CD116) -> 26932.85 | CE83: =(CE56*CE114)+(CE79*CE116) -> 26284.64 | CF83: =(CF56*CF114)+(CF79*CF116) -> 25217.402
A84: Implied international revenues from sales of liquids and gas, mm | C84: =(C57*C115)+(C78*C117) -> 28110.866 | D84: =(D57*D115)+(D78*D117) -> 37533.154 | E84: =(E57*E115)+(E78*E117) -> 48602.739 | F84: =(F57*F115)+(F78*F117) -> 47083.62 | G84: =(G57*G115)+(G78*G117) -> 13555.108 | H84: =(H57*H115)+(H78*H117) -> 13033.033 | I84: =(I57*I115)+(I78*I117) -> 14474.385 | J84: =(J57*J115)+(J78*J117) -> 14103.297 | ... BW84: =(BW57*BW115)+(BW78*BW117) -> 10596.14 | BX84: =SUM(BT84,BU84,BV84,BW84) -> 44899.25 | BY84: =(BY57*BY115)+(BY78*BY117) -> 10164.64 | BZ84: =(BZ57*BZ115)+(BZ78*BZ117) -> 9294.47 | CA84: =(CA57*CA115)+(CA78*CA117) -> 9467.37 | CB84: =(CB57*CB115)+(CB78*CB117) -> 9683.32 | CC84: =SUM(BY84,BZ84,CA84,CB84) -> 38609.8 | CD84: =(CD57*CD115)+(CD78*CD117) -> 41015.91 | CE84: =(CE57*CE115)+(CE78*CE117) -> 40479.575 | CF84: =(CF57*CF115)+(CF78*CF117) -> 39737.517
A85: Total implied upstream revenue, mm | C85: =SUM(C83:C84) -> 45748.02 | D85: =SUM(D83:D84) -> 59534.562 | E85: =SUM(E83:E84) -> 73758.39 | F85: =SUM(F83:F84) -> 68224.274 | G85: =SUM(G83:G84) -> 19130.464 | H85: =SUM(H83:H84) -> 18796.475 | I85: =SUM(I83:I84) -> 20156.63 | J85: =SUM(J83:J84) -> 19146.455 | ... CF85: =SUM(CF83:CF84) -> 64954.92
A87: Discrepancy, implied US revenues to reported US revenues, mm | C87: =C90-C83 -> 1884.846 | D87: =D90-D83 -> 2153.592 | E87: =E90-E83 -> 2582.3497 | F87: =F90-F83 -> 2504.3459 | G87: =G90-G83 -> 691.644 | H87: =H90-H83 -> 649.55777 | I87: =I90-I83 -> 713.75524 | J87: =J90-J83 -> 797.8418 | ... BT87: =BT90-BT83 -> 4655.7998 | BU87: 4000 | BV87: 4000 | BW87: 4600 | BX87: =SUM(BT87,BU87,BV87,BW87) -> 17255.8 | BY87: 4000 | BZ87: 4000 | CA87: 4000 | CB87: 4000 | CC87: =SUM(BY87,BZ87,CA87,CB87) -> 16000 | CD87: 12000 | CE87: 12000 | CF87: 12000
A88: Discrepancy, implied international revenues to reported US revenues, mm | C88: =C91-C84 -> 3829.1345 | D88: =D91-D84 -> 3600.8456 | E88: =E91-E84 -> 6495.2607 | F88: =F91-F84 -> 6469.3802 | G88: =G91-G84 -> -644.1079 | H88: =H91-H84 -> -1287.0327 | I88: =I91-I84 -> -1475.3848 | J88: =J91-J84 -> -1118.2971 | ... BT88: =BT91-BT84 -> 1819.0645 | BU88: 1000 | BV88: 1000 | BW88: 1000 | BX88: =SUM(BT88,BU88,BV88,BW88) -> 4819.0645 | BY88: 1000 | BZ88: 1000 | CA88: 1000 | CB88: 1000 | CC88: =SUM(BY88,BZ88,CA88,CB88) -> 4000 | CD88: 3000 | CE88: 3000 | CF88: 3000
A90: Reported US upstream revenues, mm | C90: 19522 | D90: 24155 | E90: 27738 | F90: 23645 | G90: 6267 | H90: 6413 | I90: 6396 | J90: =K90-SUM(G90,H90,I90) -> 5841 | K90: 24917 | L90: 6745 | M90: 5965 | N90: 5676 | O90: =P90-SUM(L90,M90,N90) -> 4524 | P90: 22910 | Q90: 3349 | R90: 3533 | S90: 3207 | T90: =U90-SUM(Q90,R90,S90) -> 2659 | U90: 12748 | V90: 2072 | W90: 2467 | X90: 2847 | Y90: =Z90-SUM(V90,W90,X90) -> 2979 | Z90: 10365 | AA90: 3240 | AB90: 3135 | AC90: 3245 | AD90: =AE90-SUM(AA90,AB90,AC90) -> 3622 | AE90: 13242 | AF90: 4577 | AG90: 5044 | AH90: 6784 | AI90: =AJ90-SUM(AF90,AG90,AH90) -> 6486 | AJ90: 22891 | AK90: 5882 | AL90: 5927 | AM90: 5602 | AN90: =AO90-SUM(AK90,AL90,AM90) -> 5947 | AO90: 23358 | AP90: 4466 | AQ90: 2544 | AR90: 3367 | AS90: =AT90-SUM(AP90,AQ90,AR90) -> 4200 | AT90: 14577 | AU90: 5791 | AV90: 6034 | AW90: 7374 | AX90: =AY90-SUM(AU90,AV90,AW90) -> 10020 | AY90: 29219 | AZ90: 11316 | BA90: 14232 | BB90: 13183 | BC90: =BD90-SUM(AZ90,BA90,BB90) -> 12091 | BD90: 50822 | BE90: 9623 | BF90: 8755 | BG90: 10278 | BH90: =BI90-SUM(BE90,BF90,BG90) -> 11459 | BI90: 40115 | BJ90: 11167 | BK90: 11287 | BL90: 10730 | BM90: =BN90-SUM(BJ90,BK90,BL90) -> 11118 | BN90: 44302 | BO90: 11515 | BP90: 10385 | BQ90: 12161 | BR90: =BS90-SUM(BO90,BP90,BQ90) -> 11457 | BS90: 45518 | BT90: 12842 | BU90: =BU83+BU87 -> 14016.2 | BV90: =BV83+BV87 -> 12962.53 | BW90: =BW83+BW87 -> 13224.69 | BX90: =SUM(BT90,BU90,BV90,BW90) -> 53045.42 | BY90: =BY83+BY87 -> 12059.61 | BZ90: =BZ83+BZ87 -> 11535.813 | CA90: =CA83+CA87 -> 11630.722 | CB90: =CB83+CB87 -> 11766.144 | CC90: =SUM(BY90,BZ90,CA90,CB90) -> 46992.289 | CD90: =CD83+CD87 -> 38932.85 | CE90: =CE83+CE87 -> 38284.64 | CF90: =CF83+CF87 -> 37217.402
A91: Reported international upstream revenues, mm | C91: 31940 | D91: 41134 | E91: 55098 | F91: 53553 | G91: 12911 | H91: 11746 | I91: 12999 | J91: =K91-SUM(G91,H91,I91) -> 12985 | K91: 50641 | L91: 11881 | M91: 13454 | N91: 12084 | O91: =P91-SUM(L91,M91,N91) -> 9496 | P91: 46915 | Q91: 7215 | R91: 7408 | S91: 6540 | T91: =U91-SUM(Q91,R91,S91) -> 5916 | U91: 27079 | V91: 5021 | W91: 5377 | X91: 5927 | Y91: =Z91-SUM(V91,W91,X91) -> 6455 | Z91: 22780 | AA91: 6581 | AB91: 6852 | AC91: 7191 | AD91: =AE91-SUM(AA91,AB91,AC91) -> 8056 | AE91: 28680 | AF91: 8656 | AG91: 8880 | AH91: 10312 | AI91: =AJ91-SUM(AF91,AG91,AH91) -> 9974 | AJ91: 37822 | AK91: 9369 | AL91: 8977 | AM91: 8607 | AN91: =AO91-SUM(AK91,AL91,AM91) -> 8675 | AO91: 35628 | AP91: 9013 | AQ91: 4554 | AR91: 5911 | AS91: =AT91-SUM(AP91,AQ91,AR91) -> 7326 | AT91: 26804 | AU91: 8790 | AV91: 9516 | AW91: 11262 | AX91: =AY91-SUM(AU91,AV91,AW91) -> 11353 | AY91: 40921 | AZ91: 13502 | BA91: 14230 | BB91: 15286 | BC91: =BD91-SUM(AZ91,BA91,BB91) -> 13138 | BD91: 56156 | BE91: 11196 | BF91: 9876 | BG91: 10633 | BH91: =BI91-SUM(BE91,BF91,BG91) -> 12100 | BI91: 43805 | BJ91: 10783 | BK91: 10221 | BL91: 11330 | BM91: =BN91-SUM(BJ91,BK91,BL91) -> 11132 | BN91: 43466 | BO91: 9971 | BP91: 9182 | BQ91: 12118 | BR91: =BS91-SUM(BO91,BP91,BQ91) -> 11590 | BS91: 42861 | BT91: 12013 | BU91: =BU84+BU88 -> 12843.925 | BV91: =BV84+BV88 -> 13265.25 | BW91: =BW84+BW88 -> 11596.14 | BX91: =SUM(BT91,BU91,BV91,BW91) -> 49718.315 | BY91: =BY84+BY88 -> 11164.64 | BZ91: =BZ84+BZ88 -> 10294.47 | CA91: =CA84+CA88 -> 10467.37 | CB91: =CB84+CB88 -> 10683.32 | CC91: =SUM(BY91,BZ91,CA91,CB91) -> 42609.8 | CD91: =CD84+CD88 -> 44015.91 | CE91: =CE84+CE88 -> 43479.575 | CF91: =CF84+CF88 -> 42737.517
A92: Subtotal upstream revenues, mm | C92: =SUM(C90:C91) -> 51462 | D92: =SUM(D90:D91) -> 65289 | E92: =SUM(E90:E91) -> 82836 | F92: =SUM(F90:F91) -> 77198 | G92: =SUM(G90:G91) -> 19178 | H92: =SUM(H90:H91) -> 18159 | I92: =SUM(I90:I91) -> 19395 | J92: =SUM(J90:J91) -> 18826 | ... CF92: =SUM(CF90:CF91) -> 79954.92
A93: US intersegment eliminations, mm | C93: -10297 | D93: -13839 | E93: -18115 | F93: -17229 | G93: -4194 | H93: -4217 | I93: -4405 | J93: =K93-SUM(G93,H93,I93) -> -4049 | K93: -16865 | L93: -3932 | M93: -4260 | N93: -4127 | O93: =P93-SUM(L93,M93,N93) -> -3136 | P93: -15455 | Q93: -2111 | R93: -2553 | S93: -2165 | T93: =U93-SUM(Q93,R93,S93) -> -1802 | U93: -8631 | V93: -1331 | W93: -1810 | X93: -1979 | Y93: =Z93-SUM(V93,W93,X93) -> -2097 | Z93: -7217 | AA93: -2241 | AB93: -2198 | AC93: -2298 | AD93: =AE93-SUM(AA93,AB93,AC93) -> -2604 | AE93: -9341 | AF93: -2757 | AG93: -3185 | AH93: -4277 | AI93: =AJ93-SUM(AF93,AG93,AH93) -> -3746 | AJ93: -13965 | AK93: -3519 | AL93: -3865 | AM93: -3686 | AN93: =AO93-SUM(AK93,AL93,AM93) -> -3874 | AO93: -14944 | AP93: -2812 | AQ93: -1420 | AR93: -1916 | AS93: =AT93-SUM(AP93,AQ93,AR93) -> -1920 | AT93: -8068 | AU93: -2855 | AV93: -3256 | AW93: -3520 | AX93: =AY93-SUM(AU93,AV93,AW93) -> -5523 | AY93: -15154 | AZ93: -6919 | BA93: -8475 | BB93: -7138 | BC93: =BD93-SUM(AZ93,BA93,BB93) -> -7338 | BD93: -29870 | BE93: -5902 | BF93: -6067 | BG93: -6797 | BH93: =BI93-SUM(BE93,BF93,BG93) -> -7541 | BI93: -26307 | BJ93: -7589 | BK93: -7890 | BL93: -7432 | BM93: =BN93-SUM(BJ93,BK93,BL93) -> -6751 | BN93: -29662 | BO93: -7112 | BP93: -6321 | BQ93: -6538 | BR93: =BS93-SUM(BO93,BP93,BQ93) -> -5939 | BS93: -25910 | BT93: -6755 | BU93: -4000 | BV93: -5000 | BW93: -5000 | BX93: =SUM(BT93,BU93,BV93,BW93) -> -20755 | BY93: -5000 | BZ93: -5000 | CA93: -5000 | CB93: -5000 | CC93: =SUM(BY93,BZ93,CA93,CB93) -> -20000 | CD93: -20000 | CE93: -20000 | CF93: -20000
A94: International intersegment eliminations, mm | C94: -18477 | D94: -23834 | E94: -35012 | F94: -34094 | G94: -8356 | H94: -7449 | I94: -8715 | J94: =K94-SUM(G94,H94,I94) -> -8514 | K94: -33034 | L94: -5762 | M94: -6597 | N94: -6317 | O94: =P94-SUM(L94,M94,N94) -> -4431 | P94: -23107 | Q94: -2992 | R94: -3281 | S94: -2774 | T94: =U94-SUM(Q94,R94,S94) -> -2445 | U94: -11492 | V94: -1929 | W94: -2278 | X94: -2742 | Y94: =Z94-SUM(V94,W94,X94) -> -2569 | Z94: -9518 | AA94: -2720 | AB94: -2708 | AC94: -2828 | AD94: =AE94-SUM(AA94,AB94,AC94) -> -3215 | AE94: -11471 | AF94: -3215 | AG94: -3421 | AH94: -4045 | AI94: =AJ94-SUM(AF94,AG94,AH94) -> -2998 | AJ94: -13679 | AK94: -3292 | AL94: -3104 | AM94: -3015 | AN94: =AO94-SUM(AK94,AL94,AM94) -> -2924 | AO94: -12335 | AP94: -2541 | AQ94: -1021 | AR94: -1661 | AS94: =AT94-SUM(AP94,AQ94,AR94) -> -1779 | AT94: -7002 | AU94: -2375 | AV94: -2761 | AW94: -3141 | AX94: =AY94-SUM(AU94,AV94,AW94) -> -2717 | AY94: -10994 | AZ94: -3649 | BA94: -4138 | BB94: -3102 | BC94: =BD94-SUM(AZ94,BA94,BB94) -> -2926 | BD94: -13815 | BE94: -2606 | BF94: -2419 | BG94: -3256 | BH94: =BI94-SUM(BE94,BF94,BG94) -> -3590 | BI94: -11871 | BJ94: -2925 | BK94: -3072 | BL94: -2745 | BM94: =BN94-SUM(BJ94,BK94,BL94) -> -2516 | BN94: -11258 | BO94: -1953 | BP94: -2178 | BQ94: -2576 | BR94: =BS94-SUM(BO94,BP94,BQ94) -> -2310 | BS94: -9017 | BT94: -4921 | BU94: -2000 | BV94: -3000 | BW94: -2000 | BX94: =SUM(BT94,BU94,BV94,BW94) -> -11921 | BY94: -3000 | BZ94: -3000 | CA94: -3000 | CB94: -3000 | CC94: =SUM(BY94,BZ94,CA94,CB94) -> -12000 | CD94: -12000 | CE94: -12000 | CF94: -12000
A95: Total upstream revenues, mm | C95: =SUM(C92:C94) -> 22688 | D95: =SUM(D92:D94) -> 27616 | E95: =SUM(E92:E94) -> 29709 | F95: =SUM(F92:F94) -> 25875 | G95: =SUM(G92:G94) -> 6628 | H95: =SUM(H92:H94) -> 6493 | I95: =SUM(I92:I94) -> 6275 | J95: =SUM(J92:J94) -> 6263 | ... CF95: =SUM(CF92:CF94) -> 47954.92
A97: Upstream US Earnings, mm | C97: 2262 | D97: 4122 | E97: 6512 | F97: 5332 | G97: 1132 | H97: 1083 | I97: 1026 | J97: 803 | K97: 4044 | L97: 912 | M97: 1054 | N97: 929 | O97: 432 | P97: 3327 | Q97: -460 | R97: -1038 | S97: -603 | T97: -1954 | U97: -4055 | V97: -850 | W97: -1113 | X97: -212 | Y97: 121 | Z97: -2054 | AA97: 80 | AB97: -102 | AC97: -26 | AD97: 3688 | AE97: 3640 | AF97: 648 | AG97: 838 | AH97: 828 | AI97: 964 | AJ97: 3278 | AK97: 748 | AL97: 896 | AM97: 727 | AN97: -7465 | AO97: -5094 | AP97: 241 | AQ97: -2066 | AR97: 116 | AS97: 101 | AT97: -1608 | AU97: 941 | AV97: 1446 | AW97: 1962 | AX97: 2970 | AY97: 7319 | AZ97: 3238 | BA97: 3367 | BB97: 3398 | BC97: 2618 | BD97: 12621 | BE97: 1781 | BF97: 1640 | BG97: 2074 | BH97: -1347 | BI97: 4148 | BJ97: 2075 | BK97: 2161 | BL97: 1946 | BM97: 1420 | BN97: 7602 | BO97: 1858 | BP97: 1418 | BQ97: 1282 | BR97: 1258 | BS97: 5815 | BT97: 2112
A98: Upstream International Earnings, mm | C98: 8670 | D98: 13555 | E98: 18274 | F98: 18456 | G98: 4784 | H98: 3866 | I98: 4066 | J98: 4049 | K98: 16765 | L98: 3395 | M98: 4210 | N98: 3720 | O98: 2241 | P98: 13566 | Q98: 2020 | R98: -1181 | S98: 662 | T98: 593 | U98: 2094 | V98: -609 | W98: -1349 | X98: 666 | Y98: 809 | Z98: -483 | AA98: 1437 | AB98: 955 | AC98: 515 | AD98: 1603 | AE98: 4510 | AF98: 2704 | AG98: 2457 | AH98: 2551 | AI98: 2326 | AJ98: 10038 | AK98: 2375 | AL98: 2587 | AM98: 1977 | AN98: 731 | AO98: 7670 | AP98: 2679 | AQ98: -4023 | AR98: 119 | AS98: 400 | AT98: -825 | AU98: 1409 | AV98: 1732 | AW98: 3173 | AX98: 2185 | AY98: 8499 | AZ98: 3696 | BA98: 5191 | BB98: 5909 | BC98: 2867 | BD98: 17663 | BE98: 3380 | BF98: 3296 | BG98: 3681 | BH98: 2933 | BI98: 13290 | BJ98: 3164 | BK98: 2309 | BL98: 2643 | BM98: 2884 | BN98: 11000 | BO98: 1900 | BP98: 1309 | BQ98: 2020 | BR98: 1777 | BS98: 7007 | BT98: 1797
A99: Upstream Earnings, mm | C99: 10932 | D99: 17677 | E99: 24786 | F99: 23788 | G99: 5916 | H99: 4949 | I99: 5092 | J99: 4852 | K99: 20809 | L99: 4307 | M99: 5264 | N99: 4649 | O99: 2673 | P99: 16893 | Q99: 1560 | R99: -2219 | S99: 59 | T99: -1361 | U99: -1961 | V99: -1459 | W99: -2462 | X99: 454 | Y99: 930 | Z99: -2537 | AA99: 1517 | AB99: 853 | AC99: 489 | AD99: =SUM(AD97:AD98) -> 5291 | AE99: =SUM(AE97:AE98) -> 8150 | AF99: =SUM(AF97:AF98) -> 3352 | AG99: =SUM(AG97:AG98) -> 3295 | AH99: =SUM(AH97:AH98) -> 3379 | AI99: =SUM(AI97:AI98) -> 3290 | AJ99: =SUM(AJ97:AJ98) -> 13316 | AK99: =SUM(AK97:AK98) -> 3123 | ... BT99: =SUM(BT97:BT98) -> 3909
A101: Upstream US Adjusted Earnings, mm | AK101: =AK435 -> 748 | AL101: =AL435 -> 896 | AM101: =AM435 -> 727 | AN101: =AN435 -> 705 | AO101: =AO435 -> 3076 | AP101: =AP435 -> 241 | AQ101: =AQ435 -> -756 | AR101: =AR435 -> 116 | ... BT101: =BT435 -> 2112
A102: Upstream International Adjusted Earnings, mm | AK102: =AK445 -> 2543 | AL102: =AL445 -> 2385 | AM102: =AM445 -> 1928 | AN102: =AN445 -> 1937 | AO102: =AO445 -> 8793 | AP102: =AP445 -> 1531 | AQ102: =AQ445 -> -571 | AR102: =AR445 -> 356 | ... BT102: =BT445 -> 2030
A103: Upstream Adjusted Earnings, mm | AK103: =SUM(AK101:AK102) -> 3291 | AL103: =SUM(AL101:AL102) -> 3281 | AM103: =SUM(AM101:AM102) -> 2655 | AN103: =SUM(AN101:AN102) -> 2642 | AO103: =SUM(AO101:AO102) -> 11869 | AP103: =SUM(AP101:AP102) -> 1772 | AQ103: =SUM(AQ101:AQ102) -> -1327 | AR103: =SUM(AR101:AR102) -> 472 | ... BT103: =SUM(BT101:BT102) -> 4142
A105: Upstream production expenses excluding taxes, mm | C105: 8224 | D105: 9182 | E105: 11425 | F105: 12346 | K105: 13304 | P105: 13689 | U105: 11481 | Z105: 10141 | AE105: 9091 | AJ105: 9410 | AO105: 9709 | AT105: 9460 | AY105: 9484 | BD105: 9328 | BI105: 9801 | BN105: 9615 | BS105: 10935
A106: Upstream taxes other than on income, mm | C106: 836 | D106: 1195 | E106: 1527 | F106: 1522 | K106: 1408 | P106: 1331 | U106: 866 | Z106: 701 | AE106: 800 | AJ106: 996 | AO106: 999 | AT106: 870 | AY106: 1368 | BD106: 1949 | BI106: 1720 | BN106: 1913 | BS106: 1928
A107: Upstream depreciation and depletion, mm | C107: 9545 | D107: 10398 | E107: 10026 | F107: 10700 | K107: 11568 | P107: 13026 | U107: 17325 | Z107: 16010 | AE107: 15647 | AJ107: 15177 | AO107: 21029 | AT107: 15776 | AY107: 14289 | BD107: 12180 | BI107: 13379 | BN107: 13714 | BS107: 16415
A109: Upstream production expenses excluding taxes, $/Company0325 | C109: =C105/C62 -> 9.5939991 | D109: =D105/D62 -> 10.497043 | E109: =E105/E62 -> 13.538655 | F109: =F105/F62 -> 14.958865 | K109: =K105/K62 -> 14.036356 | P109: =P105/P62 -> 14.588692 | U109: =U105/U62 -> 11.996884 | Z109: =Z105/Z62 -> 10.680066 | AE109: =AE105/AE62 -> 9.1289613 | AJ109: =AJ105/AJ62 -> 8.7984149 | AO109: =AO105/AO62 -> 8.6989699 | AT109: =AT105/AT62 -> 8.3837154 | AY109: =AY105/AY62 -> 8.3849497 | BD109: =BD105/BD62 -> 8.5196681 | BI109: =BI105/BI62 -> 8.6045892 | BN109: =BN105/BN62 -> 7.8701294 | BS109: =BS105/BS62 -> 8.0487809
A110: Upstream taxes other than on income, $/Company0325 | C110: =C106/C62 -> 0.97526547 | D110: =D106/D62 -> 1.3661475 | E110: =E106/E62 -> 1.809499 | F110: =F106/F62 -> 1.8441108 | K110: =K106/K62 -> 1.4855073 | P110: =P106/P62 -> 1.4184783 | U110: =U106/U62 -> 0.9049126 | Z110: =Z106/Z62 -> 0.73826309 | AE110: =AE106/AE62 -> 0.80334056 | AJ110: =AJ106/AJ62 -> 0.93126686 | AO110: =AO106/AO62 -> 0.89507373 | AT110: =AT106/AT62 -> 0.77101822 | AY110: =AY106/AY62 -> 1.2094698 | BD110: =BD106/BD62 -> 1.7801065 | BI110: =BI106/BI62 -> 1.5100391 | BN110: =BN106/BN62 -> 1.5658406 | BS110: =BS106/BS62 -> 1.4191175
A111: Upstream Depreciation and Depletion, $/Company0325 | C111: =C107/C62 -> 11.135059 | D111: =D107/D62 -> 11.887199 | E111: =E107/E62 -> 11.880836 | F111: =F107/F62 -> 12.964511 | K111: =K107/K62 -> 12.204793 | P111: =P107/P62 -> 13.882117 | U111: =U107/U62 -> 18.103477 | Z111: =Z107/Z62 -> 16.861044 | AE111: =AE107/AE62 -> 15.712337 | AJ111: =AJ107/AJ62 -> 14.1906 | AO111: =AO107/AO62 -> 18.841347 | AT111: =AT107/AT62 -> 13.98113 | AY111: =AY107/AY62 -> 12.633124 | BD111: =BD107/BD62 -> 11.124524 | BI111: =BI107/BI62 -> 11.745822 | BN111: =BN107/BN62 -> 11.225268 | BS111: =BS107/BS62 -> 12.082372
A113: Operating Stats - Realized Pricing Excluding Hedging (MD&A)
A114: Realized US Liquids, $/bbl | C114: 54.36 | D114: 71.59 | E114: 97.51 | F114: 95.21 | G114: 94.49 | H114: 92.25 | I114: 97.18 | J114: 89.88 | K114: 93.46 | L114: 91.49 | M114: 92.44 | N114: 87.42 | O114: 65.83 | P114: 84.13 | Q114: 43.11 | R114: 50.29 | S114: 41.98 | T114: 35.33 | U114: 42.7 | V114: 26.49 | W114: 35.79 | X114: 36.88 | Y114: 40.42 | Z114: 35 | AA114: 44.83 | AB114: 41.42 | AC114: 41.83 | AD114: 50.12 | AE114: 44.53 | AF114: 56.12 | AG114: 58.79 | AH114: 61.99 | AI114: 55.62 | AJ114: 58.17 | AK114: 48.46 | AL114: 52.41 | AM114: 46.84 | AN114: 46.67 | AO114: 48.54 | AP114: 37.42 | AQ114: 19.29 | AR114: 31.33 | AS114: 33.1 | AT114: 30.53 | AU114: 47.7 | AV114: 54.08 | AW114: 57.81 | AX114: 63.33 | AY114: 56.06 | AZ114: 76.6 | BA114: 88.71 | BB114: 75.73 | BC114: 66 | BD114: 76.71 | BE114: 59.06 | BF114: 56.29 | BG114: 62.42 | BH114: 58.69 | BI114: 59.19 | BJ114: 57.37 | BK114: 59.85 | BL114: 54.86 | BM114: 53.12 | BN114: 56.24 | BO114: 55.26 | BP114: 47.77 | BQ114: 48.12 | BR114: 42.99 | BS114: 48.13 | BT114: 51.94 | BU114: =BU122+BU126 -> 68.3 | BV114: =BV122+BV126 -> 59.3 | BW114: =BW122+BW126 -> 53.77 | BX114: =SUM(BT114*BT56,BU114*BU56,BV114*BV56,BW114*BW56)/BX56 -> 58.376442 | BY114: =BY122+BY126 -> 51.23 | BZ114: =BZ122+BZ126 -> 50.05 | CA114: =CA122+CA126 -> 49.08 | CB114: =CB122+CB126 -> 48.45 | CC114: =SUM(BY114*BY56,BZ114*BZ56,CA114*CA56,CB114*CB56)/CC56 -> 49.693178 | CD114: =CD122+CD126 -> 47.24 | CE114: =CE122+CE126 -> 46.24 | CF114: =CF122+CF126 -> 44.38
A115: Realized International Liquids, $/bbl | C115: 55.97 | D115: 72.68 | E115: 101.53 | F115: 101.88 | G115: 94.49 | H115: 93.71 | I115: 104.29 | J115: 100.57 | K115: 100.26 | L115: 98.6 | M115: 101.15 | N115: 93.45 | O115: 68.32 | P115: 90.42 | Q115: 46.49 | R115: 55.94 | S115: 44.85 | T115: 38.71 | U115: 46.52 | V115: 29.14 | W115: 40.25 | X115: 41.08 | Y115: 44.43 | Z115: 38.61 | AA115: 48.56 | AB115: 44.94 | AC115: 47.81 | AD115: 56.68 | AE115: 49.46 | AF115: 61.13 | AG115: 67.61 | AH115: 68.73 | AI115: 59.11 | AJ115: 64.25 | AK115: 57.99 | AL115: 62.03 | AM115: 56.07 | AN115: 56.52 | AO115: 58.14 | AP115: 42.64 | AQ115: 21.19 | AR115: 38.96 | AS115: 40.3 | AT115: 45.7 | AU115: 55.62 | AV115: 62.12 | AW115: 67.92 | AX115: 73.71 | AY115: 64.53 | AZ115: 93.31 | BA115: 102.3 | BB115: 89.14 | BC115: 77.67 | BD115: 90.71 | BE115: 68.89 | BF115: 68.06 | BG115: 75.64 | BH115: 74.54 | BI115: 71.7 | BJ115: 72.52 | BK115: 74.92 | BL115: 70.59 | BM115: 67.33 | BN115: 71.38 | BO115: 67.69 | BP115: 58.88 | BQ115: 63.16 | BR115: 57.53 | BS115: 61.58 | BT115: 77.5 | BU115: =BU122+BU127 -> 86.3 | BV115: =BV122+BV127 -> 74.3 | BW115: =BW122+BW127 -> 68.77 | BX115: =SUM(BT115*BT57,BU115*BU57,BV115*BV57,BW115*BW57)/BX57 -> 76.539672 | BY115: =BY122+BY127 -> 66.23 | BZ115: =BZ122+BZ127 -> 65.05 | CA115: =CA122+CA127 -> 64.08 | CB115: =CB122+CB127 -> 63.45 | CC115: =SUM(BY115*BY57,BZ115*BZ57,CA115*CA57,CB115*CB57)/CC57 -> 64.693178 | CD115: =CD122+CD127 -> 62.24 | CE115: =CE122+CE127 -> 61.24 | CF115: =CF122+CF127 -> 59.38
A116: Realized US gas, $/Mcf | C116: 3.73 | D116: 4.26 | E116: 4.04 | F116: 2.64 | G116: 3.11 | H116: 3.78 | I116: 3.23 | J116: 3.35 | K116: 3.37 | L116: 4.77 | M116: 4.09 | N116: 3.46 | O116: 3.34 | P116: 3.9 | Q116: 2.27 | R116: 1.92 | S116: 1.96 | T116: 1.54 | U116: 1.92 | V116: 1.32 | W116: 1.21 | X116: 1.89 | Y116: 1.98 | Z116: 1.59 | AA116: 2.39 | AB116: 2.32 | AC116: 1.8 | AD116: 1.86 | AE116: 2.1 | AF116: 2.02 | AG116: 1.61 | AH116: 1.8 | AI116: 2.01 | AJ116: 1.86 | AK116: 1.64 | AL116: 0.68 | AM116: 0.95 | AN116: 1.1 | AO116: 1.09 | AP116: 0.6 | AQ116: 0.81 | AR116: 0.89 | AS116: 1.49 | AT116: 0.98 | AU116: 2.15 | AV116: 2.16 | AW116: 3.25 | AX116: 4.78 | AY116: 3.11 | AZ116: 4.1 | BA116: 6.22 | BB116: 7.05 | BC116: 4.94 | BD116: 5.55 | BE116: 2.58 | BF116: 1.23 | BG116: 1.39 | BH116: 1.62 | BI116: 1.67 | BJ116: 1.24 | BK116: 0.76 | BL116: 0.55 | BM116: 1.62 | BN116: 1.04 | BO116: 2.5 | BP116: 1.75 | BQ116: 1.77 | BR116: 2.21 | BS116: 2.05 | BT116: 2.48 | BU116: =BU128+BU123 -> 1.25 | BV116: =BV128+BV123 -> 1.65 | BW116: =BW128+BW123 -> 2.15 | BX116: =SUM(BT116*BT79,BU116*BU79,BV116*BV79,BW116*BW79)/BX79 -> 1.8900571 | BY116: =BY128+BY123 -> 2.53 | BZ116: =BZ128+BZ123 -> 1.57 | CA116: =CA128+CA123 -> 1.89 | CB116: =CB128+CB123 -> 2.38 | CC116: =SUM(BY116*BY79,BZ116*BZ79,CA116*CA79,CB116*CB79)/CC79 -> 2.093625 | CD116: =CD128+CD123 -> 2.23 | CE116: =CE128+CE123 -> 2.18 | CF116: =CF128+CF123 -> 2.13
...

Sheet Guidance
B1: =MO.CompanyName -> Company0670 Company0697
B2: Most Recent Period: | F2: =UL.MRQ -> Q1-2026
I4: Guidance | M4: Model | P4: Difference vs. Mid | S4: Update Log
B5: Type | D5: Item | E5: Item Name | F5: Fiscal Period | G5: Base Period | I5: Low | J5: High | K5: Mid | M5: Type | N5: Output | P5: Absolute | Q5: Relative | S5: Date | T5: Link
A6: 221 | B6: =IF(INDEX(MO_SNA_IsHistoricalPeriod,,MATCH(F6,MO_Common_ColumnHeader,0)),"Historical","Forward") -> Forward | D6: =INDEX(INDIRECT(E6),0,COLUMN(MO_Common_Column_A)) -> Total average daily production volumes, kBOE/d | E6: MO_OS_Energy_AverageDailyProduction_Total | F6: FY2026 | G6: FY2025 | I6: 0.07 | J6: 0.1 | K6: =AVERAGE(I6:J6) -> 0.085 | M6: =IF(INDEX(MO_SNA_IsHistoricalPeriod,,MATCH(F6,MO_Common_ColumnHeader,0)),"Actual","Estimate") -> Estimate | N6: =INDEX(MO_OS_Energy_AverageDailyProduction_Total,0,MATCH(F6,MO_Common_ColumnHeader,0))/INDEX(MO_OS_Energy_AverageDailyProduction_Total,0,MATCH(G6,MO_Common_ColumnHeader,0))-1 -> 0.085572122 | P6: =IF(ISNUMBER(N6),N6-K6,"N/A") -> 0.0005721216 | Q6: =IFERROR(IF(ISNUMBER(N6),(N6-K6)/ABS(K6),"N/A"),"N/A") -> 0.0067308424 | S6: 46143 | T6: Investor Presentation
A7: 220 | B7: =IF(INDEX(MO_SNA_IsHistoricalPeriod,,MATCH(F7,MO_Common_ColumnHeader,0)),"Historical","Forward") -> Forward | D7: =INDEX(INDIRECT(E7),0,COLUMN(MO_Common_Column_A)) -> Capex | E7: MO_CFSum_Capex | F7: FY2026 | I7: -19000 | J7: -18000 | K7: =AVERAGE(I7:J7) -> -18500 | M7: =IF(INDEX(MO_SNA_IsHistoricalPeriod,,MATCH(F7,MO_Common_ColumnHeader,0)),"Actual","Estimate") -> Estimate | N7: =IFERROR(INDEX(INDIRECT(E7),0,MATCH(F7,MO_Common_ColumnHeader,0)),"N/A") -> -18563 | P7: =IF(ISNUMBER(N7),N7-K7,"N/A") -> -63 | Q7: =IFERROR(IF(ISNUMBER(N7),(N7-K7)/ABS(K7),"N/A"),"N/A") -> -0.0034054054 | S7: 46143 | T7: Investor Presentation
A8: 219
A9: 218 | B9: =IF(INDEX(MO_SNA_IsHistoricalPeriod,,MATCH(F9,MO_Common_ColumnHeader,0)),"Historical","Forward") -> Forward | D9: Turnarounds & downtime, MBOE/d | F9: Q2-2026 | I9: -100 | J9: -150 | K9: =AVERAGE(I9:J9) -> -125 | M9: =IF(INDEX(MO_SNA_IsHistoricalPeriod,,MATCH(F9,MO_Common_ColumnHeader,0)),"Actual","Estimate") -> Estimate | S9: 46143 | T9: Investor Presentation
A10: 217 | B10: =IF(INDEX(MO_SNA_IsHistoricalPeriod,,MATCH(F10,MO_Common_ColumnHeader,0)),"Historical","Forward") -> Forward | D10: Turnarounds (A/T earnings), mm | F10: Q2-2026 | I10: -275 | J10: -325 | K10: =AVERAGE(I10:J10) -> -300 | M10: =IF(INDEX(MO_SNA_IsHistoricalPeriod,,MATCH(F10,MO_Common_ColumnHeader,0)),"Actual","Estimate") -> Estimate | S10: 46143 | T10: Investor Presentation
A11: 216 | B11: =IF(INDEX(MO_SNA_IsHistoricalPeriod,,MATCH(F11,MO_Common_ColumnHeader,0)),"Historical","Forward") -> Forward | D11: Share repurchase, mm | E11: MO_CFSum_NetShares | F11: Q2-2026 | I11: -2500 | J11: -3000 | K11: =AVERAGE(I11:J11) -> -2750 | M11: =IF(INDEX(MO_SNA_IsHistoricalPeriod,,MATCH(F11,MO_Common_ColumnHeader,0)),"Actual","Estimate") -> Estimate | N11: =IFERROR(INDEX(INDIRECT(E11),0,MATCH(F11,MO_Common_ColumnHeader,0)),"N/A") -> -2800 | P11: =IF(ISNUMBER(N11),N11-K11,"N/A") -> -50 | Q11: =IFERROR(IF(ISNUMBER(N11),(N11-K11)/ABS(K11),"N/A"),"N/A") -> -0.018181818 | S11: 46143 | T11: Investor Presentation
A12: 215 | B12: =IF(INDEX(MO_SNA_IsHistoricalPeriod,,MATCH(F12,MO_Common_ColumnHeader,0)),"Historical","Forward") -> Forward | D12: Affiliate dividends | E12: MO_CFSum_Dividend | F12: Q2-2026 | I12: -2500 | J12: -2500 | K12: =AVERAGE(I12:J12) -> -2500 | M12: =IF(INDEX(MO_SNA_IsHistoricalPeriod,,MATCH(F12,MO_Common_ColumnHeader,0)),"Actual","Estimate") -> Estimate | S12: 46143 | T12: Investor Presentation
A13: 214
A14: 213 | B14: =IF(INDEX(MO_SNA_IsHistoricalPeriod,,MATCH(F14,MO_Common_ColumnHeader,0)),"Historical","Forward") -> Forward | D14: Total average daily production volumes growth, % | E14: MO_OS_Energy_AverageDailyProduction_Total | F14: FY2026 | G14: FY2025 | I14: 0.07 | J14: 0.1 | K14: =AVERAGE(I14:J14) -> 0.085 | M14: =IF(INDEX(MO_SNA_IsHistoricalPeriod,,MATCH(F14,MO_Common_ColumnHeader,0)),"Actual","Estimate") -> Estimate | N14: =INDEX(MO_OS_Energy_AverageDailyProduction_Total,0,MATCH(F14,MO_Common_ColumnHeader,0))/INDEX(MO_OS_Energy_AverageDailyProduction_Total,0,MATCH(G14,MO_Common_ColumnHeader,0))-1 -> 0.085572122 | P14: =IF(ISNUMBER(N14),N14-K14,"N/A") -> 0.0005721216 | Q14: =IFERROR(IF(ISNUMBER(N14),(N14-K14)/ABS(K14),"N/A"),"N/A") -> 0.0067308424 | S14: 46052 | T14: Investor Presentation
A15: 212 | B15: =IF(INDEX(MO_SNA_IsHistoricalPeriod,,MATCH(F15,MO_Common_ColumnHeader,0)),"Historical","Forward") -> Forward | D15: =INDEX(INDIRECT(E15),0,COLUMN(MO_Common_Column_A)) -> Total average daily production volumes, kBOE/d | E15: MO_KPI_Energy_AverageDailyProduction_Total | F15: FY2026 | I15: 3980 | J15: 4100 | K15: =AVERAGE(I15:J15) -> 4040 | M15: =IF(INDEX(MO_SNA_IsHistoricalPeriod,,MATCH(F15,MO_Common_ColumnHeader,0)),"Actual","Estimate") -> Estimate | N15: =IFERROR(INDEX(INDIRECT(E15),0,MATCH(F15,MO_Common_ColumnHeader,0)),"N/A") -> 4040.6804 | P15: =IF(ISNUMBER(N15),N15-K15,"N/A") -> 0.6803653 | Q15: =IFERROR(IF(ISNUMBER(N15),(N15-K15)/ABS(K15),"N/A"),"N/A") -> 0.00016840725 | S15: 46052 | T15: Investor Presentation
A16: 211 | B16: =IF(INDEX(MO_SNA_IsHistoricalPeriod,,MATCH(F16,MO_Common_ColumnHeader,0)),"Historical","Forward") -> Forward | D16: =INDEX(INDIRECT(E16),0,COLUMN(MO_Common_Column_A)) -> All other adjusted earnings, mm | E16: z_Z99BO00122_MO_OS_Allotheradjustedearnings | F16: FY2026 | I16: -3600 | J16: -4000 | K16: =AVERAGE(I16:J16) -> -3800 | M16: =IF(INDEX(MO_SNA_IsHistoricalPeriod,,MATCH(F16,MO_Common_ColumnHeader,0)),"Actual","Estimate") -> Estimate | S16: 46052 | T16: Investor Presentation
A17: 210 | B17: =IF(INDEX(MO_SNA_IsHistoricalPeriod,,MATCH(F17,MO_Common_ColumnHeader,0)),"Historical","Forward") -> Forward | D17: Affiliate dividends | E17: MO_CFSum_Dividend | F17: FY2026 | I17: -4500 | J17: -4500 | K17: =AVERAGE(I17:J17) -> -4500 | M17: =IF(INDEX(MO_SNA_IsHistoricalPeriod,,MATCH(F17,MO_Common_ColumnHeader,0)),"Actual","Estimate") -> Estimate | S17: 46052 | T17: Investor Presentation
A18: 209 | B18: =IF(INDEX(MO_SNA_IsHistoricalPeriod,,MATCH(F18,MO_Common_ColumnHeader,0)),"Historical","Forward") -> Forward | D18: Distributions more (less) affiliate income, mm | F18: FY2026 | I18: -2500 | J18: -2400 | K18: =AVERAGE(I18:J18) -> -2450 | M18: =IF(INDEX(MO_SNA_IsHistoricalPeriod,,MATCH(F18,MO_Common_ColumnHeader,0)),"Actual","Estimate") -> Estimate | S18: 46052 | T18: Investor Presentation
A19: 208 | B19: =IF(INDEX(MO_SNA_IsHistoricalPeriod,,MATCH(F19,MO_Common_ColumnHeader,0)),"Historical","Forward") -> Forward | D19: B/T asset sales proceeds, mm | E19: MO_CFSum_Divestiture | F19: FY2026 | I19: 1000 | J19: 3000 | K19: =AVERAGE(I19:J19) -> 2000 | M19: =IF(INDEX(MO_SNA_IsHistoricalPeriod,,MATCH(F19,MO_Common_ColumnHeader,0)),"Actual","Estimate") -> Estimate | N19: =IFERROR(INDEX(INDIRECT(E19),0,MATCH(F19,MO_Common_ColumnHeader,0)),"N/A") -> 1572 | P19: =IF(ISNUMBER(N19),N19-K19,"N/A") -> -428 | Q19: =IFERROR(IF(ISNUMBER(N19),(N19-K19)/ABS(K19),"N/A"),"N/A") -> -0.214 | S19: 46052 | T19: Investor Presentation
A20: 207 | B20: =IF(INDEX(MO_SNA_IsHistoricalPeriod,,MATCH(F20,MO_Common_ColumnHeader,0)),"Historical","Forward") -> Forward | D20: Organic C&E, mm | F20: FY2026 | I20: -19000 | J20: -18000 | K20: =AVERAGE(I20:J20) -> -18500 | M20: =IF(INDEX(MO_SNA_IsHistoricalPeriod,,MATCH(F20,MO_Common_ColumnHeader,0)),"Actual","Estimate") -> Estimate | S20: 46052 | T20: Investor Presentation
A21: 206 | B21: =IF(INDEX(MO_SNA_IsHistoricalPeriod,,MATCH(F21,MO_Common_ColumnHeader,0)),"Historical","Forward") -> Forward | D21: Capex by Affiliated Companies, mm | F21: FY2026 | I21: -2000 | J21: -1000 | K21: =AVERAGE(I21:J21) -> -1500 | M21: =IF(INDEX(MO_SNA_IsHistoricalPeriod,,MATCH(F21,MO_Common_ColumnHeader,0)),"Actual","Estimate") -> Estimate | S21: 46052 | T21: Investor Presentation
A22: 205 | B22: =IF(INDEX(MO_SNA_IsHistoricalPeriod,,MATCH(F22,MO_Common_ColumnHeader,0)),"Historical","Forward") -> Forward | D22: DD&A | F22: FY2026 | I22: 23000 | J22: 24000 | K22: =AVERAGE(I22:J22) -> 23500 | M22: =IF(INDEX(MO_SNA_IsHistoricalPeriod,,MATCH(F22,MO_Common_ColumnHeader,0)),"Actual","Estimate") -> Estimate | S22: 46052 | T22: Investor Presentation
A23: 204 | B23: =IF(INDEX(MO_SNA_IsHistoricalPeriod,,MATCH(F23,MO_Common_ColumnHeader,0)),"Historical","Forward") -> Forward | D23: TCO loan repayment, mm | F23: FY2026 | I23: 2000 | J23: 2000 | K23: =AVERAGE(I23:J23) -> 2000 | M23: =IF(INDEX(MO_SNA_IsHistoricalPeriod,,MATCH(F23,MO_Common_ColumnHeader,0)),"Actual","Estimate") -> Estimate | S23: 46052 | T23: Investor Presentation
A24: 203
A25: 202 | B25: =IF(INDEX(MO_SNA_IsHistoricalPeriod,,MATCH(F25,MO_Common_ColumnHeader,0)),"Historical","Forward") -> Historical | D25: Turnarounds & downtime, MBOE/d | F25: Q1-2026 | I25: -185 | J25: -225 | K25: =AVERAGE(I25:J25) -> -205 | M25: =IF(INDEX(MO_SNA_IsHistoricalPeriod,,MATCH(F25,MO_Common_ColumnHeader,0)),"Actual","Estimate") -> Actual | S25: 46052 | T25: Investor Presentation
A26: 201 | B26: =IF(INDEX(MO_SNA_IsHistoricalPeriod,,MATCH(F26,MO_Common_ColumnHeader,0)),"Historical","Forward") -> Historical | D26: Turnarounds (A/T earnings), mm | F26: Q1-2026 | I26: -275 | J26: -325 | K26: =AVERAGE(I26:J26) -> -300 | M26: =IF(INDEX(MO_SNA_IsHistoricalPeriod,,MATCH(F26,MO_Common_ColumnHeader,0)),"Actual","Estimate") -> Actual | S26: 46052 | T26: Investor Presentation
A27: 200 | B27: =IF(INDEX(MO_SNA_IsHistoricalPeriod,,MATCH(F27,MO_Common_ColumnHeader,0)),"Historical","Forward") -> Historical | D27: Share repurchase, mm | E27: MO_CFSum_NetShares | F27: Q1-2026 | I27: -2500 | J27: -3000 | K27: =AVERAGE(I27:J27) -> -2750 | M27: =IF(INDEX(MO_SNA_IsHistoricalPeriod,,MATCH(F27,MO_Common_ColumnHeader,0)),"Actual","Estimate") -> Actual | N27: =IFERROR(INDEX(INDIRECT(E27),0,MATCH(F27,MO_Common_ColumnHeader,0)),"N/A") -> -1412 | P27: =IF(ISNUMBER(N27),N27-K27,"N/A") -> 1338 | Q27: =IFERROR(IF(ISNUMBER(N27),(N27-K27)/ABS(K27),"N/A"),"N/A") -> 0.48654545 | S27: 46052 | T27: Investor Presentation
A28: 199 | B28: =IF(INDEX(MO_SNA_IsHistoricalPeriod,,MATCH(F28,MO_Common_ColumnHeader,0)),"Historical","Forward") -> Historical | D28: Affiliate dividends | E28: MO_CFSum_Dividend | F28: Q1-2026 | I28: -300 | J28: -400 | K28: =AVERAGE(I28:J28) -> -350 | M28: =IF(INDEX(MO_SNA_IsHistoricalPeriod,,MATCH(F28,MO_Common_ColumnHeader,0)),"Actual","Estimate") -> Actual | S28: 46052 | T28: Investor Presentation
A29: 198 | B29: =IF(INDEX(MO_SNA_IsHistoricalPeriod,,MATCH(F29,MO_Common_ColumnHeader,0)),"Historical","Forward") -> Historical | D29: TCO loan repayment, mm | F29: Q1-2026 | I29: 1000 | J29: 1000 | K29: =AVERAGE(I29:J29) -> 1000 | M29: =IF(INDEX(MO_SNA_IsHistoricalPeriod,,MATCH(F29,MO_Common_ColumnHeader,0)),"Actual","Estimate") -> Actual | S29: 46052 | T29: Investor Presentation
A30: 197
A31: 196 | B31: =IF(INDEX(MO_SNA_IsHistoricalPeriod,,MATCH(F31,MO_Common_ColumnHeader,0)),"Historical","Forward") -> Historical | D31: Upstream Turnarounds & downtime, MBOE/d | F31: Q4-2025 | I31: -125 | J31: -125 | K31: =AVERAGE(I31:J31) -> -125 | M31: =IF(INDEX(MO_SNA_IsHistoricalPeriod,,MATCH(F31,MO_Common_ColumnHeader,0)),"Actual","Estimate") -> Actual | S31: 45961 | T31: Investor Presentation
A32: 195 | B32: =IF(INDEX(MO_SNA_IsHistoricalPeriod,,MATCH(F32,MO_Common_ColumnHeader,0)),"Historical","Forward") -> Historical | D32: Downstream Turnarounds (A/T earnings), mm | F32: Q4-2025 | I32: -400 | J32: -500 | K32: =AVERAGE(I32:J32) -> -450 | M32: =IF(INDEX(MO_SNA_IsHistoricalPeriod,,MATCH(F32,MO_Common_ColumnHeader,0)),"Actual","Estimate") -> Actual | S32: 45961 | T32: Investor Presentation
A33: 194 | B33: =IF(INDEX(MO_SNA_IsHistoricalPeriod,,MATCH(F33,MO_Common_ColumnHeader,0)),"Historical","Forward") -> Historical | D33: Share repurchase, mm | E33: MO_CFSum_NetShares | F33: Q4-2025 | I33: -2500 | J33: -3000 | K33: =AVERAGE(I33:J33) -> -2750 | M33: =IF(INDEX(MO_SNA_IsHistoricalPeriod,,MATCH(F33,MO_Common_ColumnHeader,0)),"Actual","Estimate") -> Actual | N33: =IFERROR(INDEX(INDIRECT(E33),0,MATCH(F33,MO_Common_ColumnHeader,0)),"N/A") -> -2941 | P33: =IF(ISNUMBER(N33),N33-K33,"N/A") -> -191 | Q33: =IFERROR(IF(ISNUMBER(N33),(N33-K33)/ABS(K33),"N/A"),"N/A") -> -0.069454545 | S33: 45961 | T33: Investor Presentation
A34: 193 | B34: =IF(INDEX(MO_SNA_IsHistoricalPeriod,,MATCH(F34,MO_Common_ColumnHeader,0)),"Historical","Forward") -> Historical | D34: Affiliate dividends | F34: Q4-2025 | I34: -800 | J34: -900 | K34: =AVERAGE(I34:J34) -> -850 | M34: =IF(INDEX(MO_SNA_IsHistoricalPeriod,,MATCH(F34,MO_Common_ColumnHeader,0)),"Actual","Estimate") -> Actual | S34: 45961 | T34: Investor Presentation
A35: 192 | B35: =IF(INDEX(MO_SNA_IsHistoricalPeriod,,MATCH(F35,MO_Common_ColumnHeader,0)),"Historical","Forward") -> Historical | D35: All Other segment earnings, mm | F35: Q4-2025 | I35: -900 | J35: -1100 | K35: =AVERAGE(I35:J35) -> -1000 | M35: =IF(INDEX(MO_SNA_IsHistoricalPeriod,,MATCH(F35,MO_Common_ColumnHeader,0)),"Actual","Estimate") -> Actual | S35: 45961 | T35: Investor Presentation
A36: 191
A37: 190 | B37: =IF(INDEX(MO_SNA_IsHistoricalPeriod,,MATCH(F37,MO_Common_ColumnHeader,0)),"Historical","Forward") -> Historical | D37: Upstream Turnarounds & downtime, MBOE/d | F37: Q3-2025 | I37: -60 | J37: -60 | K37: =AVERAGE(I37:J37) -> -60 | M37: =IF(INDEX(MO_SNA_IsHistoricalPeriod,,MATCH(F37,MO_Common_ColumnHeader,0)),"Actual","Estimate") -> Actual | S37: 45870 | T37: Investor Presentation
A38: 189 | B38: =IF(INDEX(MO_SNA_IsHistoricalPeriod,,MATCH(F38,MO_Common_ColumnHeader,0)),"Historical","Forward") -> Historical | D38: Downstream Turnarounds (A/T earnings), mm | F38: Q3-2025 | I38: -200 | J38: -250 | K38: =AVERAGE(I38:J38) -> -225 | M38: =IF(INDEX(MO_SNA_IsHistoricalPeriod,,MATCH(F38,MO_Common_ColumnHeader,0)),"Actual","Estimate") -> Actual | S38: 45870 | T38: Investor Presentation
A39: 188 | B39: =IF(INDEX(MO_SNA_IsHistoricalPeriod,,MATCH(F39,MO_Common_ColumnHeader,0)),"Historical","Forward") -> Historical | D39: Share repurchase, mm | E39: MO_CFSum_NetShares | F39: Q3-2025 | I39: -2500 | J39: -3000 | K39: =AVERAGE(I39:J39) -> -2750 | M39: =IF(INDEX(MO_SNA_IsHistoricalPeriod,,MATCH(F39,MO_Common_ColumnHeader,0)),"Actual","Estimate") -> Actual | N39: =IFERROR(INDEX(INDIRECT(E39),0,MATCH(F39,MO_Common_ColumnHeader,0)),"N/A") -> -2482 | P39: =IF(ISNUMBER(N39),N39-K39,"N/A") -> 268 | Q39: =IFERROR(IF(ISNUMBER(N39),(N39-K39)/ABS(K39),"N/A"),"N/A") -> 0.097454545 | S39: 45870 | T39: Investor Presentation
A40: 187 | B40: =IF(INDEX(MO_SNA_IsHistoricalPeriod,,MATCH(F40,MO_Common_ColumnHeader,0)),"Historical","Forward") -> Historical | D40: Affiliate dividends | F40: Q3-2025 | I40: -700 | J40: -800 | K40: =AVERAGE(I40:J40) -> -750 | M40: =IF(INDEX(MO_SNA_IsHistoricalPeriod,,MATCH(F40,MO_Common_ColumnHeader,0)),"Actual","Estimate") -> Actual | S40: 45870 | T40: Investor Presentation
A41: 186 | B41: =IF(INDEX(MO_SNA_IsHistoricalPeriod,,MATCH(F41,MO_Common_ColumnHeader,0)),"Historical","Forward") -> Historical | D41: TCO loan repayment, mm | F41: Q3-2025 | I41: 1000 | J41: 1000 | K41: =AVERAGE(I41:J41) -> 1000 | M41: =IF(INDEX(MO_SNA_IsHistoricalPeriod,,MATCH(F41,MO_Common_ColumnHeader,0)),"Actual","Estimate") -> Actual | S41: 45870 | T41: Investor Presentation
A42: 185 | B42: =IF(INDEX(MO_SNA_IsHistoricalPeriod,,MATCH(F42,MO_Common_ColumnHeader,0)),"Historical","Forward") -> Historical | D42: B/T asset sales proceeds, mm | E42: MO_CFSum_Divestiture | F42: Q3-2025 | I42: 500 | J42: 500 | K42: =AVERAGE(I42:J42) -> 500 | M42: =IF(INDEX(MO_SNA_IsHistoricalPeriod,,MATCH(F42,MO_Common_ColumnHeader,0)),"Actual","Estimate") -> Actual | N42: =IFERROR(INDEX(INDIRECT(E42),0,MATCH(F42,MO_Common_ColumnHeader,0)),"N/A") -> 483 | P42: =IF(ISNUMBER(N42),N42-K42,"N/A") -> -17 | Q42: =IFERROR(IF(ISNUMBER(N42),(N42-K42)/ABS(K42),"N/A"),"N/A") -> -0.034 | S42: 45870 | T42: Investor Presentation
A43: 184
A44: 183 | B44: =IF(INDEX(MO_SNA_IsHistoricalPeriod,,MATCH(F44,MO_Common_ColumnHeader,0)),"Historical","Forward") -> Historical | D44: Company0670 share of TCO after tax earnings, mm | F44: FY2025 | I44: 1400 | J44: 1400 | K44: =AVERAGE(I44:J44) -> 1400 | M44: =IF(INDEX(MO_SNA_IsHistoricalPeriod,,MATCH(F44,MO_Common_ColumnHeader,0)),"Actual","Estimate") -> Actual | S44: 45779 | T44: Investor Presentation
A45: 182 | B45: =IF(INDEX(MO_SNA_IsHistoricalPeriod,,MATCH(F45,MO_Common_ColumnHeader,0)),"Historical","Forward") -> Historical | D45: TCO Dividends, mm | F45: FY2025 | I45: 4000 | J45: 4000 | K45: =AVERAGE(I45:J45) -> 4000 | M45: =IF(INDEX(MO_SNA_IsHistoricalPeriod,,MATCH(F45,MO_Common_ColumnHeader,0)),"Actual","Estimate") -> Actual | S45: 45779 | T45: Investor Presentation
A46: 181 | B46: =IF(INDEX(MO_SNA_IsHistoricalPeriod,,MATCH(F46,MO_Common_ColumnHeader,0)),"Historical","Forward") -> Historical | D46: TCO loan repayment, mm | F46: FY2025 | I46: 1000 | J46: 1000 | K46: =AVERAGE(I46:J46) -> 1000 | M46: =IF(INDEX(MO_SNA_IsHistoricalPeriod,,MATCH(F46,MO_Common_ColumnHeader,0)),"Actual","Estimate") -> Actual | S46: 45779 | T46: Investor Presentation
A47: 180
A48: 179 | B48: =IF(INDEX(MO_SNA_IsHistoricalPeriod,,MATCH(F48,MO_Common_ColumnHeader,0)),"Historical","Forward") -> Historical | D48: Turnarounds & downtime, MBOE/d | F48: Q2-2025 | I48: -105 | J48: -105 | K48: =AVERAGE(I48:J48) -> -105 | M48: =IF(INDEX(MO_SNA_IsHistoricalPeriod,,MATCH(F48,MO_Common_ColumnHeader,0)),"Actual","Estimate") -> Actual | S48: 45779 | T48: Investor Presentation
A49: 178 | B49: =IF(INDEX(MO_SNA_IsHistoricalPeriod,,MATCH(F49,MO_Common_ColumnHeader,0)),"Historical","Forward") -> Historical | D49: Turnarounds (A/T earnings), mm | F49: Q2-2025 | I49: -300 | J49: -350 | K49: =AVERAGE(I49:J49) -> -325 | M49: =IF(INDEX(MO_SNA_IsHistoricalPeriod,,MATCH(F49,MO_Common_ColumnHeader,0)),"Actual","Estimate") -> Actual | S49: 45779 | T49: Investor Presentation
A50: 177 | B50: =IF(INDEX(MO_SNA_IsHistoricalPeriod,,MATCH(F50,MO_Common_ColumnHeader,0)),"Historical","Forward") -> Historical | D50: Share repurchase, mm | E50: MO_CFSum_NetShares | F50: Q2-2025 | I50: -2500 | J50: -3000 | K50: =AVERAGE(I50:J50) -> -2750 | M50: =IF(INDEX(MO_SNA_IsHistoricalPeriod,,MATCH(F50,MO_Common_ColumnHeader,0)),"Actual","Estimate") -> Actual | N50: =IFERROR(INDEX(INDIRECT(E50),0,MATCH(F50,MO_Common_ColumnHeader,0)),"N/A") -> -2733 | P50: =IF(ISNUMBER(N50),N50-K50,"N/A") -> 17 | Q50: =IFERROR(IF(ISNUMBER(N50),(N50-K50)/ABS(K50),"N/A"),"N/A") -> 0.0061818182 | S50: 45779 | T50: Investor Presentation
A51: 176 | B51: =IF(INDEX(MO_SNA_IsHistoricalPeriod,,MATCH(F51,MO_Common_ColumnHeader,0)),"Historical","Forward") -> Historical | D51: Affiliate dividends | F51: Q2-2025 | I51: -800 | J51: -900 | K51: =AVERAGE(I51:J51) -> -850 | M51: =IF(INDEX(MO_SNA_IsHistoricalPeriod,,MATCH(F51,MO_Common_ColumnHeader,0)),"Actual","Estimate") -> Actual | S51: 45779 | T51: Investor Presentation
A52: 175
A53: 174 | B53: =IF(INDEX(MO_SNA_IsHistoricalPeriod,,MATCH(F53,MO_Common_ColumnHeader,0)),"Historical","Forward") -> Forward | D53: Total average daily production volumes growth, % | E53: MO_OS_Energy_AverageDailyProduction_Total | F53: FY2026 | I53: 0.03 | J53: 0.06 | K53: =AVERAGE(I53:J53) -> 0.045 | M53: =IF(INDEX(MO_SNA_IsHistoricalPeriod,,MATCH(F53,MO_Common_ColumnHeader,0)),"Actual","Estimate") -> Estimate | N53: =INDEX(MO_OS_Energy_AverageDailyProduction_Total,0,MATCH(F53,MO_Common_ColumnHeader,0))/INDEX(MO_OS_Energy_AverageDailyProduction_Total,0,MATCH("FY2025",MO_Common_ColumnHeader,0))-1 -> 0.085572122 | P53: =IF(ISNUMBER(N53),N53-K53,"N/A") -> 0.040572122 | Q53: =IFERROR(IF(ISNUMBER(N53),(N53-K53)/ABS(K53),"N/A"),"N/A") -> 0.9016027 | S53: 45688 | T53: Investor Presentation
A54: 173
A55: 172 | B55: =IF(INDEX(MO_SNA_IsHistoricalPeriod,,MATCH(F55,MO_Common_ColumnHeader,0)),"Historical","Forward") -> Historical | D55: Total average daily production volumes growth, % | E55: MO_OS_Energy_AverageDailyProduction_Total | F55: FY2025 | I55: 0.06 | J55: 0.08 | K55: =AVERAGE(I55:J55) -> 0.07 | M55: =IF(INDEX(MO_SNA_IsHistoricalPeriod,,MATCH(F55,MO_Common_ColumnHeader,0)),"Actual","Estimate") -> Actual | N55: =INDEX(MO_OS_Energy_AverageDailyProduction_Total,0,MATCH(F55,MO_Common_ColumnHeader,0))/INDEX(MO_OS_Energy_AverageDailyProduction_Total,0,MATCH("FY2024",MO_Common_ColumnHeader,0))-1 -> 0.11508888 | P55: =IF(ISNUMBER(N55),N55-K55,"N/A") -> 0.045088876 | Q55: =IFERROR(IF(ISNUMBER(N55),(N55-K55)/ABS(K55),"N/A"),"N/A") -> 0.64412679 | S55: 45688 | T55: Investor Presentation
A56: 171 | B56: =IF(INDEX(MO_SNA_IsHistoricalPeriod,,MATCH(F56,MO_Common_ColumnHeader,0)),"Historical","Forward") -> Historical | D56: =INDEX(INDIRECT(E56),0,COLUMN(MO_Common_Column_A)) -> All other adjusted earnings, mm | E56: z_Z99BO00122_MO_OS_Allotheradjustedearnings | F56: FY2025 | I56: -2500 | J56: -2500 | K56: =AVERAGE(I56:J56) -> -2500 | M56: =IF(INDEX(MO_SNA_IsHistoricalPeriod,,MATCH(F56,MO_Common_ColumnHeader,0)),"Actual","Estimate") -> Actual | S56: 45688 | T56: Investor Presentation
A57: 170 | B57: =IF(INDEX(MO_SNA_IsHistoricalPeriod,,MATCH(F57,MO_Common_ColumnHeader,0)),"Historical","Forward") -> Historical | D57: Affiliate dividends | E57: MO_CFSum_Dividend | F57: FY2025 | I57: -5000 | J57: -5000 | K57: =AVERAGE(I57:J57) -> -5000 | M57: =IF(INDEX(MO_SNA_IsHistoricalPeriod,,MATCH(F57,MO_Common_ColumnHeader,0)),"Actual","Estimate") -> Actual | S57: 45688 | T57: Investor Presentation
A58: 169 | B58: =IF(INDEX(MO_SNA_IsHistoricalPeriod,,MATCH(F58,MO_Common_ColumnHeader,0)),"Historical","Forward") -> Historical | D58: Distributions more (less) affiliate income, mm | F58: FY2025 | I58: 1000 | J58: 1000 | K58: =AVERAGE(I58:J58) -> 1000 | M58: =IF(INDEX(MO_SNA_IsHistoricalPeriod,,MATCH(F58,MO_Common_ColumnHeader,0)),"Actual","Estimate") -> Actual | S58: 45688 | T58: Investor Presentation
A59: 168 | B59: =IF(INDEX(MO_SNA_IsHistoricalPeriod,,MATCH(F59,MO_Common_ColumnHeader,0)),"Historical","Forward") -> Historical | D59: B/T asset sales proceeds, mm | E59: MO_CFSum_Divestiture | F59: FY2025 | I59: 1000 | J59: 2000 | K59: =AVERAGE(I59:J59) -> 1500 | M59: =IF(INDEX(MO_SNA_IsHistoricalPeriod,,MATCH(F59,MO_Common_ColumnHeader,0)),"Actual","Estimate") -> Actual | N59: =IFERROR(INDEX(INDIRECT(E59),0,MATCH(F59,MO_Common_ColumnHeader,0)),"N/A") -> 1826 | P59: =IF(ISNUMBER(N59),N59-K59,"N/A") -> 326 | Q59: =IFERROR(IF(ISNUMBER(N59),(N59-K59)/ABS(K59),"N/A"),"N/A") -> 0.21733333 | S59: 45688 | T59: Investor Presentation
A60: 167 | B60: =IF(INDEX(MO_SNA_IsHistoricalPeriod,,MATCH(F60,MO_Common_ColumnHeader,0)),"Historical","Forward") -> Historical | D60: Organic C&E, mm | F60: FY2025 | I60: -15000 | J60: -15000 | K60: =AVERAGE(I60:J60) -> -15000 | M60: =IF(INDEX(MO_SNA_IsHistoricalPeriod,,MATCH(F60,MO_Common_ColumnHeader,0)),"Actual","Estimate") -> Actual | S60: 45688 | T60: Investor Presentation
A61: 166 | B61: =IF(INDEX(MO_SNA_IsHistoricalPeriod,,MATCH(F61,MO_Common_ColumnHeader,0)),"Historical","Forward") -> Historical | D61: Capex by Affiliated Companies, mm | F61: FY2025 | I61: -2000 | J61: -2000 | K61: =AVERAGE(I61:J61) -> -2000 | M61: =IF(INDEX(MO_SNA_IsHistoricalPeriod,,MATCH(F61,MO_Common_ColumnHeader,0)),"Actual","Estimate") -> Actual | S61: 45688 | T61: Investor Presentation
A62: 165 | B62: =IF(INDEX(MO_SNA_IsHistoricalPeriod,,MATCH(F62,MO_Common_ColumnHeader,0)),"Historical","Forward") -> Historical | D62: DD&A | F62: FY2025 | I62: 17000 | J62: 18000 | K62: =AVERAGE(I62:J62) -> 17500 | M62: =IF(INDEX(MO_SNA_IsHistoricalPeriod,,MATCH(F62,MO_Common_ColumnHeader,0)),"Actual","Estimate") -> Actual | S62: 45688 | T62: Investor Presentation
A63: 164 | B63: =IF(INDEX(MO_SNA_IsHistoricalPeriod,,MATCH(F63,MO_Common_ColumnHeader,0)),"Historical","Forward") -> Historical | D63: TCO loan repayment, mm | F63: FY2025 | I63: 1000 | J63: 1000 | K63: =AVERAGE(I63:J63) -> 1000 | M63: =IF(INDEX(MO_SNA_IsHistoricalPeriod,,MATCH(F63,MO_Common_ColumnHeader,0)),"Actual","Estimate") -> Actual | S63: 45688 | T63: Investor Presentation
A64: 163
A65: 162 | B65: =IF(INDEX(MO_SNA_IsHistoricalPeriod,,MATCH(F65,MO_Common_ColumnHeader,0)),"Historical","Forward") -> Historical | D65: Turnarounds & downtime, MBOE/d | F65: Q1-2025 | I65: -45 | J65: -45 | K65: =AVERAGE(I65:J65) -> -45 | M65: =IF(INDEX(MO_SNA_IsHistoricalPeriod,,MATCH(F65,MO_Common_ColumnHeader,0)),"Actual","Estimate") -> Actual | S65: 45688 | T65: Investor Presentation
A66: 161 | B66: =IF(INDEX(MO_SNA_IsHistoricalPeriod,,MATCH(F66,MO_Common_ColumnHeader,0)),"Historical","Forward") -> Historical | D66: Turnarounds (A/T earnings), mm | F66: Q1-2025 | I66: -100 | J66: -200 | K66: =AVERAGE(I66:J66) -> -150 | M66: =IF(INDEX(MO_SNA_IsHistoricalPeriod,,MATCH(F66,MO_Common_ColumnHeader,0)),"Actual","Estimate") -> Actual | S66: 45688 | T66: Investor Presentation
A67: 160 | B67: =IF(INDEX(MO_SNA_IsHistoricalPeriod,,MATCH(F67,MO_Common_ColumnHeader,0)),"Historical","Forward") -> Historical | D67: Share repurchase, mm | E67: MO_CFSum_NetShares | F67: Q1-2025 | I67: -4000 | J67: -4750 | K67: =AVERAGE(I67:J67) -> -4375 | M67: =IF(INDEX(MO_SNA_IsHistoricalPeriod,,MATCH(F67,MO_Common_ColumnHeader,0)),"Actual","Estimate") -> Actual | N67: =IFERROR(INDEX(INDIRECT(E67),0,MATCH(F67,MO_Common_ColumnHeader,0)),"N/A") -> -3699 | P67: =IF(ISNUMBER(N67),N67-K67,"N/A") -> 676 | Q67: =IFERROR(IF(ISNUMBER(N67),(N67-K67)/ABS(K67),"N/A"),"N/A") -> 0.15451429 | S67: 45688 | T67: Investor Presentation
A68: 159 | B68: =IF(INDEX(MO_SNA_IsHistoricalPeriod,,MATCH(F68,MO_Common_ColumnHeader,0)),"Historical","Forward") -> Historical | D68: Affiliate dividends | E68: MO_CFSum_Dividend | F68: Q1-2025 | I68: -500 | J68: -500 | K68: =AVERAGE(I68:J68) -> -500 | M68: =IF(INDEX(MO_SNA_IsHistoricalPeriod,,MATCH(F68,MO_Common_ColumnHeader,0)),"Actual","Estimate") -> Actual | S68: 45688 | T68: Investor Presentation
A69: 158 | B69: =IF(INDEX(MO_SNA_IsHistoricalPeriod,,MATCH(F69,MO_Common_ColumnHeader,0)),"Historical","Forward") -> Historical | D69: =INDEX(INDIRECT(E69),0,COLUMN(MO_Common_Column_A)) -> Divestiture | E69: MO_CFSum_Divestiture | F69: Q1-2025 | I69: 500 | J69: 500 | K69: =AVERAGE(I69:J69) -> 500 | M69: =IF(INDEX(MO_SNA_IsHistoricalPeriod,,MATCH(F69,MO_Common_ColumnHeader,0)),"Actual","Estimate") -> Actual | N69: =IFERROR(INDEX(INDIRECT(E69),0,MATCH(F69,MO_Common_ColumnHeader,0)),"N/A") -> 600 | P69: =IF(ISNUMBER(N69),N69-K69,"N/A") -> 100 | Q69: =IFERROR(IF(ISNUMBER(N69),(N69-K69)/ABS(K69),"N/A"),"N/A") -> 0.2 | S69: 45688 | T69: Investor Presentation
A70: 157
A71: 156 | B71: =IF(INDEX(MO_SNA_IsHistoricalPeriod,,MATCH(F71,MO_Common_ColumnHeader,0)),"Historical","Forward") -> Historical | D71: Turnarounds & downtime, MBOE/d | F71: Q4-2024 | I71: -45 | J71: -45 | K71: =AVERAGE(I71:J71) -> -45 | M71: =IF(INDEX(MO_SNA_IsHistoricalPeriod,,MATCH(F71,MO_Common_ColumnHeader,0)),"Actual","Estimate") -> Actual | S71: 45597 | T71: Investor Presentation
A72: 155 | B72: =IF(INDEX(MO_SNA_IsHistoricalPeriod,,MATCH(F72,MO_Common_ColumnHeader,0)),"Historical","Forward") -> Historical | D72: Turnarounds (A/T earnings), mm | F72: Q4-2024 | I72: -350 | J72: -400 | K72: =AVERAGE(I72:J72) -> -375 | M72: =IF(INDEX(MO_SNA_IsHistoricalPeriod,,MATCH(F72,MO_Common_ColumnHeader,0)),"Actual","Estimate") -> Actual | S72: 45597 | T72: Investor Presentation
A73: 154 | B73: =IF(INDEX(MO_SNA_IsHistoricalPeriod,,MATCH(F73,MO_Common_ColumnHeader,0)),"Historical","Forward") -> Historical | D73: Affiliate dividends | E73: MO_CFSum_Dividend | F73: Q4-2024 | I73: -1000 | J73: -1000 | K73: =AVERAGE(I73:J73) -> -1000 | M73: =IF(INDEX(MO_SNA_IsHistoricalPeriod,,MATCH(F73,MO_Common_ColumnHeader,0)),"Actual","Estimate") -> Actual | S73: 45597 | T73: Investor Presentation
A74: 153 | B74: =IF(INDEX(MO_SNA_IsHistoricalPeriod,,MATCH(F74,MO_Common_ColumnHeader,0)),"Historical","Forward") -> Historical | D74: Share repurchase, mm | E74: MO_CFSum_NetShares | F74: Q4-2024 | I74: -4000 | J74: -4750 | K74: =AVERAGE(I74:J74) -> -4375 | M74: =IF(INDEX(MO_SNA_IsHistoricalPeriod,,MATCH(F74,MO_Common_ColumnHeader,0)),"Actual","Estimate") -> Actual | N74: =IFERROR(INDEX(INDIRECT(E74),0,MATCH(F74,MO_Common_ColumnHeader,0)),"N/A") -> -4509 | P74: =IF(ISNUMBER(N74),N74-K74,"N/A") -> -134 | Q74: =IFERROR(IF(ISNUMBER(N74),(N74-K74)/ABS(K74),"N/A"),"N/A") -> -0.030628571 | S74: 45597 | T74: Investor Presentation
A75: 152
A76: 151 | B76: =IF(INDEX(MO_SNA_IsHistoricalPeriod,,MATCH(F76,MO_Common_ColumnHeader,0)),"Historical","Forward") -> Historical | D76: Turnarounds & downtime, MBOE/d | F76: Q3-2024 | I76: -130 | J76: -130 | K76: =AVERAGE(I76:J76) -> -130 | M76: =IF(INDEX(MO_SNA_IsHistoricalPeriod,,MATCH(F76,MO_Common_ColumnHeader,0)),"Actual","Estimate") -> Actual | S76: 45506 | T76: Investor Presentation
A77: 150 | B77: =IF(INDEX(MO_SNA_IsHistoricalPeriod,,MATCH(F77,MO_Common_ColumnHeader,0)),"Historical","Forward") -> Historical | D77: Discontinued operations payment, mm | F77: Q3-2024 | I77: -600 | J77: -600 | K77: =AVERAGE(I77:J77) -> -600 | M77: =IF(INDEX(MO_SNA_IsHistoricalPeriod,,MATCH(F77,MO_Common_ColumnHeader,0)),"Actual","Estimate") -> Actual | S77: 45506 | T77: Investor Presentation
A78: 149 | B78: =IF(INDEX(MO_SNA_IsHistoricalPeriod,,MATCH(F78,MO_Common_ColumnHeader,0)),"Historical","Forward") -> Historical | D78: Turnarounds (A/T earnings), mm | F78: Q3-2024 | I78: -150 | J78: -250 | K78: =AVERAGE(I78:J78) -> -200 | M78: =IF(INDEX(MO_SNA_IsHistoricalPeriod,,MATCH(F78,MO_Common_ColumnHeader,0)),"Actual","Estimate") -> Actual | S78: 45506 | T78: Investor Presentation
A79: 148 | B79: =IF(INDEX(MO_SNA_IsHistoricalPeriod,,MATCH(F79,MO_Common_ColumnHeader,0)),"Historical","Forward") -> Historical | D79: Affiliate dividends | E79: MO_CFSum_Dividend | F79: Q3-2024 | I79: -1000 | J79: -1000 | K79: =AVERAGE(I79:J79) -> -1000 | M79: =IF(INDEX(MO_SNA_IsHistoricalPeriod,,MATCH(F79,MO_Common_ColumnHeader,0)),"Actual","Estimate") -> Actual | S79: 45506 | T79: Investor Presentation
A80: 147 | B80: =IF(INDEX(MO_SNA_IsHistoricalPeriod,,MATCH(F80,MO_Common_ColumnHeader,0)),"Historical","Forward") -> Historical | D80: Share repurchase, mm | E80: MO_CFSum_NetShares | F80: Q3-2024 | I80: -4000 | J80: -4750 | K80: =AVERAGE(I80:J80) -> -4375 | M80: =IF(INDEX(MO_SNA_IsHistoricalPeriod,,MATCH(F80,MO_Common_ColumnHeader,0)),"Actual","Estimate") -> Actual | N80: =IFERROR(INDEX(INDIRECT(E80),0,MATCH(F80,MO_Common_ColumnHeader,0)),"N/A") -> -4714 | P80: =IF(ISNUMBER(N80),N80-K80,"N/A") -> -339 | Q80: =IFERROR(IF(ISNUMBER(N80),(N80-K80)/ABS(K80),"N/A"),"N/A") -> -0.077485714 | S80: 45506 | T80: Investor Presentation
A81: 146
A82: 145 | B82: =IF(INDEX(MO_SNA_IsHistoricalPeriod,,MATCH(F82,MO_Common_ColumnHeader,0)),"Historical","Forward") -> Historical | D82: Turnarounds & downtime, MBOE/d | F82: Q2-2024 | I82: -65 | J82: -65 | K82: =AVERAGE(I82:J82) -> -65 | M82: =IF(INDEX(MO_SNA_IsHistoricalPeriod,,MATCH(F82,MO_Common_ColumnHeader,0)),"Actual","Estimate") -> Actual | S82: 45408 | T82: Investor Presentation
A83: 144 | B83: =IF(INDEX(MO_SNA_IsHistoricalPeriod,,MATCH(F83,MO_Common_ColumnHeader,0)),"Historical","Forward") -> Historical | D83: Turnarounds (A/T earnings), mm | F83: Q2-2024 | I83: -300 | J83: -400 | K83: =AVERAGE(I83:J83) -> -350 | M83: =IF(INDEX(MO_SNA_IsHistoricalPeriod,,MATCH(F83,MO_Common_ColumnHeader,0)),"Actual","Estimate") -> Actual | S83: 45408 | T83: Investor Presentation
A84: 143 | B84: =IF(INDEX(MO_SNA_IsHistoricalPeriod,,MATCH(F84,MO_Common_ColumnHeader,0)),"Historical","Forward") -> Historical | D84: Affiliate dividends | E84: MO_CFSum_Dividend | F84: Q2-2024 | I84: -1000 | J84: -1500 | K84: =AVERAGE(I84:J84) -> -1250 | M84: =IF(INDEX(MO_SNA_IsHistoricalPeriod,,MATCH(F84,MO_Common_ColumnHeader,0)),"Actual","Estimate") -> Actual | S84: 45408 | T84: Investor Presentation
A85: 142 | B85: =IF(INDEX(MO_SNA_IsHistoricalPeriod,,MATCH(F85,MO_Common_ColumnHeader,0)),"Historical","Forward") -> Historical | D85: Share repurchase, mm | E85: MO_CFSum_NetShares | F85: Q2-2024 | I85: -2500 | J85: -3000 | K85: =AVERAGE(I85:J85) -> -2750 | M85: =IF(INDEX(MO_SNA_IsHistoricalPeriod,,MATCH(F85,MO_Common_ColumnHeader,0)),"Actual","Estimate") -> Actual | N85: =IFERROR(INDEX(INDIRECT(E85),0,MATCH(F85,MO_Common_ColumnHeader,0)),"N/A") -> -2930 | P85: =IF(ISNUMBER(N85),N85-K85,"N/A") -> -180 | Q85: =IFERROR(IF(ISNUMBER(N85),(N85-K85)/ABS(K85),"N/A"),"N/A") -> -0.065454545 | S85: 45408 | T85: Investor Presentation
A86: 141
A87: 140 | B87: =IF(INDEX(MO_SNA_IsHistoricalPeriod,,MATCH(F87,MO_Common_ColumnHeader,0)),"Historical","Forward") -> Historical | D87: Total average daily production volumes growth, % | E87: MO_OS_Energy_AverageDailyProduction_Total | F87: FY2024 | I87: 0.04 | J87: 0.07 | K87: =AVERAGE(I87:J87) -> 0.055 | M87: =IF(INDEX(MO_SNA_IsHistoricalPeriod,,MATCH(F87,MO_Common_ColumnHeader,0)),"Actual","Estimate") -> Actual | N87: =INDEX(MO_OS_Energy_AverageDailyProduction_Total,0,MATCH(F87,MO_Common_ColumnHeader,0))/INDEX(MO_OS_Energy_AverageDailyProduction_Total,0,MATCH("FY2023",MO_Common_ColumnHeader,0))-1 -> 0.069643239 | P87: =IF(ISNUMBER(N87),N87-K87,"N/A") -> 0.014643239 | Q87: =IFERROR(IF(ISNUMBER(N87),(N87-K87)/ABS(K87),"N/A"),"N/A") -> 0.2662407 | S87: 45324 | T87: Investor Presentation
A88: 139 | B88: =IF(INDEX(MO_SNA_IsHistoricalPeriod,,MATCH(F88,MO_Common_ColumnHeader,0)),"Historical","Forward") -> Historical | D88: =INDEX(INDIRECT(E88),0,COLUMN(MO_Common_Column_A)) -> All other adjusted earnings, mm | E88: z_Z99BO00122_MO_OS_Allotheradjustedearnings | F88: FY2024 | I88: -2200 | J88: -2200 | K88: =AVERAGE(I88:J88) -> -2200 | M88: =IF(INDEX(MO_SNA_IsHistoricalPeriod,,MATCH(F88,MO_Common_ColumnHeader,0)),"Actual","Estimate") -> Actual | S88: 45324 | T88: Investor Presentation
A89: 138 | B89: =IF(INDEX(MO_SNA_IsHistoricalPeriod,,MATCH(F89,MO_Common_ColumnHeader,0)),"Historical","Forward") -> Historical | D89: Affiliate dividends | E89: MO_CFSum_Dividend | F89: FY2024 | I89: -4000 | J89: -4000 | K89: =AVERAGE(I89:J89) -> -4000 | M89: =IF(INDEX(MO_SNA_IsHistoricalPeriod,,MATCH(F89,MO_Common_ColumnHeader,0)),"Actual","Estimate") -> Actual | N89: =IFERROR(INDEX(INDIRECT(E89),0,MATCH(F89,MO_Common_ColumnHeader,0)),"N/A") -> -11801 | P89: =IF(ISNUMBER(N89),N89-K89,"N/A") -> -7801 | Q89: =IFERROR(IF(ISNUMBER(N89),(N89-K89)/ABS(K89),"N/A"),"N/A") -> -1.95025 | S89: 45324 | T89: Investor Presentation
A90: 137 | B90: =IF(INDEX(MO_SNA_IsHistoricalPeriod,,MATCH(F90,MO_Common_ColumnHeader,0)),"Historical","Forward") -> Historical | D90: Distributions less affiliate income, mm | F90: FY2024 | I90: -1000 | J90: -1000 | K90: =AVERAGE(I90:J90) -> -1000 | M90: =IF(INDEX(MO_SNA_IsHistoricalPeriod,,MATCH(F90,MO_Common_ColumnHeader,0)),"Actual","Estimate") -> Actual | S90: 45324 | T90: Investor Presentation
A91: 136 | B91: =IF(INDEX(MO_SNA_IsHistoricalPeriod,,MATCH(F91,MO_Common_ColumnHeader,0)),"Historical","Forward") -> Historical | D91: B/T asset sales proceeds, mm | E91: MO_CFSum_Divestiture | F91: FY2024 | I91: 1000 | J91: 2000 | K91: =AVERAGE(I91:J91) -> 1500 | M91: =IF(INDEX(MO_SNA_IsHistoricalPeriod,,MATCH(F91,MO_Common_ColumnHeader,0)),"Actual","Estimate") -> Actual | N91: =IFERROR(INDEX(INDIRECT(E91),0,MATCH(F91,MO_Common_ColumnHeader,0)),"N/A") -> 7704 | P91: =IF(ISNUMBER(N91),N91-K91,"N/A") -> 6204 | Q91: =IFERROR(IF(ISNUMBER(N91),(N91-K91)/ABS(K91),"N/A"),"N/A") -> 4.136 | S91: 45324 | T91: Investor Presentation
A92: 135 | B92: =IF(INDEX(MO_SNA_IsHistoricalPeriod,,MATCH(F92,MO_Common_ColumnHeader,0)),"Historical","Forward") -> Historical | D92: Organic C&E, mm | F92: FY2024 | I92: -15500 | J92: -16500 | K92: =AVERAGE(I92:J92) -> -16000 | M92: =IF(INDEX(MO_SNA_IsHistoricalPeriod,,MATCH(F92,MO_Common_ColumnHeader,0)),"Actual","Estimate") -> Actual | S92: 45324 | T92: Investor Presentation
A93: 134 | B93: =IF(INDEX(MO_SNA_IsHistoricalPeriod,,MATCH(F93,MO_Common_ColumnHeader,0)),"Historical","Forward") -> Historical | D93: Capex by Affiliated Companies, mm | F93: FY2024 | I93: -3000 | J93: -3000 | K93: =AVERAGE(I93:J93) -> -3000 | M93: =IF(INDEX(MO_SNA_IsHistoricalPeriod,,MATCH(F93,MO_Common_ColumnHeader,0)),"Actual","Estimate") -> Actual | S93: 45324 | T93: Investor Presentation
A94: 133 | B94: =IF(INDEX(MO_SNA_IsHistoricalPeriod,,MATCH(F94,MO_Common_ColumnHeader,0)),"Historical","Forward") -> Historical | D94: DD&A | F94: FY2024 | I94: 16000 | J94: 17000 | K94: =AVERAGE(I94:J94) -> 16500 | M94: =IF(INDEX(MO_SNA_IsHistoricalPeriod,,MATCH(F94,MO_Common_ColumnHeader,0)),"Actual","Estimate") -> Actual | S94: 45324 | T94: Investor Presentation
A95: 132
A96: 131 | B96: =IF(INDEX(MO_SNA_IsHistoricalPeriod,,MATCH(F96,MO_Common_ColumnHeader,0)),"Historical","Forward") -> Historical | D96: Turnarounds & downtime, MBOE/d | F96: Q1-2024 | I96: -70 | J96: -70 | K96: =AVERAGE(I96:J96) -> -70 | M96: =IF(INDEX(MO_SNA_IsHistoricalPeriod,,MATCH(F96,MO_Common_ColumnHeader,0)),"Actual","Estimate") -> Actual | S96: 45324 | T96: Investor Presentation
A97: 130 | B97: =IF(INDEX(MO_SNA_IsHistoricalPeriod,,MATCH(F97,MO_Common_ColumnHeader,0)),"Historical","Forward") -> Historical | D97: Turnarounds (A/T earnings), mm | F97: Q1-2024 | I97: -250 | J97: -350 | K97: =AVERAGE(I97:J97) -> -300 | M97: =IF(INDEX(MO_SNA_IsHistoricalPeriod,,MATCH(F97,MO_Common_ColumnHeader,0)),"Actual","Estimate") -> Actual | S97: 45324 | T97: Investor Presentation
A98: 129 | B98: =IF(INDEX(MO_SNA_IsHistoricalPeriod,,MATCH(F98,MO_Common_ColumnHeader,0)),"Historical","Forward") -> Historical | D98: Share repurchase, mm | E98: MO_CFSum_NetShares | F98: Q1-2024 | I98: -2400 | J98: -3600 | K98: =AVERAGE(I98:J98) -> -3000 | M98: =IF(INDEX(MO_SNA_IsHistoricalPeriod,,MATCH(F98,MO_Common_ColumnHeader,0)),"Actual","Estimate") -> Actual | N98: =IFERROR(INDEX(INDIRECT(E98),0,MATCH(F98,MO_Common_ColumnHeader,0)),"N/A") -> -2891 | P98: =IF(ISNUMBER(N98),N98-K98,"N/A") -> 109 | Q98: =IFERROR(IF(ISNUMBER(N98),(N98-K98)/ABS(K98),"N/A"),"N/A") -> 0.036333333 | S98: 45324 | T98: Investor Presentation
A99: 128
A100: 127 | B100: =IF(INDEX(MO_SNA_IsHistoricalPeriod,,MATCH(F100,MO_Common_ColumnHeader,0)),"Historical","Forward") -> Historical | D100: Turnarounds & downtime, MBOE/d | F100: Q4-2023 | I100: -60 | J100: -60 | K100: =AVERAGE(I100:J100) -> -60 | M100: =IF(INDEX(MO_SNA_IsHistoricalPeriod,,MATCH(F100,MO_Common_ColumnHeader,0)),"Actual","Estimate") -> Actual | S100: 45226 | T100: Investor Presentation
A101: 126 | B101: =IF(INDEX(MO_SNA_IsHistoricalPeriod,,MATCH(F101,MO_Common_ColumnHeader,0)),"Historical","Forward") -> Historical | D101: Company2054 Energy capex | F101: Q4-2023 | I101: -300 | J101: -300 | K101: =AVERAGE(I101:J101) -> -300 | M101: =IF(INDEX(MO_SNA_IsHistoricalPeriod,,MATCH(F101,MO_Common_ColumnHeader,0)),"Actual","Estimate") -> Actual | S101: 45226 | T101: Investor Presentation
...

Sheet Supplemental
A1: =MO.CompanyName -> Company0670 Company0697
A2: =MO.Ticker -> Ticker0006 US | C2: =Model!C2 -> 39813 | D2: =Model!D2 -> 0 | E2: =Model!E2 -> 0 | F2: =Model!F2 -> 0 | G2: =Model!G2 -> 0 | H2: =Model!H2 -> 0 | I2: =Model!I2 -> 0 | J2: =Model!J2 -> 0 | ... CF2: =Model!CF2 -> 0
A3: =MO.TradingCurrency -> USD | B3: =MO.LastPrice -> 185.16 | C3: =INDEX(MO_Common_FPDays,0,MATCH(C$5,MO_Common_ColumnHeader,0)) -> 365 | D3: =INDEX(MO_Common_FPDays,0,MATCH(D$5,MO_Common_ColumnHeader,0)) -> 365 | E3: =INDEX(MO_Common_FPDays,0,MATCH(E$5,MO_Common_ColumnHeader,0)) -> 365 | F3: =INDEX(MO_Common_FPDays,0,MATCH(F$5,MO_Common_ColumnHeader,0)) -> 366 | G3: =INDEX(MO_Common_FPDays,0,MATCH(G$5,MO_Common_ColumnHeader,0)) -> 90 | H3: =INDEX(MO_Common_FPDays,0,MATCH(H$5,MO_Common_ColumnHeader,0)) -> 91 | I3: =INDEX(MO_Common_FPDays,0,MATCH(I$5,MO_Common_ColumnHeader,0)) -> 92 | J3: =INDEX(MO_Common_FPDays,0,MATCH(J$5,MO_Common_ColumnHeader,0)) -> 92 | ... CF3: =INDEX(MO_Common_FPDays,0,MATCH(CF$5,MO_Common_ColumnHeader,0)) -> 365
A4: =MO.DataSourceName -> Bloomberg | B4: =MO.RealTime -> OFF | C4: =INDEX(MO_Common_QEndDate,0,MATCH(C$5,MO_Common_ColumnHeader,0)) -> 40178 | D4: =INDEX(MO_Common_QEndDate,0,MATCH(D$5,MO_Common_ColumnHeader,0)) -> 40543 | E4: =INDEX(MO_Common_QEndDate,0,MATCH(E$5,MO_Common_ColumnHeader,0)) -> 40908 | F4: =INDEX(MO_Common_QEndDate,0,MATCH(F$5,MO_Common_ColumnHeader,0)) -> 41274 | G4: =INDEX(MO_Common_QEndDate,0,MATCH(G$5,MO_Common_ColumnHeader,0)) -> 41364 | H4: =INDEX(MO_Common_QEndDate,0,MATCH(H$5,MO_Common_ColumnHeader,0)) -> 41455 | I4: =INDEX(MO_Common_QEndDate,0,MATCH(I$5,MO_Common_ColumnHeader,0)) -> 41547 | J4: =INDEX(MO_Common_QEndDate,0,MATCH(J$5,MO_Common_ColumnHeader,0)) -> 41639 | ... CF4: =INDEX(MO_Common_QEndDate,0,MATCH(CF$5,MO_Common_ColumnHeader,0)) -> 47848
A5: =MO.ReportFX -> USD | C5: =Model!C5 -> FY2009 | D5: =Model!D5 -> FY2010 | E5: =Model!E5 -> FY2011 | F5: =Model!F5 -> FY2012 | G5: =Model!G5 -> Q1-2013 | H5: =Model!H5 -> Q2-2013 | I5: =Model!I5 -> Q3-2013 | J5: =Model!J5 -> Q4-2013 | ... CF5: =Model!CF5 -> FY2030
A6: Costs Incurred in Exploration, Property Acquisitions and Development
A7: U.S. Wells, mm | AO7: 571 | AT7: 190 | AY7: 184 | BD7: 239 | BI7: 280 | BN7: 193 | BS7: 127
A8: U.S. Geological and geophysical, mm | AO8: 82 | AT8: 83 | AY8: 67 | BD8: 98 | BI8: 84 | BN8: 173 | BS8: 115
A9: U.S. Other, mm | AO9: 140 | AT9: 125 | AY9: 80 | BD9: 53 | BI9: 50 | BN9: 62 | BS9: 75
A10: U.S. Total exploration, mm | AO10: =SUM(AO7:AO9) -> 793 | AT10: =SUM(AT7:AT9) -> 398 | AY10: =SUM(AY7:AY9) -> 331 | BD10: =SUM(BD7:BD9) -> 390 | BI10: =SUM(BI7:BI9) -> 414 | BN10: =SUM(BN7:BN9) -> 428 | BS10: =SUM(BS7:BS9) -> 317
A11: U.S. Proved - Company1944, mm | AO11: 81 | AT11: 3463
A12: U.S. Proved - Other, mm | AT12: 23 | AY12: 98 | BD12: 18 | BI12: 10123 | BN12: 11 | BS12: 19947
A13: U.S. Unproved - Company1944, mm | AO13: 68 | AT13: 2845
A14: U.S. Unproved - Other, mm | AT14: 35 | AY14: 13 | BD14: 104 | BI14: 504 | BN14: 69 | BS14: 1783
A15: U.S. Total property acquisitions, mm | AO15: =SUM(AO11:AO14) -> 149 | AT15: =SUM(AT11:AT14) -> 6366 | AY15: =SUM(AY11:AY14) -> 111 | BD15: =SUM(BD11:BD14) -> 122 | BI15: =SUM(BI11:BI14) -> 10627 | BN15: =SUM(BN11:BN14) -> 80 | BS15: =SUM(BS11:BS14) -> 21730
A16: U.S. Development, mm | AO16: 7072 | AT16: 4622 | AY16: 4360 | BD16: 6221 | BI16: 9645 | BN16: 9334 | BS16: 8532
A17: U.S. Total Costs Incurred, mm | AO17: =AO10+AO15+AO16 -> 8014 | AT17: =AT10+AT15+AT16 -> 11386 | AY17: =AY10+AY15+AY16 -> 4802 | BD17: =BD10+BD15+BD16 -> 6733 | BI17: =BI10+BI15+BI16 -> 20686 | BN17: =BN10+BN15+BN16 -> 9842 | BS17: =BS10+BS15+BS16 -> 30579
A18: Other Americas Wells, mm | AO18: 44 | AT18: 181 | AY18: 31 | BD18: 84 | BI18: 92 | BN18: 2 | BS18: 161
A19: Other Americas Geological and geophysical, mm | AO19: 118 | AT19: 29 | AY19: 58 | BD19: 28 | BI19: 49 | BN19: 81 | BS19: 140
A20: Other Americas Other, mm | AO20: 52 | AT20: 77 | AY20: 80 | BD20: 72 | BI20: 104 | BN20: 62 | BS20: 71
A21: Other Americas Total exploration, mm | AO21: =SUM(AO18:AO20) -> 214 | AT21: =SUM(AT18:AT20) -> 287 | AY21: =SUM(AY18:AY20) -> 169 | BD21: =SUM(BD18:BD20) -> 184 | BI21: =SUM(BI18:BI20) -> 245 | BN21: =SUM(BN18:BN20) -> 145 | BS21: =SUM(BS18:BS20) -> 372
A22: Other Americas Proved - Company1944, mm | AO22: 34 | AT22: 0
A23: Other Americas Proved - Other, mm | AT23: 0 | AY23: 0 | BD23: 0 | BI23: 0 | BN23: 0 | BS23: 22987
A24: Other Americas Unproved - Company1944, mm | AO24: 150 | AT24: 2
A25: Other Americas Unproved - Other, mm | AT25: 0 | AY25: 16 | BD25: 78 | BI25: 1 | BN25: 38 | BS25: 28141
A26: Other Americas Total property acquisitions, mm | AO26: =SUM(AO22:AO25) -> 184 | AT26: =SUM(AT22:AT25) -> 2 | AY26: =SUM(AY22:AY25) -> 16 | BD26: =SUM(BD22:BD25) -> 78 | BI26: =SUM(BI22:BI25) -> 1 | BN26: =SUM(BN22:BN25) -> 38 | BS26: =SUM(BS22:BS25) -> 51128
A27: Other Americas Development, mm | AO27: 1216 | AT27: 740 | AY27: 640 | BD27: 863 | BI27: 986 | BN27: 1261 | BS27: 2402
A28: Other Americas Total Costs Incurred, mm | AO28: =AO21+AO26+AO27 -> 1614 | AT28: =AT21+AT26+AT27 -> 1029 | AY28: =AY21+AY26+AY27 -> 825 | BD28: =BD21+BD26+BD27 -> 1125 | BI28: =BI21+BI26+BI27 -> 1232 | BN28: =BN21+BN26+BN27 -> 1444 | BS28: =BS21+BS26+BS27 -> 53902
A29: Africa Wells, mm | AO29: 9 | AT29: 1 | AY29: 5 | BD29: 78 | BI29: 36 | BN29: 155 | BS29: 109
A30: Africa Geological and geophysical, mm | AO30: 21 | AT30: 58 | AY30: 40 | BD30: 110 | BI30: 83 | BN30: 47 | BS30: 162
A31: Africa Other, mm | AO31: 35 | AT31: 42 | AY31: 39 | BD31: 75 | BI31: 57 | BN31: 70 | BS31: 92
A32: Africa Total exploration, mm | AO32: =SUM(AO29:AO31) -> 65 | AT32: =SUM(AT29:AT31) -> 101 | AY32: =SUM(AY29:AY31) -> 84 | BD32: =SUM(BD29:BD31) -> 263 | BI32: =SUM(BI29:BI31) -> 176 | BN32: =SUM(BN29:BN31) -> 272 | BS32: =SUM(BS29:BS31) -> 363
A33: Africa Proved - Company1944, mm | AT33: 438
A34: Africa Proved - Other, mm | AT34: 2 | AY34: 15 | BD34: 63 | BN34: 95 | BS34: 0
A35: Africa Unproved - Company1944, mm | AT35: 113
A36: Africa Unproved - Other, mm | AT36: 10 | AY36: 0 | BD36: 73 | BN36: 22 | BS36: 15
A37: Africa Total property acquisitions, mm | AO37: =SUM(AO34:AO36) -> 0 | AT37: =SUM(AT33:AT36) -> 563 | AY37: =SUM(AY33:AY36) -> 15 | BD37: =SUM(BD33:BD36) -> 136 | BI37: =SUM(BI33:BI36) -> 0 | BN37: =SUM(BN33:BN36) -> 117 | BS37: =SUM(BS33:BS36) -> 15
A38: Africa Development, mm | AO38: 279 | AT38: 386 | AY38: 383 | BD38: 21 | BI38: 784 | BN38: 895 | BS38: 1390
A39: Africa Total Costs Incurred, mm | AO39: =AO32+AO37+AO38 -> 344 | AT39: =AT32+AT37+AT38 -> 1050 | AY39: =AY32+AY37+AY38 -> 482 | BD39: =BD32+BD37+BD38 -> 420 | BI39: =BI32+BI37+BI38 -> 960 | BN39: =BN32+BN37+BN38 -> 1284 | BS39: =BS32+BS37+BS38 -> 1768
A40: Asia Wells, mm | AO40: 2 | AT40: 8 | AY40: 36 | BD40: 34 | BI40: 111 | BN40: 94 | BS40: 32
A41: Asia Geological and geophysical, mm | AO41: 5 | AT41: 3 | AY41: 0 | BD41: 0 | BI41: 0 | BN41: 23 | BS41: 19
A42: Asia Other, mm | AO42: 29 | AT42: 22 | AY42: 14 | BD42: 30 | BI42: 15 | BN42: 15 | BS42: 21
A43: Asia Total exploration, mm | AO43: =SUM(AO40:AO42) -> 36 | AT43: =SUM(AT40:AT42) -> 33 | AY43: =SUM(AY40:AY42) -> 50 | BD43: =SUM(BD40:BD42) -> 64 | BI43: =SUM(BI40:BI42) -> 126 | BN43: =SUM(BN40:BN42) -> 132 | BS43: =SUM(BS40:BS42) -> 72
A44: Asia Proved - Company1944, mm | AO44: 93 | AT44: 7945
A45: Asia Proved - Other, mm | AT45: 56 | AY45: 53 | BD45: 13 | BN45: 0 | BS45: 838
A46: Asia Unproved - Company1944, mm | AO46: 17 | AT46: 129
A47: Asia Unproved - Other, mm | AT47: 0 | AY47: 0 | BD47: 0 | BI47: 3 | BN47: 0 | BS47: 0
A48: Asia Total property acquisitions, mm | AO48: =SUM(AO44:AO47) -> 110 | AT48: =SUM(AT44:AT47) -> 8130 | AY48: =SUM(AY44:AY47) -> 53 | BD48: =SUM(BD44:BD47) -> 13 | BI48: =SUM(BI44:BI47) -> 3 | BN48: =SUM(BN44:BN47) -> 0 | BS48: =SUM(BS44:BS47) -> 838
A49: Asia Development, mm | AO49: 1020 | AT49: 1034 | AY49: 545 | BD49: 649 | BI49: 619 | BN49: 774 | BS49: 1180
A50: Asia Total Costs Incurred, mm | AO50: =AO43+AO48+AO49 -> 1166 | AT50: =AT43+AT48+AT49 -> 9197 | AY50: =AY43+AY48+AY49 -> 648 | BD50: =BD43+BD48+BD49 -> 726 | BI50: =BI43+BI48+BI49 -> 748 | BN50: =BN43+BN48+BN49 -> 906 | BS50: =BS43+BS48+BS49 -> 2090
A51: Australia Wells, mm | AO51: 4 | AT51: 1 | AY51: 0 | BD51: 4 | BI51: 11 | BN51: 4 | BS51: 82
A52: Australia Geological and geophysical, mm | AO52: 11 | AT52: 12 | AY52: 22 | BD52: 1 | BI52: 0 | BN52: 3 | BS52: 2
A53: Australia Other, mm | AO53: 44 | AT53: 39 | AY53: 25 | BD53: 27 | BI53: 32 | BN53: 30 | BS53: 28
A54: Australia Total exploration, mm | AO54: =SUM(AO51:AO53) -> 59 | AT54: =SUM(AT51:AT53) -> 52 | AY54: =SUM(AY51:AY53) -> 47 | BD54: =SUM(BD51:BD53) -> 32 | BI54: =SUM(BI51:BI53) -> 43 | BN54: =SUM(BN51:BN53) -> 37 | BS54: =SUM(BS51:BS53) -> 112
A55: Australia Proved - Company1944, mm | AO55: 0 | AT55: 0
A56: Australia Proved - Other, mm | AT56: 0 | AY56: 0 | BN56: 0 | BS56: 0
A57: Australia Unproved - Company1944, mm | AO57: 1 | AT57: 0
A58: Australia Unproved - Other, mm | AT58: 0 | AY58: 0 | BN58: 0 | BS58: 0
A59: Australia Total property acquisitions, mm | AO59: =SUM(AO55:AO58) -> 1 | AT59: =SUM(AT55:AT58) -> 0 | AY59: =SUM(AY55:AY58) -> 0 | BD59: =SUM(BD55:BD58) -> 0 | BI59: =SUM(BI55:BI58) -> 0 | BN59: =SUM(BN55:BN58) -> 0 | BS59: =SUM(BS55:BS58) -> 0
A60: Australia Development, mm | AO60: 518 | AT60: 753 | AY60: 526 | BD60: 719 | BI60: 822 | BN60: 1015 | BS60: 963
A61: Australia Total Costs Incurred, mm | AO61: =AO54+AO59+AO60 -> 578 | AT61: =AT54+AT59+AT60 -> 805 | AY61: =AY54+AY59+AY60 -> 573 | BD61: =BD54+BD59+BD60 -> 751 | BI61: =BI54+BI59+BI60 -> 865 | BN61: =BN54+BN59+BN60 -> 1052 | BS61: =BS54+BS59+BS60 -> 1075
A62: Europe Wells, mm | AO62: 4 | AT62: 0 | AY62: 0 | BD62: 0 | BI62: 0 | BN62: 0 | BS62: 0
A63: Europe Geological and geophysical, mm | AO63: 1 | AT63: 0 | AY63: 0 | BD63: 0 | BI63: 0 | BN63: 0 | BS63: 0
A64: Europe Other, mm | AO64: 6 | AT64: 2 | AY64: 1 | BD64: 2 | BI64: 4 | BN64: 0 | BS64: 0
A65: Europe Total exploration, mm | AO65: =SUM(AO62:AO64) -> 11 | AT65: =SUM(AT62:AT64) -> 2 | AY65: =SUM(AY62:AY64) -> 1 | BD65: =SUM(BD62:BD64) -> 2 | BI65: =SUM(BI62:BI64) -> 4 | BN65: =SUM(BN62:BN64) -> 0 | BS65: =SUM(BS62:BS64) -> 0
A66: Europe Proved - Company1944, mm | AT66: 0
A67: Europe Proved - Other, mm | AT67: 0 | AY67: 0 | BN67: 0 | BS67: 0
A68: Europe Unproved - Company1944, mm | AT68: 0
A69: Europe Unproved - Other, mm | AT69: 0 | AY69: 0 | BN69: 0 | BS69: 0
A70: Europe Total property acquisitions, mm | AO70: =SUM(AO66:AO69) -> 0 | AT70: =SUM(AT66:AT69) -> 0 | AY70: =SUM(AY66:AY69) -> 0 | BD70: =SUM(BD66:BD69) -> 0 | BI70: =SUM(BI66:BI69) -> 0 | BN70: =SUM(BN66:BN69) -> 0 | BS70: =SUM(BS66:BS69) -> 0
A71: Europe Development, mm | AO71: 199 | AT71: 37 | AY71: 44 | BD71: 35 | BI71: 64 | BN71: 54 | BS71: 71
A72: Europe Total Costs Incurred, mm | AO72: =AO65+AO70+AO71 -> 210 | AT72: =AT65+AT70+AT71 -> 39 | AY72: =AY65+AY70+AY71 -> 45 | BD72: =BD65+BD70+BD71 -> 37 | BI72: =BI65+BI70+BI71 -> 68 | BN72: =BN65+BN70+BN71 -> 54 | BS72: =BS65+BS70+BS71 -> 71
A73: Total Wells, mm | AO73: =AO7+AO18+AO29+AO40+AO51+AO62 -> 634 | AT73: =AT7+AT18+AT29+AT40+AT51+AT62 -> 381 | AY73: =AY7+AY18+AY29+AY40+AY51+AY62 -> 256 | BD73: =BD7+BD18+BD29+BD40+BD51+BD62 -> 439 | BI73: =BI7+BI18+BI29+BI40+BI51+BI62 -> 530 | BN73: =BN7+BN18+BN29+BN40+BN51+BN62 -> 448 | BS73: =BS7+BS18+BS29+BS40+BS51+BS62 -> 511
A74: Total Geological and geophysical, mm | AO74: =AO8+AO19+AO30+AO41+AO52+AO63 -> 238 | AT74: =AT8+AT19+AT30+AT41+AT52+AT63 -> 185 | AY74: =AY8+AY19+AY30+AY41+AY52+AY63 -> 187 | BD74: =BD8+BD19+BD30+BD41+BD52+BD63 -> 237 | BI74: =BI8+BI19+BI30+BI41+BI52+BI63 -> 216 | BN74: =BN8+BN19+BN30+BN41+BN52+BN63 -> 327 | BS74: =BS8+BS19+BS30+BS41+BS52+BS63 -> 438
A75: Total Other, mm | AO75: =AO9+AO20+AO31+AO42+AO53+AO64 -> 306 | AT75: =AT9+AT20+AT31+AT42+AT53+AT64 -> 307 | AY75: =AY9+AY20+AY31+AY42+AY53+AY64 -> 239 | BD75: =BD9+BD20+BD31+BD42+BD53+BD64 -> 259 | BI75: =BI9+BI20+BI31+BI42+BI53+BI64 -> 262 | BN75: =BN9+BN20+BN31+BN42+BN53+BN64 -> 239 | BS75: =BS9+BS20+BS31+BS42+BS53+BS64 -> 287
A76: Total exploration, mm | AO76: =SUM(AO73:AO75) -> 1178 | AT76: =SUM(AT73:AT75) -> 873 | AY76: =SUM(AY73:AY75) -> 682 | BD76: =SUM(BD73:BD75) -> 935 | BI76: =SUM(BI73:BI75) -> 1008 | BN76: =SUM(BN73:BN75) -> 1014 | BS76: =SUM(BS73:BS75) -> 1236
A77: Total Proved - Company1944, mm | AO77: =AO11+AO22+AO33+AO44+AO55+AO66 -> 208 | AT77: =AT11+AT22+AT33+AT44+AT55+AT66 -> 11846 | AY77: =AY11+AY22+AY33+AY44+AY55+AY66 -> 0 | BD77: =BD11+BD22+BD33+BD44+BD55+BD66 -> 0 | BI77: =BI11+BI22+BI33+BI44+BI55+BI66 -> 0 | BN77: =BN11+BN22+BN33+BN44+BN55+BN66 -> 0 | BS77: =BS11+BS22+BS33+BS44+BS55+BS66 -> 0
A78: Total Proved - Other, mm | AO78: =AO12+AO23+AO34+AO45+AO56+AO67 -> 0 | AT78: =AT12+AT23+AT34+AT45+AT56+AT67 -> 81 | AY78: =AY12+AY23+AY34+AY45+AY56+AY67 -> 166 | BD78: =BD12+BD23+BD34+BD45+BD56+BD67 -> 94 | BI78: =BI12+BI23+BI34+BI45+BI56+BI67 -> 10123 | BN78: =BN12+BN23+BN34+BN45+BN56+BN67 -> 106 | BS78: =BS12+BS23+BS34+BS45+BS56+BS67 -> 43772
A79: Total Unproved - Company1944, mm | AO79: =AO13+AO24+AO35+AO46+AO57+AO68 -> 236 | AT79: =AT13+AT24+AT35+AT46+AT57+AT68 -> 3089 | AY79: =AY13+AY24+AY35+AY46+AY57+AY68 -> 0 | BD79: =BD13+BD24+BD35+BD46+BD57+BD68 -> 0 | BI79: =BI13+BI24+BI35+BI46+BI57+BI68 -> 0 | BN79: =BN13+BN24+BN35+BN46+BN57+BN68 -> 0 | BS79: =BS13+BS24+BS35+BS46+BS57+BS68 -> 0
A80: Total Unproved - Other, mm | AO80: =AO14+AO25+AO36+AO47+AO58+AO69 -> 0 | AT80: =AT14+AT25+AT36+AT47+AT58+AT69 -> 45 | AY80: =AY14+AY25+AY36+AY47+AY58+AY69 -> 29 | BD80: =BD14+BD25+BD36+BD47+BD58+BD69 -> 255 | BI80: =BI14+BI25+BI36+BI47+BI58+BI69 -> 508 | BN80: =BN14+BN25+BN36+BN47+BN58+BN69 -> 129 | BS80: =BS14+BS25+BS36+BS47+BS58+BS69 -> 29939
A81: Total property acquisitions, mm | AO81: =SUM(AO77:AO80) -> 444 | AT81: =SUM(AT77:AT80) -> 15061 | AY81: =SUM(AY77:AY80) -> 195 | BD81: =SUM(BD77:BD80) -> 349 | BI81: =SUM(BI77:BI80) -> 10631 | BN81: =SUM(BN77:BN80) -> 235 | BS81: =SUM(BS77:BS80) -> 73711
A82: Total Development, mm | AO82: =AO16+AO27+AO38+AO49+AO60+AO71 -> 10304 | AT82: =AT16+AT27+AT38+AT49+AT60+AT71 -> 7572 | AY82: =AY16+AY27+AY38+AY49+AY60+AY71 -> 6498 | BD82: =BD16+BD27+BD38+BD49+BD60+BD71 -> 8508 | BI82: =BI16+BI27+BI38+BI49+BI60+BI71 -> 12920 | BN82: =BN16+BN27+BN38+BN49+BN60+BN71 -> 13333 | BS82: =BS16+BS27+BS38+BS49+BS60+BS71 -> 14538
A83: Total Costs Incurred, mm | AO83: =AO76+AO81+AO82 -> 11926 | AT83: =AT76+AT81+AT82 -> 23506 | AY83: =AY76+AY81+AY82 -> 7375 | BD83: =BD76+BD81+BD82 -> 9792 | BI83: =BI76+BI81+BI82 -> 24559 | BN83: =BN76+BN81+BN82 -> 14582 | BS83: =BS76+BS81+BS82 -> 89485
A85: TCO Wells, mm | AO85: 0 | AT85: 0 | AY85: 0 | BD85: 0 | BI85: 0 | BN85: 0 | BS85: 0
A86: TCO Geological and geophysical, mm | AO86: 0 | AT86: 0 | AY86: 0 | BD86: 0 | BI86: 0 | BN86: 0 | BS86: 0
A87: TCO Other, mm | AO87: 0 | AT87: 0 | AY87: 0 | BD87: 0 | BI87: 0 | BN87: 0 | BS87: 0
A88: TCO Total exploration, mm | AO88: =SUM(AO85:AO87) -> 0 | AT88: =SUM(AT85:AT87) -> 0 | AY88: =SUM(AY85:AY87) -> 0 | BD88: =SUM(BD85:BD87) -> 0 | BI88: =SUM(BI85:BI87) -> 0 | BN88: =SUM(BN85:BN87) -> 0 | BS88: =SUM(BS85:BS87) -> 0
A89: TCO Proved - Company1944, mm
A90: TCO Proved - Other, mm | BN90: 0 | BS90: 0
A91: TCO Unproved - Company1944, mm
A92: TCO Unproved - Other, mm | BN92: 0 | BS92: 0
A93: TCO Total property acquisitions, mm | AO93: =SUM(AO89:AO92) -> 0 | AT93: =SUM(AT89:AT92) -> 0 | AY93: =SUM(AY89:AY92) -> 0 | BD93: =SUM(BD89:BD92) -> 0 | BI93: =SUM(BI89:BI92) -> 0 | BN93: =SUM(BN89:BN92) -> 0 | BS93: =SUM(BS89:BS92) -> 0
A94: TCO Development, mm | AO94: 5112 | AT94: 2998 | AY94: 2442 | BD94: 2429 | BI94: 2278 | BN94: 1480 | BS94: 577
A95: TCO Total Costs Incurred, mm | AO95: =AO88+AO93+AO94 -> 5112 | AT95: =AT88+AT93+AT94 -> 2998 | AY95: =AY88+AY93+AY94 -> 2442 | BD95: =BD88+BD93+BD94 -> 2429 | BI95: =BI88+BI93+BI94 -> 2278 | BN95: =BN88+BN93+BN94 -> 1480 | BS95: =BS88+BS93+BS94 -> 577
A97: Other Wells, mm | AO97: 0 | AT97: 0 | AY97: 0 | BN97: 0 | BS97: 0
A98: Other Geological and geophysical, mm | AO98: 0 | AT98: 0 | AY98: 0 | BN98: 0 | BS98: 0
A99: Other Other, mm | AO99: 8 | AT99: 0 | AY99: 0 | BN99: 0 | BS99: 0
A100: Other Total exploration, mm | AO100: =SUM(AO97:AO99) -> 8 | AT100: =SUM(AT97:AT99) -> 0 | AY100: =SUM(AY97:AY99) -> 0 | BD100: =SUM(BD97:BD99) -> 0 | BI100: =SUM(BI97:BI99) -> 0 | BN100: =SUM(BN97:BN99) -> 0 | BS100: =SUM(BS97:BS99) -> 0
A101: Other Proved - Company1944, mm | AT101: 0
A102: Other Proved - Other, mm | AT102: 0 | AY102: 0 | BN102: 0 | BS102: 0
...

Sheet Summary Page
A1: =MO.CompanyName -> Company0670 Company0697 | C1: =INDEX(MO_Common_QEndDate,0,COLUMN()) -> 40178 | D1: =INDEX(MO_Common_QEndDate,0,COLUMN()) -> 40543 | E1: =INDEX(MO_Common_QEndDate,0,COLUMN()) -> 40908 | F1: =INDEX(MO_Common_QEndDate,0,COLUMN()) -> 41274 | G1: =INDEX(MO_Common_QEndDate,0,COLUMN()) -> 41364 | H1: =INDEX(MO_Common_QEndDate,0,COLUMN()) -> 41455 | I1: =INDEX(MO_Common_QEndDate,0,COLUMN()) -> 41547 | J1: =INDEX(MO_Common_QEndDate,0,COLUMN()) -> 41639 | ... CF1: =INDEX(MO_Common_QEndDate,0,COLUMN()) -> 47848
A2: Reports | B2: =MO.ReportFX -> USD | C2: =INDEX(MO_Common_ColumnHeader,0,COLUMN()) -> FY2009 | D2: =INDEX(MO_Common_ColumnHeader,0,COLUMN()) -> FY2010 | E2: =INDEX(MO_Common_ColumnHeader,0,COLUMN()) -> FY2011 | F2: =INDEX(MO_Common_ColumnHeader,0,COLUMN()) -> FY2012 | G2: =INDEX(MO_Common_ColumnHeader,0,COLUMN()) -> Q1-2013 | H2: =INDEX(MO_Common_ColumnHeader,0,COLUMN()) -> Q2-2013 | I2: =INDEX(MO_Common_ColumnHeader,0,COLUMN()) -> Q3-2013 | J2: =INDEX(MO_Common_ColumnHeader,0,COLUMN()) -> Q4-2013 | ... CF2: =INDEX(MO_Common_ColumnHeader,0,COLUMN()) -> FY2030
A3: Capitalization Summary
A4: ="Stock Price - "&SP.ValuationToggle -> Stock Price - EoP | B4: EoP | C4: =IF(INDEX(MO_SNA_IsHistoricalPeriod,1,COLUMN())=FALSE,MO.LastPrice/HP.MRFX,CHOOSE(VLOOKUP(SP.ValuationToggle,tb_ValuationToggle,COLUMNS(tb_ValuationToggle),FALSE),INDEX(MO_SPT_StockHigh,1,COLUMN()),INDEX(MO_SPT_StockLow,1,COLUMN()),INDEX(MO_SPT_StockAverage,1,COLUMN()),INDEX(MO_SPT_StockEoP,1,COLUMN()))/IF(SP.ValuationToggle="EoP",IF(INDEX(MO_SPT_FXEoP,1,COLUMN())=0,1,INDEX(MO_SPT_FXEoP,1,COLUMN())),IF(INDEX(MO_SPT_FXAverage,1,COLUMN())=0,1,INDEX(MO_SPT_FXAverage,1,COLUMN())))) -> 77.65 | D4: =IF(INDEX(MO_SNA_IsHistoricalPeriod,1,COLUMN())=FALSE,MO.LastPrice/HP.MRFX,CHOOSE(VLOOKUP(SP.ValuationToggle,tb_ValuationToggle,COLUMNS(tb_ValuationToggle),FALSE),INDEX(MO_SPT_StockHigh,1,COLUMN()),INDEX(MO_SPT_StockLow,1,COLUMN()),INDEX(MO_SPT_StockAverage,1,COLUMN()),INDEX(MO_SPT_StockEoP,1,COLUMN()))/IF(SP.ValuationToggle="EoP",IF(INDEX(MO_SPT_FXEoP,1,COLUMN())=0,1,INDEX(MO_SPT_FXEoP,1,COLUMN())),IF(INDEX(MO_SPT_FXAverage,1,COLUMN())=0,1,INDEX(MO_SPT_FXAverage,1,COLUMN())))) -> 91.6 | E4: =IF(INDEX(MO_SNA_IsHistoricalPeriod,1,COLUMN())=FALSE,MO.LastPrice/HP.MRFX,CHOOSE(VLOOKUP(SP.ValuationToggle,tb_ValuationToggle,COLUMNS(tb_ValuationToggle),FALSE),INDEX(MO_SPT_StockHigh,1,COLUMN()),INDEX(MO_SPT_StockLow,1,COLUMN()),INDEX(MO_SPT_StockAverage,1,COLUMN()),INDEX(MO_SPT_StockEoP,1,COLUMN()))/IF(SP.ValuationToggle="EoP",IF(INDEX(MO_SPT_FXEoP,1,COLUMN())=0,1,INDEX(MO_SPT_FXEoP,1,COLUMN())),IF(INDEX(MO_SPT_FXAverage,1,COLUMN())=0,1,INDEX(MO_SPT_FXAverage,1,COLUMN())))) -> 106.4 | F4: =IF(INDEX(MO_SNA_IsHistoricalPeriod,1,COLUMN())=FALSE,MO.LastPrice/HP.MRFX,CHOOSE(VLOOKUP(SP.ValuationToggle,tb_ValuationToggle,COLUMNS(tb_ValuationToggle),FALSE),INDEX(MO_SPT_StockHigh,1,COLUMN()),INDEX(MO_SPT_StockLow,1,COLUMN()),INDEX(MO_SPT_StockAverage,1,COLUMN()),INDEX(MO_SPT_StockEoP,1,COLUMN()))/IF(SP.ValuationToggle="EoP",IF(INDEX(MO_SPT_FXEoP,1,COLUMN())=0,1,INDEX(MO_SPT_FXEoP,1,COLUMN())),IF(INDEX(MO_SPT_FXAverage,1,COLUMN())=0,1,INDEX(MO_SPT_FXAverage,1,COLUMN())))) -> 106.45 | G4: =IF(INDEX(MO_SNA_IsHistoricalPeriod,1,COLUMN())=FALSE,MO.LastPrice/HP.MRFX,CHOOSE(VLOOKUP(SP.ValuationToggle,tb_ValuationToggle,COLUMNS(tb_ValuationToggle),FALSE),INDEX(MO_SPT_StockHigh,1,COLUMN()),INDEX(MO_SPT_StockLow,1,COLUMN()),INDEX(MO_SPT_StockAverage,1,COLUMN()),INDEX(MO_SPT_StockEoP,1,COLUMN()))/IF(SP.ValuationToggle="EoP",IF(INDEX(MO_SPT_FXEoP,1,COLUMN())=0,1,INDEX(MO_SPT_FXEoP,1,COLUMN())),IF(INDEX(MO_SPT_FXAverage,1,COLUMN())=0,1,INDEX(MO_SPT_FXAverage,1,COLUMN())))) -> 118.82 | H4: =IF(INDEX(MO_SNA_IsHistoricalPeriod,1,COLUMN())=FALSE,MO.LastPrice/HP.MRFX,CHOOSE(VLOOKUP(SP.ValuationToggle,tb_ValuationToggle,COLUMNS(tb_ValuationToggle),FALSE),INDEX(MO_SPT_StockHigh,1,COLUMN()),INDEX(MO_SPT_StockLow,1,COLUMN()),INDEX(MO_SPT_StockAverage,1,COLUMN()),INDEX(MO_SPT_StockEoP,1,COLUMN()))/IF(SP.ValuationToggle="EoP",IF(INDEX(MO_SPT_FXEoP,1,COLUMN())=0,1,INDEX(MO_SPT_FXEoP,1,COLUMN())),IF(INDEX(MO_SPT_FXAverage,1,COLUMN())=0,1,INDEX(MO_SPT_FXAverage,1,COLUMN())))) -> 118.34 | I4: =IF(INDEX(MO_SNA_IsHistoricalPeriod,1,COLUMN())=FALSE,MO.LastPrice/HP.MRFX,CHOOSE(VLOOKUP(SP.ValuationToggle,tb_ValuationToggle,COLUMNS(tb_ValuationToggle),FALSE),INDEX(MO_SPT_StockHigh,1,COLUMN()),INDEX(MO_SPT_StockLow,1,COLUMN()),INDEX(MO_SPT_StockAverage,1,COLUMN()),INDEX(MO_SPT_StockEoP,1,COLUMN()))/IF(SP.ValuationToggle="EoP",IF(INDEX(MO_SPT_FXEoP,1,COLUMN())=0,1,INDEX(MO_SPT_FXEoP,1,COLUMN())),IF(INDEX(MO_SPT_FXAverage,1,COLUMN())=0,1,INDEX(MO_SPT_FXAverage,1,COLUMN())))) -> 122.64 | J4: =IF(INDEX(MO_SNA_IsHistoricalPeriod,1,COLUMN())=FALSE,MO.LastPrice/HP.MRFX,CHOOSE(VLOOKUP(SP.ValuationToggle,tb_ValuationToggle,COLUMNS(tb_ValuationToggle),FALSE),INDEX(MO_SPT_StockHigh,1,COLUMN()),INDEX(MO_SPT_StockLow,1,COLUMN()),INDEX(MO_SPT_StockAverage,1,COLUMN()),INDEX(MO_SPT_StockEoP,1,COLUMN()))/IF(SP.ValuationToggle="EoP",IF(INDEX(MO_SPT_FXEoP,1,COLUMN())=0,1,INDEX(MO_SPT_FXEoP,1,COLUMN())),IF(INDEX(MO_SPT_FXAverage,1,COLUMN())=0,1,INDEX(MO_SPT_FXAverage,1,COLUMN())))) -> 124.23 | ... CF4: =IF(INDEX(MO_SNA_IsHistoricalPeriod,1,COLUMN())=FALSE,MO.LastPrice/HP.MRFX,CHOOSE(VLOOKUP(SP.ValuationToggle,tb_ValuationToggle,COLUMNS(tb_ValuationToggle),FALSE),INDEX(MO_SPT_StockHigh,1,COLUMN()),INDEX(MO_SPT_StockLow,1,COLUMN()),INDEX(MO_SPT_StockAverage,1,COLUMN()),INDEX(MO_SPT_StockEoP,1,COLUMN()))/IF(SP.ValuationToggle="EoP",IF(INDEX(MO_SPT_FXEoP,1,COLUMN())=0,1,INDEX(MO_SPT_FXEoP,1,COLUMN())),IF(INDEX(MO_SPT_FXAverage,1,COLUMN())=0,1,INDEX(MO_SPT_FXAverage,1,COLUMN())))) -> 185.16
A5: =INDEX(MO_SCA_ShareCount_EoP_Diluted,0,COLUMN()) -> Total diluted common stock outstanding - EoP, mm shares | C5: =INDEX(MO_SCA_ShareCount_EoP_Diluted,0,COLUMN()) -> 2016.7218 | D5: =INDEX(MO_SCA_ShareCount_EoP_Diluted,0,COLUMN()) -> 2017.2358 | E5: =INDEX(MO_SCA_ShareCount_EoP_Diluted,0,COLUMN()) -> 1995.4699 | F5: =INDEX(MO_SCA_ShareCount_EoP_Diluted,0,COLUMN()) -> 1960.9729 | G5: =INDEX(MO_SCA_ShareCount_EoP_Diluted,0,COLUMN()) -> 1953.8948 | H5: =INDEX(MO_SCA_ShareCount_EoP_Diluted,0,COLUMN()) -> 1947.4157 | I5: =INDEX(MO_SCA_ShareCount_EoP_Diluted,0,COLUMN()) -> 1938.957 | J5: =INDEX(MO_SCA_ShareCount_EoP_Diluted,0,COLUMN()) -> 1928.9971 | ... CF5: =INDEX(MO_SCA_ShareCount_EoP_Diluted,0,COLUMN()) -> 1984.1731
A6: ="Market Cap - "&SP.ValuationToggle -> Market Cap - EoP | C6: =INDEX(SP_CS_StockPrice,0,COLUMN())*INDEX(SP_CS_ShareCount_EoP_Diluted,0,COLUMN()) -> 156598.45 | D6: =INDEX(SP_CS_StockPrice,0,COLUMN())*INDEX(SP_CS_ShareCount_EoP_Diluted,0,COLUMN()) -> 184778.8 | E6: =INDEX(SP_CS_StockPrice,0,COLUMN())*INDEX(SP_CS_ShareCount_EoP_Diluted,0,COLUMN()) -> 212318 | F6: =INDEX(SP_CS_StockPrice,0,COLUMN())*INDEX(SP_CS_ShareCount_EoP_Diluted,0,COLUMN()) -> 208745.56 | G6: =INDEX(SP_CS_StockPrice,0,COLUMN())*INDEX(SP_CS_ShareCount_EoP_Diluted,0,COLUMN()) -> 232161.78 | H6: =INDEX(SP_CS_StockPrice,0,COLUMN())*INDEX(SP_CS_ShareCount_EoP_Diluted,0,COLUMN()) -> 230457.18 | I6: =INDEX(SP_CS_StockPrice,0,COLUMN())*INDEX(SP_CS_ShareCount_EoP_Diluted,0,COLUMN()) -> 237793.69 | J6: =INDEX(SP_CS_StockPrice,0,COLUMN())*INDEX(SP_CS_ShareCount_EoP_Diluted,0,COLUMN()) -> 239639.31 | ... CF6: =INDEX(SP_CS_StockPrice,0,COLUMN())*INDEX(SP_CS_ShareCount_EoP_Diluted,0,COLUMN()) -> 367389.5
A7: =+INDEX(MO_BSS_WC,0,COLUMN()) -> WC Sur/Def, ex Cash & STD | C7: =+INDEX(MO_BSS_WC,0,COLUMN()) -> 2567 | D7: =+INDEX(MO_BSS_WC,0,COLUMN()) -> 2946 | E7: =+INDEX(MO_BSS_WC,0,COLUMN()) -> -97 | F7: =+INDEX(MO_BSS_WC,0,COLUMN()) -> -278 | G7: =+INDEX(MO_BSS_WC,0,COLUMN()) -> 3053 | H7: =+INDEX(MO_BSS_WC,0,COLUMN()) -> 2308 | I7: =+INDEX(MO_BSS_WC,0,COLUMN()) -> 1980 | J7: =+INDEX(MO_BSS_WC,0,COLUMN()) -> 1090 | ... CF7: =+INDEX(MO_BSS_WC,0,COLUMN()) -> 3492
A8: =INDEX(MO_BSS_Cash,0,COLUMN()) -> Cash | C8: =INDEX(MO_BSS_Cash,0,COLUMN()) -> 8822 | D8: =INDEX(MO_BSS_Cash,0,COLUMN()) -> 17070 | E8: =INDEX(MO_BSS_Cash,0,COLUMN()) -> 20071 | F8: =INDEX(MO_BSS_Cash,0,COLUMN()) -> 21913 | G8: =INDEX(MO_BSS_Cash,0,COLUMN()) -> 19048 | H8: =INDEX(MO_BSS_Cash,0,COLUMN()) -> 22296 | I8: =INDEX(MO_BSS_Cash,0,COLUMN()) -> 18580 | J8: =INDEX(MO_BSS_Cash,0,COLUMN()) -> 16516 | ... CF8: =INDEX(MO_BSS_Cash,0,COLUMN()) -> 75752.979
A9: =INDEX(MO_BSS_Debt,0,COLUMN()) -> Debt | C9: =INDEX(MO_BSS_Debt,0,COLUMN()) -> 10514 | D9: =INDEX(MO_BSS_Debt,0,COLUMN()) -> 11476 | E9: =INDEX(MO_BSS_Debt,0,COLUMN()) -> 10152 | F9: =INDEX(MO_BSS_Debt,0,COLUMN()) -> 12192 | G9: =INDEX(MO_BSS_Debt,0,COLUMN()) -> 14143 | H9: =INDEX(MO_BSS_Debt,0,COLUMN()) -> 19964 | I9: =INDEX(MO_BSS_Debt,0,COLUMN()) -> 18581 | J9: =INDEX(MO_BSS_Debt,0,COLUMN()) -> 20431 | ... CF9: =INDEX(MO_BSS_Debt,0,COLUMN()) -> 45428
A10: Other EV Components | C10: =INDEX(MO_VA_EVCalc_NCI,0,COLUMN())+INDEX(MO_VA_EVCalc_Prefs,0,COLUMN())+INDEX(MO_VA_EVCalc_Other,0,COLUMN()) -> 7106 | D10: =INDEX(MO_VA_EVCalc_NCI,0,COLUMN())+INDEX(MO_VA_EVCalc_Prefs,0,COLUMN())+INDEX(MO_VA_EVCalc_Other,0,COLUMN()) -> 7115 | E10: =INDEX(MO_VA_EVCalc_NCI,0,COLUMN())+INDEX(MO_VA_EVCalc_Prefs,0,COLUMN())+INDEX(MO_VA_EVCalc_Other,0,COLUMN()) -> 9657 | F10: =INDEX(MO_VA_EVCalc_NCI,0,COLUMN())+INDEX(MO_VA_EVCalc_Prefs,0,COLUMN())+INDEX(MO_VA_EVCalc_Other,0,COLUMN()) -> 10725 | G10: =INDEX(MO_VA_EVCalc_NCI,0,COLUMN())+INDEX(MO_VA_EVCalc_Prefs,0,COLUMN())+INDEX(MO_VA_EVCalc_Other,0,COLUMN()) -> 10607 | H10: =INDEX(MO_VA_EVCalc_NCI,0,COLUMN())+INDEX(MO_VA_EVCalc_Prefs,0,COLUMN())+INDEX(MO_VA_EVCalc_Other,0,COLUMN()) -> 10343 | I10: =INDEX(MO_VA_EVCalc_NCI,0,COLUMN())+INDEX(MO_VA_EVCalc_Prefs,0,COLUMN())+INDEX(MO_VA_EVCalc_Other,0,COLUMN()) -> 10125 | J10: =INDEX(MO_VA_EVCalc_NCI,0,COLUMN())+INDEX(MO_VA_EVCalc_Prefs,0,COLUMN())+INDEX(MO_VA_EVCalc_Other,0,COLUMN()) -> 7042 | ... CF10: =INDEX(MO_VA_EVCalc_NCI,0,COLUMN())+INDEX(MO_VA_EVCalc_Prefs,0,COLUMN())+INDEX(MO_VA_EVCalc_Other,0,COLUMN()) -> 9529
A11: ="Enterprise Value - "&SP.ValuationToggle -> Enterprise Value - EoP | C11: =INDEX(SP_CS_MarketCap,0,COLUMN())-INDEX(SP_CS_Cash,0,COLUMN())+INDEX(SP_CS_Debt,0,COLUMN())+INDEX(SP_CS_EVCalc_Other,0,COLUMN())-INDEX(SP_CS_WC,0,COLUMN()) -> 162829.45 | D11: =INDEX(SP_CS_MarketCap,0,COLUMN())-INDEX(SP_CS_Cash,0,COLUMN())+INDEX(SP_CS_Debt,0,COLUMN())+INDEX(SP_CS_EVCalc_Other,0,COLUMN())-INDEX(SP_CS_WC,0,COLUMN()) -> 183353.8 | E11: =INDEX(SP_CS_MarketCap,0,COLUMN())-INDEX(SP_CS_Cash,0,COLUMN())+INDEX(SP_CS_Debt,0,COLUMN())+INDEX(SP_CS_EVCalc_Other,0,COLUMN())-INDEX(SP_CS_WC,0,COLUMN()) -> 212153 | F11: =INDEX(SP_CS_MarketCap,0,COLUMN())-INDEX(SP_CS_Cash,0,COLUMN())+INDEX(SP_CS_Debt,0,COLUMN())+INDEX(SP_CS_EVCalc_Other,0,COLUMN())-INDEX(SP_CS_WC,0,COLUMN()) -> 210027.56 | G11: =INDEX(SP_CS_MarketCap,0,COLUMN())-INDEX(SP_CS_Cash,0,COLUMN())+INDEX(SP_CS_Debt,0,COLUMN())+INDEX(SP_CS_EVCalc_Other,0,COLUMN())-INDEX(SP_CS_WC,0,COLUMN()) -> 234810.78 | H11: =INDEX(SP_CS_MarketCap,0,COLUMN())-INDEX(SP_CS_Cash,0,COLUMN())+INDEX(SP_CS_Debt,0,COLUMN())+INDEX(SP_CS_EVCalc_Other,0,COLUMN())-INDEX(SP_CS_WC,0,COLUMN()) -> 236160.18 | I11: =INDEX(SP_CS_MarketCap,0,COLUMN())-INDEX(SP_CS_Cash,0,COLUMN())+INDEX(SP_CS_Debt,0,COLUMN())+INDEX(SP_CS_EVCalc_Other,0,COLUMN())-INDEX(SP_CS_WC,0,COLUMN()) -> 245939.69 | J11: =INDEX(SP_CS_MarketCap,0,COLUMN())-INDEX(SP_CS_Cash,0,COLUMN())+INDEX(SP_CS_Debt,0,COLUMN())+INDEX(SP_CS_EVCalc_Other,0,COLUMN())-INDEX(SP_CS_WC,0,COLUMN()) -> 249506.31 | ... CF11: =INDEX(SP_CS_MarketCap,0,COLUMN())-INDEX(SP_CS_Cash,0,COLUMN())+INDEX(SP_CS_Debt,0,COLUMN())+INDEX(SP_CS_EVCalc_Other,0,COLUMN())-INDEX(SP_CS_WC,0,COLUMN()) -> 343101.52
A13: Company-Specific Operational Data
A14: =+Model!A97 -> Upstream US Earnings, mm | C14: =+Model!C97 -> 2262 | D14: =+Model!D97 -> 4122 | E14: =+Model!E97 -> 6512 | F14: =+Model!F97 -> 5332 | G14: =+Model!G97 -> 1132 | H14: =+Model!H97 -> 1083 | I14: =+Model!I97 -> 1026 | J14: =+Model!J97 -> 803 | ... CF14: =+Model!CF97 -> 0
A15: =+Model!A98 -> Upstream International Earnings, mm | C15: =+Model!C98 -> 8670 | D15: =+Model!D98 -> 13555 | E15: =+Model!E98 -> 18274 | F15: =+Model!F98 -> 18456 | G15: =+Model!G98 -> 4784 | H15: =+Model!H98 -> 3866 | I15: =+Model!I98 -> 4066 | J15: =+Model!J98 -> 4049 | ... CF15: =+Model!CF98 -> 0
A16: =+Model!A99 -> Upstream Earnings, mm | C16: =+Model!C99 -> 10932 | D16: =+Model!D99 -> 17677 | E16: =+Model!E99 -> 24786 | F16: =+Model!F99 -> 23788 | G16: =+Model!G99 -> 5916 | H16: =+Model!H99 -> 4949 | I16: =+Model!I99 -> 5092 | J16: =+Model!J99 -> 4852 | ... CF16: =+Model!CF99 -> 0
A18: =+Model!A241 -> US Downstream Earnings, mm | C18: =+Model!C241 -> -121 | D18: =+Model!D241 -> 1339 | E18: =+Model!E241 -> 1506 | F18: =+Model!F241 -> 2048 | G18: =+Model!G241 -> 135 | H18: =+Model!H241 -> 138 | I18: =+Model!I241 -> 249 | J18: =+Model!J241 -> 265 | ... CF18: =+Model!CF241 -> 0
A19: =+Model!A242 -> International Downstream Earnings, mm | C19: =+Model!C242 -> 594 | D19: =+Model!D242 -> 1139 | E19: =+Model!E242 -> 2085 | F19: =+Model!F242 -> 2251 | G19: =+Model!G242 -> 566 | H19: =+Model!H242 -> 628 | I19: =+Model!I242 -> 131 | J19: =+Model!J242 -> 125 | ... CF19: =+Model!CF242 -> 0
A20: =+Model!A243 -> Total Downstream Earnings, mm | C20: =+Model!C243 -> 473 | D20: =+Model!D243 -> 2478 | E20: =+Model!E243 -> 3591 | F20: =+Model!F243 -> 4299 | G20: =+Model!G243 -> 701 | H20: =+Model!H243 -> 766 | I20: =+Model!I243 -> 380 | J20: =+Model!J243 -> 390 | ... CF20: =+Model!CF243 -> 0
A22: =+Model!A260 -> All other earnings, mm | C22: =+Model!C260 -> -922 | D22: =+Model!D260 -> -1131 | E22: =+Model!E260 -> -1482 | F22: =+Model!F260 -> -1908 | G22: =+Model!G260 -> -439 | H22: =+Model!H260 -> -350 | I22: =+Model!I260 -> -522 | J22: =+Model!J260 -> -312 | ... CF22: =+Model!CF260 -> 0
A24: GAAP Financials
A25: =INDEX(MO_RIS_REV,0,COLUMN()) -> Net Revenue | C25: =INDEX(MO_RIS_REV,0,COLUMN()) -> 171636 | D25: =INDEX(MO_RIS_REV,0,COLUMN()) -> 204928 | E25: =INDEX(MO_RIS_REV,0,COLUMN()) -> 253706 | F25: =INDEX(MO_RIS_REV,0,COLUMN()) -> 241909 | G25: =INDEX(MO_RIS_REV,0,COLUMN()) -> 56818 | H25: =INDEX(MO_RIS_REV,0,COLUMN()) -> 57369 | I25: =INDEX(MO_RIS_REV,0,COLUMN()) -> 58503 | J25: =INDEX(MO_RIS_REV,0,COLUMN()) -> 56158 | ... CF25: =INDEX(MO_RIS_REV,0,COLUMN()) -> 197660.48
A26: =INDEX(MO_RIS_ExciseTax_AdValorem,0,COLUMN()) -> Taxes other than on income | C26: =INDEX(MO_RIS_ExciseTax_AdValorem,0,COLUMN()) -> 17591 | D26: =INDEX(MO_RIS_ExciseTax_AdValorem,0,COLUMN()) -> 18191 | E26: =INDEX(MO_RIS_ExciseTax_AdValorem,0,COLUMN()) -> 15628 | F26: =INDEX(MO_RIS_ExciseTax_AdValorem,0,COLUMN()) -> 12376 | G26: =INDEX(MO_RIS_ExciseTax_AdValorem,0,COLUMN()) -> 3137 | H26: =INDEX(MO_RIS_ExciseTax_AdValorem,0,COLUMN()) -> 3349 | I26: =INDEX(MO_RIS_ExciseTax_AdValorem,0,COLUMN()) -> 3366 | J26: =INDEX(MO_RIS_ExciseTax_AdValorem,0,COLUMN()) -> 3211 | ... CF26: =INDEX(MO_RIS_ExciseTax_AdValorem,0,COLUMN()) -> 3953.2096
A27: =INDEX(MO_RIS_SGA,0,COLUMN()) -> SG&A | C27: =INDEX(MO_RIS_SGA,0,COLUMN()) -> 4527 | D27: =INDEX(MO_RIS_SGA,0,COLUMN()) -> 4767 | E27: =INDEX(MO_RIS_SGA,0,COLUMN()) -> 4745 | F27: =INDEX(MO_RIS_SGA,0,COLUMN()) -> 4724 | G27: =INDEX(MO_RIS_SGA,0,COLUMN()) -> 998 | H27: =INDEX(MO_RIS_SGA,0,COLUMN()) -> 1139 | I27: =INDEX(MO_RIS_SGA,0,COLUMN()) -> 1197 | J27: =INDEX(MO_RIS_SGA,0,COLUMN()) -> 1176 | ... CF27: =INDEX(MO_RIS_SGA,0,COLUMN()) -> 3953.2096
A28: =INDEX(MO_RIS_OPEX,0,COLUMN()) -> Operating expenses | C28: =INDEX(MO_RIS_OPEX,0,COLUMN()) -> 17857 | D28: =INDEX(MO_RIS_OPEX,0,COLUMN()) -> 19188 | E28: =INDEX(MO_RIS_OPEX,0,COLUMN()) -> 21649 | F28: =INDEX(MO_RIS_OPEX,0,COLUMN()) -> 22570 | G28: =INDEX(MO_RIS_OPEX,0,COLUMN()) -> 5762 | H28: =INDEX(MO_RIS_OPEX,0,COLUMN()) -> 6278 | I28: =INDEX(MO_RIS_OPEX,0,COLUMN()) -> 6066 | J28: =INDEX(MO_RIS_OPEX,0,COLUMN()) -> 6521 | ... CF28: =INDEX(MO_RIS_OPEX,0,COLUMN()) -> 25695.863
A29: =INDEX(MO_RIS_COGS,0,COLUMN()) -> COGS | C29: =INDEX(MO_RIS_COGS,0,COLUMN()) -> 99653 | D29: =INDEX(MO_RIS_COGS,0,COLUMN()) -> 116467 | E29: =INDEX(MO_RIS_COGS,0,COLUMN()) -> 149923 | F29: =INDEX(MO_RIS_COGS,0,COLUMN()) -> 140766 | G29: =INDEX(MO_RIS_COGS,0,COLUMN()) -> 32910 | H29: =INDEX(MO_RIS_COGS,0,COLUMN()) -> 34273 | I29: =INDEX(MO_RIS_COGS,0,COLUMN()) -> 34822 | J29: =INDEX(MO_RIS_COGS,0,COLUMN()) -> 32691 | ... CF29: =INDEX(MO_RIS_COGS,0,COLUMN()) -> 108713.27
A30: =INDEX(MO_RIS_EBITDAX,0,COLUMN()) -> EBITDAX | C30: =IFERROR(INDEX(SP_GF_Rev,0,COLUMN()),0)-IFERROR(INDEX(SP_GF_COGS,0,COLUMN()),0)-IFERROR(INDEX(SP_GF_SGA,0,COLUMN()),0)-IFERROR(INDEX(SP_GF_SM,0,COLUMN()),0)-IFERROR(INDEX(SP_GF_GA,0,COLUMN()),0)-IFERROR(INDEX(SP_GF_OPEX,0,COLUMN()),0)-IFERROR(INDEX(SP_GF_RD,0,COLUMN()),0)-IFERROR(INDEX(SP_GF_ExciseTax,0,COLUMN()),0)-IFERROR(INDEX(SP_GF_ProductionCost,0,COLUMN()),0) -> 32008 | D30: =IFERROR(INDEX(SP_GF_Rev,0,COLUMN()),0)-IFERROR(INDEX(SP_GF_COGS,0,COLUMN()),0)-IFERROR(INDEX(SP_GF_SGA,0,COLUMN()),0)-IFERROR(INDEX(SP_GF_SM,0,COLUMN()),0)-IFERROR(INDEX(SP_GF_GA,0,COLUMN()),0)-IFERROR(INDEX(SP_GF_OPEX,0,COLUMN()),0)-IFERROR(INDEX(SP_GF_RD,0,COLUMN()),0)-IFERROR(INDEX(SP_GF_ExciseTax,0,COLUMN()),0)-IFERROR(INDEX(SP_GF_ProductionCost,0,COLUMN()),0) -> 46315 | E30: =IFERROR(INDEX(SP_GF_Rev,0,COLUMN()),0)-IFERROR(INDEX(SP_GF_COGS,0,COLUMN()),0)-IFERROR(INDEX(SP_GF_SGA,0,COLUMN()),0)-IFERROR(INDEX(SP_GF_SM,0,COLUMN()),0)-IFERROR(INDEX(SP_GF_GA,0,COLUMN()),0)-IFERROR(INDEX(SP_GF_OPEX,0,COLUMN()),0)-IFERROR(INDEX(SP_GF_RD,0,COLUMN()),0)-IFERROR(INDEX(SP_GF_ExciseTax,0,COLUMN()),0)-IFERROR(INDEX(SP_GF_ProductionCost,0,COLUMN()),0) -> 61761 | F30: =IFERROR(INDEX(SP_GF_Rev,0,COLUMN()),0)-IFERROR(INDEX(SP_GF_COGS,0,COLUMN()),0)-IFERROR(INDEX(SP_GF_SGA,0,COLUMN()),0)-IFERROR(INDEX(SP_GF_SM,0,COLUMN()),0)-IFERROR(INDEX(SP_GF_GA,0,COLUMN()),0)-IFERROR(INDEX(SP_GF_OPEX,0,COLUMN()),0)-IFERROR(INDEX(SP_GF_RD,0,COLUMN()),0)-IFERROR(INDEX(SP_GF_ExciseTax,0,COLUMN()),0)-IFERROR(INDEX(SP_GF_ProductionCost,0,COLUMN()),0) -> 61473 | G30: =IFERROR(INDEX(SP_GF_Rev,0,COLUMN()),0)-IFERROR(INDEX(SP_GF_COGS,0,COLUMN()),0)-IFERROR(INDEX(SP_GF_SGA,0,COLUMN()),0)-IFERROR(INDEX(SP_GF_SM,0,COLUMN()),0)-IFERROR(INDEX(SP_GF_GA,0,COLUMN()),0)-IFERROR(INDEX(SP_GF_OPEX,0,COLUMN()),0)-IFERROR(INDEX(SP_GF_RD,0,COLUMN()),0)-IFERROR(INDEX(SP_GF_ExciseTax,0,COLUMN()),0)-IFERROR(INDEX(SP_GF_ProductionCost,0,COLUMN()),0) -> 14011 | H30: =IFERROR(INDEX(SP_GF_Rev,0,COLUMN()),0)-IFERROR(INDEX(SP_GF_COGS,0,COLUMN()),0)-IFERROR(INDEX(SP_GF_SGA,0,COLUMN()),0)-IFERROR(INDEX(SP_GF_SM,0,COLUMN()),0)-IFERROR(INDEX(SP_GF_GA,0,COLUMN()),0)-IFERROR(INDEX(SP_GF_OPEX,0,COLUMN()),0)-IFERROR(INDEX(SP_GF_RD,0,COLUMN()),0)-IFERROR(INDEX(SP_GF_ExciseTax,0,COLUMN()),0)-IFERROR(INDEX(SP_GF_ProductionCost,0,COLUMN()),0) -> 12330 | I30: =IFERROR(INDEX(SP_GF_Rev,0,COLUMN()),0)-IFERROR(INDEX(SP_GF_COGS,0,COLUMN()),0)-IFERROR(INDEX(SP_GF_SGA,0,COLUMN()),0)-IFERROR(INDEX(SP_GF_SM,0,COLUMN()),0)-IFERROR(INDEX(SP_GF_GA,0,COLUMN()),0)-IFERROR(INDEX(SP_GF_OPEX,0,COLUMN()),0)-IFERROR(INDEX(SP_GF_RD,0,COLUMN()),0)-IFERROR(INDEX(SP_GF_ExciseTax,0,COLUMN()),0)-IFERROR(INDEX(SP_GF_ProductionCost,0,COLUMN()),0) -> 13052 | J30: =IFERROR(INDEX(SP_GF_Rev,0,COLUMN()),0)-IFERROR(INDEX(SP_GF_COGS,0,COLUMN()),0)-IFERROR(INDEX(SP_GF_SGA,0,COLUMN()),0)-IFERROR(INDEX(SP_GF_SM,0,COLUMN()),0)-IFERROR(INDEX(SP_GF_GA,0,COLUMN()),0)-IFERROR(INDEX(SP_GF_OPEX,0,COLUMN()),0)-IFERROR(INDEX(SP_GF_RD,0,COLUMN()),0)-IFERROR(INDEX(SP_GF_ExciseTax,0,COLUMN()),0)-IFERROR(INDEX(SP_GF_ProductionCost,0,COLUMN()),0) -> 12559 | ... CF30: =IFERROR(INDEX(SP_GF_Rev,0,COLUMN()),0)-IFERROR(INDEX(SP_GF_COGS,0,COLUMN()),0)-IFERROR(INDEX(SP_GF_SGA,0,COLUMN()),0)-IFERROR(INDEX(SP_GF_SM,0,COLUMN()),0)-IFERROR(INDEX(SP_GF_GA,0,COLUMN()),0)-IFERROR(INDEX(SP_GF_OPEX,0,COLUMN()),0)-IFERROR(INDEX(SP_GF_RD,0,COLUMN()),0)-IFERROR(INDEX(SP_GF_ExciseTax,0,COLUMN()),0)-IFERROR(INDEX(SP_GF_ProductionCost,0,COLUMN()),0) -> 55344.935
A31: =INDEX(MO_RIS_EE,0,COLUMN()) -> Exploration Expense | C31: =INDEX(MO_RIS_EE,0,COLUMN()) -> 1342 | D31: =INDEX(MO_RIS_EE,0,COLUMN()) -> 1147 | E31: =INDEX(MO_RIS_EE,0,COLUMN()) -> 1216 | F31: =INDEX(MO_RIS_EE,0,COLUMN()) -> 1728 | G31: =INDEX(MO_RIS_EE,0,COLUMN()) -> 247 | H31: =INDEX(MO_RIS_EE,0,COLUMN()) -> 329 | I31: =INDEX(MO_RIS_EE,0,COLUMN()) -> 559 | J31: =INDEX(MO_RIS_EE,0,COLUMN()) -> 726 | ... CF31: =INDEX(MO_RIS_EE,0,COLUMN()) -> 2400
A32: =INDEX(MO_RIS_DA,0,COLUMN()) -> DD&A | C32: =IFERROR(INDEX(MO_RIS_DA,0,COLUMN()),0)+IFERROR(INDEX(MO_RIS_DAintangible,0,COLUMN()),0)+IFERROR(INDEX(MO_RIS_DAintangibles,0,COLUMN()),0) -> 12110 | D32: =IFERROR(INDEX(MO_RIS_DA,0,COLUMN()),0)+IFERROR(INDEX(MO_RIS_DAintangible,0,COLUMN()),0)+IFERROR(INDEX(MO_RIS_DAintangibles,0,COLUMN()),0) -> 13063 | E32: =IFERROR(INDEX(MO_RIS_DA,0,COLUMN()),0)+IFERROR(INDEX(MO_RIS_DAintangible,0,COLUMN()),0)+IFERROR(INDEX(MO_RIS_DAintangibles,0,COLUMN()),0) -> 12911 | F32: =IFERROR(INDEX(MO_RIS_DA,0,COLUMN()),0)+IFERROR(INDEX(MO_RIS_DAintangible,0,COLUMN()),0)+IFERROR(INDEX(MO_RIS_DAintangibles,0,COLUMN()),0) -> 13413 | G32: =IFERROR(INDEX(MO_RIS_DA,0,COLUMN()),0)+IFERROR(INDEX(MO_RIS_DAintangible,0,COLUMN()),0)+IFERROR(INDEX(MO_RIS_DAintangibles,0,COLUMN()),0) -> 3481 | H32: =IFERROR(INDEX(MO_RIS_DA,0,COLUMN()),0)+IFERROR(INDEX(MO_RIS_DAintangible,0,COLUMN()),0)+IFERROR(INDEX(MO_RIS_DAintangibles,0,COLUMN()),0) -> 3412 | I32: =IFERROR(INDEX(MO_RIS_DA,0,COLUMN()),0)+IFERROR(INDEX(MO_RIS_DAintangible,0,COLUMN()),0)+IFERROR(INDEX(MO_RIS_DAintangibles,0,COLUMN()),0) -> 3658 | J32: =IFERROR(INDEX(MO_RIS_DA,0,COLUMN()),0)+IFERROR(INDEX(MO_RIS_DAintangible,0,COLUMN()),0)+IFERROR(INDEX(MO_RIS_DAintangibles,0,COLUMN()),0) -> 3635 | ... CF32: =IFERROR(INDEX(MO_RIS_DA,0,COLUMN()),0)+IFERROR(INDEX(MO_RIS_DAintangible,0,COLUMN()),0)+IFERROR(INDEX(MO_RIS_DAintangibles,0,COLUMN()),0) -> 26000
A33: =INDEX(MO_RIS_IE,0,COLUMN()) -> Interest expense | C33: =IFERROR(INDEX(MO_RIS_IE_Net,0,COLUMN()),INDEX(MO_RIS_IE,0,COLUMN())+INDEX(MO_RIS_II,0,COLUMN())) -> 28 | D33: =IFERROR(INDEX(MO_RIS_IE_Net,0,COLUMN()),INDEX(MO_RIS_IE,0,COLUMN())+INDEX(MO_RIS_II,0,COLUMN())) -> 50 | E33: =IFERROR(INDEX(MO_RIS_IE_Net,0,COLUMN()),INDEX(MO_RIS_IE,0,COLUMN())+INDEX(MO_RIS_II,0,COLUMN())) -> 0 | F33: =IFERROR(INDEX(MO_RIS_IE_Net,0,COLUMN()),INDEX(MO_RIS_IE,0,COLUMN())+INDEX(MO_RIS_II,0,COLUMN())) -> 0 | G33: =IFERROR(INDEX(MO_RIS_IE_Net,0,COLUMN()),INDEX(MO_RIS_IE,0,COLUMN())+INDEX(MO_RIS_II,0,COLUMN())) -> 0 | H33: =IFERROR(INDEX(MO_RIS_IE_Net,0,COLUMN()),INDEX(MO_RIS_IE,0,COLUMN())+INDEX(MO_RIS_II,0,COLUMN())) -> 0 | I33: =IFERROR(INDEX(MO_RIS_IE_Net,0,COLUMN()),INDEX(MO_RIS_IE,0,COLUMN())+INDEX(MO_RIS_II,0,COLUMN())) -> 0 | J33: =IFERROR(INDEX(MO_RIS_IE_Net,0,COLUMN()),INDEX(MO_RIS_IE,0,COLUMN())+INDEX(MO_RIS_II,0,COLUMN())) -> 0 | ... CF33: =IFERROR(INDEX(MO_RIS_IE_Net,0,COLUMN()),INDEX(MO_RIS_IE,0,COLUMN())+INDEX(MO_RIS_II,0,COLUMN())) -> 1135.7
A34: =INDEX(MO_RIS_Impairment,0,COLUMN()) -> Impairment | C34: =INDEX(MO_RIS_Impairment,0,COLUMN()) -> 0 | D34: =INDEX(MO_RIS_Impairment,0,COLUMN()) -> 0 | E34: =INDEX(MO_RIS_Impairment,0,COLUMN()) -> 0 | F34: =INDEX(MO_RIS_Impairment,0,COLUMN()) -> 0 | G34: =INDEX(MO_RIS_Impairment,0,COLUMN()) -> 0 | H34: =INDEX(MO_RIS_Impairment,0,COLUMN()) -> 0 | I34: =INDEX(MO_RIS_Impairment,0,COLUMN()) -> 0 | J34: =INDEX(MO_RIS_Impairment,0,COLUMN()) -> 0 | ... CF34: =INDEX(MO_RIS_Impairment,0,COLUMN()) -> 0
A35: =INDEX(MO_RIS_EBT,0,COLUMN()) -> EBT | C35: =INDEX(SP_GF_EBITDAX,0,COLUMN())-INDEX(SP_GF_DA,0,COLUMN())-INDEX(SP_GF_IE,0,COLUMN())-INDEX(SP_GF_ExplorationExpense,0,COLUMN())-INDEX(SP_GF_Impairment,0,COLUMN()) -> 18528 | D35: =INDEX(SP_GF_EBITDAX,0,COLUMN())-INDEX(SP_GF_DA,0,COLUMN())-INDEX(SP_GF_IE,0,COLUMN())-INDEX(SP_GF_ExplorationExpense,0,COLUMN())-INDEX(SP_GF_Impairment,0,COLUMN()) -> 32055 | E35: =INDEX(SP_GF_EBITDAX,0,COLUMN())-INDEX(SP_GF_DA,0,COLUMN())-INDEX(SP_GF_IE,0,COLUMN())-INDEX(SP_GF_ExplorationExpense,0,COLUMN())-INDEX(SP_GF_Impairment,0,COLUMN()) -> 47634 | F35: =INDEX(SP_GF_EBITDAX,0,COLUMN())-INDEX(SP_GF_DA,0,COLUMN())-INDEX(SP_GF_IE,0,COLUMN())-INDEX(SP_GF_ExplorationExpense,0,COLUMN())-INDEX(SP_GF_Impairment,0,COLUMN()) -> 46332 | G35: =INDEX(SP_GF_EBITDAX,0,COLUMN())-INDEX(SP_GF_DA,0,COLUMN())-INDEX(SP_GF_IE,0,COLUMN())-INDEX(SP_GF_ExplorationExpense,0,COLUMN())-INDEX(SP_GF_Impairment,0,COLUMN()) -> 10283 | H35: =INDEX(SP_GF_EBITDAX,0,COLUMN())-INDEX(SP_GF_DA,0,COLUMN())-INDEX(SP_GF_IE,0,COLUMN())-INDEX(SP_GF_ExplorationExpense,0,COLUMN())-INDEX(SP_GF_Impairment,0,COLUMN()) -> 8589 | I35: =INDEX(SP_GF_EBITDAX,0,COLUMN())-INDEX(SP_GF_DA,0,COLUMN())-INDEX(SP_GF_IE,0,COLUMN())-INDEX(SP_GF_ExplorationExpense,0,COLUMN())-INDEX(SP_GF_Impairment,0,COLUMN()) -> 8835 | J35: =INDEX(SP_GF_EBITDAX,0,COLUMN())-INDEX(SP_GF_DA,0,COLUMN())-INDEX(SP_GF_IE,0,COLUMN())-INDEX(SP_GF_ExplorationExpense,0,COLUMN())-INDEX(SP_GF_Impairment,0,COLUMN()) -> 8198 | ... CF35: =INDEX(SP_GF_EBITDAX,0,COLUMN())-INDEX(SP_GF_DA,0,COLUMN())-INDEX(SP_GF_IE,0,COLUMN())-INDEX(SP_GF_ExplorationExpense,0,COLUMN())-INDEX(SP_GF_Impairment,0,COLUMN()) -> 25809.235
A36: Tax | C36: =INDEX(MO_RIS_Tax_Current,0,COLUMN())+INDEX(MO_RIS_Tax_Deferred,0,COLUMN()) -> 7965 | D36: =INDEX(MO_RIS_Tax_Current,0,COLUMN())+INDEX(MO_RIS_Tax_Deferred,0,COLUMN()) -> 12919 | E36: =INDEX(MO_RIS_Tax_Current,0,COLUMN())+INDEX(MO_RIS_Tax_Deferred,0,COLUMN()) -> 20626 | F36: =INDEX(MO_RIS_Tax_Current,0,COLUMN())+INDEX(MO_RIS_Tax_Deferred,0,COLUMN()) -> 19996 | G36: =INDEX(MO_RIS_Tax_Current,0,COLUMN())+INDEX(MO_RIS_Tax_Deferred,0,COLUMN()) -> 4044 | H36: =INDEX(MO_RIS_Tax_Current,0,COLUMN())+INDEX(MO_RIS_Tax_Deferred,0,COLUMN()) -> 3185 | I36: =INDEX(MO_RIS_Tax_Current,0,COLUMN())+INDEX(MO_RIS_Tax_Deferred,0,COLUMN()) -> 3839 | J36: =INDEX(MO_RIS_Tax_Current,0,COLUMN())+INDEX(MO_RIS_Tax_Deferred,0,COLUMN()) -> 3240 | ... CF36: =INDEX(MO_RIS_Tax_Current,0,COLUMN())+INDEX(MO_RIS_Tax_Deferred,0,COLUMN()) -> 9549.417
A37: =INDEX(MO_RIS_DisCont,0,COLUMN()) -> Discontinued Operations | C37: =INDEX(MO_RIS_DisCont,0,COLUMN()) -> 0 | D37: =INDEX(MO_RIS_DisCont,0,COLUMN()) -> 0 | E37: =INDEX(MO_RIS_DisCont,0,COLUMN()) -> 0 | F37: =INDEX(MO_RIS_DisCont,0,COLUMN()) -> 0 | G37: =INDEX(MO_RIS_DisCont,0,COLUMN()) -> 0 | H37: =INDEX(MO_RIS_DisCont,0,COLUMN()) -> 0 | I37: =INDEX(MO_RIS_DisCont,0,COLUMN()) -> 0 | J37: =INDEX(MO_RIS_DisCont,0,COLUMN()) -> 0 | ... CF37: =INDEX(MO_RIS_DisCont,0,COLUMN()) -> 0
A38: =INDEX(MO_RIS_NCI,0,COLUMN()) -> Net Income to NCI | C38: =INDEX(MO_RIS_NCI,0,COLUMN()) -> 80 | D38: =INDEX(MO_RIS_NCI,0,COLUMN()) -> 112 | E38: =INDEX(MO_RIS_NCI,0,COLUMN()) -> 113 | F38: =INDEX(MO_RIS_NCI,0,COLUMN()) -> 157 | G38: =INDEX(MO_RIS_NCI,0,COLUMN()) -> 61 | H38: =INDEX(MO_RIS_NCI,0,COLUMN()) -> 39 | I38: =INDEX(MO_RIS_NCI,0,COLUMN()) -> 46 | J38: =INDEX(MO_RIS_NCI,0,COLUMN()) -> 28 | ... CF38: =INDEX(MO_RIS_NCI,0,COLUMN()) -> 40
A39: =INDEX(MO_RIS_Dividend_Prefs,0,COLUMN()) -> Earnings to Preferred and Other Securities | C39: =INDEX(MO_RIS_Dividend_Prefs,0,COLUMN()) -> 0 | D39: =INDEX(MO_RIS_Dividend_Prefs,0,COLUMN()) -> 0 | E39: =INDEX(MO_RIS_Dividend_Prefs,0,COLUMN()) -> 0 | F39: =INDEX(MO_RIS_Dividend_Prefs,0,COLUMN()) -> 0 | G39: =INDEX(MO_RIS_Dividend_Prefs,0,COLUMN()) -> 0 | H39: =INDEX(MO_RIS_Dividend_Prefs,0,COLUMN()) -> 0 | I39: =INDEX(MO_RIS_Dividend_Prefs,0,COLUMN()) -> 0 | J39: =INDEX(MO_RIS_Dividend_Prefs,0,COLUMN()) -> 0 | ... CF39: =INDEX(MO_RIS_Dividend_Prefs,0,COLUMN()) -> 0
A40: =INDEX(MO_RIS_NI_GAAP_Basic,0,COLUMN()) -> Net Income to Common Shareholders | C40: =INDEX(SP_GF_EBT,0,COLUMN())-INDEX(SP_GF_Tax,0,COLUMN())-INDEX(SP_GF_DisCont,0,COLUMN())-INDEX(SP_GF_NCI,0,COLUMN())-INDEX(SP_GF_Div_Prefs,0,COLUMN()) -> 10483 | D40: =INDEX(SP_GF_EBT,0,COLUMN())-INDEX(SP_GF_Tax,0,COLUMN())-INDEX(SP_GF_DisCont,0,COLUMN())-INDEX(SP_GF_NCI,0,COLUMN())-INDEX(SP_GF_Div_Prefs,0,COLUMN()) -> 19024 | E40: =INDEX(SP_GF_EBT,0,COLUMN())-INDEX(SP_GF_Tax,0,COLUMN())-INDEX(SP_GF_DisCont,0,COLUMN())-INDEX(SP_GF_NCI,0,COLUMN())-INDEX(SP_GF_Div_Prefs,0,COLUMN()) -> 26895 | F40: =INDEX(SP_GF_EBT,0,COLUMN())-INDEX(SP_GF_Tax,0,COLUMN())-INDEX(SP_GF_DisCont,0,COLUMN())-INDEX(SP_GF_NCI,0,COLUMN())-INDEX(SP_GF_Div_Prefs,0,COLUMN()) -> 26179 | G40: =INDEX(SP_GF_EBT,0,COLUMN())-INDEX(SP_GF_Tax,0,COLUMN())-INDEX(SP_GF_DisCont,0,COLUMN())-INDEX(SP_GF_NCI,0,COLUMN())-INDEX(SP_GF_Div_Prefs,0,COLUMN()) -> 6178 | H40: =INDEX(SP_GF_EBT,0,COLUMN())-INDEX(SP_GF_Tax,0,COLUMN())-INDEX(SP_GF_DisCont,0,COLUMN())-INDEX(SP_GF_NCI,0,COLUMN())-INDEX(SP_GF_Div_Prefs,0,COLUMN()) -> 5365 | I40: =INDEX(SP_GF_EBT,0,COLUMN())-INDEX(SP_GF_Tax,0,COLUMN())-INDEX(SP_GF_DisCont,0,COLUMN())-INDEX(SP_GF_NCI,0,COLUMN())-INDEX(SP_GF_Div_Prefs,0,COLUMN()) -> 4950 | J40: =INDEX(SP_GF_EBT,0,COLUMN())-INDEX(SP_GF_Tax,0,COLUMN())-INDEX(SP_GF_DisCont,0,COLUMN())-INDEX(SP_GF_NCI,0,COLUMN())-INDEX(SP_GF_Div_Prefs,0,COLUMN()) -> 4930 | ... CF40: =INDEX(SP_GF_EBT,0,COLUMN())-INDEX(SP_GF_Tax,0,COLUMN())-INDEX(SP_GF_DisCont,0,COLUMN())-INDEX(SP_GF_NCI,0,COLUMN())-INDEX(SP_GF_Div_Prefs,0,COLUMN()) -> 16219.818
A41: =INDEX(MO_RIS_EPS_WAD,0,COLUMN()) -> Earnings Per Share - WAD | C41: =INDEX(MO_RIS_EPS_WAD,0,COLUMN()) -> 5.2388806 | D41: =INDEX(MO_RIS_EPS_WAD,0,COLUMN()) -> 9.4809924 | E41: =INDEX(MO_RIS_EPS_WAD,0,COLUMN()) -> 13.442224 | F41: =INDEX(MO_RIS_EPS_WAD,0,COLUMN()) -> 13.324308 | G41: =INDEX(MO_RIS_EPS_WAD,0,COLUMN()) -> 3.1780963 | H41: =INDEX(MO_RIS_EPS_WAD,0,COLUMN()) -> 2.7700574 | I41: =INDEX(MO_RIS_EPS_WAD,0,COLUMN()) -> 2.5649914 | J41: =INDEX(MO_RIS_EPS_WAD,0,COLUMN()) -> 2.5686127 | ... CF41: =INDEX(MO_RIS_EPS_WAD,0,COLUMN()) -> 8.1745982
A42: =INDEX(MO_RIS_ShareCount_WAD_Adj,0,COLUMN()) -> Adjusted Shares Outstanding - WAD | C42: =INDEX(MO_RIS_ShareCount_WAD_Adj,0,COLUMN()) -> 2001 | D42: =INDEX(MO_RIS_ShareCount_WAD_Adj,0,COLUMN()) -> 2006.541 | E42: =INDEX(MO_RIS_ShareCount_WAD_Adj,0,COLUMN()) -> 2000.785 | F42: =INDEX(MO_RIS_ShareCount_WAD_Adj,0,COLUMN()) -> 1964.755 | G42: =INDEX(MO_RIS_ShareCount_WAD_Adj,0,COLUMN()) -> 1943.931 | H42: =INDEX(MO_RIS_ShareCount_WAD_Adj,0,COLUMN()) -> 1936.783 | I42: =INDEX(MO_RIS_ShareCount_WAD_Adj,0,COLUMN()) -> 1929.831 | J42: =INDEX(MO_RIS_ShareCount_WAD_Adj,0,COLUMN()) -> 1919.324 | ... CF42: =INDEX(MO_RIS_ShareCount_WAD_Adj,0,COLUMN()) -> 1984.1731
A44: Non-GAAP Financials
A45: =INDEX(MO_RIS_EBITDAX_Adj,0,COLUMN()) -> Adjusted EBITDAX (No Adjustments) | C45: =INDEX(MO_RIS_EBITDAX_Adj,0,COLUMN()) -> 32008 | D45: =INDEX(MO_RIS_EBITDAX_Adj,0,COLUMN()) -> 46315 | E45: =INDEX(MO_RIS_EBITDAX_Adj,0,COLUMN()) -> 61761 | F45: =INDEX(MO_RIS_EBITDAX_Adj,0,COLUMN()) -> 61473 | G45: =INDEX(MO_RIS_EBITDAX_Adj,0,COLUMN()) -> 14011 | H45: =INDEX(MO_RIS_EBITDAX_Adj,0,COLUMN()) -> 12330 | I45: =INDEX(MO_RIS_EBITDAX_Adj,0,COLUMN()) -> 13052 | J45: =INDEX(MO_RIS_EBITDAX_Adj,0,COLUMN()) -> 12559 | ... CF45: =INDEX(MO_RIS_EBITDAX_Adj,0,COLUMN()) -> 55344.935
A46: =INDEX(MO_RIS_NI_NONGAAP_Diluted,0,COLUMN()) -> Adjusted Net Income | C46: =INDEX(MO_RIS_NI_NONGAAP_Diluted,0,COLUMN()) -> 10483 | D46: =INDEX(MO_RIS_NI_NONGAAP_Diluted,0,COLUMN()) -> 19024 | E46: =INDEX(MO_RIS_NI_NONGAAP_Diluted,0,COLUMN()) -> 26895 | F46: =INDEX(MO_RIS_NI_NONGAAP_Diluted,0,COLUMN()) -> 26179 | G46: =INDEX(MO_RIS_NI_NONGAAP_Diluted,0,COLUMN()) -> 6178 | H46: =INDEX(MO_RIS_NI_NONGAAP_Diluted,0,COLUMN()) -> 5365 | I46: =INDEX(MO_RIS_NI_NONGAAP_Diluted,0,COLUMN()) -> 4950 | J46: =INDEX(MO_RIS_NI_NONGAAP_Diluted,0,COLUMN()) -> 4930 | ... CF46: =INDEX(MO_RIS_NI_NONGAAP_Diluted,0,COLUMN()) -> 16219.818
A47: =INDEX(MO_RIS_EPS_WAD_Adj,0,COLUMN()) -> Adjusted Earnings Per Share - WAD | C47: =INDEX(MO_RIS_EPS_WAD_Adj,0,COLUMN()) -> 5.2388806 | D47: =INDEX(MO_RIS_EPS_WAD_Adj,0,COLUMN()) -> 9.4809924 | E47: =INDEX(MO_RIS_EPS_WAD_Adj,0,COLUMN()) -> 13.442224 | F47: =INDEX(MO_RIS_EPS_WAD_Adj,0,COLUMN()) -> 13.324308 | G47: =INDEX(MO_RIS_EPS_WAD_Adj,0,COLUMN()) -> 3.1780963 | H47: =INDEX(MO_RIS_EPS_WAD_Adj,0,COLUMN()) -> 2.7700574 | I47: =INDEX(MO_RIS_EPS_WAD_Adj,0,COLUMN()) -> 2.5649914 | J47: =INDEX(MO_RIS_EPS_WAD_Adj,0,COLUMN()) -> 2.5686127 | ... CF47: =INDEX(MO_RIS_EPS_WAD_Adj,0,COLUMN()) -> 8.1745982
A49: Margin Analysis
A50: =INDEX(MO_MA_COGS,0,COLUMN()) -> COGS Margin, % | C50: =INDEX(SP_GF_COGS,0,COLUMN())/INDEX(SP_GF_Rev,0,COLUMN()) -> 0.58060663 | D50: =INDEX(SP_GF_COGS,0,COLUMN())/INDEX(SP_GF_Rev,0,COLUMN()) -> 0.56833132 | E50: =INDEX(SP_GF_COGS,0,COLUMN())/INDEX(SP_GF_Rev,0,COLUMN()) -> 0.59093202 | F50: =INDEX(SP_GF_COGS,0,COLUMN())/INDEX(SP_GF_Rev,0,COLUMN()) -> 0.5818965 | G50: =INDEX(SP_GF_COGS,0,COLUMN())/INDEX(SP_GF_Rev,0,COLUMN()) -> 0.57921785 | H50: =INDEX(SP_GF_COGS,0,COLUMN())/INDEX(SP_GF_Rev,0,COLUMN()) -> 0.59741324 | I50: =INDEX(SP_GF_COGS,0,COLUMN())/INDEX(SP_GF_Rev,0,COLUMN()) -> 0.59521734 | J50: =INDEX(SP_GF_COGS,0,COLUMN())/INDEX(SP_GF_Rev,0,COLUMN()) -> 0.58212543 | ... CF50: =INDEX(SP_GF_COGS,0,COLUMN())/INDEX(SP_GF_Rev,0,COLUMN()) -> 0.55
A51: =INDEX(MO_MA_SGA,0,COLUMN()) -> SG&A Margin, % | C51: =INDEX(SP_GF_SGA,0,COLUMN())/INDEX(SP_GF_Rev,0,COLUMN()) -> 0.026375586 | D51: =INDEX(SP_GF_SGA,0,COLUMN())/INDEX(SP_GF_Rev,0,COLUMN()) -> 0.023261829 | E51: =INDEX(SP_GF_SGA,0,COLUMN())/INDEX(SP_GF_Rev,0,COLUMN()) -> 0.01870275 | F51: =INDEX(SP_GF_SGA,0,COLUMN())/INDEX(SP_GF_Rev,0,COLUMN()) -> 0.019528004 | G51: =INDEX(SP_GF_SGA,0,COLUMN())/INDEX(SP_GF_Rev,0,COLUMN()) -> 0.017564856 | H51: =INDEX(SP_GF_SGA,0,COLUMN())/INDEX(SP_GF_Rev,0,COLUMN()) -> 0.019853928 | I51: =INDEX(SP_GF_SGA,0,COLUMN())/INDEX(SP_GF_Rev,0,COLUMN()) -> 0.020460489 | J51: =INDEX(SP_GF_SGA,0,COLUMN())/INDEX(SP_GF_Rev,0,COLUMN()) -> 0.020940917 | ... CF51: =INDEX(SP_GF_SGA,0,COLUMN())/INDEX(SP_GF_Rev,0,COLUMN()) -> 0.02
A52: =INDEX(MO_MA_ExciseTax,0,COLUMN()) -> Other Taxes Margin, % | C52: =INDEX(SP_GF_ExciseTax,0,COLUMN())/INDEX(SP_GF_Rev,0,COLUMN()) -> 0.10249015 | D52: =INDEX(SP_GF_ExciseTax,0,COLUMN())/INDEX(SP_GF_Rev,0,COLUMN()) -> 0.088767762 | E52: =INDEX(SP_GF_ExciseTax,0,COLUMN())/INDEX(SP_GF_Rev,0,COLUMN()) -> 0.061598859 | F52: =INDEX(SP_GF_ExciseTax,0,COLUMN())/INDEX(SP_GF_Rev,0,COLUMN()) -> 0.051159734 | G52: =INDEX(SP_GF_ExciseTax,0,COLUMN())/INDEX(SP_GF_Rev,0,COLUMN()) -> 0.055211377 | H52: =INDEX(SP_GF_ExciseTax,0,COLUMN())/INDEX(SP_GF_Rev,0,COLUMN()) -> 0.058376475 | I52: =INDEX(SP_GF_ExciseTax,0,COLUMN())/INDEX(SP_GF_Rev,0,COLUMN()) -> 0.057535511 | J52: =INDEX(SP_GF_ExciseTax,0,COLUMN())/INDEX(SP_GF_Rev,0,COLUMN()) -> 0.057177962 | ... CF52: =INDEX(SP_GF_ExciseTax,0,COLUMN())/INDEX(SP_GF_Rev,0,COLUMN()) -> 0.02
A53: =INDEX(MO_MA_OPEX,0,COLUMN()) -> OPEX Margin, % | C53: =INDEX(SP_GF_OPEX,0,COLUMN())/INDEX(SP_GF_Rev,0,COLUMN()) -> 0.10403994 | D53: =INDEX(SP_GF_OPEX,0,COLUMN())/INDEX(SP_GF_Rev,0,COLUMN()) -> 0.093632886 | E53: =INDEX(SP_GF_OPEX,0,COLUMN())/INDEX(SP_GF_Rev,0,COLUMN()) -> 0.085331052 | F53: =INDEX(SP_GF_OPEX,0,COLUMN())/INDEX(SP_GF_Rev,0,COLUMN()) -> 0.093299547 | G53: =INDEX(SP_GF_OPEX,0,COLUMN())/INDEX(SP_GF_Rev,0,COLUMN()) -> 0.10141152 | H53: =INDEX(SP_GF_OPEX,0,COLUMN())/INDEX(SP_GF_Rev,0,COLUMN()) -> 0.10943192 | I53: =INDEX(SP_GF_OPEX,0,COLUMN())/INDEX(SP_GF_Rev,0,COLUMN()) -> 0.10368699 | J53: =INDEX(SP_GF_OPEX,0,COLUMN())/INDEX(SP_GF_Rev,0,COLUMN()) -> 0.11611881 | ... CF53: =INDEX(SP_GF_OPEX,0,COLUMN())/INDEX(SP_GF_Rev,0,COLUMN()) -> 0.13
A54: =INDEX(MO_MA_EBITDAX,0,COLUMN()) -> EBITDAX Margin, % | C54: =INDEX(SP_GF_EBITDAX,0,COLUMN())/INDEX(SP_GF_Rev,0,COLUMN()) -> 0.18648768 | D54: =INDEX(SP_GF_EBITDAX,0,COLUMN())/INDEX(SP_GF_Rev,0,COLUMN()) -> 0.22600621 | E54: =INDEX(SP_GF_EBITDAX,0,COLUMN())/INDEX(SP_GF_Rev,0,COLUMN()) -> 0.24343531 | F54: =INDEX(SP_GF_EBITDAX,0,COLUMN())/INDEX(SP_GF_Rev,0,COLUMN()) -> 0.25411622 | G54: =INDEX(SP_GF_EBITDAX,0,COLUMN())/INDEX(SP_GF_Rev,0,COLUMN()) -> 0.24659439 | H54: =INDEX(SP_GF_EBITDAX,0,COLUMN())/INDEX(SP_GF_Rev,0,COLUMN()) -> 0.21492444 | I54: =INDEX(SP_GF_EBITDAX,0,COLUMN())/INDEX(SP_GF_Rev,0,COLUMN()) -> 0.22309967 | J54: =INDEX(SP_GF_EBITDAX,0,COLUMN())/INDEX(SP_GF_Rev,0,COLUMN()) -> 0.22363688 | ... CF54: =INDEX(SP_GF_EBITDAX,0,COLUMN())/INDEX(SP_GF_Rev,0,COLUMN()) -> 0.28
A55: =INDEX(MO_MA_EBITDAX_Adj,0,COLUMN()) -> Adjusted EBITDAX Margin, % | C55: =INDEX(SP_Company1876_EBITDAX,0,COLUMN())/INDEX(SP_GF_Rev,0,COLUMN()) -> 0.18648768 | D55: =INDEX(SP_Company1876_EBITDAX,0,COLUMN())/INDEX(SP_GF_Rev,0,COLUMN()) -> 0.22600621 | E55: =INDEX(SP_Company1876_EBITDAX,0,COLUMN())/INDEX(SP_GF_Rev,0,COLUMN()) -> 0.24343531 | F55: =INDEX(SP_Company1876_EBITDAX,0,COLUMN())/INDEX(SP_GF_Rev,0,COLUMN()) -> 0.25411622 | G55: =INDEX(SP_Company1876_EBITDAX,0,COLUMN())/INDEX(SP_GF_Rev,0,COLUMN()) -> 0.24659439 | H55: =INDEX(SP_Company1876_EBITDAX,0,COLUMN())/INDEX(SP_GF_Rev,0,COLUMN()) -> 0.21492444 | I55: =INDEX(SP_Company1876_EBITDAX,0,COLUMN())/INDEX(SP_GF_Rev,0,COLUMN()) -> 0.22309967 | J55: =INDEX(SP_Company1876_EBITDAX,0,COLUMN())/INDEX(SP_GF_Rev,0,COLUMN()) -> 0.22363688 | ... CF55: =INDEX(SP_Company1876_EBITDAX,0,COLUMN())/INDEX(SP_GF_Rev,0,COLUMN()) -> 0.28
A57: Cash Flow Analysis
A58: =INDEX(MO_CFSum_CFO_BeforeWC,0,COLUMN()) -> Operating Cash Flow before WC | C58: =INDEX(MO_CFSum_CFO_BeforeWC,0,COLUMN()) -> 21674 | D58: =INDEX(MO_CFSum_CFO_BeforeWC,0,COLUMN()) -> 31278 | E58: =INDEX(MO_CFSum_CFO_BeforeWC,0,COLUMN()) -> 38777 | F58: =INDEX(MO_CFSum_CFO_BeforeWC,0,COLUMN()) -> 38449 | G58: =INDEX(MO_CFSum_CFO_BeforeWC,0,COLUMN()) -> 9074 | H58: =INDEX(MO_CFSum_CFO_BeforeWC,0,COLUMN()) -> 7675 | I58: =INDEX(MO_CFSum_CFO_BeforeWC,0,COLUMN()) -> 9889 | J58: =INDEX(MO_CFSum_CFO_BeforeWC,0,COLUMN()) -> 9695 | ... CF58: =INDEX(MO_CFSum_CFO_BeforeWC,0,COLUMN()) -> 42776.003
A59: Change in WC | C59: =SUM(OFFSET(INDEX(MO_CFS_CFO_BeforeWC,0,COLUMN()),1,0,ROW(INDEX(MO_CFS_CFO,0,COLUMN()))-ROW(INDEX(MO_CFS_CFO_BeforeWC,0,COLUMN()))-1,1)) -> -2301 | D59: =SUM(OFFSET(INDEX(MO_CFS_CFO_BeforeWC,0,COLUMN()),1,0,ROW(INDEX(MO_CFS_CFO,0,COLUMN()))-ROW(INDEX(MO_CFS_CFO_BeforeWC,0,COLUMN()))-1,1)) -> 76 | E59: =SUM(OFFSET(INDEX(MO_CFS_CFO_BeforeWC,0,COLUMN()),1,0,ROW(INDEX(MO_CFS_CFO,0,COLUMN()))-ROW(INDEX(MO_CFS_CFO_BeforeWC,0,COLUMN()))-1,1)) -> 2318 | F59: =SUM(OFFSET(INDEX(MO_CFS_CFO_BeforeWC,0,COLUMN()),1,0,ROW(INDEX(MO_CFS_CFO,0,COLUMN()))-ROW(INDEX(MO_CFS_CFO_BeforeWC,0,COLUMN()))-1,1)) -> 363 | G59: =SUM(OFFSET(INDEX(MO_CFS_CFO_BeforeWC,0,COLUMN()),1,0,ROW(INDEX(MO_CFS_CFO,0,COLUMN()))-ROW(INDEX(MO_CFS_CFO_BeforeWC,0,COLUMN()))-1,1)) -> -3360 | H59: =SUM(OFFSET(INDEX(MO_CFS_CFO_BeforeWC,0,COLUMN()),1,0,ROW(INDEX(MO_CFS_CFO,0,COLUMN()))-ROW(INDEX(MO_CFS_CFO_BeforeWC,0,COLUMN()))-1,1)) -> 845 | I59: =SUM(OFFSET(INDEX(MO_CFS_CFO_BeforeWC,0,COLUMN()),1,0,ROW(INDEX(MO_CFS_CFO,0,COLUMN()))-ROW(INDEX(MO_CFS_CFO_BeforeWC,0,COLUMN()))-1,1)) -> 427 | J59: =SUM(OFFSET(INDEX(MO_CFS_CFO_BeforeWC,0,COLUMN()),1,0,ROW(INDEX(MO_CFS_CFO,0,COLUMN()))-ROW(INDEX(MO_CFS_CFO_BeforeWC,0,COLUMN()))-1,1)) -> 757 | ... CF59: =SUM(OFFSET(INDEX(MO_CFS_CFO_BeforeWC,0,COLUMN()),1,0,ROW(INDEX(MO_CFS_CFO,0,COLUMN()))-ROW(INDEX(MO_CFS_CFO_BeforeWC,0,COLUMN()))-1,1)) -> 0
A60: Operating Cash Flow after WC | C60: =SUM(C58:C59) -> 19373 | D60: =SUM(D58:D59) -> 31354 | E60: =SUM(E58:E59) -> 41095 | F60: =SUM(F58:F59) -> 38812 | G60: =SUM(G58:G59) -> 5714 | H60: =SUM(H58:H59) -> 8520 | I60: =SUM(I58:I59) -> 10316 | J60: =SUM(J58:J59) -> 10452 | ... CF60: =SUM(CF58:CF59) -> 42776.003
A61: =INDEX(MO_CFSum_Capex,0,COLUMN()) -> Capex | C61: =INDEX(MO_CFSum_Capex,0,COLUMN()) -> -19843 | D61: =INDEX(MO_CFSum_Capex,0,COLUMN()) -> -19612 | E61: =INDEX(MO_CFSum_Capex,0,COLUMN()) -> -26500 | F61: =INDEX(MO_CFSum_Capex,0,COLUMN()) -> -30938 | G61: =INDEX(MO_CFSum_Capex,0,COLUMN()) -> -8192 | H61: =INDEX(MO_CFSum_Capex,0,COLUMN()) -> -8573 | I61: =INDEX(MO_CFSum_Capex,0,COLUMN()) -> -9607 | J61: =INDEX(MO_CFSum_Capex,0,COLUMN()) -> -11613 | ... CF61: =INDEX(MO_CFSum_Capex,0,COLUMN()) -> -20000
A62: Core FCF, Pre Div | C62: =SUM(C60:C61) -> -470 | D62: =SUM(D60:D61) -> 11742 | E62: =SUM(E60:E61) -> 14595 | F62: =SUM(F60:F61) -> 7874 | G62: =SUM(G60:G61) -> -2478 | H62: =SUM(H60:H61) -> -53 | I62: =SUM(I60:I61) -> 709 | J62: =SUM(J60:J61) -> -1161 | ... CF62: =SUM(CF60:CF61) -> 22776.003
A63: =INDEX(MO_CFSum_Dividend,0,COLUMN()) -> Dividend Paid | C63: =INDEX(MO_CFSum_Dividend,0,COLUMN()) -> -5302 | D63: =INDEX(MO_CFSum_Dividend,0,COLUMN()) -> -5669 | E63: =INDEX(MO_CFSum_Dividend,0,COLUMN()) -> -6136 | F63: =INDEX(MO_CFSum_Dividend,0,COLUMN()) -> -6844 | G63: =INDEX(MO_CFSum_Dividend,0,COLUMN()) -> -1735 | H63: =INDEX(MO_CFSum_Dividend,0,COLUMN()) -> -1921 | I63: =INDEX(MO_CFSum_Dividend,0,COLUMN()) -> -1915 | J63: =INDEX(MO_CFSum_Dividend,0,COLUMN()) -> -1903 | ... CF63: =INDEX(MO_CFSum_Dividend,0,COLUMN()) -> -14072.414
A64: Core FCF, Post Div | C64: =SUM(C62:C63) -> -5772 | D64: =SUM(D62:D63) -> 6073 | E64: =SUM(E62:E63) -> 8459 | F64: =SUM(F62:F63) -> 1030 | G64: =SUM(G62:G63) -> -4213 | H64: =SUM(H62:H63) -> -1974 | I64: =SUM(I62:I63) -> -1206 | J64: =SUM(J62:J63) -> -3064 | ... CF64: =SUM(CF62:CF63) -> 8703.5891
A65: =INDEX(MO_CFSum_Acquisition,0,COLUMN()) -> Acquisitions | C65: =INDEX(MO_CFSum_Acquisition,0,COLUMN()) -> 0 | D65: =INDEX(MO_CFSum_Acquisition,0,COLUMN()) -> 0 | E65: =INDEX(MO_CFSum_Acquisition,0,COLUMN()) -> -3009 | F65: =INDEX(MO_CFSum_Acquisition,0,COLUMN()) -> 0 | G65: =INDEX(MO_CFSum_Acquisition,0,COLUMN()) -> 0 | H65: =INDEX(MO_CFSum_Acquisition,0,COLUMN()) -> 0 | I65: =INDEX(MO_CFSum_Acquisition,0,COLUMN()) -> 0 | J65: =INDEX(MO_CFSum_Acquisition,0,COLUMN()) -> 0 | ... CF65: =INDEX(MO_CFSum_Acquisition,0,COLUMN()) -> 0
A66: =INDEX(MO_CFSum_Divestiture,0,COLUMN()) -> Divestiture | C66: =INDEX(MO_CFSum_Divestiture,0,COLUMN()) -> 2564 | D66: =INDEX(MO_CFSum_Divestiture,0,COLUMN()) -> 1995 | E66: =INDEX(MO_CFSum_Divestiture,0,COLUMN()) -> 3517 | F66: =INDEX(MO_CFSum_Divestiture,0,COLUMN()) -> 2777 | G66: =INDEX(MO_CFSum_Divestiture,0,COLUMN()) -> 76 | H66: =INDEX(MO_CFSum_Divestiture,0,COLUMN()) -> 565 | I66: =INDEX(MO_CFSum_Divestiture,0,COLUMN()) -> 216 | J66: =INDEX(MO_CFSum_Divestiture,0,COLUMN()) -> 286 | ... CF66: =INDEX(MO_CFSum_Divestiture,0,COLUMN()) -> 0
A67: New Equity Issuance | C67: =INDEX(MO_CFSum_NetShares,0,COLUMN()) -> 168 | D67: =INDEX(MO_CFSum_NetShares,0,COLUMN()) -> -306 | E67: =INDEX(MO_CFSum_NetShares,0,COLUMN()) -> -3193 | F67: =INDEX(MO_CFSum_NetShares,0,COLUMN()) -> -4142 | G67: =INDEX(MO_CFSum_NetShares,0,COLUMN()) -> -1027 | H67: =INDEX(MO_CFSum_NetShares,0,COLUMN()) -> -1001 | I67: =INDEX(MO_CFSum_NetShares,0,COLUMN()) -> -1278 | J67: =INDEX(MO_CFSum_NetShares,0,COLUMN()) -> -1188 | ... CF67: =INDEX(MO_CFSum_NetShares,0,COLUMN()) -> 0
A68: New Debt Issuance | C68: =INDEX(MO_CFSum_NetDebtIssuance,0,COLUMN()) -> 1659 | D68: =INDEX(MO_CFSum_NetDebtIssuance,0,COLUMN()) -> 882 | E68: =INDEX(MO_CFSum_NetDebtIssuance,0,COLUMN()) -> -2369 | F68: =INDEX(MO_CFSum_NetDebtIssuance,0,COLUMN()) -> 2047 | G68: =INDEX(MO_CFSum_NetDebtIssuance,0,COLUMN()) -> 1967 | H68: =INDEX(MO_CFSum_NetDebtIssuance,0,COLUMN()) -> 5826 | I68: =INDEX(MO_CFSum_NetDebtIssuance,0,COLUMN()) -> -1381 | J68: =INDEX(MO_CFSum_NetDebtIssuance,0,COLUMN()) -> 1834 | ... CF68: =INDEX(MO_CFSum_NetDebtIssuance,0,COLUMN()) -> 0
A69: Other Items | C69: =+Model!C701+Model!C705+Model!C706+Model!C707+Model!C708+Model!C716+Model!C722+Model!C704 -> 750 | D69: =+Model!D701+Model!D705+Model!D706+Model!D707+Model!D708+Model!D716+Model!D722+Model!D704 -> -3300 | E69: =+Model!E701+Model!E705+Model!E706+Model!E707+Model!E708+Model!E716+Model!E722+Model!E704 -> -1601 | F69: =+Model!F701+Model!F705+Model!F706+Model!F707+Model!F708+Model!F716+Model!F722+Model!F704 -> 3363 | G69: =+Model!G701+Model!G705+Model!G706+Model!G707+Model!G708+Model!G716+Model!G722+Model!G704 -> -368 | H69: =+Model!H701+Model!H705+Model!H706+Model!H707+Model!H708+Model!H716+Model!H722+Model!H704 -> -160 | I69: =+Model!I701+Model!I705+Model!I706+Model!I707+Model!I708+Model!I716+Model!I722+Model!I704 -> 33 | J69: =+Model!J701+Model!J705+Model!J706+Model!J707+Model!J708+Model!J716+Model!J722+Model!J704 -> 1363 | ... CF69: =+Model!CF701+Model!CF705+Model!CF706+Model!CF707+Model!CF708+Model!CF716+Model!CF722+Model!CF704 -> 0
A70: Change in Cash Position | C70: =SUM(C64:C69) -> -631 | D70: =SUM(D64:D69) -> 5344 | E70: =SUM(E64:E69) -> 1804 | F70: =SUM(F64:F69) -> 5075 | G70: =SUM(G64:G69) -> -3565 | H70: =SUM(H64:H69) -> 3256 | I70: =SUM(I64:I69) -> -3616 | J70: =SUM(J64:J69) -> -769 | ... CF70: =SUM(CF64:CF69) -> 8703.5891
A72: Operating Cash Flow Per Share | C72: =INDEX(SP_CFA_CFO,0,COLUMN())/INDEX(SP_GF_ShareCount,0,COLUMN()) -> 9.6816592 | D72: =INDEX(SP_CFA_CFO,0,COLUMN())/INDEX(SP_GF_ShareCount,0,COLUMN()) -> 15.625896 | E72: =INDEX(SP_CFA_CFO,0,COLUMN())/INDEX(SP_GF_ShareCount,0,COLUMN()) -> 20.539438 | F72: =INDEX(SP_CFA_CFO,0,COLUMN())/INDEX(SP_GF_ShareCount,0,COLUMN()) -> 19.754117 | G72: =INDEX(SP_CFA_CFO,0,COLUMN())/INDEX(SP_GF_ShareCount,0,COLUMN()) -> 2.9394047 | H72: =INDEX(SP_CFA_CFO,0,COLUMN())/INDEX(SP_GF_ShareCount,0,COLUMN()) -> 4.3990473 | I72: =INDEX(SP_CFA_CFO,0,COLUMN())/INDEX(SP_GF_ShareCount,0,COLUMN()) -> 5.3455458 | J72: =INDEX(SP_CFA_CFO,0,COLUMN())/INDEX(SP_GF_ShareCount,0,COLUMN()) -> 5.4456673 | ... CF72: =INDEX(SP_CFA_CFO,0,COLUMN())/INDEX(SP_GF_ShareCount,0,COLUMN()) -> 21.558604
A73: Core Free Cash Flow Per Share, Pre Div | C73: =INDEX(SP_CFA_FCF_PreDiv,0,COLUMN())/INDEX(SP_GF_ShareCount,0,COLUMN()) -> -0.23488256 | D73: =INDEX(SP_CFA_FCF_PreDiv,0,COLUMN())/INDEX(SP_GF_ShareCount,0,COLUMN()) -> 5.8518615 | E73: =INDEX(SP_CFA_FCF_PreDiv,0,COLUMN())/INDEX(SP_GF_ShareCount,0,COLUMN()) -> 7.2946369 | F73: =INDEX(SP_CFA_FCF_PreDiv,0,COLUMN())/INDEX(SP_GF_ShareCount,0,COLUMN()) -> 4.0076244 | G73: =INDEX(SP_CFA_FCF_PreDiv,0,COLUMN())/INDEX(SP_GF_ShareCount,0,COLUMN()) -> -1.2747366 | H73: =INDEX(SP_CFA_FCF_PreDiv,0,COLUMN())/INDEX(SP_GF_ShareCount,0,COLUMN()) -> -0.027364966 | I73: =INDEX(SP_CFA_FCF_PreDiv,0,COLUMN())/INDEX(SP_GF_ShareCount,0,COLUMN()) -> 0.36738968 | J73: =INDEX(SP_CFA_FCF_PreDiv,0,COLUMN())/INDEX(SP_GF_ShareCount,0,COLUMN()) -> -0.60490048 | ... CF73: =INDEX(SP_CFA_FCF_PreDiv,0,COLUMN())/INDEX(SP_GF_ShareCount,0,COLUMN()) -> 11.478838
A74: Dividend Per Share | C74: =INDEX(MO_CFSum_DPS,0,COLUMN()) -> 2.66 | D74: =INDEX(MO_CFSum_DPS,0,COLUMN()) -> 2.84 | E74: =INDEX(MO_CFSum_DPS,0,COLUMN()) -> 3.09 | F74: =INDEX(MO_CFSum_DPS,0,COLUMN()) -> 3.51 | G74: =INDEX(MO_CFSum_DPS,0,COLUMN()) -> 0.9 | H74: =INDEX(MO_CFSum_DPS,0,COLUMN()) -> 1 | I74: =INDEX(MO_CFSum_DPS,0,COLUMN()) -> 1 | J74: =INDEX(MO_CFSum_DPS,0,COLUMN()) -> 1 | ... CF74: =INDEX(MO_CFSum_DPS,0,COLUMN()) -> 7.12
A75: Dividend Payout Ratio vs Core FCF, Pre Div | C75: =C74/C73 -> -11.324809 | D75: =D74/D73 -> 0.48531566 | E75: =E74/E73 -> 0.42359888 | F75: =F74/F73 -> 0.87583059 | G75: =G74/G73 -> -0.70602821 | H75: =H74/H73 -> -36.543075 | I75: =I74/I73 -> 2.7219055 | J75: =J74/J73 -> -1.6531645 | ... CF75: =CF74/CF73 -> 0.62027182
A76: Dividend Payout Ratio vs Earnings Per Share | C76: =C74/C47 -> 0.50774206 | D76: =D74/D47 -> 0.2995467 | E76: =E74/E47 -> 0.22987268 | F76: =F74/F47 -> 0.26342832 | G76: =G74/G47 -> 0.28318839 | H76: =H74/H47 -> 0.36100336 | I76: =I74/I47 -> 0.38986485 | J76: =J74/J47 -> 0.38931521 | ... CF76: =CF74/CF47 -> 0.87099082
A78: Balance Sheet Ratios
A79: Net Debt / EBITDA | C79: =INDEX(MO_BSS_Debt_Net,0,COLUMN())/INDEX(SP_BSR_EBITDA_LTM,0,COLUMN()) -> -0.027336916 | D79: =INDEX(MO_BSS_Debt_Net,0,COLUMN())/INDEX(SP_BSR_EBITDA_LTM,0,COLUMN()) -> -0.18438951 | E79: =INDEX(MO_BSS_Debt_Net,0,COLUMN())/INDEX(SP_BSR_EBITDA_LTM,0,COLUMN()) -> -0.1590324 | F79: =INDEX(MO_BSS_Debt_Net,0,COLUMN())/INDEX(SP_BSR_EBITDA_LTM,0,COLUMN()) -> -0.15361215 | J79: =INDEX(MO_BSS_Debt_Net,0,COLUMN())/INDEX(SP_BSR_EBITDA_LTM,0,COLUMN()) -> 0.054377117 | K79: =INDEX(MO_BSS_Debt_Net,0,COLUMN())/INDEX(SP_BSR_EBITDA_LTM,0,COLUMN()) -> 0.054377117 | L79: =INDEX(MO_BSS_Debt_Net,0,COLUMN())/INDEX(SP_BSR_EBITDA_LTM,0,COLUMN()) -> 0.11800294 | M79: =INDEX(MO_BSS_Debt_Net,0,COLUMN())/INDEX(SP_BSR_EBITDA_LTM,0,COLUMN()) -> 0.14440335 | N79: =INDEX(MO_BSS_Debt_Net,0,COLUMN())/INDEX(SP_BSR_EBITDA_LTM,0,COLUMN()) -> 0.19410106 | O79: =INDEX(MO_BSS_Debt_Net,0,COLUMN())/INDEX(SP_BSR_EBITDA_LTM,0,COLUMN()) -> 0.27454982 | P79: =INDEX(MO_BSS_Debt_Net,0,COLUMN())/INDEX(SP_BSR_EBITDA_LTM,0,COLUMN()) -> 0.27454982 | Q79: =INDEX(MO_BSS_Debt_Net,0,COLUMN())/INDEX(SP_BSR_EBITDA_LTM,0,COLUMN()) -> 0.40074865 | ... CF79: =INDEX(MO_BSS_Debt_Net,0,COLUMN())/INDEX(SP_BSR_EBITDA_LTM,0,COLUMN()) -> -0.61102211
A80: Net Debt / Cash Flow | C80: =INDEX(MO_BSS_Debt_Net,0,COLUMN())/INDEX(SP_BSR_CashFlow_LTM,0,COLUMN()) -> -0.045165953 | D80: =INDEX(MO_BSS_Debt_Net,0,COLUMN())/INDEX(SP_BSR_CashFlow_LTM,0,COLUMN()) -> -0.27237354 | E80: =INDEX(MO_BSS_Debt_Net,0,COLUMN())/INDEX(SP_BSR_CashFlow_LTM,0,COLUMN()) -> -0.23900718 | F80: =INDEX(MO_BSS_Debt_Net,0,COLUMN())/INDEX(SP_BSR_CashFlow_LTM,0,COLUMN()) -> -0.24330104 | J80: =INDEX(MO_BSS_Debt_Net,0,COLUMN())/INDEX(SP_BSR_CashFlow_LTM,0,COLUMN()) -> 0.080709674 | K80: =INDEX(MO_BSS_Debt_Net,0,COLUMN())/INDEX(SP_BSR_CashFlow_LTM,0,COLUMN()) -> 0.080709674 | L80: =INDEX(MO_BSS_Debt_Net,0,COLUMN())/INDEX(SP_BSR_CashFlow_LTM,0,COLUMN()) -> 0.15777748 | M80: =INDEX(MO_BSS_Debt_Net,0,COLUMN())/INDEX(SP_BSR_CashFlow_LTM,0,COLUMN()) -> 0.20120865 | N80: =INDEX(MO_BSS_Debt_Net,0,COLUMN())/INDEX(SP_BSR_CashFlow_LTM,0,COLUMN()) -> 0.28362969 | O80: =INDEX(MO_BSS_Debt_Net,0,COLUMN())/INDEX(SP_BSR_CashFlow_LTM,0,COLUMN()) -> 0.43596505 | P80: =INDEX(MO_BSS_Debt_Net,0,COLUMN())/INDEX(SP_BSR_CashFlow_LTM,0,COLUMN()) -> 0.43596505 | Q80: =INDEX(MO_BSS_Debt_Net,0,COLUMN())/INDEX(SP_BSR_CashFlow_LTM,0,COLUMN()) -> 0.71718485 | ... CF80: =INDEX(MO_BSS_Debt_Net,0,COLUMN())/INDEX(SP_BSR_CashFlow_LTM,0,COLUMN()) -> -0.79055958
A81: Net Debt / Capital | C81: =INDEX(MO_BSS_Debt_Net,0,COLUMN())/SUM(INDEX(MO_BS_SE,0,COLUMN()),INDEX(MO_BSS_Debt,0,COLUMN()),IFERROR(INDEX(MO_BSS_OL,0,COLUMN()),0)) -> -0.008542586 | D81: =INDEX(MO_BSS_Debt_Net,0,COLUMN())/SUM(INDEX(MO_BS_SE,0,COLUMN()),INDEX(MO_BSS_Debt,0,COLUMN()),IFERROR(INDEX(MO_BSS_OL,0,COLUMN()),0)) -> -0.073268873 | E81: =INDEX(MO_BSS_Debt_Net,0,COLUMN())/SUM(INDEX(MO_BS_SE,0,COLUMN()),INDEX(MO_BSS_Debt,0,COLUMN()),IFERROR(INDEX(MO_BSS_OL,0,COLUMN()),0)) -> -0.074672708 | F81: =INDEX(MO_BSS_Debt_Net,0,COLUMN())/SUM(INDEX(MO_BS_SE,0,COLUMN()),INDEX(MO_BSS_Debt,0,COLUMN()),IFERROR(INDEX(MO_BSS_OL,0,COLUMN()),0)) -> -0.063496867 | J81: =INDEX(MO_BSS_Debt_Net,0,COLUMN())/SUM(INDEX(MO_BS_SE,0,COLUMN()),INDEX(MO_BSS_Debt,0,COLUMN()),IFERROR(INDEX(MO_BSS_OL,0,COLUMN()),0)) -> 0.016662341 | K81: =INDEX(MO_BSS_Debt_Net,0,COLUMN())/SUM(INDEX(MO_BS_SE,0,COLUMN()),INDEX(MO_BSS_Debt,0,COLUMN()),IFERROR(INDEX(MO_BSS_OL,0,COLUMN()),0)) -> 0.016662341 | L81: =INDEX(MO_BSS_Debt_Net,0,COLUMN())/SUM(INDEX(MO_BS_SE,0,COLUMN()),INDEX(MO_BSS_Debt,0,COLUMN()),IFERROR(INDEX(MO_BSS_OL,0,COLUMN()),0)) -> 0.034245747 | M81: =INDEX(MO_BSS_Debt_Net,0,COLUMN())/SUM(INDEX(MO_BS_SE,0,COLUMN()),INDEX(MO_BSS_Debt,0,COLUMN()),IFERROR(INDEX(MO_BSS_OL,0,COLUMN()),0)) -> 0.042104907 | N81: =INDEX(MO_BSS_Debt_Net,0,COLUMN())/SUM(INDEX(MO_BS_SE,0,COLUMN()),INDEX(MO_BSS_Debt,0,COLUMN()),IFERROR(INDEX(MO_BSS_OL,0,COLUMN()),0)) -> 0.055260133 | O81: =INDEX(MO_BSS_Debt_Net,0,COLUMN())/SUM(INDEX(MO_BS_SE,0,COLUMN()),INDEX(MO_BSS_Debt,0,COLUMN()),IFERROR(INDEX(MO_BSS_OL,0,COLUMN()),0)) -> 0.075046761 | P81: =INDEX(MO_BSS_Debt_Net,0,COLUMN())/SUM(INDEX(MO_BS_SE,0,COLUMN()),INDEX(MO_BSS_Debt,0,COLUMN()),IFERROR(INDEX(MO_BSS_OL,0,COLUMN()),0)) -> 0.075046761 | Q81: =INDEX(MO_BSS_Debt_Net,0,COLUMN())/SUM(INDEX(MO_BS_SE,0,COLUMN()),INDEX(MO_BSS_Debt,0,COLUMN()),IFERROR(INDEX(MO_BSS_OL,0,COLUMN()),0)) -> 0.095922756 | ... CF81: =INDEX(MO_BSS_Debt_Net,0,COLUMN())/SUM(INDEX(MO_BS_SE,0,COLUMN()),INDEX(MO_BSS_Debt,0,COLUMN()),IFERROR(INDEX(MO_BSS_OL,0,COLUMN()),0)) -> -0.12512574
A82: LTM EBITDA | C82: =C45 -> 32008 | D82: =D45 -> 46315 | E82: =E45 -> 61761 | F82: =F45 -> 61473 | J82: =SUM(J45,I45,H45,G45) -> 51952 | K82: =K45 -> 51952 | L82: =SUM(L45,J45,I45,H45) -> 50414 | M82: =SUM(M45,L45,J45,I45) -> 51647 | N82: =SUM(N45,M45,L45,J45) -> 51772 | O82: =SUM(O45,N45,M45,L45) -> 49980 | P82: =P45 -> 49980 | Q82: =SUM(Q45,O45,N45,M45) -> 45415 | R82: =SUM(R45,Q45,O45,N45) -> 41248 | S82: =SUM(S45,R45,Q45,O45) -> 35438 | T82: =SUM(T45,S45,R45,Q45) -> 29219 | U82: =U45 -> 29219 | V82: =SUM(V45,T45,S45,R45) -> 24373 | W82: =SUM(W45,V45,T45,S45) -> 19921 | X82: =SUM(X45,W45,V45,T45) -> 18115 | Y82: =SUM(Y45,X45,W45,V45) -> 18531 | Z82: =Z45 -> 18531 | AA82: =SUM(AA45,Y45,X45,W45) -> 22987 | AB82: =SUM(AB45,AA45,Y45,X45) -> 25480 | AC82: =SUM(AC45,AB45,AA45,Y45) -> 27960 | AD82: =SUM(AD45,AC45,AB45,AA45) -> 29741 | AE82: =AE45 -> 29741 | AF82: =SUM(AF45,AD45,AC45,AB45) -> 31902 | AG82: =SUM(AG45,AF45,AD45,AC45) -> 34262 | AH82: =SUM(AH45,AG45,AF45,AD45) -> 38107 | AI82: =SUM(AI45,AH45,AG45,AF45) -> 41952 | AJ82: =AJ45 -> 41952 | AK82: =SUM(AK45,AI45,AH45,AG45) -> 40738 | AL82: =SUM(AL45,AK45,AI45,AH45) -> 41549 | AM82: =SUM(AM45,AL45,AK45,AI45) -> 38438 | AN82: =SUM(AN45,AM45,AL45,AK45) -> 36322 | AO82: =AO45 -> 36322 | AP82: =SUM(AP45,AN45,AM45,AL45) -> 36610 | AQ82: =SUM(AQ45,AP45,AN45,AM45) -> 23189 | AR82: =SUM(AR45,AQ45,AP45,AN45) -> 18668 | AS82: =SUM(AS45,AR45,AQ45,AP45) -> 14289 | AT82: =AT45 -> 14289 | AU82: =SUM(AU45,AS45,AR45,AQ45) -> 12283 | AV82: =SUM(AV45,AU45,AS45,AR45) -> 24338 | AW82: =SUM(AW45,AV45,AU45,AS45) -> 32775 | AX82: =SUM(AX45,AW45,AV45,AU45) -> 40825 | AY82: =AY45 -> 40825 | AZ82: =SUM(AZ45,AX45,AW45,AV45) -> 47131 | BA82: =SUM(BA45,AZ45,AX45,AW45) -> 57917 | BB82: =SUM(BB45,BA45,AZ45,AX45) -> 64480 | BC82: =SUM(BC45,BB45,BA45,AZ45) -> 67483 | BD82: =BD45 -> 67483 | BE82: =SUM(BE45,BC45,BB45,BA45) -> 67780 | BF82: =SUM(BF45,BE45,BC45,BB45) -> 59399 | BG82: =SUM(BG45,BF45,BE45,BC45) -> 53323 | BH82: =SUM(BH45,BG45,BF45,BE45) -> 48293 | BI82: =BI45 -> 48293 | BJ82: =SUM(BJ45,BH45,BG45,BF45) -> 47203 | BK82: =SUM(BK45,BJ45,BH45,BG45) -> 46972 | BL82: =SUM(BL45,BK45,BJ45,BH45) -> 44815 | BM82: =SUM(BM45,BL45,BK45,BJ45) -> 46377 | BN82: =BN45 -> 46377 | BO82: =SUM(BO45,BM45,BL45,BK45) -> 44222 | BP82: =SUM(BP45,BO45,BM45,BL45) -> 41823 | BQ82: =SUM(BQ45,BP45,BO45,BM45) -> 42655 | BR82: =SUM(BR45,BQ45,BP45,BO45) -> 42143 | BS82: =BS45 -> 42143 | BT82: =SUM(BT45,BR45,BQ45,BP45) -> 42342 | BU82: =SUM(BU45,BT45,BR45,BQ45) -> 53789.368 | BV82: =SUM(BV45,BU45,BT45,BR45) -> 57634.949 | BW82: =SUM(BW45,BV45,BU45,BT45) -> 61428.017 | BX82: =BX45 -> 61428.017 | BY82: =SUM(BY45,BW45,BV45,BU45) -> 67537.684 | BZ82: =SUM(BZ45,BY45,BW45,BV45) -> 64016.631 | CA82: =SUM(CA45,BZ45,BY45,BW45) -> 65525.753 | CB82: =SUM(CB45,CA45,BZ45,BY45) -> 67629.226 | CC82: =CC45 -> 67629.226 | CD82: =CD45 -> 66347.733 | CE82: =CE45 -> 61835.631 | CF82: =CF45 -> 55344.935
A83: LTM Cash Flow | C83: =C60 -> 19373 | D83: =D60 -> 31354 | E83: =E60 -> 41095 | F83: =F60 -> 38812 | J83: =SUM(J60,I60,H60,G60) -> 35002 | K83: =K60 -> 35002 | L83: =SUM(L60,J60,I60,H60) -> 37705 | M83: =SUM(M60,L60,J60,I60) -> 37066 | N83: =SUM(N60,M60,L60,J60) -> 35430 | O83: =SUM(O60,N60,M60,L60) -> 31475 | P83: =P60 -> 31475 | Q83: =SUM(Q60,O60,N60,M60) -> 25377 | R83: =SUM(R60,Q60,O60,N60) -> 24716 | S83: =SUM(S60,R60,Q60,O60) -> 21396 | T83: =SUM(T60,S60,R60,Q60) -> 19456 | U83: =U60 -> 19456 | V83: =SUM(V60,T60,S60,R60) -> 18278 | W83: =SUM(W60,V60,T60,S60) -> 13589 | X83: =SUM(X60,W60,V60,T60) -> 13540 | Y83: =SUM(Y60,X60,W60,V60) -> 12846 | Z83: =Z60 -> 12846 | AA83: =SUM(AA60,Y60,X60,W60) -> 15584 | AB83: =SUM(AB60,AA60,Y60,X60) -> 18089 | AC83: =SUM(AC60,AB60,AA60,Y60) -> 18148 | AD83: =SUM(AD60,AC60,AB60,AA60) -> 20515 | AE83: =AE60 -> 20515 | AF83: =SUM(AF60,AD60,AC60,AB60) -> 21679 | AG83: =SUM(AG60,AF60,AD60,AC60) -> 23498 | AH83: =SUM(AH60,AG60,AF60,AD60) -> 27697 | AI83: =SUM(AI60,AH60,AG60,AF60) -> 30618 | AJ83: =AJ60 -> 30618 | AK83: =SUM(AK60,AI60,AH60,AG60) -> 30632 | AL83: =SUM(AL60,AK60,AI60,AH60) -> 32560 | AM83: =SUM(AM60,AL60,AK60,AI60) -> 30808 | AN83: =SUM(AN60,AM60,AL60,AK60) -> 27314 | AO83: =AO60 -> 27314 | AP83: =SUM(AP60,AN60,AM60,AL60) -> 26979 | AQ83: =SUM(AQ60,AP60,AN60,AM60) -> 18276 | AR83: =SUM(AR60,AQ60,AP60,AN60) -> 13996 | AS83: =SUM(AS60,AR60,AQ60,AP60) -> 10577 | AT83: =AT60 -> 10577 | AU83: =SUM(AU60,AS60,AR60,AQ60) -> 10051 | AV83: =SUM(AV60,AU60,AS60,AR60) -> 16925 | AW83: =SUM(AW60,AV60,AU60,AS60) -> 21967 | AX83: =SUM(AX60,AW60,AV60,AU60) -> 29187 | AY83: =AY60 -> 29187 | AZ83: =SUM(AZ60,AX60,AW60,AV60) -> 33046 | BA83: =SUM(BA60,AZ60,AX60,AW60) -> 39874 | BB83: =SUM(BB60,BA60,AZ60,AX60) -> 46562 | BC83: =SUM(BC60,BB60,BA60,AZ60) -> 49602 | BD83: =BD60 -> 49602 | BE83: =SUM(BE60,BC60,BB60,BA60) -> 48752 | BF83: =SUM(BF60,BE60,BC60,BB60) -> 41267 | BG83: =SUM(BG60,BF60,BE60,BC60) -> 35673 | BH83: =SUM(BH60,BG60,BF60,BE60) -> 35609 | BI83: =BI60 -> 35609 | BJ83: =SUM(BJ60,BH60,BG60,BF60) -> 35232 | BK83: =SUM(BK60,BJ60,BH60,BG60) -> 35230 | BL83: =SUM(BL60,BK60,BJ60,BH60) -> 35231 | BM83: =SUM(BM60,BL60,BK60,BJ60) -> 31492 | BN83: =BN60 -> 31492 | BO83: =SUM(BO60,BM60,BL60,BK60) -> 29853 | BP83: =SUM(BP60,BO60,BM60,BL60) -> 32134 | BQ83: =SUM(BQ60,BP60,BO60,BM60) -> 31845 | BR83: =SUM(BR60,BQ60,BP60,BO60) -> 33939 | BS83: =BS60 -> 33939 | BT83: =SUM(BT60,BR60,BQ60,BP60) -> 31264 | BU83: =SUM(BU60,BT60,BR60,BQ60) -> 37874.855 | BV83: =SUM(BV60,BU60,BT60,BR60) -> 40128.48 | BW83: =SUM(BW60,BV60,BU60,BT60) -> 40671.847 | BX83: =BX60 -> 40671.847 | BY83: =SUM(BY60,BW60,BV60,BU60) -> 50354.707 | BZ83: =SUM(BZ60,BY60,BW60,BV60) -> 47881.961 | CA83: =SUM(CA60,BZ60,BY60,BW60) -> 49127.275 | CB83: =SUM(CB60,CA60,BZ60,BY60) -> 50585.792 | CC83: =CC60 -> 50585.792 | CD83: =CD60 -> 49927.821 | CE83: =CE60 -> 48642.951 | CF83: =CF60 -> 42776.003
A85: Profitability Ratios
A86: Net Income | C86: =INDEX(SP_Company1876_NI,0,COLUMN()) -> 10483 | D86: =INDEX(SP_Company1876_NI,0,COLUMN()) -> 19024 | E86: =INDEX(SP_Company1876_NI,0,COLUMN()) -> 26895 | F86: =INDEX(SP_Company1876_NI,0,COLUMN()) -> 26179 | G86: =INDEX(SP_Company1876_NI,0,COLUMN()) -> 6178 | H86: =INDEX(SP_Company1876_NI,0,COLUMN()) -> 5365 | I86: =INDEX(SP_Company1876_NI,0,COLUMN()) -> 4950 | J86: =INDEX(SP_Company1876_NI,0,COLUMN()) -> 4930 | ... CF86: =INDEX(SP_Company1876_NI,0,COLUMN()) -> 16219.818
A87: LTM Net Income | C87: =C86 -> 10483 | D87: =D86 -> 19024 | E87: =E86 -> 26895 | F87: =F86 -> 26179 | J87: =SUM(J86,I86,H86,G86) -> 21423 | K87: =K86 -> 21423 | L87: =SUM(L86,J86,I86,H86) -> 19757 | M87: =SUM(M86,L86,J86,I86) -> 20057 | N87: =SUM(N86,M86,L86,J86) -> 20700 | O87: =SUM(O86,N86,M86,L86) -> 19241 | P87: =P86 -> 19241 | Q87: =SUM(Q86,O86,N86,M86) -> 17296 | R87: =SUM(R86,Q86,O86,N86) -> 12202 | S87: =SUM(S86,R86,Q86,O86) -> 8646 | T87: =SUM(T86,S86,R86,Q86) -> 4587 | U87: =U86 -> 4587 | V87: =SUM(V86,T86,S86,R86) -> 1295 | W87: =SUM(W86,V86,T86,S86) -> -746 | X87: =SUM(X86,W86,V86,T86) -> -1500 | Y87: =SUM(Y86,X86,W86,V86) -> -497 | Z87: =Z86 -> -497 | AA87: =SUM(AA86,Y86,X86,W86) -> 2910 | AB87: =SUM(AB86,AA86,Y86,X86) -> 5830 | AC87: =SUM(AC86,AB86,AA86,Y86) -> 6499 | AD87: =SUM(AD86,AC86,AB86,AA86) -> 9195 | AE87: =AE86 -> 9195 | AF87: =SUM(AF86,AD86,AC86,AB86) -> 10151 | AG87: =SUM(AG86,AF86,AD86,AC86) -> 12110 | AH87: =SUM(AH86,AG86,AF86,AD86) -> 14205 | AI87: =SUM(AI86,AH86,AG86,AF86) -> 14824 | AJ87: =AJ86 -> 14824 | AK87: =SUM(AK86,AI86,AH86,AG86) -> 13972 | AL87: =SUM(AL86,AK86,AI86,AH86) -> 13933 | AM87: =SUM(AM86,AL86,AK86,AI86) -> 12822 | AN87: =SUM(AN86,AM86,AL86,AK86) -> 11888 | AO87: =AO86 -> 11888 | AP87: =SUM(AP86,AN86,AM86,AL86) -> 11507 | AQ87: =SUM(AQ86,AP86,AN86,AM86) -> 5174 | AR87: =SUM(AR86,AQ86,AP86,AN86) -> 2439 | AS87: =SUM(AS86,AR86,AQ86,AP86) -> -368 | AT87: =AT86 -> -368 | AU87: =SUM(AU86,AS86,AR86,AQ86) -> -1043 | AV87: =SUM(AV86,AU86,AS86,AR86) -> 5194 | AW87: =SUM(AW86,AV86,AU86,AS86) -> 10680 | AX87: =SUM(AX86,AW86,AV86,AU86) -> 15608 | AY87: =AY86 -> 15608 | AZ87: =SUM(AZ86,AX86,AW86,AV86) -> 20421 | BA87: =SUM(BA86,AZ86,AX86,AW86) -> 28512 | BB87: =SUM(BB86,BA86,AZ86,AX86) -> 33609 | BC87: =SUM(BC86,BB86,BA86,AZ86) -> 36542 | BD87: =BD86 -> 36542 | BE87: =SUM(BE86,BC86,BB86,BA86) -> 36743 | BF87: =SUM(BF86,BE86,BC86,BB86) -> 31153 | BG87: =SUM(BG86,BF86,BE86,BC86) -> 26090 | BH87: =SUM(BH86,BG86,BF86,BE86) -> 24693 | BI87: =BI86 -> 24693 | BJ87: =SUM(BJ86,BH86,BG86,BF86) -> 23365 | BK87: =SUM(BK86,BJ86,BH86,BG86) -> 22267 | BL87: =SUM(BL86,BK86,BJ86,BH86) -> 21077 | BM87: =SUM(BM86,BL86,BK86,BJ86) -> 18256 | BN87: =BN86 -> 18256 | BO87: =SUM(BO86,BM86,BL86,BK86) -> 16653 | BP87: =SUM(BP86,BO86,BM86,BL86) -> 15029 | BQ87: =SUM(BQ86,BP86,BO86,BM86) -> 14125 | BR87: =SUM(BR86,BQ86,BP86,BO86) -> 13521 | BS87: =BS86 -> 13521 | BT87: =SUM(BT86,BR86,BQ86,BP86) -> 12501 | BU87: =SUM(BU86,BT86,BR86,BQ86) -> 19346.357 | BV87: =SUM(BV86,BU86,BT86,BR86) -> 23094.997 | BW87: =SUM(BW86,BV86,BU86,BT86) -> 26656.127 | BX87: =BX86 -> 26656.127 | BY87: =SUM(BY86,BW86,BV86,BU86) -> 29859.315 | BZ87: =SUM(BZ86,BY86,BW86,BV86) -> 25973.863 | CA87: =SUM(CA86,BZ86,BY86,BW86) -> 24775.733 | CB87: =SUM(CB86,CA86,BZ86,BY86) -> 24273.921 | CC87: =CC86 -> 24273.921 | CD87: =CD86 -> 23151.581 | CE87: =CE86 -> 23269.952 | CF87: =CF86 -> 16219.818
A88: Shareholder's Equity | C88: =INDEX(MO_BS_SE,0,COLUMN()) -> 91914 | D88: =INDEX(MO_BS_SE,0,COLUMN()) -> 105081 | E88: =INDEX(MO_BS_SE,0,COLUMN()) -> 121382 | F88: =INDEX(MO_BS_SE,0,COLUMN()) -> 136524 | G88: =INDEX(MO_BS_SE,0,COLUMN()) -> 140134 | H88: =INDEX(MO_BS_SE,0,COLUMN()) -> 142841 | I88: =INDEX(MO_BS_SE,0,COLUMN()) -> 144779 | J88: =INDEX(MO_BS_SE,0,COLUMN()) -> 149113 | ... CF88: =INDEX(MO_BS_SE,0,COLUMN()) -> 224835.96
