Workbook
Name Diluted_Shares: #REF!
Name FO_Forward_Year_1_EBITDA: #REF!
Name FO_Forward_Year_1_Net_Income: #REF!
Name FO_Forward_Year_1_Revenue: #REF!
Name FO_Greenshoe_Pct: #REF!
Name FO_Greenshoe_Primary_Pct: #REF!
Name FO_Offering_Size: #REF!
Name FO_Pre_Transaction_EPS: #REF!
Name FO_Primary_Pct: #REF!
Name FO_Spread: #REF!
Name Forward_Year_1_EBITDA: 'IPO-Model'!$J$16
Name Forward_Year_1_Net_Income: 'IPO-Model'!$J$17
Name Forward_Year_1_Revenue: 'IPO-Model'!$J$15
Name Greenshoe_Pct: 'IPO-Model'!$E$15
Name Greenshoe_Primary_Pct: 'IPO-Model'!$E$16
Name IPO_Discount: 'IPO-Model'!$E$10
Name IPO_Offering_Size: 'IPO-Model'!$E$7
Name IPO_Spread: 'IPO-Model'!$E$9
Name Issuer_Existing_Shares: 'IPO-Model'!$E$18
Name Primary_Share_Pct: 'IPO-Model'!$E$12
Name Primary_Shares: 'Alt-IPO-Model'!$E$10
Name Secondary_Shares: 'Alt-IPO-Model'!$E$11
Name Share_Price: #REF!

Sheet IPO-Model
B2: IPO Valuation & Financing Model
B3: ($ USD in Millions Except Per Share Values in $ as Stated)
B5: IPO Transaction Assumptions:
C7: Funds Raised in IPO: | E7: 1000 | G7: Expense Assumptions: | J7: $ in Millions
C9: Underwriting Discount: | E9: 0.05 | G9: (+) SEC Filing & Registration Fees: | J9: 1.5
C10: IPO Pricing Discount: | E10: 0.15 | G10: (+) Printing Fees: | J10: 1
G11: (+) Accounting & Legal Fees: | J11: 6
C12: Primary Share %: | E12: 0.75 | G12: (+) Miscellaneous / Other Fees: | J12: 1.5
C13: Secondary Share %: | E13: =1-E12 -> 0.25 | G13: Total Fees: | J13: =SUM(J9:J12) -> 10
C15: Greenshoe Provision %: | E15: 0.15 | G15: Forward Year 1 Revenue: | J15: 483.95526
C16: Primary Allocation %: | E16: 0.75 | G16: Forward Year 1 EBITDA: | J16: 249.74514
G17: Forward Year 1 Net Income: | J17: 175.94642
C18: Issuer - Existing Shares: | E18: 66.914438
G20: Filing Range - 1-Year Forward P / E Multiples
B21: ="Forward Year 1 P / E Multiple at Trading:" -> Forward Year 1 P / E Multiple at Trading: | F21: Units: | G21: 17.5 | H21: =+G21+2.5 -> 20 | I21: =+H21+2.5 -> 22.5 | J21: =+I21+2.5 -> 25
C23: Forward Year 1 Net Income: | F23: $ M | G23: =+Forward_Year_1_Net_Income -> 175.94642 | H23: =+Forward_Year_1_Net_Income -> 175.94642 | I23: =+Forward_Year_1_Net_Income -> 175.94642 | J23: =+Forward_Year_1_Net_Income -> 175.94642
C24: Implied Post-Money Equity Value @ Trading: | F24: $ M | G24: =+G21*G23 -> 3079.0623 | H24: =+H21*H23 -> 3518.9284 | I24: =+I21*I23 -> 3958.7944 | J24: =+J21*J23 -> 4398.6605
C26: Pricing Discount %: | F26: % | G26: =+IPO_Discount -> 0.15 | H26: =+IPO_Discount -> 0.15 | I26: =+IPO_Discount -> 0.15 | J26: =+IPO_Discount -> 0.15
C27: Pricing Discount Amount: | F27: $ M | G27: =+G24-G29 -> 401.61683 | H27: =+H24-H29 -> 458.99066 | I27: =+I24-I29 -> 516.36449 | J27: =+J24-J29 -> 573.73832
C29: Implied Post-Money Equity Value @ Pricing: | F29: $ M | G29: =+G24/(1+G26) -> 2677.4455 | H29: =+H24/(1+H26) -> 3059.9377 | I29: =+I24/(1+I26) -> 3442.4299 | J29: =+J24/(1+J26) -> 3824.9222
C31: Issuer - Existing Shares Outstanding: | F31: M Shares | G31: =+Issuer_Existing_Shares -> 66.914438 | H31: =+Issuer_Existing_Shares -> 66.914438 | I31: =+Issuer_Existing_Shares -> 66.914438 | J31: =+Issuer_Existing_Shares -> 66.914438
C32: Implied Offering Price per Share: | F32: $ as Stated | G32: =(+G29-IPO_Offering_Size)/G31 -> 25.068514 | H32: =(+H29-IPO_Offering_Size)/H31 -> 30.784652 | I32: =(+I29-IPO_Offering_Size)/I31 -> 36.500791 | J32: =(+J29-IPO_Offering_Size)/J31 -> 42.21693
C34: Post-Transaction Shares Outstanding Calculations:
C35: (+) Primary Shares Issued in IPO: | F35: M Shares | G35: =+G29/G32-G31 -> 39.890678 | H35: =+H29/H32-H31 -> 32.483719 | I35: =+I29/I32-I31 -> 27.396666 | J35: =+J29/J32-J31 -> 23.68718
C36: (+) Secondary Shares Sold in IPO: | F36: M Shares | G36: =+G35/Primary_Share_Pct-G35 -> 13.296893 | H36: =+H35/Primary_Share_Pct-H35 -> 10.827906 | I36: =+I35/Primary_Share_Pct-I35 -> 9.1322222 | J36: =+J35/Primary_Share_Pct-J35 -> 7.8957265
C37: Total Shares Issued or Sold in IPO: | F37: M Shares | G37: =SUM(G35:G36) -> 53.18757 | H37: =SUM(H35:H36) -> 43.311625 | I37: =SUM(I35:I36) -> 36.528889 | J37: =SUM(J35:J36) -> 31.582906
C39: Total Shares Issued or Sold in Base Deal: | F39: M Shares | G39: =+G37/(1+Greenshoe_Pct) -> 46.250061 | H39: =+H37/(1+Greenshoe_Pct) -> 37.662283 | I39: =+I37/(1+Greenshoe_Pct) -> 31.764251 | J39: =+J37/(1+Greenshoe_Pct) -> 27.463397
C40: Total Overallotment Shares: | F40: M Shares | G40: =+G37-G39 -> 6.9375092 | H40: =+H37-H39 -> 5.6493425 | I40: =+I37-I39 -> 4.7646376 | J40: =+J37-J39 -> 4.1195095
C42: Pro-Forma Shares Outstanding, Post-IPO: | F42: M Shares | G42: =+G29/G32 -> 106.80512 | H42: =+H29/H32 -> 99.398158 | I42: =+I29/I32 -> 94.311105 | J42: =+J29/J32 -> 90.601618
C44: Primary Shares Issued - Basic Offering: | F44: M Shares | G44: =+G35-G45 -> 34.687546 | H44: =+H35-H45 -> 28.246712 | I44: =+I35-I45 -> 23.823188 | J44: =+J35-J45 -> 20.597547
C45: Primary Shares Issued - Overallotment: | F45: M Shares | G45: =+G40*Greenshoe_Primary_Pct -> 5.2031319 | H45: =+H40*Greenshoe_Primary_Pct -> 4.2370068 | I45: =+I40*Greenshoe_Primary_Pct -> 3.5734782 | J45: =+J40*Greenshoe_Primary_Pct -> 3.0896321
C47: Secondary Shares Sold - Basic Offering: | F47: M Shares | G47: =+G36-G48 -> 11.562515 | H47: =+H36-H48 -> 9.4155708 | I47: =+I36-I48 -> 7.9410627 | J47: =+J36-J48 -> 6.8658492
C48: Secondary Shares Sold - Overallotment: | F48: M Shares | G48: =+G40*(1-Greenshoe_Primary_Pct) -> 1.7343773 | H48: =+H40*(1-Greenshoe_Primary_Pct) -> 1.4123356 | I48: =+I40*(1-Greenshoe_Primary_Pct) -> 1.1911594 | J48: =+J40*(1-Greenshoe_Primary_Pct) -> 1.0298774
C50: Deal Size & Gross and Net Proceeds to Issuer:
C52: Base Deal Size (Primary + Secondary): | F52: $ M | G52: =+G39*G32 -> 1159.4203 | H52: =+H39*H32 -> 1159.4203 | I52: =+I39*I32 -> 1159.4203 | J52: =+J39*J32 -> 1159.4203
C53: (+) Total Overallotment: | F53: $ M | G53: =+G40*G32 -> 173.91304 | H53: =+H40*H32 -> 173.91304 | I53: =+I40*I32 -> 173.91304 | J53: =+J40*J32 -> 173.91304
C54: Total Offering Size: | F54: $ M | G54: =SUM(G52:G53) -> 1333.3333 | H54: =SUM(H52:H53) -> 1333.3333 | I54: =SUM(I52:I53) -> 1333.3333 | J54: =SUM(J52:J53) -> 1333.3333
C56: Gross Primary Proceeds: | F56: $ M | G56: =+G35*G32 -> 1000 | H56: =+H35*H32 -> 1000 | I56: =+I35*I32 -> 1000 | J56: =+J35*J32 -> 1000
C57: (-) Underwriting Discount: | F57: $ M | G57: =-G56*IPO_Spread -> -50 | H57: =-H56*IPO_Spread -> -50 | I57: =-I56*IPO_Spread -> -50 | J57: =-J56*IPO_Spread -> -50
C58: (-) Deal-Related Fees: | F58: $ M | G58: =-$J$13 -> -10 | H58: =-$J$13 -> -10 | I58: =-$J$13 -> -10 | J58: =-$J$13 -> -10
C59: Net IPO Proceeds to Issuer: | F59: $ M | G59: =SUM(G56:G58) -> 940 | H59: =SUM(H56:H58) -> 940 | I59: =SUM(I56:I58) -> 940 | J59: =SUM(J56:J58) -> 940
C61: Implied Pre-Money Equity Value: | F61: $ M | G61: =+G29-G56 -> 1677.4455 | H61: =+H29-H56 -> 2059.9377 | I61: =+I29-I56 -> 2442.4299 | J61: =+J29-J56 -> 2824.9222
C62: % Company Sold in IPO: | F62: % | G62: =+G56/G29 -> 0.37349033 | H62: =+H56/H29 -> 0.32680404 | I62: =+I56/I29 -> 0.29049248 | J62: =+J56/J29 -> 0.26144323
C64: Valuation Multiples @ Pricing and Trading:
C66: Implied Post-Money Equity Value @ Trading: | F66: $ M | G66: =+G24 -> 3079.0623 | H66: =+H24 -> 3518.9284 | I66: =+I24 -> 3958.7944 | J66: =+J24 -> 4398.6605
C67: (-) Net IPO Proceeds: | F67: $ M | G67: =-G59 -> -940 | H67: =-H59 -> -940 | I67: =-I59 -> -940 | J67: =-J59 -> -940
C68: (-) Cash & Cash-Equivalents: | F68: $ M | G68: -158.10071 | H68: -158.10071 | I68: -158.10071 | J68: -158.10071
C69: (-) Equity Investments: | F69: $ M | G69: 0 | H69: 0 | I69: 0 | J69: 0
C70: (-) Other Non-Core Assets, Net: | F70: $ M | G70: 0 | H70: 0 | I70: 0 | J70: 0
C71: (-) Net Operating Losses: | F71: $ M | G71: 0 | H71: 0 | I71: 0 | J71: 0
C72: (+) Total Debt: | F72: $ M | G72: 29.434871 | H72: 29.434871 | I72: 29.434871 | J72: 29.434871
C73: (+) Noncontrolling Interests: | F73: $ M | G73: 0 | H73: 0 | I73: 0 | J73: 0
C74: Implied Post-Money Enterprise Value @ Trading: | F74: $ M | G74: =SUM(G66:G73) -> 2010.3965 | H74: =SUM(H66:H73) -> 2450.2626 | I74: =SUM(I66:I73) -> 2890.1286 | J74: =SUM(J66:J73) -> 3329.9946
C76: Implied Post-Money Equity Value @ Pricing: | F76: $ M | G76: =+G29 -> 2677.4455 | H76: =+H29 -> 3059.9377 | I76: =+I29 -> 3442.4299 | J76: =+J29 -> 3824.9222
C77: Implied Post-Money Enterprise Value @ Pricing: | F77: $ M | G77: =+G76+SUM(G67:G73) -> 1608.7797 | H77: =+H76+SUM(H67:H73) -> 1991.2719 | I77: =+I76+SUM(I67:I73) -> 2373.7641 | J77: =+J76+SUM(J67:J73) -> 2756.2563
C79: Implied Forward P / E Multiple at Pricing: | F79: x | G79: =+G76/Forward_Year_1_Net_Income -> 15.217391 | H79: =+H76/Forward_Year_1_Net_Income -> 17.391304 | I79: =+I76/Forward_Year_1_Net_Income -> 19.565217 | J79: =+J76/Forward_Year_1_Net_Income -> 21.73913
C80: Implied Forward P / E Multiple at Trading: | F80: x | G80: =+G66/Forward_Year_1_Net_Income -> 17.5 | H80: =+H66/Forward_Year_1_Net_Income -> 20 | I80: =+I66/Forward_Year_1_Net_Income -> 22.5 | J80: =+J66/Forward_Year_1_Net_Income -> 25
C82: Implied Forward EV / EBITDA Multiple at Pricing: | F82: x | G82: =+G77/Forward_Year_1_EBITDA -> 6.4416857 | H82: =+H77/Forward_Year_1_EBITDA -> 7.9732159 | I82: =+I77/Forward_Year_1_EBITDA -> 9.5047461 | J82: =+J77/Forward_Year_1_EBITDA -> 11.036276
C83: Implied Forward EV / EBITDA Multiple at Trading: | F83: x | G83: =+G74/Forward_Year_1_EBITDA -> 8.0497924 | H83: =+H74/Forward_Year_1_EBITDA -> 9.8110522 | I83: =+I74/Forward_Year_1_EBITDA -> 11.572312 | J83: =+J74/Forward_Year_1_EBITDA -> 13.333572
C85: Implied Forward EV / Revenue Multiple at Pricing: | F85: x | G85: =+G77/Forward_Year_1_Revenue -> 3.3242322 | H85: =+H77/Forward_Year_1_Revenue -> 4.1145784 | I85: =+I77/Forward_Year_1_Revenue -> 4.9049247 | J85: =+J77/Forward_Year_1_Revenue -> 5.6952709
C86: Implied Forward EV / Revenue Multiple at Trading: | F86: x | G86: =+G74/Forward_Year_1_Revenue -> 4.1540957 | H86: =+H74/Forward_Year_1_Revenue -> 5.0629939 | I86: =+I74/Forward_Year_1_Revenue -> 5.9718921 | J86: =+J74/Forward_Year_1_Revenue -> 6.8807902

Sheet Alt-IPO-Model
B2: IPO Valuation & Financing Model - Alternate Version Based on Shares Issued and Offering Price
B3: =+'IPO-Model'!$B$3 -> ($ USD in Millions Except Per Share Values in $ as Stated)
B5: IPO Transaction Assumptions:
C7: Underwriting Discount: | E7: =+IPO_Spread -> 0.05 | G7: Expense Assumptions: | J7: $ in Millions
C8: IPO Pricing Discount: | E8: =+IPO_Discount -> 0.15 | G8: (+) SEC Filing & Registration Fees: | J8: =+'IPO-Model'!J9 -> 1.5
G9: (+) Printing Fees: | J9: =+'IPO-Model'!J10 -> 1
C10: Primary Shares Issued: | E10: 30 | G10: (+) Accounting & Legal Fees: | J10: =+'IPO-Model'!J11 -> 6
C11: Secondary Shares Sold: | E11: 10 | G11: (+) Miscellaneous / Other Fees: | J11: =+'IPO-Model'!J12 -> 1.5
G12: Total Fees: | J12: =SUM(J8:J11) -> 10
C13: Greenshoe Provision %: | E13: =+Greenshoe_Pct -> 0.15
C14: Primary Allocation %: | E14: =+Greenshoe_Primary_Pct -> 0.75 | G14: Forward Year 1 Revenue: | J14: =+Forward_Year_1_Revenue -> 483.95526
G15: Forward Year 1 EBITDA: | J15: =+Forward_Year_1_EBITDA -> 249.74514
C16: Issuer - Existing Shares: | E16: =+'IPO-Model'!E18 -> 66.914438 | G16: Forward Year 1 Net Income: | J16: =+Forward_Year_1_Net_Income -> 175.94642
G18: Filing Range - Offering Prices:
B19: Offering Price per Share: | F19: Units: | G19: 25 | H19: =+G19+5 -> 30 | I19: =+H19+5 -> 35 | J19: =+I19+5 -> 40
C21: (+) Primary Shares Issued: | F21: M Shares | G21: =+Primary_Shares -> 30 | H21: =+Primary_Shares -> 30 | I21: =+Primary_Shares -> 30 | J21: =+Primary_Shares -> 30
C22: (+) Secondary Shares Sold: | F22: M Shares | G22: =+Secondary_Shares -> 10 | H22: =+Secondary_Shares -> 10 | I22: =+Secondary_Shares -> 10 | J22: =+Secondary_Shares -> 10
C23: Total Shares Issued or Sold in Base Deal: | F23: M Shares | G23: =SUM(G21:G22) -> 40 | H23: =SUM(H21:H22) -> 40 | I23: =SUM(I21:I22) -> 40 | J23: =SUM(J21:J22) -> 40
C25: (+) Overallotment - Primary Shares Issued: | F25: M Shares | G25: =+G23*Greenshoe_Pct*Greenshoe_Primary_Pct -> 4.5 | H25: =+H23*Greenshoe_Pct*Greenshoe_Primary_Pct -> 4.5 | I25: =+I23*Greenshoe_Pct*Greenshoe_Primary_Pct -> 4.5 | J25: =+J23*Greenshoe_Pct*Greenshoe_Primary_Pct -> 4.5
C26: (+) Overallotment - Secondary Shares Sold: | F26: M Shares | G26: =+G23*Greenshoe_Pct*(1-Greenshoe_Primary_Pct) -> 1.5 | H26: =+H23*Greenshoe_Pct*(1-Greenshoe_Primary_Pct) -> 1.5 | I26: =+I23*Greenshoe_Pct*(1-Greenshoe_Primary_Pct) -> 1.5 | J26: =+J23*Greenshoe_Pct*(1-Greenshoe_Primary_Pct) -> 1.5
C27: Total Overallotment: | F27: M Shares | G27: =SUM(G25:G26) -> 6 | H27: =SUM(H25:H26) -> 6 | I27: =SUM(I25:I26) -> 6 | J27: =SUM(J25:J26) -> 6
C29: Issuer - Existing Shares Outstanding: | F29: M Shares | G29: =+Issuer_Existing_Shares -> 66.914438 | H29: =+Issuer_Existing_Shares -> 66.914438 | I29: =+Issuer_Existing_Shares -> 66.914438 | J29: =+Issuer_Existing_Shares -> 66.914438
C30: (+) Total Primary Shares Issued: | F30: M Shares | G30: =+G21+G25 -> 34.5 | H30: =+H21+H25 -> 34.5 | I30: =+I21+I25 -> 34.5 | J30: =+J21+J25 -> 34.5
C31: Pro-Forma Shares Outstanding, Post-IPO: | F31: M Shares | G31: =SUM(G29:G30) -> 101.41444 | H31: =SUM(H29:H30) -> 101.41444 | I31: =SUM(I29:I30) -> 101.41444 | J31: =SUM(J29:J30) -> 101.41444
C33: Post-Money Equity Value @ Trading and @ Pricing:
C35: Implied Post-Money Equity Value @ Pricing: | F35: $ M | G35: =+G19*G31 -> 2535.361 | H35: =+H19*H31 -> 3042.4332 | I35: =+I19*I31 -> 3549.5053 | J35: =+J19*J31 -> 4056.5775
C37: Pricing Discount %: | F37: % | G37: =+IPO_Discount -> 0.15 | H37: =+IPO_Discount -> 0.15 | I37: =+IPO_Discount -> 0.15 | J37: =+IPO_Discount -> 0.15
C38: Pricing Discount Amount: | F38: $ M | G38: =+G40-G35 -> 380.30414 | H38: =+H40-H35 -> 456.36497 | I38: =+I40-I35 -> 532.4258 | J38: =+J40-J35 -> 608.48663
C40: Implied Post-Money Equity Value @ Trading: | F40: $ M | G40: =+G35*(1+G37) -> 2915.6651 | H40: =+H35*(1+H37) -> 3498.7981 | I40: =+I35*(1+I37) -> 4081.9311 | J40: =+J35*(1+J37) -> 4665.0642
C42: Deal Size & Gross and Net Proceeds to Issuer:
C44: Base Deal Size (Primary + Secondary): | F44: $ M | G44: =+G23*G19 -> 1000 | H44: =+H23*H19 -> 1200 | I44: =+I23*I19 -> 1400 | J44: =+J23*J19 -> 1600
C45: (+) Total Overallotment: | F45: $ M | G45: =+G27*G19 -> 150 | H45: =+H27*H19 -> 180 | I45: =+I27*I19 -> 210 | J45: =+J27*J19 -> 240
C46: Total Offering Size: | F46: $ M | G46: =SUM(G44:G45) -> 1150 | H46: =SUM(H44:H45) -> 1380 | I46: =SUM(I44:I45) -> 1610 | J46: =SUM(J44:J45) -> 1840
C48: Gross Primary Proceeds: | F48: $ M | G48: =+G30*G19 -> 862.5 | H48: =+H30*H19 -> 1035 | I48: =+I30*I19 -> 1207.5 | J48: =+J30*J19 -> 1380
C49: (-) Underwriting Discount: | F49: $ M | G49: =-G30*G19*IPO_Spread -> -43.125 | H49: =-H30*H19*IPO_Spread -> -51.75 | I49: =-I30*I19*IPO_Spread -> -60.375 | J49: =-J30*J19*IPO_Spread -> -69
C50: (-) Deal-Related Fees: | F50: $ M | G50: =-$J$12 -> -10 | H50: =-$J$12 -> -10 | I50: =-$J$12 -> -10 | J50: =-$J$12 -> -10
C51: Net IPO Proceeds to Issuer: | F51: $ M | G51: =SUM(G48:G50) -> 809.375 | H51: =SUM(H48:H50) -> 973.25 | I51: =SUM(I48:I50) -> 1137.125 | J51: =SUM(J48:J50) -> 1301
C53: Implied Pre-Money Equity Value: | F53: $ M | G53: =+G35-G48 -> 1672.861 | H53: =+H35-H48 -> 2007.4332 | I53: =+I35-I48 -> 2342.0053 | J53: =+J35-J48 -> 2676.5775
C54: % Company Sold in IPO: | F54: % | G54: =+G48/G35 -> 0.34018825 | H54: =+H48/H35 -> 0.34018825 | I54: =+I48/I35 -> 0.34018825 | J54: =+J48/J35 -> 0.34018825
C56: Valuation Multiples @ Pricing and Trading:
C58: Implied Post-Money Equity Value @ Trading: | F58: $ M | G58: =+G40 -> 2915.6651 | H58: =+H40 -> 3498.7981 | I58: =+I40 -> 4081.9311 | J58: =+J40 -> 4665.0642
C59: (-) Net IPO Proceeds: | F59: $ M | G59: =-G51 -> -809.375 | H59: =-H51 -> -973.25 | I59: =-I51 -> -1137.125 | J59: =-J51 -> -1301
C60: (-) Cash & Cash-Equivalents: | F60: $ M | G60: =+'IPO-Model'!G68 -> -158.10071 | H60: =+'IPO-Model'!H68 -> -158.10071 | I60: =+'IPO-Model'!I68 -> -158.10071 | J60: =+'IPO-Model'!J68 -> -158.10071
C61: (-) Equity Investments: | F61: $ M | G61: =+'IPO-Model'!G69 -> 0 | H61: =+'IPO-Model'!H69 -> 0 | I61: =+'IPO-Model'!I69 -> 0 | J61: =+'IPO-Model'!J69 -> 0
C62: (-) Other Non-Core Assets, Net: | F62: $ M | G62: =+'IPO-Model'!G70 -> 0 | H62: =+'IPO-Model'!H70 -> 0 | I62: =+'IPO-Model'!I70 -> 0 | J62: =+'IPO-Model'!J70 -> 0
C63: (-) Net Operating Losses: | F63: $ M | G63: =+'IPO-Model'!G71 -> 0 | H63: =+'IPO-Model'!H71 -> 0 | I63: =+'IPO-Model'!I71 -> 0 | J63: =+'IPO-Model'!J71 -> 0
C64: (+) Total Debt: | F64: $ M | G64: =+'IPO-Model'!G72 -> 29.434871 | H64: =+'IPO-Model'!H72 -> 29.434871 | I64: =+'IPO-Model'!I72 -> 29.434871 | J64: =+'IPO-Model'!J72 -> 29.434871
C65: (+) Noncontrolling Interests: | F65: $ M | G65: =+'IPO-Model'!G73 -> 0 | H65: =+'IPO-Model'!H73 -> 0 | I65: =+'IPO-Model'!I73 -> 0 | J65: =+'IPO-Model'!J73 -> 0
C66: Implied Post-Money Enterprise Value @ Trading: | F66: $ M | G66: =SUM(G58:G65) -> 1977.6243 | H66: =SUM(H58:H65) -> 2396.8823 | I66: =SUM(I58:I65) -> 2816.1403 | J66: =SUM(J58:J65) -> 3235.3983
C68: Implied Post-Money Equity Value @ Pricing: | F68: $ M | G68: =+G35 -> 2535.361 | H68: =+H35 -> 3042.4332 | I68: =+I35 -> 3549.5053 | J68: =+J35 -> 4056.5775
C69: Implied Post-Money Enterprise Value @ Pricing: | F69: $ M | G69: =+G68+SUM(G59:G65) -> 1597.3201 | H69: =+H68+SUM(H59:H65) -> 1940.5173 | I69: =+I68+SUM(I59:I65) -> 2283.7145 | J69: =+J68+SUM(J59:J65) -> 2626.9117
C71: Implied Forward P / E Multiple at Pricing: | F71: x | G71: =+G68/Forward_Year_1_Net_Income -> 14.409847 | H71: =+H68/Forward_Year_1_Net_Income -> 17.291816 | I71: =+I68/Forward_Year_1_Net_Income -> 20.173786 | J71: =+J68/Forward_Year_1_Net_Income -> 23.055755
C72: Implied Forward P / E Multiple at Trading: | F72: x | G72: =+G58/Forward_Year_1_Net_Income -> 16.571324 | H72: =+H58/Forward_Year_1_Net_Income -> 19.885589 | I72: =+I58/Forward_Year_1_Net_Income -> 23.199853 | J72: =+J58/Forward_Year_1_Net_Income -> 26.514118
C74: Implied Forward EV / EBITDA Multiple at Pricing: | F74: x | G74: =+G69/Forward_Year_1_EBITDA -> 6.3958008 | H74: =+H69/Forward_Year_1_EBITDA -> 7.7699905 | I74: =+I69/Forward_Year_1_EBITDA -> 9.1441802 | J74: =+J69/Forward_Year_1_EBITDA -> 10.51837
C75: Implied Forward EV / EBITDA Multiple at Trading: | F75: x | G75: =+G66/Forward_Year_1_EBITDA -> 7.9185697 | H75: =+H66/Forward_Year_1_EBITDA -> 9.5973132 | I75: =+I66/Forward_Year_1_EBITDA -> 11.276057 | J75: =+J66/Forward_Year_1_EBITDA -> 12.9548
C77: Implied Forward EV / Revenue Multiple at Pricing: | F77: x | G77: =+G69/Forward_Year_1_Revenue -> 3.3005533 | H77: =+H69/Forward_Year_1_Revenue -> 4.0097039 | I77: =+I69/Forward_Year_1_Revenue -> 4.7188546 | J77: =+J69/Forward_Year_1_Revenue -> 5.4280052
C78: Implied Forward EV / Revenue Multiple at Trading: | F78: x | G78: =+G66/Forward_Year_1_Revenue -> 4.0863783 | H78: =+H66/Forward_Year_1_Revenue -> 4.9526939 | I78: =+I66/Forward_Year_1_Revenue -> 5.8190096 | J78: =+J66/Forward_Year_1_Revenue -> 6.6853252
