Workbook
Name Ccy: Inputs!$C$19
Name circ: Inputs!#REF!
Name CoName: Inputs!#REF!
Name D_EBITDA: Company0650_data!$G$19
Name D_EBITDA: Company0777_data!$G$19
Name D_EBITDA: Company1507_data!$G$19
Name D_EBITDA: Company1930_data!$G$19
Name Data: Company0650_data!$B$6:$M$9
Name Data: #REF!
Name Data: Company0777_data!$B$6:$M$9
Name Data: #REF!
Name Data: Company1507_data!$B$6:$M$9
Name Data: #REF!
Name Data: Company1930_data!$B$6:$M$9
Name Data: #REF!
Name DIVYIELD: Company0650!$I$30
Name DIVYIELD: Company0777!$I$30
Name DIVYIELD: Company1507!$I$30
Name DIVYIELD: Company1930!$I$30
Name E_Int: Company0650_data!$G$21
Name E_Int: Company0777_data!$G$21
Name E_Int: Company1507_data!$G$21
Name E_Int: Company1930_data!$G$21
Name EBITCY1: Company0650!$L$64
Name EBITCY1: Company0777!$L$64
Name EBITCY1: Company1507!$L$64
Name EBITCY1: Company1930!$L$64
Name EBITCY2: Company0650!$M$64
Name EBITCY2: Company0777!$M$64
Name EBITCY2: Company1507!$M$64
Name EBITCY2: Company1930!$M$64
Name EBITDACY1: Company0650!$L$63
Name EBITDACY1: Company0777!$L$63
Name EBITDACY1: Company1507!$L$63
Name EBITDACY1: Company1930!$L$63
Name EBITDACY2: Company0650!$M$63
Name EBITDACY2: Company0777!$M$63
Name EBITDACY2: Company1507!$M$63
Name EBITDACY2: Company1930!$M$63
Name EBITDAMLTM: Company0650_data!$H$14
Name EBITDAMLTM: Company0777_data!$H$14
Name EBITDAMLTM: Company1507_data!$H$14
Name EBITDAMLTM: Company1930_data!$H$14
Name EBITMLTM: Company0650_data!$H$15
Name EBITMLTM: Company0777_data!$H$15
Name EBITMLTM: Company1507_data!$H$15
Name EBITMLTM: Company1930_data!$H$15
Name EnterpriseValue: Company0650!$D$8
Name EnterpriseValue: Company0777!$D$8
Name EnterpriseValue: Company1507!$D$8
Name EnterpriseValue: Company1930!$D$8
Name EPS5YGROWTH: Company0650!$I$29
Name EPS5YGROWTH: Company0777!$I$29
Name EPS5YGROWTH: Company1507!$I$29
Name EPS5YGROWTH: Company1930!$I$29
Name Equityvalue: Company0650!$D$7
Name Equityvalue: Company0777!$D$7
Name Equityvalue: Company1507!$D$7
Name Equityvalue: Company1930!$D$7
Name EV_EBIT1F: Company0650!$E$19

Sheet Inputs
A1: Valuation Training
A2: Comparable companies analysis
A4: Special features
B6: Enterprise value
B7: Normalized earnings
B8: Operating statistics
B9: Credit statistics
B10: Multiples
B11: Output summaries
A17: Model information
B19: Currency | C19: USD
B20: Units | C20: m
B21: Analyst name | C21: Analyst name

Sheet Summary
A1: Trading Summary of Comparable Companies
A2: (Figures in millions, except per-share data)
A4: Date of analysis: April, 12th 2018
F5: EV multiples | O5: P/E
C6: Current | D6: Equity | E6: Enterprise | F6: Revenue | G6: Revenue | H6: Revenue | I6: EBITDA | J6: EBITDA | K6: EBITDA | L6: EBIT | M6: EBIT | N6: EBIT
A7: Company | C7: Price | D7: Value ($) | E7: Value ($) | F7: LTM | G7: CY 1 | H7: CY 2 | I7: =F7 | J7: =G7 | K7: =H7 | L7: =I7 | M7: =J7 | N7: =K7 | O7: =M7 | P7: =N7
A8: Company0650 | C8: =INDIRECT($A8&"!"&"shareprice") | D8: =INDIRECT($A8&"!"&"EquityValue")*INDIRECT($A8&"!"&"FX") | E8: =INDIRECT($A8&"!"&"EnterpriseValue")*INDIRECT($A8&"!"&"FX") | F8: =INDIRECT($A8&"!"&"EV_SLTM") | G8: =INDIRECT($A8&"!"&"EV_S1F") | H8: =INDIRECT($A8&"!"&"EV_S2F") | I8: =INDIRECT($A8&"!"&"EV_EBITDALTM") | J8: =INDIRECT($A8&"!"&"EV_EBITDA1F") | K8: =INDIRECT($A8&"!"&"EV_EBITDA2F") | L8: =INDIRECT($A8&"!"&"EV_EBITLTM") | M8: =INDIRECT($A8&"!"&"EV_EBIT1F") | N8: =INDIRECT($A8&"!"&"EV_EBIT2F") | O8: =INDIRECT($A8&"!"&"PE1F") | P8: =INDIRECT($A8&"!"&"PE2F")
A9: Company0691 | C9: 37.72 | D9: 15182.3 | E9: 18800.9 | F9: 1.97 | G9: 1.88 | H9: 1.86 | I9: 14.51 | J9: 12.31 | K9: 12.32 | L9: 18.26 | M9: 15.21 | N9: 15.19 | O9: 18.42 | P9: 16.38
A10: Company0777 | C10: =INDIRECT($A10&"!"&"shareprice") | D10: =INDIRECT($A10&"!"&"EquityValue")*INDIRECT($A10&"!"&"FX") | E10: =INDIRECT($A10&"!"&"EnterpriseValue")*INDIRECT($A10&"!"&"FX") | F10: =INDIRECT($A10&"!"&"EV_SLTM") | G10: =INDIRECT($A10&"!"&"EV_S1F") | H10: =INDIRECT($A10&"!"&"EV_S2F") | I10: =INDIRECT($A10&"!"&"EV_EBITDALTM") | J10: =INDIRECT($A10&"!"&"EV_EBITDA1F") | K10: =INDIRECT($A10&"!"&"EV_EBITDA2F") | L10: =INDIRECT($A10&"!"&"EV_EBITLTM") | M10: =INDIRECT($A10&"!"&"EV_EBIT1F") | N10: =INDIRECT($A10&"!"&"EV_EBIT2F") | O10: =INDIRECT($A10&"!"&"PE1F") | P10: =INDIRECT($A10&"!"&"PE2F")
A11: Company1137 | C11: 42.81 | D11: 24945.4 | E11: 33986.3 | F11: 2.2 | G11: 2.18 | H11: 2.05 | I11: 10.94 | J11: 10.59 | K11: 9.72 | L11: 13.46 | M11: 12.93 | N11: 12.16 | O11: 13.86 | P11: 13.35
A12: Company1243 | C12: 92.6 | D12: 19627 | E12: 23777.6 | F12: 2.58 | G12: 2.46 | H12: 2.41 | I12: 12.83 | J12: 12.53 | K12: 12.1 | L12: 15.05 | M12: 14.77 | N12: 14.21 | O12: 17.32 | P12: 16.47
A13: Company1507 | C13: =INDIRECT($A13&"!"&"shareprice") | D13: =INDIRECT($A13&"!"&"EquityValue")*INDIRECT($A13&"!"&"FX") | E13: =INDIRECT($A13&"!"&"EnterpriseValue")*INDIRECT($A13&"!"&"FX") | F13: =INDIRECT($A13&"!"&"EV_SLTM") | G13: =INDIRECT($A13&"!"&"EV_S1F") | H13: =INDIRECT($A13&"!"&"EV_S2F") | I13: =INDIRECT($A13&"!"&"EV_EBITDALTM") | J13: =INDIRECT($A13&"!"&"EV_EBITDA1F") | K13: =INDIRECT($A13&"!"&"EV_EBITDA2F") | L13: =INDIRECT($A13&"!"&"EV_EBITLTM") | M13: =INDIRECT($A13&"!"&"EV_EBIT1F") | N13: =INDIRECT($A13&"!"&"EV_EBIT2F") | O13: =INDIRECT($A13&"!"&"PE1F") | P13: =INDIRECT($A13&"!"&"PE2F")
A14: Company1523 | C14: 58.06 | D14: 71297.7 | E14: 102022.7 | F14: 3.88 | G14: 3.86 | H14: 3.81 | I14: 13.16 | J14: 12.94 | K14: 12.58 | L14: 15.14 | M14: 14.5 | N14: 14.2 | O14: 15.42 | P14: 14.62
A15: Company1825 | C15: 39.52 | D15: 59477.6 | E15: 77233.6 | F15: 2.9 | G15: 2.85 | H15: 2.78 | I15: 16.14 | J15: 14.02 | K15: 12.89 | L15: 19.55 | M15: 16.88 | N15: 15.93 | O15: 16.07 | P15: 14.82
A16: Company1930 | C16: =INDIRECT($A16&"!"&"shareprice") | D16: =INDIRECT($A16&"!"&"EquityValue")*INDIRECT($A16&"!"&"FX") | E16: =INDIRECT($A16&"!"&"EnterpriseValue")*INDIRECT($A16&"!"&"FX") | F16: =INDIRECT($A16&"!"&"EV_SLTM") | G16: =INDIRECT($A16&"!"&"EV_S1F") | H16: =INDIRECT($A16&"!"&"EV_S2F") | I16: =INDIRECT($A16&"!"&"EV_EBITDALTM") | J16: =INDIRECT($A16&"!"&"EV_EBITDA1F") | K16: =INDIRECT($A16&"!"&"EV_EBITDA2F") | L16: =INDIRECT($A16&"!"&"EV_EBITLTM") | M16: =INDIRECT($A16&"!"&"EV_EBIT1F") | N16: =INDIRECT($A16&"!"&"EV_EBIT2F") | O16: =INDIRECT($A16&"!"&"PE1F") | P16: =INDIRECT($A16&"!"&"PE2F")
A17: Pinnacle Foods | C17: 63.65 | D17: 7626.1 | E17: 10308.1 | F17: 3.25 | G17: 3.26 | H17: 3.2 | I17: 17.43 | J17: 14.66 | K17: 13.78 | L17: 22.7 | M17: 17.47 | N17: 16.38 | O17: 21.93 | P17: 20
A18: Company2838 | C18: 55.82 | D18: 131828.1 | E18: 153100.1 | F18: 3.01 | G18: 3.11 | H18: 3.06 | I18: 15.23 | J18: 14.9 | K18: 14.21 | L18: 17.81 | M18: 16.66 | N18: 16.01 | O18: 20.35 | P18: 18.74
B20: High | D20: =MAX(D8:D18) | E20: =MAX(E8:E18) | F20: =MAX(F8:F18) | G20: =MAX(G8:G18) | H20: =MAX(H8:H18) | I20: =MAX(I8:I18) | J20: =MAX(J8:J18) | K20: =MAX(K8:K18) | ... P20: =MAX(P8:P18)
B21: Mean | D21: =AVERAGE(D8:D18) | E21: =AVERAGE(E8:E18) | F21: =AVERAGE(F8:F18) | G21: =AVERAGE(G8:G18) | H21: =AVERAGE(H8:H18) | I21: =AVERAGE(I8:I18) | J21: =AVERAGE(J8:J18) | K21: =AVERAGE(K8:K18) | ... P21: =AVERAGE(P8:P18)
B22: Median | D22: =MEDIAN(D8:D18) | E22: =MEDIAN(E8:E18) | F22: =MEDIAN(F8:F18) | G22: =MEDIAN(G8:G18) | H22: =MEDIAN(H8:H18) | I22: =MEDIAN(I8:I18) | J22: =MEDIAN(J8:J18) | K22: =MEDIAN(K8:K18) | ... P22: =MEDIAN(P8:P18)
B23: Low | D23: =MIN(D8:D18) | E23: =MIN(E8:E18) | F23: =MIN(F8:F18) | G23: =MIN(G8:G18) | H23: =MIN(H8:H18) | I23: =MIN(I8:I18) | J23: =MIN(J8:J18) | K23: =MIN(K8:K18) | ... P23: =MIN(P8:P18)
A28: Performance Analysis of Comparable Companies
A29: =A2
D32: Margins
C33: 52 wk | D33: EBITDA | E33: EBITDA | F33: EBITDA | G33: EBIT | H33: Sales | I33: LT EPS | J33: PEG | K33: Dividend | N33: Debt/ | O33: Net Debt/ | P33: EBITDA/
A34: =A7 | C34: High % | D34: =F7 | E34: =G7 | F34: =H7 | G34: =I7 | H34: CAGR | I34: Growth | J34: =E34 | K34: Yield | L34: ROIC | M34: ROE | N34: EBITDA | O34: EBITDA | P34: Int. Exp.
A35: =A8 | C35: =INDIRECT($A8&"!"&"shareprice")/INDIRECT($A35&"!"&"SharePriceHigh") | D35: =INDIRECT($A35&"_data"&"!"&"EBITDAMLTM") | E35: =INDIRECT($A35&"!"&"EBITDACY1")/INDIRECT($A35&"!"&"SalesCY1") | F35: =INDIRECT($A35&"!"&"EBITDACY2")/INDIRECT($A35&"!"&"SalesCY2") | G35: =INDIRECT($A35&"_data"&"!"&"EBITMLTM") | H35: =INDIRECT($A35&"_data"&"!"&"SalesCAGR") | I35: =INDIRECT($A35&"!"&"EPS5YGROWTH") | J35: =O8/I35/100 | K35: =INDIRECT($A35&"!"&"DIVYIELD") | L35: =INDIRECT($A35&"_data"&"!"&"ROIC") | M35: =INDIRECT($A35&"_data"&"!"&"ROE") | N35: =INDIRECT($A35&"_data"&"!"&"D_EBITDA") | O35: =INDIRECT($A35&"_data"&"!"&"ND_EBITDA") | P35: =INDIRECT($A35&"_data"&"!"&"E_Int")
A36: =A9 | C36: 0.93725929 | D36: =F9/I9 | E36: =G9/J9 | F36: =H9/K9 | G36: =F9/L9 | H36: -0.101 | I36: 0.1035 | J36: 1.78 | K36: 0.0225 | L36: 0.0754 | M36: 0.166 | N36: 2.51 | O36: 2.3 | P36: 5.84
A37: =A10 | C37: =INDIRECT($A10&"!"&"shareprice")/INDIRECT($A37&"!"&"SharePriceHigh") | D37: =INDIRECT($A37&"_data"&"!"&"EBITDAMLTM") | E37: =INDIRECT($A37&"!"&"EBITDACY1")/INDIRECT($A37&"!"&"SalesCY1") | F37: =INDIRECT($A37&"!"&"EBITDACY2")/INDIRECT($A37&"!"&"SalesCY2") | G37: =INDIRECT($A37&"_data"&"!"&"EBITMLTM") | H37: =INDIRECT($A37&"_data"&"!"&"SalesCAGR") | I37: =INDIRECT($A37&"!"&"EPS5YGROWTH") | J37: =O10/I37/100 | K37: =INDIRECT($A37&"!"&"DIVYIELD") | L37: =INDIRECT($A37&"_data"&"!"&"ROIC") | M37: =INDIRECT($A37&"_data"&"!"&"ROE") | N37: =INDIRECT($A37&"_data"&"!"&"D_EBITDA") | O37: =INDIRECT($A37&"_data"&"!"&"ND_EBITDA") | P37: =INDIRECT($A37&"_data"&"!"&"E_Int")
A38: =A11 | C38: 0.70538804 | D38: =F11/I11 | E38: =G11/J11 | F38: =H11/K11 | G38: =F11/L11 | H38: -0.057 | I38: 0.073 | J38: 1.89 | K38: 0.0458 | L38: 0.1121 | M38: 0.301 | N38: 2.99 | O38: 2.75 | P38: 10.49
A39: =A12 | C39: 0.79491802 | D39: =F12/I12 | E39: =G12/J12 | F39: =H12/K12 | G39: =F12/L12 | H39: 0.0249 | I39: 0.048 | J39: 2.14 | K39: 0.0283 | L39: 0.2325 | M39: 0.9205 | N39: 1.9 | O39: 1.65 | P39: 15.35
A40: =A13 | C40: =INDIRECT($A13&"!"&"shareprice")/INDIRECT($A40&"!"&"SharePriceHigh") | D40: =INDIRECT($A40&"_data"&"!"&"EBITDAMLTM") | E40: =INDIRECT($A40&"!"&"EBITDACY1")/INDIRECT($A40&"!"&"SalesCY1") | F40: =INDIRECT($A40&"!"&"EBITDACY2")/INDIRECT($A40&"!"&"SalesCY2") | G40: =INDIRECT($A40&"_data"&"!"&"EBITMLTM") | H40: =INDIRECT($A40&"_data"&"!"&"SalesCAGR") | I40: =INDIRECT($A40&"!"&"EPS5YGROWTH") | J40: =O13/I40/100 | K40: =INDIRECT($A40&"!"&"DIVYIELD") | L40: =INDIRECT($A40&"_data"&"!"&"ROIC") | M40: =INDIRECT($A40&"_data"&"!"&"ROE") | N40: =INDIRECT($A40&"_data"&"!"&"D_EBITDA") | O40: =INDIRECT($A40&"_data"&"!"&"ND_EBITDA") | P40: =INDIRECT($A40&"_data"&"!"&"E_Int")
A41: =A14 | C41: 0.61844908 | D41: =F14/I14 | E41: =G14/J14 | F41: =H14/K14 | G41: =F14/L14 | H41: 0.012 | I41: 0.0704 | J41: 2.19 | K41: 0.0431 | L41: 0.1042 | M41: 0.1783 | N41: 4.04 | O41: 3.83 | P41: 6.33
A42: =A15 | C42: 0.8367563 | D42: =F15/I15 | E42: =G15/J15 | F42: =H15/K15 | G42: =F15/L15 | H42: -0.0586 | I42: 0.0224 | J42: 1.5 | K42: 0.0223 | L42: 0.0683 | M42: 0.114 | N42: 4.08 | O42: 3.91 | P42: 10
A43: =A16 | C43: =INDIRECT($A16&"!"&"shareprice")/INDIRECT($A43&"!"&"SharePriceHigh") | D43: =INDIRECT($A43&"_data"&"!"&"EBITDAMLTM") | E43: =INDIRECT($A43&"!"&"EBITDACY1")/INDIRECT($A43&"!"&"SalesCY1") | F43: =INDIRECT($A43&"!"&"EBITDACY2")/INDIRECT($A43&"!"&"SalesCY2") | G43: =INDIRECT($A43&"_data"&"!"&"EBITMLTM") | H43: =INDIRECT($A43&"_data"&"!"&"SalesCAGR") | I43: =INDIRECT($A43&"!"&"EPS5YGROWTH") | J43: =O16/I43/100 | K43: =INDIRECT($A43&"!"&"DIVYIELD") | L43: =INDIRECT($A43&"_data"&"!"&"ROIC") | M43: =INDIRECT($A43&"_data"&"!"&"ROE") | N43: =INDIRECT($A43&"_data"&"!"&"D_EBITDA") | O43: =INDIRECT($A43&"_data"&"!"&"ND_EBITDA") | P43: =INDIRECT($A43&"_data"&"!"&"E_Int")
A44: =A17 | C44: 0.95477387 | D44: =F17/I17 | E44: =G17/J17 | F44: =H17/K17 | G44: =F17/L17 | H44: 0.0487 | I44: 0.489 | J44: 2.28 | K44: 0.0204 | L44: 0.1065 | M44: 0.2459 | N44: 5.05 | O44: 4.63 | P44: 3.46
A45: =A18 | C45: 0.90587472 | D45: =F18/I18 | E45: =G18/J18 | F45: =H18/K18 | G45: =F18/L18 | H45: 0.0091 | I45: 0.0747 | J45: 3.08 | K45: 0.0311 | L45: 0.1995 | M45: 0.4038 | N45: 2.29 | O45: 1.93 | P45: 18.78
B47: High | C47: =MAX(C35:C45) | D47: =MAX(D35:D45) | E47: =MAX(E35:E45) | F47: =MAX(F35:F45) | G47: =MAX(G35:G45) | H47: =MAX(H35:H45) | I47: =MAX(I35:I45) | J47: =MAX(J35:J45) | ... P47: =MAX(P35:P45)
B48: Mean | C48: =AVERAGE(C35:C45) | D48: =AVERAGE(D35:D45) | E48: =AVERAGE(E35:E45) | F48: =AVERAGE(F35:F45) | G48: =AVERAGE(G35:G45) | H48: =AVERAGE(H35:H45) | I48: =AVERAGE(I35:I45) | J48: =AVERAGE(J35:J45) | ... P48: =AVERAGE(P35:P45)
B49: Median | C49: =MEDIAN(C35:C45) | D49: =MEDIAN(D35:D45) | E49: =MEDIAN(E35:E45) | F49: =MEDIAN(F35:F45) | G49: =MEDIAN(G35:G45) | H49: =MEDIAN(H35:H45) | I49: =MEDIAN(I35:I45) | J49: =MEDIAN(J35:J45) | ... P49: =MEDIAN(P35:P45)
B50: Low | C50: =MIN(C35:C45) | D50: =MIN(D35:D45) | E50: =MIN(E35:E45) | F50: =MIN(F35:F45) | G50: =MIN(G35:G45) | H50: =MIN(H35:H45) | I50: =MIN(I35:I45) | J50: =MIN(J35:J45) | ... P50: =MIN(P35:P45)

Sheet Company0650
A1: ="Comparable companies analysis - "&D26
A2: Input sheet (figures in millions, except per-share data)
A4: Summary Data
B5: Value numbers
C6: =F26 | D6: =I26
C7: =C40 | D7: =D40
C8: =C49 | D8: =D49
E9: Calendarized
B10: Value driver numbers | D10: LTM | E10: =DATE(YEAR(D35)+1,MONTH(D35),DAY(D35)) | F10: =DATE(YEAR(E10)+1,MONTH(E10),DAY(E10))
C11: Sales | D11: =F62 | E11: =L62 | F11: =M62
C12: EBITDA | D12: =F63 | E12: =L63 | F12: =M63
C13: EBIT | D13: =F64 | E13: =L64 | F13: =M64
C14: =C66 | E14: =L66 | F14: =M66
E16: Calendarized
B17: Valuation multiples | D17: =D10 | E17: =E10 | F17: =F10
C18: EV / Sales | D18: =EnterpriseValue/D11 | E18: =EnterpriseValue/E11 | F18: =EnterpriseValue/F11
C19: EV / EBIT | D19: =EnterpriseValue/D13 | E19: =EnterpriseValue/E13 | F19: =EnterpriseValue/F13
C20: EV / EBITDA | D20: =EnterpriseValue/D12 | E20: =EnterpriseValue/E12 | F20: =EnterpriseValue/F12
C21: P/E | E21: =SharePrice/E14 | F21: =SharePrice/F14
C22: PEG | E22: =PE1F/$I$29/100 | F22: =PE1F/$I$29/100
A24: Inputs
B25: Key company data | F25: Share data
C26: Company name | D26: Company0650 | F26: Share price | I26: 42.84
C27: Ticker symbol | D27: Ticker0005 | F27: 52 week high | I27: 59.14
C28: Date of analysis | D28: 43202 | F28: 52 week low | I28: 40.99
C29: Currency | D29: USD | F29: EPS 5yr growth rate | I29: =13.68/2.46/100
C30: FX rate to standard currency | D30: 1 | F30: Dividend yield | I30: 0.0327
C31: Historical year end | D31: 42946 | F31: Credit rating | I31: BBB
C32: Latest filing | D32: 43128 | F32: Shares outstanding basic | I32: 300.63399
C33: Type of filing | D33: Q | F33: Net new shares from stock compensation | I33: =K46
C34: What quarter? | D34: 2 | F34: Fully diluted shares outstanding | I34: =I32+I33
C35: Calendarize to: | D35: 43100
C36: Research used | D36: Consensus
C37: Research date | D37: =D28
B39: Enterprise value calculation | F39: Stock compensation | I39: =YEAR($D$31) | J39: =YEAR($D$31)
C40: Fully diluted equity value | D40: =I34*I26 | I40: Number | J40: Strike price | K40: Net shares
C41: =F52 | D41: =I52+(2516-2486)+6200 | F41: Stock options outstanding | I41: 1.617 | J41: 50.34 | K41: =MAX(($I$26-J41)/$I$26*I41,0)
C42: Cash and equivalents | D42: =SUM(D52:D53) | F42: Restricted stock units outstanding | I42: 1.236 | J42: 0 | K42: =MAX(($I$26-J42)/$I$26*I42,0)
C43: Net debt | D43: =D41-D42 | F43: TSR performance units | I43: 1.832 | J43: 0 | K43: =MAX(($I$26-J43)/$I$26*I43,0)
C44: =F53 | D44: =I53 | F44: Item 4 | I44: 0 | J44: 0 | K44: =MAX(($I$26-J44)/$I$26*I44,0)
C45: =F56 | D45: =I56 | F45: Item 5 | I45: 0 | J45: 0 | K45: =MAX(($I$26-J45)/$I$26*I45,0)
C46: =F57 | D46: =I57 | F46: Net new shares from stock compensation | K46: =SUM(K41:K45)
C47: =C54 | D47: =D54
C48: =C55 | D48: =D55
C49: Enterprise value | D49: =D40+SUM(D43:D46)-SUM(D47:D48)
B51: Balance sheet data | D51: =YEAR($D$32)&" "&+D33 | I51: =D51
C52: Cash and cash equivalents | D52: =196-106 | F52: Total debt | I52: =1659+2247
C53: Highly liquid investments | D53: 0 | F53: Debt equivalents | I53: 0
C54: Equity affiliates/associates and JVs | D54: 0 | F54: Operating liabilities | I54: =8336-106-SUM(I52:I53,I55:I57)
C55: Non-core assets | D55: 0 | F55: Shareholder equity | I55: 1942
C56: Operating assets | D56: =8336-106-SUM(D52:D55) | F56: Preferred stock | I56: 0 | K56: Calendarization
F57: Noncontrolling interest | I57: 7 | K57: Days: | L57: =D35-D31
C58: Total assets | D58: =SUM(D52:D56) | F58: Total liabilities and equity | I58: =SUM(I52:I57) | K58: % prior yr. | L58: % curr yr. | M58: % next yr.
C59: BS check | D59: =IF(D58=I58,"OK",D58-I58) | K59: =MAX(-L57/365,0) | L59: =1-K59-M59 | M59: =MAX(L57/365,0)
B61: Income statement data | D61: =YEAR($D$31)-1 | E61: =YEAR($D$31) | F61: LTM | G61: =YEAR($D$31)+1 & "E" | H61: =YEAR($D$31)+2 & "E" | I61: =YEAR($D$31)+3 & "E" | K61: =D35 | L61: =DATE(YEAR(K61)+1,MONTH(K61),DAY(K61)) | M61: =DATE(YEAR(L61)+1,MONTH(L61),DAY(L61))
C62: Sales | D62: =VLOOKUP($C62,Company0650_data!Data,5,0) | E62: =VLOOKUP($C62,Company0650_data!Data,6,0)+(E69*$K$74) | F62: =VLOOKUP($C62,Company0650_data!Data,7,0)+(F69*$K$74) | G62: =VLOOKUP($C62,Company0650_data!Data,10,0)+(G69*$L$74) | H62: =VLOOKUP($C62,Company0650_data!Data,11,0) | I62: =VLOOKUP($C62,Company0650_data!Data,12,0) | K62: =D62*$K$59+E62*$L$59+G62*$M$59 | L62: =E62*$K$59+G62*$L$59+H62*$M$59 | M62: =G62*$K$59+H62*$L$59+I62*$M$59
C63: EBITDA | D63: =VLOOKUP($C63,Company0650_data!Data,5,0) | E63: =VLOOKUP($C63,Company0650_data!Data,6,0)+(E70*$K$74) | F63: =VLOOKUP($C63,Company0650_data!Data,7,0)+(F70*$K$74) | G63: =VLOOKUP($C63,Company0650_data!Data,10,0)+(G70*$L$74) | H63: =VLOOKUP($C63,Company0650_data!Data,11,0) | I63: =VLOOKUP($C63,Company0650_data!Data,12,0) | K63: =D63*$K$59+E63*$L$59+G63*$M$59 | L63: =E63*$K$59+G63*$L$59+H63*$M$59 | M63: =G63*$K$59+H63*$L$59+I63*$M$59
C64: EBIT | D64: =VLOOKUP($C64,Company0650_data!Data,5,0) | E64: =VLOOKUP($C64,Company0650_data!Data,6,0)+(E71*$K$74) | F64: =VLOOKUP($C64,Company0650_data!Data,7,0)+(F71*$K$74) | G64: =VLOOKUP($C64,Company0650_data!Data,10,0)+(G71*$L$74) | H64: =VLOOKUP($C64,Company0650_data!Data,11,0) | I64: =VLOOKUP($C64,Company0650_data!Data,12,0) | K64: =D64*$K$59+E64*$L$59+G64*$M$59 | L64: =E64*$K$59+G64*$L$59+H64*$M$59 | M64: =G64*$K$59+H64*$L$59+I64*$M$59
C65: Net income | D65: =Company0650_data!F76 | E65: =Company0650_data!G76+E72*K74-Company0650_data!E145 | G65: =937+(G72-Company0650_data!$E$145)*L74 | H65: 978.41 | I65: 990.7 | K65: =D65*$K$59+E65*$L$59+G65*$M$59 | L65: =E65*$K$59+G65*$L$59+H65*$M$59 | M65: =G65*$K$59+H65*$L$59+I65*$M$59
C66: Recurring diluted EPS | D66: =VLOOKUP($C66,Company0650_data!Data,5,0) | E66: =E65/Company0650_data!G81 | G66: =G65/I34 | H66: =VLOOKUP($C66,Company0650_data!Data,11,0) | I66: =VLOOKUP($C66,Company0650_data!Data,12,0) | K66: =D66*$K$59+E66*$L$59+G66*$M$59 | L66: =E66*$K$59+G66*$L$59+H66*$M$59 | M66: =G66*$K$59+H66*$L$59+I66*$M$59
B68: Person1067 Company1596 Income statement data Calendarized | E68: =E61 | F68: LTM | G68: =G61 | K68: Person1067 Company1596 Calendarization to Ticker0005 year end
C69: Sales | E69: =D75*$K$71+E75*$L$71+G75*$M$71 | F69: =F75 | G69: =E75*$K$71+G75*$L$71+H75*$M$71 | K69: Days: | L69: =D31-E74
C70: EBITDA | E70: =D76*$K$71+E76*$L$71+G76*$M$71 | F70: =F76 | G70: =E76*$K$71+G76*$L$71+H76*$M$71 | K70: % prior yr. | L70: % curr yr. | M70: % next yr.
C71: EBIT | E71: =D77*$K$71+E77*$L$71+G77*$M$71 | F71: =F77 | G71: =E77*$K$71+G77*$L$71+H77*$M$71 | K71: =MAX(-L69/365,0) | L71: =1-K71-M71 | M71: =MAX(L69/365,0)
C72: Net income | E72: =D78*$K$71+E78*$L$71+G78*$M$71 | G72: =E78*$K$71+G78*$L$71+H78*$M$71
K73: Proforma adjustment needed
B74: Person1067 Company1596 Income statement data | D74: 42735 | E74: 43100 | F74: LTM | G74: 43465 | K74: 1 | L74: =1-(Company0650_data!K3-Company0650_data!E139)/365
C75: Sales | D75: =Company0650_data!C148 | E75: =Company0650_data!D148 | F75: =Company0650_data!E148 | G75: =Company0650_data!F148
C76: EBITDA | D76: =Company0650_data!C149 | E76: =Company0650_data!D149 | F76: =Company0650_data!E149 | G76: =Company0650_data!F149
C77: EBIT | D77: =Company0650_data!C150 | E77: =Company0650_data!D150 | F77: =Company0650_data!E150 | G77: =Company0650_data!F150
C78: Net income | D78: =Company0650_data!C151 | E78: =Company0650_data!D151 | G78: =Company0650_data!F151

Sheet Company0650_data
A1: Financial statement analysis - Company0650
C2: History | D2: History | E2: History | F2: History | G2: History | I2: Interim | J2: Interim | K2: Forecast | L2: Forecast | M2: Forecast
A3: Figures in millions, except per-share data | C3: =EDATE(D3,-12) | D3: =EDATE(E3,-12) | E3: =EDATE(F3,-12) | F3: 42582 | G3: =Company0650!D31 | H3: LTM | I3: Old | J3: New | K3: =EDATE(G3,12) | L3: =EDATE(K3,12) | M3: =EDATE(L3,12)
A5: Key income statement data
B6: Sales | C6: =C27 | D6: =D27 | E6: =E27 | F6: =F27 | G6: =G27 | H6: =G6-I6+J6 | I6: =I27 | J6: =J27 | K6: 8690.33 | L6: 10274 | M6: 10340.8
B7: EBITDA | F7: =F52 | G7: =G52 | H7: =G7-I7+J7 | I7: =I52 | J7: =J52 | K7: 1853 | L7: 2125.83 | M7: 2249
B8: EBIT | F8: =F46 | G8: =G46 | H8: =G8-I8+J8 | I8: =I46 | J8: =J46 | K8: 1479.79 | L8: 1663.61 | M8: 1703.5
B9: Recurring diluted EPS | F9: =F82 | G9: =G82 | K9: 3.11 | L9: 3.21 | M9: 3.401
N10: CAGR | O10: CAGR
A11: Key ratios | N11: =TEXT(YEAR(C3),"0000")&" - "&TEXT(YEAR(G3),"0000") | O11: =TEXT(YEAR(G3),"0000")&" - "&TEXT(YEAR(M3),"0000")
B12: Sales growth | D12: =D28 | E12: =E28 | F12: =F28 | G12: =G28 | K12: =K6/G6-1 | L12: =L6/K6-1 | M12: =M6/L6-1 | N12: =(G6/C6)^(1/4)-1 | O12: =(M6/G6)^(1/3)-1
B13: =B32 | F13: =F32 | G13: =G32
B14: EBITDA margin | F14: =F7/F6 | G14: =G7/G6 | H14: =H7/H6 | I14: =I7/I6 | J14: =J7/J6 | K14: =K7/K6 | L14: =L7/L6 | M14: =M7/M6
B15: EBIT margin | F15: =F8/F6 | G15: =G8/G6 | H15: =H8/H6 | I15: =I8/I6 | J15: =J8/J6 | K15: =K8/K6 | L15: =L8/L6 | M15: =M8/M6
B16: OWC / sales | F16: =F100 | G16: =G100
B17: Net PP&E / sales | F17: =F107 | G17: =G107
B18: CAPEX / depreciation | F18: =F109 | G18: =G109
B19: Total debt / EBITDA | F19: =F120 | G19: =G120
B20: Total net debt / EBITDA | F20: =F121 | G20: =G121
B21: EBITDA / interest expense | F21: =F124 | G21: =G124
B22: =B126 | F22: =F126 | G22: =G126
B23: ROIC | F23: =F135 | G23: =G135
B24: ROE | F24: =F129 | G24: =G129
A26: Income statement
B27: Sales | C27: 8052 | D27: 8268 | E27: 8082 | F27: 7961 | G27: 7890 | I27: 4373 | J27: 4341
B28: Sales growth | D28: =D27/C27-1 | E28: =E27/D27-1 | F28: =F27/E27-1 | G28: =G27/F27-1
B30: COGS | F30: 5181 | G30: =4831-4 | I30: 2711 | J30: =2792-6
B31: Gross profit | F31: =F27-F30 | G31: =G27-G30 | I31: =I27-I30 | J31: =J27-J30
B32: Gross margin | F32: =F31/F27 | G32: =G31/G27 | I32: =I31/I27 | J32: =J31/J27
B34: Reported operating profit | F34: 960 | G34: 1400 | I34: 662 | J34: 655
B35: Operating profit margin | F35: =F34/F27 | G35: =G34/G27 | I35: =I34/I27 | J35: =J34/J27
B36: Employee benefit plans remeasurement (gain) loss | F36: 313 | G36: -178 | I36: 20 | J36: -14
B37: Restructuring charges | F37: =35+47-4 | G37: =18+36+4 | I37: 11 | J37: =35+38+6
B38: Impairments of intangibles | F38: 141 | G38: =147+65 | I38: =147+65 | J38: 75
B39: Gain on settlement of claim on Company1509 acquisition | F39: -25 | G39: 0 | I39: 0 | J39: 0
B40: Transaction costs (Company2571- Company1596 acquisition) | F40: 0 | G40: 0 | I40: 0 | J40: 24
B41: Non-recurring item 6 | F41: 0 | G41: 0 | I41: 0 | J41: 0
B42: Non-recurring item 7 | F42: 0 | G42: 0 | I42: 0 | J42: 0
B43: Non-recurring item 8 | F43: 0 | G43: 0 | I43: 0 | J43: 0
B44: Non-recurring item 9 | F44: 0 | G44: 0 | I44: 0 | J44: 0
B45: Non-recurring item 10 | F45: 0 | G45: 0 | I45: 0 | J45: 0
B46: EBIT | F46: =F34+SUM(F36:F45) | G46: =G34+SUM(G36:G45) | I46: =I34+SUM(I36:I45) | J46: =J34+SUM(J36:J45)
B47: EBIT margin | F47: =F46/F27 | G47: =G46/G27 | I47: =I46/I27 | J47: =J46/J27
B49: Depreciation | F49: 288 | G49: 299 | I49: =154-I50 | J49: =161-J50
B50: Amortization | F50: 20 | G50: 19 | I50: 10 | J50: 8
B51: Depreciation and amortization | F51: =SUM(F49:F50) | G51: =SUM(G49:G50) | I51: =SUM(I49:I50) | J51: =SUM(J49:J50)
B52: EBITDA | F52: =F46+F51 | G52: =G46+G51 | I52: =I46+I51 | J52: =J46+J51
B53: EBITDA margin | F53: =F52/F27 | G53: =G52/G27 | I53: =I52/I27 | J53: =J52/J27
B55: Earnings before taxes | F55: 849 | G55: 1293
B56: Taxes | F56: 286 | G56: 406
B57: Reported ETR | F57: =F56/F55 | G57: =G56/G55
B58: Statutory tax rate | F58: 0.35 | G58: 0.35
B59: Other taxes affecting marginal tax rate | F59: 0.027 | G59: 0.021
B60: MTR | F60: =SUM(F58:F59) | G60: =SUM(G58:G59)
B62: NOPAT | F62: =F46*(1-F57) | G62: =G46*(1-G57)
B64: Reported net income (total) | F64: 563 | G64: 887
B65: Net income margin | F65: =F64/F27 | G65: =G64/G27
B66: =B36 | F66: 200 | G66: -116
B67: =B37 | F67: 49 | G67: 37
B68: =B38 | F68: 127 | G68: =139+41
B69: =B39 | F69: =F39 | G69: 0
B70: Tax and interest reduction | F70: 0 | G70: -56
B71: Non-recurring item 6 | F71: 0 | G71: 0
B72: Non-recurring item 7 | F72: 0 | G72: 0
B73: Non-recurring item 8 | F73: 0 | G73: 0
B74: Non-recurring item 9 | F74: 0 | G74: 0
B75: Non-recurring item 10 | F75: 0 | G75: 0
B76: Normalized net income | F76: =F64+SUM(F66:F75) | G76: =G64+SUM(G66:G75)
B77: Normalized net income margin | F77: =F76/F27 | G77: =G76/G27
B79: WASO - basic | F79: 309 | G79: 305
B80: Recurring basic EPS | F80: =F76/F79 | G80: =G76/G79
B81: WASO - diluted | F81: 311 | G81: 307
B82: Recurring diluted EPS | F82: =F76/F81 | G82: =G76/G81
A84: Current assets and liabilities
B85: Total current assets | F85: 1908 | G85: 1900
B86: Total current liabilities | F86: 2555 | G86: 2395
B87: Working Capital | F87: =F85-F86 | G87: =G85-G86
B89: Accounts receivable | F89: 626 | G89: 605
B90: Inventories | F90: 940 | G90: 902
B91: Other current assets | F91: 46 | G91: 74
B92: Current operating asset 4 | F92: 0 | G92: 0
B93: Current operating asset 5 | F93: 0 | G93: 0
B94: Payable to suppliers and others | F94: 610 | G94: 666
B95: Accrued liabilities | F95: 604 | G95: 561
B96: Accrued income taxes | F96: 22 | G96: 20
B97: Current operating liability 4 | F97: 0 | G97: 0
B98: Current operating liability 5 | F98: 0 | G98: 0
B99: OWC | F99: =SUM(F89:F93)-SUM(F94:F98) | G99: =SUM(G89:G93)-SUM(G94:G98)
B100: OWC % sales | F100: =F99/F27 | G100: =G99/G27
B101: Receivable days | F101: =F89/F27*365 | G101: =G89/G27*365
B102: Inventory days | F102: =F90/F30*365 | G102: =G90/G30*365
B103: Payable days | F103: =F94/F30*365 | G103: =G94/G30*365
A105: Non current assets
B106: Net PP&E | F106: 2407 | G106: 2454
B107: Net PPE % sales | F107: =F106/F27 | G107: =G106/G27
B108: Capital expenditure | F108: 341 | G108: 338
B109: Capex / depreciation | F109: =F108/F49 | G109: =G108/G49
A111: Debt and equity
B112: Short-term borrowings | F112: 1219 | G112: 1037
B113: Long-term debt | F113: 2314 | G113: 2499
...

Sheet Company0777
A1: ="Comparable companies analysis - "&D26
A2: Input sheet (figures in millions, except per-share data)
A4: Summary Data
B5: Value numbers
C6: =F26 | D6: =I26
C7: =C40 | D7: =D40
C8: =C49 | D8: =D49
E9: Calendarized
B10: Value driver numbers | D10: LTM | E10: =DATE(YEAR(D35)+1,MONTH(D35),DAY(D35)) | F10: =DATE(YEAR(E10)+1,MONTH(E10),DAY(E10))
C11: Sales | D11: =F62 | E11: =L62 | F11: =M62
C12: EBITDA | D12: =F63 | E12: =L63 | F12: =M63
C13: EBIT | D13: =F64 | E13: =L64 | F13: =M64
C14: =C65 | E14: =L65 | F14: =M65
E16: Calendarized
B17: Valuation multiples | D17: =D10 | E17: =E10 | F17: =F10
C18: EV / Sales | D18: =EnterpriseValue/D11 | E18: =EnterpriseValue/E11 | F18: =EnterpriseValue/F11
C19: EV / EBIT | D19: =EnterpriseValue/D13 | E19: =EnterpriseValue/E13 | F19: =EnterpriseValue/F13
C20: EV / EBITDA | D20: =EnterpriseValue/D12 | E20: =EnterpriseValue/E12 | F20: =EnterpriseValue/F12
C21: P/E | E21: =SharePrice/E14 | F21: =SharePrice/F14
C22: PEG | E22: =PE1F/$I$29/100 | F22: =PE1F/$I$29/100
A24: Inputs
B25: Key company data | F25: Share data
C26: Company name | D26: Company0777 | F26: Share price | I26: 64.84
C27: Ticker symbol | D27: Ticker0003 | F27: 52 week high | I27: 72.13
C28: Date of analysis | D28: 43202 | F28: 52 week low | I28: 61.87
C29: Currency | D29: EUR | F29: EPS 5yr growth rate | I29: =17.48/2.11/100
C30: FX rate to standard currency | D30: 1.233 | F30: Dividend yield | I30: 0.0293
C31: Historical year end | D31: 43100 | F31: Credit rating | I31: BBB+
C32: Latest filing | D32: 43100 | F32: Shares outstanding basic | I32: 632.4034
C33: Type of filing | D33: Annual | F33: Net new shares from stock compensation | I33: =K44
C34: What quarter? | F34: Fully diluted shares outstanding | I34: =I32+I33
C35: Calendarize to: | D35: 43100
C36: Research used | D36: Consensus
C37: Research date | D37: 43202
B39: Enterprise value calculation | F39: Stock compensation | I39: =YEAR($D$31) | J39: =YEAR($D$31)
C40: Fully diluted equity value | D40: =I34*I26 | I40: Number | J40: Strike price | K40: Net shares
C41: =F52 | D41: =19279+150+607 | F41: Performance shares outstanding | I41: 2.31499 | J41: 0 | K41: =MAX(($I$26-J41)/$I$26*I41,0)
C42: Cash and equivalents | D42: =SUM(D52:D53) | F42: Item 2 | I42: 0 | J42: 0 | K42: =MAX(($I$26-J42)/$I$26*I42,0)
C43: Net debt | D43: =D41-D42 | F43: Item 3 | I43: 0 | J43: 0 | K43: =MAX(($I$26-J43)/$I$26*I43,0)
C44: =F53 | D44: =I53 | F44: Net new shares from stock compensation | K44: =SUM(K41:K43)
C45: =F56 | D45: =I56
C46: =F57 | D46: =I57
C47: =C54 | D47: =0.099*9742+0.25*759+0.213*11077+(D54-786-324-824)
C48: =C55 | D48: =D55
C49: Enterprise value | D49: =D40+SUM(D43:D46)-SUM(D47:D48)
B51: Balance sheet data | D51: =YEAR($D$32)&" "&+D33 | I51: =D51
C52: Cash and cash equivalents | D52: 638 | F52: Total debt | I52: =SUM(Company0777_data!G115:G116)
C53: Highly liquid investments | D53: 3462 | F53: Debt equivalents | I53: 0
C54: Equity affiliates/associates and JVs | D54: 2678 | F54: Operating liabilities | I54: =44268-SUM(I52:I53,I55:I57)
C55: Non-core assets | D55: =14+260-SUM(Company0777_data!G117:G118) | F55: Shareholder equity | I55: 14501
C56: Operating assets | D56: =44268-SUM(D52:D55) | F56: Preferred stock | I56: 0 | K56: Calendarization
F57: Noncontrolling interest | I57: 73 | K57: Days: | L57: =D35-D31
C58: Total assets | D58: =SUM(D52:D56) | F58: Total liabilities and equity | I58: =SUM(I52:I57) | K58: % prior yr. | L58: % curr yr. | M58: % next yr.
C59: BS check | D59: =IF(D58=I58,"OK",D58-I58) | K59: =MAX(-L57/365,0) | L59: =1-K59-M59 | M59: =MAX(L57/365,0)
B61: Income statement data | D61: =YEAR($D$31)-1 | E61: =YEAR($D$31) | F61: LTM | G61: =YEAR($D$31)+1 & "E" | H61: =YEAR($D$31)+2 & "E" | I61: =YEAR($D$31)+3 & "E" | K61: =D35 | L61: =DATE(YEAR(K61)+1,MONTH(K61),DAY(K61)) | M61: =DATE(YEAR(L61)+1,MONTH(L61),DAY(L61))
C62: Sales | D62: =VLOOKUP($C62,Company0777_data!Data,5,0) | E62: =VLOOKUP($C62,Company0777_data!Data,6,0) | F62: =VLOOKUP($C62,Company0777_data!Data,7,0) | G62: =VLOOKUP($C62,Company0777_data!Data,10,0) | H62: =VLOOKUP($C62,Company0777_data!Data,11,0) | I62: =VLOOKUP($C62,Company0777_data!Data,12,0) | K62: =D62*$K$59+E62*$L$59+G62*$M$59 | L62: =E62*$K$59+G62*$L$59+H62*$M$59 | M62: =G62*$K$59+H62*$L$59+I62*$M$59
C63: EBITDA | D63: =VLOOKUP($C63,Company0777_data!Data,5,0) | E63: =VLOOKUP($C63,Company0777_data!Data,6,0) | F63: =VLOOKUP($C63,Company0777_data!Data,7,0) | G63: =VLOOKUP($C63,Company0777_data!Data,10,0) | H63: =VLOOKUP($C63,Company0777_data!Data,11,0) | I63: =VLOOKUP($C63,Company0777_data!Data,12,0) | K63: =D63*$K$59+E63*$L$59+G63*$M$59 | L63: =E63*$K$59+G63*$L$59+H63*$M$59 | M63: =G63*$K$59+H63*$L$59+I63*$M$59
C64: EBIT | D64: =VLOOKUP($C64,Company0777_data!Data,5,0) | E64: =VLOOKUP($C64,Company0777_data!Data,6,0) | F64: =VLOOKUP($C64,Company0777_data!Data,7,0) | G64: =VLOOKUP($C64,Company0777_data!Data,10,0) | H64: =VLOOKUP($C64,Company0777_data!Data,11,0) | I64: =VLOOKUP($C64,Company0777_data!Data,12,0) | K64: =D64*$K$59+E64*$L$59+G64*$M$59 | L64: =E64*$K$59+G64*$L$59+H64*$M$59 | M64: =G64*$K$59+H64*$L$59+I64*$M$59
C65: Recurring diluted EPS | D65: =VLOOKUP($C65,Company0777_data!Data,5,0) | E65: =VLOOKUP($C65,Company0777_data!Data,6,0) | G65: =VLOOKUP($C65,Company0777_data!Data,10,0) | H65: =VLOOKUP($C65,Company0777_data!Data,11,0) | I65: =VLOOKUP($C65,Company0777_data!Data,12,0) | K65: =D65*$K$59+E65*$L$59+G65*$M$59 | L65: =E65*$K$59+G65*$L$59+H65*$M$59 | M65: =G65*$K$59+H65*$L$59+I65*$M$59

Sheet Company0777_data
A1: Financial statement analysis - Company0777
C2: History | D2: History | E2: History | F2: History | G2: History | I2: Interim | J2: Interim | K2: Forecast | L2: Forecast | M2: Forecast
A3: Figures in millions, except per-share data | C3: =EDATE(D3,-12) | D3: =EDATE(E3,-12) | E3: =EDATE(F3,-12) | F3: =EDATE(G3,-12) | G3: =Company0777!D31 | H3: LTM | I3: Old | J3: New | K3: =EDATE(G3,12) | L3: =EDATE(K3,12) | M3: =EDATE(L3,12)
A5: Key income statement data
B6: Sales | C6: =C27 | D6: =D27 | E6: =E27 | F6: =F27 | G6: =G27 | H6: =G6-I6+J6 | I6: =I27 | J6: =J27 | K6: 24943 | L6: 25987 | M6: 27084
B7: EBITDA | F7: =F52 | G7: =G52 | H7: =G7-I7+J7 | I7: =I52 | J7: =J52 | K7: 4698 | L7: 5023.5 | M7: 5393.5
B8: EBIT | F8: =F46 | G8: =G46 | H8: =G8-I8+J8 | I8: =I46 | J8: =J46 | K8: 3759.66 | L8: 4046 | M8: 4378
B9: Recurring diluted EPS | F9: =F85 | G9: =G85 | K9: 3.69 | L9: 4.05 | M9: 4.418
N10: CAGR | O10: CAGR
A11: Key ratios | N11: =TEXT(YEAR(E3),"0000")&" - "&TEXT(YEAR(G3),"0000") | O11: =TEXT(YEAR(G3),"0000")&" - "&TEXT(YEAR(M3),"0000")
B12: Sales growth | D12: =D28 | E12: =E28 | F12: =F28 | G12: =G28 | K12: =K6/G6-1 | L12: =L6/K6-1 | M12: =M6/L6-1 | N12: =(G6/E6)^(1/2)-1 | O12: =(M6/G6)^(1/3)-1
B13: =B32 | F13: =F32 | G13: =G32
B14: EBITDA margin | F14: =F7/F6 | G14: =G7/G6 | H14: =H7/H6 | I14: =I7/I6 | J14: =J7/J6 | K14: =K7/K6 | L14: =L7/L6 | M14: =M7/M6
B15: EBIT margin | F15: =F8/F6 | G15: =G8/G6 | H15: =H8/H6 | I15: =I8/I6 | J15: =J8/J6 | K15: =K8/K6 | L15: =L8/L6 | M15: =M8/M6
B16: OWC / sales | F16: =F103 | G16: =G103
B17: Net PP&E / sales | F17: =F110 | G17: =G110
B18: CAPEX / depreciation | F18: =F112 | G18: =G112
B19: Total debt / EBITDA | F19: =F123 | G19: =G123
B20: Total net debt / EBITDA | F20: =F124 | G20: =G124
B21: EBITDA / interest expense | F21: =F127 | G21: =G127
B22: =B129 | F22: =F129 | G22: =G129
B23: ROIC | F23: =F138 | G23: =G138
B24: ROE | F24: =F132 | G24: =G132
A26: Income statement
B27: Sales | C27: 21298 | D27: 21144 | E27: 22412 | F27: 21944 | G27: 24677 | I27: 0 | J27: 0
B28: Sales growth | D28: =D27/C27-1 | E28: =E27/D27-1 | F28: =F27/E27-1 | G28: =G27/F27-1
B30: COGS | F30: 10744 | G30: 12459 | I30: 0 | J30: 0
B31: Gross profit | F31: =F27-F30 | G31: =G27-G30 | I31: =I27-I30 | J31: =J27-J30
B32: Gross margin | F32: =F31/F27 | G32: =G31/G27 | I32: =I31/I27 | J32: =J31/J27
B34: Reported operating profit | F34: 2923 | G34: 3734 | I34: 0 | J34: 0
B35: Operating profit margin | F35: =F34/F27 | G35: =G34/G27 | I35: =I34/I27 | J35: =J34/J27
B36: Restructuring costs | F36: 42 | G36: 60 | I36: 0 | J36: 0
B37: Other operating (income) / expense | F37: 99 | G37: -192 | I37: 0 | J37: 0
B38: Non-recurring item 3 | F38: 0 | G38: 0 | I38: 0 | J38: 0
B39: Non-recurring item 4 | F39: 0 | G39: 0 | I39: 0 | J39: 0
B40: Non-recurring item 5 | F40: 0 | G40: 0 | I40: 0 | J40: 0
B41: Non-recurring item 6 | F41: 0 | G41: 0 | I41: 0 | J41: 0
B42: Non-recurring item 7 | F42: 0 | G42: 0 | I42: 0 | J42: 0
B43: Non-recurring item 8 | F43: 0 | G43: 0 | I43: 0 | J43: 0
B44: Non-recurring item 9 | F44: 0 | G44: 0 | I44: 0 | J44: 0
B45: Non-recurring item 10 | F45: 0 | G45: 0 | I45: 0 | J45: 0
B46: EBIT | F46: =F34+SUM(F36:F45) | G46: =G34+SUM(G36:G45) | I46: =I34+SUM(I36:I45) | J46: =J34+SUM(J36:J45)
B47: EBIT margin | F47: =F46/F27 | G47: =G46/G27 | I47: =I46/I27 | J47: =J46/J27
B49: Depreciation | F49: =684 | G49: 737 | I49: 0 | J49: 0
B50: Amortization | F50: 70 | G50: 93 | I50: 0 | J50: 0
B51: Depreciation and amortization | F51: =SUM(F49:F50) | G51: =SUM(G49:G50) | I51: =SUM(I49:I50) | J51: =SUM(J49:J50)
B52: EBITDA | F52: =F46+F51 | G52: =G46+G51 | I52: =I46+I51 | J52: =J46+J51
B53: EBITDA margin | F53: =F52/F27 | G53: =G52/G27 | I53: =I52/I27 | J53: =J52/J27
B55: Earnings before taxes | F55: 2630 | G55: 3296
B56: Taxes | F56: 804 | G56: 842
B57: Reported ETR | F57: =F56/F55 | G57: =G56/G55
B58: Statutory tax rate | F58: 0.3443 | G58: 0.3443
B59: Other taxes affecting marginal tax rate | F59: 0 | G59: 0
B60: MTR | F60: =SUM(F58:F59) | G60: =SUM(G58:G59)
B62: NOPAT | F62: =F46*(1-F57) | G62: =G46*(1-G57)
B64: Reported net income (total) | F64: 1827 | G64: 2563
B65: Net income margin | F65: =F64/F27 | G65: =G64/G27
B66: =B36 | F66: =F36*(1-F$60) | G66: =G36*(1-G$60)
B67: =B37 | F67: =F37*(1-F$60) | G67: =G37*(1-G$60)
B68: Impairment charge in associate income | F68: 98 | G68: 0
B69: Losses on disposals of associates | F69: 5 | G69: 5
B70: Non-recurring item 5 | F70: 0 | G70: 0
B71: Non-recurring item 6 | F71: 0 | G71: 0
B72: Non-recurring item 7 | F72: 0 | G72: 0
B73: Non-recurring item 8 | F73: 0 | G73: 0
B74: Non-recurring item 9 | F74: 0 | G74: 0
B75: Non-recurring item 10 | F75: 0 | G75: 0
B76: Normalized net income | F76: =F64+SUM(F66:F75) | G76: =G64+SUM(G66:G75)
B77: Normalized net income margin | F77: =F76/F27 | G77: =G76/G27
B79: Noncontrolling interest income | F79: 107 | G79: 110
B80: Normalized net income attributable to parent | F80: =F76-F79 | G80: =G76-G79
B82: WASO - basic | F82: 616.44204 | G82: 625.98664
B83: Recurring basic EPS | F83: =F$80/F82 | G83: =G$80/G82
B84: WASO - diluted | F84: 616.70062 | G84: 627.12127
B85: Recurring diluted EPS | F85: =F$80/F84 | G85: =G$80/G84
A87: Current assets and liabilities
B88: Total current assets | F88: 19113 | G88: 9641
B89: Total current liabilities | F89: 9050 | G89: 10411
B90: Working Capital | F90: =F88-F89 | G90: =G88-G89
B92: Inventories | F92: 1380 | G92: 1668
B93: Trade receivables | F93: 2524 | G93: 2794
B94: Other current assets | F94: 1061 | G94: 1046
B95: Current operating asset 4 | F95: 0 | G95: 0
B96: Current operating asset 5 | F96: 0 | G96: 0
B97: Trade payables | F97: 3772 | G97: 3904
B98: Other current liabilities | F98: 2741 | G98: 2716
B99: Current operating liability 3 | F99: 0 | G99: 0
B100: Current operating liability 4 | F100: 0 | G100: 0
B101: Current operating liability 5 | F101: 0 | G101: 0
B102: OWC | F102: =SUM(F92:F96)-SUM(F97:F101) | G102: =SUM(G92:G96)-SUM(G97:G101)
B103: OWC % sales | F103: =F102/F27 | G103: =G102/G27
B104: Receivable days | F104: =F93/F27*365 | G104: =G93/G27*365
B105: Inventory days | F105: =F92/F30*365 | G105: =G92/G30*365
B106: Payable days | F106: =F97/F30*365 | G106: =G97/G30*365
A108: Non current assets
B109: Net PP&E | F109: 5036 | G109: 6005
B110: Net PPE % sales | F110: =F109/F27 | G110: =G109/G27
B111: Capital expenditure | F111: =974 | G111: 1018
B112: Capex / depreciation | F112: =F111/F49 | G112: =G111/G49
A114: Debt and equity
...

Sheet Company1507
A1: ="Comparable companies analysis - "&D26
A2: Input sheet (figures in millions, except per-share data)
A4: Summary Data
B5: Value numbers
C6: =F26 | D6: =I26
C7: =C40 | D7: =D40
C8: =C49 | D8: =D49
E9: Calendarized
B10: Value driver numbers | D10: LTM | E10: =DATE(YEAR(D35)+1,MONTH(D35),DAY(D35)) | F10: =DATE(YEAR(E10)+1,MONTH(E10),DAY(E10))
C11: Sales | D11: =F62 | E11: =L62 | F11: =M62
C12: EBITDA | D12: =F63 | E12: =L63 | F12: =M63
C13: EBIT | D13: =F64 | E13: =L64 | F13: =M64
C14: =C65 | E14: =L65 | F14: =M65
E16: Calendarized
B17: Valuation multiples | D17: =D10 | E17: =E10 | F17: =F10
C18: EV / Sales | D18: =EnterpriseValue/D11 | E18: =EnterpriseValue/E11 | F18: =EnterpriseValue/F11
C19: EV / EBIT | D19: =EnterpriseValue/D13 | E19: =EnterpriseValue/E13 | F19: =EnterpriseValue/F13
C20: EV / EBITDA | D20: =EnterpriseValue/D12 | E20: =EnterpriseValue/E12 | F20: =EnterpriseValue/F12
C21: P/E | E21: =SharePrice/E14 | F21: =SharePrice/F14
C22: PEG | E22: =PE1F/$I$29/100 | F22: =PE1F/$I$29/100
A24: Inputs
B25: Key company data | F25: Share data
C26: Company name | D26: Company1507 | F26: Share price | I26: 63.35
C27: Ticker symbol | D27: Ticker0019 | F27: 52 week high | I27: 74.28
C28: Date of analysis | D28: 43202 | F28: 52 week low | I28: 58.76
C29: Currency | D29: USD | F29: EPS 5yr growth rate | I29: =14.26/1.87/100
C30: FX rate to standard currency | D30: 1 | F30: Dividend yield | I30: 0.0341
C31: Historical year end | D31: 43100 | F31: Credit rating | I31: BBB
C32: Latest filing | D32: 43100 | F32: Shares outstanding basic | I32: 345.74875
C33: Type of filing | D33: Ticker0019 | F33: Net new shares from stock compensation | I33: =K46
C34: What quarter? | F34: Fully diluted shares outstanding | I34: =I32+I33
C35: Calendarize to: | D35: 43100
C36: Research used | D36: Consensus
C37: Research date | D37: 43202
B39: Enterprise value calculation | F39: Stock compensation | I39: =YEAR($D$31) | J39: =YEAR($D$31)
C40: Fully diluted equity value | D40: =I34*I26 | I40: Number | J40: Strike price | K40: Net shares
C41: =F52 | D41: =I52+(8300-7800) | F41: Stock options outstanding | I41: 14 | J41: 64 | K41: =MAX(($I$26-J41)/$I$26*I41,0)
C42: Cash and equivalents | D42: =SUM(D52:D53) | F42: Performance shares | I42: =0.126+0.133+0.145 | J42: 0 | K42: =MAX(($I$26-J42)/$I$26*I42,0)
C43: Net debt | D43: =D41-D42 | F43: Restricted stock units | I43: 1.673 | J43: 0 | K43: =MAX(($I$26-J43)/$I$26*I43,0)
C44: =F53 | D44: =I53 | F44: Item 4 | I44: 0 | J44: 0 | K44: =MAX(($I$26-J44)/$I$26*I44,0)
C45: =F56 | D45: =I56 | F45: Item 5 | I45: 0 | J45: 0 | K45: =MAX(($I$26-J45)/$I$26*I45,0)
C46: =F57 | D46: =I57 | F46: Net new shares from stock compensation | K46: =SUM(K41:K45)
C47: =C54 | D47: =D54
C48: =C55 | D48: =D55
C49: Enterprise value | D49: =D40+SUM(D43:D46)-SUM(D47:D48)
B51: Balance sheet data | D51: =YEAR($D$32)&" "&+D33 | I51: =D51
C52: Cash and cash equivalents | D52: =Company1507_data!G121 | F52: Total debt | I52: =Company1507_data!G120
C53: Highly liquid investments | D53: 0 | F53: Debt equivalents | I53: 0
C54: Equity affiliates/associates and JVs | D54: 429 | F54: Operating liabilities | I54: =16350-SUM(I52:I53,I55:I57)
C55: Non-core assets | D55: 0 | F55: Shareholder equity | I55: 2212
C56: Operating assets | D56: =16350-SUM(D52:D55) | F56: Preferred stock | I56: 0 | K56: Calendarization
F57: Noncontrolling interest | I57: 16 | K57: Days: | L57: =D35-D31
C58: Total assets | D58: =SUM(D52:D56) | F58: Total liabilities and equity | I58: =SUM(I52:I57) | K58: % prior yr. | L58: % curr yr. | M58: % next yr.
C59: BS check | D59: =IF(D58=I58,"OK",D58-I58) | K59: =MAX(-L57/365,0) | L59: =1-K59-M59 | M59: =MAX(L57/365,0)
B61: Income statement data | D61: =YEAR($D$31)-1 | E61: =YEAR($D$31) | F61: LTM | G61: =YEAR($D$31)+1 & "E" | H61: =YEAR($D$31)+2 & "E" | I61: =YEAR($D$31)+3 & "E" | K61: =D35 | L61: =DATE(YEAR(K61)+1,MONTH(K61),DAY(K61)) | M61: =DATE(YEAR(L61)+1,MONTH(L61),DAY(L61))
C62: Sales | D62: =VLOOKUP($C62,Company1507_data!Data,5,0) | E62: =VLOOKUP($C62,Company1507_data!Data,6,0) | F62: =VLOOKUP($C62,Company1507_data!Data,7,0) | G62: =VLOOKUP($C62,Company1507_data!Data,10,0) | H62: =VLOOKUP($C62,Company1507_data!Data,11,0) | I62: =VLOOKUP($C62,Company1507_data!Data,12,0) | K62: =D62*$K$59+E62*$L$59+G62*$M$59 | L62: =E62*$K$59+G62*$L$59+H62*$M$59 | M62: =G62*$K$59+H62*$L$59+I62*$M$59
C63: EBITDA | D63: =VLOOKUP($C63,Company1507_data!Data,5,0) | E63: =VLOOKUP($C63,Company1507_data!Data,6,0) | F63: =VLOOKUP($C63,Company1507_data!Data,7,0) | G63: =VLOOKUP($C63,Company1507_data!Data,10,0) | H63: =VLOOKUP($C63,Company1507_data!Data,11,0) | I63: =VLOOKUP($C63,Company1507_data!Data,12,0) | K63: =D63*$K$59+E63*$L$59+G63*$M$59 | L63: =E63*$K$59+G63*$L$59+H63*$M$59 | M63: =G63*$K$59+H63*$L$59+I63*$M$59
C64: EBIT | D64: =VLOOKUP($C64,Company1507_data!Data,5,0) | E64: =VLOOKUP($C64,Company1507_data!Data,6,0) | F64: =VLOOKUP($C64,Company1507_data!Data,7,0) | G64: =VLOOKUP($C64,Company1507_data!Data,10,0) | H64: =VLOOKUP($C64,Company1507_data!Data,11,0) | I64: =VLOOKUP($C64,Company1507_data!Data,12,0) | K64: =D64*$K$59+E64*$L$59+G64*$M$59 | L64: =E64*$K$59+G64*$L$59+H64*$M$59 | M64: =G64*$K$59+H64*$L$59+I64*$M$59
C65: Recurring diluted EPS | D65: =VLOOKUP($C65,Company1507_data!Data,5,0) | E65: =VLOOKUP($C65,Company1507_data!Data,6,0) | G65: =VLOOKUP($C65,Company1507_data!Data,10,0) | H65: =VLOOKUP($C65,Company1507_data!Data,11,0) | I65: =VLOOKUP($C65,Company1507_data!Data,12,0) | K65: =D65*$K$59+E65*$L$59+G65*$M$59 | L65: =E65*$K$59+G65*$L$59+H65*$M$59 | M65: =G65*$K$59+H65*$L$59+I65*$M$59

Sheet Company1507_data
A1: Financial statement analysis - Company1507
C2: History | D2: History | E2: History | F2: History | G2: History | I2: Interim | J2: Interim | K2: Forecast | L2: Forecast | M2: Forecast
A3: Figures in millions, except per-share data | C3: =EDATE(D3,-12) | D3: =EDATE(E3,-12) | E3: =EDATE(F3,-12) | F3: =EDATE(G3,-12) | G3: =Company1507!D31 | H3: LTM | I3: Old | J3: New | K3: =EDATE(G3,12) | L3: =EDATE(K3,12) | M3: =EDATE(L3,12)
A5: Key income statement data
B6: Sales | C6: =C27 | D6: =D27 | E6: =E27 | F6: =F27 | G6: =G27 | H6: =G6-I6+J6 | I6: =I27 | J6: =J27 | K6: 13025.5 | L6: 13131 | M6: 13441
B7: EBITDA | F7: =F52 | G7: =G52 | H7: =G7-I7+J7 | I7: =I52 | J7: =J52 | K7: 2699.7 | L7: 2769.8 | M7: 2842.81
B8: EBIT | F8: =F46 | G8: =G46 | H8: =G8-I8+J8 | I8: =I46 | J8: =J46 | K8: 2020.4 | L8: 2108.05 | M8: 2182.18
B9: Recurring diluted EPS | F9: =F85 | G9: =G85 | K9: 4.45 | L9: 4.73 | M9: 4.91
N10: CAGR | O10: CAGR
A11: Key ratios | N11: =TEXT(YEAR(C3),"0000")&" - "&TEXT(YEAR(G3),"0000") | O11: =TEXT(YEAR(G3),"0000")&" - "&TEXT(YEAR(M3),"0000")
B12: Sales growth | D12: =D28 | E12: =E28 | F12: =F28 | G12: =G28 | K12: =K6/G6-1 | L12: =L6/K6-1 | M12: =M6/L6-1 | N12: =(G6/C6)^(1/4)-1 | O12: =(M6/G6)^(1/3)-1
B13: =B32 | F13: =F32 | G13: =G32
B14: EBITDA margin | F14: =F7/F6 | G14: =G7/G6 | H14: =H7/H6 | I14: =I7/I6 | J14: =J7/J6 | K14: =K7/K6 | L14: =L7/L6 | M14: =M7/M6
B15: EBIT margin | F15: =F8/F6 | G15: =G8/G6 | H15: =H8/H6 | I15: =I8/I6 | J15: =J8/J6 | K15: =K8/K6 | L15: =L8/L6 | M15: =M8/M6
B16: OWC / sales | F16: =F103 | G16: =G103
B17: Net PP&E / sales | F17: =F110 | G17: =G110
B18: CAPEX / depreciation | F18: =F112 | G18: =G112
B19: Total debt / EBITDA | F19: =F123 | G19: =G123
B20: Total net debt / EBITDA | F20: =F124 | G20: =G124
B21: EBITDA / interest expense | F21: =F127 | G21: =G127
B22: =B129 | F22: =F129 | G22: =G129
B23: ROIC | F23: =F138 | G23: =G138
B24: ROE | F24: =F132 | G24: =G132
A26: Income statement
B27: Sales | C27: 14792 | D27: 14580 | E27: 13525 | F27: =13014-31 | G27: =12923-14 | I27: 0 | J27: 0
B28: Sales growth | D28: =D27/C27-1 | E28: =E27/D27-1 | F28: =F27/E27-1 | G28: =G27/F27-1 | I28: =I27/H27-1 | J28: =J27/I27-1
B30: COGS | F30: =8259-159-173-2+11-12 | G30: =7901+8-46-1-(14-6) | I30: 0 | J30: 0
B31: Gross profit | F31: =F27-F30 | G31: =G27-G30 | I31: =I27-I30 | J31: =J27-J30
B32: Gross margin | F32: =F31/F27 | G32: =G31/G27 | I32: =I31/I27 | J32: =J31/J27
B34: Reported operating profit | F34: 1395 | G34: 1946 | I34: 0 | J34: 0
B35: Operating profit margin | F35: =F34/F27 | G35: =G34/G27 | I35: =I34/I27 | J35: =J34/J27
B36: Mark-to-market | F36: 261 | G36: -45 | I36: 0 | J36: 0
B37: Project Ticker0019 and cost reduction activities | F37: 325 | G37: 263 | I37: 0 | J37: 0
B38: Integration and transaction costs | F38: 10 | G38: 5 | I38: 0 | J38: 0
B39: Venezuela adjustments | F39: =13-9 | G39: 0 | I39: 0 | J39: 0
B40: Non-recurring item 5 | F40: 0 | G40: 0 | I40: 0 | J40: 0
B41: Non-recurring item 6 | F41: 0 | G41: 0 | I41: 0 | J41: 0
B42: Non-recurring item 7 | F42: 0 | G42: 0 | I42: 0 | J42: 0
B43: Non-recurring item 8 | F43: 0 | G43: 0 | I43: 0 | J43: 0
B44: Non-recurring item 9 | F44: 0 | G44: 0 | I44: 0 | J44: 0
B45: Non-recurring item 10 | F45: 0 | G45: 0 | I45: 0 | J45: 0
B46: EBIT | F46: =F34+SUM(F36:F45) | G46: =G34+SUM(G36:G45) | I46: =I34+SUM(I36:I45) | J46: =J34+SUM(J36:J45)
B47: EBIT margin | F47: =F46/F27 | G47: =G46/G27 | I47: =I46/I27 | J47: =J46/J27
B49: Depreciation | F49: =510-46-50 | G49: =469-77 | I49: 0 | J49: 0
B50: Amortization | F50: 7 | G50: 12 | I50: 0 | J50: 0
B51: Depreciation and amortization | F51: =SUM(F49:F50) | G51: =SUM(G49:G50) | I51: =SUM(I49:I50) | J51: =SUM(J49:J50)
B52: EBITDA | F52: =F46+F51 | G52: =G46+G51 | I52: =I46+I51 | J52: =J46+J51
B53: EBITDA margin | F53: =F52/F27 | G53: =G52/G27 | I53: =I52/I27 | J53: =J52/J27
B55: Earnings before taxes | F55: 927 | G55: 1674
B56: Taxes | F56: 233 | G56: 412
B57: Reported ETR | F57: =F56/F55 | G57: =G56/G55
B58: Statutory tax rate | F58: 0.35 | G58: 0.35
B59: Other taxes affecting marginal tax rate | F59: 0.024 | G59: 0.014
B60: MTR | F60: =SUM(F58:F59) | G60: =SUM(G58:G59)
B62: NOPAT | F62: =F46*(1-F57) | G62: =G46*(1-G57)
B64: Reported net income (total) | F64: 695 | G64: 1269
B65: Net income margin | F65: =F64/F27 | G65: =G64/G27
B66: =B36 | F66: =F36-59 | G66: =G36+6
B67: =B37 | F67: =F37-85 | G67: =G37-86
B68: Debt redemption | F68: =153-54 | G68: 0
B69: =B38 | F69: =12-3 | G69: =G38-2
B70: Shipping day differences | F70: 0 | G70: 1
B71: =B39 | F71: =-9+72+11+1 | G71: 0
B72: US tax reform | F72: 0 | G72: 4
B73: =B43 | F73: 0 | G73: 0
B74: =B44 | F74: 0 | G74: 0
B75: =B45 | F75: 0 | G75: 0
B76: Normalized net income | F76: =F64+SUM(F66:F75) | G76: =G64+SUM(G66:G75)
B77: Normalized net income margin | F77: =F76/F27 | G77: =G76/G27
B79: Noncontrolling interest income | F79: 1 | G79: 0
B80: Normalized net income attributable to parent | F80: =F76-F79 | G80: =G76-G79
B82: WASO - basic | F82: 350 | G82: 348
B83: Recurring basic EPS | F83: =F$80/F82 | G83: =G$80/G82
B84: WASO - diluted | F84: 354 | G84: 350
B85: Recurring diluted EPS | F85: =F$80/F84 | G85: =G$80/G84
A87: Current assets and liabilities
B88: Total current assets | F88: 2940 | G88: 3036
B89: Total current liabilities | F89: 4474 | G89: 4479
B90: Working Capital | F90: =F88-F89 | G90: =G88-G89
B92: Accounts receivable, net | F92: 1231 | G92: 1389
B93: Inventories | F93: 1238 | G93: 1217
B94: Other current assets | F94: 191 | G94: 149
B95: Current operating asset 4 | F95: 0 | G95: 0
B96: Current operating asset 5 | F96: 0 | G96: 0
B97: Accounts payable | F97: 2014 | G97: 2269
B98: Other current liabilities | F98: 1391 | G98: 1431
B99: Current operating liability 3 | F99: 0 | G99: 0
B100: Current operating liability 4 | F100: 0 | G100: 0
B101: Current operating liability 5 | F101: 0 | G101: 0
B102: OWC | F102: =SUM(F92:F96)-SUM(F97:F101) | G102: =SUM(G92:G96)-SUM(G97:G101)
B103: OWC % sales | F103: =F102/F27 | G103: =G102/G27
B104: Receivable days | F104: =F92/F27*365 | G104: =G92/G27*365
B105: Inventory days | F105: =F93/F30*365 | G105: =G93/G30*365
B106: Payable days | F106: =F97/F30*365 | G106: =G97/G30*365
A108: Non current assets
B109: Net PP&E | F109: 3569 | G109: 3716
B110: Net PPE % sales | F110: =F109/F27 | G110: =G109/G27
B111: Capital expenditure | F111: 507 | G111: 501
B112: Capex / depreciation | F112: =F111/F49 | G112: =G111/G49
A114: Debt and equity
...

Sheet Company1930
A1: ="Comparable companies analysis - "&D26
A2: Input sheet (figures in millions, except per-share data)
A4: Summary Data
B5: Value numbers
C6: =F26 | D6: =I26
C7: =C40 | D7: =D40
C8: =C49 | D8: =D49
E9: Calendarized
B10: Value driver numbers | D10: LTM | E10: =DATE(YEAR(D35)+1,MONTH(D35),DAY(D35)) | F10: =DATE(YEAR(E10)+1,MONTH(E10),DAY(E10))
C11: Sales | D11: =F62 | E11: =L62 | F11: =M62
C12: EBITDA | D12: =F63 | E12: =L63 | F12: =M63
C13: EBIT | D13: =F64 | E13: =L64 | F13: =M64
C14: =C65 | E14: =L65 | F14: =M65
E16: Calendarized
B17: Valuation multiples | D17: =D10 | E17: =E10 | F17: =F10
C18: EV / Sales | D18: =EnterpriseValue/D11 | E18: =EnterpriseValue/E11 | F18: =EnterpriseValue/F11
C19: EV / EBIT | D19: =EnterpriseValue/D13 | E19: =EnterpriseValue/E13 | F19: =EnterpriseValue/F13
C20: EV / EBITDA | D20: =EnterpriseValue/D12 | E20: =EnterpriseValue/E12 | F20: =EnterpriseValue/F12
C21: P/E | E21: =SharePrice/E14 | F21: =SharePrice/F14
C22: PEG | E22: =PE1F/$I$29/100 | F22: =PE1F/$I$29/100
A24: Inputs
B25: Key company data | F25: Share data
C26: Company name | D26: Company1931 | F26: Share price | I26: 76.18
C27: Ticker symbol | D27: Ticker0025 | F27: 52 week high | I27: 86.4
C28: Date of analysis | D28: 43202 | F28: 52 week low | I28: 73
C29: Currency | D29: CHF | F29: EPS 5yr growth rate | I29: =19.95/1.77/100
C30: FX rate to standard currency | D30: =1/0.9623 | F30: Dividend yield | I30: 0.0308
C31: Historical year end | D31: 43100 | F31: Credit rating | I31: AA-
C32: Latest filing | D32: 43100 | F32: Shares outstanding basic | I32: 3057.6
C33: Type of filing | D33: Annual | F33: Net new shares from stock compensation | I33: =K46
C34: What quarter? | F34: Fully diluted shares outstanding | I34: =I32+I33
C35: Calendarize to: | D35: 43100
C36: Research used | D36: Consensus
C37: Research date | D37: 43202
B39: Enterprise value calculation | F39: Stock compensation | I39: =YEAR($D$31) | J39: =YEAR($D$31)
C40: Fully diluted equity value | D40: =I34*I26 | I40: Number | J40: Strike price | K40: Net shares
C41: =F52 | D41: =I52 | F41: Dilutive instruments | I41: 6 | J41: 0 | K41: =MAX(($I$26-J41)/$I$26*I41,0)
C42: Cash and equivalents | D42: =SUM(D52:D53) | F42: Item 2 | I42: 0 | J42: 0 | K42: =MAX(($I$26-J42)/$I$26*I42,0)
C43: Net debt | D43: =D41-D42 | F43: Item 3 | I43: 0 | J43: 0 | K43: =MAX(($I$26-J43)/$I$26*I43,0)
C44: =F53 | D44: =I53 | F44: Item 4 | I44: 0 | J44: 0 | K44: =MAX(($I$26-J44)/$I$26*I44,0)
C45: =F56 | D45: =I56 | F45: Item 5 | I45: 0 | J45: 0 | K45: =MAX(($I$26-J45)/$I$26*I45,0)
C46: =F57 | D46: =I57 | F46: Net new shares from stock compensation | K46: =SUM(K41:K45)
C47: =C54 | D47: =28000+(D54-8200)
C48: =C55 | D48: =D55
C49: Enterprise value | D49: =D40+SUM(D43:D46)-SUM(D47:D48)
B51: Balance sheet data | D51: =YEAR($D$32)&" "&+D33 | I51: =D51
C52: Cash and cash equivalents | D52: 7938 | F52: Total debt | I52: =Company1930_data!G120
C53: Highly liquid investments | D53: 655 | F53: Debt equivalents | I53: 0
C54: Equity affiliates/associates and JVs | D54: 11628 | F54: Operating liabilities | I54: =130380-SUM(I52:I53,I55:I57)
C55: Non-core assets | D55: =6003+(357-12) | F55: Shareholder equity | I55: 61504
C56: Operating assets | D56: =130380-SUM(D52:D55) | F56: Preferred stock | I56: 0 | K56: Calendarization
F57: Noncontrolling interest | I57: 1273 | K57: Days: | L57: =D35-D31
C58: Total assets | D58: =SUM(D52:D56) | F58: Total liabilities and equity | I58: =SUM(I52:I57) | K58: % prior yr. | L58: % curr yr. | M58: % next yr.
C59: BS check | D59: =IF(D58=I58,"OK",D58-I58) | K59: =MAX(-L57/365,0) | L59: =1-K59-M59 | M59: =MAX(L57/365,0)
B61: Income statement data | D61: =YEAR($D$31)-1 | E61: =YEAR($D$31) | F61: LTM | G61: =YEAR($D$31)+1 & "E" | H61: =YEAR($D$31)+2 & "E" | I61: =YEAR($D$31)+3 & "E" | K61: =D35 | L61: =DATE(YEAR(K61)+1,MONTH(K61),DAY(K61)) | M61: =DATE(YEAR(L61)+1,MONTH(L61),DAY(L61))
C62: Sales | D62: =VLOOKUP($C62,Company1930_data!Data,5,0) | E62: =VLOOKUP($C62,Company1930_data!Data,6,0) | F62: =VLOOKUP($C62,Company1930_data!Data,7,0) | G62: =VLOOKUP($C62,Company1930_data!Data,10,0) | H62: =VLOOKUP($C62,Company1930_data!Data,11,0) | I62: =VLOOKUP($C62,Company1930_data!Data,12,0) | K62: =D62*$K$59+E62*$L$59+G62*$M$59 | L62: =E62*$K$59+G62*$L$59+H62*$M$59 | M62: =G62*$K$59+H62*$L$59+I62*$M$59
C63: EBITDA | D63: =VLOOKUP($C63,Company1930_data!Data,5,0) | E63: =VLOOKUP($C63,Company1930_data!Data,6,0) | F63: =VLOOKUP($C63,Company1930_data!Data,7,0) | G63: =VLOOKUP($C63,Company1930_data!Data,10,0) | H63: =VLOOKUP($C63,Company1930_data!Data,11,0) | I63: =VLOOKUP($C63,Company1930_data!Data,12,0) | K63: =D63*$K$59+E63*$L$59+G63*$M$59 | L63: =E63*$K$59+G63*$L$59+H63*$M$59 | M63: =G63*$K$59+H63*$L$59+I63*$M$59
C64: EBIT | D64: =VLOOKUP($C64,Company1930_data!Data,5,0) | E64: =VLOOKUP($C64,Company1930_data!Data,6,0) | F64: =VLOOKUP($C64,Company1930_data!Data,7,0) | G64: =VLOOKUP($C64,Company1930_data!Data,10,0) | H64: =VLOOKUP($C64,Company1930_data!Data,11,0) | I64: =VLOOKUP($C64,Company1930_data!Data,12,0) | K64: =D64*$K$59+E64*$L$59+G64*$M$59 | L64: =E64*$K$59+G64*$L$59+H64*$M$59 | M64: =G64*$K$59+H64*$L$59+I64*$M$59
C65: Recurring diluted EPS | D65: =VLOOKUP($C65,Company1930_data!Data,5,0) | E65: =VLOOKUP($C65,Company1930_data!Data,6,0) | G65: =VLOOKUP($C65,Company1930_data!Data,10,0) | H65: =VLOOKUP($C65,Company1930_data!Data,11,0) | I65: =VLOOKUP($C65,Company1930_data!Data,12,0) | K65: =D65*$K$59+E65*$L$59+G65*$M$59 | L65: =E65*$K$59+G65*$L$59+H65*$M$59 | M65: =G65*$K$59+H65*$L$59+I65*$M$59

Sheet Company1930_data
A1: Financial statement analysis - Company1930
C2: History | D2: History | E2: History | F2: History | G2: History | I2: Interim | J2: Interim | K2: Forecast | L2: Forecast | M2: Forecast
A3: Figures in millions, except per-share data | C3: =EDATE(D3,-12) | D3: =EDATE(E3,-12) | E3: =EDATE(F3,-12) | F3: =EDATE(G3,-12) | G3: =Company1930!D31 | H3: LTM | I3: Old | J3: New | K3: =EDATE(G3,12) | L3: =EDATE(K3,12) | M3: =EDATE(L3,12)
A5: Key income statement data
B6: Sales | C6: =C27 | D6: =D27 | E6: =E27 | F6: =F27 | G6: =G27 | H6: =G6-I6+J6 | I6: =I27 | J6: =J27 | K6: 91665 | L6: 94959 | M6: 98343.7
B7: EBITDA | F7: =F52 | G7: =G52 | H7: =G7-I7+J7 | I7: =I52 | J7: =J52 | K7: 18712 | L7: 19906.5 | M7: 21248
B8: EBIT | F8: =F46 | G8: =G46 | H8: =G8-I8+J8 | I8: =I46 | J8: =J46 | K8: 15406 | L8: 16416 | M8: 17643
B9: Recurring diluted EPS | F9: =F85 | G9: =G85 | K9: 3.85 | L9: 4.175 | M9: 4.63
N10: CAGR | O10: CAGR
A11: Key ratios | N11: =TEXT(YEAR(C3),"0000")&" - "&TEXT(YEAR(G3),"0000") | O11: =TEXT(YEAR(G3),"0000")&" - "&TEXT(YEAR(M3),"0000")
B12: Sales growth | D12: =D28 | E12: =E28 | F12: =F28 | G12: =G28 | K12: =K6/G6-1 | L12: =L6/K6-1 | M12: =M6/L6-1 | N12: =(G6/C6)^(1/4)-1 | O12: =(M6/G6)^(1/3)-1
B13: =B32 | F13: =F32 | G13: =G32
B14: EBITDA margin | F14: =F7/F6 | G14: =G7/G6 | H14: =H7/H6 | I14: =I7/I6 | J14: =J7/J6 | K14: =K7/K6 | L14: =L7/L6 | M14: =M7/M6
B15: EBIT margin | F15: =F8/F6 | G15: =G8/G6 | H15: =H8/H6 | I15: =I8/I6 | J15: =J8/J6 | K15: =K8/K6 | L15: =L8/L6 | M15: =M8/M6
B16: OWC / sales | F16: =F103 | G16: =G103
B17: Net PP&E / sales | F17: =F110 | G17: =G110
B18: CAPEX / depreciation | F18: =F112 | G18: =G112
B19: Total debt / EBITDA | F19: =F123 | G19: =G123
B20: Total net debt / EBITDA | F20: =F124 | G20: =G124
B21: EBITDA / interest expense | F21: =F127 | G21: =G127
B22: =B129 | F22: =F129 | G22: =G129
B23: ROIC | F23: =F138 | G23: =G138
B24: ROE | F24: =F132 | G24: =G132
A26: Income statement
B27: Sales | C27: =92158 | D27: =91612 | E27: =88785 | F27: =89469 | G27: 89791 | I27: 0 | J27: 0
B28: Sales growth | D28: =D27/C27-1 | E28: =E27/D27-1 | F28: =F27/E27-1 | G28: =G27/F27-1 | I28: =I27/H27-1 | J28: =J27/I27-1
B30: COGS | F30: =44199 | G30: 44923 | I30: 0 | J30: 0
B31: Gross profit | F31: =F27-F30 | G31: =G27-G30 | I31: =I27-I30 | J31: =J27-J30
B32: Gross margin | F32: =F31/F27 | G32: =G31/G27 | I32: =I31/I27 | J32: =J31/J27
B34: Reported operating profit | F34: =13163 | G34: 10112 | I34: 0 | J34: 0
B35: Operating profit margin | F35: =F34/F27 | G35: =G34/G27 | I35: =I34/I27 | J35: =J34/J27
B36: Other trading income | F36: -99 | G36: -111 | I36: 0 | J36: 0
B37: Other trading expenses | F37: =713 | G37: 1607 | I37: 0 | J37: 0
B38: Other operating income | F38: -354 | G38: -379 | I38: 0 | J38: 0
B39: Other operating expenses | F39: 884 | G39: 3500 | I39: 0 | J39: 0
B40: Non-recurring item 5 | F40: 0 | G40: 0 | I40: 0 | J40: 0
B41: Non-recurring item 6 | F41: 0 | G41: 0 | I41: 0 | J41: 0
B42: Non-recurring item 7 | F42: 0 | G42: 0 | I42: 0 | J42: 0
B43: Non-recurring item 8 | F43: 0 | G43: 0 | I43: 0 | J43: 0
B44: Non-recurring item 9 | F44: 0 | G44: 0 | I44: 0 | J44: 0
B45: Non-recurring item 10 | F45: 0 | G45: 0 | I45: 0 | J45: 0
B46: EBIT | F46: =F34+SUM(F36:F45) | G46: =G34+SUM(G36:G45) | I46: =I34+SUM(I36:I45) | J46: =J34+SUM(J36:J45)
B47: EBIT margin | F47: =F46/F27 | G47: =G46/G27 | I47: =I46/I27 | J47: =J46/J27
B49: Depreciation | F49: =2795 | G49: 2853 | I49: 0 | J49: 0
B50: Amortization | F50: 337 | G50: 374 | I50: 0 | J50: 0
B51: Depreciation and amortization | F51: =SUM(F49:F50) | G51: =SUM(G49:G50) | I51: =SUM(I49:I50) | J51: =SUM(J49:J50)
B52: EBITDA | F52: =F46+F51 | G52: =G46+G51 | I52: =I46+I51 | J52: =J46+J51
B53: EBITDA margin | F53: =F52/F27 | G53: =G52/G27 | I53: =I52/I27 | J53: =J52/J27
B55: Earnings before taxes | F55: =12526 | G55: 9493
B56: Taxes | F56: =4413 | G56: 2779
B57: Reported ETR | F57: =F56/F55 | G57: =G56/G55
B58: Statutory tax rate | F58: =3331/F55 | G58: =3163/G55
B59: Other taxes affecting marginal tax rate | F59: 0 | G59: 0
B60: MTR | F60: =SUM(F58:F59) | G60: =SUM(G58:G59)
B62: NOPAT | F62: =F46*(1-F57) | G62: =G46*(1-G57)
B64: Reported net income (total) | F64: =8883 | G64: 7538
B65: Net income margin | F65: =F64/F27 | G65: =G64/G27
B66: Pre-tax non-recurring items (as above) | F66: =SUM(F36:F39) | G66: =SUM(G36:G39)
B67: Tax adjustment, as reported | F67: 610 | G67: -1065
B68: Adjustment for income from associates and JVs, as reported | F68: 241 | G68: 265
B69: Non-recurring item 4 | F69: 0 | G69: 0
B70: Non-recurring item 5 | F70: 0 | G70: 0
B71: Non-recurring item 6 | F71: 0 | G71: 0
B72: Non-recurring item 7 | F72: 0 | G72: 0
B73: Non-recurring item 8 | F73: 0 | G73: 0
B74: Non-recurring item 9 | F74: 0 | G74: 0
B75: Non-recurring item 10 | F75: 0 | G75: 0
B76: Normalized net income | F76: =F64+SUM(F66:F75) | G76: =G64+SUM(G66:G75)
B77: Normalized net income margin | F77: =F76/F27 | G77: =G76/G27
B79: Noncontrolling interest income | F79: 352 | G79: 355
B80: Normalized net income attributable to parent | F80: =F76-F79 | G80: =G76-G79
B82: WASO - basic | F82: =3091 | G82: =3092
B83: Recurring basic EPS | F83: =F$80/F82 | G83: =G$80/G82
B84: WASO - diluted | F84: =3097 | G84: =3098
B85: Recurring diluted EPS | F85: =F$80/F84 | G85: =G$80/G84
A87: Current assets and liabilities
B88: Total current assets | F88: 29434 | G88: =32042
B89: Total current liabilities | F89: 33321 | G89: =37517
B90: Working Capital | F90: =F88-F89 | G90: =G88-G89
B92: Inventories | F92: 8401 | G92: 9061
B93: Trade and other receivables | F93: 12411 | G93: 12422
B94: Prepayments and accrued income | F94: 573 | G94: 607
B95: Derivative assets | F95: 550 | G95: 231
B96: Current income tax assets | F96: 786 | G96: 919
B97: Trade and other payables | F97: 18629 | G97: 18872
B98: Accruals and deferred income | F98: 3855 | G98: 4094
B99: Provisions | F99: 620 | G99: 863
B100: Derivative liabilities | F100: 1068 | G100: 507
B101: Current income tax liabilities | F101: 1221 | G101: 1170
B102: OWC | F102: =SUM(F92:F96)-SUM(F97:F101) | G102: =SUM(G92:G96)-SUM(G97:G101)
B103: OWC % sales | F103: =F102/F27 | G103: =G102/G27
B104: Receivable days | F104: =F93/F27*365 | G104: =G93/G27*365
B105: Inventory days | F105: =F92/F30*365 | G105: =G92/G30*365
B106: Payable days | F106: =F97/F30*365 | G106: =G97/G30*365
A108: Non current assets
B109: Net PP&E | F109: =27554 | G109: 27775
B110: Net PPE % sales | F110: =F109/F27 | G110: =G109/G27
B111: Capital expenditure | F111: =4010 | G111: 3934
B112: Capex / depreciation | F112: =F111/F49 | G112: =G111/G49
A114: Debt and equity
...
