Workbook

Sheet Deal Summary
A1: Property Details | D1: Acquisition Loan Info
A2: Address | B2: N/A | D2: Loan Proceeds | E2: ='Pro Forma Cash Flow Statement'!E21 -> 3562500
A3: City/State/Zip | B3: 10032 | D3: LTV | E3: ='Pro Forma Cash Flow Statement'!B17 -> 0.75
A4: Gross SF | B4: 10247 | D4: Going- In DSCR | E4: {=SUM('Pro Forma Cash Flow Statement'!F9:Q9/ABS(SUM('Pro Forma Cash Flow Statement'!F13:Q14)))} -> 1.1917046
A5: Net RSF | B5: 0 | D5: Going- In Debt Yield | E5: =SUM('Pro Forma Cash Flow Statement'!F9:R9)/'Deal Summary'!E2 -> 0.093674155
A6: Number of Building | B6: 3 | D6: Interests Rate Index | E6: 0.0208 | F6: SOFR
A7: Number of Units | B7: 9 | D7: Interests Rate Spread | E7: 0.0325
A8: Commercial SF | B8: 0 | D8: Interests Rate | E8: =E7+E6 -> 0.0533
A9: Zoning | B9: R7-2 | D9: Interests Only Period | E9: 0
A10: FAR | B10: 3.44 | D10: Term | E10: 60
A11: Air Rights | B11: 11972 | D11: Loan Fee (%) | E11: 0.01
D12: Amortization | E12: ='Pro Forma Cash Flow Statement'!B20 -> 25
A13: Acquisition Info
A14: Purchase Price | B14: ='Pro Forma Cash Flow Statement'!B2 -> 4750000 | D14: Project Level Returns
A15: Going -In NOI | B15: ='Rent Roll'!C17-Expenses!F11 -> 351132.88 | D15: Pro Forma Cap Rate | E15: ='Pro Forma Cash Flow Statement'!B28 -> 0.064778572
A16: Purchase Price/Unit | B16: =B14/B7 -> 527777.78 | D16: Loan Constant | E16: ='Pro Forma Cash Flow Statement'!B29 -> 0.072477213
A17: Price/GSF | B17: =B14/B4 -> 463.55031 | D17: Unlevered IRR | E17: ='Pro Forma Cash Flow Statement'!B30 -> 0.16178309
A18: Price/NRSF | B18: 3 | D18: Levered IRR | E18: ='Pro Forma Cash Flow Statement'!B31 -> 0.3279777
A19: Going-In Cap Rate | B19: =B15/B14 -> 0.073922712 | D19: Unlevered Equity Multiple | E19: ='Pro Forma Cash Flow Statement'!B32 -> 1.1711477
A20: Capital Imrpovements | B20: ='Pro Forma Cash Flow Statement'!B11 -> 50000 | D20: Levered Equity Multiple | E20: ='Pro Forma Cash Flow Statement'!B33 -> 1.3530567
A21: Acquisition Fee | B21: 0.01 | D21: Average Unlevered Cash on Cash | E21: ='Pro Forma Cash Flow Statement'!B34 -> 0.06735949
A22: Closing Cost | B22: ='Pro Forma Cash Flow Statement'!C4 -> 0.02 | D22: Average Levered Cash on Cash | E22: ='Pro Forma Cash Flow Statement'!B35 -> 0.051707279
A23: Closing Date | B23: ='Pro Forma Cash Flow Statement'!B3 -> 44805
A25: Sale Information
A26: Exit Cap Rate | B26: ='Pro Forma Cash Flow Statement'!B23 -> 0.0475
A27: Closing Cost (% of Sale) | B27: ='Pro Forma Cash Flow Statement'!B25 -> 0.03
A28: Hold Period | B28: ='Pro Forma Cash Flow Statement'!B24 -> 12

Sheet Rent Roll
A1: Rent Roll As-Is | K1: Rent Roll Stabalized
A2: Building 521 | B2: Monthly Rent | C2: Annual Rent | D2: # of Bedroom | E2: # of Bathrooms | F2: Lease Start | G2: Lease End | H2: Notes | I2: Market Rate | K2: Building 521 | L2: Monthly Rent | M2: Annual Rent | N2: # of Bedroom | O2: # of Bathrooms | P2: Lease Start | Q2: Lease End | R2: Notes | S2: Market Rate
A3: Unit 1 | B3: 3950 | C3: =B3*12 -> 47400 | D3: 3 | E3: 2 | F3: 44317 | G3: 4/31/2023 | I3: Free Market | K3: Unit 1 | L3: 3950 | M3: =L3*12 -> 47400 | N3: 3 | O3: 2 | P3: 44317 | Q3: 4/31/2023 | S3: Free Market
A4: Unit 2 | B4: 3250 | C4: =B4*12 -> 39000 | D4: 3 | E4: 2 | F4: 44348 | G4: 44712 | I4: Free Market | K4: Unit 2 | L4: 3600 | M4: =L4*12 -> 43200 | N4: 3 | O4: 2 | P4: 44348 | Q4: 44712 | S4: Free Market
A5: Unit 3 | B5: 3136 | C5: =B5*12 -> 37632 | D5: 3 | E5: 2 | F5: 44440 | G5: 44804 | I5: Free Market | K5: Unit 3 | L5: 3600 | M5: =L5*12 -> 43200 | N5: 3 | O5: 2 | P5: 44440 | Q5: 44804 | S5: Free Market
A6: Total | B6: =SUM(B3:B5) -> 10336 | C6: =B6*12 -> 124032 | D6: =SUM(D3:D5) -> 9 | E6: =SUM(E3:E5) -> 6 | K6: Total | L6: =SUM(L3:L5) -> 11150 | M6: =L6*12 -> 133800 | N6: =SUM(N3:N5) -> 9 | O6: =SUM(O3:O5) -> 6
A7: Building 519 | K7: Building 519
A8: Unit 1 | B8: 4300 | C8: =B8*12 -> 51600 | D8: 3 | E8: 3 | F8: MTM | G8: MTM | H8: Units are furnished | I8: Free Market | K8: Unit 1 | L8: 4000 | M8: =L8*12 -> 48000 | N8: 3 | O8: 3 | P8: MTM | Q8: MTM | R8: Units are furnished | S8: Free Market
A9: Unit 2 | B9: 6350 | C9: =B9*12 -> 76200 | D9: 3 | E9: 2 | F9: MTM | G9: MTM | H9: Units are furnished | I9: Free Market | K9: Unit 2 | L9: 3600 | M9: =L9*12 -> 43200 | N9: 3 | O9: 2 | P9: MTM | Q9: MTM | R9: Units are furnished | S9: Free Market
A10: Unit 3 | B10: 6850 | C10: =B10*12 -> 82200 | D10: 3 | E10: 2 | F10: MTM | G10: MTM | H10: Units are furnished | I10: Free Market | K10: Unit 3 | L10: 3600 | M10: =L10*12 -> 43200 | N10: 3 | O10: 2 | P10: MTM | Q10: MTM | R10: Units are furnished | S10: Free Market
A11: Total | B11: =SUM(B8:B10) -> 17500 | C11: =B11*12 -> 210000 | D11: =SUM(D8:D10) -> 9 | E11: =SUM(E8:E10) -> 7 | K11: Total | L11: =SUM(L8:L10) -> 11200 | M11: =L11*12 -> 134400 | N11: =SUM(N8:N10) -> 9 | O11: =SUM(O8:O10) -> 7
A12: Building 515 | K12: Building 515
A13: Unit 1 | B13: 3195 | C13: =B13*12 -> 38340 | D13: 3 | E13: 2 | F13: 44263 | G13: 44712 | I13: Free Market | K13: Unit 1 | L13: 3600 | M13: =L13*12 -> 43200 | N13: 3 | O13: 2 | P13: 44263 | Q13: 44712 | S13: Free Market
A14: Unit 2 | B14: 2700 | C14: =B14*12 -> 32400 | D14: 2 | E14: 1 | F14: 44440 | G14: 44804 | I14: Free Market | K14: Unit 2 | L14: 3100 | M14: =L14*12 -> 37200 | N14: 2 | O14: 1 | P14: 44440 | Q14: 44804 | S14: Free Market
A15: Unit 3 | B15: 2500 | C15: =B15*12 -> 30000 | D15: 2 | E15: 1 | F15: 44197 | G15: 44711 | I15: Free Market | K15: Unit 3 | L15: 3100 | M15: =L15*12 -> 37200 | N15: 2 | O15: 1 | P15: 44197 | Q15: 44711 | S15: Free Market
A16: Total | B16: =SUM(B13:B15) -> 8395 | C16: =B16*12 -> 100740 | D16: =SUM(D13:D15) -> 7 | E16: =SUM(E13:E15) -> 4 | K16: Total | L16: =SUM(L13:L15) -> 9800 | M16: =L16*12 -> 117600 | N16: =SUM(N13:N15) -> 7 | O16: =SUM(O13:O15) -> 4
A17: Portfolio Total | B17: =SUM(B16,B11,B6) -> 36231 | C17: =B17*12 -> 434772 | D17: =SUM(D16,D11,D6) -> 25 | E17: =SUM(E16,E11,E6) -> 17 | K17: Portfolio Total | L17: =SUM(L16,L11,L6) -> 32150 | M17: =L17*12 -> 385800 | N17: =SUM(N16,N11,N6) -> 25 | O17: =SUM(O16,O11,O6) -> 17

Sheet Expenses
A1: Annnual Expenses (As - Is) | H1: Annnual Expenses (Pro Forma)
A2: Building 521 | C2: Building 519 | E2: Building 515 | H2: Building 521 | J2: Building 519 | L2: Building 515
A3: Taxes | B3: 4667.56 | C3: Taxes | D3: 2628.96 | E3: Taxes | F3: 4272.28 | H3: Taxes | I3: 4667.56 | J3: Taxes | K3: 2628.96 | L3: Taxes | M3: 4272.28
A4: Insurance | B4: 4128 | C4: Insurance | D4: 4128 | E4: Insurance | F4: 4128 | H4: Insurance | I4: 4128 | J4: Insurance | K4: 4128 | L4: Insurance | M4: 4128
A5: Super/Garbage | B5: 3200 | C5: Super/Garbage | D5: 3200 | E5: Super/Garbage | F5: 3200 | H5: Super/Garbage | I5: 3200 | J5: Super/Garbage | K5: 3200 | L5: Super/Garbage | M5: 3200
A6: Electric | B6: 600 | C6: Electric | D6: 600 | E6: Electric | F6: 600 | H6: Electric | I6: 600 | J6: Electric | K6: 600 | L6: Electric | M6: 600
A7: Water | B7: 1200 | C7: Water | D7: 1200 | E7: Water | F7: 1200 | H7: Water | I7: 1200 | J7: Water | K7: 1200 | L7: Water | M7: 1200
A8: Maintenance | B8: 2000 | C8: Maintenance | D8: 2000 | E8: Maintenance | F8: 2000 | H8: Maintenance | I8: 2000 | J8: Maintenance | K8: 2000 | L8: Maintenance | M8: 2000
A9: Management | B9: 7441.92 | C9: Management | D9: 25200 | E9: Management | F9: 6044.4 | H9: Management | I9: 7441.92 | J9: Management | K9: 8000 | L9: Management | M9: 6044.4
A10: Total | B10: =SUM(B3:B9) -> 23237.48 | C10: Total | D10: =SUM(D3:D9) -> 38956.96 | E10: Total | F10: =SUM(F3:F9) -> 21444.68 | H10: Total | I10: =SUM(I3:I9) -> 23237.48 | J10: Total | K10: =SUM(K3:K9) -> 21756.96 | L10: Total | M10: =SUM(M3:M9) -> 21444.68
E11: Portfolio Total | F11: =SUM(F10,D10,B10) -> 83639.12 | L11: Portfolio Total | M11: =SUM(M10,K10,I10) -> 66439.12

Sheet Pro Forma Cash Flow Statement
A1: Purchase and Deal Metrics | D1: 5 Year Hold Analysis
A2: Purchase Price | B2: 4750000 | D2: Month Ending | E2: ='Deal Summary'!B23 -> 44805 | F2: =EOMONTH(E2,1) -> 44865 | G2: =EOMONTH(F2,1) -> 44895 | H2: =EOMONTH(G2,1) -> 44926 | I2: =EOMONTH(H2,1) -> 44957 | J2: =EOMONTH(I2,1) -> 44985 | K2: =EOMONTH(J2,1) -> 45016 | L2: =EOMONTH(K2,1) -> 45046 | M2: =EOMONTH(L2,1) -> 45077 | ... BY2: =EOMONTH(BX2,1) -> 47026
A3: Purchase Date | B3: 44805 | D3: Month | E3: 0 | F3: 1 | G3: =F3+1 -> 2 | H3: =G3+1 -> 3 | I3: =H3+1 -> 4 | J3: =I3+1 -> 5 | K3: =J3+1 -> 6 | L3: =K3+1 -> 7 | M3: =L3+1 -> 8 | N3: =M3+1 -> 9 | ... BY3: =BX3+1 -> 72
A4: Closing Cost | B4: =B2*C4 -> 95000 | C4: 0.02 | D4: Year | E4: 0 | F4: 1 | G4: 1 | H4: 1 | I4: 1 | J4: 1 | K4: 1 | L4: 1 | M4: 1 | N4: 1 | O4: 1 | P4: 1 | Q4: 1 | R4: =F4+1 -> 2 | S4: =G4+1 -> 2 | T4: =H4+1 -> 2 | U4: =I4+1 -> 2 | V4: =J4+1 -> 2 | W4: =K4+1 -> 2 | X4: =L4+1 -> 2 | Y4: =M4+1 -> 2 | ... BY4: =BM4+1 -> 6
D5: Gross Potential Rental Revenue | E5: 0 | F5: ='Rent Roll'!L17 -> 32150 | G5: =F5*(1+$B$9)^(1/12) -> 32216.224 | H5: =G5*(1+$B$9)^(1/12) -> 32282.584 | I5: =H5*(1+$B$9)^(1/12) -> 32349.081 | J5: =I5*(1+$B$9)^(1/12) -> 32415.715 | K5: =J5*(1+$B$9)^(1/12) -> 32482.486 | L5: =K5*(1+$B$9)^(1/12) -> 32549.394 | M5: =L5*(1+$B$9)^(1/12) -> 32616.441 | N5: =M5*(1+$B$9)^(1/12) -> 32683.625 | ... BY5: =BX5*(1+$B$9)^(1/12) -> 37207.502
A6: Operation Assumptions | D6: Vacancy | E6: 0 | F6: =-$B$8*F5 -> -1286 | G6: =-$B$8*G5 -> -1288.6489 | H6: =-$B$8*H5 -> -1291.3034 | I6: =-$B$8*I5 -> -1293.9632 | J6: =-$B$8*J5 -> -1296.6286 | K6: =-$B$8*K5 -> -1299.2994 | L6: =-$B$8*L5 -> -1301.9758 | M6: =-$B$8*M5 -> -1304.6576 | ... BY6: =-$B$8*BY5 -> -1488.3001
A7: Gross SF | B7: ='Deal Summary'!B4 -> 10247 | D7: Net Rental Income | E7: 0 | F7: =SUM(F5:F6) -> 30864 | G7: =SUM(G5:G6) -> 30927.575 | H7: =SUM(H5:H6) -> 30991.281 | I7: =SUM(I5:I6) -> 31055.117 | J7: =SUM(J5:J6) -> 31119.086 | K7: =SUM(K5:K6) -> 31183.186 | L7: =SUM(L5:L6) -> 31247.418 | M7: =SUM(M5:M6) -> 31311.783 | ... BY7: =SUM(BY5:BY6) -> 35719.202
A8: Vacancy | B8: 0.04 | D8: Operating Expenses | E8: 0 | F8: =-Expenses!$M$11/12 -> -5536.5933 | G8: =F8*(1+$B$10)^(1/12) -> -5543.4669 | H8: =G8*(1+$B$10)^(1/12) -> -5550.3491 | I8: =H8*(1+$B$10)^(1/12) -> -5557.2398 | J8: =I8*(1+$B$10)^(1/12) -> -5564.139 | K8: =J8*(1+$B$10)^(1/12) -> -5571.0468 | L8: =K8*(1+$B$10)^(1/12) -> -5577.9632 | M8: =L8*(1+$B$10)^(1/12) -> -5584.8882 | N8: =M8*(1+$B$10)^(1/12) -> -5591.8218 | ... BY8: =BX8*(1+$B$10)^(1/12) -> -6046.4441
A9: Annual Rental Growth Rate | B9: 0.025 | D9: Net Operating Income | E9: 0 | F9: =SUM(F7:F8) -> 25327.407 | G9: =SUM(G7:G8) -> 25384.108 | H9: =SUM(H7:H8) -> 25440.931 | I9: =SUM(I7:I8) -> 25497.878 | J9: =SUM(J7:J8) -> 25554.947 | K9: =SUM(K7:K8) -> 25612.139 | L9: =SUM(L7:L8) -> 25669.455 | M9: =SUM(M7:M8) -> 25726.895 | ... BY9: =SUM(BY7:BY8) -> 29672.758
A10: Annual Expense Growth rate | B10: 0.015 | D10: Capital Improvements | E10: 0 | F10: 0 | G10: 0 | H10: 0 | I10: 0 | J10: 0 | K10: 0 | L10: 0 | M10: 0 | N10: 0 | O10: 0 | P10: 0 | Q10: 0 | R10: 0 | S10: 0 | T10: 0 | U10: 0 | V10: 0 | W10: 0 | X10: 0 | Y10: 0 | Z10: 0 | AA10: 0 | AB10: 0 | AC10: 0 | AD10: 0 | AE10: 0 | AF10: 0 | AG10: 0 | AH10: 0 | AI10: 0 | AJ10: 0 | AK10: 0 | AL10: 0 | AM10: 0 | AN10: 0 | AO10: 0 | AP10: 0 | AQ10: 0 | AR10: 0 | AS10: 0 | AT10: 0 | AU10: 0 | AV10: 0 | AW10: 0 | AX10: 0 | AY10: 0 | AZ10: 0 | BA10: 0 | BB10: 0 | BC10: 0 | BD10: 0 | BE10: 0 | BF10: 0 | BG10: 0 | BH10: 0 | BI10: 0 | BJ10: 0 | BK10: 0 | BL10: 0 | BM10: 0 | BN10: 0 | BO10: 0 | BP10: 0 | BQ10: 0 | BR10: 0 | BS10: 0 | BT10: 0 | BU10: 0 | BV10: 0 | BW10: 0 | BX10: 0 | BY10: 0
A11: Capital Improvements | B11: 50000 | D11: Capital Reserves | E11: 0 | F11: 0 | G11: 0 | H11: 0 | I11: 0 | J11: 0 | K11: 0 | L11: 0 | M11: 0 | N11: 0 | O11: 0 | P11: 0 | Q11: 0 | R11: 0 | S11: 0 | T11: 0 | U11: 0 | V11: 0 | W11: 0 | X11: 0 | Y11: 0 | Z11: 0 | AA11: 0 | AB11: 0 | AC11: 0 | AD11: 0 | AE11: 0 | AF11: 0 | AG11: 0 | AH11: 0 | AI11: 0 | AJ11: 0 | AK11: 0 | AL11: 0 | AM11: 0 | AN11: 0 | AO11: 0 | AP11: 0 | AQ11: 0 | AR11: 0 | AS11: 0 | AT11: 0 | AU11: 0 | AV11: 0 | AW11: 0 | AX11: 0 | AY11: 0 | AZ11: 0 | BA11: 0 | BB11: 0 | BC11: 0 | BD11: 0 | BE11: 0 | BF11: 0 | BG11: 0 | BH11: 0 | BI11: 0 | BJ11: 0 | BK11: 0 | BL11: 0 | BM11: 0 | BN11: 0 | BO11: 0 | BP11: 0 | BQ11: 0 | BR11: 0 | BS11: 0 | BT11: 0 | BU11: 0 | BV11: 0 | BW11: 0 | BX11: 0 | BY11: 0
A12: Capital Improvements Month Start | B12: 0 | D12: Cash Flow Before Debt Service | E12: 0 | F12: =SUM(F9:F11) -> 25327.407 | G12: =SUM(G9:G11) -> 25384.108 | H12: =SUM(H9:H11) -> 25440.931 | I12: =SUM(I9:I11) -> 25497.878 | J12: =SUM(J9:J11) -> 25554.947 | K12: =SUM(K9:K11) -> 25612.139 | L12: =SUM(L9:L11) -> 25669.455 | M12: =SUM(M9:M11) -> 25726.895 | ... BY12: =SUM(BY9:BY11) -> 29672.758
A13: Capital Improvements Month End | B13: 0 | D13: Princpial Payment | E13: 0 | F13: =PPMT($B$19/12,F3,$B$20*12,$B$17*$B$2,0,) -> -5693.235 | G13: =PPMT($B$19/12,G3,$B$20*12,$B$17*$B$2,0,) -> -5718.5224 | H13: =PPMT($B$19/12,H3,$B$20*12,$B$17*$B$2,0,) -> -5743.9222 | I13: =PPMT($B$19/12,I3,$B$20*12,$B$17*$B$2,0,) -> -5769.4348 | J13: =PPMT($B$19/12,J3,$B$20*12,$B$17*$B$2,0,) -> -5795.0607 | K13: =PPMT($B$19/12,K3,$B$20*12,$B$17*$B$2,0,) -> -5820.8004 | L13: =PPMT($B$19/12,L3,$B$20*12,$B$17*$B$2,0,) -> -5846.6545 | M13: =PPMT($B$19/12,M3,$B$20*12,$B$17*$B$2,0,) -> -5872.6234 | ... BY13: =PPMT($B$19/12,BY3,$B$20*12,$B$17*$B$2,0,) -> -7798.5566
A14: Capital Reserves(% of Gross Revenue) | B14: 0 | D14: Interests Payments | E14: 0 | F14: =IPMT($B$19/12,F3,$B$20*12,$B$17*$B$2,0,) -> -15823.438 | G14: =IPMT($B$19/12,G3,$B$20*12,$B$17*$B$2,0,) -> -15798.15 | H14: =IPMT($B$19/12,H3,$B$20*12,$B$17*$B$2,0,) -> -15772.75 | I14: =IPMT($B$19/12,I3,$B$20*12,$B$17*$B$2,0,) -> -15747.238 | J14: =IPMT($B$19/12,J3,$B$20*12,$B$17*$B$2,0,) -> -15721.612 | K14: =IPMT($B$19/12,K3,$B$20*12,$B$17*$B$2,0,) -> -15695.872 | L14: =IPMT($B$19/12,L3,$B$20*12,$B$17*$B$2,0,) -> -15670.018 | M14: =IPMT($B$19/12,M3,$B$20*12,$B$17*$B$2,0,) -> -15644.049 | ... BY14: =IPMT($B$19/12,BY3,$B$20*12,$B$17*$B$2,0,) -> -13718.116
D15: Cash Flow After Debt Service | E15: 0 | F15: =SUM(F12:F14) -> 3810.7342 | G15: =SUM(G12:G14) -> 3867.4354 | H15: =SUM(H12:H14) -> 3924.2589 | I15: =SUM(I12:I14) -> 3981.2052 | J15: =SUM(J12:J14) -> 4038.2744 | K15: =SUM(K12:K14) -> 4095.4668 | L15: =SUM(L12:L14) -> 4152.7827 | M15: =SUM(M12:M14) -> 4210.2223 | ... BY15: =SUM(BY12:BY14) -> 8156.0854
A16: Loan Metrics | D16: Purchase Price | E16: =-B2 -> -4750000 | F16: 0 | G16: 0 | H16: 0 | I16: 0 | J16: 0 | K16: 0 | L16: 0 | M16: 0 | N16: 0 | O16: 0 | P16: 0 | Q16: 0 | R16: 0 | S16: 0 | T16: 0 | U16: 0 | V16: 0 | W16: 0 | X16: 0 | Y16: 0 | Z16: 0 | AA16: 0 | AB16: 0 | AC16: 0 | AD16: 0 | AE16: 0 | AF16: 0 | AG16: 0 | AH16: 0 | AI16: 0 | AJ16: 0 | AK16: 0 | AL16: 0 | AM16: 0 | AN16: 0 | AO16: 0 | AP16: 0 | AQ16: 0 | AR16: 0 | AS16: 0 | AT16: 0 | AU16: 0 | AV16: 0 | AW16: 0 | AX16: 0 | AY16: 0 | AZ16: 0 | BA16: 0 | BB16: 0 | BC16: 0 | BD16: 0 | BE16: 0 | BF16: 0 | BG16: 0 | BH16: 0 | BI16: 0 | BJ16: 0 | BK16: 0 | BL16: 0 | BM16: 0 | BN16: 0 | BO16: 0 | BP16: 0 | BQ16: 0 | BR16: 0 | BS16: 0 | BT16: 0 | BU16: 0 | BV16: 0 | BW16: 0 | BX16: 0 | BY16: 0
A17: LTV | B17: 0.75 | D17: Closing Costs | E17: =-B4 -> -95000 | F17: 0 | G17: 0 | H17: 0 | I17: 0 | J17: 0 | K17: 0 | L17: 0 | M17: 0 | N17: 0 | O17: 0 | P17: 0 | Q17: 0 | R17: 0 | S17: 0 | T17: 0 | U17: 0 | V17: 0 | W17: 0 | X17: 0 | Y17: 0 | Z17: 0 | AA17: 0 | AB17: 0 | AC17: 0 | AD17: 0 | AE17: 0 | AF17: 0 | AG17: 0 | AH17: 0 | AI17: 0 | AJ17: 0 | AK17: 0 | AL17: 0 | AM17: 0 | AN17: 0 | AO17: 0 | AP17: 0 | AQ17: 0 | AR17: 0 | AS17: 0 | AT17: 0 | AU17: 0 | AV17: 0 | AW17: 0 | AX17: 0 | AY17: 0 | AZ17: 0 | BA17: 0 | BB17: 0 | BC17: 0 | BD17: 0 | BE17: 0 | BF17: 0 | BG17: 0 | BH17: 0 | BI17: 0 | BJ17: 0 | BK17: 0 | BL17: 0 | BM17: 0 | BN17: 0 | BO17: 0 | BP17: 0 | BQ17: 0 | BR17: 0 | BS17: 0 | BT17: 0 | BU17: 0 | BV17: 0 | BW17: 0 | BX17: 0 | BY17: 0
A18: Loan Origination Fee | B18: 0.01 | D18: Sale Proceeds | E18: 0 | F18: 0 | G18: 0 | H18: 0 | I18: 0 | J18: 0 | K18: 0 | L18: 0 | M18: 0 | N18: 0 | O18: 0 | P18: 0 | Q18: =IF(Q3=$B$24,SUM(R9:AA9)/$B$23,0) -> 5532487.1 | R18: 0 | S18: 0 | T18: 0 | U18: 0 | V18: 0 | W18: 0 | X18: 0 | Y18: 0 | Z18: 0 | AA18: 0 | AB18: 0 | AC18: 0 | AD18: 0 | AE18: 0 | AF18: 0 | AG18: 0 | AH18: 0 | AI18: 0 | AJ18: 0 | AK18: 0 | AL18: 0 | AM18: 0 | AN18: 0 | AO18: 0 | AP18: 0 | AQ18: 0 | AR18: 0 | AS18: 0 | AT18: 0 | AU18: 0 | AV18: 0 | AW18: 0 | AX18: 0 | AY18: 0 | AZ18: 0 | BA18: 0 | BB18: 0 | BC18: 0 | BD18: 0 | BE18: 0 | BF18: 0 | BG18: 0 | BH18: 0 | BI18: 0 | BJ18: 0 | BK18: 0 | BL18: 0 | BM18: 0 | BN18: 0 | BO18: 0 | BP18: 0 | BQ18: 0 | BR18: 0 | BS18: 0 | BT18: 0 | BU18: 0 | BV18: 0 | BW18: 0 | BX18: 0 | BY18: 0
A19: Interests Rate | B19: ='Deal Summary'!E8 -> 0.0533 | D19: Costs of Sale | E19: 0 | F19: 0 | G19: 0 | H19: 0 | I19: 0 | J19: 0 | K19: 0 | L19: 0 | M19: 0 | N19: 0 | O19: 0 | P19: 0 | Q19: =IF(Q3=$B$24,-$B$25*Q18,0) -> -165974.61 | R19: 0 | S19: 0 | T19: 0 | U19: 0 | V19: 0 | W19: 0 | X19: 0 | Y19: 0 | Z19: 0 | AA19: 0 | AB19: 0 | AC19: 0 | AD19: 0 | AE19: 0 | AF19: 0 | AG19: 0 | AH19: 0 | AI19: 0 | AJ19: 0 | AK19: 0 | AL19: 0 | AM19: 0 | AN19: 0 | AO19: 0 | AP19: 0 | AQ19: 0 | AR19: 0 | AS19: 0 | AT19: 0 | AU19: 0 | AV19: 0 | AW19: 0 | AX19: 0 | AY19: 0 | AZ19: 0 | BA19: 0 | BB19: 0 | BC19: 0 | BD19: 0 | BE19: 0 | BF19: 0 | BG19: 0 | BH19: 0 | BI19: 0 | BJ19: 0 | BK19: 0 | BL19: 0 | BM19: 0 | BN19: 0 | BO19: 0 | BP19: 0 | BQ19: 0 | BR19: 0 | BS19: 0 | BT19: 0 | BU19: 0 | BV19: 0 | BW19: 0 | BX19: 0 | BY19: 0
A20: Amortization | B20: 25 | D20: Total Unlevered Cash Flows | E20: =SUM(E16:E19) -> -4845000 | F20: =IF(F3>$B$24,0,SUM(F12,F16:F19)) -> 25327.407 | G20: =IF(G3>$B$24,0,SUM(G12,G16:G19)) -> 25384.108 | H20: =IF(H3>$B$24,0,SUM(H12,H16:H19)) -> 25440.931 | I20: =IF(I3>$B$24,0,SUM(I12,I16:I19)) -> 25497.878 | J20: =IF(J3>$B$24,0,SUM(J12,J16:J19)) -> 25554.947 | K20: =IF(K3>$B$24,0,SUM(K12,K16:K19)) -> 25612.139 | L20: =IF(L3>$B$24,0,SUM(L12,L16:L19)) -> 25669.455 | M20: =IF(M3>$B$24,0,SUM(M12,M16:M19)) -> 25726.895 | ... Q20: =IF(Q3>$B$24,0,SUM(Q12,Q16:Q19)) -> 5392470.4 | R20: 0 | S20: 0 | T20: 0 | U20: 0 | V20: 0 | W20: 0 | X20: 0 | Y20: 0 | Z20: 0 | AA20: 0 | AB20: 0 | AC20: 0 | AD20: 0 | AE20: 0 | AF20: 0 | AG20: 0 | AH20: 0 | AI20: 0 | AJ20: 0 | AK20: 0 | AL20: 0 | AM20: 0 | AN20: 0 | AO20: 0 | AP20: 0 | AQ20: 0 | AR20: 0 | AS20: 0 | AT20: 0 | AU20: 0 | AV20: 0 | AW20: 0 | AX20: 0 | AY20: 0 | AZ20: 0 | BA20: 0 | BB20: 0 | BC20: 0 | BD20: 0 | BE20: 0 | BF20: 0 | BG20: 0 | BH20: 0 | BI20: 0 | BJ20: 0 | BK20: 0 | BL20: 0 | BM20: 0 | BN20: 0 | BO20: 0 | BP20: 0 | BQ20: 0 | BR20: 0 | BS20: 0 | BT20: 0 | BU20: 0 | BV20: 0 | BW20: 0 | BX20: 0 | BY20: 0
D21: Loan Proceeds | E21: =$B$17*$B$2 -> 3562500 | F21: 0 | G21: 0 | H21: 0 | I21: 0 | J21: 0 | K21: 0 | L21: 0 | M21: 0 | N21: 0 | O21: 0 | P21: 0 | Q21: 0 | R21: 0 | S21: 0 | T21: 0 | U21: 0 | V21: 0 | W21: 0 | X21: 0 | Y21: 0 | Z21: 0 | AA21: 0 | AB21: 0 | AC21: 0 | AD21: 0 | AE21: 0 | AF21: 0 | AG21: 0 | AH21: 0 | AI21: 0 | AJ21: 0 | AK21: 0 | AL21: 0 | AM21: 0 | AN21: 0 | AO21: 0 | AP21: 0 | AQ21: 0 | AR21: 0 | AS21: 0 | AT21: 0 | AU21: 0 | AV21: 0 | AW21: 0 | AX21: 0 | AY21: 0 | AZ21: 0 | BA21: 0 | BB21: 0 | BC21: 0 | BD21: 0 | BE21: 0 | BF21: 0 | BG21: 0 | BH21: 0 | BI21: 0 | BJ21: 0 | BK21: 0 | BL21: 0 | BM21: 0 | BN21: 0 | BO21: 0 | BP21: 0 | BQ21: 0 | BR21: 0 | BS21: 0 | BT21: 0 | BU21: 0 | BV21: 0 | BW21: 0 | BX21: 0 | BY21: 0
A22: Sale Metrics | D22: Loan Origination Fee | E22: =-$B$18*E21 -> -35625 | F22: 0 | G22: 0 | H22: 0 | I22: 0 | J22: 0 | K22: 0 | L22: 0 | M22: 0 | N22: 0 | O22: 0 | P22: 0 | Q22: 0 | R22: 0 | S22: 0 | T22: 0 | U22: 0 | V22: 0 | W22: 0 | X22: 0 | Y22: 0 | Z22: 0 | AA22: 0 | AB22: 0 | AC22: 0 | AD22: 0 | AE22: 0 | AF22: 0 | AG22: 0 | AH22: 0 | AI22: 0 | AJ22: 0 | AK22: 0 | AL22: 0 | AM22: 0 | AN22: 0 | AO22: 0 | AP22: 0 | AQ22: 0 | AR22: 0 | AS22: 0 | AT22: 0 | AU22: 0 | AV22: 0 | AW22: 0 | AX22: 0 | AY22: 0 | AZ22: 0 | BA22: 0 | BB22: 0 | BC22: 0 | BD22: 0 | BE22: 0 | BF22: 0 | BG22: 0 | BH22: 0 | BI22: 0 | BJ22: 0 | BK22: 0 | BL22: 0 | BM22: 0 | BN22: 0 | BO22: 0 | BP22: 0 | BQ22: 0 | BR22: 0 | BS22: 0 | BT22: 0 | BU22: 0 | BV22: 0 | BW22: 0 | BX22: 0 | BY22: 0
A23: Exit Cap Rate | B23: 0.0475 | D23: Loan Payoff | E23: 0 | F23: 0 | G23: 0 | H23: 0 | I23: 0 | J23: 0 | K23: 0 | L23: 0 | M23: 0 | N23: 0 | O23: 0 | P23: 0 | Q23: =IF(Q3=$B$24,-($E$21-SUM($F$13:Q13)),0) -> -3632512.8 | R23: 0 | S23: 0 | T23: 0 | U23: 0 | V23: 0 | W23: 0 | X23: 0 | Y23: 0 | Z23: 0 | AA23: 0 | AB23: 0 | AC23: 0 | AD23: 0 | AE23: 0 | AF23: 0 | AG23: 0 | AH23: 0 | AI23: 0 | AJ23: 0 | AK23: 0 | AL23: 0 | AM23: 0 | AN23: 0 | AO23: 0 | AP23: 0 | AQ23: 0 | AR23: 0 | AS23: 0 | AT23: 0 | AU23: 0 | AV23: 0 | AW23: 0 | AX23: 0 | AY23: 0 | AZ23: 0 | BA23: 0 | BB23: 0 | BC23: 0 | BD23: 0 | BE23: 0 | BF23: 0 | BG23: 0 | BH23: 0 | BI23: 0 | BJ23: 0 | BK23: 0 | BL23: 0 | BM23: 0 | BN23: 0 | BO23: 0 | BP23: 0 | BQ23: 0 | BR23: 0 | BS23: 0 | BT23: 0 | BU23: 0 | BV23: 0 | BW23: 0 | BX23: 0 | BY23: 0
A24: Hold Period | B24: 12 | D24: Total Levered Cash Flows | E24: =IF(E3>$B$24,0,SUM(E15:E19,E21:E23)) -> -1318125 | F24: =IF(F3>$B$24,0,SUM(F15:F19,F21:F23)) -> 3810.7342 | G24: =IF(G3>$B$24,0,SUM(G15:G19,G21:G23)) -> 3867.4354 | H24: =IF(H3>$B$24,0,SUM(H15:H19,H21:H23)) -> 3924.2589 | I24: =IF(I3>$B$24,0,SUM(I15:I19,I21:I23)) -> 3981.2052 | J24: =IF(J3>$B$24,0,SUM(J15:J19,J21:J23)) -> 4038.2744 | K24: =IF(K3>$B$24,0,SUM(K15:K19,K21:K23)) -> 4095.4668 | L24: =IF(L3>$B$24,0,SUM(L15:L19,L21:L23)) -> 4152.7827 | ... Q24: =IF(Q3>$B$24,0,SUM(Q15:Q19,Q21:Q23)) -> 1738440.9 | R24: 0 | S24: 0 | T24: 0 | U24: 0 | V24: 0 | W24: 0 | X24: 0 | Y24: 0 | Z24: 0 | AA24: 0 | AB24: 0 | AC24: 0 | AD24: 0 | AE24: 0 | AF24: 0 | AG24: 0 | AH24: 0 | AI24: 0 | AJ24: 0 | AK24: 0 | AL24: 0 | AM24: 0 | AN24: 0 | AO24: 0 | AP24: 0 | AQ24: 0 | AR24: 0 | AS24: 0 | AT24: 0 | AU24: 0 | AV24: 0 | AW24: 0 | AX24: 0 | AY24: 0 | AZ24: 0 | BA24: 0 | BB24: 0 | BC24: 0 | BD24: 0 | BE24: 0 | BF24: 0 | BG24: 0 | BH24: 0 | BI24: 0 | BJ24: 0 | BK24: 0 | BL24: 0 | BM24: 0 | BN24: 0 | BO24: 0 | BP24: 0 | BQ24: 0 | BR24: 0 | BS24: 0 | BT24: 0 | BU24: 0 | BV24: 0 | BW24: 0 | BX24: 0 | BY24: 0
A25: Cost of Sale | B25: 0.03
D26: Cash - on - Cash Return | E26: 1 | F26: =E26+1 -> 2 | G26: =F26+1 -> 3 | H26: =G26+1 -> 4 | I26: =H26+1 -> 5
A27: Project Level Returns | D27: Unlevered Cash on Cash Return | E27: =SUMIF($E$4:$BY$4,E26,E12:BY12)/ABS(SUMIFS($E$20:$BY$20,$E$20:$BY$20,"<0",$E$4:$BY$4,"<"&E26)) -> 0.063508404 | F27: =SUMIF($E$4:$BY$4,F26,F12:BZ12)/ABS(SUMIFS($E$20:$BY$20,$E$20:$BY$20,"<0",$E$4:$BY$4,"<"&F26)) -> 0.065380024 | G27: =SUMIF($E$4:$BY$4,G26,G12:CA12)/ABS(SUMIFS($E$20:$BY$20,$E$20:$BY$20,"<0",$E$4:$BY$4,"<"&G26)) -> 0.067304822 | H27: =SUMIF($E$4:$BY$4,H26,H12:CB12)/ABS(SUMIFS($E$20:$BY$20,$E$20:$BY$20,"<0",$E$4:$BY$4,"<"&H26)) -> 0.069284279 | I27: =SUMIF($E$4:$BY$4,I26,I12:CC12)/ABS(SUMIFS($E$20:$BY$20,$E$20:$BY$20,"<0",$E$4:$BY$4,"<"&I26)) -> 0.071319919
A28: Pro Forma Cap Rate | B28: =SUM(F9:Q9)/B2 -> 0.064778572 | D28: Levered Cash on Cash Return | E28: =SUMIF($E$4:$BY$4,E26,E15:BY15)/ABS(SUMIFS($E$24:$BY$24,$E$24:$BY$24,"<0",$E$4:$BY$4,"<"&E26)) -> 0.037551938 | F28: =SUMIF($E$4:$BY$4,F26,F15:BZ15)/ABS(SUMIFS($E$24:$BY$24,$E$24:$BY$24,"<0",$E$4:$BY$4,"<"&F26)) -> 0.044431405 | G28: =SUMIF($E$4:$BY$4,G26,G15:CA15)/ABS(SUMIFS($E$24:$BY$24,$E$24:$BY$24,"<0",$E$4:$BY$4,"<"&G26)) -> 0.051506338 | H28: =SUMIF($E$4:$BY$4,H26,H15:CB15)/ABS(SUMIFS($E$24:$BY$24,$E$24:$BY$24,"<0",$E$4:$BY$4,"<"&H26)) -> 0.058782182 | I28: =SUMIF($E$4:$BY$4,I26,I15:CC15)/ABS(SUMIFS($E$24:$BY$24,$E$24:$BY$24,"<0",$E$4:$BY$4,"<"&I26)) -> 0.066264532
A29: Loan Constant | B29: {=-SUM(F13:Q14/E21)} -> 0.072477213
A30: Unlevered IRR | B30: =XIRR(E20:BY20,E2:BY2) -> 0.16178309
A31: Levered IRR | B31: =XIRR(E24:BY24,E2:BY2) -> 0.3279777
A32: Unlevered Equity Multiple | B32: =SUMIF(E20:BY20,">0",E20:BY20)/ABS(SUMIF(E20:BY20,"<0",E20:BY20)) -> 1.1711477
A33: Levered Equity Multiple | B33: =SUMIF(E24:BY24,">0",E24:BY24)/ABS(SUMIF(E24:BY24,"<0",E24:BY24)) -> 1.3530567
A34: Average Unlevered Cash on Cash | B34: =AVERAGE(E27:I27) -> 0.06735949
A35: Average Levered Cash on Cash | B35: =AVERAGE(E28:I28) -> 0.051707279
