Workbook
Name __FDS_UNIQUE_RANGE_ID_GENERATOR_COUNTER: 1
Name A_ALL_Ticker0001: Ticker0001_Annotation_Sheet!$A$1:$FE$309
Name A_ALL_KEYWORDS_TYPE_ScalarContributed_EQTY_200000801: Ticker0001_Annotation_Sheet!$245:$245,Ticker0001_Annotation_Sheet!$248:$254,Ticker0001_Annotation_Sheet!$296:$296,Ticker0001_Annotation_Sheet!$300:$302,Ticker0001_Annotation_Sheet!$307:$309
Name A_ALL_KEYWORDS_TYPE_ScalarContributed_EQTY_200000801: Ticker0001_Annotation_Sheet!$248:$254,Ticker0001_Annotation_Sheet!$296:$296,Ticker0001_Annotation_Sheet!$300:$302,Ticker0001_Annotation_Sheet!$307:$309,Ticker0001_Annotation_Sheet!$245:$246
Name A_ALL_KEYWORDS_TYPE_ScalarContributed_ISSR_208000149: Ticker0001_Annotation_Sheet!$9:$9,Ticker0001_Annotation_Sheet!$39:$39
Name A_ALL_KEYWORDS_TYPE_ScalarReference_EQTY_200000801: Ticker0001_Annotation_Sheet!$238:$243
Name A_ALL_KEYWORDS_TYPE_ScalarReference_ISSR_208000149: Ticker0001_Annotation_Sheet!$6:$7
Name A_ALL_PERIODS_Ticker0001: Ticker0001_Annotation_Sheet!$F$1:$FE$1
Name A_ALL_SECTION_KEYWORDS_EQTY_200000801_1314: Ticker0001_Annotation_Sheet!$C$298
Name A_ALL_SECTION_KEYWORDS_EQTY_200000801_1319: Ticker0001_Annotation_Sheet!$C$300:$C$303
Name A_ALL_SECTION_KEYWORDS_EQTY_200000801_131E: Ticker0001_Annotation_Sheet!$C$305
Name A_ALL_SECTION_KEYWORDS_EQTY_200000801_131O: Ticker0001_Annotation_Sheet!$C$307:$C$309
Name A_ALL_SECTION_KEYWORDS_EQTY_200000801_13A: Ticker0001_Annotation_Sheet!$C$245:$C$254
Name A_ALL_SECTION_KEYWORDS_EQTY_200000801_13A: Ticker0001_Annotation_Sheet!$C$245:$C$254
Name A_ALL_SECTION_KEYWORDS_EQTY_200000801_13K: Ticker0001_Annotation_Sheet!$C$256:$C$271
Name A_ALL_SECTION_KEYWORDS_EQTY_200000801_13U: Ticker0001_Annotation_Sheet!$C$273:$C$288
Name A_ALL_SECTION_KEYWORDS_EQTY_200000801_13V: Ticker0001_Annotation_Sheet!$C$290
Name A_ALL_SECTION_KEYWORDS_EQTY_200000801_13W: Ticker0001_Annotation_Sheet!$C$292:$C$296
Name A_ALL_SECTION_KEYWORDS_EQTY_200000801_Reference_Data: Ticker0001_Annotation_Sheet!$C$238:$C$243
Name A_ALL_SECTION_KEYWORDS_ISSR_208000149_1314: Ticker0001_Annotation_Sheet!$C$41:$C$70
Name A_ALL_SECTION_KEYWORDS_ISSR_208000149_13168: Ticker0001_Annotation_Sheet!$C$128:$C$189
Name A_ALL_SECTION_KEYWORDS_ISSR_208000149_1316T: Ticker0001_Annotation_Sheet!$C$191:$C$197
Name A_ALL_SECTION_KEYWORDS_ISSR_208000149_1316U: Ticker0001_Annotation_Sheet!$C$199:$C$213
Name A_ALL_SECTION_KEYWORDS_ISSR_208000149_1319: Ticker0001_Annotation_Sheet!$C$72:$C$90
Name A_ALL_SECTION_KEYWORDS_ISSR_208000149_131E: Ticker0001_Annotation_Sheet!$C$92:$C$108
Name A_ALL_SECTION_KEYWORDS_ISSR_208000149_131J: Ticker0001_Annotation_Sheet!$C$110:$C$122
Name A_ALL_SECTION_KEYWORDS_ISSR_208000149_131O: Ticker0001_Annotation_Sheet!$C$124
Name A_ALL_SECTION_KEYWORDS_ISSR_208000149_131O: Ticker0001_Annotation_Sheet!$C$124,Ticker0001_Annotation_Sheet!$C$126
Name A_ALL_SECTION_KEYWORDS_ISSR_208000149_136E: Ticker0001_Annotation_Sheet!$C$215:$C$224
Name A_ALL_SECTION_KEYWORDS_ISSR_208000149_136J: Ticker0001_Annotation_Sheet!$C$226:$C$235
Name A_ALL_SECTION_KEYWORDS_ISSR_208000149_13A: Ticker0001_Annotation_Sheet!$C$9
Name A_ALL_SECTION_KEYWORDS_ISSR_208000149_13U: Ticker0001_Annotation_Sheet!$C$11:$C$30
Name A_ALL_SECTION_KEYWORDS_ISSR_208000149_13V: Ticker0001_Annotation_Sheet!$C$32:$C$39
Name A_ALL_SECTION_KEYWORDS_ISSR_208000149_Reference_Data: Ticker0001_Annotation_Sheet!$C$6:$C$7
Name A_CURRENCY_EQTY_200000801_PRI: Ticker0001_Annotation_Sheet!$E$242
Name A_CURRENCY_EQTY_200000801_PUB: Ticker0001_Annotation_Sheet!$E$241
Name A_CURRENCY_EQTY_200000801_REP: Ticker0001_Annotation_Sheet!$E$243
Name A_CURRENCY_ISSR_208000149_REP: Ticker0001_Annotation_Sheet!$E$7
Name A_ENTITY_DATA_EQTY_200000801: Ticker0001_Annotation_Sheet!$E$237:$FE$309
Name A_ENTITY_DATA_ISSR_208000149: Ticker0001_Annotation_Sheet!$E$5:$FE$235
Name A_KEYWORD_EQTY_200000801_AMER_CONVICTION: Ticker0001_Annotation_Sheet!$247:$247
Name A_KEYWORD_EQTY_200000801_AMER_LIST: Ticker0001_Annotation_Sheet!$245:$245
Name A_KEYWORD_EQTY_200000801_BETA_ANALYST: Ticker0001_Annotation_Sheet!$307:$307
Name A_KEYWORD_EQTY_200000801_BVPS: Ticker0001_Annotation_Sheet!$298:$298
Name A_KEYWORD_EQTY_200000801_BVPS_PUB: Ticker0001_Annotation_Sheet!$256:$256
Name A_KEYWORD_EQTY_200000801_CEEE_EPS: Ticker0001_Annotation_Sheet!$261:$261
Name A_KEYWORD_EQTY_200000801_CEEE_NDEBT: Ticker0001_Annotation_Sheet!$266:$266
Name A_KEYWORD_EQTY_200000801_CF_NI_PRE_PREF: Ticker0001_Annotation_Sheet!$305:$305
Name A_KEYWORD_EQTY_200000801_COMMON_DIV_PAID: Ticker0001_Annotation_Sheet!$284:$284
Name A_KEYWORD_EQTY_200000801_CURRENCY_ISO: Ticker0001_Annotation_Sheet!$243:$243
Name A_KEYWORD_EQTY_200000801_DILUTE_SHARES: Ticker0001_Annotation_Sheet!$287:$287
Name A_KEYWORD_EQTY_200000801_DPS: Ticker0001_Annotation_Sheet!$285:$285
Name A_KEYWORD_EQTY_200000801_DPS_PUB: Ticker0001_Annotation_Sheet!$257:$257
Name A_KEYWORD_EQTY_200000801_DPS_SPECIAL_PUB: Ticker0001_Annotation_Sheet!$258:$258
Name A_KEYWORD_EQTY_200000801_EBIT_PUB: Ticker0001_Annotation_Sheet!$268:$268
Name A_KEYWORD_EQTY_200000801_EBITDA_PUB: Ticker0001_Annotation_Sheet!$259:$259
Name A_KEYWORD_EQTY_200000801_EPS: Ticker0001_Annotation_Sheet!$280:$280
Name A_KEYWORD_EQTY_200000801_EPS_EX_ESO_B: Ticker0001_Annotation_Sheet!$294:$294
Name A_KEYWORD_EQTY_200000801_EPS_EX_ESO_D: Ticker0001_Annotation_Sheet!$295:$295
Name A_KEYWORD_EQTY_200000801_EPS_FUL_DIL: Ticker0001_Annotation_Sheet!$281:$281

Sheet __FDSCACHE__
B1: This sheet contains FactSet XML data for use with this workbook's =FDS codes. Modifying the worksheet's contents may damage the workbook's =FDS functionality.

Sheet Cover Sheet
I2: Company1149, Company2521 & Co.
I3: Global Investment Research
A6: Sector: Hardware and Communications Technology
A8: Company Model
A10: Company0243. (Ticker0001)
A13: Person1252 Person1255, CFA, CPA
A14: (212) 902 8618
A15: person@example.com
A31: Source: Company data, Company1150 Global Investment Research

Sheet Revenue summary
A3: Company0243. (Ticker0001)
A4: Revenue summary
A6: # weeks in the quarter | BR6: 13 | BS6: 13 | BT6: 13 | BU6: 13 | BV6: 13 | BW6: =(BW7-BV7)/7 | BX6: =(BX7-BW7)/7 | BY6: =(BY7-BX7)/7 | BZ6: =(BZ7-BY7)/7 | CA6: =(CA7-BZ7)/7 | CB6: =(CB7-CA7)/7 | CC6: =(CC7-CB7)/7 | CD6: =(CD7-CC7)/7 | ... EK6: =(EK7-EJ7)/7
A7: Quarter end date | BV7: 41636 | BW7: 41727 | BX7: 41818 | BY7: 41909 | BZ7: 42000 | CA7: 42091 | CB7: 42182 | CC7: 42273 | CD7: ='Income Statement'!CD6 | CE7: ='Income Statement'!CE6 | CF7: ='Income Statement'!CF6 | CG7: ='Income Statement'!CG6 | CH7: ='Income Statement'!CH6 | CI7: ='Income Statement'!CI6 | CJ7: ='Income Statement'!CJ6 | CK7: ='Income Statement'!CK6 | ... EK7: ='Income Statement'!EK6
B8: Q196 | C8: Q296 | D8: Q396 | E8: Q496 | F8: Q197 | G8: Q297 | H8: Q397 | I8: Q497 | J8: Q198 | K8: Q298 | L8: Q398 | M8: Q498 | N8: Q199 | O8: Q299 | P8: Q399 | Q8: Q499 | R8: Q100 | S8: Q200 | T8: Q300 | U8: Q400 | V8: Q101 | W8: Q201 | X8: Q301 | Y8: Q401 | Z8: Q102 | AA8: Q202 | AB8: Q302 | AC8: Q402 | AD8: Q103 | AE8: Q203 | AF8: Q303 | AG8: Q403 | AH8: Q104 | AI8: Q204 | AJ8: Q304 | AK8: Q404 | AL8: Q105 | AM8: Q205 | AN8: Q305 | AO8: Q405 | AP8: Q106 | AQ8: Q206 | AR8: Q306 | AS8: Q406 | AT8: Q107 | AU8: Q207 | AV8: Q307 | AW8: Q407 | AX8: Q108 | AY8: Q208 | AZ8: Q308 | BA8: Q408 | BB8: Q109 | BC8: Q209 | BD8: Q309 | BE8: Q409 | BF8: Q110 | BG8: Q210 | BH8: Q310 | BI8: Q410 | BJ8: ='Income Statement'!BJ7 | BK8: ='Income Statement'!BK7 | BL8: ='Income Statement'!BL7 | BM8: ='Income Statement'!BM7 | BN8: ='Income Statement'!BN7 | BO8: ='Income Statement'!BO7 | BP8: ='Income Statement'!BP7 | BQ8: ='Income Statement'!BQ7 | ... EK8: ='Income Statement'!EK7 | FF8: FISCAL | GQ8: CALENDAR
A9: $, millions | B9: 35064 | C9: 35155 | D9: 35246 | E9: 35338 | F9: 35430 | G9: 35520 | H9: 35611 | I9: 35703 | J9: 35795 | K9: 35885 | L9: 35976 | M9: 36068 | N9: 36160 | O9: 36250 | P9: 36341 | Q9: 36433 | R9: 36525 | S9: 36616 | T9: 36707 | U9: 36799 | V9: 36891 | W9: 36981 | X9: 37072 | Y9: 37164 | Z9: 37256 | AA9: 37346 | AB9: 37437 | AC9: 37529 | AD9: 37621 | AE9: 37711 | AF9: 37802 | AG9: 37894 | AH9: 37986 | AI9: 38077 | AJ9: 38168 | AK9: 38260 | AL9: 38352 | AM9: 38442 | AN9: 38533 | AO9: 38625 | AP9: 38717 | AQ9: 38807 | AR9: 38898 | AS9: 38990 | AT9: 39082 | AU9: 39172 | AV9: 39263 | AW9: 39355 | AX9: 39447 | AY9: 39538 | AZ9: 39629 | BA9: 39721 | BB9: 39813 | BC9: 39903 | BD9: 39994 | BE9: 40086 | BF9: 40178 | BG9: 40268 | BH9: 40359 | BI9: 40451 | BJ9: 40543 | BK9: 40633 | BL9: 40724 | BM9: 40816 | BN9: 40908 | BO9: 40999 | BP9: 41090 | BQ9: 41182 | BR9: 41274 | BS9: 41364 | BT9: 41455 | BU9: 41547 | BV9: 41639 | BW9: 41729 | BX9: 41820 | BY9: 41912 | BZ9: ='Income Statement'!BZ8 | CA9: ='Income Statement'!CA8 | CB9: ='Income Statement'!CB8 | CC9: ='Income Statement'!CC8 | CD9: ='Income Statement'!CD8 | CE9: ='Income Statement'!CE8 | CF9: ='Income Statement'!CF8 | CG9: ='Income Statement'!CG8 | ... EK9: ='Income Statement'!EK8 | EM9: 1996 | EN9: 1997 | EO9: 1998 | EP9: 1999 | EQ9: 2000 | ER9: 2001 | ES9: 2002 | ET9: 2003 | EU9: 2004 | EV9: 2005 | EW9: 2006 | EX9: 2007 | EY9: 2008 | EZ9: 2009 | FA9: 2010 | FB9: 2011 | FC9: 2012 | FD9: FY'2013 | FE9: ='Income Statement'!FE8 | FF9: ='Income Statement'!FF8 | FG9: ='Income Statement'!FG8 | FH9: ='Income Statement'!FH8 | FI9: ='Income Statement'!FI8 | FJ9: ='Income Statement'!FJ8 | FK9: ='Income Statement'!FK8 | FL9: ='Income Statement'!FL8 | ... FU9: ='Income Statement'!FU8 | FX9: 1996 | FY9: 1997 | FZ9: 1998 | GA9: 1999 | GB9: 2000 | GC9: 2001 | GD9: 2002 | GE9: 2003 | GF9: 2004 | GG9: 2005 | GH9: 2006 | GI9: 2007 | GJ9: 2008 | GK9: 2009 | GL9: 2010 | GM9: 2011 | GN9: 2012 | GO9: 2013 | GP9: ='Income Statement'!GO8 | GQ9: ='Income Statement'!GP8 | GR9: ='Income Statement'!GQ8 | GS9: ='Income Statement'!GR8 | GT9: ='Income Statement'!GS8 | GU9: ='Income Statement'!GT8 | GV9: ='Income Statement'!GU8 | GW9: ='Income Statement'!GV8 | ... HE9: ='Income Statement'!HD8
A10: Segments: | BV10: <--Accounting change in FQ1'19. Segment level #s below are estimates until FQ4'17, Company0242 restated FY18 and beyond numbers, do not compare to FY12 and prior numbers | GS10: Segment level numbers not comparable to CY18 and beyond numbers due to accounting change-->
A11: Product0489 | AV11: ='Segment - Products'!AV194 | AW11: ='Segment - Products'!AW194 | AX11: ='Segment - Products'!AX194 | AY11: ='Segment - Products'!AY194 | AZ11: ='Segment - Products'!AZ194 | BA11: ='Segment - Products'!BA194 | BB11: ='Segment - Products'!BB194 | BC11: ='Segment - Products'!BC194 | ... BU11: ='Segment - Products'!BU194 | BV11: ='Segment - Products'!BV11 | BW11: ='Segment - Products'!BW11 | BX11: ='Segment - Products'!BX11 | BY11: ='Segment - Products'!BY11 | BZ11: ='Segment - Products'!BZ11 | CA11: ='Segment - Products'!CA11 | CB11: ='Segment - Products'!CB11 | CC11: ='Segment - Products'!CC11 | ... DD11: ='Segment - Products'!DD11 | DE11: 42626 | DF11: 65775 | DG11: 51334 | DH11: 39669 | DI11: 43805 | DJ11: 69702 | DK11: 45963 | DL11: 39296 | DM11: 46222 | DN11: 69138 | DO11: 46841 | DP11: 44582 | DQ11: ='Segment - Products'!DQ11 | DR11: ='Segment - Products'!DR11 | DS11: ='Segment - Products'!DS11 | DT11: ='Segment - Products'!DT11 | DU11: ='Segment - Products'!DU11 | DV11: ='Segment - Products'!DV11 | DW11: ='Segment - Products'!DW11 | DX11: ='Segment - Products'!DX11 | ... EK11: ='Segment - Products'!EK11 | EX11: =SUM(AT11:AW11) | EY11: =SUM(AX11:BA11) | EZ11: =SUM(BB11:BE11) | FA11: =SUM(BF11:BI11) | FB11: =SUM(BJ11:BM11) | FC11: =SUM(BN11:BQ11) | FD11: =SUM(BR11:BU11) | FE11: =SUM(BV11:BY11) | FF11: =SUM(BZ11:CC11) | FG11: =SUM(CD11:CG11) | FH11: 139337 | FI11: =SUM(CL11:CO11) | FJ11: =SUM(CP11:CS11) | FK11: =SUM(CT11:CW11) | FL11: =SUM(CX11:DA11) | FM11: =SUM(DB11:DE11) | FN11: =SUM(DF11:DI11) | FO11: =SUM(DJ11:DM11) | FP11: =SUM(DN11:DQ11) | FQ11: =SUM(DR11:DU11) | FR11: =SUM(DV11:DY11) | FS11: =SUM(DZ11:EC11) | FT11: =SUM(ED11:EG11) | FU11: =SUM(EH11:EK11) | GI11: =SUM(AU11:AX11) | GJ11: =SUM(AY11:BB11) | GK11: =SUM(BC11:BF11) | GL11: =SUM(BG11:BJ11) | GM11: =SUM(BK11:BN11) | GN11: =SUM(BO11:BR11) | GO11: =SUM(BS11:BV11) | GP11: =SUM(BW11:BZ11) | GQ11: =SUM(CA11:CD11) | GR11: =SUM(CE11:CH11) | GS11: =SUM(CI11:CL11) | GT11: =SUM(CM11:CP11) | GU11: =SUM(CQ11:CT11) | GV11: =SUM(CU11:CX11) | GW11: =SUM(CY11:DB11) | GX11: =SUM(DC11:DF11) | GY11: =SUM(DG11:DJ11) | GZ11: =SUM(DK11:DN11) | HA11: =SUM(DO11:DR11) | HB11: =SUM(DS11:DV11) | HC11: =SUM(DW11:DZ11) | HD11: =SUM(EA11:ED11) | HE11: =SUM(EE11:EH11)
A12: Mac | AT12: ='Segment - Products'!AT196 | AU12: ='Segment - Products'!AU196 | AV12: ='Segment - Products'!AV196 | AW12: ='Segment - Products'!AW196 | AX12: ='Segment - Products'!AX196 | AY12: ='Segment - Products'!AY196 | AZ12: ='Segment - Products'!AZ196 | BA12: ='Segment - Products'!BA196 | ... BU12: ='Segment - Products'!BU196 | BV12: ='Segment - Products'!BV12 | BW12: ='Segment - Products'!BW12 | BX12: ='Segment - Products'!BX12 | BY12: ='Segment - Products'!BY12 | BZ12: ='Segment - Products'!BZ12 | CA12: ='Segment - Products'!CA12 | CB12: ='Segment - Products'!CB12 | CC12: ='Segment - Products'!CC12 | ... DD12: ='Segment - Products'!DD12 | DE12: 11508 | DF12: 7735 | DG12: 7168 | DH12: 6840 | DI12: 7614 | DJ12: 7780 | DK12: 7451 | DL12: 7009 | DM12: 7744 | DN12: 8987 | DO12: 7949 | DP12: 8046 | DQ12: ='Segment - Products'!DQ12 | DR12: ='Segment - Products'!DR12 | DS12: ='Segment - Products'!DS12 | DT12: ='Segment - Products'!DT12 | DU12: ='Segment - Products'!DU12 | DV12: ='Segment - Products'!DV12 | DW12: ='Segment - Products'!DW12 | DX12: ='Segment - Products'!DX12 | ... EK12: ='Segment - Products'!EK12 | EX12: =SUM(AT12:AW12) | EY12: =SUM(AX12:BA12) | EZ12: =SUM(BB12:BE12) | FA12: =SUM(BF12:BI12) | FB12: =SUM(BJ12:BM12) | FC12: =SUM(BN12:BQ12) | FD12: =SUM(BR12:BU12) | FE12: =SUM(BV12:BY12) | FF12: =SUM(BZ12:CC12) | FG12: =SUM(CD12:CG12) | FH12: 25569 | FI12: =SUM(CL12:CO12) | FJ12: =SUM(CP12:CS12) | FK12: =SUM(CT12:CW12) | FL12: =SUM(CX12:DA12) | FM12: =SUM(DB12:DE12) | FN12: =SUM(DF12:DI12) | FO12: =SUM(DJ12:DM12) | FP12: =SUM(DN12:DQ12) | FQ12: =SUM(DR12:DU12) | FR12: =SUM(DV12:DY12) | FS12: =SUM(DZ12:EC12) | FT12: =SUM(ED12:EG12) | FU12: =SUM(EH12:EK12) | GI12: =SUM(AU12:AX12) | GJ12: =SUM(AY12:BB12) | GK12: =SUM(BC12:BF12) | GL12: =SUM(BG12:BJ12) | GM12: =SUM(BK12:BN12) | GN12: =SUM(BO12:BR12) | GO12: =SUM(BS12:BV12) | GP12: =SUM(BW12:BZ12) | GQ12: =SUM(CA12:CD12) | GR12: =SUM(CE12:CH12) | GS12: =SUM(CI12:CL12) | GT12: =SUM(CM12:CP12) | GU12: =SUM(CQ12:CT12) | GV12: =SUM(CU12:CX12) | GW12: =SUM(CY12:DB12) | GX12: =SUM(DC12:DF12) | GY12: =SUM(DG12:DJ12) | GZ12: =SUM(DK12:DN12) | HA12: =SUM(DO12:DR12) | HB12: =SUM(DS12:DV12) | HC12: =SUM(DW12:DZ12) | HD12: =SUM(EA12:ED12) | HE12: =SUM(EE12:EH12)
A13: Product0487 | AV13: ='Segment - Products'!AV195 | AW13: ='Segment - Products'!AW195 | AX13: ='Segment - Products'!AX195 | AY13: ='Segment - Products'!AY195 | AZ13: ='Segment - Products'!AZ195 | BA13: ='Segment - Products'!BA195 | BB13: ='Segment - Products'!BB195 | BC13: ='Segment - Products'!BC195 | ... BU13: ='Segment - Products'!BU195 | BV13: ='Segment - Products'!BV13 | BW13: ='Segment - Products'!BW13 | BX13: ='Segment - Products'!BX13 | BY13: ='Segment - Products'!BY13 | BZ13: ='Segment - Products'!BZ13 | CA13: ='Segment - Products'!CA13 | CB13: ='Segment - Products'!CB13 | CC13: ='Segment - Products'!CC13 | ... DD13: ='Segment - Products'!DD13 | DE13: 7174 | DF13: 9396 | DG13: 6670 | DH13: 5791 | DI13: 6443 | DJ13: 7023 | DK13: 5559 | DL13: 7162 | DM13: 6950 | DN13: 8088 | DO13: 6402 | DP13: 6581 | DQ13: ='Segment - Products'!DQ13 | DR13: ='Segment - Products'!DR13 | DS13: ='Segment - Products'!DS13 | DT13: ='Segment - Products'!DT13 | DU13: ='Segment - Products'!DU13 | DV13: ='Segment - Products'!DV13 | DW13: ='Segment - Products'!DW13 | DX13: ='Segment - Products'!DX13 | ... EK13: ='Segment - Products'!EK13 | EX13: =SUM(AT13:AW13) | EY13: =SUM(AX13:BA13) | EZ13: =SUM(BB13:BE13) | FA13: =SUM(BF13:BI13) | FB13: =SUM(BJ13:BM13) | FC13: =SUM(BN13:BQ13) | FD13: =SUM(BR13:BU13) | FE13: =SUM(BV13:BY13) | FF13: =SUM(BZ13:CC13) | FG13: =SUM(CD13:CG13) | FH13: 18802 | FI13: =SUM(CL13:CO13) | FJ13: =SUM(CP13:CS13) | FK13: =SUM(CT13:CW13) | FL13: =SUM(CX13:DA13) | FM13: =SUM(DB13:DE13) | FN13: =SUM(DF13:DI13) | FO13: =SUM(DJ13:DM13) | FP13: =SUM(DN13:DQ13) | FQ13: =SUM(DR13:DU13) | FR13: =SUM(DV13:DY13) | FS13: =SUM(DZ13:EC13) | FT13: =SUM(ED13:EG13) | FU13: =SUM(EH13:EK13) | GI13: =SUM(AU13:AX13) | GJ13: =SUM(AY13:BB13) | GK13: =SUM(BC13:BF13) | GL13: =SUM(BG13:BJ13) | GM13: =SUM(BK13:BN13) | GN13: =SUM(BO13:BR13) | GO13: =SUM(BS13:BV13) | GP13: =SUM(BW13:BZ13) | GQ13: =SUM(CA13:CD13) | GR13: =SUM(CE13:CH13) | GS13: =SUM(CI13:CL13) | GT13: =SUM(CM13:CP13) | GU13: =SUM(CQ13:CT13) | GV13: =SUM(CU13:CX13) | GW13: =SUM(CY13:DB13) | GX13: =SUM(DC13:DF13) | GY13: =SUM(DG13:DJ13) | GZ13: =SUM(DK13:DN13) | HA13: =SUM(DO13:DR13) | HB13: =SUM(DS13:DV13) | HC13: =SUM(DW13:DZ13) | HD13: =SUM(EA13:ED13) | HE13: =SUM(EE13:EH13)
A14: Wearables, Home and Accessories | AT14: ='Segment - Products'!AT197 | AU14: ='Segment - Products'!AU197 | AV14: ='Segment - Products'!AV197 | AW14: ='Segment - Products'!AW197 | AX14: ='Segment - Products'!AX197 | AY14: ='Segment - Products'!AY197 | AZ14: ='Segment - Products'!AZ197 | BA14: ='Segment - Products'!BA197 | ... BU14: ='Segment - Products'!BU197 | BV14: ='Segment - Products'!BV14 | BW14: ='Segment - Products'!BW14 | BX14: ='Segment - Products'!BX14 | BY14: ='Segment - Products'!BY14 | BZ14: ='Segment - Products'!BZ14 | CA14: ='Segment - Products'!CA14 | CB14: ='Segment - Products'!CB14 | CC14: ='Segment - Products'!CC14 | ... DD14: ='Segment - Products'!DD14 | DE14: 9650 | DF14: 13482 | DG14: 8757 | DH14: 8284 | DI14: 9322 | DJ14: 11953 | DK14: 7913 | DL14: 8097 | DM14: 9042 | DN14: 11747 | DO14: 7522 | DP14: 7404 | DQ14: ='Segment - Products'!DQ14 | DR14: ='Segment - Products'!DR14 | DS14: ='Segment - Products'!DS14 | DT14: ='Segment - Products'!DT14 | DU14: ='Segment - Products'!DU14 | DV14: ='Segment - Products'!DV14 | DW14: ='Segment - Products'!DW14 | DX14: ='Segment - Products'!DX14 | ... EK14: ='Segment - Products'!EK14 | EX14: =SUM(AT14:AW14) | EY14: =SUM(AX14:BA14) | EZ14: =SUM(BB14:BE14) | FA14: =SUM(BF14:BI14) | FB14: =SUM(BJ14:BM14) | FC14: =SUM(BN14:BQ14) | FD14: =SUM(BR14:BU14) | FE14: =SUM(BV14:BY14) | FF14: =SUM(BZ14:CC14) | FG14: =SUM(CD14:CG14) | FH14: 12826 | FI14: =SUM(CL14:CO14) | FJ14: =SUM(CP14:CS14) | FK14: =SUM(CT14:CW14) | FL14: =SUM(CX14:DA14) | FM14: =SUM(DB14:DE14) | FN14: =SUM(DF14:DI14) | FO14: =SUM(DJ14:DM14) | FP14: =SUM(DN14:DQ14) | FQ14: =SUM(DR14:DU14) | FR14: =SUM(DV14:DY14) | FS14: =SUM(DZ14:EC14) | FT14: =SUM(ED14:EG14) | FU14: =SUM(EH14:EK14) | GI14: =SUM(AU14:AX14) | GJ14: =SUM(AY14:BB14) | GK14: =SUM(BC14:BF14) | GL14: =SUM(BG14:BJ14) | GM14: =SUM(BK14:BN14) | GN14: =SUM(BO14:BR14) | GO14: =SUM(BS14:BV14) | GP14: =SUM(BW14:BZ14) | GQ14: =SUM(CA14:CD14) | GR14: =SUM(CE14:CH14) | GS14: =SUM(CI14:CL14) | GT14: =SUM(CM14:CP14) | GU14: =SUM(CQ14:CT14) | GV14: =SUM(CU14:CX14) | GW14: =SUM(CY14:DB14) | GX14: =SUM(DC14:DF14) | GY14: =SUM(DG14:DJ14) | GZ14: =SUM(DK14:DN14) | HA14: =SUM(DO14:DR14) | HB14: =SUM(DS14:DV14) | HC14: =SUM(DW14:DZ14) | HD14: =SUM(EA14:ED14) | HE14: =SUM(EE14:EH14)
A15: Products | AT15: =SUM(AT11:AT14) | AU15: =SUM(AU11:AU14) | AV15: =SUM(AV11:AV14) | AW15: =SUM(AW11:AW14) | AX15: =SUM(AX11:AX14) | AY15: =SUM(AY11:AY14) | AZ15: =SUM(AZ11:AZ14) | BA15: =SUM(BA11:BA14) | ... EK15: =SUM(EK11:EK14) | EX15: =SUM(AT15:AW15) | EY15: =SUM(AX15:BA15) | EZ15: =SUM(BB15:BE15) | FA15: =SUM(BF15:BI15) | FB15: =SUM(BJ15:BM15) | FC15: =SUM(BN15:BQ15) | FD15: =SUM(BR15:BU15) | FE15: =SUM(BV15:BY15) | FF15: =SUM(BZ15:CC15) | FG15: =SUM(CD15:CG15) | FH15: =SUM(FH11:FH14) | FI15: =SUM(CL15:CO15) | FJ15: =SUM(CP15:CS15) | FK15: =SUM(CT15:CW15) | FL15: =SUM(CX15:DA15) | FM15: =SUM(DB15:DE15) | FN15: =SUM(DF15:DI15) | FO15: =SUM(DJ15:DM15) | FP15: =SUM(DN15:DQ15) | FQ15: =SUM(DR15:DU15) | FR15: =SUM(DV15:DY15) | FS15: =SUM(DZ15:EC15) | FT15: =SUM(ED15:EG15) | FU15: =SUM(EH15:EK15) | GI15: =SUM(AU15:AX15) | GJ15: =SUM(AY15:BB15) | GK15: =SUM(BC15:BF15) | GL15: =SUM(BG15:BJ15) | GM15: =SUM(BK15:BN15) | GN15: =SUM(BO15:BR15) | GO15: =SUM(BS15:BV15) | GP15: =SUM(BW15:BZ15) | GQ15: =SUM(CA15:CD15) | GR15: =SUM(CE15:CH15) | GS15: =SUM(CI15:CL15) | GT15: =SUM(CM15:CP15) | GU15: =SUM(CQ15:CT15) | GV15: =SUM(CU15:CX15) | GW15: =SUM(CY15:DB15) | GX15: =SUM(DC15:DF15) | GY15: =SUM(DG15:DJ15) | GZ15: =SUM(DK15:DN15) | HA15: =SUM(DO15:DR15) | HB15: =SUM(DS15:DV15) | HC15: =SUM(DW15:DZ15) | HD15: =SUM(EA15:ED15) | HE15: =SUM(EE15:EH15)
A16: Services | AT16: =AT17-AT15 | AU16: =AU17-AU15 | AV16: =AV17-AV15 | AW16: =AW17-AW15 | AX16: =AX17-AX15 | AY16: =AY17-AY15 | AZ16: =AZ17-AZ15 | BA16: =BA17-BA15 | ... CK16: =CK17-CK15 | CL16: ='Segment - Services'!CL21 | CM16: ='Segment - Services'!CM21 | CN16: ='Segment - Services'!CN21 | CO16: ='Segment - Services'!CO21 | CP16: ='Segment - Services'!CP21 | CQ16: ='Segment - Services'!CQ21 | CR16: ='Segment - Services'!CR21 | CS16: ='Segment - Services'!CS21 | ... DD16: ='Segment - Services'!DD21 | DE16: 19188 | DF16: 20766 | DG16: 20907 | DH16: 21213 | DI16: 22314 | DJ16: 23117 | DK16: 23867 | DL16: 24213 | DM16: 24972 | DN16: 26340 | DO16: 26645 | DP16: 27423 | DQ16: ='Segment - Services'!DQ21 | DR16: ='Segment - Services'!DR21 | DS16: ='Segment - Services'!DS21 | DT16: ='Segment - Services'!DT21 | DU16: ='Segment - Services'!DU21 | DV16: ='Segment - Services'!DV21 | DW16: ='Segment - Services'!DW21 | DX16: ='Segment - Services'!DX21 | ... EK16: ='Segment - Services'!EK21 | EX16: =SUM(AT16:AW16) | EY16: =SUM(AX16:BA16) | EZ16: =SUM(BB16:BE16) | FA16: =SUM(BF16:BI16) | FB16: =SUM(BJ16:BM16) | FC16: =SUM(BN16:BQ16) | FD16: =SUM(BR16:BU16) | FE16: =SUM(BV16:BY16) | FF16: =SUM(BZ16:CC16) | FG16: =SUM(CD16:CG16) | FH16: 32700 | FI16: =SUM(CL16:CO16) | FJ16: =SUM(CP16:CS16) | FK16: =SUM(CT16:CW16) | FL16: =SUM(CX16:DA16) | FM16: =SUM(DB16:DE16) | FN16: =SUM(DF16:DI16) | FO16: =SUM(DJ16:DM16) | FP16: =SUM(DN16:DQ16) | FQ16: =SUM(DR16:DU16) | FR16: =SUM(DV16:DY16) | FS16: =SUM(DZ16:EC16) | FT16: =SUM(ED16:EG16) | FU16: =SUM(EH16:EK16) | GI16: =SUM(AU16:AX16) | GJ16: =SUM(AY16:BB16) | GK16: =SUM(BC16:BF16) | GL16: =SUM(BG16:BJ16) | GM16: =SUM(BK16:BN16) | GN16: =SUM(BO16:BR16) | GO16: =SUM(BS16:BV16) | GP16: =SUM(BW16:BZ16) | GQ16: =SUM(CA16:CD16) | GR16: =SUM(CE16:CH16) | GS16: =SUM(CI16:CL16) | GT16: =SUM(CM16:CP16) | GU16: =SUM(CQ16:CT16) | GV16: =SUM(CU16:CX16) | GW16: =SUM(CY16:DB16) | GX16: =SUM(DC16:DF16) | GY16: =SUM(DG16:DJ16) | GZ16: =SUM(DK16:DN16) | HA16: =SUM(DO16:DR16) | HB16: =SUM(DS16:DV16) | HC16: =SUM(DW16:DZ16) | HD16: =SUM(EA16:ED16) | HE16: =SUM(EE16:EH16)
A17: Total revenue | J17: ='Income Statement'!J9 | K17: ='Income Statement'!K9 | L17: ='Income Statement'!L9 | M17: ='Income Statement'!M9 | N17: ='Income Statement'!N9 | O17: ='Income Statement'!O9 | P17: ='Income Statement'!P9 | Q17: ='Income Statement'!Q9 | ... CG17: ='Income Statement'!CG9 | CH17: 78351 | CI17: 52896 | CJ17: 45408 | CK17: 52579 | CL17: =CL15+CL16 | CM17: =CM15+CM16 | CN17: =CN15+CN16 | CO17: =CO15+CO16 | CP17: =CP15+CP16 | CQ17: =CQ15+CQ16 | CR17: =CR15+CR16 | CS17: =CS15+CS16 | ... EK17: =EK15+EK16 | EO17: =SUM(J17:M17) | EP17: =SUM(N17:Q17) | EQ17: =SUM(R17:U17) | ER17: =SUM(V17:Y17) | ES17: =SUM(Z17:AC17) | ET17: =SUM(AD17:AG17) | EU17: =SUM(AI17:AL17) | EV17: =SUM(AM17:AP17) | EW17: =SUM(AQ17:AT17) | EX17: =SUM(AT17:AW17) | EY17: =SUM(AX17:BA17) | EZ17: =SUM(BB17:BE17) | FA17: =SUM(BF17:BI17) | FB17: =SUM(BJ17:BM17) | FC17: =SUM(BN17:BQ17) | FD17: =SUM(BR17:BU17) | FE17: =SUM(BV17:BY17) | FF17: =SUM(BZ17:CC17) | FG17: =SUM(CD17:CG17) | FH17: =FH15+FH16 | FI17: =SUM(CL17:CO17) | FJ17: =SUM(CP17:CS17) | FK17: =SUM(CT17:CW17) | FL17: =SUM(CX17:DA17) | FM17: =SUM(DB17:DE17) | FN17: =SUM(DF17:DI17) | FO17: =SUM(DJ17:DM17) | FP17: =SUM(DN17:DQ17) | FQ17: =SUM(DR17:DU17) | FR17: =SUM(DV17:DY17) | FS17: =SUM(DZ17:EC17) | FT17: =SUM(ED17:EG17) | FU17: =SUM(EH17:EK17) | FY17: =SUM(G17:J17) | FZ17: =SUM(K17:N17) | GA17: =SUM(O17:R17) | GB17: =SUM(S17:V17) | GC17: =SUM(W17:Z17) | GD17: =SUM(AA17:AD17) | GE17: =SUM(AE17:AH17) | GF17: =SUM(AI17:AL17) | GG17: =SUM(AM17:AP17) | GH17: =SUM(AQ17:AT17) | GI17: =SUM(AU17:AX17) | GJ17: =SUM(AY17:BB17) | GK17: =SUM(BC17:BF17) | GL17: =SUM(BG17:BJ17) | GM17: =SUM(BK17:BN17) | GN17: =SUM(BO17:BR17) | GO17: =SUM(BS17:BV17) | GP17: =SUM(BW17:BZ17) | GQ17: =SUM(CA17:CD17) | GR17: =SUM(CE17:CH17) | GS17: =SUM(CI17:CL17) | GT17: =SUM(CM17:CP17) | GU17: =SUM(CQ17:CT17) | GV17: =SUM(CU17:CX17) | GW17: =SUM(CY17:DB17) | GX17: =SUM(DC17:DF17) | GY17: =SUM(DG17:DJ17) | GZ17: =SUM(DK17:DN17) | HA17: =SUM(DO17:DR17) | HB17: =SUM(DS17:DV17) | HC17: =SUM(DW17:DZ17) | HD17: =SUM(EA17:ED17) | HE17: =SUM(EE17:EH17)
A19: Year-over-year change (%) | B19: =B$8 | C19: =C$8 | D19: =D$8 | E19: =E$8 | F19: =F$8 | G19: =G$8 | H19: =H$8 | I19: =I$8 | ... EK19: =EK$8 | EN19: =EN$9 | EO19: =EO$9 | EP19: =EP$9 | EQ19: =EQ$9 | ER19: =ER$9 | ES19: =ES$9 | ET19: =ET$9 | EU19: =EU$9 | ... FU19: =FU$9 | FX19: =FX$9 | FY19: =FY$9 | FZ19: =FZ$9 | GA19: =GA$9 | GB19: =GB$9 | GC19: =GC$9 | GD19: =GD$9 | GE19: =GE$9 | ... HE19: =HE$9
A20: Product0489 | AZ20: =+AZ11/AV11-1 | BA20: =+BA11/AW11-1 | BB20: =+BB11/AX11-1 | BC20: =+BC11/AY11-1 | BD20: =+BD11/AZ11-1 | BE20: =+BE11/BA11-1 | BF20: =+BF11/BB11-1 | BG20: =+BG11/BC11-1 | ... EK20: =+EK11/EG11-1 | EY20: =+EY11/EX11-1 | EZ20: =+EZ11/EY11-1 | FA20: =+FA11/EZ11-1 | FB20: =+FB11/FA11-1 | FC20: =+FC11/FB11-1 | FD20: =+FD11/FC11-1 | FE20: =+FE11/FD11-1 | FF20: =+FF11/FE11-1 | FG20: =+FG11/FF11-1 | FI20: =+FI11/FH11-1 | FJ20: =+FJ11/FI11-1 | FK20: =+FK11/FJ11-1 | FL20: =+FL11/FK11-1 | FM20: =+FM11/FL11-1 | FN20: =+FN11/FM11-1 | FO20: =+FO11/FN11-1 | FP20: =+FP11/FO11-1 | ... FU20: =+FU11/FT11-1 | GJ20: =+GJ11/GI11-1 | GK20: =+GK11/GJ11-1 | GL20: =+GL11/GK11-1 | GM20: =+GM11/GL11-1 | GN20: =+GN11/GM11-1 | GO20: =+GO11/GN11-1 | GP20: =+GP11/GO11-1 | GQ20: =+GQ11/GP11-1 | ... HE20: =+HE11/HD11-1
A21: Mac | AX21: =+AX12/AT12-1 | AY21: =+AY12/AU12-1 | AZ21: =+AZ12/AV12-1 | BA21: =+BA12/AW12-1 | BB21: =+BB12/AX12-1 | BC21: =+BC12/AY12-1 | BD21: =+BD12/AZ12-1 | BE21: =+BE12/BA12-1 | ... EK21: =+EK12/EG12-1 | EY21: =+EY12/EX12-1 | EZ21: =+EZ12/EY12-1 | FA21: =+FA12/EZ12-1 | FB21: =+FB12/FA12-1 | FC21: =+FC12/FB12-1 | FD21: =+FD12/FC12-1 | FE21: =+FE12/FD12-1 | FF21: =+FF12/FE12-1 | FG21: =+FG12/FF12-1 | FI21: =+FI12/FH12-1 | FJ21: =+FJ12/FI12-1 | FK21: =+FK12/FJ12-1 | FL21: =+FL12/FK12-1 | FM21: =+FM12/FL12-1 | FN21: =+FN12/FM12-1 | FO21: =+FO12/FN12-1 | FP21: =+FP12/FO12-1 | ... FU21: =+FU12/FT12-1 | GJ21: =+GJ12/GI12-1 | GK21: =+GK12/GJ12-1 | GL21: =+GL12/GK12-1 | GM21: =+GM12/GL12-1 | GN21: =+GN12/GM12-1 | GO21: =+GO12/GN12-1 | GP21: =+GP12/GO12-1 | GQ21: =+GQ12/GP12-1 | ... HE21: =+HE12/HD12-1
A22: Product0487 | BZ22: =+BZ13/BV13-1 | CA22: =+CA13/BW13-1 | CB22: =+CB13/BX13-1 | CC22: =+CC13/BY13-1 | CD22: =+CD13/BZ13-1 | CE22: =+CE13/CA13-1 | CF22: =+CF13/CB13-1 | CG22: =+CG13/CC13-1 | ... EK22: =+EK13/EG13-1 | FE22: =+FE13/FD13-1 | FF22: =+FF13/FE13-1 | FG22: =+FG13/FF13-1 | FI22: =+FI13/FH13-1 | FJ22: =+FJ13/FI13-1 | FK22: =+FK13/FJ13-1 | FL22: =+FL13/FK13-1 | FM22: =+FM13/FL13-1 | FN22: =+FN13/FM13-1 | FO22: =+FO13/FN13-1 | FP22: =+FP13/FO13-1 | ... FU22: =+FU13/FT13-1 | GM22: =+GM13/GL13-1 | GN22: =+GN13/GM13-1 | GO22: =+GO13/GN13-1 | GP22: =+GP13/GO13-1 | GQ22: =+GQ13/GP13-1 | GR22: =+GR13/GQ13-1 | GS22: =+GS13/GR13-1 | GT22: =+GT13/GS13-1 | ... HE22: =+HE13/HD13-1
A23: Wearables, Home and Accessories | AX23: =+AX14/AT14-1 | AY23: =+AY14/AU14-1 | AZ23: =+AZ14/AV14-1 | BA23: =+BA14/AW14-1 | BB23: =+BB14/AX14-1 | BC23: =+BC14/AY14-1 | BD23: =+BD14/AZ14-1 | BE23: =+BE14/BA14-1 | ... EK23: =+EK14/EG14-1 | EY23: =+EY14/EX14-1 | EZ23: =+EZ14/EY14-1 | FA23: =+FA14/EZ14-1 | FB23: =+FB14/FA14-1 | FC23: =+FC14/FB14-1 | FD23: =+FD14/FC14-1 | FE23: =+FE14/FD14-1 | FF23: =+FF14/FE14-1 | FG23: =+FG14/FF14-1 | FI23: =+FI14/FH14-1 | FJ23: =+FJ14/FI14-1 | FK23: =+FK14/FJ14-1 | FL23: =+FL14/FK14-1 | FM23: =+FM14/FL14-1 | FN23: =+FN14/FM14-1 | FO23: =+FO14/FN14-1 | FP23: =+FP14/FO14-1 | ... FU23: =+FU14/FT14-1 | GJ23: =+GJ14/GI14-1 | GK23: =+GK14/GJ14-1 | GL23: =+GL14/GK14-1 | GM23: =+GM14/GL14-1 | GN23: =+GN14/GM14-1 | GO23: =+GO14/GN14-1 | GP23: =+GP14/GO14-1 | GQ23: =+GQ14/GP14-1 | ... HE23: =+HE14/HD14-1
A24: Products | AX24: =+AX15/AT15-1 | AY24: =+AY15/AU15-1 | AZ24: =+AZ15/AV15-1 | BA24: =+BA15/AW15-1 | BB24: =+BB15/AX15-1 | BC24: =+BC15/AY15-1 | BD24: =+BD15/AZ15-1 | BE24: =+BE15/BA15-1 | ... EK24: =+EK15/EG15-1 | EY24: =+EY15/EX15-1 | EZ24: =+EZ15/EY15-1 | FA24: =+FA15/EZ15-1 | FB24: =+FB15/FA15-1 | FC24: =+FC15/FB15-1 | FD24: =+FD15/FC15-1 | FE24: =+FE15/FD15-1 | FF24: =+FF15/FE15-1 | FG24: =+FG15/FF15-1 | FI24: =+FI15/FH15-1 | FJ24: =+FJ15/FI15-1 | FK24: =+FK15/FJ15-1 | FL24: =+FL15/FK15-1 | FM24: =+FM15/FL15-1 | FN24: =+FN15/FM15-1 | FO24: =+FO15/FN15-1 | FP24: =+FP15/FO15-1 | ... FU24: =+FU15/FT15-1 | GJ24: =+GJ15/GI15-1 | GK24: =+GK15/GJ15-1 | GL24: =+GL15/GK15-1 | GM24: =+GM15/GL15-1 | GN24: =+GN15/GM15-1 | GO24: =+GO15/GN15-1 | GP24: =+GP15/GO15-1 | GQ24: =+GQ15/GP15-1 | ... HE24: =+HE15/HD15-1
A25: Services | AX25: =+AX16/AT16-1 | AY25: =+AY16/AU16-1 | AZ25: =+AZ16/AV16-1 | BA25: =+BA16/AW16-1 | BB25: =+BB16/AX16-1 | BC25: =+BC16/AY16-1 | BD25: =+BD16/AZ16-1 | BE25: =+BE16/BA16-1 | ... CN25: =+CN16/CJ16-1 | CO25: 0.245 | CP25: =+CP16/CL16-1 | CQ25: =+CQ16/CM16-1 | CR25: =+CR16/CN16-1 | CS25: =+CS16/CO16-1 | CT25: =+CT16/CP16-1 | CU25: =+CU16/CQ16-1 | CV25: =+CV16/CR16-1 | CW25: =+CW16/CS16-1 | ... EK25: =+EK16/EG16-1 | EY25: =+EY16/EX16-1 | EZ25: =+EZ16/EY16-1 | FA25: =+FA16/EZ16-1 | FB25: =+FB16/FA16-1 | FC25: =+FC16/FB16-1 | FD25: =+FD16/FC16-1 | FE25: =+FE16/FD16-1 | FF25: =+FF16/FE16-1 | FG25: =+FG16/FF16-1 | FI25: =+FI16/FH16-1 | FJ25: =+FJ16/FI16-1 | FK25: =+FK16/FJ16-1 | FL25: =+FL16/FK16-1 | FM25: =+FM16/FL16-1 | FN25: =+FN16/FM16-1 | FO25: =+FO16/FN16-1 | FP25: =+FP16/FO16-1 | ... FU25: =+FU16/FT16-1 | GJ25: =+GJ16/GI16-1 | GK25: =+GK16/GJ16-1 | GL25: =+GL16/GK16-1 | GM25: =+GM16/GL16-1 | GN25: =+GN16/GM16-1 | GO25: =+GO16/GN16-1 | GP25: =+GP16/GO16-1 | GQ25: =+GQ16/GP16-1 | ... HE25: =+HE16/HD16-1
A26: Total revenue | N26: =+N17/J17-1 | O26: =+O17/K17-1 | P26: =+P17/L17-1 | Q26: =+Q17/M17-1 | R26: =+R17/N17-1 | S26: =+S17/O17-1 | T26: =+T17/P17-1 | U26: =+U17/Q17-1 | ... EK26: =+EK17/EG17-1 | EP26: =+EP17/EO17-1 | EQ26: =+EQ17/EP17-1 | ER26: =+ER17/EQ17-1 | ES26: =+ES17/ER17-1 | ET26: =+ET17/ES17-1 | EU26: =+EU17/ET17-1 | EV26: =+EV17/EU17-1 | EW26: =+EW17/EV17-1 | ... FU26: =+FU17/FT17-1 | GJ26: =+GJ17/GI17-1 | GK26: =+GK17/GJ17-1 | GL26: =+GL17/GK17-1 | GM26: =+GM17/GL17-1 | GN26: =+GN17/GM17-1 | GO26: =+GO17/GN17-1 | GP26: =+GP17/GO17-1 | GQ26: =+GQ17/GP17-1 | ... HE26: =+HE17/HD17-1
A27: Forex impact | BZ27: =BZ26-BZ28 | CB27: =CB26-CB28 | CC27: =CC26-CC28 | CD27: =CD26-CD28 | CE27: =CE26-CE28 | CH27: =CH26-CH28 | CI27: =CI26-CI28 | CJ27: =CJ26-CJ28 | CO27: =-200/CK17 | CP27: =CP26-CP28 | CQ27: =-1300/CM17 | CR27: -0.03 | CS27: =-1000/CO17 | CT27: =-1000/CP17 | CU27: -0.01 | CV27: -0.03 | CW27: 0 | CX27: 0 | CY27: 0.05 | CZ27: 0.05 | DA27: =CZ27-3% | DB27: 0.01 | DC27: -0.02 | DD27: -0.032 | DE27: -0.06 | DF27: -0.08 | DG27: -0.05 | DH27: -0.04 | DI27: -0.02 | DJ27: 0 | DK27: -0.014 | DL27: -0.025 | DM27: -0.015 | DN27: 0 | DO27: -0.025 | DP27: 0 | DQ27: 0.013786601 | DR27: 0.024440998 | DS27: 0.035794557 | DT27: 0.0078554353 | DU27: -0.0015877283
A28: Constant currency revenue growth | BZ28: 0.335 | CB28: 0.405 | CC28: 0.303 | CD28: 0.08 | CE28: -0.088 | CH28: 0.05 | CI28: 0.066 | CJ28: 0.092 | CO28: =CO26-CO27 | CP28: -0.03 | CQ28: =CQ26-CQ27 | CR28: =CR26-CR27 | CS28: =CS26-CS27 | CT28: =CT26-CT27 | CU28: =CU26-CU27 | CV28: =CV26-CV27 | CW28: =CW26-CW27 | CX28: =CX26-CX27 | ... EK28: =EK26-EK27
A30: Quarter-over-quarter change (%) | B30: =B$8 | C30: =C$8 | D30: =D$8 | E30: =E$8 | F30: =F$8 | G30: =G$8 | H30: =H$8 | I30: =I$8 | ... EK30: =EK$8
A31: Product0489 | AW31: =+AW11/AV11-1 | AX31: =+AX11/AW11-1 | AY31: =+AY11/AX11-1 | AZ31: =+AZ11/AY11-1 | BA31: =+BA11/AZ11-1 | BB31: =+BB11/BA11-1 | BC31: =+BC11/BB11-1 | BD31: =+BD11/BC11-1 | ... EK31: =+EK11/EJ11-1
A32: Mac | AU32: =+AU12/AT12-1 | AV32: =+AV12/AU12-1 | AW32: =+AW12/AV12-1 | AX32: =+AX12/AW12-1 | AY32: =+AY12/AX12-1 | AZ32: =+AZ12/AY12-1 | BA32: =+BA12/AZ12-1 | BB32: =+BB12/BA12-1 | ... EK32: =+EK12/EJ12-1
A33: Product0487 | BW33: =+BW13/BV13-1 | BX33: =+BX13/BW13-1 | BY33: =+BY13/BX13-1 | BZ33: =+BZ13/BY13-1 | CA33: =+CA13/BZ13-1 | CB33: =+CB13/CA13-1 | CC33: =+CC13/CB13-1 | CD33: =+CD13/CC13-1 | ... EK33: =+EK13/EJ13-1
A34: Wearables, Home and Accessories | AU34: =+AU14/AT14-1 | AV34: =+AV14/AU14-1 | AW34: =+AW14/AV14-1 | AX34: =+AX14/AW14-1 | AY34: =+AY14/AX14-1 | AZ34: =+AZ14/AY14-1 | BA34: =+BA14/AZ14-1 | BB34: =+BB14/BA14-1 | ... EK34: =+EK14/EJ14-1
A35: Products | AU35: =+AU15/AT15-1 | AV35: =+AV15/AU15-1 | AW35: =+AW15/AV15-1 | AX35: =+AX15/AW15-1 | AY35: =+AY15/AX15-1 | AZ35: =+AZ15/AY15-1 | BA35: =+BA15/AZ15-1 | BB35: =+BB15/BA15-1 | ... EK35: =+EK15/EJ15-1
A36: Services | AU36: =+AU16/AT16-1 | AV36: =+AV16/AU16-1 | AW36: =+AW16/AV16-1 | AX36: =+AX16/AW16-1 | AY36: =+AY16/AX16-1 | AZ36: =+AZ16/AY16-1 | BA36: =+BA16/AZ16-1 | BB36: =+BB16/BA16-1 | ... EK36: =+EK16/EJ16-1
A37: Total revenue | K37: =+K17/J17-1 | L37: =+L17/K17-1 | M37: =+M17/L17-1 | N37: =+N17/M17-1 | O37: =+O17/N17-1 | P37: =+P17/O17-1 | Q37: =+Q17/P17-1 | R37: =+R17/Q17-1 | ... EK37: =+EK17/EJ17-1
A39: % of revenue | B39: =B$8 | C39: =C$8 | D39: =D$8 | E39: =E$8 | F39: =F$8 | G39: =G$8 | H39: =H$8 | I39: =I$8 | ... EK39: =EK$8 | EM39: =EM$9 | EN39: =EN$9 | EO39: =EO$9 | EP39: =EP$9 | EQ39: =EQ$9 | ER39: =ER$9 | ES39: =ES$9 | ET39: =ET$9 | ... FU39: =FU$9 | FX39: =FX$9 | FY39: =FY$9 | FZ39: =FZ$9 | GA39: =GA$9 | GB39: =GB$9 | GC39: =GC$9 | GD39: =GD$9 | GE39: =GE$9 | ... HE39: =HE$9
A40: Product0489 | AT40: =AT11/AT$17 | AU40: =AU11/AU$17 | AV40: =AV11/AV$17 | AW40: =AW11/AW$17 | AX40: =AX11/AX$17 | AY40: =AY11/AY$17 | AZ40: =AZ11/AZ$17 | BA40: =BA11/BA$17 | ... EK40: =EK11/EK$17 | EX40: =EX11/EX$17 | EY40: =EY11/EY$17 | EZ40: =EZ11/EZ$17 | FA40: =FA11/FA$17 | FB40: =FB11/FB$17 | FC40: =FC11/FC$17 | FD40: =FD11/FD$17 | FE40: =FE11/FE$17 | ... FU40: =FU11/FU$17 | GI40: =GI11/GI$17 | GJ40: =GJ11/GJ$17 | GK40: =GK11/GK$17 | GL40: =GL11/GL$17 | GM40: =GM11/GM$17 | GN40: =GN11/GN$17 | GO40: =GO11/GO$17 | GP40: =GP11/GP$17 | ... HE40: =HE11/HE$17
A41: Mac | AT41: =AT12/AT$17 | AU41: =AU12/AU$17 | AV41: =AV12/AV$17 | AW41: =AW12/AW$17 | AX41: =AX12/AX$17 | AY41: =AY12/AY$17 | AZ41: =AZ12/AZ$17 | BA41: =BA12/BA$17 | ... EK41: =EK12/EK$17 | EX41: =EX12/EX$17 | EY41: =EY12/EY$17 | EZ41: =EZ12/EZ$17 | FA41: =FA12/FA$17 | FB41: =FB12/FB$17 | FC41: =FC12/FC$17 | FD41: =FD12/FD$17 | FE41: =FE12/FE$17 | ... FU41: =FU12/FU$17 | GI41: =GI12/GI$17 | GJ41: =GJ12/GJ$17 | GK41: =GK12/GK$17 | GL41: =GL12/GL$17 | GM41: =GM12/GM$17 | GN41: =GN12/GN$17 | GO41: =GO12/GO$17 | GP41: =GP12/GP$17 | ... HE41: =HE12/HE$17
A42: Product0487 | AT42: =AT13/AT$17 | AU42: =AU13/AU$17 | AV42: =AV13/AV$17 | AW42: =AW13/AW$17 | AX42: =AX13/AX$17 | AY42: =AY13/AY$17 | AZ42: =AZ13/AZ$17 | BA42: =BA13/BA$17 | ... EK42: =EK13/EK$17 | EX42: =EX13/EX$17 | EY42: =EY13/EY$17 | EZ42: =EZ13/EZ$17 | FA42: =FA13/FA$17 | FB42: =FB13/FB$17 | FC42: =FC13/FC$17 | FD42: =FD13/FD$17 | FE42: =FE13/FE$17 | ... FU42: =FU13/FU$17 | GI42: =GI13/GI$17 | GJ42: =GJ13/GJ$17 | GK42: =GK13/GK$17 | GL42: =GL13/GL$17 | GM42: =GM13/GM$17 | GN42: =GN13/GN$17 | GO42: =GO13/GO$17 | GP42: =GP13/GP$17 | ... HE42: =HE13/HE$17
A43: Wearables, Home and Accessories | AT43: =AT14/AT$17 | AU43: =AU14/AU$17 | AV43: =AV14/AV$17 | AW43: =AW14/AW$17 | AX43: =AX14/AX$17 | AY43: =AY14/AY$17 | AZ43: =AZ14/AZ$17 | BA43: =BA14/BA$17 | ... EK43: =EK14/EK$17 | EX43: =EX14/EX$17 | EY43: =EY14/EY$17 | EZ43: =EZ14/EZ$17 | FA43: =FA14/FA$17 | FB43: =FB14/FB$17 | FC43: =FC14/FC$17 | FD43: =FD14/FD$17 | FE43: =FE14/FE$17 | ... FU43: =FU14/FU$17 | GI43: =GI14/GI$17 | GJ43: =GJ14/GJ$17 | GK43: =GK14/GK$17 | GL43: =GL14/GL$17 | GM43: =GM14/GM$17 | GN43: =GN14/GN$17 | GO43: =GO14/GO$17 | GP43: =GP14/GP$17 | ... HE43: =HE14/HE$17
A44: Products | AT44: =AT15/AT$17 | AU44: =AU15/AU$17 | AV44: =AV15/AV$17 | AW44: =AW15/AW$17 | AX44: =AX15/AX$17 | AY44: =AY15/AY$17 | AZ44: =AZ15/AZ$17 | BA44: =BA15/BA$17 | ... EK44: =EK15/EK$17 | EX44: =EX15/EX$17 | EY44: =EY15/EY$17 | EZ44: =EZ15/EZ$17 | FA44: =FA15/FA$17 | FB44: =FB15/FB$17 | FC44: =FC15/FC$17 | FD44: =FD15/FD$17 | FE44: =FE15/FE$17 | ... FU44: =FU15/FU$17 | GI44: =GI15/GI$17 | GJ44: =GJ15/GJ$17 | GK44: =GK15/GK$17 | GL44: =GL15/GL$17 | GM44: =GM15/GM$17 | GN44: =GN15/GN$17 | GO44: =GO15/GO$17 | GP44: =GP15/GP$17 | ... HE44: =HE15/HE$17
A45: Services | AT45: =AT16/AT$17 | AU45: =AU16/AU$17 | AV45: =AV16/AV$17 | AW45: =AW16/AW$17 | AX45: =AX16/AX$17 | AY45: =AY16/AY$17 | AZ45: =AZ16/AZ$17 | BA45: =BA16/BA$17 | ... EK45: =EK16/EK$17 | EX45: =EX16/EX$17 | EY45: =EY16/EY$17 | EZ45: =EZ16/EZ$17 | FA45: =FA16/FA$17 | FB45: =FB16/FB$17 | FC45: =FC16/FC$17 | FD45: =FD16/FD$17 | FE45: =FE16/FE$17 | ... FU45: =FU16/FU$17 | GI45: =GI16/GI$17 | GJ45: =GJ16/GJ$17 | GK45: =GK16/GK$17 | GL45: =GL16/GL$17 | GM45: =GM16/GM$17 | GN45: =GN16/GN$17 | GO45: =GO16/GO$17 | GP45: =GP16/GP$17 | ... HE45: =HE16/HE$17
A46: Total revenue | AT46: =AT17/AT$17 | AU46: =AU17/AU$17 | AV46: =AV17/AV$17 | AW46: =AW17/AW$17 | AX46: =AX17/AX$17 | AY46: =AY17/AY$17 | AZ46: =AZ17/AZ$17 | BA46: =BA17/BA$17 | ... EK46: =EK17/EK$17 | EX46: =EX17/EX$17 | EY46: =EY17/EY$17 | EZ46: =EZ17/EZ$17 | FA46: =FA17/FA$17 | FB46: =FB17/FB$17 | FC46: =FC17/FC$17 | FD46: =FD17/FD$17 | FE46: =FE17/FE$17 | ... FU46: =FU17/FU$17 | FY46: =FY17/FY$17 | FZ46: =FZ17/FZ$17 | GA46: =GA17/GA$17 | GB46: =GB17/GB$17 | GC46: =GC17/GC$17 | GD46: =GD17/GD$17 | GE46: =GE17/GE$17 | GF46: =GF17/GF$17 | ... HE46: =HE17/HE$17
A48: Products COGS | CL48: 50575 | CM48: 33936 | CN48: 28956 | CO48: 34697 | CP48: 48238 | CQ48: 32047 | CR48: 29473 | CS48: 35238 | CT48: 52075 | CU48: 31321 | CV48: 32693 | CW48: 35197 | CX48: 62130 | CY48: 46447 | CZ48: 40899 | DA48: 42790 | DB48: 64309 | DC48: 49290 | DD48: 41485 | DE48: 46387 | DF48: 60765 | DG48: 46795 | DH48: 39136 | DI48: 42586 | DJ48: 58440 | DK48: 42424 | DL48: 39803 | DM48: 44566 | DN48: 59447 | DO48: 44030 | DP48: 43620 | DQ48: =DQ15-DQ52 | DR48: =DR15-DR52 | DS48: =DS15-DS52 | DT48: =DT15-DT52 | DU48: =DU15-DU52 | DV48: =DV15-DV52 | DW48: =DW15-DW52 | DX48: =DX15-DX52 | ... EK48: =EK15-EK52 | FH48: 126337 | FI48: =SUM(CL48:CO48) | FJ48: =SUM(CP48:CS48) | FK48: =SUM(CT48:CW48) | FL48: =SUM(CX48:DA48) | FM48: =SUM(DB48:DE48) | FN48: =SUM(DF48:DI48) | FO48: =SUM(DJ48:DM48) | FP48: =SUM(DN48:DQ48) | FQ48: =SUM(DR48:DU48) | FR48: =SUM(DV48:DY48) | FS48: =SUM(DZ48:EC48) | FT48: =SUM(ED48:EG48) | FU48: =SUM(EH48:EK48) | GT48: =SUM(CM48:CP48) | GU48: =SUM(CQ48:CT48) | GV48: =SUM(CU48:CX48) | GW48: =SUM(CY48:DB48) | GX48: =SUM(DC48:DF48) | GY48: =SUM(DG48:DJ48) | GZ48: =SUM(DK48:DN48) | HA48: =SUM(DO48:DR48) | HB48: =SUM(DS48:DV48) | HC48: =SUM(DW48:DZ48) | HD48: =SUM(EA48:ED48) | HE48: =SUM(EE48:EH48)
A49: Services COGS | CL49: 3806 | CM49: 3779 | CN49: 3888 | CO49: 4119 | CP49: 4041 | CQ49: 4147 | CR49: 4109 | CS49: 4489 | CT49: 4527 | CU49: 4622 | CV49: 4312 | CW49: 4812 | CX49: 4981 | CY49: 5058 | CZ49: 5280 | DA49: 5396 | DB49: 5393 | DC49: 5429 | DD49: 5589 | DE49: 5664 | DF49: 6057 | DG49: 6065 | DH49: 6248 | DI49: 6485 | DJ49: 6280 | DK49: 6058 | DL49: 6296 | DM49: 6485 | DN49: 6578 | DO49: 6462 | DP49: 6698 | DQ49: =DQ16-DQ53 | DR49: =DR16-DR53 | DS49: =DS16-DS53 | DT49: =DT16-DT53 | DU49: =DU16-DU53 | DV49: =DV16-DV53 | DW49: =DW16-DW53 | DX49: =DX16-DX53 | ... EK49: =EK16-EK53 | FH49: 14711 | FI49: =SUM(CL49:CO49) | FJ49: =SUM(CP49:CS49) | FK49: =SUM(CT49:CW49) | FL49: =SUM(CX49:DA49) | FM49: =SUM(DB49:DE49) | FN49: =SUM(DF49:DI49) | FO49: =SUM(DJ49:DM49) | FP49: =SUM(DN49:DQ49) | FQ49: =SUM(DR49:DU49) | FR49: =SUM(DV49:DY49) | FS49: =SUM(DZ49:EC49) | FT49: =SUM(ED49:EG49) | FU49: =SUM(EH49:EK49) | GT49: =SUM(CM49:CP49) | GU49: =SUM(CQ49:CT49) | GV49: =SUM(CU49:CX49) | GW49: =SUM(CY49:DB49) | GX49: =SUM(DC49:DF49) | GY49: =SUM(DG49:DJ49) | GZ49: =SUM(DK49:DN49) | HA49: =SUM(DO49:DR49) | HB49: =SUM(DS49:DV49) | HC49: =SUM(DW49:DZ49) | HD49: =SUM(EA49:ED49) | HE49: =SUM(EE49:EH49)
A50: COGS | B50: ='Income Statement'!B10 | C50: ='Income Statement'!C10 | D50: ='Income Statement'!D10 | E50: ='Income Statement'!E10 | F50: ='Income Statement'!F10 | G50: ='Income Statement'!G10 | H50: ='Income Statement'!H10 | I50: ='Income Statement'!I10 | ... DD50: ='Income Statement'!DD10 | DE50: =SUM(DE48:DE49) | DF50: =SUM(DF48:DF49) | DG50: =SUM(DG48:DG49) | DH50: =SUM(DH48:DH49) | DI50: =SUM(DI48:DI49) | DJ50: =SUM(DJ48:DJ49) | DK50: =SUM(DK48:DK49) | DL50: =SUM(DL48:DL49) | ... EK50: =SUM(EK48:EK49) | FH50: =FH48+FH49 | FI50: =SUM(CL50:CO50) | FJ50: =SUM(CP50:CS50) | FK50: =SUM(CT50:CW50) | FL50: =SUM(CX50:DA50) | FM50: =SUM(DB50:DE50) | FN50: =SUM(DF50:DI50) | FO50: =SUM(DJ50:DM50) | FP50: =SUM(DN50:DQ50) | FQ50: =SUM(DR50:DU50) | FR50: =SUM(DV50:DY50) | FS50: =SUM(DZ50:EC50) | FT50: =SUM(ED50:EG50) | FU50: =SUM(EH50:EK50) | GT50: =SUM(CM50:CP50) | GU50: =SUM(CQ50:CT50) | GV50: =SUM(CU50:CX50) | GW50: =SUM(CY50:DB50) | GX50: =SUM(DC50:DF50) | GY50: =SUM(DG50:DJ50) | GZ50: =SUM(DK50:DN50) | HA50: =SUM(DO50:DR50) | HB50: =SUM(DS50:DV50) | HC50: =SUM(DW50:DZ50) | HD50: =SUM(EA50:ED50) | HE50: =SUM(EE50:EH50)
A52: Products Gross Profit | CL52: =CL15-CL48 | CM52: =CM15-CM48 | CN52: =CN15-CN48 | CO52: =CO15-CO48 | CP52: =CP15-CP48 | CQ52: =CQ15-CQ48 | CR52: =CR15-CR48 | CS52: =CS15-CS48 | ... DP52: =DP15-DP48 | DQ52: =DQ57*DQ15 | DR52: =DR57*DR15 | DS52: =DS57*DS15 | DT52: =DT57*DT15 | DU52: =DU57*DU15 | DV52: =DV57*DV15 | DW52: =DW57*DW15 | DX52: =DX57*DX15 | ... EK52: =EK57*EK15 | FH52: =FH15-FH48 | FI52: =SUM(CL52:CO52) | FJ52: =SUM(CP52:CS52) | FK52: =SUM(CT52:CW52) | FL52: =SUM(CX52:DA52) | FM52: =SUM(DB52:DE52) | FN52: =SUM(DF52:DI52) | FO52: =SUM(DJ52:DM52) | FP52: =SUM(DN52:DQ52) | FQ52: =SUM(DR52:DU52) | FR52: =SUM(DV52:DY52) | FS52: =SUM(DZ52:EC52) | FT52: =SUM(ED52:EG52) | FU52: =SUM(EH52:EK52) | GT52: =SUM(CM52:CP52) | GU52: =SUM(CQ52:CT52) | GV52: =SUM(CU52:CX52) | GW52: =SUM(CY52:DB52) | GX52: =SUM(DC52:DF52) | GY52: =SUM(DG52:DJ52) | GZ52: =SUM(DK52:DN52) | HA52: =SUM(DO52:DR52) | HB52: =SUM(DS52:DV52) | HC52: =SUM(DW52:DZ52) | HD52: =SUM(EA52:ED52) | HE52: =SUM(EE52:EH52)
A53: Services Gross Profit | CL53: =CL16-CL49 | CM53: =CM16-CM49 | CN53: =CN16-CN49 | CO53: =CO16-CO49 | CP53: =CP16-CP49 | CQ53: =CQ16-CQ49 | CR53: =CR16-CR49 | CS53: =CS16-CS49 | ... DP53: =DP16-DP49 | DQ53: =DQ58*DQ16 | DR53: =DR58*DR16 | DS53: =DS58*DS16 | DT53: =DT58*DT16 | DU53: =DU58*DU16 | DV53: =DV58*DV16 | DW53: =DW58*DW16 | DX53: =DX58*DX16 | ... EK53: =EK58*EK16 | FH53: =FH16-FH49 | FI53: =SUM(CL53:CO53) | FJ53: =SUM(CP53:CS53) | FK53: =SUM(CT53:CW53) | FL53: =SUM(CX53:DA53) | FM53: =SUM(DB53:DE53) | FN53: =SUM(DF53:DI53) | FO53: =SUM(DJ53:DM53) | FP53: =SUM(DN53:DQ53) | FQ53: =SUM(DR53:DU53) | FR53: =SUM(DV53:DY53) | FS53: =SUM(DZ53:EC53) | FT53: =SUM(ED53:EG53) | FU53: =SUM(EH53:EK53) | GT53: =SUM(CM53:CP53) | GU53: =SUM(CQ53:CT53) | GV53: =SUM(CU53:CX53) | GW53: =SUM(CY53:DB53) | GX53: =SUM(DC53:DF53) | GY53: =SUM(DG53:DJ53) | GZ53: =SUM(DK53:DN53) | HA53: =SUM(DO53:DR53) | HB53: =SUM(DS53:DV53) | HC53: =SUM(DW53:DZ53) | HD53: =SUM(EA53:ED53) | HE53: =SUM(EE53:EH53)
A54: Gross profit | CL54: =SUM(CL52:CL53) | CM54: =SUM(CM52:CM53) | CN54: =SUM(CN52:CN53) | CO54: =SUM(CO52:CO53) | CP54: =SUM(CP52:CP53) | CQ54: =SUM(CQ52:CQ53) | CR54: =SUM(CR52:CR53) | CS54: =SUM(CS52:CS53) | ... EK54: =SUM(EK52:EK53) | FH54: =SUM(FH52:FH53) | FI54: =SUM(CL54:CO54) | FJ54: =SUM(CP54:CS54) | FK54: =SUM(CT54:CW54) | FL54: =SUM(CX54:DA54) | FM54: =SUM(DB54:DE54) | FN54: =SUM(DF54:DI54) | FO54: =SUM(DJ54:DM54) | FP54: =SUM(DN54:DQ54) | FQ54: =SUM(DR54:DU54) | FR54: =SUM(DV54:DY54) | FS54: =SUM(DZ54:EC54) | FT54: =SUM(ED54:EG54) | FU54: =SUM(EH54:EK54) | GT54: =SUM(CM54:CP54) | GU54: =SUM(CQ54:CT54) | GV54: =SUM(CU54:CX54) | GW54: =SUM(CY54:DB54) | GX54: =SUM(DC54:DF54) | GY54: =SUM(DG54:DJ54) | GZ54: =SUM(DK54:DN54) | HA54: =SUM(DO54:DR54) | HB54: =SUM(DS54:DV54) | HC54: =SUM(DW54:DZ54) | HD54: =SUM(EA54:ED54) | HE54: =SUM(EE54:EH54)
A56: % of revenue | B56: =B$8 | C56: =C$8 | D56: =D$8 | E56: =E$8 | F56: =F$8 | G56: =G$8 | H56: =H$8 | I56: =I$8 | ... EK56: =EK$8 | EM56: =EM$9 | EN56: =EN$9 | EO56: =EO$9 | EP56: =EP$9 | EQ56: =EQ$9 | ER56: =ER$9 | ES56: =ES$9 | ET56: =ET$9 | ... FU56: =FU$9 | FX56: =FX$9 | FY56: =FY$9 | FZ56: =FZ$9 | GA56: =GA$9 | GB56: =GB$9 | GC56: =GC$9 | GD56: =GD$9 | GE56: =GE$9 | ... HE56: =HE$9
A57: Products gross margin (%) | CL57: =1-CL48/CL15 | CM57: =1-CM48/CM15 | CN57: =1-CN48/CN15 | CO57: =1-CO48/CO15 | CP57: =1-CP48/CP15 | CQ57: =1-CQ48/CQ15 | CR57: =1-CR48/CR15 | CS57: =1-CS48/CS15 | ... DP57: =1-DP48/DP15 | DQ57: =DP57-(300/DQ15)+1.5% | DR57: =DQ57-(400/DR15)+2% | DS57: =DR57-(0/DS15)-2% | DT57: =DS57-(0/DT15)-1% | DU57: =DT57+1% | DV57: =DU57+3% | DW57: =DV57-3% | DX57: =DW57-1% | DY57: =DX57+1% | DZ57: =DY57+3% | EA57: =DZ57-3% | EB57: =EA57-1% | EC57: =EB57+1% | ED57: =EC57+3% | EE57: =ED57-3% | EF57: =EE57-1% | EG57: =EF57+1% | EH57: =EG57+3% | EI57: =EH57-3% | EJ57: =EI57-1% | EK57: =EJ57+1% | FH57: =1-FH48/FH15 | FI57: =1-FI48/FI15 | FJ57: =(FJ59*FJ17-FJ58*FJ16)/FJ15 | FK57: =(FK59*FK17-FK58*FK16)/FK15 | FL57: =(FL59*FL17-FL58*FL16)/FL15 | FM57: =(FM59*FM17-FM58*FM16)/FM15 | FN57: =(FN59*FN17-FN58*FN16)/FN15 | FO57: =(FO59*FO17-FO58*FO16)/FO15 | FP57: =(FP59*FP17-FP58*FP16)/FP15 | FQ57: =(FQ59*FQ17-FQ58*FQ16)/FQ15 | ... FU57: =(FU59*FU17-FU58*FU16)/FU15 | GT57: =(GT59*GT17-GT58*GT16)/GT15 | GU57: =(GU59*GU17-GU58*GU16)/GU15 | GV57: =(GV59*GV17-GV58*GV16)/GV15 | GW57: =(GW59*GW17-GW58*GW16)/GW15 | GX57: =(GX59*GX17-GX58*GX16)/GX15 | GY57: =(GY59*GY17-GY58*GY16)/GY15 | GZ57: =(GZ59*GZ17-GZ58*GZ16)/GZ15 | HA57: =(HA59*HA17-HA58*HA16)/HA15 | ... HE57: =(HE59*HE17-HE58*HE16)/HE15
A58: Services gross margin (%) | CL58: =1-CL49/CL16 | CM58: =1-CM49/CM16 | CN58: =1-CN49/CN16 | CO58: =1-CO49/CO16 | CP58: =1-CP49/CP16 | CQ58: =1-CQ49/CQ16 | CR58: =1-CR49/CR16 | CS58: =1-CS49/CS16 | ... DP58: =1-DP49/DP16 | DQ58: 0.755 | DR58: 0.755 | DS58: =DO58+0% | DT58: =DP58+0.1% | DU58: =DQ58+0.1% | DV58: =DR58+0.1% | DW58: =DS58+0.1% | DX58: =DT58+0.1% | DY58: =DU58+0.1% | DZ58: =DV58+0.1% | EA58: =DW58+0.1% | ... EK58: =EG58+0.1% | FH58: =1-FH49/FH16 | FI58: =1-FI49/FI16 | FJ58: =1-FJ49/FJ16 | FK58: =1-FK49/FK16 | FL58: =1-FL49/FL16 | FM58: =1-FM49/FM16 | FN58: =1-FN49/FN16 | FO58: =1-FO49/FO16 | ... FU58: =1-FU49/FU16 | GT58: =1-GT49/GT16 | GU58: =1-GU49/GU16 | GV58: =1-GV49/GV16 | GW58: =1-GW49/GW16 | GX58: =1-GX49/GX16 | GY58: =1-GY49/GY16 | GZ58: =1-GZ49/GZ16 | HA58: =1-HA49/HA16 | ... HE58: =1-HE49/HE16
A59: Gross margin (%) | B59: ='Income Statement'!B62 | C59: ='Income Statement'!C62 | D59: ='Income Statement'!D62 | E59: ='Income Statement'!E62 | F59: ='Income Statement'!F62 | G59: ='Income Statement'!G62 | H59: ='Income Statement'!H62 | I59: ='Income Statement'!I62 | ... EK59: ='Income Statement'!EK62 | FH59: =1-FH50/FH17 | FI59: =1-FI50/FI17 | FJ59: =1-FJ50/FJ17 | FK59: =1-FK50/FK17 | FL59: =1-FL50/FL17 | FM59: =1-FM50/FM17 | FN59: =1-FN50/FN17 | FO59: =1-FO50/FO17 | ... FU59: =1-FU50/FU17 | GT59: =1-GT50/GT17 | GU59: =1-GU50/GU17 | GV59: =1-GV50/GV17 | GW59: =1-GW50/GW17 | GX59: =1-GX50/GX17 | GY59: =1-GY50/GY17 | GZ59: =1-GZ50/GZ17 | HA59: =1-HA50/HA17 | ... HE59: =1-HE50/HE17
CL60: =CL57-CK57 | CM60: =CM57-CL57 | CN60: =CN57-CM57 | CO60: =CO57-CN57 | CP60: =CP57-CO57 | CQ60: =CQ57-CP57 | CR60: =CR57-CQ57 | CS60: =CS57-CR57 | ... DE60: =DE57-DD57
A61: Revenue per active Product0489 user | CL61: =CL58-CK58 | CM61: =CM58-CL58 | CN61: =CN58-CM58 | CO61: =CO58-CN58 | CP61: =CP58-CO58 | CQ61: =CQ58-CP58 | CR61: =CR58-CQ58 | CS61: =CS58-CR58 | ... DE61: =DE58-DD58
A62: Product0489 | AX62: =AX11/AX$79 | AY62: =AY11/AY$79 | AZ62: =AZ11/AZ$79 | BA62: =BA11/BA$79 | BB62: =BB11/BB$79 | BC62: =BC11/BC$79 | BD62: =BD11/BD$79 | BE62: =BE11/BE$79 | ... DQ62: =DQ11/DQ$79 | DR62: =DR11/'Segment - Products'!DR$231 | DS62: =DS11/'Segment - Products'!DS$231 | DT62: =DT11/'Segment - Products'!DT$231 | DU62: =DU11/'Segment - Products'!DU$231 | DV62: =DV11/'Segment - Products'!DV$231 | DW62: =DW11/'Segment - Products'!DW$231 | DX62: =DX11/'Segment - Products'!DX$231 | DY62: =DY11/'Segment - Products'!DY$231 | ... EK62: =EK11/'Segment - Products'!EK$231 | FB62: =FB11/FB$79 | FC62: =FC11/FC$79 | FD62: =FD11/FD$79 | FE62: =FE11/FE$79 | FF62: =FF11/FF$79 | FG62: =FG11/FG$79 | FH62: =FH11/FH$79 | FI62: =FI11/FI$79 | ... FU62: =FU11/FU$79 | GO62: =GO11/'Segment - Products'!GN$231 | GP62: =GP11/'Segment - Products'!GO$231 | GQ62: =GQ11/'Segment - Products'!GP$231 | GR62: =GR11/'Segment - Products'!GQ$231 | GS62: =GS11/'Segment - Products'!GR$231
A63: Product0487 | AX63: =AX13/AX$79 | AY63: =AY13/AY$79 | AZ63: =AZ13/AZ$79 | BA63: =BA13/BA$79 | BB63: =BB13/BB$79 | BC63: =BC13/BC$79 | BD63: =BD13/BD$79 | BE63: =BE13/BE$79 | ... DQ63: =DQ13/DQ$79 | DR63: =DR13/'Segment - Products'!DR$231 | DS63: =DS13/'Segment - Products'!DS$231 | DT63: =DT13/'Segment - Products'!DT$231 | DU63: =DU13/'Segment - Products'!DU$231 | DV63: =DV13/'Segment - Products'!DV$231 | DW63: =DW13/'Segment - Products'!DW$231 | DX63: =DX13/'Segment - Products'!DX$231 | DY63: =DY13/'Segment - Products'!DY$231 | ... EK63: =EK13/'Segment - Products'!EK$231 | FB63: =FB13/FB$79 | FC63: =FC13/FC$79 | FD63: =FD13/FD$79 | FE63: =FE13/FE$79 | FF63: =FF13/FF$79 | FG63: =FG13/FG$79 | FH63: =FH13/FH$79 | FI63: =FI13/FI$79 | ... FU63: =FU13/FU$79 | GO63: =GO13/'Segment - Products'!GN$231 | GP63: =GP13/'Segment - Products'!GO$231 | GQ63: =GQ13/'Segment - Products'!GP$231 | GR63: =GR13/'Segment - Products'!GQ$231 | GS63: =GS13/'Segment - Products'!GR$231
A64: Mac | AX64: =AX12/AX$79 | AY64: =AY12/AY$79 | AZ64: =AZ12/AZ$79 | BA64: =BA12/BA$79 | BB64: =BB12/BB$79 | BC64: =BC12/BC$79 | BD64: =BD12/BD$79 | BE64: =BE12/BE$79 | ... DQ64: =DQ12/DQ$79 | DR64: =DR12/'Segment - Products'!DR$231 | DS64: =DS12/'Segment - Products'!DS$231 | DT64: =DT12/'Segment - Products'!DT$231 | DU64: =DU12/'Segment - Products'!DU$231 | DV64: =DV12/'Segment - Products'!DV$231 | DW64: =DW12/'Segment - Products'!DW$231 | DX64: =DX12/'Segment - Products'!DX$231 | DY64: =DY12/'Segment - Products'!DY$231 | ... EK64: =EK12/'Segment - Products'!EK$231 | FB64: =FB12/FB$79 | FC64: =FC12/FC$79 | FD64: =FD12/FD$79 | FE64: =FE12/FE$79 | FF64: =FF12/FF$79 | FG64: =FG12/FG$79 | FH64: =FH12/FH$79 | FI64: =FI12/FI$79 | ... FU64: =FU12/FU$79 | GO64: =GO12/'Segment - Products'!GN$231 | GP64: =GP12/'Segment - Products'!GO$231 | GQ64: =GQ12/'Segment - Products'!GP$231 | GR64: =GR12/'Segment - Products'!GQ$231 | GS64: =GS12/'Segment - Products'!GR$231
A65: Wearables, Home and Accessories | AX65: =AX14/AX$79 | AY65: =AY14/AY$79 | AZ65: =AZ14/AZ$79 | BA65: =BA14/BA$79 | BB65: =BB14/BB$79 | BC65: =BC14/BC$79 | BD65: =BD14/BD$79 | BE65: =BE14/BE$79 | ... DQ65: =DQ14/DQ$79 | DR65: =DR14/'Segment - Products'!DR$231 | DS65: =DS14/'Segment - Products'!DS$231 | DT65: =DT14/'Segment - Products'!DT$231 | DU65: =DU14/'Segment - Products'!DU$231 | DV65: =DV14/'Segment - Products'!DV$231 | DW65: =DW14/'Segment - Products'!DW$231 | DX65: =DX14/'Segment - Products'!DX$231 | DY65: =DY14/'Segment - Products'!DY$231 | ... EK65: =EK14/'Segment - Products'!EK$231 | FB65: =FB14/FB$79 | FC65: =FC14/FC$79 | FD65: =FD14/FD$79 | FE65: =FE14/FE$79 | FF65: =FF14/FF$79 | FG65: =FG14/FG$79 | FH65: =FH14/FH$79 | FI65: =FI14/FI$79 | ... FU65: =FU14/FU$79 | GO65: =GO14/'Segment - Products'!GN$231 | GP65: =GP14/'Segment - Products'!GO$231 | GQ65: =GQ14/'Segment - Products'!GP$231 | GR65: =GR14/'Segment - Products'!GQ$231 | GS65: =GS14/'Segment - Products'!GR$231
A66: Products | AX66: =AX15/AX$79 | AY66: =AY15/AY$79 | AZ66: =AZ15/AZ$79 | BA66: =BA15/BA$79 | BB66: =BB15/BB$79 | BC66: =BC15/BC$79 | BD66: =BD15/BD$79 | BE66: =BE15/BE$79 | ... DQ66: =DQ15/DQ$79 | DR66: =DR15/'Segment - Products'!DR$231 | DS66: =DS15/'Segment - Products'!DS$231 | DT66: =DT15/'Segment - Products'!DT$231 | DU66: =DU15/'Segment - Products'!DU$231 | DV66: =DV15/'Segment - Products'!DV$231 | DW66: =DW15/'Segment - Products'!DW$231 | DX66: =DX15/'Segment - Products'!DX$231 | DY66: =DY15/'Segment - Products'!DY$231 | ... EK66: =EK15/'Segment - Products'!EK$231 | FB66: =FB15/FB$79 | FC66: =FC15/FC$79 | FD66: =FD15/FD$79 | FE66: =FE15/FE$79 | FF66: =FF15/FF$79 | FG66: =FG15/FG$79 | FH66: =FH15/FH$79 | FI66: =FI15/FI$79 | ... FU66: =FU15/FU$79 | GO66: =GO15/'Segment - Products'!GN$231 | GP66: =GP15/'Segment - Products'!GO$231 | GQ66: =GQ15/'Segment - Products'!GP$231 | GR66: =GR15/'Segment - Products'!GQ$231 | GS66: =GS15/'Segment - Products'!GR$231
A67: Services | AX67: =AX16/AX$79 | AY67: =AY16/AY$79 | AZ67: =AZ16/AZ$79 | BA67: =BA16/BA$79 | BB67: =BB16/BB$79 | BC67: =BC16/BC$79 | BD67: =BD16/BD$79 | BE67: =BE16/BE$79 | ... DQ67: =DQ16/DQ$79 | DR67: =DR16/'Segment - Products'!DR$231 | DS67: =DS16/'Segment - Products'!DS$231 | DT67: =DT16/'Segment - Products'!DT$231 | DU67: =DU16/'Segment - Products'!DU$231 | DV67: =DV16/'Segment - Products'!DV$231 | DW67: =DW16/'Segment - Products'!DW$231 | DX67: =DX16/'Segment - Products'!DX$231 | DY67: =DY16/'Segment - Products'!DY$231 | ... EK67: =EK16/'Segment - Products'!EK$231 | FB67: =FB16/FB$79 | FC67: =FC16/FC$79 | FD67: =FD16/FD$79 | FE67: =FE16/FE$79 | FF67: =FF16/FF$79 | FG67: =FG16/FG$79 | FH67: =FH16/FH$79 | FI67: =FI16/FI$79 | ... FU67: =FU16/FU$79 | GO67: =GO16/'Segment - Products'!GN$231 | GP67: =GP16/'Segment - Products'!GO$231 | GQ67: =GQ16/'Segment - Products'!GP$231 | GR67: =GR16/'Segment - Products'!GQ$231 | GS67: =GS16/'Segment - Products'!GR$231
A68: Total ARPU | AX68: =AX17/AX$79 | AY68: =AY17/AY$79 | AZ68: =AZ17/AZ$79 | BA68: =BA17/BA$79 | BB68: =BB17/BB$79 | BC68: =BC17/BC$79 | BD68: =BD17/BD$79 | BE68: =BE17/BE$79 | ... DQ68: =DQ17/DQ$79 | DR68: =DR17/'Segment - Products'!DR$231 | DS68: =DS17/'Segment - Products'!DS$231 | DT68: =DT17/'Segment - Products'!DT$231 | DU68: =DU17/'Segment - Products'!DU$231 | DV68: =DV17/'Segment - Products'!DV$231 | DW68: =DW17/'Segment - Products'!DW$231 | DX68: =DX17/'Segment - Products'!DX$231 | DY68: =DY17/'Segment - Products'!DY$231 | ... EK68: =EK17/'Segment - Products'!EK$231 | FB68: =FB17/FB$79 | FC68: =FC17/FC$79 | FD68: =FD17/FD$79 | FE68: =FE17/FE$79 | FF68: =FF17/FF$79 | FG68: =FG17/FG$79 | FH68: =FH17/FH$79 | FI68: =FI17/FI$79 | ... FU68: =FU17/FU$79 | GO68: =GO17/'Segment - Products'!GN$231 | GP68: =GP17/'Segment - Products'!GO$231 | GQ68: =GQ17/'Segment - Products'!GP$231 | GR68: =GR17/'Segment - Products'!GQ$231 | GS68: =GS17/'Segment - Products'!GR$231
A70: Y/Y Revenue per user
A71: Product0489 | BB71: =(BB62/AX62)-1 | BC71: =(BC62/AY62)-1 | BD71: =(BD62/AZ62)-1 | BE71: =(BE62/BA62)-1 | BF71: =(BF62/BB62)-1 | BG71: =(BG62/BC62)-1 | BH71: =(BH62/BD62)-1 | BI71: =(BI62/BE62)-1 | ... EK71: =(EK62/EG62)-1 | FJ71: =(FJ62/FI62)-1 | FK71: =(FK62/FJ62)-1 | FL71: =(FL62/FK62)-1 | FM71: =(FM62/FL62)-1 | FN71: =(FN62/FM62)-1 | FO71: =(FO62/FN62)-1 | FP71: =(FP62/FO62)-1 | FQ71: =(FQ62/FP62)-1 | ... FU71: =(FU62/FT62)-1 | GP71: =(GP62/GO62)-1 | GQ71: =(GQ62/GP62)-1 | GR71: =(GR62/GQ62)-1 | GS71: =(GS62/GR62)-1
A72: Product0487 | BB72: =(BB63/AX63)-1 | BC72: =(BC63/AY63)-1 | BD72: =(BD63/AZ63)-1 | BE72: =(BE63/BA63)-1 | BF72: =(BF63/BB63)-1 | BG72: =(BG63/BC63)-1 | BH72: =(BH63/BD63)-1 | BI72: =(BI63/BE63)-1 | ... EK72: =(EK63/EG63)-1 | FJ72: =(FJ63/FI63)-1 | FK72: =(FK63/FJ63)-1 | FL72: =(FL63/FK63)-1 | FM72: =(FM63/FL63)-1 | FN72: =(FN63/FM63)-1 | FO72: =(FO63/FN63)-1 | FP72: =(FP63/FO63)-1 | FQ72: =(FQ63/FP63)-1 | ... FU72: =(FU63/FT63)-1 | GP72: =(GP63/GO63)-1 | GQ72: =(GQ63/GP63)-1 | GR72: =(GR63/GQ63)-1 | GS72: =(GS63/GR63)-1
A73: Mac | BB73: =(BB64/AX64)-1 | BC73: =(BC64/AY64)-1 | BD73: =(BD64/AZ64)-1 | BE73: =(BE64/BA64)-1 | BF73: =(BF64/BB64)-1 | BG73: =(BG64/BC64)-1 | BH73: =(BH64/BD64)-1 | BI73: =(BI64/BE64)-1 | ... EK73: =(EK64/EG64)-1 | FJ73: =(FJ64/FI64)-1 | FK73: =(FK64/FJ64)-1 | FL73: =(FL64/FK64)-1 | FM73: =(FM64/FL64)-1 | FN73: =(FN64/FM64)-1 | FO73: =(FO64/FN64)-1 | FP73: =(FP64/FO64)-1 | FQ73: =(FQ64/FP64)-1 | ... FU73: =(FU64/FT64)-1 | GP73: =(GP64/GO64)-1 | GQ73: =(GQ64/GP64)-1 | GR73: =(GR64/GQ64)-1 | GS73: =(GS64/GR64)-1
A74: Wearables, Home and Accessories | BB74: =(BB65/AX65)-1 | BC74: =(BC65/AY65)-1 | BD74: =(BD65/AZ65)-1 | BE74: =(BE65/BA65)-1 | BF74: =(BF65/BB65)-1 | BG74: =(BG65/BC65)-1 | BH74: =(BH65/BD65)-1 | BI74: =(BI65/BE65)-1 | ... EK74: =(EK65/EG65)-1 | FJ74: =(FJ65/FI65)-1 | FK74: =(FK65/FJ65)-1 | FL74: =(FL65/FK65)-1 | FM74: =(FM65/FL65)-1 | FN74: =(FN65/FM65)-1 | FO74: =(FO65/FN65)-1 | FP74: =(FP65/FO65)-1 | FQ74: =(FQ65/FP65)-1 | ... FU74: =(FU65/FT65)-1 | GP74: =(GP65/GO65)-1 | GQ74: =(GQ65/GP65)-1 | GR74: =(GR65/GQ65)-1 | GS74: =(GS65/GR65)-1
A75: Products | BB75: =(BB66/AX66)-1 | BC75: =(BC66/AY66)-1 | BD75: =(BD66/AZ66)-1 | BE75: =(BE66/BA66)-1 | BF75: =(BF66/BB66)-1 | BG75: =(BG66/BC66)-1 | BH75: =(BH66/BD66)-1 | BI75: =(BI66/BE66)-1 | ... EK75: =(EK66/EG66)-1 | FJ75: =(FJ66/FI66)-1 | FK75: =(FK66/FJ66)-1 | FL75: =(FL66/FK66)-1 | FM75: =(FM66/FL66)-1 | FN75: =(FN66/FM66)-1 | FO75: =(FO66/FN66)-1 | FP75: =(FP66/FO66)-1 | FQ75: =(FQ66/FP66)-1 | ... FU75: =(FU66/FT66)-1 | GP75: =(GP66/GO66)-1 | GQ75: =(GQ66/GP66)-1 | GR75: =(GR66/GQ66)-1 | GS75: =(GS66/GR66)-1
A76: Services | BB76: =(BB67/AX67)-1 | BC76: =(BC67/AY67)-1 | BD76: =(BD67/AZ67)-1 | BE76: =(BE67/BA67)-1 | BF76: =(BF67/BB67)-1 | BG76: =(BG67/BC67)-1 | BH76: =(BH67/BD67)-1 | BI76: =(BI67/BE67)-1 | ... EK76: =(EK67/EG67)-1 | FJ76: =(FJ67/FI67)-1 | FK76: =(FK67/FJ67)-1 | FL76: =(FL67/FK67)-1 | FM76: =(FM67/FL67)-1 | FN76: =(FN67/FM67)-1 | FO76: =(FO67/FN67)-1 | FP76: =(FP67/FO67)-1 | FQ76: =(FQ67/FP67)-1 | ... FU76: =(FU67/FT67)-1 | GP76: =(GP67/GO67)-1 | GQ76: =(GQ67/GP67)-1 | GR76: =(GR67/GQ67)-1 | GS76: =(GS67/GR67)-1
A77: Total ARPU | BB77: =(BB68/AX68)-1 | BC77: =(BC68/AY68)-1 | BD77: =(BD68/AZ68)-1 | BE77: =(BE68/BA68)-1 | BF77: =(BF68/BB68)-1 | BG77: =(BG68/BC68)-1 | BH77: =(BH68/BD68)-1 | BI77: =(BI68/BE68)-1 | ... EK77: =(EK68/EG68)-1 | FJ77: =(FJ68/FI68)-1 | FK77: =(FK68/FJ68)-1 | FL77: =(FL68/FK68)-1 | FM77: =(FM68/FL68)-1 | FN77: =(FN68/FM68)-1 | FO77: =(FO68/FN68)-1 | FP77: =(FP68/FO68)-1 | FQ77: =(FQ68/FP68)-1 | ... FU77: =(FU68/FT68)-1 | GP77: =(GP68/GO68)-1 | GQ77: =(GQ68/GP68)-1 | GR77: =(GR68/GQ68)-1 | GS77: =(GS68/GR68)-1
A79: Product0489 installed base (mn) | B79: ='Segment - Products'!B231 | C79: ='Segment - Products'!C231 | D79: ='Segment - Products'!D231 | E79: ='Segment - Products'!E231 | F79: ='Segment - Products'!F231 | G79: ='Segment - Products'!G231 | H79: ='Segment - Products'!H231 | I79: ='Segment - Products'!I231 | ... EK79: ='Segment - Products'!EK231 | EM79: ='Segment - Products'!EM231 | EN79: ='Segment - Products'!EN231 | EO79: ='Segment - Products'!EO231 | EP79: ='Segment - Products'!EP231 | EQ79: ='Segment - Products'!EQ231 | ER79: ='Segment - Products'!ER231 | ES79: ='Segment - Products'!ES231 | ET79: ='Segment - Products'!ET231 | ... FU79: ='Segment - Products'!FU231
A80: Company0242 all devices installed base (mn) | B80: ='Segment - Products'!B232 | C80: ='Segment - Products'!C232 | D80: ='Segment - Products'!D232 | E80: ='Segment - Products'!E232 | F80: ='Segment - Products'!F232 | G80: ='Segment - Products'!G232 | H80: ='Segment - Products'!H232 | I80: ='Segment - Products'!I232 | ... EK80: ='Segment - Products'!EK232 | EM80: ='Segment - Products'!EM232 | EN80: ='Segment - Products'!EN232 | EO80: ='Segment - Products'!EO232 | EP80: ='Segment - Products'!EP232 | EQ80: ='Segment - Products'!EQ232 | ER80: ='Segment - Products'!ER232 | ES80: ='Segment - Products'!ES232 | ET80: ='Segment - Products'!ET232 | ... FU80: ='Segment - Products'!FU232
CL82: =CL50-'Income Statement'!CL10+'Income Statement'!CL10-'Revenue summary'!CL49-'Revenue summary'!CL48 | CM82: =CM50-'Income Statement'!CM10+'Income Statement'!CM10-'Revenue summary'!CM49-'Revenue summary'!CM48 | CN82: =CN50-'Income Statement'!CN10+'Income Statement'!CN10-'Revenue summary'!CN49-'Revenue summary'!CN48 | CO82: =CO50-'Income Statement'!CO10+'Income Statement'!CO10-'Revenue summary'!CO49-'Revenue summary'!CO48 | CP82: =CP50-'Income Statement'!CP10+'Income Statement'!CP10-'Revenue summary'!CP49-'Revenue summary'!CP48 | CQ82: =CQ50-'Income Statement'!CQ10+'Income Statement'!CQ10-'Revenue summary'!CQ49-'Revenue summary'!CQ48 | CR82: =CR50-'Income Statement'!CR10+'Income Statement'!CR10-'Revenue summary'!CR49-'Revenue summary'!CR48 | CS82: =CS50-'Income Statement'!CS10+'Income Statement'!CS10-'Revenue summary'!CS49-'Revenue summary'!CS48 | ... DF82: =DF50-'Income Statement'!DF10+'Income Statement'!DF10-'Revenue summary'!DF49-'Revenue summary'!DF48
A83: Direct sales | CE83: 0.11 | DO83: 0.15 | FD83: 0.3 | FE83: 0.28 | FF83: 0.26 | FG83: 0.25 | FH83: 0.28 | FI83: 0.29 | FJ83: 0.31 | FK83: 0.34 | FL83: 0.36 | FM83: 0.38 | FN83: 0.37
A84: Indirect sales | CE84: 0.75 | DO84: 0.75 | FD84: 0.7 | FE84: 0.72 | FF84: 0.74 | FG84: 0.75 | FH84: 0.72 | FI84: 0.71 | FJ84: 0.69 | FK84: 0.66 | FL84: 0.64 | FM84: 0.62 | FN84: 0.63
FM87: Product0489 seasonality (qoq, %) | FS87: Product0487 seasonality (qoq, %)
FN88: Q1 | FO88: Q2 | FP88: Q3 | FQ88: Q4 | FT88: Q1 | FU88: Q2 | FV88: Q3 | FW88: Q4
FM89: '13 | FN89: =VLOOKUP($A$31,$A$31:$EL$31,MATCH(CONCATENATE(FN$88,$FM89),$A$8:$EL$8,0),0) | FO89: =VLOOKUP($A$31,$A$31:$EL$31,MATCH(CONCATENATE(FO$88,$FM89),$A$8:$EL$8,0),0) | FP89: =VLOOKUP($A$31,$A$31:$EL$31,MATCH(CONCATENATE(FP$88,$FM89),$A$8:$EL$8,0),0) | FQ89: =VLOOKUP($A$31,$A$31:$EL$31,MATCH(CONCATENATE(FQ$88,$FM89),$A$8:$EL$8,0),0) | FS89: =$FM89
FM90: '14 | FN90: =VLOOKUP($A$31,$A$31:$EL$31,MATCH(CONCATENATE(FN$88,$FM90),$A$8:$EL$8,0),0) | FO90: =VLOOKUP($A$31,$A$31:$EL$31,MATCH(CONCATENATE(FO$88,$FM90),$A$8:$EL$8,0),0) | FP90: =VLOOKUP($A$31,$A$31:$EL$31,MATCH(CONCATENATE(FP$88,$FM90),$A$8:$EL$8,0),0) | FQ90: =VLOOKUP($A$31,$A$31:$EL$31,MATCH(CONCATENATE(FQ$88,$FM90),$A$8:$EL$8,0),0) | FS90: =$FM90 | FU90: =VLOOKUP($A$33,$A$33:$EL$33,MATCH(CONCATENATE(FU$88,$FM90),$A$8:$EL$8,0),0) | FV90: =VLOOKUP($A$33,$A$33:$EL$33,MATCH(CONCATENATE(FV$88,$FM90),$A$8:$EL$8,0),0) | FW90: =VLOOKUP($A$33,$A$33:$EL$33,MATCH(CONCATENATE(FW$88,$FM90),$A$8:$EL$8,0),0)
FM91: '15 | FN91: =VLOOKUP($A$31,$A$31:$EL$31,MATCH(CONCATENATE(FN$88,$FM91),$A$8:$EL$8,0),0) | FO91: =VLOOKUP($A$31,$A$31:$EL$31,MATCH(CONCATENATE(FO$88,$FM91),$A$8:$EL$8,0),0) | FP91: =VLOOKUP($A$31,$A$31:$EL$31,MATCH(CONCATENATE(FP$88,$FM91),$A$8:$EL$8,0),0) | FQ91: =VLOOKUP($A$31,$A$31:$EL$31,MATCH(CONCATENATE(FQ$88,$FM91),$A$8:$EL$8,0),0) | FS91: =$FM91 | FT91: =VLOOKUP($A$33,$A$33:$EL$33,MATCH(CONCATENATE(FT$88,$FM91),$A$8:$EL$8,0),0) | FU91: =VLOOKUP($A$33,$A$33:$EL$33,MATCH(CONCATENATE(FU$88,$FM91),$A$8:$EL$8,0),0) | FV91: =VLOOKUP($A$33,$A$33:$EL$33,MATCH(CONCATENATE(FV$88,$FM91),$A$8:$EL$8,0),0) | FW91: =VLOOKUP($A$33,$A$33:$EL$33,MATCH(CONCATENATE(FW$88,$FM91),$A$8:$EL$8,0),0)
FM92: '16 | FN92: =VLOOKUP($A$31,$A$31:$EL$31,MATCH(CONCATENATE(FN$88,$FM92),$A$8:$EL$8,0),0) | FO92: =VLOOKUP($A$31,$A$31:$EL$31,MATCH(CONCATENATE(FO$88,$FM92),$A$8:$EL$8,0),0) | FP92: =VLOOKUP($A$31,$A$31:$EL$31,MATCH(CONCATENATE(FP$88,$FM92),$A$8:$EL$8,0),0) | FQ92: =VLOOKUP($A$31,$A$31:$EL$31,MATCH(CONCATENATE(FQ$88,$FM92),$A$8:$EL$8,0),0) | FS92: =$FM92 | FT92: =VLOOKUP($A$33,$A$33:$EL$33,MATCH(CONCATENATE(FT$88,$FM92),$A$8:$EL$8,0),0) | FU92: =VLOOKUP($A$33,$A$33:$EL$33,MATCH(CONCATENATE(FU$88,$FM92),$A$8:$EL$8,0),0) | FV92: =VLOOKUP($A$33,$A$33:$EL$33,MATCH(CONCATENATE(FV$88,$FM92),$A$8:$EL$8,0),0) | FW92: =VLOOKUP($A$33,$A$33:$EL$33,MATCH(CONCATENATE(FW$88,$FM92),$A$8:$EL$8,0),0)
FM93: '17 | FN93: =VLOOKUP($A$31,$A$31:$EL$31,MATCH(CONCATENATE(FN$88,$FM93),$A$8:$EL$8,0),0) | FO93: =VLOOKUP($A$31,$A$31:$EL$31,MATCH(CONCATENATE(FO$88,$FM93),$A$8:$EL$8,0),0) | FP93: =VLOOKUP($A$31,$A$31:$EL$31,MATCH(CONCATENATE(FP$88,$FM93),$A$8:$EL$8,0),0) | FQ93: =VLOOKUP($A$31,$A$31:$EL$31,MATCH(CONCATENATE(FQ$88,$FM93),$A$8:$EL$8,0),0) | FS93: =$FM93 | FT93: =VLOOKUP($A$33,$A$33:$EL$33,MATCH(CONCATENATE(FT$88,$FM93),$A$8:$EL$8,0),0) | FU93: =VLOOKUP($A$33,$A$33:$EL$33,MATCH(CONCATENATE(FU$88,$FM93),$A$8:$EL$8,0),0) | FV93: =VLOOKUP($A$33,$A$33:$EL$33,MATCH(CONCATENATE(FV$88,$FM93),$A$8:$EL$8,0),0) | FW93: =VLOOKUP($A$33,$A$33:$EL$33,MATCH(CONCATENATE(FW$88,$FM93),$A$8:$EL$8,0),0)
FM94: '18 | FN94: =VLOOKUP($A$31,$A$31:$EL$31,MATCH(CONCATENATE(FN$88,$FM94),$A$8:$EL$8,0),0) | FO94: =VLOOKUP($A$31,$A$31:$EL$31,MATCH(CONCATENATE(FO$88,$FM94),$A$8:$EL$8,0),0) | FP94: =VLOOKUP($A$31,$A$31:$EL$31,MATCH(CONCATENATE(FP$88,$FM94),$A$8:$EL$8,0),0) | FQ94: =VLOOKUP($A$31,$A$31:$EL$31,MATCH(CONCATENATE(FQ$88,$FM94),$A$8:$EL$8,0),0) | FS94: =$FM94 | FT94: =VLOOKUP($A$33,$A$33:$EL$33,MATCH(CONCATENATE(FT$88,$FM94),$A$8:$EL$8,0),0) | FU94: =VLOOKUP($A$33,$A$33:$EL$33,MATCH(CONCATENATE(FU$88,$FM94),$A$8:$EL$8,0),0) | FV94: =VLOOKUP($A$33,$A$33:$EL$33,MATCH(CONCATENATE(FV$88,$FM94),$A$8:$EL$8,0),0) | FW94: =VLOOKUP($A$33,$A$33:$EL$33,MATCH(CONCATENATE(FW$88,$FM94),$A$8:$EL$8,0),0)
FM95: '19 | FN95: =VLOOKUP($A$31,$A$31:$EL$31,MATCH(CONCATENATE(FN$88,$FM95),$A$8:$EL$8,0),0) | FO95: =VLOOKUP($A$31,$A$31:$EL$31,MATCH(CONCATENATE(FO$88,$FM95),$A$8:$EL$8,0),0) | FP95: =VLOOKUP($A$31,$A$31:$EL$31,MATCH(CONCATENATE(FP$88,$FM95),$A$8:$EL$8,0),0) | FQ95: =VLOOKUP($A$31,$A$31:$EL$31,MATCH(CONCATENATE(FQ$88,$FM95),$A$8:$EL$8,0),0) | FS95: =$FM95 | FT95: =VLOOKUP($A$33,$A$33:$EL$33,MATCH(CONCATENATE(FT$88,$FM95),$A$8:$EL$8,0),0) | FU95: =VLOOKUP($A$33,$A$33:$EL$33,MATCH(CONCATENATE(FU$88,$FM95),$A$8:$EL$8,0),0) | FV95: =VLOOKUP($A$33,$A$33:$EL$33,MATCH(CONCATENATE(FV$88,$FM95),$A$8:$EL$8,0),0) | FW95: =VLOOKUP($A$33,$A$33:$EL$33,MATCH(CONCATENATE(FW$88,$FM95),$A$8:$EL$8,0),0)
FM96: '20 | FN96: =VLOOKUP($A$31,$A$31:$EL$31,MATCH(CONCATENATE(FN$88,$FM96),$A$8:$EL$8,0),0) | FO96: =VLOOKUP($A$31,$A$31:$EL$31,MATCH(CONCATENATE(FO$88,$FM96),$A$8:$EL$8,0),0) | FP96: =VLOOKUP($A$31,$A$31:$EL$31,MATCH(CONCATENATE(FP$88,$FM96),$A$8:$EL$8,0),0) | FQ96: =VLOOKUP($A$31,$A$31:$EL$31,MATCH(CONCATENATE(FQ$88,$FM96),$A$8:$EL$8,0),0) | FS96: =$FM96 | FT96: =VLOOKUP($A$33,$A$33:$EL$33,MATCH(CONCATENATE(FT$88,$FM96),$A$8:$EL$8,0),0) | FU96: =VLOOKUP($A$33,$A$33:$EL$33,MATCH(CONCATENATE(FU$88,$FM96),$A$8:$EL$8,0),0) | FV96: =VLOOKUP($A$33,$A$33:$EL$33,MATCH(CONCATENATE(FV$88,$FM96),$A$8:$EL$8,0),0) | FW96: =VLOOKUP($A$33,$A$33:$EL$33,MATCH(CONCATENATE(FW$88,$FM96),$A$8:$EL$8,0),0)
FM97: '21 | FN97: =VLOOKUP($A$31,$A$31:$EL$31,MATCH(CONCATENATE(FN$88,$FM97),$A$8:$EL$8,0),0) | FO97: =VLOOKUP($A$31,$A$31:$EL$31,MATCH(CONCATENATE(FO$88,$FM97),$A$8:$EL$8,0),0) | FP97: =VLOOKUP($A$31,$A$31:$EL$31,MATCH(CONCATENATE(FP$88,$FM97),$A$8:$EL$8,0),0) | FQ97: =VLOOKUP($A$31,$A$31:$EL$31,MATCH(CONCATENATE(FQ$88,$FM97),$A$8:$EL$8,0),0) | FS97: =$FM97 | FT97: =VLOOKUP($A$33,$A$33:$EL$33,MATCH(CONCATENATE(FT$88,$FM97),$A$8:$EL$8,0),0) | FU97: =VLOOKUP($A$33,$A$33:$EL$33,MATCH(CONCATENATE(FU$88,$FM97),$A$8:$EL$8,0),0) | FV97: =VLOOKUP($A$33,$A$33:$EL$33,MATCH(CONCATENATE(FV$88,$FM97),$A$8:$EL$8,0),0) | FW97: =VLOOKUP($A$33,$A$33:$EL$33,MATCH(CONCATENATE(FW$88,$FM97),$A$8:$EL$8,0),0)
FM98: '22 | FN98: =VLOOKUP($A$31,$A$31:$EL$31,MATCH(CONCATENATE(FN$88,$FM98),$A$8:$EL$8,0),0) | FO98: =VLOOKUP($A$31,$A$31:$EL$31,MATCH(CONCATENATE(FO$88,$FM98),$A$8:$EL$8,0),0) | FP98: =VLOOKUP($A$31,$A$31:$EL$31,MATCH(CONCATENATE(FP$88,$FM98),$A$8:$EL$8,0),0) | FQ98: =VLOOKUP($A$31,$A$31:$EL$31,MATCH(CONCATENATE(FQ$88,$FM98),$A$8:$EL$8,0),0) | FS98: =$FM98 | FT98: =VLOOKUP($A$33,$A$33:$EL$33,MATCH(CONCATENATE(FT$88,$FM98),$A$8:$EL$8,0),0) | FU98: =VLOOKUP($A$33,$A$33:$EL$33,MATCH(CONCATENATE(FU$88,$FM98),$A$8:$EL$8,0),0) | FV98: =VLOOKUP($A$33,$A$33:$EL$33,MATCH(CONCATENATE(FV$88,$FM98),$A$8:$EL$8,0),0) | FW98: =VLOOKUP($A$33,$A$33:$EL$33,MATCH(CONCATENATE(FW$88,$FM98),$A$8:$EL$8,0),0)
FM99: '23 | FN99: =VLOOKUP($A$31,$A$31:$EL$31,MATCH(CONCATENATE(FN$88,$FM99),$A$8:$EL$8,0),0) | FO99: =VLOOKUP($A$31,$A$31:$EL$31,MATCH(CONCATENATE(FO$88,$FM99),$A$8:$EL$8,0),0) | FP99: =VLOOKUP($A$31,$A$31:$EL$31,MATCH(CONCATENATE(FP$88,$FM99),$A$8:$EL$8,0),0) | FQ99: =VLOOKUP($A$31,$A$31:$EL$31,MATCH(CONCATENATE(FQ$88,$FM99),$A$8:$EL$8,0),0) | FS99: =$FM99 | FT99: =VLOOKUP($A$33,$A$33:$EL$33,MATCH(CONCATENATE(FT$88,$FM99),$A$8:$EL$8,0),0) | FU99: =VLOOKUP($A$33,$A$33:$EL$33,MATCH(CONCATENATE(FU$88,$FM99),$A$8:$EL$8,0),0) | FV99: =VLOOKUP($A$33,$A$33:$EL$33,MATCH(CONCATENATE(FV$88,$FM99),$A$8:$EL$8,0),0) | FW99: =VLOOKUP($A$33,$A$33:$EL$33,MATCH(CONCATENATE(FW$88,$FM99),$A$8:$EL$8,0),0)
FM100: '24 | FN100: =VLOOKUP($A$31,$A$31:$EL$31,MATCH(CONCATENATE(FN$88,$FM100),$A$8:$EL$8,0),0) | FO100: =VLOOKUP($A$31,$A$31:$EL$31,MATCH(CONCATENATE(FO$88,$FM100),$A$8:$EL$8,0),0) | FP100: =VLOOKUP($A$31,$A$31:$EL$31,MATCH(CONCATENATE(FP$88,$FM100),$A$8:$EL$8,0),0) | FQ100: =VLOOKUP($A$31,$A$31:$EL$31,MATCH(CONCATENATE(FQ$88,$FM100),$A$8:$EL$8,0),0) | FS100: =$FM100 | FT100: =VLOOKUP($A$33,$A$33:$EL$33,MATCH(CONCATENATE(FT$88,LEFT($FM100,3)),$A$8:$EL$8,0),0) | FU100: =VLOOKUP($A$33,$A$33:$EL$33,MATCH(CONCATENATE(FU$88,LEFT($FM100,3)),$A$8:$EL$8,0),0) | FV100: =VLOOKUP($A$33,$A$33:$EL$33,MATCH(CONCATENATE(FV$88,LEFT($FM100,3)),$A$8:$EL$8,0),0) | FW100: =VLOOKUP($A$33,$A$33:$EL$33,MATCH(CONCATENATE(FW$88,LEFT($FM100,3)),$A$8:$EL$8,0),0)
FM101: '25E | FN101: =VLOOKUP($A$31,$A$31:$EL$31,MATCH(CONCATENATE(FN$88,LEFT($FM101,3)),$A$8:$EL$8,0),0) | FO101: =VLOOKUP($A$31,$A$31:$EL$31,MATCH(CONCATENATE(FO$88,LEFT($FM101,3)),$A$8:$EL$8,0),0) | FP101: =VLOOKUP($A$31,$A$31:$EL$31,MATCH(CONCATENATE(FP$88,$FM101),$A$8:$EL$8,0),0) | FQ101: =VLOOKUP($A$31,$A$31:$EL$31,MATCH(CONCATENATE(FQ$88,$FM101),$A$8:$EL$8,0),0) | FS101: =$FM101 | FT101: =VLOOKUP($A$33,$A$33:$EL$33,MATCH(CONCATENATE(FT$88,LEFT($FM101,3)),$A$8:$EL$8,0),0) | FU101: =VLOOKUP($A$33,$A$33:$EL$33,MATCH(CONCATENATE(FU$88,LEFT($FM101,3)),$A$8:$EL$8,0),0) | FV101: =VLOOKUP($A$33,$A$33:$EL$33,MATCH(CONCATENATE(FV$88,$FM101),$A$8:$EL$8,0),0) | FW101: =VLOOKUP($A$33,$A$33:$EL$33,MATCH(CONCATENATE(FW$88,$FM101),$A$8:$EL$8,0),0)
FM102: '26E | FN102: =VLOOKUP($A$31,$A$31:$EL$31,MATCH(CONCATENATE(FN$88,$FM102),$A$8:$EL$8,0),0) | FO102: =VLOOKUP($A$31,$A$31:$EL$31,MATCH(CONCATENATE(FO$88,$FM102),$A$8:$EL$8,0),0) | FP102: =VLOOKUP($A$31,$A$31:$EL$31,MATCH(CONCATENATE(FP$88,$FM102),$A$8:$EL$8,0),0) | FQ102: =VLOOKUP($A$31,$A$31:$EL$31,MATCH(CONCATENATE(FQ$88,$FM102),$A$8:$EL$8,0),0) | FS102: =$FM102 | FT102: =VLOOKUP($A$33,$A$33:$EL$33,MATCH(CONCATENATE(FT$88,$FM102),$A$8:$EL$8,0),0) | FU102: =VLOOKUP($A$33,$A$33:$EL$33,MATCH(CONCATENATE(FU$88,$FM102),$A$8:$EL$8,0),0) | FV102: =VLOOKUP($A$33,$A$33:$EL$33,MATCH(CONCATENATE(FV$88,$FM102),$A$8:$EL$8,0),0) | FW102: =VLOOKUP($A$33,$A$33:$EL$33,MATCH(CONCATENATE(FW$88,$FM102),$A$8:$EL$8,0),0)
FM104: Mac seasonality (qoq, %) | FS104: Company2944 seasonality (qoq, %)
FN105: Q1 | FO105: Q2 | FP105: Q3 | FQ105: Q4 | FT105: Q1 | FU105: Q2 | FV105: Q3 | FW105: Q4
FM106: =$FM89 | FN106: =VLOOKUP($A$32,$A$32:$EL$32,MATCH(CONCATENATE(FN$88,$FM106),$A$8:$EL$8,0),0) | FO106: =VLOOKUP($A$32,$A$32:$EL$32,MATCH(CONCATENATE(FO$88,$FM106),$A$8:$EL$8,0),0) | FP106: =VLOOKUP($A$32,$A$32:$EL$32,MATCH(CONCATENATE(FP$88,$FM106),$A$8:$EL$8,0),0) | FQ106: =VLOOKUP($A$32,$A$32:$EL$32,MATCH(CONCATENATE(FQ$88,$FM106),$A$8:$EL$8,0),0) | FS106: =$FM89 | FT106: =VLOOKUP($A$34,$A$34:$EL$34,MATCH(CONCATENATE(FT$88,$FM106),$A$8:$EL$8,0),0) | FU106: =VLOOKUP($A$34,$A$34:$EL$34,MATCH(CONCATENATE(FU$88,$FM106),$A$8:$EL$8,0),0) | FV106: =VLOOKUP($A$34,$A$34:$EL$34,MATCH(CONCATENATE(FV$88,$FM106),$A$8:$EL$8,0),0) | FW106: =VLOOKUP($A$34,$A$34:$EL$34,MATCH(CONCATENATE(FW$88,$FM106),$A$8:$EL$8,0),0)
FM107: =$FM90 | FN107: =VLOOKUP($A$32,$A$32:$EL$32,MATCH(CONCATENATE(FN$88,$FM107),$A$8:$EL$8,0),0) | FO107: =VLOOKUP($A$32,$A$32:$EL$32,MATCH(CONCATENATE(FO$88,$FM107),$A$8:$EL$8,0),0) | FP107: =VLOOKUP($A$32,$A$32:$EL$32,MATCH(CONCATENATE(FP$88,$FM107),$A$8:$EL$8,0),0) | FQ107: =VLOOKUP($A$32,$A$32:$EL$32,MATCH(CONCATENATE(FQ$88,$FM107),$A$8:$EL$8,0),0) | FS107: =$FM90 | FT107: =VLOOKUP($A$34,$A$34:$EL$34,MATCH(CONCATENATE(FT$88,$FM107),$A$8:$EL$8,0),0) | FU107: =VLOOKUP($A$34,$A$34:$EL$34,MATCH(CONCATENATE(FU$88,$FM107),$A$8:$EL$8,0),0) | FV107: =VLOOKUP($A$34,$A$34:$EL$34,MATCH(CONCATENATE(FV$88,$FM107),$A$8:$EL$8,0),0) | FW107: =VLOOKUP($A$34,$A$34:$EL$34,MATCH(CONCATENATE(FW$88,$FM107),$A$8:$EL$8,0),0)
FM108: =$FM91 | FN108: =VLOOKUP($A$32,$A$32:$EL$32,MATCH(CONCATENATE(FN$88,$FM108),$A$8:$EL$8,0),0) | FO108: =VLOOKUP($A$32,$A$32:$EL$32,MATCH(CONCATENATE(FO$88,$FM108),$A$8:$EL$8,0),0) | FP108: =VLOOKUP($A$32,$A$32:$EL$32,MATCH(CONCATENATE(FP$88,$FM108),$A$8:$EL$8,0),0) | FQ108: =VLOOKUP($A$32,$A$32:$EL$32,MATCH(CONCATENATE(FQ$88,$FM108),$A$8:$EL$8,0),0) | FS108: =$FM91 | FT108: =VLOOKUP($A$34,$A$34:$EL$34,MATCH(CONCATENATE(FT$88,$FM108),$A$8:$EL$8,0),0) | FU108: =VLOOKUP($A$34,$A$34:$EL$34,MATCH(CONCATENATE(FU$88,$FM108),$A$8:$EL$8,0),0) | FV108: =VLOOKUP($A$34,$A$34:$EL$34,MATCH(CONCATENATE(FV$88,$FM108),$A$8:$EL$8,0),0) | FW108: =VLOOKUP($A$34,$A$34:$EL$34,MATCH(CONCATENATE(FW$88,$FM108),$A$8:$EL$8,0),0)
FM109: =$FM92 | FN109: =VLOOKUP($A$32,$A$32:$EL$32,MATCH(CONCATENATE(FN$88,$FM109),$A$8:$EL$8,0),0) | FO109: =VLOOKUP($A$32,$A$32:$EL$32,MATCH(CONCATENATE(FO$88,$FM109),$A$8:$EL$8,0),0) | FP109: =VLOOKUP($A$32,$A$32:$EL$32,MATCH(CONCATENATE(FP$88,$FM109),$A$8:$EL$8,0),0) | FQ109: =VLOOKUP($A$32,$A$32:$EL$32,MATCH(CONCATENATE(FQ$88,$FM109),$A$8:$EL$8,0),0) | FS109: =$FM92 | FT109: =VLOOKUP($A$34,$A$34:$EL$34,MATCH(CONCATENATE(FT$88,$FM109),$A$8:$EL$8,0),0) | FU109: =VLOOKUP($A$34,$A$34:$EL$34,MATCH(CONCATENATE(FU$88,$FM109),$A$8:$EL$8,0),0) | FV109: =VLOOKUP($A$34,$A$34:$EL$34,MATCH(CONCATENATE(FV$88,$FM109),$A$8:$EL$8,0),0) | FW109: =VLOOKUP($A$34,$A$34:$EL$34,MATCH(CONCATENATE(FW$88,$FM109),$A$8:$EL$8,0),0)
FM110: =$FM93 | FN110: =VLOOKUP($A$32,$A$32:$EL$32,MATCH(CONCATENATE(FN$88,$FM110),$A$8:$EL$8,0),0) | FO110: =VLOOKUP($A$32,$A$32:$EL$32,MATCH(CONCATENATE(FO$88,$FM110),$A$8:$EL$8,0),0) | FP110: =VLOOKUP($A$32,$A$32:$EL$32,MATCH(CONCATENATE(FP$88,$FM110),$A$8:$EL$8,0),0) | FQ110: =VLOOKUP($A$32,$A$32:$EL$32,MATCH(CONCATENATE(FQ$88,$FM110),$A$8:$EL$8,0),0) | FS110: =$FM93 | FT110: =VLOOKUP($A$34,$A$34:$EL$34,MATCH(CONCATENATE(FT$88,$FM110),$A$8:$EL$8,0),0) | FU110: =VLOOKUP($A$34,$A$34:$EL$34,MATCH(CONCATENATE(FU$88,$FM110),$A$8:$EL$8,0),0) | FV110: =VLOOKUP($A$34,$A$34:$EL$34,MATCH(CONCATENATE(FV$88,$FM110),$A$8:$EL$8,0),0) | FW110: =VLOOKUP($A$34,$A$34:$EL$34,MATCH(CONCATENATE(FW$88,$FM110),$A$8:$EL$8,0),0)
FM111: =$FM94 | FN111: =VLOOKUP($A$32,$A$32:$EL$32,MATCH(CONCATENATE(FN$88,$FM111),$A$8:$EL$8,0),0) | FO111: =VLOOKUP($A$32,$A$32:$EL$32,MATCH(CONCATENATE(FO$88,$FM111),$A$8:$EL$8,0),0) | FP111: =VLOOKUP($A$32,$A$32:$EL$32,MATCH(CONCATENATE(FP$88,$FM111),$A$8:$EL$8,0),0) | FQ111: =VLOOKUP($A$32,$A$32:$EL$32,MATCH(CONCATENATE(FQ$88,$FM111),$A$8:$EL$8,0),0) | FS111: =$FM94 | FT111: =VLOOKUP($A$34,$A$34:$EL$34,MATCH(CONCATENATE(FT$88,$FM111),$A$8:$EL$8,0),0) | FU111: =VLOOKUP($A$34,$A$34:$EL$34,MATCH(CONCATENATE(FU$88,$FM111),$A$8:$EL$8,0),0) | FV111: =VLOOKUP($A$34,$A$34:$EL$34,MATCH(CONCATENATE(FV$88,$FM111),$A$8:$EL$8,0),0) | FW111: =VLOOKUP($A$34,$A$34:$EL$34,MATCH(CONCATENATE(FW$88,$FM111),$A$8:$EL$8,0),0)
FM112: =$FM95 | FN112: =VLOOKUP($A$32,$A$32:$EL$32,MATCH(CONCATENATE(FN$88,$FM112),$A$8:$EL$8,0),0) | FO112: =VLOOKUP($A$32,$A$32:$EL$32,MATCH(CONCATENATE(FO$88,$FM112),$A$8:$EL$8,0),0) | FP112: =VLOOKUP($A$32,$A$32:$EL$32,MATCH(CONCATENATE(FP$88,$FM112),$A$8:$EL$8,0),0) | FQ112: =VLOOKUP($A$32,$A$32:$EL$32,MATCH(CONCATENATE(FQ$88,$FM112),$A$8:$EL$8,0),0) | FS112: =$FM95 | FT112: =VLOOKUP($A$34,$A$34:$EL$34,MATCH(CONCATENATE(FT$88,$FM112),$A$8:$EL$8,0),0) | FU112: =VLOOKUP($A$34,$A$34:$EL$34,MATCH(CONCATENATE(FU$88,$FM112),$A$8:$EL$8,0),0) | FV112: =VLOOKUP($A$34,$A$34:$EL$34,MATCH(CONCATENATE(FV$88,$FM112),$A$8:$EL$8,0),0) | FW112: =VLOOKUP($A$34,$A$34:$EL$34,MATCH(CONCATENATE(FW$88,$FM112),$A$8:$EL$8,0),0)
FM113: =$FM96 | FN113: =VLOOKUP($A$32,$A$32:$EL$32,MATCH(CONCATENATE(FN$88,$FM113),$A$8:$EL$8,0),0) | FO113: =VLOOKUP($A$32,$A$32:$EL$32,MATCH(CONCATENATE(FO$88,$FM113),$A$8:$EL$8,0),0) | FP113: =VLOOKUP($A$32,$A$32:$EL$32,MATCH(CONCATENATE(FP$88,$FM113),$A$8:$EL$8,0),0) | FQ113: =VLOOKUP($A$32,$A$32:$EL$32,MATCH(CONCATENATE(FQ$88,$FM113),$A$8:$EL$8,0),0) | FS113: =$FM96 | FT113: =VLOOKUP($A$34,$A$34:$EL$34,MATCH(CONCATENATE(FT$88,$FM113),$A$8:$EL$8,0),0) | FU113: =VLOOKUP($A$34,$A$34:$EL$34,MATCH(CONCATENATE(FU$88,$FM113),$A$8:$EL$8,0),0) | FV113: =VLOOKUP($A$34,$A$34:$EL$34,MATCH(CONCATENATE(FV$88,$FM113),$A$8:$EL$8,0),0) | FW113: =VLOOKUP($A$34,$A$34:$EL$34,MATCH(CONCATENATE(FW$88,$FM113),$A$8:$EL$8,0),0)
FM114: =$FM97 | FN114: =VLOOKUP($A$32,$A$32:$EL$32,MATCH(CONCATENATE(FN$88,$FM114),$A$8:$EL$8,0),0) | FO114: =VLOOKUP($A$32,$A$32:$EL$32,MATCH(CONCATENATE(FO$88,$FM114),$A$8:$EL$8,0),0) | FP114: =VLOOKUP($A$32,$A$32:$EL$32,MATCH(CONCATENATE(FP$88,$FM114),$A$8:$EL$8,0),0) | FQ114: =VLOOKUP($A$32,$A$32:$EL$32,MATCH(CONCATENATE(FQ$88,$FM114),$A$8:$EL$8,0),0) | FS114: =$FM97 | FT114: =VLOOKUP($A$34,$A$34:$EL$34,MATCH(CONCATENATE(FT$88,$FM114),$A$8:$EL$8,0),0) | FU114: =VLOOKUP($A$34,$A$34:$EL$34,MATCH(CONCATENATE(FU$88,$FM114),$A$8:$EL$8,0),0) | FV114: =VLOOKUP($A$34,$A$34:$EL$34,MATCH(CONCATENATE(FV$88,$FM114),$A$8:$EL$8,0),0) | FW114: =VLOOKUP($A$34,$A$34:$EL$34,MATCH(CONCATENATE(FW$88,$FM114),$A$8:$EL$8,0),0)
FM115: =$FM98 | FN115: =VLOOKUP($A$32,$A$32:$EL$32,MATCH(CONCATENATE(FN$88,$FM115),$A$8:$EL$8,0),0) | FO115: =VLOOKUP($A$32,$A$32:$EL$32,MATCH(CONCATENATE(FO$88,$FM115),$A$8:$EL$8,0),0) | FP115: =VLOOKUP($A$32,$A$32:$EL$32,MATCH(CONCATENATE(FP$88,$FM115),$A$8:$EL$8,0),0) | FQ115: =VLOOKUP($A$32,$A$32:$EL$32,MATCH(CONCATENATE(FQ$88,$FM115),$A$8:$EL$8,0),0) | FS115: =$FM98 | FT115: =VLOOKUP($A$34,$A$34:$EL$34,MATCH(CONCATENATE(FT$88,$FM115),$A$8:$EL$8,0),0) | FU115: =VLOOKUP($A$34,$A$34:$EL$34,MATCH(CONCATENATE(FU$88,$FM115),$A$8:$EL$8,0),0) | FV115: =VLOOKUP($A$34,$A$34:$EL$34,MATCH(CONCATENATE(FV$88,$FM115),$A$8:$EL$8,0),0) | FW115: =VLOOKUP($A$34,$A$34:$EL$34,MATCH(CONCATENATE(FW$88,$FM115),$A$8:$EL$8,0),0)
...

Sheet Segment - Products
A3: Company0243. (Ticker0001)
A4: Products
A6: # weeks in the quarter | BR6: =BS6 | BS6: =BT6 | BT6: =BU6 | BU6: =BV6 | BV6: =BW6 | BW6: =(BW7-BV7)/7 | BX6: =(BX7-BW7)/7 | BY6: =(BY7-BX7)/7 | BZ6: =(BZ7-BY7)/7 | CA6: =(CA7-BZ7)/7 | CB6: =(CB7-CA7)/7 | CC6: =(CC7-CB7)/7 | CD6: =(CD7-CC7)/7 | ... EK6: =(EK7-EJ7)/7
A7: Quarter end date | BV7: 41636 | BW7: 41727 | BX7: 41818 | BY7: 41909 | BZ7: 42000 | CA7: 42091 | CB7: 42182 | CC7: 42273 | CD7: ='Income Statement'!CD6 | CE7: ='Income Statement'!CE6 | CF7: ='Income Statement'!CF6 | CG7: ='Income Statement'!CG6 | CH7: ='Income Statement'!CH6 | CI7: ='Income Statement'!CI6 | CJ7: ='Income Statement'!CJ6 | CK7: ='Income Statement'!CK6 | ... EK7: ='Income Statement'!EK6
B8: Q196 | C8: Q296 | D8: Q396 | E8: Q496 | F8: Q197 | G8: Q297 | H8: Q397 | I8: Q497 | J8: Q198 | K8: Q298 | L8: Q398 | M8: Q498 | N8: Q199 | O8: Q299 | P8: Q399 | Q8: Q499 | R8: Q100 | S8: Q200 | T8: Q300 | U8: Q400 | V8: Q101 | W8: Q201 | X8: Q301 | Y8: Q401 | Z8: Q102 | AA8: Q202 | AB8: Q302 | AC8: Q402 | AD8: Q103 | AE8: Q203 | AF8: Q303 | AG8: Q403 | AH8: Q104 | AI8: Q204 | AJ8: Q304 | AK8: Q404 | AL8: Q105 | AM8: Q205 | AN8: Q305 | AO8: Q405 | AP8: Q106 | AQ8: Q206 | AR8: Q306 | AS8: Q406 | AT8: Q107 | AU8: Q207 | AV8: Q307 | AW8: Q407 | AX8: Q108 | AY8: Q208 | AZ8: Q308 | BA8: Q408 | BB8: Q109 | BC8: Q209 | BD8: Q309 | BE8: Q409 | BF8: Q110 | BG8: Q210 | BH8: Q310 | BI8: Q410 | BJ8: ='Income Statement'!BJ7 | BK8: ='Income Statement'!BK7 | BL8: ='Income Statement'!BL7 | BM8: ='Income Statement'!BM7 | BN8: ='Income Statement'!BN7 | BO8: ='Income Statement'!BO7 | BP8: ='Income Statement'!BP7 | BQ8: ='Income Statement'!BQ7 | ... EK8: ='Income Statement'!EK7 | FF8: FISCAL | GR8: CALENDAR
A9: $, millions | B9: 35064 | C9: 35155 | D9: 35246 | E9: 35338 | F9: 35430 | G9: 35520 | H9: 35611 | I9: 35703 | J9: 35795 | K9: 35885 | L9: 35976 | M9: 36068 | N9: 36160 | O9: 36250 | P9: 36341 | Q9: 36433 | R9: 36525 | S9: 36616 | T9: 36707 | U9: 36799 | V9: 36891 | W9: 36981 | X9: 37072 | Y9: 37164 | Z9: 37256 | AA9: 37346 | AB9: 37437 | AC9: 37529 | AD9: 37621 | AE9: 37711 | AF9: 37802 | AG9: 37894 | AH9: 37986 | AI9: 38077 | AJ9: 38168 | AK9: 38260 | AL9: 38352 | AM9: 38442 | AN9: 38533 | AO9: 38625 | AP9: 38717 | AQ9: 38807 | AR9: 38898 | AS9: 38990 | AT9: 39082 | AU9: 39172 | AV9: 39263 | AW9: 39355 | AX9: 39447 | AY9: 39538 | AZ9: 39629 | BA9: 39721 | BB9: 39813 | BC9: 39903 | BD9: 39994 | BE9: 40086 | BF9: 40178 | BG9: 40268 | BH9: 40359 | BI9: 40451 | BJ9: 40543 | BK9: 40633 | BL9: 40724 | BM9: 40816 | BN9: 40908 | BO9: 40999 | BP9: 41090 | BQ9: 41182 | BR9: 41274 | BS9: 41364 | BT9: 41455 | BU9: 41547 | BV9: 41639 | BW9: 41729 | BX9: 41820 | BY9: 41912 | BZ9: ='Income Statement'!BZ8 | CA9: ='Income Statement'!CA8 | CB9: ='Income Statement'!CB8 | CC9: ='Income Statement'!CC8 | CD9: ='Income Statement'!CD8 | CE9: ='Income Statement'!CE8 | CF9: ='Income Statement'!CF8 | CG9: ='Income Statement'!CG8 | ... EK9: ='Income Statement'!EK8 | EM9: 1996 | EN9: 1997 | EO9: 1998 | EP9: 1999 | EQ9: 2000 | ER9: 2001 | ES9: 2002 | ET9: 2003 | EU9: 2004 | EV9: 2005 | EW9: 2006 | EX9: 2007 | EY9: 2008 | EZ9: 2009 | FA9: 2010 | FB9: 2011 | FC9: 2012 | FD9: 2013 | FE9: ='Income Statement'!FE8 | FF9: ='Income Statement'!FF8 | FG9: ='Income Statement'!FG8 | FH9: ='Income Statement'!FH8 | FI9: ='Income Statement'!FI8 | FJ9: ='Income Statement'!FJ8 | FK9: ='Income Statement'!FK8 | FL9: ='Income Statement'!FL8 | ... FU9: ='Income Statement'!FU8 | FY9: 1996 | FZ9: 1997 | GA9: 1998 | GB9: 1999 | GC9: 2000 | GD9: 2001 | GE9: 2002 | GF9: 2003 | GG9: 2004 | GH9: 2005 | GI9: 2006 | GJ9: 2007 | GK9: 2008 | GL9: 2009 | GM9: 2010 | GN9: 2011 | GO9: 2012 | GP9: 2013 | GQ9: ='Income Statement'!GO8 | GR9: ='Income Statement'!GP8 | GS9: ='Income Statement'!GQ8 | GT9: ='Income Statement'!GR8 | GU9: ='Income Statement'!GS8 | GV9: ='Income Statement'!GT8 | GW9: ='Income Statement'!GU8 | GX9: ='Income Statement'!GV8 | ... HF9: ='Income Statement'!HD8
A10: Product revenue ($, mn) | B10: ='Revenue summary'!B$8 | C10: ='Revenue summary'!C$8 | D10: ='Revenue summary'!D$8 | E10: ='Revenue summary'!E$8 | F10: ='Revenue summary'!F$8 | G10: ='Revenue summary'!G$8 | H10: ='Revenue summary'!H$8 | I10: ='Revenue summary'!I$8 | ... CK10: ='Revenue summary'!CK$8
A11: Product0489 | BB11: =BB194 | BC11: =BC194 | BD11: =BD194 | BE11: =BE194 | BF11: =BF194 | BG11: =BG194 | BH11: =BH194 | BI11: =BI194 | ... BU11: =BU194 | BV11: =BZ11/BZ194*BV194 | BW11: =CA11/CA194*BW194 | BX11: =CB11/CB194*BX194 | BY11: =CC11/CC194*BY194 | BZ11: =CD11/CD194*BZ194 | CA11: =CE11/CE194*CA194 | CB11: =CF11/CF194*CB194 | CC11: =CG11/CG194*CC194 | ... CK11: =CO11/CO194*CK194 | CL11: 61104 | CM11: 37559 | CN11: 29470 | CO11: 36755 | CP11: 51982 | CQ11: 31051 | CR11: 25986 | CS11: 33362 | CT11: 55957 | CU11: 28962 | CV11: 26418 | CW11: 26444 | CX11: 65597 | CY11: 47938 | CZ11: 39570 | DA11: 38868 | DB11: 71628 | DC11: 50570 | DD11: 40665 | DE11: ='Revenue summary'!DE11 | DF11: ='Revenue summary'!DF11 | DG11: ='Revenue summary'!DG11 | DH11: ='Revenue summary'!DH11 | DI11: ='Revenue summary'!DI11 | DJ11: ='Revenue summary'!DJ11 | DK11: ='Revenue summary'!DK11 | DL11: ='Revenue summary'!DL11 | ... DP11: ='Revenue summary'!DP11 | DQ11: =DQ70 | DR11: =DR70 | DS11: =DS70 | DT11: =DT70 | DU11: =DU70 | DV11: =DV70 | DW11: =DW70 | DX11: =DX70 | ... EK11: =EK70 | EO11: =SUM(J11:M11) | EP11: =SUM(N11:Q11) | EQ11: =SUM(R11:U11) | ER11: =SUM(V11:Y11) | ES11: =SUM(Z11:AC11) | ET11: =SUM(AD11:AG11) | EU11: =SUM(AH11:AK11) | EV11: =SUM(AL11:AO11) | EW11: =SUM(AP11:AS11) | EX11: =SUM(AT11:AW11) | EY11: =SUM(AX11:BA11) | EZ11: =SUM(BB11:BE11) | FA11: =SUM(BF11:BI11) | FB11: =SUM(BJ11:BM11) | FC11: =SUM(BN11:BQ11) | FD11: =SUM(BR11:BU11) | FE11: =SUM(BV11:BY11) | FF11: =SUM(BZ11:CC11) | FG11: =SUM(CD11:CG11) | FH11: ='Revenue summary'!FH11 | FI11: =SUM(CL11:CO11) | FJ11: =SUM(CP11:CS11) | FK11: =SUM(CT11:CW11) | FL11: =SUM(CX11:DA11) | FM11: =SUM(DB11:DE11) | FN11: =SUM(DF11:DI11) | FO11: =SUM(DJ11:DM11) | FP11: =SUM(DN11:DQ11) | FQ11: =SUM(DR11:DU11) | FR11: =SUM(DV11:DY11) | FS11: =SUM(DZ11:EC11) | FT11: =SUM(ED11:EG11) | FU11: =SUM(EH11:EK11) | FZ11: =SUM(G11:J11) | GA11: =SUM(K11:N11) | GB11: =SUM(O11:R11) | GC11: =SUM(S11:V11) | GD11: =SUM(W11:Z11) | GE11: =SUM(AA11:AD11) | GF11: =SUM(AE11:AH11) | GG11: =SUM(AI11:AL11) | GH11: =SUM(AM11:AP11) | GI11: =SUM(AQ11:AT11) | GJ11: =SUM(AU11:AX11) | GK11: =SUM(AY11:BB11) | GL11: =SUM(BC11:BF11) | GM11: =SUM(BG11:BJ11) | GN11: =SUM(BK11:BN11) | GO11: =SUM(BO11:BR11) | GP11: =SUM(BS11:BV11) | GQ11: =SUM(BW11:BZ11) | GR11: =SUM(CA11:CD11) | GS11: =SUM(CE11:CH11) | GT11: =SUM(CI11:CL11) | GU11: =SUM(CM11:CP11) | GV11: =SUM(CQ11:CT11) | GW11: =SUM(CU11:CX11) | GX11: =SUM(CY11:DB11) | GY11: =SUM(DC11:DF11) | GZ11: =SUM(DG11:DJ11) | HA11: =SUM(DK11:DN11) | HB11: =SUM(DO11:DR11) | HC11: =SUM(DS11:DV11) | HD11: =SUM(DW11:DZ11) | HE11: =SUM(EA11:ED11) | HF11: =SUM(EE11:EH11)
A12: Mac | J12: =N12/N196*J196 | K12: =O12/O196*K196 | L12: =P12/P196*L196 | M12: =Q12/Q196*M196 | N12: =R12/R196*N196 | O12: =S12/S196*O196 | P12: =T12/T196*P196 | Q12: =U12/U196*Q196 | ... Y12: =AC12/AC196*Y196 | Z12: =Z196 | AA12: =AA196 | AB12: =AB196 | AC12: =AC196 | AD12: =AD196 | AE12: =AE196 | AF12: =AF196 | AG12: =AG196 | ... BU12: =BU196 | BV12: =BZ12/BZ196*BV196 | BW12: =CA12/CA196*BW196 | BX12: =CB12/CB196*BX196 | BY12: =CC12/CC196*BY196 | BZ12: =CD12/CD196*BZ196 | CA12: =CE12/CE196*CA196 | CB12: =CF12/CF196*CB196 | CC12: =CG12/CG196*CC196 | ... CK12: =CO12/CO196*CK196 | CL12: 6824 | CM12: 5776 | CN12: 5258 | CO12: 7340 | CP12: 7416 | CQ12: 5513 | CR12: 5820 | CS12: 6991 | CT12: 7160 | CU12: 5351 | CV12: 7079 | CW12: 9032 | CX12: 8675 | CY12: 9102 | CZ12: 8235 | DA12: 9178 | DB12: 10852 | DC12: 10435 | DD12: 7382 | DE12: ='Revenue summary'!DE12 | DF12: ='Revenue summary'!DF12 | DG12: ='Revenue summary'!DG12 | DH12: ='Revenue summary'!DH12 | DI12: ='Revenue summary'!DI12 | DJ12: ='Revenue summary'!DJ12 | DK12: ='Revenue summary'!DK12 | DL12: ='Revenue summary'!DL12 | ... DP12: ='Revenue summary'!DP12 | DQ12: =DQ93*DQ152 | DR12: =DR93*DR152 | DS12: =DS93*DS152 | DT12: =DT93*DT152 | DU12: =DU93*DU152 | DV12: =DV93*DV152 | DW12: =DW93*DW152 | DX12: =DX93*DX152 | ... EK12: =EK93*EK152 | EO12: =SUM(J12:M12) | EP12: =SUM(N12:Q12) | EQ12: =SUM(R12:U12) | ER12: =SUM(V12:Y12) | ES12: =SUM(Z12:AC12) | ET12: =SUM(AD12:AG12) | EU12: =SUM(AH12:AK12) | EV12: =SUM(AL12:AO12) | EW12: =SUM(AP12:AS12) | EX12: =SUM(AT12:AW12) | EY12: =SUM(AX12:BA12) | EZ12: =SUM(BB12:BE12) | FA12: =SUM(BF12:BI12) | FB12: =SUM(BJ12:BM12) | FC12: =SUM(BN12:BQ12) | FD12: =SUM(BR12:BU12) | FE12: =SUM(BV12:BY12) | FF12: =SUM(BZ12:CC12) | FG12: =SUM(CD12:CG12) | FH12: ='Revenue summary'!FH12 | FI12: =SUM(CL12:CO12) | FJ12: =SUM(CP12:CS12) | FK12: =SUM(CT12:CW12) | FL12: =SUM(CX12:DA12) | FM12: =SUM(DB12:DE12) | FN12: =SUM(DF12:DI12) | FO12: =SUM(DJ12:DM12) | FP12: =SUM(DN12:DQ12) | FQ12: =SUM(DR12:DU12) | FR12: =SUM(DV12:DY12) | FS12: =SUM(DZ12:EC12) | FT12: =SUM(ED12:EG12) | FU12: =SUM(EH12:EK12) | FZ12: =SUM(G12:J12) | GA12: =SUM(K12:N12) | GB12: =SUM(O12:R12) | GC12: =SUM(S12:V12) | GD12: =SUM(W12:Z12) | GE12: =SUM(AA12:AD12) | GF12: =SUM(AE12:AH12) | GG12: =SUM(AI12:AL12) | GH12: =SUM(AM12:AP12) | GI12: =SUM(AQ12:AT12) | GJ12: =SUM(AU12:AX12) | GK12: =SUM(AY12:BB12) | GL12: =SUM(BC12:BF12) | GM12: =SUM(BG12:BJ12) | GN12: =SUM(BK12:BN12) | GO12: =SUM(BO12:BR12) | GP12: =SUM(BS12:BV12) | GQ12: =SUM(BW12:BZ12) | GR12: =SUM(CA12:CD12) | GS12: =SUM(CE12:CH12) | GT12: =SUM(CI12:CL12) | GU12: =SUM(CM12:CP12) | GV12: =SUM(CQ12:CT12) | GW12: =SUM(CU12:CX12) | GX12: =SUM(CY12:DB12) | GY12: =SUM(DC12:DF12) | GZ12: =SUM(DG12:DJ12) | HA12: =SUM(DK12:DN12) | HB12: =SUM(DO12:DR12) | HC12: =SUM(DS12:DV12) | HD12: =SUM(DW12:DZ12) | HE12: =SUM(EA12:ED12) | HF12: =SUM(EE12:EH12)
A13: Product0487 | BH13: =BH195 | BI13: =BI195 | BJ13: =BJ195 | BK13: =BK195 | BL13: =BL195 | BM13: =BM195 | BN13: =BN195 | BO13: =BO195 | ... BU13: =BU195 | BV13: =BZ13/BZ195*BV195 | BW13: =CA13/CA195*BW195 | BX13: =CB13/CB195*BX195 | BY13: =CC13/CC195*BY195 | BZ13: =CD13/CD195*BZ195 | CA13: =CE13/CE195*CA195 | CB13: =CF13/CF195*CB195 | CC13: =CG13/CG195*CC195 | ... CK13: =CO13/CO195*CK195 | CL13: 5755 | CM13: 4008 | CN13: 4634 | CO13: 3983 | CP13: 6729 | CQ13: 4872 | CR13: 5023 | CS13: 4656 | CT13: 5977 | CU13: 4368 | CV13: 6582 | CW13: 6797 | CX13: 8435 | CY13: 7807 | CZ13: 7368 | DA13: 8252 | DB13: 7248 | DC13: 7646 | DD13: 7224 | DE13: ='Revenue summary'!DE13 | DF13: ='Revenue summary'!DF13 | DG13: ='Revenue summary'!DG13 | DH13: ='Revenue summary'!DH13 | DI13: ='Revenue summary'!DI13 | DJ13: ='Revenue summary'!DJ13 | DK13: ='Revenue summary'!DK13 | DL13: ='Revenue summary'!DL13 | ... DP13: ='Revenue summary'!DP13 | DQ13: =DQ49 | DR13: =DR49 | DS13: =DS49 | DT13: =DT49 | DU13: =DU49 | DV13: =DV49 | DW13: =DW49 | DX13: =DX49 | ... EK13: =EK49 | EO13: =SUM(J13:M13) | EP13: =SUM(N13:Q13) | EQ13: =SUM(R13:U13) | ER13: =SUM(V13:Y13) | ES13: =SUM(Z13:AC13) | ET13: =SUM(AD13:AG13) | EU13: =SUM(AH13:AK13) | EV13: =SUM(AL13:AO13) | EW13: =SUM(AP13:AS13) | EX13: =SUM(AT13:AW13) | EY13: =SUM(AX13:BA13) | EZ13: =SUM(BB13:BE13) | FA13: =SUM(BF13:BI13) | FB13: =SUM(BJ13:BM13) | FC13: =SUM(BN13:BQ13) | FD13: =SUM(BR13:BU13) | FE13: =SUM(BV13:BY13) | FF13: =SUM(BZ13:CC13) | FG13: =SUM(CD13:CG13) | FH13: ='Revenue summary'!FH13 | FI13: =SUM(CL13:CO13) | FJ13: =SUM(CP13:CS13) | FK13: =SUM(CT13:CW13) | FL13: =SUM(CX13:DA13) | FM13: =SUM(DB13:DE13) | FN13: =SUM(DF13:DI13) | FO13: =SUM(DJ13:DM13) | FP13: =SUM(DN13:DQ13) | FQ13: =SUM(DR13:DU13) | FR13: =SUM(DV13:DY13) | FS13: =SUM(DZ13:EC13) | FT13: =SUM(ED13:EG13) | FU13: =SUM(EH13:EK13) | FZ13: =SUM(G13:J13) | GA13: =SUM(K13:N13) | GB13: =SUM(O13:R13) | GC13: =SUM(S13:V13) | GD13: =SUM(W13:Z13) | GE13: =SUM(AA13:AD13) | GF13: =SUM(AE13:AH13) | GG13: =SUM(AI13:AL13) | GH13: =SUM(AM13:AP13) | GI13: =SUM(AQ13:AT13) | GJ13: =SUM(AU13:AX13) | GK13: =SUM(AY13:BB13) | GL13: =SUM(BC13:BF13) | GM13: =SUM(BG13:BJ13) | GN13: =SUM(BK13:BN13) | GO13: =SUM(BO13:BR13) | GP13: =SUM(BS13:BV13) | GQ13: =SUM(BW13:BZ13) | GR13: =SUM(CA13:CD13) | GS13: =SUM(CE13:CH13) | GT13: =SUM(CI13:CL13) | GU13: =SUM(CM13:CP13) | GV13: =SUM(CQ13:CT13) | GW13: =SUM(CU13:CX13) | GX13: =SUM(CY13:DB13) | GY13: =SUM(DC13:DF13) | GZ13: =SUM(DG13:DJ13) | HA13: =SUM(DK13:DN13) | HB13: =SUM(DO13:DR13) | HC13: =SUM(DS13:DV13) | HD13: =SUM(DW13:DZ13) | HE13: =SUM(EA13:ED13) | HF13: =SUM(EE13:EH13)
A14: Wearables, Home and Accessories | Z14: =Z197 | AA14: =AA197 | AB14: =AB197 | AC14: =AC197 | AD14: =AD197 | AE14: =AE197 | AF14: =AF197 | AG14: =AG197 | ... BU14: =BU197 | BV14: =BZ14/BZ197*BV197 | BW14: =CA14/CA197*BW197 | BX14: =CB14/CB197*BX197 | BY14: =CC14/CC197*BY197 | BZ14: =CD14/CD197*BZ197 | CA14: =CE14/CE197*CA197 | CB14: =CF14/CF197*CB197 | CC14: =CG14/CG197*CC197 | ... CK14: =CO14/CO197*CK197 | CL14: 5481 | CM14: 3944 | CN14: 3733 | CO14: 4223 | CP14: 7308 | CQ14: 5129 | CR14: 5525 | CS14: 6520 | CT14: 10010 | CU14: 6284 | CV14: 6450 | CW14: 7876 | CX14: 12971 | CY14: 7836 | CZ14: 8775 | DA14: 8785 | DB14: 14701 | DC14: 8806 | DD14: 8084 | DE14: ='Revenue summary'!DE14 | DF14: ='Revenue summary'!DF14 | DG14: ='Revenue summary'!DG14 | DH14: ='Revenue summary'!DH14 | DI14: ='Revenue summary'!DI14 | DJ14: ='Revenue summary'!DJ14 | DK14: ='Revenue summary'!DK14 | DL14: ='Revenue summary'!DL14 | ... DP14: ='Revenue summary'!DP14 | DQ14: =DQ15+DQ16+DQ17+DQ18 | DR14: =DR15+DR16+DR17+DR18 | DS14: =DS15+DS16+DS17+DS18 | DT14: =DT15+DT16+DT17+DT18 | DU14: =DU15+DU16+DU17+DU18 | DV14: =DV15+DV16+DV17+DV18 | DW14: =DW15+DW16+DW17+DW18 | DX14: =DX15+DX16+DX17+DX18 | ... EK14: =EK15+EK16+EK17+EK18 | ES14: =SUM(Z14:AC14) | ET14: =SUM(AD14:AG14) | EU14: =SUM(AH14:AK14) | EV14: =SUM(AL14:AO14) | EW14: =SUM(AP14:AS14) | EX14: =SUM(AT14:AW14) | EY14: =SUM(AX14:BA14) | EZ14: =SUM(BB14:BE14) | FA14: =SUM(BF14:BI14) | FB14: =SUM(BJ14:BM14) | FC14: =SUM(BN14:BQ14) | FD14: =SUM(BR14:BU14) | FE14: =SUM(BV14:BY14) | FF14: =SUM(BZ14:CC14) | FG14: =SUM(CD14:CG14) | FH14: ='Revenue summary'!FH14 | FI14: =SUM(CL14:CO14) | FJ14: =SUM(CP14:CS14) | FK14: =SUM(CT14:CW14) | FL14: =SUM(CX14:DA14) | FM14: =SUM(DB14:DE14) | FN14: =SUM(DF14:DI14) | FO14: =SUM(DJ14:DM14) | FP14: =SUM(DN14:DQ14) | FQ14: =SUM(DR14:DU14) | FR14: =SUM(DV14:DY14) | FS14: =SUM(DZ14:EC14) | FT14: =SUM(ED14:EG14) | FU14: =SUM(EH14:EK14) | FZ14: =SUM(G14:J14) | GA14: =SUM(K14:N14) | GB14: =SUM(O14:R14) | GC14: =SUM(S14:V14) | GD14: =SUM(W14:Z14) | GE14: =SUM(AA14:AD14) | GF14: =SUM(AE14:AH14) | GG14: =SUM(AI14:AL14) | GH14: =SUM(AM14:AP14) | GI14: =SUM(AQ14:AT14) | GJ14: =SUM(AU14:AX14) | GK14: =SUM(AY14:BB14) | GL14: =SUM(BC14:BF14) | GM14: =SUM(BG14:BJ14) | GN14: =SUM(BK14:BN14) | GO14: =SUM(BO14:BR14) | GP14: =SUM(BS14:BV14) | GQ14: =SUM(BW14:BZ14) | GR14: =SUM(CA14:CD14) | GS14: =SUM(CE14:CH14) | GT14: =SUM(CI14:CL14) | GU14: =SUM(CM14:CP14) | GV14: =SUM(CQ14:CT14) | GW14: =SUM(CU14:CX14) | GX14: =SUM(CY14:DB14) | GY14: =SUM(DC14:DF14) | GZ14: =SUM(DG14:DJ14) | HA14: =SUM(DK14:DN14) | HB14: =SUM(DO14:DR14) | HC14: =SUM(DS14:DV14) | HD14: =SUM(DW14:DZ14) | HE14: =SUM(EA14:ED14) | HF14: =SUM(EE14:EH14)
A15: Watch revenue | CB15: =+CB100*CB159 | CC15: =+CC100*CC159 | CD15: =+CD100*CD159 | CE15: =+CE100*CE159 | CF15: =+CF100*CF159 | CG15: =+CG100*CG159 | CH15: =+CH100*CH159 | CI15: =+CI100*CI159 | ... EK15: =+EK100*EK159 | FF15: =SUM(BZ15:CC15) | FG15: =SUM(CD15:CG15) | FH15: =SUM(CH15:CK15) | FI15: =SUM(CL15:CO15) | FJ15: =SUM(CP15:CS15) | FK15: =SUM(CT15:CW15) | FL15: =SUM(CX15:DA15) | FM15: =SUM(DB15:DE15) | FN15: =SUM(DF15:DI15) | FO15: =SUM(DJ15:DM15) | FP15: =SUM(DN15:DQ15) | FQ15: =SUM(DR15:DU15) | FR15: =SUM(DV15:DY15) | FS15: =SUM(DZ15:EC15) | FT15: =SUM(ED15:EG15) | FU15: =SUM(EH15:EK15) | GD15: =SUM(W15:Z15) | GE15: =SUM(AA15:AD15) | GF15: =SUM(AE15:AH15) | GG15: =SUM(AI15:AL15) | GH15: =SUM(AM15:AP15) | GI15: =SUM(AQ15:AT15) | GJ15: =SUM(AU15:AX15) | GK15: =SUM(AY15:BB15) | GL15: =SUM(BC15:BF15) | GM15: =SUM(BG15:BJ15) | GN15: =SUM(BK15:BN15) | GO15: =SUM(BO15:BR15) | GP15: =SUM(BS15:BV15) | GQ15: =SUM(BW15:BZ15) | GR15: =SUM(CA15:CD15) | GS15: =SUM(CE15:CH15) | GT15: =SUM(CI15:CL15) | GU15: =SUM(CM15:CP15) | GV15: =SUM(CQ15:CT15) | GW15: =SUM(CU15:CX15) | GX15: =SUM(CY15:DB15) | GY15: =SUM(DC15:DF15) | GZ15: =SUM(DG15:DJ15) | HA15: =SUM(DK15:DN15) | HB15: =SUM(DO15:DR15) | HC15: =SUM(DS15:DV15) | HD15: =SUM(DW15:DZ15) | HE15: =SUM(EA15:ED15) | HF15: =SUM(EE15:EH15)
A16: Accessories / Other | AV16: 308 | AZ16: 437 | BB16: 387 | BC16: 357 | BD16: 340 | BE16: =1475-BD16-BC16-BB16 | BF16: 469 | BG16: 472 | BH16: 396 | BI16: =1814-BH16-BG16-BF16 | BJ16: =+BJ197-BJ18-BJ15 | BK16: =+BK197-BK18-BK15 | BL16: =+BL197-BL18-BL15 | BM16: =+BM197-BM18-BM15 | BN16: =+BN197-BN18-BN15 | BO16: 1195 | BP16: 1227 | BQ16: =+BQ197-BQ18-BQ15 | BR16: 1829 | BS16: 1379 | BT16: 1179 | BU16: =+BU197-BU18-BU15 | BV16: =+BV14-BV18-BV15 | BW16: =+BW14-BW18-BW15 | BX16: =+BX14-BX18-BX15 | BY16: =+BY14-BY18-BY15 | BZ16: =+BZ14-BZ18-BZ15 | CA16: =+CA14-CA18-CA15 | CB16: =CB14-CB18-CB15 | CC16: =CC14-CC18-CC15 | CD16: =CD14-CD18-CD15 | CE16: =CE14-CE18-CE15 | CF16: =CF14-CF18-CF15 | CG16: =CG14-CG18-CG15 | CH16: =CH14-CH18-CH15 | CI16: =CI14-CI18-CI15 | ... CK16: =CK14-CK18-CK15 | CL16: =CL14-CL15 | CM16: =CM14-CM15 | CN16: =CN14-CN15 | CO16: =CO14-CO15 | CP16: =CP14-CP15 | CQ16: =CQ14-CQ15 | CR16: =CR14-CR15 | CS16: =CS14-CS15 | ... DA16: =DA14-DA15 | DB16: =DB14-DB15-DB18 | DC16: =DC14-DC15-DC18 | DD16: =DD14-DD15-DD18 | DE16: =DE14-DE15-DE18 | DF16: =DF14-DF15-DF18 | DG16: =DG14-DG15-DG18 | DH16: =DH14-DH15-DH18 | DI16: =DI14-DI15-DI18 | DJ16: =DJ14-DJ15-DJ18 | DK16: =DK14-DK15-DK18-DK17 | DL16: =DL14-DL15-DL18-DL17 | DM16: =DM14-DM15-DM18-DM17 | DN16: =DN14-DN15-DN18-DN17 | DO16: =DO14-DO15-DO18-DO17 | DP16: =DP14-DP15-DP18-DP17 | DQ16: =+DM16*(1+DQ27) | DR16: =+DN16*(1+DR27) | DS16: =+DO16*(1+DS27) | DT16: =+DP16*(1+DT27) | DU16: =+DQ16*(1+DU27) | DV16: =+DR16*(1+DV27) | DW16: =+DS16*(1+DW27) | DX16: =+DT16*(1+DX27) | ... EK16: =+EG16*(1+EK27) | FB16: =SUM(BJ16:BM16) | FC16: =SUM(BN16:BQ16) | FD16: =SUM(BR16:BU16) | FE16: =SUM(BV16:BY16) | FF16: =SUM(BZ16:CC16) | FG16: =SUM(CD16:CG16) | FH16: =SUM(CH16:CK16) | FI16: =SUM(CL16:CO16) | FJ16: =SUM(CP16:CS16) | FK16: =SUM(CT16:CW16) | FL16: =SUM(CX16:DA16) | FM16: =SUM(DB16:DE16) | FN16: =SUM(DF16:DI16) | FO16: =SUM(DJ16:DM16) | FP16: =SUM(DN16:DQ16) | FQ16: =SUM(DR16:DU16) | FR16: =SUM(DV16:DY16) | FS16: =SUM(DZ16:EC16) | FT16: =SUM(ED16:EG16) | FU16: =SUM(EH16:EK16) | GN16: =SUM(BK16:BN16) | GO16: =SUM(BO16:BR16) | GP16: =SUM(BS16:BV16) | GQ16: =SUM(BW16:BZ16) | GR16: =SUM(CA16:CD16) | GS16: =SUM(CE16:CH16) | GT16: =SUM(CI16:CL16) | GU16: =SUM(CM16:CP16) | GV16: =SUM(CQ16:CT16) | GW16: =SUM(CU16:CX16) | GX16: =SUM(CY16:DB16) | GY16: =SUM(DC16:DF16) | GZ16: =SUM(DG16:DJ16) | HA16: =SUM(DK16:DN16) | HB16: =SUM(DO16:DR16) | HC16: =SUM(DS16:DV16) | HD16: =SUM(DW16:DZ16) | HE16: =SUM(EA16:ED16) | HF16: =SUM(EE16:EH16)
A17: Product0448 | DK17: =0.1*3500 | DL17: =0.125*3500 | DM17: =0.1*3500 | DN17: =0.2*3000 | DO17: =0.2*3000 | DP17: =0.2*3000 | DQ17: =0.2*3000 | DR17: =0.5*2000 | DS17: =0.5*2000 | DT17: =0.5*2000 | DU17: =0.5*2000 | DV17: =0.5*2000 | DW17: =0.5*2000 | DX17: =0.5*2000 | DY17: =0.5*2000 | ... EK17: =0.5*2000 | FI17: =SUM(CL17:CO17) | FJ17: =SUM(CP17:CS17) | FK17: =SUM(CT17:CW17) | FL17: =SUM(CX17:DA17) | FM17: =SUM(DB17:DE17) | FN17: =SUM(DF17:DI17) | FO17: =SUM(DJ17:DM17) | FP17: =SUM(DN17:DQ17) | FQ17: =SUM(DR17:DU17) | FR17: =SUM(DV17:DY17) | FS17: =SUM(DZ17:EC17) | FT17: =SUM(ED17:EG17) | FU17: =SUM(EH17:EK17)
A18: Product0490 revenue | Z18: 46.625 | AA18: 21.375 | AB18: 22 | AC18: 53 | AD18: 81 | AE18: 32 | AF18: 111 | AG18: 121 | AH18: 256 | AI18: 264 | AJ18: 249 | AK18: 537 | AL18: 1211 | AM18: 1014 | AN18: 1103 | AO18: 1212 | AP18: 2906 | AQ18: 1714 | AR18: 1497 | AS18: 1559 | AT18: 3427 | AU18: 1689 | AV18: 1570 | AW18: 1619 | AX18: 3997 | AY18: 1818 | AZ18: 1678 | BA18: 1660 | BB18: 3371 | BC18: 1665 | BD18: 1492 | BE18: 1563 | BF18: 3391 | BG18: 1861 | BH18: 1545 | BI18: 1477 | BJ18: 3425 | BK18: 1600 | BL18: 1325 | BM18: 1103 | BN18: 2528 | BO18: 1207 | BP18: 1060 | BQ18: 820 | BR18: 2143 | BS18: 962 | BT18: 733 | BU18: 573 | BV18: 973 | BW18: 461 | BX18: 442 | BY18: 410 | BZ18: 653.87913 | CA18: 249.65013 | CB18: =+CB101*CB160 | CC18: =+CC101*CC160 | CD18: =+CD101*CD160 | CE18: =+CE101*CE160 | CF18: =+CF101*CF160 | CG18: =+CG101*CG160 | CH18: =+CH101*CH160 | CI18: =+CI101*CI160 | ... EK18: =+EK101*EK160 | ES18: =SUM(Z18:AC18) | ET18: =SUM(AD18:AG18) | EU18: =SUM(AH18:AK18) | EV18: =SUM(AL18:AO18) | EW18: =SUM(AP18:AS18) | EX18: =SUM(AT18:AW18) | EY18: =SUM(AX18:BA18) | EZ18: =SUM(BB18:BE18) | FA18: =SUM(BF18:BI18) | FB18: =SUM(BJ18:BM18) | FC18: =SUM(BN18:BQ18) | FD18: =SUM(BR18:BU18) | FE18: =SUM(BV18:BY18) | FF18: =SUM(BZ18:CC18) | FG18: =SUM(CD18:CG18) | FH18: =SUM(CH18:CK18) | FI18: =SUM(CL18:CO18) | FJ18: =SUM(CP18:CS18) | FK18: =SUM(CT18:CW18) | FL18: =SUM(CX18:DA18) | FM18: =SUM(DB18:DE18) | FN18: =SUM(DF18:DI18) | FO18: =SUM(DJ18:DM18) | FP18: =SUM(DN18:DQ18) | FQ18: =SUM(DR18:DU18) | FR18: =SUM(DV18:DY18) | FS18: =SUM(DZ18:EC18) | FT18: =SUM(ED18:EG18) | FU18: =SUM(EH18:EK18) | GD18: =SUM(W18:Z18) | GE18: =SUM(AA18:AD18) | GF18: =SUM(AE18:AH18) | GG18: =SUM(AI18:AL18) | GH18: =SUM(AM18:AP18) | GI18: =SUM(AQ18:AT18) | GJ18: =SUM(AU18:AX18) | GK18: =SUM(AY18:BB18) | GL18: =SUM(BC18:BF18) | GM18: =SUM(BG18:BJ18) | GN18: =SUM(BK18:BN18) | GO18: =SUM(BO18:BR18) | GP18: =SUM(BS18:BV18) | GQ18: =SUM(BW18:BZ18) | GR18: =SUM(CA18:CD18) | GS18: =SUM(CE18:CH18) | GT18: =SUM(CI18:CL18) | GU18: =SUM(CM18:CP18) | GV18: =SUM(CQ18:CT18) | GW18: =SUM(CU18:CX18) | GX18: =SUM(CY18:DB18) | GY18: =SUM(DC18:DF18) | GZ18: =SUM(DG18:DJ18) | HA18: =SUM(DK18:DN18) | HB18: =SUM(DO18:DR18) | HC18: =SUM(DS18:DV18) | HD18: =SUM(DW18:DZ18) | HE18: =SUM(EA18:ED18) | HF18: =SUM(EE18:EH18)
A19: Total product revenue | R19: =SUM(R12:R18) | S19: =SUM(S12:S18) | T19: =SUM(T12:T18) | U19: =SUM(U12:U18) | V19: =SUM(V12:V18) | W19: =SUM(W12:W18) | X19: =SUM(X12:X18) | Y19: =SUM(Y12:Y18) | ... AS19: =SUM(AS12:AS18) | AT19: ='Revenue summary'!AT15 | AU19: ='Revenue summary'!AU15 | AV19: ='Revenue summary'!AV15 | AW19: ='Revenue summary'!AW15 | AX19: ='Revenue summary'!AX15 | AY19: ='Revenue summary'!AY15 | AZ19: ='Revenue summary'!AZ15 | BA19: ='Revenue summary'!BA15 | ... BU19: ='Revenue summary'!BU15 | BV19: =SUM(BV11:BV14) | BW19: =SUM(BW11:BW14) | BX19: =SUM(BX11:BX14) | BY19: =SUM(BY11:BY14) | BZ19: =SUM(BZ11:BZ14) | CA19: =SUM(CA11:CA14) | CB19: =SUM(CB11:CB14) | CC19: =SUM(CC11:CC14) | ... EK19: =SUM(EK11:EK14) | EO19: =SUM(EO11+EO13+EO12+EO14) | EP19: =SUM(EP11+EP13+EP12+EP14) | EQ19: =SUM(EQ11+EQ13+EQ12+EQ14) | ER19: =SUM(ER11+ER13+ER12+ER14) | ES19: =SUM(ES11+ES13+ES12+ES14) | ET19: =SUM(ET11+ET13+ET12+ET14) | EU19: =SUM(EU11+EU13+EU12+EU14) | EV19: =SUM(EV11+EV13+EV12+EV14) | ... FU19: =SUM(FU11+FU13+FU12+FU14) | FZ19: =SUM(FZ11+FZ13+FZ12+FZ14) | GA19: =SUM(GA11+GA13+GA12+GA14) | GB19: =SUM(GB11+GB13+GB12+GB14) | GC19: =SUM(GC11+GC13+GC12+GC14) | GD19: =SUM(GD11+GD13+GD12+GD14) | GE19: =SUM(GE11+GE13+GE12+GE14) | GF19: =SUM(GF11+GF13+GF12+GF14) | GG19: =SUM(GG11+GG13+GG12+GG14) | ... HF19: =SUM(HF11+HF13+HF12+HF14)
A21: Product revenue, year-over-year change (%) | B21: ='Revenue summary'!B$8 | C21: ='Revenue summary'!C$8 | D21: ='Revenue summary'!D$8 | E21: ='Revenue summary'!E$8 | F21: ='Revenue summary'!F$8 | G21: ='Revenue summary'!G$8 | H21: ='Revenue summary'!H$8 | I21: ='Revenue summary'!I$8 | ... EK21: ='Revenue summary'!EK$8 | EM21: =EM$9 | EN21: =EN$9 | EO21: =EO$9 | EP21: =EP$9 | EQ21: =EQ$9 | ER21: =ER$9 | ES21: =ES$9 | ET21: =ET$9 | ... FU21: =FU$9 | FY21: =FY$9 | FZ21: =FZ$9 | GA21: =GA$9 | GB21: =GB$9 | GC21: =GC$9 | GD21: =GD$9 | GE21: =GE$9 | GF21: =GF$9 | ... HF21: =HF$9
A22: Product0489 | BF22: =+BF11/BB11-1 | BG22: =+BG11/BC11-1 | BH22: =+BH11/BD11-1 | BI22: =+BI11/BE11-1 | BJ22: =+BJ11/BF11-1 | BK22: =+BK11/BG11-1 | BL22: =+BL11/BH11-1 | BM22: =+BM11/BI11-1 | ... EK22: =+EK11/EG11-1 | FA22: =+FA11/EZ11-1 | FB22: =+FB11/FA11-1 | FC22: =+FC11/FB11-1 | FD22: =+FD11/FC11-1 | FE22: =+FE11/FD11-1 | FF22: =+FF11/FE11-1 | FG22: =+FG11/FF11-1 | FH22: =+FH11/FG11-1 | ... FU22: =+FU11/FT11-1 | GL22: =+GL11/GK11-1 | GM22: =+GM11/GL11-1 | GN22: =+GN11/GM11-1 | GO22: =+GO11/GN11-1 | GP22: =+GP11/GO11-1 | GQ22: =+GQ11/GP11-1 | GR22: =+GR11/GQ11-1 | GS22: =+GS11/GR11-1 | ... HF22: =+HF11/HE11-1
A23: Mac | AX23: =+AX12/AT12-1 | AY23: =+AY12/AU12-1 | AZ23: =+AZ12/AV12-1 | BA23: =+BA12/AW12-1 | BB23: =+BB12/AX12-1 | BC23: =+BC12/AY12-1 | BD23: =+BD12/AZ12-1 | BE23: =+BE12/BA12-1 | ... EK23: =+EK12/EG12-1 | EP23: =+EP12/EO12-1 | EQ23: =+EQ12/EP12-1 | ER23: =+ER12/EQ12-1 | ES23: =+ES12/ER12-1 | ET23: =+ET12/ES12-1 | EU23: =+EU12/ET12-1 | EV23: =+EV12/EU12-1 | EW23: =+EW12/EV12-1 | ... FU23: =+FU12/FT12-1 | GA23: =+GA12/FZ12-1 | GB23: =+GB12/GA12-1 | GC23: =+GC12/GB12-1 | GD23: =+GD12/GC12-1 | GE23: =+GE12/GD12-1 | GF23: =+GF12/GE12-1 | GG23: =+GG12/GF12-1 | GH23: =+GH12/GG12-1 | ... HF23: =+HF12/HE12-1
A24: Product0487 | BZ24: =+BZ13/BV13-1 | CA24: =+CA13/BW13-1 | CB24: =+CB13/BX13-1 | CC24: =+CC13/BY13-1 | CD24: =+CD13/BZ13-1 | CE24: =+CE13/CA13-1 | CF24: =+CF13/CB13-1 | CG24: =+CG13/CC13-1 | ... EK24: =+EK13/EG13-1 | FB24: =+FB13/FA13-1 | FC24: =+FC13/FB13-1 | FD24: =+FD13/FC13-1 | FE24: =+FE13/FD13-1 | FF24: =+FF13/FE13-1 | FG24: =+FG13/FF13-1 | FH24: =+FH13/FG13-1 | FI24: =+FI13/FH13-1 | ... FU24: =+FU13/FT13-1 | GN24: =+GN13/GM13-1 | GO24: =+GO13/GN13-1 | GP24: =+GP13/GO13-1 | GQ24: =+GQ13/GP13-1 | GR24: =+GR13/GQ13-1 | GS24: =+GS13/GR13-1 | GT24: =+GT13/GS13-1 | GU24: =+GU13/GT13-1 | ... HF24: =+HF13/HE13-1
A25: Wearables, Home and Accessories | AX25: =+AX14/AT14-1 | AY25: =+AY14/AU14-1 | AZ25: =+AZ14/AV14-1 | BA25: =+BA14/AW14-1 | BB25: =+BB14/AX14-1 | BC25: =+BC14/AY14-1 | BD25: =+BD14/AZ14-1 | BE25: =+BE14/BA14-1 | ... EK25: =+EK14/EG14-1 | ET25: =+ET14/ES14-1 | EU25: =+EU14/ET14-1 | EV25: =+EV14/EU14-1 | EW25: =+EW14/EV14-1 | EX25: =+EX14/EW14-1 | EY25: =+EY14/EX14-1 | EZ25: =+EZ14/EY14-1 | FA25: =+FA14/EZ14-1 | ... FU25: =+FU14/FT14-1 | GE25: =+GE14/GD14-1 | GF25: =+GF14/GE14-1 | GG25: =+GG14/GF14-1 | GH25: =+GH14/GG14-1 | GI25: =+GI14/GH14-1 | GJ25: =+GJ14/GI14-1 | GK25: =+GK14/GJ14-1 | GL25: =+GL14/GK14-1 | ... HF25: =+HF14/HE14-1
A26: Watch revenue | CF26: =+CF15/CB15-1 | CG26: =+CG15/CC15-1 | CH26: =+CH15/CD15-1 | CI26: =+CI15/CE15-1 | CJ26: =+CJ15/CF15-1 | CK26: =+CK15/CG15-1 | CL26: =+CL15/CH15-1 | CM26: =+CM15/CI15-1 | ... EK26: =+EK15/EG15-1 | FG26: =+FG15/FF15-1 | FH26: =+FH15/FG15-1 | FI26: =+FI15/FH15-1 | FJ26: =+FJ15/FI15-1 | FK26: =+FK15/FJ15-1 | FL26: =+FL15/FK15-1 | FM26: =+FM15/FL15-1 | FN26: =+FN15/FM15-1 | ... FU26: =+FU15/FT15-1 | GS26: =+GS15/GR15-1 | GT26: =+GT15/GS15-1 | GU26: =+GU15/GT15-1 | GV26: =+GV15/GU15-1 | GW26: =+GW15/GV15-1 | GX26: =+GX15/GW15-1 | GY26: =+GY15/GX15-1 | GZ26: =+GZ15/GY15-1 | ... HF26: =+HF15/HE15-1
A27: Accessories / Other | BN27: =+BN16/BJ16-1 | BO27: =+BO16/BK16-1 | BP27: =+BP16/BL16-1 | BQ27: =+BQ16/BM16-1 | BR27: =+BR16/BN16-1 | BS27: =+BS16/BO16-1 | BT27: =+BT16/BP16-1 | BU27: =+BU16/BQ16-1 | ... DH27: =+DH16/DD16-1 | DI27: =DI16/DE16-1 | DJ27: =+DJ16/DF16-1 | DK27: =+DK16/DG16-1 | DL27: =+DL16/DH16-1 | DM27: =DM16/DI16-1 | DN27: =+DN16/DJ16-1 | DO27: =+DO16/DK16-1 | DP27: =+DP16/DL16-1 | DQ27: -0.05 | DR27: 0 | DS27: 0 | DT27: 0 | DU27: 0 | DV27: 0 | DW27: 0 | DX27: 0 | DY27: 0 | DZ27: 0 | EA27: 0 | EB27: 0 | EC27: 0 | ED27: 0 | EE27: 0 | EF27: 0 | EG27: 0 | EH27: 0 | EI27: 0 | EJ27: 0 | EK27: 0 | FC27: =+FC16/FB16-1 | FD27: =+FD16/FC16-1 | FE27: =+FE16/FD16-1 | FF27: =+FF16/FE16-1 | FG27: =+FG16/FF16-1 | FH27: =+FH16/FG16-1 | FI27: =+FI16/FH16-1 | FJ27: =+FJ16/FI16-1 | ... FU27: =+FU16/FT16-1 | GO27: =+GO16/GN16-1 | GP27: =+GP16/GO16-1 | GQ27: =+GQ16/GP16-1 | GR27: =+GR16/GQ16-1 | GS27: =+GS16/GR16-1 | GT27: =+GT16/GS16-1 | GU27: =+GU16/GT16-1 | GV27: =+GV16/GU16-1 | ... HF27: =+HF16/HE16-1
A28: =A17 | DB28: =IF(ISERROR(DB17/CX17-1),"NA",DB17/CX17-1) | DC28: =IF(ISERROR(DC17/CY17-1),"NA",DC17/CY17-1) | DD28: =IF(ISERROR(DD17/CZ17-1),"NA",DD17/CZ17-1) | DE28: =IF(ISERROR(DE17/DA17-1),"NA",DE17/DA17-1) | DF28: =IF(ISERROR(DF17/DB17-1),"NA",DF17/DB17-1) | DG28: =IF(ISERROR(DG17/DC17-1),"NA",DG17/DC17-1) | DH28: =IF(ISERROR(DH17/DD17-1),"NA",DH17/DD17-1) | DI28: =IF(ISERROR(DI17/DE17-1),"NA",DI17/DE17-1) | ... EK28: =IF(ISERROR(EK17/EG17-1),"NA",EK17/EG17-1) | FP28: =+FP17/FO17-1 | FQ28: =+FQ17/FP17-1 | FR28: =+FR17/FQ17-1 | FS28: =+FS17/FR17-1 | FT28: =+FT17/FS17-1 | FU28: =+FU17/FT17-1
A29: Product0490 revenue | AT29: =+AT18/AP18-1 | AU29: =+AU18/AQ18-1 | AV29: =+AV18/AR18-1 | AW29: =+AW18/AS18-1 | AX29: =+AX18/AT18-1 | AY29: =+AY18/AU18-1 | AZ29: =+AZ18/AV18-1 | BA29: =+BA18/AW18-1 | ... CN29: =+CN18/CJ18-1 | CO29: =IF(ISERROR(CO18/CK18-1),"NA",CO18/CK18-1) | CP29: =IF(ISERROR(CP18/CL18-1),"NA",CP18/CL18-1) | CQ29: =IF(ISERROR(CQ18/CM18-1),"NA",CQ18/CM18-1) | CR29: =IF(ISERROR(CR18/CN18-1),"NA",CR18/CN18-1) | CS29: =IF(ISERROR(CS18/CO18-1),"NA",CS18/CO18-1) | CT29: =IF(ISERROR(CT18/CP18-1),"NA",CT18/CP18-1) | CU29: =IF(ISERROR(CU18/CQ18-1),"NA",CU18/CQ18-1) | CV29: =IF(ISERROR(CV18/CR18-1),"NA",CV18/CR18-1) | ... EK29: =IF(ISERROR(EK18/EG18-1),"NA",EK18/EG18-1) | ET29: =+ET18/ES18-1 | EU29: =+EU18/ET18-1 | EV29: =+EV18/EU18-1 | EW29: =+EW18/EV18-1 | EX29: =+EX18/EW18-1 | EY29: =+EY18/EX18-1 | EZ29: =+EZ18/EY18-1 | FA29: =+FA18/EZ18-1 | ... FI29: =+FI18/FH18-1 | GE29: =+GE18/GD18-1 | GF29: =+GF18/GE18-1 | GG29: =+GG18/GF18-1 | GH29: =+GH18/GG18-1 | GI29: =+GI18/GH18-1 | GJ29: =+GJ18/GI18-1 | GK29: =+GK18/GJ18-1 | GL29: =+GL18/GK18-1 | ... GU29: =+GU18/GT18-1
A30: Total product revenue | AX30: =+AX19/AT19-1 | AY30: =+AY19/AU19-1 | AZ30: =+AZ19/AV19-1 | BA30: =+BA19/AW19-1 | BB30: =+BB19/AX19-1 | BC30: =+BC19/AY19-1 | BD30: =+BD19/AZ19-1 | BE30: =+BE19/BA19-1 | ... EK30: =+EK19/EG19-1 | EP30: =+EP19/EO19-1 | EQ30: =+EQ19/EP19-1 | ER30: =+ER19/EQ19-1 | ES30: =+ES19/ER19-1 | ET30: =+ET19/ES19-1 | EU30: =+EU19/ET19-1 | EV30: =+EV19/EU19-1 | EW30: =+EW19/EV19-1 | ... FU30: =+FU19/FT19-1 | GA30: =+GA19/FZ19-1 | GB30: =+GB19/GA19-1 | GC30: =+GC19/GB19-1 | GD30: =+GD19/GC19-1 | GE30: =+GE19/GD19-1 | GF30: =+GF19/GE19-1 | GG30: =+GG19/GF19-1 | GH30: =+GH19/GG19-1 | ... HF30: =+HF19/HE19-1
A32: Product revenue, quarter-over-quarter change (%) | B32: ='Revenue summary'!B$8 | C32: ='Revenue summary'!C$8 | D32: ='Revenue summary'!D$8 | E32: ='Revenue summary'!E$8 | F32: ='Revenue summary'!F$8 | G32: ='Revenue summary'!G$8 | H32: ='Revenue summary'!H$8 | I32: ='Revenue summary'!I$8 | ... EK32: ='Revenue summary'!EK$8
A33: Product0489 | BD33: =IF(ISERROR(BD11/BC11-1),"NA",BD11/BC11-1) | BE33: =IF(ISERROR(BE11/BD11-1),"NA",BE11/BD11-1) | BF33: =IF(ISERROR(BF11/BE11-1),"NA",BF11/BE11-1) | BG33: =IF(ISERROR(BG11/BF11-1),"NA",BG11/BF11-1) | BH33: =IF(ISERROR(BH11/BG11-1),"NA",BH11/BG11-1) | BI33: =IF(ISERROR(BI11/BH11-1),"NA",BI11/BH11-1) | BJ33: =IF(ISERROR(BJ11/BI11-1),"NA",BJ11/BI11-1) | BK33: =IF(ISERROR(BK11/BJ11-1),"NA",BK11/BJ11-1) | ... EK33: =IF(ISERROR(EK11/EJ11-1),"NA",EK11/EJ11-1)
A34: Mac | AT34: =IF(ISERROR(AT12/AS12-1),"NA",AT12/AS12-1) | AU34: =IF(ISERROR(AU12/AT12-1),"NA",AU12/AT12-1) | AV34: =IF(ISERROR(AV12/AU12-1),"NA",AV12/AU12-1) | AW34: =IF(ISERROR(AW12/AV12-1),"NA",AW12/AV12-1) | AX34: =IF(ISERROR(AX12/AW12-1),"NA",AX12/AW12-1) | AY34: =IF(ISERROR(AY12/AX12-1),"NA",AY12/AX12-1) | AZ34: =IF(ISERROR(AZ12/AY12-1),"NA",AZ12/AY12-1) | BA34: =IF(ISERROR(BA12/AZ12-1),"NA",BA12/AZ12-1) | ... EK34: =IF(ISERROR(EK12/EJ12-1),"NA",EK12/EJ12-1)
A35: Product0487 | BD35: =IF(ISERROR(BD13/BC13-1),"NA",BD13/BC13-1) | BE35: =IF(ISERROR(BE13/BD13-1),"NA",BE13/BD13-1) | BF35: =IF(ISERROR(BF13/BE13-1),"NA",BF13/BE13-1) | BG35: =IF(ISERROR(BG13/BF13-1),"NA",BG13/BF13-1) | BH35: =IF(ISERROR(BH13/BG13-1),"NA",BH13/BG13-1) | BI35: =IF(ISERROR(BI13/BH13-1),"NA",BI13/BH13-1) | BJ35: =IF(ISERROR(BJ13/BI13-1),"NA",BJ13/BI13-1) | BK35: =IF(ISERROR(BK13/BJ13-1),"NA",BK13/BJ13-1) | ... EK35: =IF(ISERROR(EK13/EJ13-1),"NA",EK13/EJ13-1)
A36: Wearables, Home and Accessories | AT36: =IF(ISERROR(AT14/AS14-1),"NA",AT14/AS14-1) | AU36: =IF(ISERROR(AU14/AT14-1),"NA",AU14/AT14-1) | AV36: =IF(ISERROR(AV14/AU14-1),"NA",AV14/AU14-1) | AW36: =IF(ISERROR(AW14/AV14-1),"NA",AW14/AV14-1) | AX36: =IF(ISERROR(AX14/AW14-1),"NA",AX14/AW14-1) | AY36: =IF(ISERROR(AY14/AX14-1),"NA",AY14/AX14-1) | AZ36: =IF(ISERROR(AZ14/AY14-1),"NA",AZ14/AY14-1) | BA36: =IF(ISERROR(BA14/AZ14-1),"NA",BA14/AZ14-1) | ... EK36: =IF(ISERROR(EK14/EJ14-1),"NA",EK14/EJ14-1)
A37: Watch revenue | BC37: =IF(ISERROR(BC15/BB15-1),"NA",BC15/BB15-1) | BD37: =IF(ISERROR(BD15/BC15-1),"NA",BD15/BC15-1) | BE37: =IF(ISERROR(BE15/BD15-1),"NA",BE15/BD15-1) | BF37: =IF(ISERROR(BF15/BE15-1),"NA",BF15/BE15-1) | BG37: =IF(ISERROR(BG15/BF15-1),"NA",BG15/BF15-1) | BH37: =IF(ISERROR(BH15/BG15-1),"NA",BH15/BG15-1) | BI37: =IF(ISERROR(BI15/BH15-1),"NA",BI15/BH15-1) | BJ37: =IF(ISERROR(BJ15/BI15-1),"NA",BJ15/BI15-1) | ... EK37: =IF(ISERROR(EK15/EJ15-1),"NA",EK15/EJ15-1)
A38: Accessories / Other | BC38: =IF(ISERROR(BC16/BB16-1),"NA",BC16/BB16-1) | BD38: =IF(ISERROR(BD16/BC16-1),"NA",BD16/BC16-1) | BE38: =IF(ISERROR(BE16/BD16-1),"NA",BE16/BD16-1) | BF38: =IF(ISERROR(BF16/BE16-1),"NA",BF16/BE16-1) | BG38: =IF(ISERROR(BG16/BF16-1),"NA",BG16/BF16-1) | BH38: =IF(ISERROR(BH16/BG16-1),"NA",BH16/BG16-1) | BI38: =IF(ISERROR(BI16/BH16-1),"NA",BI16/BH16-1) | BJ38: =IF(ISERROR(BJ16/BI16-1),"NA",BJ16/BI16-1) | ... EK38: =IF(ISERROR(EK16/EJ16-1),"NA",EK16/EJ16-1)
A39: =A28 | AT39: =IF(ISERROR(AT17/AS17-1),"NA",AT17/AS17-1) | AU39: =IF(ISERROR(AU17/AT17-1),"NA",AU17/AT17-1) | AV39: =IF(ISERROR(AV17/AU17-1),"NA",AV17/AU17-1) | AW39: =IF(ISERROR(AW17/AV17-1),"NA",AW17/AV17-1) | AX39: =IF(ISERROR(AX17/AW17-1),"NA",AX17/AW17-1) | AY39: =IF(ISERROR(AY17/AX17-1),"NA",AY17/AX17-1) | AZ39: =IF(ISERROR(AZ17/AY17-1),"NA",AZ17/AY17-1) | BA39: =IF(ISERROR(BA17/AZ17-1),"NA",BA17/AZ17-1) | ... EK39: =IF(ISERROR(EK17/EJ17-1),"NA",EK17/EJ17-1)
A40: Product0490 revenue | AT40: =IF(ISERROR(AT18/AS18-1),"NA",AT18/AS18-1) | AU40: =IF(ISERROR(AU18/AT18-1),"NA",AU18/AT18-1) | AV40: =IF(ISERROR(AV18/AU18-1),"NA",AV18/AU18-1) | AW40: =IF(ISERROR(AW18/AV18-1),"NA",AW18/AV18-1) | AX40: =IF(ISERROR(AX18/AW18-1),"NA",AX18/AW18-1) | AY40: =IF(ISERROR(AY18/AX18-1),"NA",AY18/AX18-1) | AZ40: =IF(ISERROR(AZ18/AY18-1),"NA",AZ18/AY18-1) | BA40: =IF(ISERROR(BA18/AZ18-1),"NA",BA18/AZ18-1) | ... EK40: =IF(ISERROR(EK18/EJ18-1),"NA",EK18/EJ18-1)
A41: Total product revenue | AT41: =IF(ISERROR(AT19/AS19-1),"NA",AT19/AS19-1) | AU41: =IF(ISERROR(AU19/AT19-1),"NA",AU19/AT19-1) | AV41: =IF(ISERROR(AV19/AU19-1),"NA",AV19/AU19-1) | AW41: =IF(ISERROR(AW19/AV19-1),"NA",AW19/AV19-1) | AX41: =IF(ISERROR(AX19/AW19-1),"NA",AX19/AW19-1) | AY41: =IF(ISERROR(AY19/AX19-1),"NA",AY19/AX19-1) | AZ41: =IF(ISERROR(AZ19/AY19-1),"NA",AZ19/AY19-1) | BA41: =IF(ISERROR(BA19/AZ19-1),"NA",BA19/AZ19-1) | ... EK41: =IF(ISERROR(EK19/EJ19-1),"NA",EK19/EJ19-1)
A43: Estimated product revenue ($, mn) | B43: ='Revenue summary'!B$8 | C43: ='Revenue summary'!C$8 | D43: ='Revenue summary'!D$8 | E43: ='Revenue summary'!E$8 | F43: ='Revenue summary'!F$8 | G43: ='Revenue summary'!G$8 | H43: ='Revenue summary'!H$8 | I43: ='Revenue summary'!I$8 | ... CJ43: ='Revenue summary'!CJ$8 | CK43: =CK$32 | CL43: =CL$32 | CM43: =CM$32 | CN43: =CN$32 | CO43: =CO$32 | CP43: =CP$32 | CQ43: =CQ$32 | CR43: =CR$32 | ... EK43: =EK$32
A44: Product0487 | CH44: =CH94*CH153 | CI44: =CI94*CI153 | CJ44: =CJ94*CJ153 | CK44: =CK94*CK153 | CL44: =CL94*CL153 | CM44: =CM94*CM153 | CN44: =CN94*CN153 | CO44: =CO94*CO153 | ... EK44: =EK94*EK153 | EM44: =SUM(B44:E44) | EN44: =SUM(F44:I44) | EO44: =SUM(J44:M44) | EP44: =SUM(N44:Q44) | EQ44: =SUM(R44:U44) | ER44: =SUM(V44:Y44) | ES44: =SUM(Z44:AC44) | ET44: =SUM(AD44:AG44) | EU44: =SUM(AH44:AK44) | EV44: =SUM(AL44:AO44) | EW44: =SUM(AP44:AS44) | EX44: =SUM(AT44:AW44) | EY44: =SUM(AX44:BA44) | EZ44: =SUM(BB44:BE44) | FA44: =SUM(BF44:BI44) | FB44: =SUM(BJ44:BM44) | FC44: =SUM(BN44:BQ44) | FD44: =SUM(BR44:BU44) | FE44: =SUM(BV44:BY44) | FF44: =SUM(BZ44:CC44) | FH44: =SUM(CH44:CK44) | FI44: =SUM(CL44:CO44) | FJ44: =SUM(CP44:CS44) | FK44: =SUM(CT44:CW44) | FL44: =SUM(CX44:DA44) | FM44: =SUM(DB44:DE44) | FN44: =SUM(DF44:DI44) | FO44: =SUM(DJ44:DM44) | FP44: =SUM(DN44:DQ44) | FQ44: =SUM(DR44:DU44) | FR44: =SUM(DV44:DY44) | FS44: =SUM(DZ44:EC44) | FT44: =SUM(ED44:EG44) | FU44: =SUM(EH44:EK44) | FZ44: =SUM(G44:J44) | GA44: =SUM(K44:N44) | GB44: =SUM(O44:R44) | GC44: =SUM(S44:V44) | GD44: =SUM(W44:Z44) | GE44: =SUM(AA44:AD44) | GF44: =SUM(AE44:AH44) | GG44: =SUM(AI44:AL44) | GH44: =SUM(AM44:AP44) | GI44: =SUM(AQ44:AT44) | GJ44: =SUM(AU44:AX44) | GK44: =SUM(AY44:BB44) | GL44: =SUM(BC44:BF44) | GM44: =SUM(BG44:BJ44) | GN44: =SUM(BK44:BN44) | GO44: =SUM(BO44:BR44) | GP44: =SUM(BS44:BV44) | GQ44: =SUM(BW44:BZ44) | GR44: =SUM(CA44:CD44) | GS44: =SUM(CE44:CH44) | GT44: =SUM(CI44:CL44) | GU44: =SUM(CM44:CP44) | GV44: =SUM(CQ44:CT44) | GW44: =SUM(CU44:CX44) | GX44: =SUM(CY44:DB44) | GY44: =SUM(DC44:DF44) | GZ44: =SUM(DG44:DJ44) | HA44: =SUM(DK44:DN44) | HB44: =SUM(DO44:DR44) | HC44: =SUM(DS44:DV44) | HD44: =SUM(DW44:DZ44) | HE44: =SUM(EA44:ED44) | HF44: =SUM(EE44:EH44)
A45: Product0487 Pro | CH45: =CH95*CH154 | CI45: =CI95*CI154 | CJ45: =CJ95*CJ154 | CK45: =CK95*CK154 | CL45: =CL95*CL154 | CM45: =CM95*CM154 | CN45: =CN95*CN154 | CO45: =CO95*CO154 | ... EK45: =EK95*EK154 | EM45: =SUM(B45:E45) | EN45: =SUM(F45:I45) | EO45: =SUM(J45:M45) | EP45: =SUM(N45:Q45) | EQ45: =SUM(R45:U45) | ER45: =SUM(V45:Y45) | ES45: =SUM(Z45:AC45) | ET45: =SUM(AD45:AG45) | EU45: =SUM(AH45:AK45) | EV45: =SUM(AL45:AO45) | EW45: =SUM(AP45:AS45) | EX45: =SUM(AT45:AW45) | EY45: =SUM(AX45:BA45) | EZ45: =SUM(BB45:BE45) | FA45: =SUM(BF45:BI45) | FB45: =SUM(BJ45:BM45) | FC45: =SUM(BN45:BQ45) | FD45: =SUM(BR45:BU45) | FE45: =SUM(BV45:BY45) | FF45: =SUM(BZ45:CC45) | FH45: =SUM(CH45:CK45) | FI45: =SUM(CL45:CO45) | FJ45: =SUM(CP45:CS45) | FK45: =SUM(CT45:CW45) | FL45: =SUM(CX45:DA45) | FM45: =SUM(DB45:DE45) | FN45: =SUM(DF45:DI45) | FO45: =SUM(DJ45:DM45) | FP45: =SUM(DN45:DQ45) | FQ45: =SUM(DR45:DU45) | FR45: =SUM(DV45:DY45) | FS45: =SUM(DZ45:EC45) | FT45: =SUM(ED45:EG45) | FU45: =SUM(EH45:EK45) | FZ45: =SUM(G45:J45) | GA45: =SUM(K45:N45) | GB45: =SUM(O45:R45) | GC45: =SUM(S45:V45) | GD45: =SUM(W45:Z45) | GE45: =SUM(AA45:AD45) | GF45: =SUM(AE45:AH45) | GG45: =SUM(AI45:AL45) | GH45: =SUM(AM45:AP45) | GI45: =SUM(AQ45:AT45) | GJ45: =SUM(AU45:AX45) | GK45: =SUM(AY45:BB45) | GL45: =SUM(BC45:BF45) | GM45: =SUM(BG45:BJ45) | GN45: =SUM(BK45:BN45) | GO45: =SUM(BO45:BR45) | GP45: =SUM(BS45:BV45) | GQ45: =SUM(BW45:BZ45) | GR45: =SUM(CA45:CD45) | GS45: =SUM(CE45:CH45) | GT45: =SUM(CI45:CL45) | GU45: =SUM(CM45:CP45) | GV45: =SUM(CQ45:CT45) | GW45: =SUM(CU45:CX45) | GX45: =SUM(CY45:DB45) | GY45: =SUM(DC45:DF45) | GZ45: =SUM(DG45:DJ45) | HA45: =SUM(DK45:DN45) | HB45: =SUM(DO45:DR45) | HC45: =SUM(DS45:DV45) | HD45: =SUM(DW45:DZ45) | HE45: =SUM(EA45:ED45) | HF45: =SUM(EE45:EH45)
A46: Product0487 Air | CH46: =CH96*CH155 | CI46: =CI96*CI155 | CJ46: =CJ96*CJ155 | CK46: =CK96*CK155 | CL46: =CL96*CL155 | CM46: =CM96*CM155 | CN46: =CN96*CN155 | CO46: =CO96*CO155 | ... EK46: =EK96*EK155 | EM46: =SUM(B46:E46) | EN46: =SUM(F46:I46) | EO46: =SUM(J46:M46) | EP46: =SUM(N46:Q46) | EQ46: =SUM(R46:U46) | ER46: =SUM(V46:Y46) | ES46: =SUM(Z46:AC46) | ET46: =SUM(AD46:AG46) | EU46: =SUM(AH46:AK46) | EV46: =SUM(AL46:AO46) | EW46: =SUM(AP46:AS46) | EX46: =SUM(AT46:AW46) | EY46: =SUM(AX46:BA46) | EZ46: =SUM(BB46:BE46) | FA46: =SUM(BF46:BI46) | FB46: =SUM(BJ46:BM46) | FC46: =SUM(BN46:BQ46) | FD46: =SUM(BR46:BU46) | FE46: =SUM(BV46:BY46) | FF46: =SUM(BZ46:CC46) | FH46: =SUM(CH46:CK46) | FI46: =SUM(CL46:CO46) | FJ46: =SUM(CP46:CS46) | FK46: =SUM(CT46:CW46) | FL46: =SUM(CX46:DA46) | FM46: =SUM(DB46:DE46) | FN46: =SUM(DF46:DI46) | FO46: =SUM(DJ46:DM46) | FP46: =SUM(DN46:DQ46) | FQ46: =SUM(DR46:DU46) | FR46: =SUM(DV46:DY46) | FS46: =SUM(DZ46:EC46) | FT46: =SUM(ED46:EG46) | FU46: =SUM(EH46:EK46) | FZ46: =SUM(G46:J46) | GA46: =SUM(K46:N46) | GB46: =SUM(O46:R46) | GC46: =SUM(S46:V46) | GD46: =SUM(W46:Z46) | GE46: =SUM(AA46:AD46) | GF46: =SUM(AE46:AH46) | GG46: =SUM(AI46:AL46) | GH46: =SUM(AM46:AP46) | GI46: =SUM(AQ46:AT46) | GJ46: =SUM(AU46:AX46) | GK46: =SUM(AY46:BB46) | GL46: =SUM(BC46:BF46) | GM46: =SUM(BG46:BJ46) | GN46: =SUM(BK46:BN46) | GO46: =SUM(BO46:BR46) | GP46: =SUM(BS46:BV46) | GQ46: =SUM(BW46:BZ46) | GR46: =SUM(CA46:CD46) | GS46: =SUM(CE46:CH46) | GT46: =SUM(CI46:CL46) | GU46: =SUM(CM46:CP46) | GV46: =SUM(CQ46:CT46) | GW46: =SUM(CU46:CX46) | GX46: =SUM(CY46:DB46) | GY46: =SUM(DC46:DF46) | GZ46: =SUM(DG46:DJ46) | HA46: =SUM(DK46:DN46) | HB46: =SUM(DO46:DR46) | HC46: =SUM(DS46:DV46) | HD46: =SUM(DW46:DZ46) | HE46: =SUM(EA46:ED46) | HF46: =SUM(EE46:EH46)
A47: Product0487 Mini | CH47: =CH97*CH156 | CI47: =CI97*CI156 | CJ47: =CJ97*CJ156 | CK47: =CK97*CK156 | CL47: =CL97*CL156 | CM47: =CM97*CM156 | CN47: =CN97*CN156 | CO47: =CO97*CO156 | ... EK47: =EK97*EK156 | EM47: =SUM(B47:E47) | EN47: =SUM(F47:I47) | EO47: =SUM(J47:M47) | EP47: =SUM(N47:Q47) | EQ47: =SUM(R47:U47) | ER47: =SUM(V47:Y47) | ES47: =SUM(Z47:AC47) | ET47: =SUM(AD47:AG47) | EU47: =SUM(AH47:AK47) | EV47: =SUM(AL47:AO47) | EW47: =SUM(AP47:AS47) | EX47: =SUM(AT47:AW47) | EY47: =SUM(AX47:BA47) | EZ47: =SUM(BB47:BE47) | FA47: =SUM(BF47:BI47) | FB47: =SUM(BJ47:BM47) | FC47: =SUM(BN47:BQ47) | FD47: =SUM(BR47:BU47) | FE47: =SUM(BV47:BY47) | FF47: =SUM(BZ47:CC47) | FH47: =SUM(CH47:CK47) | FI47: =SUM(CL47:CO47) | FJ47: =SUM(CP47:CS47) | FK47: =SUM(CT47:CW47) | FL47: =SUM(CX47:DA47) | FM47: =SUM(DB47:DE47) | FN47: =SUM(DF47:DI47) | FO47: =SUM(DJ47:DM47) | FP47: =SUM(DN47:DQ47) | FQ47: =SUM(DR47:DU47) | FR47: =SUM(DV47:DY47) | FS47: =SUM(DZ47:EC47) | FT47: =SUM(ED47:EG47) | FU47: =SUM(EH47:EK47) | FZ47: =SUM(G47:J47) | GA47: =SUM(K47:N47) | GB47: =SUM(O47:R47) | GC47: =SUM(S47:V47) | GD47: =SUM(W47:Z47) | GE47: =SUM(AA47:AD47) | GF47: =SUM(AE47:AH47) | GG47: =SUM(AI47:AL47) | GH47: =SUM(AM47:AP47) | GI47: =SUM(AQ47:AT47) | GJ47: =SUM(AU47:AX47) | GK47: =SUM(AY47:BB47) | GL47: =SUM(BC47:BF47) | GM47: =SUM(BG47:BJ47) | GN47: =SUM(BK47:BN47) | GO47: =SUM(BO47:BR47) | GP47: =SUM(BS47:BV47) | GQ47: =SUM(BW47:BZ47) | GR47: =SUM(CA47:CD47) | GS47: =SUM(CE47:CH47) | GT47: =SUM(CI47:CL47) | GU47: =SUM(CM47:CP47) | GV47: =SUM(CQ47:CT47) | GW47: =SUM(CU47:CX47) | GX47: =SUM(CY47:DB47) | GY47: =SUM(DC47:DF47) | GZ47: =SUM(DG47:DJ47) | HA47: =SUM(DK47:DN47) | HB47: =SUM(DO47:DR47) | HC47: =SUM(DS47:DV47) | HD47: =SUM(DW47:DZ47) | HE47: =SUM(EA47:ED47) | HF47: =SUM(EE47:EH47)
A48: Other | CH48: =CH13-CH47-CH46-CH45-CH44 | CI48: =CI13-CI47-CI46-CI45-CI44 | CJ48: =CJ13-CJ47-CJ46-CJ45-CJ44 | CK48: =CK13-CK47-CK46-CK45-CK44 | CL48: =CL13-CL47-CL46-CL45-CL44 | CM48: =CM13-CM47-CM46-CM45-CM44 | CN48: =CN13-CN47-CN46-CN45-CN44 | CO48: =CO13-CO47-CO46-CO45-CO44 | ... DP48: =DP13-DP47-DP46-DP45-DP44 | DQ48: =DQ98*DQ157 | DR48: =DR98*DR157 | DS48: =DS98*DS157 | DT48: =DT98*DT157 | DU48: =DU98*DU157 | DV48: =DV98*DV157 | DW48: =DW98*DW157 | DX48: =DX98*DX157 | ... EK48: =EK98*EK157 | EM48: =SUM(B48:E48) | EN48: =SUM(F48:I48) | EO48: =SUM(J48:M48) | EP48: =SUM(N48:Q48) | EQ48: =SUM(R48:U48) | ER48: =SUM(V48:Y48) | ES48: =SUM(Z48:AC48) | ET48: =SUM(AD48:AG48) | EU48: =SUM(AH48:AK48) | EV48: =SUM(AL48:AO48) | EW48: =SUM(AP48:AS48) | EX48: =SUM(AT48:AW48) | EY48: =SUM(AX48:BA48) | EZ48: =SUM(BB48:BE48) | FA48: =SUM(BF48:BI48) | FB48: =SUM(BJ48:BM48) | FC48: =SUM(BN48:BQ48) | FD48: =SUM(BR48:BU48) | FE48: =SUM(BV48:BY48) | FF48: =SUM(BZ48:CC48) | FH48: =SUM(CH48:CK48) | FI48: =SUM(CL48:CO48) | FJ48: =SUM(CP48:CS48) | FK48: =SUM(CT48:CW48) | FL48: =SUM(CX48:DA48) | FM48: =SUM(DB48:DE48) | FN48: =SUM(DF48:DI48) | FO48: =SUM(DJ48:DM48) | FP48: =SUM(DN48:DQ48) | FQ48: =SUM(DR48:DU48) | FR48: =SUM(DV48:DY48) | FS48: =SUM(DZ48:EC48) | FT48: =SUM(ED48:EG48) | FU48: =SUM(EH48:EK48) | FZ48: =SUM(G48:J48) | GA48: =SUM(K48:N48) | GB48: =SUM(O48:R48) | GC48: =SUM(S48:V48) | GD48: =SUM(W48:Z48) | GE48: =SUM(AA48:AD48) | GF48: =SUM(AE48:AH48) | GG48: =SUM(AI48:AL48) | GH48: =SUM(AM48:AP48) | GI48: =SUM(AQ48:AT48) | GJ48: =SUM(AU48:AX48) | GK48: =SUM(AY48:BB48) | GL48: =SUM(BC48:BF48) | GM48: =SUM(BG48:BJ48) | GN48: =SUM(BK48:BN48) | GO48: =SUM(BO48:BR48) | GP48: =SUM(BS48:BV48) | GQ48: =SUM(BW48:BZ48) | GR48: =SUM(CA48:CD48) | GS48: =SUM(CE48:CH48) | GT48: =SUM(CI48:CL48) | GU48: =SUM(CM48:CP48) | GV48: =SUM(CQ48:CT48) | GW48: =SUM(CU48:CX48) | GX48: =SUM(CY48:DB48) | GY48: =SUM(DC48:DF48) | GZ48: =SUM(DG48:DJ48) | HA48: =SUM(DK48:DN48) | HB48: =SUM(DO48:DR48) | HC48: =SUM(DS48:DV48) | HD48: =SUM(DW48:DZ48) | HE48: =SUM(EA48:ED48) | HF48: =SUM(EE48:EH48)
A49: Product0487 revenue | CH49: =SUM(CH44:CH48) | CI49: =SUM(CI44:CI48) | CJ49: =SUM(CJ44:CJ48) | CK49: =SUM(CK44:CK48) | CL49: =SUM(CL44:CL48) | CM49: =SUM(CM44:CM48) | CN49: =SUM(CN44:CN48) | CO49: =SUM(CO44:CO48) | ... EK49: =SUM(EK44:EK48) | EM49: =SUM(B49:E49) | EN49: =SUM(F49:I49) | EO49: =SUM(J49:M49) | EP49: =SUM(N49:Q49) | EQ49: =SUM(R49:U49) | ER49: =SUM(V49:Y49) | ES49: =SUM(Z49:AC49) | ET49: =SUM(AD49:AG49) | EU49: =SUM(AH49:AK49) | EV49: =SUM(AL49:AO49) | EW49: =SUM(AP49:AS49) | EX49: =SUM(AT49:AW49) | EY49: =SUM(AX49:BA49) | EZ49: =SUM(BB49:BE49) | FA49: =SUM(BF49:BI49) | FB49: =SUM(BJ49:BM49) | FC49: =SUM(BN49:BQ49) | FD49: =SUM(BR49:BU49) | FE49: =SUM(BV49:BY49) | FF49: =SUM(BZ49:CC49) | FH49: =SUM(CH49:CK49) | FI49: =SUM(CL49:CO49) | FJ49: =SUM(CP49:CS49) | FK49: =SUM(CT49:CW49) | FL49: =SUM(CX49:DA49) | FM49: =SUM(DB49:DE49) | FN49: =SUM(DF49:DI49) | FO49: =SUM(DJ49:DM49) | FP49: =SUM(DN49:DQ49) | FQ49: =SUM(DR49:DU49) | FR49: =SUM(DV49:DY49) | FS49: =SUM(DZ49:EC49) | FT49: =SUM(ED49:EG49) | FU49: =SUM(EH49:EK49) | FZ49: =SUM(G49:J49) | GA49: =SUM(K49:N49) | GB49: =SUM(O49:R49) | GC49: =SUM(S49:V49) | GD49: =SUM(W49:Z49) | GE49: =SUM(AA49:AD49) | GF49: =SUM(AE49:AH49) | GG49: =SUM(AI49:AL49) | GH49: =SUM(AM49:AP49) | GI49: =SUM(AQ49:AT49) | GJ49: =SUM(AU49:AX49) | GK49: =SUM(AY49:BB49) | GL49: =SUM(BC49:BF49) | GM49: =SUM(BG49:BJ49) | GN49: =SUM(BK49:BN49) | GO49: =SUM(BO49:BR49) | GP49: =SUM(BS49:BV49) | GQ49: =SUM(BW49:BZ49) | GR49: =SUM(CA49:CD49) | GS49: =SUM(CE49:CH49) | GT49: =SUM(CI49:CL49) | GU49: =SUM(CM49:CP49) | GV49: =SUM(CQ49:CT49) | GW49: =SUM(CU49:CX49) | GX49: =SUM(CY49:DB49) | GY49: =SUM(DC49:DF49) | GZ49: =SUM(DG49:DJ49) | HA49: =SUM(DK49:DN49) | HB49: =SUM(DO49:DR49) | HC49: =SUM(DS49:DV49) | HD49: =SUM(DW49:DZ49) | HE49: =SUM(EA49:ED49) | HF49: =SUM(EE49:EH49)
A51: Product0489 5 | CH51: =CH73*CH132 | CI51: =CI73*CI132 | CJ51: =CJ73*CJ132 | CK51: =CK73*CK132 | CL51: =CL73*CL132 | CM51: =CM73*CM132 | CN51: =CN73*CN132 | CO51: =CO73*CO132 | ... EK51: =EK73*EK132 | EM51: =SUM(B51:E51) | EN51: =SUM(F51:I51) | EO51: =SUM(J51:M51) | EP51: =SUM(N51:Q51) | EQ51: =SUM(R51:U51) | ER51: =SUM(V51:Y51) | ES51: =SUM(Z51:AC51) | ET51: =SUM(AD51:AG51) | EU51: =SUM(AH51:AK51) | EV51: =SUM(AL51:AO51) | EW51: =SUM(AP51:AS51) | EX51: =SUM(AT51:AW51) | EY51: =SUM(AX51:BA51) | EZ51: =SUM(BB51:BE51) | FA51: =SUM(BF51:BI51) | FB51: =SUM(BJ51:BM51) | FC51: =SUM(BN51:BQ51) | FD51: =SUM(BR51:BU51) | FE51: =SUM(BV51:BY51) | FF51: =SUM(BZ51:CC51) | FH51: =SUM(CH51:CK51) | FI51: =SUM(CL51:CO51) | FJ51: =SUM(CP51:CS51) | FK51: =SUM(CT51:CW51) | FL51: =SUM(CX51:DA51) | FM51: =SUM(DB51:DE51) | FN51: =SUM(DF51:DI51) | FO51: =SUM(DJ51:DM51) | FP51: =SUM(DN51:DQ51) | FQ51: =SUM(DR51:DU51) | FR51: =SUM(DV51:DY51) | FS51: =SUM(DZ51:EC51) | FT51: =SUM(ED51:EG51) | FU51: =SUM(EH51:EK51) | FZ51: =SUM(G51:J51) | GA51: =SUM(K51:N51) | GB51: =SUM(O51:R51) | GC51: =SUM(S51:V51) | GD51: =SUM(W51:Z51) | GE51: =SUM(AA51:AD51) | GF51: =SUM(AE51:AH51) | GG51: =SUM(AI51:AL51) | GH51: =SUM(AM51:AP51) | GI51: =SUM(AQ51:AT51) | GJ51: =SUM(AU51:AX51) | GK51: =SUM(AY51:BB51) | GL51: =SUM(BC51:BF51) | GM51: =SUM(BG51:BJ51) | GN51: =SUM(BK51:BN51) | GO51: =SUM(BO51:BR51) | GP51: =SUM(BS51:BV51) | GQ51: =SUM(BW51:BZ51) | GR51: =SUM(CA51:CD51) | GS51: =SUM(CE51:CH51) | GT51: =SUM(CI51:CL51) | GU51: =SUM(CM51:CP51) | GV51: =SUM(CQ51:CT51) | GW51: =SUM(CU51:CX51) | GX51: =SUM(CY51:DB51) | GY51: =SUM(DC51:DF51) | GZ51: =SUM(DG51:DJ51) | HA51: =SUM(DK51:DN51) | HB51: =SUM(DO51:DR51) | HC51: =SUM(DS51:DV51) | HD51: =SUM(DW51:DZ51) | HE51: =SUM(EA51:ED51) | HF51: =SUM(EE51:EH51)
A52: Product0489 6 | CH52: =CH74*CH133 | CI52: =CI74*CI133 | CJ52: =CJ74*CJ133 | CK52: =CK74*CK133 | CL52: =CL74*CL133 | CM52: =CM74*CM133 | CN52: =CN74*CN133 | CO52: =CO74*CO133 | ... EK52: =EK74*EK133 | EM52: =SUM(B52:E52) | EN52: =SUM(F52:I52) | EO52: =SUM(J52:M52) | EP52: =SUM(N52:Q52) | EQ52: =SUM(R52:U52) | ER52: =SUM(V52:Y52) | ES52: =SUM(Z52:AC52) | ET52: =SUM(AD52:AG52) | EU52: =SUM(AH52:AK52) | EV52: =SUM(AL52:AO52) | EW52: =SUM(AP52:AS52) | EX52: =SUM(AT52:AW52) | EY52: =SUM(AX52:BA52) | EZ52: =SUM(BB52:BE52) | FA52: =SUM(BF52:BI52) | FB52: =SUM(BJ52:BM52) | FC52: =SUM(BN52:BQ52) | FD52: =SUM(BR52:BU52) | FE52: =SUM(BV52:BY52) | FF52: =SUM(BZ52:CC52) | FH52: =SUM(CH52:CK52) | FI52: =SUM(CL52:CO52) | FJ52: =SUM(CP52:CS52) | FK52: =SUM(CT52:CW52) | FL52: =SUM(CX52:DA52) | FM52: =SUM(DB52:DE52) | FN52: =SUM(DF52:DI52) | FO52: =SUM(DJ52:DM52) | FP52: =SUM(DN52:DQ52) | FQ52: =SUM(DR52:DU52) | FR52: =SUM(DV52:DY52) | FS52: =SUM(DZ52:EC52) | FT52: =SUM(ED52:EG52) | FU52: =SUM(EH52:EK52) | FZ52: =SUM(G52:J52) | GA52: =SUM(K52:N52) | GB52: =SUM(O52:R52) | GC52: =SUM(S52:V52) | GD52: =SUM(W52:Z52) | GE52: =SUM(AA52:AD52) | GF52: =SUM(AE52:AH52) | GG52: =SUM(AI52:AL52) | GH52: =SUM(AM52:AP52) | GI52: =SUM(AQ52:AT52) | GJ52: =SUM(AU52:AX52) | GK52: =SUM(AY52:BB52) | GL52: =SUM(BC52:BF52) | GM52: =SUM(BG52:BJ52) | GN52: =SUM(BK52:BN52) | GO52: =SUM(BO52:BR52) | GP52: =SUM(BS52:BV52) | GQ52: =SUM(BW52:BZ52) | GR52: =SUM(CA52:CD52) | GS52: =SUM(CE52:CH52) | GT52: =SUM(CI52:CL52) | GU52: =SUM(CM52:CP52) | GV52: =SUM(CQ52:CT52) | GW52: =SUM(CU52:CX52) | GX52: =SUM(CY52:DB52) | GY52: =SUM(DC52:DF52) | GZ52: =SUM(DG52:DJ52) | HA52: =SUM(DK52:DN52) | HB52: =SUM(DO52:DR52) | HC52: =SUM(DS52:DV52) | HD52: =SUM(DW52:DZ52) | HE52: =SUM(EA52:ED52) | HF52: =SUM(EE52:EH52)
A53: Product0489 7 | CH53: =CH75*CH134 | CI53: =CI75*CI134 | CJ53: =CJ75*CJ134 | CK53: =CK75*CK134 | CL53: =CL75*CL134 | CM53: =CM75*CM134 | CN53: =CN75*CN134 | CO53: =CO75*CO134 | ... EK53: =EK75*EK134 | EM53: =SUM(B53:E53) | EN53: =SUM(F53:I53) | EO53: =SUM(J53:M53) | EP53: =SUM(N53:Q53) | EQ53: =SUM(R53:U53) | ER53: =SUM(V53:Y53) | ES53: =SUM(Z53:AC53) | ET53: =SUM(AD53:AG53) | EU53: =SUM(AH53:AK53) | EV53: =SUM(AL53:AO53) | EW53: =SUM(AP53:AS53) | EX53: =SUM(AT53:AW53) | EY53: =SUM(AX53:BA53) | EZ53: =SUM(BB53:BE53) | FA53: =SUM(BF53:BI53) | FB53: =SUM(BJ53:BM53) | FC53: =SUM(BN53:BQ53) | FD53: =SUM(BR53:BU53) | FE53: =SUM(BV53:BY53) | FF53: =SUM(BZ53:CC53) | FH53: =SUM(CH53:CK53) | FI53: =SUM(CL53:CO53) | FJ53: =SUM(CP53:CS53) | FK53: =SUM(CT53:CW53) | FL53: =SUM(CX53:DA53) | FM53: =SUM(DB53:DE53) | FN53: =SUM(DF53:DI53) | FO53: =SUM(DJ53:DM53) | FP53: =SUM(DN53:DQ53) | FQ53: =SUM(DR53:DU53) | FR53: =SUM(DV53:DY53) | FS53: =SUM(DZ53:EC53) | FT53: =SUM(ED53:EG53) | FU53: =SUM(EH53:EK53) | FZ53: =SUM(G53:J53) | GA53: =SUM(K53:N53) | GB53: =SUM(O53:R53) | GC53: =SUM(S53:V53) | GD53: =SUM(W53:Z53) | GE53: =SUM(AA53:AD53) | GF53: =SUM(AE53:AH53) | GG53: =SUM(AI53:AL53) | GH53: =SUM(AM53:AP53) | GI53: =SUM(AQ53:AT53) | GJ53: =SUM(AU53:AX53) | GK53: =SUM(AY53:BB53) | GL53: =SUM(BC53:BF53) | GM53: =SUM(BG53:BJ53) | GN53: =SUM(BK53:BN53) | GO53: =SUM(BO53:BR53) | GP53: =SUM(BS53:BV53) | GQ53: =SUM(BW53:BZ53) | GR53: =SUM(CA53:CD53) | GS53: =SUM(CE53:CH53) | GT53: =SUM(CI53:CL53) | GU53: =SUM(CM53:CP53) | GV53: =SUM(CQ53:CT53) | GW53: =SUM(CU53:CX53) | GX53: =SUM(CY53:DB53) | GY53: =SUM(DC53:DF53) | GZ53: =SUM(DG53:DJ53) | HA53: =SUM(DK53:DN53) | HB53: =SUM(DO53:DR53) | HC53: =SUM(DS53:DV53) | HD53: =SUM(DW53:DZ53) | HE53: =SUM(EA53:ED53) | HF53: =SUM(EE53:EH53)
A54: Product0489 8 | CH54: =CH76*CH135 | CI54: =CI76*CI135 | CJ54: =CJ76*CJ135 | CK54: =CK76*CK135 | CL54: =CL76*CL135 | CM54: =CM76*CM135 | CN54: =CN76*CN135 | CO54: =CO76*CO135 | ... EK54: =EK76*EK135 | EM54: =SUM(B54:E54) | EN54: =SUM(F54:I54) | EO54: =SUM(J54:M54) | EP54: =SUM(N54:Q54) | EQ54: =SUM(R54:U54) | ER54: =SUM(V54:Y54) | ES54: =SUM(Z54:AC54) | ET54: =SUM(AD54:AG54) | EU54: =SUM(AH54:AK54) | EV54: =SUM(AL54:AO54) | EW54: =SUM(AP54:AS54) | EX54: =SUM(AT54:AW54) | EY54: =SUM(AX54:BA54) | EZ54: =SUM(BB54:BE54) | FA54: =SUM(BF54:BI54) | FB54: =SUM(BJ54:BM54) | FC54: =SUM(BN54:BQ54) | FD54: =SUM(BR54:BU54) | FE54: =SUM(BV54:BY54) | FF54: =SUM(BZ54:CC54) | FH54: =SUM(CH54:CK54) | FI54: =SUM(CL54:CO54) | FJ54: =SUM(CP54:CS54) | FK54: =SUM(CT54:CW54) | FL54: =SUM(CX54:DA54) | FM54: =SUM(DB54:DE54) | FN54: =SUM(DF54:DI54) | FO54: =SUM(DJ54:DM54) | FP54: =SUM(DN54:DQ54) | FQ54: =SUM(DR54:DU54) | FR54: =SUM(DV54:DY54) | FS54: =SUM(DZ54:EC54) | FT54: =SUM(ED54:EG54) | FU54: =SUM(EH54:EK54) | FZ54: =SUM(G54:J54) | GA54: =SUM(K54:N54) | GB54: =SUM(O54:R54) | GC54: =SUM(S54:V54) | GD54: =SUM(W54:Z54) | GE54: =SUM(AA54:AD54) | GF54: =SUM(AE54:AH54) | GG54: =SUM(AI54:AL54) | GH54: =SUM(AM54:AP54) | GI54: =SUM(AQ54:AT54) | GJ54: =SUM(AU54:AX54) | GK54: =SUM(AY54:BB54) | GL54: =SUM(BC54:BF54) | GM54: =SUM(BG54:BJ54) | GN54: =SUM(BK54:BN54) | GO54: =SUM(BO54:BR54) | GP54: =SUM(BS54:BV54) | GQ54: =SUM(BW54:BZ54) | GR54: =SUM(CA54:CD54) | GS54: =SUM(CE54:CH54) | GT54: =SUM(CI54:CL54) | GU54: =SUM(CM54:CP54) | GV54: =SUM(CQ54:CT54) | GW54: =SUM(CU54:CX54) | GX54: =SUM(CY54:DB54) | GY54: =SUM(DC54:DF54) | GZ54: =SUM(DG54:DJ54) | HA54: =SUM(DK54:DN54) | HB54: =SUM(DO54:DR54) | HC54: =SUM(DS54:DV54) | HD54: =SUM(DW54:DZ54) | HE54: =SUM(EA54:ED54) | HF54: =SUM(EE54:EH54)
A55: Product0489 X | CH55: =CH77*CH136 | CI55: =CI77*CI136 | CJ55: =CJ77*CJ136 | CK55: =CK77*CK136 | CL55: =CL77*CL136 | CM55: =CM77*CM136 | CN55: =CN77*CN136 | CO55: =CO77*CO136 | ... EK55: =EK77*EK136 | EM55: =SUM(B55:E55) | EN55: =SUM(F55:I55) | EO55: =SUM(J55:M55) | EP55: =SUM(N55:Q55) | EQ55: =SUM(R55:U55) | ER55: =SUM(V55:Y55) | ES55: =SUM(Z55:AC55) | ET55: =SUM(AD55:AG55) | EU55: =SUM(AH55:AK55) | EV55: =SUM(AL55:AO55) | EW55: =SUM(AP55:AS55) | EX55: =SUM(AT55:AW55) | EY55: =SUM(AX55:BA55) | EZ55: =SUM(BB55:BE55) | FA55: =SUM(BF55:BI55) | FB55: =SUM(BJ55:BM55) | FC55: =SUM(BN55:BQ55) | FD55: =SUM(BR55:BU55) | FE55: =SUM(BV55:BY55) | FF55: =SUM(BZ55:CC55) | FH55: =SUM(CH55:CK55) | FI55: =SUM(CL55:CO55) | FJ55: =SUM(CP55:CS55) | FK55: =SUM(CT55:CW55) | FL55: =SUM(CX55:DA55) | FM55: =SUM(DB55:DE55) | FN55: =SUM(DF55:DI55) | FO55: =SUM(DJ55:DM55) | FP55: =SUM(DN55:DQ55) | FQ55: =SUM(DR55:DU55) | FR55: =SUM(DV55:DY55) | FS55: =SUM(DZ55:EC55) | FT55: =SUM(ED55:EG55) | FU55: =SUM(EH55:EK55) | FZ55: =SUM(G55:J55) | GA55: =SUM(K55:N55) | GB55: =SUM(O55:R55) | GC55: =SUM(S55:V55) | GD55: =SUM(W55:Z55) | GE55: =SUM(AA55:AD55) | GF55: =SUM(AE55:AH55) | GG55: =SUM(AI55:AL55) | GH55: =SUM(AM55:AP55) | GI55: =SUM(AQ55:AT55) | GJ55: =SUM(AU55:AX55) | GK55: =SUM(AY55:BB55) | GL55: =SUM(BC55:BF55) | GM55: =SUM(BG55:BJ55) | GN55: =SUM(BK55:BN55) | GO55: =SUM(BO55:BR55) | GP55: =SUM(BS55:BV55) | GQ55: =SUM(BW55:BZ55) | GR55: =SUM(CA55:CD55) | GS55: =SUM(CE55:CH55) | GT55: =SUM(CI55:CL55) | GU55: =SUM(CM55:CP55) | GV55: =SUM(CQ55:CT55) | GW55: =SUM(CU55:CX55) | GX55: =SUM(CY55:DB55) | GY55: =SUM(DC55:DF55) | GZ55: =SUM(DG55:DJ55) | HA55: =SUM(DK55:DN55) | HB55: =SUM(DO55:DR55) | HC55: =SUM(DS55:DV55) | HD55: =SUM(DW55:DZ55) | HE55: =SUM(EA55:ED55) | HF55: =SUM(EE55:EH55)
A56: Product0489 11 | CH56: =CH78*CH137 | CI56: =CI78*CI137 | CJ56: =CJ78*CJ137 | CK56: =CK78*CK137 | CL56: =CL78*CL137 | CM56: =CM78*CM137 | CN56: =CN78*CN137 | CO56: =CO78*CO137 | ... EK56: =EK78*EK137 | EM56: =SUM(B56:E56) | EN56: =SUM(F56:I56) | EO56: =SUM(J56:M56) | EP56: =SUM(N56:Q56) | EQ56: =SUM(R56:U56) | ER56: =SUM(V56:Y56) | ES56: =SUM(Z56:AC56) | ET56: =SUM(AD56:AG56) | EU56: =SUM(AH56:AK56) | EV56: =SUM(AL56:AO56) | EW56: =SUM(AP56:AS56) | EX56: =SUM(AT56:AW56) | EY56: =SUM(AX56:BA56) | EZ56: =SUM(BB56:BE56) | FA56: =SUM(BF56:BI56) | FB56: =SUM(BJ56:BM56) | FC56: =SUM(BN56:BQ56) | FD56: =SUM(BR56:BU56) | FE56: =SUM(BV56:BY56) | FF56: =SUM(BZ56:CC56) | FH56: =SUM(CH56:CK56) | FI56: =SUM(CL56:CO56) | FJ56: =SUM(CP56:CS56) | FK56: =SUM(CT56:CW56) | FL56: =SUM(CX56:DA56) | FM56: =SUM(DB56:DE56) | FN56: =SUM(DF56:DI56) | FO56: =SUM(DJ56:DM56) | FP56: =SUM(DN56:DQ56) | FQ56: =SUM(DR56:DU56) | FR56: =SUM(DV56:DY56) | FS56: =SUM(DZ56:EC56) | FT56: =SUM(ED56:EG56) | FU56: =SUM(EH56:EK56) | FZ56: =SUM(G56:J56) | GA56: =SUM(K56:N56) | GB56: =SUM(O56:R56) | GC56: =SUM(S56:V56) | GD56: =SUM(W56:Z56) | GE56: =SUM(AA56:AD56) | GF56: =SUM(AE56:AH56) | GG56: =SUM(AI56:AL56) | GH56: =SUM(AM56:AP56) | GI56: =SUM(AQ56:AT56) | GJ56: =SUM(AU56:AX56) | GK56: =SUM(AY56:BB56) | GL56: =SUM(BC56:BF56) | GM56: =SUM(BG56:BJ56) | GN56: =SUM(BK56:BN56) | GO56: =SUM(BO56:BR56) | GP56: =SUM(BS56:BV56) | GQ56: =SUM(BW56:BZ56) | GR56: =SUM(CA56:CD56) | GS56: =SUM(CE56:CH56) | GT56: =SUM(CI56:CL56) | GU56: =SUM(CM56:CP56) | GV56: =SUM(CQ56:CT56) | GW56: =SUM(CU56:CX56) | GX56: =SUM(CY56:DB56) | GY56: =SUM(DC56:DF56) | GZ56: =SUM(DG56:DJ56) | HA56: =SUM(DK56:DN56) | HB56: =SUM(DO56:DR56) | HC56: =SUM(DS56:DV56) | HD56: =SUM(DW56:DZ56) | HE56: =SUM(EA56:ED56) | HF56: =SUM(EE56:EH56)
A57: Product0489 12 | CH57: =CH79*CH138 | CI57: =CI79*CI138 | CJ57: =CJ79*CJ138 | CK57: =CK79*CK138 | CL57: =CL79*CL138 | CM57: =CM79*CM138 | CN57: =CN79*CN138 | CO57: =CO79*CO138 | ... EK57: =EK79*EK138 | EM57: =SUM(B57:E57) | EN57: =SUM(F57:I57) | EO57: =SUM(J57:M57) | EP57: =SUM(N57:Q57) | EQ57: =SUM(R57:U57) | ER57: =SUM(V57:Y57) | ES57: =SUM(Z57:AC57) | ET57: =SUM(AD57:AG57) | EU57: =SUM(AH57:AK57) | EV57: =SUM(AL57:AO57) | EW57: =SUM(AP57:AS57) | EX57: =SUM(AT57:AW57) | EY57: =SUM(AX57:BA57) | EZ57: =SUM(BB57:BE57) | FA57: =SUM(BF57:BI57) | FB57: =SUM(BJ57:BM57) | FC57: =SUM(BN57:BQ57) | FD57: =SUM(BR57:BU57) | FE57: =SUM(BV57:BY57) | FF57: =SUM(BZ57:CC57) | FH57: =SUM(CH57:CK57) | FI57: =SUM(CL57:CO57) | FJ57: =SUM(CP57:CS57) | FK57: =SUM(CT57:CW57) | FL57: =SUM(CX57:DA57) | FM57: =SUM(DB57:DE57) | FN57: =SUM(DF57:DI57) | FO57: =SUM(DJ57:DM57) | FP57: =SUM(DN57:DQ57) | FQ57: =SUM(DR57:DU57) | FR57: =SUM(DV57:DY57) | FS57: =SUM(DZ57:EC57) | FT57: =SUM(ED57:EG57) | FU57: =SUM(EH57:EK57) | FZ57: =SUM(G57:J57) | GA57: =SUM(K57:N57) | GB57: =SUM(O57:R57) | GC57: =SUM(S57:V57) | GD57: =SUM(W57:Z57) | GE57: =SUM(AA57:AD57) | GF57: =SUM(AE57:AH57) | GG57: =SUM(AI57:AL57) | GH57: =SUM(AM57:AP57) | GI57: =SUM(AQ57:AT57) | GJ57: =SUM(AU57:AX57) | GK57: =SUM(AY57:BB57) | GL57: =SUM(BC57:BF57) | GM57: =SUM(BG57:BJ57) | GN57: =SUM(BK57:BN57) | GO57: =SUM(BO57:BR57) | GP57: =SUM(BS57:BV57) | GQ57: =SUM(BW57:BZ57) | GR57: =SUM(CA57:CD57) | GS57: =SUM(CE57:CH57) | GT57: =SUM(CI57:CL57) | GU57: =SUM(CM57:CP57) | GV57: =SUM(CQ57:CT57) | GW57: =SUM(CU57:CX57) | GX57: =SUM(CY57:DB57) | GY57: =SUM(DC57:DF57) | GZ57: =SUM(DG57:DJ57) | HA57: =SUM(DK57:DN57) | HB57: =SUM(DO57:DR57) | HC57: =SUM(DS57:DV57) | HD57: =SUM(DW57:DZ57) | HE57: =SUM(EA57:ED57) | HF57: =SUM(EE57:EH57)
A58: Product0489 13 | CH58: =CH80*CH139 | CI58: =CI80*CI139 | CJ58: =CJ80*CJ139 | CK58: =CK80*CK139 | CL58: =CL80*CL139 | CM58: =CM80*CM139 | CN58: =CN80*CN139 | CO58: =CO80*CO139 | ... EK58: =EK80*EK139 | EM58: =SUM(B58:E58) | EN58: =SUM(F58:I58) | EO58: =SUM(J58:M58) | EP58: =SUM(N58:Q58) | EQ58: =SUM(R58:U58) | ER58: =SUM(V58:Y58) | ES58: =SUM(Z58:AC58) | ET58: =SUM(AD58:AG58) | EU58: =SUM(AH58:AK58) | EV58: =SUM(AL58:AO58) | EW58: =SUM(AP58:AS58) | EX58: =SUM(AT58:AW58) | EY58: =SUM(AX58:BA58) | EZ58: =SUM(BB58:BE58) | FA58: =SUM(BF58:BI58) | FB58: =SUM(BJ58:BM58) | FC58: =SUM(BN58:BQ58) | FD58: =SUM(BR58:BU58) | FE58: =SUM(BV58:BY58) | FF58: =SUM(BZ58:CC58) | FH58: =SUM(CH58:CK58) | FI58: =SUM(CL58:CO58) | FJ58: =SUM(CP58:CS58) | FK58: =SUM(CT58:CW58) | FL58: =SUM(CX58:DA58) | FM58: =SUM(DB58:DE58) | FN58: =SUM(DF58:DI58) | FO58: =SUM(DJ58:DM58) | FP58: =SUM(DN58:DQ58) | FQ58: =SUM(DR58:DU58) | FR58: =SUM(DV58:DY58) | FS58: =SUM(DZ58:EC58) | FT58: =SUM(ED58:EG58) | FU58: =SUM(EH58:EK58) | FZ58: =SUM(G58:J58) | GA58: =SUM(K58:N58) | GB58: =SUM(O58:R58) | GC58: =SUM(S58:V58) | GD58: =SUM(W58:Z58) | GE58: =SUM(AA58:AD58) | GF58: =SUM(AE58:AH58) | GG58: =SUM(AI58:AL58) | GH58: =SUM(AM58:AP58) | GI58: =SUM(AQ58:AT58) | GJ58: =SUM(AU58:AX58) | GK58: =SUM(AY58:BB58) | GL58: =SUM(BC58:BF58) | GM58: =SUM(BG58:BJ58) | GN58: =SUM(BK58:BN58) | GO58: =SUM(BO58:BR58) | GP58: =SUM(BS58:BV58) | GQ58: =SUM(BW58:BZ58) | GR58: =SUM(CA58:CD58) | GS58: =SUM(CE58:CH58) | GT58: =SUM(CI58:CL58) | GU58: =SUM(CM58:CP58) | GV58: =SUM(CQ58:CT58) | GW58: =SUM(CU58:CX58) | GX58: =SUM(CY58:DB58) | GY58: =SUM(DC58:DF58) | GZ58: =SUM(DG58:DJ58) | HA58: =SUM(DK58:DN58) | HB58: =SUM(DO58:DR58) | HC58: =SUM(DS58:DV58) | HD58: =SUM(DW58:DZ58) | HE58: =SUM(EA58:ED58) | HF58: =SUM(EE58:EH58)
A59: Product0489 14 | CH59: =CH81*CH140 | CI59: =CI81*CI140 | CJ59: =CJ81*CJ140 | CK59: =CK81*CK140 | CL59: =CL81*CL140 | CM59: =CM81*CM140 | CN59: =CN81*CN140 | CO59: =CO81*CO140 | ... EK59: =EK81*EK140 | EM59: =SUM(B59:E59) | EN59: =SUM(F59:I59) | EO59: =SUM(J59:M59) | EP59: =SUM(N59:Q59) | EQ59: =SUM(R59:U59) | ER59: =SUM(V59:Y59) | ES59: =SUM(Z59:AC59) | ET59: =SUM(AD59:AG59) | EU59: =SUM(AH59:AK59) | EV59: =SUM(AL59:AO59) | EW59: =SUM(AP59:AS59) | EX59: =SUM(AT59:AW59) | EY59: =SUM(AX59:BA59) | EZ59: =SUM(BB59:BE59) | FA59: =SUM(BF59:BI59) | FB59: =SUM(BJ59:BM59) | FC59: =SUM(BN59:BQ59) | FD59: =SUM(BR59:BU59) | FE59: =SUM(BV59:BY59) | FF59: =SUM(BZ59:CC59) | FH59: =SUM(CH59:CK59) | FI59: =SUM(CL59:CO59) | FJ59: =SUM(CP59:CS59) | FK59: =SUM(CT59:CW59) | FL59: =SUM(CX59:DA59) | FM59: =SUM(DB59:DE59) | FN59: =SUM(DF59:DI59) | FO59: =SUM(DJ59:DM59) | FP59: =SUM(DN59:DQ59) | FQ59: =SUM(DR59:DU59) | FR59: =SUM(DV59:DY59) | FS59: =SUM(DZ59:EC59) | FT59: =SUM(ED59:EG59) | FU59: =SUM(EH59:EK59) | FZ59: =SUM(G59:J59) | GA59: =SUM(K59:N59) | GB59: =SUM(O59:R59) | GC59: =SUM(S59:V59) | GD59: =SUM(W59:Z59) | GE59: =SUM(AA59:AD59) | GF59: =SUM(AE59:AH59) | GG59: =SUM(AI59:AL59) | GH59: =SUM(AM59:AP59) | GI59: =SUM(AQ59:AT59) | GJ59: =SUM(AU59:AX59) | GK59: =SUM(AY59:BB59) | GL59: =SUM(BC59:BF59) | GM59: =SUM(BG59:BJ59) | GN59: =SUM(BK59:BN59) | GO59: =SUM(BO59:BR59) | GP59: =SUM(BS59:BV59) | GQ59: =SUM(BW59:BZ59) | GR59: =SUM(CA59:CD59) | GS59: =SUM(CE59:CH59) | GT59: =SUM(CI59:CL59) | GU59: =SUM(CM59:CP59) | GV59: =SUM(CQ59:CT59) | GW59: =SUM(CU59:CX59) | GX59: =SUM(CY59:DB59) | GY59: =SUM(DC59:DF59) | GZ59: =SUM(DG59:DJ59) | HA59: =SUM(DK59:DN59) | HB59: =SUM(DO59:DR59) | HC59: =SUM(DS59:DV59) | HD59: =SUM(DW59:DZ59) | HE59: =SUM(EA59:ED59) | HF59: =SUM(EE59:EH59)
A60: Product0489 15 | CH60: =CH82*CH141 | CI60: =CI82*CI141 | CJ60: =CJ82*CJ141 | CK60: =CK82*CK141 | CL60: =CL82*CL141 | CM60: =CM82*CM141 | CN60: =CN82*CN141 | CO60: =CO82*CO141 | ... EK60: =EK82*EK141 | EM60: =SUM(B60:E60) | EN60: =SUM(F60:I60) | EO60: =SUM(J60:M60) | EP60: =SUM(N60:Q60) | EQ60: =SUM(R60:U60) | ER60: =SUM(V60:Y60) | ES60: =SUM(Z60:AC60) | ET60: =SUM(AD60:AG60) | EU60: =SUM(AH60:AK60) | EV60: =SUM(AL60:AO60) | EW60: =SUM(AP60:AS60) | EX60: =SUM(AT60:AW60) | EY60: =SUM(AX60:BA60) | EZ60: =SUM(BB60:BE60) | FA60: =SUM(BF60:BI60) | FB60: =SUM(BJ60:BM60) | FC60: =SUM(BN60:BQ60) | FD60: =SUM(BR60:BU60) | FE60: =SUM(BV60:BY60) | FF60: =SUM(BZ60:CC60) | FH60: =SUM(CH60:CK60) | FI60: =SUM(CL60:CO60) | FJ60: =SUM(CP60:CS60) | FK60: =SUM(CT60:CW60) | FL60: =SUM(CX60:DA60) | FM60: =SUM(DB60:DE60) | FN60: =SUM(DF60:DI60) | FO60: =SUM(DJ60:DM60) | FP60: =SUM(DN60:DQ60) | FQ60: =SUM(DR60:DU60) | FR60: =SUM(DV60:DY60) | FS60: =SUM(DZ60:EC60) | FT60: =SUM(ED60:EG60) | FU60: =SUM(EH60:EK60) | FZ60: =SUM(G60:J60) | GA60: =SUM(K60:N60) | GB60: =SUM(O60:R60) | GC60: =SUM(S60:V60) | GD60: =SUM(W60:Z60) | GE60: =SUM(AA60:AD60) | GF60: =SUM(AE60:AH60) | GG60: =SUM(AI60:AL60) | GH60: =SUM(AM60:AP60) | GI60: =SUM(AQ60:AT60) | GJ60: =SUM(AU60:AX60) | GK60: =SUM(AY60:BB60) | GL60: =SUM(BC60:BF60) | GM60: =SUM(BG60:BJ60) | GN60: =SUM(BK60:BN60) | GO60: =SUM(BO60:BR60) | GP60: =SUM(BS60:BV60) | GQ60: =SUM(BW60:BZ60) | GR60: =SUM(CA60:CD60) | GS60: =SUM(CE60:CH60) | GT60: =SUM(CI60:CL60) | GU60: =SUM(CM60:CP60) | GV60: =SUM(CQ60:CT60) | GW60: =SUM(CU60:CX60) | GX60: =SUM(CY60:DB60) | GY60: =SUM(DC60:DF60) | GZ60: =SUM(DG60:DJ60) | HA60: =SUM(DK60:DN60) | HB60: =SUM(DO60:DR60) | HC60: =SUM(DS60:DV60) | HD60: =SUM(DW60:DZ60) | HE60: =SUM(EA60:ED60) | HF60: =SUM(EE60:EH60)
A61: Product0489 16 | CH61: =CH83*CH142 | CI61: =CI83*CI142 | CJ61: =CJ83*CJ142 | CK61: =CK83*CK142 | CL61: =CL83*CL142 | CM61: =CM83*CM142 | CN61: =CN83*CN142 | CO61: =CO83*CO142 | ... EK61: =EK83*EK142 | EM61: =SUM(B61:E61) | EN61: =SUM(F61:I61) | EO61: =SUM(J61:M61) | EP61: =SUM(N61:Q61) | EQ61: =SUM(R61:U61) | ER61: =SUM(V61:Y61) | ES61: =SUM(Z61:AC61) | ET61: =SUM(AD61:AG61) | EU61: =SUM(AH61:AK61) | EV61: =SUM(AL61:AO61) | EW61: =SUM(AP61:AS61) | EX61: =SUM(AT61:AW61) | EY61: =SUM(AX61:BA61) | EZ61: =SUM(BB61:BE61) | FA61: =SUM(BF61:BI61) | FB61: =SUM(BJ61:BM61) | FC61: =SUM(BN61:BQ61) | FD61: =SUM(BR61:BU61) | FE61: =SUM(BV61:BY61) | FF61: =SUM(BZ61:CC61) | FH61: =SUM(CH61:CK61) | FI61: =SUM(CL61:CO61) | FJ61: =SUM(CP61:CS61) | FK61: =SUM(CT61:CW61) | FL61: =SUM(CX61:DA61) | FM61: =SUM(DB61:DE61) | FN61: =SUM(DF61:DI61) | FO61: =SUM(DJ61:DM61) | FP61: =SUM(DN61:DQ61) | FQ61: =SUM(DR61:DU61) | FR61: =SUM(DV61:DY61) | FS61: =SUM(DZ61:EC61) | FT61: =SUM(ED61:EG61) | FU61: =SUM(EH61:EK61) | FZ61: =SUM(G61:J61) | GA61: =SUM(K61:N61) | GB61: =SUM(O61:R61) | GC61: =SUM(S61:V61) | GD61: =SUM(W61:Z61) | GE61: =SUM(AA61:AD61) | GF61: =SUM(AE61:AH61) | GG61: =SUM(AI61:AL61) | GH61: =SUM(AM61:AP61) | GI61: =SUM(AQ61:AT61) | GJ61: =SUM(AU61:AX61) | GK61: =SUM(AY61:BB61) | GL61: =SUM(BC61:BF61) | GM61: =SUM(BG61:BJ61) | GN61: =SUM(BK61:BN61) | GO61: =SUM(BO61:BR61) | GP61: =SUM(BS61:BV61) | GQ61: =SUM(BW61:BZ61) | GR61: =SUM(CA61:CD61) | GS61: =SUM(CE61:CH61) | GT61: =SUM(CI61:CL61) | GU61: =SUM(CM61:CP61) | GV61: =SUM(CQ61:CT61) | GW61: =SUM(CU61:CX61) | GX61: =SUM(CY61:DB61) | GY61: =SUM(DC61:DF61) | GZ61: =SUM(DG61:DJ61) | HA61: =SUM(DK61:DN61) | HB61: =SUM(DO61:DR61) | HC61: =SUM(DS61:DV61) | HD61: =SUM(DW61:DZ61) | HE61: =SUM(EA61:ED61) | HF61: =SUM(EE61:EH61)
A62: Product0489 17 | CH62: =CH84*CH143 | CI62: =CI84*CI143 | CJ62: =CJ84*CJ143 | CK62: =CK84*CK143 | CL62: =CL84*CL143 | CM62: =CM84*CM143 | CN62: =CN84*CN143 | CO62: =CO84*CO143 | ... EK62: =EK84*EK143 | EM62: =SUM(B62:E62) | EN62: =SUM(F62:I62) | EO62: =SUM(J62:M62) | EP62: =SUM(N62:Q62) | EQ62: =SUM(R62:U62) | ER62: =SUM(V62:Y62) | ES62: =SUM(Z62:AC62) | ET62: =SUM(AD62:AG62) | EU62: =SUM(AH62:AK62) | EV62: =SUM(AL62:AO62) | EW62: =SUM(AP62:AS62) | EX62: =SUM(AT62:AW62) | EY62: =SUM(AX62:BA62) | EZ62: =SUM(BB62:BE62) | FA62: =SUM(BF62:BI62) | FB62: =SUM(BJ62:BM62) | FC62: =SUM(BN62:BQ62) | FD62: =SUM(BR62:BU62) | FE62: =SUM(BV62:BY62) | FF62: =SUM(BZ62:CC62) | FH62: =SUM(CH62:CK62) | FI62: =SUM(CL62:CO62) | FJ62: =SUM(CP62:CS62) | FK62: =SUM(CT62:CW62) | FL62: =SUM(CX62:DA62) | FM62: =SUM(DB62:DE62) | FN62: =SUM(DF62:DI62) | FO62: =SUM(DJ62:DM62) | FP62: =SUM(DN62:DQ62) | FQ62: =SUM(DR62:DU62) | FR62: =SUM(DV62:DY62) | FS62: =SUM(DZ62:EC62) | FT62: =SUM(ED62:EG62) | FU62: =SUM(EH62:EK62) | FZ62: =SUM(G62:J62) | GA62: =SUM(K62:N62) | GB62: =SUM(O62:R62) | GC62: =SUM(S62:V62) | GD62: =SUM(W62:Z62) | GE62: =SUM(AA62:AD62) | GF62: =SUM(AE62:AH62) | GG62: =SUM(AI62:AL62) | GH62: =SUM(AM62:AP62) | GI62: =SUM(AQ62:AT62) | GJ62: =SUM(AU62:AX62) | GK62: =SUM(AY62:BB62) | GL62: =SUM(BC62:BF62) | GM62: =SUM(BG62:BJ62) | GN62: =SUM(BK62:BN62) | GO62: =SUM(BO62:BR62) | GP62: =SUM(BS62:BV62) | GQ62: =SUM(BW62:BZ62) | GR62: =SUM(CA62:CD62) | GS62: =SUM(CE62:CH62) | GT62: =SUM(CI62:CL62) | GU62: =SUM(CM62:CP62) | GV62: =SUM(CQ62:CT62) | GW62: =SUM(CU62:CX62) | GX62: =SUM(CY62:DB62) | GY62: =SUM(DC62:DF62) | GZ62: =SUM(DG62:DJ62) | HA62: =SUM(DK62:DN62) | HB62: =SUM(DO62:DR62) | HC62: =SUM(DS62:DV62) | HD62: =SUM(DW62:DZ62) | HE62: =SUM(EA62:ED62) | HF62: =SUM(EE62:EH62)
A63: Product0489 18 | DR63: =DR85*DR144 | DS63: =DS85*DS144 | DT63: =DT85*DT144 | DU63: =DU85*DU144 | DV63: =DV85*DV144 | DW63: =DW85*DW144 | DX63: =DX85*DX144 | DY63: =DY85*DY144 | ... EK63: =EK85*EK144 | EM63: =SUM(B63:E63) | EN63: =SUM(F63:I63) | EO63: =SUM(J63:M63) | EP63: =SUM(N63:Q63) | EQ63: =SUM(R63:U63) | ER63: =SUM(V63:Y63) | ES63: =SUM(Z63:AC63) | ET63: =SUM(AD63:AG63) | EU63: =SUM(AH63:AK63) | EV63: =SUM(AL63:AO63) | EW63: =SUM(AP63:AS63) | EX63: =SUM(AT63:AW63) | EY63: =SUM(AX63:BA63) | EZ63: =SUM(BB63:BE63) | FA63: =SUM(BF63:BI63) | FB63: =SUM(BJ63:BM63) | FC63: =SUM(BN63:BQ63) | FD63: =SUM(BR63:BU63) | FE63: =SUM(BV63:BY63) | FF63: =SUM(BZ63:CC63) | FH63: =SUM(CH63:CK63) | FI63: =SUM(CL63:CO63) | FJ63: =SUM(CP63:CS63) | FK63: =SUM(CT63:CW63) | FL63: =SUM(CX63:DA63) | FM63: =SUM(DB63:DE63) | FN63: =SUM(DF63:DI63) | FO63: =SUM(DJ63:DM63) | FP63: =SUM(DN63:DQ63) | FQ63: =SUM(DR63:DU63) | FR63: =SUM(DV63:DY63) | FS63: =SUM(DZ63:EC63) | FT63: =SUM(ED63:EG63) | FU63: =SUM(EH63:EK63) | FZ63: =SUM(G63:J63) | GA63: =SUM(K63:N63) | GB63: =SUM(O63:R63) | GC63: =SUM(S63:V63) | GD63: =SUM(W63:Z63) | GE63: =SUM(AA63:AD63) | GF63: =SUM(AE63:AH63) | GG63: =SUM(AI63:AL63) | GH63: =SUM(AM63:AP63) | GI63: =SUM(AQ63:AT63) | GJ63: =SUM(AU63:AX63) | GK63: =SUM(AY63:BB63) | GL63: =SUM(BC63:BF63) | GM63: =SUM(BG63:BJ63) | GN63: =SUM(BK63:BN63) | GO63: =SUM(BO63:BR63) | GP63: =SUM(BS63:BV63) | GQ63: =SUM(BW63:BZ63) | GR63: =SUM(CA63:CD63) | GS63: =SUM(CE63:CH63) | GT63: =SUM(CI63:CL63) | GU63: =SUM(CM63:CP63) | GV63: =SUM(CQ63:CT63) | GW63: =SUM(CU63:CX63) | GX63: =SUM(CY63:DB63) | GY63: =SUM(DC63:DF63) | GZ63: =SUM(DG63:DJ63) | HA63: =SUM(DK63:DN63) | HB63: =SUM(DO63:DR63) | HC63: =SUM(DS63:DV63) | HD63: =SUM(DW63:DZ63) | HE63: =SUM(EA63:ED63) | HF63: =SUM(EE63:EH63)
A64: Product0489 19 | DR64: =DR86*DR145 | DS64: =DS86*DS145 | DT64: =DT86*DT145 | DU64: =DU86*DU145 | DV64: =DV86*DV145 | DW64: =DW86*DW145 | DX64: =DX86*DX145 | DY64: =DY86*DY145 | ... EK64: =EK86*EK145 | EM64: =SUM(B64:E64) | EN64: =SUM(F64:I64) | EO64: =SUM(J64:M64) | EP64: =SUM(N64:Q64) | EQ64: =SUM(R64:U64) | ER64: =SUM(V64:Y64) | ES64: =SUM(Z64:AC64) | ET64: =SUM(AD64:AG64) | EU64: =SUM(AH64:AK64) | EV64: =SUM(AL64:AO64) | EW64: =SUM(AP64:AS64) | EX64: =SUM(AT64:AW64) | EY64: =SUM(AX64:BA64) | EZ64: =SUM(BB64:BE64) | FA64: =SUM(BF64:BI64) | FB64: =SUM(BJ64:BM64) | FC64: =SUM(BN64:BQ64) | FD64: =SUM(BR64:BU64) | FE64: =SUM(BV64:BY64) | FF64: =SUM(BZ64:CC64) | FH64: =SUM(CH64:CK64) | FI64: =SUM(CL64:CO64) | FJ64: =SUM(CP64:CS64) | FK64: =SUM(CT64:CW64) | FL64: =SUM(CX64:DA64) | FM64: =SUM(DB64:DE64) | FN64: =SUM(DF64:DI64) | FO64: =SUM(DJ64:DM64) | FP64: =SUM(DN64:DQ64) | FQ64: =SUM(DR64:DU64) | FR64: =SUM(DV64:DY64) | FS64: =SUM(DZ64:EC64) | FT64: =SUM(ED64:EG64) | FU64: =SUM(EH64:EK64) | FZ64: =SUM(G64:J64) | GA64: =SUM(K64:N64) | GB64: =SUM(O64:R64) | GC64: =SUM(S64:V64) | GD64: =SUM(W64:Z64) | GE64: =SUM(AA64:AD64) | GF64: =SUM(AE64:AH64) | GG64: =SUM(AI64:AL64) | GH64: =SUM(AM64:AP64) | GI64: =SUM(AQ64:AT64) | GJ64: =SUM(AU64:AX64) | GK64: =SUM(AY64:BB64) | GL64: =SUM(BC64:BF64) | GM64: =SUM(BG64:BJ64) | GN64: =SUM(BK64:BN64) | GO64: =SUM(BO64:BR64) | GP64: =SUM(BS64:BV64) | GQ64: =SUM(BW64:BZ64) | GR64: =SUM(CA64:CD64) | GS64: =SUM(CE64:CH64) | GT64: =SUM(CI64:CL64) | GU64: =SUM(CM64:CP64) | GV64: =SUM(CQ64:CT64) | GW64: =SUM(CU64:CX64) | GX64: =SUM(CY64:DB64) | GY64: =SUM(DC64:DF64) | GZ64: =SUM(DG64:DJ64) | HA64: =SUM(DK64:DN64) | HB64: =SUM(DO64:DR64) | HC64: =SUM(DS64:DV64) | HD64: =SUM(DW64:DZ64) | HE64: =SUM(EA64:ED64) | HF64: =SUM(EE64:EH64)
A65: Product0489 20 | DR65: =DR87*DR146 | DS65: =DS87*DS146 | DT65: =DT87*DT146 | DU65: =DU87*DU146 | DV65: =DV87*DV146 | DW65: =DW87*DW146 | DX65: =DX87*DX146 | DY65: =DY87*DY146 | ... EK65: =EK87*EK146 | EM65: =SUM(B65:E65) | EN65: =SUM(F65:I65) | EO65: =SUM(J65:M65) | EP65: =SUM(N65:Q65) | EQ65: =SUM(R65:U65) | ER65: =SUM(V65:Y65) | ES65: =SUM(Z65:AC65) | ET65: =SUM(AD65:AG65) | EU65: =SUM(AH65:AK65) | EV65: =SUM(AL65:AO65) | EW65: =SUM(AP65:AS65) | EX65: =SUM(AT65:AW65) | EY65: =SUM(AX65:BA65) | EZ65: =SUM(BB65:BE65) | FA65: =SUM(BF65:BI65) | FB65: =SUM(BJ65:BM65) | FC65: =SUM(BN65:BQ65) | FD65: =SUM(BR65:BU65) | FE65: =SUM(BV65:BY65) | FF65: =SUM(BZ65:CC65) | FH65: =SUM(CH65:CK65) | FI65: =SUM(CL65:CO65) | FJ65: =SUM(CP65:CS65) | FK65: =SUM(CT65:CW65) | FL65: =SUM(CX65:DA65) | FM65: =SUM(DB65:DE65) | FN65: =SUM(DF65:DI65) | FO65: =SUM(DJ65:DM65) | FP65: =SUM(DN65:DQ65) | FQ65: =SUM(DR65:DU65) | FR65: =SUM(DV65:DY65) | FS65: =SUM(DZ65:EC65) | FT65: =SUM(ED65:EG65) | FU65: =SUM(EH65:EK65) | FZ65: =SUM(G65:J65) | GA65: =SUM(K65:N65) | GB65: =SUM(O65:R65) | GC65: =SUM(S65:V65) | GD65: =SUM(W65:Z65) | GE65: =SUM(AA65:AD65) | GF65: =SUM(AE65:AH65) | GG65: =SUM(AI65:AL65) | GH65: =SUM(AM65:AP65) | GI65: =SUM(AQ65:AT65) | GJ65: =SUM(AU65:AX65) | GK65: =SUM(AY65:BB65) | GL65: =SUM(BC65:BF65) | GM65: =SUM(BG65:BJ65) | GN65: =SUM(BK65:BN65) | GO65: =SUM(BO65:BR65) | GP65: =SUM(BS65:BV65) | GQ65: =SUM(BW65:BZ65) | GR65: =SUM(CA65:CD65) | GS65: =SUM(CE65:CH65) | GT65: =SUM(CI65:CL65) | GU65: =SUM(CM65:CP65) | GV65: =SUM(CQ65:CT65) | GW65: =SUM(CU65:CX65) | GX65: =SUM(CY65:DB65) | GY65: =SUM(DC65:DF65) | GZ65: =SUM(DG65:DJ65) | HA65: =SUM(DK65:DN65) | HB65: =SUM(DO65:DR65) | HC65: =SUM(DS65:DV65) | HD65: =SUM(DW65:DZ65) | HE65: =SUM(EA65:ED65) | HF65: =SUM(EE65:EH65)
A66: Product0489 21 | DR66: =DR88*DR147 | DS66: =DS88*DS147 | DT66: =DT88*DT147 | DU66: =DU88*DU147 | DV66: =DV88*DV147 | DW66: =DW88*DW147 | DX66: =DX88*DX147 | DY66: =DY88*DY147 | ... EK66: =EK88*EK147 | EM66: =SUM(B66:E66) | EN66: =SUM(F66:I66) | EO66: =SUM(J66:M66) | EP66: =SUM(N66:Q66) | EQ66: =SUM(R66:U66) | ER66: =SUM(V66:Y66) | ES66: =SUM(Z66:AC66) | ET66: =SUM(AD66:AG66) | EU66: =SUM(AH66:AK66) | EV66: =SUM(AL66:AO66) | EW66: =SUM(AP66:AS66) | EX66: =SUM(AT66:AW66) | EY66: =SUM(AX66:BA66) | EZ66: =SUM(BB66:BE66) | FA66: =SUM(BF66:BI66) | FB66: =SUM(BJ66:BM66) | FC66: =SUM(BN66:BQ66) | FD66: =SUM(BR66:BU66) | FE66: =SUM(BV66:BY66) | FF66: =SUM(BZ66:CC66) | FH66: =SUM(CH66:CK66) | FI66: =SUM(CL66:CO66) | FJ66: =SUM(CP66:CS66) | FK66: =SUM(CT66:CW66) | FL66: =SUM(CX66:DA66) | FM66: =SUM(DB66:DE66) | FN66: =SUM(DF66:DI66) | FO66: =SUM(DJ66:DM66) | FP66: =SUM(DN66:DQ66) | FQ66: =SUM(DR66:DU66) | FR66: =SUM(DV66:DY66) | FS66: =SUM(DZ66:EC66) | FT66: =SUM(ED66:EG66) | FU66: =SUM(EH66:EK66) | FZ66: =SUM(G66:J66) | GA66: =SUM(K66:N66) | GB66: =SUM(O66:R66) | GC66: =SUM(S66:V66) | GD66: =SUM(W66:Z66) | GE66: =SUM(AA66:AD66) | GF66: =SUM(AE66:AH66) | GG66: =SUM(AI66:AL66) | GH66: =SUM(AM66:AP66) | GI66: =SUM(AQ66:AT66) | GJ66: =SUM(AU66:AX66) | GK66: =SUM(AY66:BB66) | GL66: =SUM(BC66:BF66) | GM66: =SUM(BG66:BJ66) | GN66: =SUM(BK66:BN66) | GO66: =SUM(BO66:BR66) | GP66: =SUM(BS66:BV66) | GQ66: =SUM(BW66:BZ66) | GR66: =SUM(CA66:CD66) | GS66: =SUM(CE66:CH66) | GT66: =SUM(CI66:CL66) | GU66: =SUM(CM66:CP66) | GV66: =SUM(CQ66:CT66) | GW66: =SUM(CU66:CX66) | GX66: =SUM(CY66:DB66) | GY66: =SUM(DC66:DF66) | GZ66: =SUM(DG66:DJ66) | HA66: =SUM(DK66:DN66) | HB66: =SUM(DO66:DR66) | HC66: =SUM(DS66:DV66) | HD66: =SUM(DW66:DZ66) | HE66: =SUM(EA66:ED66) | HF66: =SUM(EE66:EH66)
A67: Product0489 SE or low-end equivalent | CH67: =CH89*CH148 | CI67: =CI89*CI148 | CJ67: =CJ89*CJ148 | CK67: =CK89*CK148 | CL67: =CL89*CL148 | CM67: =CM89*CM148 | CN67: =CN89*CN148 | CO67: =CO89*CO148 | ... EK67: =EK89*EK148 | EM67: =SUM(B67:E67) | EN67: =SUM(F67:I67) | EO67: =SUM(J67:M67) | EP67: =SUM(N67:Q67) | EQ67: =SUM(R67:U67) | ER67: =SUM(V67:Y67) | ES67: =SUM(Z67:AC67) | ET67: =SUM(AD67:AG67) | EU67: =SUM(AH67:AK67) | EV67: =SUM(AL67:AO67) | EW67: =SUM(AP67:AS67) | EX67: =SUM(AT67:AW67) | EY67: =SUM(AX67:BA67) | EZ67: =SUM(BB67:BE67) | FA67: =SUM(BF67:BI67) | FB67: =SUM(BJ67:BM67) | FC67: =SUM(BN67:BQ67) | FD67: =SUM(BR67:BU67) | FE67: =SUM(BV67:BY67) | FF67: =SUM(BZ67:CC67) | FH67: =SUM(CH67:CK67) | FI67: =SUM(CL67:CO67) | FJ67: =SUM(CP67:CS67) | FK67: =SUM(CT67:CW67) | FL67: =SUM(CX67:DA67) | FM67: =SUM(DB67:DE67) | FN67: =SUM(DF67:DI67) | FO67: =SUM(DJ67:DM67) | FP67: =SUM(DN67:DQ67) | FQ67: =SUM(DR67:DU67) | FR67: =SUM(DV67:DY67) | FS67: =SUM(DZ67:EC67) | FT67: =SUM(ED67:EG67) | FU67: =SUM(EH67:EK67) | FZ67: =SUM(G67:J67) | GA67: =SUM(K67:N67) | GB67: =SUM(O67:R67) | GC67: =SUM(S67:V67) | GD67: =SUM(W67:Z67) | GE67: =SUM(AA67:AD67) | GF67: =SUM(AE67:AH67) | GG67: =SUM(AI67:AL67) | GH67: =SUM(AM67:AP67) | GI67: =SUM(AQ67:AT67) | GJ67: =SUM(AU67:AX67) | GK67: =SUM(AY67:BB67) | GL67: =SUM(BC67:BF67) | GM67: =SUM(BG67:BJ67) | GN67: =SUM(BK67:BN67) | GO67: =SUM(BO67:BR67) | GP67: =SUM(BS67:BV67) | GQ67: =SUM(BW67:BZ67) | GR67: =SUM(CA67:CD67) | GS67: =SUM(CE67:CH67) | GT67: =SUM(CI67:CL67) | GU67: =SUM(CM67:CP67) | GV67: =SUM(CQ67:CT67) | GW67: =SUM(CU67:CX67) | GX67: =SUM(CY67:DB67) | GY67: =SUM(DC67:DF67) | GZ67: =SUM(DG67:DJ67) | HA67: =SUM(DK67:DN67) | HB67: =SUM(DO67:DR67) | HC67: =SUM(DS67:DV67) | HD67: =SUM(DW67:DZ67) | HE67: =SUM(EA67:ED67) | HF67: =SUM(EE67:EH67)
A68: Prior generation | CH68: =CH90*CH149 | CI68: =CI90*CI149 | CJ68: =CJ90*CJ149 | CK68: =CK90*CK149 | CL68: =CL90*CL149 | CM68: =CM90*CM149 | CN68: =CN90*CN149 | CO68: =CO90*CO149 | ... EK68: =EK90*EK149 | EM68: =SUM(B68:E68) | EN68: =SUM(F68:I68) | EO68: =SUM(J68:M68) | EP68: =SUM(N68:Q68) | EQ68: =SUM(R68:U68) | ER68: =SUM(V68:Y68) | ES68: =SUM(Z68:AC68) | ET68: =SUM(AD68:AG68) | EU68: =SUM(AH68:AK68) | EV68: =SUM(AL68:AO68) | EW68: =SUM(AP68:AS68) | EX68: =SUM(AT68:AW68) | EY68: =SUM(AX68:BA68) | EZ68: =SUM(BB68:BE68) | FA68: =SUM(BF68:BI68) | FB68: =SUM(BJ68:BM68) | FC68: =SUM(BN68:BQ68) | FD68: =SUM(BR68:BU68) | FE68: =SUM(BV68:BY68) | FF68: =SUM(BZ68:CC68) | FH68: =SUM(CH68:CK68) | FI68: =SUM(CL68:CO68) | FJ68: =SUM(CP68:CS68) | FK68: =SUM(CT68:CW68) | FL68: =SUM(CX68:DA68) | FM68: =SUM(DB68:DE68) | FN68: =SUM(DF68:DI68) | FO68: =SUM(DJ68:DM68) | FP68: =SUM(DN68:DQ68) | FQ68: =SUM(DR68:DU68) | FR68: =SUM(DV68:DY68) | FS68: =SUM(DZ68:EC68) | FT68: =SUM(ED68:EG68) | FU68: =SUM(EH68:EK68) | FZ68: =SUM(G68:J68) | GA68: =SUM(K68:N68) | GB68: =SUM(O68:R68) | GC68: =SUM(S68:V68) | GD68: =SUM(W68:Z68) | GE68: =SUM(AA68:AD68) | GF68: =SUM(AE68:AH68) | GG68: =SUM(AI68:AL68) | GH68: =SUM(AM68:AP68) | GI68: =SUM(AQ68:AT68) | GJ68: =SUM(AU68:AX68) | GK68: =SUM(AY68:BB68) | GL68: =SUM(BC68:BF68) | GM68: =SUM(BG68:BJ68) | GN68: =SUM(BK68:BN68) | GO68: =SUM(BO68:BR68) | GP68: =SUM(BS68:BV68) | GQ68: =SUM(BW68:BZ68) | GR68: =SUM(CA68:CD68) | GS68: =SUM(CE68:CH68) | GT68: =SUM(CI68:CL68) | GU68: =SUM(CM68:CP68) | GV68: =SUM(CQ68:CT68) | GW68: =SUM(CU68:CX68) | GX68: =SUM(CY68:DB68) | GY68: =SUM(DC68:DF68) | GZ68: =SUM(DG68:DJ68) | HA68: =SUM(DK68:DN68) | HB68: =SUM(DO68:DR68) | HC68: =SUM(DS68:DV68) | HD68: =SUM(DW68:DZ68) | HE68: =SUM(EA68:ED68) | HF68: =SUM(EE68:EH68)
A69: Other | CH69: =CH11-SUM(CH51:CH68) | CI69: =CI11-SUM(CI51:CI68) | CJ69: =CJ11-SUM(CJ51:CJ68) | CK69: =CK11-SUM(CK51:CK68) | CL69: =CL11-SUM(CL51:CL68) | CM69: =CM11-SUM(CM51:CM68) | CN69: =CN11-SUM(CN51:CN68) | CO69: =CO11-SUM(CO51:CO68) | ... DP69: =DP11-SUM(DP51:DP68) | DQ69: =DQ91*DQ150 | DR69: =DR91*DR150 | DS69: =DS91*DS150 | DT69: =DT91*DT150 | DU69: =DU91*DU150 | DV69: =DV91*DV150 | DW69: =DW91*DW150 | DX69: =DX91*DX150 | ... EK69: =EK91*EK150 | EM69: =SUM(B69:E69) | EN69: =SUM(F69:I69) | EO69: =SUM(J69:M69) | EP69: =SUM(N69:Q69) | EQ69: =SUM(R69:U69) | ER69: =SUM(V69:Y69) | ES69: =SUM(Z69:AC69) | ET69: =SUM(AD69:AG69) | EU69: =SUM(AH69:AK69) | EV69: =SUM(AL69:AO69) | EW69: =SUM(AP69:AS69) | EX69: =SUM(AT69:AW69) | EY69: =SUM(AX69:BA69) | EZ69: =SUM(BB69:BE69) | FA69: =SUM(BF69:BI69) | FB69: =SUM(BJ69:BM69) | FC69: =SUM(BN69:BQ69) | FD69: =SUM(BR69:BU69) | FE69: =SUM(BV69:BY69) | FF69: =SUM(BZ69:CC69) | FH69: =SUM(CH69:CK69) | FI69: =SUM(CL69:CO69) | FJ69: =SUM(CP69:CS69) | FK69: =SUM(CT69:CW69) | FL69: =SUM(CX69:DA69) | FM69: =SUM(DB69:DE69) | FN69: =SUM(DF69:DI69) | FO69: =SUM(DJ69:DM69) | FP69: =SUM(DN69:DQ69) | FQ69: =SUM(DR69:DU69) | FR69: =SUM(DV69:DY69) | FS69: =SUM(DZ69:EC69) | FT69: =SUM(ED69:EG69) | FU69: =SUM(EH69:EK69) | FZ69: =SUM(G69:J69) | GA69: =SUM(K69:N69) | GB69: =SUM(O69:R69) | GC69: =SUM(S69:V69) | GD69: =SUM(W69:Z69) | GE69: =SUM(AA69:AD69) | GF69: =SUM(AE69:AH69) | GG69: =SUM(AI69:AL69) | GH69: =SUM(AM69:AP69) | GI69: =SUM(AQ69:AT69) | GJ69: =SUM(AU69:AX69) | GK69: =SUM(AY69:BB69) | GL69: =SUM(BC69:BF69) | GM69: =SUM(BG69:BJ69) | GN69: =SUM(BK69:BN69) | GO69: =SUM(BO69:BR69) | GP69: =SUM(BS69:BV69) | GQ69: =SUM(BW69:BZ69) | GR69: =SUM(CA69:CD69) | GS69: =SUM(CE69:CH69) | GT69: =SUM(CI69:CL69) | GU69: =SUM(CM69:CP69) | GV69: =SUM(CQ69:CT69) | GW69: =SUM(CU69:CX69) | GX69: =SUM(CY69:DB69) | GY69: =SUM(DC69:DF69) | GZ69: =SUM(DG69:DJ69) | HA69: =SUM(DK69:DN69) | HB69: =SUM(DO69:DR69) | HC69: =SUM(DS69:DV69) | HD69: =SUM(DW69:DZ69) | HE69: =SUM(EA69:ED69) | HF69: =SUM(EE69:EH69)
A70: Product0489 revenue | CH70: =SUM(CH51:CH69) | CI70: =SUM(CI51:CI69) | CJ70: =SUM(CJ51:CJ69) | CK70: =SUM(CK51:CK69) | CL70: =SUM(CL51:CL69) | CM70: =SUM(CM51:CM69) | CN70: =SUM(CN51:CN69) | CO70: =SUM(CO51:CO69) | ... EK70: =SUM(EK51:EK69) | EM70: =SUM(B70:E70) | EN70: =SUM(F70:I70) | EO70: =SUM(J70:M70) | EP70: =SUM(N70:Q70) | EQ70: =SUM(R70:U70) | ER70: =SUM(V70:Y70) | ES70: =SUM(Z70:AC70) | ET70: =SUM(AD70:AG70) | EU70: =SUM(AH70:AK70) | EV70: =SUM(AL70:AO70) | EW70: =SUM(AP70:AS70) | EX70: =SUM(AT70:AW70) | EY70: =SUM(AX70:BA70) | EZ70: =SUM(BB70:BE70) | FA70: =SUM(BF70:BI70) | FB70: =SUM(BJ70:BM70) | FC70: =SUM(BN70:BQ70) | FD70: =SUM(BR70:BU70) | FE70: =SUM(BV70:BY70) | FF70: =SUM(BZ70:CC70) | FH70: =SUM(CH70:CK70) | FI70: =SUM(CL70:CO70) | FJ70: =SUM(CP70:CS70) | FK70: =SUM(CT70:CW70) | FL70: =SUM(CX70:DA70) | FM70: =SUM(DB70:DE70) | FN70: =SUM(DF70:DI70) | FO70: =SUM(DJ70:DM70) | FP70: =SUM(DN70:DQ70) | FQ70: =SUM(DR70:DU70) | FR70: =SUM(DV70:DY70) | FS70: =SUM(DZ70:EC70) | FT70: =SUM(ED70:EG70) | FU70: =SUM(EH70:EK70) | FZ70: =SUM(G70:J70) | GA70: =SUM(K70:N70) | GB70: =SUM(O70:R70) | GC70: =SUM(S70:V70) | GD70: =SUM(W70:Z70) | GE70: =SUM(AA70:AD70) | GF70: =SUM(AE70:AH70) | GG70: =SUM(AI70:AL70) | GH70: =SUM(AM70:AP70) | GI70: =SUM(AQ70:AT70) | GJ70: =SUM(AU70:AX70) | GK70: =SUM(AY70:BB70) | GL70: =SUM(BC70:BF70) | GM70: =SUM(BG70:BJ70) | GN70: =SUM(BK70:BN70) | GO70: =SUM(BO70:BR70) | GP70: =SUM(BS70:BV70) | GQ70: =SUM(BW70:BZ70) | GR70: =SUM(CA70:CD70) | GS70: =SUM(CE70:CH70) | GT70: =SUM(CI70:CL70) | GU70: =SUM(CM70:CP70) | GV70: =SUM(CQ70:CT70) | GW70: =SUM(CU70:CX70) | GX70: =SUM(CY70:DB70) | GY70: =SUM(DC70:DF70) | GZ70: =SUM(DG70:DJ70) | HA70: =SUM(DK70:DN70) | HB70: =SUM(DO70:DR70) | HC70: =SUM(DS70:DV70) | HD70: =SUM(DW70:DZ70) | HE70: =SUM(EA70:ED70) | HF70: =SUM(EE70:EH70)
A72: Product units sell-in (mn) | B72: ='Revenue summary'!B$8 | C72: ='Revenue summary'!C$8 | D72: ='Revenue summary'!D$8 | E72: ='Revenue summary'!E$8 | F72: ='Revenue summary'!F$8 | G72: ='Revenue summary'!G$8 | H72: ='Revenue summary'!H$8 | I72: ='Revenue summary'!I$8 | ... EK72: ='Revenue summary'!EK$8 | EM72: =EM$9 | EN72: =EN$9 | EO72: =EO$9 | EP72: =EP$9 | EQ72: =EQ$9 | ER72: =ER$9 | ES72: =ES$9 | ET72: =ET$9 | ... FU72: =FU$9 | FY72: =FY$9 | FZ72: =FZ$9 | GA72: =GA$9 | GB72: =GB$9 | GC72: =GC$9 | GD72: =GD$9 | GE72: =GE$9 | GF72: =GF$9 | ... HF72: =HF$9
A73: Product0489 5 | EM73: =SUM(B73:E73) | EN73: =SUM(F73:I73) | EO73: =SUM(J73:M73) | EP73: =SUM(N73:Q73) | EQ73: =SUM(R73:U73) | ER73: =SUM(V73:Y73) | ES73: =SUM(Z73:AC73) | ET73: =SUM(AD73:AG73) | EU73: =SUM(AH73:AK73) | EV73: =SUM(AL73:AO73) | EW73: =SUM(AP73:AS73) | EX73: =SUM(AT73:AW73) | EY73: =SUM(AX73:BA73) | EZ73: =SUM(BB73:BE73) | FA73: =SUM(BF73:BI73) | FB73: =SUM(BJ73:BM73) | FC73: =SUM(BN73:BQ73) | FD73: =SUM(BR73:BU73) | FE73: =SUM(BV73:BY73) | FF73: =SUM(BZ73:CC73) | FH73: =SUM(CH73:CK73) | FI73: =SUM(CL73:CO73) | FJ73: =SUM(CP73:CS73) | FK73: =SUM(CT73:CW73) | FL73: =SUM(CX73:DA73) | FM73: =SUM(DB73:DE73) | FN73: =SUM(DF73:DI73) | FO73: =SUM(DJ73:DM73) | FP73: =SUM(DN73:DQ73) | FQ73: =SUM(DR73:DU73) | FR73: =SUM(DV73:DY73) | FS73: =SUM(DZ73:EC73) | FT73: =SUM(ED73:EG73) | FU73: =SUM(EH73:EK73) | FY73: =SUM(C73:F73) | FZ73: =SUM(G73:J73) | GA73: =SUM(K73:N73) | GB73: =SUM(O73:R73) | GC73: =SUM(S73:V73) | GD73: =SUM(W73:Z73) | GE73: =SUM(AA73:AD73) | GF73: =SUM(AE73:AH73) | GG73: =SUM(AI73:AL73) | GH73: =SUM(AM73:AP73) | GI73: =SUM(AQ73:AT73) | GJ73: =SUM(AU73:AX73) | GK73: =SUM(AY73:BB73) | GL73: =SUM(BC73:BF73) | GM73: =SUM(BG73:BJ73) | GN73: =SUM(BK73:BN73) | GO73: =SUM(BO73:BR73) | GP73: =SUM(BS73:BV73) | GQ73: =SUM(BW73:BZ73) | GR73: =SUM(CA73:CD73) | GS73: =SUM(CE73:CH73) | GT73: =SUM(CI73:CL73) | GU73: =SUM(CM73:CP73) | GV73: =SUM(CQ73:CT73) | GW73: =SUM(CU73:CX73) | GX73: =SUM(CY73:DB73) | GY73: =SUM(DC73:DF73) | GZ73: =SUM(DG73:DJ73) | HA73: =SUM(DK73:DN73) | HB73: =SUM(DO73:DR73) | HC73: =SUM(DS73:DV73) | HD73: =SUM(DW73:DZ73) | HE73: =SUM(EA73:ED73) | HF73: =SUM(EE73:EH73)
A74: Product0489 6 | CH74: 14.9 | CI74: 8.8 | CJ74: 7.9 | CK74: 5.8 | CL74: 5.3 | CM74: 4 | CN74: 3.2 | CO74: 2 | CP74: 0 | CQ74: 0 | CR74: 0 | CS74: 0 | CT74: 0 | CU74: 0 | CV74: 0 | CW74: 0 | EM74: =SUM(B74:E74) | EN74: =SUM(F74:I74) | EO74: =SUM(J74:M74) | EP74: =SUM(N74:Q74) | EQ74: =SUM(R74:U74) | ER74: =SUM(V74:Y74) | ES74: =SUM(Z74:AC74) | ET74: =SUM(AD74:AG74) | EU74: =SUM(AH74:AK74) | EV74: =SUM(AL74:AO74) | EW74: =SUM(AP74:AS74) | EX74: =SUM(AT74:AW74) | EY74: =SUM(AX74:BA74) | EZ74: =SUM(BB74:BE74) | FA74: =SUM(BF74:BI74) | FB74: =SUM(BJ74:BM74) | FC74: =SUM(BN74:BQ74) | FD74: =SUM(BR74:BU74) | FE74: =SUM(BV74:BY74) | FF74: =SUM(BZ74:CC74) | FH74: =SUM(CH74:CK74) | FI74: =SUM(CL74:CO74) | FJ74: =SUM(CP74:CS74) | FK74: =SUM(CT74:CW74) | FL74: =SUM(CX74:DA74) | FM74: =SUM(DB74:DE74) | FN74: =SUM(DF74:DI74) | FO74: =SUM(DJ74:DM74) | FP74: =SUM(DN74:DQ74) | FQ74: =SUM(DR74:DU74) | FR74: =SUM(DV74:DY74) | FS74: =SUM(DZ74:EC74) | FT74: =SUM(ED74:EG74) | FU74: =SUM(EH74:EK74) | FY74: =SUM(C74:F74) | FZ74: =SUM(G74:J74) | GA74: =SUM(K74:N74) | GB74: =SUM(O74:R74) | GC74: =SUM(S74:V74) | GD74: =SUM(W74:Z74) | GE74: =SUM(AA74:AD74) | GF74: =SUM(AE74:AH74) | GG74: =SUM(AI74:AL74) | GH74: =SUM(AM74:AP74) | GI74: =SUM(AQ74:AT74) | GJ74: =SUM(AU74:AX74) | GK74: =SUM(AY74:BB74) | GL74: =SUM(BC74:BF74) | GM74: =SUM(BG74:BJ74) | GN74: =SUM(BK74:BN74) | GO74: =SUM(BO74:BR74) | GP74: =SUM(BS74:BV74) | GQ74: =SUM(BW74:BZ74) | GR74: =SUM(CA74:CD74) | GS74: =SUM(CE74:CH74) | GT74: =SUM(CI74:CL74) | GU74: =SUM(CM74:CP74) | GV74: =SUM(CQ74:CT74) | GW74: =SUM(CU74:CX74) | GX74: =SUM(CY74:DB74) | GY74: =SUM(DC74:DF74) | GZ74: =SUM(DG74:DJ74) | HA74: =SUM(DK74:DN74) | HB74: =SUM(DO74:DR74) | HC74: =SUM(DS74:DV74) | HD74: =SUM(DW74:DZ74) | HE74: =SUM(EA74:ED74) | HF74: =SUM(EE74:EH74)
A75: Product0489 7 | CH75: 59 | CI75: 37.5 | CJ75: 28.5 | CK75: 20.8 | CL75: 10.5 | CM75: 8 | CN75: 6.7 | CO75: 6.2 | CP75: 6.7 | CQ75: 5 | CR75: 4 | CS75: 3.4 | CT75: 0 | CU75: 0 | CV75: 0 | CW75: 0 | EM75: =SUM(B75:E75) | EN75: =SUM(F75:I75) | EO75: =SUM(J75:M75) | EP75: =SUM(N75:Q75) | EQ75: =SUM(R75:U75) | ER75: =SUM(V75:Y75) | ES75: =SUM(Z75:AC75) | ET75: =SUM(AD75:AG75) | EU75: =SUM(AH75:AK75) | EV75: =SUM(AL75:AO75) | EW75: =SUM(AP75:AS75) | EX75: =SUM(AT75:AW75) | EY75: =SUM(AX75:BA75) | EZ75: =SUM(BB75:BE75) | FA75: =SUM(BF75:BI75) | FB75: =SUM(BJ75:BM75) | FC75: =SUM(BN75:BQ75) | FD75: =SUM(BR75:BU75) | FE75: =SUM(BV75:BY75) | FF75: =SUM(BZ75:CC75) | FH75: =SUM(CH75:CK75) | FI75: =SUM(CL75:CO75) | FJ75: =SUM(CP75:CS75) | FK75: =SUM(CT75:CW75) | FL75: =SUM(CX75:DA75) | FM75: =SUM(DB75:DE75) | FN75: =SUM(DF75:DI75) | FO75: =SUM(DJ75:DM75) | FP75: =SUM(DN75:DQ75) | FQ75: =SUM(DR75:DU75) | FR75: =SUM(DV75:DY75) | FS75: =SUM(DZ75:EC75) | FT75: =SUM(ED75:EG75) | FU75: =SUM(EH75:EK75) | FY75: =SUM(C75:F75) | FZ75: =SUM(G75:J75) | GA75: =SUM(K75:N75) | GB75: =SUM(O75:R75) | GC75: =SUM(S75:V75) | GD75: =SUM(W75:Z75) | GE75: =SUM(AA75:AD75) | GF75: =SUM(AE75:AH75) | GG75: =SUM(AI75:AL75) | GH75: =SUM(AM75:AP75) | GI75: =SUM(AQ75:AT75) | GJ75: =SUM(AU75:AX75) | GK75: =SUM(AY75:BB75) | GL75: =SUM(BC75:BF75) | GM75: =SUM(BG75:BJ75) | GN75: =SUM(BK75:BN75) | GO75: =SUM(BO75:BR75) | GP75: =SUM(BS75:BV75) | GQ75: =SUM(BW75:BZ75) | GR75: =SUM(CA75:CD75) | GS75: =SUM(CE75:CH75) | GT75: =SUM(CI75:CL75) | GU75: =SUM(CM75:CP75) | GV75: =SUM(CQ75:CT75) | GW75: =SUM(CU75:CX75) | GX75: =SUM(CY75:DB75) | GY75: =SUM(DC75:DF75) | GZ75: =SUM(DG75:DJ75) | HA75: =SUM(DK75:DN75) | HB75: =SUM(DO75:DR75) | HC75: =SUM(DS75:DV75) | HD75: =SUM(DW75:DZ75) | HE75: =SUM(EA75:ED75) | HF75: =SUM(EE75:EH75)
A76: Product0489 8 | CK76: 16 | CL76: 28.1 | CM76: 19.5 | CN76: 17.5 | CO76: 15.2 | CP76: 13.6 | CQ76: 10.7 | CR76: 9 | CS76: 8 | CT76: 10 | CU76: 5.3 | CV76: 2.7 | CW76: 0 | CX76: 0.4 | CY76: 0.1 | CZ76: 0.1 | EM76: =SUM(B76:E76) | EN76: =SUM(F76:I76) | EO76: =SUM(J76:M76) | EP76: =SUM(N76:Q76) | EQ76: =SUM(R76:U76) | ER76: =SUM(V76:Y76) | ES76: =SUM(Z76:AC76) | ET76: =SUM(AD76:AG76) | EU76: =SUM(AH76:AK76) | EV76: =SUM(AL76:AO76) | EW76: =SUM(AP76:AS76) | EX76: =SUM(AT76:AW76) | EY76: =SUM(AX76:BA76) | EZ76: =SUM(BB76:BE76) | FA76: =SUM(BF76:BI76) | FB76: =SUM(BJ76:BM76) | FC76: =SUM(BN76:BQ76) | FD76: =SUM(BR76:BU76) | FE76: =SUM(BV76:BY76) | FF76: =SUM(BZ76:CC76) | FH76: =SUM(CH76:CK76) | FI76: =SUM(CL76:CO76) | FJ76: =SUM(CP76:CS76) | FK76: =SUM(CT76:CW76) | FL76: =SUM(CX76:DA76) | FM76: =SUM(DB76:DE76) | FN76: =SUM(DF76:DI76) | FO76: =SUM(DJ76:DM76) | FP76: =SUM(DN76:DQ76) | FQ76: =SUM(DR76:DU76) | FR76: =SUM(DV76:DY76) | FS76: =SUM(DZ76:EC76) | FT76: =SUM(ED76:EG76) | FU76: =SUM(EH76:EK76) | FY76: =SUM(C76:F76) | FZ76: =SUM(G76:J76) | GA76: =SUM(K76:N76) | GB76: =SUM(O76:R76) | GC76: =SUM(S76:V76) | GD76: =SUM(W76:Z76) | GE76: =SUM(AA76:AD76) | GF76: =SUM(AE76:AH76) | GG76: =SUM(AI76:AL76) | GH76: =SUM(AM76:AP76) | GI76: =SUM(AQ76:AT76) | GJ76: =SUM(AU76:AX76) | GK76: =SUM(AY76:BB76) | GL76: =SUM(BC76:BF76) | GM76: =SUM(BG76:BJ76) | GN76: =SUM(BK76:BN76) | GO76: =SUM(BO76:BR76) | GP76: =SUM(BS76:BV76) | GQ76: =SUM(BW76:BZ76) | GR76: =SUM(CA76:CD76) | GS76: =SUM(CE76:CH76) | GT76: =SUM(CI76:CL76) | GU76: =SUM(CM76:CP76) | GV76: =SUM(CQ76:CT76) | GW76: =SUM(CU76:CX76) | GX76: =SUM(CY76:DB76) | GY76: =SUM(DC76:DF76) | GZ76: =SUM(DG76:DJ76) | HA76: =SUM(DK76:DN76) | HB76: =SUM(DO76:DR76) | HC76: =SUM(DS76:DV76) | HD76: =SUM(DW76:DZ76) | HE76: =SUM(EA76:ED76) | HF76: =SUM(EE76:EH76)
A77: Product0489 X | CL77: 28.9 | CM77: 16.1 | CN77: 11.5 | CO77: =7.2+6.8+8.3 | CP77: 46 | CQ77: 21 | CR77: 20 | CS77: =2.6+2.7+2.7+6.9 | CT77: =3+2.5+2.2+7.1+2 | CU77: =1.8+1.6+1.1+3.6 | CV77: =1.1+1.6+0.9+4.1 | CW77: =1.3+0.9+0.8+4.3 | CX77: 3.5 | CY77: =0.5+0.3+0.1+1.1 | CZ77: 2 | DA77: 2 | EM77: =SUM(B77:E77) | EN77: =SUM(F77:I77) | EO77: =SUM(J77:M77) | EP77: =SUM(N77:Q77) | EQ77: =SUM(R77:U77) | ER77: =SUM(V77:Y77) | ES77: =SUM(Z77:AC77) | ET77: =SUM(AD77:AG77) | EU77: =SUM(AH77:AK77) | EV77: =SUM(AL77:AO77) | EW77: =SUM(AP77:AS77) | EX77: =SUM(AT77:AW77) | EY77: =SUM(AX77:BA77) | EZ77: =SUM(BB77:BE77) | FA77: =SUM(BF77:BI77) | FB77: =SUM(BJ77:BM77) | FC77: =SUM(BN77:BQ77) | FD77: =SUM(BR77:BU77) | FE77: =SUM(BV77:BY77) | FF77: =SUM(BZ77:CC77) | FH77: =SUM(CH77:CK77) | FI77: =SUM(CL77:CO77) | FJ77: =SUM(CP77:CS77) | FK77: =SUM(CT77:CW77) | FL77: =SUM(CX77:DA77) | FM77: =SUM(DB77:DE77) | FN77: =SUM(DF77:DI77) | FO77: =SUM(DJ77:DM77) | FP77: =SUM(DN77:DQ77) | FQ77: =SUM(DR77:DU77) | FR77: =SUM(DV77:DY77) | FS77: =SUM(DZ77:EC77) | FT77: =SUM(ED77:EG77) | FU77: =SUM(EH77:EK77) | FY77: =SUM(C77:F77) | FZ77: =SUM(G77:J77) | GA77: =SUM(K77:N77) | GB77: =SUM(O77:R77) | GC77: =SUM(S77:V77) | GD77: =SUM(W77:Z77) | GE77: =SUM(AA77:AD77) | GF77: =SUM(AE77:AH77) | GG77: =SUM(AI77:AL77) | GH77: =SUM(AM77:AP77) | GI77: =SUM(AQ77:AT77) | GJ77: =SUM(AU77:AX77) | GK77: =SUM(AY77:BB77) | GL77: =SUM(BC77:BF77) | GM77: =SUM(BG77:BJ77) | GN77: =SUM(BK77:BN77) | GO77: =SUM(BO77:BR77) | GP77: =SUM(BS77:BV77) | GQ77: =SUM(BW77:BZ77) | GR77: =SUM(CA77:CD77) | GS77: =SUM(CE77:CH77) | GT77: =SUM(CI77:CL77) | GU77: =SUM(CM77:CP77) | GV77: =SUM(CQ77:CT77) | GW77: =SUM(CU77:CX77) | GX77: =SUM(CY77:DB77) | GY77: =SUM(DC77:DF77) | GZ77: =SUM(DG77:DJ77) | HA77: =SUM(DK77:DN77) | HB77: =SUM(DO77:DR77) | HC77: =SUM(DS77:DV77) | HD77: =SUM(DW77:DZ77) | HE77: =SUM(EA77:ED77) | HF77: =SUM(EE77:EH77)
A78: Product0489 11 | CS78: =7.8+3.8+4+2 | CT78: =20.4+10.1+12.5-1+4.5 | CU78: 23 | CV78: 19.5 | CW78: =10.1+4.8+6.1+2 | CX78: 9.8 | CY78: 5.9 | CZ78: 3.5 | DA78: 2.8 | DB78: 4.3 | DC78: 2.3 | DD78: 1.7 | DE78: 0.9 | EM78: =SUM(B78:E78) | EN78: =SUM(F78:I78) | EO78: =SUM(J78:M78) | EP78: =SUM(N78:Q78) | EQ78: =SUM(R78:U78) | ER78: =SUM(V78:Y78) | ES78: =SUM(Z78:AC78) | ET78: =SUM(AD78:AG78) | EU78: =SUM(AH78:AK78) | EV78: =SUM(AL78:AO78) | EW78: =SUM(AP78:AS78) | EX78: =SUM(AT78:AW78) | EY78: =SUM(AX78:BA78) | EZ78: =SUM(BB78:BE78) | FA78: =SUM(BF78:BI78) | FB78: =SUM(BJ78:BM78) | FC78: =SUM(BN78:BQ78) | FD78: =SUM(BR78:BU78) | FE78: =SUM(BV78:BY78) | FF78: =SUM(BZ78:CC78) | FH78: =SUM(CH78:CK78) | FI78: =SUM(CL78:CO78) | FJ78: =SUM(CP78:CS78) | FK78: =SUM(CT78:CW78) | FL78: =SUM(CX78:DA78) | FM78: =SUM(DB78:DE78) | FN78: =SUM(DF78:DI78) | FO78: =SUM(DJ78:DM78) | FP78: =SUM(DN78:DQ78) | FQ78: =SUM(DR78:DU78) | FR78: =SUM(DV78:DY78) | FS78: =SUM(DZ78:EC78) | FT78: =SUM(ED78:EG78) | FU78: =SUM(EH78:EK78) | FY78: =SUM(C78:F78) | FZ78: =SUM(G78:J78) | GA78: =SUM(K78:N78) | GB78: =SUM(O78:R78) | GC78: =SUM(S78:V78) | GD78: =SUM(W78:Z78) | GE78: =SUM(AA78:AD78) | GF78: =SUM(AE78:AH78) | GG78: =SUM(AI78:AL78) | GH78: =SUM(AM78:AP78) | GI78: =SUM(AQ78:AT78) | GJ78: =SUM(AU78:AX78) | GK78: =SUM(AY78:BB78) | GL78: =SUM(BC78:BF78) | GM78: =SUM(BG78:BJ78) | GN78: =SUM(BK78:BN78) | GO78: =SUM(BO78:BR78) | GP78: =SUM(BS78:BV78) | GQ78: =SUM(BW78:BZ78) | GR78: =SUM(CA78:CD78) | GS78: =SUM(CE78:CH78) | GT78: =SUM(CI78:CL78) | GU78: =SUM(CM78:CP78) | GV78: =SUM(CQ78:CT78) | GW78: =SUM(CU78:CX78) | GX78: =SUM(CY78:DB78) | GY78: =SUM(DC78:DF78) | GZ78: =SUM(DG78:DJ78) | HA78: =SUM(DK78:DN78) | HB78: =SUM(DO78:DR78) | HC78: =SUM(DS78:DV78) | HD78: =SUM(DW78:DZ78) | HE78: =SUM(EA78:ED78) | HF78: =SUM(EE78:EH78)
A79: Product0489 12 | CX79: 65 | CY79: =14.8+15.1+7.5+6 | CZ79: 35 | DA79: 25 | DB79: =4.5+2.5+2.2+1.5 | DC79: =4.6+1.6+1.8+1 | DD79: =3.2+1.4+0.6+0.3 | DE79: =2.5+0.7+0.3+0.4 | DF79: =DF92*0.04 | DG79: =DG92*0.04 | DH79: =DH92*0.04 | DI79: =DI92*0.04 | EM79: =SUM(B79:E79) | EN79: =SUM(F79:I79) | EO79: =SUM(J79:M79) | EP79: =SUM(N79:Q79) | EQ79: =SUM(R79:U79) | ER79: =SUM(V79:Y79) | ES79: =SUM(Z79:AC79) | ET79: =SUM(AD79:AG79) | EU79: =SUM(AH79:AK79) | EV79: =SUM(AL79:AO79) | EW79: =SUM(AP79:AS79) | EX79: =SUM(AT79:AW79) | EY79: =SUM(AX79:BA79) | EZ79: =SUM(BB79:BE79) | FA79: =SUM(BF79:BI79) | FB79: =SUM(BJ79:BM79) | FC79: =SUM(BN79:BQ79) | FD79: =SUM(BR79:BU79) | FE79: =SUM(BV79:BY79) | FF79: =SUM(BZ79:CC79) | FH79: =SUM(CH79:CK79) | FI79: =SUM(CL79:CO79) | FJ79: =SUM(CP79:CS79) | FK79: =SUM(CT79:CW79) | FL79: =SUM(CX79:DA79) | FM79: =SUM(DB79:DE79) | FN79: =SUM(DF79:DI79) | FO79: =SUM(DJ79:DM79) | FP79: =SUM(DN79:DQ79) | FQ79: =SUM(DR79:DU79) | FR79: =SUM(DV79:DY79) | FS79: =SUM(DZ79:EC79) | FT79: =SUM(ED79:EG79) | FU79: =SUM(EH79:EK79) | FY79: =SUM(C79:F79) | FZ79: =SUM(G79:J79) | GA79: =SUM(K79:N79) | GB79: =SUM(O79:R79) | GC79: =SUM(S79:V79) | GD79: =SUM(W79:Z79) | GE79: =SUM(AA79:AD79) | GF79: =SUM(AE79:AH79) | GG79: =SUM(AI79:AL79) | GH79: =SUM(AM79:AP79) | GI79: =SUM(AQ79:AT79) | GJ79: =SUM(AU79:AX79) | GK79: =SUM(AY79:BB79) | GL79: =SUM(BC79:BF79) | GM79: =SUM(BG79:BJ79) | GN79: =SUM(BK79:BN79) | GO79: =SUM(BO79:BR79) | GP79: =SUM(BS79:BV79) | GQ79: =SUM(BW79:BZ79) | GR79: =SUM(CA79:CD79) | GS79: =SUM(CE79:CH79) | GT79: =SUM(CI79:CL79) | GU79: =SUM(CM79:CP79) | GV79: =SUM(CQ79:CT79) | GW79: =SUM(CU79:CX79) | GX79: =SUM(CY79:DB79) | GY79: =SUM(DC79:DF79) | GZ79: =SUM(DG79:DJ79) | HA79: =SUM(DK79:DN79) | HB79: =SUM(DO79:DR79) | HC79: =SUM(DS79:DV79) | HD79: =SUM(DW79:DZ79) | HE79: =SUM(EA79:ED79) | HF79: =SUM(EE79:EH79)
A80: Product0489 13 | DA80: 14 | DB80: 63 | DC80: 37.5 | DD80: 30 | DE80: 16 | DF80: =DF92*0.15 | DG80: 7 | DH80: 4.8 | DI80: 2.5 | DJ80: =DJ92*0.11 | DK80: 2 | DL80: =DH79/DG79*DK80 | DM80: =DI79/DH79*DL80 | EM80: =SUM(B80:E80) | EN80: =SUM(F80:I80) | EO80: =SUM(J80:M80) | EP80: =SUM(N80:Q80) | EQ80: =SUM(R80:U80) | ER80: =SUM(V80:Y80) | ES80: =SUM(Z80:AC80) | ET80: =SUM(AD80:AG80) | EU80: =SUM(AH80:AK80) | EV80: =SUM(AL80:AO80) | EW80: =SUM(AP80:AS80) | EX80: =SUM(AT80:AW80) | EY80: =SUM(AX80:BA80) | EZ80: =SUM(BB80:BE80) | FA80: =SUM(BF80:BI80) | FB80: =SUM(BJ80:BM80) | FC80: =SUM(BN80:BQ80) | FD80: =SUM(BR80:BU80) | FE80: =SUM(BV80:BY80) | FF80: =SUM(BZ80:CC80) | FH80: =SUM(CH80:CK80) | FI80: =SUM(CL80:CO80) | FJ80: =SUM(CP80:CS80) | FK80: =SUM(CT80:CW80) | FL80: =SUM(CX80:DA80) | FM80: =SUM(DB80:DE80) | FN80: =SUM(DF80:DI80) | FO80: =SUM(DJ80:DM80) | FP80: =SUM(DN80:DQ80) | FQ80: =SUM(DR80:DU80) | FR80: =SUM(DV80:DY80) | FS80: =SUM(DZ80:EC80) | FT80: =SUM(ED80:EG80) | FU80: =SUM(EH80:EK80) | FY80: =SUM(C80:F80) | FZ80: =SUM(G80:J80) | GA80: =SUM(K80:N80) | GB80: =SUM(O80:R80) | GC80: =SUM(S80:V80) | GD80: =SUM(W80:Z80) | GE80: =SUM(AA80:AD80) | GF80: =SUM(AE80:AH80) | GG80: =SUM(AI80:AL80) | GH80: =SUM(AM80:AP80) | GI80: =SUM(AQ80:AT80) | GJ80: =SUM(AU80:AX80) | GK80: =SUM(AY80:BB80) | GL80: =SUM(BC80:BF80) | GM80: =SUM(BG80:BJ80) | GN80: =SUM(BK80:BN80) | GO80: =SUM(BO80:BR80) | GP80: =SUM(BS80:BV80) | GQ80: =SUM(BW80:BZ80) | GR80: =SUM(CA80:CD80) | GS80: =SUM(CE80:CH80) | GT80: =SUM(CI80:CL80) | GU80: =SUM(CM80:CP80) | GV80: =SUM(CQ80:CT80) | GW80: =SUM(CU80:CX80) | GX80: =SUM(CY80:DB80) | GY80: =SUM(DC80:DF80) | GZ80: =SUM(DG80:DJ80) | HA80: =SUM(DK80:DN80) | HB80: =SUM(DO80:DR80) | HC80: =SUM(DS80:DV80) | HD80: =SUM(DW80:DZ80) | HE80: =SUM(EA80:ED80) | HF80: =SUM(EE80:EH80)
A81: Product0489 14 | DC81: 2 | DD81: 5 | DE81: 25 | DF81: =DF92*0.75 | DG81: 44.5 | DH81: 34.5 | DI81: 20 | DJ81: =DJ92*0.12+2 | DK81: 5 | DL81: 4.5 | DM81: 2 | DN81: 7 | DO81: =DK80*1 | DP81: 1 | DQ81: =DM80*1-1 | EM81: =SUM(B81:E81) | EN81: =SUM(F81:I81) | EO81: =SUM(J81:M81) | EP81: =SUM(N81:Q81) | EQ81: =SUM(R81:U81) | ER81: =SUM(V81:Y81) | ES81: =SUM(Z81:AC81) | ET81: =SUM(AD81:AG81) | EU81: =SUM(AH81:AK81) | EV81: =SUM(AL81:AO81) | EW81: =SUM(AP81:AS81) | EX81: =SUM(AT81:AW81) | EY81: =SUM(AX81:BA81) | EZ81: =SUM(BB81:BE81) | FA81: =SUM(BF81:BI81) | FB81: =SUM(BJ81:BM81) | FC81: =SUM(BN81:BQ81) | FD81: =SUM(BR81:BU81) | FE81: =SUM(BV81:BY81) | FF81: =SUM(BZ81:CC81) | FH81: =SUM(CH81:CK81) | FI81: =SUM(CL81:CO81) | FJ81: =SUM(CP81:CS81) | FK81: =SUM(CT81:CW81) | FL81: =SUM(CX81:DA81) | FM81: =SUM(DB81:DE81) | FN81: =SUM(DF81:DI81) | FO81: =SUM(DJ81:DM81) | FP81: =SUM(DN81:DQ81) | FQ81: =SUM(DR81:DU81) | FR81: =SUM(DV81:DY81) | FS81: =SUM(DZ81:EC81) | FT81: =SUM(ED81:EG81) | FU81: =SUM(EH81:EK81) | FY81: =SUM(C81:F81) | FZ81: =SUM(G81:J81) | GA81: =SUM(K81:N81) | GB81: =SUM(O81:R81) | GC81: =SUM(S81:V81) | GD81: =SUM(W81:Z81) | GE81: =SUM(AA81:AD81) | GF81: =SUM(AE81:AH81) | GG81: =SUM(AI81:AL81) | GH81: =SUM(AM81:AP81) | GI81: =SUM(AQ81:AT81) | GJ81: =SUM(AU81:AX81) | GK81: =SUM(AY81:BB81) | GL81: =SUM(BC81:BF81) | GM81: =SUM(BG81:BJ81) | GN81: =SUM(BK81:BN81) | GO81: =SUM(BO81:BR81) | GP81: =SUM(BS81:BV81) | GQ81: =SUM(BW81:BZ81) | GR81: =SUM(CA81:CD81) | GS81: =SUM(CE81:CH81) | GT81: =SUM(CI81:CL81) | GU81: =SUM(CM81:CP81) | GV81: =SUM(CQ81:CT81) | GW81: =SUM(CU81:CX81) | GX81: =SUM(CY81:DB81) | GY81: =SUM(DC81:DF81) | GZ81: =SUM(DG81:DJ81) | HA81: =SUM(DK81:DN81) | HB81: =SUM(DO81:DR81) | HC81: =SUM(DS81:DV81) | HD81: =SUM(DW81:DZ81) | HE81: =SUM(EA81:ED81) | HF81: =SUM(EE81:EH81)
A82: Product0489 15 | DI82: =DE81*1.05 | DJ82: 53.5 | DK82: =DG81-2.5 | DL82: =DH81 | DM82: 22 | DN82: 12.6 | DO82: 4 | DP82: 4 | DQ82: 1 | DR82: =DN81*0.95 | DS82: =DO81*0.95 | DT82: =DP81*0.95 | DU82: =DQ81*0.95 | EM82: =SUM(B82:E82) | EN82: =SUM(F82:I82) | EO82: =SUM(J82:M82) | EP82: =SUM(N82:Q82) | EQ82: =SUM(R82:U82) | ER82: =SUM(V82:Y82) | ES82: =SUM(Z82:AC82) | ET82: =SUM(AD82:AG82) | EU82: =SUM(AH82:AK82) | EV82: =SUM(AL82:AO82) | EW82: =SUM(AP82:AS82) | EX82: =SUM(AT82:AW82) | EY82: =SUM(AX82:BA82) | EZ82: =SUM(BB82:BE82) | FA82: =SUM(BF82:BI82) | FB82: =SUM(BJ82:BM82) | FC82: =SUM(BN82:BQ82) | FD82: =SUM(BR82:BU82) | FE82: =SUM(BV82:BY82) | FF82: =SUM(BZ82:CC82) | FH82: =SUM(CH82:CK82) | FI82: =SUM(CL82:CO82) | FJ82: =SUM(CP82:CS82) | FK82: =SUM(CT82:CW82) | FL82: =SUM(CX82:DA82) | FM82: =SUM(DB82:DE82) | FN82: =SUM(DF82:DI82) | FO82: =SUM(DJ82:DM82) | FP82: =SUM(DN82:DQ82) | FQ82: =SUM(DR82:DU82) | FR82: =SUM(DV82:DY82) | FS82: =SUM(DZ82:EC82) | FT82: =SUM(ED82:EG82) | FU82: =SUM(EH82:EK82) | FY82: =SUM(C82:F82) | FZ82: =SUM(G82:J82) | GA82: =SUM(K82:N82) | GB82: =SUM(O82:R82) | GC82: =SUM(S82:V82) | GD82: =SUM(W82:Z82) | GE82: =SUM(AA82:AD82) | GF82: =SUM(AE82:AH82) | GG82: =SUM(AI82:AL82) | GH82: =SUM(AM82:AP82) | GI82: =SUM(AQ82:AT82) | GJ82: =SUM(AU82:AX82) | GK82: =SUM(AY82:BB82) | GL82: =SUM(BC82:BF82) | GM82: =SUM(BG82:BJ82) | GN82: =SUM(BK82:BN82) | GO82: =SUM(BO82:BR82) | GP82: =SUM(BS82:BV82) | GQ82: =SUM(BW82:BZ82) | GR82: =SUM(CA82:CD82) | GS82: =SUM(CE82:CH82) | GT82: =SUM(CI82:CL82) | GU82: =SUM(CM82:CP82) | GV82: =SUM(CQ82:CT82) | GW82: =SUM(CU82:CX82) | GX82: =SUM(CY82:DB82) | GY82: =SUM(DC82:DF82) | GZ82: =SUM(DG82:DJ82) | HA82: =SUM(DK82:DN82) | HB82: =SUM(DO82:DR82) | HC82: =SUM(DS82:DV82) | HD82: =SUM(DW82:DZ82) | HE82: =SUM(EA82:ED82) | HF82: =SUM(EE82:EH82)
A83: Product0489 16 | DM83: 26.25 | DN83: 55 | DO83: 42 | DP83: 39 | DQ83: 23 | DR83: =DN82*1.07 | DS83: =DO82*1.07 | DT83: =DP82*1.07 | DU83: =DQ82*1.07 | DV83: =DR82*1 | DW83: =DS82*1 | DX83: =DT82*1 | DY83: =DU82*1 | ED83: =DZ82*1.03 | EE83: =EA82*1.03 | EF83: =EB82*1.03 | EG83: =EC82*1.03 | EH83: =ED82*1.03 | EI83: =EE82*1.03 | EJ83: =EF82*1.03 | EK83: =EG82*1.03 | EM83: =SUM(B83:E83) | EN83: =SUM(F83:I83) | EO83: =SUM(J83:M83) | EP83: =SUM(N83:Q83) | EQ83: =SUM(R83:U83) | ER83: =SUM(V83:Y83) | ES83: =SUM(Z83:AC83) | ET83: =SUM(AD83:AG83) | EU83: =SUM(AH83:AK83) | EV83: =SUM(AL83:AO83) | EW83: =SUM(AP83:AS83) | EX83: =SUM(AT83:AW83) | EY83: =SUM(AX83:BA83) | EZ83: =SUM(BB83:BE83) | FA83: =SUM(BF83:BI83) | FB83: =SUM(BJ83:BM83) | FC83: =SUM(BN83:BQ83) | FD83: =SUM(BR83:BU83) | FE83: =SUM(BV83:BY83) | FF83: =SUM(BZ83:CC83) | FH83: =SUM(CH83:CK83) | FI83: =SUM(CL83:CO83) | FJ83: =SUM(CP83:CS83) | FK83: =SUM(CT83:CW83) | FL83: =SUM(CX83:DA83) | FM83: =SUM(DB83:DE83) | FN83: =SUM(DF83:DI83) | FO83: =SUM(DJ83:DM83) | FP83: =SUM(DN83:DQ83) | FQ83: =SUM(DR83:DU83) | FR83: =SUM(DV83:DY83) | FS83: =SUM(DZ83:EC83) | FT83: =SUM(ED83:EG83) | FU83: =SUM(EH83:EK83) | FY83: =SUM(C83:F83) | FZ83: =SUM(G83:J83) | GA83: =SUM(K83:N83) | GB83: =SUM(O83:R83) | GC83: =SUM(S83:V83) | GD83: =SUM(W83:Z83) | GE83: =SUM(AA83:AD83) | GF83: =SUM(AE83:AH83) | GG83: =SUM(AI83:AL83) | GH83: =SUM(AM83:AP83) | GI83: =SUM(AQ83:AT83) | GJ83: =SUM(AU83:AX83) | GK83: =SUM(AY83:BB83) | GL83: =SUM(BC83:BF83) | GM83: =SUM(BG83:BJ83) | GN83: =SUM(BK83:BN83) | GO83: =SUM(BO83:BR83) | GP83: =SUM(BS83:BV83) | GQ83: =SUM(BW83:BZ83) | GR83: =SUM(CA83:CD83) | GS83: =SUM(CE83:CH83) | GT83: =SUM(CI83:CL83) | GU83: =SUM(CM83:CP83) | GV83: =SUM(CQ83:CT83) | GW83: =SUM(CU83:CX83) | GX83: =SUM(CY83:DB83) | GY83: =SUM(DC83:DF83) | GZ83: =SUM(DG83:DJ83) | HA83: =SUM(DK83:DN83) | HB83: =SUM(DO83:DR83) | HC83: =SUM(DS83:DV83) | HD83: =SUM(DW83:DZ83) | HE83: =SUM(EA83:ED83) | HF83: =SUM(EE83:EH83)
A84: Product0489 17 | DQ84: =DM83*1.03 | DR84: =DN83*1.05 | DS84: =DO83*1.05 | DT84: =DP83*1.05 | DU84: =DQ83*1.05 | DV84: =DR83*1 | DW84: =DS83*1 | DX84: =DT83*1 | DY84: =DU83*1 | DZ84: =DV83*1 | EA84: =DW83*1 | EB84: =DX83*1 | EC84: =DY83*1 | ED84: =DZ83*1.05 | EE84: =EA83*1.05 | EF84: =EB83*1.05 | EG84: =EC83*1.05 | EH84: =ED83*1.05 | EI84: =EE83*1.05 | EJ84: =EF83*1.05 | EK84: =EG83*1.05 | EM84: =SUM(B84:E84) | EN84: =SUM(F84:I84) | EO84: =SUM(J84:M84) | EP84: =SUM(N84:Q84) | EQ84: =SUM(R84:U84) | ER84: =SUM(V84:Y84) | ES84: =SUM(Z84:AC84) | ET84: =SUM(AD84:AG84) | EU84: =SUM(AH84:AK84) | EV84: =SUM(AL84:AO84) | EW84: =SUM(AP84:AS84) | EX84: =SUM(AT84:AW84) | EY84: =SUM(AX84:BA84) | EZ84: =SUM(BB84:BE84) | FA84: =SUM(BF84:BI84) | FB84: =SUM(BJ84:BM84) | FC84: =SUM(BN84:BQ84) | FD84: =SUM(BR84:BU84) | FE84: =SUM(BV84:BY84) | FF84: =SUM(BZ84:CC84) | FH84: =SUM(CH84:CK84) | FI84: =SUM(CL84:CO84) | FJ84: =SUM(CP84:CS84) | FK84: =SUM(CT84:CW84) | FL84: =SUM(CX84:DA84) | FM84: =SUM(DB84:DE84) | FN84: =SUM(DF84:DI84) | FO84: =SUM(DJ84:DM84) | FP84: =SUM(DN84:DQ84) | FQ84: =SUM(DR84:DU84) | FR84: =SUM(DV84:DY84) | FS84: =SUM(DZ84:EC84) | FT84: =SUM(ED84:EG84) | FU84: =SUM(EH84:EK84) | FY84: =SUM(C84:F84) | FZ84: =SUM(G84:J84) | GA84: =SUM(K84:N84) | GB84: =SUM(O84:R84) | GC84: =SUM(S84:V84) | GD84: =SUM(W84:Z84) | GE84: =SUM(AA84:AD84) | GF84: =SUM(AE84:AH84) | GG84: =SUM(AI84:AL84) | GH84: =SUM(AM84:AP84) | GI84: =SUM(AQ84:AT84) | GJ84: =SUM(AU84:AX84) | GK84: =SUM(AY84:BB84) | GL84: =SUM(BC84:BF84) | GM84: =SUM(BG84:BJ84) | GN84: =SUM(BK84:BN84) | GO84: =SUM(BO84:BR84) | GP84: =SUM(BS84:BV84) | GQ84: =SUM(BW84:BZ84) | GR84: =SUM(CA84:CD84) | GS84: =SUM(CE84:CH84) | GT84: =SUM(CI84:CL84) | GU84: =SUM(CM84:CP84) | GV84: =SUM(CQ84:CT84) | GW84: =SUM(CU84:CX84) | GX84: =SUM(CY84:DB84) | GY84: =SUM(DC84:DF84) | GZ84: =SUM(DG84:DJ84) | HA84: =SUM(DK84:DN84) | HB84: =SUM(DO84:DR84) | HC84: =SUM(DS84:DV84) | HD84: =SUM(DW84:DZ84) | HE84: =SUM(EA84:ED84) | HF84: =SUM(EE84:EH84)
A85: Product0489 18 | DU85: =DQ84*1.03 | DV85: =DR84*1.03 | DW85: =DS84*1.03 | DX85: =DT84*1.03 | DY85: =DU84*1.03 | DZ85: =DV84*1.02 | EA85: =DW84*1.02 | EB85: =DX84*1.02 | EC85: =DY84*1.02 | ED85: =DZ84*1.02 | EE85: =EA84*1.02 | EF85: =EB84*1.02 | EG85: =EC84*1.02 | ... EK85: =EG84*1.02 | FH85: =SUM(CH85:CK85) | FI85: =SUM(CL85:CO85) | FJ85: =SUM(CP85:CS85) | FK85: =SUM(CT85:CW85) | FL85: =SUM(CX85:DA85) | FM85: =SUM(DB85:DE85) | FN85: =SUM(DF85:DI85) | FO85: =SUM(DJ85:DM85) | FP85: =SUM(DN85:DQ85) | FQ85: =SUM(DR85:DU85) | FR85: =SUM(DV85:DY85) | FS85: =SUM(DZ85:EC85) | FT85: =SUM(ED85:EG85) | FU85: =SUM(EH85:EK85) | GU85: =SUM(CM85:CP85) | GV85: =SUM(CQ85:CT85) | GW85: =SUM(CU85:CX85) | GX85: =SUM(CY85:DB85) | GY85: =SUM(DC85:DF85) | GZ85: =SUM(DG85:DJ85) | HA85: =SUM(DK85:DN85) | HB85: =SUM(DO85:DR85) | HC85: =SUM(DS85:DV85) | HD85: =SUM(DW85:DZ85) | HE85: =SUM(EA85:ED85) | HF85: =SUM(EE85:EH85)
A86: Product0489 19 | DY86: =DU85*1.02 | DZ86: =DV85*1.02 | EA86: =DW85*1.02 | EB86: =DX85*1.02 | EC86: =DY85*1.02 | ED86: =DZ85*1.02 | EE86: =EA85*1.02 | EF86: =EB85*1.02 | ... EK86: =EG85*1.02 | FH86: =SUM(CH86:CK86) | FI86: =SUM(CL86:CO86) | FJ86: =SUM(CP86:CS86) | FK86: =SUM(CT86:CW86) | FL86: =SUM(CX86:DA86) | FM86: =SUM(DB86:DE86) | FN86: =SUM(DF86:DI86) | FO86: =SUM(DJ86:DM86) | FP86: =SUM(DN86:DQ86) | FQ86: =SUM(DR86:DU86) | FR86: =SUM(DV86:DY86) | FS86: =SUM(DZ86:EC86) | FT86: =SUM(ED86:EG86) | FU86: =SUM(EH86:EK86) | GU86: =SUM(CM86:CP86) | GV86: =SUM(CQ86:CT86) | GW86: =SUM(CU86:CX86) | GX86: =SUM(CY86:DB86) | GY86: =SUM(DC86:DF86) | GZ86: =SUM(DG86:DJ86) | HA86: =SUM(DK86:DN86) | HB86: =SUM(DO86:DR86) | HC86: =SUM(DS86:DV86) | HD86: =SUM(DW86:DZ86) | HE86: =SUM(EA86:ED86) | HF86: =SUM(EE86:EH86)
A87: Product0489 20 | EC87: =DY86*1.02 | ED87: =DZ86*1.02 | EE87: =EA86*1.02 | EF87: =EB86*1.02 | EG87: =EC86*1.02 | EH87: =ED86*1.02 | EI87: =EE86*1.02 | EJ87: =EF86*1.02 | EK87: =EG86*1.02 | FH87: =SUM(CH87:CK87) | FI87: =SUM(CL87:CO87) | FJ87: =SUM(CP87:CS87) | FK87: =SUM(CT87:CW87) | FL87: =SUM(CX87:DA87) | FM87: =SUM(DB87:DE87) | FN87: =SUM(DF87:DI87) | FO87: =SUM(DJ87:DM87) | FP87: =SUM(DN87:DQ87) | FQ87: =SUM(DR87:DU87) | FR87: =SUM(DV87:DY87) | FS87: =SUM(DZ87:EC87) | FT87: =SUM(ED87:EG87) | FU87: =SUM(EH87:EK87) | GU87: =SUM(CM87:CP87) | GV87: =SUM(CQ87:CT87) | GW87: =SUM(CU87:CX87) | GX87: =SUM(CY87:DB87) | GY87: =SUM(DC87:DF87) | GZ87: =SUM(DG87:DJ87) | HA87: =SUM(DK87:DN87) | HB87: =SUM(DO87:DR87) | HC87: =SUM(DS87:DV87) | HD87: =SUM(DW87:DZ87) | HE87: =SUM(EA87:ED87) | HF87: =SUM(EE87:EH87)
A88: Product0489 21 | EG88: =EC87*1.02 | EH88: =ED87*1.02 | EI88: =EE87*1.02 | EJ88: =EF87*1.02 | EK88: =EG87*1.02 | FH88: =SUM(CH88:CK88) | FI88: =SUM(CL88:CO88) | FJ88: =SUM(CP88:CS88) | FK88: =SUM(CT88:CW88) | FL88: =SUM(CX88:DA88) | FM88: =SUM(DB88:DE88) | FN88: =SUM(DF88:DI88) | FO88: =SUM(DJ88:DM88) | FP88: =SUM(DN88:DQ88) | FQ88: =SUM(DR88:DU88) | FR88: =SUM(DV88:DY88) | FS88: =SUM(DZ88:EC88) | FT88: =SUM(ED88:EG88) | FU88: =SUM(EH88:EK88) | GU88: =SUM(CM88:CP88) | GV88: =SUM(CQ88:CT88) | GW88: =SUM(CU88:CX88) | GX88: =SUM(CY88:DB88) | GY88: =SUM(DC88:DF88) | GZ88: =SUM(DG88:DJ88) | HA88: =SUM(DK88:DN88) | HB88: =SUM(DO88:DR88) | HC88: =SUM(DS88:DV88) | HD88: =SUM(DW88:DZ88) | HE88: =SUM(EA88:ED88) | HF88: =SUM(EE88:EH88)
A89: Product0489 SE or low-end equivalent | CH89: 4 | CI89: 4 | CJ89: 4 | CK89: 4 | CL89: 4 | CM89: 4 | CN89: 2 | CO89: 1 | CP89: 1 | CV89: 7.2 | CW89: 11 | CX89: 8 | CY89: 3.5 | CZ89: 3 | DA89: 6 | DB89: 6 | DC89: 5 | DD89: 3 | DE89: 6 | DF89: =DF92*0.05 | DG89: 1.5 | DH89: 3 | DI89: 3 | DJ89: =DJ92*0.07 | DK89: 3 | DL89: 4 | DM89: 3 | DN89: 2 | DO89: 8 | DP89: 5 | DQ89: 4 | DR89: 3 | DS89: 7 | DT89: 3 | DU89: 4 | DV89: 2 | DW89: 7 | DX89: 3 | DY89: 4 | DZ89: 2 | EA89: 7 | EB89: 3 | EC89: 4 | ED89: 2 | EE89: 7 | EF89: 3 | EG89: 4 | EH89: 2 | EI89: 7 | EJ89: 3 | EK89: 4 | EM89: =SUM(B89:E89) | EN89: =SUM(F89:I89) | EO89: =SUM(J89:M89) | EP89: =SUM(N89:Q89) | EQ89: =SUM(R89:U89) | ER89: =SUM(V89:Y89) | ES89: =SUM(Z89:AC89) | ET89: =SUM(AD89:AG89) | EU89: =SUM(AH89:AK89) | EV89: =SUM(AL89:AO89) | EW89: =SUM(AP89:AS89) | EX89: =SUM(AT89:AW89) | EY89: =SUM(AX89:BA89) | EZ89: =SUM(BB89:BE89) | FA89: =SUM(BF89:BI89) | FB89: =SUM(BJ89:BM89) | FC89: =SUM(BN89:BQ89) | FD89: =SUM(BR89:BU89) | FE89: =SUM(BV89:BY89) | FF89: =SUM(BZ89:CC89) | FH89: =SUM(CH89:CK89) | FI89: =SUM(CL89:CO89) | FJ89: =SUM(CP89:CS89) | FK89: =SUM(CT89:CW89) | FL89: =SUM(CX89:DA89) | FM89: =SUM(DB89:DE89) | FN89: =SUM(DF89:DI89) | FO89: =SUM(DJ89:DM89) | FP89: =SUM(DN89:DQ89) | FQ89: =SUM(DR89:DU89) | FR89: =SUM(DV89:DY89) | FS89: =SUM(DZ89:EC89) | FT89: =SUM(ED89:EG89) | FU89: =SUM(EH89:EK89) | FY89: =SUM(C89:F89) | FZ89: =SUM(G89:J89) | GA89: =SUM(K89:N89) | GB89: =SUM(O89:R89) | GC89: =SUM(S89:V89) | GD89: =SUM(W89:Z89) | GE89: =SUM(AA89:AD89) | GF89: =SUM(AE89:AH89) | GG89: =SUM(AI89:AL89) | GH89: =SUM(AM89:AP89) | GI89: =SUM(AQ89:AT89) | GJ89: =SUM(AU89:AX89) | GK89: =SUM(AY89:BB89) | GL89: =SUM(BC89:BF89) | GM89: =SUM(BG89:BJ89) | GN89: =SUM(BK89:BN89) | GO89: =SUM(BO89:BR89) | GP89: =SUM(BS89:BV89) | GQ89: =SUM(BW89:BZ89) | GR89: =SUM(CA89:CD89) | GS89: =SUM(CE89:CH89) | GT89: =SUM(CI89:CL89) | GU89: =SUM(CM89:CP89) | GV89: =SUM(CQ89:CT89) | GW89: =SUM(CU89:CX89) | GX89: =SUM(CY89:DB89) | GY89: =SUM(DC89:DF89) | GZ89: =SUM(DG89:DJ89) | HA89: =SUM(DK89:DN89) | HB89: =SUM(DO89:DR89) | HC89: =SUM(DS89:DV89) | HD89: =SUM(DW89:DZ89) | HE89: =SUM(EA89:ED89) | HF89: =SUM(EE89:EH89)
A90: Next generation | EK90: 30.5 | EM90: =SUM(B90:E90) | EN90: =SUM(F90:I90) | EO90: =SUM(J90:M90) | EP90: =SUM(N90:Q90) | EQ90: =SUM(R90:U90) | ER90: =SUM(V90:Y90) | ES90: =SUM(Z90:AC90) | ET90: =SUM(AD90:AG90) | EU90: =SUM(AH90:AK90) | EV90: =SUM(AL90:AO90) | EW90: =SUM(AP90:AS90) | EX90: =SUM(AT90:AW90) | EY90: =SUM(AX90:BA90) | EZ90: =SUM(BB90:BE90) | FA90: =SUM(BF90:BI90) | FB90: =SUM(BJ90:BM90) | FC90: =SUM(BN90:BQ90) | FD90: =SUM(BR90:BU90) | FE90: =SUM(BV90:BY90) | FF90: =SUM(BZ90:CC90) | FH90: =SUM(CH90:CK90) | FI90: =SUM(CL90:CO90) | FJ90: =SUM(CP90:CS90) | FK90: =SUM(CT90:CW90) | FL90: =SUM(CX90:DA90) | FM90: =SUM(DB90:DE90) | FN90: =SUM(DF90:DI90) | FO90: =SUM(DJ90:DM90) | FP90: =SUM(DN90:DQ90) | FQ90: =SUM(DR90:DU90) | FR90: =SUM(DV90:DY90) | FS90: =SUM(DZ90:EC90) | FT90: =SUM(ED90:EG90) | FU90: =SUM(EH90:EK90) | FY90: =SUM(C90:F90) | FZ90: =SUM(G90:J90) | GA90: =SUM(K90:N90) | GB90: =SUM(O90:R90) | GC90: =SUM(S90:V90) | GD90: =SUM(W90:Z90) | GE90: =SUM(AA90:AD90) | GF90: =SUM(AE90:AH90) | GG90: =SUM(AI90:AL90) | GH90: =SUM(AM90:AP90) | GI90: =SUM(AQ90:AT90) | GJ90: =SUM(AU90:AX90) | GK90: =SUM(AY90:BB90) | GL90: =SUM(BC90:BF90) | GM90: =SUM(BG90:BJ90) | GN90: =SUM(BK90:BN90) | GO90: =SUM(BO90:BR90) | GP90: =SUM(BS90:BV90) | GQ90: =SUM(BW90:BZ90) | GR90: =SUM(CA90:CD90) | GS90: =SUM(CE90:CH90) | GT90: =SUM(CI90:CL90) | GU90: =SUM(CM90:CP90) | GV90: =SUM(CQ90:CT90) | GW90: =SUM(CU90:CX90) | GX90: =SUM(CY90:DB90) | GY90: =SUM(DC90:DF90) | GZ90: =SUM(DG90:DJ90) | HA90: =SUM(DK90:DN90) | HB90: =SUM(DO90:DR90) | HC90: =SUM(DS90:DV90) | HD90: =SUM(DW90:DZ90) | HE90: =SUM(EA90:ED90) | HF90: =SUM(EE90:EH90)
A91: Other | CH91: =CH92-SUM(CH73:CH90) | CI91: =CI92-SUM(CI73:CI90) | CJ91: =CJ92-SUM(CJ73:CJ90) | CK91: =CK92-SUM(CK73:CK90) | CL91: =CL92-SUM(CL73:CL90) | CM91: =CM92-SUM(CM73:CM90) | CN91: =CN92-SUM(CN73:CN90) | CO91: =CO92-SUM(CO73:CO90) | ... DP91: =DP92-SUM(DP73:DP90) | DQ91: 0.5 | DR91: 0.5 | DS91: 0.5 | DT91: 0.5 | DU91: 0.5 | DV91: 0.5 | DW91: 0.5 | DX91: 0.5 | DY91: 0.5 | DZ91: 0.5 | EA91: 0.5 | EB91: 0.5 | EC91: 0.5 | ED91: 0.5 | EE91: 0.5 | EF91: 0.5 | EG91: 0.5 | EH91: 0.5 | EI91: 0.5 | EJ91: 0.5 | EK91: 0.5 | EM91: =SUM(B91:E91) | EN91: =SUM(F91:I91) | EO91: =SUM(J91:M91) | EP91: =SUM(N91:Q91) | EQ91: =SUM(R91:U91) | ER91: =SUM(V91:Y91) | ES91: =SUM(Z91:AC91) | ET91: =SUM(AD91:AG91) | EU91: =SUM(AH91:AK91) | EV91: =SUM(AL91:AO91) | EW91: =SUM(AP91:AS91) | EX91: =SUM(AT91:AW91) | EY91: =SUM(AX91:BA91) | EZ91: =SUM(BB91:BE91) | FA91: =SUM(BF91:BI91) | FB91: =SUM(BJ91:BM91) | FC91: =SUM(BN91:BQ91) | FD91: =SUM(BR91:BU91) | FE91: =SUM(BV91:BY91) | FF91: =SUM(BZ91:CC91) | FH91: =SUM(CH91:CK91) | FI91: =SUM(CL91:CO91) | FJ91: =SUM(CP91:CS91) | FK91: =SUM(CT91:CW91) | FL91: =SUM(CX91:DA91) | FM91: =SUM(DB91:DE91) | FN91: =SUM(DF91:DI91) | FO91: =SUM(DJ91:DM91) | FP91: =SUM(DN91:DQ91) | FQ91: =SUM(DR91:DU91) | FR91: =SUM(DV91:DY91) | FS91: =SUM(DZ91:EC91) | FT91: =SUM(ED91:EG91) | FU91: =SUM(EH91:EK91) | FY91: =SUM(C91:F91) | FZ91: =SUM(G91:J91) | GA91: =SUM(K91:N91) | GB91: =SUM(O91:R91) | GC91: =SUM(S91:V91) | GD91: =SUM(W91:Z91) | GE91: =SUM(AA91:AD91) | GF91: =SUM(AE91:AH91) | GG91: =SUM(AI91:AL91) | GH91: =SUM(AM91:AP91) | GI91: =SUM(AQ91:AT91) | GJ91: =SUM(AU91:AX91) | GK91: =SUM(AY91:BB91) | GL91: =SUM(BC91:BF91) | GM91: =SUM(BG91:BJ91) | GN91: =SUM(BK91:BN91) | GO91: =SUM(BO91:BR91) | GP91: =SUM(BS91:BV91) | GQ91: =SUM(BW91:BZ91) | GR91: =SUM(CA91:CD91) | GS91: =SUM(CE91:CH91) | GT91: =SUM(CI91:CL91) | GU91: =SUM(CM91:CP91) | GV91: =SUM(CQ91:CT91) | GW91: =SUM(CU91:CX91) | GX91: =SUM(CY91:DB91) | GY91: =SUM(DC91:DF91) | GZ91: =SUM(DG91:DJ91) | HA91: =SUM(DK91:DN91) | HB91: =SUM(DO91:DR91) | HC91: =SUM(DS91:DV91) | HD91: =SUM(DW91:DZ91) | HE91: =SUM(EA91:ED91) | HF91: =SUM(EE91:EH91)
A92: Product0489 | AV92: 0.27 | AW92: 1.119 | AX92: 2.315 | AY92: 1.703 | AZ92: 0.717 | BA92: 6.892 | BB92: 4.363 | BC92: 3.793 | BD92: 5.208 | BE92: 7.367 | BF92: 8.737 | BG92: 8.752 | BH92: 8.398 | BI92: 14.102 | BJ92: 16.235 | BK92: 18.647 | BL92: 20.338 | BM92: 17.073 | BN92: 37.044 | BO92: 35.064 | BP92: 26.028 | BQ92: 26.91 | BR92: 47.789 | BS92: 37.43 | BT92: 31.241 | BU92: 33.797 | BV92: 51.025 | BW92: 43.719 | BX92: 35.203 | BY92: 39.272 | BZ92: 74.468 | CA92: 61.17 | CB92: 47.534 | CC92: 48.046 | CD92: 74.779 | CE92: 51.193 | CF92: 40.399 | CG92: 45.513 | CH92: 78.29 | CI92: 50.763 | CJ92: 41.026 | CK92: 46.677 | CL92: 77.316 | CM92: 52.217 | CN92: 41.3 | CO92: 46.889 | CP92: 68.4 | CQ92: 36.834919 | CR92: 33.787287 | CS92: 46.583824 | CT92: 73.754638 | CU92: 36.728983 | CV92: 37.551239 | CW92: 41.69316 | CX92: 87.5 | CY92: 55.26259 | CZ92: 44.389116 | DA92: 51.136678 | DB92: 85 | DC92: 56.46636 | DD92: 45.388769 | DE92: 52.25311 | DF92: 72.138878 | DG92: 55.442642 | DH92: 44.545004 | DI92: 54.095735 | DJ92: 80.190387 | DK92: 52.59013 | DL92: 45.2 | DM92: 56 | DN92: 76.9 | DO92: 57.9 | DP92: =46.4+3.5 | DQ92: =SUM(DQ73:DQ91) | DR92: =SUM(DR73:DR91) | DS92: =SUM(DS73:DS91) | DT92: =SUM(DT73:DT91) | DU92: =SUM(DU73:DU91) | DV92: =SUM(DV73:DV91) | DW92: =SUM(DW73:DW91) | DX92: =SUM(DX73:DX91) | ... EK92: =SUM(EK73:EK91) | EM92: =SUM(B92:E92) | EN92: =SUM(F92:I92) | EO92: =SUM(J92:M92) | EP92: =SUM(N92:Q92) | EQ92: =SUM(R92:U92) | ER92: =SUM(V92:Y92) | ES92: =SUM(Z92:AC92) | ET92: =SUM(AD92:AG92) | EU92: =SUM(AH92:AK92) | EV92: =SUM(AL92:AO92) | EW92: =SUM(AP92:AS92) | EX92: =SUM(AT92:AW92) | EY92: =SUM(AX92:BA92) | EZ92: =SUM(BB92:BE92) | FA92: =SUM(BF92:BI92) | FB92: =SUM(BJ92:BM92) | FC92: =SUM(BN92:BQ92) | FD92: =SUM(BR92:BU92) | FE92: =SUM(BV92:BY92) | FF92: =SUM(BZ92:CC92) | FG92: =SUM(CD92:CG92) | FH92: =SUM(FH73:FH91) | FI92: =SUM(FI73:FI91) | FJ92: =SUM(FJ73:FJ91) | FK92: =SUM(FK73:FK91) | FL92: =SUM(FL73:FL91) | FM92: =SUM(FM73:FM91) | FN92: =SUM(FN73:FN91) | FO92: =SUM(FO73:FO91) | ... FU92: =SUM(FU73:FU91) | FY92: =SUM(C92:F92) | FZ92: =SUM(G92:J92) | GA92: =SUM(K92:N92) | GB92: =SUM(O92:R92) | GC92: =SUM(S92:V92) | GD92: =SUM(W92:Z92) | GE92: =SUM(AA92:AD92) | GF92: =SUM(AE92:AH92) | GG92: =SUM(AI92:AL92) | GH92: =SUM(AM92:AP92) | GI92: =SUM(AQ92:AT92) | GJ92: =SUM(AU92:AX92) | GK92: =SUM(AY92:BB92) | GL92: =SUM(BC92:BF92) | GM92: =SUM(BG92:BJ92) | GN92: =SUM(BK92:BN92) | GO92: =SUM(BO92:BR92) | GP92: =SUM(BS92:BV92) | GQ92: =SUM(BW92:BZ92) | GR92: =SUM(CA92:CD92) | GS92: =SUM(CE92:CH92) | GT92: =SUM(CI92:CL92) | GU92: =SUM(GU73:GU91) | GV92: =SUM(GV73:GV91) | GW92: =SUM(GW73:GW91) | GX92: =SUM(GX73:GX91) | GY92: =SUM(GY73:GY91) | GZ92: =SUM(GZ73:GZ91) | HA92: =SUM(HA73:HA91) | HB92: =SUM(HB73:HB91) | ... HF92: =SUM(HF73:HF91)
A93: Mac | J93: 0.635 | K93: 0.65 | L93: 0.644 | M93: 0.834 | N93: 0.944 | O93: 0.827 | P93: 0.905 | Q93: 0.772 | R93: 1.377 | S93: 1.043 | T93: 1.016 | U93: 1.122 | V93: 0.659 | W93: 0.751 | X93: 0.827 | Y93: 0.85 | Z93: 0.746 | AA93: 0.813 | AB93: 0.808 | AC93: 0.734 | AD93: 0.743 | AE93: 0.711 | AF93: 0.771 | AG93: 0.787 | AH93: 0.829 | AI93: 0.749 | AJ93: 0.876 | AK93: 0.836 | AL93: 1.046 | AM93: 1.07 | AN93: 1.182 | AO93: 1.236 | AP93: 1.254 | AQ93: 1.112 | AR93: 1.327 | AS93: 1.61 | AT93: 1.606 | AU93: 1.517 | AV93: 1.764 | AW93: 2.164 | AX93: 2.319 | AY93: 2.289 | AZ93: 2.496 | BA93: 2.611 | BB93: 2.524 | BC93: 2.216 | BD93: 2.603 | BE93: 3.053 | BF93: 3.362 | BG93: 2.943 | BH93: 3.472 | BI93: 3.885 | BJ93: 4.134 | BK93: 3.76 | BL93: 3.947 | BM93: 4.894 | BN93: 5.198 | BO93: 4.017 | BP93: 4.02 | BQ93: 4.923 | BR93: 4.061 | BS93: 3.952 | BT93: 3.754 | BU93: 4.574 | BV93: 4.837 | BW93: 4.136 | BX93: 4.423364 | BY93: 5.513558 | BZ93: 5.503627 | CA93: 4.5603741 | CB93: 4.8196469 | CC93: 5.760531 | CD93: 5.311307 | CE93: 4.036361 | CF93: 4.259926 | CG93: 4.886 | CH93: 5.374 | CI93: 4.199 | CJ93: 4.292 | CK93: 5.386 | CL93: 5.112 | CM93: 4.078 | CN93: 3.72 | CO93: 5.299 | CP93: 4.983569 | CQ93: 3.896446 | CR93: 4.111739 | CS93: 4.959373 | CT93: 4.926852 | CU93: 3.164426 | CV93: 5.629789 | CW93: 6.958718 | CX93: 7.001052 | CY93: 6.843261 | CZ93: 6.153426 | DA93: 7.161931 | DB93: 7.687786 | DC93: 6.783578 | DD93: 4.800015 | DE93: 9.362318 | DF93: 6.981576 | DG93: 4.204895 | DH93: 4.74749 | DI93: 7.040124 | DJ93: 5.941058 | DK93: 4.791646 | DL93: 5.143166 | DM93: 6.00567 | DN93: 7.094066 | DO93: 5.679554 | DP93: 6.2 | DQ93: =DM93*(1+DQ105) | DR93: =DN93*(1+DR105) | DS93: =DO93*(1+DS105) | DT93: =DP93*(1+DT105) | DU93: =DQ93*(1+DU105) | DV93: =DR93*(1+DV105) | DW93: =DS93*(1+DW105) | DX93: =DT93*(1+DX105) | ... EK93: =EG93*(1+EK105) | EM93: =SUM(B93:E93) | EN93: =SUM(F93:I93) | EO93: =SUM(J93:M93) | EP93: =SUM(N93:Q93) | EQ93: =SUM(R93:U93) | ER93: =SUM(V93:Y93) | ES93: =SUM(Z93:AC93) | ET93: =SUM(AD93:AG93) | EU93: =SUM(AH93:AK93) | EV93: =SUM(AL93:AO93) | EW93: =SUM(AP93:AS93) | EX93: =SUM(AT93:AW93) | EY93: =SUM(AX93:BA93) | EZ93: =SUM(BB93:BE93) | FA93: =SUM(BF93:BI93) | FB93: =SUM(BJ93:BM93) | FC93: =SUM(BN93:BQ93) | FD93: =SUM(BR93:BU93) | FE93: =SUM(BV93:BY93) | FF93: =SUM(BZ93:CC93) | FG93: =SUM(CD93:CG93) | FH93: =SUM(CH93:CK93) | FI93: =SUM(CL93:CO93) | FJ93: =SUM(CP93:CS93) | FK93: =SUM(CT93:CW93) | FL93: =SUM(CX93:DA93) | FM93: =SUM(DB93:DE93) | FN93: =SUM(DF93:DI93) | FO93: =SUM(DJ93:DM93) | FP93: =SUM(DN93:DQ93) | FQ93: =SUM(DR93:DU93) | FR93: =SUM(DV93:DY93) | FS93: =SUM(DZ93:EC93) | FT93: =SUM(ED93:EG93) | FU93: =SUM(EH93:EK93) | FZ93: =SUM(G93:J93) | GA93: =SUM(K93:N93) | GB93: =SUM(O93:R93) | GC93: =SUM(S93:V93) | GD93: =SUM(W93:Z93) | GE93: =SUM(AA93:AD93) | GF93: =SUM(AE93:AH93) | GG93: =SUM(AI93:AL93) | GH93: =SUM(AM93:AP93) | GI93: =SUM(AQ93:AT93) | GJ93: =SUM(AU93:AX93) | GK93: =SUM(AY93:BB93) | GL93: =SUM(BC93:BF93) | GM93: =SUM(BG93:BJ93) | GN93: =SUM(BK93:BN93) | GO93: =SUM(BO93:BR93) | GP93: =SUM(BS93:BV93) | GQ93: =SUM(BW93:BZ93) | GR93: =SUM(CA93:CD93) | GS93: =SUM(CE93:CH93) | GT93: =SUM(CI93:CL93) | GU93: =SUM(CM93:CP93) | GV93: =SUM(CQ93:CT93) | GW93: =SUM(CU93:CX93) | GX93: =SUM(CY93:DB93) | GY93: =SUM(DC93:DF93) | GZ93: =SUM(DG93:DJ93) | HA93: =SUM(DK93:DN93) | HB93: =SUM(DO93:DR93) | HC93: =SUM(DS93:DV93) | HD93: =SUM(DW93:DZ93) | HE93: =SUM(EA93:ED93) | HF93: =SUM(EE93:EH93)
