Workbook
Name ACQPRICE: [3]Summary!$B$14
Name ACQPRICE: [4]Summary!$B$20
Name AMORT: Waterfall!$O$3
Name EXITCAP: Waterfall!$L$5
Name GLA: [3]Summary!$B$3
Name GOINGINCAP: Waterfall!$L$2
Name GPCF1: Waterfall!$E$2
Name GPCF2: Waterfall!$E$3
Name GPCF3: Waterfall!$E$4
Name GPCF4: Waterfall!$E$5
Name GPEQUITY: Waterfall!$C$8
Name HOLD: [3]Summary!$B$25
Name HOLD: [4]Summary!$B$31
Name HURDLE2: Waterfall!$C$3
Name HURDLE3: Waterfall!$C$4
Name INTEREST: Waterfall!#REF!
Name LPCF1: Waterfall!$F$2
Name LPCF2: Waterfall!$F$3
Name LPCF3: Waterfall!$F$4
Name LPCF4: Waterfall!$F$5
Name LPEQUITY: Waterfall!$C$9
Name LTV: Waterfall!#REF!
Name NLA: [3]Summary!$B$3
Name NOIGROWTH: Waterfall!$L$3
Name PREF: Waterfall!$C$2
Name PROMOTE2: Waterfall!$D$3
Name PROMOTE3: Waterfall!$D$4
Name PROMOTE4: Waterfall!$D$5
Name PURCHPRICE: Waterfall!#REF!
Name SALEMONTH: Waterfall!$L$1
Name UNITS: [4]Revenue!$A$17
Name WORKINGCAP: [3]Summary!$B$18
Name WORKINGCAP: [4]Summary!$B$24

Sheet S&U
A1: # Units | B1: ='Unit Mix'!C7 -> 61
B2: Funded at Closing | E2: Funded Post Closing | H2: Total Funding
A3: USES OF FUNDS | B3: Total | C3: % Cost | D3: Per Unit | E3: Total | F3: % Cost | G3: Per Unit | H3: Total | I3: % Cost | J3: Per Unit
A4: Land | B4: =Budget!E34 -> 4800000 | C4: =B4/$H$15 -> 0.19974427 | D4: =B4/$B$1 -> 78688.525 | E4: =Budget!F34 -> 0 | F4: =E4/$H$15 -> 0 | G4: =E4/$B$1 -> 0 | H4: =B4+E4 -> 4800000 | I4: =H4/$H$15 -> 0.19974427 | J4: =H4/$B$1 -> 78688.525
A5: Pre-Development | B5: =Budget!E35 -> 0 | C5: =B5/$H$15 -> 0 | D5: =B5/$B$1 -> 0 | E5: =Budget!F35 -> 200000 | F5: =E5/$H$15 -> 0.0083226779 | G5: =E5/$B$1 -> 3278.6885 | H5: =B5+E5 -> 200000 | I5: =H5/$H$15 -> 0.0083226779 | J5: =H5/$B$1 -> 3278.6885
A6: Hard Cost & Contingency | B6: =Budget!E36 -> 0 | C6: =B6/$H$15 -> 0 | D6: =B6/$B$1 -> 0 | E6: =Budget!F36 -> 16200000 | F6: =E6/$H$15 -> 0.67413691 | G6: =E6/$B$1 -> 265573.77 | H6: =B6+E6 -> 16200000 | I6: =H6/$H$15 -> 0.67413691 | J6: =H6/$B$1 -> 265573.77
A7: Soft Cost & Contingency | B7: =Budget!E37 -> 203435 | C7: =B7/$H$15 -> 0.0084656199 | D7: =B7/$B$1 -> 3335 | E7: =Budget!F37 -> 1013415 | F7: =E7/$H$15 -> 0.042171633 | G7: =E7/$B$1 -> 16613.361 | H7: =B7+E7 -> 1216850 | I7: =H7/$H$15 -> 0.050637253 | J7: =H7/$B$1 -> 19948.361
A8: Dvlp & Constr Mgt Fee | B8: =Budget!E38 -> 0 | C8: =B8/$H$15 -> 0 | D8: =B8/$B$1 -> 0 | E8: =Budget!F38 -> 280000 | F8: =E8/$H$15 -> 0.011651749 | G8: =E8/$B$1 -> 4590.1639 | H8: =B8+E8 -> 280000 | I8: =H8/$H$15 -> 0.011651749 | J8: =H8/$B$1 -> 4590.1639
A9: Closing Costs | B9: =Budget!E39 -> 150000 | C9: =B9/$H$15 -> 0.0062420084 | D9: =B9/$B$1 -> 2459.0164 | E9: =Budget!F39 -> 0 | F9: =E9/$H$15 -> 0 | G9: =E9/$B$1 -> 0 | H9: =B9+E9 -> 150000 | I9: =H9/$H$15 -> 0.0062420084 | J9: =H9/$B$1 -> 2459.0164
A10: Ops Deficit Rsv | B10: =Budget!E40 -> 0 | C10: =B10/$H$15 -> 0 | D10: =B10/$B$1 -> 0 | E10: =Budget!F40 -> 120381.34 | F10: =E10/$H$15 -> 0.0050094754 | G10: =E10/$B$1 -> 1973.4645 | H10: =B10+E10 -> 120381.34 | I10: =H10/$H$15 -> 0.0050094754 | J10: =H10/$B$1 -> 1973.4645
A11: Sr. Debt: Commit Fee | B11: =Budget!E41 -> 156000 | C11: =B11/$H$15 -> 0.0064916888 | D11: =B11/$B$1 -> 2557.377 | E11: =Budget!F41 -> 0 | F11: =E11/$H$15 -> 0 | G11: =E11/$B$1 -> 0 | H11: =B11+E11 -> 156000 | I11: =H11/$H$15 -> 0.0064916888 | J11: =H11/$B$1 -> 2557.377
A12: Sr. Debt: Debt Service | B12: =Budget!E42 -> 0 | C12: =B12/$H$15 -> 0 | D12: =B12/$B$1 -> 0 | E12: =Budget!F42 -> 907495.55 | F12: =E12/$H$15 -> 0.037763966 | G12: =E12/$B$1 -> 14876.976 | H12: =B12+E12 -> 907495.55 | I12: =H12/$H$15 -> 0.037763966 | J12: =H12/$B$1 -> 14876.976
C13: =B13/$B$20 -> #DIV/0! | D13: =B13/$B$1 -> 0 | E13: =SUM(E4:E12) -> 18721292 | F13: =E13/$B$20 -> #DIV/0! | G13: =E13/$B$1 -> 306906.42
C14: =B14/$B$20 -> #DIV/0! | D14: =B14/$B$1 -> 0
A15: Total | B15: =SUM(B4:B12) -> 5309435 | C15: =SUM(C4:C12) -> 0.22094359 | D15: =SUM(D4:D12) -> 87039.918 | E15: =SUM(E4:E12) -> 18721292 | F15: =SUM(F4:F12) -> 0.77905641 | G15: =SUM(G4:G12) -> 306906.42 | H15: =SUM(H4:H12) -> 24030727 | I15: =SUM(I4:I12) -> 1 | J15: =SUM(J4:J12) -> 393946.34
A17: SOURCE OF FUNDS | B17: Total | C17: % Cost | D17: Per Unit | E17: Total | F17: % Cost | G17: Per Unit | H17: Total | I17: % Cost | J17: Per Unit
A18: Property CashFlow | B18: =Draws!E13 -> 0 | C18: =B18/$H$21 -> 0 | D18: =B18/$B$1 -> 0 | E18: =Draws!F13 -> 94333.686 | F18: =E18/$H$21 -> 0.0039255444 | G18: =E18/$B$1 -> 1546.4539 | H18: =B18+E18 -> 94333.686 | I18: =H18/$H$21 -> 0.0039255444 | J18: =H18/$B$1 -> 1546.4539
A19: Equity | B19: =Draws!E15 -> 5309435 | C19: =B19/$H$21 -> 0.22094359 | D19: =B19/$B$1 -> 87039.918 | E19: =Draws!F15 -> 3090565 | F19: =E19/$H$21 -> 0.12860889 | G19: =E19/$B$1 -> 50665 | H19: =B19+E19 -> 8400000 | I19: =H19/$H$21 -> 0.34955247 | J19: =H19/$B$1 -> 137704.92
A20: Debt | B20: =Draws!E14 -> 0 | C20: =B20/$H$21 -> 0 | D20: =B20/$B$1 -> 0 | E20: =Draws!F14 -> 15536393 | F20: =E20/$H$21 -> 0.64652198 | G20: =E20/$B$1 -> 254694.97 | H20: =B20+E20 -> 15536393 | I20: =H20/$H$21 -> 0.64652198 | J20: =H20/$B$1 -> 254694.97
A21: Total | B21: =SUM(B18:B20) -> 5309435 | C21: =SUM(C18:C20) -> 0.22094359 | D21: =SUM(D18:D20) -> 87039.918 | E21: =SUM(E18:E20) -> 18721292 | F21: =SUM(F18:F20) -> 0.77905641 | G21: =SUM(G18:G20) -> 306906.42 | H21: =SUM(H18:H20) -> 24030727 | I21: =SUM(I18:I20) -> 1 | J21: =SUM(J18:J20) -> 393946.34
E23: Total Cost After Excess CF | H23: =H21-H18 -> 23936393
E24: Equity % Total | H24: 0.35
E25: Total Equity Required | H25: =H23*H24 -> 8377737.6

Sheet Budget
B1: Construction Budget
E2: At Closing | F2: Post Closing | G2: Total Cost
B3: Land | E3: =Draws!E69 -> 4800000 | F3: =Draws!F69 -> 0 | G3: =SUM(E3:F3) -> 4800000
B4: Pre-Development | E4: =Draws!E71 -> 0 | F4: =Draws!F71 -> 200000 | G4: =SUM(E4:F4) -> 200000
B5: Hard Costs
C6: Hard Costs (Construction) | E6: =Draws!E74 -> 0 | F6: =Draws!F74 -> 16200000 | G6: =SUM(E6:F6) -> 16200000
C7: Hard Cost Contingency | D7: (2) | E7: =Draws!E75 -> 0 | F7: =Draws!F75 -> 0 | G7: =SUM(E7:F7) -> 0
B8: Total Hard Costs + Contingency | E8: =SUM(E6:E7) -> 0 | F8: =SUM(F6:F7) -> 16200000 | G8: =SUM(G6:G7) -> 16200000
B9: Soft Costs
C10: =Draws!C79 -> Architectural | E10: =Draws!E79 -> 0 | F10: =Draws!F79 -> 244000 | G10: =SUM(E10:F10) -> 244000
C11: =Draws!C80 -> Engineering & Related | E11: =Draws!E80 -> 0 | F11: =Draws!F80 -> 33550 | G11: =SUM(E11:F11) -> 33550
C12: =Draws!C81 -> Impact/Permits | E12: =Draws!E81 -> 0 | F12: =Draws!F81 -> 549000 | G12: =SUM(E12:F12) -> 549000
C13: =Draws!C82 -> Marketing | E13: =Draws!E82 -> 0 | F13: =Draws!F82 -> 24400 | G13: =SUM(E13:F13) -> 24400
C14: =Draws!C83 -> Bldr Risk & Perf Bond | E14: =Draws!E83 -> 154635 | F14: =Draws!F83 -> 0 | G14: =SUM(E14:F14) -> 154635
C15: =Draws!C84 -> Legal & Professional | E15: =Draws!E84 -> 48800 | F15: =Draws!F84 -> 0 | G15: =SUM(E15:F15) -> 48800
C16: =Draws!C85 -> Investor Admin Costs | E16: =Draws!E85 -> 0 | F16: =Draws!F85 -> 9150 | G16: =SUM(E16:F16) -> 9150
C17: =Draws!C86 -> RE Tax During Constr | E17: =Draws!E86 -> 0 | F17: =Draws!F86 -> 92315 | G17: =SUM(E17:F17) -> 92315
B18: Subtotal Soft Costs | E18: =SUM(E10:E17) -> 203435 | F18: =SUM(F10:F17) -> 952415 | G18: =SUM(G10:G17) -> 1155850
B20: Soft Cost Contingency | D20: (3) | E20: =Draws!E89 -> 0 | F20: =Draws!F89 -> 61000 | G20: =Draws!G89 -> 61000
B21: Dvlp & Constr Mgt Fee | D21: (4) | E21: =Draws!E90 -> 0 | F21: =Draws!F90 -> 280000 | G21: =Draws!G90 -> 280000
B22: Closing Costs | E22: =Draws!E91 -> 150000 | F22: =Draws!F91 -> 0 | G22: =Draws!G91 -> 150000
B23: =Draws!C27 -> Ops Deficit Rsv | E23: =Draws!E92 -> 0 | F23: =Draws!F92 -> 120381.34 | G23: =Draws!G92 -> 120381.34
B24: =Draws!C28 -> Sr. Debt: Commit Fee | D24: 0.01 | E24: =Draws!E93 -> 156000 | F24: =Draws!F93 -> 0 | G24: =Draws!G93 -> 156000
B25: Sr. Debt: Debt Service | D25: (5) | E25: =Draws!E94 -> 0 | F25: =Draws!F94 -> 907495.55 | G25: =Draws!G94 -> 907495.55
C27: Total Development Costs | E27: =E3+E4+E8+E18+SUM(E20:E25) -> 5309435 | F27: =F3+F4+F8+F18+SUM(F20:F25) -> 18721292 | G27: =G3+G4+G8+G18+SUM(G20:G25) -> 24030727
B28: (2) Hard cost contingency: | D28: =G7/G6 -> 0 | E28: % hard costs.
B29: (3) Soft cost contingency: | D29: =G20/G18 -> 0.052775014 | E29: % soft costs.
B30: (4) Dvlp Fee | D30: =G21/(G18+G8) -> 0.016132889 | E30: % hard+soft costs
B32: Summary Construction Budget
E33: At Closing | F33: Post Closing | G33: Total Cost
B34: Land | E34: =Budget!E3 -> 4800000 | F34: =Budget!F3 -> 0 | G34: =Budget!G3 -> 4800000
B35: Pre-Development | E35: =E4 -> 0 | F35: =F4 -> 200000 | G35: =G4 -> 200000
B36: Hard Cost & Contingency | E36: =Budget!E8 -> 0 | F36: =Budget!F8 -> 16200000 | G36: =Budget!G8 -> 16200000
B37: Soft Cost & Contingency | E37: =Budget!E18+Budget!E20 -> 203435 | F37: =Budget!F18+Budget!F20 -> 1013415 | G37: =Budget!G18+Budget!G20 -> 1216850
B38: Dvlp & Constr Mgt Fee | E38: =Budget!E21 -> 0 | F38: =Budget!F21 -> 280000 | G38: =Budget!G21 -> 280000
B39: Closing Costs | E39: =Budget!E22 -> 150000 | F39: =Budget!F22 -> 0 | G39: =Budget!G22 -> 150000
B40: Ops Deficit Rsv | E40: =Budget!E23 -> 0 | F40: =Budget!F23 -> 120381.34 | G40: =Budget!G23 -> 120381.34
B41: Sr. Debt: Commit Fee | E41: =Budget!E24 -> 156000 | F41: =Budget!F24 -> 0 | G41: =Budget!G24 -> 156000
B42: Sr. Debt: Debt Service | E42: =Budget!E25 -> 0 | F42: =Budget!F25 -> 907495.55 | G42: =Budget!G25 -> 907495.55
B43: Total Development Costs | E43: =SUM(E34:E42) -> 5309435 | F43: =SUM(F34:F42) -> 18721292 | G43: =SUM(G34:G42) -> 24030727

Sheet Draws
B1: Sr. Interest | D1: =G29 -> 907495.55 | H1: =G16 -> 24030727
B2: IR Sized Based on | D2: Forward Rate | E2: (Rate Today or Forward Rate)
D3: Start Mo. | E3: End Mo. | F3: # Ms. | G3: Start Date
B4: Pre-Development | D4: 1 | E4: =D4+F4-1 -> 6 | F4: 6 | G4: 45597
B5: Construction | D5: =E4+1 -> 7 | E5: =D5+F5-1 -> 20 | F5: 14 | G5: =EDATE(G4,F4) -> 45778
B6: Lease-Up | D6: =E5+1 -> 21 | E6: =D6+F6-1 -> 22 | F6: 2 | G6: =EDATE(G5,F5) -> 46204
B7: NOI+ | D7: =E6+1 -> 23 | E7: =D7+F7-1 -> 24 | F7: 2 | G7: =EDATE(G6,F6) -> 46266
B8: Brk Even CF | D8: =E7+1 -> 25 | E8: =D8+F8-1 -> 29 | F8: 5 | G8: =EDATE(G7,F7) -> 46327 | H8: YEAR 0 | I8: YEAR 1 | U8: YEAR 2 | AG8: YEAR 3 | AS8: YEAR 4 | BE8: YEAR 5
B9: Sale Date | F9: 36 | G9: =EDATE(G4,F9-1) -> 46661 | I9: =IF(I11<=$E$4,"Pre-Dvlp",IF(I11<=$E$5,"Constr",IF(I11<=$E$6,"Lease-Up",IF(I11<=$E$7,"NOI+","B/E")))) -> Pre-Dvlp | J9: =IF(J11<=$E$4,"Pre-Dvlp",IF(J11<=$E$5,"Constr",IF(J11<=$E$6,"Lease-Up",IF(J11<=$E$7,"NOI+","B/E")))) -> Pre-Dvlp | K9: =IF(K11<=$E$4,"Pre-Dvlp",IF(K11<=$E$5,"Constr",IF(K11<=$E$6,"Lease-Up",IF(K11<=$E$7,"NOI+","B/E")))) -> Pre-Dvlp | L9: =IF(L11<=$E$4,"Pre-Dvlp",IF(L11<=$E$5,"Constr",IF(L11<=$E$6,"Lease-Up",IF(L11<=$E$7,"NOI+","B/E")))) -> Pre-Dvlp | M9: =IF(M11<=$E$4,"Pre-Dvlp",IF(M11<=$E$5,"Constr",IF(M11<=$E$6,"Lease-Up",IF(M11<=$E$7,"NOI+","B/E")))) -> Pre-Dvlp | N9: =IF(N11<=$E$4,"Pre-Dvlp",IF(N11<=$E$5,"Constr",IF(N11<=$E$6,"Lease-Up",IF(N11<=$E$7,"NOI+","B/E")))) -> Pre-Dvlp | O9: =IF(O11<=$E$4,"Pre-Dvlp",IF(O11<=$E$5,"Constr",IF(O11<=$E$6,"Lease-Up",IF(O11<=$E$7,"NOI+","B/E")))) -> Constr | P9: =IF(P11<=$E$4,"Pre-Dvlp",IF(P11<=$E$5,"Constr",IF(P11<=$E$6,"Lease-Up",IF(P11<=$E$7,"NOI+","B/E")))) -> Constr | ... BP9: =IF(BP11<=$E$4,"Pre-Dvlp",IF(BP11<=$E$5,"Constr",IF(BP11<=$E$6,"Lease-Up",IF(BP11<=$E$7,"NOI+","B/E")))) -> B/E
H10: =EDATE(G4,-1) -> 45566 | I10: =EOMONTH(H10,1) -> 45626 | J10: =EOMONTH(I10,1) -> 45657 | K10: =EOMONTH(J10,1) -> 45688 | L10: =EOMONTH(K10,1) -> 45716 | M10: =EOMONTH(L10,1) -> 45747 | N10: =EOMONTH(M10,1) -> 45777 | O10: =EOMONTH(N10,1) -> 45808 | P10: =EOMONTH(O10,1) -> 45838 | ... BP10: =EOMONTH(BO10,1) -> 47422
D11: Total | E11: at Closing | F11: To B/E | G11: Total | H11: Closing | I11: 1 | J11: =I11+1 -> 2 | K11: =J11+1 -> 3 | L11: =K11+1 -> 4 | M11: =L11+1 -> 5 | N11: =M11+1 -> 6 | O11: =N11+1 -> 7 | P11: =O11+1 -> 8 | Q11: =P11+1 -> 9 | ... BP11: =BO11+1 -> 60
B12: FUNDING SOURCES
C13: Excess Property CF | E13: =SUM(H13) -> 0 | F13: =SUM(I13:BP13) -> 94333.686 | G13: =E13+F13 -> 94333.686 | H13: 0 | I13: =IF(I9="B/E",0,IF('Lease Up'!I46>0,'Lease Up'!I46,0)) -> 0 | J13: =IF(J9="B/E",0,IF('Lease Up'!J46>0,'Lease Up'!J46,0)) -> 0 | K13: =IF(K9="B/E",0,IF('Lease Up'!K46>0,'Lease Up'!K46,0)) -> 0 | L13: =IF(L9="B/E",0,IF('Lease Up'!L46>0,'Lease Up'!L46,0)) -> 0 | M13: =IF(M9="B/E",0,IF('Lease Up'!M46>0,'Lease Up'!M46,0)) -> 0 | N13: =IF(N9="B/E",0,IF('Lease Up'!N46>0,'Lease Up'!N46,0)) -> 0 | O13: =IF(O9="B/E",0,IF('Lease Up'!O46>0,'Lease Up'!O46,0)) -> 0 | P13: =IF(P9="B/E",0,IF('Lease Up'!P46>0,'Lease Up'!P46,0)) -> 0 | ... BP13: =IF(BP9="B/E",0,IF('Lease Up'!BP46>0,'Lease Up'!BP46,0)) -> 0
C14: Senior Debt | E14: =SUM(H14) -> 0 | F14: =SUM(I14:BP14) -> 15536393 | G14: =E14+F14 -> 15536393 | H14: =IF(H15=H32,0,IF(H49=$D$15,H32,H32-H50)) -> 0 | I14: =I44+I45 -> 0 | J14: =J44+J45 -> 0 | K14: =K44+K45 -> 0 | L14: =L44+L45 -> 0 | M14: =M44+M45 -> 0 | N14: =N44+N45 -> 0 | O14: =O44+O45 -> 0 | P14: =P44+P45 -> 0 | ... BP14: =BP44+BP45 -> 0
C15: Equity | D15: 8400000 | E15: =SUM(H15) -> 5309435 | F15: =SUM(I15:BP15) -> 3090565 | G15: =E15+F15 -> 8400000 | H15: =IF(H49=$D$15,0,IF(H32+H49<=$D$15,H32,IF(H32+H49>$D$15,$D$15-H49,0))) -> 5309435 | I15: =IF(I49=$D$15,0,IF(I32+I49<=$D$15,I32,IF(I32+I49>$D$15,$D$15-I49,0))) -> 33333.333 | J15: =IF(J49=$D$15,0,IF(J32+J49<=$D$15,J32,IF(J32+J49>$D$15,$D$15-J49,0))) -> 33333.333 | K15: =IF(K49=$D$15,0,IF(K32+K49<=$D$15,K32,IF(K32+K49>$D$15,$D$15-K49,0))) -> 33333.333 | L15: =IF(L49=$D$15,0,IF(L32+L49<=$D$15,L32,IF(L32+L49>$D$15,$D$15-L49,0))) -> 33333.333 | M15: =IF(M49=$D$15,0,IF(M32+M49<=$D$15,M32,IF(M32+M49>$D$15,$D$15-M49,0))) -> 33333.333 | N15: =IF(N49=$D$15,0,IF(N32+N49<=$D$15,N32,IF(N32+N49>$D$15,$D$15-N49,0))) -> 33333.333 | O15: =IF(O49=$D$15,0,IF(O32+O49<=$D$15,O32,IF(O32+O49>$D$15,$D$15-O49,0))) -> 1249529.6 | ... BP15: =IF(BP49=$D$15,0,IF(BP32+BP49<=$D$15,BP32,IF(BP32+BP49>$D$15,$D$15-BP49,0))) -> 0
B16: TOTAL FUNDING SOURCES | E16: =SUM(E13:E15) -> 5309435 | F16: =SUM(F13:F15) -> 18721292 | G16: =SUM(G13:G15) -> 24030727 | H16: =SUM(H13:H15) -> 5309435 | I16: =SUM(I13:I15) -> 33333.333 | J16: =SUM(J13:J15) -> 33333.333 | K16: =SUM(K13:K15) -> 33333.333 | L16: =SUM(L13:L15) -> 33333.333 | ... BP16: =SUM(BP13:BP15) -> 0
B18: COSTS
C19: Land Acquisition | E19: =SUM(H19) -> 4800000 | F19: =SUM(I19:BP19) -> 0 | G19: =E19+F19 -> 4800000 | H19: =H69 -> 4800000 | I19: =I69 -> 0 | J19: =J69 -> 0 | K19: =K69 -> 0 | L19: =L69 -> 0 | M19: =M69 -> 0 | N19: =N69 -> 0 | O19: =O69 -> 0 | ... BP19: =BP69 -> 0
C20: Pre-Development | E20: =SUM(H20) -> 0 | F20: =SUM(I20:BP20) -> 200000 | G20: =E20+F20 -> 200000 | I20: =I71 -> 33333.333 | J20: =J71 -> 33333.333 | K20: =K71 -> 33333.333 | L20: =L71 -> 33333.333 | M20: =M71 -> 33333.333 | N20: =N71 -> 33333.333 | O20: =O71 -> 0 | P20: =P71 -> 0 | ... BP20: =BP71 -> 0
C21: Hard Costs | E21: =SUM(H21) -> 0 | F21: =SUM(I21:BP21) -> 16200000 | G21: =E21+F21 -> 16200000 | H21: =H74 -> 0 | I21: =I74 -> 0 | J21: =J74 -> 0 | K21: =K74 -> 0 | L21: =L74 -> 0 | M21: =M74 -> 0 | N21: =N74 -> 0 | O21: =O74 -> 1157142.9 | ... BP21: =BP74 -> 0
C22: Hard Cost Contingency | E22: =SUM(H22) -> 0 | F22: =SUM(I22:BP22) -> 0 | G22: =E22+F22 -> 0 | H22: =H75 -> 0 | I22: =I75 -> 0 | J22: =J75 -> 0 | K22: =K75 -> 0 | L22: =L75 -> 0 | M22: =M75 -> 0 | N22: =N75 -> 0 | O22: =O75 -> 0 | ... BP22: =BP75 -> 0
C23: Soft Costs | E23: =SUM(H23) -> 203435 | F23: =SUM(I23:BP23) -> 952415 | G23: =E23+F23 -> 1155850 | H23: =SUM(H79:H86) -> 203435 | I23: =SUM(I79:I86) -> 0 | J23: =SUM(J79:J86) -> 0 | K23: =SUM(K79:K86) -> 0 | L23: =SUM(L79:L86) -> 0 | M23: =SUM(M79:M86) -> 0 | N23: =SUM(N79:N86) -> 0 | O23: =SUM(O79:O86) -> 68029.643 | ... BP23: =SUM(BP79:BP86) -> 0
C24: Soft Cost Contingency | E24: =SUM(H24) -> 0 | F24: =SUM(I24:BP24) -> 61000 | G24: =E24+F24 -> 61000 | H24: =H89 -> 0 | I24: =I89 -> 0 | J24: =J89 -> 0 | K24: =K89 -> 0 | L24: =L89 -> 0 | M24: =M89 -> 0 | N24: =N89 -> 0 | O24: =O89 -> 4357.1429 | ... BP24: =BP89 -> 0
C25: Dvlp/Const Mgt Fees | E25: =SUM(H25) -> 0 | F25: =SUM(I25:BP25) -> 280000 | G25: =E25+F25 -> 280000 | H25: =H90 -> 0 | I25: =I90 -> 0 | J25: =J90 -> 0 | K25: =K90 -> 0 | L25: =L90 -> 0 | M25: =M90 -> 0 | N25: =N90 -> 0 | O25: =O90 -> 20000 | ... BP25: =BP90 -> 0
C26: Closing Costs | E26: =SUM(H26) -> 150000 | F26: =SUM(I26:BP26) -> 0 | G26: =E26+F26 -> 150000 | H26: =H91 -> 150000 | I26: =I91 -> 0 | J26: =J91 -> 0 | K26: =K91 -> 0 | L26: =L91 -> 0 | M26: =M91 -> 0 | N26: =N91 -> 0 | O26: =O91 -> 0 | ... BP26: =BP91 -> 0
C27: Ops Deficit Rsv | E27: =SUM(H27) -> 0 | F27: =SUM(I27:BP27) -> 120381.34 | G27: =E27+F27 -> 120381.34 | H27: =H92 -> 0 | I27: =I92 -> 0 | J27: =J92 -> 0 | K27: =K92 -> 0 | L27: =L92 -> 0 | M27: =M92 -> 0 | N27: =N92 -> 0 | O27: =O92 -> 0 | ... BP27: =BP92 -> 0
C28: Sr. Debt: Commit Fee | D28: 0.01 | E28: =SUM(H28) -> 156000 | F28: =SUM(I28:BP28) -> 0 | G28: =E28+F28 -> 156000 | H28: =H93 -> 156000 | I28: =I93 -> 0 | J28: =J93 -> 0 | K28: =K93 -> 0 | L28: =L93 -> 0 | M28: =M93 -> 0 | N28: =N93 -> 0 | O28: =O93 -> 0 | ... BP28: =BP93 -> 0
C29: Sr. Debt: Debt Service | E29: =SUM(H29) -> 0 | F29: =SUM(I29:BP29) -> 907495.55 | G29: =E29+F29 -> 907495.55 | H29: =H41 -> 0 | I29: =I41 -> 0 | J29: =J41 -> 0 | K29: =K41 -> 0 | L29: =L41 -> 0 | M29: =M41 -> 0 | N29: =N41 -> 0 | O29: =O41 -> 0 | ... BP29: =BP41 -> 0
B30: TOTAL COST | E30: =SUM(E19:E29) -> 5309435 | F30: =SUM(F19:F29) -> 18721292 | G30: =SUM(G19:G29) -> 24030727 | H30: =SUM(H19:H29) -> 5309435 | I30: =SUM(I19:I29) -> 33333.333 | J30: =SUM(J19:J29) -> 33333.333 | K30: =SUM(K19:K29) -> 33333.333 | L30: =SUM(L19:L29) -> 33333.333 | ... BP30: =SUM(BP19:BP29) -> 0
C31: Less: Excess Property CF | E31: =H31 -> 0 | F31: =SUM(I31:AN31) -> -94333.686 | G31: =-G13 -> -94333.686 | H31: =-H13 -> 0 | I31: =-I13 -> 0 | J31: =-J13 -> 0 | K31: =-K13 -> 0 | L31: =-L13 -> 0 | M31: =-M13 -> 0 | N31: =-N13 -> 0 | ... BP31: =-BP13 -> 0
B32: TOTAL CAPITALIZATION | E32: =H32 -> 5309435 | G32: =SUM(G30:G31) -> 23936393 | H32: =SUM(H30:H31) -> 5309435 | I32: =SUM(I30:I31) -> 33333.333 | J32: =SUM(J30:J31) -> 33333.333 | K32: =SUM(K30:K31) -> 33333.333 | L32: =SUM(L30:L31) -> 33333.333 | M32: =SUM(M30:M31) -> 33333.333 | N32: =SUM(N30:N31) -> 33333.333 | ... BP32: =SUM(BP30:BP31) -> 0
C33: 1 ms. Term SOFR - forward curve | H33: ='Forward Rate'!G6 -> 0.0530533 | I33: ='Forward Rate'!H6 -> 0.0523577 | J33: ='Forward Rate'!I6 -> 0.0518021 | K33: ='Forward Rate'!J6 -> 0.0512678 | L33: ='Forward Rate'!K6 -> 0.0496218 | M33: ='Forward Rate'!L6 -> 0.0493128 | N33: ='Forward Rate'!M6 -> 0.0493027 | O33: ='Forward Rate'!N6 -> 0.0474269 | ... BP33: ='Forward Rate'!BO6 -> 0.0375526
C34: Spread | H34: 0.03 | I34: =$H$34 -> 0.03 | J34: =$H$34 -> 0.03 | K34: =$H$34 -> 0.03 | L34: =$H$34 -> 0.03 | M34: =$H$34 -> 0.03 | N34: =$H$34 -> 0.03 | O34: =$H$34 -> 0.03 | P34: =$H$34 -> 0.03 | ... BP34: =$H$34 -> 0.03
C35: Total Rate | H35: =H33+H34 -> 0.0830533 | I35: =I33+I34 -> 0.0823577 | J35: =J33+J34 -> 0.0818021 | K35: =K33+K34 -> 0.0812678 | L35: =L33+L34 -> 0.0796218 | M35: =M33+M34 -> 0.0793128 | N35: =N33+N34 -> 0.0793027 | O35: =O33+O34 -> 0.0774269 | ... BP35: =BP33+BP34 -> 0.0675526
C36: Total Rate Floor | H36: =H35-2% -> 0.0630533 | I36: =$H$36 -> 0.0630533 | J36: =$H$36 -> 0.0630533 | K36: =$H$36 -> 0.0630533 | L36: =$H$36 -> 0.0630533 | M36: =$H$36 -> 0.0630533 | N36: =$H$36 -> 0.0630533 | O36: =$H$36 -> 0.0630533 | P36: =$H$36 -> 0.0630533 | ... BP36: =$H$36 -> 0.0630533
C37: Greater of Index + Spread or Floor | H37: =MAX(H35:H36) -> 0.0830533 | I37: =MAX(I35:I36) -> 0.0823577 | J37: =MAX(J35:J36) -> 0.0818021 | K37: =MAX(K35:K36) -> 0.0812678 | L37: =MAX(L35:L36) -> 0.0796218 | M37: =MAX(M35:M36) -> 0.0793128 | N37: =MAX(N35:N36) -> 0.0793027 | O37: =MAX(O35:O36) -> 0.0774269 | ... BP37: =MAX(BP35:BP36) -> 0.0675526
C38: Premium for Rate Sizing | H38: 0.005 | I38: =$H$38 -> 0.005 | J38: =$H$38 -> 0.005 | K38: =$H$38 -> 0.005 | L38: =$H$38 -> 0.005 | M38: =$H$38 -> 0.005 | N38: =$H$38 -> 0.005 | O38: =$H$38 -> 0.005 | P38: =$H$38 -> 0.005 | ... BP38: =$H$38 -> 0.005
C39: Rate for Sizing IR | H39: =IF($D$2="Forward Rate",SUM(H37:H38),H40) -> 0.0880533 | I39: =IF($D$2="Forward Rate",SUM(I37:I38),I40) -> 0.0873577 | J39: =IF($D$2="Forward Rate",SUM(J37:J38),J40) -> 0.0868021 | K39: =IF($D$2="Forward Rate",SUM(K37:K38),K40) -> 0.0862678 | L39: =IF($D$2="Forward Rate",SUM(L37:L38),L40) -> 0.0846218 | M39: =IF($D$2="Forward Rate",SUM(M37:M38),M40) -> 0.0843128 | N39: =IF($D$2="Forward Rate",SUM(N37:N38),N40) -> 0.0843027 | O39: =IF($D$2="Forward Rate",SUM(O37:O38),O40) -> 0.0824269 | ... BP39: =IF($D$2="Forward Rate",SUM(BP37:BP38),BP40) -> 0.0725526
C40: Today's Rate | H40: =$H$33+$H$34 -> 0.0830533 | I40: =$H$33+$H$34 -> 0.0830533 | J40: =$H$33+$H$34 -> 0.0830533 | K40: =$H$33+$H$34 -> 0.0830533 | L40: =$H$33+$H$34 -> 0.0830533 | M40: =$H$33+$H$34 -> 0.0830533 | N40: =$H$33+$H$34 -> 0.0830533 | O40: =$H$33+$H$34 -> 0.0830533 | ... BP40: =$H$33+$H$34 -> 0.0830533
C41: + Sr. Debt: Debt Service | E41: =H41 -> 0 | F41: =SUM(I41:BP41) -> 907495.55 | G41: =SUM(E41:F41) -> 907495.55 | H41: 0 | I41: =IF(I9="B/E",0,H47*I39/12*365/360) -> 0 | J41: =IF(J9="B/E",0,I47*J39/12*365/360) -> 0 | K41: =IF(K9="B/E",0,J47*K39/12*365/360) -> 0 | L41: =IF(L9="B/E",0,K47*L39/12*365/360) -> 0 | M41: =IF(M9="B/E",0,L47*M39/12*365/360) -> 0 | N41: =IF(N9="B/E",0,M47*N39/12*365/360) -> 0 | O41: =IF(O9="B/E",0,N47*O39/12*365/360) -> 0 | P41: =IF(P9="B/E",0,O47*P39/12*365/360) -> 0 | ... BP41: =IF(BP9="B/E",0,BO47*BP39/12*365/360) -> 0
B42: SENIOR DEBT
B43: Sr. Debt: BOP | H43: 0 | I43: =H47 -> 0 | J43: =I47 -> 0 | K43: =J47 -> 0 | L43: =K47 -> 0 | M43: =L47 -> 0 | N43: =M47 -> 0 | O43: =N47 -> 0 | P43: =O47 -> 0 | ... BP43: =BO47 -> 15536393
C44: + Cost Draw | E44: =H44 -> 0 | F44: =SUM(I44:BP44) -> 14628898 | G44: =SUM(E44:F44) -> 14628898 | H44: =H14-H41 -> 0 | I44: =IF(I9="B/E",0,IF(I30>I29,I30-I15-I13-I29,I32-I29)) -> 0 | J44: =IF(J9="B/E",0,IF(J30>J29,J30-J15-J13-J29,J32-J29)) -> 0 | K44: =IF(K9="B/E",0,IF(K30>K29,K30-K15-K13-K29,K32-K29)) -> 0 | L44: =IF(L9="B/E",0,IF(L30>L29,L30-L15-L13-L29,L32-L29)) -> 0 | M44: =IF(M9="B/E",0,IF(M30>M29,M30-M15-M13-M29,M32-M29)) -> 0 | N44: =IF(N9="B/E",0,IF(N30>N29,N30-N15-N13-N29,N32-N29)) -> 0 | O44: =IF(O9="B/E",0,IF(O30>O29,O30-O15-O13-O29,O32-O29)) -> 0 | P44: =IF(P9="B/E",0,IF(P30>P29,P30-P15-P13-P29,P32-P29)) -> 0 | ... BP44: =IF(BP9="B/E",0,IF(BP30>BP29,BP30-BP15-BP13-BP29,BP32-BP29)) -> 0
C45: + Debt Service | E45: =H45 -> 0 | F45: =SUM(I45:BP45) -> 907495.55 | G45: =SUM(E45:F45) -> 907495.55 | H45: =H41 -> 0 | I45: =I41 -> 0 | J45: =J41 -> 0 | K45: =K41 -> 0 | L45: =L41 -> 0 | M45: =M41 -> 0 | N45: =N41 -> 0 | O45: =O41 -> 0 | ... BP45: =BP41 -> 0
C46: - Repayment | H46: 0 | I46: 0 | J46: 0 | K46: 0 | L46: 0 | M46: 0 | N46: 0 | O46: 0 | P46: 0 | Q46: 0 | R46: 0 | S46: 0 | T46: 0 | U46: 0 | V46: 0 | W46: 0 | X46: 0 | Y46: 0 | Z46: 0 | AA46: 0 | AB46: 0 | AC46: 0 | AD46: 0 | AE46: 0 | AF46: 0 | AG46: 0 | AH46: 0 | AI46: 0 | AJ46: 0 | AK46: 0 | AL46: 0 | AM46: 0 | AN46: 0 | AO46: 0 | AP46: 0 | AQ46: 0 | AR46: 0 | AS46: 0 | AT46: 0 | AU46: 0 | AV46: 0 | AW46: 0 | AX46: 0 | AY46: 0 | AZ46: 0 | BA46: 0 | BB46: 0 | BC46: 0 | BD46: 0 | BE46: 0 | BF46: 0 | BG46: 0 | BH46: 0 | BI46: 0 | BJ46: 0 | BK46: 0 | BL46: 0 | BM46: 0 | BN46: 0 | BO46: 0 | BP46: 0
B47: Sr. Debt: EOP | G47: =SUM(G44:G46) -> 15536393 | H47: =SUM(H43:H46) -> 0 | I47: =SUM(I43:I46) -> 0 | J47: =SUM(J43:J46) -> 0 | K47: =SUM(K43:K46) -> 0 | L47: =SUM(L43:L46) -> 0 | M47: =SUM(M43:M46) -> 0 | N47: =SUM(N43:N46) -> 0 | O47: =SUM(O43:O46) -> 0 | ... BP47: =SUM(BP43:BP46) -> 15536393
B48: EQUITY
B49: GP Equity: BOP | H49: 0 | I49: =H52 -> 5309435 | J49: =I52 -> 5342768.3 | K49: =J52 -> 5376101.7 | L49: =K52 -> 5409435 | M49: =L52 -> 5442768.3 | N49: =M52 -> 5476101.7 | O49: =N52 -> 5509435 | P49: =O52 -> 6758964.6 | ... BP49: =BO52 -> 8400000
C50: + Cost Draw | E50: =H50 -> 5309435 | F50: =SUM(I50:BP50) -> 3090565 | G50: =SUM(E50:F50) -> 8400000 | H50: =H15 -> 5309435 | I50: =I15 -> 33333.333 | J50: =J15 -> 33333.333 | K50: =K15 -> 33333.333 | L50: =L15 -> 33333.333 | M50: =M15 -> 33333.333 | N50: =N15 -> 33333.333 | O50: =O15 -> 1249529.6 | ... BP50: =BP15 -> 0
C51: - Repayment | H51: 0 | I51: 0 | J51: 0 | K51: 0 | L51: 0 | M51: 0 | N51: 0 | O51: 0 | P51: 0 | Q51: 0 | R51: 0 | S51: 0 | T51: 0 | U51: 0 | V51: 0 | W51: 0 | X51: 0 | Y51: 0 | Z51: 0 | AA51: 0 | AB51: 0 | AC51: 0 | AD51: 0 | AE51: 0 | AF51: 0 | AG51: 0 | AH51: 0 | AI51: 0 | AJ51: 0 | AK51: 0 | AL51: 0 | AM51: 0 | AN51: 0 | AO51: 0 | AP51: 0 | AQ51: 0 | AR51: 0 | AS51: 0 | AT51: 0 | AU51: 0 | AV51: 0 | AW51: 0 | AX51: 0 | AY51: 0 | AZ51: 0 | BA51: 0 | BB51: 0 | BC51: 0 | BD51: 0 | BE51: 0 | BF51: 0 | BG51: 0 | BH51: 0 | BI51: 0 | BJ51: 0 | BK51: 0 | BL51: 0 | BM51: 0 | BN51: 0 | BO51: 0 | BP51: 0
B52: GP Equity: EOP | E52: =SUM(E50:E51) -> 5309435 | F52: =SUM(F50:F51) -> 3090565 | G52: =SUM(G50:G51) -> 8400000 | H52: =SUM(H49:H51) -> 5309435 | I52: =SUM(I49:I51) -> 5342768.3 | J52: =SUM(J49:J51) -> 5376101.7 | K52: =SUM(K49:K51) -> 5409435 | L52: =SUM(L49:L51) -> 5442768.3 | M52: =SUM(M49:M51) -> 5476101.7 | N52: =SUM(N49:N51) -> 5509435 | O52: =SUM(O49:O51) -> 6758964.6 | ... BP52: =SUM(BP49:BP51) -> 8400000
C53: CF to Equity | AG53: =IF(AG11>$F$9,0,'Lease Up'!AG48) -> 86611.366 | AH53: =IF(AH11>$F$9,0,'Lease Up'!AH48) -> 119448.4 | AI53: =IF(AI11>$F$9,0,'Lease Up'!AI48) -> 152134.81 | AJ53: =IF(AJ11>$F$9,0,'Lease Up'!AJ48) -> 155401.77 | AK53: =IF(AK11>$F$9,0,'Lease Up'!AK48) -> 155401.77 | AL53: =IF(AL11>$F$9,0,'Lease Up'!AL48) -> 155401.77 | AM53: =IF(AM11>$F$9,0,'Lease Up'!AM48) -> 155401.77 | AN53: =IF(AN11>$F$9,0,'Lease Up'!AN48) -> 155401.77 | ... BP53: =IF(BP11>$F$9,0,'Lease Up'!BP48) -> 0
C54: Equity Payments | H54: =-H15 -> -5309435 | I54: =-I15 -> -33333.333 | J54: =-J15 -> -33333.333 | K54: =-K15 -> -33333.333 | L54: =-L15 -> -33333.333 | M54: =-M15 -> -33333.333 | N54: =-N15 -> -33333.333 | O54: =-O15 -> -1249529.6 | ... BP54: =-BP15 -> 0
C55: Sale Price | H55: 0 | I55: ='Lease Up'!I52 -> 0 | J55: ='Lease Up'!J52 -> 0 | K55: ='Lease Up'!K52 -> 0 | L55: ='Lease Up'!L52 -> 0 | M55: ='Lease Up'!M52 -> 0 | N55: ='Lease Up'!N52 -> 0 | O55: ='Lease Up'!O52 -> 0 | P55: ='Lease Up'!P52 -> 0 | ... BP55: ='Lease Up'!BP52 -> 0
C56: Less: Debt | H56: 0 | I56: =IF(I11=$F$9,-I47,0) -> 0 | J56: =IF(J11=$F$9,-J47,0) -> 0 | K56: =IF(K11=$F$9,-K47,0) -> 0 | L56: =IF(L11=$F$9,-L47,0) -> 0 | M56: =IF(M11=$F$9,-M47,0) -> 0 | N56: =IF(N11=$F$9,-N47,0) -> 0 | O56: =IF(O11=$F$9,-O47,0) -> 0 | P56: =IF(P11=$F$9,-P47,0) -> 0 | ... BP56: =IF(BP11=$F$9,-BP47,0) -> 0
B57: Total Equity CF | H57: =SUM(H53:H56) -> -5309435 | I57: =SUM(I53:I56) -> -33333.333 | J57: =SUM(J53:J56) -> -33333.333 | K57: =SUM(K53:K56) -> -33333.333 | L57: =SUM(L53:L56) -> -33333.333 | M57: =SUM(M53:M56) -> -33333.333 | N57: =SUM(N53:N56) -> -33333.333 | O57: =SUM(O53:O56) -> -1249529.6 | ... BP57: =SUM(BP53:BP56) -> 0
B58: Discount Rate | H58: 1 | I58: =1/((1+('Lease Up'!$N$11/12))^Draws!I11) -> 0.99296649 | J58: =1/((1+('Lease Up'!$N$11/12))^Draws!J11) -> 0.98598245 | K58: =1/((1+('Lease Up'!$N$11/12))^Draws!K11) -> 0.97904753 | L58: =1/((1+('Lease Up'!$N$11/12))^Draws!L11) -> 0.97216138 | M58: =1/((1+('Lease Up'!$N$11/12))^Draws!M11) -> 0.96532367 | N58: =1/((1+('Lease Up'!$N$11/12))^Draws!N11) -> 0.95853406 | O58: =1/((1+('Lease Up'!$N$11/12))^Draws!O11) -> 0.9517922 | P58: =1/((1+('Lease Up'!$N$11/12))^Draws!P11) -> 0.94509775 | ... BP58: =1/((1+('Lease Up'!$N$11/12))^Draws!BP11) -> 0.65474996
B59: Discounted CF to Equity | H59: =H57*H58 -> -5309435 | I59: =I57*I58 -> -33098.883 | J59: =J57*J58 -> -32866.082 | K59: =K57*K58 -> -32634.918 | L59: =L57*L58 -> -32405.379 | M59: =M57*M58 -> -32177.456 | N59: =N57*N58 -> -31951.135 | O59: =O57*O58 -> -1189292.6 | ... BP59: =BP57*BP58 -> 0
B60: IRR | H60: =NPV(H59,I59:AR59)*12 -> 0.074807695
B61: Multiple | H61: =SUM(AG57:AR57)/-SUM(H57:Q57) -> 1.7719232
B63: DETAIL
H64: =$G$4 -> 45597 | I64: =EOMONTH(H64,1) -> 45657 | J64: =EOMONTH(I64,1) -> 45688 | K64: =EOMONTH(J64,1) -> 45716 | L64: =EOMONTH(K64,1) -> 45747 | M64: =EOMONTH(L64,1) -> 45777 | N64: =EOMONTH(M64,1) -> 45808 | O64: =EOMONTH(N64,1) -> 45838 | P64: =EOMONTH(O64,1) -> 45869 | ... BP64: =EOMONTH(BO64,1) -> 47452
D65: Total | E65: at Closing | F65: After Close | G65: Total | H65: Closing | I65: 1 | J65: =I65+1 -> 2 | K65: =J65+1 -> 3 | L65: =K65+1 -> 4 | M65: =L65+1 -> 5 | N65: =M65+1 -> 6 | O65: =N65+1 -> 7 | P65: =O65+1 -> 8 | Q65: =P65+1 -> 9 | ... BP65: =BO65+1 -> 60
C66: LAND ACQUISITION
C67: North Lot | D67: =61*40000 -> 2440000 | E67: =H67 -> 2440000 | F67: =SUM(I67:BP67) -> 0 | G67: =E67+F67 -> 2440000 | H67: =D67 -> 2440000
C68: South Lot | D68: =59*40000 -> 2360000 | E68: =H68 -> 2360000 | F68: =SUM(I68:BP68) -> 0 | G68: =E68+F68 -> 2360000 | H68: =D68 -> 2360000
C69: TOTAL LAND ACQU | D69: =SUM(D67:D68) -> 4800000 | E69: =SUM(E67:E68) -> 4800000 | F69: =SUM(F67:F68) -> 0 | G69: =SUM(G67:G68) -> 4800000 | H69: =SUM(H67:H68) -> 4800000 | I69: =SUM(I67:I68) -> 0 | J69: =SUM(J67:J68) -> 0 | K69: =SUM(K67:K68) -> 0 | ... BP69: =SUM(BP67:BP68) -> 0
C71: PRE-DVLP COSTS | D71: 200000 | E71: =H71 -> 0 | F71: =SUM(I71:BP71) -> 200000 | G71: =E71+F71 -> 200000 | H71: 0 | I71: =IF(AND(I$11>=$D$4,I$11<=$E$4),($D71-$H71)/$F$4,0) -> 33333.333 | J71: =IF(AND(J$11>=$D$4,J$11<=$E$4),($D71-$H71)/$F$4,0) -> 33333.333 | K71: =IF(AND(K$11>=$D$4,K$11<=$E$4),($D71-$H71)/$F$4,0) -> 33333.333 | L71: =IF(AND(L$11>=$D$4,L$11<=$E$4),($D71-$H71)/$F$4,0) -> 33333.333 | M71: =IF(AND(M$11>=$D$4,M$11<=$E$4),($D71-$H71)/$F$4,0) -> 33333.333 | N71: =IF(AND(N$11>=$D$4,N$11<=$E$4),($D71-$H71)/$F$4,0) -> 33333.333 | O71: =IF(AND(O$11>=$D$4,O$11<=$E$4),($D71-$H71)/$F$4,0) -> 0 | P71: =IF(AND(P$11>=$D$4,P$11<=$E$4),($D71-$H71)/$F$4,0) -> 0 | ... BP71: =IF(AND(BP$11>=$D$4,BP$11<=$E$4),($D71-$H71)/$F$4,0) -> 0
C73: HARD COSTS
C74: Hard Costs | D74: 16200000 | E74: =H74 -> 0 | F74: =SUM(I74:BP74) -> 16200000 | G74: =E74+F74 -> 16200000 | H74: 0 | I74: =IF(AND(I$11>=$D$5,I$11<=$E$5),($D74-$H74)/$F$5,0) -> 0 | J74: =IF(AND(J$11>=$D$5,J$11<=$E$5),($D74-$H74)/$F$5,0) -> 0 | K74: =IF(AND(K$11>=$D$5,K$11<=$E$5),($D74-$H74)/$F$5,0) -> 0 | L74: =IF(AND(L$11>=$D$5,L$11<=$E$5),($D74-$H74)/$F$5,0) -> 0 | M74: =IF(AND(M$11>=$D$5,M$11<=$E$5),($D74-$H74)/$F$5,0) -> 0 | N74: =IF(AND(N$11>=$D$5,N$11<=$E$5),($D74-$H74)/$F$5,0) -> 0 | O74: =IF(AND(O$11>=$D$5,O$11<=$E$5),($D74-$H74)/$F$5,0) -> 1157142.9 | P74: =IF(AND(P$11>=$D$5,P$11<=$E$5),($D74-$H74)/$F$5,0) -> 1157142.9 | ... BP74: =IF(AND(BP$11>=$D$5,BP$11<=$E$5),($D74-$H74)/$F$5,0) -> 0
C75: HC Contingency | D75: 0 | E75: =H75 -> 0 | F75: =SUM(I75:BP75) -> 0 | G75: =E75+F75 -> 0 | H75: 0 | I75: =IF(AND(I$11>=$D$5,I$11<=$E$5),($D75-$H75)/$F$5,0) -> 0 | J75: =IF(AND(J$11>=$D$5,J$11<=$E$5),($D75-$H75)/$F$5,0) -> 0 | K75: =IF(AND(K$11>=$D$5,K$11<=$E$5),($D75-$H75)/$F$5,0) -> 0 | L75: =IF(AND(L$11>=$D$5,L$11<=$E$5),($D75-$H75)/$F$5,0) -> 0 | M75: =IF(AND(M$11>=$D$5,M$11<=$E$5),($D75-$H75)/$F$5,0) -> 0 | N75: =IF(AND(N$11>=$D$5,N$11<=$E$5),($D75-$H75)/$F$5,0) -> 0 | O75: =IF(AND(O$11>=$D$5,O$11<=$E$5),($D75-$H75)/$F$5,0) -> 0 | P75: =IF(AND(P$11>=$D$5,P$11<=$E$5),($D75-$H75)/$F$5,0) -> 0 | ... BP75: =IF(AND(BP$11>=$D$5,BP$11<=$E$5),($D75-$H75)/$F$5,0) -> 0
C76: TOTAL HARD COSTS | D76: =D74+D75 -> 16200000 | E76: =SUM(E74:E75) -> 0 | F76: =SUM(F74:F75) -> 16200000 | G76: =SUM(G74:G75) -> 16200000 | H76: =SUM(H74:H75) -> 0 | I76: =I74+I75 -> 0 | J76: =J74+J75 -> 0 | K76: =K74+K75 -> 0 | L76: =L74+L75 -> 0 | M76: =M74+M75 -> 0 | N76: =N74+N75 -> 0 | O76: =O74+O75 -> 1157142.9 | P76: =P74+P75 -> 1157142.9 | ... BP76: =BP74+BP75 -> 0
C78: SOFT COSTS
B79: s | C79: Architectural | D79: 244000 | E79: =H79 -> 0 | F79: =SUM(I79:BP79) -> 244000 | G79: =E79+F79 -> 244000 | I79: =IF(AND(I$11>=$D$5,I$11<=$E$5),($D79-$H79)/$F$5,0) -> 0 | J79: =IF(AND(J$11>=$D$5,J$11<=$E$5),($D79-$H79)/$F$5,0) -> 0 | K79: =IF(AND(K$11>=$D$5,K$11<=$E$5),($D79-$H79)/$F$5,0) -> 0 | L79: =IF(AND(L$11>=$D$5,L$11<=$E$5),($D79-$H79)/$F$5,0) -> 0 | M79: =IF(AND(M$11>=$D$5,M$11<=$E$5),($D79-$H79)/$F$5,0) -> 0 | N79: =IF(AND(N$11>=$D$5,N$11<=$E$5),($D79-$H79)/$F$5,0) -> 0 | O79: =IF(AND(O$11>=$D$5,O$11<=$E$5),($D79-$H79)/$F$5,0) -> 17428.571 | P79: =IF(AND(P$11>=$D$5,P$11<=$E$5),($D79-$H79)/$F$5,0) -> 17428.571 | ... BP79: =IF(AND(BP$11>=$D$5,BP$11<=$E$5),($D79-$H79)/$F$5,0) -> 0
B80: s | C80: Engineering & Related | D80: 33550 | E80: =H80 -> 0 | F80: =SUM(I80:BP80) -> 33550 | G80: =E80+F80 -> 33550 | I80: =IF(AND(I$11>=$D$5,I$11<=$E$5),($D80-$H80)/$F$5,0) -> 0 | J80: =IF(AND(J$11>=$D$5,J$11<=$E$5),($D80-$H80)/$F$5,0) -> 0 | K80: =IF(AND(K$11>=$D$5,K$11<=$E$5),($D80-$H80)/$F$5,0) -> 0 | L80: =IF(AND(L$11>=$D$5,L$11<=$E$5),($D80-$H80)/$F$5,0) -> 0 | M80: =IF(AND(M$11>=$D$5,M$11<=$E$5),($D80-$H80)/$F$5,0) -> 0 | N80: =IF(AND(N$11>=$D$5,N$11<=$E$5),($D80-$H80)/$F$5,0) -> 0 | O80: =IF(AND(O$11>=$D$5,O$11<=$E$5),($D80-$H80)/$F$5,0) -> 2396.4286 | P80: =IF(AND(P$11>=$D$5,P$11<=$E$5),($D80-$H80)/$F$5,0) -> 2396.4286 | ... BP80: =IF(AND(BP$11>=$D$5,BP$11<=$E$5),($D80-$H80)/$F$5,0) -> 0
B81: s | C81: Impact/Permits | D81: 549000 | E81: =H81 -> 0 | F81: =SUM(I81:BP81) -> 549000 | G81: =E81+F81 -> 549000 | I81: =IF(AND(I$11>=$D$5,I$11<=$E$5),($D81-$H81)/$F$5,0) -> 0 | J81: =IF(AND(J$11>=$D$5,J$11<=$E$5),($D81-$H81)/$F$5,0) -> 0 | K81: =IF(AND(K$11>=$D$5,K$11<=$E$5),($D81-$H81)/$F$5,0) -> 0 | L81: =IF(AND(L$11>=$D$5,L$11<=$E$5),($D81-$H81)/$F$5,0) -> 0 | M81: =IF(AND(M$11>=$D$5,M$11<=$E$5),($D81-$H81)/$F$5,0) -> 0 | N81: =IF(AND(N$11>=$D$5,N$11<=$E$5),($D81-$H81)/$F$5,0) -> 0 | O81: =IF(AND(O$11>=$D$5,O$11<=$E$5),($D81-$H81)/$F$5,0) -> 39214.286 | P81: =IF(AND(P$11>=$D$5,P$11<=$E$5),($D81-$H81)/$F$5,0) -> 39214.286 | ... BP81: =IF(AND(BP$11>=$D$5,BP$11<=$E$5),($D81-$H81)/$F$5,0) -> 0
B82: s | C82: Marketing | D82: 24400 | E82: =H82 -> 0 | F82: =SUM(I82:BP82) -> 24400 | G82: =E82+F82 -> 24400 | I82: =IF(AND(I$11>=$D$5,I$11<=$E$5),($D82-$H82)/$F$5,0) -> 0 | J82: =IF(AND(J$11>=$D$5,J$11<=$E$5),($D82-$H82)/$F$5,0) -> 0 | K82: =IF(AND(K$11>=$D$5,K$11<=$E$5),($D82-$H82)/$F$5,0) -> 0 | L82: =IF(AND(L$11>=$D$5,L$11<=$E$5),($D82-$H82)/$F$5,0) -> 0 | M82: =IF(AND(M$11>=$D$5,M$11<=$E$5),($D82-$H82)/$F$5,0) -> 0 | N82: =IF(AND(N$11>=$D$5,N$11<=$E$5),($D82-$H82)/$F$5,0) -> 0 | O82: =IF(AND(O$11>=$D$5,O$11<=$E$5),($D82-$H82)/$F$5,0) -> 1742.8571 | P82: =IF(AND(P$11>=$D$5,P$11<=$E$5),($D82-$H82)/$F$5,0) -> 1742.8571 | ... BP82: =IF(AND(BP$11>=$D$5,BP$11<=$E$5),($D82-$H82)/$F$5,0) -> 0
B83: s | C83: Bldr Risk & Perf Bond | D83: 154635 | E83: =H83 -> 154635 | F83: =SUM(I83:BP83) -> 0 | G83: =E83+F83 -> 154635 | H83: =D83 -> 154635 | I83: =IF(AND(I$11>=$D$5,I$11<=$E$5),($D83-$H83)/$F$5,0) -> 0 | J83: =IF(AND(J$11>=$D$5,J$11<=$E$5),($D83-$H83)/$F$5,0) -> 0 | K83: =IF(AND(K$11>=$D$5,K$11<=$E$5),($D83-$H83)/$F$5,0) -> 0 | L83: =IF(AND(L$11>=$D$5,L$11<=$E$5),($D83-$H83)/$F$5,0) -> 0 | M83: =IF(AND(M$11>=$D$5,M$11<=$E$5),($D83-$H83)/$F$5,0) -> 0 | N83: =IF(AND(N$11>=$D$5,N$11<=$E$5),($D83-$H83)/$F$5,0) -> 0 | O83: =IF(AND(O$11>=$D$5,O$11<=$E$5),($D83-$H83)/$F$5,0) -> 0 | P83: =IF(AND(P$11>=$D$5,P$11<=$E$5),($D83-$H83)/$F$5,0) -> 0 | ... BP83: =IF(AND(BP$11>=$D$5,BP$11<=$E$5),($D83-$H83)/$F$5,0) -> 0
B84: s | C84: Legal & Professional | D84: 48800 | E84: =H84 -> 48800 | F84: =SUM(I84:BP84) -> 0 | G84: =E84+F84 -> 48800 | H84: =D84 -> 48800 | I84: =IF(AND(I$11>=$D$5,I$11<=$E$5),($D84-$H84)/$F$5,0) -> 0 | J84: =IF(AND(J$11>=$D$5,J$11<=$E$5),($D84-$H84)/$F$5,0) -> 0 | K84: =IF(AND(K$11>=$D$5,K$11<=$E$5),($D84-$H84)/$F$5,0) -> 0 | L84: =IF(AND(L$11>=$D$5,L$11<=$E$5),($D84-$H84)/$F$5,0) -> 0 | M84: =IF(AND(M$11>=$D$5,M$11<=$E$5),($D84-$H84)/$F$5,0) -> 0 | N84: =IF(AND(N$11>=$D$5,N$11<=$E$5),($D84-$H84)/$F$5,0) -> 0 | O84: =IF(AND(O$11>=$D$5,O$11<=$E$5),($D84-$H84)/$F$5,0) -> 0 | P84: =IF(AND(P$11>=$D$5,P$11<=$E$5),($D84-$H84)/$F$5,0) -> 0 | ... BP84: =IF(AND(BP$11>=$D$5,BP$11<=$E$5),($D84-$H84)/$F$5,0) -> 0
B85: s | C85: Investor Admin Costs | D85: 9150 | E85: =H85 -> 0 | F85: =SUM(I85:BP85) -> 9150 | G85: =E85+F85 -> 9150 | I85: =IF(AND(I$11>=$D$5,I$11<=$E$5),($D85-$H85)/$F$5,0) -> 0 | J85: =IF(AND(J$11>=$D$5,J$11<=$E$5),($D85-$H85)/$F$5,0) -> 0 | K85: =IF(AND(K$11>=$D$5,K$11<=$E$5),($D85-$H85)/$F$5,0) -> 0 | L85: =IF(AND(L$11>=$D$5,L$11<=$E$5),($D85-$H85)/$F$5,0) -> 0 | M85: =IF(AND(M$11>=$D$5,M$11<=$E$5),($D85-$H85)/$F$5,0) -> 0 | N85: =IF(AND(N$11>=$D$5,N$11<=$E$5),($D85-$H85)/$F$5,0) -> 0 | O85: =IF(AND(O$11>=$D$5,O$11<=$E$5),($D85-$H85)/$F$5,0) -> 653.57143 | P85: =IF(AND(P$11>=$D$5,P$11<=$E$5),($D85-$H85)/$F$5,0) -> 653.57143 | ... BP85: =IF(AND(BP$11>=$D$5,BP$11<=$E$5),($D85-$H85)/$F$5,0) -> 0
B86: s | C86: RE Tax During Constr | D86: 92315 | E86: =H86 -> 0 | F86: =SUM(I86:BP86) -> 92315 | G86: =E86+F86 -> 92315 | I86: =IF(AND(I$11>=$D$5,I$11<=$E$5),($D86-$H86)/$F$5,0) -> 0 | J86: =IF(AND(J$11>=$D$5,J$11<=$E$5),($D86-$H86)/$F$5,0) -> 0 | K86: =IF(AND(K$11>=$D$5,K$11<=$E$5),($D86-$H86)/$F$5,0) -> 0 | L86: =IF(AND(L$11>=$D$5,L$11<=$E$5),($D86-$H86)/$F$5,0) -> 0 | M86: =IF(AND(M$11>=$D$5,M$11<=$E$5),($D86-$H86)/$F$5,0) -> 0 | N86: =IF(AND(N$11>=$D$5,N$11<=$E$5),($D86-$H86)/$F$5,0) -> 0 | O86: =IF(AND(O$11>=$D$5,O$11<=$E$5),($D86-$H86)/$F$5,0) -> 6593.9286 | P86: =IF(AND(P$11>=$D$5,P$11<=$E$5),($D86-$H86)/$F$5,0) -> 6593.9286 | ... BP86: =IF(AND(BP$11>=$D$5,BP$11<=$E$5),($D86-$H86)/$F$5,0) -> 0
C87: TOTAL SOFT COSTS | D87: =SUM(D79:D86) -> 1155850 | E87: =SUM(E79:E86) -> 203435 | F87: =SUM(F79:F86) -> 952415 | G87: =SUM(G79:G86) -> 1155850 | H87: =SUM(H79:H86) -> 203435 | I87: =SUM(I79:I86) -> 0 | J87: =SUM(J79:J86) -> 0 | K87: =SUM(K79:K86) -> 0 | ... BP87: =SUM(BP79:BP86) -> 0
C89: Soft Cost Contingency | D89: 61000 | E89: =H89 -> 0 | F89: =SUM(I89:BP89) -> 61000 | G89: =E89+F89 -> 61000 | I89: =IF(AND(I$11>=$D$5,I$11<=$E$5),($D89-$H89)/$F$5,0) -> 0 | J89: =IF(AND(J$11>=$D$5,J$11<=$E$5),($D89-$H89)/$F$5,0) -> 0 | K89: =IF(AND(K$11>=$D$5,K$11<=$E$5),($D89-$H89)/$F$5,0) -> 0 | L89: =IF(AND(L$11>=$D$5,L$11<=$E$5),($D89-$H89)/$F$5,0) -> 0 | M89: =IF(AND(M$11>=$D$5,M$11<=$E$5),($D89-$H89)/$F$5,0) -> 0 | N89: =IF(AND(N$11>=$D$5,N$11<=$E$5),($D89-$H89)/$F$5,0) -> 0 | O89: =IF(AND(O$11>=$D$5,O$11<=$E$5),($D89-$H89)/$F$5,0) -> 4357.1429 | P89: =IF(AND(P$11>=$D$5,P$11<=$E$5),($D89-$H89)/$F$5,0) -> 4357.1429 | ... BP89: =IF(AND(BP$11>=$D$5,BP$11<=$E$5),($D89-$H89)/$F$5,0) -> 0
C90: Dvlp & Constr Mgt Fee | D90: 280000 | E90: =H90 -> 0 | F90: =SUM(I90:BP90) -> 280000 | G90: =E90+F90 -> 280000 | I90: =IF(AND(I$11>=$D$5,I$11<=$E$5),($D90-$H90)/$F$5,0) -> 0 | J90: =IF(AND(J$11>=$D$5,J$11<=$E$5),($D90-$H90)/$F$5,0) -> 0 | K90: =IF(AND(K$11>=$D$5,K$11<=$E$5),($D90-$H90)/$F$5,0) -> 0 | L90: =IF(AND(L$11>=$D$5,L$11<=$E$5),($D90-$H90)/$F$5,0) -> 0 | M90: =IF(AND(M$11>=$D$5,M$11<=$E$5),($D90-$H90)/$F$5,0) -> 0 | N90: =IF(AND(N$11>=$D$5,N$11<=$E$5),($D90-$H90)/$F$5,0) -> 0 | O90: =IF(AND(O$11>=$D$5,O$11<=$E$5),($D90-$H90)/$F$5,0) -> 20000 | P90: =IF(AND(P$11>=$D$5,P$11<=$E$5),($D90-$H90)/$F$5,0) -> 20000 | ... BP90: =IF(AND(BP$11>=$D$5,BP$11<=$E$5),($D90-$H90)/$F$5,0) -> 0
C91: Closing Costs | D91: 150000 | E91: =H91 -> 150000 | F91: =SUM(I91:BP91) -> 0 | G91: =E91+F91 -> 150000 | H91: =D91 -> 150000 | I91: =IF(AND(I$11>=$D$5,I$11<=$E$5),($D91-$H91)/$F$5,0) -> 0 | J91: =IF(AND(J$11>=$D$5,J$11<=$E$5),($D91-$H91)/$F$5,0) -> 0 | K91: =IF(AND(K$11>=$D$5,K$11<=$E$5),($D91-$H91)/$F$5,0) -> 0 | L91: =IF(AND(L$11>=$D$5,L$11<=$E$5),($D91-$H91)/$F$5,0) -> 0 | M91: =IF(AND(M$11>=$D$5,M$11<=$E$5),($D91-$H91)/$F$5,0) -> 0 | N91: =IF(AND(N$11>=$D$5,N$11<=$E$5),($D91-$H91)/$F$5,0) -> 0 | O91: =IF(AND(O$11>=$D$5,O$11<=$E$5),($D91-$H91)/$F$5,0) -> 0 | P91: =IF(AND(P$11>=$D$5,P$11<=$E$5),($D91-$H91)/$F$5,0) -> 0 | ... BP91: =IF(AND(BP$11>=$D$5,BP$11<=$E$5),($D91-$H91)/$F$5,0) -> 0
C92: Operating Deficit Reserve | D92: =109800 -> 109800 | E92: =H92 -> 0 | F92: =SUM(I92:BP92) -> 120381.34 | G92: =E92+F92 -> 120381.34 | I92: =IF('Lease Up'!I46<0,-'Lease Up'!I46,0) -> 0 | J92: =IF('Lease Up'!J46<0,-'Lease Up'!J46,0) -> 0 | K92: =IF('Lease Up'!K46<0,-'Lease Up'!K46,0) -> 0 | L92: =IF('Lease Up'!L46<0,-'Lease Up'!L46,0) -> 0 | M92: =IF('Lease Up'!M46<0,-'Lease Up'!M46,0) -> 0 | N92: =IF('Lease Up'!N46<0,-'Lease Up'!N46,0) -> 0 | O92: =IF('Lease Up'!O46<0,-'Lease Up'!O46,0) -> 0 | P92: =IF('Lease Up'!P46<0,-'Lease Up'!P46,0) -> 0 | ... BP92: =IF('Lease Up'!BP46<0,-'Lease Up'!BP46,0) -> 0
C93: Sr. Debt: Commit Fee - 1% | D93: =15600000*1% -> 156000 | E93: =H93 -> 156000 | F93: =SUM(I93:BP93) -> 0 | G93: =E93+F93 -> 156000 | H93: =D93 -> 156000 | I93: =IF(AND(I$11>=$D$5,I$11<=$E$5),($D93-$H93)/$F$5,0) -> 0 | J93: =IF(AND(J$11>=$D$5,J$11<=$E$5),($D93-$H93)/$F$5,0) -> 0 | K93: =IF(AND(K$11>=$D$5,K$11<=$E$5),($D93-$H93)/$F$5,0) -> 0 | L93: =IF(AND(L$11>=$D$5,L$11<=$E$5),($D93-$H93)/$F$5,0) -> 0 | M93: =IF(AND(M$11>=$D$5,M$11<=$E$5),($D93-$H93)/$F$5,0) -> 0 | N93: =IF(AND(N$11>=$D$5,N$11<=$E$5),($D93-$H93)/$F$5,0) -> 0 | O93: =IF(AND(O$11>=$D$5,O$11<=$E$5),($D93-$H93)/$F$5,0) -> 0 | P93: =IF(AND(P$11>=$D$5,P$11<=$E$5),($D93-$H93)/$F$5,0) -> 0 | ... BP93: =IF(AND(BP$11>=$D$5,BP$11<=$E$5),($D93-$H93)/$F$5,0) -> 0
C94: Sr. Debt: Debt Service | D94: 0 | E94: =H94 -> 0 | F94: =SUM(I94:BP94) -> 907495.55 | G94: =E94+F94 -> 907495.55 | H94: =H41 -> 0 | I94: =I41 -> 0 | J94: =J41 -> 0 | K94: =K41 -> 0 | L94: =L41 -> 0 | M94: =M41 -> 0 | N94: =N41 -> 0 | O94: =O41 -> 0 | ... BP94: =BP41 -> 0
C96: TOTAL COSTS | D96: =D69+D76+D87+SUM(D89:D94) -> 22912650 | E96: =E69+E76+E87+SUM(E89:E94) -> 5309435 | F96: =F69+F76+F87+SUM(F89:F94) -> 18521292 | G96: =G69+G76+G87+SUM(G89:G94) -> 23830727 | H96: =H69+H76+H87+SUM(H89:H94) -> 5309435 | I96: =I69+I76+I87+SUM(I89:I94) -> 0 | J96: =J69+J76+J87+SUM(J89:J94) -> 0 | K96: =K69+K76+K87+SUM(K89:K94) -> 0 | ... BP96: =BP69+BP76+BP87+SUM(BP89:BP94) -> 0

Sheet Lease Up
Q1: Start Mo. | R1: End Mo. | S1: # Ms. To complete | T1: Start Date
K2: # units | L2: $/Unit | M2: Utiliz Rt | N2: Tot $/Mo. | P2: =Draws!B4 -> Pre-Development | Q2: =Draws!D4 -> 1 | R2: =Draws!E4 -> 6 | S2: =Draws!F4 -> 6 | T2: =Draws!G4 -> 45597
I3: Apartments (Unit) | K3: ='Unit Mix'!C7 -> 61 | L3: ='Unit Mix'!E7 -> 3288 | M3: 1 | N3: =K3*L3 -> 200568 | P3: =Draws!B5 -> Construction | Q3: =Draws!D5 -> 7 | R3: =Draws!E5 -> 20 | S3: =Draws!F5 -> 14 | T3: =Draws!G5 -> 45778
I4: Apartments (SF) | L4: ='Unit Mix'!F7 -> 2.7500686 | M4: Unit Mix Tab controls rents | P4: =Draws!B6 -> Lease-Up | Q4: =Draws!D6 -> 21 | R4: =Draws!E6 -> 22 | S4: =Draws!F6 -> 2 | T4: =Draws!G6 -> 46204
I5: Lease-up/Mo. | K5: 10 | L5: Tot. ls up ms | M5: =K3/K5 -> 6.1 | P5: =Draws!B7 -> NOI+ | Q5: =Draws!D7 -> 23 | R5: =Draws!E7 -> 24 | S5: =Draws!F7 -> 2 | T5: =Draws!G7 -> 46266
I6: Vacancy After Lease Up | M6: 0.05 | P6: =Draws!B8 -> Brk Even CF | Q6: =Draws!D8 -> 25 | R6: =Draws!E8 -> 29 | S6: =Draws!F8 -> 5 | T6: =Draws!G8 -> 46327
I7: Parking | K7: =ROUNDUP(161/2,0) -> 81 | L7: 150 | M7: 0.8 | N7: =K7*L7*M7 -> 9720 | P7: =Draws!B9 -> Sale Date | Q7: =Draws!D9 -> 0 | R7: =Draws!E9 -> 0 | S7: =Draws!F9 -> 36 | T7: =Draws!G9 -> 46661 | V7: if sale ms > | W7: =60-12 -> 48 | X7: then extend cash flows
I8: Other Services | K8: =$K$3 -> 61 | L8: 100 | M8: 0.8 | N8: =K8*L8*M8 -> 4880 | Q8: Start Mo. | R8: End Mo. | S8: # Ms. | T8: % | AI8: =AH19+K5 -> 70
I9: Premiums | K9: =$K$3 -> 61 | L9: 0 | M9: 1 | N9: =K9*L9*M9 -> 0 | P9: Pre-ls up exp | Q9: =Q4-4 -> 17 | R9: =Q9+S9-1 -> 20 | S9: 4 | T9: 0.5
I10: Lease-Up Concession % | K10: 0.01 | P10: Ls up exp | Q10: =R9+1 -> 21 | R10: =Q10+S10-1 -> 24 | S10: =ROUNDUP(M5*50%,0) -> 4 | T10: 0.75
I11: Sale Cap | J11: 0.065 | K11: Cost of Sale | L11: 0.03 | M11: Dsct Rt | N11: =J11+2% -> 0.085 | S11: eye-ball to get correct periods for Draw Schedule timing | AC11: Lease-Up | AD11: Lease-Up | AE11: NOI+ | AF11: NOI+ | AG11: B/E
I12: =Draws!I9 -> Pre-Dvlp | J12: =Draws!J9 -> Pre-Dvlp | K12: =Draws!K9 -> Pre-Dvlp | L12: =Draws!L9 -> Pre-Dvlp | M12: =Draws!M9 -> Pre-Dvlp | N12: =Draws!N9 -> Pre-Dvlp | O12: =Draws!O9 -> Constr | P12: =Draws!P9 -> Constr | ... BP12: =Draws!BP9 -> B/E
I13: =Draws!G4 -> 45597 | J13: =EDATE(I13,1) -> 45627 | K13: =EDATE(J13,1) -> 45658 | L13: =EDATE(K13,1) -> 45689 | M13: =EDATE(L13,1) -> 45717 | N13: =EDATE(M13,1) -> 45748 | O13: =EDATE(N13,1) -> 45778 | P13: =EDATE(O13,1) -> 45809 | Q13: =EDATE(P13,1) -> 45839 | ... BP13: =EDATE(BO13,1) -> 47392
F14: Year for Growth Calcs | I14: 1 | J14: 1 | K14: 1 | L14: 1 | M14: 1 | N14: 1 | O14: 1 | P14: 1 | Q14: 1 | R14: 1 | S14: 1 | T14: 1 | U14: 2 | V14: 2 | W14: 2 | X14: 2 | Y14: 2 | Z14: 2 | AA14: 2 | AB14: 2 | AC14: 2 | AD14: 2 | AE14: 2 | AF14: 2 | AG14: 3 | AH14: 3 | AI14: 3 | AJ14: 3 | AK14: 3 | AL14: 3 | AM14: 3 | AN14: 3 | AO14: 3 | AP14: 3 | AQ14: 3 | AR14: 3 | AS14: 4 | AT14: 4 | AU14: 4 | AV14: 4 | AW14: 4 | AX14: 4 | AY14: 4 | AZ14: 4 | BA14: 4 | BB14: 4 | BC14: 4 | BD14: 4 | BE14: 5 | BF14: 5 | BG14: 5 | BH14: 5 | BI14: 5 | BJ14: 5 | BK14: 5 | BL14: 5 | BM14: 5 | BN14: 5 | BO14: 5 | BP14: 5
F15: Month | I15: 1 | J15: =I15+1 -> 2 | K15: =J15+1 -> 3 | L15: =K15+1 -> 4 | M15: =L15+1 -> 5 | N15: =M15+1 -> 6 | O15: =N15+1 -> 7 | P15: =O15+1 -> 8 | Q15: =P15+1 -> 9 | ... BP15: =BO15+1 -> 60
F17: ASSUMPTIONS
F18: Apts: New Leases | I18: =IF(OR(I12="Constr",I12="Pre-Dvlp"),0,IF(H19=$K$3,0,IF((H19+$K$5)>$K$3,($K$3-H$19),$K$5))) -> 0 | J18: =IF(OR(J12="Constr",J12="Pre-Dvlp"),0,IF(I19=$K$3,0,IF((I19+$K$5)>$K$3,($K$3-I$19),$K$5))) -> 0 | K18: =IF(OR(K12="Constr",K12="Pre-Dvlp"),0,IF(J19=$K$3,0,IF((J19+$K$5)>$K$3,($K$3-J$19),$K$5))) -> 0 | L18: =IF(OR(L12="Constr",L12="Pre-Dvlp"),0,IF(K19=$K$3,0,IF((K19+$K$5)>$K$3,($K$3-K$19),$K$5))) -> 0 | M18: =IF(OR(M12="Constr",M12="Pre-Dvlp"),0,IF(L19=$K$3,0,IF((L19+$K$5)>$K$3,($K$3-L$19),$K$5))) -> 0 | N18: =IF(OR(N12="Constr",N12="Pre-Dvlp"),0,IF(M19=$K$3,0,IF((M19+$K$5)>$K$3,($K$3-M$19),$K$5))) -> 0 | O18: =IF(OR(O12="Constr",O12="Pre-Dvlp"),0,IF(N19=$K$3,0,IF((N19+$K$5)>$K$3,($K$3-N$19),$K$5))) -> 0 | P18: =IF(OR(P12="Constr",P12="Pre-Dvlp"),0,IF(O19=$K$3,0,IF((O19+$K$5)>$K$3,($K$3-O$19),$K$5))) -> 0 | ... BP18: =IF(OR(BP12="Constr",BP12="Pre-Dvlp"),0,IF(BO19=$K$3,0,IF((BO19+$K$5)>$K$3,($K$3-BO$19),$K$5))) -> 0
F19: Apts: Total Leased Up | I19: =I18+H19 -> 0 | J19: =J18+I19 -> 0 | K19: =K18+J19 -> 0 | L19: =L18+K19 -> 0 | M19: =M18+L19 -> 0 | N19: =N18+M19 -> 0 | O19: =O18+N19 -> 0 | P19: =P18+O19 -> 0 | ... BP19: =BP18+BO19 -> 61
F20: Apt - Occ. % | I20: =I19/$K$3 -> 0 | J20: =J19/$K$3 -> 0 | K20: =K19/$K$3 -> 0 | L20: =L19/$K$3 -> 0 | M20: =M19/$K$3 -> 0 | N20: =N19/$K$3 -> 0 | O20: =O19/$K$3 -> 0 | P20: =P19/$K$3 -> 0 | ... BP20: =BP19/$K$3 -> 1
F21: Share of Exp. | I21: =IF(I15<$Q$9,0,IF(I15<=$R$9,$T$9,IF(I15<=$R$10,$T$10,100%))) -> 0 | J21: =IF(J15<$Q$9,0,IF(J15<=$R$9,$T$9,IF(J15<=$R$10,$T$10,100%))) -> 0 | K21: =IF(K15<$Q$9,0,IF(K15<=$R$9,$T$9,IF(K15<=$R$10,$T$10,100%))) -> 0 | L21: =IF(L15<$Q$9,0,IF(L15<=$R$9,$T$9,IF(L15<=$R$10,$T$10,100%))) -> 0 | M21: =IF(M15<$Q$9,0,IF(M15<=$R$9,$T$9,IF(M15<=$R$10,$T$10,100%))) -> 0 | N21: =IF(N15<$Q$9,0,IF(N15<=$R$9,$T$9,IF(N15<=$R$10,$T$10,100%))) -> 0 | O21: =IF(O15<$Q$9,0,IF(O15<=$R$9,$T$9,IF(O15<=$R$10,$T$10,100%))) -> 0 | P21: =IF(P15<$Q$9,0,IF(P15<=$R$9,$T$9,IF(P15<=$R$10,$T$10,100%))) -> 0 | ... BP21: =IF(BP15<$Q$9,0,IF(BP15<=$R$9,$T$9,IF(BP15<=$R$10,$T$10,100%))) -> 1
F22: REVENUES | G22: Growth % | H22: Per Unit
F23: Rental Income | G23: 0.03 | H23: =L3 -> 3288 | I23: =(H$19*$H23)*((1+$G23)^I$14) -> 0 | J23: =(I$19*$H23)*((1+$G23)^J$14) -> 0 | K23: =(J$19*$H23)*((1+$G23)^K$14) -> 0 | L23: =(K$19*$H23)*((1+$G23)^L$14) -> 0 | M23: =(L$19*$H23)*((1+$G23)^M$14) -> 0 | N23: =(M$19*$H23)*((1+$G23)^N$14) -> 0 | O23: =(N$19*$H23)*((1+$G23)^O$14) -> 0 | P23: =(O$19*$H23)*((1+$G23)^P$14) -> 0 | ... BP23: =(BO$19*$H23)*((1+$G23)^BP$14) -> 232513.28
F24: Parking | G24: 0.03 | H24: =N7/K7 -> 120 | I24: =(($H24/12)*I$20)*((1+$G24)^I$14)*$K$3 -> 0 | J24: =(($H24/12)*J$20)*((1+$G24)^J$14)*$K$3 -> 0 | K24: =(($H24/12)*K$20)*((1+$G24)^K$14)*$K$3 -> 0 | L24: =(($H24/12)*L$20)*((1+$G24)^L$14)*$K$3 -> 0 | M24: =(($H24/12)*M$20)*((1+$G24)^M$14)*$K$3 -> 0 | N24: =(($H24/12)*N$20)*((1+$G24)^N$14)*$K$3 -> 0 | O24: =(($H24/12)*O$20)*((1+$G24)^O$14)*$K$3 -> 0 | P24: =(($H24/12)*P$20)*((1+$G24)^P$14)*$K$3 -> 0 | ... BP24: =(($H24/12)*BP$20)*((1+$G24)^BP$14)*$K$3 -> 707.15719
F25: Other Services | G25: 0.03 | H25: =N8/K8 -> 80 | I25: =(($H25/12)*I$20)*((1+$G25)^I$14)*$K$3 -> 0 | J25: =(($H25/12)*J$20)*((1+$G25)^J$14)*$K$3 -> 0 | K25: =(($H25/12)*K$20)*((1+$G25)^K$14)*$K$3 -> 0 | L25: =(($H25/12)*L$20)*((1+$G25)^L$14)*$K$3 -> 0 | M25: =(($H25/12)*M$20)*((1+$G25)^M$14)*$K$3 -> 0 | N25: =(($H25/12)*N$20)*((1+$G25)^N$14)*$K$3 -> 0 | O25: =(($H25/12)*O$20)*((1+$G25)^O$14)*$K$3 -> 0 | P25: =(($H25/12)*P$20)*((1+$G25)^P$14)*$K$3 -> 0 | ... BP25: =(($H25/12)*BP$20)*((1+$G25)^BP$14)*$K$3 -> 471.43812
F26: Premiums | G26: 0.03 | H26: =N9/K9 -> 0 | I26: =(($H26/12)*I$20)*((1+$G26)^I$14)*$K$3 -> 0 | J26: =(($H26/12)*J$20)*((1+$G26)^J$14)*$K$3 -> 0 | K26: =(($H26/12)*K$20)*((1+$G26)^K$14)*$K$3 -> 0 | L26: =(($H26/12)*L$20)*((1+$G26)^L$14)*$K$3 -> 0 | M26: =(($H26/12)*M$20)*((1+$G26)^M$14)*$K$3 -> 0 | N26: =(($H26/12)*N$20)*((1+$G26)^N$14)*$K$3 -> 0 | O26: =(($H26/12)*O$20)*((1+$G26)^O$14)*$K$3 -> 0 | P26: =(($H26/12)*P$20)*((1+$G26)^P$14)*$K$3 -> 0 | ... BP26: =(($H26/12)*BP$20)*((1+$G26)^BP$14)*$K$3 -> 0
F27: Gross Pot. Rev. | I27: =SUM(I23:I26) -> 0 | J27: =SUM(J23:J26) -> 0 | K27: =SUM(K23:K26) -> 0 | L27: =SUM(L23:L26) -> 0 | M27: =SUM(M23:M26) -> 0 | N27: =SUM(N23:N26) -> 0 | O27: =SUM(O23:O26) -> 0 | P27: =SUM(P23:P26) -> 0 | ... BP27: =SUM(BP23:BP26) -> 233691.88
F28: Less: Ls-Up Conc. | H28: =-K10 -> -0.01 | I28: =I23*$H$28 -> 0 | J28: =J23*$H$28 -> 0 | K28: =K23*$H$28 -> 0 | L28: =L23*$H$28 -> 0 | M28: =M23*$H$28 -> 0 | N28: =N23*$H$28 -> 0 | O28: =O23*$H$28 -> 0 | P28: =P23*$H$28 -> 0 | ... BP28: =BP23*$H$28 -> -2325.1328
F29: Less: Bad Debt | H29: -0.005 | I29: =I$27*$H29 -> 0 | J29: =J$27*$H29 -> 0 | K29: =K$27*$H29 -> 0 | L29: =L$27*$H29 -> 0 | M29: =M$27*$H29 -> 0 | N29: =N$27*$H29 -> 0 | O29: =O$27*$H29 -> 0 | P29: =P$27*$H29 -> 0 | ... BP29: =BP$27*$H29 -> -1168.4594
F30: Less: Apt Vac. | H30: -0.05 | I30: =I$27*$H30 -> 0 | J30: =J$27*$H30 -> 0 | K30: =K$27*$H30 -> 0 | L30: =L$27*$H30 -> 0 | M30: =M$27*$H30 -> 0 | N30: =N$27*$H30 -> 0 | O30: =O$27*$H30 -> 0 | P30: =P$27*$H30 -> 0 | ... BP30: =BP$27*$H30 -> -11684.594
F31: Eff. Gross Income | I31: =SUM(I27:I30) -> 0 | J31: =SUM(J27:J30) -> 0 | K31: =SUM(K27:K30) -> 0 | L31: =SUM(L27:L30) -> 0 | M31: =SUM(M27:M30) -> 0 | N31: =SUM(N27:N30) -> 0 | O31: =SUM(O27:O30) -> 0 | P31: =SUM(P27:P30) -> 0 | ... BP31: =SUM(BP27:BP30) -> 218513.69
F32: EXPENSES | G32: Growth % | H32: Per Unit
F33: Real Estate Taxes | G33: 0.03 | H33: 2995 | I33: =(($H33/12)*I$21)*((1+$G33)^I$14)*$K$3 -> 0 | J33: =(($H33/12)*J$21)*((1+$G33)^J$14)*$K$3 -> 0 | K33: =(($H33/12)*K$21)*((1+$G33)^K$14)*$K$3 -> 0 | L33: =(($H33/12)*L$21)*((1+$G33)^L$14)*$K$3 -> 0 | M33: =(($H33/12)*M$21)*((1+$G33)^M$14)*$K$3 -> 0 | N33: =(($H33/12)*N$21)*((1+$G33)^N$14)*$K$3 -> 0 | O33: =(($H33/12)*O$21)*((1+$G33)^O$14)*$K$3 -> 0 | P33: =(($H33/12)*P$21)*((1+$G33)^P$14)*$K$3 -> 0 | ... BP33: =(($H33/12)*BP$21)*((1+$G33)^BP$14)*$K$3 -> 17649.465
F34: Insurance | G34: 0.03 | H34: 900 | I34: =(($H34/12)*I$21)*((1+$G34)^I$14)*$K$3 -> 0 | J34: =(($H34/12)*J$21)*((1+$G34)^J$14)*$K$3 -> 0 | K34: =(($H34/12)*K$21)*((1+$G34)^K$14)*$K$3 -> 0 | L34: =(($H34/12)*L$21)*((1+$G34)^L$14)*$K$3 -> 0 | M34: =(($H34/12)*M$21)*((1+$G34)^M$14)*$K$3 -> 0 | N34: =(($H34/12)*N$21)*((1+$G34)^N$14)*$K$3 -> 0 | O34: =(($H34/12)*O$21)*((1+$G34)^O$14)*$K$3 -> 0 | P34: =(($H34/12)*P$21)*((1+$G34)^P$14)*$K$3 -> 0 | ... BP34: =(($H34/12)*BP$21)*((1+$G34)^BP$14)*$K$3 -> 5303.6789
F35: Utilities | G35: 0.03 | H35: 668 | I35: =(($H35/12)*I$21)*((1+$G35)^I$14)*$K$3 -> 0 | J35: =(($H35/12)*J$21)*((1+$G35)^J$14)*$K$3 -> 0 | K35: =(($H35/12)*K$21)*((1+$G35)^K$14)*$K$3 -> 0 | L35: =(($H35/12)*L$21)*((1+$G35)^L$14)*$K$3 -> 0 | M35: =(($H35/12)*M$21)*((1+$G35)^M$14)*$K$3 -> 0 | N35: =(($H35/12)*N$21)*((1+$G35)^N$14)*$K$3 -> 0 | O35: =(($H35/12)*O$21)*((1+$G35)^O$14)*$K$3 -> 0 | P35: =(($H35/12)*P$21)*((1+$G35)^P$14)*$K$3 -> 0 | ... BP35: =(($H35/12)*BP$21)*((1+$G35)^BP$14)*$K$3 -> 3936.5083
F36: Repairs & Maint. | G36: 0.03 | H36: 829 | I36: =(($H36/12)*I$21)*((1+$G36)^I$14)*$K$3 -> 0 | J36: =(($H36/12)*J$21)*((1+$G36)^J$14)*$K$3 -> 0 | K36: =(($H36/12)*K$21)*((1+$G36)^K$14)*$K$3 -> 0 | L36: =(($H36/12)*L$21)*((1+$G36)^L$14)*$K$3 -> 0 | M36: =(($H36/12)*M$21)*((1+$G36)^M$14)*$K$3 -> 0 | N36: =(($H36/12)*N$21)*((1+$G36)^N$14)*$K$3 -> 0 | O36: =(($H36/12)*O$21)*((1+$G36)^O$14)*$K$3 -> 0 | P36: =(($H36/12)*P$21)*((1+$G36)^P$14)*$K$3 -> 0 | ... BP36: =(($H36/12)*BP$21)*((1+$G36)^BP$14)*$K$3 -> 4885.2776
F37: Mgt. Fee | H37: 0.0275 | I37: =$H37*I31 -> 0 | J37: =$H37*J31 -> 0 | K37: =$H37*K31 -> 0 | L37: =$H37*L31 -> 0 | M37: =$H37*M31 -> 0 | N37: =$H37*N31 -> 0 | O37: =$H37*O31 -> 0 | P37: =$H37*P31 -> 0 | ... BP37: =$H37*BP31 -> 6009.1265
F38: Payroll & Benefits | G38: 0.03 | H38: 1800 | I38: =(($H38/12)*I$21)*((1+$G38)^I$14)*$K$3 -> 0 | J38: =(($H38/12)*J$21)*((1+$G38)^J$14)*$K$3 -> 0 | K38: =(($H38/12)*K$21)*((1+$G38)^K$14)*$K$3 -> 0 | L38: =(($H38/12)*L$21)*((1+$G38)^L$14)*$K$3 -> 0 | M38: =(($H38/12)*M$21)*((1+$G38)^M$14)*$K$3 -> 0 | N38: =(($H38/12)*N$21)*((1+$G38)^N$14)*$K$3 -> 0 | O38: =(($H38/12)*O$21)*((1+$G38)^O$14)*$K$3 -> 0 | P38: =(($H38/12)*P$21)*((1+$G38)^P$14)*$K$3 -> 0 | ... BP38: =(($H38/12)*BP$21)*((1+$G38)^BP$14)*$K$3 -> 10607.358
F39: Advertis. & Mktg | G39: 0.03 | H39: 346 | I39: =(($H39/12)*I$21)*((1+$G39)^I$14)*$K$3 -> 0 | J39: =(($H39/12)*J$21)*((1+$G39)^J$14)*$K$3 -> 0 | K39: =(($H39/12)*K$21)*((1+$G39)^K$14)*$K$3 -> 0 | L39: =(($H39/12)*L$21)*((1+$G39)^L$14)*$K$3 -> 0 | M39: =(($H39/12)*M$21)*((1+$G39)^M$14)*$K$3 -> 0 | N39: =(($H39/12)*N$21)*((1+$G39)^N$14)*$K$3 -> 0 | O39: =(($H39/12)*O$21)*((1+$G39)^O$14)*$K$3 -> 0 | P39: =(($H39/12)*P$21)*((1+$G39)^P$14)*$K$3 -> 0 | ... BP39: =(($H39/12)*BP$21)*((1+$G39)^BP$14)*$K$3 -> 2038.9699
F40: Rental Expense | G40: 0.03 | H40: 0 | I40: =(($H40/12)*I$21)*((1+$G40)^I$14)*$K$3 -> 0 | J40: =(($H40/12)*J$21)*((1+$G40)^J$14)*$K$3 -> 0 | K40: =(($H40/12)*K$21)*((1+$G40)^K$14)*$K$3 -> 0 | L40: =(($H40/12)*L$21)*((1+$G40)^L$14)*$K$3 -> 0 | M40: =(($H40/12)*M$21)*((1+$G40)^M$14)*$K$3 -> 0 | N40: =(($H40/12)*N$21)*((1+$G40)^N$14)*$K$3 -> 0 | O40: =(($H40/12)*O$21)*((1+$G40)^O$14)*$K$3 -> 0 | P40: =(($H40/12)*P$21)*((1+$G40)^P$14)*$K$3 -> 0 | ... BP40: =(($H40/12)*BP$21)*((1+$G40)^BP$14)*$K$3 -> 0
F41: General & Admin. | G41: 0.03 | H41: 346 | I41: =(($H41/12)*I$21)*((1+$G41)^I$14)*$K$3 -> 0 | J41: =(($H41/12)*J$21)*((1+$G41)^J$14)*$K$3 -> 0 | K41: =(($H41/12)*K$21)*((1+$G41)^K$14)*$K$3 -> 0 | L41: =(($H41/12)*L$21)*((1+$G41)^L$14)*$K$3 -> 0 | M41: =(($H41/12)*M$21)*((1+$G41)^M$14)*$K$3 -> 0 | N41: =(($H41/12)*N$21)*((1+$G41)^N$14)*$K$3 -> 0 | O41: =(($H41/12)*O$21)*((1+$G41)^O$14)*$K$3 -> 0 | P41: =(($H41/12)*P$21)*((1+$G41)^P$14)*$K$3 -> 0 | ... BP41: =(($H41/12)*BP$21)*((1+$G41)^BP$14)*$K$3 -> 2038.9699
F42: Other Expense | G42: 0.03 | H42: 0 | I42: =(($H42/12)*I$21)*((1+$G42)^I$14)*$K$3 -> 0 | J42: =(($H42/12)*J$21)*((1+$G42)^J$14)*$K$3 -> 0 | K42: =(($H42/12)*K$21)*((1+$G42)^K$14)*$K$3 -> 0 | L42: =(($H42/12)*L$21)*((1+$G42)^L$14)*$K$3 -> 0 | M42: =(($H42/12)*M$21)*((1+$G42)^M$14)*$K$3 -> 0 | N42: =(($H42/12)*N$21)*((1+$G42)^N$14)*$K$3 -> 0 | O42: =(($H42/12)*O$21)*((1+$G42)^O$14)*$K$3 -> 0 | P42: =(($H42/12)*P$21)*((1+$G42)^P$14)*$K$3 -> 0 | ... BP42: =(($H42/12)*BP$21)*((1+$G42)^BP$14)*$K$3 -> 0
F43: Total Expenses | H43: =SUM(H33:H36)+SUM(H38:H42)+(H37*H23) -> 7974.42 | I43: =SUM(I33:I42) -> 0 | J43: =SUM(J33:J42) -> 0 | K43: =SUM(K33:K42) -> 0 | L43: =SUM(L33:L42) -> 0 | M43: =SUM(M33:M42) -> 0 | N43: =SUM(N33:N42) -> 0 | O43: =SUM(O33:O42) -> 0 | P43: =SUM(P33:P42) -> 0 | ... BP43: =SUM(BP33:BP42) -> 52469.354
F44: NOI | I44: =I31-I43 -> 0 | J44: =J31-J43 -> 0 | K44: =K31-K43 -> 0 | L44: =L31-L43 -> 0 | M44: =M31-M43 -> 0 | N44: =N31-N43 -> 0 | O44: =O31-O43 -> 0 | P44: =P31-P43 -> 0 | ... BP44: =BP31-BP43 -> 166044.34
F45: Replacement Rsv | G45: 0.03 | H45: 200 | I45: =(($H45/12)*I$21)*((1+$G45)^I$14)*$K$3 -> 0 | J45: =(($H45/12)*J$21)*((1+$G45)^J$14)*$K$3 -> 0 | K45: =(($H45/12)*K$21)*((1+$G45)^K$14)*$K$3 -> 0 | L45: =(($H45/12)*L$21)*((1+$G45)^L$14)*$K$3 -> 0 | M45: =(($H45/12)*M$21)*((1+$G45)^M$14)*$K$3 -> 0 | N45: =(($H45/12)*N$21)*((1+$G45)^N$14)*$K$3 -> 0 | O45: =(($H45/12)*O$21)*((1+$G45)^O$14)*$K$3 -> 0 | P45: =(($H45/12)*P$21)*((1+$G45)^P$14)*$K$3 -> 0 | ... BP45: =(($H45/12)*BP$21)*((1+$G45)^BP$14)*$K$3 -> 1178.5953
F46: CF After Rpl Rsv | I46: =I44-I45 -> 0 | J46: =J44-J45 -> 0 | K46: =K44-K45 -> 0 | L46: =L44-L45 -> 0 | M46: =M44-M45 -> 0 | N46: =N44-N45 -> 0 | O46: =O44-O45 -> 0 | P46: =P44-P45 -> 0 | ... BP46: =BP44-BP45 -> 164865.74
F47: Debt Service | I47: =Draws!I94 -> 0 | J47: =Draws!J94 -> 0 | K47: =Draws!K94 -> 0 | L47: =Draws!L94 -> 0 | M47: =Draws!M94 -> 0 | N47: =Draws!N94 -> 0 | O47: =Draws!O94 -> 0 | P47: =Draws!P94 -> 0 | ... BP47: =Draws!BP94 -> 0
F48: CF After DS | I48: =I46-I47 -> 0 | J48: =J46-J47 -> 0 | K48: =K46-K47 -> 0 | L48: =L46-L47 -> 0 | M48: =M46-M47 -> 0 | N48: =N46-N47 -> 0 | O48: =O46-O47 -> 0 | P48: =P46-P47 -> 0 | ... BP48: =BP46-BP47 -> 164865.74
F49: Is NOI+RR > $0 | G49: Ops Deficit | I49: =IF(I46>0,"YES","NO") -> NO | J49: =IF(J46>0,"YES","NO") -> NO | K49: =IF(K46>0,"YES","NO") -> NO | L49: =IF(L46>0,"YES","NO") -> NO | M49: =IF(M46>0,"YES","NO") -> NO | N49: =IF(N46>0,"YES","NO") -> NO | O49: =IF(O46>0,"YES","NO") -> NO | P49: =IF(P46>0,"YES","NO") -> NO | ... BP49: =IF(BP46>0,"YES","NO") -> YES
F50: Is CFADS > ) | G50: CF from Ops | I50: =IF(I48>0,"YES", "NO") -> NO | J50: =IF(J48>0,"YES", "NO") -> NO | K50: =IF(K48>0,"YES", "NO") -> NO | L50: =IF(L48>0,"YES", "NO") -> NO | M50: =IF(M48>0,"YES", "NO") -> NO | N50: =IF(N48>0,"YES", "NO") -> NO | O50: =IF(O48>0,"YES", "NO") -> NO | P50: =IF(P48>0,"YES", "NO") -> NO | ... BP50: =IF(BP48>0,"YES", "NO") -> YES
F51: Not B/E & NOI > $0 | H51: =SUM(I51:AD51) -> -120381.34 | I51: =IF(I46=0,0,IF(I48<0,I46,0)) -> 0 | J51: =IF(J46=0,0,IF(J48<0,J46,0)) -> 0 | K51: =IF(K46=0,0,IF(K48<0,K46,0)) -> 0 | L51: =IF(L46=0,0,IF(L48<0,L46,0)) -> 0 | M51: =IF(M46=0,0,IF(M48<0,M46,0)) -> 0 | N51: =IF(N46=0,0,IF(N48<0,N46,0)) -> 0 | O51: =IF(O46=0,0,IF(O48<0,O46,0)) -> 0 | P51: =IF(P46=0,0,IF(P48<0,P46,0)) -> 0 | ... BP51: =IF(BP46=0,0,IF(BP48<0,BP46,0)) -> 0
F52: Net Sale Amt | I52: =IF(I15=$S$7,(SUM(J46:U46)/$J$11)*(1-$L$11),0) -> 0 | J52: =IF(J15=$S$7,(SUM(K46:V46)/$J$11)*(1-$L$11),0) -> 0 | K52: =IF(K15=$S$7,(SUM(L46:W46)/$J$11)*(1-$L$11),0) -> 0 | L52: =IF(L15=$S$7,(SUM(M46:X46)/$J$11)*(1-$L$11),0) -> 0 | M52: =IF(M15=$S$7,(SUM(N46:Y46)/$J$11)*(1-$L$11),0) -> 0 | N52: =IF(N15=$S$7,(SUM(O46:Z46)/$J$11)*(1-$L$11),0) -> 0 | O52: =IF(O15=$S$7,(SUM(P46:AA46)/$J$11)*(1-$L$11),0) -> 0 | P52: =IF(P15=$S$7,(SUM(Q46:AB46)/$J$11)*(1-$L$11),0) -> 0 | ... BP52: =IF(BP15=$S$7,(SUM(BQ46:CB46)/$J$11)*(1-$L$11),0) -> 0

Sheet Waterfall
B1: Waterfall Structure (IRR) | C1: Return | D1: GP Promote | E1: GP Cash Flow | F1: LP Cash Flow | H1: Return Metrics | K1: Sale Date | L1: =EDATE(Draws!G9,1) -> 46692
B2: Preferred Return | C2: 0.1 | E2: =+GPEQUITY -> 0.1 | F2: =+LPEQUITY -> 0.9 | H2: Project-Level IRR | I2: =IFERROR(XIRR(C34:BK34,C12:BK12),0) -> 0.19440213
B3: Hurdle #2 | C3: 0.15 | D3: 0.2 | E3: =$C$8+D3*$C$9 -> 0.28 | F3: =1-E3 -> 0.72 | H3: Project-Level EM | I3: =IFERROR(SUMIF(C34:BK34,">"&0,C34:BK34)/-SUMIF(C34:BK34,"<"&0,C34:BK34),0) -> 1.6338192
B4: Hurdle #3 | C4: 0.18 | D4: 0.3 | E4: =$C$8+D4*$C$9 -> 0.37 | F4: =1-E4 -> 0.63 | H4: LP IRR | I4: =C96 -> 0.17335182
B5: Hurdle #4 | D5: 0.4 | E5: =$C$8+D5*$C$9 -> 0.46 | F5: =1-E5 -> 0.54 | H5: LP EM | I5: =C97 -> 1.5550746
H6: GP IRR | I6: =C103 -> 0.35911848
B7: Equity Investment | H7: GP EM | I7: =C104 -> 2.3425207
B8: GP Equity | C8: 0.1 | D8: =GPEQUITY*SUM($C$14:$BK$14) -> 840000 | H8: GP Promote | I8: =C110 -> 661454.78
B9: LP Equity | C9: =1-C8 -> 0.9 | D9: =LPEQUITY*SUM($C$14:$BK$14) -> 7560000
C11: 0 | D11: =C11+1 -> 1 | E11: =D11+1 -> 2 | F11: =E11+1 -> 3 | G11: =F11+1 -> 4 | H11: =G11+1 -> 5 | I11: =H11+1 -> 6 | J11: =I11+1 -> 7 | K11: =J11+1 -> 8 | ... BK11: =BJ11+1 -> 60
B12: Total Project-Level Cash Flows | C12: =EOMONTH(Draws!H10,0) -> 45596 | D12: =EOMONTH(C12,1) -> 45626 | E12: =EOMONTH(D12,1) -> 45657 | F12: =EOMONTH(E12,1) -> 45688 | G12: =EOMONTH(F12,1) -> 45716 | H12: =EOMONTH(G12,1) -> 45747 | I12: =EOMONTH(H12,1) -> 45777 | J12: =EOMONTH(I12,1) -> 45808 | K12: =EOMONTH(J12,1) -> 45838 | ... BK12: =EOMONTH(BJ12,1) -> 47422
B14: =Draws!C15 -> Equity | C14: =IF(C$11>Draws!$F$9,0,Draws!H15) -> 5309435 | D14: =IF(D$11>Draws!$F$9,0,Draws!I15) -> 33333.333 | E14: =IF(E$11>Draws!$F$9,0,Draws!J15) -> 33333.333 | F14: =IF(F$11>Draws!$F$9,0,Draws!K15) -> 33333.333 | G14: =IF(G$11>Draws!$F$9,0,Draws!L15) -> 33333.333 | H14: =IF(H$11>Draws!$F$9,0,Draws!M15) -> 33333.333 | I14: =IF(I$11>Draws!$F$9,0,Draws!N15) -> 33333.333 | J14: =IF(J$11>Draws!$F$9,0,Draws!O15) -> 1249529.6 | ... BK14: =IF(BK$11>Draws!$F$9,0,Draws!BP15) -> 0
B15: =Draws!C14 -> Senior Debt | C15: =IF(C$11>Draws!$F$9,0,Draws!H14) -> 0 | D15: =IF(D$11>Draws!$F$9,0,Draws!I14) -> 0 | E15: =IF(E$11>Draws!$F$9,0,Draws!J14) -> 0 | F15: =IF(F$11>Draws!$F$9,0,Draws!K14) -> 0 | G15: =IF(G$11>Draws!$F$9,0,Draws!L14) -> 0 | H15: =IF(H$11>Draws!$F$9,0,Draws!M14) -> 0 | I15: =IF(I$11>Draws!$F$9,0,Draws!N14) -> 0 | J15: =IF(J$11>Draws!$F$9,0,Draws!O14) -> 0 | ... BK15: =IF(BK$11>Draws!$F$9,0,Draws!BP14) -> 0
B17: ='Lease Up'!F31 -> Eff. Gross Income | D17: =IF(D$11>Draws!$F$9,0,'Lease Up'!I31) -> 0 | E17: =IF(E$11>Draws!$F$9,0,'Lease Up'!J31) -> 0 | F17: =IF(F$11>Draws!$F$9,0,'Lease Up'!K31) -> 0 | G17: =IF(G$11>Draws!$F$9,0,'Lease Up'!L31) -> 0 | H17: =IF(H$11>Draws!$F$9,0,'Lease Up'!M31) -> 0 | I17: =IF(I$11>Draws!$F$9,0,'Lease Up'!N31) -> 0 | J17: =IF(J$11>Draws!$F$9,0,'Lease Up'!O31) -> 0 | K17: =IF(K$11>Draws!$F$9,0,'Lease Up'!P31) -> 0 | ... BK17: =IF(BK$11>Draws!$F$9,0,'Lease Up'!BP31) -> 0
B18: ='Lease Up'!F43 -> Total Expenses | D18: =IF(D$11>Draws!$F$9,0,'Lease Up'!I43) -> 0 | E18: =IF(E$11>Draws!$F$9,0,'Lease Up'!J43) -> 0 | F18: =IF(F$11>Draws!$F$9,0,'Lease Up'!K43) -> 0 | G18: =IF(G$11>Draws!$F$9,0,'Lease Up'!L43) -> 0 | H18: =IF(H$11>Draws!$F$9,0,'Lease Up'!M43) -> 0 | I18: =IF(I$11>Draws!$F$9,0,'Lease Up'!N43) -> 0 | J18: =IF(J$11>Draws!$F$9,0,'Lease Up'!O43) -> 0 | K18: =IF(K$11>Draws!$F$9,0,'Lease Up'!P43) -> 0 | ... BK18: =IF(BK$11>Draws!$F$9,0,'Lease Up'!BP43) -> 0
B19: NOI | C19: =C17-C18 -> 0 | D19: =D17-D18 -> 0 | E19: =E17-E18 -> 0 | F19: =F17-F18 -> 0 | G19: =G17-G18 -> 0 | H19: =H17-H18 -> 0 | I19: =I17-I18 -> 0 | J19: =J17-J18 -> 0 | ... BK19: =BK17-BK18 -> 0
B20: Expense Ratio | C20: =IFERROR(C18/C17," ") | D20: =IFERROR(D18/D17," ") | E20: =IFERROR(E18/E17," ") | F20: =IFERROR(F18/F17," ") | G20: =IFERROR(G18/G17," ") | H20: =IFERROR(H18/H17," ") | I20: =IFERROR(I18/I17," ") | J20: =IFERROR(J18/J17," ") | ... BK20: =IFERROR(BK18/BK17," ")
AA21: =AA22-Z22 -> 117.11817
B22: ='Lease Up'!F47 -> Debt Service | D22: ='Lease Up'!I47 -> 0 | E22: ='Lease Up'!J47 -> 0 | F22: ='Lease Up'!K47 -> 0 | G22: ='Lease Up'!L47 -> 0 | H22: ='Lease Up'!M47 -> 0 | I22: ='Lease Up'!N47 -> 0 | J22: ='Lease Up'!O47 -> 0 | K22: ='Lease Up'!P47 -> 0 | ... AA22: ='Lease Up'!AF47 -> 97470.404 | AB22: =AA22+AA21 -> 97587.522 | AC22: =AB22 -> 97587.522 | AD22: =AC22 -> 97587.522 | AE22: =AD22 -> 97587.522 | AF22: =AE22 -> 97587.522 | AG22: =AF22 -> 97587.522 | AH22: =AG22 -> 97587.522 | AI22: =AH22 -> 97587.522 | AJ22: =AI22 -> 97587.522 | ... AM22: =AL22 -> 97587.522 | AN22: ='Lease Up'!AS47 -> 0 | AO22: ='Lease Up'!AT47 -> 0 | AP22: ='Lease Up'!AU47 -> 0 | AQ22: ='Lease Up'!AV47 -> 0 | AR22: ='Lease Up'!AW47 -> 0 | AS22: ='Lease Up'!AX47 -> 0 | AT22: ='Lease Up'!AY47 -> 0 | AU22: ='Lease Up'!AZ47 -> 0 | ... BK22: ='Lease Up'!BP47 -> 0
B23: DSCR | D23: =IFERROR(MAX(D19,0)/D22," ") | E23: =IFERROR(MAX(E19,0)/E22," ") | F23: =IFERROR(MAX(F19,0)/F22," ") | G23: =IFERROR(MAX(G19,0)/G22," ") | H23: =IFERROR(MAX(H19,0)/H22," ") | I23: =IFERROR(MAX(I19,0)/I22," ") | J23: =IFERROR(MAX(J19,0)/J22," ") | K23: =IFERROR(MAX(K19,0)/K22," ") | ... BK23: =IFERROR(MAX(BK19,0)/BK22," ")
B25: Cashflow After Debt Service | C25: =C19-C22 -> 0 | D25: =D19-D22 -> 0 | E25: =E19-E22 -> 0 | F25: =F19-F22 -> 0 | G25: =G19-G22 -> 0 | H25: =H19-H22 -> 0 | I25: =I19-I22 -> 0 | J25: =J19-J22 -> 0 | ... BK25: =BK19-BK22 -> 0
B27: ='Lease Up'!F45 -> Replacement Rsv | D27: =IF(D$11>Draws!$F$9,0,'Lease Up'!I45) -> 0 | E27: =IF(E$11>Draws!$F$9,0,'Lease Up'!J45) -> 0 | F27: =IF(F$11>Draws!$F$9,0,'Lease Up'!K45) -> 0 | G27: =IF(G$11>Draws!$F$9,0,'Lease Up'!L45) -> 0 | H27: =IF(H$11>Draws!$F$9,0,'Lease Up'!M45) -> 0 | I27: =IF(I$11>Draws!$F$9,0,'Lease Up'!N45) -> 0 | J27: =IF(J$11>Draws!$F$9,0,'Lease Up'!O45) -> 0 | K27: =IF(K$11>Draws!$F$9,0,'Lease Up'!P45) -> 0 | ... BK27: =IF(BK$11>Draws!$F$9,0,'Lease Up'!BP45) -> 0
B29: Cashflow from Property After Rsv. | C29: =C25-C27 -> 0 | D29: =D25-D27 -> 0 | E29: =E25-E27 -> 0 | F29: =F25-F27 -> 0 | G29: =G25-G27 -> 0 | H29: =H25-H27 -> 0 | I29: =I25-I27 -> 0 | J29: =J25-J27 -> 0 | ... BK29: =BK25-BK27 -> 0
B31: =Draws!C55 -> Sale Price | C31: =Draws!H55 -> 0 | D31: =Draws!I55 -> 0 | E31: =Draws!J55 -> 0 | F31: =Draws!K55 -> 0 | G31: =Draws!L55 -> 0 | H31: =Draws!M55 -> 0 | I31: =Draws!N55 -> 0 | J31: =Draws!O55 -> 0 | ... BK31: =Draws!BP55 -> 0
B32: =Draws!C56 -> Less: Debt | C32: =Draws!H56 -> 0 | D32: =Draws!I56 -> 0 | E32: =Draws!J56 -> 0 | F32: =Draws!K56 -> 0 | G32: =Draws!L56 -> 0 | H32: =Draws!M56 -> 0 | I32: =Draws!N56 -> 0 | J32: =Draws!O56 -> 0 | ... BK32: =Draws!BP56 -> 0
B34: Net Cashflow from Investment | C34: =MAX(C29+C31+C32,0)-C14 -> -5309435 | D34: =MAX(D29+D31+D32,0)-D14 -> -33333.333 | E34: =MAX(E29+E31+E32,0)-E14 -> -33333.333 | F34: =MAX(F29+F31+F32,0)-F14 -> -33333.333 | G34: =MAX(G29+G31+G32,0)-G14 -> -33333.333 | H34: =MAX(H29+H31+H32,0)-H14 -> -33333.333 | I34: =MAX(I29+I31+I32,0)-I14 -> -33333.333 | J34: =MAX(J29+J31+J32,0)-J14 -> -1249529.6 | ... BK34: =MAX(BK29+BK31+BK32,0)-BK14 -> 0
B35: Property IRR | C35: =XIRR(C34:BK34,C12:BK12) -> 0.19440213
B36: Property Equity Multiple | C36: =(SUM(C34:BK34)+D8+D9)/(D8+D9) -> 1.6338192
B37: Cash on Cash | C37: =(SUM(D37:BK37)/Draws!F9) -> 0.045383866 | D37: =MAX(D34,0)/($D$8+$D$9) -> 0 | E37: =MAX(E34,0)/($D$8+$D$9) -> 0 | F37: =MAX(F34,0)/($D$8+$D$9) -> 0 | G37: =MAX(G34,0)/($D$8+$D$9) -> 0 | H37: =MAX(H34,0)/($D$8+$D$9) -> 0 | I37: =MAX(I34,0)/($D$8+$D$9) -> 0 | J37: =MAX(J34,0)/($D$8+$D$9) -> 0 | K37: =MAX(K34,0)/($D$8+$D$9) -> 0 | ... BK37: =MAX(BK34,0)/($D$8+$D$9) -> 0
B38: Net Return | C38: =SUM(C34:BK34) -> 5324081.1
B40: Equity Contributions
B41: GP Contributions | C41: =C34*GPEQUITY -> -530943.5 | D41: =IF(D34<0,D34*GPEQUITY,0) -> -3333.3333 | E41: =IF(E34<0,E34*GPEQUITY,0) -> -3333.3333 | F41: =IF(F34<0,F34*GPEQUITY,0) -> -3333.3333 | G41: =IF(G34<0,G34*GPEQUITY,0) -> -3333.3333 | H41: =IF(H34<0,H34*GPEQUITY,0) -> -3333.3333 | I41: =IF(I34<0,I34*GPEQUITY,0) -> -3333.3333 | J41: =IF(J34<0,J34*GPEQUITY,0) -> -124952.96 | K41: =IF(K34<0,K34*GPEQUITY,0) -> -124952.96 | ... BK41: =IF(BK34<0,BK34*GPEQUITY,0) -> 0
B42: LP Contributions | C42: =C34*LPEQUITY -> -4778491.5 | D42: =IF(D34<0,D34*LPEQUITY,0) -> -30000 | E42: =IF(E34<0,E34*LPEQUITY,0) -> -30000 | F42: =IF(F34<0,F34*LPEQUITY,0) -> -30000 | G42: =IF(G34<0,G34*LPEQUITY,0) -> -30000 | H42: =IF(H34<0,H34*LPEQUITY,0) -> -30000 | I42: =IF(I34<0,I34*LPEQUITY,0) -> -30000 | J42: =IF(J34<0,J34*LPEQUITY,0) -> -1124576.7 | K42: =IF(K34<0,K34*LPEQUITY,0) -> -1124576.7 | ... BK42: =IF(BK34<0,BK34*LPEQUITY,0) -> 0
B44: Preferred Return
B45: Beginning Balance | C45: 0 | D45: =IF(D12>SALEMONTH,0,C49) -> 4778491.5 | E45: =IF(E12>SALEMONTH,0,D49) -> 4846071.8 | F45: =IF(F12>SALEMONTH,0,E49) -> 4915459.2 | G45: =IF(G12>SALEMONTH,0,F49) -> 4985410.5 | H45: =IF(H12>SALEMONTH,0,G49) -> 5051994.8 | I45: =IF(I12>SALEMONTH,0,H49) -> 5123055.8 | J45: =IF(J12>SALEMONTH,0,I49) -> 5193346 | K45: =IF(K12>SALEMONTH,0,J49) -> 6360132.5 | ... AL45: =IF(AL12>SALEMONTH,0,AK49) -> 9249641.2 | AM45: =IF(AM12>SALEMONTH+1,0,AL49) -> 9270352 | AN45: =IF(AN12>SALEMONTH,0,AM49) -> 0 | AO45: =IF(AO12>SALEMONTH,0,AN49) -> 0 | AP45: =IF(AP12>SALEMONTH,0,AO49) -> 0 | AQ45: =IF(AQ12>SALEMONTH,0,AP49) -> 0 | AR45: =IF(AR12>SALEMONTH,0,AQ49) -> 0 | AS45: =IF(AS12>SALEMONTH,0,AR49) -> 0 | AT45: =IF(AT12>SALEMONTH,0,AS49) -> 0 | AU45: =IF(AU12>SALEMONTH,0,AT49) -> 0 | ... BK45: =IF(BK12>SALEMONTH,0,BJ49) -> 0
B46: Preferred Interest Accrual | C46: 0 | D46: =D45*(1+PREF)^((D12-C12)/365)-D45 -> 37580.338 | E46: =E45*(1+PREF)^((E12-D12)/365)-E45 -> 39387.365 | F46: =F45*(1+PREF)^((F12-E12)/365)-F45 -> 39951.324 | G46: =G45*(1+PREF)^((G12-F12)/365)-G45 -> 36584.238 | H46: =H45*(1+PREF)^((H12-G12)/365)-H45 -> 41061.042 | I46: =I45*(1+PREF)^((I12-H12)/365)-I45 -> 40290.156 | J46: =J45*(1+PREF)^((J12-I12)/365)-J45 -> 42209.901 | K46: =K45*(1+PREF)^((K12-J12)/365)-K45 -> 50019.117 | ... BK46: =BK45*(1+PREF)^((BK12-BJ12)/365)-BK45 -> 0
B47: LP Contributions | C47: =-C42 -> 4778491.5 | D47: =-D42 -> 30000 | E47: =-E42 -> 30000 | F47: =-F42 -> 30000 | G47: =-G42 -> 30000 | H47: =-H42 -> 30000 | I47: =-I42 -> 30000 | J47: =-J42 -> 1124576.7 | ... BK47: =-BK42 -> 0
B48: LP Distributions | C48: =MIN(C45+C46,MAX(C34,0)*LPEQUITY) -> 0 | D48: =MIN(D45+D46,MAX(D34,0)*LPEQUITY) -> 0 | E48: =MIN(E45+E46,MAX(E34,0)*LPEQUITY) -> 0 | F48: =MIN(F45+F46,MAX(F34,0)*LPEQUITY) -> 0 | G48: =MIN(G45+G46,MAX(G34,0)*LPEQUITY) -> 0 | H48: =MIN(H45+H46,MAX(H34,0)*LPEQUITY) -> 0 | I48: =MIN(I45+I46,MAX(I34,0)*LPEQUITY) -> 0 | J48: =MIN(J45+J46,MAX(J34,0)*LPEQUITY) -> 0 | ... BK48: =MIN(BK45+BK46,MAX(BK34,0)*LPEQUITY) -> 0
A49: IRR | B49: Ending Balance | C49: =C45+C46+C47-C48 -> 4778491.5 | D49: =D45+D46+D47-D48 -> 4846071.8 | E49: =E45+E46+E47-E48 -> 4915459.2 | F49: =F45+F46+F47-F48 -> 4985410.5 | G49: =G45+G46+G47-G48 -> 5051994.8 | H49: =H45+H46+H47-H48 -> 5123055.8 | I49: =I45+I46+I47-I48 -> 5193346 | J49: =J45+J46+J47-J48 -> 6360132.5 | ... BK49: =BK45+BK46+BK47-BK48 -> 0
A50: =IFERROR(XIRR(C50:BK50,$C$12:$BK$12),0) -> 0.10000001 | B50: Total LP Cash Flow | C50: =C48-C47 -> -4778491.5 | D50: =D48-D47 -> -30000 | E50: =E48-E47 -> -30000 | F50: =F48-F47 -> -30000 | G50: =G48-G47 -> -30000 | H50: =H48-H47 -> -30000 | I50: =I48-I47 -> -30000 | J50: =J48-J47 -> -1124576.7 | ... BK50: =BK48-BK47 -> 0
B52: GP Contributions | C52: =-C41 -> 530943.5 | D52: =-D41 -> 3333.3333 | E52: =-E41 -> 3333.3333 | F52: =-F41 -> 3333.3333 | G52: =-G41 -> 3333.3333 | H52: =-H41 -> 3333.3333 | I52: =-I41 -> 3333.3333 | J52: =-J41 -> 124952.96 | ... BK52: =-BK41 -> 0
A53: IRR | B53: GP Distributions | C53: =(C48/LPCF1)*GPCF1 -> 0 | D53: =(D48/LPCF1)*GPCF1 -> 0 | E53: =(E48/LPCF1)*GPCF1 -> 0 | F53: =(F48/LPCF1)*GPCF1 -> 0 | G53: =(G48/LPCF1)*GPCF1 -> 0 | H53: =(H48/LPCF1)*GPCF1 -> 0 | I53: =(I48/LPCF1)*GPCF1 -> 0 | J53: =(J48/LPCF1)*GPCF1 -> 0 | ... BK53: =(BK48/LPCF1)*GPCF1 -> 0
A54: =IFERROR(XIRR(C54:BK54,$C$12:$BK$12),0) -> 0.10000001 | B54: GP Cash Flow | C54: =C53-C52 -> -530943.5 | D54: =D53-D52 -> -3333.3333 | E54: =E53-E52 -> -3333.3333 | F54: =F53-F52 -> -3333.3333 | G54: =G53-G52 -> -3333.3333 | H54: =H53-H52 -> -3333.3333 | I54: =I53-I52 -> -3333.3333 | J54: =J53-J52 -> -124952.96 | ... BK54: =BK53-BK52 -> 0
B55: Total Distributions | C55: =C53+C48 -> 0 | D55: =D53+D48 -> 0 | E55: =E53+E48 -> 0 | F55: =F53+F48 -> 0 | G55: =G53+G48 -> 0 | H55: =H53+H48 -> 0 | I55: =I53+I48 -> 0 | J55: =J53+J48 -> 0 | ... BK55: =BK53+BK48 -> 0
B56: Cash Flow Remaining | C56: =MAX(C34-C55,0) -> 0 | D56: =MAX(D34-D55,0) -> 0 | E56: =MAX(E34-E55,0) -> 0 | F56: =MAX(F34-F55,0) -> 0 | G56: =MAX(G34-G55,0) -> 0 | H56: =MAX(H34-H55,0) -> 0 | I56: =MAX(I34-I55,0) -> 0 | J56: =MAX(J34-J55,0) -> 0 | ... BK56: =MAX(BK34-BK55,0) -> 0
B58: Hurdle #2
B59: Beginning Balance | C59: 0 | D59: =IF(D12>SALEMONTH,0,C64) -> 4778491.5 | E59: =IF(E12>SALEMONTH,0,D64) -> 4863699.9 | F59: =IF(F12>SALEMONTH,0,E64) -> 4951776.9 | G59: =IF(G12>SALEMONTH,0,F64) -> 5040905.7 | H59: =IF(H12>SALEMONTH,0,G64) -> 5125242.4 | I59: =IF(I12>SALEMONTH,0,H64) -> 5216442.5 | J59: =IF(J12>SALEMONTH,0,I64) -> 5306710.7 | K59: =IF(K12>SALEMONTH,0,J64) -> 6494654.4 | ... BK59: =IF(BK12>SALEMONTH,0,BJ64) -> 0
B60: Hurdle #2 Accrual | C60: 0 | D60: =D59*(1+HURDLE2)^((D12-C12)/365)-D59 -> 55208.374 | E60: =E59*(1+HURDLE2)^((E12-D12)/365)-E59 -> 58077.064 | F60: =F59*(1+HURDLE2)^((F12-E12)/365)-F59 -> 59128.786 | G60: =G59*(1+HURDLE2)^((G12-F12)/365)-G59 -> 54336.653 | H60: =H59*(1+HURDLE2)^((H12-G12)/365)-H59 -> 61200.123 | I60: =I59*(1+HURDLE2)^((I12-H12)/365)-I59 -> 60268.247 | J60: =J59*(1+HURDLE2)^((J12-I12)/365)-J59 -> 63367.023 | K60: =K59*(1+HURDLE2)^((K12-J12)/365)-K59 -> 75036.088 | ... BK60: =BK59*(1+HURDLE2)^((BK12-BJ12)/365)-BK59 -> 0
B61: LP Contributions | C61: =-C42 -> 4778491.5 | D61: =-D42 -> 30000 | E61: =-E42 -> 30000 | F61: =-F42 -> 30000 | G61: =-G42 -> 30000 | H61: =-H42 -> 30000 | I61: =-I42 -> 30000 | J61: =-J42 -> 1124576.7 | ... BK61: =-BK42 -> 0
B62: Prior Distributions | C62: =C48 -> 0 | D62: =D48 -> 0 | E62: =E48 -> 0 | F62: =F48 -> 0 | G62: =G48 -> 0 | H62: =H48 -> 0 | I62: =I48 -> 0 | J62: =J48 -> 0 | ... BK62: =BK48 -> 0
B63: LP Distributions | C63: =MIN(C59+C60-C62,C56*LPCF2) -> 0 | D63: =MIN(D59+D60-D62,D56*LPCF2) -> 0 | E63: =MIN(E59+E60-E62,E56*LPCF2) -> 0 | F63: =MIN(F59+F60-F62,F56*LPCF2) -> 0 | G63: =MIN(G59+G60-G62,G56*LPCF2) -> 0 | H63: =MIN(H59+H60-H62,H56*LPCF2) -> 0 | I63: =MIN(I59+I60-I62,I56*LPCF2) -> 0 | J63: =MIN(J59+J60-J62,J56*LPCF2) -> 0 | ... BK63: =MIN(BK59+BK60-BK62,BK56*LPCF2) -> 0
A64: IRR | B64: Ending Balance | C64: =C59+C60+C61-C62-C63 -> 4778491.5 | D64: =D59+D60+D61-D62-D63 -> 4863699.9 | E64: =E59+E60+E61-E62-E63 -> 4951776.9 | F64: =F59+F60+F61-F62-F63 -> 5040905.7 | G64: =G59+G60+G61-G62-G63 -> 5125242.4 | H64: =H59+H60+H61-H62-H63 -> 5216442.5 | I64: =I59+I60+I61-I62-I63 -> 5306710.7 | J64: =J59+J60+J61-J62-J63 -> 6494654.4 | ... BK64: =BK59+BK60+BK61-BK62-BK63 -> 0
A65: =IFERROR(XIRR(C65:BK65,$C$12:$BK$12),0) -> 0.15000001 | B65: Total LP Cash Flow | C65: =C63-C61+C62 -> -4778491.5 | D65: =D63-D61+D62 -> -30000 | E65: =E63-E61+E62 -> -30000 | F65: =F63-F61+F62 -> -30000 | G65: =G63-G61+G62 -> -30000 | H65: =H63-H61+H62 -> -30000 | I65: =I63-I61+I62 -> -30000 | J65: =J63-J61+J62 -> -1124576.7 | ... BK65: =BK63-BK61+BK62 -> 0
B67: Distributions to LP | C67: =C63 -> 0 | D67: =D63 -> 0 | E67: =E63 -> 0 | F67: =F63 -> 0 | G67: =G63 -> 0 | H67: =H63 -> 0 | I67: =I63 -> 0 | J67: =J63 -> 0 | ... BK67: =BK63 -> 0
B68: Distributions to GP | C68: =C67/LPCF2*GPCF2 -> 0 | D68: =D67/LPCF2*GPCF2 -> 0 | E68: =E67/LPCF2*GPCF2 -> 0 | F68: =F67/LPCF2*GPCF2 -> 0 | G68: =G67/LPCF2*GPCF2 -> 0 | H68: =H67/LPCF2*GPCF2 -> 0 | I68: =I67/LPCF2*GPCF2 -> 0 | J68: =J67/LPCF2*GPCF2 -> 0 | ... BK68: =BK67/LPCF2*GPCF2 -> 0
B69: Total Distributions | C69: =SUM(C67:C68) -> 0 | D69: =SUM(D67:D68) -> 0 | E69: =SUM(E67:E68) -> 0 | F69: =SUM(F67:F68) -> 0 | G69: =SUM(G67:G68) -> 0 | H69: =SUM(H67:H68) -> 0 | I69: =SUM(I67:I68) -> 0 | J69: =SUM(J67:J68) -> 0 | ... BK69: =SUM(BK67:BK68) -> 0
B70: Cash Flow Remaining | C70: =MAX(C34-C55-C69,0) -> 0 | D70: =MAX(D34-D55-D69,0) -> 0 | E70: =MAX(E34-E55-E69,0) -> 0 | F70: =MAX(F34-F55-F69,0) -> 0 | G70: =MAX(G34-G55-G69,0) -> 0 | H70: =MAX(H34-H55-H69,0) -> 0 | I70: =MAX(I34-I55-I69,0) -> 0 | J70: =MAX(J34-J55-J69,0) -> 0 | ... BK70: =MAX(BK34-BK55-BK69,0) -> 0
B72: Hurdle #3
B73: Beginning Balance | C73: 0 | D73: =IF(D12>SALEMONTH,0,C78) -> 4778491.5 | E73: =IF(E12>SALEMONTH,0,D78) -> 4873941.9 | F73: =IF(F12>SALEMONTH,0,E78) -> 4972940.7 | G73: =IF(G12>SALEMONTH,0,F78) -> 5073340.9 | H73: =IF(H12>SALEMONTH,0,G78) -> 5168167.8 | I73: =IF(I12>SALEMONTH,0,H78) -> 5271331.8 | J73: =IF(J12>SALEMONTH,0,I78) -> 5373532.6 | K73: =IF(K12>SALEMONTH,0,J78) -> 6574180.5 | ... BK73: =IF(BK12>SALEMONTH,0,BJ78) -> 0
B74: Hurdle #3 Accrual | C74: 0 | D74: =D73*(1+HURDLE3)^((D12-C12)/365)-D73 -> 65450.429 | E74: =E73*(1+HURDLE3)^((E12-D12)/365)-E73 -> 68998.741 | F74: =F73*(1+HURDLE3)^((F12-E12)/365)-F73 -> 70400.232 | G74: =G73*(1+HURDLE3)^((G12-F12)/365)-G73 -> 64826.882 | H74: =H73*(1+HURDLE3)^((H12-G12)/365)-H73 -> 73163.996 | I74: =I73*(1+HURDLE3)^((I12-H12)/365)-I73 -> 72200.804 | J74: =J73*(1+HURDLE3)^((J12-I12)/365)-J73 -> 76071.276 | K74: =K73*(1+HURDLE3)^((K12-J12)/365)-K73 -> 90045.768 | ... BK74: =BK73*(1+HURDLE3)^((BK12-BJ12)/365)-BK73 -> 0
B75: LP Contributions | C75: =-C42 -> 4778491.5 | D75: =-D42 -> 30000 | E75: =-E42 -> 30000 | F75: =-F42 -> 30000 | G75: =-G42 -> 30000 | H75: =-H42 -> 30000 | I75: =-I42 -> 30000 | J75: =-J42 -> 1124576.7 | ... BK75: =-BK42 -> 0
B76: Prior Distributions | C76: =C63+C48 -> 0 | D76: =D63+D48 -> 0 | E76: =E63+E48 -> 0 | F76: =F63+F48 -> 0 | G76: =G63+G48 -> 0 | H76: =H63+H48 -> 0 | I76: =I63+I48 -> 0 | J76: =J63+J48 -> 0 | ... BK76: =BK63+BK48 -> 0
B77: LP Distributions | C77: =MIN(C73+C74-C76,C70*LPCF3) -> 0 | D77: =MIN(D73+D74-D76,D70*LPCF3) -> 0 | E77: =MIN(E73+E74-E76,E70*LPCF3) -> 0 | F77: =MIN(F73+F74-F76,F70*LPCF3) -> 0 | G77: =MIN(G73+G74-G76,G70*LPCF3) -> 0 | H77: =MIN(H73+H74-H76,H70*LPCF3) -> 0 | I77: =MIN(I73+I74-I76,I70*LPCF3) -> 0 | J77: =MIN(J73+J74-J76,J70*LPCF3) -> 0 | ... BK77: =MIN(BK73+BK74-BK76,BK70*LPCF3) -> 0
A78: IRR | B78: Ending Balance | C78: =C73+C74+C75-C76-C77 -> 4778491.5 | D78: =D73+D74+D75-D76-D77 -> 4873941.9 | E78: =E73+E74+E75-E76-E77 -> 4972940.7 | F78: =F73+F74+F75-F76-F77 -> 5073340.9 | G78: =G73+G74+G75-G76-G77 -> 5168167.8 | H78: =H73+H74+H75-H76-H77 -> 5271331.8 | I78: =I73+I74+I75-I76-I77 -> 5373532.6 | J78: =J73+J74+J75-J76-J77 -> 6574180.5 | ... BK78: =BK73+BK74+BK75-BK76-BK77 -> 0
A79: =IFERROR(XIRR(C79:BK79,$C$12:$BK$12),0) -> 0.17335182 | B79: Total LP Cash Flow | C79: =C77-C75+C76 -> -4778491.5 | D79: =D77-D75+D76 -> -30000 | E79: =E77-E75+E76 -> -30000 | F79: =F77-F75+F76 -> -30000 | G79: =G77-G75+G76 -> -30000 | H79: =H77-H75+H76 -> -30000 | I79: =I77-I75+I76 -> -30000 | J79: =J77-J75+J76 -> -1124576.7 | ... BK79: =BK77-BK75+BK76 -> 0
B81: Distributions to LP | C81: =C77 -> 0 | D81: =D77 -> 0 | E81: =E77 -> 0 | F81: =F77 -> 0 | G81: =G77 -> 0 | H81: =H77 -> 0 | I81: =I77 -> 0 | J81: =J77 -> 0 | ... BK81: =BK77 -> 0
B82: Distributions to GP | C82: =C81/LPCF3*GPCF3 -> 0 | D82: =D81/LPCF3*GPCF3 -> 0 | E82: =E81/LPCF3*GPCF3 -> 0 | F82: =F81/LPCF3*GPCF3 -> 0 | G82: =G81/LPCF3*GPCF3 -> 0 | H82: =H81/LPCF3*GPCF3 -> 0 | I82: =I81/LPCF3*GPCF3 -> 0 | J82: =J81/LPCF3*GPCF3 -> 0 | ... BK82: =BK81/LPCF3*GPCF3 -> 0
B83: Total Distributions | C83: =SUM(C81:C82) -> 0 | D83: =SUM(D81:D82) -> 0 | E83: =SUM(E81:E82) -> 0 | F83: =SUM(F81:F82) -> 0 | G83: =SUM(G81:G82) -> 0 | H83: =SUM(H81:H82) -> 0 | I83: =SUM(I81:I82) -> 0 | J83: =SUM(J81:J82) -> 0 | ... BK83: =SUM(BK81:BK82) -> 0
B84: Cash Flow Remaining | C84: =MAX(C34-C55-C69-C83,0) -> 0 | D84: =MAX(D34-D55-D69-D83,0) -> 0 | E84: =MAX(E34-E55-E69-E83,0) -> 0 | F84: =MAX(F34-F55-F69-F83,0) -> 0 | G84: =MAX(G34-G55-G69-G83,0) -> 0 | H84: =MAX(H34-H55-H69-H83,0) -> 0 | I84: =MAX(I34-I55-I69-I83,0) -> 0 | J84: =MAX(J34-J55-J69-J83,0) -> 0 | ... BK84: =MAX(BK34-BK55-BK69-BK83,0) -> 0
AP85: =AO85+AN85+AM85 -> 0
B86: Hurdle #4
B87: Distribution to LP | C87: =C84*LPCF4 -> 0 | D87: =D84*LPCF4 -> 0 | E87: =E84*LPCF4 -> 0 | F87: =F84*LPCF4 -> 0 | G87: =G84*LPCF4 -> 0 | H87: =H84*LPCF4 -> 0 | I87: =I84*LPCF4 -> 0 | J87: =J84*LPCF4 -> 0 | ... BK87: =BK84*LPCF4 -> 0
B88: Distribution to GP | C88: =C84*GPCF4 -> 0 | D88: =D84*GPCF4 -> 0 | E88: =E84*GPCF4 -> 0 | F88: =F84*GPCF4 -> 0 | G88: =G84*GPCF4 -> 0 | H88: =H84*GPCF4 -> 0 | I88: =I84*GPCF4 -> 0 | J88: =J84*GPCF4 -> 0 | ... BK88: =BK84*GPCF4 -> 0
B89: Total Distributions | C89: =SUM(C87:C88) -> 0 | D89: =SUM(D87:D88) -> 0 | E89: =SUM(E87:E88) -> 0 | F89: =SUM(F87:F88) -> 0 | G89: =SUM(G87:G88) -> 0 | H89: =SUM(H87:H88) -> 0 | I89: =SUM(I87:I88) -> 0 | J89: =SUM(J87:J88) -> 0 | ... BK89: =SUM(BK87:BK88) -> 0
B90: Cash Flow Remaining | C90: =C89-C84 -> 0 | D90: =D89-D84 -> 0 | E90: =E89-E84 -> 0 | F90: =F89-F84 -> 0 | G90: =G89-G84 -> 0 | H90: =H89-H84 -> 0 | I90: =I89-I84 -> 0 | J90: =J89-J84 -> 0 | ... BK90: =BK89-BK84 -> 0
B92: LP Cash Flows
B93: Contributions | C93: =C42 -> -4778491.5 | D93: =D42 -> -30000 | E93: =E42 -> -30000 | F93: =F42 -> -30000 | G93: =G42 -> -30000 | H93: =H42 -> -30000 | I93: =I42 -> -30000 | J93: =J42 -> -1124576.7 | ... BK93: =BK42 -> 0
B94: Distributions | C94: =C48+C67+C81+C87 -> 0 | D94: =D48+D67+D81+D87 -> 0 | E94: =E48+E67+E81+E87 -> 0 | F94: =F48+F67+F81+F87 -> 0 | G94: =G48+G67+G81+G87 -> 0 | H94: =H48+H67+H81+H87 -> 0 | I94: =I48+I67+I81+I87 -> 0 | J94: =J48+J67+J81+J87 -> 0 | ... BK94: =BK48+BK67+BK81+BK87 -> 0
B95: LP Net Cash Flow | C95: =SUM(C93:C94) -> -4778491.5 | D95: =SUM(D93:D94) -> -30000 | E95: =SUM(E93:E94) -> -30000 | F95: =SUM(F93:F94) -> -30000 | G95: =SUM(G93:G94) -> -30000 | H95: =SUM(H93:H94) -> -30000 | I95: =SUM(I93:I94) -> -30000 | J95: =SUM(J93:J94) -> -1124576.7 | ... BK95: =SUM(BK93:BK94) -> 0
B96: LP IRR | C96: =IFERROR(XIRR(C95:BK95,$C$12:$BK$12),0) -> 0.17335182
B97: LP EM | C97: =IFERROR(SUMIF(C95:BK95,">"&0,C95:BK95)/ABS(SUMIF(C95:BK95,"<"&0,C95:BK95)),0) -> 1.5550746
B99: GP Cash Flows
B100: Contributions | C100: =C41 -> -530943.5 | D100: =D41 -> -3333.3333 | E100: =E41 -> -3333.3333 | F100: =F41 -> -3333.3333 | G100: =G41 -> -3333.3333 | H100: =H41 -> -3333.3333 | I100: =I41 -> -3333.3333 | J100: =J41 -> -124952.96 | ... BK100: =BK41 -> 0
B101: Distributions | C101: =C53+C68+C82+C88 -> 0 | D101: =D53+D68+D82+D88 -> 0 | E101: =E53+E68+E82+E88 -> 0 | F101: =F53+F68+F82+F88 -> 0 | G101: =G53+G68+G82+G88 -> 0 | H101: =H53+H68+H82+H88 -> 0 | I101: =I53+I68+I82+I88 -> 0 | J101: =J53+J68+J82+J88 -> 0 | ... BK101: =BK53+BK68+BK82+BK88 -> 0
B102: GP Net Cash Flow | C102: =SUM(C100:C101) -> -530943.5 | D102: =SUM(D100:D101) -> -3333.3333 | E102: =SUM(E100:E101) -> -3333.3333 | F102: =SUM(F100:F101) -> -3333.3333 | G102: =SUM(G100:G101) -> -3333.3333 | H102: =SUM(H100:H101) -> -3333.3333 | I102: =SUM(I100:I101) -> -3333.3333 | J102: =SUM(J100:J101) -> -124952.96 | ... BK102: =SUM(BK100:BK101) -> 0
B103: GP IRR | C103: =IFERROR(XIRR(C102:BK102,$C$12:$BK$12),0) -> 0.35911848
B104: GP EM | C104: =IFERROR(SUMIF(C102:BK102,">"&0,C102:BK102)/ABS(SUMIF(C102:BK102,"<"&0,C102:BK102)),0) -> 2.3425207
B106: GP Promote
B107: Hurdle #2 | C107: =SUM(C69:BK69)*PROMOTE2 -> 357720.07
B108: Hurdle #3 | C108: =SUM(C83:BK83)*PROMOTE3 -> 303734.71
B109: Hurdle #4 | C109: =SUM(C89:BK89)*PROMOTE4 -> 4.6566129e-11
B110: Total GP Promote | C110: =SUM(C107:C109) -> 661454.78
B112: Total Distributions
B113: LP | C113: =SUM(C48:BK48,C63:BK63,C77:BK77,) -> 11756364
B114: GP | C114: =SUM(C53:BK53,C68:BK68,C82:BK82) -> 1967717.4
B115: Total | C115: =SUM(C113:C114) -> 13724081

Sheet Unit Mix
B1: Multifamily
B2: Market Rate
B3: Unit Type | C3: No. of Units | D3: SF | E3: Rent /mo. | F3: Rent PSF | G3: Annual Rent | H3: Tot SF | I3: W/Conc | J3: Concession/yr
B4: 1 BD / 1 BA | C4: 10 | D4: 740 | E4: ='Rent Comps'!S23 -> 2315 | F4: =IF(C4=0,0,E4/D4) -> 3.1283784 | G4: =C4*E4*12 -> 277800 | H4: =C4*D4 -> 7400 | I4: ='Rent Comps'!T23*'Unit Mix'!C4*12 -> 275030 | J4: =G4-I4 -> 2770 | K4: 23 | L4: =K4/$K$7 -> 0.19166667 | M4: =L4*$M$7 -> 11.691667 | N4: 12
B5: 2 BD / 2 BA | C5: 28 | D5: 1105 | E5: ='Rent Comps'!Z23 -> 3000.3333 | F5: =IF(C5=0,0,E5/D5) -> 2.7152338 | G5: =C5*E5*12 -> 1008112 | H5: =C5*D5 -> 30940 | I5: ='Rent Comps'!AA23*'Unit Mix'!C5*12 -> 999292 | J5: =G5-I5 -> 8820 | K5: 66 | L5: =K5/$K$7 -> 0.55 | M5: =L5*$M$7 -> 33.55 | N5: 33
B6: 3 BD / 2 BA | C6: 23 | D6: 1504 | E6: ='Rent Comps'!AG23 -> 4397.8889 | F6: =IF(C6=0,0,E6/D6) -> 2.9241283 | G6: =C6*E6*12 -> 1213817.3 | H6: =C6*D6 -> 34592 | I6: ='Rent Comps'!AH23*'Unit Mix'!C6*12 -> 1204218.7 | J6: =G6-I6 -> 9598.6667 | K6: 31 | L6: =K6/$K$7 -> 0.25833333 | M6: =L6*$M$7 -> 15.758333 | N6: 16
B7: Total/Average | C7: =SUM(C4:C6) -> 61 | D7: =IF(C7=0,0,SUMPRODUCT(C4:C6,D4:D6)/SUM(C4:C6)) -> 1195.6066 | E7: 3288 | F7: =IF(C7=0,0,E7/D7) -> 2.7500686 | G7: =SUM(G4:G6) -> 2499729.3 | H7: =SUM(H4:H6) -> 72932 | I7: =SUM(I4:I6) -> 2478540.7 | J7: =G7-I7 -> 21188.667 | K7: =SUM(K4:K6) -> 120 | M7: 61
E8: cell E7 controls rental rates
C9: # Units | E9: =C7 -> 61 | F9: 61
C10: Avg. SF | E10: =D7 -> 1195.6066 | F10: =D7 -> 1195.6066
C11: Avg. Rent/SF | E11: 2.75 | F11: 3
C12: Avg. Rent/Unit | E12: =(E9*E10*E11)/E9 -> 3287.918 | F12: =(F9*F10*F11)/F9 -> 3586.8197
B14: Rent Comps
B15: Unit Type | C15: No. of Units | D15: SF | E15: Rent /mo. | F15: Rent PSF | G15: Annual Rent | H15: Tot SF | I15: W/Conc | J15: Concession/yr
B16: 1 BD / 1 BA | C16: 10 | D16: ='Rent Comps'!R23 -> 800.41667 | E16: ='Rent Comps'!S23 -> 2315 | F16: =IF(C16=0,0,E16/D16) -> 2.8922436 | G16: =C16*E16*12 -> 277800 | H16: =C16*D16 -> 8004.1667 | I16: ='Rent Comps'!T30*'Unit Mix'!C16*12 -> 0 | J16: =G16-I16 -> 277800 | K16: 23 | L16: =K16/$K$7 -> 0.19166667 | M16: =L16*$M$7 -> 11.691667 | N16: 12
B17: 2 BD / 2 BA | C17: 28 | D17: ='Rent Comps'!Y23 -> 1169.5 | E17: ='Rent Comps'!Z23 -> 3000.3333 | F17: =IF(C17=0,0,E17/D17) -> 2.5654838 | G17: =C17*E17*12 -> 1008112 | H17: =C17*D17 -> 32746 | I17: ='Rent Comps'!AA30*'Unit Mix'!C17*12 -> 0 | J17: =G17-I17 -> 1008112 | K17: 66 | L17: =K17/$K$7 -> 0.55 | M17: =L17*$M$7 -> 33.55 | N17: 33
B18: 3 BD / 2 BA | C18: 23 | D18: ='Rent Comps'!AF23 -> 1565.3333 | E18: ='Rent Comps'!AG23 -> 4397.8889 | F18: =IF(C18=0,0,E18/D18) -> 2.8095542 | G18: =C18*E18*12 -> 1213817.3 | H18: =C18*D18 -> 36002.667 | I18: ='Rent Comps'!AH30*'Unit Mix'!C18*12 -> 0 | J18: =G18-I18 -> 1213817.3 | K18: 31 | L18: =K18/$K$7 -> 0.25833333 | M18: =L18*$M$7 -> 15.758333 | N18: 16
B19: Total/Average | C19: =SUM(C16:C18) -> 61 | D19: =IF(C19=0,0,SUMPRODUCT(C16:C18,D16:D18)/SUM(C16:C18)) -> 1258.2432 | E19: =IF(C19=0,0,G19/C19/12) -> 3414.9308 | F19: =IF(C19=0,0,E19/D19) -> 2.7140467 | G19: =SUM(G16:G18) -> 2499729.3 | H19: =SUM(H16:H18) -> 76752.833 | I19: =SUM(I16:I18) -> 0 | J19: =G19-I19 -> 2499729.3 | K19: =SUM(K16:K18) -> 120 | M19: 61
B23: Affordable
B24: Unit Type | C24: No. of Units | D24: Square Feet | E24: Rent | F24: Rent PSF | G24: Annual Rent
B25: 1 BD | C25: 0 | D25: 0 | E25: 0 | F25: =IF(C25=0,0,E25/D25) -> 0 | G25: =C25*E25*12 -> 0
B26: 1 BD + Den | C26: 0 | D26: 0 | E26: 0 | F26: =IF(C26=0,0,E26/D26) -> 0 | G26: =C26*E26*12 -> 0
B27: 2 BD / 2 BA | C27: 0 | D27: 0 | E27: 0 | F27: =IF(C27=0,0,E27/D27) -> 0 | G27: =C27*E27*12 -> 0
B28: 3 BD / 1 BA | C28: 0 | D28: 0 | E28: 0 | F28: =IF(C28=0,0,E28/D28) -> 0 | G28: =C28*E28*12 -> 0
B29: 3 BD / 2 BA | C29: 0 | D29: 0 | E29: 0 | F29: =IF(C29=0,0,E29/D29) -> 0 | G29: =C29*E29*12 -> 0
C30: 0 | D30: 0 | E30: 0 | F30: =IF(C30=0,0,E30/D30) -> 0 | G30: =C30*E30*12 -> 0
B31: Total/Average | C31: =SUM(C25:C30) -> 0 | D31: =IF(C31=0,0,SUMPRODUCT(C25:C30,D25:D30)/SUM(C25:C30)) -> 0 | E31: =IF(C31=0,0,G31/C31/12) -> 0 | F31: =IF(C31=0,0,E31/D31) -> 0 | G31: =SUM(G25:G30) -> 0
B33: Weighted Average
B34: Total/Average | C34: =+C31+C7 -> 61 | D34: =IF(C34=0,0,((C7*D7)+(C31*D31))/C34) -> 1195.6066 | E34: =IF(C34=0,0,G34/C34/12) -> 3414.9308 | F34: =IF(C34=0,0,E34/D34) -> 2.8562329 | G34: =+G31+G7 -> 2499729.3
B37: Commercial
B38: Type | C38: Status | D38: Suite | E38: Tenant | F38: Square Feet | G38: % of Total | H38: Rent PSF | I38: Annual Rent | J38: Annual Reimb. | K38: Lease Start | L38: Lease End | M38: Option
B39: Retail | C39: Leased | E39: Tenant 1 | F39: 0 | G39: =IF($F$46=0,0,F39/$F$46) -> 0 | H39: 0 | I39: =H39*F39 -> 0 | J39: 0 | K39: 43101 | L39: 43101
B40: Retail | C40: Vacant | E40: Tenant 2 | F40: 0 | G40: =IF($F$46=0,0,F40/$F$46) -> 0 | H40: 0 | I40: =H40*F40 -> 0 | J40: 0 | K40: 43101 | L40: 43102
B41: Retail | C41: Leased | E41: Tenant 3 | F41: 0 | G41: =IF($F$46=0,0,F41/$F$46) -> 0 | H41: 0 | I41: =H41*F41 -> 0 | J41: 0 | K41: 43101 | L41: 43103
B42: Retail | C42: Leased | E42: Tenant 4 | F42: 0 | G42: =IF($F$46=0,0,F42/$F$46) -> 0 | H42: 0 | I42: =H42*F42 -> 0 | J42: 0 | K42: 43101 | L42: 43103
B43: Retail | C43: Leased | E43: Tenant 5 | F43: 0 | G43: =IF($F$46=0,0,F43/$F$46) -> 0 | H43: 0 | I43: =H43*F43 -> 0 | J43: 0 | K43: 43101 | L43: 43103
B44: Office | C44: Vacant | E44: Tenant 6 | F44: 0 | G44: =IF($F$46=0,0,F44/$F$46) -> 0 | H44: 0 | I44: =H44*F44 -> 0 | J44: 0 | K44: 43101 | L44: 43106
B45: Office | C45: Vacant | E45: Tenant 7 | F45: 0 | G45: =IF($F$46=0,0,F45/$F$46) -> 0 | H45: 0 | I45: =H45*F45 -> 0 | J45: 0 | K45: 43101 | L45: 43107
B46: Total | F46: =SUM(F39:F45) -> 0 | G46: =SUM(G39:G45) -> 0 | H46: =IFERROR(I46/F46,0) -> 0 | I46: =SUM(I39:I45) -> 0 | J46: =SUM(J39:J45) -> 0
I47: Reimbursement Override | J47: 0
B49: Commercial Vacancy
B50: Occupied | C50: Vacant Sq. Ft. | D50: Total Sq. Ft. | E50: Economic Vacancy
B51: =SUMIF(C39:C45,"leased",F39:F45) -> 0 | C51: =SUMIF(C39:C45,"Vacant",F39:F45) -> 0 | D51: =SUM(B51:C51) -> 0
B52: =IF(D51=0,0,B51/$D$51) -> 0 | C52: =IF(D51=0,0,C51/$D$51) -> 0 | D52: =IF(D51=0,0,D51/$D$51) -> 0 | E52: =IF(F46=0,0,SUMIF(C39:C45,"Vacant",I39:I45)/I46) -> 0
Y57: Studio | Z57: Leased
Y58: Jr. 1 BD | Z58: Vacant
Y59: 1 BD / 1 BA
Y60: 1 BD + Den / 1 BA
Y61: 1 BD + Den / 2 BA
Y62: 2 BD / 2 BA
Y63: 2 BD + Den / 2 BA
Y64: 3 BD / 1 BA
Y65: 3 BD / 2 BA

Sheet Forward Rate
B1: https://example.com/
D2: Loan Yrs | E2: 5
D3: Min.Index | E3: =MIN($E$6:BL6) -> 0.0371808 | G3: 1 | H3: 2 | I3: 3 | J3: 4 | K3: 5 | L3: 6 | M3: 7 | N3: 8 | O3: 9 | P3: 10 | Q3: 11 | R3: 12 | S3: 13 | T3: 14 | U3: 15 | V3: 16 | W3: 17 | X3: 18 | Y3: 19 | Z3: 20 | AA3: 21 | AB3: 22 | AC3: 23 | AD3: 24 | AE3: 25 | AF3: 26 | AG3: 27 | AH3: 28 | AI3: 29 | AJ3: 30 | AK3: 31 | AL3: 32 | AM3: 33 | AN3: 34 | AO3: 35 | AP3: 36 | AQ3: 37 | AR3: 38 | AS3: 39 | AT3: 40 | AU3: 41 | AV3: 42 | AW3: 43 | AX3: 44 | AY3: 45 | AZ3: 46 | BA3: 47 | BB3: 48 | BC3: 49 | BD3: 50 | BE3: 51 | BF3: 52 | BG3: 53 | BH3: 54 | BI3: 55 | BJ3: 56 | BK3: 57 | BL3: 58
D4: Year | E4: 1 | F4: 1 | G4: 1 | H4: 1 | I4: 1 | J4: 1 | K4: 1 | L4: 1 | M4: 1 | N4: 1 | O4: 1 | P4: 1 | Q4: =E4+1 -> 2 | R4: =F4+1 -> 2 | S4: =G4+1 -> 2 | T4: =H4+1 -> 2 | U4: =I4+1 -> 2 | V4: =J4+1 -> 2 | W4: =K4+1 -> 2 | X4: =L4+1 -> 2 | ... DU4: =DI4+1 -> 11
D5: Date | E5: 45455 | F5: 45485 | G5: 45516 | H5: 45547 | I5: 45580 | J5: 45608 | K5: 45638 | L5: 45670 | M5: 45700 | N5: 45728 | O5: 45761 | P5: 45789 | Q5: 45820 | R5: 45852 | S5: 45881 | T5: 45912 | U5: 45944 | V5: 45973 | W5: 46003 | X5: 46034 | Y5: 46065 | Z5: 46093 | AA5: 46125 | AB5: 46154 | AC5: 46185 | AD5: 46216 | AE5: 46246 | AF5: 46279 | AG5: 46308 | AH5: 46338 | AI5: 46370 | AJ5: 46399 | AK5: 46430 | AL5: 46458 | AM5: 46489 | AN5: 46519 | AO5: 46552 | AP5: 46580 | AQ5: 46611 | AR5: 46643 | AS5: 46672 | AT5: 46703 | AU5: 46734 | AV5: 46764 | AW5: 46797 | AX5: 46825 | AY5: 46855 | AZ5: 46885 | BA5: 46916 | BB5: 46946 | BC5: 46979 | BD5: 47008 | BE5: 47038 | BF5: 47070 | BG5: 47099 | BH5: 47130 | BI5: 47161 | BJ5: 47189 | BK5: 47220 | BL5: 47252 | BM5: 47281 | BN5: 47311 | BO5: 47343 | BP5: 47373 | BQ5: 47403 | BR5: 47435 | BS5: 47464 | BT5: 47497 | BU5: 47526 | BV5: 47554 | BW5: 47585 | BX5: 47616 | BY5: 47646 | BZ5: 47676 | CA5: 47707 | CB5: 47738 | CC5: 47771 | CD5: 47799 | CE5: 47829 | CF5: 47861 | CG5: 47891 | CH5: 47919 | CI5: 47952 | CJ5: 47980 | CK5: 48011 | CL5: 48043 | CM5: 48072 | CN5: 48103 | CO5: 48135 | CP5: 48164 | CQ5: 48194 | CR5: 48225 | CS5: 48256 | CT5: 48285 | CU5: 48316 | CV5: 48346 | CW5: 48379 | CX5: 48407 | CY5: 48438 | CZ5: 48470 | DA5: 48499 | DB5: 48530 | DC5: 48561 | DD5: 48591 | DE5: 48624 | DF5: 48652 | DG5: 48681 | DH5: 48711 | DI5: 48743 | DJ5: 48772 | DK5: 48803 | DL5: 48834 | DM5: 48864 | DN5: 48897 | DO5: 48925 | DP5: 48956 | DQ5: 48988 | DR5: 49016 | DS5: 49046 | DT5: 49076 | DU5: 49107
A6: Date | B6: 1-month Term SOFR | D6: 1-month Term SOFR | E6: 0.053291 | F6: 0.0532664 | G6: 0.0530533 | H6: 0.0523577 | I6: 0.0518021 | J6: 0.0512678 | K6: 0.0496218 | L6: 0.0493128 | M6: 0.0493027 | N6: 0.0474269 | O6: 0.0469083 | P6: 0.0469113 | Q6: 0.0451619 | R6: 0.0447548 | S6: 0.0447548 | T6: 0.0437221 | U6: 0.042989 | V6: 0.0424915 | W6: 0.0420029 | X6: 0.0415444 | Y6: 0.0411388 | Z6: 0.0407816 | AA6: 0.040438 | AB6: 0.040156 | AC6: 0.0398925 | AD6: 0.0396465 | AE6: 0.0394175 | AF6: 0.0391868 | AG6: 0.038991 | AH6: 0.0388005 | AI6: 0.0386124 | AJ6: 0.0384527 | AK6: 0.0382955 | AL6: 0.0381622 | AM6: 0.038028 | AN6: 0.0379106 | AO6: 0.0377935 | AP6: 0.0377035 | AQ6: 0.0376126 | AR6: 0.0375261 | AS6: 0.0374577 | AT6: 0.0373924 | AU6: 0.037336 | AV6: 0.0372924 | AW6: 0.0372459 | AX6: 0.0372216 | AY6: 0.0371989 | AZ6: 0.0371878 | BA6: 0.0371808 | BB6: 0.0371865 | BC6: 0.0371872 | BD6: 0.0371933 | BE6: 0.0372102 | BF6: 0.0372237 | BG6: 0.0372463 | BH6: 0.0372723 | BI6: 0.0372953 | BJ6: 0.037334 | BK6: 0.0373754 | BL6: 0.0374175 | BM6: 0.0374584 | BN6: 0.0375087 | BO6: 0.0375526 | BP6: 0.0375925 | BQ6: 0.0376392 | BR6: 0.0376769 | BS6: 0.0377226 | BT6: 0.0377592 | BU6: 0.0377871 | BV6: 0.0378283 | BW6: 0.0378642 | BX6: 0.0378989 | BY6: 0.0379288 | BZ6: 0.0379627 | CA6: 0.0379939 | CB6: 0.0380289 | CC6: 0.0380546 | CD6: 0.0380772 | CE6: 0.0381077 | CF6: 0.0381315 | CG6: 0.0381477 | CH6: 0.0381805 | CI6: 0.0381967 | CJ6: 0.0382178 | CK6: 0.03824 | CL6: 0.0382584 | CM6: 0.0382777 | CN6: 0.0383011 | CO6: 0.038321 | CP6: 0.0383393 | CQ6: 0.0383634 | CR6: 0.0383864 | CS6: 0.038405 | CT6: 0.0384323 | CU6: 0.0384543 | CV6: 0.0384858 | CW6: 0.0385054 | CX6: 0.0385313 | CY6: 0.0385601 | CZ6: 0.0385828 | DA6: 0.0386109 | DB6: 0.0386387 | DC6: 0.038667 | DD6: 0.0386999 | DE6: 0.0387183 | DF6: 0.0387528 | DG6: 0.0387785 | DH6: 0.0388133 | DI6: 0.0388403 | DJ6: 0.0388725 | DK6: 0.0389046 | DL6: 0.0389346 | DM6: 0.0389745 | DN6: 0.0390023 | DO6: 0.0390357 | DP6: 0.0390729 | DQ6: 0.0390983 | DR6: 0.0391384 | DS6: 0.0391705 | DT6: 0.0392084 | DU6: 0.0392423
A7: 45455 | B7: 0.053291
A8: 45485 | B8: 0.0532664
A9: 45516 | B9: 0.0530533
A10: 45547 | B10: 0.0523577
A11: 45580 | B11: 0.0518021
A12: 45608 | B12: 0.0512678
A13: 45638 | B13: 0.0496218
A14: 45670 | B14: 0.0493128
A15: 45700 | B15: 0.0493027
A16: 45728 | B16: 0.0474269
A17: 45761 | B17: 0.0469083
A18: 45789 | B18: 0.0469113
... A127: 49107 | B127: 0.0392423

Sheet Rent Comps
AT2: Apart | AU2: Note | AV2: units | AW2: Occ | AX2: Built | AY2: Rent | AZ2: PSF | BA2: Builder | BB2: Bldg. Address
AT3: Subject
C8: RENTAL COMPS
I9: Studios | P9: 1BR | W9: 2BR | AD9: 3BR | AK9: Total | AS9: .
C10: Name | D10: Address | E10: Submkt | F10: Built | G10: # Unit | H10: Occ. | I10: # Unit | J10: # Vac | K10: SF | L10: Avg $ | M10: Eff. $ | N10: $/SF | O10: Conc % | P10: # Unit | Q10: # Vac | R10: SF | S10: Avg $ | T10: Eff $ | U10: $/SF | V10: Conc% | W10: # Unit | X10: # Vac | Y10: SF | Z10: Avg $ | AA10: Eff. $ | AB10: $/SF | AC10: Conc% | AD10: # Unit | AE10: # Vac | AF10: SF | AG10: Avg $ | AH10: Eff $ | AI10: $/SF | AJ10: Conc% | AK10: # Unit | AL10: # Vac | AM10: SF | AN10: Avg $ | AO10: Eff $ | AP10: $/SF | AQ10: Conc%
C11: The Harrison | D11: 2555-2575 University Pkwy | E11: Person1180 | F11: 2020 | G11: =AK11 -> 240 | H11: =1-(AL11/AK11) -> 0.93333333 | I11: 0 | J11: 0 | K11: 0 | L11: 0 | M11: 0 | N11: =IF(K11=0,0,L11/K11) -> 0 | O11: =IF(L11=0,0,(L11-M11)/L11) -> 0 | P11: 96 | Q11: 7 | R11: 810 | S11: 1864 | T11: 1864 | U11: =IF(R11=0,0,S11/R11) -> 2.3012346 | V11: =IF(S11=0,0,(S11-T11)/S11) -> 0 | W11: 113 | X11: 6 | Y11: 1140 | Z11: 2158 | AA11: 2158 | AB11: =IF(Y11=0,0,Z11/Y11) -> 1.8929825 | AC11: =IF(Z11=0,0,(Z11-AA11)/Z11) -> 0 | AD11: 31 | AE11: 3 | AF11: 1351 | AG11: 2789 | AH11: 2789 | AI11: =IF(AF11=0,0,AG11/AF11) -> 2.0643967 | AJ11: =IF(AG11=0,0,(AG11-AH11)/AG11) -> 0 | AK11: =I11+P11+W11+AD11 -> 240 | AL11: =J11+Q11+X11+AE11 -> 16 | AM11: =((I11*K11)+(P11*R11)+(W11*Y11)+(AD11*AF11))/AK11 -> 1035.2542 | AN11: =(($I11*L11)+($P11*S11)+($W11*Z11)+($AD11*AG11))/$AK11 -> 2121.9042 | AO11: =(($I11*M11)+($P11*T11)+($W11*AA11)+($AD11*AH11))/$AK11 -> 2121.9042 | AP11: =IF(AM11=0,0,AN11/AM11) -> 2.0496456 | AQ11: =IF(AN11=0,0,(AN11-AO11)/AN11) -> 0
C12: Loop 2800 | D12: 2800 Telluride Loop | E12: Person1180 | F12: 2018 | G12: =AK12 -> 324 | H12: =1-(AL12/AK12) -> 0.95679012 | I12: 0 | J12: 0 | K12: 0 | L12: 0 | M12: 0 | N12: =IF(K12=0,0,L12/K12) -> 0 | O12: =IF(L12=0,0,(L12-M12)/L12) -> 0 | P12: 110 | Q12: 5 | R12: 814 | S12: 1741 | T12: 1741 | U12: =IF(R12=0,0,S12/R12) -> 2.1388206 | V12: =IF(S12=0,0,(S12-T12)/S12) -> 0 | W12: 178 | X12: 7 | Y12: 1167 | Z12: 2089 | AA12: 2089 | AB12: =IF(Y12=0,0,Z12/Y12) -> 1.79006 | AC12: =IF(Z12=0,0,(Z12-AA12)/Z12) -> 0 | AD12: 36 | AE12: 2 | AF12: 1319 | AG12: 2532 | AH12: 2532 | AI12: =IF(AF12=0,0,AG12/AF12) -> 1.9196361 | AJ12: =IF(AG12=0,0,(AG12-AH12)/AG12) -> 0 | AK12: =I12+P12+W12+AD12 -> 324 | AL12: =J12+Q12+X12+AE12 -> 14 | AM12: =((I12*K12)+(P12*R12)+(W12*Y12)+(AD12*AF12))/AK12 -> 1064.0432 | AN12: =(($I12*L12)+($P12*S12)+($W12*Z12)+($AD12*AG12))/$AK12 -> 2020.0741 | AO12: =(($I12*M12)+($P12*T12)+($W12*AA12)+($AD12*AH12))/$AK12 -> 2020.0741 | AP12: =IF(AM12=0,0,AN12/AM12) -> 1.8984888 | AQ12: =IF(AN12=0,0,(AN12-AO12)/AN12) -> 0
C13: Pt @ Bella Grove | D13: 8310 Bella Grove Cir | E13: Person1180 | F13: 2017 | G13: =AK13 -> 180 | H13: =1-(AL13/AK13) -> 0.88888889 | I13: 0 | J13: 0 | K13: 0 | L13: 0 | M13: 0 | N13: =IF(K13=0,0,L13/K13) -> 0 | O13: =IF(L13=0,0,(L13-M13)/L13) -> 0 | P13: 79 | Q13: 6 | R13: 741 | S13: 1784 | T13: 1766 | U13: =IF(R13=0,0,S13/R13) -> 2.4075574 | V13: =IF(S13=0,0,(S13-T13)/S13) -> 0.010089686 | W13: 95 | X13: 12 | Y13: 1040 | Z13: 2023 | AA13: 2003 | AB13: =IF(Y13=0,0,Z13/Y13) -> 1.9451923 | AC13: =IF(Z13=0,0,(Z13-AA13)/Z13) -> 0.0098863075 | AD13: 6 | AE13: 2 | AF13: 1240 | AG13: 2604 | AH13: 2578 | AI13: =IF(AF13=0,0,AG13/AF13) -> 2.1 | AJ13: =IF(AG13=0,0,(AG13-AH13)/AG13) -> 0.009984639 | AK13: =I13+P13+W13+AD13 -> 180 | AL13: =J13+Q13+X13+AE13 -> 20 | AM13: =((I13*K13)+(P13*R13)+(W13*Y13)+(AD13*AF13))/AK13 -> 915.43889 | AN13: =(($I13*L13)+($P13*S13)+($W13*Z13)+($AD13*AG13))/$AK13 -> 1937.4722 | AO13: =(($I13*M13)+($P13*T13)+($W13*AA13)+($AD13*AH13))/$AK13 -> 1918.15 | AP13: =IF(AM13=0,0,AN13/AM13) -> 2.1164408 | AQ13: =IF(AN13=0,0,(AN13-AO13)/AN13) -> 0.0099729028
C14: Product0040 @ Univ | D14: 3540 Broadway | E14: Person1180 | F14: 2023 | G14: =AK14 -> 183 | H14: =1-(AL14/AK14) -> 0.80327869 | I14: 0 | J14: 0 | K14: 0 | L14: 0 | M14: 0 | N14: =IF(K14=0,0,L14/K14) -> 0 | O14: =IF(L14=0,0,(L14-M14)/L14) -> 0 | P14: 82 | Q14: 15 | R14: 798 | S14: 2664 | T14: 2614 | U14: =IF(R14=0,0,S14/R14) -> 3.3383459 | V14: =IF(S14=0,0,(S14-T14)/S14) -> 0.018768769 | W14: 101 | X14: 21 | Y14: 1295 | Z14: 3903 | AA14: 3830 | AB14: =IF(Y14=0,0,Z14/Y14) -> 3.0138996 | AC14: =IF(Z14=0,0,(Z14-AA14)/Z14) -> 0.018703561 | AD14: 0 | AE14: 0 | AF14: 0 | AG14: 0 | AH14: 0 | AI14: =IF(AF14=0,0,AG14/AF14) -> 0 | AJ14: =IF(AG14=0,0,(AG14-AH14)/AG14) -> 0 | AK14: =I14+P14+W14+AD14 -> 183 | AL14: =J14+Q14+X14+AE14 -> 36 | AM14: =((I14*K14)+(P14*R14)+(W14*Y14)+(AD14*AF14))/AK14 -> 1072.3005 | AN14: =(($I14*L14)+($P14*S14)+($W14*Z14)+($AD14*AG14))/$AK14 -> 3347.8197 | AO14: =(($I14*M14)+($P14*T14)+($W14*AA14)+($AD14*AH14))/$AK14 -> 3285.1257 | AP14: =IF(AM14=0,0,AN14/AM14) -> 3.1220908 | AQ14: =IF(AN14=0,0,(AN14-AO14)/AN14) -> 0.018726812
C15: Person1071 Apt | D15: 2413 N. Tamiami Trl | E15: Downtown Sarasota | F15: 2022 | G15: =AK15 -> 47 | H15: =1-(AL15/AK15) -> 0.91489362 | I15: 0 | J15: 0 | K15: 0 | L15: 0 | M15: 0 | N15: =IF(K15=0,0,L15/K15) -> 0 | O15: =IF(L15=0,0,(L15-M15)/L15) -> 0 | P15: 20 | Q15: 1 | R15: 713 | S15: 2553 | T15: 2538 | U15: =IF(R15=0,0,S15/R15) -> 3.5806452 | V15: =IF(S15=0,0,(S15-T15)/S15) -> 0.0058754407 | W15: 24 | X15: 3 | Y15: 1073 | Z15: 3254 | AA15: 3236 | AB15: =IF(Y15=0,0,Z15/Y15) -> 3.0326188 | AC15: =IF(Z15=0,0,(Z15-AA15)/Z15) -> 0.0055316533 | AD15: 3 | AE15: 0 | AF15: 1073 | AG15: 4040 | AH15: 4015 | AI15: =IF(AF15=0,0,AG15/AF15) -> 3.7651445 | AJ15: =IF(AG15=0,0,(AG15-AH15)/AG15) -> 0.0061881188 | AK15: =I15+P15+W15+AD15 -> 47 | AL15: =J15+Q15+X15+AE15 -> 4 | AM15: =((I15*K15)+(P15*R15)+(W15*Y15)+(AD15*AF15))/AK15 -> 919.80851 | AN15: =(($I15*L15)+($P15*S15)+($W15*Z15)+($AD15*AG15))/$AK15 -> 3005.8723 | AO15: =(($I15*M15)+($P15*T15)+($W15*AA15)+($AD15*AH15))/$AK15 -> 2988.7021 | AP15: =IF(AM15=0,0,AN15/AM15) -> 3.2679327 | AQ15: =IF(AN15=0,0,(AN15-AO15)/AN15) -> 0.0057122229
C16: Product0108 Apt | D16: 700 Coconut | E16: Downtown Sarasota | F16: 2016 | G16: =AK16 -> 228 | H16: =1-(AL16/AK16) -> 0.96929825 | I16: 39 | J16: 1 | K16: 636 | L16: 2224 | M16: 2217 | N16: =IF(K16=0,0,L16/K16) -> 3.4968553 | O16: =IF(L16=0,0,(L16-M16)/L16) -> 0.003147482 | P16: 96 | Q16: 0 | R16: 840 | S16: 2597 | T16: 2589 | U16: =IF(R16=0,0,S16/R16) -> 3.0916667 | V16: =IF(S16=0,0,(S16-T16)/S16) -> 0.0030804775 | W16: 93 | X16: 6 | Y16: 1166 | Z16: 3522 | AA16: 3511 | AB16: =IF(Y16=0,0,Z16/Y16) -> 3.0205832 | AC16: =IF(Z16=0,0,(Z16-AA16)/Z16) -> 0.0031232254 | AD16: 0 | AE16: 0 | AF16: 0 | AG16: 0 | AH16: 0 | AI16: =IF(AF16=0,0,AG16/AF16) -> 0 | AJ16: =IF(AG16=0,0,(AG16-AH16)/AG16) -> 0 | AK16: =I16+P16+W16+AD16 -> 228 | AL16: =J16+Q16+X16+AE16 -> 7 | AM16: =((I16*K16)+(P16*R16)+(W16*Y16)+(AD16*AF16))/AK16 -> 938.07895 | AN16: =(($I16*L16)+($P16*S16)+($W16*Z16)+($AD16*AG16))/$AK16 -> 2910.5 | AO16: =(($I16*M16)+($P16*T16)+($W16*AA16)+($AD16*AH16))/$AK16 -> 2901.4474 | AP16: =IF(AM16=0,0,AN16/AM16) -> 3.1026173 | AQ16: =IF(AN16=0,0,(AN16-AO16)/AN16) -> 0.0031103355
C17: District @ Rosemary | D17: 710 Lemon Ave | E17: Downtown Sarasota | F17: 2018 | G17: =AK17 -> 286 | H17: =1-(AL17/AK17) -> 0.8986014 | I17: 23 | J17: 6 | K17: 550 | L17: 1745 | M17: 1734 | N17: =IF(K17=0,0,L17/K17) -> 3.1727273 | O17: =IF(L17=0,0,(L17-M17)/L17) -> 0.0063037249 | P17: 163 | Q17: 17 | R17: 764 | S17: 2238 | T17: 2224 | U17: =IF(R17=0,0,S17/R17) -> 2.9293194 | V17: =IF(S17=0,0,(S17-T17)/S17) -> 0.0062555853 | W17: 100 | X17: 6 | Y17: 1312 | Z17: 3271 | AA17: 3252 | AB17: =IF(Y17=0,0,Z17/Y17) -> 2.4931402 | AC17: =IF(Z17=0,0,(Z17-AA17)/Z17) -> 0.0058086212 | AD17: 0 | AE17: 0 | AF17: 0 | AG17: 0 | AH17: 0 | AI17: =IF(AF17=0,0,AG17/AF17) -> 0 | AJ17: =IF(AG17=0,0,(AG17-AH17)/AG17) -> 0 | AK17: =I17+P17+W17+AD17 -> 286 | AL17: =J17+Q17+X17+AE17 -> 29 | AM17: =((I17*K17)+(P17*R17)+(W17*Y17)+(AD17*AF17))/AK17 -> 938.3986 | AN17: =(($I17*L17)+($P17*S17)+($W17*Z17)+($AD17*AG17))/$AK17 -> 2559.542 | AO17: =(($I17*M17)+($P17*T17)+($W17*AA17)+($AD17*AH17))/$AK17 -> 2544.035 | AP17: =IF(AM17=0,0,AN17/AM17) -> 2.7275637 | AQ17: =IF(AN17=0,0,(AN17-AO17)/AN17) -> 0.0060585031
C18: ARCOS | D18: 320 Central Ave | E18: Downtown Sarasota | F18: 2018 | G18: =AK18 -> 228 | H18: =1-(AL18/AK18) -> 0.9254386 | I18: 26 | J18: 2 | K18: 686 | L18: 2353 | M18: 2267 | N18: =IF(K18=0,0,L18/K18) -> 3.4300292 | O18: =IF(L18=0,0,(L18-M18)/L18) -> 0.036549086 | P18: 95 | Q18: 4 | R18: 813 | S18: 2724 | T18: 2625 | U18: =IF(R18=0,0,S18/R18) -> 3.3505535 | V18: =IF(S18=0,0,(S18-T18)/S18) -> 0.036343612 | W18: 96 | X18: 8 | Y18: 1260 | Z18: 2941 | AA18: 2865 | AB18: =IF(Y18=0,0,Z18/Y18) -> 2.334127 | AC18: =IF(Z18=0,0,(Z18-AA18)/Z18) -> 0.02584155 | AD18: 11 | AE18: 3 | AF18: 1672 | AG18: 4639 | AH18: 4549 | AI18: =IF(AF18=0,0,AG18/AF18) -> 2.7745215 | AJ18: =IF(AG18=0,0,(AG18-AH18)/AG18) -> 0.019400733 | AK18: =I18+P18+W18+AD18 -> 228 | AL18: =J18+Q18+X18+AE18 -> 17 | AM18: =((I18*K18)+(P18*R18)+(W18*Y18)+(AD18*AF18))/AK18 -> 1028.1711 | AN18: =(($I18*L18)+($P18*S18)+($W18*Z18)+($AD18*AG18))/$AK18 -> 2865.4518 | AO18: =(($I18*M18)+($P18*T18)+($W18*AA18)+($AD18*AH18))/$AK18 -> 2778.0526 | AP18: =IF(AM18=0,0,AN18/AM18) -> 2.7869407 | AQ18: =IF(AN18=0,0,(AN18-AO18)/AN18) -> 0.030500993
C19: Bold Lofts | D19: 1659 2nd St | E19: Downtown Sarasota | F19: 2019 | G19: =AK19 -> 97 | H19: =1-(AL19/AK19) -> 0.97938144 | I19: 8 | J19: 0 | K19: 570 | L19: 1952 | M19: 1933 | N19: =IF(K19=0,0,L19/K19) -> 3.4245614 | O19: =IF(L19=0,0,(L19-M19)/L19) -> 0.0097336066 | P19: 28 | Q19: 0 | R19: 780 | S19: 1950 | T19: 1931 | U19: =IF(R19=0,0,S19/R19) -> 2.5 | V19: =IF(S19=0,0,(S19-T19)/S19) -> 0.0097435897 | W19: 50 | X19: 1 | Y19: 1060 | Z19: 2620 | AA19: 2594 | AB19: =IF(Y19=0,0,Z19/Y19) -> 2.4716981 | AC19: =IF(Z19=0,0,(Z19-AA19)/Z19) -> 0.0099236641 | AD19: 11 | AE19: 1 | AF19: 1374 | AG19: 3059 | AH19: 3028 | AI19: =IF(AF19=0,0,AG19/AF19) -> 2.2263464 | AJ19: =IF(AG19=0,0,(AG19-AH19)/AG19) -> 0.010134031 | AK19: =I19+P19+W19+AD19 -> 97 | AL19: =J19+Q19+X19+AE19 -> 2 | AM19: =((I19*K19)+(P19*R19)+(W19*Y19)+(AD19*AF19))/AK19 -> 974.37113 | AN19: =(($I19*L19)+($P19*S19)+($W19*Z19)+($AD19*AG19))/$AK19 -> 2421.2887 | AO19: =(($I19*M19)+($P19*T19)+($W19*AA19)+($AD19*AH19))/$AK19 -> 2397.3196 | AP19: =IF(AM19=0,0,AN19/AM19) -> 2.4849758 | AQ19: =IF(AN19=0,0,(AN19-AO19)/AN19) -> 0.0098993039
C20: The Desota | D20: 1415 2nd St | E20: Downtown Sarasota | F20: 2017 | G20: =AK20 -> 180 | H20: =1-(AL20/AK20) -> 0.84444444 | I20: 0 | J20: 0 | K20: 0 | L20: 0 | M20: 0 | N20: =IF(K20=0,0,L20/K20) -> 0 | O20: =IF(L20=0,0,(L20-M20)/L20) -> 0 | P20: 84 | Q20: 15 | R20: 863 | S20: 2679 | T20: 2662 | U20: =IF(R20=0,0,S20/R20) -> 3.1042874 | V20: =IF(S20=0,0,(S20-T20)/S20) -> 0.0063456514 | W20: 84 | X20: 12 | Y20: 1240 | Z20: 3707 | AA20: 3684 | AB20: =IF(Y20=0,0,Z20/Y20) -> 2.9895161 | AC20: =IF(Z20=0,0,(Z20-AA20)/Z20) -> 0.006204478 | AD20: 12 | AE20: 1 | AF20: 2408 | AG20: 7646 | AH20: 7599 | AI20: =IF(AF20=0,0,AG20/AF20) -> 3.1752492 | AJ20: =IF(AG20=0,0,(AG20-AH20)/AG20) -> 0.006147005 | AK20: =I20+P20+W20+AD20 -> 180 | AL20: =J20+Q20+X20+AE20 -> 28 | AM20: =((I20*K20)+(P20*R20)+(W20*Y20)+(AD20*AF20))/AK20 -> 1141.9333 | AN20: =(($I20*L20)+($P20*S20)+($W20*Z20)+($AD20*AG20))/$AK20 -> 3489.8667 | AO20: =(($I20*M20)+($P20*T20)+($W20*AA20)+($AD20*AH20))/$AK20 -> 3468.0667 | AP20: =IF(AM20=0,0,AN20/AM20) -> 3.0561037 | AQ20: =IF(AN20=0,0,(AN20-AO20)/AN20) -> 0.006246657
C21: One Palm | D21: 201 S Palm | E21: Downtown Sarasota | F21: 2016 | G21: =AK21 -> 138 | H21: =1-(AL21/AK21) -> 0.95652174 | I21: 0 | J21: 0 | K21: 0 | L21: 0 | M21: 0 | N21: =IF(K21=0,0,L21/K21) -> 0 | O21: =IF(L21=0,0,(L21-M21)/L21) -> 0 | P21: 56 | Q21: 3 | R21: 854 | S21: 2830 | T21: 2808 | U21: =IF(R21=0,0,S21/R21) -> 3.3138173 | V21: =IF(S21=0,0,(S21-T21)/S21) -> 0.0077738516 | W21: 76 | X21: 2 | Y21: 1262 | Z21: 3913 | AA21: 3882 | AB21: =IF(Y21=0,0,Z21/Y21) -> 3.1006339 | AC21: =IF(Z21=0,0,(Z21-AA21)/Z21) -> 0.0079223102 | AD21: 6 | AE21: 1 | AF21: 2310 | AG21: 9174 | AH21: 9101 | AI21: =IF(AF21=0,0,AG21/AF21) -> 3.9714286 | AJ21: =IF(AG21=0,0,(AG21-AH21)/AG21) -> 0.0079572705 | AK21: =I21+P21+W21+AD21 -> 138 | AL21: =J21+Q21+X21+AE21 -> 6 | AM21: =((I21*K21)+(P21*R21)+(W21*Y21)+(AD21*AF21))/AK21 -> 1142 | AN21: =(($I21*L21)+($P21*S21)+($W21*Z21)+($AD21*AG21))/$AK21 -> 3702.2609 | AO21: =(($I21*M21)+($P21*T21)+($W21*AA21)+($AD21*AH21))/$AK21 -> 3673.087 | AP21: =IF(AM21=0,0,AN21/AM21) -> 3.2419097 | AQ21: =IF(AN21=0,0,(AN21-AO21)/AN21) -> 0.0078800263
C22: Company1629 | D22: 2260 Ringling | E22: Downtown Sarasota | F22: 2020 | G22: =AK22 -> 222 | H22: =1-(AL22/AK22) -> 0.93243243 | I22: 13 | J22: 2 | K22: 645 | L22: 1960 | M22: 1946 | N22: =IF(K22=0,0,L22/K22) -> 3.0387597 | O22: =IF(L22=0,0,(L22-M22)/L22) -> 0.0071428571 | P22: 70 | Q22: 7 | R22: 815 | S22: 2156 | T22: 2141 | U22: =IF(R22=0,0,S22/R22) -> 2.6453988 | V22: =IF(S22=0,0,(S22-T22)/S22) -> 0.0069573284 | W22: 117 | X22: 5 | Y22: 1019 | Z22: 2603 | AA22: 2585 | AB22: =IF(Y22=0,0,Z22/Y22) -> 2.5544652 | AC22: =IF(Z22=0,0,(Z22-AA22)/Z22) -> 0.006915098 | AD22: 22 | AE22: 1 | AF22: 1341 | AG22: 3098 | AH22: 3077 | AI22: =IF(AF22=0,0,AG22/AF22) -> 2.3102163 | AJ22: =IF(AG22=0,0,(AG22-AH22)/AG22) -> 0.0067785668 | AK22: =I22+P22+W22+AD22 -> 222 | AL22: =J22+Q22+X22+AE22 -> 15 | AM22: =((I22*K22)+(P22*R22)+(W22*Y22)+(AD22*AF22))/AK22 -> 964.68468 | AN22: =(($I22*L22)+($P22*S22)+($W22*Z22)+($AD22*AG22))/$AK22 -> 2473.455 | AO22: =(($I22*M22)+($P22*T22)+($W22*AA22)+($AD22*AH22))/$AK22 -> 2456.3378 | AP22: =IF(AM22=0,0,AN22/AM22) -> 2.5640035 | AQ22: =IF(AN22=0,0,(AN22-AO22)/AN22) -> 0.006920327
C23: Avg. | G23: =AK23 -> 196.08333 | I23: =AVERAGE(I16,I17,I18,I19,I22) -> 21.8 | J23: =AVERAGE(J16,J17,J18,J19,J22) -> 2.2 | K23: =AVERAGE(K16,K17,K18,K19,K22) -> 617.4 | L23: =AVERAGE(L16,L17,L18,L19,L22) -> 2046.8 | M23: =AVERAGE(M16,M17,M18,M19,M22) -> 2019.4 | N23: =IF(K23=0,0,L23/K23) -> 3.3151927 | O23: =IF(L23=0,0,(L23-M23)/L23) -> 0.01338675 | P23: =AVERAGE(P11:P22) -> 81.583333 | Q23: =AVERAGE(Q11:Q22) -> 6.6666667 | R23: =AVERAGE(R11:R22) -> 800.41667 | S23: =AVERAGE(S11:S22) -> 2315 | T23: =AVERAGE(T11:T22) -> 2291.9167 | U23: =IF(R23=0,0,S23/R23) -> 2.8922436 | V23: =IF(S23=0,0,(S23-T23)/S23) -> 0.0099712023 | W23: =AVERAGE(W11:W22) -> 93.916667 | X23: =AVERAGE(X11:X22) -> 7.4166667 | Y23: =AVERAGE(Y11:Y22) -> 1169.5 | Z23: =AVERAGE(Z11:Z22) -> 3000.3333 | AA23: =AVERAGE(AA11:AA22) -> 2974.0833 | AB23: =IF(Y23=0,0,Z23/Y23) -> 2.5654838 | AC23: =IF(Z23=0,0,(Z23-AA23)/Z23) -> 0.0087490279 | AD23: =AVERAGE(AD11,AD12,AD13,AD15,AD18,AD19,AD20,AD21,AD22) -> 15.333333 | AE23: =AVERAGE(AE11,AE12,AE13,AE15,AE18,AE19,AE20,AE21,AE22) -> 1.5555556 | AF23: =AVERAGE(AF11,AF12,AF13,AF15,AF18,AF19,AF20,AF21,AF22) -> 1565.3333 | AG23: =AVERAGE(AG11,AG12,AG13,AG15,AG18,AG19,AG20,AG21,AG22) -> 4397.8889 | AH23: =AVERAGE(AH11,AH12,AH13,AH15,AH18,AH19,AH20,AH21,AH22) -> 4363.1111 | AI23: =IF(AF23=0,0,AG23/AF23) -> 2.8095542 | AJ23: =IF(AG23=0,0,(AG23-AH23)/AG23) -> 0.0079078346 | AK23: =AVERAGE(AK11:AK22) -> 196.08333 | AL23: =AVERAGE(AL11:AL22) -> 16.166667 | AM23: =AVERAGE(AM11:AM22) -> 1011.2069 | AN23: =AVERAGE(AN11:AN22) -> 2737.9589 | AO23: =AVERAGE(AO11:AO22) -> 2712.6918 | AP23: =IF(AM23=0,0,AN23/AM23) -> 2.7076149 | AQ23: =IF(AN23=0,0,(AN23-AO23)/AN23) -> 0.009228446

Sheet DSCR
B1: Multifamily Investment Real Estate Income Analysis
B2: The Sapphire,
B3: Apartment Sq. Ft. | C3: ='Unit Mix'!D7*'Unit Mix'!C7 -> 72932 | D3: BORROWER | G3: APPRAISER | K3: LENDER - Stabil (Yr. 4) | P3: .
B4: Apartment # Units | C4: ='Unit Mix'!C7 -> 61 | D4: Yr. 1 Untrended current rate | M4: Untrended current rate (Loan less Guar) | N4: Untrended future rate (Loan less Guar) | O4: Yr. 1 Untrended future rate | Q4: Breakeven Occupancy (Amort) | R4: Breakeven Rent (Amort)
B5: Loan Funding
B6: Loan Balance
B7: Perm Rate | D7: =D64 -> 0.03 | E7: =C47 -> 0.0832126 | G7: =E7 -> 0.0832126 | I7: 0.0832 | K7: =E7 -> 0.0832126 | M7: =M64 -> 0.055 | N7: =N64 -> 0.0775261 | O7: =O64 -> 0.0775261 | Q7: =Q64 -> 0 | R7: =R64 -> 0
B8: Amortization | D8: 30 | E8: 30 | G8: 30 | I8: 25 | K8: 30 | M8: =K8 -> 30 | N8: =K8 -> 30 | O8: 30 | Q8: =K8 -> 30 | R8: =K8 -> 30
B9: Debt Service
B10: Amortizing | D10: =-PMT(D7/12,D8*12,D6,0)*12 -> 0 | E10: =-PMT(E7/12,E8*12,E6,0)*12 -> 0 | G10: =-PMT(G7/12,G8*12,G6,0)*12 -> 0 | I10: =-PMT(I7/12,I8*12,I6,0)*12 -> 0 | K10: =-PMT(K7/12,K8*12,K6,0)*12 -> 0 | M10: =-PMT(M7/12,M8*12,M6,0)*12 -> 0 | N10: =-PMT(N7/12,N8*12,N6,0)*12 -> 0 | O10: =-PMT(O7/12,O8*12,O6,0)*12 -> 0 | Q10: =-PMT(Q7/12,Q8*12,Q6,0)*12 -> 0 | R10: =-PMT(R7/12,R8*12,R6,0)*12 -> 0
B11: I/O | D11: =D6*D7*365/360 -> 0 | E11: =E6*E7*365/360 -> 0 | G11: =G6*G7*365/360 -> 0 | I11: =I6*I7*365/360 -> 0 | K11: =K6*K7*365/360 -> 0 | M11: =M6*M7*365/360 -> 0 | N11: =N6*N7*365/360 -> 0 | O11: =O6*O7*365/360 -> 0 | Q11: =Q6*Q7*365/360 -> 0 | R11: =R6*R7*365/360 -> 0
B12: Units - Total | D12: ='Unit Mix'!$C$7 -> 61 | E12: ='Unit Mix'!$C$7 -> 61 | G12: ='Unit Mix'!$C$7 -> 61 | I12: ='Unit Mix'!$C$7 -> 61 | K12: ='Unit Mix'!$C$7 -> 61 | M12: ='Unit Mix'!$C$34 -> 61 | N12: ='Unit Mix'!$C$34 -> 61 | O12: ='Unit Mix'!$C$34 -> 61 | Q12: =$K$12 -> 61 | R12: =$K$12 -> 61
B13: Units - Occupied | D13: =ROUNDDOWN(D12*D17,0) -> 57 | E13: =ROUNDDOWN(E12*E17,0) -> 57 | G13: =ROUNDDOWN(G12*G17,0) -> 57 | I13: =ROUNDDOWN(I12*I17,0) -> 57 | K13: =ROUNDDOWN(K12*K17,0) -> 57 | M13: =ROUNDDOWN(M12*M17,0) -> 57 | N13: =ROUNDDOWN(N12*N17,0) -> 57 | O13: =ROUNDDOWN(O12*O17,0) -> 57 | Q13: =ROUNDDOWN(Q12*Q17,0) -> 57 | R13: =ROUNDDOWN(R12*R17,0) -> 57
B14: Total (SF) | D14: ='Unit Mix'!$D$34*D12 -> 72932 | E14: ='Unit Mix'!$D$34*E12 -> 72932 | G14: ='Unit Mix'!$D$34*G12 -> 72932 | I14: ='Unit Mix'!$D$34*I12 -> 72932 | K14: ='Unit Mix'!$D$34*K12 -> 72932 | M14: ='Unit Mix'!$D$34*M12 -> 72932 | N14: ='Unit Mix'!$D$34*N12 -> 72932 | O14: ='Unit Mix'!$D$34*O12 -> 72932 | Q14: =$K$14 -> 72932 | R14: =$K$14 -> 72932
B15: Occupied (SF) | D15: =ROUNDDOWN(D14*D17,0) -> 68920 | E15: =ROUNDDOWN(E14*E17,0) -> 68920 | G15: =ROUNDDOWN(G14*G17,0) -> 68920 | I15: =ROUNDDOWN(I14*I17,0) -> 68920 | K15: =ROUNDDOWN(K14*K17,0) -> 68920 | M15: =ROUNDDOWN(M14*M17,0) -> 68920 | N15: =ROUNDDOWN(N14*N17,0) -> 68920 | O15: =ROUNDDOWN(O14*O17,0) -> 68920 | Q15: =ROUNDDOWN(Q14*Q17,0) -> 68920 | R15: =ROUNDDOWN(R14*R17,0) -> 68920
B17: Occupancy | D17: 0.945 | E17: 0.945 | G17: 0.945 | I17: 0.945 | K17: =E17 -> 0.945 | M17: =1-$C$26 -> 0.945 | N17: =1-$C$26 -> 0.945 | O17: =1-$C$26 -> 0.945 | Q17: 0.945 | R17: =+K17 -> 0.945
B18: Apartment Rent PSF | C18: 0.04 | D18: =7586280/245968/12 -> 2.5702124 | E18: =(E19*C4)/C3 -> 3.2340264 | G18: =7586280/C3/12 -> 8.6682115 | I18: =8360137/C3/12 -> 9.5524335 | K18: ='Unit Mix'!F7 -> 2.7500686 | M18: =K18 -> 2.7500686 | N18: =K18 -> 2.7500686 | O18: =K18 -> 2.7500686 | Q18: =#REF! -> #REF! | R18: 2.9476919
B19: Apt. Rent /Unit (info) | D19: =7586280/180/12 -> 3512.1667 | E19: =8351906/180/12 -> 3866.6231 | G19: =(G18*$C$3)/$C$4 -> 10363.77 | I19: =(I18*$C$3)/$C$4 -> 11420.952 | K19: =(K18*$C$3)/$C$4 -> 3288 | M19: =(M18*$C$3)/$C$4 -> 3288 | N19: =(N18*$C$3)/$C$4 -> 3288 | O19: =(O18*$C$3)/$C$4 -> 3288 | Q19: =(Q18*$C$3)/$C$4 -> #REF! | R19: =(R18*$C$3)/$C$4 -> 3524.2797
B20: Income | D20: Total | E20: Total | F20: $/Unit/Mo | G20: Total | H20: $/Unit/Mo | I20: Total | J20: $/Unit/Mo | K20: Total | L20: $/Unit/Mo | M20: Total | N20: Total | O20: Total
B21: Multifamily Potential Rent | J21: =+I21/$K$12/12 -> 0 | K21: ='Unit Mix'!G7 -> 2499729.3 | L21: =+K21/$K$12/12 -> 3414.9308 | M21: =K21 -> 2499729.3 | N21: =K21 -> 2499729.3 | O21: =K21 -> 2499729.3 | Q21: =(Q18*12)*Q14 -> #REF! | R21: =(R18*12)*R14 -> 2579772.7
B22: Parking Income | J22: =+I22/$K$12/12 -> 0 | K22: =D22 -> 0 | L22: =+K22/$K$12/12 -> 0 | M22: =K22 -> 0 | N22: =K22 -> 0 | O22: =K22 -> 0 | Q22: =$K$22 -> 0 | R22: =$K$22 -> 0
B23: Premium Income | J23: =+I23/$K$12/12 -> 0 | K23: =D23 -> 0 | L23: =+K23/$K$12/12 -> 0 | M23: =K23 -> 0 | N23: =K23 -> 0 | O23: =K23 -> 0 | Q23: =$K$23 -> 0 | R23: =$K$23 -> 0
B24: Misc/Other Income | J24: =+I24/$K$12/12 -> 0 | K24: =E24 -> 0 | L24: =+K24/$K$12/12 -> 0 | M24: =K24*((1+$C$18)^($Y$9-1)) -> 0 | N24: =K24*((1+$C$18)^($Y$9-1)) -> 0 | O24: =K24 -> 0 | Q24: =$K$24 -> 0 | R24: =$K$24 -> 0
B25: Gross Income | J25: =+I25/$K$12/12 -> 0 | K25: =SUM(K21:K24) -> 2499729.3 | L25: =+K25/$K$12/12 -> 3414.9308 | M25: =SUM(M21:M24) -> 2499729.3 | N25: =SUM(N21:N24) -> 2499729.3 | O25: =SUM(O21:O24) -> 2499729.3 | Q25: =SUM(Q21:Q24) -> #REF! | R25: =SUM(R21:R24) -> 2579772.7
B26: Vacancy & Bad Debt Loss | C26: 0.055 | J26: =+I26/$K$12/12 -> 0 | K26: =-K25*(1-K17) -> -137485.11 | L26: =+K26/$K$12/12 -> -187.82119 | M26: =-M25*(1-M17) -> -137485.11 | N26: =-N25*(1-N17) -> -137485.11 | O26: =-O25*(1-O17) -> -137485.11 | Q26: =-Q25*(1-Q17) -> #REF! | R26: =-R25*(1-R17) -> -141887.5
B27: Effective Gross Income | D27: =SUM(D25:D26) -> 0 | E27: =SUM(E25:E26) -> 0 | F27: =SUM(F25:F26) -> 0 | G27: =SUM(G25:G26) -> 0 | H27: =SUM(H25:H26) -> 0 | I27: =SUM(I25:I26) -> 0 | J27: =SUM(J25:J26) -> 0 | K27: =SUM(K25:K26) -> 2362244.2 | ... O27: =SUM(O25:O26) -> 2362244.2 | Q27: =SUM(Q25:Q26) -> #REF! | R27: =SUM(R25:R26) -> 2437885.2
B28: Operating Expenses | D28: Total | E28: Total | F28: $/Unit/Mo | G28: Total | H28: $/Unit/Mo | I28: Total | J28: $/Unit/Mo | K28: Total | L28: $/Unit/Mo | M28: Total | N28: Total | O28: Total
B29: Real Estate Taxes | L29: =K29/$K$12 -> 0 | M29: =K29 -> 0 | N29: =K29 -> 0 | O29: =M29 -> 0 | Q29: =$K$29 -> 0 | R29: =$K$29 -> 0
B30: Property Insurance | L30: =K30/$K$12 -> 0 | M30: =K30 -> 0 | N30: =K30 -> 0 | O30: =M30 -> 0 | Q30: =$K$30 -> 0 | R30: =$K$30 -> 0
B31: Utilities | L31: =K31/$K$12 -> 0 | M31: =K31 -> 0 | N31: =K31 -> 0 | O31: =M31 -> 0 | Q31: =$K$31 -> 0 | R31: =$K$31 -> 0
B32: R&M | L32: =K32/$K$12 -> 0 | M32: =K32 -> 0 | N32: =K32 -> 0 | O32: =M32 -> 0 | Q32: =$K$32 -> 0 | R32: =$K$32 -> 0
B33: Management Fee | L33: 0.0275 | M33: =#REF!*M27 -> #REF! | N33: =#REF!*N27 -> #REF! | O33: =#REF!*O27 -> #REF! | Q33: =+#REF!*Q27 -> #REF! | R33: =+#REF!*R27 -> #REF!
B34: Payroll & Benefits | L34: =K34/$K$12 -> 0 | M34: =K34 -> 0 | N34: =K34 -> 0 | O34: =M34 -> 0 | Q34: =$K$34 -> 0 | R34: =$K$34 -> 0
B35: Rental Expense | L35: =K35/$K$12 -> 0 | M35: =K35 -> 0 | N35: =K35 -> 0 | O35: =M35 -> 0 | Q35: =$K$35 -> 0 | R35: =$K$35 -> 0
B36: General & Adm. | L36: =K36/$K$12 -> 0 | M36: =K36 -> 0 | N36: =K36 -> 0 | O36: =M36 -> 0 | Q36: =$K$36 -> 0 | R36: =$K$36 -> 0
B37: HOA | L37: =K37/$K$12 -> 0 | M37: =K37 -> 0 | N37: =K37 -> 0 | O37: =M37 -> 0 | Q37: =$K$37 -> 0 | R37: =$K$37 -> 0
B38: Ground Lease | D38: 0 | E38: 0 | F38: =+E38/$E$12 -> 0 | G38: 0 | H38: =G38/$K$12 -> 0 | I38: 0 | J38: =I38/$K$12 -> 0 | K38: =D38 -> 0 | L38: =K38/$K$12 -> 0 | M38: =K38 -> 0 | N38: =K38 -> 0 | O38: =M38 -> 0 | Q38: =$K$38 -> 0 | R38: =$K$38 -> 0
B39: Total Operating Expenses | D39: =SUM(D29:D38) -> 0 | E39: =SUM(E29:E38) -> 0 | F39: =E39/$C$4 -> 0 | G39: =SUM(G29:G38) -> 0 | H39: =G39/$C$4 -> 0 | I39: =SUM(I29:I38) -> 0 | J39: =I39/$C$4 -> 0 | K39: =SUM(K29:K38) -> 0 | L39: =K39/$C$4 -> 0 | M39: =SUM(M29:M38) -> #REF! | N39: =SUM(N29:N38) -> #REF! | O39: =SUM(O29:O38) -> #REF! | Q39: =SUM(Q29:Q38) -> #REF! | R39: =SUM(R29:R38) -> #REF!
B40: OpEx % of Company0843 (excl. ground lease) | D40: =(D39-D38)/D27 -> #DIV/0! | E40: =(E39-E38)/E27 -> #DIV/0! | F40: =(F39-F38)/F27 -> #DIV/0! | G40: =(G39-G38)/G27 -> #DIV/0! | H40: =(H39-H38)/H27 -> #DIV/0! | I40: =(I39-I38)/I27 -> #DIV/0! | J40: =(J39-J38)/J27 -> #DIV/0! | K40: =(K39-K38)/K27 -> 0 | ... O40: =(O39-O38)/O27 -> #REF! | Q40: =+Q39/Q27 -> #REF! | R40: =+R39/R27 -> #REF!
B41: Net Operating Income | D41: =D27-D39 -> 0 | E41: =E27-E39 -> 0 | G41: =G27-G39 -> 0 | K41: =K27-K39 -> 2362244.2 | M41: =M27-M39 -> #REF! | N41: =N27-N39 -> #REF! | O41: =O27-O39 -> #REF! | Q41: =Q27-Q39 -> #REF! | R41: =R27-R39 -> #REF!
B42: Less: Replacement Rsv | J42: 250 | K42: =250*K12 -> 15250 | L42: 250 | M42: =250*M12 -> 15250 | N42: =250*N12 -> 15250 | O42: =250*O12 -> 15250 | Q42: =M42 -> 15250 | R42: =M42 -> 15250
B43: Net Cash Flow | D43: =+D41-D42 -> 0 | E43: =+E41-E42 -> 0 | G43: =+G41-G42 -> 0 | I43: =+I41-I42 -> 0 | K43: =+K41-K42 -> 2346994.2 | M43: =+M41-M42 -> #REF! | N43: =+N41-N42 -> #REF! | O43: =+O41-O42 -> #REF! | Q43: =+Q41-Q42 -> #REF! | R43: =+R41-R42 -> #REF!
B44: Cash Flow After DS | C44: I/O | D44: =IF($C$44="I/O",D43-D11,D43-D10) -> 0 | E44: =IF($C$44="I/O",E43-E11,E43-E10) -> 0 | G44: =IF($C$44="I/O",G43-G11,G43-G10) -> 0 | I44: =IF($C$44="I/O",I43-I11,I43-I10) -> 0 | K44: =IF($C$44="I/O",K43-K11,K43-K10) -> 2346994.2 | M44: =IF($C$44="I/O",M43-M11,M43-M10) -> #REF! | N44: =IF($C$44="I/O",N43-N11,N43-N10) -> #REF! | O44: =IF($C$44="I/O",O43-O11,O43-O10) -> #REF! | Q44: =IF($C$44="I/O",Q43-Q11,Q43-Q10) -> #REF! | R44: =IF($C$44="I/O",R43-R11,R43-R10) -> #REF!
B45: Debt Yield | D45: =D41/D6 -> #DIV/0! | E45: =E41/E6 -> #DIV/0! | G45: =G41/G6 -> #DIV/0! | I45: =I41/I6 -> #DIV/0! | K45: =K41/K6 -> #DIV/0! | M45: =M41/M6 -> #REF! | N45: =N41/N6 -> #REF! | O45: =O41/O6 -> #REF! | Q45: =Q41/Q6 -> #REF! | R45: =R41/R6 -> #REF!
B46: DSCR MATRIX
B47: I/O @ Note Rate | C47: =C60+3% -> 0.0832126 | D47: =D41/D11 -> #DIV/0! | E47: =E41/E11 -> #DIV/0! | G47: =G41/G11 -> #DIV/0! | I47: =I41/I11 -> #DIV/0! | K47: =K41/K11 -> #DIV/0! | M47: =M41/M11 -> #REF! | N47: =N41/N11 -> #REF! | O47: =O41/O11 -> #REF! | Q47: =Q41/Q11 -> #REF! | R47: =R41/R11 -> #REF!
B48: Amortizing @ Note Rate | C48: =+C47 -> 0.0832126 | D48: =D41/D10 -> #DIV/0! | E48: =E41/E10 -> #DIV/0! | G48: =G41/G10 -> #DIV/0! | I48: =I41/I10 -> #DIV/0! | K48: =K41/K10 -> #DIV/0! | M48: =M41/M10 -> #REF! | N48: =N41/N10 -> #REF! | O48: =O41/O10 -> #REF! | Q48: =Q41/Q10 -> #REF! | R48: =R41/R10 -> #REF!
B49: Conduit: 10yr T + 200 (30yr) | C49: =4.22%+2% -> 0.0622 | D49: =D$41/(-PMT($C49/12,360,D$6,0)*12) -> #DIV/0! | E49: =E$41/(-PMT($C49/12,360,E$6,0)*12) -> #DIV/0! | G49: =G$41/(-PMT($C49/12,360,G$6,0)*12) -> #DIV/0! | I49: =I$41/(-PMT($C49/12,360,I$6,0)*12) -> #DIV/0! | K49: =K$41/(-PMT($C49/12,360,K$6,0)*12) -> #DIV/0! | M49: =M$41/(-PMT($C49/12,360,M$6,0)*12) -> #REF! | N49: =N$41/(-PMT($C49/12,360,N$6,0)*12) -> #REF! | O49: =O$41/(-PMT($C49/12,360,O$6,0)*12) -> #REF! | Q49: =Q$41/(-PMT($C49/12,360,Q$6,0)*12) -> #REF! | R49: =R$41/(-PMT($C49/12,360,R$6,0)*12) -> #REF!
B50: Agency: 10yr T+ 100 (35 yr) | C50: =4.22%+1% -> 0.0522 | D50: =D$41/(-PMT($C50/12,420,D$6,0)*12) -> #DIV/0! | E50: =E$41/(-PMT($C50/12,420,E$6,0)*12) -> #DIV/0! | G50: =G$41/(-PMT($C50/12,420,G$6,0)*12) -> #DIV/0! | I50: =I$41/(-PMT($C50/12,420,I$6,0)*12) -> #DIV/0! | K50: =K$41/(-PMT($C50/12,420,K$6,0)*12) -> #DIV/0! | M50: =M$41/(-PMT($C50/12,420,M$6,0)*12) -> #REF! | N50: =N$41/(-PMT($C50/12,420,N$6,0)*12) -> #REF! | O50: =O$41/(-PMT($C50/12,420,O$6,0)*12) -> #REF! | Q50: =Q$41/(-PMT($C50/12,420,Q$6,0)*12) -> #REF! | R50: =R$41/(-PMT($C50/12,420,R$6,0)*12) -> #REF!
B51: Stressed: 10yr T + 350 (30 yr) | C51: =4.22%+3.5% -> 0.0772 | D51: =D$41/(-PMT($C51/12,D$8*12,D$6,0)*12) -> #DIV/0! | E51: =E$41/(-PMT($C51/12,E$8*12,E$6,0)*12) -> #DIV/0! | G51: =G$41/(-PMT($C51/12,G$8*12,G$6,0)*12) -> #DIV/0! | I51: =I$41/(-PMT($C51/12,I$8*12,I$6,0)*12) -> #DIV/0! | K51: =K$41/(-PMT($C51/12,K$8*12,K$6,0)*12) -> #DIV/0! | M51: =M$41/(-PMT($C51/12,M$8*12,M$6,0)*12) -> #REF! | N51: =N$41/(-PMT($C51/12,N$8*12,N$6,0)*12) -> #REF! | O51: =O$41/(-PMT($C51/12,O$8*12,O$6,0)*12) -> #REF! | Q51: =Q$41/(-PMT($C51/12,Q$8*12,Q$6,0)*12) -> #REF! | R51: =R$41/(-PMT($C51/12,R$8*12,R$6,0)*12) -> #REF!
B52: VALUATION
B53: Cap Rate (3/24 apprs 5.75%) | D53: 0.0575 | E53: 0.0575 | G53: 0.0575 | I53: 0.0575 | K53: 0.0575 | M53: 0.055 | N53: 0.055 | O53: 0.055 | Q53: 0.055 | R53: 0.055
B54: Est. Value | D54: =D41/D53 -> 0 | E54: =E41/E53 -> 0 | G54: =G41/G53 -> 0 | I54: =I41/I53 -> 0 | K54: =K41/K53 -> 41082508 | M54: =M41/M53 -> #REF! | N54: =N41/N53 -> #REF! | O54: =O41/O53 -> #REF! | Q54: =Q41/Q53 -> #REF! | R54: =R41/R53 -> #REF!
B55: Est. Loan-to-Value | D55: =D6/D54 -> #DIV/0! | E55: =E6/E54 -> #DIV/0! | G55: =G6/G54 -> #DIV/0! | I55: =I6/I54 -> #DIV/0! | K55: =K6/K54 -> 0 | M55: =M6/M54 -> #REF! | N55: =N6/N54 -> #REF! | O55: =O6/O54 -> #REF! | Q55: =Q6/Q54 -> #REF! | R55: =R6/R54 -> #REF!
B56: Loan Per Unit | D56: =D6/D12 -> 0 | E56: =E6/E12 -> 0 | G56: =G6/G12 -> 0 | I56: =I6/I12 -> 0 | K56: =K6/K12 -> 0 | M56: =M6/M12 -> 0 | N56: =N6/N12 -> 0 | O56: =O6/O12 -> 0 | Q56: =Q6/(Q12+#REF!) -> #REF! | R56: =R6/(R12+#REF!) -> #REF!
B57: Value Per Unit | D57: =D54/D12 -> 0 | E57: =E54/E12 -> 0 | G57: =G54/G12 -> 0 | I57: =I54/I12 -> 0 | K57: =K54/K12 -> 673483.74 | M57: =M54/M12 -> #REF! | N57: =N54/N12 -> #REF! | O57: =O54/O12 -> #REF! | Q57: =Q54/(Q12+#REF!) -> #REF! | R57: =R54/(R12+#REF!) -> #REF!
B58: RATE
B59: Rate Description | D59: Current Rate | E59: Current Rate | G59: Current Rate | I59: Current Rate | K59: Current Rate | M59: Current | N59: 48 ms SOFR | O59: 48 ms SOFR
B60: Index - 3/4/24 | C60: 0.0532126 | M60: =K60 -> 0 | N60: =Draws!AS33 -> 0.0375261 | O60: =N60 -> 0.0375261
B61: Spread | C61: 0.03 | D61: =C61 -> 0.03 | E61: =$C$61 -> 0.03 | G61: =$C$61 -> 0.03 | I61: =$C$61 -> 0.03 | K61: =$C$61 -> 0.03 | M61: =$C$61 -> 0.03 | N61: =$C$61 -> 0.03 | O61: =$C$61 -> 0.03
B62: Risk Premium | C62: 0.01 | D62: 0 | E62: 0 | G62: 0 | I62: 0 | K62: 0 | M62: 0 | N62: 0.01 | O62: 0.01
B63: Floor | C63: 0.055 | M63: =$C$63 -> 0.055 | N63: =$C$63 -> 0.055 | O63: =$C$63 -> 0.055
B64: Rate | D64: =MAX(D63,D60+D61+D62) -> 0.03 | E64: =MAX(E63,E60+E61+E62) -> 0.03 | G64: =MAX(G63,G60+G61+G62) -> 0.03 | I64: =MAX(I63,I60+I61+I62) -> 0.03 | K64: =MAX(K63,K60+K61+K62) -> 0.03 | M64: =MAX(M63,M60+M61+M62) -> 0.055 | N64: =MAX(N63,N60+N61+N62) -> 0.0775261 | O64: =MAX(O63,O60+O61+O62) -> 0.0775261 | Q64: =MAX(Q60+Q61,Q63) -> 0 | R64: =MAX(R60+R61,R63) -> 0
K65: =K41/(PMT(K64/12*(365/360),(25*12),-K6)*12) -> #DIV/0!

Sheet Property
B59: NORTH PLAN
B102: SOUTH PLAN
B159: LOT PLAN

Sheet Mortgage-50% LTC
B1: Mortgageability Gap - Untrended Rents - Forward SOFR
B2: Interest Rate and DSCR Sensitivity
A3: NOI: | C3: =#REF! -> #REF!
A4: Loan Amount: | C4: =+#REF! -> #REF!
A5: Amortization: | C5: =+#REF!*12 -> #REF!
C6: Interest Rate
F7: Note Rate
C8: =+D8-0.005 -> #REF! | D8: =+E8-0.005 -> #REF! | E8: =+F8-0.005 -> #REF! | F8: =#REF! -> #REF! | G8: =+F8+0.005 -> #REF! | H8: =+G8+0.005 -> #REF! | I8: =+H8+0.005 -> #REF! | J8: =+I8+0.005 -> #REF!
B9: 1 | C9: =$C$3/B9/(PMT($C$8/12,$C$5,1)*-12)-$C$4 -> #REF! | D9: =$C$3/B9/(PMT($D$8/12,$C$5,1)*-12)-$C$4 -> #REF! | E9: =$C$3/B9/(PMT($E$8/12,$C$5,1)*-12)-$C$4 -> #REF! | F9: =$C$3/B9/(PMT($F$8/12,$C$5,1)*-12)-$C$4 -> #REF! | G9: =$C$3/B9/(PMT($G$8/12,$C$5,1)*-12)-$C$4 -> #REF! | H9: =$C$3/B9/(PMT($H$8/12,$C$5,1)*-12)-$C$4 -> #REF! | I9: =$C$3/B9/(PMT($I$8/12,$C$5,1)*-12)-$C$4 -> #REF! | J9: =$C$3/B9/(PMT($J$8/12,$C$5,1)*-12)-$C$4 -> #REF!
B10: =+B9+0.05 -> 1.05 | C10: =$C$3/B10/(PMT($C$8/12,$C$5,1)*-12)-$C$4 -> #REF! | D10: =$C$3/B10/(PMT($D$8/12,$C$5,1)*-12)-$C$4 -> #REF! | E10: =$C$3/B10/(PMT($E$8/12,$C$5,1)*-12)-$C$4 -> #REF! | F10: =$C$3/B10/(PMT($F$8/12,$C$5,1)*-12)-$C$4 -> #REF! | G10: =$C$3/B10/(PMT($G$8/12,$C$5,1)*-12)-$C$4 -> #REF! | H10: =$C$3/B10/(PMT($H$8/12,$C$5,1)*-12)-$C$4 -> #REF! | I10: =$C$3/B10/(PMT($I$8/12,$C$5,1)*-12)-$C$4 -> #REF! | J10: =$C$3/B10/(PMT($J$8/12,$C$5,1)*-12)-$C$4 -> #REF!
A11: R | B11: =+B10+0.05 -> 1.1 | C11: =$C$3/B11/(PMT($C$8/12,$C$5,1)*-12)-$C$4 -> #REF! | D11: =$C$3/B11/(PMT($D$8/12,$C$5,1)*-12)-$C$4 -> #REF! | E11: =$C$3/B11/(PMT($E$8/12,$C$5,1)*-12)-$C$4 -> #REF! | F11: =$C$3/B11/(PMT($F$8/12,$C$5,1)*-12)-$C$4 -> #REF! | G11: =$C$3/B11/(PMT($G$8/12,$C$5,1)*-12)-$C$4 -> #REF! | H11: =$C$3/B11/(PMT($H$8/12,$C$5,1)*-12)-$C$4 -> #REF! | I11: =$C$3/B11/(PMT($I$8/12,$C$5,1)*-12)-$C$4 -> #REF! | J11: =$C$3/B11/(PMT($J$8/12,$C$5,1)*-12)-$C$4 -> #REF!
A12: C | B12: =+B11+0.05 -> 1.15 | C12: =$C$3/B12/(PMT($C$8/12,$C$5,1)*-12)-$C$4 -> #REF! | D12: =$C$3/B12/(PMT($D$8/12,$C$5,1)*-12)-$C$4 -> #REF! | E12: =$C$3/B12/(PMT($E$8/12,$C$5,1)*-12)-$C$4 -> #REF! | F12: =$C$3/B12/(PMT($F$8/12,$C$5,1)*-12)-$C$4 -> #REF! | G12: =$C$3/B12/(PMT($G$8/12,$C$5,1)*-12)-$C$4 -> #REF! | H12: =$C$3/B12/(PMT($H$8/12,$C$5,1)*-12)-$C$4 -> #REF! | I12: =$C$3/B12/(PMT($I$8/12,$C$5,1)*-12)-$C$4 -> #REF! | J12: =$C$3/B12/(PMT($J$8/12,$C$5,1)*-12)-$C$4 -> #REF!
A13: S | B13: =+B12+0.05 -> 1.2 | C13: =$C$3/B13/(PMT($C$8/12,$C$5,1)*-12)-$C$4 -> #REF! | D13: =$C$3/B13/(PMT($D$8/12,$C$5,1)*-12)-$C$4 -> #REF! | E13: =$C$3/B13/(PMT($E$8/12,$C$5,1)*-12)-$C$4 -> #REF! | F13: =$C$3/B13/(PMT($F$8/12,$C$5,1)*-12)-$C$4 -> #REF! | G13: =$C$3/B13/(PMT($G$8/12,$C$5,1)*-12)-$C$4 -> #REF! | H13: =$C$3/B13/(PMT($H$8/12,$C$5,1)*-12)-$C$4 -> #REF! | I13: =$C$3/B13/(PMT($I$8/12,$C$5,1)*-12)-$C$4 -> #REF! | J13: =$C$3/B13/(PMT($J$8/12,$C$5,1)*-12)-$C$4 -> #REF!
A14: D | B14: =+B13+0.05 -> 1.25 | C14: =$C$3/B14/(PMT($C$8/12,$C$5,1)*-12)-$C$4 -> #REF! | D14: =$C$3/B14/(PMT($D$8/12,$C$5,1)*-12)-$C$4 -> #REF! | E14: =$C$3/B14/(PMT($E$8/12,$C$5,1)*-12)-$C$4 -> #REF! | F14: =$C$3/B14/(PMT($F$8/12,$C$5,1)*-12)-$C$4 -> #REF! | G14: =$C$3/B14/(PMT($G$8/12,$C$5,1)*-12)-$C$4 -> #REF! | H14: =$C$3/B14/(PMT($H$8/12,$C$5,1)*-12)-$C$4 -> #REF! | I14: =$C$3/B14/(PMT($I$8/12,$C$5,1)*-12)-$C$4 -> #REF! | J14: =$C$3/B14/(PMT($J$8/12,$C$5,1)*-12)-$C$4 -> #REF!
B15: =+B14+0.05 -> 1.3 | C15: =$C$3/B15/(PMT($C$8/12,$C$5,1)*-12)-$C$4 -> #REF! | D15: =$C$3/B15/(PMT($D$8/12,$C$5,1)*-12)-$C$4 -> #REF! | E15: =$C$3/B15/(PMT($E$8/12,$C$5,1)*-12)-$C$4 -> #REF! | F15: =$C$3/B15/(PMT($F$8/12,$C$5,1)*-12)-$C$4 -> #REF! | G15: =$C$3/B15/(PMT($G$8/12,$C$5,1)*-12)-$C$4 -> #REF! | H15: =$C$3/B15/(PMT($H$8/12,$C$5,1)*-12)-$C$4 -> #REF! | I15: =$C$3/B15/(PMT($I$8/12,$C$5,1)*-12)-$C$4 -> #REF! | J15: =$C$3/B15/(PMT($J$8/12,$C$5,1)*-12)-$C$4 -> #REF!
B16: =+B15+0.05 -> 1.35 | C16: =$C$3/B16/(PMT($C$8/12,$C$5,1)*-12)-$C$4 -> #REF! | D16: =$C$3/B16/(PMT($D$8/12,$C$5,1)*-12)-$C$4 -> #REF! | E16: =$C$3/B16/(PMT($E$8/12,$C$5,1)*-12)-$C$4 -> #REF! | F16: =$C$3/B16/(PMT($F$8/12,$C$5,1)*-12)-$C$4 -> #REF! | G16: =$C$3/B16/(PMT($G$8/12,$C$5,1)*-12)-$C$4 -> #REF! | H16: =$C$3/B16/(PMT($H$8/12,$C$5,1)*-12)-$C$4 -> #REF! | I16: =$C$3/B16/(PMT($I$8/12,$C$5,1)*-12)-$C$4 -> #REF! | J16: =$C$3/B16/(PMT($J$8/12,$C$5,1)*-12)-$C$4 -> #REF!
B17: =+B16+0.05 -> 1.4 | C17: =$C$3/B17/(PMT($C$8/12,$C$5,1)*-12)-$C$4 -> #REF! | D17: =$C$3/B17/(PMT($D$8/12,$C$5,1)*-12)-$C$4 -> #REF! | E17: =$C$3/B17/(PMT($E$8/12,$C$5,1)*-12)-$C$4 -> #REF! | F17: =$C$3/B17/(PMT($F$8/12,$C$5,1)*-12)-$C$4 -> #REF! | G17: =$C$3/B17/(PMT($G$8/12,$C$5,1)*-12)-$C$4 -> #REF! | H17: =$C$3/B17/(PMT($H$8/12,$C$5,1)*-12)-$C$4 -> #REF! | I17: =$C$3/B17/(PMT($I$8/12,$C$5,1)*-12)-$C$4 -> #REF! | J17: =$C$3/B17/(PMT($J$8/12,$C$5,1)*-12)-$C$4 -> #REF!
B18: =+B17+0.05 -> 1.45 | C18: =$C$3/B18/(PMT($C$8/12,$C$5,1)*-12)-$C$4 -> #REF! | D18: =$C$3/B18/(PMT($D$8/12,$C$5,1)*-12)-$C$4 -> #REF! | E18: =$C$3/B18/(PMT($E$8/12,$C$5,1)*-12)-$C$4 -> #REF! | F18: =$C$3/B18/(PMT($F$8/12,$C$5,1)*-12)-$C$4 -> #REF! | G18: =$C$3/B18/(PMT($G$8/12,$C$5,1)*-12)-$C$4 -> #REF! | H18: =$C$3/B18/(PMT($H$8/12,$C$5,1)*-12)-$C$4 -> #REF! | I18: =$C$3/B18/(PMT($I$8/12,$C$5,1)*-12)-$C$4 -> #REF! | J18: =$C$3/B18/(PMT($J$8/12,$C$5,1)*-12)-$C$4 -> #REF!
B19: =+B18+0.05 -> 1.5 | C19: =$C$3/B19/(PMT($C$8/12,$C$5,1)*-12)-$C$4 -> #REF! | D19: =$C$3/B19/(PMT($D$8/12,$C$5,1)*-12)-$C$4 -> #REF! | E19: =$C$3/B19/(PMT($E$8/12,$C$5,1)*-12)-$C$4 -> #REF! | F19: =$C$3/B19/(PMT($F$8/12,$C$5,1)*-12)-$C$4 -> #REF! | G19: =$C$3/B19/(PMT($G$8/12,$C$5,1)*-12)-$C$4 -> #REF! | H19: =$C$3/B19/(PMT($H$8/12,$C$5,1)*-12)-$C$4 -> #REF! | I19: =$C$3/B19/(PMT($I$8/12,$C$5,1)*-12)-$C$4 -> #REF! | J19: =$C$3/B19/(PMT($J$8/12,$C$5,1)*-12)-$C$4 -> #REF!
C20: * Loan underwritten at 1.15x DSCR, 30 year amortization and 8.32% rate.
B22: DSCR Sensitivity - Untrended Rents - Forward SOFR
B23: Interest Rate and NOI
A24: NOI: | C24: =+C3 -> #REF!
A25: Loan Amount: | C25: =+C4 -> #REF!
A26: Amortization: | C26: =+C5 -> #REF!
C27: Interest Rate
F28: Note Rate
C29: =+C8 -> #REF! | D29: =+D8 -> #REF! | E29: =+E8 -> #REF! | F29: =F8 -> #REF! | G29: =+G8 -> #REF! | H29: =+H8 -> #REF! | I29: =+I8 -> #REF! | J29: =+J8 -> #REF!
A30: I | B30: =+B31-0.05 -> 0.6 | C30: =($C$24*B30)/(PMT($C$29/12,$C$26,$C$25)*-12) -> #REF! | D30: =($C$24*B30)/(PMT($D$29/12,$C$26,$C$25)*-12) -> #REF! | E30: =($C$24*B30)/(PMT($E$29/12,$C$26,$C$25)*-12) -> #REF! | F30: =($C$24*B30)/(PMT($F$29/12,$C$26,$C$25)*-12) -> #REF! | G30: =($C$24*B30)/(PMT($G$29/12,$C$26,$C$25)*-12) -> #REF! | H30: =($C$24*B30)/(PMT($H$29/12,$C$26,$C$25)*-12) -> #REF! | I30: =($C$24*B30)/(PMT($I$29/12,$C$26,$C$25)*-12) -> #REF! | J30: =($C$24*B30)/(PMT($J$29/12,$C$26,$C$25)*-12) -> #REF!
A31: O | B31: =+B32-0.05 -> 0.65 | C31: =($C$24*B31)/(PMT($C$29/12,$C$26,$C$25)*-12) -> #REF! | D31: =($C$24*B31)/(PMT($D$29/12,$C$26,$C$25)*-12) -> #REF! | E31: =($C$24*B31)/(PMT($E$29/12,$C$26,$C$25)*-12) -> #REF! | F31: =($C$24*B31)/(PMT($F$29/12,$C$26,$C$25)*-12) -> #REF! | G31: =($C$24*B31)/(PMT($G$29/12,$C$26,$C$25)*-12) -> #REF! | H31: =($C$24*B31)/(PMT($H$29/12,$C$26,$C$25)*-12) -> #REF! | I31: =($C$24*B31)/(PMT($I$29/12,$C$26,$C$25)*-12) -> #REF! | J31: =($C$24*B31)/(PMT($J$29/12,$C$26,$C$25)*-12) -> #REF!
A32: N | B32: =+B33-0.05 -> 0.7 | C32: =($C$24*B32)/(PMT($C$29/12,$C$26,$C$25)*-12) -> #REF! | D32: =($C$24*B32)/(PMT($D$29/12,$C$26,$C$25)*-12) -> #REF! | E32: =($C$24*B32)/(PMT($E$29/12,$C$26,$C$25)*-12) -> #REF! | F32: =($C$24*B32)/(PMT($F$29/12,$C$26,$C$25)*-12) -> #REF! | G32: =($C$24*B32)/(PMT($G$29/12,$C$26,$C$25)*-12) -> #REF! | H32: =($C$24*B32)/(PMT($H$29/12,$C$26,$C$25)*-12) -> #REF! | I32: =($C$24*B32)/(PMT($I$29/12,$C$26,$C$25)*-12) -> #REF! | J32: =($C$24*B32)/(PMT($J$29/12,$C$26,$C$25)*-12) -> #REF!
B33: =+B34-0.05 -> 0.75 | C33: =($C$24*B33)/(PMT($C$29/12,$C$26,$C$25)*-12) -> #REF! | D33: =($C$24*B33)/(PMT($D$29/12,$C$26,$C$25)*-12) -> #REF! | E33: =($C$24*B33)/(PMT($E$29/12,$C$26,$C$25)*-12) -> #REF! | F33: =($C$24*B33)/(PMT($F$29/12,$C$26,$C$25)*-12) -> #REF! | G33: =($C$24*B33)/(PMT($G$29/12,$C$26,$C$25)*-12) -> #REF! | H33: =($C$24*B33)/(PMT($H$29/12,$C$26,$C$25)*-12) -> #REF! | I33: =($C$24*B33)/(PMT($I$29/12,$C$26,$C$25)*-12) -> #REF! | J33: =($C$24*B33)/(PMT($J$29/12,$C$26,$C$25)*-12) -> #REF!
A34: E | B34: =+B35-0.05 -> 0.8 | C34: =($C$24*B34)/(PMT($C$29/12,$C$26,$C$25)*-12) -> #REF! | D34: =($C$24*B34)/(PMT($D$29/12,$C$26,$C$25)*-12) -> #REF! | E34: =($C$24*B34)/(PMT($E$29/12,$C$26,$C$25)*-12) -> #REF! | F34: =($C$24*B34)/(PMT($F$29/12,$C$26,$C$25)*-12) -> #REF! | G34: =($C$24*B34)/(PMT($G$29/12,$C$26,$C$25)*-12) -> #REF! | H34: =($C$24*B34)/(PMT($H$29/12,$C$26,$C$25)*-12) -> #REF! | I34: =($C$24*B34)/(PMT($I$29/12,$C$26,$C$25)*-12) -> #REF! | J34: =($C$24*B34)/(PMT($J$29/12,$C$26,$C$25)*-12) -> #REF!
A35: G | B35: =+B36-0.05 -> 0.85 | C35: =($C$24*B35)/(PMT($C$29/12,$C$26,$C$25)*-12) -> #REF! | D35: =($C$24*B35)/(PMT($D$29/12,$C$26,$C$25)*-12) -> #REF! | E35: =($C$24*B35)/(PMT($E$29/12,$C$26,$C$25)*-12) -> #REF! | F35: =($C$24*B35)/(PMT($F$29/12,$C$26,$C$25)*-12) -> #REF! | G35: =($C$24*B35)/(PMT($G$29/12,$C$26,$C$25)*-12) -> #REF! | H35: =($C$24*B35)/(PMT($H$29/12,$C$26,$C$25)*-12) -> #REF! | I35: =($C$24*B35)/(PMT($I$29/12,$C$26,$C$25)*-12) -> #REF! | J35: =($C$24*B35)/(PMT($J$29/12,$C$26,$C$25)*-12) -> #REF!
A36: A | B36: =+B37-0.05 -> 0.9 | C36: =($C$24*B36)/(PMT($C$29/12,$C$26,$C$25)*-12) -> #REF! | D36: =($C$24*B36)/(PMT($D$29/12,$C$26,$C$25)*-12) -> #REF! | E36: =($C$24*B36)/(PMT($E$29/12,$C$26,$C$25)*-12) -> #REF! | F36: =($C$24*B36)/(PMT($F$29/12,$C$26,$C$25)*-12) -> #REF! | G36: =($C$24*B36)/(PMT($G$29/12,$C$26,$C$25)*-12) -> #REF! | H36: =($C$24*B36)/(PMT($H$29/12,$C$26,$C$25)*-12) -> #REF! | I36: =($C$24*B36)/(PMT($I$29/12,$C$26,$C$25)*-12) -> #REF! | J36: =($C$24*B36)/(PMT($J$29/12,$C$26,$C$25)*-12) -> #REF!
A37: % | B37: =+B38-0.05 -> 0.95 | C37: =($C$24*B37)/(PMT($C$29/12,$C$26,$C$25)*-12) -> #REF! | D37: =($C$24*B37)/(PMT($D$29/12,$C$26,$C$25)*-12) -> #REF! | E37: =($C$24*B37)/(PMT($E$29/12,$C$26,$C$25)*-12) -> #REF! | F37: =($C$24*B37)/(PMT($F$29/12,$C$26,$C$25)*-12) -> #REF! | G37: =($C$24*B37)/(PMT($G$29/12,$C$26,$C$25)*-12) -> #REF! | H37: =($C$24*B37)/(PMT($H$29/12,$C$26,$C$25)*-12) -> #REF! | I37: =($C$24*B37)/(PMT($I$29/12,$C$26,$C$25)*-12) -> #REF! | J37: =($C$24*B37)/(PMT($J$29/12,$C$26,$C$25)*-12) -> #REF!
B38: 1 | C38: =($C$24*B38)/(PMT($C$29/12,$C$26,$C$25)*-12) -> #REF! | D38: =($C$24*B38)/(PMT($D$29/12,$C$26,$C$25)*-12) -> #REF! | E38: =($C$24*B38)/(PMT($E$29/12,$C$26,$C$25)*-12) -> #REF! | F38: =($C$24*B38)/(PMT($F$29/12,$C$26,$C$25)*-12) -> #REF! | G38: =($C$24*B38)/(PMT($G$29/12,$C$26,$C$25)*-12) -> #REF! | H38: =($C$24*B38)/(PMT($H$29/12,$C$26,$C$25)*-12) -> #REF! | I38: =($C$24*B38)/(PMT($I$29/12,$C$26,$C$25)*-12) -> #REF! | J38: =($C$24*B38)/(PMT($J$29/12,$C$26,$C$25)*-12) -> #REF!
C39: =+C20 -> * Loan underwritten at 1.15x DSCR, 30 year amortization and 8.32% rate.

Sheet Cap Sens-50% LTC
A1: Loan-to-Value Sensitivity to Capitalization Rates & NOI
B3: Cap Rate | C3: Value at Underwritten NOI | D3: Loan-to-Value
A4: Less 100 bps | B4: =+B5-0.0025 -> #REF! | C4: =+#REF!/'Cap Sens-50% LTC'!B4 -> #REF! | D4: =+#REF!/'Cap Sens-50% LTC'!C4 -> #REF!
A5: Less 75 bps | B5: =+B6-0.0025 -> #REF! | C5: =+#REF!/'Cap Sens-50% LTC'!B5 -> #REF! | D5: =+#REF!/'Cap Sens-50% LTC'!C5 -> #REF!
A6: Less 50 bps | B6: =+B7-0.0025 -> #REF! | C6: =+#REF!/'Cap Sens-50% LTC'!B6 -> #REF! | D6: =+#REF!/'Cap Sens-50% LTC'!C6 -> #REF! | E6: Stabilized
A7: Less 25 bps | B7: =+B8-0.0025 -> #REF! | C7: =+#REF!/'Cap Sens-50% LTC'!B7 -> #REF! | D7: =+#REF!/'Cap Sens-50% LTC'!C7 -> #REF! | E7: Appraised Value | G7: Comments
A8: UW Cap Rate | B8: =#REF! -> #REF! | C8: =+#REF!/'Cap Sens-50% LTC'!B8 -> #REF! | D8: =+#REF!/'Cap Sens-50% LTC'!C8 -> #REF! | E8: 72700000
A9: Plus 25 bps | B9: =+B8+0.0025 -> #REF! | C9: =+#REF!/'Cap Sens-50% LTC'!B9 -> #REF! | D9: =+#REF!/'Cap Sens-50% LTC'!C9 -> #REF!
A10: Plus 50 bps | B10: =+B9+0.0025 -> #REF! | C10: =+#REF!/'Cap Sens-50% LTC'!B10 -> #REF! | D10: =+#REF!/'Cap Sens-50% LTC'!C10 -> #REF!
A11: Plus 75 bps | B11: =+B10+0.0025 -> #REF! | C11: =+#REF!/'Cap Sens-50% LTC'!B11 -> #REF! | D11: =+#REF!/'Cap Sens-50% LTC'!C11 -> #REF!
A12: Plus 100 bps | B12: =+B11+0.0025 -> #REF! | C12: =+#REF!/'Cap Sens-50% LTC'!B12 -> #REF! | D12: =+#REF!/'Cap Sens-50% LTC'!C12 -> #REF!
A13: Plus 125 bps | B13: =+B12+0.0025 -> #REF! | C13: =+#REF!/'Cap Sens-50% LTC'!B13 -> #REF! | D13: =+#REF!/'Cap Sens-50% LTC'!C13 -> #REF!
A14: Plus 150 bps | B14: =+B13+0.0025 -> #REF! | C14: =+#REF!/'Cap Sens-50% LTC'!B14 -> #REF! | D14: =+#REF!/'Cap Sens-50% LTC'!C14 -> #REF!
A15: Plus 175 bps | B15: =+B14+0.0025 -> #REF! | C15: =+#REF!/'Cap Sens-50% LTC'!B15 -> #REF! | D15: =+#REF!/'Cap Sens-50% LTC'!C15 -> #REF!
A16: Plus 200 bps | B16: =+B15+0.0025 -> #REF! | C16: =+#REF!/'Cap Sens-50% LTC'!B16 -> #REF! | D16: =+#REF!/'Cap Sens-50% LTC'!C16 -> #REF!
C19: Positive <----------------------------------------------------------NOI----------------------------------------------------> Negative
G20: Underwritten
C21: =+C22/$G$22 -> #REF! | D21: =+D22/$G$22 -> #REF! | E21: =+E22/$G$22 -> #REF! | F21: =+F22/$G$22 -> #REF! | G21: =+G22/$G$22 -> #REF! | H21: =+H22/$G$22 -> #REF! | I21: =+I22/$G$22 -> #REF! | J21: =+J22/$G$22 -> #REF! | K21: =+K22/$G$22 -> #REF!
C22: =+G22*1.2 -> #REF! | D22: =+G22*1.15 -> #REF! | E22: =+G22*1.1 -> #REF! | F22: =+G22*1.05 -> #REF! | G22: =+#REF! -> #REF! | H22: =+G22*0.95 -> #REF! | I22: =+G22*0.9 -> #REF! | J22: =+G22*0.85 -> #REF! | K22: =+G22*0.8 -> #REF!
A23: Less 100 bps | B23: =+B24-0.0025 -> #REF! | C23: =+#REF!/(C$22/$B23) -> #REF! | D23: =+#REF!/(D$22/$B23) -> #REF! | E23: =+#REF!/(E$22/$B23) -> #REF! | F23: =+#REF!/(F$22/$B23) -> #REF! | G23: =+#REF!/(G$22/$B23) -> #REF! | H23: =+#REF!/(H$22/$B23) -> #REF! | I23: =+#REF!/(I$22/$B23) -> #REF! | J23: =+#REF!/(J$22/$B23) -> #REF! | K23: =+#REF!/(K$22/$B23) -> #REF!
A24: Less 75 bps | B24: =+B25-0.0025 -> #REF! | C24: =+#REF!/(C$22/$B24) -> #REF! | D24: =+#REF!/(D$22/$B24) -> #REF! | E24: =+#REF!/(E$22/$B24) -> #REF! | F24: =+#REF!/(F$22/$B24) -> #REF! | G24: =+#REF!/(G$22/$B24) -> #REF! | H24: =+#REF!/(H$22/$B24) -> #REF! | I24: =+#REF!/(I$22/$B24) -> #REF! | J24: =+#REF!/(J$22/$B24) -> #REF! | K24: =+#REF!/(K$22/$B24) -> #REF!
A25: Less 50 bps | B25: =+B26-0.0025 -> #REF! | C25: =+#REF!/(C$22/$B25) -> #REF! | D25: =+#REF!/(D$22/$B25) -> #REF! | E25: =+#REF!/(E$22/$B25) -> #REF! | F25: =+#REF!/(F$22/$B25) -> #REF! | G25: =+#REF!/(G$22/$B25) -> #REF! | H25: =+#REF!/(H$22/$B25) -> #REF! | I25: =+#REF!/(I$22/$B25) -> #REF! | J25: =+#REF!/(J$22/$B25) -> #REF! | K25: =+#REF!/(K$22/$B25) -> #REF!
A26: Less 25 bps | B26: =+B27-0.0025 -> #REF! | C26: =+#REF!/(C$22/$B26) -> #REF! | D26: =+#REF!/(D$22/$B26) -> #REF! | E26: =+#REF!/(E$22/$B26) -> #REF! | F26: =+#REF!/(F$22/$B26) -> #REF! | G26: =+#REF!/(G$22/$B26) -> #REF! | H26: =+#REF!/(H$22/$B26) -> #REF! | I26: =+#REF!/(I$22/$B26) -> #REF! | J26: =+#REF!/(J$22/$B26) -> #REF! | K26: =+#REF!/(K$22/$B26) -> #REF!
A27: UW Cap Rate | B27: =+#REF! -> #REF! | C27: =+#REF!/(C$22/$B27) -> #REF! | D27: =+#REF!/(D$22/$B27) -> #REF! | E27: =+#REF!/(E$22/$B27) -> #REF! | F27: =+#REF!/(F$22/$B27) -> #REF! | G27: =+#REF!/(G$22/$B27) -> #REF! | H27: =+#REF!/(H$22/$B27) -> #REF! | I27: =+#REF!/(I$22/$B27) -> #REF! | J27: =+#REF!/(J$22/$B27) -> #REF! | K27: =+#REF!/(K$22/$B27) -> #REF!
A28: Plus 25 bps | B28: =+B27+0.0025 -> #REF! | C28: =+#REF!/(C$22/$B28) -> #REF! | D28: =+#REF!/(D$22/$B28) -> #REF! | E28: =+#REF!/(E$22/$B28) -> #REF! | F28: =+#REF!/(F$22/$B28) -> #REF! | G28: =+#REF!/(G$22/$B28) -> #REF! | H28: =+#REF!/(H$22/$B28) -> #REF! | I28: =+#REF!/(I$22/$B28) -> #REF! | J28: =+#REF!/(J$22/$B28) -> #REF! | K28: =+#REF!/(K$22/$B28) -> #REF!
A29: Plus 50 bps | B29: =+B28+0.0025 -> #REF! | C29: =+#REF!/(C$22/$B29) -> #REF! | D29: =+#REF!/(D$22/$B29) -> #REF! | E29: =+#REF!/(E$22/$B29) -> #REF! | F29: =+#REF!/(F$22/$B29) -> #REF! | G29: =+#REF!/(G$22/$B29) -> #REF! | H29: =+#REF!/(H$22/$B29) -> #REF! | I29: =+#REF!/(I$22/$B29) -> #REF! | J29: =+#REF!/(J$22/$B29) -> #REF! | K29: =+#REF!/(K$22/$B29) -> #REF!
A30: Plus 75 bps | B30: =+B29+0.0025 -> #REF! | C30: =+#REF!/(C$22/$B30) -> #REF! | D30: =+#REF!/(D$22/$B30) -> #REF! | E30: =+#REF!/(E$22/$B30) -> #REF! | F30: =+#REF!/(F$22/$B30) -> #REF! | G30: =+#REF!/(G$22/$B30) -> #REF! | H30: =+#REF!/(H$22/$B30) -> #REF! | I30: =+#REF!/(I$22/$B30) -> #REF! | J30: =+#REF!/(J$22/$B30) -> #REF! | K30: =+#REF!/(K$22/$B30) -> #REF!
A31: Plus 100 bps | B31: =+B30+0.0025 -> #REF! | C31: =+#REF!/(C$22/$B31) -> #REF! | D31: =+#REF!/(D$22/$B31) -> #REF! | E31: =+#REF!/(E$22/$B31) -> #REF! | F31: =+#REF!/(F$22/$B31) -> #REF! | G31: =+#REF!/(G$22/$B31) -> #REF! | H31: =+#REF!/(H$22/$B31) -> #REF! | I31: =+#REF!/(I$22/$B31) -> #REF! | J31: =+#REF!/(J$22/$B31) -> #REF! | K31: =+#REF!/(K$22/$B31) -> #REF!
A32: Plus 125 bps | B32: =+B31+0.0025 -> #REF! | C32: =+#REF!/(C$22/$B32) -> #REF! | D32: =+#REF!/(D$22/$B32) -> #REF! | E32: =+#REF!/(E$22/$B32) -> #REF! | F32: =+#REF!/(F$22/$B32) -> #REF! | G32: =+#REF!/(G$22/$B32) -> #REF! | H32: =+#REF!/(H$22/$B32) -> #REF! | I32: =+#REF!/(I$22/$B32) -> #REF! | J32: =+#REF!/(J$22/$B32) -> #REF! | K32: =+#REF!/(K$22/$B32) -> #REF!
A33: Plus 150 bps | B33: =+B32+0.0025 -> #REF! | C33: =+#REF!/(C$22/$B33) -> #REF! | D33: =+#REF!/(D$22/$B33) -> #REF! | E33: =+#REF!/(E$22/$B33) -> #REF! | F33: =+#REF!/(F$22/$B33) -> #REF! | G33: =+#REF!/(G$22/$B33) -> #REF! | H33: =+#REF!/(H$22/$B33) -> #REF! | I33: =+#REF!/(I$22/$B33) -> #REF! | J33: =+#REF!/(J$22/$B33) -> #REF! | K33: =+#REF!/(K$22/$B33) -> #REF!
A34: Plus 175 bps | B34: =+B33+0.0025 -> #REF! | C34: =+#REF!/(C$22/$B34) -> #REF! | D34: =+#REF!/(D$22/$B34) -> #REF! | E34: =+#REF!/(E$22/$B34) -> #REF! | F34: =+#REF!/(F$22/$B34) -> #REF! | G34: =+#REF!/(G$22/$B34) -> #REF! | H34: =+#REF!/(H$22/$B34) -> #REF! | I34: =+#REF!/(I$22/$B34) -> #REF! | J34: =+#REF!/(J$22/$B34) -> #REF! | K34: =+#REF!/(K$22/$B34) -> #REF!
A35: Plus 200 bps | B35: =+B34+0.0025 -> #REF! | C35: =+#REF!/(C$22/$B35) -> #REF! | D35: =+#REF!/(D$22/$B35) -> #REF! | E35: =+#REF!/(E$22/$B35) -> #REF! | F35: =+#REF!/(F$22/$B35) -> #REF! | G35: =+#REF!/(G$22/$B35) -> #REF! | H35: =+#REF!/(H$22/$B35) -> #REF! | I35: =+#REF!/(I$22/$B35) -> #REF! | J35: =+#REF!/(J$22/$B35) -> #REF! | K35: =+#REF!/(K$22/$B35) -> #REF!

Sheet Site Inspection
A4: Multifamily Site Inspection Form
A7: I. Loan/ Inspection Information
B9: Borrower | T9: Overall Property Rating
B10: Property Name | T10: Deferred Maintenance?
B11: Property Address | T11: Date of Inspection
B12: City, State, Zip | T12: Inspected By
B13: Borrower Contact | T13: Inspector Name
B14: Contact Phone
T15: Loan Balance
B17: General Comments for Subject Property:
A25: II. Site Data & Property Information
B27: Street Appeal | S27: Access to Major Arteries
B28: Visibility | S28: Access to Local Amenities
B29: Ingress and Egress | S29: Access to Public Transportation:
B30: Traffic Volume | S30: Compatibility with Neighborhood
B32: Number of Buildings | S32: Number of Units
B33: Number of Floors | S33: Number of Units Occupied
B34: Number of Parking Spaces | S34: Percent Occupied
B35: Number of Elevators | S35: Number of Down Units
B36: Annual Tenant Turnover (%) | S36: Sprinklers
B37: Average Lease Term | S37: Months of Free Rent
E39: Please verify rent roll during manager interview.
E41: Unit Type | P41: # of Units | T41: Avg. SF/Unit | X41: Monthly Rent | AB41: # Vacant
E42: Studio
E43: One Bedroom Units
E44: Two Bedroom/One Bath
E45: Two Bedroom/Two Bath
E46: Three Bedroom
E47: Other Unit Type
E50: Project Amenities | T50: Unit Amenities
B59: Comments regarding competitiveness of improvements and existing tenants:
A67: III. Property Condition
B69: Please answer each question using Excellent, Good, Fair, Poor, Not Accessible, Not Inspected, or N/A ratings
B71: Exterior | S71: Interior
B73: Ingress/Egress | S73: Lobbies
B74: Parking Lot | S74: Hallways
B75: Striping | S75: Stairways
B76: Drainage | S76: Interior Walls
B77: Retaining Walls | S77: Painting/Wallcoverings
B78: Sidewalks | S78: Flooring/Carpets/Tiles
B79: Landscaping | S79: Ceilings
B80: Signage | S80: Interior Doors
B81: Site Lighting | S81: Curtains/Blinds
B82: Roof Condition | S82: Electrical
B83: Flashing/Eaves/Ventilators | S83: Lighting
... B96: Other ____________________ | S96: Tub, Toilet & Sink Condition
S97: Laundry Rooms
S98: Other __________________
B100: Describe any observed deferred maintenance or planned major improvements. Please also include comments for any fair or poor item noted above, as well as any health & safety concerns.
BY165: 24 Hour Security | CV165: 0
BY166: 24 Hour Staffing | CH166: Excellent | CM166: Urban | CQ166: Over 75% | CV166: 0.05
BY167: Ballroom | CH167: Good | CM167: Suburban | CQ167: 25-75% | CV167: 0.1
BY168: Cable TV | CH168: Fair | CM168: Rural | CQ168: Under 25% | CV168: 0.15
BY169: Carports | CH169: Poor | CV169: 0.2
BY170: Ceiling Fans | CH170: N/A | CM170: Fully Developed | CV170: 0.25
BY171: Club House | CM171: Rapid | CV171: 0.3
BY172: Club Room | CH172: Monthly | CM172: Steady | CV172: 0.35
BY173: Cocktail Lounge | CH173: Weekly | CM173: Slow | CV173: 0.4
BY174: Coffee Shop | CH174: Daily | CV174: 0.45
BY175: Concierge | CH175: On-site | CM175: Likely | CP175: Improving | CV175: 0.5
BY176: Conference Facility | CM176: Unlikely | CP176: Stable | CV176: 0.55
CP177: Declining | CV177: 0.6
BY178: Dining Room | CH178: Responsive | CV178: 0.65
BY179: Fitness Room | CH179: Satisfactory | CM179: Medium | CV179: 0.7
BY180: Garage | CH180: Inadequate | CV180: 0.75
BY181: Golf Course | CH181: Absent | CV181: 0.8
BY182: Health Club | CM182: Excellent | CP182: Yes | CS182: Yes, see page 3 | CV182: 0.85
BY183: Kitchen in Room | CH183: Congregate Care | CM183: Good | CP183: No | CS183: No | CV183: 0.9
BY184: Laundry Rooms | CH184: Education | CM184: Fair | CV184: 0.95
BY185: Library | CH185: Healthcare | CM185: Poor | CV185: 1
BY186: Microwave | CH186: Hospitality | CM186: Not Accessible
BY187: Office Support | CH187: Industrial | CM187: Not Inspected
BY188: Parking - Covered | CH188: Mixed Use | CM188: None
BY189: Parking - Garage | CH189: Mobile Home | CM189: N/A
BY190: RV Parking | CH190: Multifamily
BY191: Secured Access | CH191: Office
BY192: Security | CH192: Retail
BY193: Storage | CH193: Self Storage
BY194: Swimming Pool
BY195: Tennis Court | CH195: Superior
BY196: Transportation | CH196: Similar
BY197: Underground Parking | CH197: Inferior
BY198: Volleyball Courts
BY199: Washer/Dryer
BY200: Product0460
