Workbook
Name Ccy: Inputs!$C$17
Name circ: Inputs!$C$20
Name CoName: Inputs!$C$15
Name ExitMultiple: Sensitivity!$E$6
Name IQ_CH: 110000
Name IQ_CQ: 5000
Name IQ_CY: 10000
Name IQ_DAILY: 500000
Name IQ_FH: 100000
Name IQ_FQ: 500
Name IQ_FY: 1000
Name IQ_LTM: 2000
Name IQ_MONTH: 15000
Name IQ_NTM: 6000
Name IQ_WEEK: 50000
Name IQ_YTD: 3000
Name OpCase: Sensitivity!$E$5
Name Premium: Sensitivity!$E$4
Name Units: Inputs!$C$18

Sheet Inputs
A1: Deal Structuring Training
A2: LBO modeling
A4: Special features
B6: Integrated LBO model
B7: Circular reference switch
B8: Sources and uses of funds
B9: Debt schedule
B10: Income statement, balance sheet, and cash flow statement
B11: Sensitivity analysis
A13: Model information
B15: Company name | C15: Company2272
B16: Latest BS date | C16: 42369
B17: Currency | C17: $
B18: Units | C18: m
B19: Analyst name | C19: Your name
B20: Circular switch | C20: 1

Sheet S&U
A1: =CoName -> Company2272
A2: =Ccy&Units&" unless otherwise stated" -> $m unless otherwise stated
A4: Acquisition analysis and assumptions
A6: Offer price | G6: =B13 -> Net shares to dilutive instruments | J6: Options | K6: RSU
B7: Unaffected share price | E7: 23.19 | F7: =Ccy -> $ | G7: Options outstanding | J7: 4.5 | K7: 5.4 | L7: =Units -> m
B8: Premium paid | E8: 0.38 | G8: Options strike price | J8: 37.34 | K8: 0 | L8: =Ccy -> $
B9: Acquisition price | E9: =E7*(1+Premium) -> 32.0022 | F9: =Ccy -> $ | G9: Net new shares | J9: =MAX(0,$E$9-J8)*J7/$E$9 -> 0 | K9: =MAX(0,$E$9-K8)*K7/$E$9 -> 5.4 | L9: =Units -> m
A11: Acquisition equity value | G11: Fee assumptions
B12: Basic shares outstanding | E12: 125.80522 | F12: =Units -> m | G12: Debt financing fees % debt issued | J12: 0.02
B13: Net shares to dilutive instruments | E13: =SUM(J9:K9) -> 5.4 | F13: =Units -> m | G13: Debt financing fees amortization (yrs) | J13: 6
B14: Diluted shares outstanding | E14: =SUM(E12:E13) -> 131.20522 | F14: =Units -> m | G14: Advisory fees % acquisition EV | J14: 0.015
B15: Acquisition equity value | E15: =E9*E14 -> 4198.8557
G16: Ownership structure | J16: % on entry | K16: % on exit
A17: Acquisition valuation bridge | G17: Mezzanine | J17: 0 | K17: 0.01
B18: Acquisition equity value | E18: =E15 -> 4198.8557 | G18: Management | J18: 0.01 | K18: 0.03
B19: Existing net debt (from latest balance sheet) | E19: =BS!C18+BS!C19+BS!C24-BS!C7 -> 9.6 | G19: Institutions | J19: =1-SUM(J17:J18) -> 0.99 | K19: =1-SUM(K17:K18) -> 0.96
B20: Acquisition enterprise value | E20: =E18+E19 -> 4208.4557
A22: Acquisition multiples
B23: LTM EBITDA | E23: =OpMod!E78 -> 599.9
B24: LTM EBITDA multiple | E24: =$E$20/E23 -> 7.015262
A26: Sources and uses of funds
A28: Uses of funds
B29: Acquisition equity value | C29: =E18 -> 4198.8557
B30: Refinanced debt
B31: Short-term debt | C31: =BS!C18+BS!C19 -> 1.7
B32: Long-term debt | C32: =BS!C24 -> 492.6
B33: Financing fees | C33: =SUM('S&U'!C41:C44)*J12 -> 64
B34: Advisory fees | C34: =E20*J14 -> 63.126835
B35: Total uses of funds | C35: =SUM(C29:C34) -> 4820.2825
A37: Sources of funds | E37: Analysis of sources of funds
G38: % of total | H38: Debt/EBITDA | I38: Swap rate | J38: Spread | K38: Interest rate | L38: Average life | M38: Year paid off
B39: Target cash | C39: =BS!C7 -> 484.7 | E39: =B39 -> Target cash | G39: =C39/$C$35 -> 0.10055427 | K39: 0.01
B40: Revolver | C40: 0 | E40: =B40 -> Revolver | G40: =C40/$C$35 -> 0 | I40: 0.0055 | J40: 0.03 | K40: =I40+J40 -> 0.0355
B41: Term debt A | C41: 1200 | E41: =B41 -> Term debt A | G41: =C41/$C$35 -> 0.24894806 | H41: =SUM($C$41:C41)/$E$23 -> 2.0003334 | I41: 0.0184 | J41: 0.04 | K41: =I41+J41 -> 0.0584 | L41: =IFERROR(SUMPRODUCT(FS!F78:O78,Returns!F9:O9)/-'S&U'!C41,"nm") -> 4.8544874 | M41: =COUNTIF(Debt!E82:O82,">0") -> 7
B42: Term debt B | C42: 900 | E42: =B42 -> Term debt B | G42: =C42/$C$35 -> 0.18671105 | H42: =SUM($C$41:C42)/$E$23 -> 3.5005834 | I42: 0.0236 | J42: 0.045 | K42: =I42+J42 -> 0.0686 | M42: =COUNTIF(Debt!E83:O83,">0") -> 8
B43: High yield | C43: 600 | E43: =B43 -> High yield | G43: =C43/$C$35 -> 0.12447403 | H43: =SUM($C$41:C43)/$E$23 -> 4.5007501 | K43: 0.08625 | M43: =COUNTIF(Debt!E84:O84,">0") -> 10
B44: Mezzanine (PIK) | C44: 500 | E44: =B44 -> Mezzanine (PIK) | G44: =C44/$C$35 -> 0.10372836 | H44: =SUM($C$41:C44)/$E$23 -> 5.3342224 | I44: 0.0281 | J44: 0.1 | K44: =I44+J44 -> 0.1281 | M44: =COUNTIF(Debt!E85:O85,">0") -> 10
B45: Shareholder Loan (PIK) | C45: =C35-SUM(C39:C44,C46) -> 535.58253 | E45: =B45 -> Shareholder Loan (PIK) | G45: =C45/$C$35 -> 0.11111019 | K45: 0.15
B46: Ordinary shares | C46: 600 | E46: =B46 -> Ordinary shares | G46: =C46/$C$35 -> 0.12447403
B47: Total sources | C47: =SUM(C39:C46) -> 4820.2825 | E47: =B47 -> Total sources | G47: =SUM(G39:G46) -> 1

Sheet OpMod
A1: =CoName -> Company2272 | C1: Hist. | D1: Hist. | E1: Hist. | F1: Proj. | G1: Proj. | H1: Proj. | I1: Proj. | J1: Proj. | K1: Proj. | L1: Proj. | M1: Proj. | N1: Proj. | O1: Proj.
A2: =Ccy&Units&" unless otherwise stated" -> $m unless otherwise stated | C2: =DATE(YEAR(D2)-1,MONTH(D2),DAY(D2)) -> 41639 | D2: =DATE(YEAR(E2)-1,MONTH(E2),DAY(E2)) -> 42004 | E2: =Inputs!C16 -> 42369 | F2: =DATE(YEAR(E2)+1,MONTH(E2),DAY(E2)) -> 42735 | G2: =DATE(YEAR(F2)+1,MONTH(F2),DAY(F2)) -> 43100 | H2: =DATE(YEAR(G2)+1,MONTH(G2),DAY(G2)) -> 43465 | I2: =DATE(YEAR(H2)+1,MONTH(H2),DAY(H2)) -> 43830 | J2: =DATE(YEAR(I2)+1,MONTH(I2),DAY(I2)) -> 44196 | K2: =DATE(YEAR(J2)+1,MONTH(J2),DAY(J2)) -> 44561 | L2: =DATE(YEAR(K2)+1,MONTH(K2),DAY(K2)) -> 44926 | M2: =DATE(YEAR(L2)+1,MONTH(L2),DAY(L2)) -> 45291 | ... O2: =DATE(YEAR(N2)+1,MONTH(N2),DAY(N2)) -> 46022
A4: =CHOOSE(OpCase,A27,A50) -> Operating model assumptions - Base case
A6: Case | C6: 1
A8: Income statement
B9: Sales growth | D9: =D76/C76-1 -> 0.16914256 | E9: =E76/D76-1 -> 0.11530317 | F9: =CHOOSE(OpCase,F32,F55) -> 0.115 | G9: =CHOOSE(OpCase,G32,G55) -> 0.1 | H9: =CHOOSE(OpCase,H32,H55) -> 0.09 | I9: =CHOOSE(OpCase,I32,I55) -> 0.08 | J9: =CHOOSE(OpCase,J32,J55) -> 0.07 | K9: =CHOOSE(OpCase,K32,K55) -> 0.06 | L9: =CHOOSE(OpCase,L32,L55) -> 0.05 | M9: =CHOOSE(OpCase,M32,M55) -> 0.04 | ... O9: =CHOOSE(OpCase,O32,O55) -> 0.03
B10: EBITDA margin | C10: =C78/C76 -> 0.28922335 | D10: =D78/D76 -> 0.29547481 | E10: =E78/E76 -> 0.29975516 | F10: =CHOOSE(OpCase,F33,F56) -> 0.33 | G10: =CHOOSE(OpCase,G33,G56) -> 0.33 | H10: =CHOOSE(OpCase,H33,H56) -> 0.33 | I10: =CHOOSE(OpCase,I33,I56) -> 0.33 | J10: =CHOOSE(OpCase,J33,J56) -> 0.33 | K10: =CHOOSE(OpCase,K33,K56) -> 0.33 | L10: =CHOOSE(OpCase,L33,L56) -> 0.33 | M10: =CHOOSE(OpCase,M33,M56) -> 0.33 | ... O10: =CHOOSE(OpCase,O33,O56) -> 0.33
B11: Tax rate | F11: =CHOOSE(OpCase,F34,F57) -> 0.35 | G11: =CHOOSE(OpCase,G34,G57) -> 0.35 | H11: =CHOOSE(OpCase,H34,H57) -> 0.35 | I11: =CHOOSE(OpCase,I34,I57) -> 0.35 | J11: =CHOOSE(OpCase,J34,J57) -> 0.35 | K11: =CHOOSE(OpCase,K34,K57) -> 0.35 | L11: =CHOOSE(OpCase,L34,L57) -> 0.35 | M11: =CHOOSE(OpCase,M34,M57) -> 0.35 | ... O11: =CHOOSE(OpCase,O34,O57) -> 0.35
A13: Property, plant & equipment
B14: Capital expenditure % of sales | C14: =C86/C76 -> 0.29489184 | D14: =D86/D76 -> 0.2398016 | E14: =E86/E76 -> 0.23729576 | F14: =CHOOSE(OpCase,F37,F60) -> 0.23 | G14: =CHOOSE(OpCase,G37,G60) -> 0.22 | H14: =CHOOSE(OpCase,H37,H60) -> 0.21 | I14: =CHOOSE(OpCase,I37,I60) -> 0.2 | J14: =CHOOSE(OpCase,J37,J60) -> 0.2 | K14: =CHOOSE(OpCase,K37,K60) -> 0.2 | L14: =CHOOSE(OpCase,L37,L60) -> 0.2 | M14: =CHOOSE(OpCase,M37,M60) -> 0.2 | ... O14: =CHOOSE(OpCase,O37,O60) -> 0.2
B15: Depreciation % of beginning PP&E | E15: =E87/D88 -> -0.37808452 | F15: =CHOOSE(OpCase,F38,F61) -> -0.38 | G15: =CHOOSE(OpCase,G38,G61) -> -0.38 | H15: =CHOOSE(OpCase,H38,H61) -> -0.38 | I15: =CHOOSE(OpCase,I38,I61) -> -0.38 | J15: =CHOOSE(OpCase,J38,J61) -> -0.38 | K15: =CHOOSE(OpCase,K38,K61) -> -0.38 | L15: =CHOOSE(OpCase,L38,L61) -> -0.38 | M15: =CHOOSE(OpCase,M38,M61) -> -0.38 | ... O15: =CHOOSE(OpCase,O38,O61) -> -0.38
A17: Operating working capital
B18: Inventories % of sales | E18: =E91/E$76 -> 0 | F18: =CHOOSE(OpCase,F41,F64) -> 0 | G18: =CHOOSE(OpCase,G41,G64) -> 0 | H18: =CHOOSE(OpCase,H41,H64) -> 0 | I18: =CHOOSE(OpCase,I41,I64) -> 0 | J18: =CHOOSE(OpCase,J41,J64) -> 0 | K18: =CHOOSE(OpCase,K41,K64) -> 0 | L18: =CHOOSE(OpCase,L41,L64) -> 0 | M18: =CHOOSE(OpCase,M41,M64) -> 0 | ... O18: =CHOOSE(OpCase,O41,O64) -> 0
B19: Trade and other receivables % of sales | E19: =E92/E$76 -> 0.1167741 | F19: =CHOOSE(OpCase,F42,F65) -> 0.12 | G19: =CHOOSE(OpCase,G42,G65) -> 0.12 | H19: =CHOOSE(OpCase,H42,H65) -> 0.12 | I19: =CHOOSE(OpCase,I42,I65) -> 0.12 | J19: =CHOOSE(OpCase,J42,J65) -> 0.12 | K19: =CHOOSE(OpCase,K42,K65) -> 0.12 | L19: =CHOOSE(OpCase,L42,L65) -> 0.12 | M19: =CHOOSE(OpCase,M42,M65) -> 0.12 | ... O19: =CHOOSE(OpCase,O42,O65) -> 0.12
B20: Trade and other payables % of sales | E20: =E93/E$76 -> 0.068105731 | F20: =CHOOSE(OpCase,F43,F66) -> 0.08 | G20: =CHOOSE(OpCase,G43,G66) -> 0.08 | H20: =CHOOSE(OpCase,H43,H66) -> 0.08 | I20: =CHOOSE(OpCase,I43,I66) -> 0.08 | J20: =CHOOSE(OpCase,J43,J66) -> 0.08 | K20: =CHOOSE(OpCase,K43,K66) -> 0.08 | L20: =CHOOSE(OpCase,L43,L66) -> 0.08 | M20: =CHOOSE(OpCase,M43,M66) -> 0.08 | ... O20: =CHOOSE(OpCase,O43,O66) -> 0.08
B21: Other current liabilities % of sales | E21: =E94/E$76 -> 0.049417878 | F21: =CHOOSE(OpCase,F44,F67) -> 0.05 | G21: =CHOOSE(OpCase,G44,G67) -> 0.05 | H21: =CHOOSE(OpCase,H44,H67) -> 0.05 | I21: =CHOOSE(OpCase,I44,I67) -> 0.05 | J21: =CHOOSE(OpCase,J44,J67) -> 0.05 | K21: =CHOOSE(OpCase,K44,K67) -> 0.05 | L21: =CHOOSE(OpCase,L44,L67) -> 0.05 | M21: =CHOOSE(OpCase,M44,M67) -> 0.05 | ... O21: =CHOOSE(OpCase,O44,O67) -> 0.05
A23: Other operating items
B24: Other long-term assets % of sales | E24: =E98/E76 -> 0.033328337 | F24: =CHOOSE(OpCase,F47,F70) -> 0.033 | G24: =CHOOSE(OpCase,G47,G70) -> 0.033 | H24: =CHOOSE(OpCase,H47,H70) -> 0.033 | I24: =CHOOSE(OpCase,I47,I70) -> 0.033 | J24: =CHOOSE(OpCase,J47,J70) -> 0.033 | K24: =CHOOSE(OpCase,K47,K70) -> 0.033 | L24: =CHOOSE(OpCase,L47,L70) -> 0.033 | M24: =CHOOSE(OpCase,M47,M70) -> 0.033 | ... O24: =CHOOSE(OpCase,O47,O70) -> 0.033
B25: Other long-term liabilities % of sales | E25: =E99/E76 -> 0.15819717 | F25: =CHOOSE(OpCase,F48,F71) -> 0.158 | G25: =CHOOSE(OpCase,G48,G71) -> 0.158 | H25: =CHOOSE(OpCase,H48,H71) -> 0.158 | I25: =CHOOSE(OpCase,I48,I71) -> 0.158 | J25: =CHOOSE(OpCase,J48,J71) -> 0.158 | K25: =CHOOSE(OpCase,K48,K71) -> 0.158 | L25: =CHOOSE(OpCase,L48,L71) -> 0.158 | M25: =CHOOSE(OpCase,M48,M71) -> 0.158 | ... O25: =CHOOSE(OpCase,O48,O71) -> 0.158
A27: ="Operating model assumptions - "&A29 -> Operating model assumptions - Base case
A29: Base case
A31: Income statement
B32: Sales growth | D32: =D9 -> 0.16914256 | E32: =E9 -> 0.11530317 | F32: 0.115 | G32: 0.1 | H32: 0.09 | I32: 0.08 | J32: 0.07 | K32: 0.06 | L32: 0.05 | M32: 0.04 | N32: 0.03 | O32: 0.03
B33: EBITDA margin | C33: =C10 -> 0.28922335 | D33: =D10 -> 0.29547481 | E33: =E10 -> 0.29975516 | F33: 0.33 | G33: 0.33 | H33: 0.33 | I33: 0.33 | J33: 0.33 | K33: 0.33 | L33: 0.33 | M33: 0.33 | N33: 0.33 | O33: 0.33
B34: Tax rate | F34: 0.35 | G34: 0.35 | H34: 0.35 | I34: 0.35 | J34: 0.35 | K34: 0.35 | L34: 0.35 | M34: 0.35 | N34: 0.35 | O34: 0.35
A36: Property, plant & equipment
B37: Capital expenditure % of sales | C37: =C14 -> 0.29489184 | D37: =D14 -> 0.2398016 | E37: =E14 -> 0.23729576 | F37: 0.23 | G37: 0.22 | H37: 0.21 | I37: 0.2 | J37: 0.2 | K37: 0.2 | L37: 0.2 | M37: 0.2 | N37: 0.2 | O37: 0.2
B38: Depreciation % of beginning PP&E | E38: =E15 -> -0.37808452 | F38: -0.38 | G38: -0.38 | H38: -0.38 | I38: -0.38 | J38: -0.38 | K38: -0.38 | L38: -0.38 | M38: -0.38 | N38: -0.38 | O38: -0.38
A40: Operating working capital
B41: Inventories % of sales | E41: =E18 -> 0 | F41: 0 | G41: 0 | H41: 0 | I41: 0 | J41: 0 | K41: 0 | L41: 0 | M41: 0 | N41: 0 | O41: 0
B42: Trade and other receivables % of sales | E42: =E19 -> 0.1167741 | F42: 0.12 | G42: 0.12 | H42: 0.12 | I42: 0.12 | J42: 0.12 | K42: 0.12 | L42: 0.12 | M42: 0.12 | N42: 0.12 | O42: 0.12
B43: Trade and other payables % of sales | E43: =E20 -> 0.068105731 | F43: 0.08 | G43: 0.08 | H43: 0.08 | I43: 0.08 | J43: 0.08 | K43: 0.08 | L43: 0.08 | M43: 0.08 | N43: 0.08 | O43: 0.08
B44: Other current liabilities % of sales | E44: =E21 -> 0.049417878 | F44: 0.05 | G44: 0.05 | H44: 0.05 | I44: 0.05 | J44: 0.05 | K44: 0.05 | L44: 0.05 | M44: 0.05 | N44: 0.05 | O44: 0.05
A46: Other operating items
B47: Other long-term assets % of sales | E47: =E24 -> 0.033328337 | F47: 0.033 | G47: 0.033 | H47: 0.033 | I47: 0.033 | J47: 0.033 | K47: 0.033 | L47: 0.033 | M47: 0.033 | N47: 0.033 | O47: 0.033
B48: Other long-term liabilities % of sales | E48: =E25 -> 0.15819717 | F48: 0.158 | G48: 0.158 | H48: 0.158 | I48: 0.158 | J48: 0.158 | K48: 0.158 | L48: 0.158 | M48: 0.158 | N48: 0.158 | O48: 0.158
A50: ="Operating model assumptions - "&A52 -> Operating model assumptions - Management case
A52: Management case
A54: Income statement
B55: Sales growth | D55: =D32 -> 0.16914256 | E55: =E32 -> 0.11530317 | F55: 0.12 | G55: 0.12 | H55: 0.12 | I55: 0.12 | J55: 0.12 | K55: 0.06 | L55: 0.05 | M55: 0.04 | N55: 0.03 | O55: 0.03
B56: EBITDA margin | C56: =C33 -> 0.28922335 | D56: =D33 -> 0.29547481 | E56: =E33 -> 0.29975516 | F56: 0.33 | G56: 0.33 | H56: 0.33 | I56: 0.33 | J56: 0.33 | K56: 0.33 | L56: 0.33 | M56: 0.33 | N56: 0.33 | O56: 0.33
B57: Tax rate | F57: 0.35 | G57: 0.35 | H57: 0.35 | I57: 0.35 | J57: 0.35 | K57: 0.35 | L57: 0.35 | M57: 0.35 | N57: 0.35 | O57: 0.35
A59: Property, plant & equipment
B60: Capital expenditure % of sales | C60: =C37 -> 0.29489184 | D60: =D37 -> 0.2398016 | E60: =E37 -> 0.23729576 | F60: 0.2 | G60: 0.2 | H60: 0.2 | I60: 0.2 | J60: 0.2 | K60: 0.2 | L60: 0.2 | M60: 0.2 | N60: 0.2 | O60: 0.2
B61: Depreciation % of beginning PP&E | E61: =E38 -> -0.37808452 | F61: -0.38 | G61: -0.38 | H61: -0.38 | I61: -0.38 | J61: -0.38 | K61: -0.38 | L61: -0.38 | M61: -0.38 | N61: -0.38 | O61: -0.38
A63: Operating working capital
B64: Inventories % of sales | E64: =E41 -> 0 | F64: 0 | G64: 0 | H64: 0 | I64: 0 | J64: 0 | K64: 0 | L64: 0 | M64: 0 | N64: 0 | O64: 0
B65: Trade and other receivables % of sales | E65: =E42 -> 0.1167741 | F65: 0.117 | G65: 0.117 | H65: 0.117 | I65: 0.117 | J65: 0.117 | K65: 0.117 | L65: 0.117 | M65: 0.117 | N65: 0.117 | O65: 0.117
B66: Trade and other payables % of sales | E66: =E43 -> 0.068105731 | F66: 0.068 | G66: 0.068 | H66: 0.068 | I66: 0.068 | J66: 0.068 | K66: 0.068 | L66: 0.068 | M66: 0.068 | N66: 0.068 | O66: 0.068
B67: Other current liabilities % of sales | E67: =E44 -> 0.049417878 | F67: 0.049 | G67: 0.049 | H67: 0.049 | I67: 0.049 | J67: 0.049 | K67: 0.049 | L67: 0.049 | M67: 0.049 | N67: 0.049 | O67: 0.049
A69: Other operating items
B70: Other long-term assets % of sales | E70: =E47 -> 0.033328337 | F70: 0.033 | G70: 0.033 | H70: 0.033 | I70: 0.033 | J70: 0.033 | K70: 0.033 | L70: 0.033 | M70: 0.033 | N70: 0.033 | O70: 0.033
B71: Other long-term liabilities % of sales | E71: =E48 -> 0.15819717 | F71: 0.158 | G71: 0.158 | H71: 0.158 | I71: 0.158 | J71: 0.158 | K71: 0.158 | L71: 0.158 | M71: 0.158 | N71: 0.158 | O71: 0.158
A73: Operating model calculations
A75: Unlevered net income
B76: Sales | C76: 1534.8 | D76: 1794.4 | E76: 2001.3 | F76: =E76*(1+F9) -> 2231.4495 | G76: =F76*(1+G9) -> 2454.5945 | H76: =G76*(1+H9) -> 2675.508 | I76: =H76*(1+I9) -> 2889.5486 | J76: =I76*(1+J9) -> 3091.817 | K76: =J76*(1+K9) -> 3277.326 | L76: =K76*(1+L9) -> 3441.1923 | M76: =L76*(1+M9) -> 3578.84 | ... O76: =N76*(1+O9) -> 3796.7914
B78: EBITDA | C78: 443.9 | D78: 530.2 | E78: 599.9 | F78: =F76*F10 -> 736.37833 | G78: =G76*G10 -> 810.01617 | H78: =H76*H10 -> 882.91762 | I78: =I76*I10 -> 953.55103 | J78: =J76*J10 -> 1020.2996 | K78: =K76*K10 -> 1081.5176 | L78: =L76*L10 -> 1135.5935 | M78: =M76*M10 -> 1181.0172 | ... O78: =O76*O10 -> 1252.9411
B79: Depreciation and amortization expense | F79: =F87 -> -436.24 | G79: =G87 -> -465.49749 | H79: =H87 -> -493.81254 | I79: =I87 -> -519.66931 | J79: =J87 -> -541.80066 | K79: =K87 -> -570.8945 | L79: =L87 -> -603.03137 | M79: =M87 -> -635.41006 | ... O79: =O87 -> -693.03816
B80: EBIT | F80: =SUM(F78:F79) -> 300.13833 | G80: =SUM(G78:G79) -> 344.51868 | H80: =SUM(H78:H79) -> 389.10509 | I80: =SUM(I78:I79) -> 433.88173 | J80: =SUM(J78:J79) -> 478.49894 | K80: =SUM(K78:K79) -> 510.62308 | L80: =SUM(L78:L79) -> 532.56209 | M80: =SUM(M78:M79) -> 545.60714 | ... O80: =SUM(O78:O79) -> 559.90298
B81: Tax on EBIT | F81: =-F80*F11 -> -105.04842 | G81: =-G80*G11 -> -120.58154 | H81: =-H80*H11 -> -136.18678 | I81: =-I80*I11 -> -151.8586 | J81: =-J80*J11 -> -167.47463 | K81: =-K80*K11 -> -178.71808 | L81: =-L80*L11 -> -186.39673 | M81: =-M80*M11 -> -190.9625 | ... O81: =-O80*O11 -> -195.96604
B82: Unlevered net income | F82: =F80+F81 -> 195.08992 | G82: =G80+G81 -> 223.93714 | H82: =H80+H81 -> 252.91831 | I82: =I80+I81 -> 282.02312 | J82: =J80+J81 -> 311.02431 | K82: =K80+K81 -> 331.905 | L82: =L80+L81 -> 346.16536 | M82: =M80+M81 -> 354.64464 | ... O82: =O80+O81 -> 363.93694
A84: Property, plant & equipment
B85: PP&E - Beginning balance | F85: =E88 -> 1148 | G85: =F88 -> 1224.9934 | H85: =G88 -> 1299.5067 | I85: =H88 -> 1367.5508 | J85: =I88 -> 1425.7912 | K85: =J88 -> 1502.354 | L85: =K88 -> 1586.9247 | M85: =L88 -> 1672.1317 | ... O85: =N88 -> 1823.7846
B86: Capital expenditure | C86: 452.6 | D86: 430.3 | E86: 474.9 | F86: =F14*F76 -> 513.23338 | G86: =G14*G76 -> 540.01078 | H86: =H14*H76 -> 561.85667 | I86: =I14*I76 -> 577.90972 | J86: =J14*J76 -> 618.3634 | K86: =K14*K76 -> 655.4652 | L86: =L14*L76 -> 688.23846 | M86: =M14*M76 -> 715.768 | ... O86: =O14*O76 -> 759.35827
B87: Depreciation | C87: -313.1 | D87: -371.9 | E87: -399.9 | F87: =E88*F15 -> -436.24 | G87: =F88*G15 -> -465.49749 | H87: =G88*H15 -> -493.81254 | I87: =H88*I15 -> -519.66931 | J87: =I88*J15 -> -541.80066 | K87: =J88*K15 -> -570.8945 | L87: =K88*L15 -> -603.03137 | M87: =L88*M15 -> -635.41006 | ... O87: =N88*O15 -> -693.03816
B88: PP&E - Ending balance | D88: 1057.7 | E88: 1148 | F88: =SUM(F85:F87) -> 1224.9934 | G88: =SUM(G85:G87) -> 1299.5067 | H88: =SUM(H85:H87) -> 1367.5508 | I88: =SUM(I85:I87) -> 1425.7912 | J88: =SUM(J85:J87) -> 1502.354 | K88: =SUM(K85:K87) -> 1586.9247 | L88: =SUM(L85:L87) -> 1672.1317 | M88: =SUM(M85:M87) -> 1752.4897 | ... O88: =SUM(O85:O87) -> 1890.1047
A90: Operating working capital
B91: Inventories | E91: =BS!C8 -> 0 | F91: =F$76*F18 -> 0 | G91: =G$76*G18 -> 0 | H91: =H$76*H18 -> 0 | I91: =I$76*I18 -> 0 | J91: =J$76*J18 -> 0 | K91: =K$76*K18 -> 0 | L91: =L$76*L18 -> 0 | M91: =M$76*M18 -> 0 | ... O91: =O$76*O18 -> 0
B92: Trade and other receivables | E92: =BS!C9 -> 233.7 | F92: =F$76*F19 -> 267.77394 | G92: =G$76*G19 -> 294.55133 | H92: =H$76*H19 -> 321.06095 | I92: =I$76*I19 -> 346.74583 | J92: =J$76*J19 -> 371.01804 | K92: =K$76*K19 -> 393.27912 | L92: =L$76*L19 -> 412.94308 | M92: =M$76*M19 -> 429.4608 | ... O92: =O$76*O19 -> 455.61496
B93: Trade and other payables | E93: =BS!C20 -> 136.3 | F93: =F$76*F20 -> 178.51596 | G93: =G$76*G20 -> 196.36756 | H93: =H$76*H20 -> 214.04064 | I93: =I$76*I20 -> 231.16389 | J93: =J$76*J20 -> 247.34536 | K93: =K$76*K20 -> 262.18608 | L93: =L$76*L20 -> 275.29538 | M93: =M$76*M20 -> 286.3072 | ... O93: =O$76*O20 -> 303.74331
B94: Other current liabilities | E94: =BS!C21 -> 98.9 | F94: =F$76*F21 -> 111.57247 | G94: =G$76*G21 -> 122.72972 | H94: =H$76*H21 -> 133.7754 | I94: =I$76*I21 -> 144.47743 | J94: =J$76*J21 -> 154.59085 | K94: =K$76*K21 -> 163.8663 | L94: =L$76*L21 -> 172.05962 | M94: =M$76*M21 -> 178.942 | ... O94: =O$76*O21 -> 189.83957
B95: OWC | E95: =SUM(E91:E92)-SUM(E93:E94) -> -1.5 | F95: =SUM(F91:F92)-SUM(F93:F94) -> -22.314495 | G95: =SUM(G91:G92)-SUM(G93:G94) -> -24.545945 | H95: =SUM(H91:H92)-SUM(H93:H94) -> -26.75508 | I95: =SUM(I91:I92)-SUM(I93:I94) -> -28.895486 | J95: =SUM(J91:J92)-SUM(J93:J94) -> -30.91817 | K95: =SUM(K91:K92)-SUM(K93:K94) -> -32.77326 | L95: =SUM(L91:L92)-SUM(L93:L94) -> -34.411923 | ... O95: =SUM(O91:O92)-SUM(O93:O94) -> -37.967914
A97: Other operating items
B98: Other long-term assets | E98: 66.7 | F98: =F24*F76 -> 73.637833 | G98: =G24*G76 -> 81.001617 | H98: =H24*H76 -> 88.291762 | I98: =I24*I76 -> 95.355103 | J98: =J24*J76 -> 102.02996 | K98: =K24*K76 -> 108.15176 | L98: =L24*L76 -> 113.55935 | M98: =M24*M76 -> 118.10172 | ... O98: =O24*O76 -> 125.29411
B99: Other long-term liabilities | E99: 316.6 | F99: =F25*F76 -> 352.56902 | G99: =G25*G76 -> 387.82592 | H99: =H25*H76 -> 422.73026 | I99: =I25*I76 -> 456.54868 | J99: =J25*J76 -> 488.50708 | K99: =K25*K76 -> 517.81751 | L99: =L25*L76 -> 543.70838 | M99: =M25*M76 -> 565.45672 | ... O99: =O25*O76 -> 599.89303

Sheet Calcs
A1: =CoName -> Company2272 | E1: Hist. | F1: Proj. | G1: Proj. | H1: Proj. | I1: Proj. | J1: Proj. | K1: Proj. | L1: Proj. | M1: Proj. | N1: Proj. | O1: Proj.
A2: =Ccy&Units&" unless otherwise stated" -> $m unless otherwise stated | E2: =Inputs!C16 -> 42369 | F2: =DATE(YEAR(E2)+1,MONTH(E2),DAY(E2)) -> 42735 | G2: =DATE(YEAR(F2)+1,MONTH(F2),DAY(F2)) -> 43100 | H2: =DATE(YEAR(G2)+1,MONTH(G2),DAY(G2)) -> 43465 | I2: =DATE(YEAR(H2)+1,MONTH(H2),DAY(H2)) -> 43830 | J2: =DATE(YEAR(I2)+1,MONTH(I2),DAY(I2)) -> 44196 | K2: =DATE(YEAR(J2)+1,MONTH(J2),DAY(J2)) -> 44561 | L2: =DATE(YEAR(K2)+1,MONTH(K2),DAY(K2)) -> 44926 | M2: =DATE(YEAR(L2)+1,MONTH(L2),DAY(L2)) -> 45291 | ... O2: =DATE(YEAR(N2)+1,MONTH(N2),DAY(N2)) -> 46022
A4: Goodwill
B6: Purchase price | E6: ='S&U'!E15 -> 4198.8557
B8: Fair value of net assets acquired
B9: Book value of net assets acquired | E9: =BS!C15-BS!C31 -> 968.1
B10: Deduct existing goodwill of target | E10: =-BS!C13 -> -81.1
B11: Fair value of net assets acquired | E11: =SUM(E9:E10) -> 887
B13: Goodwill | E13: =E6-E11 -> 3311.8557
A15: Debt issuance fees
B17: Beginning debt issuance fees | F17: =E19 -> 64 | G17: =F19 -> 53.333333 | H17: =G19 -> 42.666667 | I17: =H19 -> 32 | J17: =I19 -> 21.333333 | K17: =J19 -> 10.666667 | L17: =K19 -> 0 | M17: =L19 -> 0 | ... O17: =N19 -> 0
B18: Amortization | F18: =-MIN(F17,$E$19/'S&U'!$J$13) -> -10.666667 | G18: =-MIN(G17,$E$19/'S&U'!$J$13) -> -10.666667 | H18: =-MIN(H17,$E$19/'S&U'!$J$13) -> -10.666667 | I18: =-MIN(I17,$E$19/'S&U'!$J$13) -> -10.666667 | J18: =-MIN(J17,$E$19/'S&U'!$J$13) -> -10.666667 | K18: =-MIN(K17,$E$19/'S&U'!$J$13) -> -10.666667 | L18: =-MIN(L17,$E$19/'S&U'!$J$13) -> 0 | M18: =-MIN(M17,$E$19/'S&U'!$J$13) -> 0 | ... O18: =-MIN(O17,$E$19/'S&U'!$J$13) -> 0
B19: Ending debt issuance fees | E19: ='S&U'!C33 -> 64 | F19: =SUM(F17:F18) -> 53.333333 | G19: =SUM(G17:G18) -> 42.666667 | H19: =SUM(H17:H18) -> 32 | I19: =SUM(I17:I18) -> 21.333333 | J19: =SUM(J17:J18) -> 10.666667 | K19: =SUM(K17:K18) -> 0 | L19: =SUM(L17:L18) -> 0 | M19: =SUM(M17:M18) -> 0 | ... O19: =SUM(O17:O18) -> 0
A21: Retained earnings
B23: Beginning retained earnings | F23: =E25 -> -63.126835 | G23: =F25 -> -114.99289 | H23: =G25 -> -152.36979 | I23: =H25 -> -176.31329 | J23: =I25 -> -187.83277 | K23: =J25 -> -188.99531 | L23: =K25 -> -190.81416 | M23: =L25 -> -196.04803 | ... O23: =N25 -> -255.98156
B24: Net income | F24: =FS!F21 -> -51.866053 | G24: =FS!G21 -> -37.376905 | H24: =FS!H21 -> -23.943501 | I24: =FS!I21 -> -11.519472 | J24: =FS!J21 -> -1.1625428 | K24: =FS!K21 -> -1.8188522 | L24: =FS!L21 -> -5.233872 | M24: =FS!M21 -> -17.614846 | ... O24: =FS!O21 -> -105.98469
B25: Ending retained earnings | E25: =BS!F35 -> -63.126835 | F25: =SUM(F23:F24) -> -114.99289 | G25: =SUM(G23:G24) -> -152.36979 | H25: =SUM(H23:H24) -> -176.31329 | I25: =SUM(I23:I24) -> -187.83277 | J25: =SUM(J23:J24) -> -188.99531 | K25: =SUM(K23:K24) -> -190.81416 | L25: =SUM(L23:L24) -> -196.04803 | M25: =SUM(M23:M24) -> -213.66288 | ... O25: =SUM(O23:O24) -> -361.96625

Sheet BS
A1: =CoName -> Company2272 | C1: Op Co | D1: New Co | E1: Adj. | F1: Combo
A2: =Ccy&Units&" unless otherwise stated" -> $m unless otherwise stated | C2: =Inputs!$C$16 -> 42369 | D2: =Inputs!$C$16 -> 42369 | E2: =Inputs!$C$16 -> 42369 | F2: =Inputs!$C$16 -> 42369
A4: Balance sheet | C4: Op Co | D4: New Co | E4: Adj. | F4: Combo
A6: Assets
B7: Cash and financial investments | C7: 484.7 | D7: ='S&U'!C47-'S&U'!C39-'S&U'!C33 -> 4271.5825 | E7: =-D7-C7 -> -4756.2825 | F7: =SUM(C7:E7) -> 0
B8: Inventories | C8: 0 | F8: =SUM(C8:E8) -> 0
B9: Trade and other receivables | C9: 233.7 | F9: =SUM(C9:E9) -> 233.7
B10: Total current assets | C10: =SUM(C7:C9) -> 718.4 | D10: =SUM(D7:D9) -> 4271.5825 | E10: =SUM(E7:E9) -> -4756.2825 | F10: =SUM(F7:F9) -> 233.7
B12: Property, plant and equipment | C12: 1148 | F12: =SUM(C12:E12) -> 1148
B13: Goodwill | C13: 81.1 | E13: =Calcs!E13-BS!C13 -> 3230.7557 | F13: =SUM(C13:E13) -> 3311.8557
B14: Other LT assets | C14: 66.7 | F14: =SUM(C14:E14) -> 66.7
B15: Total assets | C15: =SUM(C10,C12:C14) -> 2014.2 | D15: =SUM(D10,D12:D14) -> 4271.5825 | E15: =SUM(E10,E12:E14) -> -1525.5268 | F15: =SUM(F10,F12:F14) -> 4760.2557
A17: Liabilities and equity
B18: Short-term debt | C18: 1.7 | E18: =-C18 -> -1.7 | F18: =SUM(C18:E18) -> 0
B19: Revolver | C19: 0 | D19: ='S&U'!C40 -> 0 | E19: =-C19 -> 0 | F19: =SUM(C19:E19) -> 0
B20: Trade and other payables | C20: 136.3 | F20: =SUM(C20:E20) -> 136.3
B21: Other current liabilities | C21: 98.9 | F21: =SUM(C21:E21) -> 98.9
B22: Total current liabilities | C22: =SUM(C18:C21) -> 236.9 | D22: =SUM(D18:D21) -> 0 | E22: =SUM(E18:E21) -> -1.7 | F22: =SUM(F18:F21) -> 235.2
B24: Long-term debt | C24: 492.6 | E24: =-C24 -> -492.6 | F24: =SUM(C24:E24) -> 0
B25: Term debt A | D25: ='S&U'!C41 -> 1200 | F25: =SUM(C25:E25) -> 1200
B26: Term debt B | D26: ='S&U'!C42 -> 900 | F26: =SUM(C26:E26) -> 900
B27: High yield | D27: ='S&U'!C43 -> 600 | F27: =SUM(C27:E27) -> 600
B28: Mezzanine (PIK) | D28: ='S&U'!C44 -> 500 | F28: =SUM(C28:E28) -> 500
B29: Debt financing fees | D29: =-'S&U'!C33 -> -64 | F29: =SUM(C29:E29) -> -64
B30: Other LT liabilities | C30: 316.6 | F30: =SUM(C30:E30) -> 316.6
B31: Total liabilities | C31: =SUM(C22,C24:C30) -> 1046.1 | D31: =SUM(D22,D24:D30) -> 3136 | E31: =SUM(E22,E24:E30) -> -494.3 | F31: =SUM(F22,F24:F30) -> 3687.8
B33: Shareholder loan | D33: ='S&U'!C45 -> 535.58253 | F33: =SUM(C33:E33) -> 535.58253
B34: Ordinary equity | C34: 798.4 | D34: ='S&U'!C46 -> 600 | E34: =-C34 -> -798.4 | F34: =SUM(C34:E34) -> 600
B35: Retained earnings (deficit) | C35: 169.7 | E35: =-C35-'S&U'!C34 -> -232.82684 | F35: =SUM(C35:E35) -> -63.126835
B36: Shareholders equity | C36: =SUM(C33:C35) -> 968.1 | D36: =SUM(D33:D35) -> 1135.5825 | E36: =SUM(E33:E35) -> -1031.2268 | F36: =SUM(F33:F35) -> 1072.4557
B38: Total liabilities & equity | C38: =SUM(C36,C31) -> 2014.2 | D38: =SUM(D36,D31) -> 4271.5825 | E38: =SUM(E36,E31) -> -1525.5268 | F38: =SUM(F36,F31) -> 4760.2557
B40: Check | C40: =IF(C38=C15,"OK",C15-C38) -> OK | D40: =IF(D38=D15,"OK",D15-D38) -> OK | E40: =IF(E38=E15,"OK",E15-E38) -> OK | F40: =IF(F38=F15,"OK",F15-F38) -> OK

Sheet FS
A1: =CoName -> Company2272 | C1: Hist. | D1: Hist. | E1: Hist. | F1: Proj. | G1: Proj. | H1: Proj. | I1: Proj. | J1: Proj. | K1: Proj. | L1: Proj. | M1: Proj. | N1: Proj. | O1: Proj.
A2: =Ccy&Units&" unless otherwise stated" -> $m unless otherwise stated | C2: =DATE(YEAR(D2)-1,MONTH(D2),DAY(D2)) -> 41639 | D2: =DATE(YEAR(E2)-1,MONTH(E2),DAY(E2)) -> 42004 | E2: =Inputs!C16 -> 42369 | F2: =DATE(YEAR(E2)+1,MONTH(E2),DAY(E2)) -> 42735 | G2: =DATE(YEAR(F2)+1,MONTH(F2),DAY(F2)) -> 43100 | H2: =DATE(YEAR(G2)+1,MONTH(G2),DAY(G2)) -> 43465 | I2: =DATE(YEAR(H2)+1,MONTH(H2),DAY(H2)) -> 43830 | J2: =DATE(YEAR(I2)+1,MONTH(I2),DAY(I2)) -> 44196 | K2: =DATE(YEAR(J2)+1,MONTH(J2),DAY(J2)) -> 44561 | L2: =DATE(YEAR(K2)+1,MONTH(K2),DAY(K2)) -> 44926 | M2: =DATE(YEAR(L2)+1,MONTH(L2),DAY(L2)) -> 45291 | ... O2: =DATE(YEAR(N2)+1,MONTH(N2),DAY(N2)) -> 46022
A4: Income statement
B6: Sales | C6: =OpMod!C76 -> 1534.8 | D6: =OpMod!D76 -> 1794.4 | E6: =OpMod!E76 -> 2001.3 | F6: =OpMod!F76 -> 2231.4495 | G6: =OpMod!G76 -> 2454.5945 | H6: =OpMod!H76 -> 2675.508 | I6: =OpMod!I76 -> 2889.5486 | J6: =OpMod!J76 -> 3091.817 | ... O6: =OpMod!O76 -> 3796.7914
B8: EBITDA | C8: =OpMod!C78 -> 443.9 | D8: =OpMod!D78 -> 530.2 | E8: =OpMod!E78 -> 599.9 | F8: =OpMod!F78 -> 736.37833 | G8: =OpMod!G78 -> 810.01617 | H8: =OpMod!H78 -> 882.91762 | I8: =OpMod!I78 -> 953.55103 | J8: =OpMod!J78 -> 1020.2996 | ... O8: =OpMod!O78 -> 1252.9411
B9: Depreciation | F9: =OpMod!F79 -> -436.24 | G9: =OpMod!G79 -> -465.49749 | H9: =OpMod!H79 -> -493.81254 | I9: =OpMod!I79 -> -519.66931 | J9: =OpMod!J79 -> -541.80066 | K9: =OpMod!K79 -> -570.8945 | L9: =OpMod!L79 -> -603.03137 | M9: =OpMod!M79 -> -635.41006 | ... O9: =OpMod!O79 -> -693.03816
B10: Amortization of debt financing fees | F10: =Calcs!F18 -> -10.666667 | G10: =Calcs!G18 -> -10.666667 | H10: =Calcs!H18 -> -10.666667 | I10: =Calcs!I18 -> -10.666667 | J10: =Calcs!J18 -> -10.666667 | K10: =Calcs!K18 -> -10.666667 | L10: =Calcs!L18 -> 0 | M10: =Calcs!M18 -> 0 | ... O10: =Calcs!O18 -> 0
B11: Interest income on cash | F11: =IF(circ=1,Debt!F107,Debt!F98) -> 0.055786238 | G11: =IF(circ=1,Debt!G107,Debt!G98) -> 0.1171511 | H11: =IF(circ=1,Debt!H107,Debt!H98) -> 0.12825256 | I11: =IF(circ=1,Debt!I107,Debt!I98) -> 0.13912641 | J11: =IF(circ=1,Debt!J107,Debt!J98) -> 0.14953414 | K11: =IF(circ=1,Debt!K107,Debt!K98) -> 0.15922857 | L11: =IF(circ=1,Debt!L107,Debt!L98) -> 0.16796296 | M11: =IF(circ=1,Debt!M107,Debt!M98) -> 0.17550081 | ... O11: =IF(circ=1,Debt!O107,Debt!O98) -> 0.18707491
B12: Interest expense on revolver | F12: =IF(circ=1,Debt!F108,Debt!F99) -> 0 | G12: =IF(circ=1,Debt!G108,Debt!G99) -> 0 | H12: =IF(circ=1,Debt!H108,Debt!H99) -> 0 | I12: =IF(circ=1,Debt!I108,Debt!I99) -> 0 | J12: =IF(circ=1,Debt!J108,Debt!J99) -> 0 | K12: =IF(circ=1,Debt!K108,Debt!K99) -> 0 | L12: =IF(circ=1,Debt!L108,Debt!L99) -> -0.80749895 | M12: =IF(circ=1,Debt!M108,Debt!M99) -> -12.574909 | ... O12: =IF(circ=1,Debt!O108,Debt!O99) -> -47.081385
B13: Interest expense on Term debt A | F13: =IF(circ=1,Debt!F109,Debt!F100) -> -68.185415 | G13: =IF(circ=1,Debt!G109,Debt!G100) -> -63.59193 | H13: =IF(circ=1,Debt!H109,Debt!H100) -> -56.946514 | I13: =IF(circ=1,Debt!I109,Debt!I100) -> -47.660273 | J13: =IF(circ=1,Debt!J109,Debt!J100) -> -36.378987 | K13: =IF(circ=1,Debt!K109,Debt!K100) -> -23.809036 | L13: =IF(circ=1,Debt!L109,Debt!L100) -> -8.5903233 | M13: =IF(circ=1,Debt!M109,Debt!M100) -> 0 | ... O13: =IF(circ=1,Debt!O109,Debt!O100) -> 0
B14: Interest expense on Term debt B | F14: =IF(circ=1,Debt!F110,Debt!F101) -> -61.74 | G14: =IF(circ=1,Debt!G110,Debt!G101) -> -61.74 | H14: =IF(circ=1,Debt!H110,Debt!H101) -> -61.74 | I14: =IF(circ=1,Debt!I110,Debt!I101) -> -61.74 | J14: =IF(circ=1,Debt!J110,Debt!J101) -> -61.74 | K14: =IF(circ=1,Debt!K110,Debt!K101) -> -61.74 | L14: =IF(circ=1,Debt!L110,Debt!L101) -> -61.74 | M14: =IF(circ=1,Debt!M110,Debt!M101) -> -30.87 | ... O14: =IF(circ=1,Debt!O110,Debt!O101) -> 0
B15: Interest expense on high yield bond | F15: =Debt!F102 -> -51.75 | G15: =Debt!G102 -> -51.75 | H15: =Debt!H102 -> -51.75 | I15: =Debt!I102 -> -51.75 | J15: =Debt!J102 -> -51.75 | K15: =Debt!K102 -> -51.75 | L15: =Debt!L102 -> -51.75 | M15: =Debt!M102 -> -51.75 | ... O15: =Debt!O102 -> -51.75
B16: Interest expense on mezzanine finance | F16: =Debt!F103 -> -64.05 | G16: =Debt!G103 -> -72.254805 | H16: =Debt!H103 -> -81.510646 | I16: =Debt!I103 -> -91.952159 | J16: =Debt!J103 -> -103.73123 | K16: =Debt!K103 -> -117.0192 | L16: =Debt!L103 -> -132.00936 | M16: =Debt!M103 -> -148.91976 | ... O16: =Debt!O103 -> -189.51672
B17: Interest expense on shareholder loan | F17: =Debt!F104 -> -80.337379 | G17: =Debt!G104 -> -92.387986 | H17: =Debt!H104 -> -106.24618 | I17: =Debt!I104 -> -122.18311 | J17: =Debt!J104 -> -140.51058 | K17: =Debt!K104 -> -161.58716 | L17: =Debt!L104 -> -185.82524 | M17: =Debt!M104 -> -213.69903 | ... O17: =Debt!O104 -> -282.61696
B18: Income before tax | F18: =SUM(F8:F17) -> -36.53534 | G18: =SUM(G8:G17) -> -7.755554 | H18: =SUM(H8:H17) -> 20.373328 | I18: =SUM(I8:I17) -> 48.068642 | J18: =SUM(J8:J17) -> 73.871015 | K18: =SUM(K8:K17) -> 84.210239 | L18: =SUM(L8:L17) -> 92.007634 | M18: =SUM(M8:M17) -> 87.968942 | ... O18: =SUM(O8:O17) -> -10.875006
B20: Tax expense | F20: =-OpMod!F11*(F18-F17) -> -15.330714 | G20: =-OpMod!G11*(G18-G17) -> -29.621351 | H20: =-OpMod!H11*(H18-H17) -> -44.316829 | I20: =-OpMod!I11*(I18-I17) -> -59.588114 | J20: =-OpMod!J11*(J18-J17) -> -75.033557 | K20: =-OpMod!K11*(K18-K17) -> -86.029091 | L20: =-OpMod!L11*(L18-L17) -> -97.241506 | M20: =-OpMod!M11*(M18-M17) -> -105.58379 | ... O20: =-OpMod!O11*(O18-O17) -> -95.109684
B21: Net income | F21: =SUM(F18,F20) -> -51.866053 | G21: =SUM(G18,G20) -> -37.376905 | H21: =SUM(H18,H20) -> -23.943501 | I21: =SUM(I18,I20) -> -11.519472 | J21: =SUM(J18,J20) -> -1.1625428 | K21: =SUM(K18,K20) -> -1.8188522 | L21: =SUM(L18,L20) -> -5.233872 | M21: =SUM(M18,M20) -> -17.614846 | ... O21: =SUM(O18,O20) -> -105.98469
A23: Balance sheet
A25: Assets
B26: Cash and financial investments | E26: =BS!F7 -> 0 | F26: =F83 -> 11.157248 | G26: =G83 -> 12.272972 | H26: =H83 -> 13.37754 | I26: =I83 -> 14.447743 | J26: =J83 -> 15.459085 | K26: =K83 -> 16.38663 | L26: =L83 -> 17.205962 | M26: =M83 -> 17.8942 | ... O26: =O83 -> 18.983957
B27: Inventories | E27: =BS!F8 -> 0 | F27: =OpMod!F91 -> 0 | G27: =OpMod!G91 -> 0 | H27: =OpMod!H91 -> 0 | I27: =OpMod!I91 -> 0 | J27: =OpMod!J91 -> 0 | K27: =OpMod!K91 -> 0 | L27: =OpMod!L91 -> 0 | M27: =OpMod!M91 -> 0 | ... O27: =OpMod!O91 -> 0
B28: Trade and other receivables | E28: =BS!F9 -> 233.7 | F28: =OpMod!F92 -> 267.77394 | G28: =OpMod!G92 -> 294.55133 | H28: =OpMod!H92 -> 321.06095 | I28: =OpMod!I92 -> 346.74583 | J28: =OpMod!J92 -> 371.01804 | K28: =OpMod!K92 -> 393.27912 | L28: =OpMod!L92 -> 412.94308 | M28: =OpMod!M92 -> 429.4608 | ... O28: =OpMod!O92 -> 455.61496
B29: Total current assets | E29: =SUM(E26:E28) -> 233.7 | F29: =SUM(F26:F28) -> 278.93119 | G29: =SUM(G26:G28) -> 306.82431 | H29: =SUM(H26:H28) -> 334.43849 | I29: =SUM(I26:I28) -> 361.19357 | J29: =SUM(J26:J28) -> 386.47712 | K29: =SUM(K26:K28) -> 409.66575 | L29: =SUM(L26:L28) -> 430.14904 | ... O29: =SUM(O26:O28) -> 474.59892
B31: Property, plant and equipment | E31: =BS!F12 -> 1148 | F31: =OpMod!F88 -> 1224.9934 | G31: =OpMod!G88 -> 1299.5067 | H31: =OpMod!H88 -> 1367.5508 | I31: =OpMod!I88 -> 1425.7912 | J31: =OpMod!J88 -> 1502.354 | K31: =OpMod!K88 -> 1586.9247 | L31: =OpMod!L88 -> 1672.1317 | M31: =OpMod!M88 -> 1752.4897 | ... O31: =OpMod!O88 -> 1890.1047
B32: Goodwill | E32: =BS!F13 -> 3311.8557 | F32: =$E$32 -> 3311.8557 | G32: =$E$32 -> 3311.8557 | H32: =$E$32 -> 3311.8557 | I32: =$E$32 -> 3311.8557 | J32: =$E$32 -> 3311.8557 | K32: =$E$32 -> 3311.8557 | L32: =$E$32 -> 3311.8557 | M32: =$E$32 -> 3311.8557 | ... O32: =$E$32 -> 3311.8557
B33: Other LT assets | E33: =BS!F14 -> 66.7 | F33: =OpMod!F98 -> 73.637833 | G33: =OpMod!G98 -> 81.001617 | H33: =OpMod!H98 -> 88.291762 | I33: =OpMod!I98 -> 95.355103 | J33: =OpMod!J98 -> 102.02996 | K33: =OpMod!K98 -> 108.15176 | L33: =OpMod!L98 -> 113.55935 | M33: =OpMod!M98 -> 118.10172 | ... O33: =OpMod!O98 -> 125.29411
B34: Total assets | E34: =SUM(E29,E31:E33) -> 4760.2557 | F34: =SUM(F29,F31:F33) -> 4889.4181 | G34: =SUM(G29,G31:G33) -> 4999.1883 | H34: =SUM(H29,H31:H33) -> 5102.1368 | I34: =SUM(I29,I31:I33) -> 5194.1956 | J34: =SUM(J29,J31:J33) -> 5302.7167 | K34: =SUM(K29,K31:K33) -> 5416.5979 | L34: =SUM(L29,L31:L33) -> 5527.6958 | ... O34: =SUM(O29,O31:O33) -> 5801.8535
A36: Liabilities and equity
B37: Short-term debt | E37: =BS!F18 -> 0 | F37: =E37 -> 0 | G37: =F37 -> 0 | H37: =G37 -> 0 | I37: =H37 -> 0 | J37: =I37 -> 0 | K37: =J37 -> 0 | L37: =K37 -> 0 | M37: =L37 -> 0 | ... O37: =N37 -> 0
B38: Revolver | E38: =BS!F19 -> 0 | F38: =Debt!F81 -> 0 | G38: =Debt!G81 -> 0 | H38: =Debt!H81 -> 0 | I38: =Debt!I81 -> 0 | J38: =Debt!J81 -> 0 | K38: =Debt!K81 -> 0 | L38: =Debt!L81 -> 45.492899 | M38: =Debt!M81 -> 662.9527 | ... O38: =Debt!O81 -> 2303.6138
B39: Trade and other payables | E39: =BS!F20 -> 136.3 | F39: =OpMod!F93 -> 178.51596 | G39: =OpMod!G93 -> 196.36756 | H39: =OpMod!H93 -> 214.04064 | I39: =OpMod!I93 -> 231.16389 | J39: =OpMod!J93 -> 247.34536 | K39: =OpMod!K93 -> 262.18608 | L39: =OpMod!L93 -> 275.29538 | M39: =OpMod!M93 -> 286.3072 | ... O39: =OpMod!O93 -> 303.74331
B40: Other current liabilities | E40: =BS!F21 -> 98.9 | F40: =OpMod!F94 -> 111.57247 | G40: =OpMod!G94 -> 122.72972 | H40: =OpMod!H94 -> 133.7754 | I40: =OpMod!I94 -> 144.47743 | J40: =OpMod!J94 -> 154.59085 | K40: =OpMod!K94 -> 163.8663 | L40: =OpMod!L94 -> 172.05962 | M40: =OpMod!M94 -> 178.942 | ... O40: =OpMod!O94 -> 189.83957
B41: Total current liabilities | E41: =SUM(E37:E40) -> 235.2 | F41: =SUM(F37:F40) -> 290.08844 | G41: =SUM(G37:G40) -> 319.09728 | H41: =SUM(H37:H40) -> 347.81603 | I41: =SUM(I37:I40) -> 375.64132 | J41: =SUM(J37:J40) -> 401.93621 | K41: =SUM(K37:K40) -> 426.05238 | L41: =SUM(L37:L40) -> 492.8479 | ... O41: =SUM(O37:O40) -> 2797.1967
B43: Long-term debt | E43: =BS!F24 -> 0 | F43: =E43 -> 0 | G43: =F43 -> 0 | H43: =G43 -> 0 | I43: =H43 -> 0 | J43: =I43 -> 0 | K43: =J43 -> 0 | L43: =K43 -> 0 | M43: =L43 -> 0 | ... O43: =N43 -> 0
B44: Term debt A | E44: =BS!F25 -> 1200 | F44: =Debt!F82 -> 1135.117 | G44: =Debt!G82 -> 1042.6889 | H44: =Debt!H82 -> 907.53424 | I44: =Debt!I82 -> 724.6669 | J44: =Debt!J82 -> 521.18881 | K44: =Debt!K82 -> 294.18915 | L44: =Debt!L82 -> 0 | M44: =Debt!M82 -> 0 | ... O44: =Debt!O82 -> 0
B45: Term debt B | E45: =BS!F26 -> 900 | F45: =Debt!F83 -> 900 | G45: =Debt!G83 -> 900 | H45: =Debt!H83 -> 900 | I45: =Debt!I83 -> 900 | J45: =Debt!J83 -> 900 | K45: =Debt!K83 -> 900 | L45: =Debt!L83 -> 900 | M45: =Debt!M83 -> 0 | ... O45: =Debt!O83 -> 0
B46: High yield | E46: =BS!F27 -> 600 | F46: =Debt!F84 -> 600 | G46: =Debt!G84 -> 600 | H46: =Debt!H84 -> 600 | I46: =Debt!I84 -> 600 | J46: =Debt!J84 -> 600 | K46: =Debt!K84 -> 600 | L46: =Debt!L84 -> 600 | M46: =Debt!M84 -> 600 | ... O46: =Debt!O84 -> 0
B47: Mezzanine (PIK) | E47: =BS!F28 -> 500 | F47: =Debt!F85 -> 564.05 | G47: =Debt!G85 -> 636.3048 | H47: =Debt!H85 -> 717.81545 | I47: =Debt!I85 -> 809.76761 | J47: =Debt!J85 -> 913.49884 | K47: =Debt!K85 -> 1030.518 | L47: =Debt!L85 -> 1162.5274 | M47: =Debt!M85 -> 1311.4472 | ... O47: =Debt!O85 -> 0
B48: Debt financing fees | E48: =BS!F29 -> -64 | F48: =-Calcs!F19 -> -53.333333 | G48: =-Calcs!G19 -> -42.666667 | H48: =-Calcs!H19 -> -32 | I48: =-Calcs!I19 -> -21.333333 | J48: =-Calcs!J19 -> -10.666667 | K48: =-Calcs!K19 -> 0 | L48: =-Calcs!L19 -> 0 | M48: =-Calcs!M19 -> 0 | ... O48: =-Calcs!O19 -> 0
B49: Other LT liabilities | E49: =BS!F30 -> 316.6 | F49: =OpMod!F99 -> 352.56902 | G49: =OpMod!G99 -> 387.82592 | H49: =OpMod!H99 -> 422.73026 | I49: =OpMod!I99 -> 456.54868 | J49: =OpMod!J99 -> 488.50708 | K49: =OpMod!K99 -> 517.81751 | L49: =OpMod!L99 -> 543.70838 | M49: =OpMod!M99 -> 565.45672 | ... O49: =OpMod!O99 -> 599.89303
B50: Total liabilities | E50: =SUM(E41,E43:E49) -> 3687.8 | F50: =SUM(F41,F43:F49) -> 3788.4911 | G50: =SUM(G41,G43:G49) -> 3843.2502 | H50: =SUM(H41,H43:H49) -> 3863.896 | I50: =SUM(I41,I43:I49) -> 3845.2912 | J50: =SUM(J41,J43:J49) -> 3814.4643 | K50: =SUM(K41,K43:K49) -> 3768.5771 | L50: =SUM(L41,L43:L49) -> 3699.0837 | ... O50: =SUM(O41,O43:O49) -> 3397.0897
B52: Shareholder loan | E52: =BS!F33 -> 535.58253 | F52: =Debt!F86 -> 615.91991 | G52: =Debt!G86 -> 708.30789 | H52: =Debt!H86 -> 814.55408 | I52: =Debt!I86 -> 936.73719 | J52: =Debt!J86 -> 1077.2478 | K52: =Debt!K86 -> 1238.8349 | L52: =Debt!L86 -> 1424.6602 | M52: =Debt!M86 -> 1638.3592 | ... O52: =Debt!O86 -> 2166.73
B53: Ordinary equity | E53: =BS!F34 -> 600 | F53: =E53 -> 600 | G53: =F53 -> 600 | H53: =G53 -> 600 | I53: =H53 -> 600 | J53: =I53 -> 600 | K53: =J53 -> 600 | L53: =K53 -> 600 | M53: =L53 -> 600 | ... O53: =N53 -> 600
B54: Retained earnings (deficit) | E54: =BS!F35 -> -63.126835 | F54: =Calcs!F25 -> -114.99289 | G54: =Calcs!G25 -> -152.36979 | H54: =Calcs!H25 -> -176.31329 | I54: =Calcs!I25 -> -187.83277 | J54: =Calcs!J25 -> -188.99531 | K54: =Calcs!K25 -> -190.81416 | L54: =Calcs!L25 -> -196.04803 | M54: =Calcs!M25 -> -213.66288 | ... O54: =Calcs!O25 -> -361.96625
B55: Shareholders equity | E55: =SUM(E52:E54) -> 1072.4557 | F55: =SUM(F52:F54) -> 1100.927 | G55: =SUM(G52:G54) -> 1155.9381 | H55: =SUM(H52:H54) -> 1238.2408 | I55: =SUM(I52:I54) -> 1348.9044 | J55: =SUM(J52:J54) -> 1488.2525 | K55: =SUM(K52:K54) -> 1648.0208 | L55: =SUM(L52:L54) -> 1828.6121 | ... O55: =SUM(O52:O54) -> 2404.7638
B57: Total liabilities & equity | E57: =SUM(E50,E55) -> 4760.2557 | F57: =SUM(F50,F55) -> 4889.4181 | G57: =SUM(G50,G55) -> 4999.1883 | H57: =SUM(H50,H55) -> 5102.1368 | I57: =SUM(I50,I55) -> 5194.1956 | J57: =SUM(J50,J55) -> 5302.7167 | K57: =SUM(K50,K55) -> 5416.5979 | L57: =SUM(L50,L55) -> 5527.6958 | ... O57: =SUM(O50,O55) -> 5801.8535
B59: Check | E59: =IF(E57=E34,"OK",E57-E34) -> OK | F59: =IF(F57=F34,"OK",F57-F34) -> OK | G59: =IF(G57=G34,"OK",G57-G34) -> OK | H59: =IF(H57=H34,"OK",H57-H34) -> OK | I59: =IF(I57=I34,"OK",I57-I34) -> OK | J59: =IF(J57=J34,"OK",J57-J34) -> OK | K59: =IF(K57=K34,"OK",K57-K34) -> OK | L59: =IF(L57=L34,"OK",L57-L34) -> OK | ... O59: =IF(O57=O34,"OK",O57-O34) -> OK
A61: Cash flow statement
B62: EBITDA | C62: =C8 -> 443.9 | D62: =D8 -> 530.2 | E62: =E8 -> 599.9 | F62: =F8 -> 736.37833 | G62: =G8 -> 810.01617 | H62: =H8 -> 882.91762 | I62: =I8 -> 953.55103 | J62: =J8 -> 1020.2996 | ... O62: =O8 -> 1252.9411
B63: Cash taxes | F63: =F20 -> -15.330714 | G63: =G20 -> -29.621351 | H63: =H20 -> -44.316829 | I63: =I20 -> -59.588114 | J63: =J20 -> -75.033557 | K63: =K20 -> -86.029091 | L63: =L20 -> -97.241506 | M63: =M20 -> -105.58379 | ... O63: =O20 -> -95.109684
B64: (Increase) decrease in operating working capital | F64: =OpMod!E95-OpMod!F95 -> 20.814495 | G64: =OpMod!F95-OpMod!G95 -> 2.2314495 | H64: =OpMod!G95-OpMod!H95 -> 2.209135 | I64: =OpMod!H95-OpMod!I95 -> 2.1404064 | J64: =OpMod!I95-OpMod!J95 -> 2.022684 | K64: =OpMod!J95-OpMod!K95 -> 1.8550902 | L64: =OpMod!K95-OpMod!L95 -> 1.638663 | M64: =OpMod!L95-OpMod!M95 -> 1.3764769 | ... O64: =OpMod!N95-OpMod!O95 -> 1.1058616
B65: Change in other long-term assets | F65: =E33-F33 -> -6.9378335 | G65: =F33-G33 -> -7.3637834 | H65: =G33-H33 -> -7.2901455 | I65: =H33-I33 -> -7.063341 | J65: =I33-J33 -> -6.6748572 | K65: =J33-K33 -> -6.1217976 | L65: =K33-L33 -> -5.4075879 | M65: =L33-M33 -> -4.5423738 | ... O65: =N33-O33 -> -3.6493431
B66: Change in other long term liabilities | F66: =F49-E49 -> 35.969021 | G66: =G49-F49 -> 35.256902 | H66: =H49-G49 -> 34.904333 | I66: =I49-H49 -> 33.81842 | J66: =J49-I49 -> 31.958407 | K66: =K49-J49 -> 29.310425 | L66: =L49-K49 -> 25.890875 | M66: =M49-L49 -> 21.748335 | ... O66: =O49-N49 -> 17.472613
B67: (Capital expenditure) | F67: =-OpMod!F86 -> -513.23338 | G67: =-OpMod!G86 -> -540.01078 | H67: =-OpMod!H86 -> -561.85667 | I67: =-OpMod!I86 -> -577.90972 | J67: =-OpMod!J86 -> -618.3634 | K67: =-OpMod!K86 -> -655.4652 | L67: =-OpMod!L86 -> -688.23846 | M67: =-OpMod!M86 -> -715.768 | ... O67: =-OpMod!O86 -> -759.35827
B68: Cash flow available for debt service | F68: =SUM(F62:F67) -> 257.65992 | G68: =SUM(G62:G67) -> 270.50861 | H68: =SUM(H62:H67) -> 306.56745 | I68: =SUM(I62:I67) -> 344.94869 | J68: =SUM(J62:J67) -> 354.20889 | K68: =SUM(K62:K67) -> 365.06701 | L68: =SUM(L62:L67) -> 372.23544 | M68: =SUM(M62:M67) -> 378.24785 | ... O68: =SUM(O62:O67) -> 413.40232
B70: Interest income on cash | F70: =F11 -> 0.055786238 | G70: =G11 -> 0.1171511 | H70: =H11 -> 0.12825256 | I70: =I11 -> 0.13912641 | J70: =J11 -> 0.14953414 | K70: =K11 -> 0.15922857 | L70: =L11 -> 0.16796296 | M70: =M11 -> 0.17550081 | ... O70: =O11 -> 0.18707491
B71: Interest expense on revolver | F71: =F12 -> 0 | G71: =G12 -> 0 | H71: =H12 -> 0 | I71: =I12 -> 0 | J71: =J12 -> 0 | K71: =K12 -> 0 | L71: =L12 -> -0.80749895 | M71: =M12 -> -12.574909 | ... O71: =O12 -> -47.081385
B72: Term debt A interest expense | F72: =F13 -> -68.185415 | G72: =G13 -> -63.59193 | H72: =H13 -> -56.946514 | I72: =I13 -> -47.660273 | J72: =J13 -> -36.378987 | K72: =K13 -> -23.809036 | L72: =L13 -> -8.5903233 | M72: =M13 -> 0 | ... O72: =O13 -> 0
B73: Term debt B interest expense | F73: =F14 -> -61.74 | G73: =G14 -> -61.74 | H73: =H14 -> -61.74 | I73: =I14 -> -61.74 | J73: =J14 -> -61.74 | K73: =K14 -> -61.74 | L73: =L14 -> -61.74 | M73: =M14 -> -30.87 | ... O73: =O14 -> 0
B74: Interest on high yield bond | F74: =F15 -> -51.75 | G74: =G15 -> -51.75 | H74: =H15 -> -51.75 | I74: =I15 -> -51.75 | J74: =J15 -> -51.75 | K74: =K15 -> -51.75 | L74: =L15 -> -51.75 | M74: =M15 -> -51.75 | ... O74: =O15 -> -51.75
B75: Cash flow available for debt repayment | F75: =SUM(F68,F70:F74) -> 76.04029 | G75: =SUM(G68,G70:G74) -> 93.543828 | H75: =SUM(H68,H70:H74) -> 136.25919 | I75: =SUM(I68,I70:I74) -> 183.93754 | J75: =SUM(J68,J70:J74) -> 204.48943 | K75: =SUM(K68,K70:K74) -> 227.9272 | L75: =SUM(L68,L70:L74) -> 249.51559 | M75: =SUM(M68,M70:M74) -> 283.22844 | ... O75: =SUM(O68,O70:O74) -> 314.75801
B77: Issuance (repayment) of revolver | F77: =F38-E38 -> 0 | G77: =G38-F38 -> 0 | H77: =H38-G38 -> 0 | I77: =I38-H38 -> 0 | J77: =J38-I38 -> 0 | K77: =K38-J38 -> 0 | L77: =L38-K38 -> 45.492899 | M77: =M38-L38 -> 617.4598 | ... O77: =O38-N38 -> 1954.7552
B78: Repayment of term debt A | F78: =F44-E44 -> -64.883042 | G78: =G44-F44 -> -92.428103 | H78: =H44-G44 -> -135.15462 | I78: =I44-H44 -> -182.86734 | J78: =J44-I44 -> -203.47809 | K78: =K44-J44 -> -226.99965 | L78: =L44-K44 -> -294.18915 | M78: =M44-L44 -> 0 | ... O78: =O44-N44 -> 0
B79: Repayment of term debt B | F79: =F45-E45 -> 0 | G79: =G45-F45 -> 0 | H79: =H45-G45 -> 0 | I79: =I45-H45 -> 0 | J79: =J45-I45 -> 0 | K79: =K45-J45 -> 0 | L79: =L45-K45 -> 0 | M79: =M45-L45 -> -900 | ... O79: =O45-N45 -> 0
B80: Repayment of high yield bond | F80: =F46-E46 -> 0 | G80: =G46-F46 -> 0 | H80: =H46-G46 -> 0 | I80: =I46-H46 -> 0 | J80: =J46-I46 -> 0 | K80: =K46-J46 -> 0 | L80: =L46-K46 -> 0 | M80: =M46-L46 -> 0 | ... O80: =O46-N46 -> -600
B81: Repayment of mezzanine | F81: =Debt!F67 -> 0 | G81: =Debt!G67 -> 0 | H81: =Debt!H67 -> 0 | I81: =Debt!I67 -> 0 | J81: =Debt!J67 -> 0 | K81: =Debt!K67 -> 0 | L81: =Debt!L67 -> 0 | M81: =Debt!M67 -> 0 | ... O81: =Debt!O67 -> -1668.9603
B82: Net cash flow | F82: =SUM(F75,F77:F81) -> 11.157248 | G82: =SUM(G75,G77:G81) -> 1.1157247 | H82: =SUM(H75,H77:H81) -> 1.1045675 | I82: =SUM(I75,I77:I81) -> 1.0702032 | J82: =SUM(J75,J77:J81) -> 1.011342 | K82: =SUM(K75,K77:K81) -> 0.9275451 | L82: =SUM(L75,L77:L81) -> 0.8193315 | M82: =SUM(M75,M77:M81) -> 0.68823846 | ... O82: =SUM(O75,O77:O81) -> 0.55293078
B83: Cash balance | E83: =E26 -> 0 | F83: =E83+F82 -> 11.157248 | G83: =F83+G82 -> 12.272972 | H83: =G83+H82 -> 13.37754 | I83: =H83+I82 -> 14.447743 | J83: =I83+J82 -> 15.459085 | K83: =J83+K82 -> 16.38663 | L83: =K83+L82 -> 17.205962 | M83: =L83+M82 -> 17.8942 | ... O83: =N83+O82 -> 18.983957

Sheet Debt
A1: =CoName -> Company2272 | E1: Hist. | F1: Proj. | G1: Proj. | H1: Proj. | I1: Proj. | J1: Proj. | K1: Proj. | L1: Proj. | M1: Proj. | N1: Proj. | O1: Proj.
A2: =Ccy&Units&" unless otherwise stated" -> $m unless otherwise stated | E2: =Inputs!C16 -> 42369 | F2: =DATE(YEAR(E2)+1,MONTH(E2),DAY(E2)) -> 42735 | G2: =DATE(YEAR(F2)+1,MONTH(F2),DAY(F2)) -> 43100 | H2: =DATE(YEAR(G2)+1,MONTH(G2),DAY(G2)) -> 43465 | I2: =DATE(YEAR(H2)+1,MONTH(H2),DAY(H2)) -> 43830 | J2: =DATE(YEAR(I2)+1,MONTH(I2),DAY(I2)) -> 44196 | K2: =DATE(YEAR(J2)+1,MONTH(J2),DAY(J2)) -> 44561 | L2: =DATE(YEAR(K2)+1,MONTH(K2),DAY(K2)) -> 44926 | M2: =DATE(YEAR(L2)+1,MONTH(L2),DAY(L2)) -> 45291 | ... O2: =DATE(YEAR(N2)+1,MONTH(N2),DAY(N2)) -> 46022
A4: Cash available for debt repayment
B6: Minimum cash as % of sales | F6: 0.005 | G6: 0.005 | H6: 0.005 | I6: 0.005 | J6: 0.005 | K6: 0.005 | L6: 0.005 | M6: 0.005 | N6: 0.005 | O6: 0.005
B8: Beginning cash | F8: =FS!E83 -> 0 | G8: =FS!F83 -> 11.157248 | H8: =FS!G83 -> 12.272972 | I8: =FS!H83 -> 13.37754 | J8: =FS!I83 -> 14.447743 | K8: =FS!J83 -> 15.459085 | L8: =FS!K83 -> 16.38663 | M8: =FS!L83 -> 17.205962 | ... O8: =FS!N83 -> 18.431026
B9: Cash flow available for debt repayment | F9: =FS!F75 -> 76.04029 | G9: =FS!G75 -> 93.543828 | H9: =FS!H75 -> 136.25919 | I9: =FS!I75 -> 183.93754 | J9: =FS!J75 -> 204.48943 | K9: =FS!K75 -> 227.9272 | L9: =FS!L75 -> 249.51559 | M9: =FS!M75 -> 283.22844 | ... O9: =FS!O75 -> 314.75801
B10: Minimum cash required | F10: =F6*OpMod!F76 -> 11.157247 | G10: =G6*OpMod!G76 -> 12.272972 | H10: =H6*OpMod!H76 -> 13.37754 | I10: =I6*OpMod!I76 -> 14.447743 | J10: =J6*OpMod!J76 -> 15.459085 | K10: =K6*OpMod!K76 -> 16.38663 | L10: =L6*OpMod!L76 -> 17.205962 | M10: =M6*OpMod!M76 -> 17.8942 | ... O10: =O6*OpMod!O76 -> 18.983957
B11: Cash available for debt repayment | F11: =F8+F9-F10 -> 64.883042 | G11: =G8+G9-G10 -> 92.428103 | H11: =H8+H9-H10 -> 135.15462 | I11: =I8+I9-I10 -> 182.86734 | J11: =J8+J9-J10 -> 203.47809 | K11: =K8+K9-K10 -> 226.99965 | L11: =L8+L9-L10 -> 248.69625 | M11: =M8+M9-M10 -> 282.5402 | ... O11: =O8+O9-O10 -> 314.20508
A13: Mandated repayments
A15: Mandated repayment terms
B16: Term debt A | F16: 0.025 | G16: 0.025 | H16: 0.05 | I16: 0.05 | J16: 0.05 | K16: 0.05 | L16: 0.75 | M16: 0 | N16: 0 | O16: 0
B17: Term debt B | F17: 0 | G17: 0 | H17: 0 | I17: 0 | J17: 0 | K17: 0 | L17: 0 | M17: 1 | N17: 0 | O17: 0
B18: High Yield | O18: 1
B19: Mezzanine (PIK) | O19: 1
A21: Mandated repayment amounts
B22: Term debt A | F22: =F47 -> -30 | G22: =G47 -> -30 | H22: =H47 -> -60 | I22: =I47 -> -60 | J22: =J47 -> -60 | K22: =K47 -> -60 | L22: =L47 -> -294.18915 | M22: =M47 -> 0 | ... O22: =O47 -> 0
B23: Term debt B | F23: =F55 -> 0 | G23: =G55 -> 0 | H23: =H55 -> 0 | I23: =I55 -> 0 | J23: =J55 -> 0 | K23: =K55 -> 0 | L23: =L55 -> 0 | M23: =M55 -> -900 | ... O23: =O55 -> 0
B24: High Yield | F24: =F61 -> 0 | G24: =G61 -> 0 | H24: =H61 -> 0 | I24: =I61 -> 0 | J24: =J61 -> 0 | K24: =K61 -> 0 | L24: =L61 -> 0 | M24: =M61 -> 0 | ... O24: =O61 -> -600
B25: Mezzanine (PIK) | F25: =F67 -> 0 | G25: =G67 -> 0 | H25: =H67 -> 0 | I25: =I67 -> 0 | J25: =J67 -> 0 | K25: =K67 -> 0 | L25: =L67 -> 0 | M25: =M67 -> 0 | ... O25: =O67 -> -1668.9603
A27: Cash available after mandated repayment
B28: Cash available for debt repayment | F28: =F11 -> 64.883042 | G28: =G11 -> 92.428103 | H28: =H11 -> 135.15462 | I28: =I11 -> 182.86734 | J28: =J11 -> 203.47809 | K28: =K11 -> 226.99965 | L28: =L11 -> 248.69625 | M28: =M11 -> 282.5402 | ... O28: =O11 -> 314.20508
B29: Mandated payment amount | F29: =SUM(F22:F25) -> -30 | G29: =SUM(G22:G25) -> -30 | H29: =SUM(H22:H25) -> -60 | I29: =SUM(I22:I25) -> -60 | J29: =SUM(J22:J25) -> -60 | K29: =SUM(K22:K25) -> -60 | L29: =SUM(L22:L25) -> -294.18915 | M29: =SUM(M22:M25) -> -900 | ... O29: =SUM(O22:O25) -> -2268.9603
B30: Cash available after mandated repayment | F30: =SUM(F28:F29) -> 34.883042 | G30: =SUM(G28:G29) -> 62.428103 | H30: =SUM(H28:H29) -> 75.154618 | I30: =SUM(I28:I29) -> 122.86734 | J30: =SUM(J28:J29) -> 143.47809 | K30: =SUM(K28:K29) -> 166.99965 | L30: =SUM(L28:L29) -> -45.492899 | M30: =SUM(M28:M29) -> -617.4598 | ... O30: =SUM(O28:O29) -> -1954.7552
A32: Revolving credit facility
B34: Beginning balance | F34: =E36 -> 0 | G34: =F36 -> 0 | H34: =G36 -> 0 | I34: =H36 -> 0 | J34: =I36 -> 0 | K34: =J36 -> 0 | L34: =K36 -> 0 | M34: =L36 -> 45.492899 | ... O34: =N36 -> 348.8586
B35: Issuance (repayment) | F35: =-MIN(F34,F30) -> 0 | G35: =-MIN(G34,G30) -> 0 | H35: =-MIN(H34,H30) -> 0 | I35: =-MIN(I34,I30) -> 0 | J35: =-MIN(J34,J30) -> 0 | K35: =-MIN(K34,K30) -> 0 | L35: =-MIN(L34,L30) -> 45.492899 | M35: =-MIN(M34,M30) -> 617.4598 | ... O35: =-MIN(O34,O30) -> 1954.7552
B36: Ending balance | E36: ='S&U'!C40 -> 0 | F36: =SUM(F34:F35) -> 0 | G36: =SUM(G34:G35) -> 0 | H36: =SUM(H34:H35) -> 0 | I36: =SUM(I34:I35) -> 0 | J36: =SUM(J34:J35) -> 0 | K36: =SUM(K34:K35) -> 0 | L36: =SUM(L34:L35) -> 45.492899 | M36: =SUM(M34:M35) -> 662.9527 | ... O36: =SUM(O34:O35) -> 2303.6138
A38: Cash sweep
B40: Cash flow available for accelerated repayment after servicing revolver | F40: =SUM(F30,F35) -> 34.883042 | G40: =SUM(G30,G35) -> 62.428103 | H40: =SUM(H30,H35) -> 75.154618 | I40: =SUM(I30,I35) -> 122.86734 | J40: =SUM(J30,J35) -> 143.47809 | K40: =SUM(K30,K35) -> 166.99965 | L40: =SUM(L30,L35) -> 0 | M40: =SUM(M30,M35) -> 0 | ... O40: =SUM(O30,O35) -> 0
B41: % of surplus cash used to sweep debt | F41: 1 | G41: 1 | H41: 1 | I41: 1 | J41: 1 | K41: 1 | L41: 1 | M41: 1 | N41: 1 | O41: 1
B42: Cash used in sweep | F42: =F40*F41 -> 34.883042 | G42: =G40*G41 -> 62.428103 | H42: =H40*H41 -> 75.154618 | I42: =I40*I41 -> 122.86734 | J42: =J40*J41 -> 143.47809 | K42: =K40*K41 -> 166.99965 | L42: =L40*L41 -> 0 | M42: =M40*M41 -> 0 | ... O42: =O40*O41 -> 0
A44: Debt balances and accelerated repayments
A45: Term debt A
B46: Beginning balance | F46: =E49 -> 1200 | G46: =F49 -> 1135.117 | H46: =G49 -> 1042.6889 | I46: =H49 -> 907.53424 | J46: =I49 -> 724.6669 | K46: =J49 -> 521.18881 | L46: =K49 -> 294.18915 | M46: =L49 -> 0 | ... O46: =N49 -> 0
B47: Mandated repayment | F47: =-MIN(F46,F16*$E$49) -> -30 | G47: =-MIN(G46,G16*$E$49) -> -30 | H47: =-MIN(H46,H16*$E$49) -> -60 | I47: =-MIN(I46,I16*$E$49) -> -60 | J47: =-MIN(J46,J16*$E$49) -> -60 | K47: =-MIN(K46,K16*$E$49) -> -60 | L47: =-MIN(L46,L16*$E$49) -> -294.18915 | M47: =-MIN(M46,M16*$E$49) -> 0 | ... O47: =-MIN(O46,O16*$E$49) -> 0
B48: Accelerated repayment | C48: 1 | F48: =-MIN(F46+F47,F42)*$C$48 -> -34.883042 | G48: =-MIN(G46+G47,G42)*$C$48 -> -62.428103 | H48: =-MIN(H46+H47,H42)*$C$48 -> -75.154618 | I48: =-MIN(I46+I47,I42)*$C$48 -> -122.86734 | J48: =-MIN(J46+J47,J42)*$C$48 -> -143.47809 | K48: =-MIN(K46+K47,K42)*$C$48 -> -166.99965 | L48: =-MIN(L46+L47,L42)*$C$48 -> 0 | M48: =-MIN(M46+M47,M42)*$C$48 -> 0 | ... O48: =-MIN(O46+O47,O42)*$C$48 -> 0
B49: Ending balance | E49: ='S&U'!C41 -> 1200 | F49: =SUM(F46:F48) -> 1135.117 | G49: =SUM(G46:G48) -> 1042.6889 | H49: =SUM(H46:H48) -> 907.53424 | I49: =SUM(I46:I48) -> 724.6669 | J49: =SUM(J46:J48) -> 521.18881 | K49: =SUM(K46:K48) -> 294.18915 | L49: =SUM(L46:L48) -> 0 | M49: =SUM(M46:M48) -> 0 | ... O49: =SUM(O46:O48) -> 0
B51: Cash available for term debt B accelerated repayment | F51: =SUM(F42,F48) -> 0 | G51: =SUM(G42,G48) -> 0 | H51: =SUM(H42,H48) -> 0 | I51: =SUM(I42,I48) -> 0 | J51: =SUM(J42,J48) -> 0 | K51: =SUM(K42,K48) -> 0 | L51: =SUM(L42,L48) -> 0 | M51: =SUM(M42,M48) -> 0 | ... O51: =SUM(O42,O48) -> 0
A53: Term debt B
B54: Beginning balance | F54: =E57 -> 900 | G54: =F57 -> 900 | H54: =G57 -> 900 | I54: =H57 -> 900 | J54: =I57 -> 900 | K54: =J57 -> 900 | L54: =K57 -> 900 | M54: =L57 -> 900 | ... O54: =N57 -> 0
B55: Mandated repayment | F55: =-MIN(F54,F17*$E$57) -> 0 | G55: =-MIN(G54,G17*$E$57) -> 0 | H55: =-MIN(H54,H17*$E$57) -> 0 | I55: =-MIN(I54,I17*$E$57) -> 0 | J55: =-MIN(J54,J17*$E$57) -> 0 | K55: =-MIN(K54,K17*$E$57) -> 0 | L55: =-MIN(L54,L17*$E$57) -> 0 | M55: =-MIN(M54,M17*$E$57) -> -900 | ... O55: =-MIN(O54,O17*$E$57) -> 0
B56: Accelerated repayment | C56: 0 | F56: =-MIN(F54+F55,F51)*$C$56 -> 0 | G56: =-MIN(G54+G55,G51)*$C$56 -> 0 | H56: =-MIN(H54+H55,H51)*$C$56 -> 0 | I56: =-MIN(I54+I55,I51)*$C$56 -> 0 | J56: =-MIN(J54+J55,J51)*$C$56 -> 0 | K56: =-MIN(K54+K55,K51)*$C$56 -> 0 | L56: =-MIN(L54+L55,L51)*$C$56 -> 0 | M56: =-MIN(M54+M55,M51)*$C$56 -> 0 | ... O56: =-MIN(O54+O55,O51)*$C$56 -> 0
B57: Ending balance | E57: ='S&U'!C42 -> 900 | F57: =SUM(F54:F56) -> 900 | G57: =SUM(G54:G56) -> 900 | H57: =SUM(H54:H56) -> 900 | I57: =SUM(I54:I56) -> 900 | J57: =SUM(J54:J56) -> 900 | K57: =SUM(K54:K56) -> 900 | L57: =SUM(L54:L56) -> 900 | M57: =SUM(M54:M56) -> 0 | ... O57: =SUM(O54:O56) -> 0
A59: High yield
B60: Beginning balance | F60: =E62 -> 600 | G60: =F62 -> 600 | H60: =G62 -> 600 | I60: =H62 -> 600 | J60: =I62 -> 600 | K60: =J62 -> 600 | L60: =K62 -> 600 | M60: =L62 -> 600 | ... O60: =N62 -> 600
B61: Mandated repayment | F61: =-MIN(F60,F18*$E$62) -> 0 | G61: =-MIN(G60,G18*$E$62) -> 0 | H61: =-MIN(H60,H18*$E$62) -> 0 | I61: =-MIN(I60,I18*$E$62) -> 0 | J61: =-MIN(J60,J18*$E$62) -> 0 | K61: =-MIN(K60,K18*$E$62) -> 0 | L61: =-MIN(L60,L18*$E$62) -> 0 | M61: =-MIN(M60,M18*$E$62) -> 0 | ... O61: =-MIN(O60,O18*$E$62) -> -600
B62: Ending balance | E62: ='S&U'!C43 -> 600 | F62: =SUM(F60:F61) -> 600 | G62: =SUM(G60:G61) -> 600 | H62: =SUM(H60:H61) -> 600 | I62: =SUM(I60:I61) -> 600 | J62: =SUM(J60:J61) -> 600 | K62: =SUM(K60:K61) -> 600 | L62: =SUM(L60:L61) -> 600 | M62: =SUM(M60:M61) -> 600 | ... O62: =SUM(O60:O61) -> 0
A64: Mezzanine (PIK)
B65: Beginning balance | F65: =E68 -> 500 | G65: =F68 -> 564.05 | H65: =G68 -> 636.3048 | I65: =H68 -> 717.81545 | J65: =I68 -> 809.76761 | K65: =J68 -> 913.49884 | L65: =K68 -> 1030.518 | M65: =L68 -> 1162.5274 | ... O65: =N68 -> 1479.4435
B66: Interest accrued | F66: =F65*F69 -> 64.05 | G66: =G65*G69 -> 72.254805 | H66: =H65*H69 -> 81.510646 | I66: =I65*I69 -> 91.952159 | J66: =J65*J69 -> 103.73123 | K66: =K65*K69 -> 117.0192 | L66: =L65*L69 -> 132.00936 | M66: =M65*M69 -> 148.91976 | ... O66: =O65*O69 -> 189.51672
B67: Mandated repayment | F67: =-SUM(F65:F66)*F19 -> 0 | G67: =-SUM(G65:G66)*G19 -> 0 | H67: =-SUM(H65:H66)*H19 -> 0 | I67: =-SUM(I65:I66)*I19 -> 0 | J67: =-SUM(J65:J66)*J19 -> 0 | K67: =-SUM(K65:K66)*K19 -> 0 | L67: =-SUM(L65:L66)*L19 -> 0 | M67: =-SUM(M65:M66)*M19 -> 0 | ... O67: =-SUM(O65:O66)*O19 -> -1668.9603
B68: Ending balance | E68: ='S&U'!C44 -> 500 | F68: =SUM(F65:F67) -> 564.05 | G68: =SUM(G65:G67) -> 636.3048 | H68: =SUM(H65:H67) -> 717.81545 | I68: =SUM(I65:I67) -> 809.76761 | J68: =SUM(J65:J67) -> 913.49884 | K68: =SUM(K65:K67) -> 1030.518 | L68: =SUM(L65:L67) -> 1162.5274 | M68: =SUM(M65:M67) -> 1311.4472 | ... O68: =SUM(O65:O67) -> 0
B69: Interest rate | F69: ='S&U'!$K$44 -> 0.1281 | G69: ='S&U'!$K$44 -> 0.1281 | H69: ='S&U'!$K$44 -> 0.1281 | I69: ='S&U'!$K$44 -> 0.1281 | J69: ='S&U'!$K$44 -> 0.1281 | K69: ='S&U'!$K$44 -> 0.1281 | L69: ='S&U'!$K$44 -> 0.1281 | M69: ='S&U'!$K$44 -> 0.1281 | ... O69: ='S&U'!$K$44 -> 0.1281
A71: Shareholder loan (PIK)
B72: Beginning balance | F72: =E74 -> 535.58253 | G72: =F74 -> 615.91991 | H72: =G74 -> 708.30789 | I72: =H74 -> 814.55408 | J72: =I74 -> 936.73719 | K72: =J74 -> 1077.2478 | L72: =K74 -> 1238.8349 | M72: =L74 -> 1424.6602 | ... O72: =N74 -> 1884.1131
B73: Interest accrued | F73: =F72*F75 -> 80.337379 | G73: =G72*G75 -> 92.387986 | H73: =H72*H75 -> 106.24618 | I73: =I72*I75 -> 122.18311 | J73: =J72*J75 -> 140.51058 | K73: =K72*K75 -> 161.58716 | L73: =L72*L75 -> 185.82524 | M73: =M72*M75 -> 213.69903 | ... O73: =O72*O75 -> 282.61696
B74: Ending balance | E74: ='S&U'!C45 -> 535.58253 | F74: =SUM(F72:F73) -> 615.91991 | G74: =SUM(G72:G73) -> 708.30789 | H74: =SUM(H72:H73) -> 814.55408 | I74: =SUM(I72:I73) -> 936.73719 | J74: =SUM(J72:J73) -> 1077.2478 | K74: =SUM(K72:K73) -> 1238.8349 | L74: =SUM(L72:L73) -> 1424.6602 | M74: =SUM(M72:M73) -> 1638.3592 | ... O74: =SUM(O72:O73) -> 2166.73
B75: Interest rate | F75: ='S&U'!$K$45 -> 0.15 | G75: ='S&U'!$K$45 -> 0.15 | H75: ='S&U'!$K$45 -> 0.15 | I75: ='S&U'!$K$45 -> 0.15 | J75: ='S&U'!$K$45 -> 0.15 | K75: ='S&U'!$K$45 -> 0.15 | L75: ='S&U'!$K$45 -> 0.15 | M75: ='S&U'!$K$45 -> 0.15 | ... O75: ='S&U'!$K$45 -> 0.15
A77: Debt and interest summary
A79: Debt and cash balances
B80: Cash | E80: =FS!E83 -> 0 | F80: =FS!F83 -> 11.157248 | G80: =FS!G83 -> 12.272972 | H80: =FS!H83 -> 13.37754 | I80: =FS!I83 -> 14.447743 | J80: =FS!J83 -> 15.459085 | K80: =FS!K83 -> 16.38663 | L80: =FS!L83 -> 17.205962 | ... O80: =FS!O83 -> 18.983957
B81: Revolver | E81: =E36 -> 0 | F81: =F36 -> 0 | G81: =G36 -> 0 | H81: =H36 -> 0 | I81: =I36 -> 0 | J81: =J36 -> 0 | K81: =K36 -> 0 | L81: =L36 -> 45.492899 | ... O81: =O36 -> 2303.6138
B82: Term debt A | E82: =E49 -> 1200 | F82: =F49 -> 1135.117 | G82: =G49 -> 1042.6889 | H82: =H49 -> 907.53424 | I82: =I49 -> 724.6669 | J82: =J49 -> 521.18881 | K82: =K49 -> 294.18915 | L82: =L49 -> 0 | ... O82: =O49 -> 0
B83: Term debt B | E83: =E57 -> 900 | F83: =F57 -> 900 | G83: =G57 -> 900 | H83: =H57 -> 900 | I83: =I57 -> 900 | J83: =J57 -> 900 | K83: =K57 -> 900 | L83: =L57 -> 900 | ... O83: =O57 -> 0
B84: High Yield | E84: =E62 -> 600 | F84: =F62 -> 600 | G84: =G62 -> 600 | H84: =H62 -> 600 | I84: =I62 -> 600 | J84: =J62 -> 600 | K84: =K62 -> 600 | L84: =L62 -> 600 | ... O84: =O62 -> 0
B85: Mezzanine (PIK) | E85: =E68 -> 500 | F85: =F68 -> 564.05 | G85: =G68 -> 636.3048 | H85: =H68 -> 717.81545 | I85: =I68 -> 809.76761 | J85: =J68 -> 913.49884 | K85: =K68 -> 1030.518 | L85: =L68 -> 1162.5274 | ... O85: =O68 -> 0
B86: Shareholder Loan (PIK) | E86: =E74 -> 535.58253 | F86: =F74 -> 615.91991 | G86: =G74 -> 708.30789 | H86: =H74 -> 814.55408 | I86: =I74 -> 936.73719 | J86: =J74 -> 1077.2478 | K86: =K74 -> 1238.8349 | L86: =L74 -> 1424.6602 | ... O86: =O74 -> 2166.73
A88: Interest rates
B89: Cash | F89: ='S&U'!$K39 -> 0.01 | G89: ='S&U'!$K39 -> 0.01 | H89: ='S&U'!$K39 -> 0.01 | I89: ='S&U'!$K39 -> 0.01 | J89: ='S&U'!$K39 -> 0.01 | K89: ='S&U'!$K39 -> 0.01 | L89: ='S&U'!$K39 -> 0.01 | M89: ='S&U'!$K39 -> 0.01 | ... O89: ='S&U'!$K39 -> 0.01
B90: Revolver | F90: ='S&U'!$K40 -> 0.0355 | G90: ='S&U'!$K40 -> 0.0355 | H90: ='S&U'!$K40 -> 0.0355 | I90: ='S&U'!$K40 -> 0.0355 | J90: ='S&U'!$K40 -> 0.0355 | K90: ='S&U'!$K40 -> 0.0355 | L90: ='S&U'!$K40 -> 0.0355 | M90: ='S&U'!$K40 -> 0.0355 | ... O90: ='S&U'!$K40 -> 0.0355
B91: Term debt A | F91: ='S&U'!$K41 -> 0.0584 | G91: ='S&U'!$K41 -> 0.0584 | H91: ='S&U'!$K41 -> 0.0584 | I91: ='S&U'!$K41 -> 0.0584 | J91: ='S&U'!$K41 -> 0.0584 | K91: ='S&U'!$K41 -> 0.0584 | L91: ='S&U'!$K41 -> 0.0584 | M91: ='S&U'!$K41 -> 0.0584 | ... O91: ='S&U'!$K41 -> 0.0584
B92: Term debt B | F92: ='S&U'!$K42 -> 0.0686 | G92: ='S&U'!$K42 -> 0.0686 | H92: ='S&U'!$K42 -> 0.0686 | I92: ='S&U'!$K42 -> 0.0686 | J92: ='S&U'!$K42 -> 0.0686 | K92: ='S&U'!$K42 -> 0.0686 | L92: ='S&U'!$K42 -> 0.0686 | M92: ='S&U'!$K42 -> 0.0686 | ... O92: ='S&U'!$K42 -> 0.0686
B93: High Yield | F93: ='S&U'!$K43 -> 0.08625 | G93: ='S&U'!$K43 -> 0.08625 | H93: ='S&U'!$K43 -> 0.08625 | I93: ='S&U'!$K43 -> 0.08625 | J93: ='S&U'!$K43 -> 0.08625 | K93: ='S&U'!$K43 -> 0.08625 | L93: ='S&U'!$K43 -> 0.08625 | M93: ='S&U'!$K43 -> 0.08625 | ... O93: ='S&U'!$K43 -> 0.08625
B94: Mezzanine (PIK) | F94: ='S&U'!$K44 -> 0.1281 | G94: ='S&U'!$K44 -> 0.1281 | H94: ='S&U'!$K44 -> 0.1281 | I94: ='S&U'!$K44 -> 0.1281 | J94: ='S&U'!$K44 -> 0.1281 | K94: ='S&U'!$K44 -> 0.1281 | L94: ='S&U'!$K44 -> 0.1281 | M94: ='S&U'!$K44 -> 0.1281 | ... O94: ='S&U'!$K44 -> 0.1281
B95: Shareholder Loan (PIK) | F95: ='S&U'!$K45 -> 0.15 | G95: ='S&U'!$K45 -> 0.15 | H95: ='S&U'!$K45 -> 0.15 | I95: ='S&U'!$K45 -> 0.15 | J95: ='S&U'!$K45 -> 0.15 | K95: ='S&U'!$K45 -> 0.15 | L95: ='S&U'!$K45 -> 0.15 | M95: ='S&U'!$K45 -> 0.15 | ... O95: ='S&U'!$K45 -> 0.15
A97: Opening balance driven interest income and expense
B98: Cash | F98: =F89*E80 -> 0 | G98: =G89*F80 -> 0.11157248 | H98: =H89*G80 -> 0.12272972 | I98: =I89*H80 -> 0.1337754 | J98: =J89*I80 -> 0.14447743 | K98: =K89*J80 -> 0.15459085 | L98: =L89*K80 -> 0.1638663 | M98: =M89*L80 -> 0.17205962 | ... O98: =O89*N80 -> 0.18431026
B99: Revolver | F99: =-F90*E81 -> 0 | G99: =-G90*F81 -> 0 | H99: =-H90*G81 -> 0 | I99: =-I90*H81 -> 0 | J99: =-J90*I81 -> 0 | K99: =-K90*J81 -> 0 | L99: =-L90*K81 -> 0 | M99: =-M90*L81 -> -1.6149979 | ... O99: =-O90*N81 -> -12.38448
B100: Term debt A | F100: =-F91*E82 -> -70.08 | G100: =-G91*F82 -> -66.29083 | H100: =-H91*G82 -> -60.893029 | I100: =-I91*H82 -> -52.999999 | J100: =-J91*I82 -> -42.320547 | K100: =-K91*J82 -> -30.437426 | L100: =-L91*K82 -> -17.180647 | M100: =-M91*L82 -> 0 | ... O100: =-O91*N82 -> 0
B101: Term debt B | F101: =-F92*E83 -> -61.74 | G101: =-G92*F83 -> -61.74 | H101: =-H92*G83 -> -61.74 | I101: =-I92*H83 -> -61.74 | J101: =-J92*I83 -> -61.74 | K101: =-K92*J83 -> -61.74 | L101: =-L92*K83 -> -61.74 | M101: =-M92*L83 -> -61.74 | ... O101: =-O92*N83 -> 0
B102: High Yield | F102: =-F93*E84 -> -51.75 | G102: =-G93*F84 -> -51.75 | H102: =-H93*G84 -> -51.75 | I102: =-I93*H84 -> -51.75 | J102: =-J93*I84 -> -51.75 | K102: =-K93*J84 -> -51.75 | L102: =-L93*K84 -> -51.75 | M102: =-M93*L84 -> -51.75 | ... O102: =-O93*N84 -> -51.75
B103: Mezzanine (PIK) | F103: =-F94*E85 -> -64.05 | G103: =-G94*F85 -> -72.254805 | H103: =-H94*G85 -> -81.510646 | I103: =-I94*H85 -> -91.952159 | J103: =-J94*I85 -> -103.73123 | K103: =-K94*J85 -> -117.0192 | L103: =-L94*K85 -> -132.00936 | M103: =-M94*L85 -> -148.91976 | ... O103: =-O94*N85 -> -189.51672
B104: Shareholder Loan (PIK) | F104: =-F95*E86 -> -80.337379 | G104: =-G95*F86 -> -92.387986 | H104: =-H95*G86 -> -106.24618 | I104: =-I95*H86 -> -122.18311 | J104: =-J95*I86 -> -140.51058 | K104: =-K95*J86 -> -161.58716 | L104: =-L95*K86 -> -185.82524 | M104: =-M95*L86 -> -213.69903 | ... O104: =-O95*N86 -> -282.61696
A106: Average balance driven interest income and expense
B107: Cash | F107: =AVERAGE(E80:F80)*F89 -> 0.055786238 | G107: =AVERAGE(F80:G80)*G89 -> 0.1171511 | H107: =AVERAGE(G80:H80)*H89 -> 0.12825256 | I107: =AVERAGE(H80:I80)*I89 -> 0.13912641 | J107: =AVERAGE(I80:J80)*J89 -> 0.14953414 | K107: =AVERAGE(J80:K80)*K89 -> 0.15922857 | L107: =AVERAGE(K80:L80)*L89 -> 0.16796296 | M107: =AVERAGE(L80:M80)*M89 -> 0.17550081 | ... O107: =AVERAGE(N80:O80)*O89 -> 0.18707491
B108: Revolver | F108: =-AVERAGE(E81:F81)*F90 -> 0 | G108: =-AVERAGE(F81:G81)*G90 -> 0 | H108: =-AVERAGE(G81:H81)*H90 -> 0 | I108: =-AVERAGE(H81:I81)*I90 -> 0 | J108: =-AVERAGE(I81:J81)*J90 -> 0 | K108: =-AVERAGE(J81:K81)*K90 -> 0 | L108: =-AVERAGE(K81:L81)*L90 -> -0.80749895 | M108: =-AVERAGE(L81:M81)*M90 -> -12.574909 | ... O108: =-AVERAGE(N81:O81)*O90 -> -47.081385
B109: Term debt A | F109: =-AVERAGE(E82:F82)*F91 -> -68.185415 | G109: =-AVERAGE(F82:G82)*G91 -> -63.59193 | H109: =-AVERAGE(G82:H82)*H91 -> -56.946514 | I109: =-AVERAGE(H82:I82)*I91 -> -47.660273 | J109: =-AVERAGE(I82:J82)*J91 -> -36.378987 | K109: =-AVERAGE(J82:K82)*K91 -> -23.809036 | L109: =-AVERAGE(K82:L82)*L91 -> -8.5903233 | M109: =-AVERAGE(L82:M82)*M91 -> 0 | ... O109: =-AVERAGE(N82:O82)*O91 -> 0
B110: Term debt B | F110: =-AVERAGE(E83:F83)*F92 -> -61.74 | G110: =-AVERAGE(F83:G83)*G92 -> -61.74 | H110: =-AVERAGE(G83:H83)*H92 -> -61.74 | I110: =-AVERAGE(H83:I83)*I92 -> -61.74 | J110: =-AVERAGE(I83:J83)*J92 -> -61.74 | K110: =-AVERAGE(J83:K83)*K92 -> -61.74 | L110: =-AVERAGE(K83:L83)*L92 -> -61.74 | M110: =-AVERAGE(L83:M83)*M92 -> -30.87 | ... O110: =-AVERAGE(N83:O83)*O92 -> 0
A112: Debt ratios
B113: Total debt | E113: =SUM(E81:E85) -> 3200 | F113: =SUM(F81:F85) -> 3199.167 | G113: =SUM(G81:G85) -> 3178.9937 | H113: =SUM(H81:H85) -> 3125.3497 | I113: =SUM(I81:I85) -> 3034.4345 | J113: =SUM(J81:J85) -> 2934.6876 | K113: =SUM(K81:K85) -> 2824.7072 | L113: =SUM(L81:L85) -> 2708.0203 | ... O113: =SUM(O81:O85) -> 2303.6138
B114: Total debt / EBITDA | E114: =E113/FS!E62 -> 5.3342224 | F114: =F113/FS!F62 -> 4.344461 | G114: =G113/FS!G62 -> 3.9246052 | H114: =H113/FS!H62 -> 3.5397976 | I114: =I113/FS!I62 -> 3.1822466 | J114: =J113/FS!J62 -> 2.8762999 | K114: =K113/FS!K62 -> 2.6117996 | L114: =L113/FS!L62 -> 2.3846741 | ... O114: =O113/FS!O62 -> 1.838565
B115: Senior Debt / EBITDA | E115: =SUM(E81:E83)/FS!E62 -> 3.5005834 | F115: =SUM(F81:F83)/FS!F62 -> 2.7636839 | G115: =SUM(G81:G83)/FS!G62 -> 2.3983334 | H115: =SUM(H81:H83)/FS!H62 -> 2.0472286 | I115: =SUM(I81:I83)/FS!I62 -> 1.703807 | J115: =SUM(J81:J83)/FS!J62 -> 1.3929132 | K115: =SUM(K81:K83)/FS!K62 -> 1.1041791 | L115: =SUM(L81:L83)/FS!L62 -> 0.83259805 | ... O115: =SUM(O81:O83)/FS!O62 -> 1.838565
B116: EBITDA / total debt interest | F116: =-FS!F62/SUM(FS!F12:F16) -> 2.9967528 | G116: =-FS!G62/SUM(FS!G12:G16) -> 3.2486836 | H116: =-FS!H62/SUM(FS!H12:H16) -> 3.5043762 | I116: =-FS!I62/SUM(FS!I12:I16) -> 3.7674511 | J116: =-FS!J62/SUM(FS!J12:J16) -> 4.02326 | K116: =-FS!K62/SUM(FS!K12:K16) -> 4.2526151 | L116: =-FS!L62/SUM(FS!L12:L16) -> 4.455104 | M116: =-FS!M62/SUM(FS!M12:M16) -> 4.8379608 | ... O116: =-FS!O62/SUM(FS!O12:O16) -> 4.345238
B117: EBITDA / Cash interest | F117: =-FS!F62/SUM(FS!F71:F74) -> 4.0532635 | G117: =-FS!G62/SUM(FS!G71:G74) -> 4.5742452 | H117: =-FS!H62/SUM(FS!H71:H74) -> 5.1803314 | I117: =-FS!I62/SUM(FS!I71:I74) -> 5.9171543 | J117: =-FS!J62/SUM(FS!J71:J74) -> 6.8079436 | K117: =-FS!K62/SUM(FS!K71:K74) -> 7.8770952 | L117: =-FS!L62/SUM(FS!L71:L74) -> 9.240895 | M117: =-FS!M62/SUM(FS!M71:M74) -> 12.406306 | ... O117: =-FS!O62/SUM(FS!O71:O74) -> 12.677563
B118: Fixed charge ratio | F118: =FS!F62/(-F29-SUM(FS!F71:F74)) -> 3.478809 | G118: =FS!G62/(-G29-SUM(FS!G71:G74)) -> 3.9115734 | H118: =FS!H62/(-H29-SUM(FS!H71:H74)) -> 3.8315005 | I118: =FS!I62/(-I29-SUM(FS!I71:I74)) -> 4.3117787 | J118: =FS!J62/(-J29-SUM(FS!J71:J74)) -> 4.8616026 | K118: =FS!K62/(-K29-SUM(FS!K71:K74)) -> 5.4816161 | L118: =FS!L62/(-L29-SUM(FS!L71:L74)) -> 2.7227431 | M118: =FS!M62/(-M29-SUM(FS!M71:M74)) -> 1.1867195 | ... O118: =FS!O62/(-O29-SUM(FS!O71:O74)) -> 0.52916022
B120: Interest expense as a % of EBITDA | F120: =1/F116 -> 0.33369452 | G120: =1/G116 -> 0.30781698 | H120: =1/H116 -> 0.28535749 | I120: =1/I116 -> 0.26543145 | J120: =1/J116 -> 0.24855466 | K120: =1/K116 -> 0.23514943 | L120: =1/L116 -> 0.22446165 | M120: =1/M116 -> 0.20669866 | ... O120: =1/O116 -> 0.23013699
B121: Cap | E121: 0.3 | F121: =E121 -> 0.3 | G121: =F121 -> 0.3 | H121: =G121 -> 0.3 | I121: =H121 -> 0.3 | J121: =I121 -> 0.3 | K121: =J121 -> 0.3 | L121: =K121 -> 0.3 | M121: =L121 -> 0.3 | ... O121: =N121 -> 0.3

Sheet Returns
A1: =CoName -> Company2272 | E1: Hist. | F1: Proj. | G1: Proj. | H1: Proj. | I1: Proj. | J1: Proj. | K1: Proj. | L1: Proj. | M1: Proj. | N1: Proj. | O1: Proj.
A2: =Ccy&Units&" unless otherwise stated" -> $m unless otherwise stated | E2: =Inputs!C16 -> 42369 | F2: =DATE(YEAR(E2)+1,MONTH(E2),DAY(E2)) -> 42735 | G2: =DATE(YEAR(F2)+1,MONTH(F2),DAY(F2)) -> 43100 | H2: =DATE(YEAR(G2)+1,MONTH(G2),DAY(G2)) -> 43465 | I2: =DATE(YEAR(H2)+1,MONTH(H2),DAY(H2)) -> 43830 | J2: =DATE(YEAR(I2)+1,MONTH(I2),DAY(I2)) -> 44196 | K2: =DATE(YEAR(J2)+1,MONTH(J2),DAY(J2)) -> 44561 | L2: =DATE(YEAR(K2)+1,MONTH(K2),DAY(K2)) -> 44926 | M2: =DATE(YEAR(L2)+1,MONTH(L2),DAY(L2)) -> 45291 | ... O2: =DATE(YEAR(N2)+1,MONTH(N2),DAY(N2)) -> 46022
B4: Entry EBITDA multiple | E4: ='S&U'!E24 -> 7.015262
B5: Exit EBITDA multiple | E5: 7
B6: Basis of interest calcuations: | E6: =IF(circ=1,"Average","Beginning")&" balance driven" -> Average balance driven
A8: Sources and uses of funds at exit
B9: Year | E9: =YEAR(E$2)-YEAR($E$2) -> 0 | F9: =YEAR(F$2)-YEAR($E$2) -> 1 | G9: =YEAR(G$2)-YEAR($E$2) -> 2 | H9: =YEAR(H$2)-YEAR($E$2) -> 3 | I9: =YEAR(I$2)-YEAR($E$2) -> 4 | J9: =YEAR(J$2)-YEAR($E$2) -> 5 | K9: =YEAR(K$2)-YEAR($E$2) -> 6 | L9: =YEAR(L$2)-YEAR($E$2) -> 7 | ... O9: =YEAR(O$2)-YEAR($E$2) -> 10
B10: EBITDA | E10: =OpMod!E78 -> 599.9 | F10: =OpMod!F78 -> 736.37833 | G10: =OpMod!G78 -> 810.01617 | H10: =OpMod!H78 -> 882.91762 | I10: =OpMod!I78 -> 953.55103 | J10: =OpMod!J78 -> 1020.2996 | K10: =OpMod!K78 -> 1081.5176 | L10: =OpMod!L78 -> 1135.5935 | ... O10: =OpMod!O78 -> 1252.9411
B12: Enterprise value on exit | F12: =F10*ExitMultiple -> 5154.6483 | G12: =G10*ExitMultiple -> 5670.1132 | H12: =H10*ExitMultiple -> 6180.4234 | I12: =I10*ExitMultiple -> 6674.8572 | J12: =J10*ExitMultiple -> 7142.0972 | K12: =K10*ExitMultiple -> 7570.6231 | L12: =L10*ExitMultiple -> 7949.1542 | M12: =M10*ExitMultiple -> 8267.1204 | ... O12: =O10*ExitMultiple -> 8770.588
B13: Cash | E13: =FS!E83 -> 0 | F13: =Debt!F80 -> 11.157248 | G13: =Debt!G80 -> 12.272972 | H13: =Debt!H80 -> 13.37754 | I13: =Debt!I80 -> 14.447743 | J13: =Debt!J80 -> 15.459085 | K13: =Debt!K80 -> 16.38663 | L13: =Debt!L80 -> 17.205962 | M13: =Debt!M80 -> 17.8942 | ... O13: =Debt!O80 -> 18.983957
B14: Revolver | E14: =-Debt!E81 -> 0 | F14: =-Debt!F81 -> 0 | G14: =-Debt!G81 -> 0 | H14: =-Debt!H81 -> 0 | I14: =-Debt!I81 -> 0 | J14: =-Debt!J81 -> 0 | K14: =-Debt!K81 -> 0 | L14: =-Debt!L81 -> -45.492899 | ... O14: =-Debt!O81 -> -2303.6138
B15: Term debt A | E15: =-Debt!E82 -> -1200 | F15: =-Debt!F82 -> -1135.117 | G15: =-Debt!G82 -> -1042.6889 | H15: =-Debt!H82 -> -907.53424 | I15: =-Debt!I82 -> -724.6669 | J15: =-Debt!J82 -> -521.18881 | K15: =-Debt!K82 -> -294.18915 | L15: =-Debt!L82 -> 0 | ... O15: =-Debt!O82 -> 0
B16: Term debt B | E16: =-Debt!E83 -> -900 | F16: =-Debt!F83 -> -900 | G16: =-Debt!G83 -> -900 | H16: =-Debt!H83 -> -900 | I16: =-Debt!I83 -> -900 | J16: =-Debt!J83 -> -900 | K16: =-Debt!K83 -> -900 | L16: =-Debt!L83 -> -900 | ... O16: =-Debt!O83 -> 0
B17: High Yield | E17: =-Debt!E84 -> -600 | F17: =-Debt!F84 -> -600 | G17: =-Debt!G84 -> -600 | H17: =-Debt!H84 -> -600 | I17: =-Debt!I84 -> -600 | J17: =-Debt!J84 -> -600 | K17: =-Debt!K84 -> -600 | L17: =-Debt!L84 -> -600 | ... O17: =-Debt!O84 -> 0
B18: Mezzanine (PIK) | E18: =-Debt!E85 -> -500 | F18: =-Debt!F85 -> -564.05 | G18: =-Debt!G85 -> -636.3048 | H18: =-Debt!H85 -> -717.81545 | I18: =-Debt!I85 -> -809.76761 | J18: =-Debt!J85 -> -913.49884 | K18: =-Debt!K85 -> -1030.518 | L18: =-Debt!L85 -> -1162.5274 | ... O18: =-Debt!O85 -> 0
B19: Shareholder Loan (PIK) | E19: =-Debt!E86 -> -535.58253 | F19: =-Debt!F86 -> -615.91991 | G19: =-Debt!G86 -> -708.30789 | H19: =-Debt!H86 -> -814.55408 | I19: =-Debt!I86 -> -936.73719 | J19: =-Debt!J86 -> -1077.2478 | K19: =-Debt!K86 -> -1238.8349 | L19: =-Debt!L86 -> -1424.6602 | ... O19: =-Debt!O86 -> -2166.73
B20: Equity value on exit | F20: =SUM(F12:F19) -> 1350.7187 | G20: =SUM(G12:G19) -> 1795.0846 | H20: =SUM(H12:H19) -> 2253.8971 | I20: =SUM(I12:I19) -> 2718.1333 | J20: =SUM(J12:J19) -> 3145.6209 | K20: =SUM(K12:K19) -> 3523.4676 | L20: =SUM(L12:L19) -> 3833.6797 | M20: =SUM(M12:M19) -> 4072.2555 | ... O20: =SUM(O12:O19) -> 4319.2282
A22: Total equity returns
B23: Year | E23: =YEAR(E$2)-YEAR($E$2) -> 0 | F23: =YEAR(F$2)-YEAR($E$2) -> 1 | G23: =YEAR(G$2)-YEAR($E$2) -> 2 | H23: =YEAR(H$2)-YEAR($E$2) -> 3 | I23: =YEAR(I$2)-YEAR($E$2) -> 4 | J23: =YEAR(J$2)-YEAR($E$2) -> 5 | K23: =YEAR(K$2)-YEAR($E$2) -> 6 | L23: =YEAR(L$2)-YEAR($E$2) -> 7 | ... O23: =YEAR(O$2)-YEAR($E$2) -> 10
B24: Shareholder loan | E24: =-E19 -> 535.58253 | F24: =-F19 -> 615.91991 | G24: =-G19 -> 708.30789 | H24: =-H19 -> 814.55408 | I24: =-I19 -> 936.73719 | J24: =-J19 -> 1077.2478 | K24: =-K19 -> 1238.8349 | L24: =-L19 -> 1424.6602 | ... O24: =-O19 -> 2166.73
B25: Ordinary equity | E25: ='S&U'!C46 -> 600 | F25: =F20 -> 1350.7187 | G25: =G20 -> 1795.0846 | H25: =H20 -> 2253.8971 | I25: =I20 -> 2718.1333 | J25: =J20 -> 3145.6209 | K25: =K20 -> 3523.4676 | L25: =L20 -> 3833.6797 | M25: =M20 -> 4072.2555 | ... O25: =O20 -> 4319.2282
B27: Exit year | C27: MOIC | D27: IRR | E27: Investment | F27: Return
B28: Year 1 | C28: =SUM(F28:J28)/-E28 -> 1.7318324 | D28: =IRR(E28:O28) -> 0.73183242 | E28: =-SUM(E$24:E$25) -> -1135.5825 | F28: =SUM(F$24:F$25) -> 1966.6386
B29: Year 2 | C29: =SUM(F29:J29)/-E29 -> 2.2045007 | D29: =IRR(E29:O29) -> 0.48475611 | E29: =-SUM(E$24:E$25) -> -1135.5825 | F29: 0 | G29: =SUM(G$24:G$25) -> 2503.3925
B30: Year 3 | C30: =SUM(F30:J30)/-E30 -> 2.7020944 | D30: =IRR(E30:O30) -> 0.39283661 | E30: =-SUM(E$24:E$25) -> -1135.5825 | F30: 0 | G30: 0 | H30: =SUM(H$24:H$25) -> 3068.4512
B31: Year 4 | C31: =SUM(F31:J31)/-E31 -> 3.2184983 | D31: =IRR(E31:O31) -> 0.33940934 | E31: =-SUM(E$24:E$25) -> -1135.5825 | F31: 0 | G31: 0 | H31: 0 | I31: =SUM(I$24:I$25) -> 3654.8705
B32: Year 5 | C32: =SUM(F32:J32)/-E32 -> 3.7186806 | D32: =IRR(E32:O32) -> 0.30040244 | E32: =-SUM(E$24:E$25) -> -1135.5825 | F32: 0 | G32: 0 | H32: 0 | I32: 0 | J32: =SUM(J$24:J$25) -> 4222.8687
A34: Returns to institutional investors
B35: Year | E35: =YEAR(E$2)-YEAR($E$2) -> 0 | F35: =YEAR(F$2)-YEAR($E$2) -> 1 | G35: =YEAR(G$2)-YEAR($E$2) -> 2 | H35: =YEAR(H$2)-YEAR($E$2) -> 3 | I35: =YEAR(I$2)-YEAR($E$2) -> 4 | J35: =YEAR(J$2)-YEAR($E$2) -> 5 | K35: =YEAR(K$2)-YEAR($E$2) -> 6 | L35: =YEAR(L$2)-YEAR($E$2) -> 7 | ... O35: =YEAR(O$2)-YEAR($E$2) -> 10
B36: Shareholder loan | E36: =-E19 -> 535.58253 | F36: =-F19 -> 615.91991 | G36: =-G19 -> 708.30789 | H36: =-H19 -> 814.55408 | I36: =-I19 -> 936.73719 | J36: =-J19 -> 1077.2478 | K36: =-K19 -> 1238.8349 | L36: =-L19 -> 1424.6602 | ... O36: =-O19 -> 2166.73
B37: Ordinary equity | E37: =E25*'S&U'!$J$19 -> 594 | F37: =F25*'S&U'!$K$19 -> 1296.69 | G37: =G25*'S&U'!$K$19 -> 1723.2812 | H37: =H25*'S&U'!$K$19 -> 2163.7413 | I37: =I25*'S&U'!$K$19 -> 2609.408 | J37: =J25*'S&U'!$K$19 -> 3019.7961 | K37: =K25*'S&U'!$K$19 -> 3382.5289 | L37: =L25*'S&U'!$K$19 -> 3680.3325 | M37: =M25*'S&U'!$K$19 -> 3909.3653 | ... O37: =O25*'S&U'!$K$19 -> 4146.459
B39: Exit year | C39: MOIC | D39: IRR | E39: Investment | F39: Return
B40: Year 1 | C40: =SUM(F40:J40)/-E40 -> 1.6932007 | D40: =IRR(E40:O40) -> 0.69320066 | E40: =-SUM($E$36:$E$37) -> -1129.5825 | F40: =SUM(F$36:F$37) -> 1912.6099
B41: Year 2 | C41: =SUM(F41:J41)/-E41 -> 2.1526441 | D41: =IRR(E41:O41) -> 0.46718917 | E41: =-SUM($E$36:$E$37) -> -1129.5825 | F41: 0 | G41: =SUM(G$36:G$37) -> 2431.5891
B42: Year 3 | C42: =SUM(F42:J42)/-E42 -> 2.6366337 | D42: =IRR(E42:O42) -> 0.38149695 | E42: =-SUM($E$36:$E$37) -> -1129.5825 | F42: 0 | G42: 0 | H42: =SUM(H$36:H$37) -> 2978.2953
B43: Year 4 | C43: =SUM(F43:J43)/-E43 -> 3.1393414 | D43: =IRR(E43:O43) -> 0.33109679 | E43: =-SUM($E$36:$E$37) -> -1129.5825 | F43: 0 | G43: 0 | H43: 0 | I43: =SUM(I$36:I$37) -> 3546.1451
B44: Year 5 | C44: =SUM(F44:J44)/-E44 -> 3.6270425 | D44: =IRR(E44:O44) -> 0.29392925 | E44: =-SUM($E$36:$E$37) -> -1129.5825 | F44: 0 | G44: 0 | H44: 0 | I44: 0 | J44: =SUM(J$36:J$37) -> 4097.0438
A46: Returns to mezzanine investors
B47: Year | E47: =YEAR(E$2)-YEAR($E$2) -> 0 | F47: =YEAR(F$2)-YEAR($E$2) -> 1 | G47: =YEAR(G$2)-YEAR($E$2) -> 2 | H47: =YEAR(H$2)-YEAR($E$2) -> 3 | I47: =YEAR(I$2)-YEAR($E$2) -> 4 | J47: =YEAR(J$2)-YEAR($E$2) -> 5 | K47: =YEAR(K$2)-YEAR($E$2) -> 6 | L47: =YEAR(L$2)-YEAR($E$2) -> 7 | ... O47: =YEAR(O$2)-YEAR($E$2) -> 10
B48: Mezzanine loan plus accrued interest | E48: =-E18 -> 500 | F48: =-F18 -> 564.05 | G48: =-G18 -> 636.3048 | H48: =-H18 -> 717.81545 | I48: =-I18 -> 809.76761 | J48: =-J18 -> 913.49884 | K48: =-K18 -> 1030.518 | L48: =-L18 -> 1162.5274 | ... O48: =-O18 -> 0
B49: Value of warrants at exit | F49: ='S&U'!$K$17*Returns!F25 -> 13.507187 | G49: ='S&U'!$K$17*Returns!G25 -> 17.950846 | H49: ='S&U'!$K$17*Returns!H25 -> 22.538971 | I49: ='S&U'!$K$17*Returns!I25 -> 27.181333 | J49: ='S&U'!$K$17*Returns!J25 -> 31.456209 | K49: ='S&U'!$K$17*Returns!K25 -> 35.234676 | L49: ='S&U'!$K$17*Returns!L25 -> 38.336797 | M49: ='S&U'!$K$17*Returns!M25 -> 40.722555 | ... O49: ='S&U'!$K$17*Returns!O25 -> 43.192282
B51: Exit year | C51: MOIC | D51: IRR | E51: Investment | F51: Return
B52: Year 1 | C52: =SUM(F52:J52)/-E52 -> 1.1551144 | D52: =IRR(E52:O52) -> 0.15511437 | E52: =-$E$48 -> -500 | F52: =SUM(F$48:F$49) -> 577.55719
B53: Year 2 | C53: =SUM(F53:J53)/-E53 -> 1.3085113 | D53: =IRR(E53:O53) -> 0.14390179 | E53: =-$E$48 -> -500 | F53: 0 | G53: =SUM(G$48:G$49) -> 654.25565
B54: Year 3 | C54: =SUM(F54:J54)/-E54 -> 1.4807088 | D54: =IRR(E54:O54) -> 0.13978575 | E54: =-$E$48 -> -500 | F54: 0 | G54: 0 | H54: =SUM(H$48:H$49) -> 740.35442
B55: Year 4 | C55: =SUM(F55:J55)/-E55 -> 1.6738979 | D55: =IRR(E55:O55) -> 0.1374498 | E55: =-$E$48 -> -500 | F55: 0 | G55: 0 | H55: 0 | I55: =SUM(I$48:I$49) -> 836.94894
B56: Year 5 | C56: =SUM(F56:J56)/-E56 -> 1.8899101 | D56: =IRR(E56:O56) -> 0.13576434 | E56: =-$E$48 -> -500 | F56: 0 | G56: 0 | H56: 0 | I56: 0 | J56: =SUM(J$48:J$49) -> 944.95505
A58: Returns to management
B59: Year | E59: =YEAR(E$2)-YEAR($E$2) -> 0 | F59: =YEAR(F$2)-YEAR($E$2) -> 1 | G59: =YEAR(G$2)-YEAR($E$2) -> 2 | H59: =YEAR(H$2)-YEAR($E$2) -> 3 | I59: =YEAR(I$2)-YEAR($E$2) -> 4 | J59: =YEAR(J$2)-YEAR($E$2) -> 5 | K59: =YEAR(K$2)-YEAR($E$2) -> 6 | L59: =YEAR(L$2)-YEAR($E$2) -> 7 | ... O59: =YEAR(O$2)-YEAR($E$2) -> 10
B60: Ordinary equity | E60: =E25*'S&U'!$J$18 -> 6 | F60: =F25*'S&U'!$K$18 -> 40.521562 | G60: =G25*'S&U'!$K$18 -> 53.852538 | H60: =H25*'S&U'!$K$18 -> 67.616914 | I60: =I25*'S&U'!$K$18 -> 81.543999 | J60: =J25*'S&U'!$K$18 -> 94.368627 | K60: =K25*'S&U'!$K$18 -> 105.70403 | L60: =L25*'S&U'!$K$18 -> 115.01039 | M60: =M25*'S&U'!$K$18 -> 122.16767 | ... O60: =O25*'S&U'!$K$18 -> 129.57685
B62: Exit year | C62: MOIC | D62: IRR | E62: Investment | F62: Return
B63: Year 1 | C63: =SUM(F63:J63)/-E63 -> 6.7535936 | D63: =IRR(E63:J63) -> 5.7535936 | E63: =-$E$60 -> -6 | F63: =F$60 -> 40.521562
B64: Year 2 | C64: =SUM(F64:J64)/-E64 -> 8.975423 | D64: =IRR(E64:J64) -> 1.995901 | E64: =-$E$60 -> -6 | F64: 0 | G64: =G$60 -> 53.852538
B65: Year 3 | C65: =SUM(F65:J65)/-E65 -> 11.269486 | D65: =IRR(E65:J65) -> 1.2419953 | E65: =-$E$60 -> -6 | F65: 0 | G65: 0 | H65: =H$60 -> 67.616914
B66: Year 4 | C66: =SUM(F66:J66)/-E66 -> 13.590666 | D66: =IRR(E66:J66) -> 0.92003961 | E66: =-$E$60 -> -6 | F66: 0 | G66: 0 | H66: 0 | I66: =I$60 -> 81.543999
B67: Year 5 | C67: =SUM(F67:J67)/-E67 -> 15.728105 | D67: =IRR(E67:J67) -> 0.73514302 | E67: =-$E$60 -> -6 | F67: 0 | G67: 0 | H67: 0 | I67: 0 | J67: =J$60 -> 94.368627

Sheet Sensitivity
A1: =CoName -> Company2272
A2: =Ccy&Units&" unless otherwise stated" -> $m unless otherwise stated
B4: Premium paid (clone assumption) | E4: ='S&U'!E8 -> 0.38
B5: Operating case (clone assumption) | E5: =OpMod!C6 -> 1
B6: Exit multiple (clone assumption) | E6: =Returns!E5 -> 7
A8: Sensitivity analysis
B10: Sensitvity of returns to | C10: Premium | D10: Offer price | E10: Investment | F10: Institutional | G10: Mezzanine | H10: Mgmt
B11: Premium paid | C11: paid | D11: $ | E11: Year 3 IRR | F11: Year 3 IRR | G11: Year 3 IRR | H11: MOIC
D12: ='S&U'!E9 -> 32.0022 | E12: =Returns!D30 -> 0.39283661 | F12: =Returns!D42 -> 0.38149695 | G12: =Returns!D54 -> 0.13978575 | H12: =Returns!C65 -> 11.269486
C13: =C14-1% -> 0.32 | D13: 30.6108 | E13: 0.4780476 | F13: 0.46466813 | G13: 0.14123011 | H13: 12.678556
C14: =C15-1% -> 0.33 | D14: 30.8427 | E14: 0.46237449 | F14: 0.44934609 | G14: 0.14098964 | H14: 12.443711
C15: =C16-1% -> 0.34 | D15: 31.0746 | E15: 0.44734571 | F15: 0.43466394 | G15: 0.14074906 | H15: 12.208866
C16: =C17-1% -> 0.35 | D16: 31.3065 | E16: 0.43291628 | F16: 0.42057668 | G16: 0.14050839 | H16: 11.974021
C17: =C18-1% -> 0.36 | D17: 31.5384 | E17: 0.41904559 | F17: 0.40704371 | G17: 0.14026761 | H17: 11.739176
C18: =C19-1% -> 0.37 | D18: 31.7703 | E18: 0.40569685 | F18: 0.39402826 | G18: 0.14002673 | H18: 11.504331
C19: ='S&U'!E8 -> 0.38 | D19: 32.0022 | E19: 0.39283661 | F19: 0.38149695 | G19: 0.13978575 | H19: 11.269486
C20: =C19+1% -> 0.39 | D20: 32.2341 | E20: 0.38043444 | F20: 0.36941941 | G20: 0.13954467 | H20: 11.034641
C21: =C20+1% -> 0.4 | D21: 32.466 | E21: 0.36846252 | F21: 0.35776787 | G21: 0.13930348 | H21: 10.799796
C22: =C21+1% -> 0.41 | D22: 32.6979 | E22: 0.35689539 | F22: 0.34651698 | G22: 0.1390622 | H22: 10.564951
C23: =C22+1% -> 0.42 | D23: 32.9298 | E23: 0.34570969 | F23: 0.33564345 | G23: 0.13882081 | H23: 10.330105
C24: =C23+1% -> 0.43 | D24: 33.1617 | E24: 0.33488395 | F24: 0.32512588 | G24: 0.13857932 | H24: 10.09526
B26: Sensitvity of returns to | C26: Exit | D26: Offer price | E26: Investment | F26: Institutional | G26: Mezzanine | H26: Mgmt
B27: Exit multiple | C27: mulitple | D27: $ | E27: Year 3 IRR | F27: Year 3 IRR | G27: Year 3 IRR | H27: MOIC
D28: ='S&U'!$E$9 -> 32.0022 | E28: =Returns!$D$30 -> 0.39283661 | F28: =Returns!$D$42 -> 0.38149695 | G28: =Returns!$D$54 -> 0.13978575 | H28: =Returns!$C$65 -> 11.269486
C29: =C30-0.5 -> 6 | D29: 32.0022 | E29: 0.24388318 | F29: 0.23557108 | G29: 0.13523674 | H29: 6.8548976
C30: =C31-0.5 -> 6.5 | D30: 32.0022 | E30: 0.32255387 | F30: 0.31258979 | G30: 0.13751579 | H30: 9.0621917
C31: =Returns!E5 -> 7 | D31: 32.0022 | E31: 0.39283661 | F31: 0.38149695 | G31: 0.13978575 | H31: 11.269486
C32: =C31+0.5 -> 7.5 | D32: 32.0022 | E32: 0.45666302 | F32: 0.44414075 | G32: 0.1420467 | H32: 13.47678
C33: =C32+0.5 -> 8 | D33: 32.0022 | E33: 0.51533838 | F33: 0.50177571 | G33: 0.14429874 | H33: 15.684074
B35: Sensitvity of returns to | C35: Operating | D35: Offer price | E35: Investment | F35: Institutional | G35: Mezzanine | H35: Mgmt
B36: Operating case | C36: case | D36: $ | E36: Year 3 IRR | F36: Year 3 IRR | G36: Year 3 IRR | H36: MOIC
D37: ='S&U'!$E$9 -> 32.0022 | E37: =Returns!$D$30 -> 0.39283661 | F37: =Returns!$D$42 -> 0.38149695 | G37: =Returns!$D$54 -> 0.13978575 | H37: =Returns!$C$65 -> 11.269486
B38: Base | C38: 1 | D38: 32.0022 | E38: 0.39283661 | F38: 0.38149695 | G38: 0.13978575 | H38: 11.269486
B39: Management | C39: 2 | D39: 32.0022 | E39: 0.4563533 | F39: 0.44383664 | G39: 0.14203526 | H39: 13.465588
