Workbook
Name NA: "NA "
Name NM: "NM "

Sheet Cover
D11: Company1438
B21: Person0091, CFA | D21: SUMMARY DATA
B22: Company1150 & Co. | D22: Company Name: | G22: Company1438
B23: US Pharmaceuticals | D23: Ticker: | G23: Ticker0018
B24: +1 212.902.0691 (New York) | D24: Date of last update: | G24: 10.14.2025
B25: person@example.com
D26: QUICK LINKS
B27: Person0293 | D27: Sales Model
B28: Company1150 & Co. | D28: Consolidated Valuation
B29: Medical Technology | D29: Pharma Valuation
B30: +1 212.357.4617 (San Francisco) | D30: Income Statement
B31: person@example.com | D31: Balance Sheet
D32: Cash Flows
B33: Person0813 Person0525
B34: Company1150 & Co. | D34: COLOR CODE
B35: US Pharmaceuticals | D35: Blue | G35: Hardcoded data
B36: +1 415.249.7412 (San Francisco) | D36: Green | G36: Links to other tabs
B37: person@example.com | D37: Black | G37: Formula within sheet
B39: Person0896
B40: Company1150 & Co.
B41: Medical Technology
B42: +1 917.343.8573 (New York)
B43: person@example.com
B45: Person0522
B46: Company1150 & Co.
B47: US Pharmaceuticals
B48: +1 212.357.9930 (New York)
B49: person@example.com

Sheet Sales Model
B1: Total Sales
B2: U.S. | D2: 13050.774 | E2: 3847 | F2: 4014.1368 | G2: 4098 | H2: 3867 | I2: 15826.137 | J2: 4324 | K2: 4545 | L2: 4463 | M2: 4371 | N2: 17703 | O2: 4712 | P2: 5059 | Q2: 4976 | R2: 5075 | S2: 19822 | T2: 5521 | U2: 5599 | V2: 5589 | W2: 5746 | X2: 22455 | Y2: 6011.6 | Z2: 6112 | AA2: 6414 | AB2: 6737 | AC2: 25274.6 | AD2: 6918 | AE2: 6668 | AF2: 6790 | AG2: 7394 | AH2: 27770 | AI2: 7258 | AJ2: 7065 | AK2: 6967 | AL2: 7087 | AM2: 28377 | AN2: 7371 | AO2: 7375 | AP2: 7488 | AQ2: 7541 | AR2: 29775 | AS2: 8247.0246 | AT2: 8041 | AU2: 7927 | AV2: 8231 | AW2: 32446.025 | AX2: 8477 | AY2: 8210 | AZ2: 7955 | BA2: 7667 | BB2: 32309 | BC2: 8338 | BD2: 7983 | BE2: 7519.362 | BF2: 8235.9974 | BG2: 32076.359 | BH2: 8052 | BI2: 7779.3813 | BJ2: 7496 | BK2: 7610 | BL2: 30937.381 | BM2: 7608 | BN2: 7447 | BO2: 6868 | BP2: 6985 | BQ2: 28908 | BR2: 7219 | BS2: 7360 | BT2: 7791 | BU2: 7460 | BV2: 29830 | BW2: 7941.574 | BX2: 8006.6783 | BY2: =BY23 | BZ2: 7681.9241 | CA2: 31641.673 | CF2: 32367.79 | CK2: 33202.864 | CP2: 33656.978
B3: International | D3: 10944.224 | E3: 2947 | F3: 3002.8443 | G3: 2796 | H3: 2899 | I3: 11644.844 | J3: 3116 | K3: 3125 | L3: 2975 | M3: 2927 | N3: 12143 | O3: 3143 | P3: 3120 | Q3: 3082 | R3: 3150 | S3: 12495 | T3: 3222 | U3: 3474 | V3: 3490 | W3: 3657 | X3: 13843 | Y3: 3808.9 | Z3: 4220 | AA3: 4041 | AB3: 4517 | AC3: 16586.9 | AD3: 4641 | AE3: 4816 | AF3: 4763 | AG3: 5358 | AH3: 19578 | AI3: 5574.2 | AJ3: 5697 | AK3: 5343 | AL3: 5523 | AM3: 22137.2 | AN3: 5621 | AO3: 5988 | AP3: 5799 | AQ3: 6141 | AR3: 23549 | AS3: 6790 | AT3: 7090 | AU3: 7043 | AV3: 7727.1566 | AW3: 28650.157 | AX3: 7717 | AY3: 8240 | AZ3: 7966 | BA3: 7515 | BB3: 31438 | BC3: 6688 | BD3: 7256 | BE3: 7559.0466 | BF3: 8309.0566 | BG3: 29812.103 | BH3: 7579 | BI3: 7550.6057 | BJ3: 7486 | BK3: 8034 | BL3: 30649.606 | BM3: 8565 | BN3: 9150 | BO3: 9137 | BP3: 9270 | BQ3: 36122 | BR3: 8920 | BS3: 9115 | BT3: 9261 | BU3: 10098 | BV3: 37394 | BW3: 9728.7194 | BX3: 9969.99 | BY3: =BY24 | BZ3: 10381.806 | CA3: 39809.48 | CF3: 40900.193 | CK3: 42170.682 | CP3: 43812.993
B4: Worldwide | D4: 23994.999 | E4: 6794 | F4: 7016.9811 | G4: 6894 | H4: 6766 | I4: 27470.981 | J4: 7440 | K4: 7670 | L4: 7438 | M4: 7298 | N4: 29846 | O4: 7855 | P4: 8179 | Q4: 8058 | R4: 8225 | S4: 32317 | T4: 8743 | U4: 9073 | V4: 9079 | W4: 9403 | X4: 36298 | Y4: 9820.5 | Z4: 10332 | AA4: 10455 | AB4: 11254 | AC4: 41861.5 | AD4: 11559 | AE4: 11484 | AF4: 11553 | AG4: 12752 | AH4: 47348 | AI4: 12832.2 | AJ4: 12762 | AK4: 12310 | AL4: 12610 | AM4: 50514.2 | AN4: 12992 | AO4: 13363 | AP4: 13287 | AQ4: 13682 | AR4: 53324 | AS4: 15037.025 | AT4: 15131 | AU4: 14970 | AV4: 15958.157 | AW4: 61096.181 | AX4: 16194 | AY4: 16450 | AZ4: 15921 | BA4: 15182 | BB4: 63747 | BC4: 15026 | BD4: 15239 | BE4: 15078.409 | BF4: 16545.054 | BG4: 61888.463 | BH4: 15631 | BI4: 15329.987 | BJ4: 14982 | BK4: 15644 | BL4: 61586.987 | BM4: 16173 | BN4: 16597 | BO4: 16005 | BP4: 16255 | BQ4: 65030 | BR4: 16139 | BS4: 16475 | BT4: 17052 | BU4: 17558 | BV4: 67224 | BW4: 17670.293 | BX4: 17976.668 | BY4: =BY25 | BZ4: 18063.73 | CA4: 71451.153 | CF4: 73267.983 | CK4: 75373.547 | CP4: 77469.971
BW5: =+BW2-BW23 | BX5: =+BX2-BX23 | BY5: =+BY2-BY23 | BZ5: =+BZ2-BZ23 | CA5: =+CA2-CA23 | CF5: =+CF2-CF23 | CK5: =+CK2-CK23 | CP5: =+CP2-CP23
B9: =Cover!D11 | DP9: =DP15/DK15-1 | DQ9: =DQ15/DL15-1 | DR9: =DR15/DM15-1 | DS9: =DS15/DN15-1
DP10: =DP16/DK16-1 | DQ10: =DQ16/DL16-1 | DR10: =DR16/DM16-1 | DS10: =DS16/DN16-1
B11: Sales Model | DP11: =DP17/DK17-1 | DQ11: =DQ17/DL17-1 | DR11: =DR17/DM17-1 | DS11: =DS17/DN17-1
B13: ($ in millions)
DJ14: Pharma Revenues ex-COVID
BW15: =+BW3-BW24 | BX15: =+BX3-BX24 | BY15: =+BY3-BY24 | BZ15: =+BZ3-BZ24 | CA15: =+CA3-CA24 | DJ15: US | DK15: =DK34-DK1651 | DL15: =DL34-DL1651 | DM15: =DM34-DM1651 | DN15: =DN34-DN1651 | DO15: =DO34-DO1651 | DP15: =DP34-DP1651 | DQ15: =DQ34-DQ1651 | DR15: =DR34-DR1651 | ... EC15: =EC34-EC1651 | EI15: =EI34-EI1651 | EJ15: =EJ34-EJ1651 | EK15: =EK34-EK1651 | EL15: =EL34-EL1651 | EM15: =EM34-EM1651 | EN15: =EN34-EN1651
BW16: =+BW4-BW25 | BX16: =+BX4-BX25 | BY16: =+BY4-BY25 | BZ16: =+BZ4-BZ25 | CA16: =+CA4-CA25 | DJ16: OUS | DK16: =DK35-DK1652 | DL16: =DL35-DL1652 | DM16: =DM35-DM1652 | DN16: =DN35-DN1652 | DO16: =DO35-DO1652 | DP16: =DP35-DP1652 | DQ16: =DQ35-DQ1652 | DR16: =DR35-DR1652 | ... EC16: =EC35-EC1652 | EI16: =EI35-EI1652 | EJ16: =EJ35-EJ1652 | EK16: =EK35-EK1652 | EL16: =EL35-EL1652 | EM16: =EM35-EM1652 | EN16: =EN35-EN1652
DJ17: Total | DK17: =DK36-DK1653 | DL17: =DL36-DL1653 | DM17: =DM36-DM1653 | DN17: =DN36-DN1653 | DO17: =DO36-DO1653 | DP17: =DP36-DP1653 | DQ17: =DQ36-DQ1653 | DR17: =DR36-DR1653 | ... EC17: =EC36-EC1653 | EI17: =EI36-EI1653 | EJ17: =EJ36-EJ1653 | EK17: =EK36-EK1653 | EL17: =EL36-EL1653 | EM17: =EM36-EM1653 | EN17: =EN36-EN1653
CL18: =1.05113636363636-1 | CM18: =1.11725571725572-1 | CN18: =1.10829921845925-1 | CO18: 4Q2016A | CT18: 4Q2017E Ticker0015
B19: $ millions | C19: Patents | D19: 1998 | E19: 1Q99 | F19: 2Q99 | G19: 3Q99 | H19: 4Q99 | I19: 1999 | J19: 1Q00 | K19: 2Q00 | L19: 3Q00 | M19: 4Q00 | N19: 2000 | O19: 1Q01 | P19: 2Q01 | Q19: 3Q01 | R19: 4Q01 | S19: 2001 | T19: 1Q02 | U19: 2Q02 | V19: 3Q02 | W19: 4Q02 | X19: 2002 | Y19: 1Q03 | Z19: 2Q03 | AA19: 3Q03 | AB19: 4Q03 | AC19: 2003 | AD19: 1Q04 | AE19: 2Q04 | AF19: 3Q04 | AG19: 4Q04 | AH19: 2004 | AI19: 1Q05 | AJ19: 2Q05 | AK19: 3Q05 | AL19: 4Q05 | AM19: 2005 | AN19: 1Q06 | AO19: 2Q06 | AP19: 3Q06 | AQ19: 4Q06 | AR19: 2006 | AS19: 1Q07 | AT19: 2Q07 | AU19: 3Q07 | AV19: 4Q07 | AW19: 2007 | AX19: 1Q08 | AY19: 2Q08 | AZ19: 3Q08 | BA19: 4Q08 | BB19: 2008 | BC19: 1Q09 | BD19: 2Q09 | BE19: 3Q09 | BF19: 4Q09 | BG19: 2009 | BH19: 1Q10 | BI19: 2Q10 | BJ19: 3Q10 | BK19: 4Q10 | BL19: 2010 | BM19: 1Q11 | BN19: 2Q11 | BO19: 3Q11 | BP19: 4Q11 | BQ19: 2011 | BR19: 1Q12 | BS19: 2Q12 | BT19: 3Q12 | BU19: 4Q12 | BV19: 2012 | BW19: 1Q13 | BX19: 2Q13 | BY19: 3Q13 | BZ19: 4Q13 | CA19: 2013 | CB19: 1Q14 | CC19: 2Q14 | CD19: 3Q14 | CE19: 4Q14 | CF19: 2014 | CG19: 1Q15 | CH19: 2Q15 | CI19: 3Q15 | CJ19: 4Q15 | CK19: 2015 | CL19: 1Q16 | CM19: 2Q16 | CN19: 3Q16 | CO19: 4Q16 | CP19: 2016 | CQ19: 1Q17 | CR19: 2Q17 | CS19: 3Q17 | CT19: 4Q17 | CU19: 2017 | CV19: 1Q18 | CW19: 2Q18 | CX19: 3Q18 | CY19: 4Q18 | CZ19: 2018 | DA19: 1Q19 | DB19: 2Q19 | DC19: 3Q19 | DD19: 4Q19 | DE19: 2019 | DF19: 1Q20 | DG19: 2Q20 | DH19: 3Q20 | DI19: 4Q20 | DJ19: 2020 | DK19: 1Q21 | DL19: 2Q21 | DM19: 3Q21 | DN19: 4Q21 | DO19: 2021 | DP19: 1Q22 | DQ19: 2Q22 | DR19: 3Q22 | DS19: 4Q22 | DT19: 2022 | DU19: 1Q23 | DV19: 2Q23 | DW19: 3Q23 | DX19: 4Q23 | DY19: 2023 | DZ19: 1Q24 | EA19: 2Q24 | EB19: 3Q24 | EC19: 4Q24 | ED19: 2024 | EE19: 1Q25 | EF19: 2Q25 | EG19: 3Q25 | EH19: 4Q25E | EI19: 2025E | EJ19: 2026E | EK19: 2027 | EL19: =EK19+1 | EM19: =EL19+1 | EN19: =EM19+1 | EO19: =EN19+1 | EP19: =EO19+1 | EQ19: =EP19+1 | ER19: =EQ19+1 | ES19: =ER19+1 | ... EW19: =EV19+1
B20: Worldwide FX Revenue Impact | BM20: =+BH24*BM21/BH25 | BN20: =+BI24*BN21/BI25 | BO20: =+BJ24*BO21/BJ25 | BP20: =+BK24*BP21/BK25 | BR20: =+BM24*BR21/BM25 | BS20: =+BN24*BS21/BN25 | BT20: =+BO24*BT21/BO25 | BU20: =+BP24*BU21/BP25 | BW20: =+BR24*BW21/BR25 | BX20: =+BS24*BX21/BS25 | BY20: =+BT24*BY21/BT25 | BZ20: =+BU24*BZ21/BU25 | CB20: =+BW24*CB21/BW25 | CC20: =+BX24*CC21/BX25 | CD20: =+BY24*CD21/BY25 | CE20: =+BZ24*CE21/BZ25 | CG20: =+CB24*CG21/CB25 | CH20: =+CC24*CH21/CC25 | CI20: =+CD24*CI21/CD25 | CJ20: =+CE24*CJ21/CE25 | CL20: =+CG24*CL21/CG25 | CM20: =+CH24*CM21/CH25 | CN20: =+CI24*CN21/CI25 | CO20: =+CJ24*CO21/CJ25 | CP20: =CP21*CK24/CK25 | CQ20: =+CL24*CQ21/CL25 | CR20: =+CM24*CR21/CM25 | CS20: =+CN24*CS21/CN25 | CT20: =+CO24*CT21/CO25 | CU20: =CU21*CP24/CP25 | CV20: =+CQ24*CV21/CQ25 | CW20: =+CR24*CW21/CR25 | CX20: =+CS24*CX21/CS25 | CY20: =+CT24*CY21/CT25 | CZ20: =CZ21*CU24/CU25 | DA20: =+CV24*DA21/CV25 | DB20: =+CW24*DB21/CW25 | DC20: =+CX24*DC21/CX25 | DD20: =+CY24*DD21/CY25 | DE20: =DE21*CZ24/CZ25 | DF20: =+DA24*DF21/DA25 | DG20: =+DB24*DG21/DB25 | DH20: =+DC24*DH21/DC25 | DI20: =+DD24*DI21/DD25 | DJ20: =DJ21*DE24/DE25 | DK20: =+DF24*DK21/DF25 | DL20: =+DG24*DL21/DG25 | DM20: =+DH24*DM21/DH25 | DN20: =+DI24*DN21/DI25 | DO20: =DO21*DJ24/DJ25 | DP20: =+DK24*DP21/DK25 | DQ20: =+DL24*DQ21/DL25 | DR20: =+DM24*DR21/DM25 | DS20: =+DN24*DS21/DN25 | DT20: =DT21*DO24/DO25 | DU20: =+DP24*DU21/DP25 | DV20: =+DQ24*DV21/DQ25 | DW20: 0.004 | DX20: 0.001 | DZ20: =+DU24*DZ21/DU25 | EA20: =+DV24*EA21/DV25 | EB20: =+DW24*EB21/DW25 | EC20: =+DX24*EC21/DX25 | ED20: =ED21*DY24/DY25 | EE20: =+DZ24*EE21/DZ25 | EF20: =+EA24*EF21/EA25 | EG20: =+EB24*EG21/EB25
B21: FX impact | AI21: 0.054 | AJ21: 0.049 | AK21: 0.019 | AL21: -0.053000204 | AM21: =SUMPRODUCT(AI21:AL21,AD24:AG24/AH24) | AN21: -0.053 | AO21: -0.001 | AP21: 0.028 | AQ21: 0.054873837 | AR21: =SUMPRODUCT(AN21:AQ21,AI24:AL24)/AM24 | AS21: 0.054 | AT21: 0.054 | AU21: 0.068 | AV21: 0.10005372 | AW21: =SUMPRODUCT(AS21:AV21,AN24:AQ24)/AR24 | AX21: 0.113 | AY21: 0.119 | AZ21: 0.066 | BA21: -0.081 | BB21: =SUMPRODUCT(AX21:BA21,AS24:AV24)/AW24 | BC21: -0.126 | BD21: -0.119 | BE21: -0.049 | BF21: 0.092 | BG21: =SUMPRODUCT(BC21:BF21,AX24:BA24)/BB24 | BH21: 0.089 | BI21: 0.005 | BJ21: =-(0.8%*BE25)/BJ24 | BK21: =(-0.4%*BF25)/BK24 | BL21: =SUMPRODUCT(BH21:BK21,BC24:BF24)/BG24 | BM21: =(1.7%*BH25)/BH24 | BN21: =(5.7%*BI25)/BI24 | BO21: =(4.2%*BJ25)/BJ24 | BP21: =(-0.1%*BK25)/BK24 | BQ21: =SUMPRODUCT(BM21:BP21,BH24:BK24)/BL24 | BR21: =(-1.2%*BM25)/BM24 | BS21: =(-4.2%*BN25)/BN24 | BT21: =(-4.3%*BO25)/BO24 | BU21: =(-1.3%*BP25)/BP24 | BV21: =SUMPRODUCT(BR21:BU21,BM24:BP24)/BQ24 | BW21: =(-1.3%*BR25)/BR24 | BX21: =(-1.5%*BS25)/BS24 | BY21: =(-1.6%*BT25)/BT24 | BZ21: =(-1.8%*BU25)/BU24 | CA21: =SUMPRODUCT(BW21:BZ21,BR24:BU24)/BV24 | CB21: =(-1.8%*BW25)/BW24 | CC21: =(-0.3%*BX25)/BX24 | CD21: =(-0.7%*BY25)/BY24 | CE21: =(-4.5%*BZ25)/BZ24 | CF21: =SUMPRODUCT(CB21:CE21,BW24:BZ24)/CA24 | CG21: =(-7.2%*CB25)/CB24 | CH21: =(-7.9%*CC25)/CC24 | CI21: =(-8.2%*CD25)/CD24 | CJ21: =(-6.8%*CE25)/CE24 | CK21: =SUMPRODUCT(CG21:CJ21,CB24:CE24)/CF24 | CL21: -0.033 | CM21: -0.006 | CN21: -0.005 | CO21: -0.006 | CP21: =SUMPRODUCT(CL21:CO21,CG24:CJ24)/CK24 | CQ21: -0.009 | CR21: -0.021 | CS21: 0.016 | CT21: 0.045 | CU21: =SUMPRODUCT(CQ21:CT21,CL24:CO24)/CP24 | CV21: 0.09 | CW21: 0.04 | CX21: -0.04 | CY21: -0.047 | CZ21: =SUMPRODUCT(CV21:CY21,CQ24:CT24)/CU24 | DA21: -0.077 | DB21: -0.058 | DC21: -0.028 | DD21: -0.046 | DE21: =SUMPRODUCT(DA21:DD21,CV24:CY24)/CZ24 | DF21: -0.03 | DG21: -0.037 | DH21: -0.02 | DI21: -0.02 | DJ21: =SUMPRODUCT(DF21:DI21,DA24:DD24)/DE24 | DK21: -0.05 | DL21: -0.085457214 | DM21: 0.017 | DN21: -0.027 | DO21: =SUMPRODUCT(DK21:DN21,DF24:DI24)/DJ24 | DP21: -0.054 | DQ21: -0.101 | DR21: -0.126 | DS21: -0.104 | DT21: =SUMPRODUCT(DP21:DS21,DK24:DN24)/DO24 | DU21: -0.065 | DV21: -0.025 | DW21: 0.009 | DX21: 0.002 | EB21: -0.035 | ED21: =+ED1370 | EH21: 0.035 | EJ21: 0.015 | EK21: 0 | EL21: 0 | EM21: 0 | EN21: 0
B22: TOTAL SALES | DW22: Excludes Consumer Health -->
A23: Total Ticker0018 Sales - US | B23: US | D23: =+D1487+D885+D1348 | E23: =+E1487+E885+E1348 | F23: =+F1487+F885+F1348 | G23: =+G1487+G885+G1348 | H23: =+H1487+H885+H1348 | I23: =+I1487+I885+I1348 | J23: =+J1487+J885+J1348 | K23: =+K1487+K885+K1348 | ... DV23: =+DV1487+DV885+DV1348 | DW23: =+DW885+DW1348 | DX23: =+DX885+DX1348 | DY23: =+DY885+DY1348 | DZ23: =+DZ885+DZ1348 | EA23: =+EA885+EA1348 | EB23: =+EB885+EB1348 | EC23: =+EC885+EC1348 | ED23: =+ED885+ED1348 | ... EN23: =+EN885+EN1348
A24: =+A25&" - OUS" | B24: International | D24: =+D1488+D886+D1349 | E24: =+E1488+E886+E1349 | F24: =+F1488+F886+F1349 | G24: =+G1488+G886+G1349 | H24: =+H1488+H886+H1349 | I24: =+I1488+I886+I1349 | J24: =+J1488+J886+J1349 | K24: =+K1488+K886+K1349 | ... DV24: =+DV1488+DV886+DV1349 | DW24: =+DW886+DW1349 | DX24: =+DX886+DX1349 | DY24: =+DY886+DY1349 | DZ24: =+DZ886+DZ1349 | EA24: =+EA886+EA1349 | EB24: =+EB886+EB1349 | EC24: =+EC886+EC1349 | ED24: =+ED886+ED1349 | ... EN24: =+EN886+EN1349
A25: Total Ticker0018 Sales | B25: Worldwide | D25: =+D1489+D887+D1350 | E25: =+E1489+E887+E1350 | F25: =+F1489+F887+F1350 | G25: =+G1489+G887+G1350 | H25: =+H1489+H887+H1350 | I25: =+I1489+I887+I1350 | J25: =+J1489+J887+J1350 | K25: =+K1489+K887+K1350 | ... DV25: =+DV1489+DV887+DV1350 | DW25: =+DW887+DW1350 | DX25: =+DX887+DX1350 | DY25: =+DY887+DY1350 | DZ25: =+DZ887+DZ1350 | EA25: =+EA887+EA1350 | EB25: =+EB887+EB1350 | EC25: =+EC887+EC1350 | ED25: =+ED887+ED1350 | ... EN25: =+EN887+EN1350
B27: Total sales % growth
B28: US | I28: =IF(D23="NM","NM",IF(I23="NM","NM",IF(D23<=0,"NM",IF(I23=0,"NM",IF(ABS(I23/D23-1)>2.5,"NM",IF((ABS(I23-D23)=ABS(ABS(I23)-ABS(D23))),(I23/D23-1),"NM")))))) | J28: =IF(E23="NM","NM",IF(J23="NM","NM",IF(E23<=0,"NM",IF(J23=0,"NM",IF(ABS(J23/E23-1)>2.5,"NM",IF((ABS(J23-E23)=ABS(ABS(J23)-ABS(E23))),(J23/E23-1),"NM")))))) | K28: =IF(F23="NM","NM",IF(K23="NM","NM",IF(F23<=0,"NM",IF(K23=0,"NM",IF(ABS(K23/F23-1)>2.5,"NM",IF((ABS(K23-F23)=ABS(ABS(K23)-ABS(F23))),(K23/F23-1),"NM")))))) | L28: =IF(G23="NM","NM",IF(L23="NM","NM",IF(G23<=0,"NM",IF(L23=0,"NM",IF(ABS(L23/G23-1)>2.5,"NM",IF((ABS(L23-G23)=ABS(ABS(L23)-ABS(G23))),(L23/G23-1),"NM")))))) | M28: =IF(H23="NM","NM",IF(M23="NM","NM",IF(H23<=0,"NM",IF(M23=0,"NM",IF(ABS(M23/H23-1)>2.5,"NM",IF((ABS(M23-H23)=ABS(ABS(M23)-ABS(H23))),(M23/H23-1),"NM")))))) | N28: =IF(I23="NM","NM",IF(N23="NM","NM",IF(I23<=0,"NM",IF(N23=0,"NM",IF(ABS(N23/I23-1)>2.5,"NM",IF((ABS(N23-I23)=ABS(ABS(N23)-ABS(I23))),(N23/I23-1),"NM")))))) | O28: =IF(J23="NM","NM",IF(O23="NM","NM",IF(J23<=0,"NM",IF(O23=0,"NM",IF(ABS(O23/J23-1)>2.5,"NM",IF((ABS(O23-J23)=ABS(ABS(O23)-ABS(J23))),(O23/J23-1),"NM")))))) | P28: =IF(K23="NM","NM",IF(P23="NM","NM",IF(K23<=0,"NM",IF(P23=0,"NM",IF(ABS(P23/K23-1)>2.5,"NM",IF((ABS(P23-K23)=ABS(ABS(P23)-ABS(K23))),(P23/K23-1),"NM")))))) | ... CF28: =IF(CA23="NM","NM",IF(CF23="NM","NM",IF(CA23<=0,"NM",IF(CF23=0,"NM",IF(ABS(CF23/CA23-1)>2.5,"NM",IF((ABS(CF23-CA23)=ABS(ABS(CF23)-ABS(CA23))),(CF23/CA23-1),"NM")))))) | CG28: =IF(CB23=0, "NA", CG23/CB23-1) | CH28: =IF(CC23=0, "NA", CH23/CC23-1) | CI28: =IF(CD23=0, "NA", CI23/CD23-1) | CJ28: =IF(CE23=0, "NA", CJ23/CE23-1) | CK28: =IF(CF23=0, "NA", CK23/CF23-1) | CL28: =IF(CG23=0, "NA", CL23/CG23-1) | CM28: =IF(CH23=0, "NA", CM23/CH23-1) | CN28: =IF(CI23=0, "NA", CN23/CI23-1) | ... EI28: =IF(ED23=0, "NA", EI23/ED23-1) | EJ28: =IF(EI23=0, "NA", EJ23/EI23-1) | EK28: =IF(EJ23=0, "NA", EK23/EJ23-1) | EL28: =IF(EK23=0, "NA", EL23/EK23-1) | EM28: =IF(EL23=0, "NA", EM23/EL23-1) | EN28: =IF(EM23=0, "NA", EN23/EM23-1)
B29: Int'l | I29: =IF(D24="NM","NM",IF(I24="NM","NM",IF(D24<=0,"NM",IF(I24=0,"NM",IF(ABS(I24/D24-1)>2.5,"NM",IF((ABS(I24-D24)=ABS(ABS(I24)-ABS(D24))),(I24/D24-1),"NM")))))) | J29: =IF(E24="NM","NM",IF(J24="NM","NM",IF(E24<=0,"NM",IF(J24=0,"NM",IF(ABS(J24/E24-1)>2.5,"NM",IF((ABS(J24-E24)=ABS(ABS(J24)-ABS(E24))),(J24/E24-1),"NM")))))) | K29: =IF(F24="NM","NM",IF(K24="NM","NM",IF(F24<=0,"NM",IF(K24=0,"NM",IF(ABS(K24/F24-1)>2.5,"NM",IF((ABS(K24-F24)=ABS(ABS(K24)-ABS(F24))),(K24/F24-1),"NM")))))) | L29: =IF(G24="NM","NM",IF(L24="NM","NM",IF(G24<=0,"NM",IF(L24=0,"NM",IF(ABS(L24/G24-1)>2.5,"NM",IF((ABS(L24-G24)=ABS(ABS(L24)-ABS(G24))),(L24/G24-1),"NM")))))) | M29: =IF(H24="NM","NM",IF(M24="NM","NM",IF(H24<=0,"NM",IF(M24=0,"NM",IF(ABS(M24/H24-1)>2.5,"NM",IF((ABS(M24-H24)=ABS(ABS(M24)-ABS(H24))),(M24/H24-1),"NM")))))) | N29: =IF(I24="NM","NM",IF(N24="NM","NM",IF(I24<=0,"NM",IF(N24=0,"NM",IF(ABS(N24/I24-1)>2.5,"NM",IF((ABS(N24-I24)=ABS(ABS(N24)-ABS(I24))),(N24/I24-1),"NM")))))) | O29: =IF(J24="NM","NM",IF(O24="NM","NM",IF(J24<=0,"NM",IF(O24=0,"NM",IF(ABS(O24/J24-1)>2.5,"NM",IF((ABS(O24-J24)=ABS(ABS(O24)-ABS(J24))),(O24/J24-1),"NM")))))) | P29: =IF(K24="NM","NM",IF(P24="NM","NM",IF(K24<=0,"NM",IF(P24=0,"NM",IF(ABS(P24/K24-1)>2.5,"NM",IF((ABS(P24-K24)=ABS(ABS(P24)-ABS(K24))),(P24/K24-1),"NM")))))) | ... CF29: =IF(CA24="NM","NM",IF(CF24="NM","NM",IF(CA24<=0,"NM",IF(CF24=0,"NM",IF(ABS(CF24/CA24-1)>2.5,"NM",IF((ABS(CF24-CA24)=ABS(ABS(CF24)-ABS(CA24))),(CF24/CA24-1),"NM")))))) | CG29: =IF(CB24=0, "NA", CG24/CB24-1) | CH29: =IF(CC24=0, "NA", CH24/CC24-1) | CI29: =IF(CD24=0, "NA", CI24/CD24-1) | CJ29: =IF(CE24=0, "NA", CJ24/CE24-1) | CK29: =IF(CF24=0, "NA", CK24/CF24-1) | CL29: =IF(CG24=0, "NA", CL24/CG24-1) | CM29: =IF(CH24=0, "NA", CM24/CH24-1) | CN29: =IF(CI24=0, "NA", CN24/CI24-1) | ... EI29: =IF(ED24=0, "NA", EI24/ED24-1) | EJ29: =IF(EI24=0, "NA", EJ24/EI24-1) | EK29: =IF(EJ24=0, "NA", EK24/EJ24-1) | EL29: =IF(EK24=0, "NA", EL24/EK24-1) | EM29: =IF(EL24=0, "NA", EM24/EL24-1) | EN29: =IF(EM24=0, "NA", EN24/EM24-1)
B30: Int'l (ex-currency) | AI30: =IF(ISNUMBER(AI29),(1+AI29)/(1+AI$21)-1,"NM") | AJ30: =IF(ISNUMBER(AJ29),(1+AJ29)/(1+AJ$21)-1,"NM") | AK30: =IF(ISNUMBER(AK29),(1+AK29)/(1+AK$21)-1,"NM") | AL30: =IF(ISNUMBER(AL29),(1+AL29)/(1+AL$21)-1,"NM") | AM30: =IF(ISNUMBER(AM29),(1+AM29)/(1+AM$21)-1,"NM") | AN30: =IF(ISNUMBER(AN29),(1+AN29)/(1+AN$21)-1,"NM") | AO30: =IF(ISNUMBER(AO29),(1+AO29)/(1+AO$21)-1,"NM") | AP30: =IF(ISNUMBER(AP29),(1+AP29)/(1+AP$21)-1,"NM") | ... CF30: =IF(ISNUMBER(CF29),(1+CF29)/(1+CF$21)-1,"NM") | CG30: =CG29-CG$21 | CH30: =CH29-CH$21 | CI30: =CI29-CI$21 | CJ30: =CJ29-CJ$21 | CK30: =CK29-CK$21 | CL30: =CL29-CL$21 | CM30: =CM29-CM$21 | CN30: =CN29-CN$21 | ... EN30: =EN29-EN$21
B31: Worldwide | I31: =IF(D25="NM","NM",IF(I25="NM","NM",IF(D25<=0,"NM",IF(I25=0,"NM",IF(ABS(I25/D25-1)>2.5,"NM",IF((ABS(I25-D25)=ABS(ABS(I25)-ABS(D25))),(I25/D25-1),"NM")))))) | J31: =IF(E25="NM","NM",IF(J25="NM","NM",IF(E25<=0,"NM",IF(J25=0,"NM",IF(ABS(J25/E25-1)>2.5,"NM",IF((ABS(J25-E25)=ABS(ABS(J25)-ABS(E25))),(J25/E25-1),"NM")))))) | K31: =IF(F25="NM","NM",IF(K25="NM","NM",IF(F25<=0,"NM",IF(K25=0,"NM",IF(ABS(K25/F25-1)>2.5,"NM",IF((ABS(K25-F25)=ABS(ABS(K25)-ABS(F25))),(K25/F25-1),"NM")))))) | L31: =IF(G25="NM","NM",IF(L25="NM","NM",IF(G25<=0,"NM",IF(L25=0,"NM",IF(ABS(L25/G25-1)>2.5,"NM",IF((ABS(L25-G25)=ABS(ABS(L25)-ABS(G25))),(L25/G25-1),"NM")))))) | M31: =IF(H25="NM","NM",IF(M25="NM","NM",IF(H25<=0,"NM",IF(M25=0,"NM",IF(ABS(M25/H25-1)>2.5,"NM",IF((ABS(M25-H25)=ABS(ABS(M25)-ABS(H25))),(M25/H25-1),"NM")))))) | N31: =IF(I25="NM","NM",IF(N25="NM","NM",IF(I25<=0,"NM",IF(N25=0,"NM",IF(ABS(N25/I25-1)>2.5,"NM",IF((ABS(N25-I25)=ABS(ABS(N25)-ABS(I25))),(N25/I25-1),"NM")))))) | O31: =IF(J25="NM","NM",IF(O25="NM","NM",IF(J25<=0,"NM",IF(O25=0,"NM",IF(ABS(O25/J25-1)>2.5,"NM",IF((ABS(O25-J25)=ABS(ABS(O25)-ABS(J25))),(O25/J25-1),"NM")))))) | P31: =IF(K25="NM","NM",IF(P25="NM","NM",IF(K25<=0,"NM",IF(P25=0,"NM",IF(ABS(P25/K25-1)>2.5,"NM",IF((ABS(P25-K25)=ABS(ABS(P25)-ABS(K25))),(P25/K25-1),"NM")))))) | ... BP31: =IF(BK25="NM","NM",IF(BP25="NM","NM",IF(BK25<=0,"NM",IF(BP25=0,"NM",IF(ABS(BP25/BK25-1)>2.5,"NM",IF((ABS(BP25-BK25)=ABS(ABS(BP25)-ABS(BK25))),(BP25/BK25-1),"NM")))))) | BQ31: =IF(ISNUMBER(BQ30),(1+BQ30)/(1+BQ$21)-1,"NM") | BR31: =IF(BM25="NM","NM",IF(BR25="NM","NM",IF(BM25<=0,"NM",IF(BR25=0,"NM",IF(ABS(BR25/BM25-1)>2.5,"NM",IF((ABS(BR25-BM25)=ABS(ABS(BR25)-ABS(BM25))),(BR25/BM25-1),"NM")))))) | BS31: =IF(BN25="NM","NM",IF(BS25="NM","NM",IF(BN25<=0,"NM",IF(BS25=0,"NM",IF(ABS(BS25/BN25-1)>2.5,"NM",IF((ABS(BS25-BN25)=ABS(ABS(BS25)-ABS(BN25))),(BS25/BN25-1),"NM")))))) | BT31: =IF(BO25="NM","NM",IF(BT25="NM","NM",IF(BO25<=0,"NM",IF(BT25=0,"NM",IF(ABS(BT25/BO25-1)>2.5,"NM",IF((ABS(BT25-BO25)=ABS(ABS(BT25)-ABS(BO25))),(BT25/BO25-1),"NM")))))) | BU31: =IF(BP25="NM","NM",IF(BU25="NM","NM",IF(BP25<=0,"NM",IF(BU25=0,"NM",IF(ABS(BU25/BP25-1)>2.5,"NM",IF((ABS(BU25-BP25)=ABS(ABS(BU25)-ABS(BP25))),(BU25/BP25-1),"NM")))))) | BV31: =IF(BQ25="NM","NM",IF(BV25="NM","NM",IF(BQ25<=0,"NM",IF(BV25=0,"NM",IF(ABS(BV25/BQ25-1)>2.5,"NM",IF((ABS(BV25-BQ25)=ABS(ABS(BV25)-ABS(BQ25))),(BV25/BQ25-1),"NM")))))) | BW31: =IF(BR25="NM","NM",IF(BW25="NM","NM",IF(BR25<=0,"NM",IF(BW25=0,"NM",IF(ABS(BW25/BR25-1)>2.5,"NM",IF((ABS(BW25-BR25)=ABS(ABS(BW25)-ABS(BR25))),(BW25/BR25-1),"NM")))))) | BX31: =IF(BS25="NM","NM",IF(BX25="NM","NM",IF(BS25<=0,"NM",IF(BX25=0,"NM",IF(ABS(BX25/BS25-1)>2.5,"NM",IF((ABS(BX25-BS25)=ABS(ABS(BX25)-ABS(BS25))),(BX25/BS25-1),"NM")))))) | BY31: =IF(BT25="NM","NM",IF(BY25="NM","NM",IF(BT25<=0,"NM",IF(BY25=0,"NM",IF(ABS(BY25/BT25-1)>2.5,"NM",IF((ABS(BY25-BT25)=ABS(ABS(BY25)-ABS(BT25))),(BY25/BT25-1),"NM")))))) | ... CF31: =IF(CA25="NM","NM",IF(CF25="NM","NM",IF(CA25<=0,"NM",IF(CF25=0,"NM",IF(ABS(CF25/CA25-1)>2.5,"NM",IF((ABS(CF25-CA25)=ABS(ABS(CF25)-ABS(CA25))),(CF25/CA25-1),"NM")))))) | CG31: =IF(CB25=0, "NA", CG25/CB25-1) | CH31: =IF(CC25=0, "NA", CH25/CC25-1) | CI31: =IF(CD25=0, "NA", CI25/CD25-1) | CJ31: =IF(CE25=0, "NA", CJ25/CE25-1) | CK31: =IF(CF25=0, "NA", CK25/CF25-1) | CL31: =IF(CG25=0, "NA", CL25/CG25-1) | CM31: =IF(CH25=0, "NA", CM25/CH25-1) | CN31: =IF(CI25=0, "NA", CN25/CI25-1) | ... EI31: =IF(ED25=0, "NA", EI25/ED25-1) | EJ31: =IF(EI25=0, "NA", EJ25/EI25-1) | EK31: =IF(EJ25=0, "NA", EK25/EJ25-1) | EL31: =IF(EK25=0, "NA", EL25/EK25-1) | EM31: =IF(EL25=0, "NA", EM25/EL25-1) | EN31: =IF(EM25=0, "NA", EN25/EM25-1)
B33: Innovative Medicine
A34: Pharma - US | B34: US | D34: =+D885 | E34: =+E885 | F34: =+F885 | G34: =+G885 | H34: =+H885 | I34: =+I885 | J34: =+J885 | K34: =+K885 | ... CE34: =+CE885 | CF34: =SUM(CB34:CE34) | CG34: =+CG885 | CH34: =+CH885 | CI34: =+CI885 | CJ34: =+CJ885 | CK34: =SUM(CG34:CJ34) | CL34: =+CL885 | CM34: =+CM885 | CN34: =+CN885 | CO34: =+CO885 | CP34: =+CP885 | CQ34: =+CQ885 | CR34: =+CR885 | CS34: =+CS885 | ... ES34: =+ES885
A35: =+A36&" - OUS" | B35: International | D35: =+D886 | E35: =+E886 | F35: =+F886 | G35: =+G886 | H35: =+H886 | I35: =+I886 | J35: =+J886 | K35: =+K886 | ... CE35: =+CE886 | CF35: =SUM(CB35:CE35) | CG35: =+CG886 | CH35: =+CH886 | CI35: =+CI886 | CJ35: =+CJ886 | CK35: =SUM(CG35:CJ35) | CL35: =+CL886 | CM35: =+CM886 | CN35: =+CN886 | CO35: =+CO886 | CP35: =+CP886 | CQ35: =+CQ886 | CR35: =+CR886 | CS35: =+CS886 | ... ES35: =+ES886
A36: Pharma | B36: Worldwide | D36: =+D35+D34 | E36: =+E35+E34 | F36: =+F35+F34 | G36: =+G35+G34 | H36: =+H35+H34 | I36: =+I35+I34 | J36: =+J35+J34 | K36: =+K35+K34 | ... CE36: =+CE35+CE34 | CF36: =SUM(CB36:CE36) | CG36: =+CG35+CG34 | CH36: =+CH35+CH34 | CI36: =+CI35+CI34 | CJ36: =+CJ35+CJ34 | CK36: =SUM(CG36:CJ36) | CL36: =+CL35+CL34 | CM36: =+CM35+CM34 | CN36: =+CN35+CN34 | CO36: =+CO35+CO34 | CP36: =+CP35+CP34 | CQ36: =+CQ35+CQ34 | CR36: =+CR35+CR34 | CS36: =+CS35+CS34 | ... ES36: =+ES35+ES34
B38: Innovative Medicine sales % growth
B39: US | I39: =IF(D34="NM","NM",IF(I34="NM","NM",IF(D34<=0,"NM",IF(I34=0,"NM",IF(ABS(I34/D34-1)>2.5,"NM",IF((ABS(I34-D34)=ABS(ABS(I34)-ABS(D34))),(I34/D34-1),"NM")))))) | J39: =IF(E34="NM","NM",IF(J34="NM","NM",IF(E34<=0,"NM",IF(J34=0,"NM",IF(ABS(J34/E34-1)>2.5,"NM",IF((ABS(J34-E34)=ABS(ABS(J34)-ABS(E34))),(J34/E34-1),"NM")))))) | K39: =IF(F34="NM","NM",IF(K34="NM","NM",IF(F34<=0,"NM",IF(K34=0,"NM",IF(ABS(K34/F34-1)>2.5,"NM",IF((ABS(K34-F34)=ABS(ABS(K34)-ABS(F34))),(K34/F34-1),"NM")))))) | L39: =IF(G34="NM","NM",IF(L34="NM","NM",IF(G34<=0,"NM",IF(L34=0,"NM",IF(ABS(L34/G34-1)>2.5,"NM",IF((ABS(L34-G34)=ABS(ABS(L34)-ABS(G34))),(L34/G34-1),"NM")))))) | M39: =IF(H34="NM","NM",IF(M34="NM","NM",IF(H34<=0,"NM",IF(M34=0,"NM",IF(ABS(M34/H34-1)>2.5,"NM",IF((ABS(M34-H34)=ABS(ABS(M34)-ABS(H34))),(M34/H34-1),"NM")))))) | N39: =IF(I34="NM","NM",IF(N34="NM","NM",IF(I34<=0,"NM",IF(N34=0,"NM",IF(ABS(N34/I34-1)>2.5,"NM",IF((ABS(N34-I34)=ABS(ABS(N34)-ABS(I34))),(N34/I34-1),"NM")))))) | O39: =IF(J34="NM","NM",IF(O34="NM","NM",IF(J34<=0,"NM",IF(O34=0,"NM",IF(ABS(O34/J34-1)>2.5,"NM",IF((ABS(O34-J34)=ABS(ABS(O34)-ABS(J34))),(O34/J34-1),"NM")))))) | P39: =IF(K34="NM","NM",IF(P34="NM","NM",IF(K34<=0,"NM",IF(P34=0,"NM",IF(ABS(P34/K34-1)>2.5,"NM",IF((ABS(P34-K34)=ABS(ABS(P34)-ABS(K34))),(P34/K34-1),"NM")))))) | ... CE39: =IF(BZ34="NM","NM",IF(CE34="NM","NM",IF(BZ34<=0,"NM",IF(CE34=0,"NM",IF(ABS(CE34/BZ34-1)>2.5,"NM",IF((ABS(CE34-BZ34)=ABS(ABS(CE34)-ABS(BZ34))),(CE34/BZ34-1),"NM")))))) | CF39: =IF(CA34=0, "NA", CF34/CA34-1) | CG39: =IF(CB34=0, "NA", CG34/CB34-1) | CH39: =IF(CC34=0, "NA", CH34/CC34-1) | CI39: =IF(CD34=0, "NA", CI34/CD34-1) | CJ39: =IF(CE34=0, "NA", CJ34/CE34-1) | CK39: =IF(CF34=0, "NA", CK34/CF34-1) | CL39: =IF(CG34=0, "NA", CL34/CG34-1) | CM39: =IF(CH34=0, "NA", CM34/CH34-1) | ... EI39: =IF(ED34=0, "NA", EI34/ED34-1) | EJ39: =IF(EI34=0, "NA", EJ34/EI34-1) | EK39: =IF(EJ34=0, "NA", EK34/EJ34-1) | EL39: =IF(EK34=0, "NA", EL34/EK34-1) | EM39: =IF(EL34=0, "NA", EM34/EL34-1) | EN39: =IF(EM34=0, "NA", EN34/EM34-1) | EO39: =IF(EN34=0, "NA", EO34/EN34-1) | EP39: =IF(EO34=0, "NA", EP34/EO34-1) | EQ39: =IF(EP34=0, "NA", EQ34/EP34-1) | ... ES39: =IF(ER34=0, "NA", ES34/ER34-1)
B40: International | I40: =IF(D35="NM","NM",IF(I35="NM","NM",IF(D35<=0,"NM",IF(I35=0,"NM",IF(ABS(I35/D35-1)>2.5,"NM",IF((ABS(I35-D35)=ABS(ABS(I35)-ABS(D35))),(I35/D35-1),"NM")))))) | J40: =IF(E35="NM","NM",IF(J35="NM","NM",IF(E35<=0,"NM",IF(J35=0,"NM",IF(ABS(J35/E35-1)>2.5,"NM",IF((ABS(J35-E35)=ABS(ABS(J35)-ABS(E35))),(J35/E35-1),"NM")))))) | K40: =IF(F35="NM","NM",IF(K35="NM","NM",IF(F35<=0,"NM",IF(K35=0,"NM",IF(ABS(K35/F35-1)>2.5,"NM",IF((ABS(K35-F35)=ABS(ABS(K35)-ABS(F35))),(K35/F35-1),"NM")))))) | L40: =IF(G35="NM","NM",IF(L35="NM","NM",IF(G35<=0,"NM",IF(L35=0,"NM",IF(ABS(L35/G35-1)>2.5,"NM",IF((ABS(L35-G35)=ABS(ABS(L35)-ABS(G35))),(L35/G35-1),"NM")))))) | M40: =IF(H35="NM","NM",IF(M35="NM","NM",IF(H35<=0,"NM",IF(M35=0,"NM",IF(ABS(M35/H35-1)>2.5,"NM",IF((ABS(M35-H35)=ABS(ABS(M35)-ABS(H35))),(M35/H35-1),"NM")))))) | N40: =IF(I35="NM","NM",IF(N35="NM","NM",IF(I35<=0,"NM",IF(N35=0,"NM",IF(ABS(N35/I35-1)>2.5,"NM",IF((ABS(N35-I35)=ABS(ABS(N35)-ABS(I35))),(N35/I35-1),"NM")))))) | O40: =IF(J35="NM","NM",IF(O35="NM","NM",IF(J35<=0,"NM",IF(O35=0,"NM",IF(ABS(O35/J35-1)>2.5,"NM",IF((ABS(O35-J35)=ABS(ABS(O35)-ABS(J35))),(O35/J35-1),"NM")))))) | P40: =IF(K35="NM","NM",IF(P35="NM","NM",IF(K35<=0,"NM",IF(P35=0,"NM",IF(ABS(P35/K35-1)>2.5,"NM",IF((ABS(P35-K35)=ABS(ABS(P35)-ABS(K35))),(P35/K35-1),"NM")))))) | ... CE40: =IF(BZ35="NM","NM",IF(CE35="NM","NM",IF(BZ35<=0,"NM",IF(CE35=0,"NM",IF(ABS(CE35/BZ35-1)>2.5,"NM",IF((ABS(CE35-BZ35)=ABS(ABS(CE35)-ABS(BZ35))),(CE35/BZ35-1),"NM")))))) | CF40: =IF(CA35=0, "NA", CF35/CA35-1) | CG40: =IF(CB35=0, "NA", CG35/CB35-1) | CH40: =IF(CC35=0, "NA", CH35/CC35-1) | CI40: =IF(CD35=0, "NA", CI35/CD35-1) | CJ40: =IF(CE35=0, "NA", CJ35/CE35-1) | CK40: =IF(CF35=0, "NA", CK35/CF35-1) | CL40: =IF(CG35=0, "NA", CL35/CG35-1) | CM40: =IF(CH35=0, "NA", CM35/CH35-1) | ... EI40: =IF(ED35=0, "NA", EI35/ED35-1) | EJ40: =IF(EI35=0, "NA", EJ35/EI35-1) | EK40: =IF(EJ35=0, "NA", EK35/EJ35-1) | EL40: =IF(EK35=0, "NA", EL35/EK35-1) | EM40: =IF(EL35=0, "NA", EM35/EL35-1) | EN40: =IF(EM35=0, "NA", EN35/EM35-1) | EO40: =IF(EN35=0, "NA", EO35/EN35-1) | EP40: =IF(EO35=0, "NA", EP35/EO35-1) | EQ40: =IF(EP35=0, "NA", EQ35/EP35-1) | ... ES40: =IF(ER35=0, "NA", ES35/ER35-1)
B41: International (ex-currency) | AI41: =IF(ISNUMBER(AI40),(1+AI40)/(1+AI$21)-1,"NM") | AJ41: =IF(ISNUMBER(AJ40),(1+AJ40)/(1+AJ$21)-1,"NM") | AK41: =IF(ISNUMBER(AK40),(1+AK40)/(1+AK$21)-1,"NM") | AL41: =IF(ISNUMBER(AL40),(1+AL40)/(1+AL$21)-1,"NM") | AM41: =IF(ISNUMBER(AM40),(1+AM40)/(1+AM$21)-1,"NM") | AN41: =IF(ISNUMBER(AN40),(1+AN40)/(1+AN$21)-1,"NM") | AO41: =IF(ISNUMBER(AO40),(1+AO40)/(1+AO$21)-1,"NM") | AP41: =IF(ISNUMBER(AP40),(1+AP40)/(1+AP$21)-1,"NM") | ... CE41: =IF(ISNUMBER(CE40),(1+CE40)/(1+CE$21)-1,"NM") | CF41: =CF40-CF$21 | CG41: =CG40-CG$21 | CH41: =CH40-CH$21 | CI41: =CI40-CI$21 | CJ41: =CJ40-CJ$21 | CK41: =CK40-CK$21 | CL41: =CL40-CL$21 | CM41: =CM40-CM$21 | ... ES41: =ES40-ES$21
B42: Worldwide | I42: =IF(D36="NM","NM",IF(I36="NM","NM",IF(D36<=0,"NM",IF(I36=0,"NM",IF(ABS(I36/D36-1)>2.5,"NM",IF((ABS(I36-D36)=ABS(ABS(I36)-ABS(D36))),(I36/D36-1),"NM")))))) | J42: =IF(E36="NM","NM",IF(J36="NM","NM",IF(E36<=0,"NM",IF(J36=0,"NM",IF(ABS(J36/E36-1)>2.5,"NM",IF((ABS(J36-E36)=ABS(ABS(J36)-ABS(E36))),(J36/E36-1),"NM")))))) | K42: =IF(F36="NM","NM",IF(K36="NM","NM",IF(F36<=0,"NM",IF(K36=0,"NM",IF(ABS(K36/F36-1)>2.5,"NM",IF((ABS(K36-F36)=ABS(ABS(K36)-ABS(F36))),(K36/F36-1),"NM")))))) | L42: =IF(G36="NM","NM",IF(L36="NM","NM",IF(G36<=0,"NM",IF(L36=0,"NM",IF(ABS(L36/G36-1)>2.5,"NM",IF((ABS(L36-G36)=ABS(ABS(L36)-ABS(G36))),(L36/G36-1),"NM")))))) | M42: =IF(H36="NM","NM",IF(M36="NM","NM",IF(H36<=0,"NM",IF(M36=0,"NM",IF(ABS(M36/H36-1)>2.5,"NM",IF((ABS(M36-H36)=ABS(ABS(M36)-ABS(H36))),(M36/H36-1),"NM")))))) | N42: =IF(I36="NM","NM",IF(N36="NM","NM",IF(I36<=0,"NM",IF(N36=0,"NM",IF(ABS(N36/I36-1)>2.5,"NM",IF((ABS(N36-I36)=ABS(ABS(N36)-ABS(I36))),(N36/I36-1),"NM")))))) | O42: =IF(J36="NM","NM",IF(O36="NM","NM",IF(J36<=0,"NM",IF(O36=0,"NM",IF(ABS(O36/J36-1)>2.5,"NM",IF((ABS(O36-J36)=ABS(ABS(O36)-ABS(J36))),(O36/J36-1),"NM")))))) | P42: =IF(K36="NM","NM",IF(P36="NM","NM",IF(K36<=0,"NM",IF(P36=0,"NM",IF(ABS(P36/K36-1)>2.5,"NM",IF((ABS(P36-K36)=ABS(ABS(P36)-ABS(K36))),(P36/K36-1),"NM")))))) | ... CE42: =IF(BZ36="NM","NM",IF(CE36="NM","NM",IF(BZ36<=0,"NM",IF(CE36=0,"NM",IF(ABS(CE36/BZ36-1)>2.5,"NM",IF((ABS(CE36-BZ36)=ABS(ABS(CE36)-ABS(BZ36))),(CE36/BZ36-1),"NM")))))) | CF42: =IF(CA36=0, "NA", CF36/CA36-1) | CG42: =IF(CB36=0, "NA", CG36/CB36-1) | CH42: =IF(CC36=0, "NA", CH36/CC36-1) | CI42: =IF(CD36=0, "NA", CI36/CD36-1) | CJ42: =IF(CE36=0, "NA", CJ36/CE36-1) | CK42: =IF(CF36=0, "NA", CK36/CF36-1) | CL42: =IF(CG36=0, "NA", CL36/CG36-1) | CM42: =IF(CH36=0, "NA", CM36/CH36-1) | ... EI42: =IF(ED36=0, "NA", EI36/ED36-1) | EJ42: =IF(EI36=0, "NA", EJ36/EI36-1) | EK42: =IF(EJ36=0, "NA", EK36/EJ36-1) | EL42: =IF(EK36=0, "NA", EL36/EK36-1) | EM42: =IF(EL36=0, "NA", EM36/EL36-1) | EN42: =IF(EM36=0, "NA", EN36/EM36-1) | EO42: =IF(EN36=0, "NA", EO36/EN36-1) | EP42: =IF(EO36=0, "NA", EP36/EO36-1) | EQ42: =IF(EP36=0, "NA", EQ36/EP36-1) | ... ES42: =IF(ER36=0, "NA", ES36/ER36-1)
B44: MedTech
A45: =A47&" - US" | B45: US | D45: =+D1348 | E45: =+E1348 | F45: =+F1348 | G45: =+G1348 | H45: =+H1348 | I45: =+I1348 | J45: =+J1348 | K45: =+K1348 | ... EN45: =+EN1348
A46: =+A47&" - OUS" | B46: International | D46: =+D1349 | E46: =+E1349 | F46: =+F1349 | G46: =+G1349 | H46: =+H1349 | I46: =+I1349 | J46: =+J1349 | K46: =+K1349 | ... EN46: =+EN1349
A47: MD&D | B47: Worldwide | D47: =+D46+D45 | E47: =+E46+E45 | F47: =+F46+F45 | G47: =+G46+G45 | H47: =+H46+H45 | I47: =+I46+I45 | J47: =+J46+J45 | K47: =+K46+K45 | ... EN47: =+EN46+EN45
B49: MedTech sales % growth
B50: US | I50: =IF(D45="NM","NM",IF(I45="NM","NM",IF(D45<=0,"NM",IF(I45=0,"NM",IF(ABS(I45/D45-1)>2.5,"NM",IF((ABS(I45-D45)=ABS(ABS(I45)-ABS(D45))),(I45/D45-1),"NM")))))) | J50: =IF(E45="NM","NM",IF(J45="NM","NM",IF(E45<=0,"NM",IF(J45=0,"NM",IF(ABS(J45/E45-1)>2.5,"NM",IF((ABS(J45-E45)=ABS(ABS(J45)-ABS(E45))),(J45/E45-1),"NM")))))) | K50: =IF(F45="NM","NM",IF(K45="NM","NM",IF(F45<=0,"NM",IF(K45=0,"NM",IF(ABS(K45/F45-1)>2.5,"NM",IF((ABS(K45-F45)=ABS(ABS(K45)-ABS(F45))),(K45/F45-1),"NM")))))) | L50: =IF(G45="NM","NM",IF(L45="NM","NM",IF(G45<=0,"NM",IF(L45=0,"NM",IF(ABS(L45/G45-1)>2.5,"NM",IF((ABS(L45-G45)=ABS(ABS(L45)-ABS(G45))),(L45/G45-1),"NM")))))) | M50: =IF(H45="NM","NM",IF(M45="NM","NM",IF(H45<=0,"NM",IF(M45=0,"NM",IF(ABS(M45/H45-1)>2.5,"NM",IF((ABS(M45-H45)=ABS(ABS(M45)-ABS(H45))),(M45/H45-1),"NM")))))) | N50: =IF(I45="NM","NM",IF(N45="NM","NM",IF(I45<=0,"NM",IF(N45=0,"NM",IF(ABS(N45/I45-1)>2.5,"NM",IF((ABS(N45-I45)=ABS(ABS(N45)-ABS(I45))),(N45/I45-1),"NM")))))) | O50: =IF(J45="NM","NM",IF(O45="NM","NM",IF(J45<=0,"NM",IF(O45=0,"NM",IF(ABS(O45/J45-1)>2.5,"NM",IF((ABS(O45-J45)=ABS(ABS(O45)-ABS(J45))),(O45/J45-1),"NM")))))) | P50: =IF(K45="NM","NM",IF(P45="NM","NM",IF(K45<=0,"NM",IF(P45=0,"NM",IF(ABS(P45/K45-1)>2.5,"NM",IF((ABS(P45-K45)=ABS(ABS(P45)-ABS(K45))),(P45/K45-1),"NM")))))) | ... CA50: =IF(BV45="NM","NM",IF(CA45="NM","NM",IF(BV45<=0,"NM",IF(CA45=0,"NM",IF(ABS(CA45/BV45-1)>2.5,"NM",IF((ABS(CA45-BV45)=ABS(ABS(CA45)-ABS(BV45))),(CA45/BV45-1),"NM")))))) | CB50: =IF(BW45=0, "NA", CB45/BW45-1) | CC50: =IF(BX45=0, "NA", CC45/BX45-1) | CD50: =IF(BY45="NM","NM",IF(CD45="NM","NM",IF(BY45<=0,"NM",IF(CD45=0,"NM",IF(ABS(CD45/BY45-1)>2.5,"NM",IF((ABS(CD45-BY45)=ABS(ABS(CD45)-ABS(BY45))),(CD45/BY45-1),"NM")))))) | CE50: =IF(BZ45="NM","NM",IF(CE45="NM","NM",IF(BZ45<=0,"NM",IF(CE45=0,"NM",IF(ABS(CE45/BZ45-1)>2.5,"NM",IF((ABS(CE45-BZ45)=ABS(ABS(CE45)-ABS(BZ45))),(CE45/BZ45-1),"NM")))))) | CF50: =IF(CA45=0, "NA", CF45/CA45-1) | CG50: =IF(CB45=0, "NA", CG45/CB45-1) | CH50: =IF(CC45=0, "NA", CH45/CC45-1) | CI50: =IF(CD45=0, "NA", CI45/CD45-1) | CJ50: =IF(CE45=0, "NA", CJ45/CE45-1) | CK50: =IF(CF45=0, "NA", CK45/CF45-1) | CL50: =IF(CG45=0, "NA", CL45/CG45-1) | CM50: =IF(CH45=0, "NA", CM45/CH45-1) | ... EI50: =IF(ED45=0, "NA", EI45/ED45-1) | EJ50: =IF(EI45=0, "NA", EJ45/EI45-1) | EK50: =IF(EJ45=0, "NA", EK45/EJ45-1) | EL50: =IF(EK45=0, "NA", EL45/EK45-1) | EM50: =IF(EL45=0, "NA", EM45/EL45-1) | EN50: =IF(EM45=0, "NA", EN45/EM45-1)
B51: International | I51: =IF(D46="NM","NM",IF(I46="NM","NM",IF(D46<=0,"NM",IF(I46=0,"NM",IF(ABS(I46/D46-1)>2.5,"NM",IF((ABS(I46-D46)=ABS(ABS(I46)-ABS(D46))),(I46/D46-1),"NM")))))) | J51: =IF(E46="NM","NM",IF(J46="NM","NM",IF(E46<=0,"NM",IF(J46=0,"NM",IF(ABS(J46/E46-1)>2.5,"NM",IF((ABS(J46-E46)=ABS(ABS(J46)-ABS(E46))),(J46/E46-1),"NM")))))) | K51: =IF(F46="NM","NM",IF(K46="NM","NM",IF(F46<=0,"NM",IF(K46=0,"NM",IF(ABS(K46/F46-1)>2.5,"NM",IF((ABS(K46-F46)=ABS(ABS(K46)-ABS(F46))),(K46/F46-1),"NM")))))) | L51: =IF(G46="NM","NM",IF(L46="NM","NM",IF(G46<=0,"NM",IF(L46=0,"NM",IF(ABS(L46/G46-1)>2.5,"NM",IF((ABS(L46-G46)=ABS(ABS(L46)-ABS(G46))),(L46/G46-1),"NM")))))) | M51: =IF(H46="NM","NM",IF(M46="NM","NM",IF(H46<=0,"NM",IF(M46=0,"NM",IF(ABS(M46/H46-1)>2.5,"NM",IF((ABS(M46-H46)=ABS(ABS(M46)-ABS(H46))),(M46/H46-1),"NM")))))) | N51: =IF(I46="NM","NM",IF(N46="NM","NM",IF(I46<=0,"NM",IF(N46=0,"NM",IF(ABS(N46/I46-1)>2.5,"NM",IF((ABS(N46-I46)=ABS(ABS(N46)-ABS(I46))),(N46/I46-1),"NM")))))) | O51: =IF(J46="NM","NM",IF(O46="NM","NM",IF(J46<=0,"NM",IF(O46=0,"NM",IF(ABS(O46/J46-1)>2.5,"NM",IF((ABS(O46-J46)=ABS(ABS(O46)-ABS(J46))),(O46/J46-1),"NM")))))) | P51: =IF(K46="NM","NM",IF(P46="NM","NM",IF(K46<=0,"NM",IF(P46=0,"NM",IF(ABS(P46/K46-1)>2.5,"NM",IF((ABS(P46-K46)=ABS(ABS(P46)-ABS(K46))),(P46/K46-1),"NM")))))) | ... CA51: =IF(BV46="NM","NM",IF(CA46="NM","NM",IF(BV46<=0,"NM",IF(CA46=0,"NM",IF(ABS(CA46/BV46-1)>2.5,"NM",IF((ABS(CA46-BV46)=ABS(ABS(CA46)-ABS(BV46))),(CA46/BV46-1),"NM")))))) | CB51: =IF(BW46=0, "NA", CB46/BW46-1) | CC51: =IF(BX46=0, "NA", CC46/BX46-1) | CD51: =IF(BY46="NM","NM",IF(CD46="NM","NM",IF(BY46<=0,"NM",IF(CD46=0,"NM",IF(ABS(CD46/BY46-1)>2.5,"NM",IF((ABS(CD46-BY46)=ABS(ABS(CD46)-ABS(BY46))),(CD46/BY46-1),"NM")))))) | CE51: =IF(BZ46="NM","NM",IF(CE46="NM","NM",IF(BZ46<=0,"NM",IF(CE46=0,"NM",IF(ABS(CE46/BZ46-1)>2.5,"NM",IF((ABS(CE46-BZ46)=ABS(ABS(CE46)-ABS(BZ46))),(CE46/BZ46-1),"NM")))))) | CF51: =IF(CA46=0, "NA", CF46/CA46-1) | CG51: =IF(CB46=0, "NA", CG46/CB46-1) | CH51: =IF(CC46=0, "NA", CH46/CC46-1) | CI51: =IF(CD46=0, "NA", CI46/CD46-1) | CJ51: =IF(CE46=0, "NA", CJ46/CE46-1) | CK51: =IF(CF46=0, "NA", CK46/CF46-1) | CL51: =IF(CG46=0, "NA", CL46/CG46-1) | CM51: =IF(CH46=0, "NA", CM46/CH46-1) | ... EI51: =IF(ED46=0, "NA", EI46/ED46-1) | EJ51: =IF(EI46=0, "NA", EJ46/EI46-1) | EK51: =IF(EJ46=0, "NA", EK46/EJ46-1) | EL51: =IF(EK46=0, "NA", EL46/EK46-1) | EM51: =IF(EL46=0, "NA", EM46/EL46-1) | EN51: =IF(EM46=0, "NA", EN46/EM46-1)
B52: International (ex-currency) | AI52: =IF(ISNUMBER(AI51),(1+AI51)/(1+AI$21)-1,"NM") | AJ52: =IF(ISNUMBER(AJ51),(1+AJ51)/(1+AJ$21)-1,"NM") | AK52: =IF(ISNUMBER(AK51),(1+AK51)/(1+AK$21)-1,"NM") | AL52: =IF(ISNUMBER(AL51),(1+AL51)/(1+AL$21)-1,"NM") | AM52: =IF(ISNUMBER(AM51),(1+AM51)/(1+AM$21)-1,"NM") | AN52: =IF(ISNUMBER(AN51),(1+AN51)/(1+AN$21)-1,"NM") | AO52: =IF(ISNUMBER(AO51),(1+AO51)/(1+AO$21)-1,"NM") | AP52: =IF(ISNUMBER(AP51),(1+AP51)/(1+AP$21)-1,"NM") | ... CA52: =IF(ISNUMBER(CA51),(1+CA51)/(1+CA$21)-1,"NM") | CB52: =CB51-CB$21 | CC52: =CC51-CC$21 | CD52: =IF(ISNUMBER(CD51),(1+CD51)/(1+CD$21)-1,"NM") | CE52: =IF(ISNUMBER(CE51),(1+CE51)/(1+CE$21)-1,"NM") | CF52: =CF51-CF$21 | CG52: =CG51-CG$21 | CH52: =CH51-CH$21 | CI52: =CI51-CI$21 | CJ52: =CJ51-CJ$21 | CK52: =CK51-CK$21 | CL52: =CL51-CL$21 | CM52: =CM51-CM$21 | ... EN52: =EN51-EN$21
B53: Worldwide | I53: =IF(D47="NM","NM",IF(I47="NM","NM",IF(D47<=0,"NM",IF(I47=0,"NM",IF(ABS(I47/D47-1)>2.5,"NM",IF((ABS(I47-D47)=ABS(ABS(I47)-ABS(D47))),(I47/D47-1),"NM")))))) | J53: =IF(E47="NM","NM",IF(J47="NM","NM",IF(E47<=0,"NM",IF(J47=0,"NM",IF(ABS(J47/E47-1)>2.5,"NM",IF((ABS(J47-E47)=ABS(ABS(J47)-ABS(E47))),(J47/E47-1),"NM")))))) | K53: =IF(F47="NM","NM",IF(K47="NM","NM",IF(F47<=0,"NM",IF(K47=0,"NM",IF(ABS(K47/F47-1)>2.5,"NM",IF((ABS(K47-F47)=ABS(ABS(K47)-ABS(F47))),(K47/F47-1),"NM")))))) | L53: =IF(G47="NM","NM",IF(L47="NM","NM",IF(G47<=0,"NM",IF(L47=0,"NM",IF(ABS(L47/G47-1)>2.5,"NM",IF((ABS(L47-G47)=ABS(ABS(L47)-ABS(G47))),(L47/G47-1),"NM")))))) | M53: =IF(H47="NM","NM",IF(M47="NM","NM",IF(H47<=0,"NM",IF(M47=0,"NM",IF(ABS(M47/H47-1)>2.5,"NM",IF((ABS(M47-H47)=ABS(ABS(M47)-ABS(H47))),(M47/H47-1),"NM")))))) | N53: =IF(I47="NM","NM",IF(N47="NM","NM",IF(I47<=0,"NM",IF(N47=0,"NM",IF(ABS(N47/I47-1)>2.5,"NM",IF((ABS(N47-I47)=ABS(ABS(N47)-ABS(I47))),(N47/I47-1),"NM")))))) | O53: =IF(J47="NM","NM",IF(O47="NM","NM",IF(J47<=0,"NM",IF(O47=0,"NM",IF(ABS(O47/J47-1)>2.5,"NM",IF((ABS(O47-J47)=ABS(ABS(O47)-ABS(J47))),(O47/J47-1),"NM")))))) | P53: =IF(K47="NM","NM",IF(P47="NM","NM",IF(K47<=0,"NM",IF(P47=0,"NM",IF(ABS(P47/K47-1)>2.5,"NM",IF((ABS(P47-K47)=ABS(ABS(P47)-ABS(K47))),(P47/K47-1),"NM")))))) | ... CA53: =IF(BV47="NM","NM",IF(CA47="NM","NM",IF(BV47<=0,"NM",IF(CA47=0,"NM",IF(ABS(CA47/BV47-1)>2.5,"NM",IF((ABS(CA47-BV47)=ABS(ABS(CA47)-ABS(BV47))),(CA47/BV47-1),"NM")))))) | CB53: =IF(BW47=0, "NA", CB47/BW47-1) | CC53: =IF(BX47=0, "NA", CC47/BX47-1) | CD53: =IF(BY47="NM","NM",IF(CD47="NM","NM",IF(BY47<=0,"NM",IF(CD47=0,"NM",IF(ABS(CD47/BY47-1)>2.5,"NM",IF((ABS(CD47-BY47)=ABS(ABS(CD47)-ABS(BY47))),(CD47/BY47-1),"NM")))))) | CE53: =IF(BZ47="NM","NM",IF(CE47="NM","NM",IF(BZ47<=0,"NM",IF(CE47=0,"NM",IF(ABS(CE47/BZ47-1)>2.5,"NM",IF((ABS(CE47-BZ47)=ABS(ABS(CE47)-ABS(BZ47))),(CE47/BZ47-1),"NM")))))) | CF53: =IF(CA47=0, "NA", CF47/CA47-1) | CG53: =IF(CB47=0, "NA", CG47/CB47-1) | CH53: =IF(CC47=0, "NA", CH47/CC47-1) | CI53: =IF(CD47=0, "NA", CI47/CD47-1) | CJ53: =IF(CE47=0, "NA", CJ47/CE47-1) | CK53: =IF(CF47=0, "NA", CK47/CF47-1) | CL53: =IF(CG47=0, "NA", CL47/CG47-1) | CM53: =IF(CH47=0, "NA", CM47/CH47-1) | ... EI53: =IF(ED47=0, "NA", EI47/ED47-1) | EJ53: =IF(EI47=0, "NA", EJ47/EI47-1) | EK53: =IF(EJ47=0, "NA", EK47/EJ47-1) | EL53: =IF(EK47=0, "NA", EL47/EK47-1) | EM53: =IF(EL47=0, "NA", EM47/EL47-1) | EN53: =IF(EM47=0, "NA", EN47/EM47-1)
DO54: =(DO47-DE47)/DE47
B55: Consumer
A56: =A58&" - US" | B56: U.S. | D56: =+D1487 | E56: =+E1487 | F56: =+F1487 | G56: =+G1487 | H56: =+H1487 | I56: =+I1487 | J56: =+J1487 | K56: =+K1487 | ... CE56: =+CE1487 | CF56: =SUM(CB56:CE56) | CG56: =+CG1487 | CH56: =+CH1487 | CI56: =+CI1487 | CJ56: =+CJ1487 | CK56: =SUM(CG56:CJ56) | CL56: =+CL1487 | CM56: =+CM1487 | CN56: =+CN1487 | CO56: =+CO1487 | CP56: =+CP1487 | CQ56: =+CQ1487 | CR56: =+CR1487 | CS56: =+CS1487 | ... DV56: =+DV1487
A57: =+A58&" - OUS" | B57: International | D57: =+D1488 | E57: =+E1488 | F57: =+F1488 | G57: =+G1488 | H57: =+H1488 | I57: =+I1488 | J57: =+J1488 | K57: =+K1488 | ... CE57: =+CE1488 | CF57: =SUM(CB57:CE57) | CG57: =+CG1488 | CH57: =+CH1488 | CI57: =+CI1488 | CJ57: =+CJ1488 | CK57: =SUM(CG57:CJ57) | CL57: =+CL1488 | CM57: =+CM1488 | CN57: =+CN1488 | CO57: =+CO1488 | CP57: =+CP1488 | CQ57: =+CQ1488 | CR57: =+CR1488 | CS57: =+CS1488 | ... DV57: =+DV1488
A58: Consumer | B58: Worldwide | D58: =+D57+D56 | E58: =+E57+E56 | F58: =+F57+F56 | G58: =+G57+G56 | H58: =+H57+H56 | I58: =+I57+I56 | J58: =+J57+J56 | K58: =+K57+K56 | ... CE58: =+CE57+CE56 | CF58: =SUM(CB58:CE58) | CG58: =+CG57+CG56 | CH58: =+CH57+CH56 | CI58: =+CI57+CI56 | CJ58: =+CJ57+CJ56 | CK58: =SUM(CG58:CJ58) | CL58: =+CL57+CL56 | CM58: =+CM57+CM56 | CN58: =+CN57+CN56 | CO58: =+CO57+CO56 | CP58: =+CP57+CP56 | CQ58: =+CQ57+CQ56 | CR58: =+CR57+CR56 | CS58: =+CS57+CS56 | ... DV58: =+DV57+DV56
BL59: =+BL58/BL25
B60: Consumer sales % growth
B61: US | I61: =IF(D56="NM","NM",IF(I56="NM","NM",IF(D56<=0,"NM",IF(I56=0,"NM",IF(ABS(I56/D56-1)>2.5,"NM",IF((ABS(I56-D56)=ABS(ABS(I56)-ABS(D56))),(I56/D56-1),"NM")))))) | J61: =IF(E56="NM","NM",IF(J56="NM","NM",IF(E56<=0,"NM",IF(J56=0,"NM",IF(ABS(J56/E56-1)>2.5,"NM",IF((ABS(J56-E56)=ABS(ABS(J56)-ABS(E56))),(J56/E56-1),"NM")))))) | K61: =IF(F56="NM","NM",IF(K56="NM","NM",IF(F56<=0,"NM",IF(K56=0,"NM",IF(ABS(K56/F56-1)>2.5,"NM",IF((ABS(K56-F56)=ABS(ABS(K56)-ABS(F56))),(K56/F56-1),"NM")))))) | L61: =IF(G56="NM","NM",IF(L56="NM","NM",IF(G56<=0,"NM",IF(L56=0,"NM",IF(ABS(L56/G56-1)>2.5,"NM",IF((ABS(L56-G56)=ABS(ABS(L56)-ABS(G56))),(L56/G56-1),"NM")))))) | M61: =IF(H56="NM","NM",IF(M56="NM","NM",IF(H56<=0,"NM",IF(M56=0,"NM",IF(ABS(M56/H56-1)>2.5,"NM",IF((ABS(M56-H56)=ABS(ABS(M56)-ABS(H56))),(M56/H56-1),"NM")))))) | N61: =IF(I56="NM","NM",IF(N56="NM","NM",IF(I56<=0,"NM",IF(N56=0,"NM",IF(ABS(N56/I56-1)>2.5,"NM",IF((ABS(N56-I56)=ABS(ABS(N56)-ABS(I56))),(N56/I56-1),"NM")))))) | O61: =IF(J56="NM","NM",IF(O56="NM","NM",IF(J56<=0,"NM",IF(O56=0,"NM",IF(ABS(O56/J56-1)>2.5,"NM",IF((ABS(O56-J56)=ABS(ABS(O56)-ABS(J56))),(O56/J56-1),"NM")))))) | P61: =IF(K56="NM","NM",IF(P56="NM","NM",IF(K56<=0,"NM",IF(P56=0,"NM",IF(ABS(P56/K56-1)>2.5,"NM",IF((ABS(P56-K56)=ABS(ABS(P56)-ABS(K56))),(P56/K56-1),"NM")))))) | ... CE61: =IF(BZ56="NM","NM",IF(CE56="NM","NM",IF(BZ56<=0,"NM",IF(CE56=0,"NM",IF(ABS(CE56/BZ56-1)>2.5,"NM",IF((ABS(CE56-BZ56)=ABS(ABS(CE56)-ABS(BZ56))),(CE56/BZ56-1),"NM")))))) | CF61: =IF(CA56=0, "NA", CF56/CA56-1) | CG61: =IF(CB56=0, "NA", CG56/CB56-1) | CH61: =IF(CC56=0, "NA", CH56/CC56-1) | CI61: =IF(CD56=0, "NA", CI56/CD56-1) | CJ61: =IF(CE56=0, "NA", CJ56/CE56-1) | CK61: =IF(CF56=0, "NA", CK56/CF56-1) | CL61: =IF(CG56=0, "NA", CL56/CG56-1) | CM61: =IF(CH56=0, "NA", CM56/CH56-1) | ... DV61: =IF(DQ56=0, "NA", DV56/DQ56-1)
B62: Int'l | I62: =IF(D57="NM","NM",IF(I57="NM","NM",IF(D57<=0,"NM",IF(I57=0,"NM",IF(ABS(I57/D57-1)>2.5,"NM",IF((ABS(I57-D57)=ABS(ABS(I57)-ABS(D57))),(I57/D57-1),"NM")))))) | J62: =IF(E57="NM","NM",IF(J57="NM","NM",IF(E57<=0,"NM",IF(J57=0,"NM",IF(ABS(J57/E57-1)>2.5,"NM",IF((ABS(J57-E57)=ABS(ABS(J57)-ABS(E57))),(J57/E57-1),"NM")))))) | K62: =IF(F57="NM","NM",IF(K57="NM","NM",IF(F57<=0,"NM",IF(K57=0,"NM",IF(ABS(K57/F57-1)>2.5,"NM",IF((ABS(K57-F57)=ABS(ABS(K57)-ABS(F57))),(K57/F57-1),"NM")))))) | L62: =IF(G57="NM","NM",IF(L57="NM","NM",IF(G57<=0,"NM",IF(L57=0,"NM",IF(ABS(L57/G57-1)>2.5,"NM",IF((ABS(L57-G57)=ABS(ABS(L57)-ABS(G57))),(L57/G57-1),"NM")))))) | M62: =IF(H57="NM","NM",IF(M57="NM","NM",IF(H57<=0,"NM",IF(M57=0,"NM",IF(ABS(M57/H57-1)>2.5,"NM",IF((ABS(M57-H57)=ABS(ABS(M57)-ABS(H57))),(M57/H57-1),"NM")))))) | N62: =IF(I57="NM","NM",IF(N57="NM","NM",IF(I57<=0,"NM",IF(N57=0,"NM",IF(ABS(N57/I57-1)>2.5,"NM",IF((ABS(N57-I57)=ABS(ABS(N57)-ABS(I57))),(N57/I57-1),"NM")))))) | O62: =IF(J57="NM","NM",IF(O57="NM","NM",IF(J57<=0,"NM",IF(O57=0,"NM",IF(ABS(O57/J57-1)>2.5,"NM",IF((ABS(O57-J57)=ABS(ABS(O57)-ABS(J57))),(O57/J57-1),"NM")))))) | P62: =IF(K57="NM","NM",IF(P57="NM","NM",IF(K57<=0,"NM",IF(P57=0,"NM",IF(ABS(P57/K57-1)>2.5,"NM",IF((ABS(P57-K57)=ABS(ABS(P57)-ABS(K57))),(P57/K57-1),"NM")))))) | ... CE62: =IF(BZ57="NM","NM",IF(CE57="NM","NM",IF(BZ57<=0,"NM",IF(CE57=0,"NM",IF(ABS(CE57/BZ57-1)>2.5,"NM",IF((ABS(CE57-BZ57)=ABS(ABS(CE57)-ABS(BZ57))),(CE57/BZ57-1),"NM")))))) | CF62: =IF(CA57=0, "NA", CF57/CA57-1) | CG62: =IF(CB57=0, "NA", CG57/CB57-1) | CH62: =IF(CC57=0, "NA", CH57/CC57-1) | CI62: =IF(CD57=0, "NA", CI57/CD57-1) | CJ62: =IF(CE57=0, "NA", CJ57/CE57-1) | CK62: =IF(CF57=0, "NA", CK57/CF57-1) | CL62: =IF(CG57=0, "NA", CL57/CG57-1) | CM62: =IF(CH57=0, "NA", CM57/CH57-1) | ... DV62: =IF(DQ57=0, "NA", DV57/DQ57-1)
B63: Int'l (ex-currency) | AI63: =IF(ISNUMBER(AI62),(1+AI62)/(1+AI$21)-1,"NM") | AJ63: =IF(ISNUMBER(AJ62),(1+AJ62)/(1+AJ$21)-1,"NM") | AK63: =IF(ISNUMBER(AK62),(1+AK62)/(1+AK$21)-1,"NM") | AL63: =IF(ISNUMBER(AL62),(1+AL62)/(1+AL$21)-1,"NM") | AM63: =IF(ISNUMBER(AM62),(1+AM62)/(1+AM$21)-1,"NM") | AN63: =IF(ISNUMBER(AN62),(1+AN62)/(1+AN$21)-1,"NM") | AO63: =IF(ISNUMBER(AO62),(1+AO62)/(1+AO$21)-1,"NM") | AP63: =IF(ISNUMBER(AP62),(1+AP62)/(1+AP$21)-1,"NM") | ... CE63: =IF(ISNUMBER(CE62),(1+CE62)/(1+CE$21)-1,"NM") | CF63: =CF62-CF$21 | CG63: =CG62-CG$21 | CH63: =CH62-CH$21 | CI63: =CI62-CI$21 | CJ63: =CJ62-CJ$21 | CK63: =CK62-CK$21 | CL63: =CL62-CL$21 | CM63: =CM62-CM$21 | ... DV63: =DV62-DV$21
B64: Worldwide | I64: =IF(D58="NM","NM",IF(I58="NM","NM",IF(D58<=0,"NM",IF(I58=0,"NM",IF(ABS(I58/D58-1)>2.5,"NM",IF((ABS(I58-D58)=ABS(ABS(I58)-ABS(D58))),(I58/D58-1),"NM")))))) | J64: =IF(E58="NM","NM",IF(J58="NM","NM",IF(E58<=0,"NM",IF(J58=0,"NM",IF(ABS(J58/E58-1)>2.5,"NM",IF((ABS(J58-E58)=ABS(ABS(J58)-ABS(E58))),(J58/E58-1),"NM")))))) | K64: =IF(F58="NM","NM",IF(K58="NM","NM",IF(F58<=0,"NM",IF(K58=0,"NM",IF(ABS(K58/F58-1)>2.5,"NM",IF((ABS(K58-F58)=ABS(ABS(K58)-ABS(F58))),(K58/F58-1),"NM")))))) | L64: =IF(G58="NM","NM",IF(L58="NM","NM",IF(G58<=0,"NM",IF(L58=0,"NM",IF(ABS(L58/G58-1)>2.5,"NM",IF((ABS(L58-G58)=ABS(ABS(L58)-ABS(G58))),(L58/G58-1),"NM")))))) | M64: =IF(H58="NM","NM",IF(M58="NM","NM",IF(H58<=0,"NM",IF(M58=0,"NM",IF(ABS(M58/H58-1)>2.5,"NM",IF((ABS(M58-H58)=ABS(ABS(M58)-ABS(H58))),(M58/H58-1),"NM")))))) | N64: =IF(I58="NM","NM",IF(N58="NM","NM",IF(I58<=0,"NM",IF(N58=0,"NM",IF(ABS(N58/I58-1)>2.5,"NM",IF((ABS(N58-I58)=ABS(ABS(N58)-ABS(I58))),(N58/I58-1),"NM")))))) | O64: =IF(J58="NM","NM",IF(O58="NM","NM",IF(J58<=0,"NM",IF(O58=0,"NM",IF(ABS(O58/J58-1)>2.5,"NM",IF((ABS(O58-J58)=ABS(ABS(O58)-ABS(J58))),(O58/J58-1),"NM")))))) | P64: =IF(K58="NM","NM",IF(P58="NM","NM",IF(K58<=0,"NM",IF(P58=0,"NM",IF(ABS(P58/K58-1)>2.5,"NM",IF((ABS(P58-K58)=ABS(ABS(P58)-ABS(K58))),(P58/K58-1),"NM")))))) | ... CE64: =IF(BZ58="NM","NM",IF(CE58="NM","NM",IF(BZ58<=0,"NM",IF(CE58=0,"NM",IF(ABS(CE58/BZ58-1)>2.5,"NM",IF((ABS(CE58-BZ58)=ABS(ABS(CE58)-ABS(BZ58))),(CE58/BZ58-1),"NM")))))) | CF64: =IF(CA58=0, "NA", CF58/CA58-1) | CG64: =IF(CB58=0, "NA", CG58/CB58-1) | CH64: =IF(CC58=0, "NA", CH58/CC58-1) | CI64: =IF(CD58=0, "NA", CI58/CD58-1) | CJ64: =IF(CE58=0, "NA", CJ58/CE58-1) | CK64: =IF(CF58=0, "NA", CK58/CF58-1) | CL64: =IF(CG58=0, "NA", CL58/CG58-1) | CM64: =IF(CH58=0, "NA", CM58/CH58-1) | ... DV64: =IF(DQ58=0, "NA", DV58/DQ58-1)
B67: INNOVATIVE MEDICINE | C67: Patent
B69: Infectious Diseases | DU69: =SUM(DU127,DU171,DU182) | DV69: =SUM(DV127,DV171,DV182) | DW69: =SUM(DW127,DW171,DW182) | DX69: =SUM(DX127,DX171,DX182)
B70: US | BM70: 624 | BN70: 351 | BO70: 216 | BP70: 210 | BQ70: =SUM(BM70:BP70) | BR70: 242 | BS70: 237 | BT70: 259 | BU70: 236 | BV70: =SUM(BR70:BU70) | BW70: 238 | BX70: 259 | BY70: 278 | BZ70: 302 | CA70: =SUM(BW70:BZ70) | CB70: 561 | CC70: 1020 | CD70: 967 | CE70: 564 | CF70: =SUM(CB70:CE70) | CG70: 412 | CH70: 381 | CI70: 379 | CJ70: 363 | CK70: =SUM(CG70:CJ70) | CL70: 358 | CM70: 362 | CN70: 387 | CO70: 354 | CP70: =CP81+CP114+CP180 | CQ70: 326 | CR70: 341 | CS70: 353 | CT70: 338 | CU70: =+SUM(CQ70:CT70) | CV70: 333 | CW70: 328 | CX70: 345 | CY70: 372 | CZ70: =+SUM(CV70:CY70) | DA70: 357 | DB70: 387 | DC70: 418 | DD70: 435 | DE70: =+DE125+DE169+DE180 | DF70: 436 | DG70: 416 | DH70: 412.6 | DI70: 470 | DJ70: =+DJ125+DJ169+DJ180 | DK70: 412.4 | DL70: =444-51 | DM70: =679-270 | DN70: =614-213 | DO70: =+DO125+DO169+DO180-1 | DP70: =461-75 | DQ70: =415-45 | DR70: =390 | DS70: =414 | DT70: =+DT125+DT169+DT180 | DU70: 392 | DV70: 395 | DW70: 360 | DX70: 353.3 | DY70: =+DY125+DY169+DY180 | DZ70: 324 | EA70: 334 | EB70: 365 | EC70: 331 | ED70: =+ED125+ED169+ED180 | EE70: =+EE125+EE169+EE180 | EF70: =+EF125+EF169+EF180 | EG70: =+EG125+EG169+EG180 | EH70: =+EH125+EH169+EH180 | EI70: =+EI125+EI169+EI180 | EJ70: =+EJ125+EJ169+EJ180 | EK70: =+EK125+EK169+EK180 | ... ES70: =+ES125+ES169+ES180
B71: International | BM71: 307 | BN71: 477 | BO71: 498 | BP71: 506 | BQ71: =SUM(BM71:BP71) | BR71: 513 | BS71: 551 | BT71: 536 | BU71: 620 | BV71: =SUM(BR71:BU71) | BW71: 577 | BX71: 711 | BY71: 543 | BZ71: 642 | CA71: =SUM(BW71:BZ71) | CB71: 639 | CC71: 742 | CD71: 594 | CE71: 512 | CF71: =SUM(CB71:CE71) | CG71: 563 | CH71: 651 | CI71: 469 | CJ71: 438 | CK71: =SUM(CG71:CJ71) | CL71: 418 | CM71: 467 | CN71: 455 | CO71: 407 | CP71: =CP82+CP115+CP181 | CQ71: 423 | CR71: 451 | CS71: 460 | CT71: 462 | CU71: =+SUM(CQ71:CT71) | CV71: 497 | CW71: 521 | CX71: 478 | CY71: 430 | CZ71: =+SUM(CV71:CY71) | DA71: 489 | DB71: 475 | DC71: 421 | DD71: 430 | DE71: =+DE126+DE170+DE181 | DF71: 483 | DG71: 463.4 | DH71: 451 | DI71: 442 | DJ71: =+DJ126+DJ170+DJ181 | DK71: 494.4 | DL71: =585-113 | DM71: =709-233 | DN71: =1824-1405 | DO71: =+DO126+DO170+DO181-1 | DP71: =836-382 | DQ71: =901-499 | DR71: =905-489 | DS71: =1127-689 | DT71: =+DT126+DT170+DT181 | DU71: =1193-747 | DV71: =727-285 | DW71: =500-41 | DX71: =498.3-43.8 | DY71: =+DY126+DY170+DY181 | DZ71: =497-25 | EA71: =630.5-172 | EB71: =471-1 | EC71: 443 | ED71: =+ED126+ED170+ED181 | EE71: =+EE126+EE170+EE181 | EF71: =+EF126+EF170+EF181 | EG71: =+EG126+EG170+EG181 | EH71: =+EH126+EH170+EH181 | EI71: =+EI126+EI170+EI181 | EJ71: =+EJ126+EJ170+EJ181 | EK71: =+EK126+EK170+EK181 | ... ES71: =+ES126+ES170+ES181
A72: Infectious Diseases | B72: Worldwide | BM72: =BM71+BM70 | BN72: =BN71+BN70 | BO72: =BO71+BO70 | BP72: =BP71+BP70 | BQ72: =BQ71+BQ70 | BR72: =BR71+BR70 | BS72: =BS71+BS70 | BT72: =BT71+BT70 | ... CE72: =CE71+CE70 | CF72: =SUM(CB72:CE72) | CG72: =CG71+CG70 | CH72: =CH71+CH70 | CI72: =CI71+CI70 | CJ72: =CJ71+CJ70 | CK72: =SUM(CG72:CJ72) | CL72: =CL71+CL70 | CM72: =CM71+CM70 | CN72: =CN71+CN70 | CO72: =CO71+CO70 | CP72: =CP83+CP116+CP182 | CQ72: =CQ71+CQ70 | CR72: =CR71+CR70 | CS72: =CS71+CS70 | CT72: =CT71+CT70 | CU72: =+SUM(CQ72:CT72) | CV72: =CV71+CV70 | CW72: =CW71+CW70 | CX72: =CX71+CX70 | CY72: =CY71+CY70 | CZ72: =+SUM(CV72:CY72) | DA72: =DA71+DA70 | DB72: =DB71+DB70 | DC72: =DC71+DC70 | DD72: =DD71+DD70 | DE72: =+DE127+DE171+DE182 | DF72: =DF71+DF70 | DG72: =DG71+DG70 | DH72: =DH71+DH70 | DI72: =DI71+DI70 | DJ72: =+DJ127+DJ171+DJ182 | DK72: =DK71+DK70 | DL72: =DL71+DL70 | DM72: =DM71+DM70 | DN72: =DN71+DN70 | DO72: =SUM(DO70:DO71) | DP72: =DP71+DP70 | DQ72: =DQ71+DQ70 | DR72: =DR71+DR70 | DS72: =DS71+DS70 | DT72: =+DT127+DT171+DT182 | DU72: =DU71+DU70 | DV72: =DV71+DV70 | DW72: =DW71+DW70 | DX72: =DX71+DX70 | DY72: =+DY127+DY171+DY182 | DZ72: =DZ71+DZ70 | EA72: =EA71+EA70 | EB72: =EB71+EB70 | EC72: =EC71+EC70 | ED72: =+ED127+ED171+ED182 | EE72: =EE71+EE70 | EF72: =EF71+EF70 | EG72: 829 | EH72: =EH71+EH70 | EI72: =+EI127+EI171+EI182 | EJ72: =+EJ127+EJ171+EJ182 | EK72: =+EK127+EK171+EK182 | EL72: =+EL127+EL171+EL182 | EM72: =+EM127+EM171+EM182 | EN72: =+EN127+EN171+EN182 | EO72: =+EO127+EO171+EO182 | EP72: =+EP127+EP171+EP182 | ... ES72: =+ES127+ES171+ES182
B74: Infectious Diseases % growth
B75: US | BM75: =IF(BH70="NM","NM",IF(BM70="NM","NM",IF(BH70<=0,"NM",IF(BM70=0,"NM",IF(ABS(BM70/BH70-1)>2.5,"NM",IF((ABS(BM70-BH70)=ABS(ABS(BM70)-ABS(BH70))),(BM70/BH70-1),"NM")))))) | BN75: =IF(BI70="NM","NM",IF(BN70="NM","NM",IF(BI70<=0,"NM",IF(BN70=0,"NM",IF(ABS(BN70/BI70-1)>2.5,"NM",IF((ABS(BN70-BI70)=ABS(ABS(BN70)-ABS(BI70))),(BN70/BI70-1),"NM")))))) | BO75: =IF(BJ70="NM","NM",IF(BO70="NM","NM",IF(BJ70<=0,"NM",IF(BO70=0,"NM",IF(ABS(BO70/BJ70-1)>2.5,"NM",IF((ABS(BO70-BJ70)=ABS(ABS(BO70)-ABS(BJ70))),(BO70/BJ70-1),"NM")))))) | BP75: =IF(BK70="NM","NM",IF(BP70="NM","NM",IF(BK70<=0,"NM",IF(BP70=0,"NM",IF(ABS(BP70/BK70-1)>2.5,"NM",IF((ABS(BP70-BK70)=ABS(ABS(BP70)-ABS(BK70))),(BP70/BK70-1),"NM")))))) | BQ75: =IF(BL70="NM","NM",IF(BQ70="NM","NM",IF(BL70<=0,"NM",IF(BQ70=0,"NM",IF(ABS(BQ70/BL70-1)>2.5,"NM",IF((ABS(BQ70-BL70)=ABS(ABS(BQ70)-ABS(BL70))),(BQ70/BL70-1),"NM")))))) | BR75: =IF(BM70="NM","NM",IF(BR70="NM","NM",IF(BM70<=0,"NM",IF(BR70=0,"NM",IF(ABS(BR70/BM70-1)>2.5,"NM",IF((ABS(BR70-BM70)=ABS(ABS(BR70)-ABS(BM70))),(BR70/BM70-1),"NM")))))) | BS75: =IF(BN70="NM","NM",IF(BS70="NM","NM",IF(BN70<=0,"NM",IF(BS70=0,"NM",IF(ABS(BS70/BN70-1)>2.5,"NM",IF((ABS(BS70-BN70)=ABS(ABS(BS70)-ABS(BN70))),(BS70/BN70-1),"NM")))))) | BT75: =IF(BO70="NM","NM",IF(BT70="NM","NM",IF(BO70<=0,"NM",IF(BT70=0,"NM",IF(ABS(BT70/BO70-1)>2.5,"NM",IF((ABS(BT70-BO70)=ABS(ABS(BT70)-ABS(BO70))),(BT70/BO70-1),"NM")))))) | ... CB75: =IF(BW70="NM","NM",IF(CB70="NM","NM",IF(BW70<=0,"NM",IF(CB70=0,"NM",IF(ABS(CB70/BW70-1)>2.5,"NM",IF((ABS(CB70-BW70)=ABS(ABS(CB70)-ABS(BW70))),(CB70/BW70-1),"NM")))))) | CC75: =IF(BX70=0, "NA", CC70/BX70-1) | CD75: =IF(BY70="NM","NM",IF(CD70="NM","NM",IF(BY70<=0,"NM",IF(CD70=0,"NM",IF(ABS(CD70/BY70-1)>2.5,"NM",IF((ABS(CD70-BY70)=ABS(ABS(CD70)-ABS(BY70))),(CD70/BY70-1),"NM")))))) | CE75: =IF(BZ70="NM","NM",IF(CE70="NM","NM",IF(BZ70<=0,"NM",IF(CE70=0,"NM",IF(ABS(CE70/BZ70-1)>2.5,"NM",IF((ABS(CE70-BZ70)=ABS(ABS(CE70)-ABS(BZ70))),(CE70/BZ70-1),"NM")))))) | CF75: =IF(CA70="NM","NM",IF(CF70="NM","NM",IF(CA70<=0,"NM",IF(CF70=0,"NM",IF(ABS(CF70/CA70-1)>2.5,"NM",IF((ABS(CF70-CA70)=ABS(ABS(CF70)-ABS(CA70))),(CF70/CA70-1),"NM")))))) | CG75: =IF(CB70=0, "NA", CG70/CB70-1) | CH75: =IF(CC70=0, "NA", CH70/CC70-1) | CI75: =IF(CD70=0, "NA", CI70/CD70-1) | CJ75: =IF(CE70=0, "NA", CJ70/CE70-1) | CK75: =IF(CF70=0, "NA", CK70/CF70-1) | CL75: =IF(CG70=0, "NA", CL70/CG70-1) | CM75: =IF(CH70=0, "NA", CM70/CH70-1) | CN75: =IF(CI70=0, "NA", CN70/CI70-1) | ... EI75: =IF(ED70=0, "NA", EI70/ED70-1) | EJ75: =IF(EI70=0, "NA", EJ70/EI70-1) | EK75: =IF(EJ70=0, "NA", EK70/EJ70-1) | EL75: =IF(EK70=0, "NA", EL70/EK70-1) | EM75: =IF(EL70=0, "NA", EM70/EL70-1) | EN75: =IF(EM70=0, "NA", EN70/EM70-1) | EO75: =IF(EN70=0, "NA", EO70/EN70-1) | EP75: =IF(EO70=0, "NA", EP70/EO70-1) | EQ75: =IF(EP70=0, "NA", EQ70/EP70-1) | ... ES75: =IF(ER70=0, "NA", ES70/ER70-1)
B76: International | BM76: =IF(BH71="NM","NM",IF(BM71="NM","NM",IF(BH71<=0,"NM",IF(BM71=0,"NM",IF(ABS(BM71/BH71-1)>2.5,"NM",IF((ABS(BM71-BH71)=ABS(ABS(BM71)-ABS(BH71))),(BM71/BH71-1),"NM")))))) | BN76: =IF(BI71="NM","NM",IF(BN71="NM","NM",IF(BI71<=0,"NM",IF(BN71=0,"NM",IF(ABS(BN71/BI71-1)>2.5,"NM",IF((ABS(BN71-BI71)=ABS(ABS(BN71)-ABS(BI71))),(BN71/BI71-1),"NM")))))) | BO76: =IF(BJ71="NM","NM",IF(BO71="NM","NM",IF(BJ71<=0,"NM",IF(BO71=0,"NM",IF(ABS(BO71/BJ71-1)>2.5,"NM",IF((ABS(BO71-BJ71)=ABS(ABS(BO71)-ABS(BJ71))),(BO71/BJ71-1),"NM")))))) | BP76: =IF(BK71="NM","NM",IF(BP71="NM","NM",IF(BK71<=0,"NM",IF(BP71=0,"NM",IF(ABS(BP71/BK71-1)>2.5,"NM",IF((ABS(BP71-BK71)=ABS(ABS(BP71)-ABS(BK71))),(BP71/BK71-1),"NM")))))) | BQ76: =IF(BL71="NM","NM",IF(BQ71="NM","NM",IF(BL71<=0,"NM",IF(BQ71=0,"NM",IF(ABS(BQ71/BL71-1)>2.5,"NM",IF((ABS(BQ71-BL71)=ABS(ABS(BQ71)-ABS(BL71))),(BQ71/BL71-1),"NM")))))) | BR76: =IF(BM71="NM","NM",IF(BR71="NM","NM",IF(BM71<=0,"NM",IF(BR71=0,"NM",IF(ABS(BR71/BM71-1)>2.5,"NM",IF((ABS(BR71-BM71)=ABS(ABS(BR71)-ABS(BM71))),(BR71/BM71-1),"NM")))))) | BS76: =IF(BN71="NM","NM",IF(BS71="NM","NM",IF(BN71<=0,"NM",IF(BS71=0,"NM",IF(ABS(BS71/BN71-1)>2.5,"NM",IF((ABS(BS71-BN71)=ABS(ABS(BS71)-ABS(BN71))),(BS71/BN71-1),"NM")))))) | BT76: =IF(BO71="NM","NM",IF(BT71="NM","NM",IF(BO71<=0,"NM",IF(BT71=0,"NM",IF(ABS(BT71/BO71-1)>2.5,"NM",IF((ABS(BT71-BO71)=ABS(ABS(BT71)-ABS(BO71))),(BT71/BO71-1),"NM")))))) | ... CF76: =IF(CA71="NM","NM",IF(CF71="NM","NM",IF(CA71<=0,"NM",IF(CF71=0,"NM",IF(ABS(CF71/CA71-1)>2.5,"NM",IF((ABS(CF71-CA71)=ABS(ABS(CF71)-ABS(CA71))),(CF71/CA71-1),"NM")))))) | CG76: =IF(CB71=0, "NA", CG71/CB71-1) | CH76: =IF(CC71=0, "NA", CH71/CC71-1) | CI76: =IF(CD71=0, "NA", CI71/CD71-1) | CJ76: =IF(CE71=0, "NA", CJ71/CE71-1) | CK76: =IF(CF71=0, "NA", CK71/CF71-1) | CL76: =IF(CG71=0, "NA", CL71/CG71-1) | CM76: =IF(CH71=0, "NA", CM71/CH71-1) | CN76: =IF(CI71=0, "NA", CN71/CI71-1) | ... EI76: =IF(ED71=0, "NA", EI71/ED71-1) | EJ76: =IF(EI71=0, "NA", EJ71/EI71-1) | EK76: =IF(EJ71=0, "NA", EK71/EJ71-1) | EL76: =IF(EK71=0, "NA", EL71/EK71-1) | EM76: =IF(EL71=0, "NA", EM71/EL71-1) | EN76: =IF(EM71=0, "NA", EN71/EM71-1) | EO76: =IF(EN71=0, "NA", EO71/EN71-1) | EP76: =IF(EO71=0, "NA", EP71/EO71-1) | EQ76: =IF(EP71=0, "NA", EQ71/EP71-1) | ... ES76: =IF(ER71=0, "NA", ES71/ER71-1)
B77: International (ex-currency) | BM77: =IF(ISNUMBER(BM76),(1+BM76)/(1+BM$21)-1,"NM") | BN77: =IF(ISNUMBER(BN76),(1+BN76)/(1+BN$21)-1,"NM") | BO77: =IF(ISNUMBER(BO76),(1+BO76)/(1+BO$21)-1,"NM") | BP77: =IF(ISNUMBER(BP76),(1+BP76)/(1+BP$21)-1,"NM") | BQ77: =IF(ISNUMBER(BQ76),(1+BQ76)/(1+BQ$21)-1,"NM") | BR77: =IF(ISNUMBER(BR76),(1+BR76)/(1+BR$21)-1,"NM") | BS77: =IF(ISNUMBER(BS76),(1+BS76)/(1+BS$21)-1,"NM") | BT77: =IF(ISNUMBER(BT76),(1+BT76)/(1+BT$21)-1,"NM") | ... CF77: =IF(ISNUMBER(CF76),(1+CF76)/(1+CF$21)-1,"NM") | CG77: =CG76-CG$21 | CH77: =CH76-CH$21 | CI77: =CI76-CI$21 | CJ77: =CJ76-CJ$21 | CK77: =CK76-CK$21 | CL77: =CL76-CL$21 | CM77: =CM76-CM$21 | CN77: =CN76-CN$21 | ... DT77: =DT76-DT$21 | DU77: =DU76-(-6.4%) | DV77: =DV76-DV$21 | DW77: =DW76-DW$21 | DX77: =DX76-DX$21 | DY77: =DY76-DY$21 | DZ77: =DZ76-(-0.1%) | EA77: =EA76-(-1.5%) | EB77: =EB76-(-0.6%) | EC77: =EC76-(-1.4%) | ED77: =ED76-ED$21 | EE77: =EE76-(-0.1%) | EF77: =EF76-(-1.5%) | EG77: =EG76-(-0.6%) | EH77: =EH76-EH$21 | EI77: =EI76-EI$21 | EJ77: =EJ76-EJ$21 | EK77: =EK76-EK$21 | EL77: =EL76-EL$21 | EM77: =EM76-EM$21 | EN77: =EN76-EN$21 | EO77: =EO76-EO$21 | ... ES77: =ES76-ES$21
B78: Worldwide | BM78: =IF(BH72="NM","NM",IF(BM72="NM","NM",IF(BH72<=0,"NM",IF(BM72=0,"NM",IF(ABS(BM72/BH72-1)>2.5,"NM",IF((ABS(BM72-BH72)=ABS(ABS(BM72)-ABS(BH72))),(BM72/BH72-1),"NM")))))) | BN78: =IF(BI72="NM","NM",IF(BN72="NM","NM",IF(BI72<=0,"NM",IF(BN72=0,"NM",IF(ABS(BN72/BI72-1)>2.5,"NM",IF((ABS(BN72-BI72)=ABS(ABS(BN72)-ABS(BI72))),(BN72/BI72-1),"NM")))))) | BO78: =IF(BJ72="NM","NM",IF(BO72="NM","NM",IF(BJ72<=0,"NM",IF(BO72=0,"NM",IF(ABS(BO72/BJ72-1)>2.5,"NM",IF((ABS(BO72-BJ72)=ABS(ABS(BO72)-ABS(BJ72))),(BO72/BJ72-1),"NM")))))) | BP78: =IF(BK72="NM","NM",IF(BP72="NM","NM",IF(BK72<=0,"NM",IF(BP72=0,"NM",IF(ABS(BP72/BK72-1)>2.5,"NM",IF((ABS(BP72-BK72)=ABS(ABS(BP72)-ABS(BK72))),(BP72/BK72-1),"NM")))))) | BQ78: =IF(BL72="NM","NM",IF(BQ72="NM","NM",IF(BL72<=0,"NM",IF(BQ72=0,"NM",IF(ABS(BQ72/BL72-1)>2.5,"NM",IF((ABS(BQ72-BL72)=ABS(ABS(BQ72)-ABS(BL72))),(BQ72/BL72-1),"NM")))))) | BR78: =IF(BM72="NM","NM",IF(BR72="NM","NM",IF(BM72<=0,"NM",IF(BR72=0,"NM",IF(ABS(BR72/BM72-1)>2.5,"NM",IF((ABS(BR72-BM72)=ABS(ABS(BR72)-ABS(BM72))),(BR72/BM72-1),"NM")))))) | BS78: =IF(BN72="NM","NM",IF(BS72="NM","NM",IF(BN72<=0,"NM",IF(BS72=0,"NM",IF(ABS(BS72/BN72-1)>2.5,"NM",IF((ABS(BS72-BN72)=ABS(ABS(BS72)-ABS(BN72))),(BS72/BN72-1),"NM")))))) | BT78: =IF(BO72="NM","NM",IF(BT72="NM","NM",IF(BO72<=0,"NM",IF(BT72=0,"NM",IF(ABS(BT72/BO72-1)>2.5,"NM",IF((ABS(BT72-BO72)=ABS(ABS(BT72)-ABS(BO72))),(BT72/BO72-1),"NM")))))) | ... CF78: =IF(CA72="NM","NM",IF(CF72="NM","NM",IF(CA72<=0,"NM",IF(CF72=0,"NM",IF(ABS(CF72/CA72-1)>2.5,"NM",IF((ABS(CF72-CA72)=ABS(ABS(CF72)-ABS(CA72))),(CF72/CA72-1),"NM")))))) | CG78: =IF(CB72=0, "NA", CG72/CB72-1) | CH78: =IF(CC72=0, "NA", CH72/CC72-1) | CI78: =IF(CD72=0, "NA", CI72/CD72-1) | CJ78: =IF(CE72=0, "NA", CJ72/CE72-1) | CK78: =IF(CF72=0, "NA", CK72/CF72-1) | CL78: =IF(CG72=0, "NA", CL72/CG72-1) | CM78: =IF(CH72=0, "NA", CM72/CH72-1) | CN78: =IF(CI72=0, "NA", CN72/CI72-1) | ... EI78: =IF(ED72=0, "NA", EI72/ED72-1) | EJ78: =IF(EI72=0, "NA", EJ72/EI72-1) | EK78: =IF(EJ72=0, "NA", EK72/EJ72-1) | EL78: =IF(EK72=0, "NA", EL72/EK72-1) | EM78: =IF(EL72=0, "NA", EM72/EL72-1) | EN78: =IF(EM72=0, "NA", EN72/EM72-1) | EO78: =IF(EN72=0, "NA", EO72/EN72-1) | EP78: =IF(EO72=0, "NA", EP72/EO72-1) | EQ78: =IF(EP72=0, "NA", EQ72/EP72-1) | ... ES78: =IF(ER72=0, "NA", ES72/ER72-1)
B80: Anti-Infectives (infectious)
B81: U.S. | D81: =+D103+D874+D838+D849 | E81: =+E103+E874+E838+E849 | F81: =+F103+F874+F838+F849 | G81: =+G103+G874+G838+G849 | H81: =+H103+H874+H838+H849 | I81: =+I103+I874+I838+I849 | J81: =+J103+J874+J838+J849 | K81: =+K103+K874+K838+K849 | ... BQ81: =+BQ103+BQ874+BQ838+BQ849 | BR81: =+BR103 | BS81: =+BS103 | BT81: =+BT103 | BU81: =+BU103 | BV81: =+BV103+BV92 | BW81: =+BW103+BW92 | BX81: =+BX103+BX92 | BY81: =+BY103+BY92 | BZ81: =+BZ103+BZ92 | CA81: =+CA103+CA92 | CB81: =+CB103+CB92 | CC81: =+CC103+CC92 | ... CP81: =+CP103+CP92
B82: International | D82: =+D104+D875+D839+D850 | E82: =+E104+E875+E839+E850 | F82: =+F104+F875+F839+F850 | G82: =+G104+G875+G839+G850 | H82: =+H104+H875+H839+H850 | I82: =+I104+I875+I839+I850 | J82: =+J104+J875+J839+J850 | K82: =+K104+K875+K839+K850 | ... BQ82: =+BQ104+BQ875+BQ839+BQ850 | BR82: =+BR104 | BS82: =+BS104 | BT82: =+BT104 | BU82: =+BU104 | BV82: =+BV104+BV93 | BW82: =+BW104+BW93 | BX82: =+BX104+BX93 | BY82: =+BY104+BY93 | BZ82: =+BZ104+BZ93 | CA82: =+CA104+CA93 | CB82: =+CB104+CB93 | CC82: =+CC104+CC93 | ... CP82: =+CP104+CP93
B83: Worldwide | D83: =+D82+D81 | E83: =+E82+E81 | F83: =+F82+F81 | G83: =+G82+G81 | H83: =+H82+H81 | I83: =+I82+I81 | J83: =+J82+J81 | K83: =+K82+K81 | ... CJ83: =+CJ82+CJ81 | CK83: =SUM(CG83:CJ83) | CL83: =+CL82+CL81 | CM83: =+CM82+CM81 | CN83: =+CN82+CN81 | CO83: =+CO82+CO81 | CP83: =+CP82+CP81
B85: Anti-Infectives , % YoY growth
B86: U.S. | I86: =IF(D81="NM","NM",IF(I81="NM","NM",IF(D81<=0,"NM",IF(I81=0,"NM",IF(ABS(I81/D81-1)>2.5,"NM",IF((ABS(I81-D81)=ABS(ABS(I81)-ABS(D81))),(I81/D81-1),"NM")))))) | J86: =IF(E81="NM","NM",IF(J81="NM","NM",IF(E81<=0,"NM",IF(J81=0,"NM",IF(ABS(J81/E81-1)>2.5,"NM",IF((ABS(J81-E81)=ABS(ABS(J81)-ABS(E81))),(J81/E81-1),"NM")))))) | K86: =IF(F81="NM","NM",IF(K81="NM","NM",IF(F81<=0,"NM",IF(K81=0,"NM",IF(ABS(K81/F81-1)>2.5,"NM",IF((ABS(K81-F81)=ABS(ABS(K81)-ABS(F81))),(K81/F81-1),"NM")))))) | L86: =IF(G81="NM","NM",IF(L81="NM","NM",IF(G81<=0,"NM",IF(L81=0,"NM",IF(ABS(L81/G81-1)>2.5,"NM",IF((ABS(L81-G81)=ABS(ABS(L81)-ABS(G81))),(L81/G81-1),"NM")))))) | M86: =IF(H81="NM","NM",IF(M81="NM","NM",IF(H81<=0,"NM",IF(M81=0,"NM",IF(ABS(M81/H81-1)>2.5,"NM",IF((ABS(M81-H81)=ABS(ABS(M81)-ABS(H81))),(M81/H81-1),"NM")))))) | N86: =IF(I81="NM","NM",IF(N81="NM","NM",IF(I81<=0,"NM",IF(N81=0,"NM",IF(ABS(N81/I81-1)>2.5,"NM",IF((ABS(N81-I81)=ABS(ABS(N81)-ABS(I81))),(N81/I81-1),"NM")))))) | O86: =IF(J81="NM","NM",IF(O81="NM","NM",IF(J81<=0,"NM",IF(O81=0,"NM",IF(ABS(O81/J81-1)>2.5,"NM",IF((ABS(O81-J81)=ABS(ABS(O81)-ABS(J81))),(O81/J81-1),"NM")))))) | P86: =IF(K81="NM","NM",IF(P81="NM","NM",IF(K81<=0,"NM",IF(P81=0,"NM",IF(ABS(P81/K81-1)>2.5,"NM",IF((ABS(P81-K81)=ABS(ABS(P81)-ABS(K81))),(P81/K81-1),"NM")))))) | ... CB86: =IF(BW81="NM","NM",IF(CB81="NM","NM",IF(BW81<=0,"NM",IF(CB81=0,"NM",IF(ABS(CB81/BW81-1)>2.5,"NM",IF((ABS(CB81-BW81)=ABS(ABS(CB81)-ABS(BW81))),(CB81/BW81-1),"NM")))))) | CC86: =IF(BX81=0, "NA", CC81/BX81-1) | CD86: =IF(BY81="NM","NM",IF(CD81="NM","NM",IF(BY81<=0,"NM",IF(CD81=0,"NM",IF(ABS(CD81/BY81-1)>2.5,"NM",IF((ABS(CD81-BY81)=ABS(ABS(CD81)-ABS(BY81))),(CD81/BY81-1),"NM")))))) | CE86: =IF(BZ81="NM","NM",IF(CE81="NM","NM",IF(BZ81<=0,"NM",IF(CE81=0,"NM",IF(ABS(CE81/BZ81-1)>2.5,"NM",IF((ABS(CE81-BZ81)=ABS(ABS(CE81)-ABS(BZ81))),(CE81/BZ81-1),"NM")))))) | CF86: =IF(CA81="NM","NM",IF(CF81="NM","NM",IF(CA81<=0,"NM",IF(CF81=0,"NM",IF(ABS(CF81/CA81-1)>2.5,"NM",IF((ABS(CF81-CA81)=ABS(ABS(CF81)-ABS(CA81))),(CF81/CA81-1),"NM")))))) | CG86: =IF(CB81=0, "NA", CG81/CB81-1) | CH86: =IF(CC81=0, "NA", CH81/CC81-1) | CI86: =IF(CD81=0, "NA", CI81/CD81-1) | CJ86: =IF(CE81=0, "NA", CJ81/CE81-1) | CK86: =IF(CF81=0, "NA", CK81/CF81-1) | CL86: =IF(CG81=0, "NA", CL81/CG81-1) | CM86: =IF(CH81=0, "NA", CM81/CH81-1) | CN86: =IF(CI81=0, "NA", CN81/CI81-1) | ... CP86: =IF(CK81=0, "NA", CP81/CK81-1)
B87: International | I87: =IF(D82="NM","NM",IF(I82="NM","NM",IF(D82<=0,"NM",IF(I82=0,"NM",IF(ABS(I82/D82-1)>2.5,"NM",IF((ABS(I82-D82)=ABS(ABS(I82)-ABS(D82))),(I82/D82-1),"NM")))))) | J87: =IF(E82="NM","NM",IF(J82="NM","NM",IF(E82<=0,"NM",IF(J82=0,"NM",IF(ABS(J82/E82-1)>2.5,"NM",IF((ABS(J82-E82)=ABS(ABS(J82)-ABS(E82))),(J82/E82-1),"NM")))))) | K87: =IF(F82="NM","NM",IF(K82="NM","NM",IF(F82<=0,"NM",IF(K82=0,"NM",IF(ABS(K82/F82-1)>2.5,"NM",IF((ABS(K82-F82)=ABS(ABS(K82)-ABS(F82))),(K82/F82-1),"NM")))))) | L87: =IF(G82="NM","NM",IF(L82="NM","NM",IF(G82<=0,"NM",IF(L82=0,"NM",IF(ABS(L82/G82-1)>2.5,"NM",IF((ABS(L82-G82)=ABS(ABS(L82)-ABS(G82))),(L82/G82-1),"NM")))))) | M87: =IF(H82="NM","NM",IF(M82="NM","NM",IF(H82<=0,"NM",IF(M82=0,"NM",IF(ABS(M82/H82-1)>2.5,"NM",IF((ABS(M82-H82)=ABS(ABS(M82)-ABS(H82))),(M82/H82-1),"NM")))))) | N87: =IF(I82="NM","NM",IF(N82="NM","NM",IF(I82<=0,"NM",IF(N82=0,"NM",IF(ABS(N82/I82-1)>2.5,"NM",IF((ABS(N82-I82)=ABS(ABS(N82)-ABS(I82))),(N82/I82-1),"NM")))))) | O87: =IF(J82="NM","NM",IF(O82="NM","NM",IF(J82<=0,"NM",IF(O82=0,"NM",IF(ABS(O82/J82-1)>2.5,"NM",IF((ABS(O82-J82)=ABS(ABS(O82)-ABS(J82))),(O82/J82-1),"NM")))))) | P87: =IF(K82="NM","NM",IF(P82="NM","NM",IF(K82<=0,"NM",IF(P82=0,"NM",IF(ABS(P82/K82-1)>2.5,"NM",IF((ABS(P82-K82)=ABS(ABS(P82)-ABS(K82))),(P82/K82-1),"NM")))))) | ... CB87: =IF(BW82="NM","NM",IF(CB82="NM","NM",IF(BW82<=0,"NM",IF(CB82=0,"NM",IF(ABS(CB82/BW82-1)>2.5,"NM",IF((ABS(CB82-BW82)=ABS(ABS(CB82)-ABS(BW82))),(CB82/BW82-1),"NM")))))) | CC87: =IF(BX82=0, "NA", CC82/BX82-1) | CD87: =IF(BY82="NM","NM",IF(CD82="NM","NM",IF(BY82<=0,"NM",IF(CD82=0,"NM",IF(ABS(CD82/BY82-1)>2.5,"NM",IF((ABS(CD82-BY82)=ABS(ABS(CD82)-ABS(BY82))),(CD82/BY82-1),"NM")))))) | CE87: =IF(BZ82="NM","NM",IF(CE82="NM","NM",IF(BZ82<=0,"NM",IF(CE82=0,"NM",IF(ABS(CE82/BZ82-1)>2.5,"NM",IF((ABS(CE82-BZ82)=ABS(ABS(CE82)-ABS(BZ82))),(CE82/BZ82-1),"NM")))))) | CF87: =IF(CA82="NM","NM",IF(CF82="NM","NM",IF(CA82<=0,"NM",IF(CF82=0,"NM",IF(ABS(CF82/CA82-1)>2.5,"NM",IF((ABS(CF82-CA82)=ABS(ABS(CF82)-ABS(CA82))),(CF82/CA82-1),"NM")))))) | CG87: =IF(CB82=0, "NA", CG82/CB82-1) | CH87: =IF(CC82=0, "NA", CH82/CC82-1) | CI87: =IF(CD82=0, "NA", CI82/CD82-1) | CJ87: =IF(CE82=0, "NA", CJ82/CE82-1) | CK87: =IF(CF82=0, "NA", CK82/CF82-1) | CL87: =IF(CG82=0, "NA", CL82/CG82-1) | CM87: =IF(CH82=0, "NA", CM82/CH82-1) | CN87: =IF(CI82=0, "NA", CN82/CI82-1) | ... CP87: =IF(CK82=0, "NA", CP82/CK82-1)
B88: International (ex-currency) | AI88: =IF(ISNUMBER(AI87),(1+AI87)/(1+AI$21)-1,"NM") | AJ88: =IF(ISNUMBER(AJ87),(1+AJ87)/(1+AJ$21)-1,"NM") | AK88: =IF(ISNUMBER(AK87),(1+AK87)/(1+AK$21)-1,"NM") | AL88: =IF(ISNUMBER(AL87),(1+AL87)/(1+AL$21)-1,"NM") | AM88: =IF(ISNUMBER(AM87),(1+AM87)/(1+AM$21)-1,"NM") | AN88: =IF(ISNUMBER(AN87),(1+AN87)/(1+AN$21)-1,"NM") | AO88: =IF(ISNUMBER(AO87),(1+AO87)/(1+AO$21)-1,"NM") | AP88: =IF(ISNUMBER(AP87),(1+AP87)/(1+AP$21)-1,"NM") | ... CB88: =IF(ISNUMBER(CB87),(1+CB87)/(1+CB$21)-1,"NM") | CC88: =CC87-CC$21 | CD88: =IF(ISNUMBER(CD87),(1+CD87)/(1+CD$21)-1,"NM") | CE88: =IF(ISNUMBER(CE87),(1+CE87)/(1+CE$21)-1,"NM") | CF88: =IF(ISNUMBER(CF87),(1+CF87)/(1+CF$21)-1,"NM") | CG88: =CG87-CG$21 | CH88: =CH87-CH$21 | CI88: =CI87-CI$21 | CJ88: =CJ87-CJ$21 | CK88: =CK87-CK$21 | CL88: =CL87-CL$21 | CM88: =CM87-CM$21 | CN88: =CN87-CN$21 | ... CP88: =CP87-CP$21
B89: Worldwide | I89: =IF(D83="NM","NM",IF(I83="NM","NM",IF(D83<=0,"NM",IF(I83=0,"NM",IF(ABS(I83/D83-1)>2.5,"NM",IF((ABS(I83-D83)=ABS(ABS(I83)-ABS(D83))),(I83/D83-1),"NM")))))) | J89: =IF(E83="NM","NM",IF(J83="NM","NM",IF(E83<=0,"NM",IF(J83=0,"NM",IF(ABS(J83/E83-1)>2.5,"NM",IF((ABS(J83-E83)=ABS(ABS(J83)-ABS(E83))),(J83/E83-1),"NM")))))) | K89: =IF(F83="NM","NM",IF(K83="NM","NM",IF(F83<=0,"NM",IF(K83=0,"NM",IF(ABS(K83/F83-1)>2.5,"NM",IF((ABS(K83-F83)=ABS(ABS(K83)-ABS(F83))),(K83/F83-1),"NM")))))) | L89: =IF(G83="NM","NM",IF(L83="NM","NM",IF(G83<=0,"NM",IF(L83=0,"NM",IF(ABS(L83/G83-1)>2.5,"NM",IF((ABS(L83-G83)=ABS(ABS(L83)-ABS(G83))),(L83/G83-1),"NM")))))) | M89: =IF(H83="NM","NM",IF(M83="NM","NM",IF(H83<=0,"NM",IF(M83=0,"NM",IF(ABS(M83/H83-1)>2.5,"NM",IF((ABS(M83-H83)=ABS(ABS(M83)-ABS(H83))),(M83/H83-1),"NM")))))) | N89: =IF(I83="NM","NM",IF(N83="NM","NM",IF(I83<=0,"NM",IF(N83=0,"NM",IF(ABS(N83/I83-1)>2.5,"NM",IF((ABS(N83-I83)=ABS(ABS(N83)-ABS(I83))),(N83/I83-1),"NM")))))) | O89: =IF(J83="NM","NM",IF(O83="NM","NM",IF(J83<=0,"NM",IF(O83=0,"NM",IF(ABS(O83/J83-1)>2.5,"NM",IF((ABS(O83-J83)=ABS(ABS(O83)-ABS(J83))),(O83/J83-1),"NM")))))) | P89: =IF(K83="NM","NM",IF(P83="NM","NM",IF(K83<=0,"NM",IF(P83=0,"NM",IF(ABS(P83/K83-1)>2.5,"NM",IF((ABS(P83-K83)=ABS(ABS(P83)-ABS(K83))),(P83/K83-1),"NM")))))) | ... CB89: =IF(BW83="NM","NM",IF(CB83="NM","NM",IF(BW83<=0,"NM",IF(CB83=0,"NM",IF(ABS(CB83/BW83-1)>2.5,"NM",IF((ABS(CB83-BW83)=ABS(ABS(CB83)-ABS(BW83))),(CB83/BW83-1),"NM")))))) | CC89: =IF(BX83=0, "NA", CC83/BX83-1) | CD89: =IF(BY83="NM","NM",IF(CD83="NM","NM",IF(BY83<=0,"NM",IF(CD83=0,"NM",IF(ABS(CD83/BY83-1)>2.5,"NM",IF((ABS(CD83-BY83)=ABS(ABS(CD83)-ABS(BY83))),(CD83/BY83-1),"NM")))))) | CE89: =IF(BZ83="NM","NM",IF(CE83="NM","NM",IF(BZ83<=0,"NM",IF(CE83=0,"NM",IF(ABS(CE83/BZ83-1)>2.5,"NM",IF((ABS(CE83-BZ83)=ABS(ABS(CE83)-ABS(BZ83))),(CE83/BZ83-1),"NM")))))) | CF89: =IF(CA83="NM","NM",IF(CF83="NM","NM",IF(CA83<=0,"NM",IF(CF83=0,"NM",IF(ABS(CF83/CA83-1)>2.5,"NM",IF((ABS(CF83-CA83)=ABS(ABS(CF83)-ABS(CA83))),(CF83/CA83-1),"NM")))))) | CG89: =IF(CB83=0, "NA", CG83/CB83-1) | CH89: =IF(CC83=0, "NA", CH83/CC83-1) | CI89: =IF(CD83=0, "NA", CI83/CD83-1) | CJ89: =IF(CE83=0, "NA", CJ83/CE83-1) | CK89: =IF(CF83=0, "NA", CK83/CF83-1) | CL89: =IF(CG83=0, "NA", CL83/CG83-1) | CM89: =IF(CH83=0, "NA", CM83/CH83-1) | CN89: =IF(CI83=0, "NA", CN83/CI83-1) | ... CP89: =IF(CK83=0, "NA", CP83/CK83-1)
B91: Product0375 (bedquiline)
B92: U.S. | CA92: =SUM(BW92:BZ92) | CC92: 2.5 | CD92: 2.5 | CE92: 2.5 | CF92: =SUM(CB92:CE92) | CG92: 1.5 | CH92: 2.5 | CI92: 2.5 | CJ92: 2.5 | CK92: =SUM(CG92:CJ92) | CL92: 1.5 | CM92: 2.5 | CN92: 2.5 | CO92: 2.5 | CP92: =SUM(CL92:CO92)
B93: International | BZ93: 75 | CA93: =SUM(BW93:BZ93) | CB93: 25 | CC93: 25 | CD93: 25 | CE93: 25 | CF93: =SUM(CB93:CE93) | CG93: 27.5 | CH93: 27.5 | CI93: 27.5 | CJ93: 25 | CK93: =SUM(CG93:CJ93) | CL93: 30.0575 | CM93: 30.085 | CN93: 29.975 | CO93: 30 | CP93: =SUM(CL93:CO93)
B94: Worldwide | BZ94: =+BZ92+BZ93 | CA94: =+CA92+CA93 | CB94: =+CB92+CB93 | CC94: =+CC92+CC93 | CD94: =+CD92+CD93 | CE94: =+CE92+CE93 | CF94: =+CF92+CF93 | CG94: =+CG92+CG93 | ... CP94: =+CP92+CP93
B96: =+B91&", % YoY growth"
B97: U.S. | CF97: =IF(CA92=0, "NA", CF92/CA92-1) | CH97: =IF(CC92=0, "NA", CH92/CC92-1) | CI97: =IF(CD92=0, "NA", CI92/CD92-1) | CJ97: =IF(CE92=0, "NA", CJ92/CE92-1) | CK97: =IF(CF92=0, "NA", CK92/CF92-1) | CL97: =IF(CG92=0, "NA", CL92/CG92-1) | CM97: =IF(CH92=0, "NA", CM92/CH92-1) | CN97: =IF(CI92=0, "NA", CN92/CI92-1) | CO97: =IF(CJ92=0, "NA", CO92/CJ92-1) | CP97: =IF(CK92=0, "NA", CP92/CK92-1)
B98: International | CF98: =IF(CA93=0, "NA", CF93/CA93-1) | CG98: =IF(CB93=0, "NA", CG93/CB93-1) | CH98: =IF(CC93=0, "NA", CH93/CC93-1) | CI98: =IF(CD93=0, "NA", CI93/CD93-1) | CJ98: =IF(CE93=0, "NA", CJ93/CE93-1) | CK98: =IF(CF93=0, "NA", CK93/CF93-1) | CL98: =IF(CG93=0, "NA", CL93/CG93-1) | CM98: =IF(CH93=0, "NA", CM93/CH93-1) | ... CP98: =IF(CK93=0, "NA", CP93/CK93-1)
B99: International (ex-currency) | CF99: =CF98-CF$21 | CG99: =CG98-CG$21 | CH99: =CH98-CH$21 | CI99: =CI98-CI$21 | CJ99: =CJ98-CJ$21 | CK99: =CK98-CK$21 | CL99: =CL98-CL$21 | CM99: =CM98-CM$21 | ... CP99: =CP98-CP$21
B100: Worldwide | CE100: =IF(BZ94=0, "NA", CE94/BZ94-1) | CF100: =IF(CA94=0, "NA", CF94/CA94-1) | CG100: =IF(CB94=0, "NA", CG94/CB94-1) | CH100: =IF(CC94=0, "NA", CH94/CC94-1) | CI100: =IF(CD94=0, "NA", CI94/CD94-1) | CJ100: =IF(CE94=0, "NA", CJ94/CE94-1) | CK100: =IF(CF94=0, "NA", CK94/CF94-1) | CL100: =IF(CG94=0, "NA", CL94/CG94-1) | ... CP100: =IF(CK94=0, "NA", CP94/CK94-1)
B102: Product0160/Levaquin (anti-infectives)
B103: U.S. | C103: 40714 | D103: =+I103/(1+I108) | E103: 198 | F103: 157.59494 | G103: 168 | H103: 203 | I103: =+SUM(E103:H103) | J103: 319 | K103: 249 | L103: 238 | M103: 235 | N103: =+SUM(J103:M103) | O103: 240 | P103: 232 | Q103: 220 | R103: 301 | S103: =SUM(O103:R103) | T103: 263 | U103: 201 | V103: 228 | W103: 279 | X103: =SUM(T103:W103) | Y103: 284 | Z103: 258 | AA103: 238 | AB103: 310 | AC103: =SUM(Y103:AB103) | AD103: 364 | AE103: 253 | AF103: 256 | AG103: 357 | AH103: =SUM(AD103:AG103) | AI103: 421 | AJ103: 306 | AK103: 322 | AL103: 390 | AM103: =+SUM(AI103:AL103) | AN103: 387 | AO103: 328 | AP103: 334 | AQ103: 423 | AR103: =+SUM(AN103:AQ103) | AS103: 460 | AT103: 343 | AU103: 351 | AV103: 409 | AW103: =SUM(AS103:AV103) | AX103: 474 | AY103: 330 | AZ103: 313 | BA103: 393 | BB103: =SUM(AX103:BA103) | BC103: 408 | BD103: 343 | BE103: 294 | BF103: 433 | BG103: =SUM(BC103:BF103) | BH103: 363 | BI103: 289 | BJ103: 274 | BK103: 386 | BL103: =SUM(BH103:BK103) | BM103: 422 | BN103: 149 | BO103: 14 | BP103: -6 | BQ103: =SUM(BM103:BP103) | BR103: 18 | BS103: 7 | BT103: 10 | BU103: 0 | BV103: =SUM(BR103:BU103) | BW103: 5 | BX103: 4 | BY103: 6 | BZ103: 0 | CA103: =SUM(BW103:BZ103) | CB103: 0 | CC103: 2.4 | CD103: 3.6 | CE103: 0 | CF103: =SUM(CB103:CE103) | CG103: 0 | CH103: 1.7 | CI103: 2.5 | CJ103: 0 | CK103: =SUM(CG103:CJ103) | CL103: 0 | CM103: 2 | CN103: 1 | CO103: 1 | CP103: =SUM(CL103:CO103)
B104: International | C104: 2006 | D104: =+I104/(1+I109) | E104: 9 | F104: 8.0291971 | G104: 9 | H104: 10 | I104: =+SUM(E104:H104) | J104: 14 | K104: 11 | L104: 11 | M104: 12 | N104: =+SUM(J104:M104) | O104: 16 | P104: 12 | Q104: 15 | R104: 16 | S104: =SUM(O104:R104) | T104: 16 | U104: 15 | V104: 16 | W104: 14 | X104: =SUM(T104:W104) | Y104: 14 | Z104: 15 | AA104: 15 | AB104: 16 | AC104: =SUM(Y104:AB104) | AD104: 19 | AE104: 15.8 | AF104: 14 | AG104: 17 | AH104: =SUM(AD104:AG104) | AI104: 19.2 | AJ104: 14 | AK104: 10 | AL104: 11 | AM104: =+SUM(AI104:AL104) | AN104: 14 | AO104: 15 | AP104: 13 | AQ104: 16 | AR104: =+SUM(AN104:AQ104) | AS104: 15 | AT104: 14 | AU104: 15 | AV104: 23 | AW104: =SUM(AS104:AV104) | AX104: 22 | AY104: 21 | AZ104: 20 | BA104: 18 | BB104: =SUM(AX104:BA104) | BC104: 17 | BD104: 19 | BE104: 17 | BF104: 19 | BG104: =SUM(BC104:BF104) | BH104: 8 | BI104: 11 | BJ104: 12 | BK104: 14 | BL104: =SUM(BH104:BK104) | BM104: 12 | BN104: 10 | BO104: 11 | BP104: 11 | BQ104: =SUM(BM104:BP104) | BR104: 11 | BS104: 9 | BT104: 10 | BU104: 10 | BV104: =SUM(BR104:BU104) | BW104: 8 | BX104: 6 | BY104: 7 | BZ104: 6.8 | CA104: =SUM(BW104:BZ104) | CB104: 6 | CC104: 5 | CD104: 5.9 | CE104: 5 | CF104: =SUM(CB104:CE104) | CG104: 4.68 | CH104: 3.8 | CI104: 4.4 | CJ104: 3.8568539 | CK104: =SUM(CG104:CJ104) | CL104: 4.17924 | CM104: 3.4 | CN104: 3.916 | CO104: 3 | CP104: =SUM(CL104:CO104)
B105: Worldwide | D105: =+D103+D104 | E105: =+E103+E104 | F105: =+F103+F104 | G105: =+G103+G104 | H105: =+H103+H104 | I105: =+I103+I104 | J105: =+J103+J104 | K105: =+K103+K104 | ... BK105: =+BK103+BK104 | BL105: =SUM(BH105:BK105) | BM105: =+BM103+BM104 | BN105: =+BN103+BN104 | BO105: =+BO103+BO104 | BP105: =+BP103+BP104 | BQ105: =SUM(BM105:BP105) | BR105: =+BR103+BR104 | BS105: =+BS103+BS104 | BT105: =+BT103+BT104 | BU105: =+BU103+BU104 | BV105: =SUM(BR105:BU105) | BW105: =+BW103+BW104 | BX105: =+BX103+BX104 | BY105: =+BY103+BY104 | BZ105: =+BZ103+BZ104 | CA105: =SUM(BW105:BZ105) | CB105: =+CB103+CB104 | CC105: =+CC103+CC104 | CD105: =+CD103+CD104 | CE105: =+CE103+CE104 | CF105: =SUM(CB105:CE105) | CG105: =+CG103+CG104 | CH105: =+CH103+CH104 | CI105: =+CI103+CI104 | CJ105: =+CJ103+CJ104 | CK105: =SUM(CG105:CJ105) | CL105: =+CL103+CL104 | CM105: =+CM103+CM104 | CN105: =+CN103+CN104 | CO105: =+CO103+CO104 | CP105: =SUM(CL105:CO105)
B107: Product0160/Levaquin, % YoY growth
B108: U.S. | I108: 0.64 | J108: =IF(E103="NM","NM",IF(J103="NM","NM",IF(E103<=0,"NM",IF(J103=0,"NM",IF(ABS(J103/E103-1)>2.5,"NM",IF((ABS(J103-E103)=ABS(ABS(J103)-ABS(E103))),(J103/E103-1),"NM")))))) | K108: =IF(F103="NM","NM",IF(K103="NM","NM",IF(F103<=0,"NM",IF(K103=0,"NM",IF(ABS(K103/F103-1)>2.5,"NM",IF((ABS(K103-F103)=ABS(ABS(K103)-ABS(F103))),(K103/F103-1),"NM")))))) | L108: =IF(G103="NM","NM",IF(L103="NM","NM",IF(G103<=0,"NM",IF(L103=0,"NM",IF(ABS(L103/G103-1)>2.5,"NM",IF((ABS(L103-G103)=ABS(ABS(L103)-ABS(G103))),(L103/G103-1),"NM")))))) | M108: =IF(H103="NM","NM",IF(M103="NM","NM",IF(H103<=0,"NM",IF(M103=0,"NM",IF(ABS(M103/H103-1)>2.5,"NM",IF((ABS(M103-H103)=ABS(ABS(M103)-ABS(H103))),(M103/H103-1),"NM")))))) | N108: =IF(I103="NM","NM",IF(N103="NM","NM",IF(I103<=0,"NM",IF(N103=0,"NM",IF(ABS(N103/I103-1)>2.5,"NM",IF((ABS(N103-I103)=ABS(ABS(N103)-ABS(I103))),(N103/I103-1),"NM")))))) | O108: =IF(J103="NM","NM",IF(O103="NM","NM",IF(J103<=0,"NM",IF(O103=0,"NM",IF(ABS(O103/J103-1)>2.5,"NM",IF((ABS(O103-J103)=ABS(ABS(O103)-ABS(J103))),(O103/J103-1),"NM")))))) | P108: =IF(K103="NM","NM",IF(P103="NM","NM",IF(K103<=0,"NM",IF(P103=0,"NM",IF(ABS(P103/K103-1)>2.5,"NM",IF((ABS(P103-K103)=ABS(ABS(P103)-ABS(K103))),(P103/K103-1),"NM")))))) | Q108: =IF(L103="NM","NM",IF(Q103="NM","NM",IF(L103<=0,"NM",IF(Q103=0,"NM",IF(ABS(Q103/L103-1)>2.5,"NM",IF((ABS(Q103-L103)=ABS(ABS(Q103)-ABS(L103))),(Q103/L103-1),"NM")))))) | ... CJ108: =IF(CE103="NM","NM",IF(CJ103="NM","NM",IF(CE103<=0,"NM",IF(CJ103=0,"NM",IF(ABS(CJ103/CE103-1)>2.5,"NM",IF((ABS(CJ103-CE103)=ABS(ABS(CJ103)-ABS(CE103))),(CJ103/CE103-1),"NM")))))) | CK108: =IF(CF103=0, "NA", CK103/CF103-1) | CL108: =IF(CG103="NM","NM",IF(CL103="NM","NM",IF(CG103<=0,"NM",IF(CL103=0,"NM",IF(ABS(CL103/CG103-1)>2.5,"NM",IF((ABS(CL103-CG103)=ABS(ABS(CL103)-ABS(CG103))),(CL103/CG103-1),"NM")))))) | CM108: =IF(CH103="NM","NM",IF(CM103="NM","NM",IF(CH103<=0,"NM",IF(CM103=0,"NM",IF(ABS(CM103/CH103-1)>2.5,"NM",IF((ABS(CM103-CH103)=ABS(ABS(CM103)-ABS(CH103))),(CM103/CH103-1),"NM")))))) | CN108: =IF(CI103="NM","NM",IF(CN103="NM","NM",IF(CI103<=0,"NM",IF(CN103=0,"NM",IF(ABS(CN103/CI103-1)>2.5,"NM",IF((ABS(CN103-CI103)=ABS(ABS(CN103)-ABS(CI103))),(CN103/CI103-1),"NM")))))) | CO108: =IF(CJ103="NM","NM",IF(CO103="NM","NM",IF(CJ103<=0,"NM",IF(CO103=0,"NM",IF(ABS(CO103/CJ103-1)>2.5,"NM",IF((ABS(CO103-CJ103)=ABS(ABS(CO103)-ABS(CJ103))),(CO103/CJ103-1),"NM")))))) | CP108: =IF(CK103=0, "NA", CP103/CK103-1)
B109: International | I109: 0.28 | J109: =IF(E104="NM","NM",IF(J104="NM","NM",IF(E104<=0,"NM",IF(J104=0,"NM",IF(ABS(J104/E104-1)>2.5,"NM",IF((ABS(J104-E104)=ABS(ABS(J104)-ABS(E104))),(J104/E104-1),"NM")))))) | K109: =IF(F104="NM","NM",IF(K104="NM","NM",IF(F104<=0,"NM",IF(K104=0,"NM",IF(ABS(K104/F104-1)>2.5,"NM",IF((ABS(K104-F104)=ABS(ABS(K104)-ABS(F104))),(K104/F104-1),"NM")))))) | L109: =IF(G104="NM","NM",IF(L104="NM","NM",IF(G104<=0,"NM",IF(L104=0,"NM",IF(ABS(L104/G104-1)>2.5,"NM",IF((ABS(L104-G104)=ABS(ABS(L104)-ABS(G104))),(L104/G104-1),"NM")))))) | M109: =IF(H104="NM","NM",IF(M104="NM","NM",IF(H104<=0,"NM",IF(M104=0,"NM",IF(ABS(M104/H104-1)>2.5,"NM",IF((ABS(M104-H104)=ABS(ABS(M104)-ABS(H104))),(M104/H104-1),"NM")))))) | N109: =IF(I104="NM","NM",IF(N104="NM","NM",IF(I104<=0,"NM",IF(N104=0,"NM",IF(ABS(N104/I104-1)>2.5,"NM",IF((ABS(N104-I104)=ABS(ABS(N104)-ABS(I104))),(N104/I104-1),"NM")))))) | O109: =IF(J104="NM","NM",IF(O104="NM","NM",IF(J104<=0,"NM",IF(O104=0,"NM",IF(ABS(O104/J104-1)>2.5,"NM",IF((ABS(O104-J104)=ABS(ABS(O104)-ABS(J104))),(O104/J104-1),"NM")))))) | P109: =IF(K104="NM","NM",IF(P104="NM","NM",IF(K104<=0,"NM",IF(P104=0,"NM",IF(ABS(P104/K104-1)>2.5,"NM",IF((ABS(P104-K104)=ABS(ABS(P104)-ABS(K104))),(P104/K104-1),"NM")))))) | Q109: =IF(L104="NM","NM",IF(Q104="NM","NM",IF(L104<=0,"NM",IF(Q104=0,"NM",IF(ABS(Q104/L104-1)>2.5,"NM",IF((ABS(Q104-L104)=ABS(ABS(Q104)-ABS(L104))),(Q104/L104-1),"NM")))))) | ... CJ109: =IF(CE104="NM","NM",IF(CJ104="NM","NM",IF(CE104<=0,"NM",IF(CJ104=0,"NM",IF(ABS(CJ104/CE104-1)>2.5,"NM",IF((ABS(CJ104-CE104)=ABS(ABS(CJ104)-ABS(CE104))),(CJ104/CE104-1),"NM")))))) | CK109: =IF(CF104=0, "NA", CK104/CF104-1) | CL109: =IF(CG104="NM","NM",IF(CL104="NM","NM",IF(CG104<=0,"NM",IF(CL104=0,"NM",IF(ABS(CL104/CG104-1)>2.5,"NM",IF((ABS(CL104-CG104)=ABS(ABS(CL104)-ABS(CG104))),(CL104/CG104-1),"NM")))))) | CM109: =IF(CH104="NM","NM",IF(CM104="NM","NM",IF(CH104<=0,"NM",IF(CM104=0,"NM",IF(ABS(CM104/CH104-1)>2.5,"NM",IF((ABS(CM104-CH104)=ABS(ABS(CM104)-ABS(CH104))),(CM104/CH104-1),"NM")))))) | CN109: =IF(CI104="NM","NM",IF(CN104="NM","NM",IF(CI104<=0,"NM",IF(CN104=0,"NM",IF(ABS(CN104/CI104-1)>2.5,"NM",IF((ABS(CN104-CI104)=ABS(ABS(CN104)-ABS(CI104))),(CN104/CI104-1),"NM")))))) | CO109: =IF(CJ104="NM","NM",IF(CO104="NM","NM",IF(CJ104<=0,"NM",IF(CO104=0,"NM",IF(ABS(CO104/CJ104-1)>2.5,"NM",IF((ABS(CO104-CJ104)=ABS(ABS(CO104)-ABS(CJ104))),(CO104/CJ104-1),"NM")))))) | CP109: =IF(CK104=0, "NA", CP104/CK104-1)
B110: International (ex-currency) | AI110: =IF(ISNUMBER(AI109),(1+AI109)/(1+AI$21)-1,"NM") | AJ110: =IF(ISNUMBER(AJ109),(1+AJ109)/(1+AJ$21)-1,"NM") | AK110: =IF(ISNUMBER(AK109),(1+AK109)/(1+AK$21)-1,"NM") | AL110: =IF(ISNUMBER(AL109),(1+AL109)/(1+AL$21)-1,"NM") | AM110: =IF(ISNUMBER(AM109),(1+AM109)/(1+AM$21)-1,"NM") | AN110: =IF(ISNUMBER(AN109),(1+AN109)/(1+AN$21)-1,"NM") | AO110: =IF(ISNUMBER(AO109),(1+AO109)/(1+AO$21)-1,"NM") | AP110: =IF(ISNUMBER(AP109),(1+AP109)/(1+AP$21)-1,"NM") | ... BK110: =IF(ISNUMBER(BK109),(1+BK109)/(1+BK$21)-1,"NM") | BL110: =BL109-$BL$21 | BM110: =IF(ISNUMBER(BM109),(1+BM109)/(1+BM$21)-1,"NM") | BN110: -0.133 | BO110: -0.107 | BP110: -0.177 | BQ110: -0.037 | BR110: -0.177 | BS110: -0.027 | BT110: -0.048 | BU110: -0.105 | BV110: -0.058 | BW110: =BW109-BW$21 | BX110: =BX109-BX$21 | BY110: =BY109-BY$21 | BZ110: =BZ109-BZ$21 | CA110: =CA109-CA$21 | CB110: =CB109-CB$21 | CC110: =CC109-CC$21 | CD110: =CD109-CD$21 | ... CP110: =CP109-CP$21
B111: Worldwide | I111: 0.62 | J111: =IF(E105="NM","NM",IF(J105="NM","NM",IF(E105<=0,"NM",IF(J105=0,"NM",IF(ABS(J105/E105-1)>2.5,"NM",IF((ABS(J105-E105)=ABS(ABS(J105)-ABS(E105))),(J105/E105-1),"NM")))))) | K111: =IF(F105="NM","NM",IF(K105="NM","NM",IF(F105<=0,"NM",IF(K105=0,"NM",IF(ABS(K105/F105-1)>2.5,"NM",IF((ABS(K105-F105)=ABS(ABS(K105)-ABS(F105))),(K105/F105-1),"NM")))))) | L111: =IF(G105="NM","NM",IF(L105="NM","NM",IF(G105<=0,"NM",IF(L105=0,"NM",IF(ABS(L105/G105-1)>2.5,"NM",IF((ABS(L105-G105)=ABS(ABS(L105)-ABS(G105))),(L105/G105-1),"NM")))))) | M111: =IF(H105="NM","NM",IF(M105="NM","NM",IF(H105<=0,"NM",IF(M105=0,"NM",IF(ABS(M105/H105-1)>2.5,"NM",IF((ABS(M105-H105)=ABS(ABS(M105)-ABS(H105))),(M105/H105-1),"NM")))))) | N111: =IF(I105="NM","NM",IF(N105="NM","NM",IF(I105<=0,"NM",IF(N105=0,"NM",IF(ABS(N105/I105-1)>2.5,"NM",IF((ABS(N105-I105)=ABS(ABS(N105)-ABS(I105))),(N105/I105-1),"NM")))))) | O111: =IF(J105="NM","NM",IF(O105="NM","NM",IF(J105<=0,"NM",IF(O105=0,"NM",IF(ABS(O105/J105-1)>2.5,"NM",IF((ABS(O105-J105)=ABS(ABS(O105)-ABS(J105))),(O105/J105-1),"NM")))))) | P111: =IF(K105="NM","NM",IF(P105="NM","NM",IF(K105<=0,"NM",IF(P105=0,"NM",IF(ABS(P105/K105-1)>2.5,"NM",IF((ABS(P105-K105)=ABS(ABS(P105)-ABS(K105))),(P105/K105-1),"NM")))))) | Q111: =IF(L105="NM","NM",IF(Q105="NM","NM",IF(L105<=0,"NM",IF(Q105=0,"NM",IF(ABS(Q105/L105-1)>2.5,"NM",IF((ABS(Q105-L105)=ABS(ABS(Q105)-ABS(L105))),(Q105/L105-1),"NM")))))) | ... CI111: =IF(CD105="NM","NM",IF(CI105="NM","NM",IF(CD105<=0,"NM",IF(CI105=0,"NM",IF(ABS(CI105/CD105-1)>2.5,"NM",IF((ABS(CI105-CD105)=ABS(ABS(CI105)-ABS(CD105))),(CI105/CD105-1),"NM")))))) | CJ111: =IF(CE105=0, "NA", CJ105/CE105-1) | CK111: =IF(CF105=0, "NA", CK105/CF105-1) | CL111: =IF(CG105="NM","NM",IF(CL105="NM","NM",IF(CG105<=0,"NM",IF(CL105=0,"NM",IF(ABS(CL105/CG105-1)>2.5,"NM",IF((ABS(CL105-CG105)=ABS(ABS(CL105)-ABS(CG105))),(CL105/CG105-1),"NM")))))) | CM111: =IF(CH105="NM","NM",IF(CM105="NM","NM",IF(CH105<=0,"NM",IF(CM105=0,"NM",IF(ABS(CM105/CH105-1)>2.5,"NM",IF((ABS(CM105-CH105)=ABS(ABS(CM105)-ABS(CH105))),(CM105/CH105-1),"NM")))))) | CN111: =IF(CI105="NM","NM",IF(CN105="NM","NM",IF(CI105<=0,"NM",IF(CN105=0,"NM",IF(ABS(CN105/CI105-1)>2.5,"NM",IF((ABS(CN105-CI105)=ABS(ABS(CN105)-ABS(CI105))),(CN105/CI105-1),"NM")))))) | CO111: =IF(CJ105=0, "NA", CO105/CJ105-1) | CP111: =IF(CK105=0, "NA", CP105/CK105-1)
B113: Anti-virals (infectious)
B114: U.S. | AN114: =+AN125+AN136 | AO114: =+AO125+AO136 | AP114: =+AP125+AP136 | AQ114: =+AQ125+AQ136 | AR114: =+AR125+AR136 | AS114: =+AS125+AS136 | AT114: =+AT125+AT136 | AU114: =+AU125+AU136 | ... BB114: =+BB125+BB136 | BC114: =+BC125+BC136+BC158 | BD114: =+BD125+BD136+BD158 | BE114: =+BE125+BE136+BE158 | BF114: =+BF125+BF136+BF158 | BG114: =+BG125+BG136+BG158 | BH114: =+BH125+BH136+BH158 | BI114: =+BI125+BI136+BI158 | BJ114: =+BJ125+BJ136+BJ158 | ... BN114: =+BN125+BN136+BN158 | BO114: =+BO125+BO136+BO158+BO169 | BP114: =+BP125+BP136+BP158+BP169 | BQ114: =+BQ125+BQ136+BQ158+BQ169 | BR114: =+BR125+BR136+BR158+BR169 | BS114: =+BS125+BS136+BS158+BS169 | BT114: =+BT125+BT136+BT158+BT169 | BU114: =+BU125+BU136+BU158+BU169 | BV114: =+BV125+BV136+BV158+BV169 | BW114: =+BW125+BW136+BW158+BW169+BW147 | BX114: =+BX125+BX136+BX158+BX169+BX147 | BY114: =+BY125+BY136+BY158+BY169+BY147 | BZ114: =+BZ125+BZ136+BZ158+BZ169+BZ147 | CA114: =+CA125+CA136+CA158+CA169+CA147 | CB114: =+CB125+CB136+CB158+CB169+CB147 | CC114: =+CC125+CC136+CC158+CC169+CC147 | CD114: =+CD125+CD136+CD158+CD169+CD147 | ... CJ114: =+CJ125+CJ136+CJ158+CJ169+CJ147 | CK114: =SUM(CG114:CJ114) | CL114: =+CL125+CL136+CL158+CL169+CL147 | CM114: =+CM125+CM136+CM158+CM169+CM147 | CN114: =+CN125+CN136+CN158+CN169+CN147 | CO114: =+CO125+CO136+CO158+CO169+CO147 | CP114: =+CP125+CP136+CP158+CP169+CP147
B115: International | AN115: =+AN126+AN137 | AO115: =+AO126+AO137 | AP115: =+AP126+AP137 | AQ115: =+AQ126+AQ137 | AR115: =+AR126+AR137 | AS115: =+AS126+AS137 | AT115: =+AT126+AT137 | AU115: =+AU126+AU137 | ... BB115: =+BB126+BB137 | BC115: =+BC126+BC137+BC159 | BD115: =+BD126+BD137+BD159 | BE115: =+BE126+BE137+BE159 | BF115: =+BF126+BF137+BF159 | BG115: =+BG126+BG137+BG159 | BH115: =+BH126+BH137+BH159 | BI115: =+BI126+BI137+BI159 | BJ115: =+BJ126+BJ137+BJ159 | ... BN115: =+BN126+BN137+BN159 | BO115: =+BO126+BO137+BO159+BO170 | BP115: =+BP126+BP137+BP159+BP170 | BQ115: =+BQ126+BQ137+BQ159+BQ170 | BR115: =+BR126+BR137+BR159+BR170 | BS115: =+BS126+BS137+BS159+BS170 | BT115: =+BT126+BT137+BT159+BT170 | BU115: =+BU126+BU137+BU159+BU170 | BV115: =+BV126+BV137+BV159+BV170 | BW115: =+BW126+BW137+BW159+BW170+BW148 | BX115: =+BX126+BX137+BX159+BX170+BX148 | BY115: =+BY126+BY137+BY159+BY170+BY148 | BZ115: =+BZ126+BZ137+BZ159+BZ170+BZ148 | CA115: =+CA126+CA137+CA159+CA170+CA148 | CB115: =+CB126+CB137+CB159+CB170+CB148 | CC115: =+CC126+CC137+CC159+CC170+CC148 | CD115: =+CD126+CD137+CD159+CD170+CD148 | ... CJ115: =+CJ126+CJ137+CJ159+CJ170+CJ148 | CK115: =SUM(CG115:CJ115) | CL115: =+CL126+CL137+CL159+CL170+CL148 | CM115: =+CM126+CM137+CM159+CM170+CM148 | CN115: =+CN126+CN137+CN159+CN170+CN148 | CO115: =+CO126+CO137+CO159+CO170+CO148 | CP115: =+CP126+CP137+CP159+CP170+CP148
B116: Worldwide | AN116: =+AN114+AN115 | AO116: =+AO114+AO115 | AP116: =+AP114+AP115 | AQ116: =+AQ114+AQ115 | AR116: =+AR114+AR115 | AS116: =+AS114+AS115 | AT116: =+AT114+AT115 | AU116: =+AU114+AU115 | ... CJ116: =+CJ114+CJ115 | CK116: =SUM(CG116:CJ116) | CL116: =+CL114+CL115 | CM116: =+CM114+CM115 | CN116: =+CN114+CN115 | CO116: =+CO114+CO115 | CP116: =+CP114+CP115
B118: Anti-virals, % YoY growth
B119: U.S. | AN119: =IF(AI114="NM","NM",IF(AN114="NM","NM",IF(AI114<=0,"NM",IF(AN114=0,"NM",IF(ABS(AN114/AI114-1)>2.5,"NM",IF((ABS(AN114-AI114)=ABS(ABS(AN114)-ABS(AI114))),(AN114/AI114-1),"NM")))))) | AO119: =IF(AJ114="NM","NM",IF(AO114="NM","NM",IF(AJ114<=0,"NM",IF(AO114=0,"NM",IF(ABS(AO114/AJ114-1)>2.5,"NM",IF((ABS(AO114-AJ114)=ABS(ABS(AO114)-ABS(AJ114))),(AO114/AJ114-1),"NM")))))) | AP119: =IF(AK114="NM","NM",IF(AP114="NM","NM",IF(AK114<=0,"NM",IF(AP114=0,"NM",IF(ABS(AP114/AK114-1)>2.5,"NM",IF((ABS(AP114-AK114)=ABS(ABS(AP114)-ABS(AK114))),(AP114/AK114-1),"NM")))))) | AQ119: =IF(AL114="NM","NM",IF(AQ114="NM","NM",IF(AL114<=0,"NM",IF(AQ114=0,"NM",IF(ABS(AQ114/AL114-1)>2.5,"NM",IF((ABS(AQ114-AL114)=ABS(ABS(AQ114)-ABS(AL114))),(AQ114/AL114-1),"NM")))))) | AR119: =IF(AM114="NM","NM",IF(AR114="NM","NM",IF(AM114<=0,"NM",IF(AR114=0,"NM",IF(ABS(AR114/AM114-1)>2.5,"NM",IF((ABS(AR114-AM114)=ABS(ABS(AR114)-ABS(AM114))),(AR114/AM114-1),"NM")))))) | AS119: =IF(AN114="NM","NM",IF(AS114="NM","NM",IF(AN114<=0,"NM",IF(AS114=0,"NM",IF(ABS(AS114/AN114-1)>2.5,"NM",IF((ABS(AS114-AN114)=ABS(ABS(AS114)-ABS(AN114))),(AS114/AN114-1),"NM")))))) | AT119: =IF(AO114="NM","NM",IF(AT114="NM","NM",IF(AO114<=0,"NM",IF(AT114=0,"NM",IF(ABS(AT114/AO114-1)>2.5,"NM",IF((ABS(AT114-AO114)=ABS(ABS(AT114)-ABS(AO114))),(AT114/AO114-1),"NM")))))) | AU119: =IF(AP114="NM","NM",IF(AU114="NM","NM",IF(AP114<=0,"NM",IF(AU114=0,"NM",IF(ABS(AU114/AP114-1)>2.5,"NM",IF((ABS(AU114-AP114)=ABS(ABS(AU114)-ABS(AP114))),(AU114/AP114-1),"NM")))))) | ... CB119: =IF(BW114="NM","NM",IF(CB114="NM","NM",IF(BW114<=0,"NM",IF(CB114=0,"NM",IF(ABS(CB114/BW114-1)>2.5,"NM",IF((ABS(CB114-BW114)=ABS(ABS(CB114)-ABS(BW114))),(CB114/BW114-1),"NM")))))) | CC119: =IF(BX114=0, "NA", CC114/BX114-1) | CD119: =IF(BY114="NM","NM",IF(CD114="NM","NM",IF(BY114<=0,"NM",IF(CD114=0,"NM",IF(ABS(CD114/BY114-1)>2.5,"NM",IF((ABS(CD114-BY114)=ABS(ABS(CD114)-ABS(BY114))),(CD114/BY114-1),"NM")))))) | CE119: =IF(BZ114="NM","NM",IF(CE114="NM","NM",IF(BZ114<=0,"NM",IF(CE114=0,"NM",IF(ABS(CE114/BZ114-1)>2.5,"NM",IF((ABS(CE114-BZ114)=ABS(ABS(CE114)-ABS(BZ114))),(CE114/BZ114-1),"NM")))))) | CF119: =IF(CA114="NM","NM",IF(CF114="NM","NM",IF(CA114<=0,"NM",IF(CF114=0,"NM",IF(ABS(CF114/CA114-1)>2.5,"NM",IF((ABS(CF114-CA114)=ABS(ABS(CF114)-ABS(CA114))),(CF114/CA114-1),"NM")))))) | CG119: =IF(CB114=0, "NA", CG114/CB114-1) | CH119: =IF(CC114=0, "NA", CH114/CC114-1) | CI119: =IF(CD114=0, "NA", CI114/CD114-1) | CJ119: =IF(CE114=0, "NA", CJ114/CE114-1) | CK119: =IF(CF114=0, "NA", CK114/CF114-1) | CL119: =IF(CG114=0, "NA", CL114/CG114-1) | CM119: =IF(CH114=0, "NA", CM114/CH114-1) | CN119: =IF(CI114=0, "NA", CN114/CI114-1) | ... CP119: =IF(CK114=0, "NA", CP114/CK114-1)
B120: International | AN120: =IF(AI115="NM","NM",IF(AN115="NM","NM",IF(AI115<=0,"NM",IF(AN115=0,"NM",IF(ABS(AN115/AI115-1)>2.5,"NM",IF((ABS(AN115-AI115)=ABS(ABS(AN115)-ABS(AI115))),(AN115/AI115-1),"NM")))))) | AO120: =IF(AJ115="NM","NM",IF(AO115="NM","NM",IF(AJ115<=0,"NM",IF(AO115=0,"NM",IF(ABS(AO115/AJ115-1)>2.5,"NM",IF((ABS(AO115-AJ115)=ABS(ABS(AO115)-ABS(AJ115))),(AO115/AJ115-1),"NM")))))) | AP120: =IF(AK115="NM","NM",IF(AP115="NM","NM",IF(AK115<=0,"NM",IF(AP115=0,"NM",IF(ABS(AP115/AK115-1)>2.5,"NM",IF((ABS(AP115-AK115)=ABS(ABS(AP115)-ABS(AK115))),(AP115/AK115-1),"NM")))))) | AQ120: =IF(AL115="NM","NM",IF(AQ115="NM","NM",IF(AL115<=0,"NM",IF(AQ115=0,"NM",IF(ABS(AQ115/AL115-1)>2.5,"NM",IF((ABS(AQ115-AL115)=ABS(ABS(AQ115)-ABS(AL115))),(AQ115/AL115-1),"NM")))))) | AR120: =IF(AM115="NM","NM",IF(AR115="NM","NM",IF(AM115<=0,"NM",IF(AR115=0,"NM",IF(ABS(AR115/AM115-1)>2.5,"NM",IF((ABS(AR115-AM115)=ABS(ABS(AR115)-ABS(AM115))),(AR115/AM115-1),"NM")))))) | AS120: =IF(AN115="NM","NM",IF(AS115="NM","NM",IF(AN115<=0,"NM",IF(AS115=0,"NM",IF(ABS(AS115/AN115-1)>2.5,"NM",IF((ABS(AS115-AN115)=ABS(ABS(AS115)-ABS(AN115))),(AS115/AN115-1),"NM")))))) | AT120: =IF(AO115="NM","NM",IF(AT115="NM","NM",IF(AO115<=0,"NM",IF(AT115=0,"NM",IF(ABS(AT115/AO115-1)>2.5,"NM",IF((ABS(AT115-AO115)=ABS(ABS(AT115)-ABS(AO115))),(AT115/AO115-1),"NM")))))) | AU120: =IF(AP115="NM","NM",IF(AU115="NM","NM",IF(AP115<=0,"NM",IF(AU115=0,"NM",IF(ABS(AU115/AP115-1)>2.5,"NM",IF((ABS(AU115-AP115)=ABS(ABS(AU115)-ABS(AP115))),(AU115/AP115-1),"NM")))))) | ... CF120: =IF(CA115="NM","NM",IF(CF115="NM","NM",IF(CA115<=0,"NM",IF(CF115=0,"NM",IF(ABS(CF115/CA115-1)>2.5,"NM",IF((ABS(CF115-CA115)=ABS(ABS(CF115)-ABS(CA115))),(CF115/CA115-1),"NM")))))) | CG120: =IF(CB115=0, "NA", CG115/CB115-1) | CH120: =IF(CC115=0, "NA", CH115/CC115-1) | CI120: =IF(CD115=0, "NA", CI115/CD115-1) | CJ120: =IF(CE115=0, "NA", CJ115/CE115-1) | CK120: =IF(CF115=0, "NA", CK115/CF115-1) | CL120: =IF(CG115=0, "NA", CL115/CG115-1) | CM120: =IF(CH115=0, "NA", CM115/CH115-1) | CN120: =IF(CI115=0, "NA", CN115/CI115-1) | ... CP120: =IF(CK115=0, "NA", CP115/CK115-1)
B121: International (ex-currency) | AN121: =IF(ISNUMBER(AN120),(1+AN120)/(1+AN$21)-1,"NM") | AO121: =IF(ISNUMBER(AO120),(1+AO120)/(1+AO$21)-1,"NM") | AP121: =IF(ISNUMBER(AP120),(1+AP120)/(1+AP$21)-1,"NM") | AQ121: =IF(ISNUMBER(AQ120),(1+AQ120)/(1+AQ$21)-1,"NM") | AR121: =IF(ISNUMBER(AR120),(1+AR120)/(1+AR$21)-1,"NM") | AS121: =IF(ISNUMBER(AS120),(1+AS120)/(1+AS$21)-1,"NM") | AT121: =IF(ISNUMBER(AT120),(1+AT120)/(1+AT$21)-1,"NM") | AU121: =IF(ISNUMBER(AU120),(1+AU120)/(1+AU$21)-1,"NM") | ... CF121: =IF(ISNUMBER(CF120),(1+CF120)/(1+CF$21)-1,"NM") | CG121: =CG120-CG$21 | CH121: =CH120-CH$21 | CI121: =CI120-CI$21 | CJ121: =CJ120-CJ$21 | CK121: =CK120-CK$21 | CL121: =CL120-CL$21 | CM121: =CM120-CM$21 | CN121: =CN120-CN$21 | ... CP121: =CP120-CP$21
...

Sheet Income Statement
B1: Currency - Do not Delete | DI1: Revenues orig | DL1: 17080.278 | DM1: 17886.258 | DN1: 67580.536 | DO1: 17711.23 | DP1: 17923.25 | DQ1: 17713.758 | DR1: 18614.339 | DS1: 71962.577 | DX1: 74345.446 | EC1: 77094.753 | EH1: 77094.753 | EM1: 82418.119 | ER1: 82418.119 | EW1: 82418.119 | FB1: 82418.119 | FG1: 82418.119 | FL1: 82418.119 | FS1: 82418.119 | FX1: 82418.119 | GC1: 82418.119 | GH1: 82418.119 | GI1: 82418.119 | GJ1: 82418.119 | GK1: 82418.119 | GL1: 82418.119 | GM1: 82418.119
DI2: Revenues chg | DL2: =+DL24-DL1 | DM2: =+DM24-DM1 | DN2: =+DN24-DN1 | DO2: =+DO24-DO1 | DP2: =+DP24-DP1 | DQ2: =+DQ24-DQ1 | DR2: =+DR24-DR1 | DS2: =+DS24-DS1 | DX2: =+DX24-DX1 | EC2: =+EC24-EC1 | EH2: =+EH24-EH1 | EM2: =+EM24-EM1 | ER2: =+ER24-ER1 | EW2: =+EW24-EW1 | FB2: =+FB24-FB1 | FG2: =+FG24-FG1 | FL2: =+FL24-FL1 | FS2: =+FS24-FS1 | FX2: =+FX24-FX1 | GC2: =+GC24-GC1 | GH2: =+GH24-GH1 | GI2: =+GI24-GI1 | GJ2: =+GJ24-GJ1 | GK2: =+GK24-GK1 | GL2: =+GL24-GL1 | GM2: =+GM24-GM1
DI3: NI orig | DL3: 3402.2048 | DM3: 3269.7013 | DN3: 14119.906 | DO3: 3731.3551 | DP3: 3775.3481 | DQ3: 3734.8602 | DR3: 3926.0754 | DS3: 15167.639 | DX3: 16137.893 | EC3: 17195.504 | EH3: 17195.504 | EM3: 19271.507 | ER3: 19271.507 | EW3: 19271.507 | FB3: 19271.507 | FG3: 19271.507 | FL3: 19271.507 | FS3: 19271.507 | FX3: 19271.507 | GC3: 19271.507 | GH3: 19271.507 | GI3: 19271.507 | GJ3: 19271.507 | GK3: 19271.507 | GL3: 19271.507 | GM3: 19271.507
DI4: NI shld chg | DL4: =+DL2*30% | DM4: =+DM2*30% | DN4: =+DN2*30% | DO4: =+DO2*30% | DP4: =+DP2*30% | DQ4: =+DQ2*30% | DR4: =+DR2*30% | DS4: =+DS2*30% | DX4: =+DX2*30% | EC4: =+EC2*30% | EH4: =+EH2*30% | EM4: =+EM2*30% | ER4: =+ER2*30% | EW4: =+EW2*30% | FB4: =+FB2*30% | FG4: =+FG2*30% | FL4: =+FL2*30% | FS4: =+FS2*30% | FX4: =+FX2*30% | GC4: =+GC2*30% | GH4: =+GH2*30% | GI4: =+GI2*30% | GJ4: =+GJ2*30% | GK4: =+GK2*30% | GL4: =+GL2*30% | GM4: =+GM2*30%
DI5: NI below | DL5: =+DL43-DL3 | DM5: =+DM43-DM3 | DN5: =+DN43-DN3 | DO5: =+DO43-DO3 | DP5: =+DP43-DP3 | DQ5: =+DQ43-DQ3 | DR5: =+DR43-DR3 | DS5: =+DS43-DS3 | DX5: =+DX43-DX3 | EC5: =+EC43-EC3 | EH5: =+EH43-EH3 | EM5: =+EM43-EM3 | ER5: =+ER43-ER3 | EW5: =+EW43-EW3 | FB5: =+FB43-FB3 | FG5: =+FG43-FG3 | FL5: =+FL43-FL3 | FS5: =+FS43-FS3 | FX5: =+FX43-FX3 | GC5: =+GC43-GC3 | GH5: =+GH43-GH3 | GI5: =+GI43-GI3 | GJ5: =+GJ43-GJ3 | GK5: =+GK43-GK3 | GL5: =+GL43-GL3 | GM5: =+GM43-GM3
DI6: EPS orig | DL6: 1.2217959 | DM6: 1.1763554 | DN6: 5.0712536 | DO6: 1.3449023 | DP6: 1.3632525 | DQ6: 1.3511085 | DR6: 1.4228941 | DS6: 5.4819539 | DX6: 5.8757373 | EC6: 6.3074278 | EH6: 6.3074278 | EM6: 7.1757844 | ER6: 7.1757844 | EW6: 7.1757844 | FB6: 7.1757844 | FG6: 7.1757844 | FL6: 7.1757844 | FS6: 7.1757844 | FX6: 7.1757844 | GC6: 7.1757844 | GH6: 7.1757844 | GI6: 7.1757844 | GJ6: 7.1757844 | GK6: 7.1757844 | GL6: 7.1757844 | GM6: 7.1757844
DI7: EPS shld chg | DL7: =+DL4/DL61 | DM7: =+DM4/DM61 | DN7: =+DN4/DN61 | DO7: =+DO4/DO61 | DP7: =+DP4/DP61 | DQ7: =+DQ4/DQ61 | DR7: =+DR4/DR61 | DS7: =+DS4/DS61 | DX7: =+DX4/DX61 | EC7: =+EC4/EC61 | EH7: =+EH4/EH61 | EM7: =+EM4/EM61 | ER7: =+ER4/ER61 | EW7: =+EW4/EW61 | FB7: =+FB4/FB61 | FG7: =+FG4/FG61 | FL7: =+FL4/FL61 | FS7: =+FS4/FS61 | FX7: =+FX4/FX61 | GC7: =+GC4/GC61 | GH7: =+GH4/GH61 | GI7: =+GI4/GI61 | GJ7: =+GJ4/GJ61 | GK7: =+GK4/GK61 | GL7: =+GL4/GL61 | GM7: =+GM4/GM61
DI8: EPS below | DL8: =+DL55-DL6 | DM8: =+DM55-DM6 | DN8: =+DN55-DN6 | DO8: =+DO55-DO6 | DP8: =+DP55-DP6 | DQ8: =+DQ55-DQ6 | DR8: =+DR55-DR6 | DS8: =+DS55-DS6 | DX8: =+DX55-DX6 | EC8: =+EC55-EC6 | EH8: =+EH55-EH6 | EM8: =+EM55-EM6 | ER8: =+ER55-ER6 | EW8: =+EW55-EW6 | FB8: =+FB55-FB6 | FG8: =+FG55-FG6 | FL8: =+FL55-FL6 | FS8: =+FS55-FS6 | FX8: =+FX55-FX6 | GC8: =+GC55-GC6 | GH8: =+GH55-GH6 | GI8: =+GI55-GI6 | GJ8: =+GJ55-GJ6 | GK8: =+GK55-GK6 | GL8: =+GL55-GL6 | GM8: =+GM55-GM6
DI9: Consensus
B12: =Cover!D11
B14: Income Statement
B16: ($ in millions)
EI18: =EI28/EM28
DY19: 312 | DZ19: 307 | EA19: 293 | EB19: 288 | FO19: Restated (excl. Consumer Health)
B20: $ mn, except per share data | C20: =+#REF! | E20: 1987 | F20: 1988 | G20: 1989 | H20: 1990 | I20: 1Q91 | J20: 2Q91 | K20: 3Q91 | L20: 4Q91 | M20: 1991 | N20: 1Q92 | O20: 2Q92 | P20: 3Q92 | Q20: 4Q92 | R20: 1992 | S20: 1Q93 | T20: 2Q93 | U20: 3Q93 | V20: 4Q93 | W20: 1993 | X20: 1Q94 | Y20: 2Q94 | Z20: 3Q94 | AA20: 4Q94 | AB20: 1994 | AC20: 1Q95 | AD20: 2Q95 | AE20: 3Q95 | AF20: 4Q95 | AG20: 1995 | AH20: 1Q96 | AI20: 2Q96 | AJ20: 3Q96 | AK20: 4Q96 | AL20: 1996 | AM20: 1Q97 | AN20: 2Q97 | AO20: 3Q97 | AP20: 4Q97 | AQ20: 1997 | AR20: 1Q98 | AS20: 2Q98 | AT20: 3Q98 | AU20: 4Q98 | AV20: 1998 | AW20: 1Q99 | AX20: 2Q99 | AY20: 3Q99 | AZ20: 4Q99 | BA20: 1999 | BB20: 1Q00 | BC20: 2Q00 | BD20: 3Q00 | BE20: 4Q00 | BF20: 2000 | BG20: 1Q01 | BH20: 2Q01 | BI20: 3Q01 | BJ20: 4Q01 | BK20: 2001 | BL20: 1Q02 | BM20: 2Q02 | BN20: 3Q02 | BO20: 4Q02 | BP20: 2002 | BQ20: 1Q03 | BR20: 2Q03 | BS20: 3Q03 | BT20: 4Q03 | BU20: 2003 | BV20: 1Q04 | BW20: 2Q04 | BX20: 3Q04 | BY20: 4Q04 | BZ20: 2004 | CA20: 1Q05 | CB20: 2Q05 | CC20: 3Q05 | CD20: 4Q05 | CE20: 2005 | CF20: 1Q06 | CG20: 2Q06 | CH20: 3Q06 | CI20: 4Q06 | CJ20: 2006 | CK20: 1Q07 | CL20: 2Q07 | CM20: 3Q07 | CN20: 4Q07 | CO20: 2007 | CP20: 1Q08 | CQ20: 2Q08 | CR20: 3Q08 | CS20: 4Q08 | CT20: 2008 | CU20: 1Q09 | CV20: 2Q09 | CW20: 3Q09 | CX20: 4Q09 | CY20: 2009 | CZ20: =+'Sales Model'!BH19 | DA20: =+'Sales Model'!BI19 | DB20: =+'Sales Model'!BJ19 | DC20: =+'Sales Model'!BK19 | DD20: 2010 | DE20: =+'Sales Model'!BM19 | DF20: =+'Sales Model'!BN19 | DG20: =+'Sales Model'!BO19 | DH20: =+'Sales Model'!BP19 | DI20: 2011 | DJ20: =+'Sales Model'!BR19 | DK20: =+'Sales Model'!BS19 | DL20: =+'Sales Model'!BT19 | DM20: =+'Sales Model'!BU19 | DN20: 2012 | DO20: 1Q13 | DP20: 2Q13 | DQ20: 3Q13 | DR20: 4Q13 | DS20: 2013 | DT20: 1Q14 | DU20: 2Q14 | DV20: 3Q14 | DW20: 4Q14 | DX20: 2014 | DY20: 1Q15 | DZ20: 2Q15 | EA20: 3Q15 | EB20: 4Q15 | EC20: 2015 | ED20: 1Q16 | EE20: 2Q16 | EF20: 3Q16 | EG20: 4Q16 | EH20: 2016 | EI20: 1Q17 | EJ20: 2Q17 | EK20: 3Q17 | EL20: 4Q17 | EM20: 2017 | EN20: 1Q18 | EO20: 2Q18 | EP20: 3Q18 | EQ20: 4Q18 | ER20: 2018 | ES20: 1Q19 | ET20: 2Q19 | EU20: 3Q19 | EV20: 4Q19 | EW20: 2019 | EX20: 1Q20 | EY20: 2Q20 | EZ20: 3Q20 | FA20: 4Q20 | FB20: 2020 | FC20: 1Q21 | FD20: 2Q21 | FE20: 3Q21 | FF20: 4Q21 | FG20: 2021 | FH20: 1Q22 | FI20: 2Q22 | FJ20: 3Q22 | FK20: 4Q22 | FL20: 2022 | FM20: 1Q23 | FN20: 2Q23 | FO20: 1Q22 | FP20: 2Q22 | FQ20: 3Q22 | FR20: 4Q22 | FS20: 2022 | FT20: 1Q23 | FU20: 2Q23 | FV20: 3Q23 | FW20: 4Q23 | FX20: 2023 | FY20: 1Q24 | FZ20: 2Q24 | GA20: 3Q24 | GB20: 4Q24 | GC20: 2024 | GD20: 1Q25 | GE20: 2Q25 | GF20: 3Q25 | GG20: 4Q25E | GH20: 2025E | GI20: 2026E | GJ20: 2027E | GK20: 2028E | GL20: 2029E | GM20: 2030E
B22: Domestic | E22: 4167 | F22: 4576 | G22: 4881 | H22: =#REF! | I22: =#REF! | J22: =#REF! | K22: =#REF! | M22: =#REF! | R22: =#REF! | S22: =#REF! | T22: =#REF! | U22: =#REF! | V22: =#REF! | W22: =S22+T22+U22+V22 | X22: =#REF! | Y22: =#REF! | Z22: 2002 | AA22: 2054 | AB22: =X22+Y22+Z22+AA22 | AC22: 2176 | AD22: 2230 | AE22: 2335 | AF22: 2449 | AG22: =AC22+AD22+AE22+AF22 | AH22: 2652 | AI22: 2637 | AJ22: 2790 | AK22: 2820 | AL22: 10899 | AM22: 2947 | AN22: 2881 | AO22: 2962 | AP22: 2967 | AQ22: 11757 | AR22: 3152 | AS22: 3093 | AT22: 3149 | AU22: 3492 | AV22: ='Sales Model'!D23 | AW22: ='Sales Model'!E23 | AX22: ='Sales Model'!F23 | AY22: ='Sales Model'!G23 | AZ22: ='Sales Model'!H23 | BA22: ='Sales Model'!I23 | BB22: ='Sales Model'!J23 | BC22: ='Sales Model'!K23 | ... BE22: ='Sales Model'!M23 | BF22: =SUM(BB22:BE22) | BG22: ='Sales Model'!O23 | BH22: ='Sales Model'!P23 | BI22: ='Sales Model'!Q23 | BJ22: ='Sales Model'!R23 | BK22: =SUM(BG22:BJ22) | BL22: ='Sales Model'!T23 | BM22: ='Sales Model'!U23 | BN22: ='Sales Model'!V23 | BO22: ='Sales Model'!W23 | BP22: =SUM(BL22:BO22) | BQ22: ='Sales Model'!Y23 | BR22: ='Sales Model'!Z23 | BS22: ='Sales Model'!AA23 | BT22: ='Sales Model'!AB23 | BU22: =SUM(BQ22:BT22) | BV22: ='Sales Model'!AD23 | BW22: ='Sales Model'!AE23 | BX22: ='Sales Model'!AF23 | BY22: ='Sales Model'!AG23 | BZ22: ='Sales Model'!AH23 | CA22: ='Sales Model'!AI23 | CB22: ='Sales Model'!AJ23 | CC22: ='Sales Model'!AK23 | ... DC22: ='Sales Model'!BK23 | DD22: =SUM(CZ22,DA22,DB22,DC22) | DE22: ='Sales Model'!BM23 | DF22: 7447 | DG22: 6868 | DH22: 6985 | DI22: =SUM(DE22:DH22) | DJ22: 7219 | DK22: 7360 | DL22: 7791 | DM22: 7460 | DN22: =SUM(DJ22:DM22) | DO22: 8025 | DP22: 7946 | DQ22: 7925 | DR22: 8014 | DS22: =SUM(DO22:DR22) | DT22: 8204 | DU22: 9132 | DV22: 8842 | DW22: 8604 | DX22: =SUM(DT22:DW22) | DY22: 8692 | DZ22: 8911 | EA22: 8791 | EB22: 9293 | EC22: =SUM(DY22:EB22) | ED22: 9321 | EE22: 9572 | EF22: 9381 | EG22: 9537 | EH22: =SUM(ED22:EG22) | EI22: 9378 | EJ22: 9726 | EK22: 10290 | EL22: 10469 | EM22: =SUM(EI22:EL22) | EN22: 9951 | EO22: 10640 | EP22: =+'Sales Model'!CX23 | EQ22: =+'Sales Model'!CY23 | ER22: =SUM(EN22:EQ22) | ES22: 10129 | ET22: 10403 | EU22: 10791 | EV22: 10774 | EW22: =SUM(ES22:EV22) | EX22: 10699 | EY22: ='Sales Model'!DG23 | EZ22: ='Sales Model'!DH23 | FA22: ='Sales Model'!DI23 | FB22: =SUM(EX22:FA22) | FC22: ='Sales Model'!DK23 | FD22: ='Sales Model'!DL23 | FE22: ='Sales Model'!DM23 | FF22: ='Sales Model'!DN23 | FG22: ='Sales Model'!DO23 | FH22: ='Sales Model'!DP23 | FI22: ='Sales Model'!DQ23 | FJ22: ='Sales Model'!DR23 | ... FN22: ='Sales Model'!DV23 | FO22: 9857 | FP22: 10510 | FQ22: 10794 | FR22: 10820 | FS22: 41981 | FT22: 10782.3 | FU22: 11656.7 | FV22: 11996 | FW22: 12009 | FX22: 46444 | FY22: 11620 | FZ22: 12569 | GA22: 12909 | GB22: 13204 | GC22: =SUM(FY22:GB22) | GD22: 12305 | GE22: 13544 | GF22: 13708 | GG22: ='Sales Model'!EH23 | GH22: ='Sales Model'!EI23 | GI22: ='Sales Model'!EJ23 | GJ22: ='Sales Model'!EK23 | GK22: ='Sales Model'!EL23 | GL22: ='Sales Model'!EM23 | GM22: ='Sales Model'!EN23
B23: International | E23: 3845 | F23: 4424 | G23: 4876 | H23: =#REF! | I23: =#REF! | J23: =#REF! | K23: =#REF! | L23: =#REF! | M23: =#REF! | N23: =#REF! | O23: =#REF! | P23: =#REF! | Q23: =R23-N23-O23-P23 | R23: =#REF! | S23: =#REF! | T23: =#REF! | U23: =#REF! | V23: 125 | W23: =S23+T23+U23+V23 | X23: =#REF! | Y23: =#REF! | Z23: 2036 | AA23: 2036 | AB23: =X23+Y23+Z23+AA23 | AC23: 2320 | AD23: 2532 | AE23: 2403 | AF23: 2397 | AG23: =AC23+AD23+AE23+AF23 | AH23: 2682 | AI23: 2745 | AJ23: 2612 | AK23: 2682 | AL23: 10721 | AM23: 2768 | AN23: 2817 | AO23: 2624 | AP23: 2663 | AQ23: 10872 | AR23: 2688 | AS23: 2781 | AT23: 2662 | AU23: 2978 | AV23: ='Sales Model'!D24 | AW23: ='Sales Model'!E24 | AX23: ='Sales Model'!F24 | AY23: ='Sales Model'!G24 | AZ23: ='Sales Model'!H24 | BA23: ='Sales Model'!I24 | BB23: ='Sales Model'!J24 | BC23: ='Sales Model'!K24 | ... BE23: ='Sales Model'!M24 | BF23: =SUM(BB23:BE23) | BG23: ='Sales Model'!O24 | BH23: ='Sales Model'!P24 | BI23: ='Sales Model'!Q24 | BJ23: ='Sales Model'!R24 | BK23: =SUM(BG23:BJ23) | BL23: ='Sales Model'!T24 | BM23: ='Sales Model'!U24 | BN23: ='Sales Model'!V24 | BO23: ='Sales Model'!W24 | BP23: =SUM(BL23:BO23) | BQ23: ='Sales Model'!Y24 | BR23: ='Sales Model'!Z24 | BS23: ='Sales Model'!AA24 | BT23: ='Sales Model'!AB24 | BU23: =SUM(BQ23:BT23) | BV23: ='Sales Model'!AD24 | BW23: ='Sales Model'!AE24 | BX23: ='Sales Model'!AF24 | BY23: ='Sales Model'!AG24 | BZ23: ='Sales Model'!AH24 | CA23: ='Sales Model'!AI24 | CB23: ='Sales Model'!AJ24 | CC23: ='Sales Model'!AK24 | ... DC23: ='Sales Model'!BK24 | DD23: =SUM(CZ23,DA23,DB23,DC23) | DE23: ='Sales Model'!BM24 | DF23: 9150 | DG23: 9137 | DH23: 9270 | DI23: =SUM(DE23:DH23) | DJ23: 8920 | DK23: 9115 | DL23: 9261 | DM23: 10098 | DN23: =SUM(DJ23:DM23) | DO23: 9480 | DP23: 9931 | DQ23: 9650 | DR23: 10341 | DS23: =SUM(DO23:DR23) | DT23: 9911 | DU23: 10363 | DV23: 9625 | DW23: 9650 | DX23: =SUM(DT23:DW23) | DY23: 8682 | DZ23: 8876 | EA23: 8311 | EB23: 8518 | EC23: =SUM(DY23:EB23) | ED23: 8161 | EE23: 8910 | EF23: 8439 | EG23: 8569 | EH23: =SUM(ED23:EG23) | EI23: 8388 | EJ23: 9113 | EK23: 9360 | EL23: 9726 | EM23: =SUM(EI23:EL23) | EN23: 10058 | EO23: 10190 | EP23: =+'Sales Model'!CX24 | EQ23: =+'Sales Model'!CY24 | ER23: =SUM(EN23:EQ23) | ES23: 9892 | ET23: 10159 | EU23: 9938 | EV23: 9973 | EW23: =SUM(ES23:EV23) | EX23: 9992 | EY23: ='Sales Model'!DG24 | EZ23: ='Sales Model'!DH24 | FA23: ='Sales Model'!DI24 | FB23: =SUM(EX23:FA23) | FC23: ='Sales Model'!DK24 | FD23: ='Sales Model'!DL24 | FE23: ='Sales Model'!DM24 | FF23: ='Sales Model'!DN24 | FG23: ='Sales Model'!DO24 | FH23: ='Sales Model'!DP24 | FI23: ='Sales Model'!DQ24 | FJ23: ='Sales Model'!DR24 | ... FN23: ='Sales Model'!DV24 | FO23: 9983 | FP23: 9705 | FQ23: 9202 | FR23: 9119 | FS23: 38009 | FT23: 10112 | FU23: 9862 | FV23: 9355 | FW23: 9386 | FX23: 38715 | FY23: 9763 | FZ23: 9878 | GA23: 9562 | GB23: 9316 | GC23: =SUM(FY23:GB23) | GD23: 9588 | GE23: 10199 | GF23: 10285 | GG23: ='Sales Model'!EH24 | GH23: ='Sales Model'!EI24 | GI23: ='Sales Model'!EJ24 | GJ23: ='Sales Model'!EK24 | GK23: ='Sales Model'!EL24 | GL23: ='Sales Model'!EM24 | GM23: ='Sales Model'!EN24
B24: Total Sales | E24: =SUM(E22:E23) | F24: =SUM(F22:F23) | G24: =SUM(G22:G23) | H24: =SUM(H22:H23) | I24: =SUM(I22:I23) | J24: =SUM(J22:J23) | K24: =SUM(K22:K23) | L24: 1586 | M24: =M22+M23 | N24: 1668 | O24: 1767 | P24: 1733 | Q24: 1682 | R24: =R22+R23 | S24: =SUM(S22:S23) | T24: =SUM(T22:T23) | U24: =SUM(U22:U23) | V24: 85 | W24: =W22+W23 | X24: =SUM(X22:X23) | Y24: =SUM(Y22:Y23) | Z24: =SUM(Z22:Z23) | AA24: =SUM(AA22:AA23) | AB24: =AB22+AB23 | AC24: =SUM(AC22:AC23) | AD24: =SUM(AD22:AD23) | AE24: =SUM(AE22:AE23) | AF24: =SUM(AF22:AF23) | AG24: =AG22+AG23 | AH24: =SUM(AH22:AH23) | AI24: =SUM(AI22:AI23) | AJ24: =SUM(AJ22:AJ23) | AK24: =SUM(AK22:AK23) | AL24: =AL22+AL23 | AM24: =SUM(AM22:AM23) | AN24: =SUM(AN22:AN23) | AO24: =SUM(AO22:AO23) | AP24: =SUM(AP22:AP23) | AQ24: =AQ22+AQ23 | AR24: =SUM(AR22:AR23) | AS24: =SUM(AS22:AS23) | AT24: =SUM(AT22:AT23) | AU24: =SUM(AU22:AU23) | AV24: =AV22+AV23 | AW24: =SUM(AW22:AW23) | AX24: =SUM(AX22:AX23) | AY24: =SUM(AY22:AY23) | AZ24: =SUM(AZ22:AZ23) | BA24: =BA23+BA22 | BB24: =BB22+BB23 | BC24: =BC22+BC23 | BD24: =BD22+BD23 | BE24: =BE22+BE23 | BF24: =BF23+BF22 | BG24: =BG22+BG23 | BH24: =BH22+BH23 | BI24: =BI22+BI23 | BJ24: =BJ22+BJ23 | BK24: =BK23+BK22 | BL24: =BL22+BL23 | BM24: =BM22+BM23 | BN24: =BN22+BN23 | BO24: =BO22+BO23 | BP24: =BP23+BP22 | BQ24: =BQ22+BQ23 | BR24: =BR22+BR23 | BS24: =BS22+BS23 | BT24: =BT22+BT23 | BU24: =BU23+BU22 | BV24: =BV22+BV23 | BW24: =BW22+BW23 | BX24: =BX22+BX23 | BY24: =BY22+BY23 | BZ24: =BZ23+BZ22 | CA24: =CA22+CA23 | CB24: =CB22+CB23 | CC24: =CC22+CC23 | CD24: =CD22+CD23 | CE24: =CE23+CE22 | CF24: =CF22+CF23 | CG24: =CG22+CG23 | CH24: =CH22+CH23 | CI24: =CI22+CI23 | CJ24: =CJ23+CJ22 | CK24: =CK22+CK23 | CL24: =CL22+CL23 | CM24: =CM22+CM23 | CN24: =CN22+CN23 | CO24: =CO23+CO22 | CP24: =CP22+CP23 | CQ24: =CQ22+CQ23 | CR24: =CR22+CR23 | CS24: =CS22+CS23 | CT24: =CT23+CT22 | CU24: =CU22+CU23 | CV24: =CV22+CV23 | CW24: =CW22+CW23 | CX24: =CX22+CX23 | CY24: =CY23+CY22 | CZ24: =CZ23+CZ22 | DA24: =DA23+DA22 | DB24: =DB23+DB22 | DC24: =DC22+DC23 | DD24: =DD23+DD22 | DE24: =DE22+DE23 | DF24: =DF22+DF23 | DG24: =DG22+DG23 | DH24: =DH22+DH23 | DI24: =SUM(DE24:DH24) | DJ24: =DJ22+DJ23 | DK24: =DK22+DK23 | DL24: =DL22+DL23 | DM24: =DM22+DM23 | DN24: =DN23+DN22 | DO24: =DO22+DO23 | DP24: =DP22+DP23 | DQ24: =DQ22+DQ23 | DR24: =DR22+DR23 | DS24: =DS23+DS22 | DT24: =DT22+DT23 | DU24: =DU22+DU23 | DV24: =DV22+DV23 | DW24: =DW22+DW23 | DX24: =DX23+DX22 | DY24: =DY22+DY23 | DZ24: =DZ22+DZ23 | EA24: =EA22+EA23 | EB24: =EB22+EB23 | EC24: =EC23+EC22 | ED24: =ED22+ED23 | EE24: =EE22+EE23 | EF24: =EF22+EF23 | EG24: =EG22+EG23 | EH24: =EH23+EH22 | EI24: =EI22+EI23 | EJ24: =EJ22+EJ23 | EK24: =EK22+EK23 | EL24: =EL22+EL23 | EM24: =EM23+EM22 | EN24: =EN22+EN23 | EO24: =EO22+EO23 | EP24: =EP22+EP23 | EQ24: =EQ22+EQ23 | ER24: =ER23+ER22 | ES24: =ES22+ES23 | ET24: =ET22+ET23 | EU24: =EU22+EU23 | EV24: =EV22+EV23 | EW24: =EW23+EW22 | EX24: =EX22+EX23 | EY24: =EY22+EY23 | EZ24: =EZ22+EZ23 | FA24: =FA22+FA23 | FB24: =SUM(EX24:FA24) | FC24: =FC22+FC23 | FD24: =FD22+FD23 | FE24: =FE22+FE23 | FF24: =FF22+FF23 | FG24: =SUM(FC24:FF24) | FH24: =FH22+FH23 | FI24: =FI22+FI23 | FJ24: =FJ22+FJ23 | FK24: =FK22+FK23 | FL24: =SUM(FH24:FK24) | FM24: =FM22+FM23 | FN24: =FN22+FN23 | FO24: =FO22+FO23 | FP24: =FP22+FP23 | FQ24: =FQ22+FQ23 | FR24: =FR22+FR23 | FS24: =SUM(FO24:FR24) | FT24: =FT22+FT23 | FU24: =FU22+FU23 | FV24: =FV22+FV23 | FW24: =FW22+FW23 | FX24: =FX23+FX22 | FY24: =FY22+FY23 | FZ24: =FZ22+FZ23 | GA24: =GA22+GA23 | GB24: =GB22+GB23 | GC24: =GC23+GC22 | GD24: =GD22+GD23 | GE24: =GE22+GE23 | GF24: =GF22+GF23 | GG24: =GG22+GG23 | GH24: =GH23+GH22 | GI24: =GI23+GI22 | GJ24: =GJ23+GJ22 | GK24: =GK23+GK22 | GL24: =GL23+GL22 | GM24: =GM23+GM22
B26: Cost of Goods Sold | E26: 2958 | F26: 3292 | G26: 3480 | H26: 3937 | I26: 1039 | J26: 984 | K26: 1079 | L26: =M26-SUM(I26:K26) | M26: 4204 | N26: 1127 | O26: 1119 | P26: 1198 | Q26: =R26-N26-O26-P26 | R26: 4678 | S26: 1163 | T26: 1148 | U26: 1188 | V26: 1292 | W26: =S26+T26+U26+V26 | X26: 1181 | Y26: 1287 | Z26: 1364 | AA26: 1467 | AB26: =X26+Y26+Z26+AA26 | AC26: 1447 | AD26: 1562 | AE26: 1543 | AF26: 1683 | AG26: =AC26+AD26+AE26+AF26 | AH26: 1719 | AI26: 1732 | AJ26: 1715 | AK26: 1852 | AL26: 7018 | AM26: 1772 | AN26: 1749 | AO26: 1750 | AP26: 1881 | AQ26: 7152 | AR26: 1798 | AS26: 1827 | AT26: 1790 | AU26: 2189 | AV26: 7604 | AW26: 2070 | AX26: 2123 | AY26: 2068 | AZ26: 2181 | BA26: =SUM(AW26:AZ26) | BB26: 2242 | BC26: 2261 | BD26: 2191 | BE26: 2214 | BF26: =SUM(BB26:BE26) | BG26: 2311 | BH26: 2372 | BI26: 2396 | BJ26: 2502 | BK26: =SUM(BG26:BJ26) | BL26: 2457 | BM26: 2582 | BN26: 2611 | BO26: 2797 | BP26: =SUM(BL26:BO26) | BQ26: 2722 | BR26: 2966 | BS26: 2980 | BT26: 3508 | BU26: =SUM(BQ26:BT26) | BV26: 3367 | BW26: 3162 | BX26: 3187 | BY26: 3706 | BZ26: =SUM(BV26:BY26) | CA26: 3482 | CB26: 3508 | CC26: 3340 | CD26: 3624 | CE26: =SUM(CA26:CD26) | CF26: 3612 | CG26: 3788 | CH26: 3650 | CI26: 4007 | CJ26: =+SUM(CF26:CI26) | CK26: 4385 | CL26: 4358 | CM26: 4274 | CN26: 4734 | CO26: =+SUM(CK26:CN26) | CP26: 4614 | CQ26: 4751 | CR26: 4774 | CS26: 4372 | CT26: =SUM(CP26:CS26) | CU26: 4251 | CV26: 4450 | CW26: 4434 | CX26: =5312-113 | CY26: =SUM(CU26:CX26) | CZ26: =4528 | DA26: 4630 | DB26: 4594 | DC26: 5040 | DD26: =SUM(CZ26:DC26) | DE26: 4778 | DF26: 5172 | DG26: 5072 | DH26: 5338 | DI26: =SUM(DE26:DH26) | DJ26: 4915 | DK26: 5143 | DL26: =5597-165 | DM26: =6003-221 | DN26: =SUM(DJ26:DM26) | DO26: =5554-147 | DP26: 5489 | DQ26: 5344 | DR26: 5955 | DS26: =SUM(DO26:DR26) | DT26: =5455-351 | DU26: =6039-348 | DV26: =5399-334 | DW26: =5853-344 | DX26: =SUM(DT26:DW26) | DY26: =5282-312 | DZ26: =5357-307 | EA26: =5224-293 | EB26: =5673-288 | EC26: =SUM(DY26:EB26) | ED26: =5329-282 | EE26: =5336-326 | EF26: =5486-319 | EG26: =5534-344 | EH26: =SUM(ED26:EG26) | EI26: 5057 | EJ26: =5823-370 | EK26: 5463 | EL26: 5943 | EM26: =SUM(EI26:EL26) | EN26: 5416 | EO26: 5768 | EP26: 5481 | EQ26: 5856 | ER26: =SUM(EN26:EQ26) | ES26: 5462 | ET26: 5822 | EU26: 5709 | EV26: 5940 | EW26: =SUM(ES26:EV26) | EX26: 5915 | EY26: 5422 | EZ26: 5741 | FA26: 6550 | FB26: =SUM(EX26:FA26) | FC26: 5804 | FD26: 6345 | FE26: 6077 | FF26: 6797 | FG26: =SUM(FC26:FF26) | FH26: 6452 | FI26: 6600 | FJ26: 6622 | FK26: 6472 | FL26: =SUM(FH26:FK26) | FM26: 6954 | FN26: 6991 | FO26: 4968 | FP26: 5094 | FQ26: 5074 | FR26: 4889 | FS26: =SUM(FO26:FR26) | FT26: 5340 | FU26: 5336 | FV26: 5205 | FW26: 5530 | FX26: 21411 | FY26: 5404 | FZ26: 5677 | GA26: 5612 | GB26: 5775 | GC26: =SUM(FY26:GB26) | GD26: 6177 | GE26: 6334 | GF26: 6231 | GG26: =GG24*(1-GG65) | GH26: =SUM(GD26:GG26) | GI26: =GI24*(1-GI65) | GJ26: =GJ24*(1-GJ65) | GK26: =GK24*(1-GK65) | GL26: =GL24*(1-GL65) | GM26: =GM24*(1-GM65)
B27: SG&A | E27: 3228 | F27: 3630 | G27: 3897 | H27: 4469 | I27: 1269 | J27: 1216 | K27: 1272 | L27: =M27-SUM(I27:K27) | M27: 5099 | N27: 1355 | O27: 1389 | P27: 1431 | Q27: =R27-N27-O27-P27 | R27: 5671 | S27: 1436 | T27: 1432 | U27: 1445 | V27: 742 | W27: =S27+T27+U27+V27 | X27: 1480 | Y27: 1558 | Z27: 1601 | AA27: 1711 | AB27: =X27+Y27+Z27+AA27 | AC27: 1720 | AD27: 1857 | AE27: 1857 | AF27: 2028 | AG27: =AC27+AD27+AE27+AF27 | AH27: 1996 | AI27: 2027 | AJ27: 2092 | AK27: 2279 | AL27: 8394 | AM27: 2138 | AN27: 2142 | AO27: 2149 | AP27: 2286 | AQ27: 8715 | AR27: 2116 | AS27: 2140 | AT27: 2187 | AU27: 2584 | AV27: =SUM(AR27:AU27) | AW27: 2437 | AX27: 2588 | AY27: 2617 | AZ27: 2861 | BA27: =SUM(AW27:AZ27) | BB27: 2679 | BC27: 2829 | BD27: 2767 | BE27: 2943 | BF27: =SUM(BB27:BE27) | BG27: 2666 | BH27: 2802 | BI27: 2703 | BJ27: 3089 | BK27: =SUM(BG27:BJ27) | BL27: 2843 | BM27: 3017 | BN27: 3006 | BO27: 3350 | BP27: =SUM(BL27:BO27) | BQ27: 3253 | BR27: 3396 | BS27: 3428 | BT27: 4054 | BU27: =SUM(BQ27:BT27) | BV27: 3640 | BW27: 3711 | BX27: 3854 | BY27: 4655 | BZ27: =SUM(BV27:BY27) | CA27: 4043 | CB27: 4194 | CC27: 4078 | CD27: 4562 | CE27: =SUM(CA27:CD27) | CF27: 4095 | CG27: 4351 | CH27: 4291 | CI27: 4696 | CJ27: =+SUM(CF27:CI27) | CK27: 4802 | CL27: 5029 | CM27: 4899 | CN27: 5721 | CO27: =+SUM(CK27:CN27) | CP27: 5123 | CQ27: 5507 | CR27: 5195 | CS27: 5665 | CT27: =SUM(CP27:CS27) | CU27: 4608 | CV27: 4797 | CW27: 4767 | CX27: 5629 | CY27: =SUM(CU27:CX27) | CZ27: 4779 | DA27: 4756 | DB27: 4709 | DC27: 5180 | DD27: =SUM(CZ27:DC27) | DE27: 5056 | DF27: 5215 | DG27: 5240 | DH27: 5458 | DI27: =SUM(DE27:DH27) | DJ27: 5015 | DK27: 4965 | DL27: 5228 | DM27: 5661 | DN27: =SUM(DJ27:DM27) | DO27: 5223 | DP27: 5376 | DQ27: 5314 | DR27: 5917 | DS27: =SUM(DO27:DR27) | DT27: 5183 | DU27: 5481 | DV27: =5468-220 | DW27: 5822 | DX27: =SUM(DT27:DW27) | DY27: 4847 | DZ27: 5384 | EA27: 5081 | EB27: 5891 | EC27: =SUM(DY27:EB27) | ED27: 4688 | EE27: =5176 | EF27: 4772 | EG27: 5309 | EH27: =SUM(ED27:EG27) | EI27: 4737 | EJ27: 5262 | EK27: 5396 | EL27: 6025 | EM27: =SUM(EI27:EL27) | EN27: 5263 | EO27: 5743 | EP27: 5543 | EQ27: 5991 | ER27: =SUM(EN27:EQ27) | ES27: 5219 | ET27: 5546 | EU27: 5374 | EV27: 6039 | EW27: =SUM(ES27:EV27) | EX27: 5203 | EY27: 4987 | EZ27: 5427 | FA27: 6450 | FB27: =SUM(EX27:FA27) | FC27: 5427 | FD27: 6067 | FE27: 5994 | FF27: 7147 | FG27: =SUM(FC27:FF27) | FH27: 5932 | FI27: 6220 | FJ27: 6080 | FK27: 6460 | FL27: =SUM(FH27:FK27) | FM27: 6093 | FN27: 6613 | FO27: 4806 | FP27: 5114 | FQ27: 4968 | FR27: 5330 | FS27: =SUM(FO27:FR27) | FT27: 4899 | FU27: 5388 | FV27: 5394 | FW27: 5802 | FX27: 21483 | FY27: 5253 | FZ27: 5676 | GA27: 5475 | GB27: 6449 | GC27: =SUM(FY27:GB27) | GD27: 5112 | GE27: 5889 | GF27: 5922 | GG27: =GH27-SUM(GD27:GF27) | GH27: =GH24*GH66 | GI27: =GI24*GI66 | GJ27: =GJ24*GJ66 | GK27: =GK24*GK66 | GL27: =GL24*GL66 | GM27: =GM24*GM66
B28: R&D | E28: 617 | F28: 674 | G28: 719 | H28: 834 | I28: 219 | J28: 225 | K28: 242 | L28: 294 | M28: 980 | N28: 262 | O28: 268 | P28: 277 | Q28: =R28-N28-O28-P28 | R28: 1127 | S28: 281 | T28: 286 | U28: 277 | V28: 286 | W28: =S28+T28+U28+V28 | X28: 289 | Y28: 313 | Z28: 316 | AA28: 360 | AB28: =X28+Y28+Z28+AA28 | AC28: 353 | AD28: 380 | AE28: 395 | AF28: 506 | AG28: =AC28+AD28+AE28+AF28 | AH28: 428 | AI28: 448 | AJ28: 441 | AK28: 588 | AL28: 1905 | AM28: 478 | AN28: 520 | AO28: 516 | AP28: 626 | AQ28: 2140 | AR28: 514 | AS28: 548 | AT28: 524 | AU28: 750 | AV28: =SUM(AR28:AU28) | AW28: 557 | AX28: 596 | AY28: 635 | AZ28: 812 | BA28: =SUM(AW28:AZ28) | BB28: 677 | BC28: 713 | BD28: 739 | BE28: 976 | BF28: =SUM(BB28:BE28) | BG28: 759 | BH28: 829 | BI28: 899 | BJ28: 1104 | BK28: =SUM(BG28:BJ28) | BL28: 831 | BM28: 932 | BN28: 952 | BO28: 1242 | BP28: =SUM(BL28:BO28) | BQ28: 936 | BR28: 1082 | BS28: 1177 | BT28: 1489 | BU28: =SUM(BQ28:BT28) | BV28: 1095 | BW28: 1182 | BX28: 1198 | BY28: 1727 | BZ28: =SUM(BV28:BY28) | CA28: 1347 | CB28: 1487 | CC28: 1502 | CD28: 1976 | CE28: =SUM(CA28:CD28) | CF28: 1532 | CG28: 1828 | CH28: 1719 | CI28: 2046 | CJ28: =+SUM(CF28:CI28) | CK28: 1652 | CL28: 1866 | CM28: 1834 | CN28: 2328 | CO28: =+SUM(CK28:CN28) | CP28: 1712 | CQ28: 1896 | CR28: 1861 | CS28: 2108 | CT28: =SUM(CP28:CS28) | CU28: 1518 | CV28: 1638 | CW28: 1617 | CX28: 2213 | CY28: =SUM(CU28:CX28) | CZ28: 1557 | DA28: 1648 | DB28: 1657 | DC28: 1982 | DD28: =SUM(CZ28:DC28) | DE28: 1738 | DF28: 1882 | DG28: 1773 | DH28: 2155 | DI28: =SUM(DE28:DH28) | DJ28: 1645 | DK28: 1766 | DL28: 1923 | DM28: 2331 | DN28: =SUM(DJ28:DM28) | DO28: 1784 | DP28: 1946 | DQ28: 2042 | DR28: 2411 | DS28: =SUM(DO28:DR28) | DT28: 1831 | DU28: 2005 | DV28: 2023 | DW28: 2635 | DX28: =SUM(DT28:DW28) | DY28: 1899 | DZ28: 2129 | EA28: 2154 | EB28: 2864 | EC28: =SUM(DY28:EB28) | ED28: 2013 | EE28: 2264 | EF28: 2178 | EG28: 2640 | EH28: =SUM(ED28:EG28) | EI28: 2060 | EJ28: 2285 | EK28: 2574 | EL28: 3635 | EM28: =SUM(EI28:EL28) | EN28: 2404 | EO28: 2639 | EP28: 2508 | EQ28: 3224 | ER28: =SUM(EN28:EQ28) | ES28: 2858 | ET28: 2666 | EU28: 2599 | EV28: 3185 | EW28: =SUM(ES28:EV28) | EX28: 2580 | EY28: 2679 | EZ28: 2829 | FA28: 4003 | FB28: =SUM(EX28:FA28) | FC28: 3154 | FD28: 3364 | FE28: 3391 | FF28: 4680 | FG28: =SUM(FC28:FF28) | FH28: 3430 | FI28: 3554 | FJ28: 3475 | FK28: 3681 | FL28: =SUM(FH28:FK28) | FM28: 3495 | FN28: 3737 | FO28: 3323 | FP28: 3436 | FQ28: 3363 | FR28: 3550 | FS28: =SUM(FO28:FR28) | FT28: 3389 | FU28: 3613 | FV28: 3378 | FW28: 4425 | FX28: 14805 | FY28: 3490 | FZ28: 3382 | GA28: 4895 | GB28: 5267 | GC28: =SUM(FY28:GB28) | GD28: 3219 | GE28: 3559 | GF28: 3672 | GG28: =GH28-SUM(GD28:GF28) | GH28: =GH24*GH67 | GI28: =GI24*GI67 | GJ28: =GJ24*GJ67 | GK28: =GK24*GK67 | GL28: =GL24*GL67 | GM28: =GM24*GM67
B29: Operating Income (cont ops) | E29: =E24-E26-E27-E28 | F29: =F24-F26-F27-F28 | G29: =G24-G26-G27-G28 | H29: =H24-H26-H27-H28 | I29: =I24-I26-I27-I28 | J29: =J24-J26-J27-J28 | K29: =K24-K26-K27-K28 | L29: =L24-L26-L27-L28 | ... AF29: =AF24-AF26-AF27-AF28 | AG29: =AC29+AD29+AE29+AF29 | AH29: =AH24-AH26-AH27-AH28 | AI29: =AI24-AI26-AI27-AI28 | AJ29: =AJ24-AJ26-AJ27-AJ28 | AK29: =AK24-AK26-AK27-AK28 | AL29: =AL24-AL26-AL27-AL28 | AM29: =AM24-AM26-AM27-AM28 | AN29: =AN24-AN26-AN27-AN28 | AO29: =AO24-AO26-AO27-AO28 | ... GB29: =GB24-GB26-GB27-GB28 | GC29: =GC24-GC26-GC27-GC28-GC33 | GD29: =GD24-GD26-GD27-GD28 | GE29: =GE24-GE26-GE27-GE28 | GF29: =GF24-GF26-GF27-GF28 | GG29: =+GH29-SUM(GD29:GF29) | GH29: =GH24-GH26-GH27-GH28 | GI29: =GI24-GI26-GI27-GI28 | GJ29: =GJ24-GJ26-GJ27-GJ28 | GK29: =GK24-GK26-GK27-GK28 | GL29: =GL24-GL26-GL27-GL28 | GM29: =GM24-GM26-GM27-GM28
B31: Latin American operations | H31: -104 | V31: 220
B32: Non-recurring items, pre-tax | V32: 15
B33: In-process R&D | E33: 0 | F33: 0 | G33: 0 | H33: 0 | I33: 0 | J33: 0 | K33: 0 | L33: 0 | M33: 0 | N33: 0 | O33: 0 | P33: 0 | Q33: 0 | R33: 0 | S33: 0 | T33: 0 | U33: 0 | V33: 0 | W33: 0 | X33: 0 | Y33: 0 | Z33: 0 | AA33: 0 | AB33: 0 | AC33: 0 | AD33: 0 | AE33: 0 | AF33: 0 | AG33: 0 | AH33: 0 | AI33: 0 | AJ33: 0 | AK33: 0 | AL33: 0 | AM33: 0 | AN33: 0 | AO33: 0 | AP33: 0 | AQ33: 0 | AR33: 134 | AS33: 0 | AT33: 0 | AU33: 164 | AV33: =SUM(AR33:AU33) | AW33: 0 | AX33: 0 | AY33: 0 | AZ33: 0 | BA33: =SUM(AW33:AZ33) | BB33: 0 | BC33: 0 | BD33: 0 | BE33: 66 | BF33: =SUM(BB33:BE33) | BG33: 0 | BH33: 0 | BI33: 0 | BJ33: 0 | BK33: =SUM(BG33:BJ33) | BL33: 0 | BM33: 0 | BN33: 0 | BO33: 0 | BP33: =SUM(BL33:BO33) | BQ33: 18 | BR33: 900 | BS33: 0 | BT33: 0 | BU33: =SUM(BQ33:BT33) | BV33: 0 | BW33: 0 | BX33: 0 | BY33: 15 | BZ33: =SUM(BV33:BY33) | CA33: 0 | CB33: 353 | CD33: 9 | CE33: =SUM(CA33:CD33) | CF33: 37 | CG33: 87 | CH33: 115 | CI33: 320 | CJ33: =+SUM(CF33:CI33) | CK33: 807 | CL33: 0 | CM33: 0 | CN33: 0 | CO33: =+SUM(CK33:CN33) | CP33: 0 | CQ33: 0 | CR33: 0 | CS33: 0 | CT33: 0 | CU33: 0 | CV33: 0 | CW33: 0 | CX33: 0 | CY33: 0 | CZ33: 0 | DA33: 0 | DB33: 0 | DC33: 0 | DD33: 0 | DE33: 0 | DF33: 0 | DG33: 0 | DH33: 0 | DI33: 0 | DJ33: 0 | DK33: 0 | DL33: 0 | DM33: 0 | DN33: 0 | DO33: 0 | DP33: 0 | DQ33: 0 | DR33: 0 | DS33: =SUM(DO33:DR33) | DT33: 0 | DU33: 0 | DV33: 0 | DW33: 0 | DX33: 0 | DY33: 0 | DZ33: 0 | EA33: 0 | EB33: 0 | EC33: 0 | ED33: 0 | EE33: 0 | EF33: 0 | EG33: 0 | EH33: 0 | EI33: 0 | EJ33: 0 | EK33: 0 | EL33: 0 | EM33: 0 | EN33: 0 | EO33: 0 | EP33: 0 | EQ33: 0 | ER33: 0 | ES33: 0 | ET33: 0 | EU33: 0 | EV33: 0 | EW33: 0 | EX33: 0 | EY33: 0 | EZ33: 0 | FA33: 0 | FB33: 0 | FC33: 0 | FD33: 0 | FE33: 0 | FF33: 0 | FG33: 0 | FH33: 0 | FI33: 0 | FJ33: 0 | FK33: 0 | FL33: 0 | FM33: 0 | FN33: 0 | FO33: 0 | FP33: 0 | FQ33: 0 | FR33: 0 | FS33: 0 | FT33: 0 | FU33: 0 | FV33: 0 | FW33: 0 | FX33: 0 | FY33: 0 | FZ33: 0 | GA33: 0 | GB33: 0 | GC33: =SUM(FY33:GB33) | GD33: 0 | GE33: 0 | GF33: 0 | GG33: 0 | GH33: 0 | GI33: 0 | GJ33: 0 | GK33: 0 | GL33: 0 | GM33: 0
B34: Restructuring expense, other | E34: 0 | F34: 0 | G34: 0 | H34: 0 | I34: 0 | J34: 0 | K34: 0 | L34: 0 | M34: 0 | N34: 0 | O34: 0 | P34: 0 | Q34: 0 | R34: 0 | S34: 0 | T34: 0 | U34: 0 | V34: 0 | W34: 0 | X34: 0 | Y34: 0 | Z34: 0 | AA34: 0 | AB34: 0 | AC34: 0 | AD34: 0 | AE34: 0 | AF34: 0 | AG34: 0 | AH34: 0 | AI34: 0 | AJ34: 0 | AK34: 0 | AL34: 0 | AM34: 0 | AN34: 0 | AO34: 0 | AP34: 0 | AQ34: 0 | AR34: 0 | AS34: 0 | AT34: 0 | AU34: 553 | AV34: =SUM(AR34:AU34) | AW34: 0 | AX34: 0 | AY34: 0 | AZ34: 0 | BA34: =+-BA44+11.76 | BB34: 0 | BC34: 0 | BD34: 0 | BE34: -33 | BF34: =SUM(BB34:BE34) | BG34: 0 | BH34: 0 | BI34: 0 | BJ34: 0 | BK34: =SUM(BG34:BJ34) | BL34: 0 | BM34: 0 | BN34: 0 | BO34: 0 | BP34: =SUM(BL34:BO34) | BQ34: 0 | BR34: 0 | BS34: 0 | BT34: 0 | BU34: =SUM(BQ34:BT34) | BV34: 0 | BW34: 0 | BX34: 0 | BY34: 1007 | BZ34: =SUM(BV34:BY34) | CA34: 0 | CB34: 0 | CC34: 0 | CD34: =CE34-SUM(CA34:CC34) | CE34: 0 | CJ34: =+SUM(CF34:CI34) | CM34: 745 | CN34: 0 | CO34: =+SUM(CK34:CN34) | CP34: 0 | CQ34: 0 | CR34: 0 | CS34: 0 | CT34: 0 | CU34: 0 | CV34: 0 | CW34: 0 | CX34: 0 | CY34: 0 | CZ34: 0 | DA34: 0 | DB34: 0 | DC34: 0 | DD34: 0 | DE34: 0 | DF34: 0 | DG34: 0 | DH34: 0 | DI34: 0 | DJ34: 0 | DK34: 0 | DL34: 0 | DM34: 0 | DN34: 0 | DO34: 0 | DP34: 0 | DQ34: 0 | DR34: 0 | DS34: =SUM(DO34:DR34) | DT34: 0 | DU34: 0 | DV34: 0 | DW34: 0 | DX34: 0 | DY34: 0 | DZ34: 0 | EA34: 0 | EB34: 0 | EC34: 0 | ED34: 0 | EE34: 0 | EG34: 0 | EH34: 0 | EI34: 0 | EJ34: 0 | EK34: 0 | EL34: 0 | EM34: 0 | EN34: 0 | EO34: 0 | EP34: 0 | EQ34: 0 | ER34: 0 | ES34: 0 | ET34: 0 | EU34: 0 | EV34: 0 | EW34: 0 | EX34: 0 | EY34: 0 | EZ34: 0 | FA34: 0 | FB34: 0 | FC34: 0 | FD34: 0 | FE34: 0 | FF34: 0 | FG34: 0 | FH34: 0 | FI34: 0 | FJ34: 0 | FK34: 0 | FL34: 0 | FM34: 0 | FN34: 0 | FO34: 0 | FP34: 0 | FQ34: 0 | FR34: 0 | FS34: 0 | FT34: 0 | FU34: 0 | FV34: 0 | FW34: 0 | FX34: 0 | FY34: 0 | FZ34: 0 | GA34: 0 | GB34: 0 | GC34: =SUM(FY34:GB34) | GD34: 0 | GE34: 0 | GF34: 0 | GG34: 0 | GH34: 0 | GI34: 0 | GJ34: 0 | GK34: 0 | GL34: 0 | GM34: 0
B36: Interest income, net (expense) | E36: -21 | F36: -32 | G36: -54 | H36: -103 | I36: -18 | J36: -13 | K36: -10 | M36: -41 | R36: -31 | S36: -11 | T36: -18 | U36: -11 | V36: 29 | W36: =80-126 | X36: -26 | Y36: -24 | Z36: -12 | AA36: -20 | AB36: =60-142 | AC36: =18-45 | AD36: =33-38 | AE36: -9 | AF36: 13 | AG36: =115-143 | AH36: =30-35 | AI36: =33-30 | AJ36: 4 | AK36: 12 | AL36: 14 | AM36: -3 | AN36: 22 | AO36: 22 | AP36: 36 | AQ36: 83 | AR36: 34 | AS36: 36 | AT36: =70-32 | AU36: 21 | AV36: =SUM(AR36:AU36) | AW36: =54-54 | AX36: 0 | AY36: =63-46 | AZ36: 32 | BA36: =SUM(AW36:AZ36) | BB36: 22 | BC36: 35 | BD36: 79.4 | BE36: 89 | BF36: =SUM(BB36:BE36) | BG36: 92 | BH36: 70 | BI36: 67 | BJ36: 74 | BK36: =SUM(BG36:BJ36) | BL36: 42 | BM36: 30 | BN36: 12 | BO36: 12 | BP36: =SUM(BL36:BO36) | BQ36: 0 | BR36: -7 | BS36: -12 | BT36: -11 | BU36: =SUM(BQ36:BT36) | BV36: -6 | BW36: -17 | BX36: 19 | BY36: 12 | BZ36: =SUM(BV36:BY36) | CA36: 69 | CB36: 94 | CC36: 101 | CD36: 169 | CE36: =SUM(CA36:CD36) | CF36: 181 | CG36: 196 | CH36: 194 | CI36: 195 | CJ36: =+SUM(CF36:CI36) | CK36: 33 | CL36: 36 | CM36: 52 | CN36: 35 | CO36: =+SUM(CK36:CN36) | CP36: -16 | CQ36: -16 | CR36: -25 | CS36: -17 | CT36: =SUM(CP36:CS36) | CU36: -81 | CV36: -85 | CW36: -114 | CX36: -81 | CY36: =SUM(CU36:CX36) | CZ36: -81 | DA36: -58 | DB36: -95 | DC36: -114 | DD36: =SUM(CZ36:DC36) | DE36: -104 | DF36: -111 | DG36: -117 | DH36: -148 | DI36: =SUM(DE36:DH36) | DJ36: -130 | DK36: -129 | DL36: -120 | DM36: -89 | DN36: =SUM(DJ36:DM36) | DO36: -104 | DP36: -101 | DQ36: -87 | DR36: -115.44579 | DS36: =SUM(DO36:DR36) | DT36: -118 | DU36: -114 | DV36: -112 | DW36: -122 | DX36: =SUM(DT36:DW36) | DY36: -119 | DZ36: -107 | EA36: -91 | EB36: -107 | EC36: -424 | ED36: -77 | EE36: -102 | EF36: -95 | EG36: -84 | EH36: =SUM(ED36:EG36) | EI36: -84 | EJ36: -122 | EK36: -155 | EL36: -189 | EM36: =SUM(EI36:EL36) | EN36: -145 | EO36: -127 | EP36: -68 | EQ36: -54 | ER36: =SUM(EN36:EQ36) | ES36: -3 | ET36: 5 | EU36: 41 | EV36: 4 | EW36: =SUM(ES36:EV36) | EX36: 42 | EY36: -26 | EZ36: -32 | FA36: 74 | FB36: =SUM(EX36:FA36) | FC36: -48 | FD36: -28 | FE36: -7 | FF36: -47 | FG36: =SUM(FC36:FF36) | FH36: 12 | FI36: 26 | FJ36: 99 | FK36: 77 | FL36: =SUM(FH36:FK36) | FM36: -17 | FN36: 24 | FO36: 12 | FP36: 26 | FQ36: 99 | FR36: 77 | FS36: =SUM(FO36:FR36) | FT36: -14 | FU36: 109 | FV36: 182.2 | FW36: 211.8 | FX36: 489 | FY36: 209 | FZ36: 125 | GA36: 99 | GB36: 144 | GC36: =SUM(FY36:GB36) | GD36: 128 | GE36: -48 | GF36: -18 | GG36: =GH36-SUM(GD36:GF36) | GH36: -25 | GI36: =GI136+GI142 | GJ36: =GJ136+GJ142 | GK36: =GK136+GK142 | GL36: =GL136+GL142 | GM36: =GM136+GM142
B37: Other income (expense) | E37: 5 | F37: 24 | G37: -93 | H37: -162 | I37: 5 | J37: -14 | K37: 5 | L37: -81 | M37: -85 | N37: 32 | O37: -8 | P37: 14 | R37: -39 | S37: 31 | T37: 13 | U37: -3 | V37: -57 | W37: =S37+T37+U37+V37 | X37: 22 | Y37: 28 | Z37: -32 | AA37: -62 | AB37: =X37+Y37+Z37+AA37 | AC37: -28 | AD37: -27 | AE37: -62 | AF37: -49 | AG37: =AC37+AD37+AE37+AF37 | AH37: -62 | AI37: -59 | AJ37: -99 | AK37: -64 | AL37: -284 | AM37: -28 | AN37: -15 | AO37: 4 | AP37: -90 | AQ37: -129 | AR37: -18 | AS37: -4 | AT37: -27 | AU37: -14.998707 | AV37: =SUM(AR37:AU37) | AW37: -53 | AX37: -35 | AY37: -50 | AZ37: -53.741096 | BA37: =SUM(AW37:AZ37) | BB37: 50 | BC37: 11 | BD37: 14 | BE37: -2.4 | BF37: =SUM(BB37:BE37) | BG37: 6 | BH37: -8 | BI37: =-19+38 | BJ37: -55 | BK37: =SUM(BG37:BJ37) | BL37: -33 | BM37: 45 | BN37: -129 | BO37: -177 | BP37: =SUM(BL37:BO37) | BQ37: 37 | BR37: 75 | BS37: 91 | BT37: -311.5 | BU37: =SUM(BQ37:BT37) | BV37: 53 | BW37: 23 | BX37: -41 | BY37: -51 | BZ37: =SUM(BV37:BY37) | CA37: 33 | CB37: 88 | CC37: 63 | CD37: 30 | CE37: =SUM(CA37:CD37) | CF37: =718-622 | CG37: 98 | CH37: -45 | CI37: -100 | CJ37: =+SUM(CF37:CI37) | CK37: 228 | CL37: 117 | CM37: -2 | CN37: =-877+678 | CO37: =+SUM(CK37:CN37) | CP37: 18 | CQ37: 135 | CR37: 224 | CS37: =638-379 | CT37: =SUM(CP37:CS37) | CU37: 75 | CV37: -6 | CW37: 96 | CX37: =361-386 | CY37: =SUM(CU37:CX37) | CZ37: =1594-1497 | DA37: =-18+157 | DB37: =292 | DC37: =-1100+(374+569+280) | DD37: =SUM(CZ37:DC37) | DE37: =13+346 | DF37: =402-206 | DG37: =308+316 | DH37: =-2858+20+1134+1522-20+412+277+14 | DI37: =SUM(DE37:DH37) | DJ37: =611-(5045-4928) | DK37: 174 | DL37: =-30+116+90 | DM37: =-319+471+406+83-221 | DN37: =SUM(DJ37:DM37) | DO37: =-515+529+258-42-147 | DP37: =-172+375+122+69 | DQ37: =-943+872+122+35-43 | DR37: =+-868+506+181+134 | DS37: =SUM(DO37:DR37) | DT37: =-18-86+18+118+17 | DU37: =-4-226+276+144+4+126 | DV37: =1345+285+167+126-1948+83 | DW37: =-963-156+156+325+692+49+371-344 | DX37: =SUM(DT37:DW37) | DY37: =348-402+139+32-26 | DZ37: =931+134+49+9-3+11 | EA37: =-420+409+32+346 | EB37: =1205-509+301+590+83-33-288 | EC37: =SUM(DY37:EB37) | ED37: =39-120+(137+66+22) | EE37: =-557-29-114+141+600+29+24 | EF37: =54-62+109+55+67 | EG37: =-20-195+298+96+9+32 | EH37: =SUM(ED37:EG37) | EI37: 275 | EJ37: =EJ38-EJ29-EJ36 | EK37: =EK38-EK29-EK36 | EL37: =EL38-EL29-EL36 | EM37: =SUM(EI37:EL37) | EN37: =EN38-EN29-EN36 | EO37: 461 | EP37: =EP38-EP29-EP36 | EQ37: =EQ38-EQ29-EQ36 | ER37: =SUM(EN37:EQ37) | ES37: =ES38-ES29-ES36 | ET37: =ET38-ET29-ET36 | EU37: =EU38-EU29-EU36 | EV37: =EV38-EV29-EV36 | EW37: =SUM(ES37:EV37) | EX37: =EX38-EX29-EX36 | EY37: =EY38-EY29-EY36 | EZ37: =EZ38-EZ29-EZ36 | FA37: =FA38-FA29-FA36 | FB37: =SUM(EX37:FA37) | FC37: 403 | FD37: =FD38-FD29-FD36 | FE37: =FE38-FE29-FE36 | FF37: =FF38-FF29-FF36 | FG37: =SUM(FC37:FF37) | FH37: =FH38-FH29-FH36 | FI37: =FI38-FI29-FI36 | FJ37: =FJ38-FJ29-FJ36 | FK37: =FK38-FK29-FK36 | FL37: =SUM(FH37:FK37) | FM37: =FM38-FM29-FM36 | FN37: =FN38-FN29-FN36 | FO37: 594 | FP37: 485 | FQ37: 370 | FR37: 235 | FS37: =SUM(FO37:FR37) | FT37: 284 | FU37: 714 | FV37: 477 | FW37: 387 | FX37: 1862 | FY37: 432 | FZ37: 567 | GA37: 689 | GB37: 248 | GC37: =SUM(FY37:GB37) | GD37: 498 | GE37: 275 | GF37: 286 | GG37: =GH37-SUM(GD37:GF37) | GH37: 1200 | GI37: 800 | GJ37: 800 | GK37: 800 | GL37: 800 | GM37: 800
B38: Pretax Income (cont ops) | E38: =E29+E36+E37 | F38: =F29+F36+F37 | G38: =G29+G36+G37 | H38: =H29+H36+H37 | I38: =I29+I36+I37 | J38: =J29+J36+J37 | K38: =K29+K36+K37 | M38: =M29+M36+M37 | N38: =N29+N36+N37 | O38: =O29+O36+O37 | P38: =P29+P36+P37 | Q38: =Q29+Q36+Q37 | R38: =R29+R36+R37 | S38: =S29+S36+S37 | T38: =T29+T36+T37 | ... AY38: =AY29+AY36+AY37 | AZ38: 1020 | BA38: =BA29+BA36+BA37 | BB38: =BB29+BB36+BB37 | BC38: =BC29+BC36+BC37 | BD38: =BD29+BD36+BD37 | BE38: =BE29+BE36+BE37 | BF38: =BF29+BF36+BF37 | BG38: =BG29+BG36+BG37 | BH38: =BH29+BH36+BH37 | ... EI38: =EI29+EI36+EI37 | EJ38: 6285 | EK38: 6573 | EL38: 5251 | EM38: =EM29+EM36+EM37 | EN38: 6858 | EO38: 7014 | EP38: 6780 | EQ38: 6046 | ER38: =ER29+ER36+ER37 | ES38: 6867 | ET38: 8614 | EU38: 7116 | EV38: 5628 | EW38: =SUM(ES38:EV38) | EX38: 7244 | EY38: 5337 | EZ38: 7246 | FA38: 5601 | FB38: =SUM(EX38:FA38) | FC38: =FC29+FC36+FC37 | FD38: 7776 | FE38: 8058 | FF38: 6339 | FG38: =SUM(FC38:FF38) | FH38: 8218 | FI38: 8171 | FJ38: 8073 | FK38: 7418 | FL38: =SUM(FH38:FK38) | FM38: 8468 | FN38: =+FN43+FN41 | FO38: =+FO43+FO41 | FP38: =+FP43+FP41 | FQ38: =+FQ43+FQ41 | FR38: =+FR43+FR41 | FS38: =SUM(FO38:FR38) | FT38: =+FT43+FT41 | FU38: =+FU43+FU41 | FV38: =FV29+FV36+FV37 | FW38: =FW29+FW36+FW37 | FX38: =FX29+FX36+FX37 | FY38: =FY29+FY36+FY37 | FZ38: =FZ29+FZ36+FZ37 | GA38: =GA29+GA36+GA37+GA34 | GB38: =GB29+GB36+GB37 | GC38: =GC29+GC36+GC37-GC33 | GD38: =GD29+GD36+GD37 | GE38: =GE29+GE36+GE37 | GF38: =GF29+GF36+GF37+GF34 | GG38: =GG29+GG36+GG37 | GH38: =GH29+GH36+GH37 | GI38: =GI29+GI36+GI37 | GJ38: =GJ29+GJ36+GJ37 | GK38: =GK29+GK36+GK37 | GL38: =GL29+GL36+GL37 | GM38: =GM29+GM36+GM37
B39: Pretax Income (GAAP) | E39: =E29+E36+E37-E33-E34 | F39: =F29+F36+F37-F33-F34 | G39: =G29+G36+G37-G33-G34 | H39: =H29+H31+H35+H36+H37 | I39: =I29+I36+I37-I33-I34 | J39: 579 | K39: 521 | L39: =L29+L36+L37-L33-L34 | M39: =M29+M36+M37-M33-M34 | N39: =N29+N36+N37-N33-N34 | O39: =O29+O36+O37-O33-O34 | P39: =P29+P36+P37-P33-P34 | Q39: =Q29+Q36+Q37-Q33-Q34 | R39: =R29+R36+R37-R33-R34 | S39: =S29+S36+S37-S33-S34 | ... U39: =U29+U36+U37-U33-U34 | V39: 16 | W39: =W29+W36+W37-W33-W34 | X39: =X29+X36+X37-X33-X34 | Y39: =Y29+Y36+Y37-Y33-Y34 | Z39: =Z29+Z36+Z37-Z33-Z34 | AA39: =AA29+AA36+AA37-AA33-AA34 | AB39: =AB29+AB36+AB37-AB33-AB34 | AC39: =AC29+AC36+AC37-AC33-AC34 | AD39: =AD29+AD36+AD37-AD33-AD34 | ... EW39: =EW29+EW36+EW37-EW33-EW34 | FB39: =FB29+FB36+FB37-FB33-FB34 | FG39: =FG29+FG36+FG37-FG33-FG34 | FL39: =FL29+FL36+FL37-FL33-FL34 | FS39: =FS29+FS36+FS37-FS33-FS34 | FX39: =FX29+FX36+FX37-FX33-FX34 | GC39: =GC29+GC36+GC37-GC33-GC34 | GH39: =GH29+GH36+GH37-GH33-GH34 | GI39: =GI29+GI36+GI37-GI33-GI34 | GJ39: =GJ29+GJ36+GJ37-GJ33-GJ34 | GK39: =GK29+GK36+GK37-GK33-GK34 | GL39: =GL29+GL36+GL37-GL33-GL34 | GM39: =GM29+GM36+GM37-GM33-GM34
B41: Taxes (cont ops) | E41: 360 | F41: 422 | G41: 432 | H41: 480 | I41: 191 | J41: 173 | K41: 158 | L41: 55 | M41: 577 | N41: 192 | O41: 184 | P41: 154 | Q41: =R41-N41-O41-P41 | R41: 582 | S41: 197 | T41: 175 | U41: 128 | V41: 45 | W41: =S41+T41+U41+V41 | X41: 192 | Y41: 203 | Z41: 188 | AA41: 92 | AB41: =X41+Y41+Z41+AA41 | AC41: 267 | AD41: 270 | AE41: 249 | AF41: 128 | AG41: =AC41+AD41+AE41+AF41 | AH41: 334 | AI41: 328 | AJ41: 309 | AK41: 175 | AL41: 1146 | AM41: 393 | AN41: 385 | AO41: 342 | AP41: 153 | AQ41: 1273 | AR41: 375 | AS41: 373 | AT41: 357 | AU41: 74 | AV41: =SUM(AR41:AU41) | AW41: 484 | AX41: 465 | AY41: 420 | AZ41: 217 | BA41: =SUM(AW41:AZ41) | BB41: 583 | BC41: 550 | BD41: 511 | BE41: 271 | BF41: =SUM(BB41:BE41) | BG41: 665 | BH41: 654 | BI41: =579+14 | BJ41: 339 | BK41: =SUM(BG41:BJ41) | BL41: 787 | BM41: 774 | BN41: 668 | BO41: 465 | BP41: =SUM(BL41:BO41) | BQ41: 859 | BR41: 846 | BS41: 877 | BT41: 529 | BU41: =SUM(BQ41:BT41) | BV41: 1010.6 | BW41: 977.4 | BX41: 939 | BY41: =1408-789 | BZ41: =SUM(BV41:BY41) | CA41: 1135 | CB41: =726+225 | CC41: 929 | CD41: 458 | CE41: =SUM(CA41:CD41) | CF41: 1064 | CG41: 783 | CH41: 901 | CI41: 643 | CJ41: =+SUM(CF41:CI41) | CK41: 1079 | CL41: 950 | CM41: 935 | CN41: 462 | CO41: =+SUM(CK41:CN41) | CP41: 1148.774 | CQ41: 1048 | CR41: 980 | CS41: =803-150 | CT41: =SUM(CP41:CS41) | CU41: 1136 | CV41: 1055 | CW41: 900 | CX41: 558 | CY41: =SUM(CU41:CX41) | CZ41: 1167 | DA41: 995 | DB41: 802 | DC41: 586.67 | DD41: =SUM(CZ41,DA41,DB41,DC41) | DE41: 1109 | DF41: 865 | DG41: 984 | DH41: 528 | DI41: =SUM(DE41:DH41) | DJ41: =4928-3804 | DK41: =4646-3644 | DL41: =4525-3521 | DM41: =4115-3376 | DN41: =SUM(DJ41:DM41) | DO41: =5070-4107 | DP41: =5359-4289 | DQ41: =4831-3919 | DR41: =3909-3561 | DS41: =SUM(DO41:DR41) | DT41: =DT38-4693 | DU41: =6524-5133 | DV41: =DV38-4292 | DW41: =DW38-3887 | DX41: =SUM(DT41:DW41) | DY41: =1255-43 | DZ41: =1225+211 | EA41: =5212-4172 | EB41: =EB38-4043 | EC41: =SUM(DY41:EB41) | ED41: =1744+608+278+666+29+46-(443+217+549+23+34)-EE41 | EE41: =907+326+141+600+29+24-(238+97+493+23+18) | EF41: =1*(5831-4683) | EG41: 742 | EH41: =SUM(ED41:EG41) | EI41: 1065 | EJ41: =EJ38-EJ43 | EK41: =EK38-EK43 | EL41: =EL38-EL43 | EM41: =SUM(EI41:EL41) | EN41: =EN38-EN43 | EO41: =EO38-EO43 | EP41: =EP38-EP43 | EQ41: =EQ38-EQ43 | ER41: =SUM(EN41:EQ41) | ES41: =ES38-ES43 | ET41: =ET38-ET43 | EU41: =EU38-EU43 | EV41: =EV38-EV43 | EW41: =SUM(ES41:EV41) | EX41: =EX38-EX43 | EY41: =EY38-EY43 | EZ41: =EZ38-EZ43 | FA41: =FA38-FA43 | FB41: =SUM(EX41:FA41) | FC41: =FC38-FC43 | FD41: =FD38-FD43 | FE41: =FE38-FE43 | FF41: =FF38-FF43 | FG41: =SUM(FC41:FF41) | FH41: =FH38-FH43 | FI41: =FI38-FI43 | FJ41: =FJ38-FJ43 | FK41: =FK38-FK43 | FL41: =SUM(FH41:FK41) | FM41: =FM38-FM43 | FN41: 1465.5 | FO41: 961 | FP41: 1044 | FQ41: 1122 | FR41: 1050 | FS41: =SUM(FO41:FR41) | FT41: 1196 | FU41: 1275 | FV41: 1256 | FW41: 675 | FX41: 4402 | FY41: 1297 | FZ41: 1564 | GA41: 1401 | GB41: 475 | GC41: =SUM(FY41:GB41) | GD41: 1305 | GE41: 1489 | GF41: 1635 | GG41: =+GH41-SUM(GD41:GF41) | GH41: =GH38*GH71 | GI41: =GI38*GI71 | GJ41: =GJ38*GJ71 | GK41: =GK38*GK71 | GL41: =GL38*GL71 | GM41: =GM38*GM71
B43: Net Income (cont ops, incl ESO) | AR43: =+AR38-AR41 | AS43: =+AS38-AS41 | AT43: =+AT38-AT41 | AU43: =+AU38-AU41 | AV43: =+AV38-AV41 | AW43: =+AW38-AW41 | AX43: =+AX38-AX41 | AY43: =+AY38-AY41 | ... DR43: =+DR38-DR41 | DS43: =SUM(DO43:DR43) | DT43: =+DT38-DT41 | DU43: =+DU38-DU41 | DV43: =+DV38-DV41 | DW43: =+DW38-DW41 | DX43: =SUM(DT43:DW43) | DY43: =+DY38-DY41 | DZ43: =+DZ38-DZ41 | EA43: =+EA38-EA41 | EB43: =+EB38-EB41 | EC43: =+EC38-EC41 | ED43: =+ED38-ED41 | EE43: =+EE38-EE41 | EF43: =+EF38-EF41 | ... EI43: =+EI38-EI41 | EJ43: 5017 | EK43: 5208 | EL43: 4777 | EM43: =+EM38-EM41 | EN43: 5635 | EO43: 5718 | EP43: 5590 | EQ43: 5372 | ER43: =+ER38-ER41 | ES43: 5661 | ET43: 6950 | EU43: 5672 | EV43: 5027 | EW43: =+EW38-EW41 | EX43: 6154 | EY43: 4446 | EZ43: 5868 | FA43: 4965 | FB43: =+FB38-FB41 | FC43: 6924 | FD43: 6625 | FE43: 6968 | FF43: 5678 | FG43: =+FG38-FG41 | FH43: 7129 | FI43: 6912 | FJ43: 6779 | FK43: 6218 | FL43: =+FL38-FL41 | FM43: 7068 | FN43: 7358 | FO43: 6388 | FP43: 6038 | FQ43: 5938 | FR43: 5432 | FS43: =+FS38-FS41 | FT43: 6339.9 | FU43: 6730.3 | FV43: =+FV38-FV41 | FW43: =+FW38-FW41 | FX43: =+FX38-FX41 | FY43: =+FY38-FY41 | FZ43: =+FZ38-FZ41 | GA43: =+GA38-GA41 | GB43: =+GB38-GB41 | GC43: =+GC38-GC41 | ... GM43: =+GM38-GM41
B44: Non-recurring items, net of tax | AR44: =+AR43-AR45 | AS44: =+AS43-AS45 | AT44: =+AT43-AT45 | AU44: =+AU43-AU45 | AV44: =+AV43-AV45 | AW44: =+AW43-AW45 | AX44: =+AX43-AX45 | AY44: =+AY43-AY45 | ... CT44: =+CT43-CT45 | CU44: 0 | CV44: 0 | CW44: 0 | CX44: 640.00401 | CY44: =SUM(CU44:CX44) | CZ44: -910 | DA44: =-67 | DB44: 0 | DC44: =279+404+239 | DD44: =SUM(CZ44:DC44) | DE44: =271 | DF44: 772 | DG44: 241 | DH44: 2911 | DI44: =SUM(DE44:DH44) | DJ44: =3804-3910 | DK44: =3644-1408 | DL44: =3521-2968 | DM44: =3376-2567 | DN44: =SUM(DJ44:DM44) | DO44: =4107-3497 | DP44: =4289-3833 | DQ44: =3919-2982 | DR44: =227+294+110+118-707 | DS44: =SUM(DO44:DR44) | DT44: =84+13-398 | DU44: =342+104+3 | DV44: =-1149+231+220+130+111 | DW44: =87+652+237+115 | DX44: =SUM(DT44:DW44) | DY44: =226-253+122+25-22 | DZ44: =230+23+37+8-2 | EA44: =437+348+23+6 | EB44: =301+590+214+83-33-220-415-156-59+22 | EC44: =SUM(DY44:EB44) | ED44: =ED43-ED45 | EE44: =EE43-EE45 | EF44: =EF43-EF45 | EG44: =EG43-EG45 | EH44: =SUM(ED44:EG44) | EI44: =EI43-EI45 | EJ44: =EJ43-EJ45 | EK44: =EK43-EK45 | EL44: =EL43-EL45 | EM44: =SUM(EI44:EL44) | EN44: =EN43-EN45 | EO44: =EO43-EO45 | EP44: =EP43-EP45 | EQ44: =EQ43-EQ45 | ER44: =SUM(EN44:EQ44) | ES44: =ES43-ES45 | ET44: =ET43-ET45 | EU44: =EU43-EU45 | EV44: =EV43-EV45 | EW44: =SUM(ES44:EV44) | EX44: =EX43-EX45 | EY44: =EY43-EY45 | EZ44: =EZ43-EZ45 | FA44: =FA43-FA45 | FB44: =SUM(EX44:FA44) | FC44: =FC43-FC45 | FD44: =FD43-FD45 | FE44: =FE43-FE45 | FF44: =FF43-FF45 | FG44: =SUM(FC44:FF44) | FH44: =FH43-FH45 | FI44: =FI43-FI45 | FJ44: =FJ43-FJ45 | FK44: =FK43-FK45 | FL44: =SUM(FH44:FK44) | FM44: =FM43-FM45 | FN44: =FN43-FN45 | FO44: =FO43-FO45 | FP44: =FP43-FP45 | FQ44: =FQ43-FQ45 | FR44: =FR43-FR45 | FS44: =SUM(FO44:FR44) | FT44: =FT43-FT45 | FU44: =FU43-FU45 | FV44: =FV43-FV45 | FW44: =FW43-FW45 | FX44: =SUM(FT44:FW44) | FY44: 1500 | FZ44: =FZ43-FZ45 | GA44: =GA43-GA45 | GB44: =GB43-GB45 | GC44: =SUM(FY44:GB44) | GD44: =(932-5413+44+102+30+12) | GE44: =GE43-GE45 | GF44: =GF43-GF45 | GG44: =GF44 | GH44: =SUM(GD44:GG44) | GI44: 5000 | GJ44: =+GI44-500 | GK44: =+GJ44-500 | GL44: =+GK44 | GM44: =+GL44
B45: Net Income (GAAP, inc ESO) | AR45: =+'Cash Flows'!U12 | AS45: =+'Cash Flows'!V12 | AT45: =+'Cash Flows'!W12 | AU45: =+'Cash Flows'!X12 | AV45: =+'Cash Flows'!Y12 | AW45: =+'Cash Flows'!Z12 | AX45: =+'Cash Flows'!AA12 | AY45: =+'Cash Flows'!AB12 | ... CT45: =+'Cash Flows'!BW12 | CU45: =+CU43-CU44 | CV45: =+CV43-CV44 | CW45: =+CW43-CW44 | CX45: =+CX43-CX44 | CY45: =+CY43-CY44 | CZ45: =+CZ43-CZ44 | DA45: =+DA43-DA44 | DB45: =+DB43-DB44 | ... DR45: =+DR43-DR44 | DS45: =SUM(DO45:DR45) | DT45: =+DT43-DT44 | DU45: =+DU43-DU44 | DV45: =+DV43-DV44 | DW45: =+DW43-DW44 | DX45: =SUM(DT45:DW45) | DY45: =+DY43-DY44 | DZ45: =+DZ43-DZ44 | EA45: =+EA43-EA44 | EB45: =+EB43-EB44 | EC45: =+EC43-EC44 | ED45: =4292 | EE45: =8454-ED45 | EF45: 4272 | EG45: 3814 | EH45: =+EH43-EH44 | EI45: 4422 | EJ45: =8249-EI45 | EK45: 3764 | EL45: -10713 | EM45: =+EM43-EM44 | EN45: 4367 | EO45: 3954 | EP45: 3934 | EQ45: 3042 | ER45: =+ER43-ER44 | ES45: 3749 | ET45: 5607 | EU45: 4833 | EV45: 4010 | EW45: =+EW43-EW44 | EX45: 5796 | EY45: 3626 | EZ45: 3554 | FA45: 1738 | FB45: =+FB43-FB44 | FC45: 6197 | FD45: 6278 | FE45: 3667 | FF45: 4736 | FG45: =+FG43-FG44 | FH45: 5149 | FI45: 4814 | FJ45: 4458 | FK45: 3520 | FL45: =+FL43-FL44 | FM45: -68 | FN45: 5144 | FO45: 4571 | FP45: 4262 | FQ45: 4310 | FR45: 3227 | FS45: =+FS43-FS44 | FT45: -491 | FU45: 5376 | FV45: 4309 | FW45: 4132 | FX45: =+FX43-FX44 | FY45: =+FY43-FY44 | FZ45: 4686 | GA45: 2694 | GB45: 3431 | GC45: =+GC43-GC44 | GD45: =+GD43-GD44 | GE45: 5537 | GF45: 5152 | GG45: =+GG43-GG44 | GH45: =+GH43-GH44 | GI45: =+GI43-GI44 | GJ45: =+GJ43-GJ44 | GK45: =+GK43-GK44 | GL45: =+GL43-GL44 | GM45: =+GM43-GM44
B46: Discontinued operations, net of tax | FT46: 423 | FU46: -232 | FV46: 21719 | FW46: -83 | FX46: =SUM(FT46:FW46) | FZ46: 0
B47: Net Income (GAAP, inc ESO and disc. ops) | FT47: =+FT45+FT46 | FU47: =+FU45+FU46 | FV47: =+FV45+FV46 | FW47: =+FW45+FW46 | FX47: =SUM(FT47:FW47) | FY47: =+FY45+FY46 | FZ47: =+FZ45+FZ46 | GA47: =+GA45+GA46 | GB47: =+GB45+GB46 | GC47: =SUM(FY47:GB47) | GD47: =+GD45+GD46 | GE47: =+GE45+GE46 | GF47: =+GF45+GF46 | GG47: =+GG45+GG46 | GH47: =+GH45+GH46 | GI47: =+GI45+GI46 | GJ47: =+GJ45+GJ46 | GK47: =+GK45+GK46 | ... GM47: =+GM45+GM46
B49: Net Income (cont ops, exc ESO)) | E49: =E39-E41 | F49: =F39-F41 | G49: =G39-G41 | H49: =H39-H41 | I49: =I39-I41 | J49: =J39-J41 | K49: =K39-K41 | L49: =M49-SUM(I49:K49) | M49: =M39-M41 | N49: =N39-N41 | O49: =O39-O41 | P49: =P39-P41 | Q49: =R49-N49-O49-P49 | R49: =R39-R41 | S49: =S39-S41 | T49: =T39-T41 | U49: =U39-U41 | V49: 202 | W49: =W39-W41 | X49: =X39-X41 | Y49: =Y39-Y41 | Z49: =Z39-Z41 | AA49: =AA39-AA41 | AB49: =AB39-AB41 | AC49: =AC39-AC41 | AD49: =AD39-AD41 | ... AQ49: =AQ39-AQ41 | AR49: =AR38-AR41+AR51 | AS49: =AS38-AS41+AS51 | AT49: =AT38-AT41+AT51 | AU49: =AU38-AU41+AU51 | AV49: =AV38-AV41+AV51 | AW49: =AW38-AW41+AW51 | AX49: =AX38-AX41+AX51 | AY49: =AY38-AY41+AY51 | ... DR49: =DR38-DR41+DR51 | DS49: =SUM(DO49:DR49) | DT49: =DT38-DT41+DT51 | DU49: =DU38-DU41+DU51 | DV49: =DV38-DV41+DV51 | DW49: =DW38-DW41+DW51 | DX49: =SUM(DT49:DW49) | DY49: =DY38-DY41+DY51 | DZ49: =DZ38-DZ41+DZ51 | EA49: =EA38-EA41+EA51 | EB49: =EB38-EB41+EB51 | EC49: =EC38-EC41+EC51 | ED49: =ED38-ED41+ED51 | EE49: =EE38-EE41+EE51 | EF49: =EF38-EF41+EF51 | ... GM49: =GM38-GM41+GM51
B50: ESO expense (pre-tax) | BU50: =+BU51/(1-BU71) | BV50: =+BV51/(1-BV71) | BW50: =+BW51/(1-BW71) | BX50: =+BX51/(1-BX71) | BY50: =+BY51/(1-BY71) | BZ50: =+BZ51/(1-BZ71) | CA50: =+CA51/(1-CA71) | CB50: =+CB51/(1-CB71) | ... DC50: =+DC51/(1-DC71) | DD50: =SUM(CZ50:DC50) | DE50: =+DE51/(1-DE71) | DF50: =+DF51/(1-DF71) | DG50: =+DG51/(1-DG71) | DH50: =+DH51/(1-DH71) | DI50: =SUM(DE50:DH50) | DJ50: =+DJ51/(1-DJ71) | DK50: =+DK51/(1-DK71) | DL50: =+DL51/(1-DL71) | DM50: =+DM51/(1-DM71) | DN50: =SUM(DJ50:DM50) | DO50: =+DO51/(1-DO71) | DP50: =+DP51/(1-DP71) | DQ50: =+DQ51/(1-DQ71) | DR50: =+DR51/(1-DR71) | DS50: =SUM(DO50:DR50) | DT50: =+DT51/(1-DT71) | DU50: =+DU51/(1-DU71) | DV50: =+DV51/(1-DV71) | DW50: =+DW51/(1-DW71) | DX50: =SUM(DT50:DW50) | DY50: =+DY51/(1-DY71) | DZ50: =+DZ51/(1-DZ71) | EA50: =+EA51/(1-EA71) | EB50: =+EB51/(1-EB71) | EC50: =SUM(DY50:EB50) | ED50: =+ED51/(1-ED71) | EE50: =+EE51/(1-EE71) | EF50: =+EF51/(1-EF71) | EG50: =+EG51/(1-EG71) | EH50: =SUM(ED50:EG50) | EI50: =+EI51/(1-EI71) | EJ50: =+EJ51/(1-EJ71) | EK50: =+EK51/(1-EK71) | EL50: =+EL51/(1-EL71) | EM50: =SUM(EI50:EL50) | EN50: =+EN51/(1-EN71) | EO50: =+EO51/(1-EO71) | EP50: =+EP51/(1-EP71) | EQ50: =+EQ51/(1-EQ71) | ER50: =SUM(EN50:EQ50) | ES50: =+ES51/(1-ES71) | ET50: =+ET51/(1-ET71) | EU50: =+EU51/(1-EU71) | EV50: =+EV51/(1-EV71) | EW50: =+EW51/(1-EW71) | EX50: =+EX51/(1-EX71) | EY50: =+EY51/(1-EY71) | EZ50: =+EZ51/(1-EZ71) | FA50: =FB50-SUM(EX50:EZ50) | FB50: =+FB51/(1-FB71) | FC50: =+FC51/(1-FC71) | FD50: =+FD51/(1-FD71) | FE50: =+FE51/(1-FE71) | FF50: =+FF51/(1-FF71) | FG50: =+FG51/(1-FG71) | FH50: =+FH51/(1-FH71) | FI50: =+FI51/(1-FI71) | ... GM50: =+GM51/(1-GM71)
B51: ESO expense (post-tax) | BU51: 349 | BV51: 80 | BW51: 88 | BX51: 88 | BY51: 73 | BZ51: =+SUM(BV51:BY51) | CA51: 88 | CB51: 88 | CC51: 87 | CD51: 87 | CE51: =+SUM(CA51:CD51) | CF51: 95 | CG51: 95 | CH51: 95 | CI51: 95 | CJ51: =+SUM(CF51:CI51) | CK51: 95 | CL51: 95 | CM51: 95 | CN51: 95 | CO51: =+SUM(CK51:CN51) | CP51: 95 | CQ51: 95 | CR51: 95 | CS51: 95 | CT51: =SUM(CP51:CS51) | CU51: =+$CY51/4 | CV51: =+$CY51/4 | CW51: =+$CY51/4 | CX51: =+CY51-SUM(CU51:CW51) | CY51: 385 | CZ51: 97.5 | DA51: 97.5 | DB51: 97.5 | DC51: 97.5 | DD51: =SUM(CZ51:DC51) | DE51: 97.5 | DF51: 97.5 | DG51: 97.5 | DH51: 97.5 | DI51: =SUM(DE51:DH51) | DJ51: =+$DN$51/4 | DK51: =+$DN$51/4 | DL51: =+$DN$51/4 | DM51: =+DN51-SUM(DJ51:DL51) | DN51: 390 | DO51: =+$DN$51/4 | DP51: =+$DN$51/4 | DQ51: =+$DN$51/4 | DR51: =+DS51-SUM(DO51:DQ51) | DS51: 390 | DT51: =+$DX$51/4 | DU51: =+$DX$51/4 | DV51: =+$DX$51/4 | DW51: =+$DX$51/4 | DX51: 390 | DY51: =+$DX$51/4 | DZ51: =+$DX$51/4 | EA51: =+$DX$51/4 | EB51: =+$DX$51/4 | EC51: 390 | ED51: =+$EH$51/4 | EE51: =+$EH$51/4 | EF51: =+$EH$51/4 | EG51: =+$EH$51/4 | EH51: 390 | EI51: =+EJ51 | EJ51: =+EK51 | EK51: =+EL51 | EL51: 90 | EM51: =+SUM(EI51:EL51) | EN51: =+EO51 | EO51: =+EP51 | EP51: =+EQ51 | EQ51: 90 | ER51: =+SUM(EN51:EQ51) | ES51: =+ET51 | ET51: =+EU51 | EU51: =+EV51 | EV51: =+$EM$51/4 | EW51: 360 | EX51: =+EY51 | EY51: =+EZ51 | EZ51: =+FA51 | FA51: =+$EM$51/4 | FB51: 360 | FC51: =$FG$51/4 | FD51: =$FG$51/4 | FE51: =$FG$51/4 | FF51: =$FG$51/4 | FG51: 360 | FH51: =$FL$51/4 | FI51: =$FL$51/4 | FJ51: =$FL$51/4 | FK51: =$FL$51/4 | FL51: 390 | FM51: =$FX$51/4 | FN51: =$FX$51/4 | FO51: =$FL$51/4 | FP51: =$FL$51/4 | FQ51: =$FL$51/4 | FR51: =$FL$51/4 | FS51: 390 | FT51: =$FX$51/4 | FU51: =$FX$51/4 | FV51: =$FX$51/4 | FW51: =$FX$51/4 | FX51: 390 | FY51: =$FX$51/4 | FZ51: =$FX$51/4 | GA51: =$FX$51/4 | GB51: =$FX$51/4 | GC51: 390 | GD51: =$GH$51/4 | GE51: =$FX$51/4 | GF51: =$FX$51/4 | GG51: =$GH$51/4 | GH51: 390 | GI51: 390 | GJ51: 390 | GK51: 390 | GL51: 390 | GM51: 390
B52: Basic EPS (cont ops, inc ESO) | AV52: =+AV43/AV60 | AW52: =+AW43/AW60 | AX52: =+AX43/AX60 | AY52: =+AY43/AY60 | AZ52: =+AZ43/AZ60 | BA52: =+BA43/BA60 | BB52: =+BB43/BB60 | BC52: =+BC43/BC60 | ... GM52: =+GM43/GM60
B53: Basic EPS (cont ops, exc ESO) | AV53: =+AV49/AV60 | AW53: =+AW49/AW60 | AX53: =+AX49/AX60 | AY53: =+AY49/AY60 | AZ53: =+AZ49/AZ60 | BA53: =+BA49/BA60 | BB53: =+BB49/BB60 | BC53: =+BC49/BC60 | ... GM53: =+GM49/GM60
B54: Basic EPS (GAAP) | AV54: =+AV45/AV60 | AW54: =+AW45/AW60 | AX54: =+AX45/AX60 | AY54: =+AY45/AY60 | AZ54: =+AZ45/AZ60 | BA54: =+BA45/BA60 | BB54: =+BB45/BB60 | BC54: =+BC45/BC60 | ... GM54: =+GM45/GM60
B55: Diluted EPS (cont ops, inc ESO) | AV55: =+AV43/AV61 | AW55: =+AW43/AW61 | AX55: =+AX43/AX61 | AY55: =+AY43/AY61 | AZ55: =+AZ43/AZ61 | BA55: =+BA43/BA61 | BB55: =+BB43/BB61 | BC55: =+BC43/BC61 | ... CD55: =+CD43/CD61 | CE55: =+CE43/CE61+0.002 | CF55: =+CF43/CF61 | CG55: =+CG43/CG61 | CH55: =+CH43/CH61 | CI55: =+CI43/CI61 | CJ55: =+CJ43/CJ61 | CK55: =+CK43/CK61 | CL55: =+CL43/CL61 | CM55: =+CM43/CM61 | ... FW55: =+FW43/FW61 | FX55: =SUM(FT55:FW55) | FY55: =+FY43/FY61 | FZ55: =+FZ43/FZ61 | GA55: =+GA43/GA61 | GB55: =+GB43/GB61 | GC55: =+GC43/GC61 | GD55: =+GD43/GD61 | GE55: =+GE43/GE61 | GF55: =+GF43/GF61 | ... GM55: =+GM43/GM61
B56: Diluted EPS (cont ops, excl ESO) | AG56: =AG49/AG61 | AH56: 0.58 | AI56: 0.58 | AJ56: 0.55 | AK56: 0.41 | AL56: =AL49/AL61 | AM56: =AM49/AM61 | AN56: =AN49/AN61 | AO56: =AO49/AO61 | AP56: =AP49/AP61 | AQ56: =AQ49/AQ61 | AR56: =AR49/AR61 | AS56: =AS49/AS61 | ... GM56: =GM49/GM61
B57: Diluted EPS (GAAP) | AG57: =AG49/AG61 | AH57: 0.58 | AI57: 0.58 | AJ57: 0.55 | AK57: 0.41 | AL57: =AL49/AL61 | AM57: =AM49/AM61 | AN57: 0.67 | AO57: 0.63 | AP57: 0.453 | AQ57: =AQ49/AQ61 | AR57: =AR49/AR61 | AS57: =AS49/AS61 | AT57: =AT49/AT61 | AU57: =AU49/AU61 | AV57: =+AV45/AV61 | AW57: =+AW45/AW61 | AX57: =+AX45/AX61 | AY57: =+AY45/AY61 | AZ57: =+AZ45/AZ61 | BA57: =+BA45/BA61 | BB57: =+BB45/BB61 | BC57: =+BC45/BC61 | ... GM57: =+GM45/GM61
B59: Cash dividends declared per share | BL59: 0.18 | BM59: 0.205 | BN59: 0.205 | BO59: 0.205 | BP59: =SUM(BL59:BO59) | BQ59: 0.205 | BR59: 0.24 | BS59: 0.24 | BT59: 0.24 | BU59: =SUM(BQ59:BT59) | BV59: 0.24 | BW59: 0.285 | BX59: 0.285 | BY59: 0.285 | BZ59: =SUM(BV59:BY59) | CA59: 0.285 | CB59: 0.33 | CC59: 0.33 | CD59: 0.33 | CE59: =SUM(CA59:CD59) | CF59: 0.33 | CG59: 0.375 | CH59: 0.375 | CI59: 0.375 | CJ59: =SUM(CF59:CI59) | CK59: 0.375 | CL59: 0.415 | CM59: 0.415 | CN59: 0.415 | CO59: 1.62 | CP59: 0.415 | CQ59: 0.46 | CR59: 0.46 | CS59: 0.46 | CT59: 1.795 | CU59: 0.46 | CV59: 0.49 | CW59: 0.49 | CX59: =CY59-SUM(CU59:CW59) | CY59: 1.93 | CZ59: 0.49 | DA59: 0.54 | DB59: 0.54 | DC59: 0.54 | DD59: 2.11 | DE59: 0.54 | DF59: 0.57 | DG59: 0.57 | DH59: 0.57 | DI59: =SUM(DE59:DH59) | DJ59: 0.57 | DK59: 0.61 | DL59: 0.61 | DM59: 0.61 | DN59: ='Balance Sheet'!CO101 | DO59: ='Balance Sheet'!CP101 | DP59: ='Balance Sheet'!CQ101 | DQ59: ='Balance Sheet'!CR101 | DR59: ='Balance Sheet'!CS101 | DS59: ='Balance Sheet'!CT101 | DT59: ='Balance Sheet'!CU101 | DU59: ='Balance Sheet'!CV101 | ... FN59: ='Balance Sheet'!EO101 | FO59: =+FH59 | FP59: =+FI59 | FQ59: =+FJ59 | FR59: =+FK59 | FS59: =+FL59 | FT59: =+FM59 | FU59: =+FN59 | FV59: ='Balance Sheet'!EP101 | FW59: ='Balance Sheet'!EQ101 | FX59: ='Balance Sheet'!ER101 | FY59: ='Balance Sheet'!ES101 | FZ59: =+FY59 | GA59: =+FZ59 | GB59: =+GA59 | GC59: 4.76 | GD59: ='Balance Sheet'!EX101 | GE59: =+GD59 | GF59: =+GE59 | GG59: ='Balance Sheet'!FA101 | GH59: ='Balance Sheet'!FB101 | GI59: ='Balance Sheet'!FC101 | GJ59: ='Balance Sheet'!FD101 | GK59: ='Balance Sheet'!FE101 | GL59: ='Balance Sheet'!FF101 | GM59: ='Balance Sheet'!FG101
B60: Shares outstanding (basic) | E60: =4*690.3 | F60: =4*681.2 | G60: =4*666.2 | H60: =4*666.1 | I60: =4*666.2 | J60: =666.2*4 | K60: =4*666.2 | L60: =M60*4-I60-J60-K60 | M60: =4*666.1 | N60: =4*666 | O60: =4*660.8 | P60: =4*655.5 | Q60: =R60*4-N60-O60-P60 | R60: =4*659.5 | S60: =4*655.4 | T60: =4*655.3 | U60: =4*651.7 | V60: =+W60 | W60: =4*651.7 | X60: =4*643.1 | Y60: =4*643.3 | Z60: =4*643.3 | AA60: =4*642.9 | AB60: =4*643.1 | AC60: =4*643.1 | AD60: =4*645.6 | AE60: =4*647.8 | AF60: =4*647.6 | AG60: =2*1291.9 | AH60: =4*666.3 | AI60: =2*1332.9 | AJ60: =2*1332.9 | AK60: =2*1332.2 | AL60: =2*1332.6 | AM60: =2*1333.1 | AN60: =2*1332.5 | AO60: =2*1335.1 | AP60: =2*1342.1 | AQ60: =2*1336 | AR60: =2*1390 | AS60: =2*1390 | AT60: =2*1390 | AU60: =2*1390 | AV60: 2779.6 | AW60: =2*1390.2 | AX60: =2*1390.1 | AY60: =2*1389.9 | AZ60: =AY60 | BA60: 2780.2 | BB60: 2993 | BC60: 2993 | BD60: 2994 | BE60: 2994 | BF60: 2993.5 | BG60: 3020.4 | BH60: 3029.3 | BI60: 3039.2 | BJ60: 3020.4 | BK60: 3033.8 | BL60: 3042 | BM60: 3003.4 | BN60: 2974.4 | BO60: 3003 | BP60: 2998.3 | BQ60: 2968.4 | BR60: 2967.7 | BS60: 2968 | BT60: 3005.4 | BU60: 2968.1 | BV60: 2967.8 | BW60: 2968.2 | BX60: 2968.2 | BY60: 3012 | BZ60: =AVERAGE(BV60:BY60) | CA60: 2967.8 | CB60: 2973.7 | CC60: 2968.2 | CD60: 2960 | CE60: 2973.9 | CF60: 2979.05 | CG60: 2954 | CH60: 2928 | CI60: =+CI61-(CD61-CD60) | CJ60: =AVERAGE(CF60:CI60) | CK60: 2900 | CL60: =+CL61-CK61+CK60 | CM60: =+CM61-CL61+CL60 | CN60: =+CN61-CM61+CM60 | CO60: =+AVERAGE(CK60:CN60) | CP60: 2780.6 | CQ60: 2780.6 | CR60: 2780.6 | CS60: =+CS61-CR61+CR60 | CT60: =+CT61-CO61+CO60 | CU60: 2765.9 | CV60: 2756.2 | CW60: 2756.3 | CX60: =+CX61-CW61+CW60 | CY60: 2759.5 | CZ60: 2755.4 | DA60: 2756.6 | DB60: 2751.6 | DC60: =+DC61-DB61+DB60 | DD60: 2751.4 | DE60: 2738.4 | DF60: 2740.5 | DG60: 2738.5 | DH60: =+DH61-DG61+DG60 | DI60: 2736 | DJ60: 2736.9 | DK60: 2747.4 | DL60: 2757.4 | DM60: =+DM61-DL61+DL60 | DN60: 2753.3 | DO60: 2790.2 | DP60: 2809.7 | DQ60: =+'Balance Sheet'!CR120 | DR60: =+'Balance Sheet'!CS120 | DS60: =AVERAGE(DO60:DR60) | DT60: =+'Balance Sheet'!CU120 | DU60: =+'Balance Sheet'!CV120 | DV60: =+'Balance Sheet'!CW120 | DW60: =+'Balance Sheet'!CX120 | DX60: =AVERAGE(DT60:DW60) | DY60: =+'Balance Sheet'!CZ120 | DZ60: =+'Balance Sheet'!DA120 | EA60: =+'Balance Sheet'!DB120 | EB60: =+'Balance Sheet'!DC120 | EC60: =+'Balance Sheet'!DD120 | ED60: =+'Balance Sheet'!DE120 | EE60: =+'Balance Sheet'!DF120 | EF60: =+'Balance Sheet'!DG120 | ... FN60: =+'Balance Sheet'!EO120 | FO60: =+FH60 | FP60: =+FI60 | FQ60: =+FJ60 | FR60: =+FK60 | FS60: =+FL60 | FT60: =+FM60 | FU60: =+FN60 | FV60: =+FU60 | FW60: =+'Balance Sheet'!EQ120 | FX60: =+FX61*FX62 | FY60: =+'Balance Sheet'!ES120 | FZ60: =+'Balance Sheet'!ET120 | GA60: =+'Balance Sheet'!EU120 | GB60: =+'Balance Sheet'!EV120 | GC60: =+'Balance Sheet'!EW120 | GD60: =GD61 | GE60: =GE61 | GF60: =GF61 | GG60: ='Balance Sheet'!FA120 | GH60: ='Balance Sheet'!FB120 | GI60: ='Balance Sheet'!FC120 | GJ60: ='Balance Sheet'!FD120 | GK60: ='Balance Sheet'!FE120 | GL60: ='Balance Sheet'!FF120 | GM60: ='Balance Sheet'!FG120
B61: Shares outstanding (diluted) | M61: NA | R61: NA | V61: 30 | W61: NA | AB61: =AB60 | AG61: =2*1317.4 | AH61: 2665.2 | AI61: 2665.8 | AJ61: 2665.8 | AK61: 2664.4 | AL61: =+AQ61 | AM61: =2*1368.5 | AN61: =2*1368.8 | AO61: =2*1357.14285714286 | AP61: =2*1387.66519823789 | AQ61: =+AV61 | AR61: =2*1420.9 | AS61: =2*1419 | AT61: =2*1419 | AU61: =2*1420.4 | AV61: 2834.4 | AW61: =2*1419.7 | AX61: =2*1421.2 | AY61: =2*1419 | AZ61: =2*1419.5 | BA61: 2836.4 | BB61: 3087.1 | BC61: 3094.9 | BD61: 3113.4 | BE61: 3117.9 | BF61: 3099.2 | BG61: 3106.7 | BH61: 3110.5 | BI61: 3110.9 | BJ61: 3121.2 | BK61: 3099.3 | BL61: 3115.4 | BM61: 3069.3 | BN61: 3026.7 | BO61: 3023.7 | BP61: 3054.1 | BQ61: 3018.5 | BR61: 3015.9 | BS61: 3008.3 | BT61: 3005.4 | BU61: 3008.1 | BV61: 3004.6 | BW61: 3005.3 | BX61: 3009 | BY61: 3013.5 | BZ61: 3003.5 | CA61: 3023.7 | CB61: 3024.7 | CC61: 3017.1 | CD61: 3009.4 | CE61: 3012.5 | CF61: 2992.7 | CG61: 2974.4 | CH61: 2948.1 | CI61: 2930.7 | CJ61: 2961 | CK61: 2924.3 | CL61: 2922.5 | CM61: 2912.9 | CN61: 2889 | CO61: =+AVERAGE(CK61:CN61) | CP61: 2866.3 | CQ61: 2844.8 | CR61: 2831.3 | CS61: 2801.6 | CT61: 2835.6 | CU61: 2789.8 | CV61: 2782 | CW61: 2793 | CX61: 2796.5 | CY61: 2789.1 | CZ61: 2797.3 | DA61: 2796 | DB61: 2786.4 | DC61: 2781.6 | DD61: 2788.8 | DE61: 2772.7 | DF61: 2781.3 | DG61: 2778.2 | DH61: 2768.9 | DI61: 2775.3 | DJ61: 2774.9 | DK61: 2798.2 | DL61: 2818.1 | DM61: 2833.4 | DN61: 2812.6 | DO61: 2858.8 | DP61: 2893 | DQ61: 2881.2 | DR61: 2872 | DS61: =AVERAGE(DO61:DR61) | DT61: 2874.7 | DU61: 2874.2 | DV61: 2864.3 | DW61: 2845.3 | DX61: =AVERAGE(DT61:DW61) | DY61: 2826 | DZ61: 2812 | EA61: 2807.2 | EB61: 2803 | EC61: =AVERAGE(DY61:EB61) | ED61: 2795.4 | EE61: 2794.2 | EF61: 2785.4 | EG61: 2764.5 | EH61: 2788.9 | EI61: 2754.5 | EJ61: 2741.5 | EK61: 2737.7 | EL61: 2740.7 | EM61: 2745.3 | EN61: 2731.9 | EO61: 2721.3 | EP61: 2727.6 | EQ61: 2724 | ER61: 2728.7 | ES61: 2698.8 | ET61: 2697 | EU61: 2670 | EV61: 2669 | EW61: 2684.3 | EX61: 2671 | EY61: 2665.5 | EZ61: 2669.3 | FA61: 2669.2 | FB61: 2670.7 | FC61: 2672.7 | FD61: 2671.6 | FE61: 2674.9 | FF61: 2670.2 | FG61: 2674 | FH61: 2666.5 | FI61: 2668 | FJ61: 2661.3 | FK61: 2650.1 | FL61: =AVERAGE(FH61:FK61) | FM61: 2605.5 | FN61: 2625.7 | FO61: 2666.5 | FP61: 2667.9 | FQ61: 2661.3 | FR61: 2650.1 | FS61: 2663.9 | FT61: 2634.3 | FU61: 2625.7 | FV61: 2549.7 | FW61: 2430.7 | FX61: 2560.4 | FY61: 2430.1 | FZ61: 2422 | GA61: 2427.9 | GB61: 2427.1 | GC61: =+GC60 | GD61: 2423.8 | GE61: 2419.1 | GF61: 2428.6 | GG61: =GG60*GG62 | GH61: =AVERAGE(GD61:GG61) | GI61: =GI60*GI62 | GJ61: =GJ60*GJ62 | GK61: =GK60*GK62 | GL61: =GL60*GL62 | GM61: =GM60*GM62
B62: Dilution | AV62: =+AV61/AV60 | AW62: =+AW61/AW60 | AX62: =+AX61/AX60 | AY62: =+AY61/AY60 | AZ62: =+AZ61/AZ60 | BA62: =+BA61/BA60 | BB62: =+BB61/BB60 | BC62: =+BC61/BC60 | ... DH62: =+DH61/DH60 | DI62: =+DC62 | DJ62: =+DJ61/DJ60 | DK62: =+DK61/DK60 | DL62: =+DL61/DL60 | DM62: =+DM61/DM60 | DN62: =+DN61/DN60 | DO62: =+DO61/DO60 | DP62: =+DP61/DP60 | DQ62: =+DQ61/DQ60 | ... FV62: =+FV61/FV60 | FW62: =FV62 | FX62: 1 | FY62: =+FY61/FY60 | FZ62: =+FZ61/FZ60 | GA62: =+GA61/GA60 | GB62: =+GB61/GB60 | GC62: 1 | GE62: =+GE61/GE60 | GF62: =+GF61/GF60 | GG62: =GF62 | GH62: 1 | GI62: 1 | GJ62: 1 | GK62: 1 | GL62: 1 | GM62: 1
B64: Margins | FL64: =+FL59/FL55
B65: Gross Margin | E65: =(E24-E26)/E24 | F65: =(F24-F26)/F24 | G65: =(G24-G26)/G24 | AC65: =(AC24-AC26)/AC24 | AD65: =(AD24-AD26)/AD24 | AE65: =(AE24-AE26)/AE24 | AF65: =(AF24-AF26)/AF24 | AG65: =(AG24-AG26)/AG24 | AH65: =(AH24-AH26)/AH24 | AI65: =(AI24-AI26)/AI24 | AJ65: =(AJ24-AJ26)/AJ24 | ... CE65: =(CE24-CE26)/CE24 | CJ65: =(CJ24-CJ26)/CJ24 | CK65: =(CK24-CK26)/CK24 | CL65: =(CL24-CL26)/CL24 | CM65: =(CM24-CM26)/CM24 | CN65: =(CN24-CN26)/CN24 | CO65: =(CO24-CO26)/CO24 | CP65: =(CP24-CP26)/CP24 | CQ65: =(CQ24-CQ26)/CQ24 | ... DM65: =(DM24-DM26)/DM24 | DN65: 0.688 | DO65: =(DO24-DO26)/DO24 | DP65: =(DP24-DP26)/DP24 | DQ65: =(DQ24-DQ26)/DQ24 | DR65: =1-DR26/DR24 | DS65: =1-DS26/DS24 | DT65: =(DT24-DT26)/DT24 | DU65: =(DU24-DU26)/DU24 | DV65: =(DV24-DV26)/DV24 | DW65: =1-DW26/DW24 | DX65: =1-DX26/DX24 | DY65: =(DY24-DY26)/DY24 | DZ65: =(DZ24-DZ26)/DZ24 | EA65: =(EA24-EA26)/EA24 | EB65: =1-EB26/EB24 | EC65: =1-EC26/EC24 | ED65: =(ED24-ED26)/ED24 | EE65: =(EE24-EE26)/EE24 | EF65: =(EF24-EF26)/EF24 | EG65: =1-EG26/EG24 | EH65: =1-EH26/EH24 | EI65: =(EI24-EI26)/EI24 | EJ65: =(EJ24-EJ26)/EJ24 | EK65: =(EK24-EK26)/EK24 | EL65: =1-EL26/EL24 | EM65: =1-EM26/EM24 | EN65: =(EN24-EN26)/EN24 | EO65: =(EO24-EO26)/EO24 | EP65: =(EP24-EP26)/EP24 | EQ65: =1-EQ26/EQ24 | ER65: =1-ER26/ER24 | ES65: =(ES24-ES26)/ES24 | ET65: =(ET24-ET26)/ET24 | EU65: =(EU24-EU26)/EU24 | EV65: =1-EV26/EV24 | EW65: =1-EW26/EW24 | EX65: =(EX24-EX26)/EX24 | EY65: =(EY24-EY26)/EY24 | EZ65: =(EZ24-EZ26)/EZ24 | FA65: =1-FA26/FA24 | FB65: =1-FB26/FB24 | FC65: =(FC24-FC26)/FC24 | FD65: =(FD24-FD26)/FD24 | FE65: =(FE24-FE26)/FE24 | FF65: =1-FF26/FF24 | FG65: =1-FG26/FG24 | FH65: =(FH24-FH26)/FH24 | FI65: =(FI24-FI26)/FI24 | FJ65: =(FJ24-FJ26)/FJ24 | FK65: =1-FK26/FK24 | FL65: =1-FL26/FL24 | FM65: =(FM24-FM26)/FM24 | FN65: =(FN24-FN26)/FN24 | FO65: =(FO24-FO26)/FO24 | FP65: =(FP24-FP26)/FP24 | FQ65: =(FQ24-FQ26)/FQ24 | FR65: =1-FR26/FR24 | FS65: =1-FS26/FS24 | FT65: =(FT24-FT26)/FT24 | FU65: =(FU24-FU26)/FU24 | FV65: =(FV24-FV26)/FV24 | FW65: =1-FW26/FW24 | FX65: =1-FX26/FX24 | FY65: =1-FY26/FY24 | FZ65: =1-FZ26/FZ24 | GA65: =1-GA26/GA24 | GB65: =1-GB26/GB24 | GC65: =1-GC26/GC24 | GD65: =1-GD26/GD24 | ... GF65: =1-GF26/GF24 | GG65: 0.735 | GH65: =1-GH26/GH24 | GI65: 0.731 | GJ65: 0.734 | GK65: 0.737 | GL65: 0.737 | GM65: 0.737
B66: SG&A | E66: =E27/E24 | F66: =F27/F24 | G66: =G27/G24 | AC66: =AC27/AC24 | AD66: =AD27/AD24 | AE66: =AE27/AE24 | AF66: =AF27/AF24 | AG66: =AG27/AG24 | AH66: =AH27/AH24 | AI66: =AI27/AI24 | AJ66: =AJ27/AJ24 | ... DM66: =DM27/DM24 | DN66: 0.314 | DO66: =DO27/DO24 | DP66: =DP27/DP24 | DQ66: =DQ27/DQ24 | DR66: =DR27/DR24 | DS66: =DS27/DS24 | DT66: =DT27/DT24 | DU66: =DU27/DU24 | DV66: =DV27/DV24 | ... GG66: =GG27/GG24 | GH66: 0.248 | GI66: 0.242 | GJ66: 0.232 | GK66: 0.232 | GL66: 0.232 | GM66: 0.232
B67: Research | E67: =E28/E24 | F67: =F28/F24 | G67: =G28/G24 | AC67: =AC28/AC24 | AD67: =AD28/AD24 | AE67: =AE28/AE24 | AF67: =AF28/AF24 | AG67: =AG28/AG24 | AH67: =AH28/AH24 | AI67: =AI28/AI24 | AJ67: =AJ28/AJ24 | ... DM67: =DM28/DM24 | DN67: 0.1125 | DO67: =DO28/DO24 | DP67: =DP28/DP24 | DQ67: =DQ28/DQ24 | DR67: =DR28/DR24 | DS67: =DS28/DS24 | DT67: =DT28/DT24 | DU67: =DU28/DU24 | DV67: =DV28/DV24 | ... GG67: =GG28/GG24 | GH67: 0.155 | GI67: 0.157 | GJ67: 0.154 | GK67: 0.153 | GL67: 0.153 | GM67: 0.153
B68: Operating Margin | E68: =E29/E24 | F68: =F29/F24 | G68: =G29/G24 | AC68: =AC29/AC24 | AD68: =AD29/AD24 | AE68: =AE29/AE24 | AF68: =AF29/AF24 | AG68: =AG29/AG24 | AH68: =AH29/AH24 | AI68: =AI29/AI24 | AJ68: =AJ29/AJ24 | ... GM68: =GM29/GM24
B69: EBIT Margin | FG69: =FG29/FG24 | FH69: =FH29/FH24 | FI69: =FI29/FI24 | FJ69: =FJ29/FJ24 | FK69: =FK29/FK24 | FL69: =FL29/FL24 | FM69: =FM29/FM24 | FN69: =FN29/FN24 | ... GM69: =GM29/GM24
B70: Pretax Income Margin | E70: =E39/E24 | F70: =F39/F24 | G70: =G39/G24 | AC70: =AC39/AC24 | AD70: =AD39/AD24 | AE70: =AE39/AE24 | AF70: =AF39/AF24 | AG70: =AG39/AG24 | AH70: =AH39/AH24 | AI70: =AI39/AI24 | AJ70: =AJ39/AJ24 | ... AQ70: =AQ39/AQ24 | AR70: =AR38/AR24 | AS70: =AS38/AS24 | AT70: =AT38/AT24 | AU70: =AU38/AU24 | AV70: =AV38/AV24 | AW70: =AW38/AW24 | AX70: =AX38/AX24 | AY70: =AY38/AY24 | AZ70: =AZ38/AZ24 | BA70: =BA39/BA24 | BB70: =BB38/BB24 | BC70: =BC38/BC24 | BD70: =BD38/BD24 | BE70: =BE38/BE24 | BF70: =BF39/BF24 | BG70: =BG38/BG24 | BH70: =BH38/BH24 | BI70: =BI38/BI24 | BJ70: =BJ38/BJ24 | BK70: =BK38/BK24 | BL70: =BL38/BL24 | BM70: =BM38/BM24 | BN70: =BN38/BN24 | ... CF70: =CF38/CF24 | CG70: =CG39/CG24 | CH70: =CH39/CH24 | CI70: =CI38/CI24 | CJ70: =CJ38/CJ24 | CK70: =CK38/CK24 | CL70: =CL38/CL24 | CM70: =CM38/CM24 | CN70: =CN38/CN24 | CO70: =CO38/CO24 | CP70: =CP38/CP24 | ... GM70: =GM38/GM24
B71: Tax rate | E71: =E41/E39 | F71: =F41/F39 | G71: =G41/G39 | AC71: =AC41/AC39 | AD71: =AD41/AD39 | AE71: =AE41/AE39 | AF71: =AF41/AF39 | AG71: =AG41/AG39 | AH71: =AH41/AH39 | AI71: =AI41/AI39 | AJ71: =AJ41/AJ39 | ... AU71: =AU41/AU39 | AV71: =AV41/AV38 | AW71: =AW41/AW39 | AX71: =AX41/AX39 | AY71: =AY41/AY39 | AZ71: =AZ41/AZ39 | BA71: =BA41/BA39 | BB71: =BB41/BB39 | BC71: =BC41/BC39 | BD71: =BD41/BD39 | ... BF71: =BF41/BF39 | BG71: =BG41/BG38 | BH71: =BH41/BH38 | BI71: =BI41/BI38 | BJ71: =BJ41/BJ38 | BK71: =BK41/BK38 | BL71: =BL41/BL38 | BM71: =BM41/BM38 | BN71: =BN41/BN38 | ... BS71: =BS41/BS38 | BT71: =BT41/BT39 | BU71: =BU41/BU38 | BV71: =BV41/BV39 | BW71: =BW41/BW39 | BX71: =BX41/BX39 | BY71: =BY41/BY38 | BZ71: =BZ41/BZ38 | CA71: =CA41/CA38 | CB71: =CB41/CB38 | CC71: =CC41/CC38 | CD71: =CD41/CD38 | CE71: =CE41/CE38 | CF71: =CF41/CF38 | ... GG71: =GG41/GG38 | GH71: 0.1775 | GI71: =+GH71 | GJ71: =+GI71 | GK71: =+GJ71 | GL71: =+GK71 | GM71: =+GL71
B72: Net Margin | E72: =E49/E24 | F72: =F49/F24 | G72: =G49/G24 | AC72: =AC49/AC24 | AD72: =AD49/AD24 | AE72: =AE49/AE24 | AF72: =AF49/AF24 | AG72: =AG49/AG24 | AH72: =AH49/AH24 | AI72: =AI49/AI24 | AJ72: =AJ49/AJ24 | ... AP72: =AP49/AP24 | AQ72: =AQ43/AQ24 | AR72: =AR43/AR24 | AS72: =AS43/AS24 | AT72: =AT43/AT24 | AU72: =AU43/AU24 | AV72: =AV43/AV24 | AW72: =AW43/AW24 | AX72: =AX43/AX24 | ... GM72: =GM43/GM24
B74: Growth | X74: =#REF!/X27
B75: Sales | M75: =IF(ISNUMBER(M24/H24-1),M24/H24-1,"NM") | N75: =IF(ISNUMBER(N24/I24-1),N24/I24-1,"NM") | O75: =IF(ISNUMBER(O24/J24-1),O24/J24-1,"NM") | P75: =IF(ISNUMBER(P24/K24-1),P24/K24-1,"NM") | Q75: =IF(ISNUMBER(Q24/L24-1),Q24/L24-1,"NM") | R75: =IF(ISNUMBER(R24/M24-1),R24/M24-1,"NM") | S75: =IF(ISNUMBER(S24/N24-1),S24/N24-1,"NM") | T75: =IF(ISNUMBER(T24/O24-1),T24/O24-1,"NM") | ... FN75: =IF(ISNUMBER(FN24/FI24-1),FN24/FI24-1,"NM") | FT75: =IF(ISNUMBER(FT16/FO16-1),FT16/FO16-1,"NM") | FU75: =IF(ISNUMBER(FU16/FP16-1),FU16/FP16-1,"NM") | FV75: =IF(ISNUMBER(FV16/FQ16-1),FV16/FQ16-1,"NM") | FW75: =IF(ISNUMBER(FW16/FR16-1),FW16/FR16-1,"NM") | FX75: =IF(ISNUMBER(FX16/FS16-1),FX16/FS16-1,"NM") | FY75: =IF(ISNUMBER((FY24-'Sales Model'!DZ1653)/(FT24-'Sales Model'!DU1653)-1),(FY24-'Sales Model'!DZ1653)/(FT24-'Sales Model'!DU1653)-1,"NM") | FZ75: =IF(ISNUMBER((FZ24-'Sales Model'!EA1653)/(FU24-'Sales Model'!DV1653)-1),(FZ24-'Sales Model'!EA1653)/(FU24-'Sales Model'!DV1653)-1,"NM") | GA75: =IF(ISNUMBER((GA24-'Sales Model'!EB1653)/(FV24-'Sales Model'!DW1653)-1),(GA24-'Sales Model'!EB1653)/(FV24-'Sales Model'!DW1653)-1,"NM") | GB75: =IF(ISNUMBER((GB24-'Sales Model'!EC1653)/(FW24-'Sales Model'!DX1653)-1),(GB24-'Sales Model'!EC1653)/(FW24-'Sales Model'!DX1653)-1,"NM") | GC75: =IF(ISNUMBER((GC24-'Sales Model'!ED1653)/(FX24-'Sales Model'!DY1653)-1),(GC24-'Sales Model'!ED1653)/(FX24-'Sales Model'!DY1653)-1,"NM") | GD75: =IF(ISNUMBER((GD24-'Sales Model'!EE1653)/(FY24-'Sales Model'!DZ1653)-1),(GD24-'Sales Model'!EE1653)/(FY24-'Sales Model'!DZ1653)-1,"NM") | GE75: =IF(ISNUMBER((GE24-'Sales Model'!EF1653)/(FZ24-'Sales Model'!EA1653)-1),(GE24-'Sales Model'!EF1653)/(FZ24-'Sales Model'!EA1653)-1,"NM") | GF75: =IF(ISNUMBER((GF24-'Sales Model'!EG1653)/(GA24-'Sales Model'!EB1653)-1),(GF24-'Sales Model'!EG1653)/(GA24-'Sales Model'!EB1653)-1,"NM") | GG75: 0.074370028 | GH75: =IF(ISNUMBER(GH24/GC24-1),GH24/GC24-1,"NM") | GI75: =IF(ISNUMBER(GI24/GH24-1),GI24/GH24-1,"NM") | GJ75: =IF(ISNUMBER(GJ24/GI24-1),GJ24/GI24-1,"NM") | GK75: =IF(ISNUMBER(GK24/GJ24-1),GK24/GJ24-1,"NM") | GL75: =IF(ISNUMBER(GL24/GK24-1),GL24/GK24-1,"NM") | GM75: =IF(ISNUMBER(GM24/GL24-1),GM24/GL24-1,"NM")
B76: Cost of Goods Sold | M76: =IF(ISNUMBER(M26/H26-1),M26/H26-1,"NM") | N76: =IF(ISNUMBER(N26/I26-1),N26/I26-1,"NM") | O76: =IF(ISNUMBER(O26/J26-1),O26/J26-1,"NM") | P76: =IF(ISNUMBER(P26/K26-1),P26/K26-1,"NM") | Q76: =IF(ISNUMBER(Q26/L26-1),Q26/L26-1,"NM") | R76: =IF(ISNUMBER(R26/M26-1),R26/M26-1,"NM") | S76: =IF(ISNUMBER(S26/N26-1),S26/N26-1,"NM") | T76: =IF(ISNUMBER(T26/O26-1),T26/O26-1,"NM") | ... FN76: =IF(ISNUMBER(FN26/FI26-1),FN26/FI26-1,"NM") | FT76: =IF(ISNUMBER(FT26/FO26-1),FT26/FO26-1,"NM") | FU76: =IF(ISNUMBER(FU26/FP26-1),FU26/FP26-1,"NM") | FV76: =IF(ISNUMBER(FV26/FQ26-1),FV26/FQ26-1,"NM") | FW76: =IF(ISNUMBER(FW26/FR26-1),FW26/FR26-1,"NM") | FX76: =IF(ISNUMBER(FX26/FS26-1),FX26/FS26-1,"NM") | FY76: =IF(ISNUMBER(FY26/FT26-1),FY26/FT26-1,"NM") | FZ76: =IF(ISNUMBER(FZ26/FU26-1),FZ26/FU26-1,"NM") | GA76: =IF(ISNUMBER(GA26/FV26-1),GA26/FV26-1,"NM") | ... GH76: =IF(ISNUMBER(GH26/GC26-1),GH26/GC26-1,"NM") | GI76: =IF(ISNUMBER(GI26/GH26-1),GI26/GH26-1,"NM") | GJ76: =IF(ISNUMBER(GJ26/GI26-1),GJ26/GI26-1,"NM") | GK76: =IF(ISNUMBER(GK26/GJ26-1),GK26/GJ26-1,"NM") | GL76: =IF(ISNUMBER(GL26/GK26-1),GL26/GK26-1,"NM") | GM76: =IF(ISNUMBER(GM26/GL26-1),GM26/GL26-1,"NM")
B77: SG&A | M77: =IF(ISNUMBER(M27/H27-1),M27/H27-1,"NM") | N77: =IF(ISNUMBER(N27/I27-1),N27/I27-1,"NM") | O77: =IF(ISNUMBER(O27/J27-1),O27/J27-1,"NM") | P77: =IF(ISNUMBER(P27/K27-1),P27/K27-1,"NM") | Q77: =IF(ISNUMBER(Q27/L27-1),Q27/L27-1,"NM") | R77: =IF(ISNUMBER(R27/M27-1),R27/M27-1,"NM") | S77: =IF(ISNUMBER(S27/N27-1),S27/N27-1,"NM") | T77: =IF(ISNUMBER(T27/O27-1),T27/O27-1,"NM") | ... FN77: =IF(ISNUMBER(FN27/FI27-1),FN27/FI27-1,"NM") | FT77: =IF(ISNUMBER(FT27/FO27-1),FT27/FO27-1,"NM") | FU77: =IF(ISNUMBER(FU27/FP27-1),FU27/FP27-1,"NM") | FV77: =IF(ISNUMBER(FV27/FQ27-1),FV27/FQ27-1,"NM") | FW77: =IF(ISNUMBER(FW27/FR27-1),FW27/FR27-1,"NM") | FX77: =IF(ISNUMBER(FX27/FS27-1),FX27/FS27-1,"NM") | FY77: =IF(ISNUMBER(FY27/FT27-1),FY27/FT27-1,"NM") | FZ77: =IF(ISNUMBER(FZ27/FU27-1),FZ27/FU27-1,"NM") | GA77: =IF(ISNUMBER(GA27/FV27-1),GA27/FV27-1,"NM") | ... GH77: =IF(ISNUMBER(GH27/GC27-1),GH27/GC27-1,"NM") | GI77: =IF(ISNUMBER(GI27/GH27-1),GI27/GH27-1,"NM") | GJ77: =IF(ISNUMBER(GJ27/GI27-1),GJ27/GI27-1,"NM") | GK77: =IF(ISNUMBER(GK27/GJ27-1),GK27/GJ27-1,"NM") | GL77: =IF(ISNUMBER(GL27/GK27-1),GL27/GK27-1,"NM") | GM77: =IF(ISNUMBER(GM27/GL27-1),GM27/GL27-1,"NM")
B78: R&D | M78: =IF(ISNUMBER(M28/H28-1),M28/H28-1,"NM") | N78: =IF(ISNUMBER(N28/I28-1),N28/I28-1,"NM") | O78: =IF(ISNUMBER(O28/J28-1),O28/J28-1,"NM") | P78: =IF(ISNUMBER(P28/K28-1),P28/K28-1,"NM") | Q78: =IF(ISNUMBER(Q28/L28-1),Q28/L28-1,"NM") | R78: =IF(ISNUMBER(R28/M28-1),R28/M28-1,"NM") | S78: =IF(ISNUMBER(S28/N28-1),S28/N28-1,"NM") | T78: =IF(ISNUMBER(T28/O28-1),T28/O28-1,"NM") | ... FN78: =IF(ISNUMBER(FN28/FI28-1),FN28/FI28-1,"NM") | FT78: =IF(ISNUMBER(FT28/FO28-1),FT28/FO28-1,"NM") | FU78: =IF(ISNUMBER(FU28/FP28-1),FU28/FP28-1,"NM") | FV78: =IF(ISNUMBER(FV28/FQ28-1),FV28/FQ28-1,"NM") | FW78: =IF(ISNUMBER(FW28/FR28-1),FW28/FR28-1,"NM") | FX78: =IF(ISNUMBER(FX28/FS28-1),FX28/FS28-1,"NM") | FY78: =IF(ISNUMBER(FY28/FT28-1),FY28/FT28-1,"NM") | FZ78: =IF(ISNUMBER(FZ28/FU28-1),FZ28/FU28-1,"NM") | GA78: =IF(ISNUMBER(GA28/FV28-1),GA28/FV28-1,"NM") | ... GH78: =IF(ISNUMBER(GH28/GC28-1),GH28/GC28-1,"NM") | GI78: =IF(ISNUMBER(GI28/GH28-1),GI28/GH28-1,"NM") | GJ78: =IF(ISNUMBER(GJ28/GI28-1),GJ28/GI28-1,"NM") | GK78: =IF(ISNUMBER(GK28/GJ28-1),GK28/GJ28-1,"NM") | GL78: =IF(ISNUMBER(GL28/GK28-1),GL28/GK28-1,"NM") | GM78: =IF(ISNUMBER(GM28/GL28-1),GM28/GL28-1,"NM")
B79: Operating Income | M79: =IF(ISNUMBER(M29/H29-1),M29/H29-1,"NM") | N79: =IF(ISNUMBER(N29/I29-1),N29/I29-1,"NM") | O79: =IF(ISNUMBER(O29/J29-1),O29/J29-1,"NM") | P79: =IF(ISNUMBER(P29/K29-1),P29/K29-1,"NM") | Q79: =IF(ISNUMBER(Q29/L29-1),Q29/L29-1,"NM") | R79: =IF(ISNUMBER(R29/M29-1),R29/M29-1,"NM") | S79: =IF(ISNUMBER(S29/N29-1),S29/N29-1,"NM") | T79: =IF(ISNUMBER(T29/O29-1),T29/O29-1,"NM") | ... FN79: =IF(ISNUMBER(FN29/FI29-1),FN29/FI29-1,"NM") | FT79: =IF(ISNUMBER(FT29/FO29-1),FT29/FO29-1,"NM") | FU79: =IF(ISNUMBER(FU29/FP29-1),FU29/FP29-1,"NM") | FV79: =IF(ISNUMBER(FV29/FQ29-1),FV29/FQ29-1,"NM") | FW79: =IF(ISNUMBER(FW29/FR29-1),FW29/FR29-1,"NM") | FX79: =IF(ISNUMBER(FX29/FS29-1),FX29/FS29-1,"NM") | FY79: =IF(ISNUMBER(FY29/FT29-1),FY29/FT29-1,"NM") | FZ79: =IF(ISNUMBER(FZ29/FU29-1),FZ29/FU29-1,"NM") | GA79: =IF(ISNUMBER(GA29/FV29-1),GA29/FV29-1,"NM") | ... GH79: =IF(ISNUMBER(GH29/GC29-1),GH29/GC29-1,"NM") | GI79: =IF(ISNUMBER(GI29/GH29-1),GI29/GH29-1,"NM") | GJ79: =IF(ISNUMBER(GJ29/GI29-1),GJ29/GI29-1,"NM") | GK79: =IF(ISNUMBER(GK29/GJ29-1),GK29/GJ29-1,"NM") | GL79: =IF(ISNUMBER(GL29/GK29-1),GL29/GK29-1,"NM") | GM79: =IF(ISNUMBER(GM29/GL29-1),GM29/GL29-1,"NM")
B80: Pretax Income (cont ops) | M80: =IF(ISNUMBER(M38/H38-1),M38/H38-1,"NM") | N80: =IF(ISNUMBER(N38/I38-1),N38/I38-1,"NM") | O80: =IF(ISNUMBER(O38/J38-1),O38/J38-1,"NM") | P80: =IF(ISNUMBER(P38/K38-1),P38/K38-1,"NM") | Q80: =IF(ISNUMBER(Q38/L38-1),Q38/L38-1,"NM") | R80: =IF(ISNUMBER(R38/M38-1),R38/M38-1,"NM") | S80: =IF(ISNUMBER(S38/N38-1),S38/N38-1,"NM") | T80: =IF(ISNUMBER(T38/O38-1),T38/O38-1,"NM") | ... FN80: =IF(ISNUMBER(FN38/FI38-1),FN38/FI38-1,"NM") | FT80: =IF(ISNUMBER(FT38/FO38-1),FT38/FO38-1,"NM") | FU80: =IF(ISNUMBER(FU38/FP38-1),FU38/FP38-1,"NM") | FV80: =IF(ISNUMBER(FV38/FQ38-1),FV38/FQ38-1,"NM") | FW80: =IF(ISNUMBER(FW38/FR38-1),FW38/FR38-1,"NM") | FX80: =IF(ISNUMBER(FX38/FS38-1),FX38/FS38-1,"NM") | FY80: =IF(ISNUMBER(FY38/FT38-1),FY38/FT38-1,"NM") | FZ80: =IF(ISNUMBER(FZ38/FU38-1),FZ38/FU38-1,"NM") | GA80: =IF(ISNUMBER(GA38/FV38-1),GA38/FV38-1,"NM") | ... GH80: =IF(ISNUMBER(GH38/GC38-1),GH38/GC38-1,"NM") | GI80: =IF(ISNUMBER(GI38/GH38-1),GI38/GH38-1,"NM") | GJ80: =IF(ISNUMBER(GJ38/GI38-1),GJ38/GI38-1,"NM") | GK80: =IF(ISNUMBER(GK38/GJ38-1),GK38/GJ38-1,"NM") | GL80: =IF(ISNUMBER(GL38/GK38-1),GL38/GK38-1,"NM") | GM80: =IF(ISNUMBER(GM38/GL38-1),GM38/GL38-1,"NM")
B81: Net Income (cont ops, incl ESO) | M81: =IF(ISNUMBER(M43/H43-1),M43/H43-1,"NM") | N81: =IF(ISNUMBER(N43/I43-1),N43/I43-1,"NM") | O81: =IF(ISNUMBER(O43/J43-1),O43/J43-1,"NM") | P81: =IF(ISNUMBER(P43/K43-1),P43/K43-1,"NM") | Q81: =IF(ISNUMBER(Q43/L43-1),Q43/L43-1,"NM") | R81: =IF(ISNUMBER(R43/M43-1),R43/M43-1,"NM") | S81: =IF(ISNUMBER(S43/N43-1),S43/N43-1,"NM") | T81: =IF(ISNUMBER(T43/O43-1),T43/O43-1,"NM") | ... FN81: =IF(ISNUMBER(FN43/FI43-1),FN43/FI43-1,"NM") | FT81: =IF(ISNUMBER(FT43/FO43-1),FT43/FO43-1,"NM") | FU81: =IF(ISNUMBER(FU43/FP43-1),FU43/FP43-1,"NM") | FV81: =IF(ISNUMBER(FV43/FQ43-1),FV43/FQ43-1,"NM") | FW81: =IF(ISNUMBER(FW43/FR43-1),FW43/FR43-1,"NM") | FX81: =IF(ISNUMBER(FX43/FS43-1),FX43/FS43-1,"NM") | FY81: =IF(ISNUMBER(FY43/FT43-1),FY43/FT43-1,"NM") | FZ81: =IF(ISNUMBER(FZ43/FU43-1),FZ43/FU43-1,"NM") | GA81: =IF(ISNUMBER(GA43/FV43-1),GA43/FV43-1,"NM") | ... GH81: =IF(ISNUMBER(GH43/GC43-1),GH43/GC43-1,"NM") | GI81: =IF(ISNUMBER(GI43/GH43-1),GI43/GH43-1,"NM") | GJ81: =IF(ISNUMBER(GJ43/GI43-1),GJ43/GI43-1,"NM") | GK81: =IF(ISNUMBER(GK43/GJ43-1),GK43/GJ43-1,"NM") | GL81: =IF(ISNUMBER(GL43/GK43-1),GL43/GK43-1,"NM") | GM81: =IF(ISNUMBER(GM43/GL43-1),GM43/GL43-1,"NM")
B82: Diluted EPS (cont ops, incl ESO) | M82: =IF(ISNUMBER(M55/H55-1),M55/H55-1,"NM") | N82: =IF(ISNUMBER(N55/I55-1),N55/I55-1,"NM") | O82: =IF(ISNUMBER(O55/J55-1),O55/J55-1,"NM") | P82: =IF(ISNUMBER(P55/K55-1),P55/K55-1,"NM") | Q82: =IF(ISNUMBER(Q55/L55-1),Q55/L55-1,"NM") | R82: =IF(ISNUMBER(R55/M55-1),R55/M55-1,"NM") | S82: =IF(ISNUMBER(S55/N55-1),S55/N55-1,"NM") | T82: =IF(ISNUMBER(T55/O55-1),T55/O55-1,"NM") | ... FN82: =IF(ISNUMBER(FN55/FI55-1),FN55/FI55-1,"NM") | FT82: =IF(ISNUMBER(FT55/FO55-1),FT55/FO55-1,"NM") | FU82: =IF(ISNUMBER(FU55/FP55-1),FU55/FP55-1,"NM") | FV82: =IF(ISNUMBER(FV55/FQ55-1),FV55/FQ55-1,"NM") | FW82: =IF(ISNUMBER(FW55/FR55-1),FW55/FR55-1,"NM") | FX82: =IF(ISNUMBER(FX55/FS55-1),FX55/FS55-1,"NM") | FY82: =IF(ISNUMBER(FY55/FT55-1),FY55/FT55-1,"NM") | FZ82: =IF(ISNUMBER(FZ55/FU55-1),FZ55/FU55-1,"NM") | GA82: =IF(ISNUMBER(GA55/FV55-1),GA55/FV55-1,"NM") | ... GH82: =IF(ISNUMBER(GH55/GC55-1),GH55/GC55-1,"NM") | GI82: =IF(ISNUMBER(GI55/GH55-1),GI55/GH55-1,"NM") | GJ82: =IF(ISNUMBER(GJ55/GI55-1),GJ55/GI55-1,"NM") | GK82: =IF(ISNUMBER(GK55/GJ55-1),GK55/GJ55-1,"NM") | GL82: =IF(ISNUMBER(GL55/GK55-1),GL55/GK55-1,"NM") | GM82: =IF(ISNUMBER(GM55/GL55-1),GM55/GL55-1,"NM")
BA83: =+BA82-BA81 | BB83: =+BB82-BB81 | BC83: =+BC82-BC81 | BD83: =+BD82-BD81 | BE83: =+BE82-BE81 | BF83: =+BF82-BF81 | BG83: =+BG82-BG81 | BH83: =+BH82-BH81 | ... FN83: =+FN82-FN81 | FT83: =+FT82-FT81 | FU83: =+FU82-FU81 | FV83: =+FV82-FV81 | FW83: =+FW82-FW81 | FX83: =+FX82-FX81 | FY83: =+FY82-FY81 | FZ83: =+FZ82-FZ81 | GA83: =+GA82-GA81 | ... GM83: =+GM82-GM81
B84: Earnings Growth/Sales Growth Ratio | EH84: =EH81/EH75 | EI84: =EI81/EI75 | EJ84: =EJ81/EJ75 | EK84: =EK81/EK75 | EL84: =EL81/EL75 | EM84: =EM81/EM75 | EN84: =EN81/EN75 | EO84: =EO81/EO75 | ... FN84: =FN81/FN75 | FT84: =FT81/FT75 | FU84: =FU81/FU75 | FV84: =FV81/FV75 | FW84: =FW81/FW75 | FX84: =FX81/FX75 | FY84: =FY81/FY75 | FZ84: =FZ81/FZ75 | GA84: =GA81/GA75 | ... GM84: =GM81/GM75
B86: Sales Breakdown
B87: Consumer
B88: Domestic | H88: 2089 | I88: 658 | J88: 575 | K88: 661 | L88: =M88-SUM(I88:K88) | M88: 2460 | N88: 700 | O88: 601 | P88: 683 | Q88: =R88-N88-O88-P88 | R88: 2608 | S88: 702 | T88: 608 | U88: 682 | V88: 639 | W88: =S88+T88+U88+V88 | X88: 670 | Y88: 624 | Z88: 714 | AA88: 684 | AB88: 2692 | AC88: 729 | AD88: 685 | AE88: 717 | AF88: 727 | AG88: 2858 | AH88: 825 | AI88: 717 | AJ88: 800 | AK88: 823 | AL88: 3166 | AM88: 832 | AN88: 767 | AO88: 801 | AP88: 841 | AQ88: 3240 | AR88: 840 | AS88: 753 | AT88: 806 | AU88: 927 | AV88: =+'Sales Model'!D56 | AW88: =+'Sales Model'!E56 | AX88: =+'Sales Model'!F56 | AY88: =+'Sales Model'!G56 | AZ88: =+'Sales Model'!H56 | BA88: =+'Sales Model'!I56 | BB88: =+'Sales Model'!J56 | BC88: =+'Sales Model'!K56 | ... FN88: =+'Sales Model'!DV56
B89: International | H89: 2123 | I89: 527 | J89: 538 | K89: 532 | L89: =M89-SUM(I89:K89) | M89: 2124 | N89: 532 | O89: 564 | P89: 556 | Q89: =R89-N89-O89-P89 | R89: 2172 | S89: 575 | T89: 576 | U89: 533 | V89: 509 | W89: =S89+T89+U89+V89 | X89: 609 | Y89: 646 | Z89: 660 | AA89: 644 | AB89: 2559 | AC89: 707 | AD89: 784 | AE89: 744 | AF89: 738 | AG89: 2973 | AH89: 825 | AI89: 827 | AJ89: 783 | AK89: 795 | AL89: 3198 | AM89: 852 | AN89: 845 | AO89: 783 | AP89: 777 | AQ89: 3258 | AR89: 799 | AS89: 818 | AT89: 781 | AU89: 804 | AV89: =+'Sales Model'!D57 | AW89: =+'Sales Model'!E57 | AX89: =+'Sales Model'!F57 | AY89: =+'Sales Model'!G57 | AZ89: =+'Sales Model'!H57 | BA89: =+'Sales Model'!I57 | BB89: =+'Sales Model'!J57 | BC89: =+'Sales Model'!K57 | ... FN89: =+'Sales Model'!DV57
B90: Total | H90: =SUM(H88:H89) | I90: =SUM(I88:I89) | J90: =SUM(J88:J89) | K90: =SUM(K88:K89) | L90: =SUM(L88:L89) | M90: =SUM(M88:M89) | N90: =SUM(N88:N89) | O90: =SUM(O88:O89) | ... FN90: =SUM(FN88:FN89)
B91: Innovative Medicine
B92: US | H92: 1316 | I92: 392 | J92: 361 | K92: 396 | L92: =M92-SUM(I92:K92) | M92: 1532 | N92: 386 | O92: 391 | P92: 406 | Q92: =R92-N92-O92-P92 | R92: 1652 | S92: 429 | T92: 428 | U92: 458 | V92: 460 | W92: =S92+T92+U92+V92 | X92: 496 | Y92: 541 | Z92: 554 | AA92: 552 | AB92: 2143 | AC92: 607 | AD92: 659 | AE92: 702 | AF92: 729 | AG92: 2697 | AH92: 792 | AI92: 823 | AJ92: 864 | AK92: 877 | AL92: 3355 | AM92: 960 | AN92: 935 | AO92: 993 | AP92: 988 | AQ92: 3877 | AR92: 1169 | AS92: 1178 | AT92: 1226 | AU92: 1299 | AV92: =+'Sales Model'!D34 | AW92: =+'Sales Model'!E34 | AX92: =+'Sales Model'!F34 | AY92: =+'Sales Model'!G34 | AZ92: =+'Sales Model'!H34 | BA92: =+'Sales Model'!I34 | BB92: =+'Sales Model'!J34 | BC92: =+'Sales Model'!K34 | ... FN92: =+'Sales Model'!DV34 | FO92: =+FH92 | FP92: =+FI92 | FQ92: =+FJ92 | FR92: =+FK92 | FS92: =+FL92 | FT92: =+FM92 | FU92: =+FN92 | FV92: =+'Sales Model'!DW34 | FW92: =+'Sales Model'!DX34 | FX92: =+'Sales Model'!DY34 | FY92: =+'Sales Model'!DZ34 | FZ92: =+'Sales Model'!EA34 | GA92: =+'Sales Model'!EB34 | GB92: =+'Sales Model'!EC34 | GC92: =+'Sales Model'!ED34 | ... GM92: =+'Sales Model'!EN34
B93: International | H93: 1987 | I93: 572 | J93: 554 | K93: 547 | L93: =M93-SUM(I93:K93) | M93: 2263 | N93: 645 | O93: 692 | P93: 687 | Q93: =R93-N93-O93-P93 | R93: 2688 | S93: 683 | T93: 691 | U93: 653 | V93: 688 | W93: =S93+T93+U93+V93 | X93: 694 | Y93: 767 | Z93: 793 | AA93: 761 | AB93: 3015 | AC93: 876 | AD93: 961 | AE93: 896 | AF93: 844 | AG93: 3577 | AH93: 970 | AI93: 985 | AJ93: 953 | AK93: 924 | AL93: 3833 | AM93: 983 | AN93: 999 | AO93: 925 | AP93: 912 | AQ93: 3819 | AR93: 923 | AS93: 984 | AT93: 959 | AU93: 1014 | AV93: =+'Sales Model'!D35 | AW93: =+'Sales Model'!E35 | AX93: =+'Sales Model'!F35 | AY93: =+'Sales Model'!G35 | AZ93: =+'Sales Model'!H35 | BA93: =+'Sales Model'!I35 | BB93: =+'Sales Model'!J35 | BC93: =+'Sales Model'!K35 | ... FN93: =+'Sales Model'!DV35 | FO93: =+FH93 | FP93: =+FI93 | FQ93: =+FJ93 | FR93: =+FK93 | FS93: =+FL93 | FT93: =+FM93 | FU93: =+FN93 | FV93: =+'Sales Model'!DW35 | FW93: =+'Sales Model'!DX35 | FX93: =+'Sales Model'!DY35 | FY93: =+'Sales Model'!DZ35 | FZ93: =+'Sales Model'!EA35 | GA93: =+'Sales Model'!EB35 | GB93: =+'Sales Model'!EC35 | GC93: =+'Sales Model'!ED35 | ... GM93: =+'Sales Model'!EN35
B94: Total | H94: =SUM(H92:H93) | I94: =SUM(I92:I93) | J94: =SUM(J92:J93) | K94: =SUM(K92:K93) | L94: =SUM(L92:L93) | M94: =SUM(M92:M93) | N94: =SUM(N92:N93) | O94: =SUM(O92:O93) | ... GM94: =SUM(GM92:GM93)
B95: MedTech
B96: US | H96: 2022 | I96: 532 | J96: 558 | K96: 553 | L96: =M96-SUM(I96:K96) | M96: 2256 | N96: 603 | O96: 654 | P96: 658 | Q96: =R96-N96-O96-P96 | R96: 2643 | S96: 669 | T96: 712 | U96: 698 | V96: 718 | W96: =S96+T96+U96+V96 | X96: 681 | Y96: 744 | Z96: 734 | AA96: 818 | AB96: 2977 | AC96: 840 | AD96: 886 | AE96: 916 | AF96: 993 | AG96: 3635 | AH96: 1035 | AI96: 1097 | AJ96: 1126 | AK96: 1120 | AL96: =SUM(AH96:AK96) | AM96: 1155 | AN96: 1179 | AO96: 1168 | AP96: 1138 | AQ96: 4640 | AR96: 1086 | AS96: 1071 | AT96: 1117 | AU96: 1255 | AV96: =+'Sales Model'!D45 | AW96: =+'Sales Model'!E45 | AX96: =+'Sales Model'!F45 | AY96: =+'Sales Model'!G45 | AZ96: =+'Sales Model'!H45 | BA96: =+'Sales Model'!I45 | BB96: =+'Sales Model'!J45 | BC96: =+'Sales Model'!K45 | ... FN96: =+'Sales Model'!DV45 | FO96: =+FH96 | FP96: =+FI96 | FQ96: =+FJ96 | FR96: =+FK96 | FS96: =+FL96 | FT96: =+FM96 | FU96: =+FN96 | FV96: =+'Sales Model'!DW45 | FW96: =+'Sales Model'!DX45 | FX96: =+'Sales Model'!DY45 | FY96: =+'Sales Model'!DZ45 | FZ96: =+'Sales Model'!EA45 | GA96: =+'Sales Model'!EB45 | GB96: =+'Sales Model'!EC45 | GC96: =+'Sales Model'!ED45 | ... GM96: =+'Sales Model'!EN45
B97: International | H97: 1695 | I97: 468 | J97: 445 | K97: 430 | L97: =M97-SUM(I97:K97) | M97: 1812 | N97: 491 | O97: 511 | P97: 490 | Q97: =R97-N97-O97-P97 | R97: 1990 | S97: 502 | T97: 526 | U97: 482 | V97: 517 | W97: =S97+T97+U97+V97 | X97: 540 | Y97: 594 | Z97: 583 | AA97: 631 | AB97: 2348 | AC97: 737 | AD97: 787 | AE97: 763 | AF97: 815 | AG97: 3102 | AH97: 918 | AI97: 933 | AJ97: 876 | AK97: 963 | AL97: =SUM(AH97:AK97) | AM97: 933 | AN97: 973 | AO97: 916 | AP97: 974 | AQ97: 3795 | AR97: 966 | AS97: 979 | AT97: 922 | AU97: 1171 | AV97: =+'Sales Model'!D46 | AW97: =+'Sales Model'!E46 | AX97: =+'Sales Model'!F46 | AY97: =+'Sales Model'!G46 | AZ97: =+'Sales Model'!H46 | BA97: =+'Sales Model'!I46 | BB97: =+'Sales Model'!J46 | BC97: =+'Sales Model'!K46 | ... FN97: =+'Sales Model'!DV46 | FO97: =+FH97 | FP97: =+FI97 | FQ97: =+FJ97 | FR97: =+FK97 | FS97: =+FL97 | FT97: =+FM97 | FU97: =+FN97 | FV97: =+'Sales Model'!DW46 | FW97: =+'Sales Model'!DX46 | FX97: =+'Sales Model'!DY46 | FY97: =+'Sales Model'!DZ46 | FZ97: =+'Sales Model'!EA46 | GA97: =+'Sales Model'!EB46 | GB97: =+'Sales Model'!EC46 | GC97: =+'Sales Model'!ED46 | ... GM97: =+'Sales Model'!EN46
B98: Total | H98: =SUM(H96:H97) | I98: =SUM(I96:I97) | J98: =SUM(J96:J97) | K98: =SUM(K96:K97) | L98: =SUM(L96:L97) | M98: =SUM(M96:M97) | N98: =SUM(N96:N97) | O98: =SUM(O96:O97) | ... U98: =SUM(U96:U97) | V98: 204 | W98: =SUM(W96:W97) | X98: =SUM(X96:X97) | Y98: =SUM(Y96:Y97) | Z98: =SUM(Z96:Z97) | AA98: =SUM(AA96:AA97) | AB98: =SUM(AB96:AB97) | AC98: =SUM(AC96:AC97) | AD98: =SUM(AD96:AD97) | ... GM98: =SUM(GM96:GM97)
B100: Business mix of sales, % total
B101: Innovative Medicine | V101: 196
B102: US | H102: 0.11716524 | M102: 0.12308187 | R102: 0.12011925 | V102: 130 | W102: 0.12554817 | AB102: 0.13620186 | AG102: 0.14313767 | AL102: 0.15518039 | AQ102: 0.17132883 | AR102: 0.20214422 | AS102: 0.2037005 | AT102: 0.21097918 | AU102: 0.2007728 | AV102: 0.21654374 | AW102: =+'Sales Model'!E34/'Sales Model'!E$25 | AX102: =+'Sales Model'!F34/'Sales Model'!F$25 | AY102: =+'Sales Model'!G34/'Sales Model'!G$25 | AZ102: =+'Sales Model'!H34/'Sales Model'!H$25 | BA102: =+'Sales Model'!I34/'Sales Model'!I$25 | BB102: =+'Sales Model'!J34/'Sales Model'!J$25 | BC102: =+'Sales Model'!K34/'Sales Model'!K$25 | BD102: =+'Sales Model'!L34/'Sales Model'!L$25 | ... FN102: =+'Sales Model'!DV34/'Sales Model'!DV$25 | FO102: =+'Sales Model'!DP34/FO$24 | FP102: =+'Sales Model'!DQ34/FP$24 | FQ102: =+'Sales Model'!DR34/FQ$24 | FR102: =+'Sales Model'!DS34/FR$24 | FS102: =+'Sales Model'!DT34/FS$24 | FT102: =+'Sales Model'!DU34/FT$24 | FU102: =+'Sales Model'!DV34/FU$24 | FV102: =+'Sales Model'!DW34/'Sales Model'!DW$25 | FW102: =+'Sales Model'!DX34/'Sales Model'!DX$25 | FX102: =+'Sales Model'!DY34/'Sales Model'!DY$25 | FY102: =+'Sales Model'!DZ34/'Sales Model'!DZ$25 | FZ102: =+'Sales Model'!EA34/'Sales Model'!EA$25 | GA102: =+'Sales Model'!EB34/'Sales Model'!EB$25 | GB102: =+'Sales Model'!EC34/'Sales Model'!EC$25 | GC102: =+'Sales Model'!ED34/'Sales Model'!ED$25 | ... GM102: =+'Sales Model'!EN34/'Sales Model'!EN$25
B103: International | H103: 0.17690527 | M103: 0.18181088 | R103: 0.19544827 | W103: 0.19203565 | AB103: 0.19162324 | AG103: 0.18984184 | AL103: 0.17728955 | AQ103: 0.16876574 | AR103: 0.15960574 | AS103: 0.1701539 | AT103: 0.16503184 | AU103: 0.15672334 | AV103: 0.15436217 | AW103: =+'Sales Model'!E35/'Sales Model'!E$25 | AX103: =+'Sales Model'!F35/'Sales Model'!F$25 | AY103: =+'Sales Model'!G35/'Sales Model'!G$25 | AZ103: =+'Sales Model'!H35/'Sales Model'!H$25 | BA103: =+'Sales Model'!I35/'Sales Model'!I$25 | BB103: =+'Sales Model'!J35/'Sales Model'!J$25 | BC103: =+'Sales Model'!K35/'Sales Model'!K$25 | BD103: =+'Sales Model'!L35/'Sales Model'!L$25 | ... FN103: =+'Sales Model'!DV35/'Sales Model'!DV$25 | FO103: =+'Sales Model'!DP35/FO$24 | FP103: =+'Sales Model'!DQ35/FP$24 | FQ103: =+'Sales Model'!DR35/FQ$24 | FR103: =+'Sales Model'!DS35/FR$24 | FS103: =+'Sales Model'!DT35/FS$24 | FT103: =+'Sales Model'!DU35/FT$24 | FU103: =+'Sales Model'!DV35/FU$24 | FV103: =+'Sales Model'!DW35/'Sales Model'!DW$25 | FW103: =+'Sales Model'!DX35/'Sales Model'!DX$25 | FX103: =+'Sales Model'!DY35/'Sales Model'!DY$25 | FY103: =+'Sales Model'!DZ35/'Sales Model'!DZ$25 | FZ103: =+'Sales Model'!EA35/'Sales Model'!EA$25 | GA103: =+'Sales Model'!EB35/'Sales Model'!EB$25 | GB103: =+'Sales Model'!EC35/'Sales Model'!EC$25 | GC103: =+'Sales Model'!ED35/'Sales Model'!ED$25 | ... GM103: =+'Sales Model'!EN35/'Sales Model'!EN$25
B104: Total | H104: 0.29407051 | M104: 0.30489275 | R104: 0.31556751 | W104: 0.31758382 | AB104: 0.32782509 | AG104: 0.33297951 | AL104: 0.33246994 | AQ104: 0.34009457 | AR104: 0.36174996 | AS104: 0.3738544 | AT104: 0.37601101 | AU104: 0.35749614 | AV104: 0.3709059 | AW104: =+'Sales Model'!E36/'Sales Model'!E$25 | AX104: =+'Sales Model'!F36/'Sales Model'!F$25 | AY104: =+'Sales Model'!G36/'Sales Model'!G$25 | AZ104: =+'Sales Model'!H36/'Sales Model'!H$25 | BA104: =+'Sales Model'!I36/'Sales Model'!I$25 | BB104: =+'Sales Model'!J36/'Sales Model'!J$25 | BC104: =+'Sales Model'!K36/'Sales Model'!K$25 | BD104: =+'Sales Model'!L36/'Sales Model'!L$25 | ... FN104: =+'Sales Model'!DV36/'Sales Model'!DV$25 | FO104: =+'Sales Model'!DP36/FO$24 | FP104: =+'Sales Model'!DQ36/FP$24 | FQ104: =+'Sales Model'!DR36/FQ$24 | FR104: =+'Sales Model'!DS36/FR$24 | FS104: =+'Sales Model'!DT36/FS$24 | FT104: =+'Sales Model'!DU36/FT$24 | FU104: =+'Sales Model'!DV36/FU$24 | FV104: =+'Sales Model'!DW36/'Sales Model'!DW$25 | FW104: =+'Sales Model'!DX36/'Sales Model'!DX$25 | FX104: =+'Sales Model'!DY36/'Sales Model'!DY$25 | FY104: =+'Sales Model'!DZ36/'Sales Model'!DZ$25 | FZ104: =+'Sales Model'!EA36/'Sales Model'!EA$25 | GA104: =+'Sales Model'!EB36/'Sales Model'!EB$25 | GB104: =+'Sales Model'!EC36/'Sales Model'!EC$25 | GC104: =+'Sales Model'!ED36/'Sales Model'!ED$25 | ... GM104: =+'Sales Model'!EN36/'Sales Model'!EN$25
B105: MedTech | V105: 324
B106: US | H106: 0.18002137 | M106: 0.18124849 | R106: 0.19217625 | V106: 171 | W106: 0.19783562 | AB106: 0.18920808 | AG106: 0.19292007 | AL106: 0.20249769 | AQ106: 0.20504662 | AR106: 0.1877918 | AS106: 0.18519799 | AT106: 0.19222165 | AU106: 0.19397218 | AV106: 0.18878133 | AW106: =+'Sales Model'!E45/'Sales Model'!E$25 | AX106: =+'Sales Model'!F45/'Sales Model'!F$25 | AY106: =+'Sales Model'!G45/'Sales Model'!G$25 | AZ106: =+'Sales Model'!H45/'Sales Model'!H$25 | BA106: =+'Sales Model'!I45/'Sales Model'!I$25 | BB106: =+'Sales Model'!J45/'Sales Model'!J$25 | BC106: =+'Sales Model'!K45/'Sales Model'!K$25 | BD106: =+'Sales Model'!L45/'Sales Model'!L$25 | ... FN106: =+'Sales Model'!DV45/'Sales Model'!DV$25 | FO106: =+'Sales Model'!DP45/FO$24 | FP106: =+'Sales Model'!DQ45/FP$24 | FQ106: =+'Sales Model'!DR45/FQ$24 | FR106: =+'Sales Model'!DS45/FR$24 | FS106: =+'Sales Model'!DT45/FS$24 | FT106: =+'Sales Model'!DU45/FT$24 | FU106: =+'Sales Model'!DV45/FU$24 | FV106: =+'Sales Model'!DW45/'Sales Model'!DW$25 | FW106: =+'Sales Model'!DX45/'Sales Model'!DX$25 | FX106: =+'Sales Model'!DY45/'Sales Model'!DY$25 | FY106: =+'Sales Model'!DZ45/'Sales Model'!DZ$25 | FZ106: =+'Sales Model'!EA45/'Sales Model'!EA$25 | GA106: =+'Sales Model'!EB45/'Sales Model'!EB$25 | GB106: =+'Sales Model'!EC45/'Sales Model'!EC$25 | GC106: =+'Sales Model'!ED45/'Sales Model'!ED$25 | ... GM106: =+'Sales Model'!EN45/'Sales Model'!EN$25
B107: International | H107: 0.15090812 | M107: 0.14557725 | R107: 0.1446957 | W107: 0.14337247 | AB107: 0.14923096 | AG107: 0.1646322 | AL107: 0.1706753 | AQ107: 0.16770516 | AR107: 0.16704133 | AS107: 0.1692893 | AT107: 0.1586646 | AU107: 0.18098918 | AV107: 0.16833943 | AW107: =+'Sales Model'!E46/'Sales Model'!E$25 | AX107: =+'Sales Model'!F46/'Sales Model'!F$25 | AY107: =+'Sales Model'!G46/'Sales Model'!G$25 | AZ107: =+'Sales Model'!H46/'Sales Model'!H$25 | BA107: =+'Sales Model'!I46/'Sales Model'!I$25 | BB107: =+'Sales Model'!J46/'Sales Model'!J$25 | BC107: =+'Sales Model'!K46/'Sales Model'!K$25 | BD107: =+'Sales Model'!L46/'Sales Model'!L$25 | ... FN107: =+'Sales Model'!DV46/'Sales Model'!DV$25 | FO107: =+'Sales Model'!DP46/FO$24 | FP107: =+'Sales Model'!DQ46/FP$24 | FQ107: =+'Sales Model'!DR46/FQ$24 | FR107: =+'Sales Model'!DS46/FR$24 | FS107: =+'Sales Model'!DT46/FS$24 | FT107: =+'Sales Model'!DU46/FT$24 | FU107: =+'Sales Model'!DV46/FU$24 | FV107: =+'Sales Model'!DW46/'Sales Model'!DW$25 | FW107: =+'Sales Model'!DX46/'Sales Model'!DX$25 | FX107: =+'Sales Model'!DY46/'Sales Model'!DY$25 | FY107: =+'Sales Model'!DZ46/'Sales Model'!DZ$25 | FZ107: =+'Sales Model'!EA46/'Sales Model'!EA$25 | GA107: =+'Sales Model'!EB46/'Sales Model'!EB$25 | GB107: =+'Sales Model'!EC46/'Sales Model'!EC$25 | GC107: =+'Sales Model'!ED46/'Sales Model'!ED$25 | ... GM107: =+'Sales Model'!EN46/'Sales Model'!EN$25
B108: Total | H108: 0.33092949 | M108: 0.32682574 | R108: 0.33687196 | W108: 0.34120809 | AB108: 0.33843905 | AG108: 0.35755228 | AL108: 0.37317299 | AQ108: 0.37275178 | AR108: 0.35483313 | AS108: 0.35448729 | AT108: 0.35088625 | AU108: 0.37496136 | AV108: 0.35712075 | AW108: =+'Sales Model'!E47/'Sales Model'!E$25 | AX108: =+'Sales Model'!F47/'Sales Model'!F$25 | AY108: =+'Sales Model'!G47/'Sales Model'!G$25 | AZ108: =+'Sales Model'!H47/'Sales Model'!H$25 | BA108: =+'Sales Model'!I47/'Sales Model'!I$25 | BB108: =+'Sales Model'!J47/'Sales Model'!J$25 | BC108: =+'Sales Model'!K47/'Sales Model'!K$25 | BD108: =+'Sales Model'!L47/'Sales Model'!L$25 | ... FN108: =+'Sales Model'!DV47/'Sales Model'!DV$25 | FO108: =+'Sales Model'!DP47/FO$24 | FP108: =+'Sales Model'!DQ47/FP$24 | FQ108: =+'Sales Model'!DR47/FQ$24 | FR108: =+'Sales Model'!DS47/FR$24 | FS108: =+'Sales Model'!DT47/FS$24 | FT108: =+'Sales Model'!DU47/FT$24 | FU108: =+'Sales Model'!DV47/FU$24 | FV108: =+'Sales Model'!DW47/'Sales Model'!DW$25 | FW108: =+'Sales Model'!DX47/'Sales Model'!DX$25 | FX108: =+'Sales Model'!DY47/'Sales Model'!DY$25 | FY108: =+'Sales Model'!DZ47/'Sales Model'!DZ$25 | FZ108: =+'Sales Model'!EA47/'Sales Model'!EA$25 | GA108: =+'Sales Model'!EB47/'Sales Model'!EB$25 | GB108: =+'Sales Model'!EC47/'Sales Model'!EC$25 | GC108: =+'Sales Model'!ED47/'Sales Model'!ED$25 | ... GM108: =+'Sales Model'!EN47/'Sales Model'!EN$25
B109: Consumer | V109: 301
B110: US | H110: 0.18598647 | M110: 0.19763799 | R110: 0.18963135 | V110: 202 | W110: 0.18609421 | AB110: 0.17109445 | AG110: 0.15168241 | AL110: 0.14643848 | AQ110: 0.14317911 | AR110: 0.14525333 | AS110: 0.13020923 | AT110: 0.13870246 | AU110: 0.14327666 | AV110: 0.13857054 | AW110: =+'Sales Model'!E56/'Sales Model'!E$25 | AX110: =+'Sales Model'!F56/'Sales Model'!F$25 | AY110: =+'Sales Model'!G56/'Sales Model'!G$25 | AZ110: =+'Sales Model'!H56/'Sales Model'!H$25 | BA110: =+'Sales Model'!I56/'Sales Model'!I$25 | BB110: =+'Sales Model'!J56/'Sales Model'!J$25 | BC110: =+'Sales Model'!K56/'Sales Model'!K$25 | BD110: =+'Sales Model'!L56/'Sales Model'!L$25 | ... FN110: =+'Sales Model'!DV56/'Sales Model'!DV$25
B111: International | H111: 0.18901353 | M111: 0.17064353 | R111: 0.15792918 | W111: 0.15511388 | AB111: 0.16264141 | AG111: 0.1577858 | AL111: 0.14791859 | AQ111: 0.14397455 | AR111: 0.13816358 | AS111: 0.14144907 | AT111: 0.13440028 | AU111: 0.12426584 | AV111: 0.1334028 | AW111: =+'Sales Model'!E57/'Sales Model'!E$25 | AX111: =+'Sales Model'!F57/'Sales Model'!F$25 | AY111: =+'Sales Model'!G57/'Sales Model'!G$25 | AZ111: =+'Sales Model'!H57/'Sales Model'!H$25 | BA111: =+'Sales Model'!I57/'Sales Model'!I$25 | BB111: =+'Sales Model'!J57/'Sales Model'!J$25 | BC111: =+'Sales Model'!K57/'Sales Model'!K$25 | BD111: =+'Sales Model'!L57/'Sales Model'!L$25 | ... FN111: =+'Sales Model'!DV57/'Sales Model'!DV$25
B112: Total | H112: 0.375 | M112: 0.36828151 | R112: 0.34756053 | W112: 0.34120809 | AB112: 0.33373586 | AG112: 0.30946821 | AL112: 0.29435708 | AQ112: 0.28715365 | AR112: 0.28341691 | AS112: 0.27165831 | AT112: 0.27310274 | AU112: 0.2675425 | AV112: 0.27197334 | AW112: =+'Sales Model'!E58/'Sales Model'!E$25 | AX112: =+'Sales Model'!F58/'Sales Model'!F$25 | AY112: =+'Sales Model'!G58/'Sales Model'!G$25 | AZ112: =+'Sales Model'!H58/'Sales Model'!H$25 | BA112: =+'Sales Model'!I58/'Sales Model'!I$25 | BB112: =+'Sales Model'!J58/'Sales Model'!J$25 | BC112: =+'Sales Model'!K58/'Sales Model'!K$25 | BD112: =+'Sales Model'!L58/'Sales Model'!L$25 | ... FN112: =+'Sales Model'!DV58/'Sales Model'!DV$25
V113: 115
B114: Total US | H114: 0.48317308 | M114: 0.50196835 | R114: 0.50192685 | V114: 167 | W114: 0.509478 | AB114: 0.49650439 | AG114: 0.48774015 | AL114: 0.50411656 | AQ114: 0.51955455 | AR114: 0.53518935 | AS114: 0.51910773 | AT114: 0.54190329 | AU114: 0.53802164 | AV114: 0.54389561 | AW114: =+AW110+AW106+AW102 | AX114: =+AX110+AX106+AX102 | AY114: =+AY110+AY106+AY102 | AZ114: =+AZ110+AZ106+AZ102 | BA114: =+BA110+BA106+BA102 | BB114: =+BB110+BB106+BB102 | BC114: =+BC110+BC106+BC102 | BD114: =+BD110+BD106+BD102 | ... FN114: =+FN110+FN106+FN102 | FO114: =FO106+FO102 | FP114: =FP106+FP102 | FQ114: =FQ106+FQ102 | FR114: =FR106+FR102 | FS114: =FS106+FS102 | FT114: =FT106+FT102 | FU114: =FU106+FU102 | FV114: =FV106+FV102 | ... GM114: =GM106+GM102
B115: Total International | H115: 0.51682692 | M115: 0.49803165 | R115: 0.49807315 | W115: 0.490522 | AB115: 0.50349561 | AG115: 0.51225985 | AL115: 0.49588344 | AQ115: 0.48044545 | AR115: 0.46481065 | AS115: 0.48089227 | AT115: 0.45809671 | AU115: 0.46197836 | AV115: 0.45610439 | AW115: =+AW111+AW107+AW103 | AX115: =+AX111+AX107+AX103 | AY115: =+AY111+AY107+AY103 | AZ115: =+AZ111+AZ107+AZ103 | BA115: =+BA111+BA107+BA103 | BB115: =+BB111+BB107+BB103 | BC115: =+BC111+BC107+BC103 | BD115: =+BD111+BD107+BD103 | ... FN115: =+FN111+FN107+FN103 | FO115: =FO107+FO103 | FP115: =FP107+FP103 | FQ115: =FQ107+FQ103 | FR115: =FR107+FR103 | FS115: =FS107+FS103 | FT115: =FT107+FT103 | FU115: =FU107+FU103 | FV115: =FV107+FV103 | ... GM115: =GM107+GM103
B116: Total Worldwide | AW116: =+AW115+AW114 | AX116: =+AX115+AX114 | AY116: =+AY115+AY114 | AZ116: =+AZ115+AZ114 | BA116: =+BA115+BA114 | BB116: =+BB115+BB114 | BC116: =+BC115+BC114 | BD116: =+BD115+BD114 | ... GM116: =+GM115+GM114
B118: EBIT & EBITDA Framework
...

Sheet Balance Sheet
B3: =Cover!D11
B5: Balance Sheet
B7: ($ in millions)
B11: $ millions | C11: 1990 | D11: 1991 | E11: 1992 | F11: 1993 | G11: 1994 | H11: 1995 | I11: 1Q96 | J11: 2Q96 | K11: 3Q96 | L11: 4Q96 | M11: 1996 | N11: 1Q97 | O11: 2Q97 | P11: 3Q97 | Q11: 4Q97 | R11: 1997 | S11: 1Q98 | T11: 2Q98 | U11: 3Q98 | V11: 4Q98 | W11: 1998 | X11: 1Q99 | Y11: 2Q99 | Z11: 3Q99 | AA11: 4Q99 | AB11: 1999 | AC11: 1Q00 | AD11: 2Q00 | AE11: 3Q00 | AF11: 4Q00 | AG11: 2000 | AH11: 1Q01 | AI11: 2Q01 | AJ11: 3Q01 | AK11: 4Q01 | AL11: 2001 | AM11: 1Q02 | AN11: 2Q02 | AO11: 3Q02 | AP11: 4Q02 | AQ11: 2002 | AR11: 1Q03 | AS11: 2Q03 | AT11: 3Q03 | AU11: 4Q03 | AV11: 2003 | AW11: 1Q04 | AX11: 2Q04 | AY11: 3Q04 | AZ11: 4Q04 | BA11: 2004 | BB11: 1Q05 | BC11: 2Q05 | BD11: 3Q05 | BE11: 4Q05 | BF11: 2005 | BG11: 1Q06 | BH11: 2Q06 | BI11: 3Q06 | BJ11: 4Q06 | BK11: 2006 | BL11: 1Q07 | BM11: 2Q07 | BN11: 3Q07 | BO11: 4Q07 | BP11: 2007 | BQ11: 1Q08 | BR11: 2Q08 | BS11: 3Q08 | BT11: 4Q08 | BU11: 2008 | BV11: 1Q09 | BW11: 2Q09 | BX11: 3Q09 | BY11: 4Q09 | BZ11: 2009 | CA11: =+'Sales Model'!BH19 | CB11: =+'Sales Model'!BI19 | CC11: =+'Sales Model'!BJ19 | CD11: =+'Sales Model'!BK19 | CE11: 2010 | CF11: =+'Sales Model'!BM19 | CG11: =+'Sales Model'!BN19 | CH11: =+'Sales Model'!BO19 | CI11: =+'Sales Model'!BP19 | CJ11: 2011 | CK11: =+'Sales Model'!BR19 | CL11: =+'Sales Model'!BS19 | CM11: =+'Sales Model'!BT19 | CN11: =+'Sales Model'!BU19 | CO11: =+'Sales Model'!BV19 | CP11: =+'Sales Model'!BW19 | CQ11: 2Q13 | CR11: =+'Sales Model'!BY19 | CS11: =+'Sales Model'!BZ19 | CT11: =+'Sales Model'!CA19 | CU11: 1Q14 | CV11: 2Q14 | CW11: 3Q14 | CX11: 4Q14 | CY11: 2014 | CZ11: 1Q15 | DA11: 2Q15 | DB11: 3Q15 | DC11: 4Q15 | DD11: 2015 | DE11: 1Q16 | DF11: 2Q16 | DG11: 3Q16 | DH11: 4Q16 | DI11: 2016 | DJ11: 1Q17 | DK11: 2Q17 | DL11: 3Q17 | DM11: 4Q17 | DN11: 2017 | DO11: 1Q18 | DP11: 2Q18 | DQ11: 3Q18 | DR11: 4Q18 | DS11: 2018 | DT11: 1Q19 | DU11: 2Q19 | DV11: 3Q19 | DW11: 4Q19 | DX11: 2019 | DY11: 1Q20 | DZ11: 2Q20 | EA11: 3Q20 | EB11: 4Q20 | EC11: 2020 | ED11: 1Q21 | EE11: 2Q21 | EF11: 3Q21 | EG11: 4Q21 | EH11: 2021 | EI11: 1Q22 | EJ11: 2Q22 | EK11: 3Q22 | EL11: 4Q22 | EM11: 2022 | EN11: 1Q23 | EO11: 2Q23 | EP11: 3Q23 | EQ11: 4Q23 | ER11: 2023 | ES11: 1Q24 | ET11: 2Q24 | EU11: 3Q24 | EV11: 4Q24 | EW11: 2024 | EX11: 1Q25 | EY11: 2Q25 | EZ11: 3Q25E | FA11: 4Q25E | FB11: 2025E | FC11: 2026E | FD11: 2027E | FE11: 2028E | FF11: 2029E | FG11: 2030E
B12: Assets
B13: Current Assets
A14: x | B14: Cash & equivalents | C14: 826 | D14: 589 | E14: 745 | F14: 372 | G14: 636 | H14: 1201 | I14: 2492 | J14: 1860 | K14: 2088 | L14: 2011 | M14: =+L14 | N14: 2190 | O14: 2237 | P14: 2994 | Q14: 2753 | R14: =+Q14 | S14: 2893 | T14: 3114 | U14: 3742 | V14: =+U14 | W14: =+V14 | X14: 1780 | Y14: 2024 | Z14: 2617 | AA14: 2512 | AB14: =+AA14 | AC14: 4278 | AD14: 2937 | AE14: 4278 | AF14: 4278 | AG14: =+AF14 | AH14: 4340 | AI14: 4722 | AJ14: 5066 | AK14: 3758 | AL14: =+AK14 | AM14: 3437 | AN14: 2606 | AO14: 3161 | AP14: 2894 | AQ14: =+AP14 | AR14: 3061 | AS14: 2968 | AT14: 3850 | AU14: 5377 | AV14: =+AU14 | AW14: 5637 | AX14: 5681 | AY14: 7348 | AZ14: 9203 | BA14: =+AZ14 | BB14: 8539 | BC14: 12156 | BD14: 14825 | BE14: 16055 | BF14: =+BE14 | BG14: 16822 | BH14: 14647 | BI14: 14491 | BJ14: 4083 | BK14: =+BJ14 | BL14: 5175 | BM14: 5571 | BN14: 6640 | BO14: 7770 | BP14: =+BO14 | BQ14: 10539 | BR14: 12646 | BS14: 14018 | BT14: 10768 | BU14: =+BT14 | BV14: 12589 | BW14: 11686 | BX14: 11856 | BY14: 15810 | BZ14: =+BY14 | CA14: 13743 | CB14: 12713 | CC14: 14338 | CD14: 19355 | CE14: =+CD14 | CF14: 22356 | CG14: 14974 | CH14: 15617 | CI14: 24542 | CJ14: =CI14 | CK14: 30267 | CL14: 14042 | CM14: 15486 | CN14: 14911 | CO14: =CN14 | CP14: 14855 | CQ14: 17307 | CR14: 17204 | CS14: 20927 | CT14: =CS14 | CU14: 19722 | CV14: 14236 | CW14: 13818 | CX14: 14523 | CY14: =CX14 | CZ14: 11988 | DA14: 10639 | DB14: 13639 | DC14: 13732 | DD14: =DC14 | DE14: 13861 | DF14: 18640 | DG14: 18205 | DH14: 18972 | DI14: =DH14 | DJ14: 20909 | DK14: 12598 | DL14: 15721 | DM14: 17824 | DN14: =DM14 | DO14: 14639 | DP14: 17569 | DQ14: 16056 | DR14: 18107 | DS14: =DR14 | DT14: 14734 | DU14: 14376 | DV14: 16249 | DW14: 17305 | DX14: ='Cash Flows'!DZ54 | DY14: 15530 | DZ14: 11174 | EA14: 18965 | EB14: 13985 | EC14: ='Cash Flows'!EE54 | ED14: 12671 | EE14: 14332 | EF14: 17604 | EG14: 14487 | EH14: ='Cash Flows'!EJ54 | EI14: 10463 | EJ14: 10983 | EK14: 11355 | EL14: 14127 | EM14: ='Cash Flows'!EO54 | EN14: =19170+7695 | EO14: 21183 | EP14: 19728 | EQ14: 21859 | ER14: =+EQ14 | ES14: 25473 | ET14: 24878 | EU14: 19980 | EV14: 24105 | EW14: =+EV14 | EX14: 38474 | EY14: 18577 | EZ14: ='Cash Flows'!FB54 | FA14: ='Cash Flows'!FC54 | FB14: ='Cash Flows'!FD54 | FC14: ='Cash Flows'!FE54 | FD14: ='Cash Flows'!FF54 | FE14: ='Cash Flows'!FG54 | FF14: ='Cash Flows'!FH54 | FG14: ='Cash Flows'!FI54
