Workbook
Name _________________________2003Q4_T10: #REF!
Name _________________________TOP10: #REF!
Name ________________________2003Q4_T10: #REF!
Name ________________________TOP10: #REF!
Name _______________________2003Q4_T10: #REF!
Name _______________________TOP10: #REF!
Name ______________________2003Q4_T10: #REF!
Name ______________________TOP10: #REF!
Name _____________________2003Q4_T10: #REF!
Name _____________________TOP10: #REF!
Name ____________________2003Q4_T10: #REF!
Name ____________________TOP10: #REF!
Name ___________________2003Q4_T10: #REF!
Name ___________________TOP10: #REF!
Name __________________2003Q4_T10: #REF!
Name __________________TOP10: #REF!
Name _________________2003Q4_T10: #REF!
Name _________________TOP10: #REF!
Name ________________2003Q4_T10: #REF!
Name ________________TOP10: #REF!
Name _______________2003Q4_T10: #REF!
Name _______________TOP10: #REF!
Name ______________2003Q4_T10: #REF!
Name ______________TOP10: #REF!
Name _____________2003Q4_T10: #REF!
Name _____________TOP10: #REF!
Name ____________2003Q4_T10: #REF!
Name ____________TOP10: #REF!
Name ___________2003Q4_T10: #REF!
Name ___________TOP10: #REF!
Name __________2003Q4_T10: #REF!
Name __________TOP10: #REF!
Name _________2003Q4_T10: #REF!
Name _________TOP10: #REF!
Name ________2003Q4_T10: #REF!
Name ________TOP10: #REF!
Name _______2003Q4_T10: #REF!
Name _______CSC2: #REF!
Name _______DAT1: #REF!
Name _______DAT2: #REF!
Name _______DAT3: #REF!
Name _______DAT4: #REF!
Name _______DAT5: #REF!
Name _______DAT6: #REF!
Name _______DAT7: #REF!
Name _______DAT8: #REF!
Name _______DCF2: #REF!
Name _______eps1998: #REF!
Name _______eps1999: #REF!
Name _______eps2000: #REF!
Name _______eps2001: #REF!
Name _______EPS94: #REF!
Name _______EPS95: #REF!
Name _______EPS96: #REF!
Name _______EPS97: #REF!
Name _______EPS98: #REF!
Name _______rev1997: #REF!
Name _______rev1998: #REF!
Name _______rev1999: #REF!
Name _______rev2000: #REF!

Sheet Cover
E8: Company1953 (Ticker0027)
E9: Semiconductors
E10: Last updated: 10/06/25
F16: Analyst 1
F17: person@example.com
F18: 212-902-1000
F20: Analyst 2
F21: person@example.com
F22: 212-902-1000
F24: Analyst 3
F25: person@example.com
F27: Analyst 4
F28: person@example.com
F30: Analyst 5
F31: person@example.com
... F34: person@example.com

Sheet Worksheet
BV1: ="FY"&BZ3 | BW1: ="FY"&CA3 | BX1: ="FY"&CB3 | BY1: ="FY"&CC3 | BZ1: ="FY"&CD3 | CA1: FY2Q21 | CB1: FY3Q21 | CC1: FY4Q21 | CD1: FY1Q22 | CE1: FY2Q22 | CF1: FY3Q22 | CG1: FY4Q22 | CH1: FY1Q23 | CI1: FY2Q23 | CJ1: FY3Q23 | CK1: FY4Q23 | CL1: FY1Q24 | CM1: FY2Q24 | CN1: FY3Q24 | CO1: FY4Q24 | CP1: FY1Q25 | CQ1: FY2Q25 | CR1: FY3Q25 | CS1: FY4Q25 | CT1: FY1Q26 | CU1: FY2Q26 | CV1: FY3Q26E | CW1: FY4Q26E | CX1: FY1Q27E | CY1: FY2Q27E | CZ1: FY3Q27E | DA1: FY4Q27E | DB1: FY1Q28E | DC1: FY2Q28E | DD1: FY3Q28E | DE1: FY4Q28E | DU1: FY15 | DV1: FY16 | DW1: FY17 | DX1: FY18 | DY1: FY19 | DZ1: FY20 | EA1: FY21 | EB1: FY22 | EC1: FY23 | ED1: FY24 | EE1: FY25 | EF1: FY26E | EG1: FY27E | EH1: FY28E
AE2: =SUM(AB5:AE5) | AF2: =SUM(AC5:AF5) | AG2: =SUM(AD5:AG5) | AH2: =SUM(AE5:AH5) | AI2: =SUM(AF5:AI5) | AJ2: =SUM(AG5:AJ5) | AK2: =SUM(AH5:AK5) | AL2: =SUM(AI5:AL5) | BZ2: Company1719
B3: 1Q01 | C3: 2Q01 | D3: 3Q01 | E3: 4Q01 | F3: 1Q02 | G3: 2Q02 | H3: 3Q02 | I3: 4Q02 | J3: 1Q03 | K3: 2Q03 | L3: 3Q03 | M3: 4Q03 | N3: 1Q04 | O3: 2Q04 | P3: 3Q04 | Q3: 4Q04 | R3: 1Q05 | S3: 2Q05 | T3: 3Q05 | U3: 4Q05 | V3: 1Q06 | W3: 2Q06 | X3: 3Q06 | Y3: 4Q06 | Z3: 1Q07 | AA3: 2Q07 | AB3: 3Q07 | AC3: 4Q07 | AD3: 1Q08 | AE3: 2Q08 | AF3: 3Q08 | AG3: 4Q08 | AH3: 1Q09 | AI3: 2Q09 | AJ3: 3Q09 | AK3: 4Q09 | AL3: 1Q10 | AM3: 2Q10 | AN3: 3Q10 | AO3: 4Q10 | AP3: 1Q11 | AQ3: 2Q11 | AR3: 3Q11 | AS3: 4Q11 | AT3: 1Q12 | AU3: 2Q12 | AV3: 3Q12 | AW3: 4Q12 | AX3: 1Q13 | AY3: 2Q13 | AZ3: 3Q13 | BA3: 4Q13 | BB3: 1Q14 | BC3: 2Q14 | BD3: 3Q14 | BE3: 4Q14 | BF3: 1Q15 | BG3: 2Q15 | BH3: 3Q15 | BI3: 4Q15 | BJ3: 1Q16 | BK3: 2Q16 | BL3: 3Q16 | BM3: 4Q16 | BN3: 1Q17 | BO3: 2Q17 | BP3: 3Q17 | BQ3: 4Q17 | BR3: 1Q18 | BS3: 2Q18 | BT3: 3Q18 | BU3: 4Q18 | BV3: 1Q19 | BW3: 2Q19 | BX3: 3Q19 | BY3: 4Q19 | BZ3: 1Q20 | CA3: 2Q20 | CB3: 3Q20 | CC3: 4Q20 | CD3: 1Q21 | CE3: 2Q21 | CF3: 3Q21 | CG3: 4Q21 | CH3: 1Q22 | CI3: 2Q22 | CJ3: 3Q22 | CK3: 4Q22 | CL3: 1Q23 | CM3: 2Q23 | CN3: 3Q23 | CO3: 4Q23 | CP3: 1Q24 | CQ3: 2Q24 | CR3: 3Q24 | CS3: 4Q24 | CT3: 1Q25 | CU3: 2Q25 | CV3: 3Q25E | CW3: 4Q25E | CX3: 1Q26E | CY3: 2Q26E | CZ3: 3Q26E | DA3: 4Q26E | DB3: 1Q27E | DC3: 2Q27E | DD3: 3Q27E | DE3: 4Q27E | DH3: Calendar year
A4: Ticker0027 | B4: 37010 | C4: 37101 | D4: 37192 | E4: 37283 | F4: 37374 | G4: 37465 | H4: 37556 | I4: 37647 | J4: 37741 | K4: 37833 | L4: 37925 | M4: 38017 | N4: 38102 | O4: 38199 | P4: 38291 | Q4: 38383 | R4: 38443 | S4: 38564 | T4: 38656 | U4: 38748 | V4: 38837 | W4: 38928 | X4: 39019 | Y4: 39113 | Z4: 39201 | AA4: 39294 | AB4: 39386 | AC4: 39478 | AD4: 4/31/2008 | AE4: 39660 | AF4: 39752 | AG4: 39844 | AH4: 4/31/2009 | AI4: 40025 | AJ4: 40117 | AK4: 40209 | AL4: 4/31/2010 | AM4: 40390 | AN4: 40482 | AO4: 40574 | AP4: 4/31/2011 | AQ4: 40755 | AR4: 40847 | AS4: 40939 | AT4: 4/31/2012 | AU4: 41121 | AV4: 41213 | AW4: 41305 | AX4: 4/31/2013 | AY4: 41486 | AZ4: 41578 | BA4: 41670 | BB4: 4/31/14 | BC4: 41851 | BD4: 41943 | BE4: 42035 | BF4: 4/31/15 | BG4: 42216 | BH4: 42308 | BI4: 42400 | BJ4: 4/31/16 | BK4: 42582 | BL4: 42674 | BM4: 42766 | BN4: 4/31/2017 | BO4: 42947 | BP4: 43039 | BQ4: 43131 | BR4: 4/31/18 | BS4: 43312 | BT4: 43404 | BU4: 43496 | BV4: 4/31/19 | BW4: 43677 | BX4: 43769 | BY4: 43861 | BZ4: 4/31/20 | CA4: 44043 | CB4: 44135 | CC4: 44227 | CD4: 4/31/21 | CE4: 44408 | CF4: 44500 | CG4: 44592 | CH4: 4/31/22 | CI4: 44773 | CJ4: 44865 | CK4: 44957 | CL4: 4/31/23 | CM4: 45138 | CN4: 45230 | CO4: 45322 | CP4: 4/31/24 | CQ4: 45504 | CR4: 45596 | CS4: 45688 | CT4: 4/31/25 | CU4: 45869 | CV4: 45961 | CW4: 46053 | CX4: 4/31/26 | CY4: 46234 | CZ4: 46326 | DA4: 46418 | DB4: 4/31/26 | DC4: 46234 | DD4: 46326 | DE4: 46418 | DH4: 2001 | DI4: 2002 | DJ4: 2003 | DK4: 2004 | DL4: 2005 | DM4: 2006 | DN4: 2007 | DO4: 2008 | DP4: 2009 | DQ4: 2010 | DR4: 2011 | DS4: 2012 | DT4: 2013 | DU4: 2014 | DV4: 2015 | DW4: 2016 | DX4: 2017 | DY4: 2018 | DZ4: 2019 | EA4: 2020 | EB4: 2021 | EC4: 2022 | ED4: 2023 | EE4: 2024 | EF4: 2025E | EG4: 2026E | EH4: 2027E
A5: Revenue | B5: =Ticker0027!V7 | C5: =Ticker0027!W7 | D5: =Ticker0027!X7 | E5: =Ticker0027!Y7 | F5: =Ticker0027!AA7 | G5: =Ticker0027!AB7 | H5: =Ticker0027!AC7 | I5: =Ticker0027!AD7 | J5: =Ticker0027!AF7 | K5: =Ticker0027!AG7 | L5: =Ticker0027!AH7 | M5: =Ticker0027!AI7 | N5: =Ticker0027!AK7 | O5: =Ticker0027!AL7 | P5: =Ticker0027!AM7 | Q5: =Ticker0027!AN7 | R5: =Ticker0027!AP7 | S5: =Ticker0027!AQ7 | T5: =Ticker0027!AR7 | U5: =Ticker0027!AS7 | V5: =Ticker0027!AU7 | W5: =Ticker0027!AV7 | X5: =Ticker0027!AW7 | Y5: =Ticker0027!AX7 | Z5: =Ticker0027!AZ7 | AA5: =Ticker0027!BA7 | AB5: =Ticker0027!BB7 | AC5: =Ticker0027!BC7 | AD5: =Ticker0027!BE7 | AE5: =Ticker0027!BF7 | AF5: =Ticker0027!BG7 | AG5: =Ticker0027!BH7 | AH5: =Ticker0027!BJ7 | AI5: =Ticker0027!BK7 | AJ5: =Ticker0027!BL7 | AK5: =Ticker0027!BM7 | AL5: =Ticker0027!BO7 | AM5: =Ticker0027!BP7 | AN5: =Ticker0027!BQ7 | AO5: =Ticker0027!BR7 | AP5: =Ticker0027!BT7 | AQ5: =Ticker0027!BU7 | AR5: =Ticker0027!BV7 | AS5: =Ticker0027!BW7 | AT5: =Ticker0027!BY7 | AU5: =Ticker0027!BZ7 | AV5: =Ticker0027!CA7 | AW5: =Ticker0027!CB7 | AX5: =Ticker0027!CD7 | AY5: =Ticker0027!CE7 | AZ5: =Ticker0027!CF7 | BA5: =Ticker0027!CG7 | BB5: =Ticker0027!CI7 | BC5: =Ticker0027!CJ7 | BD5: =Ticker0027!CK7 | BE5: =Ticker0027!CL7 | BF5: =Ticker0027!CN7 | BG5: =Ticker0027!CO7 | BH5: =Ticker0027!CP7 | BI5: =Ticker0027!CQ7 | BJ5: =Ticker0027!CS7 | BK5: =Ticker0027!CT7 | BL5: =Ticker0027!CU7 | BM5: =Ticker0027!CV7 | BN5: =Ticker0027!CX7 | BO5: =Ticker0027!CY7 | BP5: =Ticker0027!CZ7 | BQ5: =Ticker0027!DA7 | BR5: =Ticker0027!DC7 | BS5: =Ticker0027!DD7 | BT5: =Ticker0027!DE7 | BU5: =Ticker0027!DF7 | BV5: =Ticker0027!DH7 | BW5: =Ticker0027!DI7 | BX5: =Ticker0027!DJ7 | BY5: =Ticker0027!DK7 | BZ5: =Ticker0027!DM7 | CA5: =Ticker0027!DN7 | CB5: =Ticker0027!DO7 | CC5: =Ticker0027!DP7 | CD5: =Ticker0027!DR7 | CE5: =Ticker0027!DS7 | CF5: =Ticker0027!DT7 | CG5: =Ticker0027!DU7 | CH5: =Ticker0027!DW7 | CI5: =Ticker0027!DX7 | CJ5: =Ticker0027!DY7 | CK5: =Ticker0027!DZ7 | CL5: =Ticker0027!EB7 | CM5: =Ticker0027!EC7 | CN5: =Ticker0027!ED7 | CO5: =Ticker0027!EE7 | CP5: =Ticker0027!EG7 | CQ5: =Ticker0027!EH7 | CR5: =Ticker0027!EI7 | CS5: =Ticker0027!EJ7 | CT5: =Ticker0027!EL7 | CU5: =Ticker0027!EM7 | CV5: =CV131 | CW5: =CW131 | CX5: =CX131 | CY5: =CY131 | CZ5: =CZ131 | DA5: =DA131 | DB5: =DB131 | DC5: =DC131 | ... DE5: =DE131 | DH5: =SUM(B5:E5) | DI5: =SUM(F5:I5) | DJ5: =SUM(J5:M5) | DK5: =SUM(N5:Q5) | DL5: =SUM(R5:U5) | DM5: =SUM(V5:Y5) | DN5: =SUM(Z5:AC5) | DO5: =SUM(AD5:AG5) | DP5: =SUM(AH5:AK5) | DQ5: =SUM(AL5:AO5) | DR5: =SUM(AP5:AS5) | DS5: =SUM(AT5:AW5) | DT5: =SUM(AX5:BA5) | DU5: =SUM(BB5:BE5) | DV5: =SUM(BF5:BI5) | DW5: =SUM(BJ5:BM5) | DX5: =SUM(BN5:BQ5) | DY5: =SUM(BR5:BU5) | DZ5: =BV5+BW5+BX5+BY5 | EA5: =CC5+CB5+CA5+BZ5 | EB5: =+CD5+CE5+CF5+CG5 | EC5: =SUM(CH5:CK5) | ED5: =SUM(CL5:CO5) | EE5: =SUM(CP5:CS5) | EF5: =SUM(CT5:CW5) | EG5: =SUM(CX5:DA5) | EH5: =SUM(DB5:DE5)
A6: qoq | C6: =C5/B5-1 | D6: =D5/C5-1 | E6: =E5/D5-1 | F6: =F5/E5-1 | G6: =G5/F5-1 | H6: =H5/G5-1 | I6: =I5/H5-1 | J6: =J5/I5-1 | ... DE6: =DE5/DD5-1 | DH6: -- | DI6: -- | DJ6: -- | DK6: -- | DL6: -- | DM6: -- | DN6: -- | DO6: -- | DP6: -- | DQ6: -- | DR6: -- | DS6: -- | DT6: -- | DU6: -- | DV6: -- | DW6: -- | DX6: -- | DY6: -- | DZ6: -- | EA6: -- | EB6: -- | EC6: -- | ED6: -- | EE6: -- | EF6: -- | EG6: -- | EH6: --
A7: yoy | F7: =F5/B5-1 | G7: =G5/C5-1 | H7: =H5/D5-1 | I7: =I5/E5-1 | J7: =J5/F5-1 | K7: =K5/G5-1 | L7: =L5/H5-1 | M7: =M5/I5-1 | ... DE7: =DE5/DA5-1 | DI7: =DI5/DH5-1 | DJ7: =DJ5/DI5-1 | DK7: =DK5/DJ5-1 | DL7: =DL5/DK5-1 | DM7: =DM5/DL5-1 | DN7: =DN5/DM5-1 | DO7: =DO5/DN5-1 | DP7: =DP5/DO5-1 | ... EH7: =EH5/EG5-1
A8: COGS (incl D&A) | B8: =Ticker0027!V10 | C8: =Ticker0027!W10 | D8: =Ticker0027!X10 | E8: =Ticker0027!Y10 | F8: =Ticker0027!AA10 | G8: =Ticker0027!AB10 | H8: =Ticker0027!AC10 | I8: =Ticker0027!AD10 | J8: =Ticker0027!AF10 | K8: =Ticker0027!AG10 | L8: =Ticker0027!AH10 | M8: =Ticker0027!AI10 | N8: =Ticker0027!AK10 | O8: =Ticker0027!AL10 | P8: =Ticker0027!AM10 | Q8: =Ticker0027!AN10 | R8: =Ticker0027!AP10 | S8: =Ticker0027!AQ10 | T8: =Ticker0027!AR10 | U8: =Ticker0027!AS10 | V8: =Ticker0027!AU10 | W8: =Ticker0027!AV10 | X8: =Ticker0027!AW10 | Y8: =Ticker0027!AX10 | Z8: =Ticker0027!AZ10 | AA8: =Ticker0027!BA10 | AB8: =Ticker0027!BB10 | AC8: =Ticker0027!BC10 | AD8: =Ticker0027!BE10 | AE8: =Ticker0027!BF10 | AF8: =Ticker0027!BG10 | AG8: =Ticker0027!BH10 | AH8: =Ticker0027!BJ10 | AI8: =Ticker0027!BK10 | AJ8: =Ticker0027!BL10 | AK8: =Ticker0027!BM10 | AL8: =Ticker0027!BO10 | AM8: =Ticker0027!BP10 | AN8: =Ticker0027!BQ10 | AO8: =Ticker0027!BR10 | AP8: =Ticker0027!BT10 | AQ8: =Ticker0027!BU10 | AR8: =Ticker0027!BV10 | AS8: =Ticker0027!BW10 | AT8: =Ticker0027!BY10 | AU8: =Ticker0027!BZ10 | AV8: =Ticker0027!CA10 | AW8: =Ticker0027!CB10 | AX8: =Ticker0027!CD10 | AY8: =Ticker0027!CE10 | AZ8: =Ticker0027!CF10 | BA8: =Ticker0027!CG10 | BB8: =Ticker0027!CI10 | BC8: =Ticker0027!CJ10 | BD8: =Ticker0027!CK10 | BE8: =Ticker0027!CL10 | BF8: =Ticker0027!CN10 | BG8: =Ticker0027!CO10 | BH8: =Ticker0027!CP10 | BI8: =Ticker0027!CQ10 | BJ8: =Ticker0027!CS10 | BK8: =Ticker0027!CT10 | BL8: =Ticker0027!CU10 | BM8: =Ticker0027!CV10 | BN8: =Ticker0027!CX10 | BO8: =Ticker0027!CY10 | BP8: =Ticker0027!CZ10 | BQ8: =Ticker0027!DA10 | BR8: =Ticker0027!DC10 | BS8: =Ticker0027!DD10 | BT8: =Ticker0027!DE10 | BU8: =Ticker0027!DF10 | BV8: =Ticker0027!DH10 | BW8: =Ticker0027!DI10 | BX8: =Ticker0027!DJ10 | BY8: =Ticker0027!DK10 | BZ8: =Ticker0027!DM10 | CA8: =Ticker0027!DN10 | CB8: =Ticker0027!DO10 | CC8: =Ticker0027!DP10 | CD8: =Ticker0027!DR10 | CE8: =Ticker0027!DS10 | CF8: =Ticker0027!DT10 | CG8: =Ticker0027!DU10 | CH8: =Ticker0027!DW10 | CI8: =Ticker0027!DX10 | CJ8: =Ticker0027!DY10 | CK8: =Ticker0027!DZ10 | CL8: =Ticker0027!EB10 | CM8: =Ticker0027!EC10 | CN8: =Ticker0027!ED10 | CO8: =Ticker0027!EE10 | CP8: =Ticker0027!EG10 | CQ8: =Ticker0027!EH10 | CR8: =Ticker0027!EI10 | CS8: =Ticker0027!EJ10 | CT8: =Ticker0027!EL10 | CU8: =Ticker0027!EM10 | CV8: =CV5-CV15 | CW8: =CW5-CW15 | CX8: =CX5-CX15 | CY8: =CY5-CY15 | CZ8: =CZ5-CZ15 | DA8: =DA5-DA15 | DB8: =DB5-DB15 | DC8: =DC5-DC15 | ... DE8: =DE5-DE15 | DH8: =SUM(B8:E8) | DI8: =SUM(F8:I8) | DJ8: =SUM(J8:M8) | DK8: =SUM(N8:Q8) | DL8: =SUM(R8:U8) | DM8: =SUM(V8:Y8) | DN8: =SUM(Z8:AC8) | DO8: =SUM(AD8:AG8) | DP8: =SUM(AH8:AK8) | DQ8: =SUM(AL8:AO8) | DR8: =SUM(AP8:AS8) | DS8: =SUM(AT8:AW8) | DT8: =SUM(AX8:BA8) | DU8: =SUM(BB8:BE8) | DV8: =SUM(BF8:BI8) | DW8: =SUM(BJ8:BM8) | DX8: =SUM(BN8:BQ8) | DY8: =SUM(BR8:BU8) | DZ8: =BV8+BW8+BX8+BY8 | EA8: =CC8+CB8+CA8+BZ8 | EB8: =+CD8+CE8+CF8+CG8 | EC8: =SUM(CH8:CK8) | ED8: =SUM(CL8:CO8) | EE8: =SUM(CP8:CS8) | EF8: =SUM(CT8:CW8) | EG8: =SUM(CX8:DA8) | EH8: =SUM(DB8:DE8)
A9: qoq | C9: =C8/B8-1 | D9: =D8/C8-1 | E9: =E8/D8-1 | F9: =F8/E8-1 | G9: =G8/F8-1 | H9: =H8/G8-1 | I9: =I8/H8-1 | J9: =J8/I8-1 | ... DE9: =DE8/DD8-1 | DH9: -- | DI9: -- | DJ9: -- | DK9: -- | DL9: -- | DM9: -- | DN9: -- | DO9: -- | DP9: -- | DQ9: -- | DR9: -- | DS9: -- | DT9: -- | DU9: -- | DV9: -- | DW9: -- | DX9: -- | DY9: -- | DZ9: -- | EA9: -- | EB9: -- | EC9: -- | ED9: -- | EE9: -- | EF9: -- | EG9: -- | EH9: --
A10: yoy | F10: =F8/B8-1 | G10: =G8/C8-1 | H10: =H8/D8-1 | I10: =I8/E8-1 | J10: =J8/F8-1 | K10: =K8/G8-1 | L10: =L8/H8-1 | M10: =M8/I8-1 | ... DE10: =DE8/DA8-1 | DI10: =DI8/DH8-1 | DJ10: =DJ8/DI8-1 | DK10: =DK8/DJ8-1 | DL10: =DL8/DK8-1 | DM10: =DM8/DL8-1 | DN10: =DN8/DM8-1 | DO10: =DO8/DN8-1 | DP10: =DP8/DO8-1 | ... EH10: =EH8/EG8-1
A11: Depreciation | B11: =Ticker0027!V11 | C11: =Ticker0027!W11 | D11: =Ticker0027!X11 | E11: =Ticker0027!Y11 | F11: =Ticker0027!AA11 | G11: =Ticker0027!AB11 | H11: =Ticker0027!AC11 | I11: =Ticker0027!AD11 | J11: =Ticker0027!AF11 | K11: =Ticker0027!AG11 | L11: =Ticker0027!AH11 | M11: =Ticker0027!AI11 | N11: =Ticker0027!AK11 | O11: =Ticker0027!AL11 | P11: =Ticker0027!AM11 | Q11: =Ticker0027!AN11 | R11: =Ticker0027!AP11 | S11: =Ticker0027!AQ11 | T11: =Ticker0027!AR11 | U11: =Ticker0027!AS11 | V11: =Ticker0027!AU11 | W11: =Ticker0027!AV11 | X11: =Ticker0027!AW11 | Y11: =Ticker0027!AX11 | Z11: =Ticker0027!AZ11 | AA11: =Ticker0027!BA11 | AB11: =Ticker0027!BB11 | AC11: =Ticker0027!BC11 | AD11: =Ticker0027!BE11 | AE11: =Ticker0027!BF11 | AF11: =Ticker0027!BG11 | AG11: =Ticker0027!BH11 | AH11: =Ticker0027!BJ11 | AI11: =Ticker0027!BK11 | AJ11: =Ticker0027!BL11 | AK11: =Ticker0027!BM11 | AL11: =Ticker0027!BO11 | AM11: =Ticker0027!BP11 | AN11: =Ticker0027!BQ11 | AO11: =Ticker0027!BR11 | AP11: =Ticker0027!BT11 | AQ11: =Ticker0027!BU11 | AR11: =Ticker0027!BV11 | AS11: =Ticker0027!BW11 | AT11: =Ticker0027!BY11 | AU11: =Ticker0027!BZ11 | AV11: =Ticker0027!CA11 | AW11: =Ticker0027!CB11 | AX11: =Ticker0027!CD11 | AY11: =Ticker0027!CE11 | AZ11: =Ticker0027!CF11 | BA11: =Ticker0027!CG11 | BB11: =Ticker0027!CI11 | BC11: =Ticker0027!CJ11 | BD11: =Ticker0027!CK11 | BE11: =Ticker0027!CL11 | BF11: =Ticker0027!CN11 | BG11: =Ticker0027!CO11 | BH11: =Ticker0027!CP11 | BI11: =Ticker0027!CQ11 | BJ11: =Ticker0027!CS11 | BK11: =Ticker0027!CT11 | BL11: =Ticker0027!CU11 | BM11: =Ticker0027!CV11 | BN11: =Ticker0027!CX11 | BO11: =Ticker0027!CY11 | BP11: =Ticker0027!CZ11 | BQ11: =Ticker0027!DA11 | BR11: =Ticker0027!DC11 | BS11: =Ticker0027!DD11 | BT11: =Ticker0027!DE11 | BU11: =Ticker0027!DF11 | BV11: =Ticker0027!DH11 | BW11: =Ticker0027!DI11 | BX11: =Ticker0027!DJ11 | BY11: =Ticker0027!DK11 | BZ11: =Ticker0027!DM11 | CA11: =Ticker0027!DN11 | CB11: =Ticker0027!DO11 | CC11: =Ticker0027!DP11 | CD11: =Ticker0027!DR11 | CE11: =Ticker0027!DS11 | CF11: =Ticker0027!DT11 | CG11: =Ticker0027!DU11 | CH11: =Ticker0027!DW11 | CI11: =Ticker0027!DX11 | CJ11: =Ticker0027!DY11 | CK11: =Ticker0027!DZ11 | CL11: =Ticker0027!EB11 | CM11: =Ticker0027!EC11 | CN11: =Ticker0027!ED11 | CO11: =Ticker0027!EE11 | CP11: =Ticker0027!EG11 | CQ11: =Ticker0027!EH11 | CR11: =Ticker0027!EI11 | CS11: =Ticker0027!EJ11 | CT11: =Ticker0027!EL11 | CU11: =Ticker0027!EM11 | CV11: =+CU11+5 | CW11: =+CV11+5 | CX11: =+CW11+5 | CY11: =+CX11+5 | CZ11: =+CY11+5 | DA11: =+CZ11+5 | DB11: =+DA11+5 | DC11: =+DB11+5 | ... DE11: =+DD11+5 | DH11: =SUM(B11:E11) | DI11: =SUM(F11:I11) | DJ11: =SUM(J11:M11) | DK11: =SUM(N11:Q11) | DL11: =SUM(R11:U11) | DM11: =SUM(V11:Y11) | DN11: =SUM(Z11:AC11) | DO11: =SUM(AD11:AG11) | DP11: =SUM(AH11:AK11) | DQ11: =SUM(AL11:AO11) | DR11: =SUM(AP11:AS11) | DS11: =SUM(AT11:AW11) | DT11: =SUM(AX11:BA11) | DU11: =SUM(BB11:BE11) | DV11: =SUM(BF11:BI11) | DW11: =SUM(BJ11:BM11) | DX11: =SUM(BN11:BQ11) | DY11: =SUM(BR11:BU11) | DZ11: =BV11+BW11+BX11+BY11 | EA11: =CC11+CB11+CA11+BZ11 | EB11: =+CD11+CE11+CF11+CG11 | EC11: =SUM(CH11:CK11) | ED11: =SUM(CL11:CO11) | EE11: =SUM(CP11:CS11) | EF11: =SUM(CT11:CW11) | EG11: =SUM(CX11:DA11) | EH11: =SUM(DB11:DE11)
A12: qoq | C12: =C11/B11-1 | D12: =D11/C11-1 | E12: =E11/D11-1 | F12: =F11/E11-1 | G12: =G11/F11-1 | H12: =H11/G11-1 | I12: =I11/H11-1 | J12: =J11/I11-1 | ... DE12: =DE11/DD11-1 | DY12: -- | DZ12: -- | EA12: -- | EB12: -- | EC12: -- | ED12: -- | EE12: -- | EF12: -- | EG12: -- | EH12: --
A13: yoy | F13: =F11/B11-1 | G13: =G11/C11-1 | H13: =H11/D11-1 | I13: =I11/E11-1 | J13: =J11/F11-1 | K13: =K11/G11-1 | L13: =L11/H11-1 | M13: =M11/I11-1 | ... DE13: =DE11/DA11-1 | DI13: =DI11/DH11-1 | DJ13: =DJ11/DI11-1 | DK13: =DK11/DJ11-1 | DL13: =DL11/DK11-1 | DM13: =DM11/DL11-1 | DN13: =DN11/DM11-1 | DO13: =DO11/DN11-1 | DP13: =DP11/DO11-1 | ... EH13: =EH11/EG11-1
A14: as a % of revenue | B14: =B11/B$5 | C14: =C11/C$5 | D14: =D11/D$5 | E14: =E11/E$5 | F14: =F11/F$5 | G14: =G11/G$5 | H14: =H11/H$5 | I14: =I11/I$5 | ... DE14: =DE11/DE$5 | DH14: =DH11/DH$5 | DI14: =DI11/DI$5 | DJ14: =DJ11/DJ$5 | DK14: =DK11/DK$5 | DL14: =DL11/DL$5 | DM14: =DM11/DM$5 | DN14: =DN11/DN$5 | DO14: =DO11/DO$5 | ... EH14: =EH11/EH$5
A15: Gross profit | B15: =B5-B8-B11 | C15: =C5-C8-C11 | D15: =D5-D8-D11 | E15: =E5-E8-E11 | F15: =F5-F8-F11 | G15: =G5-G8-G11 | H15: =H5-H8-H11 | I15: =I5-I8-I11 | ... CU15: =CU5-CU8-CU11 | CV15: =CV174 | CW15: =CW174 | CX15: =CX174 | CY15: =CY174 | CZ15: =CZ174 | DA15: =DA174 | DB15: =DB174 | DC15: =DC174 | ... DE15: =DE174 | DH15: =SUM(B15:E15) | DI15: =SUM(F15:I15) | DJ15: =SUM(J15:M15) | DK15: =SUM(N15:Q15) | DL15: =SUM(R15:U15) | DM15: =SUM(V15:Y15) | DN15: =SUM(Z15:AC15) | DO15: =SUM(AD15:AG15) | DP15: =SUM(AH15:AK15) | DQ15: =SUM(AL15:AO15) | DR15: =SUM(AP15:AS15) | DS15: =SUM(AT15:AW15) | DT15: =SUM(AX15:BA15) | DU15: =SUM(BB15:BE15) | DV15: =SUM(BF15:BI15) | DW15: =SUM(BJ15:BM15) | DX15: =SUM(BN15:BQ15) | DY15: =SUM(BR15:BU15) | DZ15: =BV15+BW15+BX15+BY15 | EA15: =CC15+CB15+CA15+BZ15 | EB15: =+CD15+CE15+CF15+CG15 | EC15: =SUM(CH15:CK15) | ED15: =SUM(CL15:CO15) | EE15: =SUM(CP15:CS15) | EF15: =SUM(CT15:CW15) | EG15: =SUM(CX15:DA15) | EH15: =SUM(DB15:DE15)
A16: qoq | C16: =C15/B15-1 | D16: =D15/C15-1 | E16: =E15/D15-1 | F16: =F15/E15-1 | G16: =G15/F15-1 | H16: =H15/G15-1 | I16: =I15/H15-1 | J16: =J15/I15-1 | ... DE16: =DE15/DD15-1 | DH16: -- | DI16: -- | DJ16: -- | DK16: -- | DL16: -- | DM16: -- | DN16: -- | DO16: -- | DP16: -- | DQ16: -- | DR16: -- | DS16: -- | DT16: -- | DU16: -- | DV16: -- | DW16: -- | DX16: -- | DY16: -- | DZ16: -- | EA16: -- | EB16: -- | EC16: -- | ED16: -- | EE16: -- | EF16: -- | EG16: -- | EH16: --
A17: yoy | F17: =F15/B15-1 | G17: =G15/C15-1 | H17: =H15/D15-1 | I17: =I15/E15-1 | J17: =J15/F15-1 | K17: =K15/G15-1 | L17: =L15/H15-1 | M17: =M15/I15-1 | ... DE17: =DE15/DA15-1 | DI17: =DI15/DH15-1 | DJ17: =DJ15/DI15-1 | DK17: =DK15/DJ15-1 | DL17: =DL15/DK15-1 | DM17: =DM15/DL15-1 | DN17: =DN15/DM15-1 | DO17: =DO15/DN15-1 | DP17: =DP15/DO15-1 | ... EH17: =EH15/EG15-1
A18: as a % of revenue | B18: =B15/B$5 | C18: =C15/C$5 | D18: =D15/D$5 | E18: =E15/E$5 | F18: =F15/F$5 | G18: =G15/G$5 | H18: =H15/H$5 | I18: =I15/I$5 | ... DE18: =DE15/DE$5 | DH18: =DH15/DH$5 | DI18: =DI15/DI$5 | DJ18: =DJ15/DJ$5 | DK18: =DK15/DK$5 | DL18: =DL15/DL$5 | DM18: =DM15/DM$5 | DN18: =DN15/DN$5 | DO18: =DO15/DO$5 | ... EH18: =EH15/EH$5
A19: as a % of revenue (ex SBC) | AL19: =(AL15+AL20)/AL5 | AM19: =(AM15+AM20)/AM5 | AN19: =(AN15+AN20)/AN5 | AO19: =(AO15+AO20)/AO5 | AP19: =(AP15+AP20)/AP5 | AQ19: =(AQ15+AQ20)/AQ5 | AR19: =(AR15+AR20)/AR5 | AS19: =(AS15+AS20)/AS5 | ... DE19: =(DE15+DE20)/DE5 | DR19: =(DR15+DR20)/DR5 | DS19: =(DS15+DS20)/DS5 | DT19: =(DT15+DT20)/DT5 | DU19: =(DU15+DU20)/DU5 | DV19: =(DV15+DV20)/DV5 | DW19: =(DW15+DW20)/DW5 | DX19: =(DX15+DX20)/DX5 | DY19: =(DY15+DY20)/DY5 | ... EH19: =(EH15+EH20)/EH5
A20: SBC in GM | AL20: 1.803 | AM20: 2.289 | AN20: 2.49 | AO20: 1.726 | AP20: 2.477 | AQ20: 2.748 | AR20: 3.049 | AS20: 3.048 | AT20: 2.526 | AU20: 2.649 | AV20: 2.489 | AW20: 2.826 | AX20: 2.653 | AY20: 2.168 | AZ20: 3.09 | BA20: 2.777 | BB20: 2.919 | BC20: 3 | BD20: 4 | BE20: 4 | BF20: 2 | BG20: 3 | BH20: 4 | BI20: 5 | BJ20: 4 | BK20: 4 | BL20: 3 | BM20: 4 | BN20: 4 | BO20: 4 | BP20: 6 | BQ20: 7 | BR20: 8 | BS20: 8 | BT20: 5 | BU20: 6 | BV20: 4 | BW20: 8 | BX20: 15 | BY20: 12 | BZ20: 21 | CA20: 14 | CB20: 28 | CC20: 26 | CD20: 25 | CE20: 32 | CF20: 44 | CG20: 39 | CH20: 38 | CI20: 38 | CJ20: 32 | CK20: 30 | CL20: 27 | CM20: 31 | CN20: 38 | CO20: 45 | CP20: 36 | CQ20: 40 | CR20: 50 | CS20: 53 | CT20: 64 | CU20: 58 | CV20: =CU20+1 | CW20: =CV20+1 | CX20: =CW20+1 | CY20: =CX20+1 | CZ20: =CY20+1 | DA20: =CZ20+1 | DB20: =DA20+1 | DC20: =DB20+1 | ... DE20: =DD20+1 | DR20: =SUM(AP20:AS20) | DS20: =SUM(AT20:AW20) | DT20: =SUM(AX20:BA20) | DU20: =SUM(BB20:BE20) | DV20: =SUM(BF20:BI20) | DW20: =SUM(BJ20:BM20) | DX20: =SUM(BN20:BQ20) | DY20: =SUM(BR20:BU20) | DZ20: =BV20+BW20+BX20+BY20 | EA20: =CC20+CB20+CA20+BZ20 | EB20: =+CD20+CE20+CF20+CG20 | EC20: =SUM(CH20:CK20) | ED20: =SUM(CL20:CO20) | EE20: =SUM(CP20:CS20) | EF20: =SUM(CT20:CW20) | EG20: =SUM(CX20:DA20) | EH20: =SUM(DB20:DE20)
A21: Opex (incl SBC) | B21: =B30+B35 | C21: =C30+C35 | D21: =D30+D35 | E21: =E30+E35 | F21: =F30+F35 | G21: =G30+G35 | H21: =H30+H35 | I21: =I30+I35 | ... DE21: =DE30+DE35 | DH21: =SUM(B21:E21) | DI21: =SUM(F21:I21) | DJ21: =SUM(J21:M21) | DK21: =SUM(N21:Q21) | DL21: =SUM(R21:U21) | DM21: =SUM(V21:Y21) | DN21: =SUM(Z21:AC21) | DO21: =SUM(AD21:AG21) | DP21: =SUM(AH21:AK21) | DQ21: =SUM(AL21:AO21) | DR21: =SUM(AP21:AS21) | DS21: =SUM(AT21:AW21) | DT21: =SUM(AX21:BA21) | DU21: =SUM(BB21:BE21) | DV21: =SUM(BF21:BI21) | DW21: =SUM(BJ21:BM21) | DX21: =SUM(BN21:BQ21) | DY21: =SUM(BR21:BU21) | DZ21: =BV21+BW21+BX21+BY21 | EA21: =CC21+CB21+CA21+BZ21 | EB21: =+CD21+CE21+CF21+CG21 | EC21: =SUM(CH21:CK21) | ED21: =SUM(CL21:CO21) | EE21: =SUM(CP21:CS21) | EF21: =SUM(CT21:CW21) | EG21: =SUM(CX21:DA21) | EH21: =SUM(DB21:DE21)
A22: qoq | C22: =C21/B21-1 | D22: =D21/C21-1 | E22: =E21/D21-1 | F22: =F21/E21-1 | G22: =G21/F21-1 | H22: =H21/G21-1 | I22: =I21/H21-1 | J22: =J21/I21-1 | ... DE22: =DE21/DD21-1 | DH22: -- | DI22: -- | DJ22: -- | DK22: -- | DL22: -- | DM22: -- | DN22: -- | DO22: -- | DP22: -- | DQ22: -- | DR22: -- | DS22: -- | DT22: -- | DU22: -- | DV22: -- | DW22: -- | DX22: -- | DY22: -- | DZ22: -- | EA22: -- | EB22: -- | EC22: -- | ED22: -- | EE22: -- | EF22: -- | EG22: -- | EH22: --
A23: yoy | F23: =F21/B21-1 | G23: =G21/C21-1 | H23: =H21/D21-1 | I23: =I21/E21-1 | J23: =J21/F21-1 | K23: =K21/G21-1 | L23: =L21/H21-1 | M23: =M21/I21-1 | ... DE23: =DE21/DA21-1 | DI23: =DI21/DH21-1 | DJ23: =DJ21/DI21-1 | DK23: =DK21/DJ21-1 | DL23: =DL21/DK21-1 | DM23: =DM21/DL21-1 | DN23: =DN21/DM21-1 | DO23: =DO21/DN21-1 | DP23: =DP21/DO21-1 | ... EH23: =EH21/EG21-1
A24: as a % of revenue | B24: =B21/B$5 | C24: =C21/C$5 | D24: =D21/D$5 | E24: =E21/E$5 | F24: =F21/F$5 | G24: =G21/G$5 | H24: =H21/H$5 | I24: =I21/I$5 | ... DE24: =DE21/DE$5 | DH24: =DH21/DH$5 | DI24: =DI21/DI$5 | DJ24: =DJ21/DJ$5 | DK24: =DK21/DK$5 | DL24: =DL21/DL$5 | DM24: =DM21/DM$5 | DN24: =DN21/DN$5 | DO24: =DO21/DO$5 | ... EH24: =EH21/EH$5
A25: Opex (ex SBC) | AL25: =+AL21-AL29 | AM25: =+AM21-AM29 | AN25: =+AN21-AN29 | AO25: =+AO21-AO29 | AP25: =+AP21-AP29 | AQ25: =+AQ21-AQ29 | AR25: =+AR21-AR29 | AS25: =+AS21-AS29 | ... DE25: =+DE21-DE29 | DR25: =SUM(AP25:AS25) | DS25: =SUM(AT25:AW25) | DT25: =SUM(AX25:BA25) | DU25: =SUM(BB25:BE25) | DV25: =SUM(BF25:BI25) | DW25: =SUM(BJ25:BM25) | DX25: =SUM(BN25:BQ25) | DY25: =SUM(BR25:BU25) | DZ25: =BV25+BW25+BX25+BY25 | EA25: =CC25+CB25+CA25+BZ25 | EB25: =+CD25+CE25+CF25+CG25 | EC25: =SUM(CH25:CK25) | ED25: =SUM(CL25:CO25) | EE25: =SUM(CP25:CS25) | EF25: =SUM(CT25:CW25) | EG25: =SUM(CX25:DA25) | EH25: =SUM(DB25:DE25)
A26: qoq | AM26: =AM25/AL25-1 | AN26: =AN25/AM25-1 | AO26: =AO25/AN25-1 | AP26: =AP25/AO25-1 | AQ26: =AQ25/AP25-1 | AR26: =AR25/AQ25-1 | AS26: =AS25/AR25-1 | AT26: =AT25/AS25-1 | ... DE26: =DE25/DD25-1 | DH26: -- | DI26: -- | DJ26: -- | DK26: -- | DL26: -- | DM26: -- | DN26: -- | DO26: -- | DP26: -- | DQ26: -- | DR26: -- | DS26: -- | DT26: -- | DU26: -- | DV26: -- | DW26: -- | DX26: -- | DY26: -- | DZ26: -- | EA26: -- | EB26: -- | EC26: -- | ED26: -- | EE26: -- | EF26: -- | EG26: -- | EH26: --
A27: yoy | AP27: =AP25/AL25-1 | AQ27: =AQ25/AM25-1 | AR27: =AR25/AN25-1 | AS27: =AS25/AO25-1 | AT27: =AT25/AP25-1 | AU27: =AU25/AQ25-1 | AV27: =AV25/AR25-1 | AW27: =AW25/AS25-1 | ... DE27: =DE25/DA25-1 | DS27: =DS25/DR25-1 | DT27: =DT25/DS25-1 | DU27: =DU25/DT25-1 | DV27: =DV25/DU25-1 | DW27: =DW25/DV25-1 | DX27: =DX25/DW25-1 | DY27: =DY25/DX25-1 | DZ27: =DZ25/DY25-1 | ... EH27: =EH25/EG25-1
A28: as a % of revenue | AL28: =AL25/AL5 | AM28: =AM25/AM5 | AN28: =AN25/AN5 | AO28: =AO25/AO5 | AP28: =AP25/AP5 | AQ28: =AQ25/AQ5 | AR28: =AR25/AR5 | AS28: =AS25/AS5 | ... DE28: =DE25/DE5 | DR28: =DR25/DR5 | DS28: =DS25/DS5 | DT28: =DT25/DT5 | DU28: =DU25/DU5 | DV28: =DV25/DV5 | DW28: =DW25/DW5 | DX28: =DX25/DX5 | DY28: =DY25/DY5 | ... EH28: =EH25/EH5
A29: SBC in opex | AL29: =+AL34+AL39 | AM29: =+AM34+AM39 | AN29: =+AN34+AN39 | AO29: =+AO34+AO39 | AP29: =+AP34+AP39 | AQ29: =+AQ34+AQ39 | AR29: =+AR34+AR39 | AS29: =+AS34+AS39 | ... BZ29: =+BZ34+BZ39 | CA29: =132+228 | CB29: =+CB34+CB39 | CC29: =+CC34+CC39 | CD29: =+CD34+CD39 | CE29: =+CE34+CE39 | CF29: =+CF34+CF39 | CG29: =+CG34+CG39 | CH29: =+CH34+CH39 | CI29: =+CI34+CI39 | ... CU29: =+CU34+CU39 | CV29: =CU29*1.05 | CW29: =CV29*1.02 | CX29: =CW29*1.02 | CY29: =CX29*1.02 | CZ29: =CY29*1.02 | DA29: =CZ29*1.02 | DB29: =DA29*1.02 | DC29: =DB29*1.02 | DD29: =DC29*1.02 | DE29: =DD29*1.02 | DR29: =SUM(AP29:AS29) | DS29: =SUM(AT29:AW29) | DT29: =SUM(AX29:BA29) | DU29: =SUM(BB29:BE29) | DV29: =SUM(BF29:BI29) | DW29: =SUM(BJ29:BM29) | DX29: =SUM(BN29:BQ29) | DY29: =SUM(BR29:BU29) | DZ29: =BV29+BW29+BX29+BY29 | EA29: =CC29+CB29+CA29+BZ29 | EB29: =+CD29+CE29+CF29+CG29 | EC29: =SUM(CH29:CK29) | ED29: =SUM(CL29:CO29) | EE29: =SUM(CP29:CS29) | EF29: =SUM(CT29:CW29) | EG29: =SUM(CX29:DA29) | EH29: =SUM(DB29:DE29)
A30: R&D | B30: =Ticker0027!V19 | C30: =Ticker0027!W19 | D30: =Ticker0027!X19 | E30: =Ticker0027!Y19 | F30: =Ticker0027!AA19 | G30: =Ticker0027!AB19 | H30: =Ticker0027!AC19 | I30: =Ticker0027!AD19 | J30: =Ticker0027!AF19 | K30: =Ticker0027!AG19 | L30: =Ticker0027!AH19 | M30: =Ticker0027!AI19 | N30: =Ticker0027!AK19 | O30: =Ticker0027!AL19 | P30: =Ticker0027!AM19 | Q30: =Ticker0027!AN19 | R30: =Ticker0027!AP19 | S30: =Ticker0027!AQ19 | T30: =Ticker0027!AR19 | U30: =Ticker0027!AS19 | V30: =Ticker0027!AU19 | W30: =Ticker0027!AV19 | X30: =Ticker0027!AW19 | Y30: =Ticker0027!AX19 | Z30: =Ticker0027!AZ19 | AA30: =Ticker0027!BA19 | AB30: =Ticker0027!BB19 | AC30: =Ticker0027!BC19 | AD30: =Ticker0027!BE19 | AE30: =Ticker0027!BF19 | AF30: =Ticker0027!BG19 | AG30: =Ticker0027!BH19 | AH30: =Ticker0027!BJ19 | AI30: =Ticker0027!BK19 | AJ30: =Ticker0027!BL19 | AK30: =Ticker0027!BM19 | AL30: =Ticker0027!BO19 | AM30: =Ticker0027!BP19 | AN30: =Ticker0027!BQ19 | AO30: =Ticker0027!BR19 | AP30: =Ticker0027!BT19 | AQ30: =Ticker0027!BU19 | AR30: =Ticker0027!BV19 | AS30: =Ticker0027!BW19 | AT30: =Ticker0027!BY19 | AU30: =Ticker0027!BZ19 | AV30: =Ticker0027!CA19 | AW30: =Ticker0027!CB19 | AX30: =Ticker0027!CD19 | AY30: =Ticker0027!CE19 | AZ30: =Ticker0027!CF19 | BA30: =Ticker0027!CG19 | BB30: =Ticker0027!CI19 | BC30: =Ticker0027!CJ19 | BD30: =Ticker0027!CK19 | BE30: =Ticker0027!CL19 | BF30: =Ticker0027!CN19 | BG30: =Ticker0027!CO19 | BH30: =Ticker0027!CP19 | BI30: =Ticker0027!CQ19 | BJ30: =Ticker0027!CS19 | BK30: =Ticker0027!CT19 | BL30: =Ticker0027!CU19 | BM30: =Ticker0027!CV19 | BN30: =Ticker0027!CX19 | BO30: =Ticker0027!CY19 | BP30: =Ticker0027!CZ19 | BQ30: =Ticker0027!DA19 | BR30: =Ticker0027!DC19 | BS30: =Ticker0027!DD19 | BT30: =Ticker0027!DE19 | BU30: =Ticker0027!DF19 | BV30: =Ticker0027!DH19 | BW30: =Ticker0027!DI19 | BX30: =Ticker0027!DJ19 | BY30: =Ticker0027!DK19 | BZ30: =Ticker0027!DM19 | CA30: =Ticker0027!DN19 | CB30: =Ticker0027!DO19 | CC30: =Ticker0027!DP19 | CD30: =Ticker0027!DR19 | CE30: =Ticker0027!DS19 | CF30: =Ticker0027!DT19 | CG30: =Ticker0027!DU19 | CH30: =Ticker0027!DW19 | CI30: =Ticker0027!DX19 | CJ30: =Ticker0027!DY19 | CK30: =Ticker0027!DZ19 | CL30: =Ticker0027!EB19 | CM30: =Ticker0027!EC19 | CN30: =Ticker0027!ED19 | CO30: =Ticker0027!EE19 | CP30: =Ticker0027!EG19 | CQ30: =Ticker0027!EH19 | CR30: =Ticker0027!EI19 | CS30: =Ticker0027!EJ19 | CT30: =Ticker0027!EL19 | CU30: =Ticker0027!EM19 | CV30: =CU30*(1+CV31) | CW30: =CV30*(1+CW31) | CX30: =CW30*(1+CX31) | CY30: =CX30*(1+CY31) | CZ30: =CY30*(1+CZ31) | DA30: =CZ30*(1+DA31) | DB30: =DA30*(1+DB31) | DC30: =DB30*(1+DC31) | ... DE30: =DD30*(1+DE31) | DH30: =SUM(B30:E30) | DI30: =SUM(F30:I30) | DJ30: =SUM(J30:M30) | DK30: =SUM(N30:Q30) | DL30: =SUM(R30:U30) | DM30: =SUM(V30:Y30) | DN30: =SUM(Z30:AC30) | DO30: =SUM(AD30:AG30) | DP30: =SUM(AH30:AK30) | DQ30: =SUM(AL30:AO30) | DR30: =SUM(AP30:AS30) | DS30: =SUM(AT30:AW30) | DT30: =SUM(AX30:BA30) | DU30: =SUM(BB30:BE30) | DV30: =SUM(BF30:BI30) | DW30: =SUM(BJ30:BM30) | DX30: =SUM(BN30:BQ30) | DY30: =SUM(BR30:BU30) | DZ30: =BV30+BW30+BX30+BY30 | EA30: =CC30+CB30+CA30+BZ30 | EB30: =+CD30+CE30+CF30+CG30 | EC30: =SUM(CH30:CK30) | ED30: =SUM(CL30:CO30) | EE30: =SUM(CP30:CS30) | EF30: =SUM(CT30:CW30) | EG30: =SUM(CX30:DA30) | EH30: =SUM(DB30:DE30)
A31: qoq | C31: =C30/B30-1 | D31: =D30/C30-1 | E31: =E30/D30-1 | F31: =F30/E30-1 | G31: =G30/F30-1 | H31: =H30/G30-1 | I31: =I30/H30-1 | J31: =J30/I30-1 | ... CU31: =CU30/CT30-1 | CV31: 0.09 | CW31: 0.07 | CX31: 0.02 | CY31: 0.03 | CZ31: 0.03 | DA31: 0.03 | DB31: 0.03 | DC31: 0.02 | DD31: 0.02 | DE31: 0.01 | DH31: -- | DI31: -- | DJ31: -- | DK31: -- | DL31: -- | DM31: -- | DN31: -- | DO31: -- | DP31: -- | DQ31: -- | DR31: -- | DS31: -- | DT31: -- | DU31: -- | DV31: -- | DW31: -- | DX31: -- | DY31: -- | DZ31: -- | EA31: -- | EB31: -- | EC31: -- | ED31: -- | EE31: -- | EF31: -- | EG31: -- | EH31: --
A32: yoy | F32: =F30/B30-1 | G32: =G30/C30-1 | H32: =H30/D30-1 | I32: =I30/E30-1 | J32: =J30/F30-1 | K32: =K30/G30-1 | L32: =L30/H30-1 | M32: =M30/I30-1 | ... DE32: =DE30/DA30-1 | DI32: =DI30/DH30-1 | DJ32: =DJ30/DI30-1 | DK32: =DK30/DJ30-1 | DL32: =DL30/DK30-1 | DM32: =DM30/DL30-1 | DN32: =DN30/DM30-1 | DO32: =DO30/DN30-1 | DP32: =DP30/DO30-1 | ... EH32: =EH30/EG30-1
A33: as a % of revenue | B33: =B30/B$5 | C33: =C30/C$5 | D33: =D30/D$5 | E33: =E30/E$5 | F33: =F30/F$5 | G33: =G30/G$5 | H33: =H30/H$5 | I33: =I30/I$5 | ... DE33: =DE30/DE$5 | DH33: =DH30/DH$5 | DI33: =DI30/DI$5 | DJ33: =DJ30/DJ$5 | DK33: =DK30/DK$5 | DL33: =DL30/DL$5 | DM33: =DM30/DM$5 | DN33: =DN30/DN$5 | DO33: =DO30/DO$5 | ... EH33: =EH30/EH$5
A34: SBC in R&D | AL34: 14.614 | AM34: 14.532 | AN34: 14.104 | AO34: 14.724 | AP34: 18.589 | AQ34: 21.697 | AR34: 19.308 | AS34: 20.908 | AT34: 21.207 | AU34: 18.885 | AV34: 20.056 | AW34: 22.009 | AX34: 21.935 | AY34: 18.555 | AZ34: 20.902 | BA34: 21.548 | BB34: 20.494 | BC34: 21 | BD34: 22 | BE34: 23 | BF34: 27 | BG34: 27 | BH34: 28 | BI34: 33 | BJ34: 29 | BK34: 30 | BL34: 35 | BM34: 40 | BN34: 41 | BO34: 44 | BP34: 61 | BQ34: 73 | BR34: 74 | BS34: 76 | BT34: 88 | BU34: 99 | BV34: 114 | BW34: 145 | BX34: 141 | BY34: 140 | BZ34: 134 | CA34: 228 | CB34: 232 | CC34: 266 | CD34: 276 | CE34: 297 | CF34: 363 | CG34: 362 | CH34: 384 | CI34: 452 | CJ34: 530 | CK34: 527 | CL34: 524 | CM34: 600 | CN34: 701 | CO34: 706 | CP34: 727 | CQ34: 832 | CR34: 910 | CS34: 955 | CT34: 1063 | CU34: 1191 | CV34: =+CV29*CU34/CU29 | CW34: =+CW29*CV34/CV29 | CX34: =+CX29*CW34/CW29 | CY34: =+CY29*CX34/CX29 | CZ34: =+CZ29*CY34/CY29 | DA34: =+DA29*CZ34/CZ29 | DB34: =+DB29*DA34/DA29 | DC34: =+DC29*DB34/DB29 | ... DE34: =+DE29*DD34/DD29 | DR34: =SUM(AP34:AS34) | DS34: =SUM(AT34:AW34) | DT34: =SUM(AX34:BA34) | DU34: =SUM(BB34:BE34) | DV34: =SUM(BF34:BI34) | DW34: =SUM(BJ34:BM34) | DX34: =SUM(BN34:BQ34) | DY34: =SUM(BR34:BU34) | DZ34: =BV34+BW34+BX34+BY34 | EA34: =CC34+CB34+CA34+BZ34 | EB34: =+CD34+CE34+CF34+CG34 | EC34: =SUM(CH34:CK34) | ED34: =SUM(CL34:CO34) | EE34: =SUM(CP34:CS34) | EF34: =SUM(CT34:CW34) | EG34: =SUM(CX34:DA34) | EH34: =SUM(DB34:DE34)
A35: SG&A | B35: =Ticker0027!V17 | C35: =Ticker0027!W17 | D35: =Ticker0027!X17 | E35: =Ticker0027!Y17 | F35: =Ticker0027!AA17 | G35: =Ticker0027!AB17 | H35: =Ticker0027!AC17 | I35: =Ticker0027!AD17 | J35: =Ticker0027!AF17 | K35: =Ticker0027!AG17 | L35: =Ticker0027!AH17 | M35: =Ticker0027!AI17 | N35: =Ticker0027!AK17 | O35: =Ticker0027!AL17 | P35: =Ticker0027!AM17 | Q35: =Ticker0027!AN17 | R35: =Ticker0027!AP17 | S35: =Ticker0027!AQ17 | T35: =Ticker0027!AR17 | U35: =Ticker0027!AS17 | V35: =Ticker0027!AU17 | W35: =Ticker0027!AV17 | X35: =Ticker0027!AW17 | Y35: =Ticker0027!AX17 | Z35: =Ticker0027!AZ17 | AA35: =Ticker0027!BA17 | AB35: =Ticker0027!BB17 | AC35: =Ticker0027!BC17 | AD35: =Ticker0027!BE17 | AE35: =Ticker0027!BF17 | AF35: =Ticker0027!BG17 | AG35: =Ticker0027!BH17 | AH35: =Ticker0027!BJ17 | AI35: =Ticker0027!BK17 | AJ35: =Ticker0027!BL17 | AK35: =Ticker0027!BM17 | AL35: =Ticker0027!BO17 | AM35: =Ticker0027!BP17 | AN35: =Ticker0027!BQ17 | AO35: =Ticker0027!BR17 | AP35: =Ticker0027!BT17 | AQ35: =Ticker0027!BU17 | AR35: =Ticker0027!BV17 | AS35: =Ticker0027!BW17 | AT35: =Ticker0027!BY17 | AU35: =Ticker0027!BZ17 | AV35: =Ticker0027!CA17 | AW35: =Ticker0027!CB17 | AX35: =Ticker0027!CD17 | AY35: =Ticker0027!CE17 | AZ35: =Ticker0027!CF17 | BA35: =Ticker0027!CG17 | BB35: =Ticker0027!CI17 | BC35: =Ticker0027!CJ17 | BD35: =Ticker0027!CK17 | BE35: =Ticker0027!CL17 | BF35: =Ticker0027!CN17 | BG35: =Ticker0027!CO17 | BH35: =Ticker0027!CP17 | BI35: =Ticker0027!CQ17 | BJ35: =Ticker0027!CS17 | BK35: =Ticker0027!CT17 | BL35: =Ticker0027!CU17 | BM35: =Ticker0027!CV17 | BN35: =Ticker0027!CX17 | BO35: =Ticker0027!CY17 | BP35: =Ticker0027!CZ17 | BQ35: =Ticker0027!DA17 | BR35: =Ticker0027!DC17 | BS35: =Ticker0027!DD17 | BT35: =Ticker0027!DE17 | BU35: =Ticker0027!DF17 | BV35: =Ticker0027!DH17 | BW35: =Ticker0027!DI17 | BX35: =Ticker0027!DJ17 | BY35: =Ticker0027!DK17 | BZ35: =Ticker0027!DM17 | CA35: =Ticker0027!DN17 | CB35: =Ticker0027!DO17 | CC35: =Ticker0027!DP17 | CD35: =Ticker0027!DR17 | CE35: =Ticker0027!DS17 | CF35: =Ticker0027!DT17 | CG35: =Ticker0027!DU17 | CH35: =Ticker0027!DW17 | CI35: =Ticker0027!DX17 | CJ35: =Ticker0027!DY17 | CK35: =Ticker0027!DZ17 | CL35: =Ticker0027!EB17 | CM35: =Ticker0027!EC17 | CN35: =Ticker0027!ED17 | CO35: =Ticker0027!EE17 | CP35: =Ticker0027!EG17 | CQ35: =Ticker0027!EH17 | CR35: =Ticker0027!EI17 | CS35: =Ticker0027!EJ17 | CT35: =Ticker0027!EL17 | CU35: =Ticker0027!EM17 | CV35: =CU35*(1+CV36) | CW35: =CV35*(1+CW36) | CX35: =CW35*(1+CX36) | CY35: =CX35*(1+CY36) | CZ35: =CY35*(1+CZ36) | DA35: =CZ35*(1+DA36) | DB35: =DA35*(1+DB36) | DC35: =DB35*(1+DC36) | ... DE35: =DD35*(1+DE36) | DH35: =SUM(B35:E35) | DI35: =SUM(F35:I35) | DJ35: =SUM(J35:M35) | DK35: =SUM(N35:Q35) | DL35: =SUM(R35:U35) | DM35: =SUM(V35:Y35) | DN35: =SUM(Z35:AC35) | DO35: =SUM(AD35:AG35) | DP35: =SUM(AH35:AK35) | DQ35: =SUM(AL35:AO35) | DR35: =SUM(AP35:AS35) | DS35: =SUM(AT35:AW35) | DT35: =SUM(AX35:BA35) | DU35: =SUM(BB35:BE35) | DV35: =SUM(BF35:BI35) | DW35: =SUM(BJ35:BM35) | DX35: =SUM(BN35:BQ35) | DY35: =SUM(BR35:BU35) | DZ35: =BV35+BW35+BX35+BY35 | EA35: =CC35+CB35+CA35+BZ35 | EB35: =+CD35+CE35+CF35+CG35 | EC35: =SUM(CH35:CK35) | ED35: =SUM(CL35:CO35) | EE35: =SUM(CP35:CS35) | EF35: =SUM(CT35:CW35) | EG35: =SUM(CX35:DA35) | EH35: =SUM(DB35:DE35)
A36: qoq | C36: =C35/B35-1 | D36: =D35/C35-1 | E36: =E35/D35-1 | F36: =F35/E35-1 | G36: =G35/F35-1 | H36: =H35/G35-1 | I36: =I35/H35-1 | J36: =J35/I35-1 | ... CU36: =CU35/CT35-1 | CV36: 0.09 | CW36: 0.06 | CX36: 0.04 | CY36: 0.03 | CZ36: 0.03 | DA36: 0.03 | DB36: 0.02 | DC36: 0.01 | DD36: 0.01 | DE36: 0.01 | DH36: -- | DI36: -- | DJ36: -- | DK36: -- | DL36: -- | DM36: -- | DN36: -- | DO36: -- | DP36: -- | DQ36: -- | DR36: -- | DS36: -- | DT36: -- | DU36: -- | DV36: -- | DW36: -- | DX36: -- | DY36: -- | DZ36: -- | EA36: -- | EB36: -- | EC36: -- | ED36: -- | EE36: -- | EF36: -- | EG36: -- | EH36: --
A37: yoy | F37: =F35/B35-1 | G37: =G35/C35-1 | H37: =H35/D35-1 | I37: =I35/E35-1 | J37: =J35/F35-1 | K37: =K35/G35-1 | L37: =L35/H35-1 | M37: =M35/I35-1 | ... DE37: =DE35/DA35-1 | DI37: =DI35/DH35-1 | DJ37: =DJ35/DI35-1 | DK37: =DK35/DJ35-1 | DL37: =DL35/DK35-1 | DM37: =DM35/DL35-1 | DN37: =DN35/DM35-1 | DO37: =DO35/DN35-1 | DP37: =DP35/DO35-1 | ... EH37: =EH35/EG35-1
A38: as a % of revenue | B38: =B35/B$5 | C38: =C35/C$5 | D38: =D35/D$5 | E38: =E35/E$5 | F38: =F35/F$5 | G38: =G35/G$5 | H38: =H35/H$5 | I38: =I35/I$5 | ... DE38: =DE35/DE$5 | DH38: =DH35/DH$5 | DI38: =DI35/DI$5 | DJ38: =DJ35/DJ$5 | DK38: =DK35/DK$5 | DL38: =DL35/DL$5 | DM38: =DM35/DM$5 | DN38: =DN35/DN$5 | DO38: =DO35/DO$5 | ... EH38: =EH35/EH$5
A39: SBC in SGA | AL39: 8.76 | AM39: 7.81 | AN39: 8.585 | AO39: 8.916 | AP39: 10.673 | AQ39: 11.505 | AR39: 10.872 | AS39: 11.48 | AT39: 11.836 | AU39: 10.721 | AV39: 10.524 | AW39: 10.934 | AX39: 8.809 | AY39: 11.687 | AZ39: 10.307 | BA39: 11.879 | BB39: 12.108 | BC39: 14 | BD39: 16 | BE39: 15 | BF39: 16 | BG39: 17 | BH39: 19 | BI39: 22 | BJ39: 20 | BK39: 24 | BL39: 27 | BM39: 27 | BN39: 31 | BO39: 33 | BP39: 40 | BQ39: 46 | BR39: 47 | BS39: 48 | BT39: 47 | BU39: 51 | BV39: 60 | BW39: 71 | BX39: 67 | BY39: 68 | BZ39: 69 | CA39: 132 | CB39: 123 | CC39: 125 | CD39: 128 | CE39: 136 | CF39: 152 | CG39: 150 | CH39: 156 | CI39: 159 | CJ39: 183 | CK39: 182 | CL39: 184 | CM39: 211 | CN39: 240 | CO39: 242 | CP39: 248 | CQ39: 282 | CR39: 292 | CS39: 313 | CT39: 347 | CU39: 375 | CV39: =+CV29-CV34 | CW39: =+CW29-CW34 | CX39: =+CX29-CX34 | CY39: =+CY29-CY34 | CZ39: =+CZ29-CZ34 | DA39: =+DA29-DA34 | DB39: =+DB29-DB34 | DC39: =+DC29-DC34 | ... DE39: =+DE29-DE34 | DR39: =SUM(AP39:AS39) | DS39: =SUM(AT39:AW39) | DT39: =SUM(AX39:BA39) | DU39: =SUM(BB39:BE39) | DV39: =SUM(BF39:BI39) | DW39: =SUM(BJ39:BM39) | DX39: =SUM(BN39:BQ39) | DY39: =SUM(BR39:BU39) | DZ39: =BV39+BW39+BX39+BY39 | EA39: =CC39+CB39+CA39+BZ39 | EB39: =+CD39+CE39+CF39+CG39 | EC39: =SUM(CH39:CK39) | ED39: =SUM(CL39:CO39) | EE39: =SUM(CP39:CS39) | EF39: =SUM(CT39:CW39) | EG39: =SUM(CX39:DA39) | EH39: =SUM(DB39:DE39)
A40: Op profit (incl SBC) | B40: =B15-B30-B35 | C40: =C15-C30-C35 | D40: =D15-D30-D35 | E40: =E15-E30-E35 | F40: =F15-F30-F35 | G40: =G15-G30-G35 | H40: =H15-H30-H35 | I40: =I15-I30-I35 | ... DE40: =DE15-DE30-DE35 | DH40: =SUM(B40:E40) | DI40: =SUM(F40:I40) | DJ40: =SUM(J40:M40) | DK40: =SUM(N40:Q40) | DL40: =SUM(R40:U40) | DM40: =SUM(V40:Y40) | DN40: =SUM(Z40:AC40) | DO40: =SUM(AD40:AG40) | DP40: =SUM(AH40:AK40) | DQ40: =SUM(AL40:AO40) | DR40: =SUM(AP40:AS40) | DS40: =SUM(AT40:AW40) | DT40: =SUM(AX40:BA40) | DU40: =SUM(BB40:BE40) | DV40: =SUM(BF40:BI40) | DW40: =SUM(BJ40:BM40) | DX40: =SUM(BN40:BQ40) | DY40: =SUM(BR40:BU40) | DZ40: =BV40+BW40+BX40+BY40 | EA40: =CC40+CB40+CA40+BZ40 | EB40: =+CD40+CE40+CF40+CG40 | EC40: =SUM(CH40:CK40) | ED40: =SUM(CL40:CO40) | EE40: =SUM(CP40:CS40) | EF40: =SUM(CT40:CW40) | EG40: =SUM(CX40:DA40) | EH40: =SUM(DB40:DE40)
A41: qoq | C41: =C40/B40-1 | D41: =D40/C40-1 | E41: =E40/D40-1 | F41: =F40/E40-1 | G41: =G40/F40-1 | H41: =H40/G40-1 | I41: =I40/H40-1 | J41: =J40/I40-1 | ... DE41: =DE40/DD40-1 | DH41: -- | DI41: -- | DJ41: -- | DK41: -- | DL41: -- | DM41: -- | DN41: -- | DO41: -- | DP41: -- | DQ41: -- | DR41: -- | DS41: -- | DT41: -- | DU41: -- | DV41: -- | DW41: -- | DX41: -- | DY41: -- | DZ41: -- | EA41: -- | EB41: -- | EC41: -- | ED41: -- | EE41: -- | EF41: -- | EG41: -- | EH41: --
A42: yoy | F42: =F40/B40-1 | G42: =G40/C40-1 | H42: =H40/D40-1 | I42: =I40/E40-1 | J42: =J40/F40-1 | K42: =K40/G40-1 | L42: =L40/H40-1 | M42: =M40/I40-1 | ... DE42: =DE40/DA40-1 | DI42: =DI40/DH40-1 | DJ42: =DJ40/DI40-1 | DK42: =DK40/DJ40-1 | DL42: =DL40/DK40-1 | DM42: =DM40/DL40-1 | DN42: =DN40/DM40-1 | DO42: =DO40/DN40-1 | DP42: =DP40/DO40-1 | ... EH42: =EH40/EG40-1
A43: as a % of revenue | B43: =B40/B$5 | C43: =C40/C$5 | D43: =D40/D$5 | E43: =E40/E$5 | F43: =F40/F$5 | G43: =G40/G$5 | H43: =H40/H$5 | I43: =I40/I$5 | ... DE43: =DE40/DE$5 | DH43: =DH40/DH$5 | DI43: =DI40/DI$5 | DJ43: =DJ40/DJ$5 | DK43: =DK40/DK$5 | DL43: =DL40/DL$5 | DM43: =DM40/DM$5 | DN43: =DN40/DN$5 | DO43: =DO40/DO$5 | ... EH43: =EH40/EH$5
A44: Op profit (ex SBC) | AL44: =AL40+AL29+AL20 | AM44: =AM40+AM29+AM20 | AN44: =AN40+AN29+AN20 | AO44: =AO40+AO29+AO20 | AP44: =AP40+AP29+AP20 | AQ44: =AQ40+AQ29+AQ20 | AR44: =AR40+AR29+AR20 | AS44: =AS40+AS29+AS20 | ... DE44: =DE40+DE29+DE20 | DR44: =DR40+DR29+DR20 | DS44: =DS40+DS29+DS20 | DT44: =DT40+DT29+DT20 | DU44: =DU40+DU29+DU20 | DV44: =DV40+DV29+DV20 | DW44: =DW40+DW29+DW20 | DX44: =DX40+DX29+DX20 | DY44: =DY40+DY29+DY20 | ... EH44: =EH40+EH29+EH20
A45: qoq | AM45: =AM44/AL44-1 | AN45: =AN44/AM44-1 | AO45: =AO44/AN44-1 | AP45: =AP44/AO44-1 | AQ45: =AQ44/AP44-1 | AR45: =AR44/AQ44-1 | AS45: =AS44/AR44-1 | AT45: =AT44/AS44-1 | ... DE45: =DE44/DD44-1 | DH45: -- | DI45: -- | DJ45: -- | DK45: -- | DL45: -- | DM45: -- | DN45: -- | DO45: -- | DP45: -- | DQ45: -- | DR45: -- | DS45: -- | DT45: -- | DU45: -- | DV45: -- | DW45: -- | DX45: -- | DY45: -- | DZ45: -- | EA45: -- | EB45: -- | EC45: -- | ED45: -- | EE45: -- | EF45: -- | EG45: -- | EH45: --
A46: yoy | AP46: =AP44/AL44-1 | AQ46: =AQ44/AM44-1 | AR46: =AR44/AN44-1 | AS46: =AS44/AO44-1 | AT46: =AT44/AP44-1 | AU46: =AU44/AQ44-1 | AV46: =AV44/AR44-1 | AW46: =AW44/AS44-1 | ... DE46: =DE44/DA44-1 | DS46: =DS44/DR44-1 | DT46: =DT44/DS44-1 | DU46: =DU44/DT44-1 | DV46: =DV44/DU44-1 | DW46: =DW44/DV44-1 | DX46: =DX44/DW44-1 | DY46: =DY44/DX44-1 | DZ46: =DZ44/DY44-1 | ... EH46: =EH44/EG44-1
A47: as a % of revenue | AL47: =+AL44/AL5 | AM47: =+AM44/AM5 | AN47: =+AN44/AN5 | AO47: =+AO44/AO5 | AP47: =+AP44/AP5 | AQ47: =+AQ44/AQ5 | AR47: =+AR44/AR5 | AS47: =+AS44/AS5 | ... DE47: =+DE44/DE5 | DR47: =+DR44/DR5 | DS47: =+DS44/DS5 | DT47: =+DT44/DT5 | DU47: =+DU44/DU5 | DV47: =+DV44/DV5 | DW47: =+DW44/DW5 | DX47: =+DX44/DX5 | DY47: =+DY44/DY5 | ... EH47: =+EH44/EH5
A49: Op EPS | B49: =Ticker0027!V54 | C49: =Ticker0027!W54 | D49: =Ticker0027!X54 | E49: =Ticker0027!Y54 | F49: =Ticker0027!AA54 | G49: =Ticker0027!AB54 | H49: =Ticker0027!AC54 | I49: =Ticker0027!AD54 | J49: =Ticker0027!AF54 | K49: =Ticker0027!AG54 | L49: =Ticker0027!AH54 | M49: =Ticker0027!AI54 | N49: =Ticker0027!AK54 | O49: =Ticker0027!AL54 | P49: =Ticker0027!AM54 | Q49: =Ticker0027!AN54 | R49: =Ticker0027!AP54 | S49: =Ticker0027!AQ54 | T49: =Ticker0027!AR54 | U49: =Ticker0027!AS54 | V49: =Ticker0027!AU54 | W49: =Ticker0027!AV54 | X49: =Ticker0027!AW54 | Y49: =Ticker0027!AX54 | Z49: =Ticker0027!AZ54 | AA49: =Ticker0027!BA54 | AB49: =Ticker0027!BB54 | AC49: =Ticker0027!BC54 | AD49: =Ticker0027!BE54 | AE49: =Ticker0027!BF54 | AF49: =Ticker0027!BG54 | AG49: =Ticker0027!BH54 | AH49: =Ticker0027!BJ54 | AI49: =Ticker0027!BK54 | AJ49: =Ticker0027!BL54 | AK49: =Ticker0027!BM54 | AL49: =Ticker0027!BO54 | AM49: =Ticker0027!BP54 | AN49: =Ticker0027!BQ54 | AO49: =Ticker0027!BR54 | AP49: =Ticker0027!BT54 | AQ49: =Ticker0027!BU54 | AR49: =Ticker0027!BV54 | AS49: =Ticker0027!BW54 | AT49: =Ticker0027!BY54 | AU49: =Ticker0027!BZ54 | AV49: =Ticker0027!CA54 | AW49: =Ticker0027!CB54 | AX49: =Ticker0027!CD54 | AY49: =Ticker0027!CE54 | AZ49: =Ticker0027!CF54 | BA49: =Ticker0027!CG54 | BB49: =Ticker0027!CI54 | BC49: =Ticker0027!CJ54 | BD49: =Ticker0027!CK54 | BE49: =Ticker0027!CL54 | BF49: =Ticker0027!CN54 | BG49: =Ticker0027!CO54 | BH49: =Ticker0027!CP54 | BI49: =Ticker0027!CQ54 | BJ49: =Ticker0027!CS54 | BK49: =Ticker0027!CT54 | BL49: =Ticker0027!CU54 | BM49: =Ticker0027!CV54 | BN49: =Ticker0027!CX54 | BO49: =Ticker0027!CY54 | BP49: =Ticker0027!CZ54 | BQ49: =Ticker0027!DA54 | BR49: =Ticker0027!DC54 | BS49: =Ticker0027!DD54 | BT49: =Ticker0027!DE54 | BU49: =Ticker0027!DF54 | BV49: =Ticker0027!DH54 | BW49: =Ticker0027!DI54 | BX49: =Ticker0027!DJ54 | BY49: =Ticker0027!DK54 | BZ49: =Ticker0027!DM54 | CA49: =Ticker0027!DN54 | CB49: =Ticker0027!DO54 | CC49: =Ticker0027!DP54 | CD49: =Ticker0027!DR54 | CE49: =Ticker0027!DS54 | CF49: =Ticker0027!DT54 | CG49: =Ticker0027!DU54 | CH49: =Ticker0027!DW54 | CI49: =Ticker0027!DX54 | CJ49: =Ticker0027!DY54 | CK49: =Ticker0027!DZ54 | CL49: =Ticker0027!EB54 | CM49: =Ticker0027!EC54 | CN49: =Ticker0027!ED54 | CO49: =Ticker0027!EE54 | CP49: =Ticker0027!EG54 | CQ49: =Ticker0027!EH54 | CR49: =Ticker0027!EI54 | CS49: =Ticker0027!EJ54 | CT49: =Ticker0027!EL54 | CU49: =Ticker0027!EM54 | CV49: =Ticker0027!EN54 | CW49: =Ticker0027!EO54 | CX49: =Ticker0027!EQ54 | CY49: =Ticker0027!ER54 | CZ49: =Ticker0027!ES54 | DA49: =Ticker0027!ET54 | DB49: =Ticker0027!EV54 | DC49: =Ticker0027!EW54 | DD49: =Ticker0027!EX54 | DE49: =Ticker0027!EY54 | DH49: =SUM(B49:E49) | DI49: =SUM(F49:I49) | DJ49: =SUM(J49:M49) | DK49: =SUM(N49:Q49) | DL49: =SUM(R49:U49) | DM49: =SUM(V49:Y49) | DN49: =SUM(Z49:AC49) | DO49: =SUM(AD49:AG49) | DP49: =SUM(AH49:AK49) | DQ49: =SUM(AL49:AO49) | DR49: =SUM(AP49:AS49) | DS49: =SUM(AT49:AW49) | DT49: =SUM(AX49:BA49) | DU49: =SUM(BB49:BE49) | DV49: =SUM(BF49:BI49) | DW49: =SUM(BJ49:BM49) | DX49: =Ticker0027!DB54 | DY49: =Ticker0027!DG54 | DZ49: =Ticker0027!DL54 | EA49: =Ticker0027!DQ54 | EB49: =Ticker0027!DV54 | EC49: =Ticker0027!EA54 | ED49: =Ticker0027!EF54 | EE49: =Ticker0027!EK54 | EF49: =Ticker0027!EP54 | EG49: =Ticker0027!EU54 | EH49: =Ticker0027!EZ54
A50: qoq | C50: =C49/B49-1 | D50: =D49/C49-1 | E50: =E49/D49-1 | F50: =F49/E49-1 | G50: =G49/F49-1 | H50: =H49/G49-1 | I50: =I49/H49-1 | J50: =J49/I49-1 | ... DE50: =DE49/DD49-1 | DH50: -- | DI50: -- | DJ50: -- | DK50: -- | DL50: -- | DM50: -- | DN50: -- | DO50: -- | DP50: -- | DQ50: -- | DR50: -- | DS50: -- | DT50: -- | DU50: -- | DV50: -- | DW50: -- | DX50: -- | DY50: -- | DZ50: -- | EA50: -- | EB50: -- | EC50: -- | ED50: -- | EE50: -- | EF50: -- | EG50: -- | EH50: --
A51: yoy | F51: =F49/B49-1 | G51: =G49/C49-1 | H51: =H49/D49-1 | I51: =I49/E49-1 | J51: =J49/F49-1 | K51: =K49/G49-1 | L51: =L49/H49-1 | M51: =M49/I49-1 | ... DE51: =DE49/DA49-1 | DI51: =DI49/DH49-1 | DJ51: =DJ49/DI49-1 | DK51: =DK49/DJ49-1 | DL51: =DL49/DK49-1 | DM51: =DM49/DL49-1 | DN51: =DN49/DM49-1 | DO51: =DO49/DN49-1 | DP51: =DP49/DO49-1 | ... EH51: =EH49/EG49-1
A52: Op EPS (ex ESO) | B52: =Ticker0027!V53 | C52: =Ticker0027!W53 | D52: =Ticker0027!X53 | E52: =Ticker0027!Y53 | F52: =Ticker0027!AA53 | G52: =Ticker0027!AB53 | H52: =Ticker0027!AC53 | I52: =Ticker0027!AD53 | J52: =Ticker0027!AF53 | K52: =Ticker0027!AG53 | L52: =Ticker0027!AH53 | M52: =Ticker0027!AI53 | N52: =Ticker0027!AK53 | O52: =Ticker0027!AL53 | P52: =Ticker0027!AM53 | Q52: =Ticker0027!AN53 | R52: =Ticker0027!AP53 | S52: =Ticker0027!AQ53 | T52: =Ticker0027!AR53 | U52: =Ticker0027!AS53 | V52: =Ticker0027!AU53 | W52: =Ticker0027!AV53 | X52: =Ticker0027!AW53 | Y52: =Ticker0027!AX53 | Z52: =Ticker0027!AZ53 | AA52: =Ticker0027!BA53 | AB52: =Ticker0027!BB53 | AC52: =Ticker0027!BC53 | AD52: =Ticker0027!BE53 | AE52: =Ticker0027!BF53 | AF52: =Ticker0027!BG53 | AG52: =Ticker0027!BH53 | AH52: =Ticker0027!BJ53 | AI52: =Ticker0027!BK53 | AJ52: =Ticker0027!BL53 | AK52: =Ticker0027!BM53 | AL52: =Ticker0027!BO53 | AM52: =Ticker0027!BP53 | AN52: =Ticker0027!BQ53 | AO52: =Ticker0027!BR53 | AP52: =Ticker0027!BT53 | AQ52: =Ticker0027!BU53 | AR52: =Ticker0027!BV53 | AS52: =Ticker0027!BW53 | AT52: =Ticker0027!BY53 | AU52: =Ticker0027!BZ53 | AV52: =Ticker0027!CA53 | AW52: =Ticker0027!CB53 | AX52: =Ticker0027!CD53 | AY52: =Ticker0027!CE53 | AZ52: =Ticker0027!CF53 | BA52: =Ticker0027!CG53 | BB52: =Ticker0027!CI53 | BC52: =Ticker0027!CJ53 | BD52: =Ticker0027!CK53 | BE52: =Ticker0027!CL53 | BF52: =Ticker0027!CN53 | BG52: =Ticker0027!CO53 | BH52: =Ticker0027!CP53 | BI52: =Ticker0027!CQ53 | BJ52: =Ticker0027!CS53 | BK52: =Ticker0027!CT53 | BL52: =Ticker0027!CU53 | BM52: =Ticker0027!CV53 | BN52: =Ticker0027!CX53 | BO52: =Ticker0027!CY53 | BP52: =Ticker0027!CZ53 | BQ52: =Ticker0027!DA53 | BR52: =Ticker0027!DC53 | BS52: =Ticker0027!DD53 | BT52: =Ticker0027!DE53 | BU52: =Ticker0027!DF53 | BV52: =Ticker0027!DH53 | BW52: =Ticker0027!DI53 | BX52: =Ticker0027!DJ53 | BY52: =Ticker0027!DK53 | BZ52: =Ticker0027!DM53 | CA52: =Ticker0027!DN53 | CB52: =Ticker0027!DO53 | CC52: =Ticker0027!DP53 | CD52: =Ticker0027!DR53 | CE52: =Ticker0027!DS53 | CF52: =Ticker0027!DT53 | CG52: =Ticker0027!DU53 | CH52: =Ticker0027!DW53 | CI52: =Ticker0027!DX53 | CJ52: =Ticker0027!DY53 | CK52: =Ticker0027!DZ53 | CL52: =Ticker0027!EB53 | CM52: =Ticker0027!EC53 | CN52: =Ticker0027!ED53 | CO52: =Ticker0027!EE53 | CP52: =Ticker0027!EG53 | CQ52: =Ticker0027!EH53 | CR52: =Ticker0027!EI53 | CS52: =Ticker0027!EJ53 | CT52: =Ticker0027!EL53 | CU52: =Ticker0027!EM53 | CV52: =Ticker0027!EN53 | CW52: =Ticker0027!EO53 | CX52: =Ticker0027!EQ53 | CY52: =Ticker0027!ER53 | CZ52: =Ticker0027!ES53 | DA52: =Ticker0027!ET53 | DB52: =Ticker0027!EV53 | DC52: =Ticker0027!EW53 | DD52: =Ticker0027!EX53 | DE52: =Ticker0027!EY53 | DH52: =SUM(B52:E52) | DI52: =SUM(F52:I52) | DJ52: =SUM(J52:M52) | DK52: =SUM(N52:Q52) | DL52: =SUM(R52:U52) | DM52: =SUM(V52:Y52) | DN52: =SUM(Z52:AC52) | DO52: =SUM(AD52:AG52) | DP52: =SUM(AH52:AK52) | DQ52: =SUM(AL52:AO52) | DR52: =SUM(AP52:AS52) | DS52: =SUM(AT52:AW52) | DT52: =SUM(AX52:BA52) | DU52: =SUM(BB52:BE52) | DV52: =SUM(BF52:BI52) | DW52: =SUM(BJ52:BM52) | DX52: =Ticker0027!DB53 | DY52: =Ticker0027!DG53 | DZ52: =Ticker0027!DL53 | EA52: =Ticker0027!DQ53 | EB52: =Ticker0027!DV53 | EC52: =Ticker0027!EA53 | ED52: =Ticker0027!EF53 | EE52: =Ticker0027!EK53 | EF52: =Ticker0027!EP53 | EG52: =Ticker0027!EU53 | EH52: =Ticker0027!EZ53
A53: qoq | C53: =C52/B52-1 | D53: =D52/C52-1 | E53: =E52/D52-1 | F53: =F52/E52-1 | G53: =G52/F52-1 | H53: =H52/G52-1 | I53: =I52/H52-1 | J53: =J52/I52-1 | ... DE53: =DE52/DD52-1 | DH53: -- | DI53: -- | DJ53: -- | DK53: -- | DL53: -- | DM53: -- | DN53: -- | DO53: -- | DP53: -- | DQ53: -- | DR53: -- | DS53: -- | DT53: -- | DU53: -- | DV53: -- | DW53: -- | DX53: -- | DY53: -- | DZ53: -- | EA53: -- | EB53: -- | EC53: -- | ED53: -- | EE53: -- | EF53: -- | EG53: -- | EH53: --
A54: yoy | F54: =F52/B52-1 | G54: =G52/C52-1 | H54: =H52/D52-1 | I54: =I52/E52-1 | J54: =J52/F52-1 | K54: =K52/G52-1 | L54: =L52/H52-1 | M54: =M52/I52-1 | ... DE54: =DE52/DA52-1 | DI54: =DI52/DH52-1 | DJ54: =DJ52/DI52-1 | DK54: =DK52/DJ52-1 | DL54: =DL52/DK52-1 | DM54: =DM52/DL52-1 | DN54: =DN52/DM52-1 | DO54: =DO52/DN52-1 | DP54: =DP52/DO52-1 | ... EH54: =EH52/EG52-1
A55: GAAP EPS | B55: =Ticker0027!V58 | C55: =Ticker0027!W58 | D55: =Ticker0027!X58 | E55: =Ticker0027!Y58 | F55: =Ticker0027!AA58 | G55: =Ticker0027!AB58 | H55: =Ticker0027!AC58 | I55: =Ticker0027!AD58 | J55: =Ticker0027!AF58 | K55: =Ticker0027!AG58 | L55: =Ticker0027!AH58 | M55: =Ticker0027!AI58 | N55: =Ticker0027!AK58 | O55: =Ticker0027!AL58 | P55: =Ticker0027!AM58 | Q55: =Ticker0027!AN58 | R55: =Ticker0027!AP58 | S55: =Ticker0027!AQ58 | T55: =Ticker0027!AR58 | U55: =Ticker0027!AS58 | V55: =Ticker0027!AU58 | W55: =Ticker0027!AV58 | X55: =Ticker0027!AW58 | Y55: =Ticker0027!AX58 | Z55: =Ticker0027!AZ58 | AA55: =Ticker0027!BA58 | AB55: =Ticker0027!BB58 | AC55: =Ticker0027!BC58 | AD55: =Ticker0027!BE58 | AE55: =Ticker0027!BF58 | AF55: =Ticker0027!BG58 | AG55: =Ticker0027!BH58 | AH55: =Ticker0027!BJ58 | AI55: =Ticker0027!BK58 | AJ55: =Ticker0027!BL58 | AK55: =Ticker0027!BM58 | AL55: =Ticker0027!BO58 | AM55: =Ticker0027!BP58 | AN55: =Ticker0027!BQ58 | AO55: =Ticker0027!BR58 | AP55: =Ticker0027!BT58 | AQ55: =Ticker0027!BU58 | AR55: =Ticker0027!BV58 | AS55: =Ticker0027!BW58 | AT55: =Ticker0027!BY58 | AU55: =Ticker0027!BZ58 | AV55: =Ticker0027!CA58 | AW55: =Ticker0027!CB58 | AX55: =Ticker0027!CD58 | AY55: =Ticker0027!CE58 | AZ55: =Ticker0027!CF58 | BA55: =Ticker0027!CG58 | BB55: =Ticker0027!CI58 | BC55: =Ticker0027!CJ58 | BD55: =Ticker0027!CK58 | BE55: =Ticker0027!CL58 | BF55: =Ticker0027!CN58 | BG55: =Ticker0027!CO58 | BH55: =Ticker0027!CP58 | BI55: =Ticker0027!CQ58 | BJ55: =Ticker0027!CS58 | BK55: =Ticker0027!CT58 | BL55: =Ticker0027!CU58 | BM55: =Ticker0027!CV58 | BN55: =Ticker0027!CX58 | BO55: =Ticker0027!CY58 | BP55: =Ticker0027!CZ58 | BQ55: =Ticker0027!DA58 | BR55: =Ticker0027!DC58 | BS55: =Ticker0027!DD58 | BT55: =Ticker0027!DE58 | BU55: =Ticker0027!DF58 | BV55: =Ticker0027!DH58 | BW55: =Ticker0027!DI58 | BX55: =Ticker0027!DJ58 | BY55: =Ticker0027!DK58 | BZ55: =Ticker0027!DM58 | CA55: =Ticker0027!DN58 | CB55: =Ticker0027!DO58 | CC55: =Ticker0027!DP58 | CD55: =Ticker0027!DR58 | CE55: =Ticker0027!DS58 | CF55: =Ticker0027!DT58 | CG55: =Ticker0027!DU58 | CH55: =Ticker0027!DW58 | CI55: =Ticker0027!DX58 | CJ55: =Ticker0027!DY58 | CK55: =Ticker0027!DZ58 | CL55: =Ticker0027!EB58 | CM55: =Ticker0027!EC58 | CN55: =Ticker0027!ED58 | CO55: =Ticker0027!EE58 | CP55: =Ticker0027!EG58 | CQ55: =Ticker0027!EH58 | CR55: =Ticker0027!EI58 | CS55: =Ticker0027!EJ58 | CT55: =Ticker0027!EL58 | CU55: =Ticker0027!EM58 | CV55: =Ticker0027!EN58 | CW55: =Ticker0027!EO58 | CX55: =Ticker0027!EQ58 | CY55: =Ticker0027!ER58 | CZ55: =Ticker0027!ES58 | DA55: =Ticker0027!ET58 | DB55: =Ticker0027!EV58 | DC55: =Ticker0027!EW58 | DD55: =Ticker0027!EX58 | DE55: =Ticker0027!EY58 | DH55: =SUM(B55:E55) | DI55: =SUM(F55:I55) | DJ55: =SUM(J55:M55) | DK55: =SUM(N55:Q55) | DL55: =SUM(R55:U55) | DM55: =SUM(V55:Y55) | DN55: =SUM(Z55:AC55) | DO55: =SUM(AD55:AG55) | DP55: =SUM(AH55:AK55) | DQ55: =SUM(AL55:AO55) | DR55: =SUM(AP55:AS55) | DS55: =SUM(AT55:AW55) | DT55: =SUM(AX55:BA55) | DU55: =SUM(BB55:BE55) | DV55: =SUM(BF55:BI55) | DW55: =SUM(BJ55:BM55) | DX55: =SUM(BN55:BQ55) | DY55: =SUM(BR55:BU55) | DZ55: =BV55+BW55+BX55+BY55 | EA55: =CC55+CB55+CA55+BZ55 | EB55: =+CD55+CE55+CF55+CG55 | EC55: =+SUM(CH55:CK55) | ED55: =+SUM(CL55:CO55) | EE55: =+SUM(CP55:CS55) | EF55: =+SUM(CT55:CW55) | EG55: =SUM(CX55:DA55) | EH55: =SUM(DB55:DE55)
A56: qoq | K56: =K55/J55-1 | L56: =L55/K55-1 | M56: =M55/L55-1 | N56: =N55/M55-1 | O56: =O55/N55-1 | P56: =P55/O55-1 | Q56: =Q55/P55-1 | R56: =R55/Q55-1 | ... DE56: =DE55/DD55-1 | DH56: -- | DI56: -- | DJ56: -- | DK56: -- | DL56: -- | DM56: -- | DN56: -- | DO56: -- | DP56: -- | DQ56: -- | DR56: -- | DS56: -- | DT56: -- | DU56: -- | DV56: -- | DW56: -- | DX56: -- | DY56: -- | DZ56: -- | EA56: -- | EB56: -- | EC56: -- | ED56: -- | EE56: -- | EF56: -- | EG56: -- | EH56: --
A57: yoy | N57: =N55/J55-1 | O57: =O55/K55-1 | P57: =P55/L55-1 | Q57: =Q55/M55-1 | R57: =R55/N55-1 | S57: =S55/O55-1 | T57: =T55/P55-1 | U57: =U55/Q55-1 | ... DE57: =DE55/DA55-1 | DK57: =DK55/DJ55-1 | DL57: =DL55/DK55-1 | DM57: =DM55/DL55-1 | DN57: =DN55/DM55-1 | DO57: =DO55/DN55-1 | DP57: =DP55/DO55-1 | DQ57: =DQ55/DP55-1 | DR57: =DR55/DQ55-1 | ... EH57: =EH55/EG55-1
A58: FCF | B58: =Ticker0027!V158 | C58: =Ticker0027!W158 | D58: =Ticker0027!X158 | E58: =Ticker0027!Y158 | F58: =Ticker0027!AA158 | G58: =Ticker0027!AB158 | H58: =Ticker0027!AC158 | I58: =Ticker0027!AD158 | J58: =Ticker0027!AF158 | K58: =Ticker0027!AG158 | L58: =Ticker0027!AH158 | M58: =Ticker0027!AI158 | N58: =Ticker0027!AK158 | O58: =Ticker0027!AL158 | P58: =Ticker0027!AM158 | Q58: =Ticker0027!AN158 | R58: =Ticker0027!AP158 | S58: =Ticker0027!AQ158 | T58: =Ticker0027!AR158 | U58: =Ticker0027!AS158 | V58: =Ticker0027!AU158 | W58: =Ticker0027!AV158 | X58: =Ticker0027!AW158 | Y58: =Ticker0027!AX158 | Z58: =Ticker0027!AZ158 | AA58: =Ticker0027!BA158 | AB58: =Ticker0027!BB158 | AC58: =Ticker0027!BC158 | AD58: =Ticker0027!BE158 | AE58: =Ticker0027!BF158 | AF58: =Ticker0027!BG158 | AG58: =Ticker0027!BH158 | AH58: =Ticker0027!BJ158 | AI58: =Ticker0027!BK158 | AJ58: =Ticker0027!BL158 | AK58: =Ticker0027!BM158 | AL58: =Ticker0027!BO158 | AM58: =Ticker0027!BP158 | AN58: =Ticker0027!BQ158 | AO58: =Ticker0027!BR158 | AP58: =Ticker0027!BT158 | AQ58: =Ticker0027!BU158 | AR58: =Ticker0027!BV158 | AS58: =Ticker0027!BW158 | AT58: =Ticker0027!BY158 | AU58: =Ticker0027!BZ158 | AV58: =Ticker0027!CA158 | AW58: =Ticker0027!CB158 | AX58: =Ticker0027!CD158 | AY58: =Ticker0027!CE158 | AZ58: =Ticker0027!CF158 | BA58: =Ticker0027!CG158 | BB58: =Ticker0027!CI158 | BC58: =Ticker0027!CJ158 | BD58: =Ticker0027!CK158 | BE58: =Ticker0027!CL158 | BF58: =Ticker0027!CN158 | BG58: =Ticker0027!CO158 | BH58: =Ticker0027!CP158 | BI58: =Ticker0027!CQ158 | BJ58: =Ticker0027!CS158 | BK58: =Ticker0027!CT158 | BL58: =Ticker0027!CU158 | BM58: =Ticker0027!CV158 | BN58: =Ticker0027!CX158 | BO58: =Ticker0027!CY158 | BP58: =Ticker0027!CZ158 | BQ58: =Ticker0027!DA158 | BR58: =Ticker0027!DC158 | BS58: =Ticker0027!DD158 | BT58: =Ticker0027!DE158 | BU58: =Ticker0027!DF158 | BV58: =Ticker0027!DH158 | BW58: =Ticker0027!DI158 | BX58: =Ticker0027!DJ158 | BY58: =Ticker0027!DK158 | BZ58: =Ticker0027!DM158 | CA58: =Ticker0027!DN158 | CB58: =Ticker0027!DO158 | CC58: =Ticker0027!DP158 | CD58: =Ticker0027!DR158 | CE58: =Ticker0027!DS158 | CF58: =Ticker0027!DT158 | CG58: =Ticker0027!DU158 | CH58: =Ticker0027!DW158 | CI58: =Ticker0027!DX158 | CJ58: =Ticker0027!DY158 | CK58: =Ticker0027!DZ158 | CL58: =Ticker0027!EB158 | CM58: =Ticker0027!EC158 | CN58: =Ticker0027!ED158 | CO58: =Ticker0027!EE158 | CP58: =Ticker0027!EG158 | CQ58: =Ticker0027!EH158 | CR58: =Ticker0027!EI158 | CS58: =Ticker0027!EJ158 | CT58: =Ticker0027!EL158 | CU58: =Ticker0027!EM158 | CV58: =Ticker0027!EN158 | CW58: =Ticker0027!EO158 | CX58: =Ticker0027!EQ158 | CY58: =Ticker0027!ER158 | CZ58: =Ticker0027!ES158 | DA58: =Ticker0027!ET158 | DB58: =Ticker0027!EV158 | DC58: =Ticker0027!EW158 | DD58: =Ticker0027!EX158 | DE58: =Ticker0027!EY158 | DH58: =SUM(B58:E58) | DI58: =SUM(F58:I58) | DJ58: =SUM(J58:M58) | DK58: =SUM(N58:Q58) | DL58: =SUM(R58:U58) | DM58: =SUM(V58:Y58) | DN58: =SUM(Z58:AC58) | DO58: =SUM(AD58:AG58) | DP58: =SUM(AH58:AK58) | DQ58: =SUM(AL58:AO58) | DR58: =SUM(AP58:AS58) | DS58: =SUM(AT58:AW58) | DT58: =SUM(AX58:BA58) | DU58: =SUM(BB58:BE58) | DV58: =SUM(BF58:BI58) | DW58: =SUM(BJ58:BM58) | DX58: =SUM(BN58:BQ58) | DY58: =SUM(BR58:BU58) | DZ58: =BV58+BW58+BX58+BY58 | EA58: =CC58+CB58+CA58+BZ58 | EB58: =+CD58+CE58+CF58+CG58 | EC58: =SUM(CH58:CK58) | ED58: =SUM(CL58:CO58) | EE58: =SUM(CP58:CS58) | EF58: =SUM(CT58:CW58) | EG58: =SUM(CX58:DA58) | EH58: =SUM(DB58:DE58)
A59: qoq | C59: =C58/B58-1 | D59: =D58/C58-1 | E59: =E58/D58-1 | F59: =F58/E58-1 | G59: =G58/F58-1 | H59: =H58/G58-1 | I59: =I58/H58-1 | J59: =J58/I58-1 | ... V59: =V58/U58-1 | W59: -- | X59: -- | Y59: =Y58/X58-1 | Z59: =Z58/Y58-1 | AA59: =AA58/Z58-1 | AB59: =AB58/AA58-1 | AC59: =AC58/AB58-1 | AD59: -- | AE59: -- | AF59: -- | AG59: -- | AH59: -- | AI59: =AI58/AH58-1 | AJ59: =AJ58/AI58-1 | AK59: =AK58/AJ58-1 | AL59: -- | AM59: -- | AN59: -- | AO59: =AO58/AN58-1 | AP59: =AP58/AO58-1 | AQ59: =AQ58/AP58-1 | AR59: =AR58/AQ58-1 | AS59: =AS58/AR58-1 | AT59: -- | AU59: -- | AV59: =AV58/AU58-1 | AW59: =AW58/AV58-1 | AX59: =AX58/AW58-1 | AY59: =AY58/AX58-1 | AZ59: =AZ58/AY58-1 | BA59: =BA58/AZ58-1 | BB59: =BB58/BA58-1 | BC59: =BC58/BB58-1 | ... CI59: =CI58/CH58-1 | CJ59: -- | CK59: -- | CL59: =CL58/CK58-1 | CM59: =CM58/CL58-1 | CN59: =CN58/CM58-1 | CO59: =CO58/CN58-1 | CP59: =CP58/CO58-1 | CQ59: =CQ58/CP58-1 | CR59: =CR58/CQ58-1 | CS59: =CS58/CR58-1 | ... DE59: =DE58/DD58-1 | DH59: -- | DI59: -- | DJ59: -- | DK59: -- | DL59: -- | DM59: -- | DN59: -- | DO59: -- | DP59: -- | DQ59: -- | DR59: -- | DS59: -- | DT59: -- | DU59: -- | DV59: -- | DW59: -- | DX59: -- | DY59: -- | DZ59: -- | EA59: -- | EB59: -- | EC59: -- | ED59: -- | EE59: -- | EF59: -- | EG59: -- | EH59: --
A60: yoy | F60: =F58/B58-1 | G60: =G58/C58-1 | H60: =H58/D58-1 | I60: =I58/E58-1 | J60: =J58/F58-1 | K60: =K58/G58-1 | L60: =L58/H58-1 | M60: =M58/I58-1 | ... V60: =V58/R58-1 | W60: -- | X60: =X58/T58-1 | Y60: =Y58/U58-1 | Z60: =Z58/V58-1 | AA60: -- | AB60: =AB58/X58-1 | AC60: =AC58/Y58-1 | AD60: -- | AE60: =AE58/AA58-1 | AF60: -- | AG60: -- | AH60: -- | AI60: =AI58/AE58-1 | AJ60: -- | AK60: -- | AL60: -- | AM60: -- | AN60: =AN58/AJ58-1 | AO60: =AO58/AK58-1 | AP60: -- | AQ60: -- | AR60: =AR58/AN58-1 | AS60: =AS58/AO58-1 | AT60: -- | AU60: =AU58/AQ58-1 | AV60: =AV58/AR58-1 | AW60: =AW58/AS58-1 | AX60: -- | AY60: =AY58/AU58-1 | AZ60: =AZ58/AV58-1 | BA60: =BA58/AW58-1 | BB60: =BB58/AX58-1 | BC60: =BC58/AY58-1 | BD60: =BD58/AZ58-1 | BE60: =BE58/BA58-1 | BF60: =BF58/BB58-1 | ... CI60: =CI58/CE58-1 | CJ60: -- | CK60: =CK58/CG58-1 | CL60: =CL58/CH58-1 | CM60: =CM58/CI58-1 | CN60: -- | CO60: =CO58/CK58-1 | CP60: =CP58/CL58-1 | CQ60: =CQ58/CM58-1 | CR60: =CR58/CN58-1 | CS60: =CS58/CO58-1 | CT60: =CT58/CP58-1 | CU60: =CU58/CQ58-1 | CV60: =CV58/CR58-1 | ... DE60: =DE58/DA58-1 | DI60: =DI58/DH58-1 | DJ60: =DJ58/DI58-1 | DK60: =DK58/DJ58-1 | DL60: =DL58/DK58-1 | DM60: =DM58/DL58-1 | DN60: =DN58/DM58-1 | DO60: =DO58/DN58-1 | DP60: =DP58/DO58-1 | ... EH60: =EH58/EG58-1
A61: as a % of sales | B61: =B58/B5 | C61: =C58/C5 | D61: =D58/D5 | E61: =E58/E5 | F61: =F58/F5 | G61: =G58/G5 | H61: =H58/H5 | I61: =I58/I5 | ... DE61: =DE58/DE5 | DH61: =DH58/DH5 | DI61: =DI58/DI5 | DJ61: =DJ58/DJ5 | DK61: =DK58/DK5 | DL61: =DL58/DL5 | DM61: =DM58/DM5 | DN61: =DN58/DN5 | DO61: =DO58/DO5 | ... EH61: =EH58/EH5
A62: Net Cash | DH62: =Ticker0027!Z62+Ticker0027!Z63+Ticker0027!Z64-Ticker0027!Z91-Ticker0027!Z96-Ticker0027!Z97 | DI62: =Ticker0027!AE62+Ticker0027!AE63+Ticker0027!AE64-Ticker0027!AE91-Ticker0027!AE96-Ticker0027!AE97 | DJ62: =Ticker0027!AJ62+Ticker0027!AJ63+Ticker0027!AJ64-Ticker0027!AJ91-Ticker0027!AJ96-Ticker0027!AJ97 | DK62: =Ticker0027!AO62+Ticker0027!AO63+Ticker0027!AO64-Ticker0027!AO91-Ticker0027!AO96-Ticker0027!AO97 | DL62: =Ticker0027!AT62+Ticker0027!AT63+Ticker0027!AT64-Ticker0027!AT91-Ticker0027!AT96-Ticker0027!AT97 | DM62: =Ticker0027!AY62+Ticker0027!AY63+Ticker0027!AY64-Ticker0027!AY91-Ticker0027!AY96-Ticker0027!AY97 | DN62: =Ticker0027!BD62+Ticker0027!BD63+Ticker0027!BD64-Ticker0027!BD91-Ticker0027!BD96-Ticker0027!BD97 | DO62: =Ticker0027!BI62+Ticker0027!BI63+Ticker0027!BI64-Ticker0027!BI91-Ticker0027!BI96-Ticker0027!BI97 | DP62: =Ticker0027!BN62+Ticker0027!BN63+Ticker0027!BN64-Ticker0027!BN91-Ticker0027!BN96-Ticker0027!BN97 | DQ62: =Ticker0027!BS62+Ticker0027!BS63+Ticker0027!BS64-Ticker0027!BS91-Ticker0027!BS96-Ticker0027!BS97 | DR62: =Ticker0027!BX62+Ticker0027!BX63+Ticker0027!BX64-Ticker0027!BX91-Ticker0027!BX96-Ticker0027!BX97 | DS62: =Ticker0027!CC62+Ticker0027!CC63+Ticker0027!CC64-Ticker0027!CC91-Ticker0027!CC96-Ticker0027!CC97 | DT62: =Ticker0027!CH62+Ticker0027!CH63+Ticker0027!CH64-Ticker0027!CH91-Ticker0027!CH96-Ticker0027!CH97 | DU62: =Ticker0027!CM62+Ticker0027!CM63+Ticker0027!CM64-Ticker0027!CM91-Ticker0027!CM96-Ticker0027!CM97 | DV62: =Ticker0027!CR62+Ticker0027!CR63+Ticker0027!CR64-Ticker0027!CR91-Ticker0027!CR96-Ticker0027!CR97 | DW62: =Ticker0027!CW62+Ticker0027!CW63+Ticker0027!CW64-Ticker0027!CW91-Ticker0027!CW96-Ticker0027!CW97 | DX62: =Ticker0027!DB62+Ticker0027!DB63+Ticker0027!DB64-Ticker0027!DB91-Ticker0027!DB96-Ticker0027!DB97 | DY62: =Ticker0027!DG62+Ticker0027!DG63+Ticker0027!DG64-Ticker0027!DG91-Ticker0027!DG96-Ticker0027!DG97 | DZ62: =Ticker0027!DL62+Ticker0027!DL63+Ticker0027!DL64-Ticker0027!DL91-Ticker0027!DL96-Ticker0027!DL97 | EA62: =Ticker0027!DQ62+Ticker0027!DQ63+Ticker0027!DQ64-Ticker0027!DQ91-Ticker0027!DQ96-Ticker0027!DQ97 | EB62: =Ticker0027!DV62+Ticker0027!DV63+Ticker0027!DV64-Ticker0027!DV91-Ticker0027!DV96-Ticker0027!DV97 | EC62: =Ticker0027!EA62+Ticker0027!EA63+Ticker0027!EA64-Ticker0027!EA91-Ticker0027!EA96-Ticker0027!EA97 | ED62: =Ticker0027!EF62+Ticker0027!EF63+Ticker0027!EF64-Ticker0027!EF91-Ticker0027!EF96-Ticker0027!EF97 | EE62: =Ticker0027!EK62+Ticker0027!EK63+Ticker0027!EK64-Ticker0027!EK91-Ticker0027!EK96-Ticker0027!EK97 | EF62: =Ticker0027!EP62+Ticker0027!EP63+Ticker0027!EP64-Ticker0027!EP91-Ticker0027!EP96-Ticker0027!EP97 | EG62: =Ticker0027!EU62+Ticker0027!EU63+Ticker0027!EU64-Ticker0027!EU91-Ticker0027!EU96-Ticker0027!EU97 | EH62: =Ticker0027!EZ62+Ticker0027!EZ63+Ticker0027!EZ64-Ticker0027!EZ91-Ticker0027!EZ96-Ticker0027!EZ97
A64: Non-GAAP Dil Shares | B64: =Ticker0027!V48 | C64: =Ticker0027!W48 | D64: =Ticker0027!X48 | E64: =Ticker0027!Y48 | F64: =Ticker0027!AA48 | G64: =Ticker0027!AB48 | H64: =Ticker0027!AC48 | I64: =Ticker0027!AD48 | J64: =Ticker0027!AF48 | K64: =Ticker0027!AG48 | L64: =Ticker0027!AH48 | M64: =Ticker0027!AI48 | N64: =Ticker0027!AK48 | O64: =Ticker0027!AL48 | P64: =Ticker0027!AM48 | Q64: =Ticker0027!AN48 | R64: =Ticker0027!AP48 | S64: =Ticker0027!AQ48 | T64: =Ticker0027!AR48 | U64: =Ticker0027!AS48 | V64: =Ticker0027!AU48 | W64: =Ticker0027!AV48 | X64: =Ticker0027!AW48 | Y64: =Ticker0027!AX48 | Z64: =Ticker0027!AZ48 | AA64: =Ticker0027!BA48 | AB64: =Ticker0027!BB48 | AC64: =Ticker0027!BC48 | AD64: =Ticker0027!BE48 | AE64: =Ticker0027!BF48 | AF64: =Ticker0027!BG48 | AG64: =Ticker0027!BH48 | AH64: =Ticker0027!BJ48 | AI64: =Ticker0027!BK48 | AJ64: =Ticker0027!BL48 | AK64: =Ticker0027!BM48 | AL64: =Ticker0027!BO48 | AM64: =Ticker0027!BP48 | AN64: =Ticker0027!BQ48 | AO64: =Ticker0027!BR48 | AP64: =Ticker0027!BT48 | AQ64: =Ticker0027!BU48 | AR64: =Ticker0027!BV48 | AS64: =Ticker0027!BW48 | AT64: =Ticker0027!BY48 | AU64: =Ticker0027!BZ48 | AV64: =Ticker0027!CA48 | AW64: =Ticker0027!CB48 | AX64: =Ticker0027!CD48 | AY64: =Ticker0027!CE48 | AZ64: =Ticker0027!CF48 | BA64: =Ticker0027!CG48 | BB64: =Ticker0027!CI48 | BC64: =Ticker0027!CJ48 | BD64: =Ticker0027!CK48 | BE64: =Ticker0027!CL48 | BF64: =Ticker0027!CN48 | BG64: =Ticker0027!CO48 | BH64: =Ticker0027!CP48 | BI64: =Ticker0027!CQ48 | BJ64: =Ticker0027!CS48 | BK64: =Ticker0027!CT48 | BL64: =Ticker0027!CU48 | BM64: =Ticker0027!CV48 | BN64: =Ticker0027!CX48 | BO64: =Ticker0027!CY48 | BP64: =Ticker0027!CZ48 | BQ64: =Ticker0027!DA48 | BR64: =Ticker0027!DC48 | BS64: =Ticker0027!DD48 | BT64: =Ticker0027!DE48 | BU64: =Ticker0027!DF48 | BV64: =Ticker0027!DH48 | BW64: =Ticker0027!DI48 | BX64: =Ticker0027!DJ48 | BY64: =Ticker0027!DK48 | BZ64: =Ticker0027!DM48 | CA64: =Ticker0027!DN48 | CB64: =Ticker0027!DO48 | CC64: =Ticker0027!DP48
A65: yoy | BB65: =BB64/AX64-1 | BC65: =BC64/AY64-1 | BD65: =BD64/AZ64-1 | BE65: =BE64/BA64-1 | BF65: =BF64/BB64-1 | BG65: =BG64/BC64-1 | BH65: =BH64/BD64-1 | BI65: =BI64/BE64-1 | ... CC65: =CC64/BY64-1
A67: Inventory | B67: =Ticker0027!V67 | C67: =Ticker0027!W67 | D67: =Ticker0027!X67 | E67: =Ticker0027!Y67 | F67: =Ticker0027!AA67 | G67: =Ticker0027!AB67 | H67: =Ticker0027!AC67 | I67: =Ticker0027!AD67 | J67: =Ticker0027!AF67 | K67: =Ticker0027!AG67 | L67: =Ticker0027!AH67 | M67: =Ticker0027!AI67 | N67: =Ticker0027!AK67 | O67: =Ticker0027!AL67 | P67: =Ticker0027!AM67 | Q67: =Ticker0027!AN67 | R67: =Ticker0027!AP67 | S67: =Ticker0027!AQ67 | T67: =Ticker0027!AR67 | U67: =Ticker0027!AS67 | V67: =Ticker0027!AU67 | W67: =Ticker0027!AV67 | X67: =Ticker0027!AW67 | Y67: =Ticker0027!AX67 | Z67: =Ticker0027!AZ67 | AA67: =Ticker0027!BA67 | AB67: =Ticker0027!BB67 | AC67: =Ticker0027!BC67 | AD67: =Ticker0027!BE67 | AE67: =Ticker0027!BF67 | AF67: =Ticker0027!BG67 | AG67: =Ticker0027!BH67 | AH67: =Ticker0027!BJ67 | AI67: =Ticker0027!BK67 | AJ67: =Ticker0027!BL67 | AK67: =Ticker0027!BM67 | AL67: =Ticker0027!BO67 | AM67: =Ticker0027!BP67 | AN67: =Ticker0027!BQ67 | AO67: =Ticker0027!BR67 | AP67: =Ticker0027!BT67 | AQ67: =Ticker0027!BU67 | AR67: =Ticker0027!BV67 | AS67: =Ticker0027!BW67 | AT67: =Ticker0027!BY67 | AU67: =Ticker0027!BZ67 | AV67: =Ticker0027!CA67 | AW67: =Ticker0027!CB67 | AX67: =Ticker0027!CD67 | AY67: =Ticker0027!CE67 | AZ67: =Ticker0027!CF67 | BA67: =Ticker0027!CG67 | BB67: =Ticker0027!CI67 | BC67: =Ticker0027!CJ67 | BD67: =Ticker0027!CK67 | BE67: =Ticker0027!CL67 | BF67: =Ticker0027!CN67 | BG67: =Ticker0027!CO67 | BH67: =Ticker0027!CP67 | BI67: =Ticker0027!CQ67 | BJ67: =Ticker0027!CS67 | BK67: =Ticker0027!CT67 | BL67: =Ticker0027!CU67 | BM67: =Ticker0027!CV67 | BN67: =Ticker0027!CX67 | BO67: =Ticker0027!CY67 | BP67: =Ticker0027!CZ67 | BQ67: =Ticker0027!DA67 | BR67: =Ticker0027!DC67 | BS67: =Ticker0027!DD67 | BT67: =Ticker0027!DE67 | BU67: =Ticker0027!DF67 | BV67: =Ticker0027!DH67 | BW67: =Ticker0027!DI67 | BX67: =Ticker0027!DJ67 | BY67: =Ticker0027!DK67 | BZ67: =Ticker0027!DM67 | CA67: =Ticker0027!DN67 | CB67: =Ticker0027!DO67 | CC67: =Ticker0027!DP67
A68: qoq | C68: =C67/B67-1 | D68: =D67/C67-1 | E68: =E67/D67-1 | F68: =F67/E67-1 | G68: =G67/F67-1 | H68: =H67/G67-1 | I68: =I67/H67-1 | J68: =J67/I67-1 | ... CC68: =CC67/CB67-1
A69: yoy | F69: =F67/B67-1 | G69: =G67/C67-1 | H69: =H67/D67-1 | I69: =I67/E67-1 | J69: =J67/F67-1 | K69: =K67/G67-1 | L69: =L67/H67-1 | M69: =M67/I67-1 | ... CC69: =CC67/BY67-1
A70: DOI (TTM) | E70: =E67/(E8+D8+C8+B8)*365 | F70: =F67/(F8+E8+D8+C8)*365 | G70: =G67/(G8+F8+E8+D8)*365 | H70: =H67/(H8+G8+F8+E8)*365 | I70: =I67/(I8+H8+G8+F8)*365 | J70: =J67/(J8+I8+H8+G8)*365 | K70: =K67/(K8+J8+I8+H8)*365 | L70: =L67/(L8+K8+J8+I8)*365 | ... CC70: =CC67/(CC8+CB8+CA8+BZ8)*365
A71: DOI (NTM) | B71: =B67/(B8+C8+D8+E8)*365 | C71: =C67/(C8+D8+E8+F8)*365 | D71: =D67/(D8+E8+F8+G8)*365 | E71: =E67/(E8+F8+G8+H8)*365 | F71: =F67/(F8+G8+H8+I8)*365 | G71: =G67/(G8+H8+I8+J8)*365 | H71: =H67/(H8+I8+J8+K8)*365 | I71: =I67/(I8+J8+K8+L8)*365 | ... CC71: =CC67/(CC8+CD8+CE8+CF8)*365
A72: AR | B72: =Ticker0027!V65 | C72: =Ticker0027!W65 | D72: =Ticker0027!X65 | E72: =Ticker0027!Y65 | F72: =Ticker0027!AA65 | G72: =Ticker0027!AB65 | H72: =Ticker0027!AC65 | I72: =Ticker0027!AD65 | J72: =Ticker0027!AF65 | K72: =Ticker0027!AG65 | L72: =Ticker0027!AH65 | M72: =Ticker0027!AI65 | N72: =Ticker0027!AK65 | O72: =Ticker0027!AL65 | P72: =Ticker0027!AM65 | Q72: =Ticker0027!AN65 | R72: =Ticker0027!AP65 | S72: =Ticker0027!AQ65 | T72: =Ticker0027!AR65 | U72: =Ticker0027!AS65 | V72: =Ticker0027!AU65 | W72: =Ticker0027!AV65 | X72: =Ticker0027!AW65 | Y72: =Ticker0027!AX65 | Z72: =Ticker0027!AZ65 | AA72: =Ticker0027!BA65 | AB72: =Ticker0027!BB65 | AC72: =Ticker0027!BC65 | AD72: =Ticker0027!BE65 | AE72: =Ticker0027!BF65 | AF72: =Ticker0027!BG65 | AG72: =Ticker0027!BH65 | AH72: =Ticker0027!BJ65 | AI72: =Ticker0027!BK65 | AJ72: =Ticker0027!BL65 | AK72: =Ticker0027!BM65 | AL72: =Ticker0027!BO65 | AM72: =Ticker0027!BP65 | AN72: =Ticker0027!BQ65 | AO72: =Ticker0027!BR65 | AP72: =Ticker0027!BT65 | AQ72: =Ticker0027!BU65 | AR72: =Ticker0027!BV65 | AS72: =Ticker0027!BW65 | AT72: =Ticker0027!BY65 | AU72: =Ticker0027!BZ65 | AV72: =Ticker0027!CA65 | AW72: =Ticker0027!CB65 | AX72: =Ticker0027!CD65 | AY72: =Ticker0027!CE65 | AZ72: =Ticker0027!CF65 | BA72: =Ticker0027!CG65 | BB72: =Ticker0027!CI65 | BC72: =Ticker0027!CJ65 | BD72: =Ticker0027!CK65 | BE72: =Ticker0027!CL65 | BF72: =Ticker0027!CN65 | BG72: =Ticker0027!CO65 | BH72: =Ticker0027!CP65 | BI72: =Ticker0027!CQ65 | BJ72: =Ticker0027!CS65 | BK72: =Ticker0027!CT65 | BL72: =Ticker0027!CU65 | BM72: =Ticker0027!CV65 | BN72: =Ticker0027!CX65 | BO72: =Ticker0027!CY65 | BP72: =Ticker0027!CZ65 | BQ72: =Ticker0027!DA65 | BR72: =Ticker0027!DC65 | BS72: =Ticker0027!DD65 | BT72: =Ticker0027!DE65 | BU72: =Ticker0027!DF65 | BV72: =Ticker0027!DH65 | BW72: =Ticker0027!DI65 | BX72: =Ticker0027!DJ65 | BY72: =Ticker0027!DK65 | BZ72: =Ticker0027!DM65 | CA72: =Ticker0027!DN65 | CB72: =Ticker0027!DO65 | CC72: =Ticker0027!DP65
A74: Segment Revenue | BB74: 1Q14 | BC74: 2Q14 | BD74: 3Q14 | BE74: 4Q14 | BF74: =BF3 | BG74: =BG3 | BH74: =BH3 | BI74: =BI3 | BJ74: =BJ3 | BK74: =BK3 | BL74: =BL3 | BM74: =BM3 | ... DE74: =DE3 | DH74: 2001 | DI74: 2002 | DJ74: 2003 | DK74: 2004 | DL74: 2005 | DM74: 2006 | DN74: 2007 | DO74: 2008 | DP74: 2009 | DQ74: 2010 | DR74: 2011 | DS74: 2012 | DT74: 2013 | DU74: =DU4 | DV74: =DV$4 | DW74: =DW$4 | DX74: =DX$4 | DY74: =DY$4 | DZ74: =DZ$4 | EA74: =EA$4 | EB74: =EB$4 | EC74: =EC$4 | ... EH74: =EH$4
A75: Gaming | BB75: 468 | BC75: 417 | BD75: 528 | BE75: 646 | BF75: 587 | BG75: 661 | BH75: 761 | BI75: 810 | BJ75: 687 | BK75: 781 | BL75: 1244 | BM75: 1348 | BN75: 1027 | BO75: 1186 | BP75: 1561 | BQ75: 1739 | BR75: 1723 | BS75: 1805 | BT75: 1764 | BU75: 954 | BV75: 1055 | BW75: 1313 | BX75: 1659 | BY75: 1491 | BZ75: 1339 | CA75: 1654 | CB75: 2271 | CC75: 2495 | CD75: 2760 | CE75: 3061 | CF75: 3221 | CG75: 3420 | CH75: 3620 | CI75: 2042 | CJ75: 1574 | CK75: 1831 | CL75: 2240 | CM75: 2486 | CN75: 2856 | CO75: 2865 | CP75: 2647 | CQ75: 2880 | CR75: 3279 | CS75: 2544 | CT75: 3763 | CU75: 4287 | CV75: =CV79+CV83+CV87 | CW75: =CW79+CW83+CW87 | CX75: =CX79+CX83+CX87 | CY75: =CY79+CY83+CY87 | CZ75: =CZ79+CZ83+CZ87 | DA75: =DA79+DA83+DA87 | DB75: =DB79+DB83+DB87 | DC75: =DC79+DC83+DC87 | ... DE75: =DE79+DE83+DE87 | DS75: 1316 | DT75: 1511 | DU75: =SUM(BB75:BE75) | DV75: =SUM(BF75:BI75) | DW75: =SUM(BJ75:BM75) | DX75: =SUM(BN75:BQ75) | DY75: =SUM(BR75:BU75) | DZ75: =BV75+BW75+BX75+BY75 | EA75: =SUM(BZ75:CC75) | EB75: =+CD75+CE75+CF75+CG75 | EC75: =SUM(CH75:CK75) | ED75: =SUM(CL75:CO75) | EE75: =SUM(CP75:CS75) | EF75: =SUM(CT75:CW75) | EG75: =SUM(CX75:DA75) | EH75: =SUM(DB75:DE75)
A76: qoq | BC76: =BC75/BB75-1 | BD76: =BD75/BC75-1 | BE76: =BE75/BD75-1 | BF76: =BF75/BE75-1 | BG76: =BG75/BF75-1 | BH76: =BH75/BG75-1 | BI76: =BI75/BH75-1 | BJ76: =BJ75/BI75-1 | ... DE76: =DE75/DD75-1 | DH76: -- | DI76: -- | DJ76: -- | DK76: -- | DL76: -- | DM76: -- | DN76: -- | DO76: -- | DP76: -- | DQ76: -- | DR76: -- | DS76: -- | DT76: -- | DU76: -- | DV76: -- | DW76: -- | DX76: -- | DY76: -- | DZ76: -- | EA76: -- | EB76: -- | EC76: -- | ED76: -- | EE76: -- | EF76: -- | EG76: -- | EH76: --
A77: yoy | BF77: =BF75/BB75-1 | BG77: =BG75/BC75-1 | BH77: =BH75/BD75-1 | BI77: =BI75/BE75-1 | BJ77: =BJ75/BF75-1 | BK77: =BK75/BG75-1 | BL77: =BL75/BH75-1 | BM77: =BM75/BI75-1 | ... DE77: =DE75/DA75-1 | DT77: =DT75/DS75-1 | DU77: =DU75/DT75-1 | DV77: =DV75/DU75-1 | DW77: =DW75/DV75-1 | DX77: =DX75/DW75-1 | DY77: =DY75/DX75-1 | DZ77: =DZ75/DY75-1 | EA77: =EA75/DZ75-1 | ... EH77: =EH75/EG75-1
A78: % total | BB78: =BB75/BB$131 | BC78: =BC75/BC$131 | BD78: =BD75/BD$131 | BE78: =BE75/BE$131 | BF78: =BF75/BF$131 | BG78: =BG75/BG$131 | BH78: =BH75/BH$131 | BI78: =BI75/BI$131 | ... DE78: =DE75/DE$131 | DS78: =DS75/DS$131 | DT78: =DT75/DT$131 | DU78: =DU75/DU$131 | DV78: =DV75/DV$131 | DW78: =DW75/DW$131 | DX78: =DX75/DX$131 | DY78: =DY75/DY$131 | DZ78: =DZ75/DZ$131 | ... EH78: =EH75/EH$131
A79: Gaming GPU (ex Switch/Crypto) | BB79: =BB75-BB83 | BC79: =BC75-BC83 | BD79: =BD75-BD83 | BE79: =BE75-BE83 | BF79: =BF75-BF83 | BG79: =BG75-BG83 | BH79: =BH75-BH83 | BI79: =BI75-BI83 | ... BM79: =BM75-BM83 | BN79: =BN75-BN83-BN87 | BO79: =BO75-BO83-BO87 | BP79: =BP75-BP83-BP87 | BQ79: =BQ75-BQ83-BQ87 | BR79: =BR75-BR83-BR87 | BS79: =BS75-BS83-BS87 | BT79: =BT75-BT83-BT87 | BU79: =BU75-BU83-BU87 | ... BY79: =BY75-BY83-BY87 | BZ79: =Gaming!AX82 | CA79: =Gaming!AY82 | CB79: =Gaming!AZ82 | CC79: =Gaming!BA82 | CD79: =Gaming!BB82 | CE79: =Gaming!BC82 | CF79: =Gaming!BD82 | CG79: =Gaming!BE82 | ... DE79: =Gaming!CC82 | DU79: =SUM(BB79:BE79) | DV79: =SUM(BF79:BI79) | DW79: =SUM(BJ79:BM79) | DX79: =SUM(BN79:BQ79) | DY79: =SUM(BR79:BU79) | DZ79: =BV79+BW79+BX79+BY79 | EA79: =SUM(BZ79:CC79) | EB79: =+CD79+CE79+CF79+CG79 | EC79: =SUM(CH79:CK79) | ED79: =SUM(CL79:CO79) | EE79: =SUM(CP79:CS79) | EF79: =SUM(CT79:CW79) | EG79: =SUM(CX79:DA79) | EH79: =SUM(DB79:DE79)
A80: qoq | BC80: =BC79/BB79-1 | BD80: =BD79/BC79-1 | BE80: =BE79/BD79-1 | BF80: =BF79/BE79-1 | BG80: =BG79/BF79-1 | BH80: =BH79/BG79-1 | BI80: =BI79/BH79-1 | BJ80: =BJ79/BI79-1 | ... DE80: =DE79/DD79-1 | DH80: -- | DI80: -- | DJ80: -- | DK80: -- | DL80: -- | DM80: -- | DN80: -- | DO80: -- | DP80: -- | DQ80: -- | DR80: -- | DS80: -- | DT80: -- | DU80: -- | DV80: -- | DW80: -- | DX80: -- | DY80: -- | DZ80: -- | EA80: -- | EB80: -- | EC80: -- | ED80: -- | EE80: -- | EF80: -- | EG80: -- | EH80: --
A81: yoy | BF81: =BF79/BB79-1 | BG81: =BG79/BC79-1 | BH81: =BH79/BD79-1 | BI81: =BI79/BE79-1 | BJ81: =BJ79/BF79-1 | BK81: =BK79/BG79-1 | BL81: =BL79/BH79-1 | BM81: =BM79/BI79-1 | ... DE81: =DE79/DA79-1 | DU81: =DU77 | DV81: =DV79/DU79-1 | DW81: =DW79/DV79-1 | DX81: =DX79/DW79-1 | DY81: =DY79/DX79-1 | DZ81: =DZ79/DY79-1 | EA81: =EA79/DZ79-1 | EB81: =EB79/EA79-1 | EC81: =EC79/EB79-1 | ... EH81: =EH79/EG79-1
A82: % total | BB82: =BB79/BB$131 | BC82: =BC79/BC$131 | BD82: =BD79/BD$131 | BE82: =BE79/BE$131 | BF82: =BF79/BF$131 | BG82: =BG79/BG$131 | BH82: =BH79/BH$131 | BI82: =BI79/BI$131 | ... DE82: =DE79/DE$131 | DU82: =DU79/DU$131 | DV82: =DV79/DV$131 | DW82: =DW79/DW$131 | DX82: =DX79/DX$131 | DY82: =DY79/DY$131 | DZ82: =DZ79/DZ$131 | EA82: =EA79/EA$131 | EB82: =EB79/EB$131 | ... EH82: =EH79/EH$131
A83: Switch | BK83: =Gaming!AI96 | BL83: =Gaming!AJ96 | BM83: =Gaming!AK96 | BN83: =Gaming!AL96 | BO83: =Gaming!AM96 | BP83: =Gaming!AN96 | BQ83: =Gaming!AO96 | BR83: =Gaming!AP96 | ... DE83: =Gaming!CC96 | DW83: =SUM(BJ83:BM83) | DX83: =SUM(BN83:BQ83) | DY83: =SUM(BR83:BU83) | DZ83: =BV83+BW83+BX83+BY83 | EA83: =SUM(BZ83:CC83) | EB83: =+CD83+CE83+CF83+CG83 | EC83: =SUM(CH83:CK83) | ED83: =SUM(CL83:CO83) | EE83: =SUM(CP83:CS83) | EF83: =SUM(CT83:CW83) | EG83: =SUM(CX83:DA83) | EH83: =SUM(DB83:DE83)
A84: qoq | BL84: =BL83/BK83-1 | BM84: =BM83/BL83-1 | BN84: =BN83/BM83-1 | BO84: =BO83/BN83-1 | BP84: =BP83/BO83-1 | BQ84: =BQ83/BP83-1 | BR84: =BR83/BQ83-1 | BS84: =BS83/BR83-1 | ... DE84: =DE83/DD83-1 | DH84: -- | DI84: -- | DJ84: -- | DK84: -- | DL84: -- | DM84: -- | DN84: -- | DO84: -- | DP84: -- | DQ84: -- | DR84: -- | DS84: -- | DT84: -- | DU84: -- | DV84: -- | DW84: -- | DX84: -- | DY84: -- | DZ84: -- | EA84: -- | EB84: -- | EC84: -- | ED84: -- | EE84: -- | EF84: -- | EG84: -- | EH84: --
A85: yoy | BO85: =BO83/BK83-1 | BP85: =BP83/BL83-1 | BQ85: =BQ83/BM83-1 | BR85: =BR83/BN83-1 | BS85: =BS83/BO83-1 | BT85: =BT83/BP83-1 | BU85: =BU83/BQ83-1 | BV85: =BV83/BR83-1 | ... DE85: =DE83/DA83-1 | DX85: =DX83/DW83-1 | DY85: =DY83/DX83-1 | DZ85: =DZ83/DY83-1 | EA85: =EA83/DZ83-1 | EB85: =EB83/EA83-1 | EC85: =EC83/EB83-1 | ED85: =ED83/EC83-1 | EE85: =EE83/ED83-1 | ... EH85: =EH83/EG83-1
A86: % total | BK86: =BK83/BK$131 | BL86: =BL83/BL$131 | BM86: =BM83/BM$131 | BN86: =BN83/BN$131 | BO86: =BO83/BO$131 | BP86: =BP83/BP$131 | BQ86: =BQ83/BQ$131 | BR86: =BR83/BR$131 | ... DE86: =DE83/DE$131 | DW86: =DW83/DW$131 | DX86: =DX83/DX$131 | DY86: =DY83/DY$131 | DZ86: =DZ83/DZ$131 | EA86: =EA83/EA$131 | EB86: =EB83/EB$131 | EC86: =EC83/EC$131 | ED86: =ED83/ED$131 | ... EH86: =EH83/EH$131
A87: Crypto | BN87: =Gaming!AL85 | BO87: =Gaming!AM85 | BP87: =Gaming!AN85 | BQ87: =Gaming!AO85 | BR87: =Gaming!AP85 | BS87: =Gaming!AQ85 | BT87: =Gaming!AR85 | BU87: =Gaming!AS85 | ... DE87: =Gaming!CC85 | DX87: =SUM(BN87:BQ87) | DY87: =SUM(BR87:BU87) | DZ87: =BV87+BW87+BX87+BY87 | EA87: =BZ87+CA87+CB87+CC87 | EB87: =+CD87+CE87+CF87+CG87 | EC87: =SUM(CH87:CK87) | ED87: =SUM(CL87:CO87) | EE87: =SUM(CP87:CS87) | EF87: =SUM(CT87:CW87) | EG87: =SUM(CX87:DA87) | EH87: =SUM(CY87:DB87)
A88: qoq | BQ88: =BQ87/BP87-1 | BR88: =BR87/BQ87-1 | BS88: =BS87/BR87-1 | BT88: -- | BU88: -- | BV88: -- | BW88: -- | BX88: -- | BY88: -- | BZ88: -- | CA88: -- | CB88: -- | CC88: -- | CD88: =CD87/CC87-1 | CE88: =CE87/CD87-1 | CF88: =CF87/CE87-1 | CG88: =CG87/CF87-1 | CH88: =CH87/CG87-1 | CI88: =CI87/CH87-1 | CJ88: =CJ87/CI87-1 | CK88: =CK87/CJ87-1 | CL88: -- | CM88: -- | CN88: -- | CO88: -- | CP88: -- | CQ88: -- | CR88: -- | CS88: -- | CT88: -- | CU88: -- | CV88: -- | CW88: -- | CX88: -- | CY88: -- | CZ88: -- | DA88: -- | DB88: -- | DC88: -- | DD88: -- | DE88: -- | DH88: -- | DI88: -- | DJ88: -- | DK88: -- | DL88: -- | DM88: -- | DN88: -- | DO88: -- | DP88: -- | DQ88: -- | DR88: -- | DS88: -- | DT88: -- | DU88: -- | DV88: -- | DW88: -- | DX88: -- | DY88: -- | DZ88: -- | EA88: -- | EB88: -- | EC88: -- | ED88: -- | EE88: -- | EF88: -- | EG88: -- | EH88: --
A89: yoy | BT89: =BT87/BP87-1 | BU89: =BU87/BQ87-1 | BV89: =BV87/BR87-1 | BW89: -- | BX89: -- | BY89: -- | BZ89: -- | CA89: -- | CB89: -- | CC89: -- | CD89: -- | CE89: -- | CF89: -- | CG89: -- | CH89: -- | CI89: -- | CJ89: -- | CK89: -- | CL89: -- | CM89: -- | CN89: -- | CO89: -- | CP89: -- | CQ89: -- | CR89: -- | CS89: -- | CT89: -- | CU89: -- | CV89: -- | CW89: -- | CX89: -- | CY89: -- | CZ89: -- | DA89: -- | DB89: -- | DC89: -- | DD89: -- | DE89: -- | DY89: =DY87/DX87-1 | DZ89: =DZ87/DY87-1 | EA89: -- | EB89: -- | EC89: -- | ED89: -- | EE89: -- | EF89: -- | EG89: -- | EH89: --
A90: % total | BN90: =BN87/BN$131 | BO90: =BO87/BO$131 | BP90: =BP87/BP$131 | BQ90: =BQ87/BQ$131 | BR90: =BR87/BR$131 | BS90: =BS87/BS$131 | BT90: =BT87/BT$131 | BU90: =BU87/BU$131 | ... DE90: =DE87/DE$131 | DX90: =DX87/DX$131 | DY90: =DY87/DY$131 | DZ90: =DZ87/DZ$131 | EA90: =EA87/EA$131 | EB90: =EB87/EB$131 | EC90: =EC87/EC$131 | ED90: =ED87/ED$131 | EE90: =EE87/EE$131 | ... EH90: =EH87/EH$131
A91: Professional Visualization | BB91: 191 | BC91: 208 | BD91: 206 | BE91: 190 | BF91: 181 | BG91: 176 | BH91: 190 | BI91: 203 | BJ91: 189 | BK91: 214 | BL91: 207 | BM91: 225 | BN91: 205 | BO91: 235 | BP91: 239 | BQ91: 254 | BR91: 251 | BS91: 281 | BT91: 305 | BU91: 293 | BV91: 266 | BW91: 291 | BX91: 324 | BY91: 331 | BZ91: 307 | CA91: 203 | CB91: 236 | CC91: 307 | CD91: 372 | CE91: 519 | CF91: 577 | CG91: 643 | CH91: 622 | CI91: 496 | CJ91: 200 | CK91: 226 | CL91: 295 | CM91: 379 | CN91: 416 | CO91: 463 | CP91: 427 | CQ91: 454 | CR91: 486 | CS91: 511 | CT91: 509 | CU91: 601 | CV91: =CU91*(1+CV92) | CW91: =CV91*(1+CW92) | CX91: =CW91*(1+CX92) | CY91: =CX91*(1+CY92) | CZ91: =CY91*(1+CZ92) | DA91: =CZ91*(1+DA92) | DB91: =DA91*(1+DB92) | DC91: =DB91*(1+DC92) | ... DE91: =DD91*(1+DE92) | DS91: 719 | DT91: 789 | DU91: =SUM(BB91:BE91) | DV91: =SUM(BF91:BI91) | DW91: =SUM(BJ91:BM91) | DX91: =SUM(BN91:BQ91) | DY91: =SUM(BR91:BU91) | DZ91: =BV91+BW91+BX91+BY91 | EA91: =SUM(BZ91:CC91) | EB91: =+CD91+CE91+CF91+CG91 | EC91: =SUM(CH91:CK91) | ED91: =SUM(CL91:CO91) | EE91: =SUM(CP91:CS91) | EF91: =SUM(CT91:CW91) | EG91: =SUM(CX91:DA91) | EH91: =SUM(DB91:DE91)
A92: qoq | BC92: =BC91/BB91-1 | BD92: =BD91/BC91-1 | BE92: =BE91/BD91-1 | BF92: =BF91/BE91-1 | BG92: =BG91/BF91-1 | BH92: =BH91/BG91-1 | BI92: =BI91/BH91-1 | BJ92: =BJ91/BI91-1 | ... CU92: =CU91/CT91-1 | CV92: 0.07 | CW92: 0.05 | CX92: -0.1 | CY92: 0.05 | CZ92: 0.07 | DA92: 0.05 | DB92: -0.08 | DC92: 0.04 | DD92: 0.06 | DE92: 0.04 | DH92: -- | DI92: -- | DJ92: -- | DK92: -- | DL92: -- | DM92: -- | DN92: -- | DO92: -- | DP92: -- | DQ92: -- | DR92: -- | DS92: -- | DT92: -- | DU92: -- | DV92: -- | DW92: -- | DX92: -- | DY92: -- | DZ92: -- | EA92: -- | EB92: -- | EC92: -- | ED92: -- | EE92: -- | EF92: -- | EG92: -- | EH92: --
A93: yoy | BF93: =BF91/BB91-1 | BG93: =BG91/BC91-1 | BH93: =BH91/BD91-1 | BI93: =BI91/BE91-1 | BJ93: =BJ91/BF91-1 | BK93: =BK91/BG91-1 | BL93: =BL91/BH91-1 | BM93: =BM91/BI91-1 | ... DE93: =DE91/DA91-1 | DT93: =DT91/DS91-1 | DU93: =DU91/DT91-1 | DV93: =DV91/DU91-1 | DW93: =DW91/DV91-1 | DX93: =DX91/DW91-1 | DY93: =DY91/DX91-1 | DZ93: =DZ91/DY91-1 | EA93: =EA91/DZ91-1 | ... EH93: =EH91/EG91-1
A94: % total | BB94: =BB91/BB$131 | BC94: =BC91/BC$131 | BD94: =BD91/BD$131 | BE94: =BE91/BE$131 | BF94: =BF91/BF$131 | BG94: =BG91/BG$131 | BH94: =BH91/BH$131 | BI94: =BI91/BI$131 | ... DE94: =DE91/DE$131 | DS94: =DS91/DS$131 | DT94: =DT91/DT$131 | DU94: =DU91/DU$131 | DV94: =DV91/DV$131 | DW94: =DW91/DW$131 | DX94: =DX91/DX$131 | DY94: =DY91/DY$131 | DZ94: =DZ91/DZ$131 | ... EH94: =EH91/EH$131
A95: Data Center | BB95: =+BB103+BB99 | BC95: =+BC103+BC99 | BD95: =+BD103+BD99 | BE95: =+BE103+BE99 | BF95: =+BF103+BF99 | BG95: =+BG103+BG99 | BH95: =+BH103+BH99 | BI95: =+BI103+BI99 | ... BZ95: =+BZ103+BZ99 | CA95: 1752 | CB95: 1900 | CC95: 1903 | CD95: 2048 | CE95: 2366 | CF95: 2936 | CG95: 3263 | CH95: 3750 | CI95: 3806 | CJ95: 3833 | CK95: 3616 | CL95: 4284 | CM95: 10323 | CN95: 14514 | CO95: 18404 | CP95: 22563 | CQ95: 26272 | CR95: 30771 | CS95: 35580 | CT95: 39112 | CU95: 41096 | CV95: =+CV103+CV99 | CW95: =+CW103+CW99 | CX95: =+CX103+CX99 | CY95: =+CY103+CY99 | CZ95: =+CZ103+CZ99 | DA95: =+DA103+DA99 | DB95: =+DB103+DB99 | DC95: =+DC103+DC99 | ... DE95: =+DE103+DE99 | DS95: 129 | DT95: 199 | DU95: =SUM(BB95:BE95) | DV95: =SUM(BF95:BI95) | DW95: =SUM(BJ95:BM95) | DX95: =SUM(BN95:BQ95) | DY95: =SUM(BR95:BU95) | DZ95: =BV95+BW95+BX95+BY95 | EA95: =SUM(BZ95:CC95) | EB95: =+CD95+CE95+CF95+CG95 | EC95: =SUM(CH95:CK95) | ED95: =SUM(CL95:CO95) | EE95: =SUM(CP95:CS95) | EF95: =SUM(CT95:CW95) | EG95: =SUM(CX95:DA95) | EH95: =SUM(DB95:DE95)
A96: qoq | BC96: =BC95/BB95-1 | BD96: =BD95/BC95-1 | BE96: =BE95/BD95-1 | BF96: =BF95/BE95-1 | BG96: =BG95/BF95-1 | BH96: =BH95/BG95-1 | BI96: =BI95/BH95-1 | BJ96: =BJ95/BI95-1 | ... DE96: =DE95/DD95-1 | DH96: -- | DI96: -- | DJ96: -- | DK96: -- | DL96: -- | DM96: -- | DN96: -- | DO96: -- | DP96: -- | DQ96: -- | DR96: -- | DS96: -- | DT96: -- | DU96: -- | DV96: -- | DW96: -- | DX96: -- | DY96: -- | DZ96: -- | EA96: -- | EB96: -- | EC96: -- | ED96: -- | EE96: -- | EF96: -- | EG96: -- | EH96: --
A97: yoy | BF97: =BF95/BB95-1 | BG97: =BG95/BC95-1 | BH97: =BH95/BD95-1 | BI97: =BI95/BE95-1 | BJ97: =BJ95/BF95-1 | BK97: =BK95/BG95-1 | BL97: =BL95/BH95-1 | BM97: =BM95/BI95-1 | ... DE97: =DE95/DA95-1 | DT97: =DT95/DS95-1 | DU97: =DU95/DT95-1 | DV97: =DV95/DU95-1 | DW97: =DW95/DV95-1 | DX97: =DX95/DW95-1 | DY97: =DY95/DX95-1 | DZ97: =DZ95/DY95-1 | EA97: =EA95/DZ95-1 | ... EH97: =EH95/EG95-1
A98: % total | BB98: =BB95/BB$131 | BC98: =BC95/BC$131 | BD98: =BD95/BD$131 | BE98: =BE95/BE$131 | BF98: =BF95/BF$131 | BG98: =BG95/BG$131 | BH98: =BH95/BH$131 | BI98: =BI95/BI$131 | ... DE98: =DE95/DE$131 | DS98: =DS95/DS$131 | DT98: =DT95/DT$131 | DU98: =DU95/DU$131 | DV98: =DV95/DV$131 | DW98: =DW95/DW$131 | DX98: =DX95/DX$131 | DY98: =DY95/DY$131 | DZ98: =DZ95/DZ$131 | ... EH98: =EH95/EH$131
A99: Classic Data Center (Compute) | BB99: 57 | BC99: 83 | BD99: 90 | BE99: 88 | BF99: 88 | BG99: 73 | BH99: 82 | BI99: 97 | BJ99: 143 | BK99: 151 | BL99: 240 | BM99: 296 | BN99: 409 | BO99: 416 | BP99: 501 | BQ99: 606 | BR99: 701 | BS99: 760 | BT99: 792 | BU99: 679 | BV99: 634 | BW99: 655 | BX99: 726 | BY99: 968 | BZ99: 1141 | CA99: =CA95-CA103 | CB99: =CB95-CB103 | CC99: =CC95-CC103 | CD99: =CD95-CD103 | CE99: =CE95-CE103 | CF99: =CF95-CF103 | CG99: =CG95-CG103 | CH99: =CH95-CH103 | ... CU99: =CU95-CU103 | CV99: =Datacenter!BT15 | CW99: =Datacenter!BU15 | CX99: =Datacenter!BV15 | CY99: =Datacenter!BW15 | CZ99: =Datacenter!BX15 | DA99: =Datacenter!BY15 | DB99: =Datacenter!BZ15 | DC99: =Datacenter!CA15 | ... DE99: =Datacenter!CC15 | DS99: 129 | DT99: 199 | DU99: =SUM(BB99:BE99) | DV99: =SUM(BF99:BI99) | DW99: =SUM(BJ99:BM99) | DX99: =SUM(BN99:BQ99) | DY99: =SUM(BR99:BU99) | DZ99: =BV99+BW99+BX99+BY99 | EA99: =SUM(BZ99:CC99) | EB99: =+CD99+CE99+CF99+CG99 | EC99: =SUM(CH99:CK99) | ED99: =SUM(CL99:CO99) | EE99: =SUM(CP99:CS99) | EF99: =SUM(CT99:CW99) | EG99: =SUM(CX99:DA99) | EH99: =SUM(DB99:DE99)
A100: qoq | BC100: =BC99/BB99-1 | BD100: =BD99/BC99-1 | BE100: =BE99/BD99-1 | BF100: =BF99/BE99-1 | BG100: =BG99/BF99-1 | BH100: =BH99/BG99-1 | BI100: =BI99/BH99-1 | BJ100: =BJ99/BI99-1 | ... DE100: =DE99/DD99-1 | DH100: -- | DI100: -- | DJ100: -- | DK100: -- | DL100: -- | DM100: -- | DN100: -- | DO100: -- | DP100: -- | DQ100: -- | DR100: -- | DS100: -- | DT100: -- | DU100: -- | DV100: -- | DW100: -- | DX100: -- | DY100: -- | DZ100: -- | EA100: -- | EB100: -- | EC100: -- | ED100: -- | EE100: -- | EF100: -- | EG100: -- | EH100: --
A101: yoy | BF101: =BF99/BB99-1 | BG101: =BG99/BC99-1 | BH101: =BH99/BD99-1 | BI101: =BI99/BE99-1 | BJ101: =BJ99/BF99-1 | BK101: =BK99/BG99-1 | BL101: =BL99/BH99-1 | BM101: =BM99/BI99-1 | ... DE101: =DE99/DA99-1 | DT101: =DT99/DS99-1 | DU101: =DU99/DT99-1 | DV101: =DV99/DU99-1 | DW101: =DW99/DV99-1 | DX101: =DX99/DW99-1 | DY101: =DY99/DX99-1 | DZ101: =DZ99/DY99-1 | EA101: =EA99/DZ99-1 | ... EH101: =EH99/EG99-1
A102: % total | BB102: =BB99/BB$131 | BC102: =BC99/BC$131 | BD102: =BD99/BD$131 | BE102: =BE99/BE$131 | BF102: =BF99/BF$131 | BG102: =BG99/BG$131 | BH102: =BH99/BH$131 | BI102: =BI99/BI$131 | ... DE102: =DE99/DE$131 | DS102: =DS99/DS$131 | DT102: =DT99/DT$131 | DU102: =DU99/DU$131 | DV102: =DV99/DV$131 | DW102: =DW99/DW$131 | DX102: =DX99/DX$131 | DY102: =DY99/DY$131 | DZ102: =DZ99/DZ$131 | ... EH102: =EH99/EH$131
A103: Classic Company1796 (Networking) | R103: 7.682 | S103: 10.04 | T103: 12.152 | U103: 12.194 | V103: 8.506 | W103: 10.813 | X103: 13.422 | Y103: 15.798 | Z103: 16.855 | AA103: 19.779 | AB103: 22.664 | AC103: 24.78 | AD103: 25.155 | AE103: 28.201 | AF103: 29.138 | AG103: 25.207 | AH103: 22.558 | AI103: 25.286 | AJ103: 32.671 | AK103: 35.529 | AL103: 36.21 | AM103: 39.958 | AN103: 37.779 | AO103: 40.693 | AP103: 55.057 | AQ103: 63.345 | AR103: 68.16 | AS103: 72.689 | AT103: 86.838 | AU103: 133.472 | AV103: 156.471 | AW103: 122.118 | AX103: 83.08 | AY103: 98.168 | AZ103: 104.067 | BA103: 105.56 | BB103: 98.705 | BC103: 102.574 | BD103: 120.708 | BE103: 141.116 | BF103: 146.675 | BG103: 163.148 | BH103: 171.377 | BI103: 176.94 | BJ103: 196.81 | BK103: 214.801 | BL103: 224.211 | BM103: 221.676 | BN103: 188.651 | BO103: 211.962 | BP103: 225.699 | BQ103: 237.581 | BR103: 251 | BS103: 268.462 | BT103: 279.211 | BU103: 290.07 | BV103: 305.217 | BW103: 310.324 | BX103: 335.251 | BY103: 379.784 | BZ103: 428.746 | CA103: 540 | CB103: 615 | CC103: =BY103*1.31 | CD103: =BZ103*1.25 | CE103: =CA103*1.2 | CF103: =+CE103*(1+CF104) | CG103: =+CF103*(1+CG104) | CH103: =+CG103*(1+CH104) | CI103: =+CH103*(1+CI104) | CJ103: =+CI103*(1+CJ104) | CK103: =+CJ103*(1+CK104) | CL103: 927 | CM103: 1711 | CN103: =CO103/1.28 | CO103: 3331 | CP103: 3171 | CQ103: 3668 | CR103: 3127 | CS103: 3024 | CT103: 4957 | CU103: 7252 | CV103: =+CU103*(1+CV104) | CW103: =+CV103*(1+CW104) | CX103: =+CW103*(1+CX104) | CY103: =+CX103*(1+CY104) | CZ103: =+CY103*(1+CZ104) | DA103: =+CZ103*(1+DA104) | DB103: =+DA103*(1+DB104) | DC103: =+DB103*(1+DC104) | ... DE103: =+DD103*(1+DE104) | DS103: 56 | DT103: 99 | DU103: =SUM(BB103:BE103) | DV103: =SUM(BF103:BI103) | DW103: =SUM(BJ103:BM103) | DX103: =SUM(BN103:BQ103) | DY103: =SUM(BR103:BU103) | DZ103: =BV103+BW103+BX103+BY103 | EA103: =SUM(BZ103:CC103) | EB103: =+CD103+CE103+CF103+CG103 | EC103: =SUM(CH103:CK103) | ED103: =SUM(CL103:CO103) | EE103: =SUM(CP103:CS103) | EF103: =SUM(CT103:CW103) | EG103: =SUM(CX103:DA103) | EH103: =SUM(DB103:DE103)
A104: qoq | BC104: =BC103/BB103-1 | BD104: =BD103/BC103-1 | BE104: =BE103/BD103-1 | BF104: =BF103/BE103-1 | BG104: =BG103/BF103-1 | BH104: =BH103/BG103-1 | BI104: =BI103/BH103-1 | BJ104: =BJ103/BI103-1 | ... CE104: =CE103/CD103-1 | CF104: 0 | CG104: 0.1 | CH104: 0.05 | CI104: 0.07 | CJ104: 0.25 | CK104: 0.05 | CL104: =CL103/CK103-1 | CM104: =CM103/CL103-1 | CN104: 0.57 | CO104: =CO103/CN103-1 | CP104: =CP103/CO103-1 | CQ104: =CQ103/CP103-1 | CR104: =CR103/CQ103-1 | CS104: =CS103/CR103-1 | CT104: =CT103/CS103-1 | CU104: =CU103/CT103-1 | CV104: 0.21 | CW104: 0.12 | CX104: 0.05 | CY104: 0.08 | CZ104: 0.11 | DA104: 0.07 | DB104: 0.02 | DC104: 0.02 | DD104: 0.03 | DE104: 0.03 | DH104: -- | DI104: -- | DJ104: -- | DK104: -- | DL104: -- | DM104: -- | DN104: -- | DO104: -- | DP104: -- | DQ104: -- | DR104: -- | DS104: -- | DT104: -- | DU104: -- | DV104: -- | DW104: -- | DX104: -- | DY104: -- | DZ104: -- | EA104: -- | EB104: -- | EC104: -- | ED104: -- | EE104: -- | EF104: -- | EG104: -- | EH104: --
...

Sheet Ticker0027
A2: Company1953 | B2: Q198 | C2: Q298 | D2: Q398 | E2: Q498 | F2: FY | G2: Q199 | H2: Q299 | I2: Q399 | J2: Q499 | K2: FY | L2: Q100 | M2: Q200 | N2: Q300 | O2: Q400 | P2: FY | Q2: Q101 | R2: Q201 | S2: Q301 | T2: Q401 | U2: FY | V2: Q102 | W2: Q202 | X2: Q302 | Y2: Q402 | Z2: FY | AA2: Q103 | AB2: Q203 | AC2: Q303 | AD2: Q403 | AE2: FY | AF2: Q104 | AG2: Q204 | AH2: Q304 | AI2: Q404 | AJ2: FY | AK2: 1Q05 | AL2: 2Q05 | AM2: 3Q05 | AN2: 4Q05 | AO2: FY | AP2: 1Q06 | AQ2: 2Q06 | AR2: 3Q06 | AS2: 4Q06 | AT2: FY | AU2: 1Q07 | AV2: 2Q07 | AW2: 3Q07 | AX2: 4Q07 | AY2: FY | AZ2: 1Q08 | BA2: 2Q08 | BB2: 3Q08 | BC2: 4Q08 | BD2: FY | BE2: 1Q09 | BF2: 2Q09 | BG2: 3Q09 | BH2: 4Q09 | BI2: FY | BJ2: 1Q10 | BK2: 2Q10 | BL2: 3Q10 | BM2: 4Q10 | BN2: FY | BO2: 1Q11 | BP2: 2Q11 | BQ2: 3Q11 | BR2: 4Q11 | BS2: FY | BT2: 1Q12 | BU2: 2Q12 | BV2: 3Q12 | BW2: 4Q12 | BX2: FY | BY2: 1Q13 | BZ2: 2Q13 | CA2: 3Q13 | CB2: 4Q13 | CC2: FY | CD2: 1Q14 | CE2: 2Q14 | CF2: 3Q14 | CG2: 4Q14 | CH2: FY | CI2: 1Q15 | CJ2: 2Q15 | CK2: 3Q15 | CL2: 4Q15 | CM2: FY | CN2: 1Q16 | CO2: 2Q16 | CP2: 3Q16 | CQ2: 4Q16 | CR2: FY | CS2: 1Q17 | CT2: 2Q17 | CU2: 3Q17 | CV2: 4Q17 | CW2: FY | CX2: 1Q18 | CY2: 2Q18 | CZ2: 3Q18 | DA2: 4Q18 | DB2: FY | DC2: 1Q19 | DD2: 2Q19 | DE2: 3Q19 | DF2: 4Q19 | DG2: FY | DH2: 1Q20 | DI2: 2Q20 | DJ2: 3Q20 | DK2: 4Q20 | DL2: FY | DM2: 1Q21 | DN2: 2Q21 | DO2: 3Q21 | DP2: 4Q21 | DQ2: FY | DR2: 1Q22 | DS2: 2Q22 | DT2: 3Q22 | DU2: 4Q22 | DV2: FY | DW2: 1Q23 | DX2: 2Q23 | DY2: 3Q23 | DZ2: 4Q23 | EA2: FY | EB2: 1Q24 | EC2: 2Q24 | ED2: 3Q24 | EE2: 4Q24 | EF2: FY | EG2: 1Q25 | EH2: 2Q25 | EI2: 3Q25 | EJ2: 4Q25 | EK2: FY | EL2: 1Q26 | EM2: 2Q26 | EN2: 3Q26E | EO2: 4Q26E | EP2: FY | EQ2: 1Q27E | ER2: 2Q27E | ES2: 3Q27E | ET2: 4Q27E | EU2: FY | EV2: 1Q28E | EW2: 2Q28E | EX2: 3Q28E | EY2: 4Q28E | EZ2: FY
B3: 35519 | C3: 35610 | D3: 35701 | E3: 35795 | F3: =K3-1 | G3: 35911 | H3: 36002 | I3: 36093 | J3: 36191 | K3: =P3-1 | L3: 36282 | M3: 36373 | N3: 36464 | O3: 36555 | P3: =U3-1 | Q3: 36646 | R3: 36737 | S3: 36828 | T3: 36919 | U3: =Z3-1 | V3: 37010 | W3: 37101 | X3: 37192 | Y3: 37283 | Z3: =AE3-1 | AA3: 37374 | AB3: 37465 | AC3: 37556 | AD3: 37647 | AE3: =AJ3-1 | AF3: 37741 | AG3: 37833 | AH3: 37925 | AI3: 38017 | AJ3: =AO3-1 | AK3: 38102 | AL3: 38199 | AM3: 38291 | AN3: 38383 | AO3: =AT3-1 | AP3: 38443 | AQ3: 38564 | AR3: 38656 | AS3: 38748 | AT3: =AY3-1 | AU3: 38837 | AV3: 38928 | AW3: 39019 | AX3: 39113 | AY3: =BD3-1 | AZ3: 39201 | BA3: 39294 | BB3: 39386 | BC3: 39478 | BD3: =BI3-1 | BE3: 4/31/2008 | BF3: 39660 | BG3: 39752 | BH3: 39844 | BI3: =BN3-1 | BJ3: 4/31/2009 | BK3: 40025 | BL3: 40117 | BM3: 40209 | BN3: =BS3-1 | BO3: 4/31/2010 | BP3: 40390 | BQ3: 40482 | BR3: 40574 | BS3: =BX3-1 | BT3: 4/31/2011 | BU3: 40755 | BV3: 40847 | BW3: 40939 | BX3: =CC3-1 | BY3: 4/31/2012 | BZ3: 41121 | CA3: 41213 | CB3: 41305 | CC3: =CH3-1 | CD3: 4/31/2013 | CE3: 41486 | CF3: 41578 | CG3: 41670 | CH3: =CM3-1 | CI3: 4/31/2014 | CJ3: 41851 | CK3: 41943 | CL3: 42035 | CM3: =CR3-1 | CN3: 4/31/2015 | CO3: 42216 | CP3: 42308 | CQ3: 42400 | CR3: =CW3-1 | CS3: 4/31/2016 | CT3: 42582 | CU3: 42674 | CV3: 42766 | CW3: =DB3-1 | CX3: 4/31/2017 | CY3: 42947 | CZ3: 43039 | DA3: 43131 | DB3: 2018 | DC3: 4/31/2018 | DD3: 43312 | DE3: 43404 | DF3: 43496 | DG3: 2019 | DH3: 4/31/2019 | DI3: 43677 | DJ3: 43769 | DK3: 43861 | DL3: 2020 | DM3: 4/31/2020 | DN3: 44043 | DO3: 44135 | DP3: 44227 | DQ3: 2021 | DR3: 4/31/2021 | DS3: 44408 | DT3: 44500 | DU3: 44592 | DV3: 2022 | DW3: 4/31/2022 | DX3: 44773 | DY3: 44865 | DZ3: 44957 | EA3: 2023 | EB3: 4/31/23 | EC3: 45138 | ED3: 45230 | EE3: 45322 | EF3: 2024 | EG3: 4/31/24 | EH3: 45504 | EI3: 45596 | EJ3: 45688 | EK3: 2025 | EL3: 4/31/25 | EM3: 45869 | EN3: 45961 | EO3: 46053 | EP3: 2026 | EQ3: 4/31/26 | ER3: 46234 | ES3: 46326 | ET3: 46418 | EU3: 2027 | EV3: 4/31/27 | EW3: 46599 | EX3: 46691 | EY3: 46783 | EZ3: 2028
A4: Fiscal year ends January | B4: Nov | C4: Feb | D4: May | E4: Aug | G4: Nov | H4: Feb | I4: May | J4: Aug | L4: Nov | M4: Feb | N4: May | O4: Aug | Q4: Nov | R4: Feb | S4: May | T4: Aug | V4: Nov | W4: Feb | X4: May | Y4: Aug | AA4: Nov | AB4: Feb | AC4: May | AD4: Aug
A5: Company1953 Income Statement
A7: Revenue | B7: 0.065 | C7: 0.006 | D7: 5.466 | E7: 23.534 | F7: =SUM(B7:E7) | G7: 28.263 | H7: 12.134 | I7: 52.303 | J7: 65.537 | K7: =SUM(G7:J7) | L7: 71.018 | M7: 78.017 | N7: 97.015 | O7: 128.455 | P7: =SUM(L7:O7) | Q7: 148.483 | R7: 169.318 | S7: 197.667 | T7: 219.796 | U7: =SUM(Q7:T7) | V7: 240.932 | W7: 259.875 | X7: 364.976 | Y7: 503.688 | Z7: =SUM(V7:Y7) | AA7: 582.905 | AB7: 427.285 | AC7: 430.304 | AD7: =468.953-40.365 | AE7: =SUM(AA7:AD7) | AF7: 404.983 | AG7: 459.774 | AH7: 486.069 | AI7: 472.119 | AJ7: =SUM(AF7:AI7) | AK7: 471.905 | AL7: 456.061 | AM7: 515.591 | AN7: 566.476 | AO7: =SUM(AK7:AN7) | AP7: 583.846 | AQ7: 574.812 | AR7: 583.415 | AS7: 633.614 | AT7: =SUM(AP7:AS7) | AU7: 681.807 | AV7: 687.519 | AW7: 820.572 | AX7: 878.873 | AY7: =SUM(AU7:AX7) | AZ7: 844.28 | BA7: 935.253 | BB7: 1115.597 | BC7: 1202.73 | BD7: =SUM(AZ7:BC7) | BE7: 1153.388 | BF7: 892.676 | BG7: 897.655 | BH7: 481.14 | BI7: =SUM(BE7:BH7) | BJ7: 664.231 | BK7: 776.52 | BL7: 903.206 | BM7: 982.488 | BN7: =SUM(BJ7:BM7) | BO7: 1001.813 | BP7: 811.208 | BQ7: 843.912 | BR7: 886.376 | BS7: =SUM(BO7:BR7) | BT7: 962.039 | BU7: 1016.517 | BV7: 1066.18 | BW7: 953.194 | BX7: =SUM(BT7:BW7) | BY7: 924.877 | BZ7: 1044.27 | CA7: 1204.11 | CB7: 1106.902 | CC7: =SUM(BY7:CB7) | CD7: 954.739 | CE7: 977.238 | CF7: 1053.967 | CG7: 1144.218 | CH7: =SUM(CD7:CG7) | CI7: 1102.787 | CJ7: 1102.824 | CK7: 1225.382 | CL7: 1250.514 | CM7: =SUM(CI7:CL7) | CN7: =1151 | CO7: =1153 | CP7: =1305 | CQ7: =1401 | CR7: =SUM(CN7:CQ7) | CS7: 1305 | CT7: 1428 | CU7: 2004 | CV7: 2173 | CW7: =SUM(CS7:CV7) | CX7: 1937 | CY7: 2230 | CZ7: 2636 | DA7: 2911 | DB7: =SUM(CX7:DA7) | DC7: 3207 | DD7: 3123 | DE7: 3181 | DF7: 2205 | DG7: =SUM(DC7:DF7) | DH7: 2220 | DI7: 2579 | DJ7: 3014 | DK7: 3105 | DL7: =SUM(DH7:DK7) | DM7: 3080 | DN7: 3866 | DO7: 4726 | DP7: 5003 | DQ7: =SUM(DM7:DP7) | DR7: 5661 | DS7: 6507 | DT7: 7103 | DU7: 7643 | DV7: =SUM(DR7:DU7) | DW7: 8288 | DX7: 6704 | DY7: 5931 | DZ7: 6051 | EA7: =SUM(DW7:DZ7) | EB7: 7192 | EC7: 13507 | ED7: 18120 | EE7: 22103 | EF7: =SUM(EB7:EE7) | EG7: 26044 | EH7: 30040 | EI7: 35082 | EJ7: 39331 | EK7: =SUM(EG7:EJ7) | EL7: 44062 | EM7: 46743 | EN7: =Worksheet!CV5 | EO7: =Worksheet!CW5 | EP7: =SUM(EL7:EO7) | EQ7: =Worksheet!CX5 | ER7: =Worksheet!CY5 | ES7: =Worksheet!CZ5 | ET7: =Worksheet!DA5 | EU7: =SUM(EQ7:ET7) | EV7: =Worksheet!DB5 | EW7: =Worksheet!DC5 | EX7: =Worksheet!DD5 | EY7: =Worksheet!DE5 | EZ7: =SUM(EV7:EY7)
A8: % Growth qoq | F8: -- | G8: =G7/E7-1 | H8: =H7/G7-1 | I8: =I7/H7-1 | J8: =J7/I7-1 | K8: -- | L8: =L7/J7-1 | M8: =M7/L7-1 | N8: =N7/M7-1 | O8: =O7/N7-1 | P8: -- | Q8: =Q7/O7-1 | R8: =R7/Q7-1 | S8: =S7/R7-1 | T8: =T7/S7-1 | U8: -- | V8: =V7/T7-1 | W8: =W7/V7-1 | X8: =X7/W7-1 | Y8: =Y7/X7-1 | Z8: -- | AA8: =AA7/Y7-1 | AB8: =AB7/AA7-1 | AC8: =AC7/AB7-1 | AD8: =AD7/AC7-1 | AE8: -- | AF8: =AF7/AD7-1 | AG8: =AG7/AF7-1 | AH8: =AH7/AG7-1 | AI8: =AI7/AH7-1 | AJ8: -- | AK8: =AK7/AI7-1 | AL8: =AL7/AK7-1 | AM8: =AM7/AL7-1 | AN8: =AN7/AM7-1 | AO8: -- | AP8: =AP7/AN7-1 | AQ8: =AQ7/AP7-1 | AR8: =AR7/AQ7-1 | AS8: =AS7/AR7-1 | AT8: -- | AU8: =AU7/AS7-1 | AV8: =AV7/AU7-1 | AW8: =AW7/AV7-1 | AX8: =AX7/AW7-1 | AY8: -- | AZ8: =AZ7/AX7-1 | BA8: =BA7/AZ7-1 | BB8: =BB7/BA7-1 | BC8: =BC7/BB7-1 | BD8: -- | BE8: =BE7/BC7-1 | BF8: =BF7/BE7-1 | BG8: =BG7/BF7-1 | BH8: =BH7/BG7-1 | BI8: -- | BJ8: =BJ7/BH7-1 | BK8: =BK7/BJ7-1 | BL8: =BL7/BK7-1 | BM8: =BM7/BL7-1 | BN8: -- | BO8: =BO7/BM7-1 | BP8: =BP7/BO7-1 | BQ8: =BQ7/BP7-1 | BR8: =BR7/BQ7-1 | BS8: -- | BT8: =BT7/BR7-1 | BU8: =BU7/BT7-1 | BV8: =BV7/BU7-1 | BW8: =BW7/BV7-1 | BX8: -- | BY8: =BY7/BW7-1 | BZ8: =BZ7/BY7-1 | CA8: =CA7/BZ7-1 | CB8: =CB7/CA7-1 | CC8: -- | CD8: =CD7/CB7-1 | CE8: =CE7/CD7-1 | CF8: =CF7/CE7-1 | CG8: =CG7/CF7-1 | CH8: -- | CI8: =CI7/CG7-1 | CJ8: =CJ7/CI7-1 | CK8: =CK7/CJ7-1 | CL8: =CL7/CK7-1 | CM8: -- | CN8: =CN7/CL7-1 | CO8: =CO7/CN7-1 | CP8: =CP7/CO7-1 | CQ8: =CQ7/CP7-1 | CR8: -- | CS8: =CS7/CQ7-1 | CT8: =CT7/CS7-1 | CU8: =CU7/CT7-1 | CV8: =CV7/CU7-1 | CW8: -- | CX8: =CX7/CV7-1 | CY8: =CY7/CX7-1 | CZ8: =CZ7/CY7-1 | DA8: =DA7/CZ7-1 | DB8: -- | DC8: =DC7/DA7-1 | DD8: =DD7/DC7-1 | DE8: =DE7/DD7-1 | DF8: =DF7/DE7-1 | DG8: -- | DH8: =DH7/DF7-1 | DI8: =DI7/DH7-1 | DJ8: =DJ7/DI7-1 | DK8: =DK7/DJ7-1 | DL8: -- | DM8: =DM7/DK7-1 | DN8: =DN7/DM7-1 | DO8: =DO7/DN7-1 | DP8: =DP7/DO7-1 | DQ8: -- | DR8: =DR7/DP7-1 | DS8: =DS7/DR7-1 | DT8: =DT7/DS7-1 | DU8: =DU7/DT7-1 | DV8: -- | DW8: =DW7/DU7-1 | DX8: =DX7/DW7-1 | DY8: =DY7/DX7-1 | DZ8: =DZ7/DY7-1 | EA8: -- | EB8: =EB7/DZ7-1 | EC8: =EC7/EB7-1 | ED8: =ED7/EC7-1 | EE8: =EE7/ED7-1 | EF8: -- | EG8: =EG7/EE7-1 | EH8: =EH7/EG7-1 | EI8: =EI7/EH7-1 | EJ8: =EJ7/EI7-1 | EK8: -- | EL8: =EL7/EJ7-1 | EM8: =EM7/EL7-1 | EN8: =EN7/EM7-1 | EO8: =EO7/EN7-1 | EP8: -- | EQ8: =EQ7/EO7-1 | ER8: =ER7/EQ7-1 | ES8: =ES7/ER7-1 | ET8: =ET7/ES7-1 | EU8: -- | EV8: =EV7/ET7-1 | EW8: =EW7/EV7-1 | EX8: =EX7/EW7-1 | EY8: =EY7/EX7-1 | EZ8: --
A9: % Growth yoy | G9: =+G7/B7-1 | H9: =+H7/C7-1 | I9: =+I7/D7-1 | J9: =+J7/E7-1 | K9: =K7/F7-1 | L9: =+L7/G7-1 | M9: =+M7/H7-1 | N9: =+N7/I7-1 | O9: =+O7/J7-1 | P9: =P7/K7-1 | Q9: =+Q7/L7-1 | R9: =+R7/M7-1 | S9: =+S7/N7-1 | T9: =+T7/O7-1 | U9: =U7/P7-1 | V9: =+V7/Q7-1 | W9: =+W7/R7-1 | X9: =+X7/S7-1 | Y9: =+Y7/T7-1 | Z9: =Z7/U7-1 | AA9: =+AA7/V7-1 | AB9: =+AB7/W7-1 | AC9: =+AC7/X7-1 | AD9: =+AD7/Y7-1 | AE9: =AE7/Z7-1 | AF9: =+AF7/AA7-1 | AG9: =+AG7/AB7-1 | AH9: =+AH7/AC7-1 | AI9: =+AI7/AD7-1 | AJ9: =AJ7/AE7-1 | AK9: =+AK7/AF7-1 | AL9: =+AL7/AG7-1 | AM9: =+AM7/AH7-1 | AN9: =+AN7/AI7-1 | AO9: =AO7/AJ7-1 | AP9: =+AP7/AK7-1 | AQ9: =+AQ7/AL7-1 | AR9: =+AR7/AM7-1 | AS9: =+AS7/AN7-1 | AT9: =AT7/AO7-1 | AU9: =+AU7/AP7-1 | AV9: =+AV7/AQ7-1 | AW9: =+AW7/AR7-1 | AX9: =+AX7/AS7-1 | AY9: =AY7/AT7-1 | AZ9: =+AZ7/AU7-1 | BA9: =+BA7/AV7-1 | BB9: =+BB7/AW7-1 | BC9: =+BC7/AX7-1 | BD9: =BD7/AY7-1 | BE9: =+BE7/AZ7-1 | BF9: =+BF7/BA7-1 | BG9: =+BG7/BB7-1 | BH9: =+BH7/BC7-1 | BI9: =BI7/BD7-1 | BJ9: =+BJ7/BE7-1 | BK9: =+BK7/BF7-1 | BL9: =+BL7/BG7-1 | BM9: =+BM7/BH7-1 | BN9: =BN7/BI7-1 | BO9: =+BO7/BJ7-1 | BP9: =+BP7/BK7-1 | BQ9: =+BQ7/BL7-1 | BR9: =+BR7/BM7-1 | BS9: =BS7/BN7-1 | BT9: =+BT7/BO7-1 | BU9: =+BU7/BP7-1 | BV9: =+BV7/BQ7-1 | BW9: =+BW7/BR7-1 | BX9: =BX7/BS7-1 | BY9: =+BY7/BT7-1 | BZ9: =+BZ7/BU7-1 | CA9: =+CA7/BV7-1 | CB9: =+CB7/BW7-1 | CC9: =CC7/BX7-1 | CD9: =+CD7/BY7-1 | CE9: =+CE7/BZ7-1 | CF9: =+CF7/CA7-1 | CG9: =+CG7/CB7-1 | CH9: =CH7/CC7-1 | CI9: =+CI7/CD7-1 | CJ9: =+CJ7/CE7-1 | CK9: =+CK7/CF7-1 | CL9: =+CL7/CG7-1 | CM9: =CM7/CH7-1 | CN9: =+CN7/CI7-1 | CO9: =+CO7/CJ7-1 | CP9: =+CP7/CK7-1 | CQ9: =+CQ7/CL7-1 | CR9: =CR7/CM7-1 | CS9: =+CS7/CN7-1 | CT9: =+CT7/CO7-1 | CU9: =+CU7/CP7-1 | CV9: =+CV7/CQ7-1 | CW9: =CW7/CR7-1 | CX9: =+CX7/CS7-1 | CY9: =+CY7/CT7-1 | CZ9: =+CZ7/CU7-1 | DA9: =+DA7/CV7-1 | DB9: =DB7/CW7-1 | DC9: =+DC7/CX7-1 | DD9: =+DD7/CY7-1 | DE9: =+DE7/CZ7-1 | DF9: =+DF7/DA7-1 | DG9: =DG7/DB7-1 | DH9: =+DH7/DC7-1 | DI9: =+DI7/DD7-1 | DJ9: =+DJ7/DE7-1 | DK9: =+DK7/DF7-1 | DL9: =DL7/DG7-1 | DM9: =+DM7/DH7-1 | DN9: =+DN7/DI7-1 | DO9: =+DO7/DJ7-1 | DP9: =+DP7/DK7-1 | DQ9: =DQ7/DL7-1 | DR9: =+DR7/DM7-1 | DS9: =+DS7/DN7-1 | DT9: =+DT7/DO7-1 | DU9: =+DU7/DP7-1 | DV9: =DV7/DQ7-1 | DW9: =+DW7/DR7-1 | DX9: =+DX7/DS7-1 | DY9: =+DY7/DT7-1 | DZ9: =+DZ7/DU7-1 | EA9: =EA7/DV7-1 | EB9: =+EB7/DW7-1 | EC9: =+EC7/DX7-1 | ED9: =+ED7/DY7-1 | EE9: =+EE7/DZ7-1 | EF9: =EF7/EA7-1 | EG9: =+EG7/EB7-1 | EH9: =+EH7/EC7-1 | EI9: =+EI7/ED7-1 | EJ9: =+EJ7/EE7-1 | EK9: =EK7/EF7-1 | EL9: =+EL7/EG7-1 | EM9: =+EM7/EH7-1 | EN9: =+EN7/EI7-1 | EO9: =+EO7/EJ7-1 | EP9: =EP7/EK7-1 | EQ9: =+EQ7/EL7-1 | ER9: =+ER7/EM7-1 | ES9: =+ES7/EN7-1 | ET9: =+ET7/EO7-1 | EU9: =EU7/EP7-1 | EV9: =+EV7/EQ7-1 | EW9: =+EW7/ER7-1 | EX9: =+EX7/ES7-1 | EY9: =+EY7/ET7-1 | EZ9: =EZ7/EU7-1
A10: COGS (ex. D&A) | B10: 0.208 | C10: 0.15 | D10: 4.548 | E10: 16.338 | F10: =SUM(B10:E10) | G10: 20.13 | H10: 11.967 | I10: 32.507 | J10: 41.136 | K10: =SUM(G10:J10) | L10: =45.946-L11 | M10: =49.225-M11 | N10: =56.747-N11 | O10: =80.744-O11 | P10: =SUM(L10:O10) | Q10: =96.964-Q11 | R10: =105.334-R11 | S10: =123.775-S11 | T10: =136.312-T11 | U10: =SUM(Q10:T10) | V10: =146.712-V11 | W10: =157.636-W11 | X10: =231.508-X11 | Y10: =314.377-Y11 | Z10: =SUM(V10:Y10) | AA10: =375.74-AA11 | AB10: =327.983-AB11-21 | AC10: =322.106-AC11 | AD10: =301.442-AD11 | AE10: =SUM(AA10:AD10) | AF10: =278.415-AF11 | AG10: =329.8-AG11 | AH10: =351.938-AH11 | AI10: =333.914-AI11 | AJ10: =SUM(AF10:AI10) | AK10: =323.069-AK11 | AL10: =315.968-AL11 | AM10: =348.849-AM11 | AN10: =372.661-AN11 | AO10: =SUM(AK10:AN10) | AP10: =373.693-AP11 | AQ10: =357.278-AQ11 | AR10: =355.247-AR11 | AS10: =378.674-AS11 | AT10: =SUM(AP10:AS10) | AU10: =393.134-AU11 | AV10: =395.391-AV11 | AW10: =486.63-AW11-16 | AX10: =493.167-AX11 | AY10: =SUM(AU10:AX10) | AZ10: =464.142-AZ11 | BA10: =511.261-BA11 | BB10: =600.044-BB11 | BC10: =653.133-BC11 | BD10: =SUM(AZ10:BC10) | BE10: =638.545-BE11 | BF10: =742.759-195.954-BF11 | BG10: 529.812 | BH10: =339.474-BH11 | BI10: =SUM(BE10:BH10) | BJ10: =463.123-BJ11 | BK10: =619.797-119.993-BK11 | BL10: =511.423+24.115-BL11 | BM10: =543.767-BM11 | BN10: =SUM(BJ10:BM10) | BO10: =545.436-BO11 | BP10: =676.916-181.193-BP11 | BQ10: =451.85-BQ11 | BR10: =460.017-BR11 | BS10: =SUM(BO10:BR10) | BT10: =477.536-BT11 | BU10: =491.233-BU11 | BV10: =509.463-BV11 | BW10: =463.181-7.3-BW11 | BX10: =SUM(BT10:BW10) | BY10: =461.513-BY11 | BZ10: =503.551-BZ11 | CA10: =567.452-CA11 | CB10: =521.3-CB11 | CC10: =SUM(BY10:CB10) | CD10: =436.171-CD11 | CE10: =431.7-2.29-CE11 | CF10: =469.552-CF11 | CG10: =524.976-1.45+7.782-CG11 | CH10: =SUM(CD10:CG10) | CI10: =498.585-CI11 | CJ10: =483.85-CJ11 | CK10: =548.684-CK11 | CL10: =550.911-CL11 | CM10: =SUM(CI10:CL10) | CN10: =498-CN11 | CO10: =519-CO11-15 | CP10: =571-CP11 | CQ10: =610-CQ11-5 | CR10: =SUM(CN10:CQ10) | CS10: =554-CS11-10 | CT10: =602-CT11 | CU10: =821-CU11 | CV10: =870-CV11 | CW10: =SUM(CS10:CV10) | CX10: =787-CX11 | CY10: =928-CY11 | CZ10: =1067-CZ11 | DA10: =1110-1-DA11 | DB10: =SUM(CX10:DA10) | DC10: =1139-DC11 | DD10: =1148-DD11 | DE10: =1260-14-DE11 | DF10: =998-21-DF11 | DG10: =SUM(DC10:DF10) | DH10: =924-10-DH11 | DI10: =1038-2-DI11 | DJ10: =1098-DJ11 | DK10: =1090-3-DK11 | DL10: =SUM(DH10:DK10) | DM10: =1076-1-DM11 | DN10: =1591-245-17-DN11 | DO10: =1766-86-21-DO11 | DP10: =1846-DP11-92-1 | DQ10: =SUM(DM10:DP10) | DR10: =2032-87-5-DR11 | DS10: =2292-86-4-DS11 | DT10: =2472-86-DT11 | DU10: =2644-DU11-86 | DV10: =SUM(DR10:DU10) | DW10: =2857-94-DW11 | DX10: =3789-121-DX11 | DY10: =2754-120-DY11 | DZ10: =2218-120-DZ11-16 | EA10: =SUM(DW10:DZ10) | EB10: =2544-119-EB11-8 | EC10: =4045-119-EC11-2 | ED10: =4720-119-ED11-26 | EE10: =5312-119-EE11-4 | EF10: =SUM(EB10:EE10) | EG10: =5638-119-EG11+1 | EH10: =7466-118-EH11+3 | EI10: =8926-116-EI11 | EJ10: =10608-118-EJ11 | EK10: =SUM(EG10:EJ10) | EL10: =17394-123-3-EL11 | EM10: =12890-49-EM11 | EN10: =EN7-EN13-EN11 | EO10: =EO7-EO13-EO11 | EP10: =SUM(EL10:EO10) | EQ10: =EQ7-EQ13-EQ11 | ER10: =ER7-ER13-ER11 | ES10: =ES7-ES13-ES11 | ET10: =ET7-ET13-ET11 | EU10: =SUM(EQ10:ET10) | EV10: =EV7-EV13-EV11 | EW10: =EW7-EW13-EW11 | EX10: =EX7-EX13-EX11 | EY10: =EY7-EY13-EY11 | EZ10: =SUM(EV10:EY10)
A11: D&A | B11: 0 | C11: 0 | D11: 0 | E11: 0 | F11: =SUM(B11:E11) | G11: 0.743 | H11: 0.994 | I11: 1.059 | J11: 1.21 | K11: =SUM(G11:J11) | L11: 1.458 | M11: 2.182 | N11: 2.503 | O11: 2.863 | P11: =SUM(L11:O11) | Q11: =3.048 | R11: =3.311 | S11: =4.362 | T11: =15.724-SUM(Q11:S11) | U11: =SUM(Q11:T11) | V11: 6.195 | W11: 10.62 | X11: 11.917 | Y11: 14.759 | Z11: =SUM(V11:Y11) | AA11: 12.83 | AB11: =26.899-AA11 | AC11: 16.166 | AD11: 15.151 | AE11: =SUM(AA11:AD11) | AF11: 15.958 | AG11: =35.568-AF11 | AH11: =58.41-+AG11-AF11 | AI11: =82.016-SUM(AF11:AH11) | AJ11: =SUM(AF11:AI11) | AK11: 23.412 | AL11: =47.486-AK11 | AM11: =71.512-+AL11-AK11 | AN11: =102.597-SUM(AK11:AM11) | AO11: =SUM(AK11:AN11) | AP11: 24.893 | AQ11: =49.667-AP11 | AR11: =74.189-SUM(AP11:AQ11) | AS11: =97.977-SUM(AP11:AR11) | AT11: =SUM(AP11:AS11) | AU11: =AU116 | AV11: =AV116 | AW11: =AW116 | AX11: =AX116 | AY11: =SUM(AU11:AX11) | AZ11: =AZ116 | BA11: =BA116 | BB11: =BB116 | BC11: =BC116 | BD11: =SUM(AZ11:BC11) | BE11: =BE116 | BF11: 46 | BG11: 49.3 | BH11: =BH116 | BI11: =SUM(BE11:BH11) | BJ11: 48.1 | BK11: 49 | BL11: 48 | BM11: 48 | BN11: =SUM(BJ11:BM11) | BO11: 47.147 | BP11: 46.573 | BQ11: 46.876 | BR11: =BR116 | BS11: =SUM(BO11:BR11) | BT11: 47.764 | BU11: =99.923-BT11 | BV11: 52.4 | BW11: 51.882 | BX11: =SUM(BT11:BW11) | BY11: 54.491 | BZ11: =110.686-BY11 | CA11: =167.834-BZ11-BY11 | CB11: 58.5 | CC11: =SUM(BY11:CB11) | CD11: 59.744 | CE11: =121.584-CD11 | CF11: =184.31-CE11-CD11 | CG11: =239.148-CF11-CE11-CD11 | CH11: =SUM(CD11:CG11) | CI11: 55.083 | CJ11: =110.69-CI11 | CK11: 55 | CL11: 55 | CM11: =SUM(CI11:CL11) | CN11: 54 | CO11: 54 | CP11: 48 | CQ11: 46 | CR11: =SUM(CN11:CQ11) | CS11: 45 | CT11: 47 | CU11: 48 | CV11: 47 | CW11: =SUM(CS11:CV11) | CX11: 47 | CY11: 49 | CZ11: 50 | DA11: 53 | DB11: =SUM(CX11:DA11) | DC11: 57 | DD11: 59 | DE11: 68 | DF11: 78 | DG11: =SUM(DC11:DF11) | DH11: 91 | DI11: 92 | DJ11: 92 | DK11: 106 | DL11: =SUM(DH11:DK11) | DM11: 107 | DN11: =404-185 | DO11: 299 | DP11: 287 | DQ11: =SUM(DM11:DP11) | DR11: 281 | DS11: =286 | DT11: 298 | DU11: 309 | DV11: =SUM(DR11:DU11) | DW11: 334 | DX11: 378 | DY11: 406 | DZ11: 426 | EA11: =SUM(DW11:DZ11) | EB11: 384 | EC11: 365 | ED11: 372 | EE11: 387 | EF11: =SUM(EB11:EE11) | EG11: 410 | EH11: 433 | EI11: 478 | EJ11: 543 | EK11: =SUM(EG11:EJ11) | EL11: 611 | EM11: 668 | EN11: =Worksheet!CV11 | EO11: =Worksheet!CW11 | EP11: =SUM(EL11:EO11) | EQ11: =Worksheet!CX11 | ER11: =Worksheet!CY11 | ES11: =Worksheet!CZ11 | ET11: =Worksheet!DA11 | EU11: =SUM(EQ11:ET11) | EV11: =Worksheet!DB11 | EW11: =Worksheet!DC11 | EX11: =Worksheet!DD11 | EY11: =Worksheet!DE11 | EZ11: =SUM(EV11:EY11)
A13: Gross Profit | B13: =B7-B10-B11 | C13: =C7-C10-C11 | D13: =D7-D10-D11 | E13: =E7-E10-E11 | F13: =SUM(B13:E13) | G13: =G7-G10-G11 | H13: =H7-H10-H11 | I13: =I7-I10-I11 | J13: =J7-J10-J11 | K13: =SUM(G13:J13) | L13: =L7-L10-L11 | M13: =M7-M10-M11 | N13: =N7-N10-N11 | O13: =O7-O10-O11 | P13: =SUM(L13:O13) | Q13: =Q7-Q10-Q11 | R13: =R7-R10-R11 | S13: =S7-S10-S11 | T13: =T7-T10-T11 | U13: =SUM(Q13:T13) | V13: =V7-V10-V11 | W13: =W7-W10-W11 | X13: =X7-X10-X11 | Y13: =Y7-Y10-Y11 | Z13: =SUM(V13:Y13) | AA13: =AA7-AA10-AA11 | AB13: =AB7-AB10-AB11 | AC13: =AC7-AC10-AC11 | AD13: =AD7-AD10-AD11 | AE13: =SUM(AA13:AD13) | AF13: =AF7-AF10-AF11 | AG13: =AG7-AG10-AG11 | AH13: =AH7-AH10-AH11 | AI13: =AI7-AI10-AI11 | AJ13: =SUM(AF13:AI13) | AK13: =AK7-AK10-AK11 | AL13: =AL7-AL10-AL11 | AM13: =AM7-AM10-AM11 | AN13: =AN7-AN10-AN11 | AO13: =SUM(AK13:AN13) | AP13: =AP7-AP10-AP11 | AQ13: =AQ7-AQ10-AQ11 | AR13: =AR7-AR10-AR11 | AS13: =AS7-AS10-AS11 | AT13: =SUM(AP13:AS13) | AU13: =AU7-AU10-AU11 | AV13: =AV7-AV10-AV11 | AW13: =AW7-AW10-AW11 | AX13: =AX7-AX10-AX11 | AY13: =SUM(AU13:AX13) | AZ13: =AZ7-AZ10-AZ11 | BA13: =BA7-BA10-BA11 | BB13: =BB7-BB10-BB11 | BC13: =BC7-BC10-BC11 | BD13: =SUM(AZ13:BC13) | BE13: =BE7-BE10-BE11 | BF13: =BF7-BF10-BF11 | BG13: =BG7-BG10-BG11 | BH13: =BH7-BH10-BH11 | BI13: =SUM(BE13:BH13) | BJ13: =BJ7-BJ10-BJ11 | BK13: =BK7-BK10-BK11 | BL13: =BL7-BL10-BL11 | BM13: =BM7-BM10-BM11 | BN13: =SUM(BJ13:BM13) | BO13: =BO7-BO10-BO11 | BP13: =BP7-BP10-BP11 | BQ13: =BQ7-BQ10-BQ11 | BR13: =BR7-BR10-BR11 | BS13: =SUM(BO13:BR13) | BT13: =BT7-BT10-BT11 | BU13: =BU7-BU10-BU11 | BV13: =BV7-BV10-BV11 | BW13: =BW7-BW10-BW11 | BX13: =SUM(BT13:BW13) | BY13: =BY7-BY10-BY11 | BZ13: =BZ7-BZ10-BZ11 | CA13: =CA7-CA10-CA11 | CB13: =CB7-CB10-CB11 | CC13: =SUM(BY13:CB13) | CD13: =CD7-CD10-CD11 | CE13: =CE7-CE10-CE11 | CF13: =CF7-CF10-CF11 | CG13: =CG7-CG10-CG11 | CH13: =SUM(CD13:CG13) | CI13: =CI7-CI10-CI11 | CJ13: =CJ7-CJ10-CJ11 | CK13: =CK7-CK10-CK11 | CL13: =CL7-CL10-CL11 | CM13: =SUM(CI13:CL13) | CN13: =CN7-CN10-CN11 | CO13: =CO7-CO10-CO11 | CP13: =CP7-CP10-CP11 | CQ13: =CQ7-CQ10-CQ11 | CR13: =SUM(CN13:CQ13) | CS13: =CS7-CS10-CS11 | CT13: =CT7-CT10-CT11 | CU13: =CU7-CU10-CU11 | CV13: =CV7-CV10-CV11 | CW13: =SUM(CS13:CV13) | CX13: =CX7-CX10-CX11 | CY13: =CY7-CY10-CY11 | CZ13: =CZ7-CZ10-CZ11 | DA13: =DA7-DA10-DA11 | DB13: =SUM(CX13:DA13) | DC13: =DC7-DC10-DC11 | DD13: =DD7-DD10-DD11 | DE13: =DE7-DE10-DE11 | DF13: =DF7-DF10-DF11 | DG13: =SUM(DC13:DF13) | DH13: =DH7-DH10-DH11 | DI13: =DI7-DI10-DI11 | DJ13: =DJ7-DJ10-DJ11 | DK13: =DK7-DK10-DK11 | DL13: =SUM(DH13:DK13) | DM13: =DM7-DM10-DM11 | DN13: =DN7-DN10-DN11 | DO13: =DO7-DO10-DO11 | DP13: =DP7-DP10-DP11 | DQ13: =SUM(DM13:DP13) | DR13: =DR7-DR10-DR11 | DS13: =DS7-DS10-DS11 | DT13: =DT7-DT10-DT11 | DU13: =DU7-DU10-DU11 | DV13: =SUM(DR13:DU13) | DW13: =DW7-DW10-DW11 | DX13: =DX7-DX10-DX11 | DY13: =DY7-DY10-DY11 | DZ13: =DZ7-DZ10-DZ11 | EA13: =SUM(DW13:DZ13) | EB13: =EB7-EB10-EB11 | EC13: =EC7-EC10-EC11 | ED13: =ED7-ED10-ED11 | EE13: =EE7-EE10-EE11 | EF13: =SUM(EB13:EE13) | EG13: =EG7-EG10-EG11 | EH13: =EH7-EH10-EH11 | EI13: =EI7-EI10-EI11 | EJ13: =EJ7-EJ10-EJ11 | EK13: =SUM(EG13:EJ13) | EL13: =EL7-EL10-EL11 | EM13: =EM7-EM10-EM11 | EN13: =Worksheet!CV15 | EO13: =Worksheet!CW15 | EP13: =SUM(EL13:EO13) | EQ13: =Worksheet!CX15 | ER13: =Worksheet!CY15 | ES13: =Worksheet!CZ15 | ET13: =Worksheet!DA15 | EU13: =SUM(EQ13:ET13) | EV13: =Worksheet!DB15 | EW13: =Worksheet!DC15 | EX13: =Worksheet!DD15 | EY13: =Worksheet!DE15 | EZ13: =SUM(EV13:EY13)
A14: Gross Margin | B14: =B13/B7 | C14: =C13/C7 | D14: =D13/D7 | E14: =E13/E7 | F14: =F13/F7 | G14: =G13/G7 | H14: =H13/H7 | I14: =I13/I7 | ... EZ14: =EZ13/EZ7
A15: Gross Margin Leverage | C15: =(C13-B13)/(C7-B7) | D15: =(D13-C13)/(D7-C7) | E15: =(E13-D13)/(E7-D7) | G15: =(G13-E13)/(G7-E7) | H15: =(H13-G13)/(H7-G7) | I15: =(I13-H13)/(I7-H7) | J15: =(J13-I13)/(J7-I7) | K15: =(K13-F13)/(K7-F7) | L15: =(L13-J13)/(L7-J7) | M15: =(M13-L13)/(M7-L7) | N15: =(N13-M13)/(N7-M7) | O15: =(O13-N13)/(O7-N7) | P15: =(P13-K13)/(P7-K7) | Q15: =(Q13-O13)/(Q7-O7) | R15: =(R13-Q13)/(R7-Q7) | S15: =(S13-R13)/(S7-R7) | T15: =(T13-S13)/(T7-S7) | U15: =(U13-P13)/(U7-P7) | V15: =(V13-T13)/(V7-T7) | W15: =(W13-V13)/(W7-V7) | X15: =(X13-W13)/(X7-W7) | Y15: =(Y13-X13)/(Y7-X7) | Z15: =(Z13-U13)/(Z7-U7) | AA15: =(AA13-Y13)/(AA7-Y7) | AB15: =(AB13-AA13)/(AB7-AA7) | AC15: =(AC13-AB13)/(AC7-AB7) | AD15: =(AD13-AC13)/(AD7-AC7) | AE15: =(AE13-Z13)/(AE7-Z7) | AF15: =(AF13-AD13)/(AF7-AD7) | AG15: =(AG13-AF13)/(AG7-AF7) | AH15: =(AH13-AG13)/(AH7-AG7) | AI15: =(AI13-AH13)/(AI7-AH7) | AJ15: =(AJ13-AE13)/(AJ7-AE7) | AK15: =(AK13-AI13)/(AK7-AI7) | AL15: =(AL13-AK13)/(AL7-AK7) | AM15: =(AM13-AL13)/(AM7-AL7) | AN15: =(AN13-AM13)/(AN7-AM7) | AO15: =(AO13-AJ13)/(AO7-AJ7) | AP15: =(AP13-AN13)/(AP7-AN7) | AQ15: =(AQ13-AP13)/(AQ7-AP7) | AR15: =(AR13-AQ13)/(AR7-AQ7) | AS15: =(AS13-AR13)/(AS7-AR7) | AT15: =(AT13-AO13)/(AT7-AO7) | AU15: =(AU13-AS13)/(AU7-AS7) | AV15: =(AV13-AU13)/(AV7-AU7) | AW15: =(AW13-AV13)/(AW7-AV7) | AX15: =(AX13-AW13)/(AX7-AW7) | AY15: =(AY13-AT13)/(AY7-AT7) | AZ15: =(AZ13-AX13)/(AZ7-AX7) | BA15: =(BA13-AZ13)/(BA7-AZ7) | BB15: =(BB13-BA13)/(BB7-BA7) | BC15: =(BC13-BB13)/(BC7-BB7) | BD15: =(BD13-AY13)/(BD7-AY7) | BE15: =(BE13-BC13)/(BE7-BC7) | BF15: =(BF13-BE13)/(BF7-BE7) | BG15: =(BG13-BF13)/(BG7-BF7) | BH15: =(BH13-BG13)/(BH7-BG7) | BI15: =(BI13-BD13)/(BI7-BD7) | BJ15: =(BJ13-BH13)/(BJ7-BH7) | BK15: =(BK13-BJ13)/(BK7-BJ7) | BL15: =(BL13-BK13)/(BL7-BK7) | BM15: =(BM13-BL13)/(BM7-BL7) | BN15: =(BN13-BI13)/(BN7-BI7) | BO15: =(BO13-BM13)/(BO7-BM7) | BP15: =(BP13-BO13)/(BP7-BO7) | BQ15: =(BQ13-BP13)/(BQ7-BP7) | BR15: =(BR13-BQ13)/(BR7-BQ7) | BS15: =(BS13-BN13)/(BS7-BN7) | BT15: =(BT13-BR13)/(BT7-BR7) | BU15: =(BU13-BT13)/(BU7-BT7) | BV15: =(BV13-BU13)/(BV7-BU7) | BW15: =(BW13-BV13)/(BW7-BV7) | BX15: =(BX13-BS13)/(BX7-BS7) | BY15: =(BY13-BW13)/(BY7-BW7) | BZ15: =(BZ13-BY13)/(BZ7-BY7) | CA15: =(CA13-BZ13)/(CA7-BZ7) | CB15: =(CB13-CA13)/(CB7-CA7) | CC15: =(CC13-BX13)/(CC7-BX7) | CD15: =(CD13-CB13)/(CD7-CB7) | CE15: =(CE13-CD13)/(CE7-CD7) | CF15: =(CF13-CE13)/(CF7-CE7) | CG15: =(CG13-CF13)/(CG7-CF7) | CH15: =(CH13-CC13)/(CH7-CC7) | CI15: =(CI13-CG13)/(CI7-CG7) | CJ15: =(CJ13-CI13)/(CJ7-CI7) | CK15: =(CK13-CJ13)/(CK7-CJ7) | CL15: =(CL13-CK13)/(CL7-CK7) | CM15: =(CM13-CH13)/(CM7-CH7) | CN15: =(CN13-CL13)/(CN7-CL7) | CO15: =(CO13-CN13)/(CO7-CN7) | CP15: =(CP13-CO13)/(CP7-CO7) | CQ15: =(CQ13-CP13)/(CQ7-CP7) | CR15: =(CR13-CM13)/(CR7-CM7) | CS15: =(CS13-CQ13)/(CS7-CQ7) | CT15: =(CT13-CS13)/(CT7-CS7) | CU15: =(CU13-CT13)/(CU7-CT7) | CV15: =(CV13-CU13)/(CV7-CU7) | CW15: =(CW13-CR13)/(CW7-CR7) | CX15: =(CX13-CV13)/(CX7-CV7) | CY15: =(CY13-CX13)/(CY7-CX7) | CZ15: =(CZ13-CY13)/(CZ7-CY7) | DA15: =(DA13-CZ13)/(DA7-CZ7) | DB15: =(DB13-CW13)/(DB7-CW7) | DC15: =(DC13-DA13)/(DC7-DA7) | DD15: =(DD13-DC13)/(DD7-DC7) | DE15: =(DE13-DD13)/(DE7-DD7) | DF15: =(DF13-DE13)/(DF7-DE7) | DG15: =(DG13-DB13)/(DG7-DB7) | DH15: =(DH13-DF13)/(DH7-DF7) | DI15: =(DI13-DH13)/(DI7-DH7) | DJ15: =(DJ13-DI13)/(DJ7-DI7) | DK15: =(DK13-DJ13)/(DK7-DJ7) | DL15: =(DL13-DG13)/(DL7-DG7) | DM15: =(DM13-DK13)/(DM7-DK7) | DN15: =(DN13-DM13)/(DN7-DM7) | DO15: =(DO13-DN13)/(DO7-DN7) | DP15: =(DP13-DO13)/(DP7-DO7) | DQ15: =(DQ13-DL13)/(DQ7-DL7) | DR15: =(DR13-DP13)/(DR7-DP7) | DS15: =(DS13-DR13)/(DS7-DR7) | DT15: =(DT13-DS13)/(DT7-DS7) | DU15: =(DU13-DT13)/(DU7-DT7) | DV15: =(DV13-DQ13)/(DV7-DQ7) | DW15: =(DW13-DU13)/(DW7-DU7) | DX15: =(DX13-DW13)/(DX7-DW7) | DY15: =(DY13-DX13)/(DY7-DX7) | DZ15: =(DZ13-DY13)/(DZ7-DY7) | EA15: =(EA13-DV13)/(EA7-DV7) | EB15: =(EB13-EA13)/(EB7-EA7) | EC15: =(EC13-EB13)/(EC7-EB7) | ED15: =(ED13-EC13)/(ED7-EC7) | EE15: =(EE13-ED13)/(EE7-ED7) | EF15: =(EF13-EA13)/(EF7-EA7) | EG15: =(EG13-EF13)/(EG7-EF7) | EH15: =(EH13-EG13)/(EH7-EG7) | EI15: =(EI13-EH13)/(EI7-EH7) | EJ15: =(EJ13-EI13)/(EJ7-EI7) | EK15: =(EK13-EF13)/(EK7-EF7) | EL15: =(EL13-EK13)/(EL7-EK7) | EM15: =(EM13-EL13)/(EM7-EL7) | EN15: =(EN13-EM13)/(EN7-EM7) | EO15: =(EO13-EN13)/(EO7-EN7) | EP15: =(EP13-EK13)/(EP7-EK7) | EQ15: =(EQ13-EO13)/(EQ7-EO7) | ER15: =(ER13-EQ13)/(ER7-EQ7) | ES15: =(ES13-ER13)/(ES7-ER7) | ET15: =(ET13-ES13)/(ET7-ES7) | EU15: =(EU13-EP13)/(EU7-EP7) | EV15: =(EV13-ET13)/(EV7-ET7) | EW15: =(EW13-EV13)/(EW7-EV7) | EX15: =(EX13-EW13)/(EX7-EW7) | EY15: =(EY13-EX13)/(EY7-EX7) | EZ15: =(EZ13-EU13)/(EZ7-EU7)
A17: SG&A | B17: 0.385 | C17: 0.569 | D17: 1.07 | E17: 2.159 | F17: =SUM(B17:E17) | G17: 3.885 | H17: 3.962 | I17: 4.697 | J17: 6.358 | K17: =SUM(G17:J17) | L17: 7.284 | M17: 8.116 | N17: 9.293 | O17: 12.386 | P17: =SUM(L17:O17) | Q17: 12.114 | R17: 14.603 | S17: 14.852 | T17: 16.861 | U17: =SUM(Q17:T17) | V17: 19.122 | W17: 20.278 | X17: 24.897 | Y17: 32.888 | Z17: =SUM(V17:Y17) | AA17: 37.482 | AB17: 35.908 | AC17: 38.693 | AD17: 39.402 | AE17: =SUM(AA17:AD17) | AF17: 40.91 | AG17: 39.722 | AH17: 42.218 | AI17: 42.399 | AJ17: =SUM(AF17:AI17) | AK17: 47.206 | AL17: 50.874 | AM17: 50.104 | AN17: 52.605 | AO17: =SUM(AK17:AN17) | AP17: 48.058 | AQ17: 51.683 | AR17: 54.537 | AS17: 50.163 | AT17: =SUM(AP17:AS17) | AU17: 63.962 | AV17: 69.055 | AW17: =75.597-1.5 | AX17: 84.916 | AY17: =SUM(AU17:AX17) | AZ17: 80.571 | BA17: 81.28 | BB17: 88.183 | BC17: 91.263 | BD17: =SUM(AZ17:BC17) | BE17: 93.034 | BF17: 92.399 | BG17: =90.349-4.5 | BH17: 86.44 | BI17: =SUM(BE17:BH17) | BJ17: 80.491 | BK17: =73.975+0.939 | BL17: 85.99 | BM17: 88.188 | BN17: =SUM(BJ17:BM17) | BO17: 90.879 | BP17: =98.864-12.705 | BQ17: 83.752 | BR17: 88.018 | BS17: =SUM(BO17:BR17) | BT17: 98.117 | BU17: =103.533-7.562 | BV17: =103.129-6.413 | BW17: =100.834-5.052 | BX17: =SUM(BT17:BW17) | BY17: =106.636-4.342-5.171 | BZ17: =119.903-4.065-4.794-20.127 | CA17: =100.261-4.402-4.666 | CB17: =104.022-4.325-4.373 | CC17: =SUM(BY17:CB17) | CD17: =108.626-3.915-4.946 | CE17: =108.266-3.98-4.984 | CF17: =103.133-4.906+0.329-2.235 | CG17: =115.677-9.25-1.845 | CH17: =SUM(CD17:CG17) | CI17: =118.58-9.441 | CJ17: =118.671-9.173 | CK17: =123.298-9.572 | CL17: =120.214-9.169/2 | CM17: =SUM(CI17:CL17) | CN17: =138-4.5 | CO17: =149+89-4-89 | CP17: =152+8-4-8 | CQ17: =161+34-34-4 | CR17: =SUM(CN17:CQ17) | CS17: =159+1-6-4-3-1 | CT17: =157+2-2-1-4 | CU17: =171-4 | CV17: =176-4 | CW17: =SUM(CS17:CV17) | CX17: =185-4-2 | CY17: =198-4 | CZ17: =212-3 | DA17: =220-2 | DB17: =SUM(CX17:DA17) | DC17: =231-2-2 | DD17: =237-2 | DE17: =258-1-1+4 | DF17: =266-7-1 | DG17: =SUM(DC17:DF17) | DH17: =264-10-1 | DI17: =266-5 | DJ17: =277-7 | DK17: =287-7 | DL17: =SUM(DH17:DK17) | DM17: =293-4 | DN17: =627-229 | DO17: =515-106+1 | DP17: =503-72 | DQ17: =SUM(DM17:DP17) | DR17: =520-80 | DS17: =526-72 | DT17: =557-70 | DU17: =563-70 | DV17: =SUM(DR17:DU17) | DW17: =592+1353-55-7-1353 | DX17: =592-54-2 | DY17: =631-54-16 | DZ17: =625-54-38 | EA17: =SUM(DW17:DZ17) | EB17: =633-54+4 | EC17: =622-18+5 | ED17: =689-16 | EE17: =711-18 | EF17: =SUM(EB17:EE17) | EG17: =777-21 | EH17: =842-26 | EI17: =897-39 | EJ17: =975-43 | EK17: =SUM(EG17:EJ17) | EL17: =1041-37 | EM17: =1122-37-15 | EN17: =Worksheet!CV35 | EO17: =Worksheet!CW35 | EP17: =SUM(EL17:EO17) | EQ17: =Worksheet!CX35 | ER17: =Worksheet!CY35 | ES17: =Worksheet!CZ35 | ET17: =Worksheet!DA35 | EU17: =SUM(EQ17:ET17) | EV17: =Worksheet!DB35 | EW17: =Worksheet!DC35 | EX17: =Worksheet!DD35 | EY17: =Worksheet!DE35 | EZ17: =SUM(EV17:EY17)
A18: % of sales | B18: =B17/B7 | C18: =C17/C7 | D18: =D17/D7 | E18: =E17/E7 | F18: =F17/F$7 | G18: =G17/G7 | H18: =H17/H7 | I18: =I17/I7 | J18: =J17/J7 | K18: =K17/K$7 | L18: =L17/L7 | M18: =M17/M7 | N18: =N17/N7 | O18: =O17/O7 | P18: =P17/P$7 | Q18: =Q17/Q7 | R18: =R17/R7 | S18: =S17/S7 | T18: =T17/T7 | U18: =U17/U$7 | V18: =V17/V7 | W18: =W17/W7 | X18: =X17/X7 | Y18: =Y17/Y7 | Z18: =Z17/Z$7 | AA18: =AA17/AA7 | AB18: =AB17/AB7 | AC18: =AC17/AC7 | AD18: =AD17/AD7 | AE18: =AE17/AE$7 | AF18: =AF17/AF7 | AG18: =AG17/AG7 | AH18: =AH17/AH7 | AI18: =AI17/AI7 | AJ18: =AJ17/AJ$7 | AK18: =AK17/AK7 | AL18: =AL17/AL7 | AM18: =AM17/AM7 | AN18: =AN17/AN7 | AO18: =AO17/AO$7 | AP18: =AP17/AP7 | AQ18: =AQ17/AQ7 | AR18: =AR17/AR7 | AS18: =AS17/AS7 | AT18: =AT17/AT$7 | AU18: =AU17/AU7 | AV18: =AV17/AV7 | AW18: =AW17/AW7 | AX18: =AX17/AX7 | AY18: =AY17/AY$7 | AZ18: =AZ17/AZ7 | BA18: =BA17/BA7 | BB18: =BB17/BB7 | BC18: =BC17/BC7 | BD18: =BD17/BD$7 | BE18: =BE17/BE7 | BF18: =BF17/BF7 | BG18: =BG17/BG7 | BH18: =BH17/BH7 | BI18: =BI17/BI$7 | BJ18: =BJ17/BJ7 | BK18: =BK17/BK7 | BL18: =BL17/BL7 | BM18: =BM17/BM7 | BN18: =BN17/BN$7 | BO18: =BO17/BO7 | BP18: =BP17/BP7 | BQ18: =BQ17/BQ7 | BR18: =BR17/BR7 | BS18: =BS17/BS$7 | BT18: =BT17/BT7 | BU18: =BU17/BU7 | BV18: =BV17/BV7 | BW18: =BW17/BW7 | BX18: =BX17/BX$7 | BY18: =BY17/BY7 | BZ18: =BZ17/BZ7 | CA18: =CA17/CA7 | CB18: =CB17/CB7 | CC18: =CC17/CC$7 | CD18: =CD17/CD7 | CE18: =CE17/CE7 | CF18: =CF17/CF7 | CG18: =CG17/CG7 | CH18: =CH17/CH$7 | CI18: =CI17/CI7 | CJ18: =CJ17/CJ7 | CK18: =CK17/CK7 | CL18: =CL17/CL7 | CM18: =CM17/CM$7 | CN18: =CN17/CN7 | CO18: =CO17/CO7 | CP18: =CP17/CP7 | CQ18: =CQ17/CQ7 | CR18: =CR17/CR$7 | CS18: =CS17/CS7 | CT18: =CT17/CT7 | CU18: =CU17/CU7 | CV18: =CV17/CV7 | CW18: =CW17/CW$7 | CX18: =CX17/CX7 | CY18: =CY17/CY7 | CZ18: =CZ17/CZ7 | DA18: =DA17/DA7 | DB18: =DB17/DB$7 | DC18: =DC17/DC7 | DD18: =DD17/DD7 | DE18: =DE17/DE7 | DF18: =DF17/DF7 | DG18: =DG17/DG$7 | DH18: =DH17/DH7 | DI18: =DI17/DI7 | DJ18: =DJ17/DJ7 | DK18: =DK17/DK7 | DL18: =DL17/DL$7 | DM18: =DM17/DM7 | DN18: =DN17/DN7 | DO18: =DO17/DO7 | DP18: =DP17/DP7 | DQ18: =DQ17/DQ$7 | DR18: =DR17/DR7 | DS18: =DS17/DS7 | DT18: =DT17/DT7 | DU18: =DU17/DU7 | DV18: =DV17/DV$7 | DW18: =DW17/DW7 | DX18: =DX17/DX7 | DY18: =DY17/DY7 | DZ18: =DZ17/DZ7 | EA18: =EA17/EA$7 | EB18: =EB17/EB7 | EC18: =EC17/EC7 | ED18: =ED17/ED7 | EE18: =EE17/EE7 | EF18: =EF17/EF$7 | EG18: =EG17/EG7 | EH18: =EH17/EH7 | EI18: =EI17/EI7 | EJ18: =EJ17/EJ7 | EK18: =EK17/EK$7 | EL18: =EL17/EL7 | EM18: =EM17/EM7 | EN18: =EN17/EN7 | EO18: =EO17/EO7 | EP18: =EP17/EP$7 | EQ18: =EQ17/EQ7 | ER18: =ER17/ER7 | ES18: =ES17/ES7 | ET18: =ET17/ET7 | EU18: =EU17/EU$7 | EV18: =EV17/EV7 | EW18: =EW17/EW7 | EX18: =EX17/EX7 | EY18: =EY17/EY7 | EZ18: =EZ17/EZ$7
A19: R&D | B19: 0.616 | C19: 0.512 | D19: 2.39 | E19: 3.585 | F19: =SUM(B19:E19) | G19: 4.642 | H19: 5.724 | I19: 6.29 | J19: 8.417 | K19: =SUM(G19:J19) | L19: 8.785 | M19: 10.813 | N19: 12.42 | O19: 15.421 | P19: =SUM(L19:O19) | Q19: 17.83 | R19: 20.141 | S19: 22.023 | T19: 26.442 | U19: =SUM(Q19:T19) | V19: 32.593 | W19: 33.894 | X19: 44.308 | Y19: 43.125 | Z19: =SUM(V19:Y19) | AA19: 52.492 | AB19: 57.229 | AC19: 57.779 | AD19: 57.373 | AE19: =SUM(AA19:AD19) | AF19: 59.31 | AG19: 65.62 | AH19: 73.052 | AI19: 71.99 | AJ19: =SUM(AF19:AI19) | AK19: 77.75 | AL19: 85.42 | AM19: 87.88 | AN19: 84.054 | AO19: =SUM(AK19:AN19) | AP19: 85.913 | AQ19: 85.814 | AR19: 87.937 | AS19: 92.435 | AT19: =SUM(AP19:AS19) | AU19: 123.202 | AV19: 127.257 | AW19: 140.732 | AX19: =162.276-13.4 | AY19: =SUM(AU19:AX19) | AZ19: 158.321 | BA19: 157.952 | BB19: 179.529 | BC19: =195.835-4 | BD19: =SUM(AZ19:BC19) | BE19: 218.83 | BF19: 212.91 | BG19: 212.36 | BH19: 211.779 | BI19: =SUM(BE19:BH19) | BJ19: 211.341 | BK19: 192.855 | BL19: 197.948 | BM19: 216.251 | BN19: =SUM(BJ19:BM19) | BO19: 218.105 | BP19: 210.635 | BQ19: 204.527 | BR19: 215.563 | BS19: =SUM(BO19:BR19) | BT19: 231.524 | BU19: 247.721 | BV19: 256.498 | BW19: 266.862 | BX19: =SUM(BT19:BW19) | BY19: 283.902 | BZ19: 281.193 | CA19: 284.18 | CB19: =298.007 | CC19: =SUM(BY19:CB19) | CD19: =327.161 | CE19: 331.738 | CF19: 340.294 | CG19: =336.641 | CH19: =SUM(CD19:CG19) | CI19: 334.263 | CJ19: 337.124 | CK19: 340.085 | CL19: =348.253-9.169/2 | CM19: =SUM(CI19:CL19) | CN19: =339-4.5 | CO19: =320 | CP19: =329 | CQ19: =344 | CR19: =SUM(CN19:CQ19) | CS19: =346 | CT19: 350 | CU19: =373 | CV19: =394 | CW19: =SUM(CS19:CV19) | CX19: =411 | CY19: 416 | CZ19: 462 | DA19: 508 | DB19: =SUM(CX19:DA19) | DC19: 542 | DD19: 581 | DE19: 605 | DF19: 647 | DG19: =SUM(DC19:DF19) | DH19: 674 | DI19: 704 | DJ19: 712 | DK19: 738 | DL19: =SUM(DH19:DK19) | DM19: 735 | DN19: 997 | DO19: 1047 | DP19: =1147 | DQ19: =SUM(DM19:DP19) | DR19: 1153 | DS19: =1245 | DT19: 1403 | DU19: =1466 | DV19: =SUM(DR19:DU19) | DW19: 1618 | DX19: 1824 | DY19: 1945 | DZ19: 1951 | EA19: =SUM(DW19:DZ19) | EB19: 1875 | EC19: 2040 | ED19: 2294 | EE19: 2465 | EF19: =SUM(EB19:EE19) | EG19: 2720 | EH19: 3090 | EI19: 3390 | EJ19: 3714 | EK19: =SUM(EG19:EJ19) | EL19: 3989 | EM19: 4291 | EN19: =Worksheet!CV30 | EO19: =Worksheet!CW30 | EP19: =SUM(EL19:EO19) | EQ19: =Worksheet!CX30 | ER19: =Worksheet!CY30 | ES19: =Worksheet!CZ30 | ET19: =Worksheet!DA30 | EU19: =SUM(EQ19:ET19) | EV19: =Worksheet!DB30 | EW19: =Worksheet!DC30 | EX19: =Worksheet!DD30 | EY19: =Worksheet!DE30 | EZ19: =SUM(EV19:EY19)
A20: % of sales | B20: =B19/B7 | C20: =C19/C7 | D20: =D19/D7 | E20: =E19/E7 | F20: =F19/F$7 | G20: =G19/G7 | H20: =H19/H7 | I20: =I19/I7 | J20: =J19/J7 | K20: =K19/K$7 | L20: =L19/L7 | M20: =M19/M7 | N20: =N19/N7 | O20: =O19/O7 | P20: =P19/P$7 | Q20: =Q19/Q7 | R20: =R19/R7 | S20: =S19/S7 | T20: =T19/T7 | U20: =U19/U$7 | V20: =V19/V7 | W20: =W19/W7 | X20: =X19/X7 | Y20: =Y19/Y7 | Z20: =Z19/Z$7 | AA20: =AA19/AA7 | AB20: =AB19/AB7 | AC20: =AC19/AC7 | AD20: =AD19/AD7 | AE20: =AE19/AE$7 | AF20: =AF19/AF7 | AG20: =AG19/AG7 | AH20: =AH19/AH7 | AI20: =AI19/AI7 | AJ20: =AJ19/AJ$7 | AK20: =AK19/AK7 | AL20: =AL19/AL7 | AM20: =AM19/AM7 | AN20: =AN19/AN7 | AO20: =AO19/AO$7 | AP20: =AP19/AP7 | AQ20: =AQ19/AQ7 | AR20: =AR19/AR7 | AS20: =AS19/AS7 | AT20: =AT19/AT$7 | AU20: =AU19/AU7 | AV20: =AV19/AV7 | AW20: =AW19/AW7 | AX20: =AX19/AX7 | AY20: =AY19/AY$7 | AZ20: =AZ19/AZ7 | BA20: =BA19/BA7 | BB20: =BB19/BB7 | BC20: =BC19/BC7 | BD20: =BD19/BD$7 | BE20: =BE19/BE7 | BF20: =BF19/BF7 | BG20: =BG19/BG7 | BH20: =BH19/BH7 | BI20: =BI19/BI$7 | BJ20: =BJ19/BJ7 | BK20: =BK19/BK7 | BL20: =BL19/BL7 | BM20: =BM19/BM7 | BN20: =BN19/BN$7 | BO20: =BO19/BO7 | BP20: =BP19/BP7 | BQ20: =BQ19/BQ7 | BR20: =BR19/BR7 | BS20: =BS19/BS$7 | BT20: =BT19/BT7 | BU20: =BU19/BU7 | BV20: =BV19/BV7 | BW20: =BW19/BW7 | BX20: =BX19/BX$7 | BY20: =BY19/BY7 | BZ20: =BZ19/BZ7 | CA20: =CA19/CA7 | CB20: =CB19/CB7 | CC20: =CC19/CC$7 | CD20: =CD19/CD7 | CE20: =CE19/CE7 | CF20: =CF19/CF7 | CG20: =CG19/CG7 | CH20: =CH19/CH$7 | CI20: =CI19/CI7 | CJ20: =CJ19/CJ7 | CK20: =CK19/CK7 | CL20: =CL19/CL7 | CM20: =CM19/CM$7 | CN20: =CN19/CN7 | CO20: =CO19/CO7 | CP20: =CP19/CP7 | CQ20: =CQ19/CQ7 | CR20: =CR19/CR$7 | CS20: =CS19/CS7 | CT20: =CT19/CT7 | CU20: =CU19/CU7 | CV20: =CV19/CV7 | CW20: =CW19/CW$7 | CX20: =CX19/CX7 | CY20: =CY19/CY7 | CZ20: =CZ19/CZ7 | DA20: =DA19/DA7 | DB20: =DB19/DB$7 | DC20: =DC19/DC7 | DD20: =DD19/DD7 | DE20: =DE19/DE7 | DF20: =DF19/DF7 | DG20: =DG19/DG$7 | DH20: =DH19/DH7 | DI20: =DI19/DI7 | DJ20: =DJ19/DJ7 | DK20: =DK19/DK7 | DL20: =DL19/DL$7 | DM20: =DM19/DM7 | DN20: =DN19/DN7 | DO20: =DO19/DO7 | DP20: =DP19/DP7 | DQ20: =DQ19/DQ$7 | DR20: =DR19/DR7 | DS20: =DS19/DS7 | DT20: =DT19/DT7 | DU20: =DU19/DU7 | DV20: =DV19/DV$7 | DW20: =DW19/DW7 | DX20: =DX19/DX7 | DY20: =DY19/DY7 | DZ20: =DZ19/DZ7 | EA20: =EA19/EA$7 | EB20: =EB19/EB7 | EC20: =EC19/EC7 | ED20: =ED19/ED7 | EE20: =EE19/EE7 | EF20: =EF19/EF$7 | EG20: =EG19/EG7 | EH20: =EH19/EH7 | EI20: =EI19/EI7 | EJ20: =EJ19/EJ7 | EK20: =EK19/EK$7 | EL20: =EL19/EL7 | EM20: =EM19/EM7 | EN20: =EN19/EN7 | EO20: =EO19/EO7 | EP20: =EP19/EP$7 | EQ20: =EQ19/EQ7 | ER20: =ER19/ER7 | ES20: =ES19/ES7 | ET20: =ET19/ET7 | EU20: =EU19/EU$7 | EV20: =EV19/EV7 | EW20: =EW19/EW7 | EX20: =EX19/EX7 | EY20: =EY19/EY7 | EZ20: =EZ19/EZ$7
A22: Operating Income | B22: =B13-B17-B19 | C22: =C13-C17-C19 | D22: =D13-D17-D19 | E22: =E13-E17-E19 | F22: =SUM(B22:E22) | G22: =G13-G17-G19 | H22: =H13-H17-H19 | I22: =I13-I17-I19 | J22: =J13-J17-J19 | K22: =SUM(G22:J22) | L22: =L13-L17-L19 | M22: =M13-M17-M19 | N22: =N13-N17-N19 | O22: =O13-O17-O19 | P22: =SUM(L22:O22) | Q22: =Q13-Q17-Q19 | R22: =R13-R17-R19 | S22: =S13-S17-S19 | T22: =T13-T17-T19 | U22: =SUM(Q22:T22) | V22: =V13-V17-V19 | W22: =W13-W17-W19 | X22: =X13-X17-X19 | Y22: =Y13-Y17-Y19 | Z22: =SUM(V22:Y22) | AA22: =AA13-AA17-AA19 | AB22: =AB13-AB17-AB19 | AC22: =AC13-AC17-AC19 | AD22: =AD13-AD17-AD19 | AE22: =SUM(AA22:AD22) | AF22: =AF13-AF17-AF19 | AG22: =AG13-AG17-AG19 | AH22: =AH13-AH17-AH19 | AI22: =AI13-AI17-AI19 | AJ22: =SUM(AF22:AI22) | AK22: =AK13-AK17-AK19 | AL22: =AL13-AL17-AL19 | AM22: =AM13-AM17-AM19 | AN22: =AN13-AN17-AN19 | AO22: =SUM(AK22:AN22) | AP22: =AP13-AP17-AP19 | AQ22: =AQ13-AQ17-AQ19 | AR22: =AR13-AR17-AR19 | AS22: =AS13-AS17-AS19 | AT22: =SUM(AP22:AS22) | AU22: =AU13-AU17-AU19 | AV22: =AV13-AV17-AV19 | AW22: =AW13-AW17-AW19 | AX22: =AX13-AX17-AX19 | AY22: =SUM(AU22:AX22) | AZ22: =AZ13-AZ17-AZ19 | BA22: =BA13-BA17-BA19 | BB22: =BB13-BB17-BB19 | BC22: =BC13-BC17-BC19 | BD22: =SUM(AZ22:BC22) | BE22: =BE13-BE17-BE19 | BF22: =BF13-BF17-BF19 | BG22: =BG13-BG17-BG19 | BH22: =BH13-BH17-BH19 | BI22: =SUM(BE22:BH22) | BJ22: =BJ13-BJ17-BJ19 | BK22: =BK13-BK17-BK19 | BL22: =BL13-BL17-BL19 | BM22: =BM13-BM17-BM19 | BN22: =SUM(BJ22:BM22) | BO22: =BO13-BO17-BO19 | BP22: =BP13-BP17-BP19 | BQ22: =BQ13-BQ17-BQ19 | BR22: =BR13-BR17-BR19 | BS22: =SUM(BO22:BR22) | BT22: =BT13-BT17-BT19 | BU22: =BU13-BU17-BU19 | BV22: =BV13-BV17-BV19 | BW22: =BW13-BW17-BW19 | BX22: =SUM(BT22:BW22) | BY22: =BY13-BY17-BY19 | BZ22: =BZ13-BZ17-BZ19 | CA22: =CA13-CA17-CA19 | CB22: =CB13-CB17-CB19 | CC22: =SUM(BY22:CB22) | CD22: =CD13-CD17-CD19 | CE22: =CE13-CE17-CE19 | CF22: =CF13-CF17-CF19 | CG22: =CG13-CG17-CG19 | CH22: =SUM(CD22:CG22) | CI22: =CI13-CI17-CI19 | CJ22: =CJ13-CJ17-CJ19 | CK22: =CK13-CK17-CK19 | CL22: =CL13-CL17-CL19 | CM22: =SUM(CI22:CL22) | CN22: =CN13-CN17-CN19 | CO22: =CO13-CO17-CO19 | CP22: =CP13-CP17-CP19 | CQ22: =CQ13-CQ17-CQ19 | CR22: =SUM(CN22:CQ22) | CS22: =CS13-CS17-CS19 | CT22: =CT13-CT17-CT19 | CU22: =CU13-CU17-CU19 | CV22: =CV13-CV17-CV19 | CW22: =SUM(CS22:CV22) | CX22: =CX13-CX17-CX19 | CY22: =CY13-CY17-CY19 | CZ22: =CZ13-CZ17-CZ19 | DA22: =DA13-DA17-DA19 | DB22: =SUM(CX22:DA22) | DC22: =DC13-DC17-DC19 | DD22: =DD13-DD17-DD19 | DE22: =DE13-DE17-DE19 | DF22: =DF13-DF17-DF19 | DG22: =SUM(DC22:DF22) | DH22: =DH13-DH17-DH19 | DI22: =DI13-DI17-DI19 | DJ22: =DJ13-DJ17-DJ19 | DK22: =DK13-DK17-DK19 | DL22: =SUM(DH22:DK22) | DM22: =DM13-DM17-DM19 | DN22: =DN13-DN17-DN19 | DO22: =DO13-DO17-DO19 | DP22: =DP13-DP17-DP19 | DQ22: =SUM(DM22:DP22) | DR22: =DR13-DR17-DR19 | DS22: =DS13-DS17-DS19 | DT22: =DT13-DT17-DT19 | DU22: =DU13-DU17-DU19 | DV22: =SUM(DR22:DU22) | DW22: =DW13-DW17-DW19 | DX22: =DX13-DX17-DX19 | DY22: =DY13-DY17-DY19 | DZ22: =DZ13-DZ17-DZ19 | EA22: =SUM(DW22:DZ22) | EB22: =EB13-EB17-EB19 | EC22: =EC13-EC17-EC19 | ED22: =ED13-ED17-ED19 | EE22: =EE13-EE17-EE19 | EF22: =SUM(EB22:EE22) | EG22: =EG13-EG17-EG19 | EH22: =EH13-EH17-EH19 | EI22: =EI13-EI17-EI19 | EJ22: =EJ13-EJ17-EJ19 | EK22: =SUM(EG22:EJ22) | EL22: =EL13-EL17-EL19 | EM22: =EM13-EM17-EM19 | EN22: =EN13-EN17-EN19 | EO22: =EO13-EO17-EO19 | EP22: =SUM(EL22:EO22) | EQ22: =EQ13-EQ17-EQ19 | ER22: =ER13-ER17-ER19 | ES22: =ES13-ES17-ES19 | ET22: =ET13-ET17-ET19 | EU22: =SUM(EQ22:ET22) | EV22: =EV13-EV17-EV19 | EW22: =EW13-EW17-EW19 | EX22: =EX13-EX17-EX19 | EY22: =EY13-EY17-EY19 | EZ22: =SUM(EV22:EY22)
A23: Operating Margin | B23: NA | C23: NA | D23: =D22/D7 | E23: =E22/E7 | F23: =F22/F$7 | G23: =G22/G7 | H23: =H22/H7 | I23: =I22/I7 | J23: =J22/J7 | K23: =K22/K$7 | L23: =L22/L7 | M23: =M22/M7 | N23: =N22/N7 | O23: =O22/O7 | P23: =P22/P$7 | Q23: =Q22/Q7 | R23: =R22/R7 | S23: =S22/S7 | T23: =T22/T7 | U23: =U22/U$7 | V23: =V22/V7 | W23: =W22/W7 | X23: =X22/X7 | Y23: =Y22/Y7 | Z23: =Z22/Z$7 | AA23: =AA22/AA7 | AB23: =AB22/AB7 | AC23: =AC22/AC7 | AD23: =AD22/AD7 | AE23: =AE22/AE$7 | AF23: =AF22/AF7 | AG23: =AG22/AG7 | AH23: =AH22/AH7 | AI23: =AI22/AI7 | AJ23: =AJ22/AJ$7 | AK23: =AK22/AK7 | AL23: =AL22/AL7 | AM23: =AM22/AM7 | AN23: =AN22/AN7 | AO23: =AO22/AO$7 | AP23: =AP22/AP7 | AQ23: =AQ22/AQ7 | AR23: =AR22/AR7 | AS23: =AS22/AS7 | AT23: =AT22/AT$7 | AU23: =AU22/AU7 | AV23: =AV22/AV7 | AW23: =AW22/AW7 | AX23: =AX22/AX7 | AY23: =AY22/AY$7 | AZ23: =AZ22/AZ7 | BA23: =BA22/BA7 | BB23: =BB22/BB7 | BC23: =BC22/BC7 | BD23: =BD22/BD$7 | BE23: =BE22/BE7 | BF23: =BF22/BF7 | BG23: =BG22/BG7 | BH23: =BH22/BH7 | BI23: =BI22/BI$7 | BJ23: =BJ22/BJ7 | BK23: =BK22/BK7 | BL23: =BL22/BL7 | BM23: =BM22/BM7 | BN23: =BN22/BN$7 | BO23: =BO22/BO7 | BP23: =BP22/BP7 | BQ23: =BQ22/BQ7 | BR23: =BR22/BR7 | BS23: =BS22/BS$7 | BT23: =BT22/BT7 | BU23: =BU22/BU7 | BV23: =BV22/BV7 | BW23: =BW22/BW7 | BX23: =BX22/BX$7 | BY23: =BY22/BY7 | BZ23: =BZ22/BZ7 | CA23: =CA22/CA7 | CB23: =CB22/CB7 | CC23: =CC22/CC$7 | CD23: =CD22/CD7 | CE23: =CE22/CE7 | CF23: =CF22/CF7 | CG23: =CG22/CG7 | CH23: =CH22/CH$7 | CI23: =CI22/CI7 | CJ23: =CJ22/CJ7 | CK23: =CK22/CK7 | CL23: =CL22/CL7 | CM23: =CM22/CM$7 | CN23: =CN22/CN7 | CO23: =CO22/CO7 | CP23: =CP22/CP7 | CQ23: =CQ22/CQ7 | CR23: =CR22/CR$7 | CS23: =CS22/CS7 | CT23: =CT22/CT7 | CU23: =CU22/CU7 | CV23: =CV22/CV7 | CW23: =CW22/CW$7 | CX23: =CX22/CX7 | CY23: =CY22/CY7 | CZ23: =CZ22/CZ7 | DA23: =DA22/DA7 | DB23: =DB22/DB$7 | DC23: =DC22/DC7 | DD23: =DD22/DD7 | DE23: =DE22/DE7 | DF23: =DF22/DF7 | DG23: =DG22/DG$7 | DH23: =DH22/DH7 | DI23: =DI22/DI7 | DJ23: =DJ22/DJ7 | DK23: =DK22/DK7 | DL23: =DL22/DL$7 | DM23: =DM22/DM7 | DN23: =DN22/DN7 | DO23: =DO22/DO7 | DP23: =DP22/DP7 | DQ23: =DQ22/DQ$7 | DR23: =DR22/DR7 | DS23: =DS22/DS7 | DT23: =DT22/DT7 | DU23: =DU22/DU7 | DV23: =DV22/DV$7 | DW23: =DW22/DW7 | DX23: =DX22/DX7 | DY23: =DY22/DY7 | DZ23: =DZ22/DZ7 | EA23: =EA22/EA$7 | EB23: =EB22/EB7 | EC23: =EC22/EC7 | ED23: =ED22/ED7 | EE23: =EE22/EE7 | EF23: =EF22/EF$7 | EG23: =EG22/EG7 | EH23: =EH22/EH7 | EI23: =EI22/EI7 | EJ23: =EJ22/EJ7 | EK23: =EK22/EK$7 | EL23: =EL22/EL7 | EM23: =EM22/EM7 | EN23: =EN22/EN7 | EO23: =EO22/EO7 | EP23: =EP22/EP$7 | EQ23: =EQ22/EQ7 | ER23: =ER22/ER7 | ES23: =ES22/ES7 | ET23: =ET22/ET7 | EU23: =EU22/EU$7 | EV23: =EV22/EV7 | EW23: =EW22/EW7 | EX23: =EX22/EX7 | EY23: =EY22/EY7 | EZ23: =EZ22/EZ$7
A24: Operating Margin Leverage | C24: =(C22-B22)/(C7-B7) | D24: =(D22-C22)/(D7-C7) | E24: =(E22-D22)/(E7-D7) | G24: =(G22-E22)/(G7-E7) | H24: =(H22-G22)/(H7-G7) | I24: =(I22-H22)/(I7-H7) | J24: =(J22-I22)/(J7-I7) | K24: =(K22-F22)/(K7-F7) | L24: =(L22-J22)/(L7-J7) | M24: =(M22-L22)/(M7-L7) | N24: =(N22-M22)/(N7-M7) | O24: =(O22-N22)/(O7-N7) | P24: =(P22-K22)/(P7-K7) | Q24: =(Q22-O22)/(Q7-O7) | R24: =(R22-Q22)/(R7-Q7) | S24: =(S22-R22)/(S7-R7) | T24: =(T22-S22)/(T7-S7) | U24: =(U22-P22)/(U7-P7) | V24: =(V22-T22)/(V7-T7) | W24: =(W22-V22)/(W7-V7) | X24: =(X22-W22)/(X7-W7) | Y24: =(Y22-X22)/(Y7-X7) | Z24: =(Z22-U22)/(Z7-U7) | AA24: =(AA22-Y22)/(AA7-Y7) | AB24: =(AB22-AA22)/(AB7-AA7) | AC24: =(AC22-AB22)/(AC7-AB7) | AD24: =(AD22-AC22)/(AD7-AC7) | AE24: =(AE22-Z22)/(AE7-Z7) | AF24: =(AF22-AD22)/(AF7-AD7) | AG24: =(AG22-AF22)/(AG7-AF7) | AH24: =(AH22-AG22)/(AH7-AG7) | AI24: =(AI22-AH22)/(AI7-AH7) | AJ24: =(AJ22-AE22)/(AJ7-AE7) | AK24: =(AK22-AI22)/(AK7-AI7) | AL24: =(AL22-AK22)/(AL7-AK7) | AM24: =(AM22-AL22)/(AM7-AL7) | AN24: =(AN22-AM22)/(AN7-AM7) | AO24: =(AO22-AJ22)/(AO7-AJ7) | AP24: =(AP22-AN22)/(AP7-AN7) | AQ24: =(AQ22-AP22)/(AQ7-AP7) | AR24: =(AR22-AQ22)/(AR7-AQ7) | AS24: =(AS22-AR22)/(AS7-AR7) | AT24: =(AT22-AO22)/(AT7-AO7) | AU24: =(AU22-AS22)/(AU7-AS7) | AV24: =(AV22-AU22)/(AV7-AU7) | AW24: =(AW22-AV22)/(AW7-AV7) | AX24: =(AX22-AW22)/(AX7-AW7) | AY24: =(AY22-AT22)/(AY7-AT7) | AZ24: =(AZ22-AX22)/(AZ7-AX7) | BA24: =(BA22-AZ22)/(BA7-AZ7) | BB24: =(BB22-BA22)/(BB7-BA7) | BC24: =(BC22-BB22)/(BC7-BB7) | BD24: =(BD22-AY22)/(BD7-AY7) | BE24: =(BE22-BC22)/(BE7-BC7) | BF24: =(BF22-BE22)/(BF7-BE7) | BG24: =(BG22-BF22)/(BG7-BF7) | BH24: =(BH22-BG22)/(BH7-BG7) | BI24: =(BI22-BD22)/(BI7-BD7) | BJ24: =(BJ22-BH22)/(BJ7-BH7) | BK24: =(BK22-BJ22)/(BK7-BJ7) | BL24: =(BL22-BK22)/(BL7-BK7) | BM24: =(BM22-BL22)/(BM7-BL7) | BN24: =(BN22-BI22)/(BN7-BI7) | BO24: =(BO22-BM22)/(BO7-BM7) | BP24: =(BP22-BO22)/(BP7-BO7) | BQ24: =(BQ22-BP22)/(BQ7-BP7) | BR24: =(BR22-BQ22)/(BR7-BQ7) | BS24: =(BS22-BN22)/(BS7-BN7) | BT24: =(BT22-BR22)/(BT7-BR7) | BU24: =(BU22-BT22)/(BU7-BT7) | BV24: =(BV22-BU22)/(BV7-BU7) | BW24: =(BW22-BV22)/(BW7-BV7) | BX24: =(BX22-BS22)/(BX7-BS7) | BY24: =(BY22-BW22)/(BY7-BW7) | BZ24: =(BZ22-BY22)/(BZ7-BY7) | CA24: =(CA22-BZ22)/(CA7-BZ7) | CB24: =(CB22-CA22)/(CB7-CA7) | CC24: =(CC22-BX22)/(CC7-BX7) | CD24: =(CD22-CB22)/(CD7-CB7) | CE24: =(CE22-CD22)/(CE7-CD7) | CF24: =(CF22-CE22)/(CF7-CE7) | CG24: =(CG22-CF22)/(CG7-CF7) | CH24: =(CH22-CC22)/(CH7-CC7) | CI24: =(CI22-CG22)/(CI7-CG7) | CJ24: =(CJ22-CI22)/(CJ7-CI7) | CK24: =(CK22-CJ22)/(CK7-CJ7) | CL24: =(CL22-CK22)/(CL7-CK7) | CM24: =(CM22-CH22)/(CM7-CH7) | CN24: =(CN22-CL22)/(CN7-CL7) | CO24: =(CO22-CN22)/(CO7-CN7) | CP24: =(CP22-CO22)/(CP7-CO7) | CQ24: =(CQ22-CP22)/(CQ7-CP7) | CR24: =(CR22-CM22)/(CR7-CM7) | CS24: =(CS22-CQ22)/(CS7-CQ7) | CT24: =(CT22-CS22)/(CT7-CS7) | CU24: =(CU22-CT22)/(CU7-CT7) | CV24: =(CV22-CU22)/(CV7-CU7) | CW24: =(CW22-CR22)/(CW7-CR7) | CX24: =(CX22-CV22)/(CX7-CV7) | CY24: =(CY22-CX22)/(CY7-CX7) | CZ24: =(CZ22-CY22)/(CZ7-CY7) | DA24: =(DA22-CZ22)/(DA7-CZ7) | DB24: =(DB22-CW22)/(DB7-CW7) | DC24: =(DC22-DA22)/(DC7-DA7) | DD24: =(DD22-DC22)/(DD7-DC7) | DE24: =(DE22-DD22)/(DE7-DD7) | DF24: =(DF22-DE22)/(DF7-DE7) | DG24: =(DG22-DB22)/(DG7-DB7) | DH24: =(DH22-DF22)/(DH7-DF7) | DI24: =(DI22-DH22)/(DI7-DH7) | DJ24: =(DJ22-DI22)/(DJ7-DI7) | DK24: =(DK22-DJ22)/(DK7-DJ7) | DL24: =(DL22-DG22)/(DL7-DG7) | DM24: =(DM22-DK22)/(DM7-DK7) | DN24: =(DN22-DM22)/(DN7-DM7) | DO24: =(DO22-DN22)/(DO7-DN7) | DP24: =(DP22-DO22)/(DP7-DO7) | DQ24: =(DQ22-DL22)/(DQ7-DL7) | DR24: =(DR22-DP22)/(DR7-DP7) | DS24: =(DS22-DR22)/(DS7-DR7) | DT24: =(DT22-DS22)/(DT7-DS7) | DU24: =(DU22-DT22)/(DU7-DT7) | DV24: =(DV22-DQ22)/(DV7-DQ7) | DW24: =(DW22-DU22)/(DW7-DU7) | DX24: =(DX22-DW22)/(DX7-DW7) | DY24: =(DY22-DX22)/(DY7-DX7) | DZ24: =(DZ22-DY22)/(DZ7-DY7) | EA24: =(EA22-DV22)/(EA7-DV7) | EB24: =(EB22-EA22)/(EB7-EA7) | EC24: =(EC22-EB22)/(EC7-EB7) | ED24: =(ED22-EC22)/(ED7-EC7) | EE24: =(EE22-ED22)/(EE7-ED7) | EF24: =(EF22-EA22)/(EF7-EA7) | EG24: =(EG22-EF22)/(EG7-EF7) | EH24: =(EH22-EG22)/(EH7-EG7) | EI24: =(EI22-EH22)/(EI7-EH7) | EJ24: =(EJ22-EI22)/(EJ7-EI7) | EK24: =(EK22-EF22)/(EK7-EF7) | EL24: =(EL22-EK22)/(EL7-EK7) | EM24: =(EM22-EL22)/(EM7-EL7) | EN24: =(EN22-EM22)/(EN7-EM7) | EO24: =(EO22-EN22)/(EO7-EN7) | EP24: =(EP22-EK22)/(EP7-EK7) | EQ24: =(EQ22-EO22)/(EQ7-EO7) | ER24: =(ER22-EQ22)/(ER7-EQ7) | ES24: =(ES22-ER22)/(ES7-ER7) | ET24: =(ET22-ES22)/(ET7-ES7) | EU24: =(EU22-EP22)/(EU7-EP7) | EV24: =(EV22-ET22)/(EV7-ET7) | EW24: =(EW22-EV22)/(EW7-EV7) | EX24: =(EX22-EW22)/(EX7-EW7) | EY24: =(EY22-EX22)/(EY7-EX7) | EZ24: =(EZ22-EU22)/(EZ7-EU7)
A26: Interest Expense | B26: 0 | C26: 0 | D26: 0 | E26: 0 | F26: =SUM(B26:E26) | G26: 0 | H26: 0 | I26: 0 | J26: 0 | K26: =SUM(G26:J26) | L26: 0 | M26: 0 | N26: 0 | O26: 0 | P26: =SUM(L26:O26) | Q26: 0 | R26: 0 | S26: 1.2895 | T26: =(0.0475/4)*300 | U26: =SUM(Q26:T26) | V26: =(0.0475/4)*300 | W26: =(0.0475/4)*300 | X26: =(0.0475/4)*300 | Y26: 5.4855 | Z26: =SUM(V26:Y26) | AA26: =(0.0475/4)*300 | AB26: =(0.0475/4)*300 | AC26: =(0.0475/4)*300 | AD26: =+AD28-AD27 | AE26: =SUM(AA26:AD26) | AF26: =(0.0475/4)*300 | AG26: =(0.0475/4)*300 | AH26: 0 | AI26: 0 | AJ26: =SUM(AF26:AI26) | AK26: 0 | AL26: 0 | AM26: 0 | AN26: 0 | AO26: =SUM(AK26:AN26) | AP26: 0.01 | AQ26: 0 | AR26: 0 | AS26: 0 | AT26: =SUM(AP26:AS26) | AU26: 0.001 | AV26: 0 | AW26: 0 | AX26: 0 | AY26: =SUM(AU26:AX26) | AZ26: 0 | BA26: 0 | BB26: 0 | BC26: 0 | BD26: =SUM(AZ26:BC26) | BE26: 0 | BF26: 0 | BG26: 0 | BH26: 0 | BI26: =SUM(BE26:BH26) | BJ26: 0 | BK26: 0 | BL26: 0 | BM26: 0 | BN26: =SUM(BJ26:BM26) | BO26: 0 | BP26: 0 | BQ26: 0 | BR26: 0 | BS26: =SUM(BO26:BR26) | BT26: 0 | BU26: 0 | BV26: 0 | BW26: 0 | BX26: =SUM(BT26:BW26) | BY26: 0 | BZ26: 0 | CA26: 0 | CB26: 0 | CC26: =SUM(BY26:CB26) | CD26: 0 | CE26: 0 | CF26: 0 | CG26: 0 | CH26: =SUM(CD26:CG26) | CI26: 0 | CJ26: 11.526 | CK26: 11.542 | CL26: =-7.083+11.594 | CM26: =SUM(CI26:CL26) | CN26: =12-7 | CO26: =13-7 | CP26: =12-7 | CQ26: =12-2-7 | CR26: =SUM(CN26:CQ26) | CS26: =12-7 | CT26: =12-7 | CU26: =16-6 | CV26: =18-4 | CW26: =SUM(CS26:CV26) | CX26: =16-2 | CY26: =15-1 | CZ26: 15 | DA26: =15+2 | DB26: =SUM(CX26:DA26) | DC26: =15-1 | DD26: 14 | DE26: 15 | DF26: 14 | DG26: =SUM(DC26:DF26) | DH26: 13 | DI26: 13 | DJ26: 13 | DK26: 12 | DL26: =SUM(DH26:DK26) | DM26: =25+1-1 | DN26: =54-2-1 | DO26: 53 | DP26: =53 | DQ26: =SUM(DM26:DP26) | DR26: =53-1 | DS26: =60-1 | DT26: =62-1 | DU26: =61 | DV26: =SUM(DR26:DU26) | DW26: =68-1 | DX26: =65-1 | DY26: =65-1 | DZ26: =65-1 | EA26: =SUM(DW26:DZ26) | EB26: =66-1 | EC26: =65-1 | ED26: =63-1 | EE26: =63-1 | EF26: =SUM(EB26:EE26) | EG26: =64-1 | EH26: =61-1 | EI26: =61-1 | EJ26: =61-1 | EK26: =SUM(EG26:EJ26) | EL26: =63-1 | EM26: =62-1 | EN26: =+EM26 | EO26: =+EN26 | EP26: =SUM(EL26:EO26) | EQ26: =+EO26 | ER26: =+EQ26 | ES26: =+ER26 | ET26: =+ES26 | EU26: =SUM(EQ26:ET26) | EV26: =+ET26 | EW26: =+EV26 | EX26: =+EW26 | EY26: =+EX26 | EZ26: =SUM(EV26:EY26)
A27: Interest (Income) | F27: =SUM(B27:E27) | K27: =SUM(G27:J27) | P27: =SUM(L27:O27) | Q27: =Q28-Q26 | R27: =R28-R26 | S27: =S28-S26 | T27: =T28-T26 | U27: =SUM(Q27:T27) | V27: =V28-V26 | W27: =W28-W26 | X27: =-1.682-X26 | Y27: =Y28-Y26 | Z27: =SUM(V27:Y27) | AA27: =AA28-AA26 | AB27: =AB28-AB26 | AC27: =AC28-AC26 | AD27: -5 | AE27: =SUM(AA27:AD27) | AF27: =AF28-AF26 | AG27: =AG28-AG26 | AH27: =AH28-AH26 | AI27: -2.433 | AJ27: =SUM(AF27:AI27) | AK27: -2.807 | AL27: -2.6 | AM27: -3.591 | AN27: -2.854 | AO27: =SUM(AK27:AN27) | AP27: -4.383 | AQ27: -5.219 | AR27: -6.146 | AS27: -4.386 | AT27: =SUM(AP27:AS27) | AU27: -8.564 | AV27: -8.706 | AW27: -10.714 | AX27: -13.045 | AY27: =SUM(AU27:AX27) | AZ27: -12.543 | BA27: -16.091 | BB27: -18.958 | BC27: -17.403 | BD27: =SUM(AZ27:BC27) | BE27: -10.039 | BF27: -8.792 | BG27: -4.207 | BH27: -4.708 | BI27: =SUM(BE27:BH27) | BJ27: -6.144 | BK27: -3.006 | BL27: -2.362 | BM27: -5.139 | BN27: =SUM(BJ27:BM27) | BO27: -3.332 | BP27: -6.16 | BQ27: 0.198 | BR27: -6.128 | BS27: =SUM(BO27:BR27) | BT27: -1.623 | BU27: -3.517 | BV27: -7.697 | BW27: -2.26 | BX27: =SUM(BT27:BW27) | BY27: -4.269 | BZ27: -5.585 | CA27: -1.411 | CB27: -2.535 | CC27: =SUM(BY27:CB27) | CD27: -5.281 | CE27: -6.286 | CF27: -0.496 | CG27: =-7.935+5.743 | CH27: =SUM(CD27:CG27) | CI27: =11.471-5.71-17.684+16.982-6.901 | CJ27: =-6.829+3.857-2.5-6.973 | CK27: =-7.422-7.01+0.125 | CL27: =-8.129-0.188 | CM27: =SUM(CI27:CL27) | CN27: =-9+1 | CO27: =-9 | CP27: =-9-3 | CQ27: -11 | CR27: =SUM(CN27:CQ27) | CS27: =-12+4 | CT27: -12 | CU27: =-14 | CV27: -17 | CW27: =SUM(CS27:CV27) | CX27: =-16 | CY27: -15 | CZ27: -17 | DA27: =-20-2 | DB27: =SUM(CX27:DA27) | DC27: =-25-6 | DD27: =-32+2 | DE27: =-37+2 | DF27: =-42+1 | DG27: =SUM(DC27:DF27) | DH27: -44 | DI27: =-47 | DJ27: =-45+1 | DK27: =-41+3 | DL27: =SUM(DH27:DK27) | DM27: =-31-3 | DN27: =-13+1 | DO27: =+-7+4-4-1 | DP27: =-6-10+9-1 | DQ27: =SUM(DM27:DP27) | DR27: =-6+134-135 | DS27: =-6-4 | DT27: =-7-22+20 | DU27: =-9+53-53 | DV27: =SUM(DR27:DU27) | DW27: =-18+13-17 | DX27: =-46+5-7 | DY27: =-88+11-11 | DZ27: =-115+18-10 | EA27: =SUM(DW27:DZ27) | EB27: =-150+15-14 | EC27: =-187-59+62 | ED27: =-234-69+66 | EE27: =-294-260+260 | EF27: =SUM(EB27:EE27) | EG27: =-359-75+69 | EH27: =-444-189+193 | EI27: =-472-36+37 | EJ27: =-511-733+727 | EK27: =SUM(EG27:EJ27) | EL27: =-515+180-175 | EM27: =-592-2236+2247 | EN27: =EM27-50 | EO27: =EN27-30 | EP27: =SUM(EL27:EO27) | EQ27: =EO27-15 | ER27: =EQ27-15 | ES27: =ER27-15 | ET27: =ES27-15 | EU27: =SUM(EQ27:ET27) | EV27: =ET27-25 | EW27: =EV27-25 | EX27: =EW27-25 | EY27: =EX27-25 | EZ27: =SUM(EV27:EY27)
A28: Net Interest Expense/(Income) | B28: 0.032 | C28: 0.04 | D28: 0.03 | E28: 0.028 | F28: =SUM(B28:E28) | G28: -0.027 | H28: -0.022 | I28: -0.011 | J28: 0.089 | K28: =SUM(G28:J28) | L28: -0.342 | M28: -0.369 | N28: -0.43 | O28: -0.613 | P28: =SUM(L28:O28) | Q28: =-1.328 | R28: -4.098 | S28: -4.63 | T28: -6.617 | U28: =SUM(Q28:T28) | V28: -5.515 | W28: -2.663 | X28: =X27+X26 | Y28: -1.848 | Z28: =SUM(V28:Y28) | AA28: -1.731 | AB28: -1.34 | AC28: -1.47 | AD28: -2.03 | AE28: =SUM(AA28:AD28) | AF28: -1.862 | AG28: -2.029 | AH28: -3.26 | AI28: =SUM(AI26:AI27) | AJ28: =SUM(AF28:AI28) | AK28: =SUM(AK26:AK27) | AL28: =SUM(AL26:AL27) | AM28: =SUM(AM26:AM27) | AN28: =SUM(AN26:AN27) | AO28: =SUM(AK28:AN28) | AP28: =SUM(AP26:AP27) | AQ28: =SUM(AQ26:AQ27) | AR28: =SUM(AR26:AR27) | AS28: =SUM(AS26:AS27) | AT28: =SUM(AP28:AS28) | AU28: =SUM(AU26:AU27) | AV28: =SUM(AV26:AV27) | AW28: =SUM(AW26:AW27) | AX28: =SUM(AX26:AX27) | AY28: =SUM(AU28:AX28) | AZ28: =SUM(AZ26:AZ27) | BA28: =SUM(BA26:BA27) | BB28: =SUM(BB26:BB27) | BC28: =SUM(BC26:BC27) | BD28: =SUM(AZ28:BC28) | BE28: =SUM(BE26:BE27) | BF28: =SUM(BF26:BF27) | BG28: =SUM(BG26:BG27) | BH28: =SUM(BH26:BH27) | BI28: =SUM(BE28:BH28) | BJ28: =SUM(BJ26:BJ27) | BK28: =SUM(BK26:BK27) | BL28: =SUM(BL26:BL27) | BM28: =SUM(BM26:BM27) | BN28: =SUM(BJ28:BM28) | BO28: =SUM(BO26:BO27) | BP28: =SUM(BP26:BP27) | BQ28: =SUM(BQ26:BQ27) | BR28: =SUM(BR26:BR27) | BS28: =SUM(BO28:BR28) | BT28: =SUM(BT26:BT27) | BU28: =SUM(BU26:BU27) | BV28: =SUM(BV26:BV27) | BW28: =SUM(BW26:BW27) | BX28: =SUM(BT28:BW28) | BY28: =SUM(BY26:BY27) | BZ28: =SUM(BZ26:BZ27) | CA28: =SUM(CA26:CA27) | CB28: =SUM(CB26:CB27) | CC28: =SUM(BY28:CB28) | CD28: =SUM(CD26:CD27) | CE28: =SUM(CE26:CE27) | CF28: =SUM(CF26:CF27) | CG28: =SUM(CG26:CG27) | CH28: =SUM(CD28:CG28) | CI28: =SUM(CI26:CI27) | CJ28: =SUM(CJ26:CJ27) | CK28: =SUM(CK26:CK27) | CL28: =SUM(CL26:CL27) | CM28: =SUM(CI28:CL28) | CN28: =SUM(CN26:CN27) | CO28: =SUM(CO26:CO27) | CP28: =SUM(CP26:CP27) | CQ28: =SUM(CQ26:CQ27) | CR28: =SUM(CN28:CQ28) | CS28: =SUM(CS26:CS27) | CT28: =SUM(CT26:CT27) | CU28: =SUM(CU26:CU27) | CV28: =SUM(CV26:CV27) | CW28: =SUM(CS28:CV28) | CX28: =SUM(CX26:CX27) | CY28: =SUM(CY26:CY27) | CZ28: =SUM(CZ26:CZ27) | DA28: =SUM(DA26:DA27) | DB28: =SUM(CX28:DA28) | DC28: =SUM(DC26:DC27) | DD28: =SUM(DD26:DD27) | DE28: =SUM(DE26:DE27) | DF28: =SUM(DF26:DF27) | DG28: =SUM(DC28:DF28) | DH28: =SUM(DH26:DH27) | DI28: =SUM(DI26:DI27) | DJ28: =SUM(DJ26:DJ27) | DK28: =SUM(DK26:DK27) | DL28: =SUM(DH28:DK28) | DM28: =SUM(DM26:DM27) | DN28: =SUM(DN26:DN27) | DO28: =SUM(DO26:DO27) | DP28: =SUM(DP26:DP27) | DQ28: =SUM(DM28:DP28) | DR28: =SUM(DR26:DR27) | DS28: =SUM(DS26:DS27) | DT28: =SUM(DT26:DT27) | DU28: =SUM(DU26:DU27) | DV28: =SUM(DR28:DU28) | DW28: =SUM(DW26:DW27) | DX28: =SUM(DX26:DX27) | DY28: =SUM(DY26:DY27) | DZ28: =SUM(DZ26:DZ27) | EA28: =SUM(DW28:DZ28) | EB28: =SUM(EB26:EB27) | EC28: =SUM(EC26:EC27) | ED28: =SUM(ED26:ED27) | EE28: =SUM(EE26:EE27) | EF28: =SUM(EB28:EE28) | EG28: =SUM(EG26:EG27) | EH28: =SUM(EH26:EH27) | EI28: =SUM(EI26:EI27) | EJ28: =SUM(EJ26:EJ27) | EK28: =SUM(EG28:EJ28) | EL28: =SUM(EL26:EL27) | EM28: =SUM(EM26:EM27) | EN28: =SUM(EN26:EN27) | EO28: =SUM(EO26:EO27) | EP28: =SUM(EL28:EO28) | EQ28: =SUM(EQ26:EQ27) | ER28: =SUM(ER26:ER27) | ES28: =SUM(ES26:ES27) | ET28: =SUM(ET26:ET27) | EU28: =SUM(EQ28:ET28) | EV28: =SUM(EV26:EV27) | EW28: =SUM(EW26:EW27) | EX28: =SUM(EX26:EX27) | EY28: =SUM(EY26:EY27) | EZ28: =SUM(EV28:EY28)
A30: Other Expense | B30: 0 | C30: 0 | D30: 0 | E30: 0 | F30: =SUM(B30:E30) | G30: 0 | H30: 0 | I30: 0 | J30: 0 | K30: =SUM(G30:J30) | L30: 0 | M30: 0.009 | N30: 0.983 | O30: -0.94 | P30: =SUM(L30:O30) | Q30: -0.397 | R30: -0.898 | S30: 0.118 | T30: 0.359 | U30: =SUM(Q30:T30) | V30: 0 | W30: 0 | X30: 0 | Y30: =0.691 | Z30: =SUM(V30:Y30) | AA30: 0 | AB30: 0 | AC30: 0 | AD30: 0 | AE30: =SUM(AA30:AD30) | AF30: 0 | AG30: 0 | AH30: 0 | AI30: 0 | AJ30: =SUM(AF30:AI30) | AK30: 0 | AL30: 0 | AM30: 0 | AN30: 0 | AO30: =SUM(AK30:AN30) | AP30: 0 | AQ30: 0 | AR30: 0 | AS30: 0 | AT30: =SUM(AP30:AS30) | AU30: 0 | AV30: 0 | AW30: 0 | AX30: 0 | AY30: =SUM(AU30:AX30) | AZ30: 0 | BA30: 0 | BB30: 0 | BC30: 0 | BD30: =SUM(AZ30:BC30) | BE30: 0 | BF30: 0 | BG30: 0 | BH30: 0 | BI30: =SUM(BE30:BH30) | BJ30: 0 | BK30: 0 | BL30: 0 | BM30: 0 | BN30: =SUM(BJ30:BM30) | BO30: 0 | BP30: 0 | BQ30: 0 | BR30: 0 | BS30: =SUM(BO30:BR30) | BT30: 0 | BU30: 0 | BV30: 0 | BW30: 0 | BX30: =SUM(BT30:BW30) | BY30: 0 | BZ30: 0 | CA30: 0 | CB30: 0 | CC30: =SUM(BY30:CB30) | CD30: 0 | CE30: 0 | CF30: 0 | CG30: 0 | CH30: =SUM(CD30:CG30) | CI30: 0 | CJ30: 0 | CK30: 0 | CL30: 0 | CM30: =SUM(CI30:CL30) | CN30: 0 | CO30: 0 | CP30: 0 | CQ30: 0 | CR30: =SUM(CN30:CQ30) | CS30: 0 | CT30: 0 | CU30: =16-15 | CV30: =6-6-1 | CW30: =SUM(CS30:CV30) | CX30: =18-14 | CY30: =4-3 | CZ30: =1-1 | DA30: 0 | DB30: =SUM(CX30:DA30) | DC30: 6 | DD30: -5 | DE30: =-1 | DF30: -2 | DG30: =SUM(DC30:DF30) | DH30: 0 | DI30: -1 | DJ30: 0 | DK30: 0 | DL30: =SUM(DH30:DK30) | DM30: 0 | DN30: 0 | DO30: 0 | DP30: 0 | DQ30: =SUM(DM30:DP30) | DR30: 0 | DS30: 0 | DT30: 0 | DU30: 0 | DV30: =SUM(DR30:DU30) | DW30: 0 | DX30: 1 | DY30: 0 | DZ30: 0 | EA30: =SUM(DW30:DZ30) | EB30: 0 | EC30: 0 | ED30: 0 | EE30: 0 | EF30: =SUM(EB30:EE30) | EG30: 0 | EH30: 0 | EI30: 0 | EJ30: 0 | EK30: =SUM(EG30:EJ30) | EL30: 0 | EM30: 0 | EN30: 0 | EO30: 0 | EP30: =SUM(EL30:EO30) | EQ30: 0 | ER30: 0 | ES30: 0 | ET30: 0 | EU30: =SUM(EQ30:ET30) | EV30: 0 | EW30: 0 | EX30: 0 | EY30: 0 | EZ30: =SUM(EV30:EY30)
A32: EBT | B32: =B22-B28-B30 | C32: =C22-C28-C30 | D32: =D22-D28-D30 | E32: =E22-E28-E30 | F32: =SUM(B32:E32) | G32: =G22-G28-G30 | H32: =H22-H28-H30 | I32: =I22-I28-I30 | J32: =J22-J28-J30 | K32: =SUM(G32:J32) | L32: =L22-L28-L30 | M32: =M22-M28-M30 | N32: =N22-N28-N30 | O32: =O22-O28-O30 | P32: =SUM(L32:O32) | Q32: =Q22-Q28-Q30 | R32: =R22-R28-R30 | S32: =S22-S28-S30 | T32: =T22-T28-T30 | U32: =SUM(Q32:T32) | V32: =V22-V28-V30 | W32: =W22-W28-W30 | X32: =X22-X28-X30 | Y32: =Y22-Y28-Y30 | Z32: =SUM(V32:Y32) | AA32: =AA22-AA28-AA30 | AB32: =AB22-AB28-AB30 | AC32: =AC22-AC28-AC30 | AD32: =AD22-AD28-AD30 | AE32: =SUM(AA32:AD32) | AF32: =AF22-AF28-AF30 | AG32: =AG22-AG28-AG30 | AH32: =AH22-AH28-AH30 | AI32: =AI22-AI28-AI30 | AJ32: =SUM(AF32:AI32) | AK32: =AK22-AK28-AK30 | AL32: =AL22-AL28-AL30 | AM32: =AM22-AM28-AM30 | AN32: =AN22-AN28-AN30 | AO32: =SUM(AK32:AN32) | AP32: =AP22-AP28-AP30 | AQ32: =AQ22-AQ28-AQ30 | AR32: =AR22-AR28-AR30 | AS32: =AS22-AS28-AS30 | AT32: =SUM(AP32:AS32) | AU32: =AU22-AU28-AU30 | AV32: =AV22-AV28-AV30 | AW32: =AW22-AW28-AW30 | AX32: =AX22-AX28-AX30 | AY32: =SUM(AU32:AX32) | AZ32: =AZ22-AZ28-AZ30 | BA32: =BA22-BA28-BA30 | BB32: =BB22-BB28-BB30 | BC32: =BC22-BC28-BC30 | BD32: =SUM(AZ32:BC32) | BE32: =BE22-BE28-BE30 | BF32: =BF22-BF28-BF30 | BG32: =BG22-BG28-BG30 | BH32: =BH22-BH28-BH30 | BI32: =SUM(BE32:BH32) | BJ32: =BJ22-BJ28-BJ30 | BK32: =BK22-BK28-BK30 | BL32: =BL22-BL28-BL30 | BM32: =BM22-BM28-BM30 | BN32: =SUM(BJ32:BM32) | BO32: =BO22-BO28-BO30 | BP32: =BP22-BP28-BP30 | BQ32: =BQ22-BQ28-BQ30 | BR32: =BR22-BR28-BR30 | BS32: =SUM(BO32:BR32) | BT32: =BT22-BT28-BT30 | BU32: =BU22-BU28-BU30 | BV32: =BV22-BV28-BV30 | BW32: =BW22-BW28-BW30 | BX32: =SUM(BT32:BW32) | BY32: =BY22-BY28-BY30 | BZ32: =BZ22-BZ28-BZ30 | CA32: =CA22-CA28-CA30 | CB32: =CB22-CB28-CB30 | CC32: =SUM(BY32:CB32) | CD32: =CD22-CD28-CD30 | CE32: =CE22-CE28-CE30 | CF32: =CF22-CF28-CF30 | CG32: =CG22-CG28-CG30 | CH32: =SUM(CD32:CG32) | CI32: =CI22-CI28-CI30 | CJ32: =CJ22-CJ28-CJ30 | CK32: =CK22-CK28-CK30 | CL32: =CL22-CL28-CL30 | CM32: =SUM(CI32:CL32) | CN32: =CN22-CN28-CN30 | CO32: =CO22-CO28-CO30 | CP32: =CP22-CP28-CP30 | CQ32: =CQ22-CQ28-CQ30 | CR32: =SUM(CN32:CQ32) | CS32: =CS22-CS28-CS30 | CT32: =CT22-CT28-CT30 | CU32: =CU22-CU28-CU30 | CV32: =CV22-CV28-CV30 | CW32: =SUM(CS32:CV32) | CX32: =CX22-CX28-CX30 | CY32: =CY22-CY28-CY30 | CZ32: =CZ22-CZ28-CZ30 | DA32: =DA22-DA28-DA30 | DB32: =SUM(CX32:DA32) | DC32: =DC22-DC28-DC30 | DD32: =DD22-DD28-DD30 | DE32: =DE22-DE28-DE30 | DF32: =DF22-DF28-DF30 | DG32: =SUM(DC32:DF32) | DH32: =DH22-DH28-DH30 | DI32: =DI22-DI28-DI30 | DJ32: =DJ22-DJ28-DJ30 | DK32: =DK22-DK28-DK30 | DL32: =SUM(DH32:DK32) | DM32: =DM22-DM28-DM30 | DN32: =DN22-DN28-DN30 | DO32: =DO22-DO28-DO30 | DP32: =DP22-DP28-DP30 | DQ32: =SUM(DM32:DP32) | DR32: =DR22-DR28-DR30 | DS32: =DS22-DS28-DS30 | DT32: =DT22-DT28-DT30 | DU32: =DU22-DU28-DU30 | DV32: =SUM(DR32:DU32) | DW32: =DW22-DW28-DW30 | DX32: =DX22-DX28-DX30 | DY32: =DY22-DY28-DY30 | DZ32: =DZ22-DZ28-DZ30 | EA32: =SUM(DW32:DZ32) | EB32: =EB22-EB28-EB30 | EC32: =EC22-EC28-EC30 | ED32: =ED22-ED28-ED30 | EE32: =EE22-EE28-EE30 | EF32: =SUM(EB32:EE32) | EG32: =EG22-EG28-EG30 | EH32: =EH22-EH28-EH30 | EI32: =EI22-EI28-EI30 | EJ32: =EJ22-EJ28-EJ30 | EK32: =SUM(EG32:EJ32) | EL32: =EL22-EL28-EL30 | EM32: =EM22-EM28-EM30 | EN32: =EN22-EN28-EN30 | EO32: =EO22-EO28-EO30 | EP32: =SUM(EL32:EO32) | EQ32: =EQ22-EQ28-EQ30 | ER32: =ER22-ER28-ER30 | ES32: =ES22-ES28-ES30 | ET32: =ET22-ET28-ET30 | EU32: =SUM(EQ32:ET32) | EV32: =EV22-EV28-EV30 | EW32: =EW22-EW28-EW30 | EX32: =EX22-EX28-EX30 | EY32: =EY22-EY28-EY30 | EZ32: =SUM(EV32:EY32)
A34: Total Taxes | B34: 0 | C34: 0 | D34: 0 | E34: 0 | F34: =SUM(B34:E34) | G34: -0.089 | H34: -0.839 | I34: 0.62 | J34: 0.665 | K34: =SUM(G34:J34) | L34: 3.084 | M34: =3.146 | N34: =4.973 | O34: =6.865 | P34: =SUM(L34:O34) | Q34: 8.605 | R34: 10.599 | S34: 13.209 | T34: 14.622 | U34: =SUM(Q34:T34) | V34: =11.422+0.3*9.573 | W34: =14.111 | X34: =17.706 | Y34: 37.6344 | Z34: =SUM(V34:Y34) | AA34: 35.677 | AB34: =2.251+0.3*21 | AC34: =0.3*AC32 | AD34: =21.83-0.3*40.365 | AE34: =SUM(AA34:AD34) | AF34: 8.463 | AG34: 2.511 | AH34: =-0.803+0.4*13.068 | AI34: 2.083 | AJ34: =SUM(AF34:AI34) | AK34: 5.338 | AL34: 1.28 | AM34: 6.47 | AN34: 12.001 | AO34: =SUM(AK34:AN34) | AP34: 16.111 | AQ34: 10.419 | AR34: =12.429+14.158*0.16 | AS34: 18.676 | AT34: =SUM(AP34:AS34) | AU34: 18.712 | AV34: 17.769 | AW34: =21.816+(6.594-(AW41-AW42)) | AX34: =AX35*AX32 | AY34: =SUM(AU34:AX34) | AZ34: 21.53 | BA34: 28.119 | BB34: 31.138 | BC34: 22.909 | BD34: =SUM(AZ34:BC34) | BE34: 36.213 | BF34: =-25.671+0.17*195.954 | BG34: =-0.745 | BH34: -22.71 | BI34: =SUM(BE34:BH34) | BJ34: =-23.483+16.142 | BK34: =-1.799+1.398 | BL34: =2.63-4.876+1.008 | BM34: 8.345 | BN34: =SUM(BJ34:BM34) | BO34: 13.131 | BP34: =-28.086+32.828 | BQ34: 18.723 | BR34: 14.255 | BS34: =SUM(BO34:BR34) | BT34: 21.266 | BU34: 25.974 | BV34: 26.514 | BW34: 8.552 | BX34: =SUM(BT34:BW34) | BY34: =16.658-7.989+(BY41-BY42) | BZ34: =26.162+9.839-5.806 | CA34: =44.548+0.556 | CB34: 12.135 | CC34: =SUM(BY34:CB34) | CD34: =10.171+6.348-3.507 | CE34: =15.372+6.767-5.183 | CF34: =22.75+6.055 | CG34: =21.971+1.924 | CH34: =SUM(CD34:CG34) | CI34: =26.766+5.342-5 | CJ34: =26.649+11.606-5 | CK34: =36.103+10.549-7 | CL34: =34.731+3.783 | CM34: =SUM(CI34:CL34) | CN34: =38+1 | CO34: =46-2-9 | CP34: =-1+57 | CQ34: =46+21 | CR34: =SUM(CN34:CQ34) | CS34: =45+14 | CT34: =64+12 | CU34: =79+62 | CV34: =71+36 | CW34: =SUM(CS34:CV34) | CX34: =29+73 | CY34: =101+34 | CZ34: =58+116 | DA34: =-40+33+133 | DB34: =SUM(CX34:DA34) | DC34: =67+87 | DD34: =79+22 | DE34: =-149+91+138 | DF34: =-243+230+25 | DG34: =SUM(DC34:DF34) | DH34: =-5+50 | DI34: =54+21 | DJ34: =60+26 | DK34: =66+8 | DL34: =SUM(DH34:DK34) | DM34: =64+30 | DN34: =-13+124 | DO34: =12+102 | DP34: =13+74 | DQ34: =SUM(DM34:DP34) | DR34: =132+67 | DS34: =20+127+252 | DT34: =174+187 | DU34: =-138+330-7+90 | DV34: =SUM(DR34:DU34) | DW34: =187+280 | DX34: =-181+197 | DY34: =-67+171 | DZ34: =-125+218 | EA34: =SUM(DW34:DZ34) | EB34: =166+257 | EC34: =793+363 | ED34: =1279+433 | EE34: =1821+321 | EF34: =SUM(EB34:EE34) | EG34: =2398+725 | EH34: =2615+750 | EI34: =3007+670 | EJ34: =3126+781 | EK34: =SUM(EG34:EJ34) | EL34: =3135+694 | EM34: =4784+166-48 | EN34: =(EN32)*EN35 | EO34: =(EO32)*EO35 | EP34: =SUM(EL34:EO34) | EQ34: =(EQ32)*EQ35 | ER34: =(ER32)*ER35 | ES34: =(ES32)*ES35 | ET34: =(ET32)*ET35 | EU34: =SUM(EQ34:ET34) | EV34: =(EV32)*EV35 | EW34: =(EW32)*EW35 | EX34: =(EX32)*EX35 | EY34: =(EY32)*EY35 | EZ34: =SUM(EV34:EY34)
A35: Tax Rate | B35: =B34/B32 | C35: =C34/C32 | D35: =D34/D32 | E35: =E34/E32 | F35: =F34/F32 | G35: =G34/G32 | H35: =H34/H32 | I35: =I34/I32 | ... AW35: =AW34/AW32 | AX35: 0.09 | AY35: =AY34/AY32 | AZ35: =AZ34/AZ32 | BA35: =BA34/BA32 | BB35: =BB34/BB32 | BC35: =BC34/BC32 | BD35: =BD34/BD32 | BE35: =BE34/BE32 | BF35: =BF34/BF32 | ... DV35: =DV34/DV32 | DW35: =DW34/(DW32+DW42) | DX35: =DX34/(DX32+DX42) | DY35: =DY34/(DY32+DY42) | DZ35: =DZ34/(DZ32+DZ42) | EA35: =EA34/(EA32+EA42) | EB35: =EB34/(EB32+EB42) | EC35: =EC34/(EC32+EC42) | ED35: =ED34/(ED32+ED42) | ... EM35: =EM34/(EM32+EM42) | EN35: 0.165 | EO35: =EN35 | EP35: =EP34/(EP32) | EQ35: 0.165 | ER35: =EQ35 | ES35: =ER35 | ET35: =ES35 | EU35: =EU34/(EU32) | EV35: 0.165 | EW35: =EV35 | EX35: =EW35 | EY35: =EX35 | EZ35: =EZ34/(EZ32)
A37: Net Income - Recurring | B37: =B32-B34 | C37: =C32-C34 | D37: =D32-D34 | E37: =E32-E34 | F37: =SUM(B37:E37) | G37: =G32-G34 | H37: =H32-H34 | I37: =I32-I34 | J37: =J32-J34 | K37: =SUM(G37:J37) | L37: =L32-L34 | M37: =M32-M34 | N37: =N32-N34 | O37: =O32-O34 | P37: =SUM(L37:O37) | Q37: =Q32-Q34 | R37: =R32-R34 | S37: =S32-S34 | T37: =T32-T34 | U37: =SUM(Q37:T37) | V37: =V32-V34 | W37: =W32-W34 | X37: =X32-X34 | Y37: =Y32-Y34 | Z37: =SUM(V37:Y37) | AA37: =AA32-AA34 | AB37: =AB32-AB34 | AC37: =AC32-AC34 | AD37: =AD32-AD34 | AE37: =SUM(AA37:AD37) | AF37: =AF32-AF34 | AG37: =AG32-AG34 | AH37: =AH32-AH34 | AI37: =AI32-AI34 | AJ37: =SUM(AF37:AI37) | AK37: =AK32-AK34 | AL37: =AL32-AL34 | AM37: =AM32-AM34 | AN37: =AN32-AN34 | AO37: =SUM(AK37:AN37) | AP37: =AP32-AP34 | AQ37: =AQ32-AQ34 | AR37: =AR32-AR34 | AS37: =AS32-AS34 | AT37: =SUM(AP37:AS37) | AU37: =AU32-AU34 | AV37: =AV32-AV34 | AW37: =AW32-AW34 | AX37: =AX32-AX34 | AY37: =SUM(AU37:AX37) | AZ37: =AZ32-AZ34 | BA37: =BA32-BA34 | BB37: =BB32-BB34 | BC37: =BC32-BC34 | BD37: =SUM(AZ37:BC37) | BE37: =BE32-BE34 | BF37: =BF32-BF34 | BG37: =BG32-BG34 | BH37: =BH32-BH34 | BI37: =SUM(BE37:BH37) | BJ37: =BJ32-BJ34 | BK37: =BK32-BK34 | BL37: =BL32-BL34 | BM37: =BM32-BM34 | BN37: =SUM(BJ37:BM37) | BO37: =BO32-BO34 | BP37: =BP32-BP34 | BQ37: =BQ32-BQ34 | BR37: =BR32-BR34 | BS37: =SUM(BO37:BR37) | BT37: =BT32-BT34 | BU37: =BU32-BU34 | BV37: =BV32-BV34 | BW37: =BW32-BW34 | BX37: =SUM(BT37:BW37) | BY37: =BY32-BY34 | BZ37: =BZ32-BZ34 | CA37: =CA32-CA34 | CB37: =CB32-CB34 | CC37: =SUM(BY37:CB37) | CD37: =CD32-CD34 | CE37: =CE32-CE34 | CF37: =CF32-CF34 | CG37: =CG32-CG34 | CH37: =SUM(CD37:CG37) | CI37: =CI32-CI34 | CJ37: =CJ32-CJ34 | CK37: =CK32-CK34 | CL37: =CL32-CL34 | CM37: =SUM(CI37:CL37) | CN37: =CN32-CN34 | CO37: =CO32-CO34 | CP37: =CP32-CP34 | CQ37: =CQ32-CQ34 | CR37: =SUM(CN37:CQ37) | CS37: =CS32-CS34 | CT37: =CT32-CT34 | CU37: =CU32-CU34 | CV37: =CV32-CV34 | CW37: =SUM(CS37:CV37) | CX37: =CX32-CX34 | CY37: =CY32-CY34 | CZ37: =CZ32-CZ34 | DA37: =DA32-DA34 | DB37: =SUM(CX37:DA37) | DC37: =DC32-DC34 | DD37: =DD32-DD34 | DE37: =DE32-DE34 | DF37: =DF32-DF34 | DG37: =SUM(DC37:DF37) | DH37: =DH32-DH34 | DI37: =DI32-DI34 | DJ37: =DJ32-DJ34 | DK37: =DK32-DK34 | DL37: =SUM(DH37:DK37) | DM37: =DM32-DM34 | DN37: =DN32-DN34 | DO37: =DO32-DO34 | DP37: =DP32-DP34 | DQ37: =SUM(DM37:DP37) | DR37: =DR32-DR34 | DS37: =DS32-DS34 | DT37: =DT32-DT34 | DU37: =DU32-DU34 | DV37: =SUM(DR37:DU37) | DW37: =DW32-DW34 | DX37: =DX32-DX34 | DY37: =DY32-DY34 | DZ37: =DZ32-DZ34 | EA37: =SUM(DW37:DZ37) | EB37: =EB32-EB34 | EC37: =EC32-EC34 | ED37: =ED32-ED34 | EE37: =EE32-EE34 | EF37: =SUM(EB37:EE37) | EG37: =EG32-EG34 | EH37: =EH32-EH34 | EI37: =EI32-EI34 | EJ37: =EJ32-EJ34 | EK37: =SUM(EG37:EJ37) | EL37: =EL32-EL34 | EM37: =EM32-EM34 | EN37: =EN32-EN34 | EO37: =EO32-EO34 | EP37: =SUM(EL37:EO37) | EQ37: =EQ32-EQ34 | ER37: =ER32-ER34 | ES37: =ES32-ES34 | ET37: =ET32-ET34 | EU37: =SUM(EQ37:ET37) | EV37: =EV32-EV34 | EW37: =EW32-EW34 | EX37: =EX32-EX34 | EY37: =EY32-EY34 | EZ37: =SUM(EV37:EY37)
A39: Extraordinary Gain (Loss) | B39: 0 | C39: 0 | D39: 0 | E39: 0 | F39: =SUM(B39:E39) | G39: 0 | H39: 0 | I39: 0 | J39: 0 | K39: =SUM(G39:J39) | L39: 0 | M39: 0 | N39: 0 | O39: 0 | P39: =SUM(L39:O39) | Q39: 0 | R39: 0 | S39: 0 | T39: 0 | U39: =SUM(Q39:T39) | V39: =-0.7*9.573 | W39: =-0.457 | X39: -3.687 | Y39: 1.2432 | Z39: =SUM(V39:Y39) | AA39: 0 | AB39: =-0.7*21 | AC39: =-61.832+AC34 | AD39: =0.7*40.365 | AE39: =SUM(AA39:AD39) | AF39: 0 | AG39: 0 | AH39: =-3.5-13.068*0.6 | AI39: 0 | AJ39: =SUM(AF39:AI39) | AK39: 0 | AL39: 0 | AM39: 0 | AN39: 0 | AO39: =SUM(AK39:AN39) | AP39: 0 | AQ39: 0 | AR39: =-14.158*(1-0.16) | AS39: 0 | AT39: =SUM(AP39:AS39) | AU39: 0.704 | AV39: 0 | AW39: =-(17.5-(6.594-(AW41-AW42))) | AX39: =-13.4+(11.947+AX34) | AY39: =SUM(AU39:AX39) | AZ39: 0 | BA39: 0 | BB39: 0 | BC39: -4 | BD39: =SUM(AZ39:BC39) | BE39: 0 | BF39: =-0.83*195.954 | BG39: =-8.338-4.5 | BH39: -18.53 | BI39: =SUM(BE39:BH39) | BJ39: =-(11.412+128.829)+16.142 | BK39: =-119.993+0.939+1.398 | BL39: =25.105-4.876+0.018 | BM39: 0 | BN39: =SUM(BJ39:BM39) | BO39: 0 | BP39: =-193.3+32.23 | BQ39: 0 | BR39: 57 | BS39: =SUM(BO39:BR39) | BT39: 0 | BU39: -7.562 | BV39: -6.413 | BW39: =-7.3-5.052 | BX39: =SUM(BT39:BW39) | BY39: =-4.342-5.171-7.989+(BY41-BY42) | BZ39: =-4.065-4.794-20.127+9.839-5.806 | CA39: =-4.402-4.666+0.556 | CB39: =-4.373-4.325 | CC39: =SUM(BY39:CB39) | CD39: =-3.915-4.946+6.348-3.507 | CE39: =-2.29-3.98-4.984+6.767-5.183 | CF39: =-4.906+0.329-2.235+6.055 | CG39: -3.067 | CH39: =SUM(CD39:CG39) | CI39: =-9.441+16.982-6.901+5.342-5 | CJ39: =-9.173-2.5-6.973+11.606-5 | CK39: =-9.572+10.549-7.01-7 | CL39: =-9.169-7.083+3.783 | CM39: =SUM(CI39:CL39) | CN39: =-9-7+1 | CO39: =-15-4-89-7-2-9 | CP39: =-4-8-7+57 | CQ39: =-5-4-34-7+21 | CR39: =SUM(CN39:CQ39) | CS39: =-10-6-4-3-1-7+14 | CT39: =-4-1-2-7+12 | CU39: =-4-6-15+62 | CV39: =-4-4-6-1+36 | CW39: =SUM(CS39:CV39) | CX39: =-4-2-2-14+73 | CY39: =-4-1-3+34 | CZ39: =-3-1+116 | DA39: =+-1-2-2+2+33+133 | DB39: =SUM(CX39:DA39) | DC39: =+-2-2+6-1+87 | DD39: =-2+2+22 | DE39: =-14-1-1+4+2+91+138 | DF39: =-21-1-7+1+25+230 | DG39: =SUM(DC39:DF39) | DH39: =-10-10-1+50 | DI39: =-2-5+21 | DJ39: =-7+1+26 | DK39: =-3-7+8 | DL39: =SUM(DH39:DK39) | DM39: =-1-4-3-1+30 | DN39: =-245-17-229-2-1+124 | DO39: =-86-21-106-4-1+102+1 | DP39: =-92-1-72+9-1+74 | DQ39: =SUM(DM39:DP39) | DR39: =-87-5-80+134-1+67 | DS39: =-86-4-72-1+127+252 | DT39: =-86-70-1+187+20 | DU39: =-86-70-53+330-7+90 | DV39: =SUM(DR39:DU39) | DW39: =-94-1353-55-7-17-1+280 | DX39: =-121-54-2-7-1+197+1 | DY39: =-120-54-16-11-1+171 | DZ39: =-120-54-38-10-1+218-16 | EA39: =SUM(DW39:DZ39) | EB39: =-119-54+4-14-1+257-8 | EC39: =-119-18+5+62-1+363-2 | ED39: =-119-26-16-69-1+433 | EE39: =-119-4-18+260-1+321 | EF39: =SUM(EB39:EE39) | EG39: =-119+1-21+69-1+725 | EH39: =-118+3-26+193-1+750 | EI39: =-116-39+37-1+670 | EJ39: =+-118-0-43+727-1+781 | EK39: =SUM(EG39:EJ39) | EL39: =-123-3-37-175-1+694 | EM39: =-49-37-15+2247-1+166-48 | EN39: 0 | EO39: 0 | EP39: =SUM(EL39:EO39) | EQ39: 0 | ER39: 0 | ES39: 0 | ET39: 0 | EU39: =SUM(EQ39:ET39) | EV39: 0 | EW39: 0 | EX39: 0 | EY39: 0 | EZ39: =SUM(EV39:EY39)
A40: Goodwill amortization | B40: 0 | C40: 0 | D40: 0 | E40: 0 | F40: =SUM(B40:E40) | G40: 0 | H40: 0 | I40: 0 | J40: 0 | K40: =SUM(G40:J40) | L40: 0 | M40: 0 | N40: 0 | O40: 0 | P40: =SUM(L40:O40) | Q40: 0 | R40: 0 | S40: 0 | T40: 0 | U40: =SUM(Q40:T40) | V40: =-0.375 | W40: =-3.236 | X40: =-3.237 | Y40: -0.2171 | Z40: =SUM(V40:Y40) | AA40: 0 | AB40: 0 | AC40: 0 | AD40: 0 | AE40: =SUM(AA40:AD40) | AF40: 0 | AG40: 0 | AH40: 0 | AI40: 0 | AJ40: =SUM(AF40:AI40) | AK40: 0 | AL40: 0 | AM40: 0 | AN40: 0 | AO40: =SUM(AK40:AN40) | AP40: 0 | AQ40: 0 | AR40: 0 | AS40: 0 | AT40: =SUM(AP40:AS40) | AU40: 0 | AV40: 0 | AW40: 0 | AX40: 0 | AY40: =SUM(AU40:AX40) | AZ40: 0 | BA40: 0 | BB40: 0 | BC40: 0 | BD40: =SUM(AZ40:BC40) | BE40: 0 | BF40: 0 | BG40: 0 | BH40: 0 | BI40: =SUM(BE40:BH40) | BJ40: 0 | BK40: 0 | BL40: 0 | BM40: 0 | BN40: =SUM(BJ40:BM40) | BO40: 0 | BP40: 0 | BQ40: 0 | BR40: 0 | BS40: =SUM(BO40:BR40) | BT40: 0 | BU40: 0 | BV40: 0 | BW40: 0 | BX40: =SUM(BT40:BW40) | BY40: 0 | BZ40: 0 | CA40: 0 | CB40: 0 | CC40: =SUM(BY40:CB40) | CD40: 0 | CE40: 0 | CF40: 0 | CG40: 0 | CH40: =SUM(CD40:CG40) | CI40: 0 | CJ40: 0 | CK40: 0 | CL40: 0 | CM40: =SUM(CI40:CL40) | CN40: 0 | CO40: 0 | CP40: 0 | CQ40: 0 | CR40: =SUM(CN40:CQ40) | CS40: 0 | CT40: 0 | CU40: 0 | CV40: 0 | CW40: =SUM(CS40:CV40) | CX40: 0 | CY40: 0 | CZ40: 0 | DA40: 0 | DB40: =SUM(CX40:DA40) | DC40: 0 | DD40: 0 | DE40: 0 | DF40: 0 | DG40: =SUM(DC40:DF40) | DH40: 0 | DI40: 0 | DJ40: 0 | DK40: 0 | DL40: =SUM(DH40:DK40) | DM40: 0 | DN40: 0 | DO40: 0 | DP40: 0 | DQ40: =SUM(DM40:DP40) | DR40: 0 | DS40: 0 | DT40: 0 | DU40: 0 | DV40: =SUM(DR40:DU40) | DW40: 0 | DX40: 0 | DY40: 0 | DZ40: 0 | EA40: =SUM(DW40:DZ40) | EB40: 0 | EC40: 0 | ED40: 0 | EE40: 0 | EF40: =SUM(EB40:EE40) | EG40: 0 | EH40: 0 | EI40: 0 | EJ40: 0 | EK40: =SUM(EG40:EJ40) | EL40: 0 | EM40: 0 | EN40: 0 | EO40: 0 | EP40: =SUM(EL40:EO40) | EQ40: 0 | ER40: 0 | ES40: 0 | ET40: 0 | EU40: =SUM(EQ40:ET40) | EV40: 0 | EW40: 0 | EX40: 0 | EY40: 0 | EZ40: =SUM(EV40:EY40)
A41: ESO Expense (pre tax) | F41: =SUM(B41:E41) | K41: =SUM(G41:J41) | P41: =SUM(L41:O41) | U41: =SUM(Q41:T41) | Z41: =SUM(V41:Y41) | AE41: =SUM(AA41:AD41) | AF41: =AF42/(1-AF35) | AG41: =AG42/(1-AG35) | AH41: =AH42/(1-AH35) | AI41: =AI42/(1-AI35) | AJ41: =SUM(AF41:AI41) | AK41: =AK42/(1-AK35) | AL41: =AL42/(1-AL35) | AM41: =AM42/(1-AM35) | AN41: =AN42/(1-AN35) | AO41: =SUM(AK41:AN41) | AP41: =AP42/(1-AP35) | AQ41: =AQ42/(1-AQ35) | AR41: =AR42/(1-AR35) | AS41: =AS42/(1-AS35) | AT41: =SUM(AP41:AS41) | AU41: 22.225 | AV41: =28.81 | AW41: 31.735 | AX41: 33.909 | AY41: =SUM(AU41:AX41) | AZ41: 37.405 | BA41: 29.46 | BB41: =2.566+18.65+10.787 | BC41: =2.809+19.146+12.542 | BD41: =SUM(AZ41:BC41) | BE41: =3.136+24.534+14.454 | BF41: =3.333+24.226+12.806 | BG41: =3.558+22.74+12.086 | BH41: 41.833 | BI41: =SUM(BE41:BH41) | BJ41: =2.23+31.883 | BK41: =4.828+13.268+7.28 | BL41: =2.65+12.853+7.479 | BM41: =2.65+12.853+7.479 | BN41: =SUM(BJ41:BM41) | BO41: =BO42/(1-BO35) | BP41: =2.289+14.5322+7.81 | BQ41: =2.49+14.104+8.585 | BR41: =100.353-BQ41-BP41-BO41 | BS41: =SUM(BO41:BR41) | BT41: 31.739 | BU41: =2.748+21.697+11.505 | BV41: =3.049+19.308+10.872 | BW41: =3.048+20.908+11.48 | BX41: =SUM(BT41:BW41) | BY41: =2.526+21.207+11.836 | BZ41: =2.649+18.885+10.721 | CA41: 30.58 | CB41: =2.826+22.009+10.934 | CC41: =SUM(BY41:CB41) | CD41: =2.653+21.935+8.809 | CE41: =30.227+2.168 | CF41: =3.09+20.902+10.307 | CG41: =2.777+33.427 | CH41: =SUM(CD41:CG41) | CI41: =32.602+2.919 | CJ41: =2.656+21.462+14.297 | CK41: =3.021+22.68+15.734 | CL41: =3.426+23.719+15.325 | CM41: =SUM(CI41:CL41) | CN41: =2+27+16 | CO41: =3+27+17 | CP41: =4+28+19 | CQ41: =5+56 | CR41: =SUM(CN41:CQ41) | CS41: =4+49 | CT41: =4+30+24 | CU41: =3+35+27 | CV41: =4+40+27 | CW41: =SUM(CS41:CV41) | CX41: =4+41+31 | CY41: =4+44+33 | CZ41: =6+61+40 | DA41: =7+73+46 | DB41: =SUM(CX41:DA41) | DC41: =8+74+47 | DD41: =8+76+48-1 | DE41: =DE42/(1-DE35) | DF41: =DF42/(1-DF35) | DG41: =SUM(DC41:DF41) | DH41: =DH42/(1-DH35) | DI41: =DI42/(1-DI35) | DJ41: =DJ42/(1-DJ35) | DK41: =DK42/(1-DK35) | DL41: =SUM(DH41:DK41) | DM41: =DM42/(1-DM35) | DN41: =DN42/(1-DN35) | DO41: =DO42/(1-DO35) | DP41: =DP42/(1-DP35) | DQ41: =SUM(DM41:DP41) | DR41: =DR42/(1-DR35) | DS41: =DS42/(1-DS35) | DT41: =DT42/(1-DT35) | DU41: =DU42/(1-DU35) | DV41: =SUM(DR41:DU41) | DW41: =DW42/(1-DW35) | DX41: =DX42/(1-DX35) | DY41: =DY42/(1-DY35) | DZ41: =DZ42/(1-DZ35) | EA41: =SUM(DW41:DZ41) | EB41: =EB42/(1-EB35) | EC41: =EC42/(1-EC35) | ED41: =ED42/(1-ED35) | EE41: =EE42/(1-EE35) | EF41: =SUM(EB41:EE41) | EG41: =EG42/(1-EG35) | EH41: =EH42/(1-EH35) | EI41: =EI42/(1-EI35) | EJ41: =EJ42/(1-EJ35) | EK41: =SUM(EG41:EJ41) | EL41: =EL42/(1-EL35) | EM41: =EM42/(1-EM35) | EN41: =EN42/(1-EN35) | EO41: =EO42/(1-EO35) | EP41: =SUM(EL41:EO41) | EQ41: =EQ42/(1-EQ35) | ER41: =ER42/(1-ER35) | ES41: =ES42/(1-ES35) | ET41: =ET42/(1-ET35) | EU41: =SUM(EQ41:ET41) | EV41: =EV42/(1-EV35) | EW41: =EW42/(1-EW35) | EX41: =EX42/(1-EX35) | EY41: =EY42/(1-EY35) | EZ41: =SUM(EV41:EY41)
A42: ESO Expense (net of tax) | F42: =SUM(B42:E42) | K42: =SUM(G42:J42) | P42: =SUM(L42:O42) | U42: =SUM(Q42:T42) | Z42: =SUM(V42:Y42) | AE42: =SUM(AA42:AD42) | AF42: 16.143 | AG42: 20.312 | AH42: =20.075-0.231 | AI42: 17.677 | AJ42: =SUM(AF42:AI42) | AK42: =20.72-0.306 | AL42: =21.699-0.291 | AM42: =25.135-0.244 | AN42: 19.288 | AO42: =SUM(AK42:AN42) | AP42: =16.846-0.228 | AQ42: =22.034-0.244 | AR42: =19.402-0.225 | AS42: =79.862-0.92-SUM(AP42:AR42) | AT42: =SUM(AP42:AS42) | AU42: =AU41-2.736 | AV42: 25.857 | AW42: =0.88*AW41 | AX42: =0.88*AX41 | AY42: =SUM(AU42:AX42) | AZ42: =AZ41-5.237 | BA42: =BA41-4.125 | BB42: =BB41-3.491 | BC42: =BC41-2.902 | BD42: =SUM(AZ42:BC42) | BE42: =BE41-7.161 | BF42: =BF41-0.17*BF41 | BG42: =BG41-1.54 | BH42: 34.8 | BI42: =SUM(BE42:BH42) | BJ42: =(1-0.104)*BJ41 | BK42: =BK41 | BL42: 23 | BM42: 23 | BN42: =SUM(BJ42:BM42) | BO42: 26 | BP42: =BP41*(1-BP35) | BQ42: =BQ41*(1-BQ35) | BR42: =BR41*(1-BR35) | BS42: =SUM(BO42:BR42) | BT42: =BT41*(1-BT35) | BU42: =BU41*(1-BU35) | BV42: =BV41*(1-BV35) | BW42: =BW41*(1-BW35) | BX42: =SUM(BT42:BW42) | BY42: =BY41*(1-0.15) | BZ42: =BZ41*(1-0.18) | CA42: =CA41*(1-0.17) | CB42: =CB41*(1-0.062) | CC42: =SUM(BY42:CB42) | CD42: =CD41*(1-0.105) | CE42: =CE41*(1-0.16) | CF42: 30.8 | CG42: =CG41*(1-0.105) | CH42: =SUM(CD42:CG42) | CI42: =+CI41-5 | CJ42: =+CJ41-5 | CK42: =+CK41-7 | CL42: =+CL41-7 | CM42: =SUM(CI42:CL42) | CN42: =+CN41-9 | CO42: =+CO41-9 | CP42: =+CP41-1 | CQ42: =+CQ41-4 | CR42: =SUM(CN42:CQ42) | CS42: =+CS41-5 | CT42: =+CT41-1 | CU42: =+CU41 | CV42: =+CV41 | CW42: =SUM(CS42:CV42) | CX42: =+CX41 | CY42: =+CY41 | CZ42: =+CZ41 | DA42: =+DA41 | DB42: =SUM(CX42:DA42) | DC42: =+DC41 | DD42: =+DD41 | DE42: =5+88+47 | DF42: =6+99+51 | DG42: =SUM(DC42:DF42) | DH42: =4+114+60 | DI42: =8+145+71 | DJ42: =15+141+67 | DK42: =12+140+68 | DL42: =SUM(DH42:DK42) | DM42: =21+134+69 | DN42: =14+228+132 | DO42: =28+232+123 | DP42: =26+266+125 | DQ42: =SUM(DM42:DP42) | DR42: =25+276+128 | DS42: =32+297+136 | DT42: =44+363+152 | DU42: =39+362+150 | DV42: =SUM(DR42:DU42) | DW42: 578 | DX42: =38+452+159 | DY42: =32+530+183 | DZ42: =30+527+182 | EA42: =SUM(DW42:DZ42) | EB42: =27+524+184 | EC42: =31+600+211 | ED42: =38+701+240 | EE42: =45+706+242 | EF42: =SUM(EB42:EE42) | EG42: =36+727+248 | EH42: =40+832+282 | EI42: =50+910+292 | EJ42: =53+955+313 | EK42: =SUM(EG42:EJ42) | EL42: 1474 | EM42: =1566+58 | EN42: =+Worksheet!CV20+Worksheet!CV29 | EO42: =+Worksheet!CW20+Worksheet!CW29 | EP42: =SUM(EL42:EO42) | EQ42: =+Worksheet!CX20+Worksheet!CX29 | ER42: =+Worksheet!CY20+Worksheet!CY29 | ES42: =+Worksheet!CZ20+Worksheet!CZ29 | ET42: =+Worksheet!DA20+Worksheet!DA29 | EU42: =SUM(EQ42:ET42) | EV42: =+Worksheet!DB20+Worksheet!DB29 | EW42: =+Worksheet!DC20+Worksheet!DC29 | EX42: =+Worksheet!DD20+Worksheet!DD29 | EY42: =+Worksheet!DE20+Worksheet!DE29 | EZ42: =SUM(EV42:EY42)
A44: Net Income - Reported (GAAP) | B44: =B37+B39+B40 | C44: =C37+C39 | D44: =D37+D39+D40 | E44: =E37+E39+E40 | F44: =SUM(B44:E44) | G44: =G37+G39+G40 | H44: =H37+H39+H40 | I44: =I37+I39+I40 | J44: =J37+J39+J40 | K44: =SUM(G44:J44) | L44: =L37+L39+L40 | M44: =M37+M39+M40 | N44: =N37+N39+N40 | O44: =O37+O39+O40 | P44: =SUM(L44:O44) | Q44: =Q37+Q39+Q40 | R44: =R37+R39+R40 | S44: =S37+S39+S40 | T44: =T37+T39+T40 | U44: =SUM(Q44:T44) | V44: =V37+V39+V40 | W44: =W37+W39+W40 | X44: =X37+X39+X40 | Y44: =Y37+Y39+Y40 | Z44: =SUM(V44:Y44) | AA44: =AA37+AA39+AA40 | AB44: =AB37+AB39+AB40 | AC44: =AC37+AC39+AC40 | AD44: =AD37+AD39+AD40 | AE44: =SUM(AA44:AD44) | AF44: =AF37+AF39+AF40 | AG44: =AG37+AG39+AG40 | AH44: =AH37+AH39+AH40 | AI44: =AI37+AI39+AI40 | AJ44: =SUM(AF44:AI44) | AK44: =AK37+AK39 | AL44: =AL37+AL39 | AM44: =AM37+AM39 | AN44: =AN37+AN39 | AO44: =SUM(AK44:AN44) | AP44: =AP37+AP39 | AQ44: =AQ37+AQ39 | AR44: =AR37+AR39 | AS44: =AS37+AS39 | AT44: =SUM(AP44:AS44) | AU44: =AU37+AU39 | AV44: =AV37+AV39 | AW44: =AW37+AW39 | AX44: =AX37+AX39 | AY44: =SUM(AU44:AX44) | AZ44: =AZ37+AZ39 | BA44: =BA37+BA39 | BB44: =BB37+BB39 | BC44: =BC37+BC39 | BD44: =SUM(AZ44:BC44) | BE44: =BE37+BE39 | BF44: =BF37+BF39 | BG44: =BG37+BG39 | BH44: =BH37+BH39 | BI44: =SUM(BE44:BH44) | BJ44: =BJ37+BJ39 | BK44: =BK37+BK39 | BL44: =BL37+BL39 | BM44: =BM37+BM39 | BN44: =SUM(BJ44:BM44) | BO44: =BO37+BO39 | BP44: =BP37+BP39 | BQ44: =BQ37+BQ39 | BR44: =BR37+BR39 | BS44: =SUM(BO44:BR44) | BT44: =BT37+BT39 | BU44: =BU37+BU39 | BV44: =BV37+BV39 | BW44: =BW37+BW39 | BX44: =SUM(BT44:BW44) | BY44: =BY37+BY39 | BZ44: =BZ37+BZ39 | CA44: =CA37+CA39 | CB44: =CB37+CB39 | CC44: =CC37+CC39 | CD44: =CD37+CD39 | CE44: =CE37+CE39 | CF44: =CF37+CF39 | CG44: =CG37+CG39 | CH44: =SUM(CD44:CG44) | CI44: =CI37+CI39 | CJ44: =CJ37+CJ39 | CK44: =CK37+CK39 | CL44: =CL37+CL39 | CM44: =SUM(CI44:CL44) | CN44: =CN37+CN39 | CO44: =CO37+CO39 | CP44: =CP37+CP39 | CQ44: =CQ37+CQ39 | CR44: =SUM(CN44:CQ44) | CS44: =CS37+CS39 | CT44: =CT37+CT39 | CU44: =CU37+CU39 | CV44: =CV37+CV39 | CW44: =SUM(CS44:CV44) | CX44: =CX37+CX39 | CY44: =CY37+CY39 | CZ44: =CZ37+CZ39 | DA44: =DA37+DA39 | DB44: =SUM(CX44:DA44) | DC44: =DC37+DC39 | DD44: =DD37+DD39 | DE44: =DE37+DE39 | DF44: =DF37+DF39 | DG44: =SUM(DC44:DF44) | DH44: =DH37+DH39 | DI44: =DI37+DI39 | DJ44: =DJ37+DJ39 | DK44: =DK37+DK39 | DL44: =SUM(DH44:DK44) | DM44: =DM37+DM39 | DN44: =DN37+DN39 | DO44: =DO37+DO39 | DP44: =DP37+DP39 | DQ44: =SUM(DM44:DP44) | DR44: =DR37+DR39 | DS44: =DS37+DS39 | DT44: =DT37+DT39 | DU44: =DU37+DU39 | DV44: =SUM(DR44:DU44) | DW44: =DW37+DW39 | DX44: =DX37+DX39 | DY44: =DY37+DY39 | DZ44: =DZ37+DZ39 | EA44: =SUM(DW44:DZ44) | EB44: =EB37+EB39 | EC44: =EC37+EC39 | ED44: =ED37+ED39 | EE44: =EE37+EE39 | EF44: =SUM(EB44:EE44) | EG44: =EG37+EG39 | EH44: =EH37+EH39 | EI44: =EI37+EI39 | EJ44: =EJ37+EJ39 | EK44: =SUM(EG44:EJ44) | EL44: =EL37+EL39 | EM44: =EM37+EM39 | EN44: =EN37+EN39 | EO44: =EO37+EO39 | EP44: =SUM(EL44:EO44) | EQ44: =EQ37+EQ39 | ER44: =ER37+ER39 | ES44: =ES37+ES39 | ET44: =ET37+ET39 | EU44: =SUM(EQ44:ET44) | EV44: =EV37+EV39 | EW44: =EW37+EW39 | EX44: =EX37+EX39 | EY44: =EY37+EY39 | EZ44: =SUM(EV44:EY44)
B45: 10
A46: Shares outstanding - basic (GAAP) | B46: 6084.96 | C46: 6084.96 | D46: 6084.96 | E46: 6084.96 | F46: =(AVERAGE(B46:E46)) | G46: 6787.68 | H46: 6791.04 | I46: 13331.52 | J46: 13844.16 | K46: =(AVERAGE(G46:J46)) | L46: 14052.96 | M46: 14085.12 | N46: 14407.2 | O46: 14928 | P46: =(AVERAGE(L46:O46)) | Q46: 15206.28 | R46: 15508.08 | S46: 15840.72 | T46: 16323.84 | U46: =(AVERAGE(Q46:T46)) | V46: 16637.16 | W46: 17025.12 | X46: 17282.04 | Y46: 17704.08 | Z46: =(AVERAGE(V46:Y46)) | AA46: 18082.08 | AB46: 18275.52 | AC46: 18408.96 | AD46: 18921.96 | AE46: =(AVERAGE(AA46:AD46)) | AF46: 19034.64 | AG46: 19209.24 | AH46: 19389.84 | AI46: 19614.72 | AJ46: =(AVERAGE(AF46:AI46)) | AK46: 19820.52 | AL46: 19950.24 | AM46: 19934.64 | AN46: 19999.08 | AO46: 19926.12 | AP46: 20237.64 | AQ46: 20273.16 | AR46: 20415.24 | AS46: 20525.04 | AT46: 20362.77 | AU46: 20876.22 | AV46: 21014.64 | AW46: 21159.42 | AX46: 21526.86 | AY46: 21144.285 | AZ46: 21649.86 | BA46: 21892.2 | BB46: 22198.64 | BC46: 22285.72 | BD46: 22006.605 | BE46: 22226.92 | BF46: 22216.68 | BG46: 21752.28 | BH46: 21503.8 | BI46: 21924.92 | BJ46: 21692.28 | BK46: 21865.56 | BL46: 22051.32 | BM46: 22299.16 | BN46: 21977.08 | BO46: 22687.32 | BP46: 22910.56 | BQ46: 23092.92 | BR46: 23337.56 | BS46: 23007.09 | BT46: 23792.08 | BU46: 24053.6 | BV46: 24282.52 | BW46: 24457.28 | BX46: 24146.37 | BY46: 24631.2 | BZ46: 24759.84 | CA46: 24894.08 | CB46: 24806.76 | CC46: 24772.97 | CD46: 24674.88 | CE46: 23413.8 | CF46: 23234.8 | CG46: 22739.32 | CH46: 23515.7 | CI46: 22363.68 | CJ46: 22328.92 | CK46: 21911.56 | CL46: 21766.8 | CM46: 22092.74 | CN46: 21960 | CO46: 21640 | CP46: 21680 | CQ46: 21560 | CR46: 21710 | CS46: 21480 | CT46: 21360 | CU46: 21520 | CV46: 22120 | CW46: 21620 | CX46: 23680 | CY46: 23880 | CZ46: 24120 | DA46: 24240 | DB46: 23980 | DC46: 24240 | DD46: 24280 | DE46: 24360 | DF46: 24360 | DG46: 24310 | DH46: 24280 | DI46: 24360 | DJ46: 24400 | DK46: 24480 | DL46: 24380 | DM46: 24560 | DN46: 24640 | DO46: 24720 | DP46: 24760 | DQ46: 24670 | DR46: 24840 | DS46: 24930 | DT46: 24990 | DU46: 25040 | DV46: =(AVERAGE(DR46:DU46)) | DW46: 25060 | DX46: 24950 | DY46: 24830 | DZ46: 24640 | EA46: =(AVERAGE(DW46:DZ46)) | EB46: 24700 | EC46: 24730 | ED46: 24680 | EE46: 24660 | EF46: =(AVERAGE(EB46:EE46)) | EG46: 24620 | EH46: 24578 | EI46: 24533 | EJ46: 24489 | EK46: =AVERAGE(EG46:EJ46) | EL46: 24441 | EM46: 24366 | EN46: =EM46+(EN48-EM48) | EO46: =EN46+(EO48-EN48) | EP46: =AVERAGE(EL46:EO46) | EQ46: =EO46+(EQ48-EO48) | ER46: =EQ46+(ER48-EQ48) | ES46: =ER46+(ES48-ER48) | ET46: =ES46+(ET48-ES48) | EU46: =AVERAGE(EQ46:ET46) | EV46: =ET46+(EV48-ET48) | EW46: =EV46+(EW48-EV48) | EX46: =EW46+(EX48-EW48) | EY46: =EX46+(EY48-EX48) | EZ46: =AVERAGE(EV46:EY46)
A47: Dilution impact from convertible note | S47: 19.416 | T47: 19.416 | V47: 19.416 | W47: 19.416 | X47: 19.416 | Y47: 19.416 | AA47: 19.416 | AB47: 19.416 | AC47: 19.416 | AD47: 19.416 | AF47: 19.416 | AG47: 19.416 | CP47: =CP49-CP48 | CQ47: =CQ49-CQ48 | CS47: =CS49-CS48 | CT47: =CT49-CT48 | CU47: =CU49-CU48 | CV47: =CV49-CV48 | CX47: =CX49-CX48 | CY47: =CY49-CY48 | CZ47: =CZ49-CZ48 | DA47: =DA49-DA48 | DD47: =DD49-DD48 | DE47: 0 | DF47: =DE47 | DH47: =DF47 | DI47: =DH47 | DJ47: =DI47 | DK47: =DJ47 | DM47: =DK47 | DN47: =DM47 | DO47: =DN47 | DP47: =DO47 | DR47: =DP47 | DS47: =DR47 | DT47: =DS47 | DU47: =DT47 | DW47: =DU47 | DX47: =DW47 | DY47: =DX47 | DZ47: =DY47 | EB47: =EA47 | EC47: =EB47 | ED47: =EC47 | EE47: =ED47 | EG47: =EF47 | EH47: =EG47 | EI47: =EH47 | EJ47: =EI47 | EL47: =EK47 | EM47: =EL47 | EN47: =EM47 | EO47: =EN47 | EQ47: =EO47 | ER47: =EQ47 | ES47: =ER47 | ET47: =ES47 | EV47: =ET47 | EW47: =EV47 | EX47: =EW47 | EY47: =EX47
A48: Shares outstanding - diluted (non-GAAP) | B48: 6084.96 | C48: 6084.96 | D48: 6084.96 | E48: 6084.96 | F48: 6084.96 | G48: 6787.68 | H48: 6791.04 | I48: 13331.52 | J48: 13844.16 | K48: 10188.6 | L48: 17017.92 | M48: 17018.4 | N48: 17246.88 | O48: 18024.48 | P48: 17326.92 | Q48: 18666.72 | R48: 19076.88 | S48: 19304.4 | T48: 19412.64 | U48: 19115.16 | V48: 19885.32 | W48: 20436.24 | X48: 20419.08 | Y48: 21267.6 | Z48: 20502.06 | AA48: 39213.24 | AB48: 20252.4 | AC48: 36817.92 | AD48: 20102.04 | AE48: 29096.4 | AF48: 20151 | AG48: 20946.12 | AH48: 20777.88 | AI48: 21174.84 | AJ48: 20762.46 | AK48: 21417.48 | AL48: 21290.28 | AM48: 20744.28 | AN48: 21270.84 | AO48: 21180.72 | AP48: 21659.04 | AQ48: 21694.8 | AR48: 22022.04 | AS48: 22334.64 | AT48: 21927.63 | AU48: 23365.68 | AV48: 23135.34 | AW48: 23472.9 | AX48: 23939.64 | AY48: 23478.39 | AZ48: 23931.96 | BA48: 24153.18 | BB48: 24519.4 | BC48: 24366.92 | BD48: 24242.865 | BE48: 23679.56 | BF48: 23179.8 | BG48: 22581.44 | BH48: 21503.8 | BI48: 22736.15 | BJ48: 21692.28 | BK48: 22505.4 | BL48: 22975.24 | BM48: 23283.24 | BN48: 22614.04 | BO48: 23639.88 | BP48: 23295.32 | BQ48: 23305.92 | BR48: 24062.36 | BS48: 23575.87 | BT48: 24538.96 | BU48: 24557.36 | BV48: 24542.4 | BW48: 24743.96 | BX48: 24595.67 | BY48: 24951.44 | BZ48: 24925.72 | CA48: 25153.8 | CB48: 24880.72 | CC48: 24977.92 | CD48: 24772.08 | CE48: 23680.24 | CF48: 23550.08 | CG48: 23094.24 | CH48: 23774.16 | CI48: 22816.88 | CJ48: 22822.88 | CK48: 22328.04 | CL48: 22262.92 | CM48: 22557.68 | CN48: 22480 | CO48: 22080 | CP48: 22200 | CQ48: 22680 | CR48: 22360 | CS48: 22720 | CT48: 23640 | CU48: 24320 | CV48: 24960 | CW48: 23910 | CX48: 25080 | CY48: 25160 | CZ48: 25040 | DA48: 25080 | DB48: 25090 | DC48: 25080 | DD48: 25000 | DE48: 25000 | DF48: 24760 | DG48: 24960 | DH48: 24640 | DI48: 24640 | DJ48: 24720 | DK48: 24840 | DL48: 24710 | DM48: 24880 | DN48: 25040 | DO48: 25200 | DP48: 25240 | DQ48: 25090 | DR48: 25280 | DS48: 25320 | DT48: 25380 | DU48: 25450 | DV48: =(DV37/DV54) | DW48: 25370 | DX48: 25160 | DY48: 24990 | DZ48: 24770 | EA48: =(EA37/EA54) | EB48: 24900 | EC48: 24990 | ED48: 24940 | EE48: 24900 | EF48: =(AVERAGE(EB48:EE48)) | EG48: 24890 | EH48: 24848 | EI48: 24774 | EJ48: 24706 | EK48: =EK37/EK54 | EL48: 24611 | EM48: 24532 | EN48: =EM$48-(-(EN$143+EN$144)/$FB$48)+(EN42/$FB$48) | EO48: =EN$48-(-(EO$143+EO$144)/$FB$48)+(EO42/$FB$48) | EP48: =EP37/EP54 | EQ48: =EO$48-(-(EQ$143+EQ$144)/$FB$48)+(EQ42/$FB$48) | ER48: =EQ$48-(-(ER$143+ER$144)/$FB$48)+(ER42/$FB$48) | ES48: =ER$48-(-(ES$143+ES$144)/$FB$48)+(ES42/$FB$48) | ET48: =ES$48-(-(ET$143+ET$144)/$FB$48)+(ET42/$FB$48) | EU48: =EU37/EU54 | EV48: =ET$48-(-(EV$143+EV$144)/$FB$48)+(EV42/$FB$48) | EW48: =EV$48-(-(EW$143+EW$144)/$FB$48)+(EW42/$FB$48) | EX48: =EW$48-(-(EX$143+EX$144)/$FB$48)+(EX42/$FB$48) | EY48: =EX$48-(-(EY$143+EY$144)/$FB$48)+(EY42/$FB$48) | EZ48: =EZ37/EZ54 | FB48: 170
A49: Shares outstanding - diluted (GAAP) | B49: 0 | C49: 0 | D49: 0 | E49: 0 | F49: 0 | G49: 0 | H49: 0 | I49: 0 | J49: 0 | K49: 0 | L49: 0 | M49: 0 | N49: 0 | O49: 0 | P49: 0 | Q49: 0 | R49: 0 | S49: 0 | T49: 0 | U49: 0 | V49: 0 | W49: 0 | X49: 0 | Y49: 0 | Z49: 0 | AA49: 0 | AB49: 0 | AC49: 0 | AD49: 0 | AE49: 0 | AF49: 0 | AG49: 0 | AH49: 0 | AI49: 0 | AJ49: 0 | AK49: 0 | AL49: 0 | AM49: 0 | AN49: 0 | AO49: 0 | AP49: 0 | AQ49: 0 | AR49: 0 | AS49: 0 | AT49: 0 | AU49: 0 | AV49: 0 | AW49: 0 | AX49: 0 | AY49: 0 | AZ49: 0 | BA49: 0 | BB49: 0 | BC49: 0 | BD49: 0 | BE49: 0 | BF49: 0 | BG49: 0 | BH49: 0 | BI49: 0 | BJ49: 0 | BK49: 0 | BL49: 0 | BM49: 0 | BN49: 0 | BO49: 0 | BP49: 0 | BQ49: 0 | BR49: 0 | BS49: 0 | BT49: 0 | BU49: 0 | BV49: 0 | BW49: 0 | BX49: 0 | BY49: 0 | BZ49: 0 | CA49: 0 | CB49: 0 | CC49: 0 | CD49: 0 | CE49: 0 | CF49: 0 | CG49: 0 | CH49: 0 | CI49: 0 | CJ49: 0 | CK49: 0 | CL49: 0 | CM49: 0 | CN49: 0 | CO49: 0 | CP49: 22600 | CQ49: 23720 | CR49: =CR48 | CS49: 23880 | CT49: 25360 | CU49: 26120 | CV49: 26400 | CW49: =CW48 | CX49: 25640 | CY49: 25320 | CZ49: 25120 | DA49: 25120 | DB49: =DB48 | DC49: 25040 | DD49: 25040 | DE49: 25000 | DF49: 24760 | DG49: =DG48 | DH49: 24640 | DI49: 24640 | DJ49: 24720 | DK49: 24840 | DL49: =DL48 | DM49: 24880 | DN49: 25040 | DO49: 25200 | DP49: 25240 | DQ49: =DQ48 | DR49: 25280 | DS49: 25320 | DT49: 25380 | DU49: 25450 | DV49: =(DV48) | DW49: 25370 | DX49: 25160 | DY49: 24990 | DZ49: 24770 | EA49: =(EA48) | EB49: 24900 | EC49: 24990 | ED49: 24940 | EE49: 24900 | EF49: =(AVERAGE(EB49:EE49)) | EG49: 24890 | EH49: 24848 | EI49: 24774 | EJ49: 24706 | EK49: =EK48 | EL49: 24611 | EM49: 24532 | EN49: =EN48+EN47 | EO49: =EO48+EO47 | EP49: =EP48 | EQ49: =EQ48+EQ47 | ER49: =ER48+ER47 | ES49: =ES48+ES47 | ET49: =ET48+ET47 | EU49: =EU48 | EV49: =EV48+EV47 | EW49: =EW48+EW47 | EX49: =EX48+EX47 | EY49: =EY48+EY47 | EZ49: =EZ48
EA50: =(EA37+EA42)/EA48
A51: Diluted EPS - Recurring (as if convertible not exercised) | B51: =B37/B48 | C51: =C37/C48 | D51: =D37/D48 | E51: =E37/E48 | G51: =G37/G48 | H51: =H37/H48 | I51: =I37/I48 | J51: =J37/J48 | L51: =L37/L48 | M51: =M37/M48 | N51: =N37/N48 | O51: =O37/O48 | Q51: =Q37/Q48 | R51: =R37/R48 | S51: =S37/S48 | T51: =T37/T48 | V51: =V37/V48 | W51: =W37/W48 | X51: =X37/X48 | Y51: =Y37/Y48 | AA51: =AA37/AA48 | AB51: =AB37/AB48 | AC51: =AC37/AC48 | AD51: =AD37/AD48 | AF51: =AF37/AF48 | AG51: =AG37/AG48
A52: Diluted EPS - Recurring (as if convertible is exercised) | B52: =#REF!/#REF! | C52: =#REF!/#REF! | D52: =#REF!/#REF! | E52: =#REF!/#REF! | G52: =#REF!/#REF! | H52: =#REF!/#REF! | I52: =#REF!/#REF! | J52: =#REF!/#REF! | L52: =#REF!/#REF! | M52: =#REF!/#REF! | N52: =#REF!/#REF! | O52: =#REF!/#REF! | Q52: =#REF!/#REF! | R52: =#REF!/#REF! | S52: =#REF!/#REF! | T52: =#REF!/#REF! | V52: =#REF!/#REF! | W52: =#REF!/#REF! | X52: =#REF!/#REF! | Y52: =#REF!/#REF! | AA52: =#REF!/#REF! | AB52: =#REF!/#REF! | AC52: =#REF!/#REF! | AD52: =#REF!/AD48 | AF52: =#REF!/AF48 | AG52: =#REF!/AG48
A53: Diluted EPS - Recurring (excl ESOs - Non-GAAP) | B53: -0.0077305356 | C53: -0.0083155847 | D53: -0.01690726 | E53: 0.0093607846 | F53: =(F37+F42)/F48 | G53: -0.0060167833 | H53: -0.056851381 | I53: 0.021425914 | J53: 0.022137855 | K53: =(K37+K42)/K48 | L53: 0.014716252 | M53: 0.016633761 | N53: 0.030217639 | O53: 0.032382626 | P53: =(P37+P42)/P48 | Q53: 0.031489196 | R53: 0.049561564 | S53: 0.058163029 | T53: 0.065559347 | U53: =(U37+U42)/U48 | V53: 0.067841201 | W53: 0.071674633 | X53: 0.094497891 | Y53: 0.14448382 | Z53: =(Z37+Z42)/Z48 | AA53: 0.084915197 | AB53: 0.039410638 | AC53: 0.010035548 | AD53: =MIN(AD51:AD52) | AE53: =(AE37+AE42)/AE48 | AF53: =MIN(AF51:AF52) | AG53: =MIN(AG51:AG52) | AH53: =AH37/AH48 | AI53: =AI37/AI48 | AJ53: =(AJ37+AJ42)/AJ48 | AK53: =AK37/AK48 | AL53: =AL37/AL48 | AM53: =AM37/AM48 | AN53: =AN37/AN48 | AO53: =(AO37+AO42)/AO48 | AP53: =AP37/AP48 | AQ53: =AQ37/AQ48 | AR53: =AR37/AR48 | AS53: =AS37/AS48 | AT53: =(AT37+AT42)/AT48 | AU53: =(AU37+AU42)/AU48 | AV53: =(AV37+AV42)/AV48 | AW53: =(AW37+AW42)/(384.826*1.5) | AX53: =(AX37+AX42)/(391.514*1.5) | AY53: =(AY37+AY42)/AY48 | AZ53: =(AZ37+AZ42)/(387.397*1.5) | BA53: =(BA37+BA42)/(392.165*1.5) | BB53: =(BB37+BB42)/595.058 | BC53: =(BC37+BC42)/593.336 | BD53: =(BD37+BD42)/BD48 | BE53: =(BE37+BE42)/BE48 | BF53: =(BF37+BF42)/BF48 | BG53: =(BG37+BG42)/BG48 | BH53: =(BH37+BH42)/BH48 | BI53: =(BI37+BI42)/BI48 | BJ53: =(BJ37+BJ42)/BJ48 | BK53: =(BK37+BK42)/BK48 | ... DA53: =(DA37+DA42)/DA48 | DB53: =SUM(CX53:DA53) | DC53: =(DC37+DC42)/DC48 | DD53: =(DD37+DD42)/DD48 | DE53: =(DE37+DE42)/DE48 | DF53: =(DF37+DF42)/DF48 | DG53: =SUM(DC53:DF53) | DH53: =(DH37+DH42)/DH48 | DI53: =(DI37+DI42)/DI48 | DJ53: =(DJ37+DJ42)/DJ48 | DK53: =(DK37+DK42)/DK48 | DL53: =SUM(DH53:DK53) | DM53: =(DM37+DM42)/DM48 | DN53: =(DN37+DN42)/DN48 | DO53: =(DO37+DO42)/DO48 | DP53: =(DP37+DP42)/DP48 | DQ53: =SUM(DM53:DP53) | DR53: =(DR37+DR42)/DR48 | DS53: =(DS37+DS42)/DS48 | DT53: =(DT37+DT42)/DT48 | DU53: =(DU37+DU42)/DU48 | DV53: =SUM(DR53:DU53) | DW53: =(DW37+DW42)/DW48 | DX53: =(DX37+DX42)/DX48 | DY53: =(DY37+DY42)/DY48 | DZ53: =(DZ37+DZ42)/DZ48 | EA53: =SUM(DW53:DZ53) | EB53: =(EB37+EB42)/EB48 | EC53: =(EC37+EC42)/EC48 | ED53: =(ED37+ED42)/ED48 | EE53: =(EE37+EE42)/EE48 | EF53: =SUM(EB53:EE53) | EG53: =(EG37+EG42)/EG48 | EH53: =(EH37+EH42)/EH48 | EI53: =(EI37+EI42)/EI48 | EJ53: =(EJ37+EJ42)/EJ48 | EK53: =SUM(EG53:EJ53) | EL53: =(EL37+EL42)/EL48 | EM53: =(EM37+EM42)/EM48 | EN53: =(EN37+EN42)/EN48 | EO53: =(EO37+EO42)/EO48 | EP53: =SUM(EL53:EO53) | EQ53: =(EQ37+EQ42)/EQ48 | ER53: =(ER37+ER42)/ER48 | ES53: =(ES37+ES42)/ES48 | ET53: =(ET37+ET42)/ET48 | EU53: =SUM(EQ53:ET53) | EV53: =(EV37+EV42)/EV48 | EW53: =(EW37+EW42)/EW48 | EX53: =(EX37+EX42)/EX48 | EY53: =(EY37+EY42)/EY48 | EZ53: =SUM(EV53:EY53)
A54: Diluted EPS - Recurring (incl ESO) | B54: =(B37-B42)/B48 | C54: =(C37-C42)/C48 | D54: =(D37-D42)/D48 | E54: =(E37-E42)/E48 | F54: =(F37/F48) | G54: =(G37-G42)/G48 | H54: =(H37-H42)/H48 | I54: =(I37-I42)/I48 | J54: =(J37-J42)/J48 | K54: =(K37/K48) | L54: =(L37-L42)/L48 | M54: =(M37-M42)/M48 | N54: =(N37-N42)/N48 | O54: =(O37-O42)/O48 | P54: =(P37/P48) | Q54: =(Q37-Q42)/Q48 | R54: =(R37-R42)/R48 | S54: =(S37-S42)/S48 | T54: =(T37-T42)/T48 | U54: =(U37/U48) | V54: =(V37-V42)/V48 | W54: =(W37-W42)/W48 | X54: =(X37-X42)/X48 | Y54: =(Y37-Y42)/Y48 | Z54: =(Z37/Z48) | AA54: =(AA37-AA42)/AA48 | AB54: =(AB37-AB42)/AB48 | AC54: =(AC37-AC42)/AC48 | AD54: =(AD37-AD42)/AD48 | AE54: =(AE37/AE48) | AF54: =(AF37-AF42)/AF48 | AG54: =(AG37-AG42)/AG48 | AH54: =(AH37-AH42)/AH48 | AI54: =(AI37-AI42)/AI48 | AJ54: =(AJ37/AJ48) | AK54: =(AK37-AK42)/AK48 | AL54: =(AL37-AL42)/AL48 | AM54: =(AM37-AM42)/AM48 | AN54: =(AN37-AN42)/AN48 | AO54: =(AO37/AO48) | AP54: =(AP37-AP42)/AP48 | AQ54: =(AQ37-AQ42)/AQ48 | AR54: =(AR37-AR42)/AR48 | AS54: =(AS37-AS42)/AS48 | AT54: =(AT37/AT48) | AU54: =(AU37/AU48) | AV54: =(AV37/AV48) | AW54: =(AW37/AW48) | AX54: =(AX37/AX48) | AY54: =(AY37/AY48) | AZ54: =(AZ37/AZ48) | BA54: =(BA37/BA48) | ... CG54: =(CG37/CG48) | CH54: =SUM(CD54:CG54) | CI54: =(CI37/CI48) | CJ54: =(CJ37/CJ48) | CK54: =(CK37/CK48) | CL54: =(CL37/CL48) | CM54: =SUM(CI54:CL54) | CN54: =(CN37/CN48) | CO54: =(CO37/CO48) | CP54: =(CP37/CP48) | CQ54: =(CQ37/CQ48) | CR54: =SUM(CN54:CQ54) | CS54: =(CS37/CS48) | CT54: =(CT37/CT48) | CU54: =(CU37/CU48) | CV54: =(CV37/CV48) | CW54: =SUM(CS54:CV54) | CX54: =(CX37/CX48) | CY54: =(CY37/CY48) | CZ54: =(CZ37/CZ48) | DA54: =(DA37/DA48) | DB54: =SUM(CX54:DA54) | DC54: =(DC37/DC48) | DD54: =(DD37/DD48) | DE54: =(DE37/DE48) | DF54: =(DF37/DF48) | DG54: =SUM(DC54:DF54) | DH54: =(DH37/DH48) | DI54: =(DI37/DI48) | DJ54: =(DJ37/DJ48) | DK54: =(DK37/DK48) | DL54: =SUM(DH54:DK54) | DM54: =(DM37/DM48) | DN54: =(DN37/DN48) | DO54: =(DO37/DO48) | DP54: =(DP37/DP48) | DQ54: =SUM(DM54:DP54) | DR54: =(DR37/DR48) | DS54: =(DS37/DS48) | DT54: =(DT37/DT48) | DU54: =(DU37/DU48) | DV54: =SUM(DR54:DU54) | DW54: =(DW37/DW48) | DX54: =(DX37/DX48) | DY54: =(DY37/DY48) | DZ54: =(DZ37/DZ48) | EA54: =SUM(DW54:DZ54) | EB54: =(EB37/EB48) | EC54: =(EC37/EC48) | ED54: =(ED37/ED48) | EE54: =(EE37/EE48) | EF54: =SUM(EB54:EE54) | EG54: =(EG37/EG48) | EH54: =(EH37/EH48) | EI54: =(EI37/EI48) | EJ54: =(EJ37/EJ48) | EK54: =SUM(EG54:EJ54) | EL54: =(EL37/EL48) | EM54: =(EM37/EM48) | EN54: =(EN37/EN48) | EO54: =(EO37/EO48) | EP54: =SUM(EL54:EO54) | EQ54: =(EQ37/EQ48) | ER54: =(ER37/ER48) | ES54: =(ES37/ES48) | ET54: =(ET37/ET48) | EU54: =SUM(EQ54:ET54) | EV54: =(EV37/EV48) | EW54: =(EW37/EW48) | EX54: =(EX37/EX48) | EY54: =(EY37/EY48) | EZ54: =SUM(EV54:EY54)
A56: EBITDA | B56: =B22+B11 | C56: =C22+C11 | D56: =D22+D11 | E56: =E22+E11 | F56: =F22+F11 | G56: =G22+G11 | H56: =H22+H11 | I56: =I22+I11 | ... EZ56: =EZ22+EZ11
A57: Dividend per share | F57: =SUM(B57:E57) | K57: =SUM(G57:J57) | P57: =SUM(L57:O57) | U57: =SUM(Q57:T57) | Z57: =SUM(V57:Y57) | AE57: =SUM(AA57:AD57) | AJ57: =SUM(AF57:AI57) | AO57: =SUM(AK57:AN57) | AT57: =SUM(AP57:AS57) | AY57: =SUM(AU57:AX57) | BD57: =SUM(AZ57:BC57) | BI57: =SUM(BE57:BH57) | BN57: =SUM(BJ57:BM57) | BS57: =SUM(BO57:BR57) | BX57: =SUM(BT57:BW57) | CB57: 0.001875 | CC57: =SUM(BY57:CB57) | CD57: 0.001875 | CE57: 0.001875 | CF57: 0.001875 | CG57: 0.002125 | CH57: =SUM(CD57:CG57) | CI57: 0.002125 | CJ57: 0.002125 | CK57: 0.002125 | CL57: 0.002125 | CM57: =SUM(CI57:CL57) | CN57: 0.002125 | CO57: 0.0024375 | CP57: 0.0024375 | CQ57: 0.002875 | CR57: =SUM(CN57:CQ57) | CS57: 0.002875 | CT57: 0.002875 | CU57: 0.002875 | CV57: 0.0035 | CW57: =SUM(CS57:CV57) | CX57: 0.0035 | CY57: 0.0035 | CZ57: 0.0035 | DA57: 0.00375 | DB57: =SUM(CX57:DA57) | DC57: 0.00375 | DD57: 0.00375 | DE57: 0.00375 | DF57: 0.004 | DG57: =SUM(DC57:DF57) | DH57: 0.004 | DI57: 0.004 | DJ57: 0.004 | DK57: 0.004 | DL57: =SUM(DH57:DK57) | DM57: 0.004 | DN57: 0.004 | DO57: 0.004 | DP57: 0.004 | DQ57: =SUM(DM57:DP57) | DR57: 0.004 | DS57: 0.004 | DT57: 0.004 | DU57: 0.004 | DV57: =SUM(DR57:DU57) | DW57: 0.004 | DX57: 0.004 | DY57: 0.004 | DZ57: 0.004 | EA57: =SUM(DW57:DZ57) | EB57: 0.004 | EC57: 0.004 | ED57: 0.004 | EE57: 0.004 | EF57: =SUM(EB57:EE57) | EG57: 0.004 | EH57: 0.01 | EI57: 0.01 | EJ57: 0.01 | EK57: =SUM(EG57:EJ57) | EL57: 0.01 | EM57: 0.01 | EN57: =EM57 | EO57: =EN57 | EP57: =SUM(EL57:EO57) | EQ57: =EO57 | ER57: =EQ57 | ES57: =ER57 | ET57: =ES57 | EU57: =SUM(EQ57:ET57) | EV57: =ET57 | EW57: =EV57 | EX57: =EW57 | EY57: =EX57 | EZ57: =SUM(EV57:EY57)
A58: GAAP Diluted EPS | F58: =+F44/F48 | K58: =+K44/K48 | P58: =+P44/P48 | U58: =+U44/U48 | Z58: =+Z44/Z48 | AE58: =+AE44/AE48 | AF58: =+AF44/AF48 | AG58: =+AG44/AG48 | AH58: =+AH44/AH48 | AI58: =+AI44/AI48 | AJ58: =+AJ44/AJ48 | AK58: =+AK44/AK48 | AL58: =+AL44/AL48 | ... CM58: =+CM44/CM48 | CN58: =+CN44/(CN48+CN47) | CO58: =+CO44/(CO48+CO47) | CP58: =+CP44/(CP48+CP47) | CQ58: =+CQ44/(CQ48+CQ47) | CR58: =+CR$44/CR$48 | CS58: =+CS44/(CS48+CS47) | CT58: =+CT44/(CT48+CT47) | CU58: =+CU44/(CU48+CU47) | CV58: =+CV44/(CV48+CV47) | CW58: =+CW44/CW48 | CX58: =+CX44/(CX48+CX47) | CY58: =+CY44/(CY48+CY47) | CZ58: =+CZ44/(CZ48+CZ47) | DA58: =+DA44/(DA48+DA47) | DB58: =+DB44/DB48 | DC58: =+DC44/(DC48+DC47) | DD58: =+DD44/(DD48+DD47) | DE58: =+DE44/(DE48+DE47) | DF58: =+DF44/(DF48+DF47) | DG58: =+DG44/DG48 | DH58: =+DH44/(DH48+DH47) | DI58: =+DI44/(DI48+DI47) | DJ58: =+DJ44/(DJ48+DJ47) | DK58: =+DK44/(DK48+DK47) | DL58: =+DL44/DL48 | DM58: =+DM44/(DM48+DM47) | DN58: =+DN44/(DN48+DN47) | DO58: =+DO44/(DO48+DO47) | DP58: =+DP44/(DP48+DP47) | DQ58: =+DQ44/DQ48 | DR58: =+DR44/(DR48+DR47) | DS58: =+DS44/(DS48+DS47) | DT58: =+DT44/(DT48+DT47) | DU58: =+DU44/(DU48+DU47) | DV58: =+DV44/DV48 | DW58: =+DW44/(DW48+DW47) | DX58: =+DX44/(DX48+DX47) | DY58: =+DY44/(DY48+DY47) | DZ58: =+DZ44/(DZ48+DZ47) | EA58: =+EA44/EA48 | EB58: =+EB44/(EB48+EB47) | EC58: =+EC44/(EC48+EC47) | ED58: =+ED44/(ED48+ED47) | EE58: =+EE44/(EE48+EE47) | EF58: =+EF44/EF48 | EG58: =+EG44/(EG48+EG47) | EH58: =+EH44/(EH48+EH47) | EI58: =+EI44/(EI48+EI47) | EJ58: =+EJ44/(EJ48+EJ47) | EK58: =+EK44/EK48 | EL58: =+EL44/(EL48+EL47) | EM58: =+EM44/(EM48+EM47) | EN58: =+EN44/(EN48+EN47) | EO58: =+EO44/(EO48+EO47) | EP58: =+EP44/EP48 | EQ58: =+EQ44/(EQ48+EQ47) | ER58: =+ER44/(ER48+ER47) | ES58: =+ES44/(ES48+ES47) | ET58: =+ET44/(ET48+ET47) | EU58: =+EU44/EU48 | EV58: =+EV44/(EV48+EV47) | EW58: =+EW44/(EW48+EW47) | EX58: =+EX44/(EX48+EX47) | EY58: =+EY44/(EY48+EY47) | EZ58: =+EZ44/EZ48
A60: Company1953 Balance Sheet
A62: Cash and Equivalents | L62: 51.823 | M62: 46.757 | N62: 55.2 | O62: 61.56 | P62: =O62 | Q62: 269.8 | R62: 289.205 | S62: 694.883 | T62: 674.275 | U62: =T62 | V62: 627.301 | W62: 681.078 | X62: 398.491 | Y62: 333 | Z62: =Y62 | AA62: 307.151 | AB62: 246.816 | AC62: 322.535 | AD62: 346.994 | AE62: =AD62 | AF62: 278.796 | AG62: 274.297 | AH62: 231.813 | AI62: 214.422 | AJ62: =AI62 | AK62: 196.675 | AL62: 180.579 | AM62: 156.687 | AN62: 208.512 | AO62: =AN62 | AP62: 281.004 | AQ62: 242.17 | AR62: =786.178-AR64 | AS62: 551.756 | AT62: =AS62 | AU62: 487.763 | AV62: 388.423 | AW62: 741.746 | AX62: 544.414 | AY62: =AX62 | AZ62: 678.951 | BA62: 914.745 | BB62: 1056.702 | BC62: =1809.478-BC64 | BD62: =BC62 | BE62: 803.308 | BF62: =1657.23-BF64 | BG62: 461.253 | BH62: 417.688 | BI62: =BH62 | BJ62: 512.274 | BK62: 523.785 | BL62: =1634.079-BL64 | BM62: 447.221 | BN62: =BM62 | BO62: 447.262 | BP62: 377.003 | BQ62: =1987.22-BQ64 | BR62: 665.361 | BS62: =BR62 | BT62: 683.633 | BU62: 532.614 | BV62: 566.816 | BW62: =3129.576-BW64 | BX62: =BW62 | BY62: 369.135 | BZ62: 499.618 | CA62: 525.388 | CB62: 732.786 | CC62: =CB62 | CD62: 561.423 | CE62: 591.321 | CF62: 562.084 | CG62: 1151.587 | CH62: =CG62 | CI62: 509.165 | CJ62: 515.092 | CK62: =CJ62+CK152 | CL62: =CK62+CL152 | CM62: =CL62 | CN62: =CL62+CN152 | CO62: =CN62+CO152 | CP62: =CO62+CP152 | CQ62: =CP62+CQ152 | CR62: =CQ62 | CS62: =CQ62+CS152 | CT62: =CS62+CT152 | CU62: =CT62+CU152 | CV62: =CU62+CV152 | CW62: =CV62 | CX62: =CV62+CX152 | CY62: =CX62+CY152 | CZ62: =CY62+CZ152 | DA62: =CZ62+DA152 | DB62: =DA62 | DC62: =DA62+DC152 | DD62: =DC62+DD152 | DE62: =DD62+DE152 | DF62: =DE62+DF152 | DG62: =DF62 | DH62: =DF62+DH152 | DI62: =DH62+DI152 | DJ62: =DI62+DJ152 | DK62: 10897 | DL62: =DK62 | DM62: 15495 | DN62: 3275 | DO62: 2252 | DP62: 848 | DQ62: =DP62 | DR62: 979 | DS62: 5629 | DT62: 1289 | DU62: 1991 | DV62: =DU62 | DW62: =3887+1 | DX62: 3014 | DY62: 2801 | DZ62: 3390 | EA62: =DZ62 | EB62: 5080 | EC62: 5883 | ED62: 5520 | EE62: 7281 | EF62: =EE62 | EG62: =7281+307 | EH62: =7281+307+984 | EI62: 9108 | EJ62: 8589 | EK62: =EJ62 | EL62: 15234 | EM62: =15234-3595 | EN62: =EM62+EN152 | EO62: =EN62+EO152 | EP62: =EO62 | EQ62: =EO62+EQ152 | ER62: =EQ62+ER152 | ES62: =ER62+ES152 | ET62: =ES62+ET152 | EU62: =ET62 | EV62: =ET62+EV152 | EW62: =EV62+EW152 | EX62: =EW62+EX152 | EY62: =EX62+EY152 | EZ62: =EY62
A63: Restricted Cash | P63: =O63 | T63: 24.5 | U63: =T63 | V63: 28.05 | W63: 28.05 | X63: 7.05 | Y63: 7 | Z63: =Y63 | AA63: 7 | AB63: 0 | AC63: 0 | AD63: 0 | AE63: =AD63 | AF63: 0 | AG63: 0 | AH63: 0 | AI63: 0 | AJ63: =AI63 | AK63: 0 | AL63: 0 | AM63: 0 | AN63: 0 | AO63: =AN63 | AP63: 0 | AQ63: 0 | AR63: 0 | AS63: 0 | AT63: =AS63 | AU63: =AS63 | AV63: =AU63 | AW63: 0 | AX63: =AW63 | AY63: =AX63 | AZ63: =AX63 | BA63: =AZ63 | BB63: =BA63 | BC63: =BB63 | BD63: =BC63 | BE63: =BC63 | BF63: =BE63 | BG63: 0 | BH63: =BG63 | BI63: =BH63 | BJ63: =BH63 | BK63: =BJ63 | BL63: 0 | BM63: =BL63 | BN63: =BM63 | BO63: =BM63 | BP63: =BO63 | BQ63: 0 | BR63: =BQ63 | BS63: =BR63 | BT63: =BR63 | BU63: =BT63 | BV63: 0 | BW63: =BV63 | BX63: =BW63 | BY63: =BW63 | BZ63: =BY63 | CA63: 0 | CB63: =CA63 | CC63: =CB63 | CD63: =CB63 | CE63: 0 | CF63: 0 | CG63: =CF63 | CH63: =CG63 | CI63: =CG63 | CJ63: =CI63 | CK63: =CJ63 | CL63: =CK63 | CM63: =CL63 | CN63: =CL63 | CO63: =CN63 | CP63: =CO63 | CQ63: =CP63 | CR63: =CQ63 | CS63: =CQ63 | CT63: =CS63 | CU63: =CT63 | CV63: =CU63 | CW63: =CV63 | CX63: =CV63 | CY63: =CX63 | CZ63: =CY63 | DA63: =CZ63 | DB63: =DA63 | DC63: =DA63 | DD63: =DC63 | DE63: 0 | DF63: 0 | DG63: =DF63 | DH63: 0 | DI63: 0 | DJ63: 0 | DK63: =DJ63 | DL63: =DK63 | DM63: =DK63 | DN63: =DM63 | DO63: =DN63 | DP63: =DO63 | DQ63: =DP63 | DR63: =DP63 | DS63: =DR63 | DT63: =DS63 | DU63: =DT63 | DV63: =DU63 | DW63: =DU63 | DX63: =DW63 | DY63: =DX63 | DZ63: =DY63 | EA63: =DZ63 | EB63: =EA63 | EC63: =EB63 | ED63: =EC63 | EE63: =ED63 | ... EP63: =EO63 | EQ63: =EO63 | ER63: =EQ63 | ES63: =ER63 | ET63: =ES63 | EU63: =ET63 | EV63: =ET63 | EW63: =EV63 | EX63: =EW63 | EY63: =EX63 | EZ63: =EY63
