Workbook
Name Scenarios: Formulas!$C$4:$C$6

Sheet Profile
A1: © Person0811. All rights reserved.
A2: MENU | B2: Advanced Financial Projection & Analysis Model
C3: This advanced financial model offers up to 10 years of projections, providing detailed insights for strategic planning. The template includes: - A scenario-based approach - 3-Statement financial model for the first year - Up to 10-year forecast analysis - Budget vs. actual variance analysis - Breakeven analysis - Financial ratios and business valuation - Professional chart presentations
C4: Table of Contents | E4: Profile
C5: Summary | E5: Business Type | F5: Financial
C6: Valuation | E6: Company Name | F6: Person0811
C7: Dashboard | E7: Country | F7: Switzerland
C8: Revenue | E8: Financial Year | F8: 2025
C9: Scenario | E9: Periods | F9: 10
C10: Actual Financial Statement | E10: Currency | F10: USD
C11: 12-Month Projection
C12: Variance Analysis
C13: Annual Forecast
C14: Breakeven Analysis | E14: Note:
C15: Ratio Analysis | E15: data | F15: input data only in blue cells like this

Sheet Summary
A1: © Person0811. All rights reserved.
A2: MENU | B2: =Profile!F6 -> Person0811
C4: Executive Summary
C5: =Formulas!A3 -> Amounts in USD
C6: Case Scenario | D6: =Scenario!E6 -> Base Case
C7: Key Financials | E7: =Profile!F8 -> 2025 | F7: =Formulas!D9 -> 2026 | G7: =Formulas!E9 -> 2027 | H7: =Formulas!F9 -> 2028 | I7: =Formulas!G9 -> 2029 | J7: =Formulas!H9 -> 2030 | K7: =Formulas!I9 -> 2031 | L7: =Formulas!J9 -> 2032 | M7: =Formulas!K9 -> 2033 | N7: =Formulas!L9 -> 2034
C9: Revenue | E9: ='Annual Forecast'!H10 -> 444500 | F9: ='Annual Forecast'!I10 -> 471170 | G9: ='Annual Forecast'!J10 -> 494728.5 | H9: ='Annual Forecast'!K10 -> 514517.64 | I9: ='Annual Forecast'!L10 -> 529953.17 | J9: ='Annual Forecast'!M10 -> 545851.76 | K9: ='Annual Forecast'!N10 -> 556768.8 | L9: ='Annual Forecast'!O10 -> 567904.18 | ... N9: ='Annual Forecast'!Q10 -> 590847.5
C10: Gross Profit | E10: ='Annual Forecast'!H18 -> 211137.5 | F10: ='Annual Forecast'!I18 -> 181400.45 | G10: ='Annual Forecast'!J18 -> 200365.04 | H10: ='Annual Forecast'!K18 -> 218670 | I10: ='Annual Forecast'!L18 -> 227879.86 | J10: ='Annual Forecast'!M18 -> 245633.29 | K10: ='Annual Forecast'!N18 -> 250545.96 | L10: ='Annual Forecast'!O18 -> 266914.96 | ... N10: ='Annual Forecast'!Q18 -> 280652.56
C11: Gross Profit Margin | E11: =IFERROR('Annual Forecast'!H19, "") -> 0.475 | F11: =IFERROR('Annual Forecast'!I19, "") -> 0.385 | G11: =IFERROR('Annual Forecast'!J19, "") -> 0.405 | H11: =IFERROR('Annual Forecast'!K19, "") -> 0.425 | I11: =IFERROR('Annual Forecast'!L19, "") -> 0.43 | J11: =IFERROR('Annual Forecast'!M19, "") -> 0.45 | K11: =IFERROR('Annual Forecast'!N19, "") -> 0.45 | L11: =IFERROR('Annual Forecast'!O19, "") -> 0.47 | ... N11: =IFERROR('Annual Forecast'!Q19, "") -> 0.475
C12: EBITDA | E12: ='Annual Forecast'!H29+'Annual Forecast'!H25 -> 104801.5 | F12: ='Annual Forecast'!I29+'Annual Forecast'!I25 -> 73784.29 | G12: ='Annual Forecast'!J29+'Annual Forecast'!J25 -> 94091.717 | H12: ='Annual Forecast'!K29+'Annual Forecast'!K25 -> 111545.74 | I12: ='Annual Forecast'!L29+'Annual Forecast'!L25 -> 120091.88 | J12: ='Annual Forecast'!M29+'Annual Forecast'!M25 -> 137161.67 | K12: ='Annual Forecast'!N29+'Annual Forecast'!N25 -> 144388.75 | L12: ='Annual Forecast'!O29+'Annual Forecast'!O25 -> 160334.6 | ... N12: ='Annual Forecast'!Q29+'Annual Forecast'!Q25 -> 173200.36
C13: Net Income | E13: ='Annual Forecast'!H36 -> 70583.137 | F13: ='Annual Forecast'!I36 -> 46776.03 | G13: ='Annual Forecast'!J36 -> 61265.553 | H13: ='Annual Forecast'!K36 -> 73946.577 | I13: ='Annual Forecast'!L36 -> 79374.697 | J13: ='Annual Forecast'!M36 -> 90823.764 | K13: ='Annual Forecast'!N36 -> 96224.13 | L13: ='Annual Forecast'!O36 -> 109030.25 | ... N13: ='Annual Forecast'!Q36 -> 121170.23
C14: Net Profit Margin | E14: =IFERROR('Annual Forecast'!H19,"") -> 0.475 | F14: =IFERROR('Annual Forecast'!I19,"") -> 0.385 | G14: =IFERROR('Annual Forecast'!J19,"") -> 0.405 | H14: =IFERROR('Annual Forecast'!K19,"") -> 0.425 | I14: =IFERROR('Annual Forecast'!L19,"") -> 0.43 | J14: =IFERROR('Annual Forecast'!M19,"") -> 0.45 | K14: =IFERROR('Annual Forecast'!N19,"") -> 0.45 | L14: =IFERROR('Annual Forecast'!O19,"") -> 0.47 | ... N14: =IFERROR('Annual Forecast'!Q19,"") -> 0.475
C16: Cumulative Cash Flow | E16: ='Annual Forecast'!H92 -> 172720.6 | F16: ='Annual Forecast'!I92 -> 201830.79 | G16: ='Annual Forecast'!J92 -> 244850.41 | H16: ='Annual Forecast'!K92 -> 295788.44 | I16: ='Annual Forecast'!L92 -> 353977.78 | J16: ='Annual Forecast'!M92 -> 424755.89 | K16: ='Annual Forecast'!N92 -> 495824.65 | L16: ='Annual Forecast'!O92 -> 584949.77 | ... N16: ='Annual Forecast'!Q92 -> 773696.06
C17: Free Cash Flow | E17: =Valuation!K17 -> 21473.719 | F17: =Valuation!L17 -> 44151.592 | G17: =Valuation!M17 -> 59959.454 | H17: =Valuation!N17 -> 69505.017 | I17: =Valuation!O17 -> 77295.546 | J17: =Valuation!P17 -> 91326.679 | K17: =Valuation!Q17 -> 92152.371 | L17: =Valuation!R17 -> 111854.66 | ... N17: =Valuation!T17 -> 123915.21
C18: EV/Revenue | E18: =IFERROR(Valuation!$K$40/E9,0) -> 0.64629787 | F18: =IFERROR(Valuation!$K$40/F9,0) -> 0.60971497 | G18: =IFERROR(Valuation!$K$40/G9,0) -> 0.58068092 | H18: =IFERROR(Valuation!$K$40/H9,0) -> 0.55834704 | I18: =IFERROR(Valuation!$K$40/I9,0) -> 0.54208451 | J18: =IFERROR(Valuation!$K$40/J9,0) -> 0.52629564 | K18: =IFERROR(Valuation!$K$40/K9,0) -> 0.51597611 | L18: =IFERROR(Valuation!$K$40/L9,0) -> 0.50585894 | ... N18: =IFERROR(Valuation!$K$40/N9,0) -> 0.48621582
C19: EV/EBITDA | E19: =IFERROR(Valuation!$K$40/E12,0) -> 2.7411764 | F19: =IFERROR(Valuation!$K$40/F12,0) -> 3.8935036 | G19: =IFERROR(Valuation!$K$40/G12,0) -> 3.0531848 | H19: =IFERROR(Valuation!$K$40/H12,0) -> 2.5754404 | I19: =IFERROR(Valuation!$K$40/I12,0) -> 2.3921635 | J19: =IFERROR(Valuation!$K$40/J12,0) -> 2.0944584 | K19: =IFERROR(Valuation!$K$40/K12,0) -> 1.9896246 | L19: =IFERROR(Valuation!$K$40/L12,0) -> 1.7917492 | ... N19: =IFERROR(Valuation!$K$40/N12,0) -> 1.6586536
C21: Return on Equity (ROE) | E21: =IFERROR(Formulas!C213,"") -> 0.41520551 | F21: =IFERROR(Formulas!D213,"") -> 0.22300286 | G21: =IFERROR(Formulas!E213,"") -> 0.23398891 | H21: =IFERROR(Formulas!F213,"") -> 0.22774825 | I21: =IFERROR(Formulas!G213,"") -> 0.20240691 | J21: =IFERROR(Formulas!H213,"") -> 0.1935079 | K21: =IFERROR(Formulas!I213,"") -> 0.17458956 | L21: =IFERROR(Formulas!J213,"") -> 0.16934883 | ... N21: =IFERROR(Formulas!L213,"") -> 0.14363565
C22: Return on Capital Employed (ROCE) | E22: =IFERROR(Formulas!C215,"") -> 0.32426125 | F22: =IFERROR(Formulas!D215,"") -> 0.18881148 | G22: =IFERROR(Formulas!E215,"") -> 0.20639391 | H22: =IFERROR(Formulas!F215,"") -> 0.20785802 | I22: =IFERROR(Formulas!G215,"") -> 0.18968494 | J22: =IFERROR(Formulas!H215,"") -> 0.18477365 | K22: =IFERROR(Formulas!I215,"") -> 0.16916169 | L22: =IFERROR(Formulas!J215,"") -> 0.16580009 | ... N22: =IFERROR(Formulas!L215,"") -> 0.14267781

Sheet Valuation
A1: © Person0811. All rights reserved.
A2: MENU | B2: =Profile!F6 -> Person0811
C4: Business Valuation
C5: =Formulas!A3 -> Amounts in USD
D6: Case Scenario | E6: =Scenario!E6 -> Base Case
C7: Discounted Cash Flow | K7: =Profile!F8 -> 2025 | L7: =Formulas!D9 -> 2026 | M7: =Formulas!E9 -> 2027 | N7: =Formulas!F9 -> 2028 | O7: =Formulas!G9 -> 2029 | P7: =Formulas!H9 -> 2030 | Q7: =Formulas!I9 -> 2031 | R7: =Formulas!J9 -> 2032 | S7: =Formulas!K9 -> 2033 | T7: =Formulas!L9 -> 2034
D9: EBT | K9: ='Annual Forecast'!H33 -> 94110.849 | L9: ='Annual Forecast'!I33 -> 62368.04 | M9: ='Annual Forecast'!J33 -> 81687.404 | N9: ='Annual Forecast'!K33 -> 98595.435 | O9: ='Annual Forecast'!L33 -> 105832.93 | P9: ='Annual Forecast'!M33 -> 121098.35 | Q9: ='Annual Forecast'!N33 -> 128298.84 | R9: ='Annual Forecast'!O33 -> 145373.67 | ... T9: ='Annual Forecast'!Q33 -> 161560.3
D10: Interest | K10: ='Annual Forecast'!H32 -> 3165.6506 | L10: ='Annual Forecast'!I32 -> 3025 | M10: ='Annual Forecast'!J32 -> 2750 | N10: ='Annual Forecast'!K32 -> 2475 | O10: ='Annual Forecast'!L32 -> 2200 | P10: ='Annual Forecast'!M32 -> 1925 | Q10: ='Annual Forecast'!N32 -> 1650 | R10: ='Annual Forecast'!O32 -> 1375 | ... T10: ='Annual Forecast'!Q32 -> 825
C11: EBIT | K11: =SUM(K9+K10) -> 97276.5 | L11: =SUM(L9+L10) -> 65393.04 | M11: =SUM(M9+M10) -> 84437.404 | N11: =SUM(N9+N10) -> 101070.44 | O11: =SUM(O9+O10) -> 108032.93 | P11: =SUM(P9+P10) -> 123023.35 | Q11: =SUM(Q9+Q10) -> 129948.84 | R11: =SUM(R9+R10) -> 146748.67 | ... T11: =SUM(T9+T10) -> 162385.3
D12: Less: Cash Taxes | K12: ='Annual Forecast'!H35 -> 23527.712 | L12: ='Annual Forecast'!I35 -> 15592.01 | M12: ='Annual Forecast'!J35 -> 20421.851 | N12: ='Annual Forecast'!K35 -> 24648.859 | O12: ='Annual Forecast'!L35 -> 26458.232 | P12: ='Annual Forecast'!M35 -> 30274.588 | Q12: ='Annual Forecast'!N35 -> 32074.71 | R12: ='Annual Forecast'!O35 -> 36343.416 | ... T12: ='Annual Forecast'!Q35 -> 40390.075
D13: Plus: Depreciation and Amortization | K13: ='Annual Forecast'!H25 -> 7525 | L13: ='Annual Forecast'!I25 -> 8391.25 | M13: ='Annual Forecast'!J25 -> 9654.3125 | N13: ='Annual Forecast'!K25 -> 10475.303 | O13: ='Annual Forecast'!L25 -> 12058.947 | P13: ='Annual Forecast'!M25 -> 14138.316 | Q13: ='Annual Forecast'!N25 -> 14439.905 | R13: ='Annual Forecast'!O25 -> 13585.938 | ... T13: ='Annual Forecast'!Q25 -> 10815.059
C14: EBITDA | K14: =K11-K12+K13 -> 81273.788 | L14: =L11-L12+L13 -> 58192.28 | M14: =M11-M12+M13 -> 73669.866 | N14: =N11-N12+N13 -> 86896.88 | O14: =O11-O12+O13 -> 93633.644 | P14: =P11-P12+P13 -> 106887.08 | Q14: =Q11-Q12+Q13 -> 112314.04 | R14: =R11-R12+R13 -> 123991.19 | ... T14: =T11-T12+T13 -> 132810.28
D15: Less: Capex | K15: =-'Annual Forecast'!H81 -> 21500 | L15: =-'Annual Forecast'!I81 -> 10000 | M15: =-'Annual Forecast'!J81 -> 12000 | N15: =-'Annual Forecast'!K81 -> 12000 | O15: =-'Annual Forecast'!L81 -> 15000 | P15: =-'Annual Forecast'!M81 -> 18000 | Q15: =-'Annual Forecast'!N81 -> 15000 | R15: =-'Annual Forecast'!O81 -> 12000 | ... T15: =-'Annual Forecast'!Q81 -> 8000
D16: Less: Changes in Working Capital | K16: =-SUM('Annual Forecast'!H74:H77) -> 38300.068 | L16: =-SUM('Annual Forecast'!I74:I77) -> 4040.6877 | M16: =-SUM('Annual Forecast'!J74:J77) -> 1710.4116 | N16: =-SUM('Annual Forecast'!K74:K77) -> 5391.8629 | O16: =-SUM('Annual Forecast'!L74:L77) -> 1338.0983 | P16: =-SUM('Annual Forecast'!M74:M77) -> -2439.5995 | Q16: =-SUM('Annual Forecast'!N74:N77) -> 5161.664 | R16: =-SUM('Annual Forecast'!O74:O77) -> 136.52276 | ... T16: =-SUM('Annual Forecast'!Q74:Q77) -> 895.07922
C17: Free Cash Flow to Firm (FCFF) | K17: =K14-K15-K16 -> 21473.719 | L17: =L14-L15-L16 -> 44151.592 | M17: =M14-M15-M16 -> 59959.454 | N17: =N14-N15-N16 -> 69505.017 | O17: =O14-O15-O16 -> 77295.546 | P17: =P14-P15-P16 -> 91326.679 | Q17: =Q14-Q15-Q16 -> 92152.371 | R17: =R14-R15-R16 -> 111854.66 | ... T17: =T14-T15-T16 -> 123915.21
D18: Terminal Value (EBITDA Multiple Approach) | K18: =K14*$K$26*Formulas!C12 -> 0 | L18: =L14*$K$26*Formulas!D12 -> 0 | M18: =M14*$K$26*Formulas!E12 -> 0 | N18: =N14*$K$26*Formulas!F12 -> 0 | O18: =O14*$K$26*Formulas!G12 -> 0 | P18: =P14*$K$26*Formulas!H12 -> 0 | Q18: =Q14*$K$26*Formulas!I12 -> 0 | R18: =R14*$K$26*Formulas!J12 -> 0 | ... T18: =T14*$K$26*Formulas!L12 -> 398430.85
C19: Net FCF | J19: =-K40 -> -287279.4 | K19: =K17+K18 -> 21473.719 | L19: =L17+L18 -> 44151.592 | M19: =M17+M18 -> 59959.454 | N19: =N17+N18 -> 69505.017 | O19: =O17+O18 -> 77295.546 | P19: =P17+P18 -> 91326.679 | Q19: =Q17+Q18 -> 92152.371 | R19: =R17+R18 -> 111854.66 | ... T19: =T17+T18 -> 522346.06
D21: PV of Terminal Value | K21: =K18/(1+$E$40)^Formulas!C13 -> 0 | L21: =L18/(1+$E$40)^Formulas!D13 -> 0 | M21: =M18/(1+$E$40)^Formulas!E13 -> 0 | N21: =N18/(1+$E$40)^Formulas!F13 -> 0 | O21: =O18/(1+$E$40)^Formulas!G13 -> 0 | P21: =P18/(1+$E$40)^Formulas!H13 -> 0 | Q21: =Q18/(1+$E$40)^Formulas!I13 -> 0 | R21: =R18/(1+$E$40)^Formulas!J13 -> 0 | ... T21: =T18/(1+$E$40)^Formulas!L13 -> 186007.64
D22: PV of Net FCF | K22: =K19/(1+$E$40)^Formulas!C13 -> 21473.719 | L22: =L19/(1+$E$40)^Formulas!D13 -> 40568.444 | M22: =M19/(1+$E$40)^Formulas!E13 -> 50622.272 | N22: =N19/(1+$E$40)^Formulas!F13 -> 53919.033 | O22: =O19/(1+$E$40)^Formulas!G13 -> 55096.295 | P22: =P19/(1+$E$40)^Formulas!H13 -> 59814.651 | Q22: =Q19/(1+$E$40)^Formulas!I13 -> 55457.259 | R22: =R19/(1+$E$40)^Formulas!J13 -> 61851.177 | ... T22: =T19/(1+$E$40)^Formulas!L13 -> 243857.52
C24: Business Valuation
C25: WACC Calculation | G25: Valuation Assumptions | M25: Equity Value Sensitivity
G26: EV/EBITDA Multiple | K26: 3 | O26: Weighted Average Cost of Capital (WACC)
D27: Debt to Total Capital | E27: =E43/E45 -> 0.35294118 | G27: Current Price | K27: 10 | M27: EV/EBITDA Multiple
D28: Equity to Total Capital | E28: =E44/E45 -> 0.64705882 | G28: Shares Outstanding | K28: 40000 | P28: =R28-2% -> 0.068323529 | Q28: =R28-1% -> 0.078323529 | R28: =E40 -> 0.088323529 | S28: =R28+1% -> 0.098323529 | T28: =R28+2% -> 0.10832353
C29: Debt / Equity | E29: =E27/E28 -> 0.54545455 | N29: =K26-2 -> 1 | O29: x | P29: =Formulas!N19 -> 969880.53 | Q29: =Formulas!O19 -> 926062.77 | R29: =Formulas!P19 -> 885558.34 | S29: =Formulas!Q19 -> 848075.91 | T29: =Formulas!R19 -> 813352.74
G30: Intrinsic Value | N30: =K26-1 -> 2 | O30: x | P30: =Formulas!N20 -> 1031361.1 | Q30: =Formulas!O20 -> 987543.35 | R30: =Formulas!P20 -> 947038.92 | S30: =Formulas!Q20 -> 909556.49 | T30: =Formulas!R20 -> 874833.32
D31: Pre-Tax Cost of Debt | E31: =Scenario!G30 -> 0.055 | H31: Sum of PV of Net FCF | K31: =SUM(K22:T22) -> 699571.05 | N31: =K26 -> 3 | O31: x | P31: =Formulas!N21 -> 1082621.5 | Q31: =Formulas!O21 -> 1038803.7 | R31: =Formulas!P21 -> 998299.29 | S31: =Formulas!Q21 -> 960816.86 | T31: =Formulas!R21 -> 926093.69
D32: Tax Rate | E32: =Scenario!G19 -> 0.25 | H32: Plus: PV of Terminal Value | K32: =SUM(K21:T21) -> 186007.64 | N32: =K26+1 -> 4 | O32: x | P32: =Formulas!N22 -> 1125025.9 | Q32: =Formulas!O22 -> 1081208.2 | R32: =Formulas!P22 -> 1040703.8 | S32: =Formulas!Q22 -> 1003221.3 | T32: =Formulas!R22 -> 968498.15
C33: After Tax Cost of Debt | E33: =E31*(1-E32) -> 0.04125 | H33: Less: Net Debt | K33: =K38-K39 -> -112720.6 | N33: =K26+2 -> 5 | O33: x | P33: =Formulas!N23 -> 1159763.4 | Q33: =Formulas!O23 -> 1115945.7 | R33: =Formulas!P23 -> 1075441.3 | S33: =Formulas!Q23 -> 1037958.8 | T33: =Formulas!R23 -> 1003235.7
G34: Equity Value | K34: =K31+K32-K33 -> 998299.29
D35: Risk Free Rate | E35: 0.03
D36: Equity Risk Premium | E36: 0.07 | G36: Market Value
D37: Levered Beta | E37: 1.2 | H37: Market Cap | K37: =K27*K28 -> 400000
C38: Cost of Equity | E38: =E35+(E36*E37) -> 0.114 | H38: Plus: Debt | K38: =E43 -> 60000
H39: Less: Cash | K39: ='12-Month Projection'!T92 -> 172720.6
C40: WACC (Discount Rate) | E40: =(E27*E33)+(E28*E38) -> 0.088323529 | G40: Enterprise Value (EV) | K40: =K37+K38-K39 -> 287279.4
C42: Capital Structure (Initial Investment) | G42: Rate of Return
D43: Debt | E43: =Scenario!G31 -> 60000 | H43: Current Share Price | K43: =K27 -> 10
D44: Equity | E44: =Scenario!G32 -> 110000 | H44: Upside | K44: =K45-K43 -> 14.957482
C45: Total | E45: =SUM(E43:E44) -> 170000 | H45: Target Share Price | K45: =K34/K28 -> 24.957482
H46: Target Price Upside % | K46: =K44/K43 -> 1.4957482
C47: =Formulas!C39 -> Good Investment | G47: IRR | K47: =IFERROR(IRR(J19:T19),0) -> 0.23146823

Sheet Dashboard
A1: © Person0811. All rights reserved.
A2: MENU | B2: =Profile!F6 -> Person0811
C4: Dashboard
C5: =Formulas!A3 -> Amounts in USD
E6: Year | F6: 2025
D8: Total Revenue | F8: Total Expenses | L8: Closing Cash Balance | N8: Long-Term Debt
D9: =Formulas!C238 -> 444500 | F9: =Formulas!C242 -> 347223.5 | L9: =Formulas!C254 -> 172720.6 | N9: =Formulas!C258 -> 55000
D10: =Formulas!C240 -> 0 | F10: =Formulas!C244 -> 0 | J10: Net Profit Margin % | L10: =Formulas!C256 -> 0 | N10: =Formulas!C260 -> 0
D11: vs. Previous Year | F11: vs. Previous Year | J11: =Formulas!C270 -> 0.15879221 | L11: vs. Previous Year | N11: vs. Previous Year
D13: Net Profit | F13: EBITDA | J13: =Formulas!C272 -> 0 | L13: Current Ratio | N13: Quick Ratio
D14: =Formulas!C246 -> 70583.137 | F14: =Formulas!C250 -> 104801.5 | J14: vs. Previous Year | L14: =Formulas!C262 -> 5.060435 | N14: =Formulas!C266 -> 4.2607865
D15: =Formulas!C248 -> 0 | F15: =Formulas!C252 -> 0 | L15: =Formulas!C264 -> 0 | N15: =Formulas!C268 -> 0
D16: vs. Previous Year | F16: vs. Previous Year | L16: vs. Previous Year | N16: vs. Previous Year
M46: Income Statement | O46: =Formulas!C305 -> 2025
M47: Total Sales | O47: =Formulas!C306 -> 444500
M48: Total Cost of Sales | O48: =Formulas!C307 -> 233362.5
M49: Gross Profit | O49: =Formulas!C308 -> 211137.5
M50: Total Operating Expenses | O50: =Formulas!C309 -> 113861
M51: Operating Profit (EBIT) | O51: =Formulas!C310 -> 97276.5
M52: Interest | O52: =Formulas!C311 -> 3165.6506
M53: Earnings Before Taxes (EBT) | O53: =Formulas!C312 -> 94110.849
M54: Income Taxes | O54: =Formulas!C313 -> 23527.712
M55: Net Income | O55: =Formulas!C314 -> 70583.137
M56: Cash Flow Statement
M57: Cash from Operations | O57: =Formulas!C316 -> 39808.069
M58: Cash from Investing | O58: =Formulas!C317 -> -21500
M59: Cash from Financing | O59: =Formulas!C318 -> 154412.53
M60: Opening Cash Balance | O60: =Formulas!C319 -> 0
M61: Closing Cash Balance | O61: =Formulas!C320 -> 172720.6

Sheet Revenue
A1: © Person0811. All rights reserved.
A2: MENU | B2: =Profile!F6 -> Person0811
C4: Business Units Revenue
C5: =Formulas!A3 -> Amounts in USD
G6: =Profile!F8 -> 2025
C7: Revenue | G7: =Formulas!C41 -> January | H7: =Formulas!D41 -> February | I7: =Formulas!E41 -> March | J7: =Formulas!F41 -> April | K7: =Formulas!G41 -> May | L7: =Formulas!H41 -> June | M7: =Formulas!I41 -> July | N7: =Formulas!J41 -> August | ... R7: =Formulas!N41 -> December | S7: FY
C8: Seasonality Adjustment | G8: 0.02 | H8: 0.03 | I8: 0.04 | J8: 0.05 | K8: 0.1 | L8: 0.12 | M8: 0.08 | N8: 0.05 | O8: -0.02 | P8: 0.03 | Q8: 0.08 | R8: 0.12
C9: Category | E9: Volume | F9: Sales Price | G9: Sales | S9: Total Sales
D10: Service 1 | E10: 250 | F10: 10 | G10: =$E10*$F10*Formulas!C$42 -> 2550 | H10: =$E10*$F10*Formulas!D$42 -> 2575 | I10: =$E10*$F10*Formulas!E$42 -> 2600 | J10: =$E10*$F10*Formulas!F$42 -> 2625 | K10: =$E10*$F10*Formulas!G$42 -> 2750 | L10: =$E10*$F10*Formulas!H$42 -> 2800 | M10: =$E10*$F10*Formulas!I$42 -> 2700 | N10: =$E10*$F10*Formulas!J$42 -> 2625 | ... R10: =$E10*$F10*Formulas!N$42 -> 2800 | S10: =SUM(G10:R10) -> 31750
D11: Service 2 | E11: 200 | F11: 20 | G11: =$E11*$F11*Formulas!C$42 -> 4080 | H11: =$E11*$F11*Formulas!D$42 -> 4120 | I11: =$E11*$F11*Formulas!E$42 -> 4160 | J11: =$E11*$F11*Formulas!F$42 -> 4200 | K11: =$E11*$F11*Formulas!G$42 -> 4400 | L11: =$E11*$F11*Formulas!H$42 -> 4480 | M11: =$E11*$F11*Formulas!I$42 -> 4320 | N11: =$E11*$F11*Formulas!J$42 -> 4200 | ... R11: =$E11*$F11*Formulas!N$42 -> 4480 | S11: =SUM(G11:R11) -> 50800
D12: Service 3 | E12: 150 | F12: 30 | G12: =$E12*$F12*Formulas!C$42 -> 4590 | H12: =$E12*$F12*Formulas!D$42 -> 4635 | I12: =$E12*$F12*Formulas!E$42 -> 4680 | J12: =$E12*$F12*Formulas!F$42 -> 4725 | K12: =$E12*$F12*Formulas!G$42 -> 4950 | L12: =$E12*$F12*Formulas!H$42 -> 5040 | M12: =$E12*$F12*Formulas!I$42 -> 4860 | N12: =$E12*$F12*Formulas!J$42 -> 4725 | ... R12: =$E12*$F12*Formulas!N$42 -> 5040 | S12: =SUM(G12:R12) -> 57150
D13: Service 4 | E13: 100 | F13: 40 | G13: =$E13*$F13*Formulas!C$42 -> 4080 | H13: =$E13*$F13*Formulas!D$42 -> 4120 | I13: =$E13*$F13*Formulas!E$42 -> 4160 | J13: =$E13*$F13*Formulas!F$42 -> 4200 | K13: =$E13*$F13*Formulas!G$42 -> 4400 | L13: =$E13*$F13*Formulas!H$42 -> 4480 | M13: =$E13*$F13*Formulas!I$42 -> 4320 | N13: =$E13*$F13*Formulas!J$42 -> 4200 | ... R13: =$E13*$F13*Formulas!N$42 -> 4480 | S13: =SUM(G13:R13) -> 50800
D14: Service 5 | E14: 50 | F14: 50 | G14: =$E14*$F14*Formulas!C$42 -> 2550 | H14: =$E14*$F14*Formulas!D$42 -> 2575 | I14: =$E14*$F14*Formulas!E$42 -> 2600 | J14: =$E14*$F14*Formulas!F$42 -> 2625 | K14: =$E14*$F14*Formulas!G$42 -> 2750 | L14: =$E14*$F14*Formulas!H$42 -> 2800 | M14: =$E14*$F14*Formulas!I$42 -> 2700 | N14: =$E14*$F14*Formulas!J$42 -> 2625 | ... R14: =$E14*$F14*Formulas!N$42 -> 2800 | S14: =SUM(G14:R14) -> 31750
D15: (Add Service) | G15: =$E15*$F15*Formulas!C$42 -> 0 | H15: =$E15*$F15*Formulas!D$42 -> 0 | I15: =$E15*$F15*Formulas!E$42 -> 0 | J15: =$E15*$F15*Formulas!F$42 -> 0 | K15: =$E15*$F15*Formulas!G$42 -> 0 | L15: =$E15*$F15*Formulas!H$42 -> 0 | M15: =$E15*$F15*Formulas!I$42 -> 0 | N15: =$E15*$F15*Formulas!J$42 -> 0 | ... R15: =$E15*$F15*Formulas!N$42 -> 0 | S15: =SUM(G15:R15) -> 0
D16: (Add Service) | G16: =$E16*$F16*Formulas!C$42 -> 0 | H16: =$E16*$F16*Formulas!D$42 -> 0 | I16: =$E16*$F16*Formulas!E$42 -> 0 | J16: =$E16*$F16*Formulas!F$42 -> 0 | K16: =$E16*$F16*Formulas!G$42 -> 0 | L16: =$E16*$F16*Formulas!H$42 -> 0 | M16: =$E16*$F16*Formulas!I$42 -> 0 | N16: =$E16*$F16*Formulas!J$42 -> 0 | ... R16: =$E16*$F16*Formulas!N$42 -> 0 | S16: =SUM(G16:R16) -> 0
D17: (Add Service) | G17: =$E17*$F17*Formulas!C$42 -> 0 | H17: =$E17*$F17*Formulas!D$42 -> 0 | I17: =$E17*$F17*Formulas!E$42 -> 0 | J17: =$E17*$F17*Formulas!F$42 -> 0 | K17: =$E17*$F17*Formulas!G$42 -> 0 | L17: =$E17*$F17*Formulas!H$42 -> 0 | M17: =$E17*$F17*Formulas!I$42 -> 0 | N17: =$E17*$F17*Formulas!J$42 -> 0 | ... R17: =$E17*$F17*Formulas!N$42 -> 0 | S17: =SUM(G17:R17) -> 0
D18: (Add Service) | G18: =$E18*$F18*Formulas!C$42 -> 0 | H18: =$E18*$F18*Formulas!D$42 -> 0 | I18: =$E18*$F18*Formulas!E$42 -> 0 | J18: =$E18*$F18*Formulas!F$42 -> 0 | K18: =$E18*$F18*Formulas!G$42 -> 0 | L18: =$E18*$F18*Formulas!H$42 -> 0 | M18: =$E18*$F18*Formulas!I$42 -> 0 | N18: =$E18*$F18*Formulas!J$42 -> 0 | ... R18: =$E18*$F18*Formulas!N$42 -> 0 | S18: =SUM(G18:R18) -> 0
D19: (Add Service) | G19: =$E19*$F19*Formulas!C$42 -> 0 | H19: =$E19*$F19*Formulas!D$42 -> 0 | I19: =$E19*$F19*Formulas!E$42 -> 0 | J19: =$E19*$F19*Formulas!F$42 -> 0 | K19: =$E19*$F19*Formulas!G$42 -> 0 | L19: =$E19*$F19*Formulas!H$42 -> 0 | M19: =$E19*$F19*Formulas!I$42 -> 0 | N19: =$E19*$F19*Formulas!J$42 -> 0 | ... R19: =$E19*$F19*Formulas!N$42 -> 0 | S19: =SUM(G19:R19) -> 0
C20: Total Services | E20: =SUM(E10:E19) -> 750 | G20: =SUM(G10:G19) -> 17850 | H20: =SUM(H10:H19) -> 18025 | I20: =SUM(I10:I19) -> 18200 | J20: =SUM(J10:J19) -> 18375 | K20: =SUM(K10:K19) -> 19250 | L20: =SUM(L10:L19) -> 19600 | M20: =SUM(M10:M19) -> 18900 | N20: =SUM(N10:N19) -> 18375 | ... S20: =SUM(S10:S19) -> 222250
D22: Product 1 | E22: 250 | F22: 10 | G22: =$E22*$F22*Formulas!C$42 -> 2550 | H22: =$E22*$F22*Formulas!D$42 -> 2575 | I22: =$E22*$F22*Formulas!E$42 -> 2600 | J22: =$E22*$F22*Formulas!F$42 -> 2625 | K22: =$E22*$F22*Formulas!G$42 -> 2750 | L22: =$E22*$F22*Formulas!H$42 -> 2800 | M22: =$E22*$F22*Formulas!I$42 -> 2700 | N22: =$E22*$F22*Formulas!J$42 -> 2625 | ... R22: =$E22*$F22*Formulas!N$42 -> 2800 | S22: =SUM(G22:R22) -> 31750
D23: Product 2 | E23: 200 | F23: 20 | G23: =$E23*$F23*Formulas!C$42 -> 4080 | H23: =$E23*$F23*Formulas!D$42 -> 4120 | I23: =$E23*$F23*Formulas!E$42 -> 4160 | J23: =$E23*$F23*Formulas!F$42 -> 4200 | K23: =$E23*$F23*Formulas!G$42 -> 4400 | L23: =$E23*$F23*Formulas!H$42 -> 4480 | M23: =$E23*$F23*Formulas!I$42 -> 4320 | N23: =$E23*$F23*Formulas!J$42 -> 4200 | ... R23: =$E23*$F23*Formulas!N$42 -> 4480 | S23: =SUM(G23:R23) -> 50800
D24: Product 3 | E24: 150 | F24: 30 | G24: =$E24*$F24*Formulas!C$42 -> 4590 | H24: =$E24*$F24*Formulas!D$42 -> 4635 | I24: =$E24*$F24*Formulas!E$42 -> 4680 | J24: =$E24*$F24*Formulas!F$42 -> 4725 | K24: =$E24*$F24*Formulas!G$42 -> 4950 | L24: =$E24*$F24*Formulas!H$42 -> 5040 | M24: =$E24*$F24*Formulas!I$42 -> 4860 | N24: =$E24*$F24*Formulas!J$42 -> 4725 | ... R24: =$E24*$F24*Formulas!N$42 -> 5040 | S24: =SUM(G24:R24) -> 57150
D25: Product 4 | E25: 100 | F25: 40 | G25: =$E25*$F25*Formulas!C$42 -> 4080 | H25: =$E25*$F25*Formulas!D$42 -> 4120 | I25: =$E25*$F25*Formulas!E$42 -> 4160 | J25: =$E25*$F25*Formulas!F$42 -> 4200 | K25: =$E25*$F25*Formulas!G$42 -> 4400 | L25: =$E25*$F25*Formulas!H$42 -> 4480 | M25: =$E25*$F25*Formulas!I$42 -> 4320 | N25: =$E25*$F25*Formulas!J$42 -> 4200 | ... R25: =$E25*$F25*Formulas!N$42 -> 4480 | S25: =SUM(G25:R25) -> 50800
D26: Product 5 | E26: 50 | F26: 50 | G26: =$E26*$F26*Formulas!C$42 -> 2550 | H26: =$E26*$F26*Formulas!D$42 -> 2575 | I26: =$E26*$F26*Formulas!E$42 -> 2600 | J26: =$E26*$F26*Formulas!F$42 -> 2625 | K26: =$E26*$F26*Formulas!G$42 -> 2750 | L26: =$E26*$F26*Formulas!H$42 -> 2800 | M26: =$E26*$F26*Formulas!I$42 -> 2700 | N26: =$E26*$F26*Formulas!J$42 -> 2625 | ... R26: =$E26*$F26*Formulas!N$42 -> 2800 | S26: =SUM(G26:R26) -> 31750
D27: (Add Product) | G27: =$E27*$F27*Formulas!C$42 -> 0 | H27: =$E27*$F27*Formulas!D$42 -> 0 | I27: =$E27*$F27*Formulas!E$42 -> 0 | J27: =$E27*$F27*Formulas!F$42 -> 0 | K27: =$E27*$F27*Formulas!G$42 -> 0 | L27: =$E27*$F27*Formulas!H$42 -> 0 | M27: =$E27*$F27*Formulas!I$42 -> 0 | N27: =$E27*$F27*Formulas!J$42 -> 0 | ... R27: =$E27*$F27*Formulas!N$42 -> 0 | S27: =SUM(G27:R27) -> 0
D28: (Add Product) | G28: =$E28*$F28*Formulas!C$42 -> 0 | H28: =$E28*$F28*Formulas!D$42 -> 0 | I28: =$E28*$F28*Formulas!E$42 -> 0 | J28: =$E28*$F28*Formulas!F$42 -> 0 | K28: =$E28*$F28*Formulas!G$42 -> 0 | L28: =$E28*$F28*Formulas!H$42 -> 0 | M28: =$E28*$F28*Formulas!I$42 -> 0 | N28: =$E28*$F28*Formulas!J$42 -> 0 | ... R28: =$E28*$F28*Formulas!N$42 -> 0 | S28: =SUM(G28:R28) -> 0
D29: (Add Product) | G29: =$E29*$F29*Formulas!C$42 -> 0 | H29: =$E29*$F29*Formulas!D$42 -> 0 | I29: =$E29*$F29*Formulas!E$42 -> 0 | J29: =$E29*$F29*Formulas!F$42 -> 0 | K29: =$E29*$F29*Formulas!G$42 -> 0 | L29: =$E29*$F29*Formulas!H$42 -> 0 | M29: =$E29*$F29*Formulas!I$42 -> 0 | N29: =$E29*$F29*Formulas!J$42 -> 0 | ... R29: =$E29*$F29*Formulas!N$42 -> 0 | S29: =SUM(G29:R29) -> 0
D30: (Add Product) | G30: =$E30*$F30*Formulas!C$42 -> 0 | H30: =$E30*$F30*Formulas!D$42 -> 0 | I30: =$E30*$F30*Formulas!E$42 -> 0 | J30: =$E30*$F30*Formulas!F$42 -> 0 | K30: =$E30*$F30*Formulas!G$42 -> 0 | L30: =$E30*$F30*Formulas!H$42 -> 0 | M30: =$E30*$F30*Formulas!I$42 -> 0 | N30: =$E30*$F30*Formulas!J$42 -> 0 | ... R30: =$E30*$F30*Formulas!N$42 -> 0 | S30: =SUM(G30:R30) -> 0
D31: (Add Product) | G31: =$E31*$F31*Formulas!C$42 -> 0 | H31: =$E31*$F31*Formulas!D$42 -> 0 | I31: =$E31*$F31*Formulas!E$42 -> 0 | J31: =$E31*$F31*Formulas!F$42 -> 0 | K31: =$E31*$F31*Formulas!G$42 -> 0 | L31: =$E31*$F31*Formulas!H$42 -> 0 | M31: =$E31*$F31*Formulas!I$42 -> 0 | N31: =$E31*$F31*Formulas!J$42 -> 0 | ... R31: =$E31*$F31*Formulas!N$42 -> 0 | S31: =SUM(G31:R31) -> 0
C32: Total Products | E32: =SUM(E22:E31) -> 750 | G32: =SUM(G22:G31) -> 17850 | H32: =SUM(H22:H31) -> 18025 | I32: =SUM(I22:I31) -> 18200 | J32: =SUM(J22:J31) -> 18375 | K32: =SUM(K22:K31) -> 19250 | L32: =SUM(L22:L31) -> 19600 | M32: =SUM(M22:M31) -> 18900 | N32: =SUM(N22:N31) -> 18375 | ... S32: =SUM(S22:S31) -> 222250
C34: Grand Total Revenue | E34: =E20+E32 -> 1500 | G34: =G20+G32 -> 35700 | H34: =H20+H32 -> 36050 | I34: =I20+I32 -> 36400 | J34: =J20+J32 -> 36750 | K34: =K20+K32 -> 38500 | L34: =L20+L32 -> 39200 | M34: =M20+M32 -> 37800 | N34: =N20+N32 -> 36750 | ... S34: =S20+S32 -> 444500
C36: Cost of Goods Sold (COGS)
C38: Category | F38: % of Revenue | G38: Cost | S38: Total Cost
D39: Service 1 | F39: 0.15 | G39: =$F39*G10 -> 382.5 | H39: =$F39*H10 -> 386.25 | I39: =$F39*I10 -> 390 | J39: =$F39*J10 -> 393.75 | K39: =$F39*K10 -> 412.5 | L39: =$F39*L10 -> 420 | M39: =$F39*M10 -> 405 | N39: =$F39*N10 -> 393.75 | ... R39: =$F39*R10 -> 420 | S39: =SUM(G39:R39) -> 4762.5
D40: Service 2 | F40: 0.15 | G40: =$F40*G11 -> 612 | H40: =$F40*H11 -> 618 | I40: =$F40*I11 -> 624 | J40: =$F40*J11 -> 630 | K40: =$F40*K11 -> 660 | L40: =$F40*L11 -> 672 | M40: =$F40*M11 -> 648 | N40: =$F40*N11 -> 630 | ... R40: =$F40*R11 -> 672 | S40: =SUM(G40:R40) -> 7620
D41: Service 3 | F41: 0.15 | G41: =$F41*G12 -> 688.5 | H41: =$F41*H12 -> 695.25 | I41: =$F41*I12 -> 702 | J41: =$F41*J12 -> 708.75 | K41: =$F41*K12 -> 742.5 | L41: =$F41*L12 -> 756 | M41: =$F41*M12 -> 729 | N41: =$F41*N12 -> 708.75 | ... R41: =$F41*R12 -> 756 | S41: =SUM(G41:R41) -> 8572.5
D42: Service 4 | F42: 0.15 | G42: =$F42*G13 -> 612 | H42: =$F42*H13 -> 618 | I42: =$F42*I13 -> 624 | J42: =$F42*J13 -> 630 | K42: =$F42*K13 -> 660 | L42: =$F42*L13 -> 672 | M42: =$F42*M13 -> 648 | N42: =$F42*N13 -> 630 | ... R42: =$F42*R13 -> 672 | S42: =SUM(G42:R42) -> 7620
D43: Service 5 | F43: 0.15 | G43: =$F43*G14 -> 382.5 | H43: =$F43*H14 -> 386.25 | I43: =$F43*I14 -> 390 | J43: =$F43*J14 -> 393.75 | K43: =$F43*K14 -> 412.5 | L43: =$F43*L14 -> 420 | M43: =$F43*M14 -> 405 | N43: =$F43*N14 -> 393.75 | ... R43: =$F43*R14 -> 420 | S43: =SUM(G43:R43) -> 4762.5
D44: (Add Service) | G44: =$F44*G15 -> 0 | H44: =$F44*H15 -> 0 | I44: =$F44*I15 -> 0 | J44: =$F44*J15 -> 0 | K44: =$F44*K15 -> 0 | L44: =$F44*L15 -> 0 | M44: =$F44*M15 -> 0 | N44: =$F44*N15 -> 0 | ... R44: =$F44*R15 -> 0 | S44: =SUM(G44:R44) -> 0
D45: (Add Service) | G45: =$F45*G16 -> 0 | H45: =$F45*H16 -> 0 | I45: =$F45*I16 -> 0 | J45: =$F45*J16 -> 0 | K45: =$F45*K16 -> 0 | L45: =$F45*L16 -> 0 | M45: =$F45*M16 -> 0 | N45: =$F45*N16 -> 0 | ... R45: =$F45*R16 -> 0 | S45: =SUM(G45:R45) -> 0
D46: (Add Service) | G46: =$F46*G17 -> 0 | H46: =$F46*H17 -> 0 | I46: =$F46*I17 -> 0 | J46: =$F46*J17 -> 0 | K46: =$F46*K17 -> 0 | L46: =$F46*L17 -> 0 | M46: =$F46*M17 -> 0 | N46: =$F46*N17 -> 0 | ... R46: =$F46*R17 -> 0 | S46: =SUM(G46:R46) -> 0
D47: (Add Service) | G47: =$F47*G18 -> 0 | H47: =$F47*H18 -> 0 | I47: =$F47*I18 -> 0 | J47: =$F47*J18 -> 0 | K47: =$F47*K18 -> 0 | L47: =$F47*L18 -> 0 | M47: =$F47*M18 -> 0 | N47: =$F47*N18 -> 0 | ... R47: =$F47*R18 -> 0 | S47: =SUM(G47:R47) -> 0
D48: (Add Service) | G48: =$F48*G19 -> 0 | H48: =$F48*H19 -> 0 | I48: =$F48*I19 -> 0 | J48: =$F48*J19 -> 0 | K48: =$F48*K19 -> 0 | L48: =$F48*L19 -> 0 | M48: =$F48*M19 -> 0 | N48: =$F48*N19 -> 0 | ... R48: =$F48*R19 -> 0 | S48: =SUM(G48:R48) -> 0
C49: Total Services | G49: =SUM(G39:G48) -> 2677.5 | H49: =SUM(H39:H48) -> 2703.75 | I49: =SUM(I39:I48) -> 2730 | J49: =SUM(J39:J48) -> 2756.25 | K49: =SUM(K39:K48) -> 2887.5 | L49: =SUM(L39:L48) -> 2940 | M49: =SUM(M39:M48) -> 2835 | N49: =SUM(N39:N48) -> 2756.25 | ... S49: =SUM(S39:S48) -> 33337.5
D51: Product 1 | F51: 0.3 | G51: =$F51*G22 -> 765 | H51: =$F51*H22 -> 772.5 | I51: =$F51*I22 -> 780 | J51: =$F51*J22 -> 787.5 | K51: =$F51*K22 -> 825 | L51: =$F51*L22 -> 840 | M51: =$F51*M22 -> 810 | N51: =$F51*N22 -> 787.5 | ... R51: =$F51*R22 -> 840 | S51: =SUM(G51:R51) -> 9525
D52: Product 2 | F52: 0.3 | G52: =$F52*G23 -> 1224 | H52: =$F52*H23 -> 1236 | I52: =$F52*I23 -> 1248 | J52: =$F52*J23 -> 1260 | K52: =$F52*K23 -> 1320 | L52: =$F52*L23 -> 1344 | M52: =$F52*M23 -> 1296 | N52: =$F52*N23 -> 1260 | ... R52: =$F52*R23 -> 1344 | S52: =SUM(G52:R52) -> 15240
D53: Product 3 | F53: 0.3 | G53: =$F53*G24 -> 1377 | H53: =$F53*H24 -> 1390.5 | I53: =$F53*I24 -> 1404 | J53: =$F53*J24 -> 1417.5 | K53: =$F53*K24 -> 1485 | L53: =$F53*L24 -> 1512 | M53: =$F53*M24 -> 1458 | N53: =$F53*N24 -> 1417.5 | ... R53: =$F53*R24 -> 1512 | S53: =SUM(G53:R53) -> 17145
D54: Product 4 | F54: 0.3 | G54: =$F54*G25 -> 1224 | H54: =$F54*H25 -> 1236 | I54: =$F54*I25 -> 1248 | J54: =$F54*J25 -> 1260 | K54: =$F54*K25 -> 1320 | L54: =$F54*L25 -> 1344 | M54: =$F54*M25 -> 1296 | N54: =$F54*N25 -> 1260 | ... R54: =$F54*R25 -> 1344 | S54: =SUM(G54:R54) -> 15240
D55: Product 5 | F55: 0.3 | G55: =$F55*G26 -> 765 | H55: =$F55*H26 -> 772.5 | I55: =$F55*I26 -> 780 | J55: =$F55*J26 -> 787.5 | K55: =$F55*K26 -> 825 | L55: =$F55*L26 -> 840 | M55: =$F55*M26 -> 810 | N55: =$F55*N26 -> 787.5 | ... R55: =$F55*R26 -> 840 | S55: =SUM(G55:R55) -> 9525
D56: (Add Product) | G56: =$F56*G27 -> 0 | H56: =$F56*H27 -> 0 | I56: =$F56*I27 -> 0 | J56: =$F56*J27 -> 0 | K56: =$F56*K27 -> 0 | L56: =$F56*L27 -> 0 | M56: =$F56*M27 -> 0 | N56: =$F56*N27 -> 0 | ... R56: =$F56*R27 -> 0 | S56: =SUM(G56:R56) -> 0
D57: (Add Product) | G57: =$F57*G28 -> 0 | H57: =$F57*H28 -> 0 | I57: =$F57*I28 -> 0 | J57: =$F57*J28 -> 0 | K57: =$F57*K28 -> 0 | L57: =$F57*L28 -> 0 | M57: =$F57*M28 -> 0 | N57: =$F57*N28 -> 0 | ... R57: =$F57*R28 -> 0 | S57: =SUM(G57:R57) -> 0
D58: (Add Product) | G58: =$F58*G29 -> 0 | H58: =$F58*H29 -> 0 | I58: =$F58*I29 -> 0 | J58: =$F58*J29 -> 0 | K58: =$F58*K29 -> 0 | L58: =$F58*L29 -> 0 | M58: =$F58*M29 -> 0 | N58: =$F58*N29 -> 0 | ... R58: =$F58*R29 -> 0 | S58: =SUM(G58:R58) -> 0
D59: (Add Product) | G59: =$F59*G30 -> 0 | H59: =$F59*H30 -> 0 | I59: =$F59*I30 -> 0 | J59: =$F59*J30 -> 0 | K59: =$F59*K30 -> 0 | L59: =$F59*L30 -> 0 | M59: =$F59*M30 -> 0 | N59: =$F59*N30 -> 0 | ... R59: =$F59*R30 -> 0 | S59: =SUM(G59:R59) -> 0
D60: (Add Product) | G60: =$F60*G31 -> 0 | H60: =$F60*H31 -> 0 | I60: =$F60*I31 -> 0 | J60: =$F60*J31 -> 0 | K60: =$F60*K31 -> 0 | L60: =$F60*L31 -> 0 | M60: =$F60*M31 -> 0 | N60: =$F60*N31 -> 0 | ... R60: =$F60*R31 -> 0 | S60: =SUM(G60:R60) -> 0
C61: Total Products | G61: =SUM(G51:G60) -> 5355 | H61: =SUM(H51:H60) -> 5407.5 | I61: =SUM(I51:I60) -> 5460 | J61: =SUM(J51:J60) -> 5512.5 | K61: =SUM(K51:K60) -> 5775 | L61: =SUM(L51:L60) -> 5880 | M61: =SUM(M51:M60) -> 5670 | N61: =SUM(N51:N60) -> 5512.5 | ... S61: =SUM(S51:S60) -> 66675
C63: Grand Total Cost | G63: =G49+G61 -> 8032.5 | H63: =H49+H61 -> 8111.25 | I63: =I49+I61 -> 8190 | J63: =J49+J61 -> 8268.75 | K63: =K49+K61 -> 8662.5 | L63: =L49+L61 -> 8820 | M63: =M49+M61 -> 8505 | N63: =N49+N61 -> 8268.75 | ... S63: =S49+S61 -> 100012.5

Sheet Scenario
A1: © Person0811. All rights reserved.
A2: MENU | B2: =Profile!F6 -> Person0811
C4: Scenario Analysis
C5: =Formulas!A3 -> Amounts in USD
D6: Case Scenario | E6: Base Case | G6: Assumptions
C7: Active Case | G7: =Formulas!C9 -> 2025 | H7: =Formulas!D9 -> 2026 | I7: =Formulas!E9 -> 2027 | J7: =Formulas!F9 -> 2028 | K7: =Formulas!G9 -> 2029 | L7: =Formulas!H9 -> 2030 | M7: =Formulas!I9 -> 2031 | N7: =Formulas!J9 -> 2032 | ... P7: =Formulas!L9 -> 2034
C8: Income Statement
D9: Revenue Growth | E9: % change | G9: =Formulas!C45 -> 0 | H9: =Formulas!D45 -> 0.06 | I9: =Formulas!E45 -> 0.05 | J9: =Formulas!F45 -> 0.04 | K9: =Formulas!G45 -> 0.03 | L9: =Formulas!H45 -> 0.03 | M9: =Formulas!I45 -> 0.02 | N9: =Formulas!J45 -> 0.02 | ... P9: =Formulas!L45 -> 0.02
D10: Service Cost | E10: % of service revenue | H10: =Formulas!D49 -> 0.25 | I10: =Formulas!E49 -> 0.25 | J10: =Formulas!F49 -> 0.24 | K10: =Formulas!G49 -> 0.24 | L10: =Formulas!H49 -> 0.23 | M10: =Formulas!I49 -> 0.23 | N10: =Formulas!J49 -> 0.22 | O10: =Formulas!K49 -> 0.22 | P10: =Formulas!L49 -> 0.21
D11: Product Cost | E11: % of product revenue | H11: =Formulas!D53 -> 0.4 | I11: =Formulas!E53 -> 0.38 | J11: =Formulas!F53 -> 0.37 | K11: =Formulas!G53 -> 0.36 | L11: =Formulas!H53 -> 0.35 | M11: =Formulas!I53 -> 0.35 | N11: =Formulas!J53 -> 0.34 | O11: =Formulas!K53 -> 0.34 | P11: =Formulas!L53 -> 0.34
D12: Direct Labor Cost | E12: % of total revenue | G12: =Formulas!C57 -> 0.18 | H12: =Formulas!D57 -> 0.18 | I12: =Formulas!E57 -> 0.18 | J12: =Formulas!F57 -> 0.18 | K12: =Formulas!G57 -> 0.18 | L12: =Formulas!H57 -> 0.18 | M12: =Formulas!I57 -> 0.18 | N12: =Formulas!J57 -> 0.18 | ... P12: =Formulas!L57 -> 0.18
D13: Discount and Promotions | E13: % of total revenue | G13: =Formulas!C61 -> 0.12 | H13: =Formulas!D61 -> 0.11 | I13: =Formulas!E61 -> 0.1 | J13: =Formulas!F61 -> 0.09 | K13: =Formulas!G61 -> 0.09 | L13: =Formulas!H61 -> 0.08 | M13: =Formulas!I61 -> 0.08 | N13: =Formulas!J61 -> 0.07 | ... P13: =Formulas!L61 -> 0.07
D14: Salaries and Benefits | E14: =Profile!$F$10 -> USD | G14: =Formulas!C65 -> 50000 | H14: =Formulas!D65 -> 50000 | I14: =Formulas!E65 -> 50000 | J14: =Formulas!F65 -> 50000 | K14: =Formulas!G65 -> 50000 | L14: =Formulas!H65 -> 50000 | M14: =Formulas!I65 -> 50000 | N14: =Formulas!J65 -> 50000 | ... P14: =Formulas!L65 -> 50000
D15: Sales and Marketing | E15: % of total revenue | G15: =Formulas!C69 -> 0.04 | H15: =Formulas!D69 -> 0.04 | I15: =Formulas!E69 -> 0.035 | J15: =Formulas!F69 -> 0.035 | K15: =Formulas!G69 -> 0.035 | L15: =Formulas!H69 -> 0.035 | M15: =Formulas!I69 -> 0.03 | N15: =Formulas!J69 -> 0.03 | ... P15: =Formulas!L69 -> 0.03
D16: General and Administration | E16: =Profile!$F$10 -> USD | G16: =Formulas!C73 -> 35000 | H16: =Formulas!D73 -> 35000 | I16: =Formulas!E73 -> 35000 | J16: =Formulas!F73 -> 35000 | K16: =Formulas!G73 -> 35000 | L16: =Formulas!H73 -> 35000 | M16: =Formulas!I73 -> 35000 | N16: =Formulas!J73 -> 35000 | ... P16: =Formulas!L73 -> 35000
D17: Credit Card Fees | E17: % of total revenue | G17: =Formulas!C77 -> 0.008 | H17: =Formulas!D77 -> 0.008 | I17: =Formulas!E77 -> 0.008 | J17: =Formulas!F77 -> 0.008 | K17: =Formulas!G77 -> 0.008 | L17: =Formulas!H77 -> 0.008 | M17: =Formulas!I77 -> 0.008 | N17: =Formulas!J77 -> 0.008 | ... P17: =Formulas!L77 -> 0.008
D18: Depreciation and Amortization | E18: % of PP&E | G18: =Formulas!C81 -> 0.35 | H18: =Formulas!D81 -> 0.35 | I18: =Formulas!E81 -> 0.35 | J18: =Formulas!F81 -> 0.35 | K18: =Formulas!G81 -> 0.35 | L18: =Formulas!H81 -> 0.35 | M18: =Formulas!I81 -> 0.35 | N18: =Formulas!J81 -> 0.35 | ... P18: =Formulas!L81 -> 0.35
D19: Tax Rate | E19: % of EBT | G19: =Formulas!C85 -> 0.25 | H19: =Formulas!D85 -> 0.25 | I19: =Formulas!E85 -> 0.25 | J19: =Formulas!F85 -> 0.25 | K19: =Formulas!G85 -> 0.25 | L19: =Formulas!H85 -> 0.25 | M19: =Formulas!I85 -> 0.25 | N19: =Formulas!J85 -> 0.25 | ... P19: =Formulas!L85 -> 0.25
C21: Balance Sheet
D22: Accounts Receivable | E22: days | G22: =Formulas!C89 -> 40 | H22: =Formulas!D89 -> 40 | I22: =Formulas!E89 -> 40 | J22: =Formulas!F89 -> 40 | K22: =Formulas!G89 -> 40 | L22: =Formulas!H89 -> 35 | M22: =Formulas!I89 -> 35 | N22: =Formulas!J89 -> 35 | ... P22: =Formulas!L89 -> 35
D23: Inventory | E23: days | G23: =Formulas!C93 -> 65 | H23: =Formulas!D93 -> 65 | I23: =Formulas!E93 -> 65 | J23: =Formulas!F93 -> 70 | K23: =Formulas!G93 -> 70 | L23: =Formulas!H93 -> 70 | M23: =Formulas!I93 -> 75 | N23: =Formulas!J93 -> 75 | ... P23: =Formulas!L93 -> 80
D24: Property, Plant and Equipment | E24: USD (initial) | G24: =Formulas!C97 -> 13500
D25: Accounts Payable | E25: days | G25: =Formulas!C101 -> 50 | H25: =Formulas!D101 -> 50 | I25: =Formulas!E101 -> 50 | J25: =Formulas!F101 -> 50 | K25: =Formulas!G101 -> 50 | L25: =Formulas!H101 -> 45 | M25: =Formulas!I101 -> 45 | N25: =Formulas!J101 -> 45 | ... P25: =Formulas!L101 -> 45
D26: Accrued Expenses and Other | E26: % of total revenue | G26: =Formulas!C105 -> 0.045 | H26: =Formulas!D105 -> 0.045 | I26: =Formulas!E105 -> 0.045 | J26: =Formulas!F105 -> 0.045 | K26: =Formulas!G105 -> 0.045 | L26: =Formulas!H105 -> 0.045 | M26: =Formulas!I105 -> 0.045 | N26: =Formulas!J105 -> 0.045 | ... P26: =Formulas!L105 -> 0.045
D27: Capital Expenditures | E27: =Profile!$F$10 -> USD | G27: =Formulas!C109 -> 8000 | H27: =Formulas!D109 -> 10000 | I27: =Formulas!E109 -> 12000 | J27: =Formulas!F109 -> 12000 | K27: =Formulas!G109 -> 15000 | L27: =Formulas!H109 -> 18000 | M27: =Formulas!I109 -> 15000 | N27: =Formulas!J109 -> 12000 | ... P27: =Formulas!L109 -> 8000
C29: Financing
D30: Interest Rate (% of Debt) | E30: % | G30: =Formulas!C113 -> 0.055 | H30: =Formulas!D113 -> 0.055 | I30: =Formulas!E113 -> 0.055 | J30: =Formulas!F113 -> 0.055 | K30: =Formulas!G113 -> 0.055 | L30: =Formulas!H113 -> 0.055 | M30: =Formulas!I113 -> 0.055 | N30: =Formulas!J113 -> 0.055 | ... P30: =Formulas!L113 -> 0.055
D31: Long-Term Debt | E31: USD (Initial) | G31: =Formulas!C117 -> 60000
D32: Equity Capital | E32: USD | G32: =Formulas!C121 -> 110000 | H32: =Formulas!D121 -> 110000 | I32: =Formulas!E121 -> 110000 | J32: =Formulas!F121 -> 110000 | K32: =Formulas!G121 -> 110000 | L32: =Formulas!H121 -> 110000 | M32: =Formulas!I121 -> 110000 | N32: =Formulas!J121 -> 110000 | ... P32: =Formulas!L121 -> 110000
D33: Debt Issued/(Repaid) | E33: =Profile!$F$10 -> USD | G33: =Formulas!C125 -> -5000 | H33: =Formulas!D125 -> -5000 | I33: =Formulas!E125 -> -5000 | J33: =Formulas!F125 -> -5000 | K33: =Formulas!G125 -> -5000 | L33: =Formulas!H125 -> -5000 | M33: =Formulas!I125 -> -5000 | N33: =Formulas!J125 -> -5000 | ... P33: =Formulas!L125 -> -5000
D34: Equity Issued/(Repaid) | E34: =Profile!$F$10 -> USD | G34: =Formulas!C129 -> 0 | H34: =Formulas!D129 -> 0 | I34: =Formulas!E129 -> 0 | J34: =Formulas!F129 -> 0 | K34: =Formulas!G129 -> 0 | L34: =Formulas!H129 -> 0 | M34: =Formulas!I129 -> 0 | N34: =Formulas!J129 -> 0 | ... P34: =Formulas!L129 -> 0
D35: Dividends | E35: % of net income | G35: =Formulas!C133 -> 0.15 | H35: =Formulas!D133 -> 0.15 | I35: =Formulas!E133 -> 0.15 | J35: =Formulas!F133 -> 0.15 | K35: =Formulas!G133 -> 0.15 | L35: =Formulas!H133 -> 0.15 | M35: =Formulas!I133 -> 0.15 | N35: =Formulas!J133 -> 0.15 | ... P35: =Formulas!L133 -> 0.15
C37: Base Case Scenario
C38: Income Statement
D39: Revenue Growth | E39: % change | H39: 0.06 | I39: 0.05 | J39: 0.04 | K39: 0.03 | L39: 0.03 | M39: 0.02 | N39: 0.02 | O39: 0.02 | P39: 0.02
D40: Service Cost | E40: % of service revenue | H40: 0.25 | I40: 0.25 | J40: 0.24 | K40: 0.24 | L40: 0.23 | M40: 0.23 | N40: 0.22 | O40: 0.22 | P40: 0.21
D41: Product Cost | E41: % of product revenue | H41: 0.4 | I41: 0.38 | J41: 0.37 | K41: 0.36 | L41: 0.35 | M41: 0.35 | N41: 0.34 | O41: 0.34 | P41: 0.34
D42: Direct Labor Cost | E42: % of total revenue | G42: 0.18 | H42: 0.18 | I42: 0.18 | J42: 0.18 | K42: 0.18 | L42: 0.18 | M42: 0.18 | N42: 0.18 | O42: 0.18 | P42: 0.18
D43: Discount and Promotions | E43: % of total revenue | G43: 0.12 | H43: 0.11 | I43: 0.1 | J43: 0.09 | K43: 0.09 | L43: 0.08 | M43: 0.08 | N43: 0.07 | O43: 0.07 | P43: 0.07
D44: Salaries and Benefits | E44: =Profile!$F$10 -> USD | G44: 50000 | H44: 50000 | I44: 50000 | J44: 50000 | K44: 50000 | L44: 50000 | M44: 50000 | N44: 50000 | O44: 50000 | P44: 50000
D45: Sales and Marketing | E45: % of total revenue | G45: 0.04 | H45: 0.04 | I45: 0.035 | J45: 0.035 | K45: 0.035 | L45: 0.035 | M45: 0.03 | N45: 0.03 | O45: 0.03 | P45: 0.03
D46: General and Administration | E46: =Profile!$F$10 -> USD | G46: 35000 | H46: 35000 | I46: 35000 | J46: 35000 | K46: 35000 | L46: 35000 | M46: 35000 | N46: 35000 | O46: 35000 | P46: 35000
D47: Credit Card Fees | E47: % of total revenue | G47: 0.008 | H47: 0.008 | I47: 0.008 | J47: 0.008 | K47: 0.008 | L47: 0.008 | M47: 0.008 | N47: 0.008 | O47: 0.008 | P47: 0.008
D48: Depreciation and Amortization | E48: % of PP&E | G48: 0.35 | H48: 0.35 | I48: 0.35 | J48: 0.35 | K48: 0.35 | L48: 0.35 | M48: 0.35 | N48: 0.35 | O48: 0.35 | P48: 0.35
D49: Tax Rate | E49: % of EBT | G49: 0.25 | H49: 0.25 | I49: 0.25 | J49: 0.25 | K49: 0.25 | L49: 0.25 | M49: 0.25 | N49: 0.25 | O49: 0.25 | P49: 0.25
C51: Balance Sheet
D52: Accounts Receivable | E52: days | G52: 40 | H52: 40 | I52: 40 | J52: 40 | K52: 40 | L52: 35 | M52: 35 | N52: 35 | O52: 35 | P52: 35
D53: Inventory | E53: days | G53: 65 | H53: 65 | I53: 65 | J53: 70 | K53: 70 | L53: 70 | M53: 75 | N53: 75 | O53: 80 | P53: 80
D54: Property, Plant and Equipment | E54: USD (initial) | G54: 13500
D55: Accounts Payable | E55: days | G55: 50 | H55: 50 | I55: 50 | J55: 50 | K55: 50 | L55: 45 | M55: 45 | N55: 45 | O55: 45 | P55: 45
D56: Accrued Expenses and Other | E56: % of total revenue | G56: 0.045 | H56: 0.045 | I56: 0.045 | J56: 0.045 | K56: 0.045 | L56: 0.045 | M56: 0.045 | N56: 0.045 | O56: 0.045 | P56: 0.045
D57: Capital Expenditures | E57: =Profile!$F$10 -> USD | G57: 8000 | H57: 10000 | I57: 12000 | J57: 12000 | K57: 15000 | L57: 18000 | M57: 15000 | N57: 12000 | O57: 10000 | P57: 8000
C59: Financing
D60: Interest Rate (% of Debt) | E60: % | G60: 0.055 | H60: 0.055 | I60: 0.055 | J60: 0.055 | K60: 0.055 | L60: 0.055 | M60: 0.055 | N60: 0.055 | O60: 0.055 | P60: 0.055
D61: Long-Term Debt | E61: USD (Initial) | G61: 60000
D62: Equity Capital | E62: USD | G62: 110000 | H62: 110000 | I62: 110000 | J62: 110000 | K62: 110000 | L62: 110000 | M62: 110000 | N62: 110000 | O62: 110000 | P62: 110000
D63: Debt Issued/(Repaid) | E63: =Profile!$F$10 -> USD | G63: -5000 | H63: -5000 | I63: -5000 | J63: -5000 | K63: -5000 | L63: -5000 | M63: -5000 | N63: -5000 | O63: -5000 | P63: -5000
D64: Equity Issued/(Repaid) | E64: =Profile!$F$10 -> USD | H64: 0
D65: Dividends | E65: % of net income | G65: 0.15 | H65: 0.15 | I65: 0.15 | J65: 0.15 | K65: 0.15 | L65: 0.15 | M65: 0.15 | N65: 0.15 | O65: 0.15 | P65: 0.15
C67: Best Case Scenario
C68: Income Statement
D69: Revenue Growth | E69: % change | H69: 0.08 | I69: 0.07 | J69: 0.06 | K69: 0.05 | L69: 0.05 | M69: 0.04 | N69: 0.04 | O69: 0.03 | P69: 0.03
D70: Service Cost | E70: % of service revenue | H70: 0.18 | I70: 0.18 | J70: 0.17 | K70: 0.17 | L70: 0.17 | M70: 0.16 | N70: 0.16 | O70: 0.16 | P70: 0.15
D71: Product Cost | E71: % of product revenue | H71: 0.4 | I71: 0.38 | J71: 0.37 | K71: 0.36 | L71: 0.35 | M71: 0.35 | N71: 0.34 | O71: 0.34 | P71: 0.33
D72: Direct Labor Cost | E72: % of total revenue | G72: 0.17 | H72: 0.17 | I72: 0.17 | J72: 0.17 | K72: 0.17 | L72: 0.17 | M72: 0.17 | N72: 0.17 | O72: 0.17 | P72: 0.17
D73: Discount and Promotions | E73: % of total revenue | G73: 0.12 | H73: 0.11 | I73: 0.1 | J73: 0.1 | K73: 0.09 | L73: 0.09 | M73: 0.08 | N73: 0.08 | O73: 0.08 | P73: 0.07
D74: Salaries and Benefits | E74: =Profile!$F$10 -> USD | G74: 50000 | H74: 50000 | I74: 50000 | J74: 50000 | K74: 50000 | L74: 50000 | M74: 50000 | N74: 50000 | O74: 50000 | P74: 50000
D75: Sales and Marketing | E75: % of total revenue | G75: 0.04 | H75: 0.04 | I75: 0.035 | J75: 0.035 | K75: 0.035 | L75: 0.03 | M75: 0.03 | N75: 0.03 | O75: 0.03 | P75: 0.025
D76: General and Administration | E76: =Profile!$F$10 -> USD | G76: 38000 | H76: 38000 | I76: 38000 | J76: 38000 | K76: 38000 | L76: 38000 | M76: 38000 | N76: 38000 | O76: 38000 | P76: 38000
D77: Credit Card Fees | E77: % of total revenue | G77: 0.008 | H77: 0.008 | I77: 0.008 | J77: 0.008 | K77: 0.008 | L77: 0.008 | M77: 0.008 | N77: 0.008 | O77: 0.008 | P77: 0.008
D78: Depreciation and Amortization | E78: % of PP&E | G78: 0.35 | H78: 0.35 | I78: 0.35 | J78: 0.35 | K78: 0.35 | L78: 0.35 | M78: 0.35 | N78: 0.35 | O78: 0.35 | P78: 0.35
D79: Tax Rate | E79: % of EBT | G79: 0.25 | H79: 0.25 | I79: 0.25 | J79: 0.25 | K79: 0.25 | L79: 0.25 | M79: 0.25 | N79: 0.25 | O79: 0.25 | P79: 0.25
C81: Balance Sheet
D82: Accounts Receivable | E82: days | G82: 40 | H82: 40 | I82: 40 | J82: 40 | K82: 40 | L82: 35 | M82: 35 | N82: 35 | O82: 35 | P82: 35
D83: Inventory | E83: days | G83: 65 | H83: 65 | I83: 65 | J83: 70 | K83: 70 | L83: 70 | M83: 75 | N83: 75 | O83: 80 | P83: 80
D84: Property, Plant and Equipment | E84: USD (initial) | G84: 18000
D85: Accounts Payable | E85: days | G85: 50 | H85: 50 | I85: 50 | J85: 50 | K85: 50 | L85: 45 | M85: 45 | N85: 45 | O85: 45 | P85: 45
D86: Accrued Expenses and Other | E86: % of total revenue | G86: 0.045 | H86: 0.045 | I86: 0.045 | J86: 0.045 | K86: 0.045 | L86: 0.045 | M86: 0.045 | N86: 0.045 | O86: 0.045 | P86: 0.045
D87: Capital Expenditures | E87: =Profile!$F$10 -> USD | G87: 12000 | H87: 15000 | I87: 20000 | J87: 20000 | K87: 25000 | L87: 25000 | M87: 20000 | N87: 15000 | O87: 10000 | P87: 5000
C89: Financing
D90: Interest Rate (% of Debt) | E90: % | G90: 0.055 | H90: 0.055 | I90: 0.055 | J90: 0.055 | K90: 0.055 | L90: 0.055 | M90: 0.055 | N90: 0.055 | O90: 0.055 | P90: 0.055
D91: Long-Term Debt | E91: USD (Initial) | G91: 60000
D92: Equity Capital | E92: USD | G92: 120000 | H92: 120000 | I92: 120000 | J92: 120000 | K92: 120000 | L92: 120000 | M92: 120000 | N92: 120000 | O92: 120000 | P92: 120000
D93: Debt Issued/(Repaid) | E93: =Profile!$F$10 -> USD | G93: -5000 | H93: -5000 | I93: -5000 | J93: -5000 | K93: -5000 | L93: -5000 | M93: -5000 | N93: -5000 | O93: -5000 | P93: -5000
D94: Equity Issued/(Repaid) | E94: =Profile!$F$10 -> USD | G94: 0
D95: Dividends | E95: % of net income | G95: 0.12 | H95: 0.12 | I95: 0.12 | J95: 0.12 | K95: 0.12 | L95: 0.12 | M95: 0.12 | N95: 0.12 | O95: 0.12 | P95: 0.12
C97: Worst Case Scenario
C98: Income Statement
D99: Revenue Growth | E99: % change | H99: 0.02 | I99: 0.02 | J99: 0.01 | K99: 0.01 | L99: 0.01 | M99: 0 | N99: 0 | O99: 0 | P99: -0.01
D100: Service Cost | E100: % of service revenue | H100: 0.3 | I100: 0.3 | J100: 0.32 | K100: 0.32 | L100: 0.33 | M100: 0.34 | N100: 0.34 | O100: 0.35 | P100: 0.36
D101: Product Cost | E101: % of product revenue | H101: 0.55 | I101: 0.56 | J101: 0.57 | K101: 0.58 | L101: 0.58 | M101: 0.59 | N101: 0.6 | O101: 0.6 | P101: 0.6
D102: Direct Labor Cost | E102: % of total revenue | G102: 0.22 | H102: 0.22 | I102: 0.22 | J102: 0.22 | K102: 0.22 | L102: 0.22 | M102: 0.22 | N102: 0.22 | O102: 0.22 | P102: 0.22
D103: Discount and Promotions | E103: % of total revenue | G103: 0.18 | H103: 0.18 | I103: 0.17 | J103: 0.17 | K103: 0.16 | L103: 0.16 | M103: 0.16 | N103: 0.15 | O103: 0.15 | P103: 0.14
D104: Salaries and Benefits | E104: =Profile!$F$10 -> USD | G104: 40000 | H104: 40000 | I104: 40000 | J104: 40000 | K104: 40000 | L104: 40000 | M104: 40000 | N104: 40000 | O104: 40000 | P104: 40000
D105: Sales and Marketing | E105: % of total revenue | G105: 0.05 | H105: 0.05 | I105: 0.05 | J105: 0.045 | K105: 0.045 | L105: 0.04 | M105: 0.04 | N105: 0.04 | O105: 0.035 | P105: 0.035
D106: General and Administration | E106: =Profile!$F$10 -> USD | G106: 45000 | H106: 45000 | I106: 45000 | J106: 45000 | K106: 45000 | L106: 45000 | M106: 45000 | N106: 45000 | O106: 45000 | P106: 45000
D107: Credit Card Fees | E107: % of total revenue | G107: 0.012 | H107: 0.012 | I107: 0.012 | J107: 0.012 | K107: 0.012 | L107: 0.012 | M107: 0.012 | N107: 0.012 | O107: 0.012 | P107: 0.012
D108: Depreciation and Amortization | E108: % of PP&E | G108: 0.45 | H108: 0.45 | I108: 0.45 | J108: 0.45 | K108: 0.45 | L108: 0.45 | M108: 0.45 | N108: 0.45 | O108: 0.45 | P108: 0.45
D109: Tax Rate | E109: % of EBT | G109: 0.31 | H109: 0.31 | I109: 0.31 | J109: 0.31 | K109: 0.31 | L109: 0.31 | M109: 0.31 | N109: 0.31 | O109: 0.31 | P109: 0.31
C111: Balance Sheet
...

Sheet Actual FS
A1: © Person0811. All rights reserved.
A2: MENU | B2: =Profile!F6 -> Person0811
C4: 12 Month Actual Financial Statement
C5: =Formulas!A3 -> Amounts in USD
H6: =Profile!F8 -> 2025
C7: Income Statement | H7: =Formulas!C41 -> January | I7: =Formulas!D41 -> February | J7: =Formulas!E41 -> March | K7: =Formulas!F41 -> April | L7: =Formulas!G41 -> May | M7: =Formulas!H41 -> June | N7: =Formulas!I41 -> July | O7: =Formulas!J41 -> August | ... S7: =Formulas!N41 -> December | T7: FY
D8: Service Sales | H8: 35000 | I8: 35000 | J8: 35000 | K8: 35000 | L8: 35000 | M8: 35000 | N8: 35000 | O8: 35000 | P8: 35000 | Q8: 35000 | R8: 35000 | S8: 35000 | T8: =SUM(H8:S8) -> 420000
D9: Product Sales | H9: 10000 | I9: 10000 | J9: 10000 | K9: 10000 | L9: 10000 | M9: 10000 | N9: 10000 | O9: 10000 | P9: 10000 | Q9: 10000 | R9: 10000 | S9: 10000 | T9: =SUM(H9:S9) -> 120000
C10: Total Sales | H10: =SUM(H8:H9) -> 45000 | I10: =SUM(I8:I9) -> 45000 | J10: =SUM(J8:J9) -> 45000 | K10: =SUM(K8:K9) -> 45000 | L10: =SUM(L8:L9) -> 45000 | M10: =SUM(M8:M9) -> 45000 | N10: =SUM(N8:N9) -> 45000 | O10: =SUM(O8:O9) -> 45000 | ... T10: =SUM(T8:T9) -> 540000
D12: Service Cost | H12: 7000 | I12: 7000 | J12: 7000 | K12: 7000 | L12: 7000 | M12: 7000 | N12: 7000 | O12: 7000 | P12: 7000 | Q12: 7000 | R12: 7000 | S12: 7000 | T12: =SUM(H12:S12) -> 84000
D13: Product Cost | H13: 5000 | I13: 5000 | J13: 5000 | K13: 5000 | L13: 5000 | M13: 5000 | N13: 5000 | O13: 5000 | P13: 5000 | Q13: 5000 | R13: 5000 | S13: 5000 | T13: =SUM(H13:S13) -> 60000
D14: Direct Labor Cost | H14: 9000 | I14: 9000 | J14: 9000 | K14: 9000 | L14: 9000 | M14: 9000 | N14: 9000 | O14: 9000 | P14: 9000 | Q14: 9000 | R14: 9000 | S14: 9000 | T14: =SUM(H14:S14) -> 108000
D15: Discounts and Promotions | H15: 7000 | I15: 7000 | J15: 7000 | K15: 7000 | L15: 7000 | M15: 7000 | N15: 7000 | O15: 7000 | P15: 7000 | Q15: 7000 | R15: 7000 | S15: 7000 | T15: =SUM(H15:S15) -> 84000
C16: Total Cost of Sales | H16: =SUM(H12:H15) -> 28000 | I16: =SUM(I12:I15) -> 28000 | J16: =SUM(J12:J15) -> 28000 | K16: =SUM(K12:K15) -> 28000 | L16: =SUM(L12:L15) -> 28000 | M16: =SUM(M12:M15) -> 28000 | N16: =SUM(N12:N15) -> 28000 | O16: =SUM(O12:O15) -> 28000 | ... T16: =SUM(T12:T15) -> 336000
C18: Gross Profit | H18: =H10-H16 -> 17000 | I18: =I10-I16 -> 17000 | J18: =J10-J16 -> 17000 | K18: =K10-K16 -> 17000 | L18: =L10-L16 -> 17000 | M18: =M10-M16 -> 17000 | N18: =N10-N16 -> 17000 | O18: =O10-O16 -> 17000 | ... T18: =T10-T16 -> 204000
C19: Gross Margin % | H19: =IFERROR(H18/H10,0) -> 0.37777778 | I19: =IFERROR(I18/I10,0) -> 0.37777778 | J19: =IFERROR(J18/J10,0) -> 0.37777778 | K19: =IFERROR(K18/K10,0) -> 0.37777778 | L19: =IFERROR(L18/L10,0) -> 0.37777778 | M19: =IFERROR(M18/M10,0) -> 0.37777778 | N19: =IFERROR(N18/N10,0) -> 0.37777778 | O19: =IFERROR(O18/O10,0) -> 0.37777778 | ... T19: =IFERROR(T18/T10,0) -> 0.37777778
D21: Salaries and Benefits | H21: 4000 | I21: 4000 | J21: 4000 | K21: 4000 | L21: 4000 | M21: 4000 | N21: 4000 | O21: 4000 | P21: 4000 | Q21: 4000 | R21: 4000 | S21: 4000 | T21: =SUM(H21:S21) -> 48000
D22: Sales and Marketing | H22: 2500 | I22: 2500 | J22: 2500 | K22: 2500 | L22: 2500 | M22: 2500 | N22: 2500 | O22: 2500 | P22: 2500 | Q22: 2500 | R22: 2500 | S22: 2500 | T22: =SUM(H22:S22) -> 30000
D23: General and Administration | H23: 3500 | I23: 3500 | J23: 3500 | K23: 3500 | L23: 3500 | M23: 3500 | N23: 3500 | O23: 3500 | P23: 3500 | Q23: 3500 | R23: 3500 | S23: 3500 | T23: =SUM(H23:S23) -> 42000
D24: Credit Card Fees | H24: 450 | I24: 450 | J24: 450 | K24: 450 | L24: 450 | M24: 450 | N24: 450 | O24: 450 | P24: 450 | Q24: 450 | R24: 450 | S24: 450 | T24: =SUM(H24:S24) -> 5400
D25: Depreciation and Amortization | H25: 800 | I25: 800 | J25: 800 | K25: 800 | L25: 800 | M25: 800 | N25: 800 | O25: 800 | P25: 800 | Q25: 800 | R25: 800 | S25: 800 | T25: =SUM(H25:S25) -> 9600
C26: Total Operating Expenses | H26: =SUM(H21:H25) -> 11250 | I26: =SUM(I21:I25) -> 11250 | J26: =SUM(J21:J25) -> 11250 | K26: =SUM(K21:K25) -> 11250 | L26: =SUM(L21:L25) -> 11250 | M26: =SUM(M21:M25) -> 11250 | N26: =SUM(N21:N25) -> 11250 | O26: =SUM(O21:O25) -> 11250 | ... T26: =SUM(T21:T25) -> 135000
C28: Operating Profit (EBIT) | H28: =H18-H26 -> 5750 | I28: =I18-I26 -> 5750 | J28: =J18-J26 -> 5750 | K28: =K18-K26 -> 5750 | L28: =L18-L26 -> 5750 | M28: =M18-M26 -> 5750 | N28: =N18-N26 -> 5750 | O28: =O18-O26 -> 5750 | ... T28: =T18-T26 -> 69000
C29: Operating Margin % | H29: =IFERROR(H28/H10,0) -> 0.12777778 | I29: =IFERROR(I28/I10,0) -> 0.12777778 | J29: =IFERROR(J28/J10,0) -> 0.12777778 | K29: =IFERROR(K28/K10,0) -> 0.12777778 | L29: =IFERROR(L28/L10,0) -> 0.12777778 | M29: =IFERROR(M28/M10,0) -> 0.12777778 | N29: =IFERROR(N28/N10,0) -> 0.12777778 | O29: =IFERROR(O28/O10,0) -> 0.12777778 | ... T29: =IFERROR(T28/T10,0) -> 0.12777778
D31: Interest | H31: 450 | I31: 450 | J31: 450 | K31: 450 | L31: 450 | M31: 450 | N31: 450 | O31: 450 | P31: 450 | Q31: 450 | R31: 450 | S31: 450 | T31: =SUM(H31:S31) -> 5400
C32: Earnings Before Taxes (EBT) | H32: =H28-H31 -> 5300 | I32: =I28-I31 -> 5300 | J32: =J28-J31 -> 5300 | K32: =K28-K31 -> 5300 | L32: =L28-L31 -> 5300 | M32: =M28-M31 -> 5300 | N32: =N28-N31 -> 5300 | O32: =O28-O31 -> 5300 | ... T32: =T28-T31 -> 63600
D34: Income Taxes | H34: 1700 | I34: 1700 | J34: 1700 | K34: 1700 | L34: 1700 | M34: 1700 | N34: 1700 | O34: 1700 | P34: 1700 | Q34: 1700 | R34: 1700 | S34: 1700 | T34: =SUM(H34:S34) -> 20400
C35: Net Income | H35: =H32-H34 -> 3600 | I35: =I32-I34 -> 3600 | J35: =J32-J34 -> 3600 | K35: =K32-K34 -> 3600 | L35: =L32-L34 -> 3600 | M35: =M32-M34 -> 3600 | N35: =N32-N34 -> 3600 | O35: =O32-O34 -> 3600 | ... T35: =T32-T34 -> 43200
C36: Net Profit Margin % | H36: =IFERROR(H35/H10,0) -> 0.08 | I36: =IFERROR(I35/I10,0) -> 0.08 | J36: =IFERROR(J35/J10,0) -> 0.08 | K36: =IFERROR(K35/K10,0) -> 0.08 | L36: =IFERROR(L35/L10,0) -> 0.08 | M36: =IFERROR(M35/M10,0) -> 0.08 | N36: =IFERROR(N35/N10,0) -> 0.08 | O36: =IFERROR(O35/O10,0) -> 0.08 | ... T36: =IFERROR(T35/T10,0) -> 0.08
C38: Balance Sheet
C39: Current Assets
D40: Cash and Cash Equivalents | H40: =H91 -> 188000 | I40: =I91 -> 186000 | J40: =J91 -> 184000 | K40: =K91 -> 182000 | L40: =L91 -> 180000 | M40: =M91 -> 178000 | N40: =N91 -> 176000 | O40: =O91 -> 174000 | ... S40: =S91 -> 166000 | T40: =S40 -> 166000
D41: Accounts Receivable | H41: 5500 | I41: 11000 | J41: 16500 | K41: 22000 | L41: 27500 | M41: 33000 | N41: 38500 | O41: 44000 | P41: 49500 | Q41: 55000 | R41: 60500 | S41: 66000 | T41: =S41 -> 66000
D42: Inventory | H42: 5300 | I42: 10600 | J42: 15900 | K42: 21200 | L42: 26500 | M42: 31800 | N42: 37100 | O42: 42400 | P42: 47700 | Q42: 53000 | R42: 58300 | S42: 63600 | T42: =S42 -> 63600
D43: Total Current Assets | H43: =SUM(H40:H42) -> 198800 | I43: =SUM(I40:I42) -> 207600 | J43: =SUM(J40:J42) -> 216400 | K43: =SUM(K40:K42) -> 225200 | L43: =SUM(L40:L42) -> 234000 | M43: =SUM(M40:M42) -> 242800 | N43: =SUM(N40:N42) -> 251600 | O43: =SUM(O40:O42) -> 260400 | ... T43: =SUM(T40:T42) -> 295600
C45: Non-Current Assets
D46: Property, Plant and Equipment | H46: 1500 | I46: 3000 | J46: 4500 | K46: 6000 | L46: 7500 | M46: 9000 | N46: 10500 | O46: 12000 | P46: 13500 | Q46: 15000 | R46: 16500 | S46: 18000 | T46: =S46 -> 18000
D47: Total Non-Current Assets | H47: =SUM(H46) -> 1500 | I47: =SUM(I46) -> 3000 | J47: =SUM(J46) -> 4500 | K47: =SUM(K46) -> 6000 | L47: =SUM(L46) -> 7500 | M47: =SUM(M46) -> 9000 | N47: =SUM(N46) -> 10500 | O47: =SUM(O46) -> 12000 | ... T47: =SUM(T46) -> 18000
C48: Total Assets | H48: =H43+H47 -> 200300 | I48: =I43+I47 -> 210600 | J48: =J43+J47 -> 220900 | K48: =K43+K47 -> 231200 | L48: =L43+L47 -> 241500 | M48: =M43+M47 -> 251800 | N48: =N43+N47 -> 262100 | O48: =O43+O47 -> 272400 | ... T48: =T43+T47 -> 313600
C50: Current Liabilities
D51: Account Payable | H51: 4500 | I51: 9000 | J51: 13500 | K51: 18000 | L51: 22500 | M51: 27000 | N51: 31500 | O51: 36000 | P51: 40500 | Q51: 45000 | R51: 49500 | S51: 54000 | T51: =S51 -> 54000
D52: Accrued Expenses and Other | H52: 2200 | I52: 4400 | J52: 6600 | K52: 8800 | L52: 11000 | M52: 13200 | N52: 15400 | O52: 17600 | P52: 19800 | Q52: 22000 | R52: 24200 | S52: 26400 | T52: =S52 -> 26400
D53: Total Current Liabilities | H53: =SUM(H51:H52) -> 6700 | I53: =SUM(I51:I52) -> 13400 | J53: =SUM(J51:J52) -> 20100 | K53: =SUM(K51:K52) -> 26800 | L53: =SUM(L51:L52) -> 33500 | M53: =SUM(M51:M52) -> 40200 | N53: =SUM(N51:N52) -> 46900 | O53: =SUM(O51:O52) -> 53600 | ... T53: =SUM(T51:T52) -> 80400
C55: Non-Current Liabilities
D56: Long-Term Debt | H56: 80000 | I56: 80000 | J56: 80000 | K56: 80000 | L56: 80000 | M56: 80000 | N56: 80000 | O56: 80000 | P56: 80000 | Q56: 80000 | R56: 80000 | S56: 80000 | T56: =S56 -> 80000
D57: Total Non-Current Liabilities | H57: =SUM(H56) -> 80000 | I57: =SUM(I56) -> 80000 | J57: =SUM(J56) -> 80000 | K57: =SUM(K56) -> 80000 | L57: =SUM(L56) -> 80000 | M57: =SUM(M56) -> 80000 | N57: =SUM(N56) -> 80000 | O57: =SUM(O56) -> 80000 | ... T57: =SUM(T56) -> 80000
C58: Total Liabilities | H58: =H53+H57 -> 86700 | I58: =I53+I57 -> 93400 | J58: =J53+J57 -> 100100 | K58: =K53+K57 -> 106800 | L58: =L53+L57 -> 113500 | M58: =M53+M57 -> 120200 | N58: =N53+N57 -> 126900 | O58: =O53+O57 -> 133600 | ... T58: =T53+T57 -> 160400
C60: Shareholders' Equity
D61: Equity Capital | H61: 110000 | I61: 110000 | J61: 110000 | K61: 110000 | L61: 110000 | M61: 110000 | N61: 110000 | O61: 110000 | P61: 110000 | Q61: 110000 | R61: 110000 | S61: 110000 | T61: =S61 -> 110000
D62: Retained Earnings | H62: =H35+H86 -> 3600 | I62: =H62+I35+I86 -> 7200 | J62: =I62+J35+J86 -> 10800 | K62: =J62+K35+K86 -> 14400 | L62: =K62+L35+L86 -> 18000 | M62: =L62+M35+M86 -> 21600 | N62: =M62+N35+N86 -> 25200 | O62: =N62+O35+O86 -> 28800 | P62: =O62+P35+P86 -> 32400 | ... S62: =R62+S35+S86 -> 43200 | T62: =S62 -> 43200
D63: Total Shareholders' Equity | H63: =SUM(H61:H62) -> 113600 | I63: =SUM(I61:I62) -> 117200 | J63: =SUM(J61:J62) -> 120800 | K63: =SUM(K61:K62) -> 124400 | L63: =SUM(L61:L62) -> 128000 | M63: =SUM(M61:M62) -> 131600 | N63: =SUM(N61:N62) -> 135200 | O63: =SUM(O61:O62) -> 138800 | ... T63: =SUM(T61:T62) -> 153200
C64: Total Liabilities and Shareholders' Equity | H64: =H58+H63 -> 200300 | I64: =I58+I63 -> 210600 | J64: =J58+J63 -> 220900 | K64: =K58+K63 -> 231200 | L64: =L58+L63 -> 241500 | M64: =M58+M63 -> 251800 | N64: =N58+N63 -> 262100 | O64: =O58+O63 -> 272400 | ... T64: =T58+T63 -> 313600
D66: Reconcile | H66: =H48-H64 -> 0 | I66: =I48-I64 -> 0 | J66: =J48-J64 -> 0 | K66: =K48-K64 -> 0 | L66: =L48-L64 -> 0 | M66: =M48-M64 -> 0 | N66: =N48-N64 -> 0 | O66: =O48-O64 -> 0 | ... T66: =T48-T64 -> 0
C68: Cash Flow Statement
C69: Operating Cash Flow
D70: Net Income | H70: =H35 -> 3600 | I70: =I35 -> 3600 | J70: =J35 -> 3600 | K70: =K35 -> 3600 | L70: =L35 -> 3600 | M70: =M35 -> 3600 | N70: =N35 -> 3600 | O70: =O35 -> 3600 | ... S70: =S35 -> 3600 | T70: =SUM(H70:S70) -> 43200
D71: (+) Depreciation and Amortization | H71: =H25 -> 800 | I71: =I25 -> 800 | J71: =J25 -> 800 | K71: =K25 -> 800 | L71: =L25 -> 800 | M71: =M25 -> 800 | N71: =N25 -> 800 | O71: =O25 -> 800 | ... S71: =S25 -> 800 | T71: =SUM(H71:S71) -> 9600
D72: (-) Changes in Working Capital
E73: Accounts Receivable | H73: =0-H41 -> -5500 | I73: =H41-I41 -> -5500 | J73: =I41-J41 -> -5500 | K73: =J41-K41 -> -5500 | L73: =K41-L41 -> -5500 | M73: =L41-M41 -> -5500 | N73: =M41-N41 -> -5500 | O73: =N41-O41 -> -5500 | P73: =O41-P41 -> -5500 | ... S73: =R41-S41 -> -5500 | T73: =-T41 -> -66000
E74: Inventory | H74: =0-H42 -> -5300 | I74: =H42-I42 -> -5300 | J74: =I42-J42 -> -5300 | K74: =J42-K42 -> -5300 | L74: =K42-L42 -> -5300 | M74: =L42-M42 -> -5300 | N74: =M42-N42 -> -5300 | O74: =N42-O42 -> -5300 | P74: =O42-P42 -> -5300 | ... S74: =R42-S42 -> -5300 | T74: =-T42 -> -63600
E75: Accounts Payable | H75: =H51-0 -> 4500 | I75: =I51-H51 -> 4500 | J75: =J51-I51 -> 4500 | K75: =K51-J51 -> 4500 | L75: =L51-K51 -> 4500 | M75: =M51-L51 -> 4500 | N75: =N51-M51 -> 4500 | O75: =O51-N51 -> 4500 | P75: =P51-O51 -> 4500 | ... S75: =S51-R51 -> 4500 | T75: =T51 -> 54000
E76: Accrued Expenses and Other | H76: =H52-0 -> 2200 | I76: =I52-H52 -> 2200 | J76: =J52-I52 -> 2200 | K76: =K52-J52 -> 2200 | L76: =L52-K52 -> 2200 | M76: =M52-L52 -> 2200 | N76: =N52-M52 -> 2200 | O76: =O52-N52 -> 2200 | P76: =P52-O52 -> 2200 | ... S76: =S52-R52 -> 2200 | T76: =T52 -> 26400
C77: Cash from Operations | H77: =SUM(H70:H76) -> 300 | I77: =SUM(I70:I76) -> 300 | J77: =SUM(J70:J76) -> 300 | K77: =SUM(K70:K76) -> 300 | L77: =SUM(L70:L76) -> 300 | M77: =SUM(M70:M76) -> 300 | N77: =SUM(N70:N76) -> 300 | O77: =SUM(O70:O76) -> 300 | ... T77: =SUM(T70:T76) -> 3600
C79: Investing Cash Flow
D80: Purchase of property, plant and equipment | H80: -2300 | I80: -2300 | J80: -2300 | K80: -2300 | L80: -2300 | M80: -2300 | N80: -2300 | O80: -2300 | P80: -2300 | Q80: -2300 | R80: -2300 | S80: -2300 | T80: =SUM(H80:S80) -> -27600
C81: Cash from Investing | H81: =SUM(H80) -> -2300 | I81: =SUM(I80) -> -2300 | J81: =SUM(J80) -> -2300 | K81: =SUM(K80) -> -2300 | L81: =SUM(L80) -> -2300 | M81: =SUM(M80) -> -2300 | N81: =SUM(N80) -> -2300 | O81: =SUM(O80) -> -2300 | ... T81: =SUM(T80) -> -27600
C83: Financing Cash Flow
D84: Proceeds (Repayments) from Long-Term Debt and Other | H84: 80000 | T84: =SUM(H84:S84) -> 80000
D85: Proceeds (Repayments) from Equity | H85: 110000 | T85: =SUM(H85:S85) -> 110000
D86: Dividends
C87: Cash from Financing | H87: =SUM(H84:H86) -> 190000 | I87: =SUM(I84:I86) -> 0 | J87: =SUM(J84:J86) -> 0 | K87: =SUM(K84:K86) -> 0 | L87: =SUM(L84:L86) -> 0 | M87: =SUM(M84:M86) -> 0 | N87: =SUM(N84:N86) -> 0 | O87: =SUM(O84:O86) -> 0 | ... S87: =SUM(S84:S86) -> 0 | T87: =SUM(T84:T85) -> 190000
D89: Net Increase (decrease) in Cash | H89: =H77+H81+H87 -> 188000 | I89: =I77+I81+I87 -> -2000 | J89: =J77+J81+J87 -> -2000 | K89: =K77+K81+K87 -> -2000 | L89: =L77+L81+L87 -> -2000 | M89: =M77+M81+M87 -> -2000 | N89: =N77+N81+N87 -> -2000 | O89: =O77+O81+O87 -> -2000 | ... T89: =T77+T81+T87 -> 166000
D90: Opening Cash Balance | H90: 0 | I90: =H91 -> 188000 | J90: =I91 -> 186000 | K90: =J91 -> 184000 | L90: =K91 -> 182000 | M90: =L91 -> 180000 | N90: =M91 -> 178000 | O90: =N91 -> 176000 | P90: =O91 -> 174000 | ... S90: =R91 -> 168000 | T90: =H90 -> 0
C91: Closing Cash Balance | H91: =SUM(H89:H90) -> 188000 | I91: =SUM(I89:I90) -> 186000 | J91: =SUM(J89:J90) -> 184000 | K91: =SUM(K89:K90) -> 182000 | L91: =SUM(L89:L90) -> 180000 | M91: =SUM(M89:M90) -> 178000 | N91: =SUM(N89:N90) -> 176000 | O91: =SUM(O89:O90) -> 174000 | ... T91: =SUM(T89:T90) -> 166000

Sheet 12-Month Projection
A1: © Person0811. All rights reserved.
A2: MENU | B2: =Profile!F6 -> Person0811
C4: 12 Month Financial Projection
C5: =Formulas!A3 -> Amounts in USD
E6: Case Scenario | F6: =Scenario!E6 -> Base Case
E7: Days in Period | F7: 365 | H7: =Profile!F8 -> 2025
C8: Income Statement | H8: =Formulas!C41 -> January | I8: =Formulas!D41 -> February | J8: =Formulas!E41 -> March | K8: =Formulas!F41 -> April | L8: =Formulas!G41 -> May | M8: =Formulas!H41 -> June | N8: =Formulas!I41 -> July | O8: =Formulas!J41 -> August | ... S8: =Formulas!N41 -> December | T8: FY
D9: Service Sales | H9: =Revenue!G20 -> 17850 | I9: =Revenue!H20 -> 18025 | J9: =Revenue!I20 -> 18200 | K9: =Revenue!J20 -> 18375 | L9: =Revenue!K20 -> 19250 | M9: =Revenue!L20 -> 19600 | N9: =Revenue!M20 -> 18900 | O9: =Revenue!N20 -> 18375 | ... S9: =Revenue!R20 -> 19600 | T9: =SUM(H9:S9) -> 222250
D10: Product Sales | H10: =Revenue!G32 -> 17850 | I10: =Revenue!H32 -> 18025 | J10: =Revenue!I32 -> 18200 | K10: =Revenue!J32 -> 18375 | L10: =Revenue!K32 -> 19250 | M10: =Revenue!L32 -> 19600 | N10: =Revenue!M32 -> 18900 | O10: =Revenue!N32 -> 18375 | ... S10: =Revenue!R32 -> 19600 | T10: =SUM(H10:S10) -> 222250
C11: Total Sales | H11: =SUM(H9:H10) -> 35700 | I11: =SUM(I9:I10) -> 36050 | J11: =SUM(J9:J10) -> 36400 | K11: =SUM(K9:K10) -> 36750 | L11: =SUM(L9:L10) -> 38500 | M11: =SUM(M9:M10) -> 39200 | N11: =SUM(N9:N10) -> 37800 | O11: =SUM(O9:O10) -> 36750 | ... T11: =SUM(T9:T10) -> 444500
D13: Service Cost | H13: =Revenue!G49 -> 2677.5 | I13: =Revenue!H49 -> 2703.75 | J13: =Revenue!I49 -> 2730 | K13: =Revenue!J49 -> 2756.25 | L13: =Revenue!K49 -> 2887.5 | M13: =Revenue!L49 -> 2940 | N13: =Revenue!M49 -> 2835 | O13: =Revenue!N49 -> 2756.25 | ... S13: =Revenue!R49 -> 2940 | T13: =SUM(H13:S13) -> 33337.5
D14: Product Cost | H14: =Revenue!G61 -> 5355 | I14: =Revenue!H61 -> 5407.5 | J14: =Revenue!I61 -> 5460 | K14: =Revenue!J61 -> 5512.5 | L14: =Revenue!K61 -> 5775 | M14: =Revenue!L61 -> 5880 | N14: =Revenue!M61 -> 5670 | O14: =Revenue!N61 -> 5512.5 | ... S14: =Revenue!R61 -> 5880 | T14: =SUM(H14:S14) -> 66675
D15: Direct Labor Cost | H15: =Scenario!$G$12*H11 -> 6426 | I15: =Scenario!$G$12*I11 -> 6489 | J15: =Scenario!$G$12*J11 -> 6552 | K15: =Scenario!$G$12*K11 -> 6615 | L15: =Scenario!$G$12*L11 -> 6930 | M15: =Scenario!$G$12*M11 -> 7056 | N15: =Scenario!$G$12*N11 -> 6804 | O15: =Scenario!$G$12*O11 -> 6615 | ... S15: =Scenario!$G$12*S11 -> 7056 | T15: =SUM(H15:S15) -> 80010
D16: Discounts and Promotions | H16: =Scenario!$G$13*H11 -> 4284 | I16: =Scenario!$G$13*I11 -> 4326 | J16: =Scenario!$G$13*J11 -> 4368 | K16: =Scenario!$G$13*K11 -> 4410 | L16: =Scenario!$G$13*L11 -> 4620 | M16: =Scenario!$G$13*M11 -> 4704 | N16: =Scenario!$G$13*N11 -> 4536 | O16: =Scenario!$G$13*O11 -> 4410 | ... S16: =Scenario!$G$13*S11 -> 4704 | T16: =SUM(H16:S16) -> 53340
C17: Total Cost of Sales | H17: =SUM(H13:H16) -> 18742.5 | I17: =SUM(I13:I16) -> 18926.25 | J17: =SUM(J13:J16) -> 19110 | K17: =SUM(K13:K16) -> 19293.75 | L17: =SUM(L13:L16) -> 20212.5 | M17: =SUM(M13:M16) -> 20580 | N17: =SUM(N13:N16) -> 19845 | O17: =SUM(O13:O16) -> 19293.75 | ... T17: =SUM(T13:T16) -> 233362.5
C19: Gross Profit | H19: =H11-H17 -> 16957.5 | I19: =I11-I17 -> 17123.75 | J19: =J11-J17 -> 17290 | K19: =K11-K17 -> 17456.25 | L19: =L11-L17 -> 18287.5 | M19: =M11-M17 -> 18620 | N19: =N11-N17 -> 17955 | O19: =O11-O17 -> 17456.25 | ... T19: =T11-T17 -> 211137.5
C20: Gross Margin % | H20: =IFERROR(H19/H11,0) -> 0.475 | I20: =IFERROR(I19/I11,0) -> 0.475 | J20: =IFERROR(J19/J11,0) -> 0.475 | K20: =IFERROR(K19/K11,0) -> 0.475 | L20: =IFERROR(L19/L11,0) -> 0.475 | M20: =IFERROR(M19/M11,0) -> 0.475 | N20: =IFERROR(N19/N11,0) -> 0.475 | O20: =IFERROR(O19/O11,0) -> 0.475 | ... T20: =IFERROR(T19/T11,0) -> 0.475
D22: Salaries and Benefits | H22: =Scenario!$G$14/12 -> 4166.6667 | I22: =Scenario!$G$14/12 -> 4166.6667 | J22: =Scenario!$G$14/12 -> 4166.6667 | K22: =Scenario!$G$14/12 -> 4166.6667 | L22: =Scenario!$G$14/12 -> 4166.6667 | M22: =Scenario!$G$14/12 -> 4166.6667 | N22: =Scenario!$G$14/12 -> 4166.6667 | O22: =Scenario!$G$14/12 -> 4166.6667 | ... S22: =Scenario!$G$14/12 -> 4166.6667 | T22: =SUM(H22:S22) -> 50000
D23: Sales and Marketing | H23: =Scenario!$G$15*H11 -> 1428 | I23: =Scenario!$G$15*I11 -> 1442 | J23: =Scenario!$G$15*J11 -> 1456 | K23: =Scenario!$G$15*K11 -> 1470 | L23: =Scenario!$G$15*L11 -> 1540 | M23: =Scenario!$G$15*M11 -> 1568 | N23: =Scenario!$G$15*N11 -> 1512 | O23: =Scenario!$G$15*O11 -> 1470 | ... S23: =Scenario!$G$15*S11 -> 1568 | T23: =SUM(H23:S23) -> 17780
D24: General and Administration | H24: =Scenario!$G$16/12 -> 2916.6667 | I24: =Scenario!$G$16/12 -> 2916.6667 | J24: =Scenario!$G$16/12 -> 2916.6667 | K24: =Scenario!$G$16/12 -> 2916.6667 | L24: =Scenario!$G$16/12 -> 2916.6667 | M24: =Scenario!$G$16/12 -> 2916.6667 | N24: =Scenario!$G$16/12 -> 2916.6667 | O24: =Scenario!$G$16/12 -> 2916.6667 | ... S24: =Scenario!$G$16/12 -> 2916.6667 | T24: =SUM(H24:S24) -> 35000
D25: Credit Card Fees | H25: =Scenario!$G$17*H11 -> 285.6 | I25: =Scenario!$G$17*I11 -> 288.4 | J25: =Scenario!$G$17*J11 -> 291.2 | K25: =Scenario!$G$17*K11 -> 294 | L25: =Scenario!$G$17*L11 -> 308 | M25: =Scenario!$G$17*M11 -> 313.6 | N25: =Scenario!$G$17*N11 -> 302.4 | O25: =Scenario!$G$17*O11 -> 294 | ... S25: =Scenario!$G$17*S11 -> 313.6 | T25: =SUM(H25:S25) -> 3556
D26: Depreciation and Amortization | H26: =Scenario!$G$18*((Scenario!$G$24+Scenario!$G$27)/12) -> 627.08333 | I26: =H26 -> 627.08333 | J26: =I26 -> 627.08333 | K26: =J26 -> 627.08333 | L26: =K26 -> 627.08333 | M26: =L26 -> 627.08333 | N26: =M26 -> 627.08333 | O26: =N26 -> 627.08333 | P26: =O26 -> 627.08333 | ... S26: =R26 -> 627.08333 | T26: =SUM(H26:S26) -> 7525
C27: Total Operating Expenses | H27: =SUM(H22:H26) -> 9424.0167 | I27: =SUM(I22:I26) -> 9440.8167 | J27: =SUM(J22:J26) -> 9457.6167 | K27: =SUM(K22:K26) -> 9474.4167 | L27: =SUM(L22:L26) -> 9558.4167 | M27: =SUM(M22:M26) -> 9592.0167 | N27: =SUM(N22:N26) -> 9524.8167 | O27: =SUM(O22:O26) -> 9474.4167 | ... T27: =SUM(T22:T26) -> 113861
C29: Operating Profit (EBIT) | H29: =H19-H27 -> 7533.4833 | I29: =I19-I27 -> 7682.9333 | J29: =J19-J27 -> 7832.3833 | K29: =K19-K27 -> 7981.8333 | L29: =L19-L27 -> 8729.0833 | M29: =M19-M27 -> 9027.9833 | N29: =N19-N27 -> 8430.1833 | O29: =O19-O27 -> 7981.8333 | ... T29: =T19-T27 -> 97276.5
C30: Operating Margin % | H30: =IFERROR(H29/H11,0) -> 0.21102194 | I30: =IFERROR(I29/I11,0) -> 0.21311882 | J30: =IFERROR(J29/J11,0) -> 0.21517537 | K30: =IFERROR(K29/K11,0) -> 0.21719274 | L30: =IFERROR(L29/L11,0) -> 0.22672944 | M30: =IFERROR(M29/M11,0) -> 0.2303057 | N30: =IFERROR(N29/N11,0) -> 0.22302072 | O30: =IFERROR(O29/O11,0) -> 0.21719274 | ... T30: =IFERROR(T29/T11,0) -> 0.21884477
D32: Interest | H32: =Scenario!$G$30*((Scenario!$G$30*((Scenario!$G$31)/12)+H57)/12) -> 274.35069 | I32: =Scenario!$G$30*((H32+I57)/12) -> 272.438 | J32: =Scenario!$G$30*((I32+J57)/12) -> 270.51951 | K32: =Scenario!$G$30*((J32+K57)/12) -> 268.60099 | L32: =Scenario!$G$30*((K32+L57)/12) -> 266.68248 | M32: =Scenario!$G$30*((L32+M57)/12) -> 264.76396 | N32: =Scenario!$G$30*((M32+N57)/12) -> 262.84545 | O32: =Scenario!$G$30*((N32+O57)/12) -> 260.92693 | P32: =Scenario!$G$30*((O32+P57)/12) -> 259.00842 | ... S32: =Scenario!$G$30*((R32+S57)/12) -> 253.25287 | T32: =SUM(H32:S32) -> 3165.6506
C33: Earnings Before Taxes (EBT) | H33: =H29-H32 -> 7259.1326 | I33: =I29-I32 -> 7410.4953 | J33: =J29-J32 -> 7561.8638 | K33: =K29-K32 -> 7713.2323 | L33: =L29-L32 -> 8462.4009 | M33: =M29-M32 -> 8763.2194 | N33: =N29-N32 -> 8167.3379 | O33: =O29-O32 -> 7720.9064 | ... T33: =T29-T32 -> 94110.849
D35: Income Taxes | H35: =IF(H33>0,Scenario!$G$19*H33,0) -> 1814.7832 | I35: =IF(I33>0,Scenario!$G$19*I33,0) -> 1852.6238 | J35: =IF(J33>0,Scenario!$G$19*J33,0) -> 1890.466 | K35: =IF(K33>0,Scenario!$G$19*K33,0) -> 1928.3081 | L35: =IF(L33>0,Scenario!$G$19*L33,0) -> 2115.6002 | M35: =IF(M33>0,Scenario!$G$19*M33,0) -> 2190.8048 | N35: =IF(N33>0,Scenario!$G$19*N33,0) -> 2041.8345 | O35: =IF(O33>0,Scenario!$G$19*O33,0) -> 1930.2266 | ... T35: =IF(T33>0,Scenario!$G$19*T33,0) -> 23527.712
C36: Net Income | H36: =H33-H35 -> 5444.3495 | I36: =I33-I35 -> 5557.8715 | J36: =J33-J35 -> 5671.3979 | K36: =K33-K35 -> 5784.9243 | L36: =L33-L35 -> 6346.8006 | M36: =M33-M35 -> 6572.4145 | N36: =N33-N35 -> 6125.5034 | O36: =O33-O35 -> 5790.6798 | ... T36: =T33-T35 -> 70583.137
C37: Net Profit Margin % | H37: =IFERROR(H36/H11,0) -> 0.15250279 | I37: =IFERROR(I36/I11,0) -> 0.15417119 | J37: =IFERROR(J36/J11,0) -> 0.15580763 | K37: =IFERROR(K36/K11,0) -> 0.1574129 | L37: =IFERROR(L36/L11,0) -> 0.16485196 | M37: =IFERROR(M36/M11,0) -> 0.16766364 | N37: =IFERROR(N36/N11,0) -> 0.16205035 | O37: =IFERROR(O36/O11,0) -> 0.15756952 | ... T37: =IFERROR(T36/T11,0) -> 0.15879221
C39: Balance Sheet
C40: Current Assets
D41: Cash and Cash Equivalents | H41: =H92 -> 157595.38 | I41: =I92 -> 158757.09 | J41: =J92 -> 159985.15 | K41: =K92 -> 161279.54 | L41: =L92 -> 162900.74 | M41: =M92 -> 164653.4 | N41: =N92 -> 166146.82 | O41: =O92 -> 167446.1 | ... S41: =S92 -> 172720.6 | T41: =S41 -> 172720.6
D42: Accounts Receivable | H42: =Scenario!$G$22*H11/$F$7 -> 3912.3288 | I42: =Scenario!$G$22*I11/$F$7+H42 -> 7863.0137 | J42: =Scenario!$G$22*J11/$F$7+I42 -> 11852.055 | K42: =Scenario!$G$22*K11/$F$7+J42 -> 15879.452 | L42: =Scenario!$G$22*L11/$F$7+K42 -> 20098.63 | M42: =Scenario!$G$22*M11/$F$7+L42 -> 24394.521 | N42: =Scenario!$G$22*N11/$F$7+M42 -> 28536.986 | O42: =Scenario!$G$22*O11/$F$7+N42 -> 32564.384 | P42: =Scenario!$G$22*P11/$F$7+O42 -> 36323.288 | ... S42: =Scenario!$G$22*S11/$F$7+R42 -> 48712.329 | T42: =S42 -> 48712.329
D43: Inventory | H43: =Scenario!$G$23*H17/$F$7 -> 3337.7055 | I43: =Scenario!$G$23*I17/$F$7+H43 -> 6708.1336 | J43: =Scenario!$G$23*J17/$F$7+I43 -> 10111.284 | K43: =Scenario!$G$23*K17/$F$7+J43 -> 13547.158 | L43: =Scenario!$G$23*L17/$F$7+K43 -> 17146.644 | M43: =Scenario!$G$23*M17/$F$7+L43 -> 20811.575 | N43: =Scenario!$G$23*N17/$F$7+M43 -> 24345.616 | O43: =Scenario!$G$23*O17/$F$7+N43 -> 27781.49 | P43: =Scenario!$G$23*P17/$F$7+O43 -> 30988.305 | ... S43: =Scenario!$G$23*S17/$F$7+R43 -> 41557.705 | T43: =S43 -> 41557.705
D44: Total Current Assets | H44: =SUM(H41:H43) -> 164845.41 | I44: =SUM(I41:I43) -> 173328.24 | J44: =SUM(J41:J43) -> 181948.49 | K44: =SUM(K41:K43) -> 190706.15 | L44: =SUM(L41:L43) -> 200146.02 | M44: =SUM(M41:M43) -> 209859.5 | N44: =SUM(N41:N43) -> 219029.42 | O44: =SUM(O41:O43) -> 227791.98 | ... T44: =SUM(T41:T43) -> 262990.63
C46: Non-Current Assets
D47: Property, Plant and Equipment | H47: =(Scenario!$G$24+(Scenario!$G$27/12))-H26 -> 13539.583 | I47: =(Scenario!$G$27)/12-I26+H47 -> 13579.167 | J47: =(Scenario!$G$27)/12-J26+I47 -> 13618.75 | K47: =(Scenario!$G$27)/12-K26+J47 -> 13658.333 | L47: =(Scenario!$G$27)/12-L26+K47 -> 13697.917 | M47: =(Scenario!$G$27)/12-M26+L47 -> 13737.5 | N47: =(Scenario!$G$27)/12-N26+M47 -> 13777.083 | O47: =(Scenario!$G$27)/12-O26+N47 -> 13816.667 | P47: =(Scenario!$G$27)/12-P26+O47 -> 13856.25 | ... S47: =(Scenario!$G$27)/12-S26+R47 -> 13975 | T47: =S47 -> 13975
D48: Total Non-Current Assets | H48: =SUM(H47) -> 13539.583 | I48: =SUM(I47) -> 13579.167 | J48: =SUM(J47) -> 13618.75 | K48: =SUM(K47) -> 13658.333 | L48: =SUM(L47) -> 13697.917 | M48: =SUM(M47) -> 13737.5 | N48: =SUM(N47) -> 13777.083 | O48: =SUM(O47) -> 13816.667 | ... T48: =SUM(T47) -> 13975
C49: Total Assets | H49: =H44+H48 -> 178385 | I49: =I44+I48 -> 186907.41 | J49: =J44+J48 -> 195567.24 | K49: =K44+K48 -> 204364.49 | L49: =L44+L48 -> 213843.93 | M49: =M44+M48 -> 223597 | N49: =N44+N48 -> 232806.5 | O49: =O44+O48 -> 241608.64 | ... T49: =T44+T48 -> 276965.63
C51: Current Liabilities
D52: Account Payable | H52: =Scenario!$G$25*H17/$F$7 -> 2567.4658 | I52: =Scenario!$G$25*I17/$F$7+H52 -> 5160.1027 | J52: =Scenario!$G$25*J17/$F$7+I52 -> 7777.911 | K52: =Scenario!$G$25*K17/$F$7+J52 -> 10420.89 | L52: =Scenario!$G$25*L17/$F$7+K52 -> 13189.726 | M52: =Scenario!$G$25*M17/$F$7+L52 -> 16008.904 | N52: =Scenario!$G$25*N17/$F$7+M52 -> 18727.397 | O52: =Scenario!$G$25*O17/$F$7+N52 -> 21370.377 | P52: =Scenario!$G$25*P17/$F$7+O52 -> 23837.158 | ... S52: =Scenario!$G$25*S17/$F$7+R52 -> 31967.466 | T52: =S52 -> 31967.466
D53: Accrued Expenses and Other | H53: =Scenario!$G$26*H11 -> 1606.5 | I53: =Scenario!$G$26*I11+H53 -> 3228.75 | J53: =Scenario!$G$26*J11+I53 -> 4866.75 | K53: =Scenario!$G$26*K11+J53 -> 6520.5 | L53: =Scenario!$G$26*L11+K53 -> 8253 | M53: =Scenario!$G$26*M11+L53 -> 10017 | N53: =Scenario!$G$26*N11+M53 -> 11718 | O53: =Scenario!$G$26*O11+N53 -> 13371.75 | P53: =Scenario!$G$26*P11+O53 -> 14915.25 | ... S53: =Scenario!$G$26*S11+R53 -> 20002.5 | T53: =S53 -> 20002.5
D54: Total Current Liabilities | H54: =SUM(H52:H53) -> 4173.9658 | I54: =SUM(I52:I53) -> 8388.8527 | J54: =SUM(J52:J53) -> 12644.661 | K54: =SUM(K52:K53) -> 16941.39 | L54: =SUM(L52:L53) -> 21442.726 | M54: =SUM(M52:M53) -> 26025.904 | N54: =SUM(N52:N53) -> 30445.397 | O54: =SUM(O52:O53) -> 34742.127 | ... T54: =SUM(T52:T53) -> 51969.966
C56: Non-Current Liabilities
D57: Long-Term Debt | H57: =Scenario!$G$31+(Scenario!$G$33/12) -> 59583.333 | I57: =H57+I85 -> 59166.667 | J57: =I57+J85 -> 58750 | K57: =J57+K85 -> 58333.333 | L57: =K57+L85 -> 57916.667 | M57: =L57+M85 -> 57500 | N57: =M57+N85 -> 57083.333 | O57: =N57+O85 -> 56666.667 | P57: =O57+P85 -> 56250 | ... S57: =R57+S85 -> 55000 | T57: =S57 -> 55000
D58: Total Non-Current Liabilities | H58: =SUM(H57) -> 59583.333 | I58: =SUM(I57) -> 59166.667 | J58: =SUM(J57) -> 58750 | K58: =SUM(K57) -> 58333.333 | L58: =SUM(L57) -> 57916.667 | M58: =SUM(M57) -> 57500 | N58: =SUM(N57) -> 57083.333 | O58: =SUM(O57) -> 56666.667 | ... T58: =SUM(T57) -> 55000
C59: Total Liabilities | H59: =H54+H58 -> 63757.299 | I59: =I54+I58 -> 67555.519 | J59: =J54+J58 -> 71394.661 | K59: =K54+K58 -> 75274.724 | L59: =L54+L58 -> 79359.393 | M59: =M54+M58 -> 83525.904 | N59: =N54+N58 -> 87528.731 | O59: =O54+O58 -> 91408.793 | ... T59: =T54+T58 -> 106969.97
C61: Shareholders' Equity
D62: Equity Capital | H62: =Scenario!$G$32 -> 110000 | I62: =H62 -> 110000 | J62: =I62 -> 110000 | K62: =J62 -> 110000 | L62: =K62 -> 110000 | M62: =L62 -> 110000 | N62: =M62 -> 110000 | O62: =N62 -> 110000 | P62: =O62 -> 110000 | ... T62: =S62 -> 110000
D63: Retained Earnings | H63: =0+H36+H87 -> 4627.6971 | I63: =H63+I36+I87 -> 9351.8878 | J63: =I63+J36+J87 -> 14172.576 | K63: =J63+K36+K87 -> 19089.762 | L63: =K63+L36+L87 -> 24484.542 | M63: =L63+M36+M87 -> 30071.095 | N63: =M63+N36+N87 -> 35277.772 | O63: =N63+O36+O87 -> 40199.85 | P63: =O63+P36+P87 -> 44456.231 | ... S63: =R63+S36+S87 -> 59995.667 | T63: =S63 -> 59995.667
D64: Total Shareholders' Equity | H64: =SUM(H62:H63) -> 114627.7 | I64: =SUM(I62:I63) -> 119351.89 | J64: =SUM(J62:J63) -> 124172.58 | K64: =SUM(K62:K63) -> 129089.76 | L64: =SUM(L62:L63) -> 134484.54 | M64: =SUM(M62:M63) -> 140071.09 | N64: =SUM(N62:N63) -> 145277.77 | O64: =SUM(O62:O63) -> 150199.85 | ... T64: =SUM(T62:T63) -> 169995.67
C65: Total Liabilities and Shareholders' Equity | H65: =H59+H64 -> 178385 | I65: =I59+I64 -> 186907.41 | J65: =J59+J64 -> 195567.24 | K65: =K59+K64 -> 204364.49 | L65: =L59+L64 -> 213843.93 | M65: =M59+M64 -> 223597 | N65: =N59+N64 -> 232806.5 | O65: =O59+O64 -> 241608.64 | ... T65: =T59+T64 -> 276965.63
D67: Reconcile | H67: =H49-H65 -> 0 | I67: =I49-I65 -> 0 | J67: =J49-J65 -> 0 | K67: =K49-K65 -> 0 | L67: =L49-L65 -> 0 | M67: =M49-M65 -> 0 | N67: =N49-N65 -> 0 | O67: =O49-O65 -> 0 | ... T67: =T49-T65 -> 0
C69: Cash Flow Statement
C70: Operating Cash Flow
D71: Net Income | H71: =H36 -> 5444.3495 | I71: =I36 -> 5557.8715 | J71: =J36 -> 5671.3979 | K71: =K36 -> 5784.9243 | L71: =L36 -> 6346.8006 | M71: =M36 -> 6572.4145 | N71: =N36 -> 6125.5034 | O71: =O36 -> 5790.6798 | ... S71: =S36 -> 6581.0478 | T71: =SUM(H71:S71) -> 70583.137
D72: (+) Depreciation and Amortization | H72: =H26 -> 627.08333 | I72: =I26 -> 627.08333 | J72: =J26 -> 627.08333 | K72: =K26 -> 627.08333 | L72: =L26 -> 627.08333 | M72: =M26 -> 627.08333 | N72: =N26 -> 627.08333 | O72: =O26 -> 627.08333 | ... S72: =S26 -> 627.08333 | T72: =SUM(H72:S72) -> 7525
D73: (-) Changes in Working Capital
E74: Accounts Receivable | H74: =0-H42 -> -3912.3288 | I74: =H42-I42 -> -3950.6849 | J74: =I42-J42 -> -3989.0411 | K74: =J42-K42 -> -4027.3973 | L74: =K42-L42 -> -4219.1781 | M74: =L42-M42 -> -4295.8904 | N74: =M42-N42 -> -4142.4658 | O74: =N42-O42 -> -4027.3973 | P74: =O42-P42 -> -3758.9041 | ... S74: =R42-S42 -> -4295.8904 | T74: =SUM(H74:S74) -> -48712.329
E75: Inventory | H75: =0-H43 -> -3337.7055 | I75: =H43-I43 -> -3370.4281 | J75: =I43-J43 -> -3403.1507 | K75: =J43-K43 -> -3435.8733 | L75: =K43-L43 -> -3599.4863 | M75: =L43-M43 -> -3664.9315 | N75: =M43-N43 -> -3534.0411 | O75: =N43-O43 -> -3435.8733 | P75: =O43-P43 -> -3206.8151 | ... S75: =R43-S43 -> -3664.9315 | T75: =SUM(H75:S75) -> -41557.705
E76: Accounts Payable | H76: =H52-0 -> 2567.4658 | I76: =I52-H52 -> 2592.637 | J76: =J52-I52 -> 2617.8082 | K76: =K52-J52 -> 2642.9795 | L76: =L52-K52 -> 2768.8356 | M76: =M52-L52 -> 2819.1781 | N76: =N52-M52 -> 2718.4932 | O76: =O52-N52 -> 2642.9795 | P76: =P52-O52 -> 2466.7808 | ... S76: =S52-R52 -> 2819.1781 | T76: =SUM(H76:S76) -> 31967.466
E77: Accrued Expenses and Other | H77: =H53-0 -> 1606.5 | I77: =I53-H53 -> 1622.25 | J77: =J53-I53 -> 1638 | K77: =K53-J53 -> 1653.75 | L77: =L53-K53 -> 1732.5 | M77: =M53-L53 -> 1764 | N77: =N53-M53 -> 1701 | O77: =O53-N53 -> 1653.75 | P77: =P53-O53 -> 1543.5 | ... S77: =S53-R53 -> 1764 | T77: =SUM(H77:S77) -> 20002.5
C78: Cash from Operations | H78: =SUM(H71:H77) -> 2995.3643 | I78: =SUM(I71:I77) -> 3078.7288 | J78: =SUM(J71:J77) -> 3162.0976 | K78: =SUM(K71:K77) -> 3245.4665 | L78: =SUM(L71:L77) -> 3656.5552 | M78: =SUM(M71:M77) -> 3821.854 | N78: =SUM(N71:N77) -> 3495.5731 | O78: =SUM(O71:O77) -> 3251.222 | ... T78: =SUM(T71:T77) -> 39808.069
C80: Investing Cash Flow
D81: Purchase of property, plant and equipment | H81: =-(Scenario!$G$24+(Scenario!$G$27/12)) -> -14166.667 | I81: =-(Scenario!$G$27)/12 -> -666.66667 | J81: =-(Scenario!$G$27)/12 -> -666.66667 | K81: =-(Scenario!$G$27)/12 -> -666.66667 | L81: =-(Scenario!$G$27)/12 -> -666.66667 | M81: =-(Scenario!$G$27)/12 -> -666.66667 | N81: =-(Scenario!$G$27)/12 -> -666.66667 | O81: =-(Scenario!$G$27)/12 -> -666.66667 | P81: =-(Scenario!$G$27)/12 -> -666.66667 | ... S81: =-(Scenario!$G$27)/12 -> -666.66667 | T81: =SUM(H81:S81) -> -21500
C82: Cash from Investing | H82: =SUM(H81) -> -14166.667 | I82: =SUM(I81) -> -666.66667 | J82: =SUM(J81) -> -666.66667 | K82: =SUM(K81) -> -666.66667 | L82: =SUM(L81) -> -666.66667 | M82: =SUM(M81) -> -666.66667 | N82: =SUM(N81) -> -666.66667 | O82: =SUM(O81) -> -666.66667 | ... T82: =SUM(T81) -> -21500
C84: Financing Cash Flow
D85: Proceeds (Repayments) from Long-Term Debt and Other | H85: =Scenario!$G$31+(Scenario!$G$33/12) -> 59583.333 | I85: =Scenario!$H$33/12 -> -416.66667 | J85: =Scenario!$H$33/12 -> -416.66667 | K85: =Scenario!$H$33/12 -> -416.66667 | L85: =Scenario!$H$33/12 -> -416.66667 | M85: =Scenario!$H$33/12 -> -416.66667 | N85: =Scenario!$H$33/12 -> -416.66667 | O85: =Scenario!$H$33/12 -> -416.66667 | P85: =Scenario!$H$33/12 -> -416.66667 | ... S85: =Scenario!$H$33/12 -> -416.66667 | T85: =SUM(H85:S85) -> 55000
D86: Proceeds (Repayments) from Equity | H86: =Scenario!G32 -> 110000 | I86: =Scenario!$G$34/12 -> 0 | J86: =Scenario!$G$34/12 -> 0 | K86: =Scenario!$G$34/12 -> 0 | L86: =Scenario!$G$34/12 -> 0 | M86: =Scenario!$G$34/12 -> 0 | N86: =Scenario!$G$34/12 -> 0 | O86: =Scenario!$G$34/12 -> 0 | P86: =Scenario!$G$34/12 -> 0 | ... S86: =Scenario!$G$34/12 -> 0 | T86: =SUM(H86:S86) -> 110000
D87: Dividends | H87: =-Scenario!$G$35*H36 -> -816.65242 | I87: =-Scenario!$G$35*I36 -> -833.68073 | J87: =-Scenario!$G$35*J36 -> -850.70968 | K87: =-Scenario!$G$35*K36 -> -867.73864 | L87: =-Scenario!$G$35*L36 -> -952.0201 | M87: =-Scenario!$G$35*M36 -> -985.86218 | N87: =-Scenario!$G$35*N36 -> -918.82551 | O87: =-Scenario!$G$35*O36 -> -868.60197 | ... S87: =-Scenario!$G$35*S36 -> -987.15718 | T87: =SUM(H87:S87) -> -10587.471
C88: Cash from Financing | H88: =SUM(H85:H87) -> 168766.68 | I88: =SUM(I85:I87) -> -1250.3474 | J88: =SUM(J85:J87) -> -1267.3763 | K88: =SUM(K85:K87) -> -1284.4053 | L88: =SUM(L85:L87) -> -1368.6868 | M88: =SUM(M85:M87) -> -1402.5288 | N88: =SUM(N85:N87) -> -1335.4922 | O88: =SUM(O85:O87) -> -1285.2686 | ... T88: =SUM(T85:T87) -> 154412.53
D90: Net Increase (decrease) in Cash | H90: =H78+H82+H88 -> 157595.38 | I90: =I78+I82+I88 -> 1161.7148 | J90: =J78+J82+J88 -> 1228.0546 | K90: =K78+K82+K88 -> 1294.3945 | L90: =L78+L82+L88 -> 1621.2018 | M90: =M78+M82+M88 -> 1752.6585 | N90: =N78+N82+N88 -> 1493.4142 | O90: =O78+O82+O88 -> 1299.2867 | ... T90: =T78+T82+T88 -> 172720.6
D91: Opening Cash Balance | H91: 0 | I91: =H92 -> 157595.38 | J91: =I92 -> 158757.09 | K91: =J92 -> 159985.15 | L91: =K92 -> 161279.54 | M91: =L92 -> 162900.74 | N91: =M92 -> 164653.4 | O91: =N92 -> 166146.82 | P91: =O92 -> 167446.1 | ... S91: =R92 -> 170960.6 | T91: =H91 -> 0
C92: Closing Cash Balance | H92: =SUM(H90:H91) -> 157595.38 | I92: =SUM(I90:I91) -> 158757.09 | J92: =SUM(J90:J91) -> 159985.15 | K92: =SUM(K90:K91) -> 161279.54 | L92: =SUM(L90:L91) -> 162900.74 | M92: =SUM(M90:M91) -> 164653.4 | N92: =SUM(N90:N91) -> 166146.82 | O92: =SUM(O90:O91) -> 167446.1 | ... T92: =SUM(T90:T91) -> 172720.6

Sheet Variance
A1: © Person0811. All rights reserved.
A2: MENU | B2: =Profile!F6 -> Person0811
C4: Variance Analysis
C5: =Formulas!A3 -> Amounts in USD
F6: Year to Date | L6: Current Month | M6: February
C7: Income Statement | F7: Actual | G7: Budget | H7: ∆PL | I7: ∆PL (%) | K7: Actual | L7: Budget | M7: ∆PL | N7: ∆PL (%)
D8: Service Sales | F8: =Formulas!$O145 -> 70000 | G8: =Formulas!$O164 -> 35875 | H8: =F8-G8 -> 34125 | I8: =H8/G8 -> 0.95121951 | K8: =Formulas!$P145 -> 35000 | L8: =Formulas!$P164 -> 18025 | M8: =K8-L8 -> 16975 | N8: =M8/L8 -> 0.94174757
D9: Product Sales | F9: =Formulas!$O146 -> 20000 | G9: =Formulas!$O165 -> 35875 | H9: =F9-G9 -> -15875 | I9: =H9/G9 -> -0.44250871 | K9: =Formulas!$P146 -> 10000 | L9: =Formulas!$P165 -> 18025 | M9: =K9-L9 -> -8025 | N9: =M9/L9 -> -0.44521498
C10: Revenue | F10: =SUM(F8:F9) -> 90000 | G10: =SUM(G8:G9) -> 71750 | H10: =F10-G10 -> 18250 | I10: =H10/G10 -> 0.2543554 | K10: =SUM(K8:K9) -> 45000 | L10: =SUM(L8:L9) -> 36050 | M10: =K10-L10 -> 8950 | N10: =M10/L10 -> 0.2482663
D11: Cost of Sales | F11: =Formulas!$O147 -> 56000 | G11: =Formulas!$O166 -> 37668.75 | H11: =F11-G11 -> 18331.25 | I11: =H11/G11 -> 0.48664344 | K11: =Formulas!$P147 -> 28000 | L11: =Formulas!$P166 -> 18926.25 | M11: =K11-L11 -> 9073.75 | N11: =M11/L11 -> 0.47942672
C12: Gross Profit | F12: =F10-F11 -> 34000 | G12: =G10-G11 -> 34081.25 | H12: =F12-G12 -> -81.25 | I12: =H12/G12 -> -0.0023840088 | K12: =SUM(K8:K9)-K11 -> 17000 | L12: =L10-L11 -> 17123.75 | M12: =K12-L12 -> -123.75 | N12: =M12/L12 -> -0.0072268049
C13: Gross Margin % | F13: =IFERROR(F12/SUM($F$8:$F$9),"") -> 0.37777778 | G13: =IFERROR(G12/SUM($G$8:$G$9),"") -> 0.475 | K13: =IFERROR(K12/SUM($K$8:$K$9),"") -> 0.37777778 | L13: =IFERROR(L12/SUM($L$8:$L$9),"") -> 0.475
D15: Salaries and Benefits | F15: =Formulas!$O148 -> 8000 | G15: =Formulas!$O167 -> 8333.3333 | H15: =F15-G15 -> -333.33333 | I15: =H15/G15 -> -0.04 | K15: =Formulas!$P148 -> 4000 | L15: =Formulas!$P167 -> 4166.6667 | M15: =K15-L15 -> -166.66667 | N15: =M15/L15 -> -0.04
D16: Sales and Marketing | F16: =Formulas!$O149 -> 5000 | G16: =Formulas!$O168 -> 2870 | H16: =F16-G16 -> 2130 | I16: =H16/G16 -> 0.74216028 | K16: =Formulas!$P149 -> 2500 | L16: =Formulas!$P168 -> 1442 | M16: =K16-L16 -> 1058 | N16: =M16/L16 -> 0.73370319
D17: General and Administration | F17: =Formulas!$O150 -> 7000 | G17: =Formulas!$O169 -> 5833.3333 | H17: =F17-G17 -> 1166.6667 | I17: =H17/G17 -> 0.2 | K17: =Formulas!$P150 -> 3500 | L17: =Formulas!$P169 -> 2916.6667 | M17: =K17-L17 -> 583.33333 | N17: =M17/L17 -> 0.2
D18: Credit Card Fees | F18: =Formulas!$O151 -> 900 | G18: =Formulas!$O170 -> 574 | H18: =F18-G18 -> 326 | I18: =H18/G18 -> 0.56794425 | K18: =Formulas!$P151 -> 450 | L18: =Formulas!$P170 -> 288.4 | M18: =K18-L18 -> 161.6 | N18: =M18/L18 -> 0.56033287
D19: Depreciation and Amortization | F19: =Formulas!$O152 -> 1600 | G19: =Formulas!$O171 -> 1254.1667 | H19: =F19-G19 -> 345.83333 | I19: =H19/G19 -> 0.27574751 | K19: =Formulas!$P152 -> 800 | L19: =Formulas!P171 -> 627.08333 | M19: =K19-L19 -> 172.91667 | N19: =M19/L19 -> 0.27574751
C20: Total Operating Expenses | F20: =SUM(F15:F19) -> 22500 | G20: =SUM(G15:G19) -> 18864.833 | H20: =F20-G20 -> 3635.1667 | I20: =H20/G20 -> 0.1926954 | K20: =SUM(K15:K19) -> 11250 | L20: =SUM(L15:L19) -> 9440.8167 | M20: =K20-L20 -> 1809.1833 | N20: =M20/L20 -> 0.1916342
C22: Operating Profit (EBIT) | F22: =F12-F20 -> 11500 | G22: =G12-G20 -> 15216.417 | H22: =F22-G22 -> -3716.4167 | I22: =H22/G22 -> -0.24423731 | K22: =K12-K20 -> 5750 | L22: =L12-L20 -> 7682.9333 | M22: =K22-L22 -> -1932.9333 | N22: =M22/L22 -> -0.25158794
C23: Operating Margin % | F23: =IFERROR(F22/SUM($F$8:$F$9),"") -> 0.12777778 | G23: =IFERROR(G22/SUM($G$8:$G$9),"") -> 0.21207549 | K23: =IFERROR(K22/SUM($K$8:$K$9),"") -> 0.12777778 | L23: =IFERROR(L22/SUM($L$8:$L$9),"") -> 0.21311882
D25: Interest | F25: =Formulas!$O153 -> 900 | G25: =Formulas!$O172 -> 546.78869 | H25: =F25-G25 -> 353.21131 | I25: =IFERROR(H25/G25,0) -> 0.64597406 | K25: =Formulas!$P153 -> 450 | L25: =Formulas!P172 -> 272.438 | M25: =K25-L25 -> 177.562 | N25: =IFERROR(M25/L25,0) -> 0.65175198
C26: Earnings Before Taxes (EBT) | F26: =F22-F25 -> 10600 | G26: =G22-G25 -> 14669.628 | H26: =F26-G26 -> -4069.628 | I26: =H26/G26 -> -0.27741862 | K26: =K22-K25 -> 5300 | L26: =L22-L25 -> 7410.4953 | M26: =K26-L26 -> -2110.4953 | N26: =M26/L26 -> -0.28479815
D28: Income Taxes | F28: =Formulas!$O154 -> 3400 | G28: =Formulas!$O173 -> 3667.407 | H28: =F28-G28 -> -267.40699 | I28: =H28/G28 -> -0.072914458 | K28: =Formulas!$P154 -> 1700 | L28: =Formulas!$P173 -> 1852.6238 | M28: =K28-L28 -> -152.62383 | N28: =M28/L28 -> -0.082382528
C29: Net Income | F29: =F26-F28 -> 7200 | G29: =G26-G28 -> 11002.221 | H29: =SUM(H28) -> -267.40699 | I29: =H29/G29 -> -0.024304819 | K29: =K26-K28 -> 3600 | L29: =L26-L28 -> 5557.8715 | M29: =K29-L29 -> -1957.8715 | N29: =M29/L29 -> -0.35227002
C30: Net Profit Margin % | F30: =IFERROR(F29/SUM($F$8:$F$9),"") -> 0.08 | G30: =IFERROR(G29/SUM($G$8:$G$9),"") -> 0.15334106 | K30: =IFERROR(K29/SUM($K$8:$K$9),"") -> 0.08 | L30: =IFERROR(L29/SUM($L$8:$L$9),"") -> 0.15417119
E33: =M6 -> February
C34: Income Statement | E34: Actual | F34: Budget
D35: Revenue | E35: =SUM(K8:K9) -> 45000 | F35: =SUM(L8:L9) -> 36050
D36: COGS | E36: =K11 -> 28000 | F36: =L11 -> 18926.25
D37: Opex | E37: =K20 -> 11250 | F37: =L20 -> 9440.8167
D38: Interest & Taxes | E38: =K25+K28 -> 2150 | F38: =L25+L28 -> 2125.0618

Sheet Annual Forecast
A1: © Person0811. All rights reserved.
A2: MENU | B2: =Profile!F6 -> Person0811
C4: Forecast
C5: =Formulas!A3 -> Amounts in USD
E6: Case Scenario | F6: =Scenario!E6 -> Base Case | H6: Financial Statements
C7: Income Statement | H7: =Formulas!C9 -> 2025 | I7: =Formulas!D9 -> 2026 | J7: =Formulas!E9 -> 2027 | K7: =Formulas!F9 -> 2028 | L7: =Formulas!G9 -> 2029 | M7: =Formulas!H9 -> 2030 | N7: =Formulas!I9 -> 2031 | O7: =Formulas!J9 -> 2032 | ... Q7: =Formulas!L9 -> 2034
D8: Service Sales | H8: ='12-Month Projection'!T9 -> 222250 | I8: =(H8*(1+Scenario!H9))*Formulas!D$8 -> 235585 | J8: =(I8*(1+Scenario!I9))*Formulas!E$8 -> 247364.25 | K8: =(J8*(1+Scenario!J9))*Formulas!F$8 -> 257258.82 | L8: =(K8*(1+Scenario!K9))*Formulas!G$8 -> 264976.58 | M8: =(L8*(1+Scenario!L9))*Formulas!H$8 -> 272925.88 | N8: =(M8*(1+Scenario!M9))*Formulas!I$8 -> 278384.4 | O8: =(N8*(1+Scenario!N9))*Formulas!J$8 -> 283952.09 | P8: =(O8*(1+Scenario!O9))*Formulas!K$8 -> 289631.13 | Q8: =(P8*(1+Scenario!P9))*Formulas!L$8 -> 295423.75
D9: Product Sales | H9: ='12-Month Projection'!T10 -> 222250 | I9: =(H9*(1+Scenario!H9))*Formulas!D$8 -> 235585 | J9: =(I9*(1+Scenario!I9))*Formulas!E$8 -> 247364.25 | K9: =(J9*(1+Scenario!J9))*Formulas!F$8 -> 257258.82 | L9: =(K9*(1+Scenario!K9))*Formulas!G$8 -> 264976.58 | M9: =(L9*(1+Scenario!L9))*Formulas!H$8 -> 272925.88 | N9: =(M9*(1+Scenario!M9))*Formulas!I$8 -> 278384.4 | O9: =(N9*(1+Scenario!N9))*Formulas!J$8 -> 283952.09 | P9: =(O9*(1+Scenario!O9))*Formulas!K$8 -> 289631.13 | Q9: =(P9*(1+Scenario!P9))*Formulas!L$8 -> 295423.75
C10: Total Sales | H10: =SUM(H8:H9) -> 444500 | I10: =SUM(I8:I9) -> 471170 | J10: =SUM(J8:J9) -> 494728.5 | K10: =SUM(K8:K9) -> 514517.64 | L10: =SUM(L8:L9) -> 529953.17 | M10: =SUM(M8:M9) -> 545851.76 | N10: =SUM(N8:N9) -> 556768.8 | O10: =SUM(O8:O9) -> 567904.18 | ... Q10: =SUM(Q8:Q9) -> 590847.5
D12: Service Cost | H12: ='12-Month Projection'!T13 -> 33337.5 | I12: =I$8*Scenario!H10*Formulas!D$8 -> 58896.25 | J12: =J$8*Scenario!I10*Formulas!E$8 -> 61841.062 | K12: =K$8*Scenario!J10*Formulas!F$8 -> 61742.117 | L12: =L$8*Scenario!K10*Formulas!G$8 -> 63594.38 | M12: =M$8*Scenario!L10*Formulas!H$8 -> 62772.953 | N12: =N$8*Scenario!M10*Formulas!I$8 -> 64028.412 | O12: =O$8*Scenario!N10*Formulas!J$8 -> 62469.459 | P12: =P$8*Scenario!O10*Formulas!K$8 -> 63718.848 | Q12: =Q$8*Scenario!P10*Formulas!L$8 -> 62038.988
D13: Product Cost | H13: ='12-Month Projection'!T14 -> 66675 | I13: =I$9*Scenario!H11*Formulas!D$8 -> 94234 | J13: =J$9*Scenario!I11*Formulas!E$8 -> 93998.415 | K13: =K$9*Scenario!J11*Formulas!F$8 -> 95185.763 | L13: =L$9*Scenario!K11*Formulas!G$8 -> 95391.57 | M13: =M$9*Scenario!L11*Formulas!H$8 -> 95524.059 | N13: =N$9*Scenario!M11*Formulas!I$8 -> 97434.54 | O13: =O$9*Scenario!N11*Formulas!J$8 -> 96543.71 | P13: =P$9*Scenario!O11*Formulas!K$8 -> 98474.584 | Q13: =Q$9*Scenario!P11*Formulas!L$8 -> 100444.08
D14: Direct Labor Cost | H14: ='12-Month Projection'!T15 -> 80010 | I14: =I$10*Scenario!H12*Formulas!D$8 -> 84810.6 | J14: =J$10*Scenario!I12*Formulas!E$8 -> 89051.13 | K14: =K$10*Scenario!J12*Formulas!F$8 -> 92613.175 | L14: =L$10*Scenario!K12*Formulas!G$8 -> 95391.57 | M14: =M$10*Scenario!L12*Formulas!H$8 -> 98253.318 | N14: =N$10*Scenario!M12*Formulas!I$8 -> 100218.38 | O14: =O$10*Scenario!N12*Formulas!J$8 -> 102222.75 | P14: =P$10*Scenario!O12*Formulas!K$8 -> 104267.21 | Q14: =Q$10*Scenario!P12*Formulas!L$8 -> 106352.55
D15: Discounts and Promotions | H15: ='12-Month Projection'!T16 -> 53340 | I15: =I$10*Scenario!H13*Formulas!D$8 -> 51828.7 | J15: =J$10*Scenario!I13*Formulas!E$8 -> 49472.85 | K15: =K$10*Scenario!J13*Formulas!F$8 -> 46306.588 | L15: =L$10*Scenario!K13*Formulas!G$8 -> 47695.785 | M15: =M$10*Scenario!L13*Formulas!H$8 -> 43668.141 | N15: =N$10*Scenario!M13*Formulas!I$8 -> 44541.504 | O15: =O$10*Scenario!N13*Formulas!J$8 -> 39753.292 | P15: =P$10*Scenario!O13*Formulas!K$8 -> 40548.358 | Q15: =Q$10*Scenario!P13*Formulas!L$8 -> 41359.325
C16: Total Cost of Sales | H16: =SUM(H12:H15) -> 233362.5 | I16: =SUM(I12:I15) -> 289769.55 | J16: =SUM(J12:J15) -> 294363.46 | K16: =SUM(K12:K15) -> 295847.64 | L16: =SUM(L12:L15) -> 302073.31 | M16: =SUM(M12:M15) -> 300218.47 | N16: =SUM(N12:N15) -> 306222.84 | O16: =SUM(O12:O15) -> 300989.21 | ... Q16: =SUM(Q12:Q15) -> 310194.94
C18: Gross Profit | H18: =H10-H16 -> 211137.5 | I18: =I10-I16 -> 181400.45 | J18: =J10-J16 -> 200365.04 | K18: =K10-K16 -> 218670 | L18: =L10-L16 -> 227879.86 | M18: =M10-M16 -> 245633.29 | N18: =N10-N16 -> 250545.96 | O18: =O10-O16 -> 266914.96 | ... Q18: =Q10-Q16 -> 280652.56
C19: Gross Margin % | H19: =IFERROR(H18/H10,0) -> 0.475 | I19: =IFERROR(I18/I10,0) -> 0.385 | J19: =IFERROR(J18/J10,0) -> 0.405 | K19: =IFERROR(K18/K10,0) -> 0.425 | L19: =IFERROR(L18/L10,0) -> 0.43 | M19: =IFERROR(M18/M10,0) -> 0.45 | N19: =IFERROR(N18/N10,0) -> 0.45 | O19: =IFERROR(O18/O10,0) -> 0.47 | ... Q19: =IFERROR(Q18/Q10,0) -> 0.475
D21: Salaries and Benefits | H21: ='12-Month Projection'!T22 -> 50000 | I21: =Scenario!H14*Formulas!D$8 -> 50000 | J21: =Scenario!I14*Formulas!E$8 -> 50000 | K21: =Scenario!J14*Formulas!F$8 -> 50000 | L21: =Scenario!K14*Formulas!G$8 -> 50000 | M21: =Scenario!L14*Formulas!H$8 -> 50000 | N21: =Scenario!M14*Formulas!I$8 -> 50000 | O21: =Scenario!N14*Formulas!J$8 -> 50000 | P21: =Scenario!O14*Formulas!K$8 -> 50000 | Q21: =Scenario!P14*Formulas!L$8 -> 50000
D22: Sales and Marketing | H22: ='12-Month Projection'!T23 -> 17780 | I22: =I$10*Scenario!H15*Formulas!D$8 -> 18846.8 | J22: =J$10*Scenario!I15*Formulas!E$8 -> 17315.498 | K22: =K$10*Scenario!J15*Formulas!F$8 -> 18008.117 | L22: =L$10*Scenario!K15*Formulas!G$8 -> 18548.361 | M22: =M$10*Scenario!L15*Formulas!H$8 -> 19104.812 | N22: =N$10*Scenario!M15*Formulas!I$8 -> 16703.064 | O22: =O$10*Scenario!N15*Formulas!J$8 -> 17037.125 | P22: =P$10*Scenario!O15*Formulas!K$8 -> 17377.868 | Q22: =Q$10*Scenario!P15*Formulas!L$8 -> 17725.425
D23: General and Administration | H23: ='12-Month Projection'!T24 -> 35000 | I23: =Scenario!H16*Formulas!D$8 -> 35000 | J23: =Scenario!I16*Formulas!E$8 -> 35000 | K23: =Scenario!J16*Formulas!F$8 -> 35000 | L23: =Scenario!K16*Formulas!G$8 -> 35000 | M23: =Scenario!L16*Formulas!H$8 -> 35000 | N23: =Scenario!M16*Formulas!I$8 -> 35000 | O23: =Scenario!N16*Formulas!J$8 -> 35000 | P23: =Scenario!O16*Formulas!K$8 -> 35000 | Q23: =Scenario!P16*Formulas!L$8 -> 35000
D24: Credit Card Fees | H24: ='12-Month Projection'!T25 -> 3556 | I24: =I$10*Scenario!H17*Formulas!D$8 -> 3769.36 | J24: =J$10*Scenario!I17*Formulas!E$8 -> 3957.828 | K24: =K$10*Scenario!J17*Formulas!F$8 -> 4116.1411 | L24: =L$10*Scenario!K17*Formulas!G$8 -> 4239.6254 | M24: =M$10*Scenario!L17*Formulas!H$8 -> 4366.8141 | N24: =N$10*Scenario!M17*Formulas!I$8 -> 4454.1504 | O24: =O$10*Scenario!N17*Formulas!J$8 -> 4543.2334 | P24: =P$10*Scenario!O17*Formulas!K$8 -> 4634.0981 | Q24: =Q$10*Scenario!P17*Formulas!L$8 -> 4726.78
D25: Depreciation and Amortization | H25: ='12-Month Projection'!T26 -> 7525 | I25: =Scenario!H18*(H47+(-I81))*Formulas!D$8 -> 8391.25 | J25: =Scenario!I18*(I47+(-J81))*Formulas!E$8 -> 9654.3125 | K25: =Scenario!J18*(J47+(-K81))*Formulas!F$8 -> 10475.303 | L25: =Scenario!K18*(K47+(-L81))*Formulas!G$8 -> 12058.947 | M25: =Scenario!L18*(L47+(-M81))*Formulas!H$8 -> 14138.316 | N25: =Scenario!M18*(M47+(-N81))*Formulas!I$8 -> 14439.905 | O25: =Scenario!N18*(N47+(-O81))*Formulas!J$8 -> 13585.938 | P25: =Scenario!O18*(O47+(-P81))*Formulas!K$8 -> 12330.86 | Q25: =Scenario!P18*(P47+(-Q81))*Formulas!L$8 -> 10815.059
C26: Total Operating Expenses | H26: =SUM(H21:H25) -> 113861 | I26: =SUM(I21:I25) -> 116007.41 | J26: =SUM(J21:J25) -> 115927.64 | K26: =SUM(K21:K25) -> 117599.56 | L26: =SUM(L21:L25) -> 119846.93 | M26: =SUM(M21:M25) -> 122609.94 | N26: =SUM(N21:N25) -> 120597.12 | O26: =SUM(O21:O25) -> 120166.3 | ... Q26: =SUM(Q21:Q25) -> 118267.26
C27: Operating Expense % | H27: =IFERROR(H26/H10,0) -> 0.25615523 | I27: =IFERROR(I26/I10,0) -> 0.24621137 | J27: =IFERROR(J26/J10,0) -> 0.23432577 | K27: =IFERROR(K26/K10,0) -> 0.22856274 | L27: =IFERROR(L26/L10,0) -> 0.22614627 | M27: =IFERROR(M26/M10,0) -> 0.22462132 | N27: =IFERROR(N26/N10,0) -> 0.21660179 | O27: =IFERROR(O26/O10,0) -> 0.21159608 | ... Q27: =IFERROR(Q26/Q10,0) -> 0.20016546
C29: Operating Profit (EBIT) | H29: =H18-H26 -> 97276.5 | I29: =I18-I26 -> 65393.04 | J29: =J18-J26 -> 84437.404 | K29: =K18-K26 -> 101070.44 | L29: =L18-L26 -> 108032.93 | M29: =M18-M26 -> 123023.35 | N29: =N18-N26 -> 129948.84 | O29: =O18-O26 -> 146748.67 | ... Q29: =Q18-Q26 -> 162385.3
C30: Operating Margin % | H30: =IFERROR(H29/H10,0) -> 0.21884477 | I30: =IFERROR(I29/I10,0) -> 0.13878863 | J30: =IFERROR(J29/J10,0) -> 0.17067423 | K30: =IFERROR(K29/K10,0) -> 0.19643726 | L30: =IFERROR(L29/L10,0) -> 0.20385373 | M30: =IFERROR(M29/M10,0) -> 0.22537868 | N30: =IFERROR(N29/N10,0) -> 0.23339821 | O30: =IFERROR(O29/O10,0) -> 0.25840392 | ... Q30: =IFERROR(Q29/Q10,0) -> 0.27483454
D32: Interest | H32: ='12-Month Projection'!T32 -> 3165.6506 | I32: =Scenario!H30*H57*Formulas!D$8 -> 3025 | J32: =Scenario!I30*I57*Formulas!E$8 -> 2750 | K32: =Scenario!J30*J57*Formulas!F$8 -> 2475 | L32: =Scenario!K30*K57*Formulas!G$8 -> 2200 | M32: =Scenario!L30*L57*Formulas!H$8 -> 1925 | N32: =Scenario!M30*M57*Formulas!I$8 -> 1650 | O32: =Scenario!N30*N57*Formulas!J$8 -> 1375 | P32: =Scenario!O30*O57*Formulas!K$8 -> 1100 | Q32: =Scenario!P30*P57*Formulas!L$8 -> 825
C33: Earnings Before Taxes (EBT) | H33: =H29-H32 -> 94110.849 | I33: =I29-I32 -> 62368.04 | J33: =J29-J32 -> 81687.404 | K33: =K29-K32 -> 98595.435 | L33: =L29-L32 -> 105832.93 | M33: =M29-M32 -> 121098.35 | N33: =N29-N32 -> 128298.84 | O33: =O29-O32 -> 145373.67 | ... Q33: =Q29-Q32 -> 161560.3
D35: Income Taxes | H35: ='12-Month Projection'!T35 -> 23527.712 | I35: =IF(I33>0,I33*Scenario!H19*Formulas!D$8,0) -> 15592.01 | J35: =IF(J33>0,J33*Scenario!I19*Formulas!E$8,0) -> 20421.851 | K35: =IF(K33>0,K33*Scenario!J19*Formulas!F$8,0) -> 24648.859 | L35: =IF(L33>0,L33*Scenario!K19*Formulas!G$8,0) -> 26458.232 | M35: =IF(M33>0,M33*Scenario!L19*Formulas!H$8,0) -> 30274.588 | N35: =IF(N33>0,N33*Scenario!M19*Formulas!I$8,0) -> 32074.71 | O35: =IF(O33>0,O33*Scenario!N19*Formulas!J$8,0) -> 36343.416 | P35: =IF(P33>0,P33*Scenario!O19*Formulas!K$8,0) -> 37952.609 | Q35: =IF(Q33>0,Q33*Scenario!P19*Formulas!L$8,0) -> 40390.075
C36: Net Income | H36: =H33-H35 -> 70583.137 | I36: =I33-I35 -> 46776.03 | J36: =J33-J35 -> 61265.553 | K36: =K33-K35 -> 73946.577 | L36: =L33-L35 -> 79374.697 | M36: =M33-M35 -> 90823.764 | N36: =N33-N35 -> 96224.13 | O36: =O33-O35 -> 109030.25 | ... Q36: =Q33-Q35 -> 121170.23
C37: Net Profit Margin % | H37: =IFERROR(H36/H10,0) -> 0.15879221 | I37: =IFERROR(I36/I10,0) -> 0.099276333 | J37: =IFERROR(J36/J10,0) -> 0.12383672 | K37: =IFERROR(K36/K10,0) -> 0.1437202 | L37: =IFERROR(L36/L10,0) -> 0.14977681 | M37: =IFERROR(M36/M10,0) -> 0.16638906 | N37: =IFERROR(N36/N10,0) -> 0.17282601 | O37: =IFERROR(O36/O10,0) -> 0.19198705 | ... Q37: =IFERROR(Q36/Q10,0) -> 0.20507868
C39: Balance Sheet
C40: Current Assets
D41: Cash and Cash Equivalents | H41: ='12-Month Projection'!T41 -> 172720.6 | I41: =I92*Formulas!D$8 -> 201830.79 | J41: =J92*Formulas!E$8 -> 244850.41 | K41: =K92*Formulas!F$8 -> 295788.44 | L41: =L92*Formulas!G$8 -> 353977.78 | M41: =M92*Formulas!H$8 -> 424755.89 | N41: =N92*Formulas!I$8 -> 495824.65 | O41: =O92*Formulas!J$8 -> 584949.77 | P41: =P92*Formulas!K$8 -> 673781.39 | Q41: =Q92*Formulas!L$8 -> 773696.06
D42: Accounts Receivable | H42: ='12-Month Projection'!T42 -> 48712.329 | I42: =Scenario!H22*I$10/365*Formulas!D$8 -> 51635.068 | J42: =Scenario!I22*J$10/365*Formulas!E$8 -> 54216.822 | K42: =Scenario!J22*K$10/365*Formulas!F$8 -> 56385.495 | L42: =Scenario!K22*L$10/365*Formulas!G$8 -> 58077.06 | M42: =Scenario!L22*M$10/365*Formulas!H$8 -> 52341.95 | N42: =Scenario!M22*N$10/365*Formulas!I$8 -> 53388.789 | O42: =Scenario!N22*O$10/365*Formulas!J$8 -> 54456.565 | P42: =Scenario!O22*P$10/365*Formulas!K$8 -> 55545.696 | Q42: =Scenario!P22*Q$10/365*Formulas!L$8 -> 56656.61
D43: Inventory | H43: ='12-Month Projection'!T43 -> 41557.705 | I43: =Scenario!H23*I$16/365*Formulas!D$8 -> 51602.797 | J43: =Scenario!I23*J$16/365*Formulas!E$8 -> 52420.89 | K43: =Scenario!J23*K$16/365*Formulas!F$8 -> 56737.904 | L43: =Scenario!K23*L$16/365*Formulas!G$8 -> 57931.867 | M43: =Scenario!L23*M$16/365*Formulas!H$8 -> 57576.145 | N43: =Scenario!M23*N$16/365*Formulas!I$8 -> 62922.501 | O43: =Scenario!N23*O$16/365*Formulas!J$8 -> 61847.099 | P43: =Scenario!O23*P$16/365*Formulas!K$8 -> 67289.643 | Q43: =Scenario!P23*Q$16/365*Formulas!L$8 -> 67987.932
D44: Total Current Assets | H44: =SUM(H41:H43) -> 262990.63 | I44: =SUM(I41:I43) -> 305068.65 | J44: =SUM(J41:J43) -> 351488.12 | K44: =SUM(K41:K43) -> 408911.84 | L44: =SUM(L41:L43) -> 469986.71 | M44: =SUM(M41:M43) -> 534673.99 | N44: =SUM(N41:N43) -> 612135.94 | O44: =SUM(O41:O43) -> 701253.44 | ... Q44: =SUM(Q41:Q43) -> 898340.6
C46: Non-Current Assets
D47: Property, Plant and Equipment | H47: ='12-Month Projection'!T47 -> 13975 | I47: =(H47+(-I81)-I25)*Formulas!D$8 -> 15583.75 | J47: =(I47+(-J81)-J25)*Formulas!E$8 -> 17929.438 | K47: =(J47+(-K81)-K25)*Formulas!F$8 -> 19454.134 | L47: =(K47+(-L81)-L25)*Formulas!G$8 -> 22395.187 | M47: =(L47+(-M81)-M25)*Formulas!H$8 -> 26256.872 | N47: =(M47+(-N81)-N25)*Formulas!I$8 -> 26816.967 | O47: =(N47+(-O81)-O25)*Formulas!J$8 -> 25231.028 | P47: =(O47+(-P81)-P25)*Formulas!K$8 -> 22900.168 | Q47: =(P47+(-Q81)-Q25)*Formulas!L$8 -> 20085.109
D48: Total Non-Current Assets | H48: =SUM(H47) -> 13975 | I48: =SUM(I47) -> 15583.75 | J48: =SUM(J47) -> 17929.438 | K48: =SUM(K47) -> 19454.134 | L48: =SUM(L47) -> 22395.187 | M48: =SUM(M47) -> 26256.872 | N48: =SUM(N47) -> 26816.967 | O48: =SUM(O47) -> 25231.028 | ... Q48: =SUM(Q47) -> 20085.109
C49: Total Assets | H49: =H44+H48 -> 276965.63 | I49: =I44+I48 -> 320652.4 | J49: =J44+J48 -> 369417.56 | K49: =K44+K48 -> 428365.97 | L49: =L44+L48 -> 492381.89 | M49: =M44+M48 -> 560930.86 | N49: =N44+N48 -> 638952.9 | O49: =O44+O48 -> 726484.46 | ... Q49: =Q44+Q48 -> 918425.71
C51: Current Liabilities
D52: Account Payable | H52: ='12-Month Projection'!T52 -> 31967.466 | I52: =Scenario!H25*I$16/365*Formulas!D$8 -> 39694.459 | J52: =Scenario!I25*J$16/365*Formulas!E$8 -> 40323.761 | K52: =Scenario!J25*K$16/365*Formulas!F$8 -> 40527.074 | L52: =Scenario!K25*L$16/365*Formulas!G$8 -> 41379.905 | M52: =Scenario!L25*M$16/365*Formulas!H$8 -> 37013.236 | N52: =Scenario!M25*N$16/365*Formulas!I$8 -> 37753.501 | O52: =Scenario!N25*O$16/365*Formulas!J$8 -> 37108.259 | P52: =Scenario!O25*P$16/365*Formulas!K$8 -> 37850.424 | Q52: =Scenario!P25*Q$16/365*Formulas!L$8 -> 38243.212
D53: Accrued Expenses and Other | H53: ='12-Month Projection'!T53 -> 20002.5 | I53: =Scenario!H26*I10*Formulas!D$8 -> 21202.65 | J53: =Scenario!I26*J10*Formulas!E$8 -> 22262.782 | K53: =Scenario!J26*K10*Formulas!F$8 -> 23153.294 | L53: =Scenario!K26*L10*Formulas!G$8 -> 23847.893 | M53: =Scenario!L26*M10*Formulas!H$8 -> 24563.329 | N53: =Scenario!M26*N10*Formulas!I$8 -> 25054.596 | O53: =Scenario!N26*O10*Formulas!J$8 -> 25555.688 | P53: =Scenario!O26*P10*Formulas!K$8 -> 26066.802 | Q53: =Scenario!P26*Q10*Formulas!L$8 -> 26588.138
D54: Total Current Liabilities | H54: =SUM(H52:H53) -> 51969.966 | I54: =SUM(I52:I53) -> 60897.109 | J54: =SUM(J52:J53) -> 62586.544 | K54: =SUM(K52:K53) -> 63680.368 | L54: =SUM(L52:L53) -> 65227.798 | M54: =SUM(M52:M53) -> 61576.565 | N54: =SUM(N52:N53) -> 62808.097 | O54: =SUM(O52:O53) -> 62663.947 | ... Q54: =SUM(Q52:Q53) -> 64831.349
C56: Non-Current Liabilities
D57: Long-Term Debt | H57: ='12-Month Projection'!T57 -> 55000 | I57: =(H57+Scenario!$G33)*Formulas!D$8 -> 50000 | J57: =(I57+Scenario!$G33)*Formulas!E$8 -> 45000 | K57: =(J57+Scenario!$G33)*Formulas!F$8 -> 40000 | L57: =(K57+Scenario!$G33)*Formulas!G$8 -> 35000 | M57: =(L57+Scenario!$G33)*Formulas!H$8 -> 30000 | N57: =(M57+Scenario!$G33)*Formulas!I$8 -> 25000 | O57: =(N57+Scenario!$G33)*Formulas!J$8 -> 20000 | P57: =(O57+Scenario!$G33)*Formulas!K$8 -> 15000 | Q57: =(P57+Scenario!$G33)*Formulas!L$8 -> 10000
D58: Total Non-Current Liabilities | H58: =SUM(H57) -> 55000 | I58: =SUM(I57) -> 50000 | J58: =SUM(J57) -> 45000 | K58: =SUM(K57) -> 40000 | L58: =SUM(L57) -> 35000 | M58: =SUM(M57) -> 30000 | N58: =SUM(N57) -> 25000 | O58: =SUM(O57) -> 20000 | ... Q58: =SUM(Q57) -> 10000
C59: Total Liabilities | H59: =H54+H58 -> 106969.97 | I59: =I54+I58 -> 110897.11 | J59: =J54+J58 -> 107586.54 | K59: =K54+K58 -> 103680.37 | L59: =L54+L58 -> 100227.8 | M59: =M54+M58 -> 91576.565 | N59: =N54+N58 -> 87808.097 | O59: =O54+O58 -> 82663.947 | ... Q59: =Q54+Q58 -> 74831.349
C61: Shareholders' Equity
D62: Equity Capital | H62: ='12-Month Projection'!T62 -> 110000 | I62: =Scenario!H32*Formulas!D$8 -> 110000 | J62: =Scenario!I32*Formulas!E$8 -> 110000 | K62: =Scenario!J32*Formulas!F$8 -> 110000 | L62: =Scenario!K32*Formulas!G$8 -> 110000 | M62: =Scenario!L32*Formulas!H$8 -> 110000 | N62: =Scenario!M32*Formulas!I$8 -> 110000 | O62: =Scenario!N32*Formulas!J$8 -> 110000 | P62: =Scenario!O32*Formulas!K$8 -> 110000 | Q62: =Scenario!P32*Formulas!L$8 -> 110000
D63: Retained Earnings | H63: ='12-Month Projection'!T63 -> 59995.667 | I63: =(H63+I36+I87)*Formulas!D$8 -> 99755.292 | J63: =(I63+J36+J87)*Formulas!E$8 -> 151831.01 | K63: =(J63+K36+K87)*Formulas!F$8 -> 214685.6 | L63: =(K63+L36+L87)*Formulas!G$8 -> 282154.09 | M63: =(L63+M36+M87)*Formulas!H$8 -> 359354.29 | N63: =(M63+N36+N87)*Formulas!I$8 -> 441144.81 | O63: =(N63+O36+O87)*Formulas!J$8 -> 533820.52 | P63: =(O63+P36+P87)*Formulas!K$8 -> 630599.67 | Q63: =(P63+Q36+Q87)*Formulas!L$8 -> 733594.36
D64: Total Shareholders' Equity | H64: =SUM(H62:H63) -> 169995.67 | I64: =SUM(I62:I63) -> 209755.29 | J64: =SUM(J62:J63) -> 261831.01 | K64: =SUM(K62:K63) -> 324685.6 | L64: =SUM(L62:L63) -> 392154.09 | M64: =SUM(M62:M63) -> 469354.29 | N64: =SUM(N62:N63) -> 551144.81 | O64: =SUM(O62:O63) -> 643820.52 | ... Q64: =SUM(Q62:Q63) -> 843594.36
C65: Total Liabilities and Shareholders' Equity | H65: =H59+H64 -> 276965.63 | I65: =I59+I64 -> 320652.4 | J65: =J59+J64 -> 369417.56 | K65: =K59+K64 -> 428365.97 | L65: =L59+L64 -> 492381.89 | M65: =M59+M64 -> 560930.86 | N65: =N59+N64 -> 638952.9 | O65: =O59+O64 -> 726484.46 | ... Q65: =Q59+Q64 -> 918425.71
D67: Reconcile | H67: =H49-H65 -> 0 | I67: =I49-I65 -> 0 | J67: =J49-J65 -> 0 | K67: =K49-K65 -> 0 | L67: =L49-L65 -> 0 | M67: =M49-M65 -> 0 | N67: =N49-N65 -> 0 | O67: =O49-O65 -> 0 | ... Q67: =Q49-Q65 -> 0
C69: Cash Flow Statement
C70: Operating Cash Flow
D71: Net Income | H71: ='12-Month Projection'!T71 -> 70583.137 | I71: =I36 -> 46776.03 | J71: =J36 -> 61265.553 | K71: =K36 -> 73946.577 | L71: =L36 -> 79374.697 | M71: =M36 -> 90823.764 | N71: =N36 -> 96224.13 | O71: =O36 -> 109030.25 | P71: =P36 -> 113857.83 | Q71: =Q36 -> 121170.23
D72: (+) Depreciation and Amortization | H72: ='12-Month Projection'!T72 -> 7525 | I72: =I25 -> 8391.25 | J72: =J25 -> 9654.3125 | K72: =K25 -> 10475.303 | L72: =L25 -> 12058.947 | M72: =M25 -> 14138.316 | N72: =N25 -> 14439.905 | O72: =O25 -> 13585.938 | P72: =P25 -> 12330.86 | Q72: =Q25 -> 10815.059
D73: (-) Changes in Working Capital | H73: ='12-Month Projection'!T73 -> 0
E74: Accounts Receivable | H74: =0-H42 -> -48712.329 | I74: =-(I42-H42)*Formulas!D$8 -> -2922.7397 | J74: =-(J42-I42)*Formulas!E$8 -> -2581.7534 | K74: =-(K42-J42)*Formulas!F$8 -> -2168.6729 | L74: =-(L42-K42)*Formulas!G$8 -> -1691.5648 | M74: =-(M42-L42)*Formulas!H$8 -> 5735.1096 | N74: =-(N42-M42)*Formulas!I$8 -> -1046.839 | O74: =-(O42-N42)*Formulas!J$8 -> -1067.7758 | P74: =-(P42-O42)*Formulas!K$8 -> -1089.1313 | Q74: =-(Q42-P42)*Formulas!L$8 -> -1110.9139
E75: Inventory | H75: =0-H43 -> -41557.705 | I75: =-(I43-H43)*Formulas!D$8 -> -10045.091 | J75: =-(J43-I43)*Formulas!E$8 -> -818.09312 | K75: =-(K43-J43)*Formulas!F$8 -> -4317.0144 | L75: =-(L43-K43)*Formulas!G$8 -> -1193.9629 | M75: =-(M43-L43)*Formulas!H$8 -> 355.72199 | N75: =-(N43-M43)*Formulas!I$8 -> -5346.3563 | O75: =-(O43-N43)*Formulas!J$8 -> 1075.4027 | P75: =-(P43-O43)*Formulas!K$8 -> -5442.5447 | Q75: =-(Q43-P43)*Formulas!L$8 -> -698.28875
E76: Accounts Payable | H76: =H52-0 -> 31967.466 | I76: =(I52-H52)*Formulas!D$8 -> 7726.9932 | J76: =(J52-I52)*Formulas!E$8 -> 629.3024 | K76: =(K52-J52)*Formulas!F$8 -> 203.31308 | L76: =(L52-K52)*Formulas!G$8 -> 852.83061 | M76: =(M52-L52)*Formulas!H$8 -> -4366.6689 | N76: =(N52-M52)*Formulas!I$8 -> 740.26472 | O76: =(O52-N52)*Formulas!J$8 -> -645.24165 | P76: =(P52-O52)*Formulas!K$8 -> 742.16518 | Q76: =(Q52-P52)*Formulas!L$8 -> 392.78742
E77: Accrued Expenses and Other | H77: =H53-0 -> 20002.5 | I77: =(I53-H53)*Formulas!D$8 -> 1200.15 | J77: =(J53-I53)*Formulas!E$8 -> 1060.1325 | K77: =(K53-J53)*Formulas!F$8 -> 890.5113 | L77: =(L53-K53)*Formulas!G$8 -> 694.59881 | M77: =(M53-L53)*Formulas!H$8 -> 715.43678 | N77: =(N53-M53)*Formulas!I$8 -> 491.26659 | O77: =(O53-N53)*Formulas!J$8 -> 501.09192 | P77: =(P53-O53)*Formulas!K$8 -> 511.11376 | Q77: =(Q53-P53)*Formulas!L$8 -> 521.33603
C78: Cash from Operations | H78: =SUM(H71:H77) -> 39808.069 | I78: =SUM(I71:I77) -> 51126.592 | J78: =SUM(J71:J77) -> 69209.454 | K78: =SUM(K71:K77) -> 79030.017 | L78: =SUM(L71:L77) -> 90095.546 | M78: =SUM(M71:M77) -> 107401.68 | N78: =SUM(N71:N77) -> 105502.37 | O78: =SUM(O71:O77) -> 122479.66 | ... Q78: =SUM(Q71:Q77) -> 131090.21
C80: Investing Cash Flow
D81: Purchase of property, plant and equipment | H81: ='12-Month Projection'!T81 -> -21500 | I81: =-Scenario!H27 -> -10000 | J81: =-Scenario!I27 -> -12000 | K81: =-Scenario!J27 -> -12000 | L81: =-Scenario!K27 -> -15000 | M81: =-Scenario!L27 -> -18000 | N81: =-Scenario!M27 -> -15000 | O81: =-Scenario!N27 -> -12000 | P81: =-Scenario!O27 -> -10000 | Q81: =-Scenario!P27 -> -8000
C82: Cash from Investing | H82: =SUM(H81) -> -21500 | I82: =SUM(I81) -> -10000 | J82: =SUM(J81) -> -12000 | K82: =SUM(K81) -> -12000 | L82: =SUM(L81) -> -15000 | M82: =SUM(M81) -> -18000 | N82: =SUM(N81) -> -15000 | O82: =SUM(O81) -> -12000 | ... Q82: =SUM(Q81) -> -8000
C84: Financing Cash Flow
D85: Proceeds (Repayments) from Long-Term Debt and Other | H85: ='12-Month Projection'!T85 -> 55000 | I85: =Scenario!H33*Formulas!D$8 -> -5000 | J85: =Scenario!I33*Formulas!E$8 -> -5000 | K85: =Scenario!J33*Formulas!F$8 -> -5000 | L85: =Scenario!K33*Formulas!G$8 -> -5000 | M85: =Scenario!L33*Formulas!H$8 -> -5000 | N85: =Scenario!M33*Formulas!I$8 -> -5000 | O85: =Scenario!N33*Formulas!J$8 -> -5000 | P85: =Scenario!O33*Formulas!K$8 -> -5000 | Q85: =Scenario!P33*Formulas!L$8 -> -5000
D86: Proceeds (Repayments) from Equity | H86: ='12-Month Projection'!T86 -> 110000 | I86: =Scenario!H34*Formulas!D$8 -> 0 | J86: =Scenario!I34*Formulas!E$8 -> 0 | K86: =Scenario!J34*Formulas!F$8 -> 0 | L86: =Scenario!K34*Formulas!G$8 -> 0 | M86: =Scenario!L34*Formulas!H$8 -> 0 | N86: =Scenario!M34*Formulas!I$8 -> 0 | O86: =Scenario!N34*Formulas!J$8 -> 0 | P86: =Scenario!O34*Formulas!K$8 -> 0 | Q86: =Scenario!P34*Formulas!L$8 -> 0
D87: Dividends | H87: ='12-Month Projection'!T87 -> -10587.471 | I87: =-Scenario!H35*'Annual Forecast'!I36*Formulas!D$8 -> -7016.4045 | J87: =-Scenario!I35*'Annual Forecast'!J36*Formulas!E$8 -> -9189.833 | K87: =-Scenario!J35*'Annual Forecast'!K36*Formulas!F$8 -> -11091.986 | L87: =-Scenario!K35*'Annual Forecast'!L36*Formulas!G$8 -> -11906.205 | M87: =-Scenario!L35*'Annual Forecast'!M36*Formulas!H$8 -> -13623.565 | N87: =-Scenario!M35*'Annual Forecast'!N36*Formulas!I$8 -> -14433.62 | O87: =-Scenario!N35*'Annual Forecast'!O36*Formulas!J$8 -> -16354.537 | P87: =-Scenario!O35*'Annual Forecast'!P36*Formulas!K$8 -> -17078.674 | Q87: =-Scenario!P35*'Annual Forecast'!Q36*Formulas!L$8 -> -18175.534
C88: Cash from Financing | H88: =SUM(H85:H87) -> 154412.53 | I88: =SUM(I85:I87) -> -12016.405 | J88: =SUM(J85:J87) -> -14189.833 | K88: =SUM(K85:K87) -> -16091.986 | L88: =SUM(L85:L87) -> -16906.205 | M88: =SUM(M85:M87) -> -18623.565 | N88: =SUM(N85:N87) -> -19433.62 | O88: =SUM(O85:O87) -> -21354.537 | ... Q88: =SUM(Q85:Q87) -> -23175.534
D90: Net Increase (decrease) in Cash | H90: =H78+H82+H88 -> 172720.6 | I90: =I78+I82+I88 -> 29110.188 | J90: =J78+J82+J88 -> 43019.621 | K90: =K78+K82+K88 -> 50938.03 | L90: =L78+L82+L88 -> 58189.341 | M90: =M78+M82+M88 -> 70778.115 | N90: =N78+N82+N88 -> 71068.752 | O90: =O78+O82+O88 -> 89125.127 | ... Q90: =Q78+Q82+Q88 -> 99914.671
D91: Opening Cash Balance | H91: 0 | I91: =H92*Formulas!D$8 -> 172720.6 | J91: =I92*Formulas!E$8 -> 201830.79 | K91: =J92*Formulas!F$8 -> 244850.41 | L91: =K92*Formulas!G$8 -> 295788.44 | M91: =L92*Formulas!H$8 -> 353977.78 | N91: =M92*Formulas!I$8 -> 424755.89 | O91: =N92*Formulas!J$8 -> 495824.65 | P91: =O92*Formulas!K$8 -> 584949.77 | Q91: =P92*Formulas!L$8 -> 673781.39
C92: Closing Cash Balance | H92: =SUM(H90:H91) -> 172720.6 | I92: =SUM(I90:I91) -> 201830.79 | J92: =SUM(J90:J91) -> 244850.41 | K92: =SUM(K90:K91) -> 295788.44 | L92: =SUM(L90:L91) -> 353977.78 | M92: =SUM(M90:M91) -> 424755.89 | N92: =SUM(N90:N91) -> 495824.65 | O92: =SUM(O90:O91) -> 584949.77 | ... Q92: =SUM(Q90:Q91) -> 773696.06

Sheet Breakeven
A1: © Person0811. All rights reserved.
A2: MENU | B2: =Profile!F6 -> Person0811
C4: Breakeven Analysis
C5: =Formulas!A3 -> Amounts in USD
E6: Case Scenario | F6: =Scenario!E6 -> Base Case
C7: Breakeven Analysis | H7: =Formulas!C9 -> 2025 | I7: =Formulas!D9 -> 2026 | J7: =Formulas!E9 -> 2027 | K7: =Formulas!F9 -> 2028 | L7: =Formulas!G9 -> 2029 | M7: =Formulas!H9 -> 2030 | N7: =Formulas!I9 -> 2031 | O7: =Formulas!J9 -> 2032 | ... Q7: =Formulas!L9 -> 2034
D8: Total Sales | H8: ='Annual Forecast'!H10 -> 444500 | I8: ='Annual Forecast'!I10 -> 471170 | J8: ='Annual Forecast'!J10 -> 494728.5 | K8: ='Annual Forecast'!K10 -> 514517.64 | L8: ='Annual Forecast'!L10 -> 529953.17 | M8: ='Annual Forecast'!M10 -> 545851.76 | N8: ='Annual Forecast'!N10 -> 556768.8 | O8: ='Annual Forecast'!O10 -> 567904.18 | ... Q8: ='Annual Forecast'!Q10 -> 590847.5
D9: Contribution Profit | H9: =H8-H16 -> 182276.5 | I9: =I8-I16 -> 150393.04 | J9: =J8-J16 -> 169437.4 | K9: =K8-K16 -> 186070.44 | L9: =L8-L16 -> 193032.93 | M9: =M8-M16 -> 208023.35 | N9: =N8-N16 -> 214948.84 | O9: =O8-O16 -> 231748.67 | ... Q9: =Q8-Q16 -> 247385.3
C10: Contribution Margin % | H10: =IFERROR(H9/H8,"") -> 0.41007087 | I10: =IFERROR(I9/I8,"") -> 0.31919061 | J10: =IFERROR(J9/J8,"") -> 0.34248564 | K10: =IFERROR(K9/K8,"") -> 0.36164054 | L10: =IFERROR(L9/L8,"") -> 0.36424526 | M10: =IFERROR(M9/M8,"") -> 0.38109862 | N10: =IFERROR(N9/N8,"") -> 0.38606481 | O10: =IFERROR(O9/O8,"") -> 0.40807706 | ... Q10: =IFERROR(Q9/Q8,"") -> 0.41869568
D12: Cost of Sales | H12: ='Annual Forecast'!H16 -> 233362.5 | I12: ='Annual Forecast'!I16 -> 289769.55 | J12: ='Annual Forecast'!J16 -> 294363.46 | K12: ='Annual Forecast'!K16 -> 295847.64 | L12: ='Annual Forecast'!L16 -> 302073.31 | M12: ='Annual Forecast'!M16 -> 300218.47 | N12: ='Annual Forecast'!N16 -> 306222.84 | O12: ='Annual Forecast'!O16 -> 300989.21 | ... Q12: ='Annual Forecast'!Q16 -> 310194.94
D13: Sales and Marketing | H13: ='Annual Forecast'!H22 -> 17780 | I13: ='Annual Forecast'!I22 -> 18846.8 | J13: ='Annual Forecast'!J22 -> 17315.498 | K13: ='Annual Forecast'!K22 -> 18008.117 | L13: ='Annual Forecast'!L22 -> 18548.361 | M13: ='Annual Forecast'!M22 -> 19104.812 | N13: ='Annual Forecast'!N22 -> 16703.064 | O13: ='Annual Forecast'!O22 -> 17037.125 | ... Q13: ='Annual Forecast'!Q22 -> 17725.425
D14: Credit Card Fees | H14: ='Annual Forecast'!H24 -> 3556 | I14: ='Annual Forecast'!I24 -> 3769.36 | J14: ='Annual Forecast'!J24 -> 3957.828 | K14: ='Annual Forecast'!K24 -> 4116.1411 | L14: ='Annual Forecast'!L24 -> 4239.6254 | M14: ='Annual Forecast'!M24 -> 4366.8141 | N14: ='Annual Forecast'!N24 -> 4454.1504 | O14: ='Annual Forecast'!O24 -> 4543.2334 | ... Q14: ='Annual Forecast'!Q24 -> 4726.78
D15: Depreciation and Amortization | H15: ='Annual Forecast'!H25 -> 7525 | I15: ='Annual Forecast'!I25 -> 8391.25 | J15: ='Annual Forecast'!J25 -> 9654.3125 | K15: ='Annual Forecast'!K25 -> 10475.303 | L15: ='Annual Forecast'!L25 -> 12058.947 | M15: ='Annual Forecast'!M25 -> 14138.316 | N15: ='Annual Forecast'!N25 -> 14439.905 | O15: ='Annual Forecast'!O25 -> 13585.938 | ... Q15: ='Annual Forecast'!Q25 -> 10815.059
C16: Variable Costs | H16: =SUM(H12:H15) -> 262223.5 | I16: =SUM(I12:I15) -> 320776.96 | J16: =SUM(J12:J15) -> 325291.1 | K16: =SUM(K12:K15) -> 328447.2 | L16: =SUM(L12:L15) -> 336920.24 | M16: =SUM(M12:M15) -> 337828.41 | N16: =SUM(N12:N15) -> 341819.96 | O16: =SUM(O12:O15) -> 336155.51 | ... Q16: =SUM(Q12:Q15) -> 343462.2
D18: Salaries and Benefits | H18: ='Annual Forecast'!H21 -> 50000 | I18: ='Annual Forecast'!I21 -> 50000 | J18: ='Annual Forecast'!J21 -> 50000 | K18: ='Annual Forecast'!K21 -> 50000 | L18: ='Annual Forecast'!L21 -> 50000 | M18: ='Annual Forecast'!M21 -> 50000 | N18: ='Annual Forecast'!N21 -> 50000 | O18: ='Annual Forecast'!O21 -> 50000 | ... Q18: ='Annual Forecast'!Q21 -> 50000
D19: General and Administration | H19: ='Annual Forecast'!H23 -> 35000 | I19: ='Annual Forecast'!I23 -> 35000 | J19: ='Annual Forecast'!J23 -> 35000 | K19: ='Annual Forecast'!K23 -> 35000 | L19: ='Annual Forecast'!L23 -> 35000 | M19: ='Annual Forecast'!M23 -> 35000 | N19: ='Annual Forecast'!N23 -> 35000 | O19: ='Annual Forecast'!O23 -> 35000 | ... Q19: ='Annual Forecast'!Q23 -> 35000
C20: Fixed Costs | H20: =SUM(H18:H19) -> 85000 | I20: =SUM(I18:I19) -> 85000 | J20: =SUM(J18:J19) -> 85000 | K20: =SUM(K18:K19) -> 85000 | L20: =SUM(L18:L19) -> 85000 | M20: =SUM(M18:M19) -> 85000 | N20: =SUM(N18:N19) -> 85000 | O20: =SUM(O18:O19) -> 85000 | ... Q20: =SUM(Q18:Q19) -> 85000
D22: Yearly Breakeven | H22: =H20/H10 -> 207281.25 | I22: =IFERROR(I20/I10,"") -> 266298.56 | J22: =IFERROR(J20/J10,"") -> 248185.59 | K22: =IFERROR(K20/K10,"") -> 235040.02 | L22: =IFERROR(L20/L10,"") -> 233359.25 | M22: =IFERROR(M20/M10,"") -> 223039.38 | N22: =IFERROR(N20/N10,"") -> 220170.29 | O22: =IFERROR(O20/O10,"") -> 208293.99 | P22: =IFERROR(P20/P10,"") -> 206957.26 | Q22: =IFERROR(Q20/Q10,"") -> 203011.41
D23: Monthly Breakeven | H23: =IFERROR(H22/12,"") -> 17273.437 | I23: =IFERROR(I22/12,"") -> 22191.547 | J23: =IFERROR(J22/12,"") -> 20682.133 | K23: =IFERROR(K22/12,"") -> 19586.669 | L23: =IFERROR(L22/12,"") -> 19446.604 | M23: =IFERROR(M22/12,"") -> 18586.615 | N23: =IFERROR(N22/12,"") -> 18347.524 | O23: =IFERROR(O22/12,"") -> 17357.833 | ... Q23: =IFERROR(Q22/12,"") -> 16917.617
E26: Year | F26: 2027
D27: Sales Volume | F27: =Formulas!M176 -> 1669.5
D28: Fixed Costs | F28: =Formulas!M177 -> 85000
D29: Variable Costs | F29: =Formulas!M178 -> 194.84342
D30: Sale Price | F30: =Formulas!M179 -> 296.33333
D31: Contribution Margin | F31: =Formulas!M180 -> 101.48991
D32: Contribution Margin % | F32: =Formulas!M181 -> 0.34248564
D33: BEP Sales Volume (Units) | F33: =Formulas!M182 -> 837.52168
D34: ="BEP"&" "&"("&Profile!F10&")" -> BEP (USD) | F34: =Formulas!M183 -> 248185.59

Sheet Ratios
A1: © Person0811. All rights reserved.
A2: MENU | B2: =Profile!F6 -> Person0811
C4: Financial Ratios
C5: =Formulas!A3 -> Amounts in USD
E6: Case Scenario | F6: =Scenario!E6 -> Base Case
C7: Profitability Ratios | H7: =Formulas!C212 -> 2025 | I7: =Formulas!D212 -> 2026 | J7: =Formulas!E212 -> 2027 | K7: =Formulas!F212 -> 2028 | L7: =Formulas!G212 -> 2029 | M7: =Formulas!H212 -> 2030 | N7: =Formulas!I212 -> 2031 | O7: =Formulas!J212 -> 2032 | ... Q7: =Formulas!L212 -> 2034
C8: Return on Equity (ROE) | H8: =Formulas!C213 -> 0.41520551 | I8: =Formulas!D213 -> 0.22300286 | J8: =Formulas!E213 -> 0.23398891 | K8: =Formulas!F213 -> 0.22774825 | L8: =Formulas!G213 -> 0.20240691 | M8: =Formulas!H213 -> 0.1935079 | N8: =Formulas!I213 -> 0.17458956 | O8: =Formulas!J213 -> 0.16934883 | ... Q8: =Formulas!L213 -> 0.14363565
C9: Return on Assets (ROA) | H9: =Formulas!C214 -> 0.25484439 | I9: =Formulas!D214 -> 0.14587769 | J9: =Formulas!E214 -> 0.16584364 | K9: =Formulas!F214 -> 0.17262477 | L9: =Formulas!G214 -> 0.16120556 | M9: =Formulas!H214 -> 0.16191615 | N9: =Formulas!I214 -> 0.15059659 | O9: =Formulas!J214 -> 0.15007926 | ... Q9: =Formulas!L214 -> 0.13193253
C10: Return on Capital Employed (ROCE) | H10: =Formulas!C215 -> 0.32426125 | I10: =Formulas!D215 -> 0.18881148 | J10: =Formulas!E215 -> 0.20639391 | K10: =Formulas!F215 -> 0.20785802 | L10: =Formulas!G215 -> 0.18968494 | M10: =Formulas!H215 -> 0.18477365 | N10: =Formulas!I215 -> 0.16916169 | O10: =Formulas!J215 -> 0.16580009 | ... Q10: =Formulas!L215 -> 0.14267781
C11: Gross Profit Margin | H11: =Formulas!C216 -> 0.475 | I11: =Formulas!D216 -> 0.385 | J11: =Formulas!E216 -> 0.405 | K11: =Formulas!F216 -> 0.425 | L11: =Formulas!G216 -> 0.43 | M11: =Formulas!H216 -> 0.45 | N11: =Formulas!I216 -> 0.45 | O11: =Formulas!J216 -> 0.47 | ... Q11: =Formulas!L216 -> 0.475
C12: Operating Profit Margin | H12: =Formulas!C217 -> 0.21884477 | I12: =Formulas!D217 -> 0.13878863 | J12: =Formulas!E217 -> 0.17067423 | K12: =Formulas!F217 -> 0.19643726 | L12: =Formulas!G217 -> 0.20385373 | M12: =Formulas!H217 -> 0.22537868 | N12: =Formulas!I217 -> 0.23339821 | O12: =Formulas!J217 -> 0.25840392 | ... Q12: =Formulas!L217 -> 0.27483454
C13: EBITDA Margin | H13: =Formulas!C218 -> 0.18284317 | I13: =Formulas!D218 -> 0.12350591 | J13: =Formulas!E218 -> 0.14890969 | K13: =Formulas!F218 -> 0.16888999 | L13: =Formulas!G218 -> 0.17668286 | M13: =Formulas!H218 -> 0.19581705 | N13: =Formulas!I218 -> 0.20172473 | O13: =Formulas!J218 -> 0.21833118 | ... Q13: =Formulas!L218 -> 0.22477929
C14: Net Profit Margin | H14: =Formulas!C219 -> 0.15879221 | I14: =Formulas!D219 -> 0.099276333 | J14: =Formulas!E219 -> 0.12383672 | K14: =Formulas!F219 -> 0.1437202 | L14: =Formulas!G219 -> 0.14977681 | M14: =Formulas!H219 -> 0.16638906 | N14: =Formulas!I219 -> 0.17282601 | O14: =Formulas!J219 -> 0.19198705 | ... Q14: =Formulas!L219 -> 0.20507868
C16: Liquidity Ratios
C17: Current Ratio | H17: =Formulas!C222 -> 5.060435 | I17: =Formulas!D222 -> 5.0095753 | J17: =Formulas!E222 -> 5.6160334 | K17: =Formulas!F222 -> 6.4213171 | L17: =Formulas!G222 -> 7.2053131 | M17: =Formulas!H222 -> 8.6830758 | N17: =Formulas!I222 -> 9.7461309 | O17: =Formulas!J222 -> 11.1907 | ... Q17: =Formulas!L222 -> 13.856577
C18: Quick Ratio | H18: =Formulas!C223 -> 4.2607865 | I18: =Formulas!D223 -> 4.1621985 | J18: =Formulas!E223 -> 4.7784589 | K18: =Formulas!F223 -> 5.5303376 | L18: =Formulas!G223 -> 6.3171662 | M18: =Formulas!H223 -> 7.7480425 | N18: =Formulas!I223 -> 8.7443094 | O18: =Formulas!J223 -> 10.203735 | ... Q18: =Formulas!L223 -> 12.807888
C19: Operating Cash Flow Ratio | H19: =Formulas!C224 -> 0.7659822 | I19: =Formulas!D224 -> 0.83955697 | J19: =Formulas!E224 -> 1.10582 | K19: =Formulas!F224 -> 1.2410421 | L19: =Formulas!G224 -> 1.3812446 | M19: =Formulas!H224 -> 1.7441973 | N19: =Formulas!I224 -> 1.6797575 | O19: =Formulas!J224 -> 1.9545476 | ... Q19: =Formulas!L224 -> 2.0220188
C21: Efficiency Ratios
C22: Days Sales Outstanding (DSO) | H22: =Formulas!C227 -> 40 | I22: =Formulas!D227 -> 40 | J22: =Formulas!E227 -> 40 | K22: =Formulas!F227 -> 40 | L22: =Formulas!G227 -> 40 | M22: =Formulas!H227 -> 35 | N22: =Formulas!I227 -> 35 | O22: =Formulas!J227 -> 35 | ... Q22: =Formulas!L227 -> 35
C23: Days Payable Outstanding (DPO) | H23: =Formulas!C228 -> 50 | I23: =Formulas!D228 -> 50 | J23: =Formulas!E228 -> 50 | K23: =Formulas!F228 -> 50 | L23: =Formulas!G228 -> 50 | M23: =Formulas!H228 -> 45 | N23: =Formulas!I228 -> 45 | O23: =Formulas!J228 -> 45 | ... Q23: =Formulas!L228 -> 45
C24: Days Inventory Outstanding (DIO) | H24: =Formulas!C229 -> 65 | I24: =Formulas!D229 -> 65 | J24: =Formulas!E229 -> 65 | K24: =Formulas!F229 -> 70 | L24: =Formulas!G229 -> 70 | M24: =Formulas!H229 -> 70 | N24: =Formulas!I229 -> 75 | O24: =Formulas!J229 -> 75 | ... Q24: =Formulas!L229 -> 80
C25: Cash Conversion Cycle | H25: =Formulas!C230 -> 55 | I25: =Formulas!D230 -> 55 | J25: =Formulas!E230 -> 55 | K25: =Formulas!F230 -> 60 | L25: =Formulas!G230 -> 60 | M25: =Formulas!H230 -> 60 | N25: =Formulas!I230 -> 65 | O25: =Formulas!J230 -> 65 | ... Q25: =Formulas!L230 -> 70
C27: Leverage Ratios
C28: Debt-to-Equity Ratio | H28: =Formulas!C233 -> 0.32353766 | I28: =Formulas!D233 -> 0.23837301 | J28: =Formulas!E233 -> 0.17186658 | K28: =Formulas!F233 -> 0.1231961 | L28: =Formulas!G233 -> 0.08925063 | M28: =Formulas!H233 -> 0.0639176 | N28: =Formulas!I233 -> 0.04536013 | O28: =Formulas!J233 -> 0.031064558 | ... Q28: =Formulas!L233 -> 0.011854038
C29: Shareholder Equity Ratio | H29: =Formulas!C234 -> 0.61377892 | I29: =Formulas!D234 -> 0.65415163 | J29: =Formulas!E234 -> 0.70876711 | K29: =Formulas!F234 -> 0.75796311 | L29: =Formulas!G234 -> 0.79644297 | M29: =Formulas!H234 -> 0.83674179 | N29: =Formulas!I234 -> 0.86257501 | O29: =Formulas!J234 -> 0.88621374 | ... Q29: =Formulas!L234 -> 0.91852215
C30: Debt-to-Total Assets Ratio | H30: =Formulas!C235 -> 0.19858059 | I30: =Formulas!D235 -> 0.15593209 | J30: =Formulas!E235 -> 0.12181338 | K30: =Formulas!F235 -> 0.093378099 | L30: =Formulas!G235 -> 0.071083036 | M30: =Formulas!H235 -> 0.053482527 | N30: =Formulas!I235 -> 0.039126515 | O30: =Formulas!J235 -> 0.027529839 | ... Q30: =Formulas!L235 -> 0.010888197
E32: Year | F32: 2025
C33: Profitability Ratios
C45: Liquidity Ratios
C57: Liquidity Ratios
C72: Leverage Ratios

Sheet Formulas
A1: © Person0811. All rights reserved.
A3: ="Amounts in"&" "&Profile!F10 -> Amounts in USD | T3: WACC | U3: EV/EBITDA Multiple | V3: Equity Value
A4: Scenarios | C4: Base Case | T4: =$A$19 -> 0.068323529 | U4: =$A$14 -> 1 | V4: =N19 -> 969880.53
C5: Best Case | T5: =$A$19 -> 0.068323529 | U5: =$A$15 -> 2 | V5: =N20 -> 1031361.1
C6: Worst Case | T6: =$A$19 -> 0.068323529 | U6: =$A$16 -> 3 | V6: =N21 -> 1082621.5
A7: Executive Summary | T7: =$A$19 -> 0.068323529 | U7: =$A$17 -> 4 | V7: =N22 -> 1125025.9
A8: Key Financial | C8: =IF((Profile!$F$9-COUNTBLANK($B2:B2))>=0,1,0) -> 1 | D8: =IF((Profile!$F$9-COUNTBLANK($B2:C2))>=0,1,0) -> 1 | E8: =IF((Profile!$F$9-COUNTBLANK($B2:D2))>=0,1,0) -> 1 | F8: =IF((Profile!$F$9-COUNTBLANK($B2:E2))>=0,1,0) -> 1 | G8: =IF((Profile!$F$9-COUNTBLANK($B2:F2))>=0,1,0) -> 1 | H8: =IF((Profile!$F$9-COUNTBLANK($B2:G2))>=0,1,0) -> 1 | I8: =IF((Profile!$F$9-COUNTBLANK($B2:H2))>=0,1,0) -> 1 | J8: =IF((Profile!$F$9-COUNTBLANK($B2:I2))>=0,1,0) -> 1 | ... L8: =IF((Profile!$F$9-COUNTBLANK($B2:K2))>=0,1,0) -> 1 | T8: =$A$19 -> 0.068323529 | U8: =$A$18 -> 5 | V8: =N23 -> 1159763.4
A9: Years | C9: =Profile!$F$8 -> 2025 | D9: =(C9+1)*D$8 -> 2026 | E9: =(D9+1)*E$8 -> 2027 | F9: =(E9+1)*F$8 -> 2028 | G9: =(F9+1)*G$8 -> 2029 | H9: =(G9+1)*H$8 -> 2030 | I9: =(H9+1)*I$8 -> 2031 | J9: =(I9+1)*J$8 -> 2032 | K9: =(J9+1)*K$8 -> 2033 | L9: =(K9+1)*L$8 -> 2034 | T9: =$A$20 -> 0.078323529 | U9: =$A$14 -> 1 | V9: =O19 -> 926062.77
T10: =$A$20 -> 0.078323529 | U10: =$A$15 -> 2 | V10: =O20 -> 987543.35
A11: Valuation | T11: =$A$20 -> 0.078323529 | U11: =$A$16 -> 3 | V11: =O21 -> 1038803.7
A12: Terminal Value | C12: =IF(COUNT($C8:C8)=Profile!$F$9,1,0) -> 0 | D12: =IF(COUNT($C8:D8)=Profile!$F$9,1,0) -> 0 | E12: =IF(COUNT($C8:E8)=Profile!$F$9,1,0) -> 0 | F12: =IF(COUNT($C8:F8)=Profile!$F$9,1,0) -> 0 | G12: =IF(COUNT($C8:G8)=Profile!$F$9,1,0) -> 0 | H12: =IF(COUNT($C8:H8)=Profile!$F$9,1,0) -> 0 | I12: =IF(COUNT($C8:I8)=Profile!$F$9,1,0) -> 0 | J12: =IF(COUNT($C8:J8)=Profile!$F$9,1,0) -> 0 | ... L12: =IF(COUNT($C8:L8)=Profile!$F$9,1,0) -> 1 | T12: =$A$20 -> 0.078323529 | U12: =$A$17 -> 4 | V12: =O22 -> 1081208.2
A13: Period | C13: 0 | D13: =COUNT($C$8:C8)*C8 -> 1 | E13: =COUNT($C$8:D8)*D8 -> 2 | F13: =COUNT($C$8:E8)*E8 -> 3 | G13: =COUNT($C$8:F8)*F8 -> 4 | H13: =COUNT($C$8:G8)*G8 -> 5 | I13: =COUNT($C$8:H8)*H8 -> 6 | J13: =COUNT($C$8:I8)*I8 -> 7 | K13: =COUNT($C$8:J8)*J8 -> 8 | L13: =COUNT($C$8:K8)*K8 -> 9 | T13: =$A$20 -> 0.078323529 | U13: =$A$18 -> 5 | V13: =O23 -> 1115945.7
A14: =Valuation!N29 -> 1 | B14: Terminal Value | C14: =Valuation!K$14*$A14*Formulas!C$12 -> 0 | D14: =Valuation!L$14*$A14*Formulas!D$12 -> 0 | E14: =Valuation!M$14*$A14*Formulas!E$12 -> 0 | F14: =Valuation!N$14*$A14*Formulas!F$12 -> 0 | G14: =Valuation!O$14*$A14*Formulas!G$12 -> 0 | H14: =Valuation!P$14*$A14*Formulas!H$12 -> 0 | I14: =Valuation!Q$14*$A14*Formulas!I$12 -> 0 | J14: =Valuation!R$14*$A14*Formulas!J$12 -> 0 | ... L14: =Valuation!T$14*$A14*Formulas!L$12 -> 132810.28 | T14: =$A$21 -> 0.088323529 | U14: =$A$14 -> 1 | V14: =P19 -> 885558.34
A15: =Valuation!N30 -> 2 | B15: Terminal Value | C15: =Valuation!K$14*$A15*Formulas!C$12 -> 0 | D15: =Valuation!L$14*$A15*Formulas!D$12 -> 0 | E15: =Valuation!M$14*$A15*Formulas!E$12 -> 0 | F15: =Valuation!N$14*$A15*Formulas!F$12 -> 0 | G15: =Valuation!O$14*$A15*Formulas!G$12 -> 0 | H15: =Valuation!P$14*$A15*Formulas!H$12 -> 0 | I15: =Valuation!Q$14*$A15*Formulas!I$12 -> 0 | J15: =Valuation!R$14*$A15*Formulas!J$12 -> 0 | ... L15: =Valuation!T$14*$A15*Formulas!L$12 -> 265620.57 | T15: =$A$21 -> 0.088323529 | U15: =$A$15 -> 2 | V15: =P20 -> 947038.92
A16: =Valuation!N31 -> 3 | B16: Terminal Value | C16: =Valuation!K$14*$A16*Formulas!C$12 -> 0 | D16: =Valuation!L$14*$A16*Formulas!D$12 -> 0 | E16: =Valuation!M$14*$A16*Formulas!E$12 -> 0 | F16: =Valuation!N$14*$A16*Formulas!F$12 -> 0 | G16: =Valuation!O$14*$A16*Formulas!G$12 -> 0 | H16: =Valuation!P$14*$A16*Formulas!H$12 -> 0 | I16: =Valuation!Q$14*$A16*Formulas!I$12 -> 0 | J16: =Valuation!R$14*$A16*Formulas!J$12 -> 0 | ... L16: =Valuation!T$14*$A16*Formulas!L$12 -> 398430.85 | T16: =$A$21 -> 0.088323529 | U16: =$A$16 -> 3 | V16: =P21 -> 998299.29
A17: =Valuation!N32 -> 4 | B17: Terminal Value | C17: =Valuation!K$14*$A17*Formulas!C$12 -> 0 | D17: =Valuation!L$14*$A17*Formulas!D$12 -> 0 | E17: =Valuation!M$14*$A17*Formulas!E$12 -> 0 | F17: =Valuation!N$14*$A17*Formulas!F$12 -> 0 | G17: =Valuation!O$14*$A17*Formulas!G$12 -> 0 | H17: =Valuation!P$14*$A17*Formulas!H$12 -> 0 | I17: =Valuation!Q$14*$A17*Formulas!I$12 -> 0 | J17: =Valuation!R$14*$A17*Formulas!J$12 -> 0 | ... L17: =Valuation!T$14*$A17*Formulas!L$12 -> 531241.14 | T17: =$A$21 -> 0.088323529 | U17: =$A$17 -> 4 | V17: =P22 -> 1040703.8
A18: =Valuation!N33 -> 5 | B18: Terminal Value | C18: =Valuation!K$14*$A18*Formulas!C$12 -> 0 | D18: =Valuation!L$14*$A18*Formulas!D$12 -> 0 | E18: =Valuation!M$14*$A18*Formulas!E$12 -> 0 | F18: =Valuation!N$14*$A18*Formulas!F$12 -> 0 | G18: =Valuation!O$14*$A18*Formulas!G$12 -> 0 | H18: =Valuation!P$14*$A18*Formulas!H$12 -> 0 | I18: =Valuation!Q$14*$A18*Formulas!I$12 -> 0 | J18: =Valuation!R$14*$A18*Formulas!J$12 -> 0 | ... L18: =Valuation!T$14*$A18*Formulas!L$12 -> 664051.42 | M18: =Valuation!$K$33 -> -112720.6 | N18: {=TRANSPOSE(M24:M28)} -> 783893.24 | O18: 740075.48 | P18: 699571.05 | Q18: 662088.62 | R18: 627365.45 | T18: =$A$21 -> 0.088323529 | U18: =$A$18 -> 5 | V18: =P23 -> 1075441.3
A19: =Valuation!P28 -> 0.068323529 | B19: PV of Terminal Value | C19: =C14/(1+$A19)^Formulas!C$13 -> 0 | D19: =D14/(1+$A19)^Formulas!D$13 -> 0 | E19: =E14/(1+$A19)^Formulas!E$13 -> 0 | F19: =F14/(1+$A19)^Formulas!F$13 -> 0 | G19: =G14/(1+$A19)^Formulas!G$13 -> 0 | H19: =H14/(1+$A19)^Formulas!H$13 -> 0 | I19: =I14/(1+$A19)^Formulas!I$13 -> 0 | J19: =J14/(1+$A19)^Formulas!J$13 -> 0 | ... L19: =L14/(1+$A19)^Formulas!L$13 -> 73266.689 | M19: =SUM(C19:L19) -> 73266.689 | N19: =N$18+$M19-$M$18 -> 969880.53 | O19: =O$18+$M19-$M$18 -> 926062.77 | P19: =P$18+$M19-$M$18 -> 885558.34 | Q19: =Q$18+$M19-$M$18 -> 848075.91 | R19: =R$18+$M19-$M$18 -> 813352.74 | T19: =$A$22 -> 0.098323529 | U19: =$A$14 -> 1 | V19: =Q19 -> 848075.91
A20: =Valuation!Q28 -> 0.078323529 | B20: PV of Terminal Value | C20: =C15/(1+$A20)^Formulas!C$13 -> 0 | D20: =D15/(1+$A20)^Formulas!D$13 -> 0 | E20: =E15/(1+$A20)^Formulas!E$13 -> 0 | F20: =F15/(1+$A20)^Formulas!F$13 -> 0 | G20: =G15/(1+$A20)^Formulas!G$13 -> 0 | H20: =H15/(1+$A20)^Formulas!H$13 -> 0 | I20: =I15/(1+$A20)^Formulas!I$13 -> 0 | J20: =J15/(1+$A20)^Formulas!J$13 -> 0 | ... L20: =L15/(1+$A20)^Formulas!L$13 -> 134747.27 | M20: =SUM(C20:L20) -> 134747.27 | N20: =N$18+$M20-$M$18 -> 1031361.1 | O20: =O$18+$M20-$M$18 -> 987543.35 | P20: =P$18+$M20-$M$18 -> 947038.92 | Q20: =Q$18+$M20-$M$18 -> 909556.49 | R20: =R$18+$M20-$M$18 -> 874833.32 | T20: =$A$22 -> 0.098323529 | U20: =$A$15 -> 2 | V20: =Q20 -> 909556.49
A21: =Valuation!R28 -> 0.088323529 | B21: PV of Terminal Value | C21: =C16/(1+$A21)^Formulas!C$13 -> 0 | D21: =D16/(1+$A21)^Formulas!D$13 -> 0 | E21: =E16/(1+$A21)^Formulas!E$13 -> 0 | F21: =F16/(1+$A21)^Formulas!F$13 -> 0 | G21: =G16/(1+$A21)^Formulas!G$13 -> 0 | H21: =H16/(1+$A21)^Formulas!H$13 -> 0 | I21: =I16/(1+$A21)^Formulas!I$13 -> 0 | J21: =J16/(1+$A21)^Formulas!J$13 -> 0 | ... L21: =L16/(1+$A21)^Formulas!L$13 -> 186007.64 | M21: =SUM(C21:L21) -> 186007.64 | N21: =N$18+$M21-$M$18 -> 1082621.5 | O21: =O$18+$M21-$M$18 -> 1038803.7 | P21: =P$18+$M21-$M$18 -> 998299.29 | Q21: =Q$18+$M21-$M$18 -> 960816.86 | R21: =R$18+$M21-$M$18 -> 926093.69 | T21: =$A$22 -> 0.098323529 | U21: =$A$16 -> 3 | V21: =Q21 -> 960816.86
A22: =Valuation!S28 -> 0.098323529 | B22: PV of Terminal Value | C22: =C17/(1+$A22)^Formulas!C$13 -> 0 | D22: =D17/(1+$A22)^Formulas!D$13 -> 0 | E22: =E17/(1+$A22)^Formulas!E$13 -> 0 | F22: =F17/(1+$A22)^Formulas!F$13 -> 0 | G22: =G17/(1+$A22)^Formulas!G$13 -> 0 | H22: =H17/(1+$A22)^Formulas!H$13 -> 0 | I22: =I17/(1+$A22)^Formulas!I$13 -> 0 | J22: =J17/(1+$A22)^Formulas!J$13 -> 0 | ... L22: =L17/(1+$A22)^Formulas!L$13 -> 228412.1 | M22: =SUM(C22:L22) -> 228412.1 | N22: =N$18+$M22-$M$18 -> 1125025.9 | O22: =O$18+$M22-$M$18 -> 1081208.2 | P22: =P$18+$M22-$M$18 -> 1040703.8 | Q22: =Q$18+$M22-$M$18 -> 1003221.3 | R22: =R$18+$M22-$M$18 -> 968498.15 | T22: =$A$22 -> 0.098323529 | U22: =$A$17 -> 4 | V22: =Q22 -> 1003221.3
A23: =Valuation!T28 -> 0.10832353 | B23: PV of Terminal Value | C23: =C18/(1+$A23)^Formulas!C$13 -> 0 | D23: =D18/(1+$A23)^Formulas!D$13 -> 0 | E23: =E18/(1+$A23)^Formulas!E$13 -> 0 | F23: =F18/(1+$A23)^Formulas!F$13 -> 0 | G23: =G18/(1+$A23)^Formulas!G$13 -> 0 | H23: =H18/(1+$A23)^Formulas!H$13 -> 0 | I23: =I18/(1+$A23)^Formulas!I$13 -> 0 | J23: =J18/(1+$A23)^Formulas!J$13 -> 0 | ... L23: =L18/(1+$A23)^Formulas!L$13 -> 263149.61 | M23: =SUM(C23:L23) -> 263149.61 | N23: =N$18+$M23-$M$18 -> 1159763.4 | O23: =O$18+$M23-$M$18 -> 1115945.7 | P23: =P$18+$M23-$M$18 -> 1075441.3 | Q23: =Q$18+$M23-$M$18 -> 1037958.8 | R23: =R$18+$M23-$M$18 -> 1003235.7 | T23: =$A$22 -> 0.098323529 | U23: =$A$18 -> 5 | V23: =Q23 -> 1037958.8
A24: =Valuation!P28 -> 0.068323529 | B24: PV of Net FCF | C24: =Valuation!K$19/(1+Formulas!$A24)^Formulas!C$13 -> 21473.719 | D24: =Valuation!L$19/(1+Formulas!$A24)^Formulas!D$13 -> 41327.923 | E24: =Valuation!M$19/(1+Formulas!$A24)^Formulas!E$13 -> 52535.405 | F24: =Valuation!N$19/(1+Formulas!$A24)^Formulas!F$13 -> 57004.32 | G24: =Valuation!O$19/(1+Formulas!$A24)^Formulas!G$13 -> 59339.42 | H24: =Valuation!P$19/(1+Formulas!$A24)^Formulas!H$13 -> 65627.173 | I24: =Valuation!Q$19/(1+Formulas!$A24)^Formulas!I$13 -> 61985.449 | J24: =Valuation!R$19/(1+Formulas!$A24)^Formulas!J$13 -> 70426.247 | ... L24: =Valuation!T$19/(1+Formulas!$A24)^Formulas!L$13 -> 288159.66 | M24: =SUM(C24:L24) -> 783893.24 | T24: =$A$23 -> 0.10832353 | U24: =$A$14 -> 1 | V24: =R19 -> 813352.74
A25: =Valuation!Q28 -> 0.078323529 | B25: PV of Net FCF | C25: =Valuation!K$19/(1+Formulas!$A25)^Formulas!C$13 -> 21473.719 | D25: =Valuation!L$19/(1+Formulas!$A25)^Formulas!D$13 -> 40944.662 | E25: =Valuation!M$19/(1+Formulas!$A25)^Formulas!E$13 -> 51565.533 | F25: =Valuation!N$19/(1+Formulas!$A25)^Formulas!F$13 -> 55433.067 | G25: =Valuation!O$19/(1+Formulas!$A25)^Formulas!G$13 -> 57168.677 | H25: =Valuation!P$19/(1+Formulas!$A25)^Formulas!H$13 -> 62640.073 | I25: =Valuation!Q$19/(1+Formulas!$A25)^Formulas!I$13 -> 58615.439 | J25: =Valuation!R$19/(1+Formulas!$A25)^Formulas!J$13 -> 65979.729 | ... L25: =Valuation!T$19/(1+Formulas!$A25)^Formulas!L$13 -> 264982.13 | M25: =SUM(C25:L25) -> 740075.48 | T25: =$A$23 -> 0.10832353 | U25: =$A$15 -> 2 | V25: =R20 -> 874833.32
A26: =Valuation!R28 -> 0.088323529 | B26: PV of Net FCF | C26: =Valuation!K$19/(1+Formulas!$A26)^Formulas!C$13 -> 21473.719 | D26: =Valuation!L$19/(1+Formulas!$A26)^Formulas!D$13 -> 40568.444 | E26: =Valuation!M$19/(1+Formulas!$A26)^Formulas!E$13 -> 50622.272 | F26: =Valuation!N$19/(1+Formulas!$A26)^Formulas!F$13 -> 53919.033 | G26: =Valuation!O$19/(1+Formulas!$A26)^Formulas!G$13 -> 55096.295 | H26: =Valuation!P$19/(1+Formulas!$A26)^Formulas!H$13 -> 59814.651 | I26: =Valuation!Q$19/(1+Formulas!$A26)^Formulas!I$13 -> 55457.259 | J26: =Valuation!R$19/(1+Formulas!$A26)^Formulas!J$13 -> 61851.177 | ... L26: =Valuation!T$19/(1+Formulas!$A26)^Formulas!L$13 -> 243857.52 | M26: =SUM(C26:L26) -> 699571.05 | T26: =$A$23 -> 0.10832353 | U26: =$A$16 -> 3 | V26: =R21 -> 926093.69
A27: =Valuation!S28 -> 0.098323529 | B27: PV of Net FCF | C27: =Valuation!K$19/(1+Formulas!$A27)^Formulas!C$13 -> 21473.719 | D27: =Valuation!L$19/(1+Formulas!$A27)^Formulas!D$13 -> 40199.077 | E27: =Valuation!M$19/(1+Formulas!$A27)^Formulas!E$13 -> 49704.659 | F27: =Valuation!N$19/(1+Formulas!$A27)^Formulas!F$13 -> 52459.638 | G27: =Valuation!O$19/(1+Formulas!$A27)^Formulas!G$13 -> 53116.973 | H27: =Valuation!P$19/(1+Formulas!$A27)^Formulas!H$13 -> 57140.789 | I27: =Valuation!Q$19/(1+Formulas!$A27)^Formulas!I$13 -> 52495.828 | J27: =Valuation!R$19/(1+Formulas!$A27)^Formulas!J$13 -> 58015.239 | ... L27: =Valuation!T$19/(1+Formulas!$A27)^Formulas!L$13 -> 224587.58 | M27: =SUM(C27:L27) -> 662088.62 | T27: =$A$23 -> 0.10832353 | U27: =$A$17 -> 4 | V27: =R22 -> 968498.15
A28: =Valuation!T28 -> 0.10832353 | B28: PV of Net FCF | C28: =Valuation!K$19/(1+Formulas!$A28)^Formulas!C$13 -> 21473.719 | D28: =Valuation!L$19/(1+Formulas!$A28)^Formulas!D$13 -> 39836.376 | E28: =Valuation!M$19/(1+Formulas!$A28)^Formulas!E$13 -> 48811.771 | F28: =Valuation!N$19/(1+Formulas!$A28)^Formulas!F$13 -> 51052.439 | G28: =Valuation!O$19/(1+Formulas!$A28)^Formulas!G$13 -> 51225.742 | H28: =Valuation!P$19/(1+Formulas!$A28)^Formulas!H$13 -> 54609.085 | I28: =Valuation!Q$19/(1+Formulas!$A28)^Formulas!I$13 -> 49717.261 | J28: =Valuation!R$19/(1+Formulas!$A28)^Formulas!J$13 -> 54448.789 | ... L28: =Valuation!T$19/(1+Formulas!$A28)^Formulas!L$13 -> 206994.76 | M28: =SUM(C28:L28) -> 627365.45 | T28: =$A$23 -> 0.10832353 | U28: =$A$18 -> 5 | V28: =R23 -> 1003235.7
C30: x | D30: x | E30: x | F30: x | G30: x | H30: x | I30: x | J30: x | K30: x | L30: x
B31: Period | C31: =C9 -> 2025 | D31: =D9 -> 2026 | E31: =E9 -> 2027 | F31: =F9 -> 2028 | G31: =G9 -> 2029 | H31: =H9 -> 2030 | I31: =I9 -> 2031 | J31: =J9 -> 2032 | ... L31: =L9 -> 2034
B32: Cumulative CashFlow | C32: =Summary!E16 -> 172720.6 | D32: =Summary!F16 -> 201830.79 | E32: =Summary!G16 -> 244850.41 | F32: =Summary!H16 -> 295788.44 | G32: =Summary!I16 -> 353977.78 | H32: =Summary!J16 -> 424755.89 | I32: =Summary!K16 -> 495824.65 | J32: =Summary!L16 -> 584949.77 | ... L32: =Summary!N16 -> 773696.06
B33: difference | C33: =C32 -> 172720.6 | D33: =D32-C32 -> 29110.188 | E33: =E32-D32 -> 43019.621 | F33: =F32-E32 -> 50938.03 | G33: =G32-F32 -> 58189.341 | H33: =H32-G32 -> 70778.115 | I33: =I32-H32 -> 71068.752 | J33: =J32-I32 -> 89125.127 | K33: =K32-J32 -> 88831.616 | L33: =L32-K32 -> 99914.671
B34: Revenue | C34: =Summary!E9 -> 444500 | D34: =Summary!F9 -> 471170 | E34: =Summary!G9 -> 494728.5 | F34: =Summary!H9 -> 514517.64 | G34: =Summary!I9 -> 529953.17 | H34: =Summary!J9 -> 545851.76 | I34: =Summary!K9 -> 556768.8 | J34: =Summary!L9 -> 567904.18 | ... L34: =Summary!N9 -> 590847.5
B35: EBITDA | C35: {=Summary!$E$12:$N$12} -> 104801.5 | D35: 73784.29 | E35: 94091.717 | F35: 111545.74 | G35: 120091.88 | H35: 137161.67 | I35: 144388.75 | J35: 160334.6 | K35: 165241.3 | L35: 173200.36
B36: EV/Revenue | C36: =Summary!E18 -> 0.64629787 | D36: =Summary!F18 -> 0.60971497 | E36: =Summary!G18 -> 0.58068092 | F36: =Summary!H18 -> 0.55834704 | G36: =Summary!I18 -> 0.54208451 | H36: =Summary!J18 -> 0.52629564 | I36: =Summary!K18 -> 0.51597611 | J36: =Summary!L18 -> 0.50585894 | ... L36: =Summary!N18 -> 0.48621582
B37: EV/EBITDA | C37: =Summary!E19 -> 2.7411764 | D37: =Summary!F19 -> 3.8935036 | E37: =Summary!G19 -> 3.0531848 | F37: =Summary!H19 -> 2.5754404 | G37: =Summary!I19 -> 2.3921635 | H37: =Summary!J19 -> 2.0944584 | I37: =Summary!K19 -> 1.9896246 | J37: =Summary!L19 -> 1.7917492 | ... L37: =Summary!N19 -> 1.6586536
B39: IRR Valuation | C39: =IF(Valuation!$K$47 >= 15%, "Good Investment", IF(Valuation!$K$47 >= 10%, "Acceptable Investment", IF(Valuation!$K$47 >= 5%, "Low Return", "Not Recommended"))) -> Good Investment
A41: Revenue | C41: January | D41: February | E41: March | F41: April | G41: May | H41: June | I41: July | J41: August | K41: September | L41: October | M41: November | N41: December
A42: Service & Product | C42: =1+Revenue!G8 -> 1.02 | D42: =1+Revenue!H8 -> 1.03 | E42: =1+Revenue!I8 -> 1.04 | F42: =1+Revenue!J8 -> 1.05 | G42: =1+Revenue!K8 -> 1.1 | H42: =1+Revenue!L8 -> 1.12 | I42: =1+Revenue!M8 -> 1.08 | J42: =1+Revenue!N8 -> 1.05 | ... N42: =1+Revenue!R8 -> 1.12
A44: Scenario | C44: =Profile!F8 -> 2025 | D44: =(C44+1)*D$8 -> 2026 | E44: =(D44+1)*E$8 -> 2027 | F44: =(E44+1)*F$8 -> 2028 | G44: =(F44+1)*G$8 -> 2029 | H44: =(G44+1)*H$8 -> 2030 | I44: =(H44+1)*I$8 -> 2031 | J44: =(I44+1)*J$8 -> 2032 | K44: =(J44+1)*K$8 -> 2033 | L44: =(K44+1)*L$8 -> 2034
A45: Revenue Growth | C45: =INDEX(C46:C48, MATCH(Scenario!$E$6, Formulas!$C$4:$C$6, 0))*C$8 -> 0 | D45: =INDEX(D46:D48, MATCH(Scenario!$E$6, Formulas!$C$4:$C$6, 0))*D$8 -> 0.06 | E45: =INDEX(E46:E48, MATCH(Scenario!$E$6, Formulas!$C$4:$C$6, 0))*E$8 -> 0.05 | F45: =INDEX(F46:F48, MATCH(Scenario!$E$6, Formulas!$C$4:$C$6, 0))*F$8 -> 0.04 | G45: =INDEX(G46:G48, MATCH(Scenario!$E$6, Formulas!$C$4:$C$6, 0))*G$8 -> 0.03 | H45: =INDEX(H46:H48, MATCH(Scenario!$E$6, Formulas!$C$4:$C$6, 0))*H$8 -> 0.03 | I45: =INDEX(I46:I48, MATCH(Scenario!$E$6, Formulas!$C$4:$C$6, 0))*I$8 -> 0.02 | J45: =INDEX(J46:J48, MATCH(Scenario!$E$6, Formulas!$C$4:$C$6, 0))*J$8 -> 0.02 | ... L45: =INDEX(L46:L48, MATCH(Scenario!$E$6, Formulas!$C$4:$C$6, 0))*L$8 -> 0.02
B46: Base Case | C46: =Scenario!G39 -> 0 | D46: =Scenario!H39 -> 0.06 | E46: =Scenario!I39 -> 0.05 | F46: =Scenario!J39 -> 0.04 | G46: =Scenario!K39 -> 0.03 | H46: =Scenario!L39 -> 0.03 | I46: =Scenario!M39 -> 0.02 | J46: =Scenario!N39 -> 0.02 | ... L46: =Scenario!P39 -> 0.02
B47: Best Case | C47: =Scenario!G69 -> 0 | D47: =Scenario!H69 -> 0.08 | E47: =Scenario!I69 -> 0.07 | F47: =Scenario!J69 -> 0.06 | G47: =Scenario!K69 -> 0.05 | H47: =Scenario!L69 -> 0.05 | I47: =Scenario!M69 -> 0.04 | J47: =Scenario!N69 -> 0.04 | ... L47: =Scenario!P69 -> 0.03
B48: Worst Case | C48: =Scenario!G99 -> 0 | D48: =Scenario!H99 -> 0.02 | E48: =Scenario!I99 -> 0.02 | F48: =Scenario!J99 -> 0.01 | G48: =Scenario!K99 -> 0.01 | H48: =Scenario!L99 -> 0.01 | I48: =Scenario!M99 -> 0 | J48: =Scenario!N99 -> 0 | ... L48: =Scenario!P99 -> -0.01
A49: Service Cost | C49: =INDEX(C50:C52, MATCH(Scenario!$E$6, Formulas!$C$4:$C$6, 0))*C$8 -> 0 | D49: =INDEX(D50:D52, MATCH(Scenario!$E$6, Formulas!$C$4:$C$6, 0))*D$8 -> 0.25 | E49: =INDEX(E50:E52, MATCH(Scenario!$E$6, Formulas!$C$4:$C$6, 0))*E$8 -> 0.25 | F49: =INDEX(F50:F52, MATCH(Scenario!$E$6, Formulas!$C$4:$C$6, 0))*F$8 -> 0.24 | G49: =INDEX(G50:G52, MATCH(Scenario!$E$6, Formulas!$C$4:$C$6, 0))*G$8 -> 0.24 | H49: =INDEX(H50:H52, MATCH(Scenario!$E$6, Formulas!$C$4:$C$6, 0))*H$8 -> 0.23 | I49: =INDEX(I50:I52, MATCH(Scenario!$E$6, Formulas!$C$4:$C$6, 0))*I$8 -> 0.23 | J49: =INDEX(J50:J52, MATCH(Scenario!$E$6, Formulas!$C$4:$C$6, 0))*J$8 -> 0.22 | ... L49: =INDEX(L50:L52, MATCH(Scenario!$E$6, Formulas!$C$4:$C$6, 0))*L$8 -> 0.21
B50: Base Case | C50: =Scenario!G40 -> 0 | D50: =Scenario!H40 -> 0.25 | E50: =Scenario!I40 -> 0.25 | F50: =Scenario!J40 -> 0.24 | G50: =Scenario!K40 -> 0.24 | H50: =Scenario!L40 -> 0.23 | I50: =Scenario!M40 -> 0.23 | J50: =Scenario!N40 -> 0.22 | ... L50: =Scenario!P40 -> 0.21
B51: Best Case | C51: =Scenario!G70 -> 0 | D51: =Scenario!H70 -> 0.18 | E51: =Scenario!I70 -> 0.18 | F51: =Scenario!J70 -> 0.17 | G51: =Scenario!K70 -> 0.17 | H51: =Scenario!L70 -> 0.17 | I51: =Scenario!M70 -> 0.16 | J51: =Scenario!N70 -> 0.16 | ... L51: =Scenario!P70 -> 0.15
B52: Worst Case | C52: =Scenario!G100 -> 0 | D52: =Scenario!H100 -> 0.3 | E52: =Scenario!I100 -> 0.3 | F52: =Scenario!J100 -> 0.32 | G52: =Scenario!K100 -> 0.32 | H52: =Scenario!L100 -> 0.33 | I52: =Scenario!M100 -> 0.34 | J52: =Scenario!N100 -> 0.34 | ... L52: =Scenario!P100 -> 0.36
A53: Product Cost | C53: =INDEX(C54:C56, MATCH(Scenario!$E$6, Formulas!$C$4:$C$6, 0))*C$8 -> 0 | D53: =INDEX(D54:D56, MATCH(Scenario!$E$6, Formulas!$C$4:$C$6, 0))*D$8 -> 0.4 | E53: =INDEX(E54:E56, MATCH(Scenario!$E$6, Formulas!$C$4:$C$6, 0))*E$8 -> 0.38 | F53: =INDEX(F54:F56, MATCH(Scenario!$E$6, Formulas!$C$4:$C$6, 0))*F$8 -> 0.37 | G53: =INDEX(G54:G56, MATCH(Scenario!$E$6, Formulas!$C$4:$C$6, 0))*G$8 -> 0.36 | H53: =INDEX(H54:H56, MATCH(Scenario!$E$6, Formulas!$C$4:$C$6, 0))*H$8 -> 0.35 | I53: =INDEX(I54:I56, MATCH(Scenario!$E$6, Formulas!$C$4:$C$6, 0))*I$8 -> 0.35 | J53: =INDEX(J54:J56, MATCH(Scenario!$E$6, Formulas!$C$4:$C$6, 0))*J$8 -> 0.34 | ... L53: =INDEX(L54:L56, MATCH(Scenario!$E$6, Formulas!$C$4:$C$6, 0))*L$8 -> 0.34
B54: Base Case | C54: =Scenario!G41 -> 0 | D54: =Scenario!H41 -> 0.4 | E54: =Scenario!I41 -> 0.38 | F54: =Scenario!J41 -> 0.37 | G54: =Scenario!K41 -> 0.36 | H54: =Scenario!L41 -> 0.35 | I54: =Scenario!M41 -> 0.35 | J54: =Scenario!N41 -> 0.34 | ... L54: =Scenario!P41 -> 0.34
B55: Best Case | C55: =Scenario!G71 -> 0 | D55: =Scenario!H71 -> 0.4 | E55: =Scenario!I71 -> 0.38 | F55: =Scenario!J71 -> 0.37 | G55: =Scenario!K71 -> 0.36 | H55: =Scenario!L71 -> 0.35 | I55: =Scenario!M71 -> 0.35 | J55: =Scenario!N71 -> 0.34 | ... L55: =Scenario!P71 -> 0.33
B56: Worst Case | C56: =Scenario!G101 -> 0 | D56: =Scenario!H101 -> 0.55 | E56: =Scenario!I101 -> 0.56 | F56: =Scenario!J101 -> 0.57 | G56: =Scenario!K101 -> 0.58 | H56: =Scenario!L101 -> 0.58 | I56: =Scenario!M101 -> 0.59 | J56: =Scenario!N101 -> 0.6 | ... L56: =Scenario!P101 -> 0.6
A57: Direct Labor Cost | C57: =INDEX(C58:C60, MATCH(Scenario!$E$6, Formulas!$C$4:$C$6, 0))*C$8 -> 0.18 | D57: =INDEX(D58:D60, MATCH(Scenario!$E$6, Formulas!$C$4:$C$6, 0))*D$8 -> 0.18 | E57: =INDEX(E58:E60, MATCH(Scenario!$E$6, Formulas!$C$4:$C$6, 0))*E$8 -> 0.18 | F57: =INDEX(F58:F60, MATCH(Scenario!$E$6, Formulas!$C$4:$C$6, 0))*F$8 -> 0.18 | G57: =INDEX(G58:G60, MATCH(Scenario!$E$6, Formulas!$C$4:$C$6, 0))*G$8 -> 0.18 | H57: =INDEX(H58:H60, MATCH(Scenario!$E$6, Formulas!$C$4:$C$6, 0))*H$8 -> 0.18 | I57: =INDEX(I58:I60, MATCH(Scenario!$E$6, Formulas!$C$4:$C$6, 0))*I$8 -> 0.18 | J57: =INDEX(J58:J60, MATCH(Scenario!$E$6, Formulas!$C$4:$C$6, 0))*J$8 -> 0.18 | ... L57: =INDEX(L58:L60, MATCH(Scenario!$E$6, Formulas!$C$4:$C$6, 0))*L$8 -> 0.18
B58: Base Case | C58: =Scenario!G42 -> 0.18 | D58: =Scenario!H42 -> 0.18 | E58: =Scenario!I42 -> 0.18 | F58: =Scenario!J42 -> 0.18 | G58: =Scenario!K42 -> 0.18 | H58: =Scenario!L42 -> 0.18 | I58: =Scenario!M42 -> 0.18 | J58: =Scenario!N42 -> 0.18 | ... L58: =Scenario!P42 -> 0.18
B59: Best Case | C59: =Scenario!G72 -> 0.17 | D59: =Scenario!H72 -> 0.17 | E59: =Scenario!I72 -> 0.17 | F59: =Scenario!J72 -> 0.17 | G59: =Scenario!K72 -> 0.17 | H59: =Scenario!L72 -> 0.17 | I59: =Scenario!M72 -> 0.17 | J59: =Scenario!N72 -> 0.17 | ... L59: =Scenario!P72 -> 0.17
B60: Worst Case | C60: =Scenario!G102 -> 0.22 | D60: =Scenario!H102 -> 0.22 | E60: =Scenario!I102 -> 0.22 | F60: =Scenario!J102 -> 0.22 | G60: =Scenario!K102 -> 0.22 | H60: =Scenario!L102 -> 0.22 | I60: =Scenario!M102 -> 0.22 | J60: =Scenario!N102 -> 0.22 | ... L60: =Scenario!P102 -> 0.22
A61: Discount and Promotions | C61: =INDEX(C62:C64, MATCH(Scenario!$E$6, Formulas!$C$4:$C$6, 0))*C$8 -> 0.12 | D61: =INDEX(D62:D64, MATCH(Scenario!$E$6, Formulas!$C$4:$C$6, 0))*D$8 -> 0.11 | E61: =INDEX(E62:E64, MATCH(Scenario!$E$6, Formulas!$C$4:$C$6, 0))*E$8 -> 0.1 | F61: =INDEX(F62:F64, MATCH(Scenario!$E$6, Formulas!$C$4:$C$6, 0))*F$8 -> 0.09 | G61: =INDEX(G62:G64, MATCH(Scenario!$E$6, Formulas!$C$4:$C$6, 0))*G$8 -> 0.09 | H61: =INDEX(H62:H64, MATCH(Scenario!$E$6, Formulas!$C$4:$C$6, 0))*H$8 -> 0.08 | I61: =INDEX(I62:I64, MATCH(Scenario!$E$6, Formulas!$C$4:$C$6, 0))*I$8 -> 0.08 | J61: =INDEX(J62:J64, MATCH(Scenario!$E$6, Formulas!$C$4:$C$6, 0))*J$8 -> 0.07 | ... L61: =INDEX(L62:L64, MATCH(Scenario!$E$6, Formulas!$C$4:$C$6, 0))*L$8 -> 0.07
B62: Base Case | C62: =Scenario!G43 -> 0.12 | D62: =Scenario!H43 -> 0.11 | E62: =Scenario!I43 -> 0.1 | F62: =Scenario!J43 -> 0.09 | G62: =Scenario!K43 -> 0.09 | H62: =Scenario!L43 -> 0.08 | I62: =Scenario!M43 -> 0.08 | J62: =Scenario!N43 -> 0.07 | ... L62: =Scenario!P43 -> 0.07
B63: Best Case | C63: =Scenario!G73 -> 0.12 | D63: =Scenario!H73 -> 0.11 | E63: =Scenario!I73 -> 0.1 | F63: =Scenario!J73 -> 0.1 | G63: =Scenario!K73 -> 0.09 | H63: =Scenario!L73 -> 0.09 | I63: =Scenario!M73 -> 0.08 | J63: =Scenario!N73 -> 0.08 | ... L63: =Scenario!P73 -> 0.07
B64: Worst Case | C64: =Scenario!G103 -> 0.18 | D64: =Scenario!H101 -> 0.55 | E64: =Scenario!I101 -> 0.56 | F64: =Scenario!J101 -> 0.57 | G64: =Scenario!K101 -> 0.58 | H64: =Scenario!L101 -> 0.58 | I64: =Scenario!M101 -> 0.59 | J64: =Scenario!N101 -> 0.6 | K64: =Scenario!O101 -> 0.6 | L64: =Scenario!P101 -> 0.6
A65: Salaries and Benefits | C65: =INDEX(C66:C68, MATCH(Scenario!$E$6, Formulas!$C$4:$C$6, 0))*C$8 -> 50000 | D65: =INDEX(D66:D68, MATCH(Scenario!$E$6, Formulas!$C$4:$C$6, 0))*D$8 -> 50000 | E65: =INDEX(E66:E68, MATCH(Scenario!$E$6, Formulas!$C$4:$C$6, 0))*E$8 -> 50000 | F65: =INDEX(F66:F68, MATCH(Scenario!$E$6, Formulas!$C$4:$C$6, 0))*F$8 -> 50000 | G65: =INDEX(G66:G68, MATCH(Scenario!$E$6, Formulas!$C$4:$C$6, 0))*G$8 -> 50000 | H65: =INDEX(H66:H68, MATCH(Scenario!$E$6, Formulas!$C$4:$C$6, 0))*H$8 -> 50000 | I65: =INDEX(I66:I68, MATCH(Scenario!$E$6, Formulas!$C$4:$C$6, 0))*I$8 -> 50000 | J65: =INDEX(J66:J68, MATCH(Scenario!$E$6, Formulas!$C$4:$C$6, 0))*J$8 -> 50000 | ... L65: =INDEX(L66:L68, MATCH(Scenario!$E$6, Formulas!$C$4:$C$6, 0))*L$8 -> 50000
B66: Base Case | C66: =Scenario!G44 -> 50000 | D66: =Scenario!H44 -> 50000 | E66: =Scenario!I44 -> 50000 | F66: =Scenario!J44 -> 50000 | G66: =Scenario!K44 -> 50000 | H66: =Scenario!L44 -> 50000 | I66: =Scenario!M44 -> 50000 | J66: =Scenario!N44 -> 50000 | ... L66: =Scenario!P44 -> 50000
B67: Best Case | C67: =Scenario!G74 -> 50000 | D67: =Scenario!H74 -> 50000 | E67: =Scenario!I74 -> 50000 | F67: =Scenario!J74 -> 50000 | G67: =Scenario!K74 -> 50000 | H67: =Scenario!L74 -> 50000 | I67: =Scenario!M74 -> 50000 | J67: =Scenario!N74 -> 50000 | ... L67: =Scenario!P74 -> 50000
B68: Worst Case | C68: =Scenario!G104 -> 40000 | D68: =Scenario!H104 -> 40000 | E68: =Scenario!I104 -> 40000 | F68: =Scenario!J104 -> 40000 | G68: =Scenario!K104 -> 40000 | H68: =Scenario!L104 -> 40000 | I68: =Scenario!M104 -> 40000 | J68: =Scenario!N104 -> 40000 | ... L68: =Scenario!P104 -> 40000
A69: Sales and Marketing | C69: =INDEX(C70:C72, MATCH(Scenario!$E$6, Formulas!$C$4:$C$6, 0))*C$8 -> 0.04 | D69: =INDEX(D70:D72, MATCH(Scenario!$E$6, Formulas!$C$4:$C$6, 0))*D$8 -> 0.04 | E69: =INDEX(E70:E72, MATCH(Scenario!$E$6, Formulas!$C$4:$C$6, 0))*E$8 -> 0.035 | F69: =INDEX(F70:F72, MATCH(Scenario!$E$6, Formulas!$C$4:$C$6, 0))*F$8 -> 0.035 | G69: =INDEX(G70:G72, MATCH(Scenario!$E$6, Formulas!$C$4:$C$6, 0))*G$8 -> 0.035 | H69: =INDEX(H70:H72, MATCH(Scenario!$E$6, Formulas!$C$4:$C$6, 0))*H$8 -> 0.035 | I69: =INDEX(I70:I72, MATCH(Scenario!$E$6, Formulas!$C$4:$C$6, 0))*I$8 -> 0.03 | J69: =INDEX(J70:J72, MATCH(Scenario!$E$6, Formulas!$C$4:$C$6, 0))*J$8 -> 0.03 | ... L69: =INDEX(L70:L72, MATCH(Scenario!$E$6, Formulas!$C$4:$C$6, 0))*L$8 -> 0.03
B70: Base Case | C70: =Scenario!G45 -> 0.04 | D70: =Scenario!H45 -> 0.04 | E70: =Scenario!I45 -> 0.035 | F70: =Scenario!J45 -> 0.035 | G70: =Scenario!K45 -> 0.035 | H70: =Scenario!L45 -> 0.035 | I70: =Scenario!M45 -> 0.03 | J70: =Scenario!N45 -> 0.03 | ... L70: =Scenario!P45 -> 0.03
B71: Best Case | C71: =Scenario!G75 -> 0.04 | D71: =Scenario!H75 -> 0.04 | E71: =Scenario!I75 -> 0.035 | F71: =Scenario!J75 -> 0.035 | G71: =Scenario!K75 -> 0.035 | H71: =Scenario!L75 -> 0.03 | I71: =Scenario!M75 -> 0.03 | J71: =Scenario!N75 -> 0.03 | ... L71: =Scenario!P75 -> 0.025
B72: Worst Case | C72: =Scenario!G105 -> 0.05 | D72: =Scenario!H105 -> 0.05 | E72: =Scenario!I105 -> 0.05 | F72: =Scenario!J105 -> 0.045 | G72: =Scenario!K105 -> 0.045 | H72: =Scenario!L105 -> 0.04 | I72: =Scenario!M105 -> 0.04 | J72: =Scenario!N105 -> 0.04 | ... L72: =Scenario!P105 -> 0.035
A73: General and Administration | C73: =INDEX(C74:C76, MATCH(Scenario!$E$6, Formulas!$C$4:$C$6, 0))*C$8 -> 35000 | D73: =INDEX(D74:D76, MATCH(Scenario!$E$6, Formulas!$C$4:$C$6, 0))*D$8 -> 35000 | E73: =INDEX(E74:E76, MATCH(Scenario!$E$6, Formulas!$C$4:$C$6, 0))*E$8 -> 35000 | F73: =INDEX(F74:F76, MATCH(Scenario!$E$6, Formulas!$C$4:$C$6, 0))*F$8 -> 35000 | G73: =INDEX(G74:G76, MATCH(Scenario!$E$6, Formulas!$C$4:$C$6, 0))*G$8 -> 35000 | H73: =INDEX(H74:H76, MATCH(Scenario!$E$6, Formulas!$C$4:$C$6, 0))*H$8 -> 35000 | I73: =INDEX(I74:I76, MATCH(Scenario!$E$6, Formulas!$C$4:$C$6, 0))*I$8 -> 35000 | J73: =INDEX(J74:J76, MATCH(Scenario!$E$6, Formulas!$C$4:$C$6, 0))*J$8 -> 35000 | ... L73: =INDEX(L74:L76, MATCH(Scenario!$E$6, Formulas!$C$4:$C$6, 0))*L$8 -> 35000
B74: Base Case | C74: =Scenario!G46 -> 35000 | D74: =Scenario!H46 -> 35000 | E74: =Scenario!I46 -> 35000 | F74: =Scenario!J46 -> 35000 | G74: =Scenario!K46 -> 35000 | H74: =Scenario!L46 -> 35000 | I74: =Scenario!M46 -> 35000 | J74: =Scenario!N46 -> 35000 | ... L74: =Scenario!P46 -> 35000
B75: Best Case | C75: =Scenario!G76 -> 38000 | D75: =Scenario!H76 -> 38000 | E75: =Scenario!I76 -> 38000 | F75: =Scenario!J76 -> 38000 | G75: =Scenario!K76 -> 38000 | H75: =Scenario!L76 -> 38000 | I75: =Scenario!M76 -> 38000 | J75: =Scenario!N76 -> 38000 | ... L75: =Scenario!P76 -> 38000
B76: Worst Case | C76: =Scenario!G106 -> 45000 | D76: =Scenario!H106 -> 45000 | E76: =Scenario!I106 -> 45000 | F76: =Scenario!J106 -> 45000 | G76: =Scenario!K106 -> 45000 | H76: =Scenario!L106 -> 45000 | I76: =Scenario!M106 -> 45000 | J76: =Scenario!N106 -> 45000 | ... L76: =Scenario!P106 -> 45000
A77: Credit Card Fees | C77: =INDEX(C78:C80, MATCH(Scenario!$E$6, Formulas!$C$4:$C$6, 0))*C$8 -> 0.008 | D77: =INDEX(D78:D80, MATCH(Scenario!$E$6, Formulas!$C$4:$C$6, 0))*D$8 -> 0.008 | E77: =INDEX(E78:E80, MATCH(Scenario!$E$6, Formulas!$C$4:$C$6, 0))*E$8 -> 0.008 | F77: =INDEX(F78:F80, MATCH(Scenario!$E$6, Formulas!$C$4:$C$6, 0))*F$8 -> 0.008 | G77: =INDEX(G78:G80, MATCH(Scenario!$E$6, Formulas!$C$4:$C$6, 0))*G$8 -> 0.008 | H77: =INDEX(H78:H80, MATCH(Scenario!$E$6, Formulas!$C$4:$C$6, 0))*H$8 -> 0.008 | I77: =INDEX(I78:I80, MATCH(Scenario!$E$6, Formulas!$C$4:$C$6, 0))*I$8 -> 0.008 | J77: =INDEX(J78:J80, MATCH(Scenario!$E$6, Formulas!$C$4:$C$6, 0))*J$8 -> 0.008 | ... L77: =INDEX(L78:L80, MATCH(Scenario!$E$6, Formulas!$C$4:$C$6, 0))*L$8 -> 0.008
B78: Base Case | C78: =Scenario!G47 -> 0.008 | D78: =Scenario!H47 -> 0.008 | E78: =Scenario!I47 -> 0.008 | F78: =Scenario!J47 -> 0.008 | G78: =Scenario!K47 -> 0.008 | H78: =Scenario!L47 -> 0.008 | I78: =Scenario!M47 -> 0.008 | J78: =Scenario!N47 -> 0.008 | ... L78: =Scenario!P47 -> 0.008
B79: Best Case | C79: =Scenario!G77 -> 0.008 | D79: =Scenario!H77 -> 0.008 | E79: =Scenario!I77 -> 0.008 | F79: =Scenario!J77 -> 0.008 | G79: =Scenario!K77 -> 0.008 | H79: =Scenario!L77 -> 0.008 | I79: =Scenario!M77 -> 0.008 | J79: =Scenario!N77 -> 0.008 | ... L79: =Scenario!P77 -> 0.008
B80: Worst Case | C80: =Scenario!G107 -> 0.012 | D80: =Scenario!H107 -> 0.012 | E80: =Scenario!I107 -> 0.012 | F80: =Scenario!J107 -> 0.012 | G80: =Scenario!K107 -> 0.012 | H80: =Scenario!L107 -> 0.012 | I80: =Scenario!M107 -> 0.012 | J80: =Scenario!N107 -> 0.012 | ... L80: =Scenario!P107 -> 0.012
A81: Depreciation | C81: =INDEX(C82:C84, MATCH(Scenario!$E$6, Formulas!$C$4:$C$6, 0))*C$8 -> 0.35 | D81: =INDEX(D82:D84, MATCH(Scenario!$E$6, Formulas!$C$4:$C$6, 0))*D$8 -> 0.35 | E81: =INDEX(E82:E84, MATCH(Scenario!$E$6, Formulas!$C$4:$C$6, 0))*E$8 -> 0.35 | F81: =INDEX(F82:F84, MATCH(Scenario!$E$6, Formulas!$C$4:$C$6, 0))*F$8 -> 0.35 | G81: =INDEX(G82:G84, MATCH(Scenario!$E$6, Formulas!$C$4:$C$6, 0))*G$8 -> 0.35 | H81: =INDEX(H82:H84, MATCH(Scenario!$E$6, Formulas!$C$4:$C$6, 0))*H$8 -> 0.35 | I81: =INDEX(I82:I84, MATCH(Scenario!$E$6, Formulas!$C$4:$C$6, 0))*I$8 -> 0.35 | J81: =INDEX(J82:J84, MATCH(Scenario!$E$6, Formulas!$C$4:$C$6, 0))*J$8 -> 0.35 | ... L81: =INDEX(L82:L84, MATCH(Scenario!$E$6, Formulas!$C$4:$C$6, 0))*L$8 -> 0.35
B82: Base Case | C82: =Scenario!G48 -> 0.35 | D82: =Scenario!H48 -> 0.35 | E82: =Scenario!I48 -> 0.35 | F82: =Scenario!J48 -> 0.35 | G82: =Scenario!K48 -> 0.35 | H82: =Scenario!L48 -> 0.35 | I82: =Scenario!M48 -> 0.35 | J82: =Scenario!N48 -> 0.35 | ... L82: =Scenario!P48 -> 0.35
B83: Best Case | C83: =Scenario!G78 -> 0.35 | D83: =Scenario!H78 -> 0.35 | E83: =Scenario!I78 -> 0.35 | F83: =Scenario!J78 -> 0.35 | G83: =Scenario!K78 -> 0.35 | H83: =Scenario!L78 -> 0.35 | I83: =Scenario!M78 -> 0.35 | J83: =Scenario!N78 -> 0.35 | ... L83: =Scenario!P78 -> 0.35
B84: Worst Case | C84: =Scenario!G108 -> 0.45 | D84: =Scenario!H108 -> 0.45 | E84: =Scenario!I108 -> 0.45 | F84: =Scenario!J108 -> 0.45 | G84: =Scenario!K108 -> 0.45 | H84: =Scenario!L108 -> 0.45 | I84: =Scenario!M108 -> 0.45 | J84: =Scenario!N108 -> 0.45 | ... L84: =Scenario!P108 -> 0.45
A85: Tax Rate | C85: =INDEX(C86:C88, MATCH(Scenario!$E$6, Formulas!$C$4:$C$6, 0))*C$8 -> 0.25 | D85: =INDEX(D86:D88, MATCH(Scenario!$E$6, Formulas!$C$4:$C$6, 0))*D$8 -> 0.25 | E85: =INDEX(E86:E88, MATCH(Scenario!$E$6, Formulas!$C$4:$C$6, 0))*E$8 -> 0.25 | F85: =INDEX(F86:F88, MATCH(Scenario!$E$6, Formulas!$C$4:$C$6, 0))*F$8 -> 0.25 | G85: =INDEX(G86:G88, MATCH(Scenario!$E$6, Formulas!$C$4:$C$6, 0))*G$8 -> 0.25 | H85: =INDEX(H86:H88, MATCH(Scenario!$E$6, Formulas!$C$4:$C$6, 0))*H$8 -> 0.25 | I85: =INDEX(I86:I88, MATCH(Scenario!$E$6, Formulas!$C$4:$C$6, 0))*I$8 -> 0.25 | J85: =INDEX(J86:J88, MATCH(Scenario!$E$6, Formulas!$C$4:$C$6, 0))*J$8 -> 0.25 | ... L85: =INDEX(L86:L88, MATCH(Scenario!$E$6, Formulas!$C$4:$C$6, 0))*L$8 -> 0.25
B86: Base Case | C86: =Scenario!G49 -> 0.25 | D86: =Scenario!H49 -> 0.25 | E86: =Scenario!I49 -> 0.25 | F86: =Scenario!J49 -> 0.25 | G86: =Scenario!K49 -> 0.25 | H86: =Scenario!L49 -> 0.25 | I86: =Scenario!M49 -> 0.25 | J86: =Scenario!N49 -> 0.25 | ... L86: =Scenario!P49 -> 0.25
B87: Best Case | C87: =Scenario!G79 -> 0.25 | D87: =Scenario!H79 -> 0.25 | E87: =Scenario!I79 -> 0.25 | F87: =Scenario!J79 -> 0.25 | G87: =Scenario!K79 -> 0.25 | H87: =Scenario!L79 -> 0.25 | I87: =Scenario!M79 -> 0.25 | J87: =Scenario!N79 -> 0.25 | ... L87: =Scenario!P79 -> 0.25
B88: Worst Case | C88: =Scenario!G109 -> 0.31 | D88: =Scenario!H109 -> 0.31 | E88: =Scenario!I109 -> 0.31 | F88: =Scenario!J109 -> 0.31 | G88: =Scenario!K109 -> 0.31 | H88: =Scenario!L109 -> 0.31 | I88: =Scenario!M109 -> 0.31 | J88: =Scenario!N109 -> 0.31 | ... L88: =Scenario!P109 -> 0.31
A89: Accounts Receivable | C89: =INDEX(C90:C92, MATCH(Scenario!$E$6, Formulas!$C$4:$C$6, 0))*C$8 -> 40 | D89: =INDEX(D90:D92, MATCH(Scenario!$E$6, Formulas!$C$4:$C$6, 0))*D$8 -> 40 | E89: =INDEX(E90:E92, MATCH(Scenario!$E$6, Formulas!$C$4:$C$6, 0))*E$8 -> 40 | F89: =INDEX(F90:F92, MATCH(Scenario!$E$6, Formulas!$C$4:$C$6, 0))*F$8 -> 40 | G89: =INDEX(G90:G92, MATCH(Scenario!$E$6, Formulas!$C$4:$C$6, 0))*G$8 -> 40 | H89: =INDEX(H90:H92, MATCH(Scenario!$E$6, Formulas!$C$4:$C$6, 0))*H$8 -> 35 | I89: =INDEX(I90:I92, MATCH(Scenario!$E$6, Formulas!$C$4:$C$6, 0))*I$8 -> 35 | J89: =INDEX(J90:J92, MATCH(Scenario!$E$6, Formulas!$C$4:$C$6, 0))*J$8 -> 35 | ... L89: =INDEX(L90:L92, MATCH(Scenario!$E$6, Formulas!$C$4:$C$6, 0))*L$8 -> 35
B90: Base Case | C90: =Scenario!G52 -> 40 | D90: =Scenario!H52 -> 40 | E90: =Scenario!I52 -> 40 | F90: =Scenario!J52 -> 40 | G90: =Scenario!K52 -> 40 | H90: =Scenario!L52 -> 35 | I90: =Scenario!M52 -> 35 | J90: =Scenario!N52 -> 35 | ... L90: =Scenario!P52 -> 35
B91: Best Case | C91: =Scenario!G82 -> 40 | D91: =Scenario!H82 -> 40 | E91: =Scenario!I82 -> 40 | F91: =Scenario!J82 -> 40 | G91: =Scenario!K82 -> 40 | H91: =Scenario!L82 -> 35 | I91: =Scenario!M82 -> 35 | J91: =Scenario!N82 -> 35 | ... L91: =Scenario!P82 -> 35
B92: Worst Case | C92: =Scenario!G112 -> 50 | D92: =Scenario!H112 -> 50 | E92: =Scenario!I112 -> 50 | F92: =Scenario!J112 -> 50 | G92: =Scenario!K112 -> 50 | H92: =Scenario!L112 -> 55 | I92: =Scenario!M112 -> 55 | J92: =Scenario!N112 -> 55 | ... L92: =Scenario!P112 -> 55
A93: Inventory | C93: =INDEX(C94:C96, MATCH(Scenario!$E$6, Formulas!$C$4:$C$6, 0))*C$8 -> 65 | D93: =INDEX(D94:D96, MATCH(Scenario!$E$6, Formulas!$C$4:$C$6, 0))*D$8 -> 65 | E93: =INDEX(E94:E96, MATCH(Scenario!$E$6, Formulas!$C$4:$C$6, 0))*E$8 -> 65 | F93: =INDEX(F94:F96, MATCH(Scenario!$E$6, Formulas!$C$4:$C$6, 0))*F$8 -> 70 | G93: =INDEX(G94:G96, MATCH(Scenario!$E$6, Formulas!$C$4:$C$6, 0))*G$8 -> 70 | H93: =INDEX(H94:H96, MATCH(Scenario!$E$6, Formulas!$C$4:$C$6, 0))*H$8 -> 70 | I93: =INDEX(I94:I96, MATCH(Scenario!$E$6, Formulas!$C$4:$C$6, 0))*I$8 -> 75 | J93: =INDEX(J94:J96, MATCH(Scenario!$E$6, Formulas!$C$4:$C$6, 0))*J$8 -> 75 | ... L93: =INDEX(L94:L96, MATCH(Scenario!$E$6, Formulas!$C$4:$C$6, 0))*L$8 -> 80
B94: Base Case | C94: =Scenario!G53 -> 65 | D94: =Scenario!H53 -> 65 | E94: =Scenario!I53 -> 65 | F94: =Scenario!J53 -> 70 | G94: =Scenario!K53 -> 70 | H94: =Scenario!L53 -> 70 | I94: =Scenario!M53 -> 75 | J94: =Scenario!N53 -> 75 | ... L94: =Scenario!P53 -> 80
B95: Best Case | C95: =Scenario!G83 -> 65 | D95: =Scenario!H83 -> 65 | E95: =Scenario!I83 -> 65 | F95: =Scenario!J83 -> 70 | G95: =Scenario!K83 -> 70 | H95: =Scenario!L83 -> 70 | I95: =Scenario!M83 -> 75 | J95: =Scenario!N83 -> 75 | ... L95: =Scenario!P83 -> 80
B96: Worst Case | C96: =Scenario!G113 -> 80 | D96: =Scenario!H113 -> 80 | E96: =Scenario!I113 -> 85 | F96: =Scenario!J113 -> 90 | G96: =Scenario!K113 -> 90 | H96: =Scenario!L113 -> 95 | I96: =Scenario!M113 -> 100 | J96: =Scenario!N113 -> 100 | ... L96: =Scenario!P113 -> 110
A97: Property, Plant and Equipment | C97: =INDEX(C98:C100, MATCH(Scenario!$E$6, Formulas!$C$4:$C$6, 0))*C$8 -> 13500
B98: Base Case | C98: =Scenario!G54 -> 13500
B99: Best Case | C99: =Scenario!G84 -> 18000
B100: Worst Case | C100: =Scenario!G114 -> 12000
A101: Accounts Payable | C101: =INDEX(C102:C104, MATCH(Scenario!$E$6, Formulas!$C$4:$C$6, 0))*C$8 -> 50 | D101: =INDEX(D102:D104, MATCH(Scenario!$E$6, Formulas!$C$4:$C$6, 0))*D$8 -> 50 | E101: =INDEX(E102:E104, MATCH(Scenario!$E$6, Formulas!$C$4:$C$6, 0))*E$8 -> 50 | F101: =INDEX(F102:F104, MATCH(Scenario!$E$6, Formulas!$C$4:$C$6, 0))*F$8 -> 50 | G101: =INDEX(G102:G104, MATCH(Scenario!$E$6, Formulas!$C$4:$C$6, 0))*G$8 -> 50 | H101: =INDEX(H102:H104, MATCH(Scenario!$E$6, Formulas!$C$4:$C$6, 0))*H$8 -> 45 | I101: =INDEX(I102:I104, MATCH(Scenario!$E$6, Formulas!$C$4:$C$6, 0))*I$8 -> 45 | J101: =INDEX(J102:J104, MATCH(Scenario!$E$6, Formulas!$C$4:$C$6, 0))*J$8 -> 45 | ... L101: =INDEX(L102:L104, MATCH(Scenario!$E$6, Formulas!$C$4:$C$6, 0))*L$8 -> 45
B102: Base Case | C102: =Scenario!G55 -> 50 | D102: =Scenario!H55 -> 50 | E102: =Scenario!I55 -> 50 | F102: =Scenario!J55 -> 50 | G102: =Scenario!K55 -> 50 | H102: =Scenario!L55 -> 45 | I102: =Scenario!M55 -> 45 | J102: =Scenario!N55 -> 45 | ... L102: =Scenario!P55 -> 45
B103: Best Case | C103: =Scenario!G85 -> 50 | D103: =Scenario!H85 -> 50 | E103: =Scenario!I85 -> 50 | F103: =Scenario!J85 -> 50 | G103: =Scenario!K85 -> 50 | H103: =Scenario!L85 -> 45 | I103: =Scenario!M85 -> 45 | J103: =Scenario!N85 -> 45 | ... L103: =Scenario!P85 -> 45
B104: Worst Case | C104: =Scenario!G115 -> 70 | D104: =Scenario!H115 -> 70 | E104: =Scenario!I115 -> 70 | F104: =Scenario!J115 -> 70 | G104: =Scenario!K115 -> 70 | H104: =Scenario!L115 -> 75 | I104: =Scenario!M115 -> 75 | J104: =Scenario!N115 -> 75 | ... L104: =Scenario!P115 -> 75
A105: Accrued Expenses and Other | C105: =INDEX(C106:C108, MATCH(Scenario!$E$6, Formulas!$C$4:$C$6, 0))*C$8 -> 0.045 | D105: =INDEX(D106:D108, MATCH(Scenario!$E$6, Formulas!$C$4:$C$6, 0))*D$8 -> 0.045 | E105: =INDEX(E106:E108, MATCH(Scenario!$E$6, Formulas!$C$4:$C$6, 0))*E$8 -> 0.045 | F105: =INDEX(F106:F108, MATCH(Scenario!$E$6, Formulas!$C$4:$C$6, 0))*F$8 -> 0.045 | G105: =INDEX(G106:G108, MATCH(Scenario!$E$6, Formulas!$C$4:$C$6, 0))*G$8 -> 0.045 | H105: =INDEX(H106:H108, MATCH(Scenario!$E$6, Formulas!$C$4:$C$6, 0))*H$8 -> 0.045 | I105: =INDEX(I106:I108, MATCH(Scenario!$E$6, Formulas!$C$4:$C$6, 0))*I$8 -> 0.045 | J105: =INDEX(J106:J108, MATCH(Scenario!$E$6, Formulas!$C$4:$C$6, 0))*J$8 -> 0.045 | ... L105: =INDEX(L106:L108, MATCH(Scenario!$E$6, Formulas!$C$4:$C$6, 0))*L$8 -> 0.045
...
