Workbook
Name IQ_CH: 110000
Name IQ_CQ: 5000
Name IQ_CY: 10000
Name IQ_DAILY: 500000
Name IQ_FH: 100000
Name IQ_FQ: 500
Name IQ_FY: 1000
Name IQ_LTM: 2000
Name IQ_MONTH: 15000
Name IQ_NTM: 6000
Name IQ_WEEK: 50000
Name IQ_YTD: 3000

Sheet GL-Summary
B2: General Ledger Summary
B4: Account | C4: Description | D4: Total Debits | E4: Total Credits | F4: Net Balance
B5: 9804018 | C5: FCOSIEGE FRAIS GENERAUX Impôts et t | D5: =SUMIFS('GL-Transactions'!C:C,'GL-Transactions'!G:G,"Total",'GL-Transactions'!E:E,B5) -> 1664283 | E5: =SUMIFS('GL-Transactions'!B:B,'GL-Transactions'!G:G,"Total",'GL-Transactions'!E:E,B5) -> 0 | F5: =D5-E5 -> 1664283
B6: 9804017 | C6: FCOSIEGE FRAIS GENERAUX Amort & pro | D6: =SUMIFS('GL-Transactions'!C:C,'GL-Transactions'!G:G,"Total",'GL-Transactions'!E:E,B6) -> 39103689 | E6: =SUMIFS('GL-Transactions'!B:B,'GL-Transactions'!G:G,"Total",'GL-Transactions'!E:E,B6) -> 0 | F6: =D6-E6 -> 39103689
B7: 9804016 | C7: FCOSIEGE FRAIS GENERAUX Intétrêts e | D7: =SUMIFS('GL-Transactions'!C:C,'GL-Transactions'!G:G,"Total",'GL-Transactions'!E:E,B7) -> 11741512 | E7: =SUMIFS('GL-Transactions'!B:B,'GL-Transactions'!G:G,"Total",'GL-Transactions'!E:E,B7) -> 23200 | F7: =D7-E7 -> 11718312
B8: 9804015 | C8: FCOSIEGE FRAIS GENERAUX Frais gx et | D8: =SUMIFS('GL-Transactions'!C:C,'GL-Transactions'!G:G,"Total",'GL-Transactions'!E:E,B8) -> 846756 | E8: =SUMIFS('GL-Transactions'!B:B,'GL-Transactions'!G:G,"Total",'GL-Transactions'!E:E,B8) -> 0 | F8: =D8-E8 -> 846756
B9: 9804011 | C9: FCOSIEGE FRAIS GENERAUX Autres frai | D9: =SUMIFS('GL-Transactions'!C:C,'GL-Transactions'!G:G,"Total",'GL-Transactions'!E:E,B9) -> 594395 | E9: =SUMIFS('GL-Transactions'!B:B,'GL-Transactions'!G:G,"Total",'GL-Transactions'!E:E,B9) -> 0 | F9: =D9-E9 -> 594395
B10: 9804009 | C10: FCOSIEGE FRAIS GENERAUX Frais télép | D10: =SUMIFS('GL-Transactions'!C:C,'GL-Transactions'!G:G,"Total",'GL-Transactions'!E:E,B10) -> 937920 | E10: =SUMIFS('GL-Transactions'!B:B,'GL-Transactions'!G:G,"Total",'GL-Transactions'!E:E,B10) -> 0 | F10: =D10-E10 -> 937920
B11: 9804007 | C11: FCOSIEGE FRAIS GENERAUX Loyers et l | D11: =SUMIFS('GL-Transactions'!C:C,'GL-Transactions'!G:G,"Total",'GL-Transactions'!E:E,B11) -> 11159715 | E11: =SUMIFS('GL-Transactions'!B:B,'GL-Transactions'!G:G,"Total",'GL-Transactions'!E:E,B11) -> 0 | F11: =D11-E11 -> 11159715
B12: 9801010 | C12: FCOSIEGE PERS ADM Salaires & chges | D12: =SUMIFS('GL-Transactions'!C:C,'GL-Transactions'!G:G,"Total",'GL-Transactions'!E:E,B12) -> 22835205 | E12: =SUMIFS('GL-Transactions'!B:B,'GL-Transactions'!G:G,"Total",'GL-Transactions'!E:E,B12) -> 39470824 | F12: =D12-E12 -> -16635619
B13: 9706016 | C13: QUALDEV Frais opérat ind impu Intét | D13: =SUMIFS('GL-Transactions'!C:C,'GL-Transactions'!G:G,"Total",'GL-Transactions'!E:E,B13) -> 84353 | E13: =SUMIFS('GL-Transactions'!B:B,'GL-Transactions'!G:G,"Total",'GL-Transactions'!E:E,B13) -> 0 | F13: =D13-E13 -> 84353
B14: 9706005 | C14: QUALDEV Frais opérat ind impu Honor | D14: =SUMIFS('GL-Transactions'!C:C,'GL-Transactions'!G:G,"Total",'GL-Transactions'!E:E,B14) -> 327750 | E14: =SUMIFS('GL-Transactions'!B:B,'GL-Transactions'!G:G,"Total",'GL-Transactions'!E:E,B14) -> 0 | F14: =D14-E14 -> 327750
B15: 9706003 | C15: QUALDEV Frais opérat ind impu Redev | D15: =SUMIFS('GL-Transactions'!C:C,'GL-Transactions'!G:G,"Total",'GL-Transactions'!E:E,B15) -> 11366472 | E15: =SUMIFS('GL-Transactions'!B:B,'GL-Transactions'!G:G,"Total",'GL-Transactions'!E:E,B15) -> 0 | F15: =D15-E15 -> 11366472
B16: 9705308 | C16: QUALDEV FR VHC S3 Frais roulement V | D16: =SUMIFS('GL-Transactions'!C:C,'GL-Transactions'!G:G,"Total",'GL-Transactions'!E:E,B16) -> 398232 | E16: =SUMIFS('GL-Transactions'!B:B,'GL-Transactions'!G:G,"Total",'GL-Transactions'!E:E,B16) -> 0 | F16: =D16-E16 -> 398232
... B574: 11 | C574: QUALITY CERT | D574: =SUMIFS('GL-Transactions'!C:C,'GL-Transactions'!G:G,"Total",'GL-Transactions'!E:E,B574) -> 48760000 | E574: =SUMIFS('GL-Transactions'!B:B,'GL-Transactions'!G:G,"Total",'GL-Transactions'!E:E,B574) -> 156386981 | F574: =D574-E574 -> -107626981
B575: GRAND TOTAL | D575: =SUM(D5:D574) -> 1712749956 | E575: =SUM(E5:E574) -> 1844657779 | F575: =D575-E575 -> -131907823

Sheet GL-Transactions
A1: Balance | B1: Credits | C1: Debits | D1: Ref# | E1: Type | F1: Description | G1: Date
A2: =C2-B2 -> 0
A3: =C3-B3 -> 0 | D3: Company1063 Company0081 Frais Missions | G3: 1110101
A4: =C4-B4 -> 0 | F4: PERDIEM AUDITS | G4: 63841000
A5: =C5-B5 -> 95881 | C5: 95881 | D5: 151 | E5: ACH | F5: PERDIEMS AUDITEUR MISSION Company1057 /Company0725 | G5: 44712
A6: =C6-B6 -> 95881 | C6: 95881
A7: =C7-B7 -> 95881 | C7: 95881 | E7: 1110101 | F7: Company1063 Company0081 Frais Missions | G7: Total
A8: =C8-B8 -> 0 | D8: Company0081 Honoraires | G8: 1110105
A9: =C9-B9 -> 0 | F9: HONORAIRE | G9: 63240000
A10: =C10-B10 -> 215625 | C10: 215625 | D10: 256 | E10: ACH | F10: FA N°01 HONORAIRES Person0864 Person0726 | G10: 44778
A11: =C11-B11 -> 215625 | C11: 215625
A12: =C12-B12 -> 215625 | C12: 215625 | E12: 1110105 | F12: Company0081 Honoraires | G12: Total
A13: =C13-B13 -> 0 | D13: Company0081 Chiffre d'affaires | G13: 1110121
A14: =C14-B14 -> 0 | F14: SERVICES VENDUS NON TAXABLES | G14: 70612000
A15: =C15-B15 -> -1589177 | B15: 1589177 | D15: 15 | E15: VTE | F15: AUDIT Company1063 ET QC FA 025 Company0081 | G15: 44600
A16: =C16-B16 -> -1589177 | B16: 1589177
A17: =C17-B17 -> -1589177 | B17: 1589177 | E17: 1110121 | F17: Company0081 Chiffre d'affaires | G17: Total
A18: =C18-B18 -> 0 | D18: Company1063 DOSSIER Company0294 Frais Missions | G18: 1110301
A19: =C19-B19 -> 0 | F19: PERDIEM AUDITS | G19: 63841000
A20: =C20-B20 -> 34500 | C20: 34500 | D20: 29 | E20: BQ 1 | F20: CHQ N°2280895 RGLT PERDIEM Person1005 Person0010 MISSION Company0294 | G20: 44631
A21: =C21-B21 -> 139495 | C21: 139495 | D21: 128 | E21: ACH | F21: PERDIEMS AUDITEUR MISSION Company0294/Company0725 | G21: 44692
A22: =C22-B22 -> 173995 | C22: 173995
A23: =C23-B23 -> 173995 | C23: 173995 | E23: 1110301 | F23: Company1063 DOSSIER Company0294 Frais Missions | G23: Total
A24: =C24-B24 -> 0 | D24: Company1063 DOSSIER Company0294 Dép.&Transp. | G24: 1110302
A25: =C25-B25 -> 0 | F25: Frais voyages et dépl. audits | G25: 61811000
A26: =C26-B26 -> 32200 | C26: 32200 | D26: 301 | E26: ACH | F26: FA N°0003471 Company2325 BILLET Person1005 Person0010 MISSION Product0082 DOR Company0551 NFG | G26: 44830
A27: =C27-B27 -> 32200 | C27: 32200
A28: =C28-B28 -> 32200 | C28: 32200 | E28: 1110302 | F28: Company1063 DOSSIER Company0294 Dép.&Transp. | G28: Total
A29: =C29-B29 -> 0 | D29: Company1063 DOSSIER Company0294 Autres frais d | G29: 1110304
A30: =C30-B30 -> 0 | F30: FRAIS DE RECEPTION | G30: 63833
A31: =C31-B31 -> 84180 | C31: 84180 | D31: 52 | E31: ACH | F31: FA N°0026 Company0831 CI FRAIS DE RESTAURAT° MISSION Company0294 | G31: 44635
A32: =C32-B32 -> 84180 | C32: 84180
A33: =C33-B33 -> 84180 | C33: 84180 | E33: 1110304 | F33: Company1063 DOSSIER Company0294 Autres frais d | G33: Total
A34: =C34-B34 -> 0 | D34: Company2372 Frais Missions | G34: 1110501
A35: =C35-B35 -> 0 | F35: PERDIEM AUDITS | G35: 63841000
A36: =C36-B36 -> 69805 | C36: 69805 | D36: 50 | E36: OD | F36: PERDIEMS AUDITEUR MISSION Company2372 | G36: 44763
A37: =C37-B37 -> 69805 | C37: 69805 | D37: 78 | E37: OD | F37: PERDIEMS AUDITEUR MISSION Company2372 | G37: 44774
A38: =C38-B38 -> 139610 | C38: 139610
A39: =C39-B39 -> 139610 | C39: 139610 | E39: 1110501 | F39: Company2372 Frais Missions | G39: Total
A40: =C40-B40 -> 0 | D40: Company2372 Honoraires | G40: 1110505
A41: =C41-B41 -> 0 | F41: HONORAIRE | G41: 63240000
A42: =C42-B42 -> 391000 | C42: 391000 | D42: 257 | E42: ACH | F42: HONORAIRES Person1008 Person0281 MISSION Company2372 | G42: 44783
A43: =C43-B43 -> 391000 | C43: 391000
A44: =C44-B44 -> 391000 | C44: 391000 | E44: 1110505 | F44: Company2372 Honoraires | G44: Total
A45: =C45-B45 -> 0 | D45: Company2372 Chiffre d'affaires | G45: 1110521
A46: =C46-B46 -> 0 | F46: SERVICES VENDUS NON TAXABLES | G46: 70612000
A47: =C47-B47 -> -1388252 | B47: 1388252 | D47: 21 | E47: VTE | F47: AUDIT QC ET Company1063 FA 033 Company2374 | G47: 44607
A48: =C48-B48 -> -287500 | B48: 287500 | D48: 46 | E48: VTE | F48: COMPLEMENT Company1106 FA078 Company2373 Company0999 | G48: 44649
A49: =C49-B49 -> -1899376 | B49: 1899376 | D49: 215 | E49: VTE | F49: FA 255 AUDIT DE RNVLLMT QC/Company2676 Company0999 SARL | G49: 44902
A50: =C50-B50 -> 1899376 | C50: 1899376 | D50: 278 | E50: OD | F50: PRODUIT CONSTATER D'AVANCE/ FA 255 Company2372 | G50: 44925
A51: =C51-B51 -> -1675752 | B51: 3575128 | C51: 1899376
A52: =C52-B52 -> -1675752 | B52: 3575128 | C52: 1899376 | E52: 1110521 | F52: Company2372 Chiffre d'affaires | G52: Total
A53: =C53-B53 -> 0 | D53: Company1063 DOSSIER Company1056 SAS Frais Missi | G53: 1110601
A54: =C54-B54 -> 0 | F54: PERDIEM AUDITS | G54: 63841000
A55: =C55-B55 -> 95881 | C55: 95881 | D55: 151 | E55: ACH | F55: PERDIEMS AUDITEUR MISSION Company1057 /Company0725 | G55: 44712
A56: =C56-B56 -> 95881 | C56: 95881
A57: =C57-B57 -> 95881 | C57: 95881 | E57: 1110601 | F57: Company1063 DOSSIER Company1056 SAS Frais Missi | G57: Total
A58: =C58-B58 -> 0 | D58: Company1063 DOSSIER Company1056 SAS Honoraires | G58: 1110605
A59: =C59-B59 -> 0 | F59: HONORAIRE | G59: 63240000
A60: =C60-B60 -> 258750 | C60: 258750 | D60: 256 | E60: ACH | F60: FA N°01 HONORAIRES Person0864 Person0726 | G60: 44778
A61: =C61-B61 -> 258750 | C61: 258750
A62: =C62-B62 -> 258750 | C62: 258750 | E62: 1110605 | F62: Company1063 DOSSIER Company1056 SAS Honoraires | G62: Total
A63: =C63-B63 -> 0 | D63: Company1063 DOSSIER Company1056 SAS Chiffre d'a | G63: 1110621
A64: =C64-B64 -> 0 | F64: SERVICES VENDUS NON TAXABLES | G64: 70612000
A65: =C65-B65 -> -1707771 | B65: 1707771 | D65: 32 | E65: VTE | F65: AUDIT QC ET Company1063 FA 051 Company1056 CI | G65: 44623
A66: =C66-B66 -> -1707771 | B66: 1707771
A67: =C67-B67 -> -1707771 | B67: 1707771 | E67: 1110621 | F67: Company1063 DOSSIER Company1056 SAS Chiffre d'a | G67: Total
A68: =C68-B68 -> 0 | D68: Company1063 NEW Company0999 GROUP Frais Missions | G68: 1110801
A69: =C69-B69 -> 0 | F69: PERDIEM AUDITS | G69: 63841000
A70: =C70-B70 -> 139438 | C70: 139438 | D70: 112 | E70: ACH | F70: PERDIEMS AUDITEUR MISSION NFG et Company1305/ Company0725 | G70: 44684
A71: =C71-B71 -> 61007 | C71: 61007 | D71: 124 | E71: OD | F71: PERDIEMS AUDITEURS MISSION IVOIRE Company1988+NFG+Company0294+Company1305 | G71: 44830
A72: =C72-B72 -> 200445 | C72: 200445
A73: =C73-B73 -> 200445 | C73: 200445 | E73: 1110801 | F73: Company1063 NEW Company0999 GROUP Frais Missions | G73: Total
A74: =C74-B74 -> 0 | D74: Company1063 NEW Company0999 GROUP Dép.&Transp. | G74: 1110802
A75: =C75-B75 -> 0 | F75: Frais voyages et dépl. audits | G75: 61811000
A76: =C76-B76 -> 32200 | C76: 32200 | D76: 301 | E76: ACH | F76: FA N°0003471 Company2325 BILLET Person1005 Person0010 MISSION Product0082 DOR Company0551 NFG | G76: 44830
A77: =C77-B77 -> 32200 | C77: 32200
A78: =C78-B78 -> 32200 | C78: 32200 | E78: 1110802 | F78: Company1063 NEW Company0999 GROUP Dép.&Transp. | G78: Total
A79: =C79-B79 -> 0 | D79: Company1063 NEW Company0999 GROUP Chiffre d'affai | G79: 1110821
A80: =C80-B80 -> 0 | F80: SERVICES VENDUS NON TAXABLES | G80: 70612000
A81: =C81-B81 -> -3041307 | B81: 3041307 | D81: 2 | E81: VTE | F81: FA 002 NEW Company0999 GROUP AUDIT QUALITY CERT | G81: 44573
A82: =C82-B82 -> -3041307 | B82: 3041307
A83: =C83-B83 -> -3041307 | B83: 3041307 | E83: 1110821 | F83: Company1063 NEW Company0999 GROUP Chiffre d'affai | G83: Total
A84: =C84-B84 -> 0 | D84: Company1063 DOSSIER Company0889 Frais Mis | G84: 1110901
A85: =C85-B85 -> 0 | F85: PERDIEM AUDITS | G85: 63841000
A86: =C86-B86 -> 182994 | C86: 182994 | D86: 95 | E86: ACH | F86: PERDIEMS AUDITEURS MISSION Company0041 Company0891 LOG /Company0725 | G86: 44663
A87: =C87-B87 -> 34903 | C87: 34903 | D87: 184 | E87: BQ 1 | F87: Company0725 N°048-2022 RGLT PERDIEMS AUDITEUR MISSIONS Company0034/IMS/Product0082 Product0117 | G87: 44725
A88: =C88-B88 -> 23268 | C88: 23268 | D88: 185 | E88: BQ 1 | F88: Company0725 N°049-2022 PERDIEMS COMPL AUDITEUR MISS° Company0034/IMS/Product0082 Product0117 | G88: 44726
A89: =C89-B89 -> -69805 | B89: 69805 | D89: 120379 | E89: BQ 1 | F89: ANNUL 049-BNA-TO 2022 COMPL PERDIEMS-MISSION Company0034/ IMS / Product0082 Product0117 | G89: 44925
A90: =C90-B90 -> -34903 | B90: 34903 | D90: 120380 | E90: BQ 1 | F90: ANNUL FA 048-BNA-TO 2022 PERDIEMS-MISSION Company0034/ IMS / Product0082 Product0117 | G90: 44925
A91: =C91-B91 -> 69805 | C91: 69805 | D91: 245 | E91: OD | F91: PERDIEMS AUDITEUR MISSION Company0034/IMS/ Product0082 Product0117 | G91: 44925
A92: =C92-B92 -> 34903 | C92: 34903 | D92: 246 | E92: OD | F92: PERDIEMS AUDITEUR MISSION Company0034/IMS/ Product0082 Product0117 | G92: 44925
A93: =C93-B93 -> 241165 | B93: 104707 | C93: 345872
A94: =C94-B94 -> 241165 | B94: 104707 | C94: 345872 | E94: 1110901 | F94: Company1063 DOSSIER Company0889 Frais Mis | G94: Total
A95: =C95-B95 -> 0 | D95: Company1063 DOSSIER Company0889 Dép.&Tran | G95: 1110902
A96: =C96-B96 -> 0 | F96: Frais voyages et dépl. audits | G96: 61811000
A97: =C97-B97 -> 69000 | C97: 69000 | D97: 94 | E97: ACH | F97: FA0000124 CBM Company2873 Person1005 Person0010/MISSION Company0041 Company0891 LOG | G97: 44662
A98: =C98-B98 -> 34500 | C98: 34500 | D98: 182 | E98: ACH | F98: FA0000132 CBM VOYAGES Person0860 Person0035( Company0034+ IMS+Product0082 DOR) | G98: 44714
A99: =C99-B99 -> 103500 | C99: 103500
A100: =C100-B100 -> 103500 | C100: 103500 | E100: 1110902 | F100: Company1063 DOSSIER Company0889 Dép.&Tran | G100: Total
...

Sheet Sheet1
F3: Debits | G3: Credits
D4: 1114701 | E4: DOSSIER AFRICA FOOD Frais Missions | F4: 103500 | G4: 0
D5: 1331302 | E5: RFA Person0018 Person0559 Dép.&Transp. | F5: 0 | G5: 0
D6: 1335801 | E6: RFA Company2197 Frais Missions | F6: 2875 | G6: 0
D7: 1116321 | E7: Company1063 Company0304 Chiffre d'affaires | F7: 1980108 | G7: 2300670
D8: 9702010 | E8: QUALDEV PERS PROF. Salaires & chges | F8: 5980000 | G8: 0
D9: 1115202 | E9: Company1063 Company1989 FRUITS Dép.&Transp. | F9: 0 | G9: 0
D10: 1114721 | E10: AFRICA FOOD Chiffre d'affaires | F10: 69748 | G10: 3515410
D11: 4170321 | E11: Company0888 Company0561 CAFE -Company0422 Chiffre | F11: 2277460 | G11: 64398168
D12: 1115805 | E12: Company0720- Company0951 Honoraires | F12: 87228 | G12: 0
D13: 1115801 | E13: Company0721 Frais Missions | F13: 883200 | G13: 0
D14: 1115502 | E14: Company1063 RPG SENEGAL Dép.&Transp. | F14: 69805 | G14: 0
D15: 1115402 | E15: Company1063 DOSSIER Product0356 Dép.&Transp. | F15: 345000 | G15: 0
... D48: 1115605 | E48: Company0048 Honoraires | F48: 139495 | G48: 0
