Workbook

Sheet Assumptions
B4: Company0191 Corp — Operating Assumptions
B6: Period | C6: FY2024A | D6: FY2025E | E6: FY2026E | F6: FY2027E | G6: FY2028E
B8: Growth
B9: Revenue Growth % | C9: 0 | D9: 0.1 | E9: 0.12 | F9: 0.1 | G9: 0.08
B11: Margins (% of Revenue)
B12: COGS % of Revenue | C12: 0.42 | D12: 0.41 | E12: 0.4 | F12: 0.4 | G12: 0.39
B13: SG&A % of Revenue | C13: 0.18 | D13: 0.18 | E13: 0.17 | F13: 0.16 | G13: 0.16
B14: R&D % of Revenue | C14: 0.08 | D14: 0.08 | E14: 0.08 | F14: 0.07 | G14: 0.07
B16: Capital
B17: Capex % of Revenue | C17: 0.05 | D17: 0.05 | E17: 0.05 | F17: 0.04 | G17: 0.04
B18: Δ NWC % of Revenue | C18: 0.02 | D18: 0.02 | E18: 0.02 | F18: 0.02 | G18: 0.02
B19: Depreciation | C19: 30 | D19: 33 | E19: 37 | F19: 41 | G19: 45
B21: Other
B22: Tax Rate | C22: 0.25 | D22: 0.25 | E22: 0.25 | F22: 0.25 | G22: 0.25
B23: Net Debt (year-end) | C23: 450 | D23: 420 | E23: 380 | F23: 320 | G23: 250

Sheet Model
B4: Company0191 Corp — Operating Model
B6: Period | C6: =Assumptions!C6 | D6: =Assumptions!D6 | E6: =Assumptions!E6 | F6: =Assumptions!F6 | G6: =Assumptions!G6
B8: Revenue | C8: 1000 | D8: =C8*(1+Assumptions!D9) | E8: =D8*(1+Assumptions!E9) | F8: =E8*(1+Assumptions!F9) | G8: =F8*(1+Assumptions!G9)
B9: % YoY Growth | D9: =D8/C8-1 | E9: =E8/D8-1 | F9: =F8/E8-1 | G9: =G8/F8-1
B11: COGS | C11: =-C8*Assumptions!C12 | D11: =-D8*Assumptions!D12 | E11: =-E8*Assumptions!E12 | F11: =-F8*Assumptions!F12 | G11: =-G8*Assumptions!G12
B12: Gross Profit | C12: =C8+C11 | D12: =D8+D11 | E12: =E8+E11 | F12: =F8+F11 | G12: =G8+G11
B13: % Gross Margin | C13: =C12/C8 | D13: =D12/D8 | E13: =E12/E8 | F13: =F12/F8 | G13: =G12/G8
B15: SG&A | C15: =-C8*Assumptions!C13 | D15: =-D8*Assumptions!D13 | E15: =-E8*Assumptions!E13 | F15: =-F8*Assumptions!F13 | G15: =-G8*Assumptions!G13
B16: R&D | C16: =-C8*Assumptions!C14 | D16: =-D8*Assumptions!D14 | E16: =-E8*Assumptions!E14 | F16: =-F8*Assumptions!F14 | G16: =-G8*Assumptions!G14
B17: Total OpEx | C17: =C15+C16 | D17: =D15+D16 | E17: =E15+E16 | F17: =F15+F16 | G17: =G15+G16
B19: EBITDA | C19: =C12+C17 | D19: =D12+D17 | E19: =E12+E17 | F19: =F12+F17 | G19: =G12+G17
B20: % EBITDA Margin | C20: =C19/C8 | D20: =D19/D8 | E20: =E19/E8 | F20: =F19/F8 | G20: =G19/G8
B22: D&A | C22: =-Assumptions!C19 | D22: =-Assumptions!D19 | E22: =-Assumptions!E19 | F22: =-Assumptions!F19 | G22: =-Assumptions!G19
B23: EBIT | C23: =C19+C22 | D23: =D19+D22 | E23: =E19+E22 | F23: =F19+F22 | G23: =G19+G22
B25: Tax Expense | C25: =-C23*Assumptions!C22 | D25: =-D23*Assumptions!D22 | E25: =-E23*Assumptions!E22 | F25: =-F23*Assumptions!F22 | G25: =-G23*Assumptions!G22
B26: Net Income | C26: =C23+C25 | D26: =D23+D25 | E26: =E23+E25 | F26: =F23+F25 | G26: =G23+G25
B27: % Net Income Margin | C27: =C26/C8 | D27: =D26/D8 | E27: =E26/E8 | F27: =F26/F8 | G27: =G26/G8

Sheet Output
B4: Company0191 Corp — Summary Output
B6: Period | C6: =Assumptions!C6 | D6: =Assumptions!D6 | E6: =Assumptions!E6 | F6: =Assumptions!F6 | G6: =Assumptions!G6
B8: Revenue | C8: =Model!C8 | D8: =Model!D8 | E8: =Model!E8 | F8: =Model!F8 | G8: =Model!G8
B9: % YoY Growth | D9: =Model!D9 | E9: =Model!E9 | F9: =Model!F9 | G9: =Model!G9
B11: EBITDA | C11: =Model!C19 | D11: =Model!D19 | E11: =Model!E19 | F11: =Model!F19 | G11: =Model!G19
B12: % EBITDA Margin | C12: =Model!C20 | D12: =Model!D20 | E12: =Model!E20 | F12: =Model!F20 | G12: =Model!G20
B14: Net Income | C14: =Model!C26 | D14: =Model!D26 | E14: =Model!E26 | F14: =Model!F26 | G14: =Model!G26
B16: Net Debt | C16: =Assumptions!C23 | D16: =Assumptions!D23 | E16: =Assumptions!E23 | F16: =Assumptions!F23 | G16: =Assumptions!G23
B17: Net Debt / EBITDA | C17: =Assumptions!C23/Model!C19 | D17: =Assumptions!D23/Model!D19 | E17: =Assumptions!E23/Model!E19 | F17: =Assumptions!F23/Model!F19 | G17: =Assumptions!G23/Model!G19
